Workbook

Sheet READ FIRST
A1: Read this first
A5: THE RULE
A6: IT CALCULATES. IT DOES NOT STORE.
A8: Exactly ONE class of cell is pasted in this workbook: a figure read off an audited or disclosed filing, or a stated house judgement. Those are the blue cells on Assumptions, and the blue lever cells that define each sensitivity grid point. Everything else is a live formula.
A10: The previous edition also pasted its sensitivity grids, its beta sweep and its bear and bull columns, on the grounds that each is a whole-model re-run and a re-run cannot be written inside a grid. That was 27.6% of the file, and it was the part a reader would most want to interrogate. Three of those pasted rows turned out not to reproduce.
A12: The Sensitivity sheet now writes the entire forecast engine out again, in formulas, once for every grid point. Change any driver on Assumptions and every sensitivity cell in the file moves with it.
A14: WHAT IS AUDITED AND WHAT IS NOT
A15: The base year is the twelve months to 30 June 2026. The first half of it — July to December 2025 — is AUDITED by Crowe with an unqualified opinion. The second half — January to June 2026 — is REPORTED: a disclosure to the Egyptian Exchange dated 29-30 July 2026, not a filing. Half of this base year is a press release and the study says so wherever it uses it.
A17: The gross profit of that reported half is NOT used as released. Run through the company's own first-quarter expense run rates the released figure implies a profit after tax about 12.6% above the profit the same release reports. The gross profit used here is solved from the profit line, which passes two independent coherence tests. Base Year rows 13 to 17 show the whole test.
A19: THE ONE OPERATING INPUT THAT IS NOT READ OFF A FILING
A20: Note 15-A discloses the cost stack for the company and not by line. The processing-intensity weights on Assumptions are therefore a judgement, and the per-line margins depend on them. They are registered, dated and sensitised like every other input rather than hidden inside a formula.

Sheet Assumptions
A1: Assumptions — every driver, with the filing it was read from
A2: Blue cells are the ONLY pasted values in this workbook. Every one is a figure read off an audited or disclosed filing, or a stated house judgement. There is no third class: the previous edition also pasted its sensitivity grids and its bear and bull columns because each is a whole-model re-run; those re-runs are now written out as live formula blocks on the Sensitivity sheet, so a reader can change a driver here and watch every one of them move.
A5: Driver | B5: Value | C5: Ring | D5: Date | E5: Source
A6: MARKET AND CAPITAL
A7: Spot price, EGP | B7: 9.1 | C7: Company | D7: 2026-08-06 | E7: AMOC closing price on the Egyptian Exchange, 6 August 2026
A8: Shares outstanding, mn | B8: 1291.5 | C8: Company | D8: 2025-12-31 | E8: Issued and paid-up capital EGP 1,291,500,000 at EGP 1 par = 1,291,500,000 shares (note 18-L, share split to EGP 1 par recorded in the Commercial Register 24-Jan-2018)
A9: THE TWELVE MONTHS TO 30 JUNE 2026 — the base year
A10: Net sales, 6M to 31-Dec-2025 (AUDITED) | B10: 20735725812 | C10: Company | D10: 2025-12-31 | E10: Net sales, six months to 31-Dec-2025. Audited consolidated FS, transition period 1-Jul-2025 to 31-Dec-2025, Crowe unqualified, 18-Feb-2026
A11: Cost of sales, 6M to 31-Dec-2025 (AUDITED) | B11: 19461550746 | C11: Company | D11: 2025-12-31 | E11: Cost of sales, six months to 31-Dec-2025. Audited consolidated FS, transition period 1-Jul-2025 to 31-Dec-2025, Crowe unqualified, 18-Feb-2026
A12: Net sales, 6M to 30-Jun-2026 (REPORTED) | B12: 26223000000 | C12: Company | D12: 2026-06-30 | E12: Net sales, six months to 30-Jun-2026. Half-year results for 1-Jan to 30-Jun-2026, disclosed to the Egyptian Exchange 29-30 July 2026. REPORTED, NOT AUDITED — a press release, not a filing
A13: Profit after tax, 6M to 30-Jun-2026 (REPORTED) | B13: 1903000000 | C13: Company | D13: 2026-06-30 | E13: Net profit after tax, six months to 30-Jun-2026. Half-year results for 1-Jan to 30-Jun-2026, disclosed to the Egyptian Exchange 29-30 July 2026. REPORTED, NOT AUDITED — a press release, not a filing
A14: Gross profit as RELEASED — rejected, see coherence test | B14: 3258000000 | C14: Company | D14: 2026-06-30 | E14: Gross profit, six months to 30-Jun-2026, AS RELEASED. This study does NOT use this figure: run through the company's own Q1-2026 expense run rates it implies a profit after tax about 12.6% above the profit the same release reports. The gross profit actually used is SOLVED from the release's own profit line, which two independent coherence tests confirm. Half-year results for 1-Jan to 30-Jun-2026, disclosed to the Egyptian Exchange 29-30 July 2026. REPORTED, NOT AUDITED — a press release, not a filing
A15: Net sales, 3M to 31-Mar-2026 (reviewed) | B15: 10510779160 | C15: Company | D15: 2026-03-31 | E15: Net sales, three months to 31-Mar-2026. Reviewed consolidated FS, three months to 31-Mar-2026
A16: Cost of sales, 3M to 31-Mar-2026 (reviewed) | B16: 9439744195 | C16: Company | D16: 2026-03-31 | E16: Cost of sales, three months to 31-Mar-2026. Reviewed consolidated FS, three months to 31-Mar-2026
A17: Administrative expense, 3M to 31-Mar-2026 | B17: 365952237 | C17: Company | D17: 2026-03-31 | E17: General and administrative expenses, three months to 31-Mar-2026. Reviewed consolidated FS, three months to 31-Mar-2026
A18: Selling expense, 3M to 31-Mar-2026 | B18: 60830975 | C18: Company | D18: 2026-03-31 | E18: Marketing and selling expenses, three months to 31-Mar-2026. Reviewed consolidated FS, three months to 31-Mar-2026
A19: Other operating expense, 3M to 31-Mar-2026 | B19: 1080000 | C19: Company | D19: 2026-03-31 | E19: Other operating expenses, three months to 31-Mar-2026. Reviewed consolidated FS, three months to 31-Mar-2026
A20: Other revenue, 3M to 31-Mar-2026 | B20: 225556509 | C20: Company | D20: 2026-03-31 | E20: Other revenue, three months to 31-Mar-2026. Reviewed consolidated FS, three months to 31-Mar-2026
A21: Formed provisions, 3M to 31-Mar-2026 | B21: 30000000 | C21: Company | D21: 2026-03-31 | E21: Formed provisions, three months to 31-Mar-2026. Reviewed consolidated FS, three months to 31-Mar-2026
... A44: Finance cost, 6M to 31-Dec-2025 | B44: 1892108 | C44: Company | D44: 2025-12-31 | E44: Finance expenses, six months to 31-Dec-2025 (note 15-E): loan interest and charges 1,130,556, lease interest 761,552. Audited consolidated FS, transition period 1-Jul-2025 to 31-Dec-2025, Crowe unqualified, 18-Feb-2026
A45: NOTE 14-A — the audited product table, 6M to 31-Dec-2025
A46: Base and special oils — tonnes sold | B46: 54968.98 | C46: Company | D46: 2025-12-31 | E46: Tonnes sold by product line, six months to 31-Dec-2025 (note 14-A). Audited consolidated FS, transition period 1-Jul-2025 to 31-Dec-2025, Crowe unqualified, 18-Feb-2026
A47: Paraffin wax — tonnes sold | B47: 41774.2 | C47: Company | D47: 2025-12-31 | E47: Tonnes sold by product line, six months to 31-Dec-2025 (note 14-A). Audited consolidated FS, transition period 1-Jul-2025 to 31-Dec-2025, Crowe unqualified, 18-Feb-2026
A48: Gas oil — tonnes sold | B48: 171684.88 | C48: Company | D48: 2025-12-31 | E48: Tonnes sold by product line, six months to 31-Dec-2025 (note 14-A). Audited consolidated FS, transition period 1-Jul-2025 to 31-Dec-2025, Crowe unqualified, 18-Feb-2026
A49: Naphtha — tonnes sold | B49: 41430.857 | C49: Company | D49: 2025-12-31 | E49: Tonnes sold by product line, six months to 31-Dec-2025 (note 14-A). Audited consolidated FS, transition period 1-Jul-2025 to 31-Dec-2025, Crowe unqualified, 18-Feb-2026
A50: Liquefied petroleum gas — tonnes sold | B50: 23735.778 | C50: Company | D50: 2025-12-31 | E50: Tonnes sold by product line, six months to 31-Dec-2025 (note 14-A). Audited consolidated FS, transition period 1-Jul-2025 to 31-Dec-2025, Crowe unqualified, 18-Feb-2026
A51: Fuel oil (mix) — tonnes sold | B51: 460153.6 | C51: Company | D51: 2025-12-31 | E51: Tonnes sold by product line, six months to 31-Dec-2025 (note 14-A). Audited consolidated FS, transition period 1-Jul-2025 to 31-Dec-2025, Crowe unqualified, 18-Feb-2026
A52: Heavy fuel oil — tonnes sold | B52: 14327.52 | C52: Company | D52: 2025-12-31 | E52: Tonnes sold by product line, six months to 31-Dec-2025 (note 14-A). Audited consolidated FS, transition period 1-Jul-2025 to 31-Dec-2025, Crowe unqualified, 18-Feb-2026
A53: Waste — tonnes sold | B53: 7.82 | C53: Company | D53: 2025-12-31 | E53: Tonnes sold by product line, six months to 31-Dec-2025 (note 14-A). Audited consolidated FS, transition period 1-Jul-2025 to 31-Dec-2025, Crowe unqualified, 18-Feb-2026
A54: Base and special oils — sales value, EGP | B54: 2597280264 | C54: Company | D54: 2025-12-31 | E54: Sales value by product line, EGP, six months to 31-Dec-2025 (note 14-A). Audited consolidated FS, transition period 1-Jul-2025 to 31-Dec-2025, Crowe unqualified, 18-Feb-2026
A55: Paraffin wax — sales value, EGP | B55: 2041969329 | C55: Company | D55: 2025-12-31 | E55: Sales value by product line, EGP, six months to 31-Dec-2025 (note 14-A). Audited consolidated FS, transition period 1-Jul-2025 to 31-Dec-2025, Crowe unqualified, 18-Feb-2026
A56: Gas oil — sales value, EGP | B56: 5121703599 | C56: Company | D56: 2025-12-31 | E56: Sales value by product line, EGP, six months to 31-Dec-2025 (note 14-A). Audited consolidated FS, transition period 1-Jul-2025 to 31-Dec-2025, Crowe unqualified, 18-Feb-2026
A57: Naphtha — sales value, EGP | B57: 958746631 | C57: Company | D57: 2025-12-31 | E57: Sales value by product line, EGP, six months to 31-Dec-2025 (note 14-A). Audited consolidated FS, transition period 1-Jul-2025 to 31-Dec-2025, Crowe unqualified, 18-Feb-2026
... A61: Waste — sales value, EGP | B61: 87400 | C61: Company | D61: 2025-12-31 | E61: Sales value by product line, EGP, six months to 31-Dec-2025 (note 14-A). Audited consolidated FS, transition period 1-Jul-2025 to 31-Dec-2025, Crowe unqualified, 18-Feb-2026
A62: NOTE 15-A — the audited cost stack, 6M to 31-Dec-2025
A63: Raw materials | B63: 17650102725 | C63: Company | D63: 2025-12-31 | E63: Cost of sales — RAW MATERIALS, six months to 31-Dec-2025 (note 15-A). 90.7% of cost of sales and 85.1% of revenue: this single line is what the company is. Audited consolidated FS, transition period 1-Jul-2025 to 31-Dec-2025, Crowe unqualified, 18-Feb-2026
A64: Salaries | B64: 881019497 | C64: Company | D64: 2025-12-31 | E64: Cost of sales — salaries, six months to 31-Dec-2025 (note 15-A). Audited consolidated FS, transition period 1-Jul-2025 to 31-Dec-2025, Crowe unqualified, 18-Feb-2026
A65: Other expenses | B65: 807146755 | C65: Company | D65: 2025-12-31 | E65: Cost of sales — other expenses, six months to 31-Dec-2025 (note 15-A): natural gas, operating electricity, operating water, spare parts, maintenance, and the operating management and technical support contract with the Egyptian Projects Operations & Maintenance Company (EPROM). Audited consolidated FS, transition period 1-Jul-2025 to 31-Dec-2025, Crowe unqualified, 18-Feb-2026
A66: Supporting materials (chemicals and additives) | B66: 64533723 | C66: Company | D66: 2025-12-31 | E66: Cost of sales — supporting materials (chemicals and additives), six months to 31-Dec-2025 (note 15-A). The previous edition estimated this charge at roughly five times the disclosed figure
A67: Depreciation | B67: 58748046 | C67: Company | D67: 2025-12-31 | E67: Cost of sales — depreciation, six months to 31-Dec-2025 (note 15-A). Audited consolidated FS, transition period 1-Jul-2025 to 31-Dec-2025, Crowe unqualified, 18-Feb-2026
A68: BALANCE SHEET AT 31 DECEMBER 2025 (AUDITED)
A69: Fixed assets, net | B69: 893016274 | C69: Company | D69: 2025-12-31 | E69: Fixed assets net of accumulated depreciation at 31-Dec-2025 (note 6). Cost 2,740,810,692 less accumulated depreciation 1,847,794,418 — the plant is 67% written down, and 273,466,121 of it is fully depreciated and still in use. Audited consolidated FS, transition period 1-Jul-2025 to 31-Dec-2025, Crowe unqualified, 18-Feb-2026
A70: Fixed assets, at COST | B70: 2740810692 | C70: Company | D70: 2025-12-31 | E70: Fixed assets at COST at 31-Dec-2025 (note 6), before accumulated depreciation of 1,847,794,418. The gross figure is what a replacement-capex line has to be built on; the net figure is what the terminal return is flattered by. Audited consolidated FS, transition period 1-Jul-2025 to 31-Dec-2025, Crowe unqualified, 18-Feb-2026
A71: Projects under construction | B71: 407323203 | C71: Company | D71: 2025-12-31 | E71: Projects under construction at 31-Dec-2025 (note 7): assets in development 376,746,526 (administrative building, warehouses, civil projects, ERP system) plus investment expenditure 30,576,677. Audited consolidated FS, transition period 1-Jul-2025 to 31-Dec-2025, Crowe unqualified, 18-Feb-2026
A72: Inventory | B72: 2847392506 | C72: Company | D72: 2025-12-31 | E72: Inventory net of impairment at 31-Dec-2025 (note 9-A): work in process 792,134,042, finished goods 1,166,168,582, spare parts 309,298,239, supporting materials 283,470,554, raw materials 118,754,225, goods for resale 155,793,361. Audited consolidated FS, transition period 1-Jul-2025 to 31-Dec-2025, Crowe unqualified, 18-Feb-2026
A73: Trade receivables | B73: 573136185 | C73: Company | D73: 2025-12-31 | E73: Accounts receivable net at 31-Dec-2025 (note 9-B). 100% undue and unimpaired on the ageing analysis. Counterparties include Shell, ExxonMobil, Chevron, Total, TAQA/Castrol, Emarat Misr, OLA Energy and Petromine alongside the state companies. Audited consolidated FS, transition period 1-Jul-2025 to 31-Dec-2025, Crowe unqualified, 18-Feb-2026
A74: Debtors and other debit balances | B74: 366012664 | C74: Company | D74: 2025-12-31 | E74: Debtors and other debit balances net at 31-Dec-2025 (notes 9-C, 9-D). Audited consolidated FS, transition period 1-Jul-2025 to 31-Dec-2025, Crowe unqualified, 18-Feb-2026
A75: Accounts and notes payable | B75: 7942650 | C75: Company | D75: 2025-12-31 | E75: Accounts and notes payable at 31-Dec-2025 (note 10-3). The previous edition modelled a trade payable of about 2.5bn funding the working capital cycle; the actual trade payable is under 8mn and the funding sits in the EGPC current account instead. Audited consolidated FS, transition period 1-Jul-2025 to 31-Dec-2025, Crowe unqualified, 18-Feb-2026
A76: Creditors and other credit balances | B76: 2044446416 | C76: Company | D76: 2025-12-31 | E76: Creditors and other credit balances at 31-Dec-2025 (note 11): EGPC current account 1,132,353,505, deposits 70,891,867, miscellaneous taxes 47,021,719, dividends payable 517,250,000, miscellaneous creditors 148,226,091, customer advances 60,028,880. Audited consolidated FS, transition period 1-Jul-2025 to 31-Dec-2025, Crowe unqualified, 18-Feb-2026
A77: of which DIVIDENDS PAYABLE — a financing claim | B77: 517250000 | C77: Company | D77: 2025-12-31 | E77: Dividends payable at 31-Dec-2025 (note 11, other credit balances) — declared and not yet paid at the reporting date. Audited consolidated FS, transition period 1-Jul-2025 to 31-Dec-2025, Crowe unqualified, 18-Feb-2026
A78: Provisions — tax disputes and claims | B78: 921440353 | C78: Company | D78: 2025-12-31 | E78: Provisions at 31-Dec-2025 (note 10-1): tax disputes 904,609,345 and claims and disputes 16,831,008. A contingent liability worth EGP 0.71 a share that the previous edition never carried at all
A79: Cash at banks and on hand, free | B79: 2463522365 | C79: Company | D79: 2025-12-31 | E79: Cash at banks and on hand at 31-Dec-2025 (note 9-E): time deposits 883,351,250 plus current accounts 2,127,100,720 plus cash on hand 166,405, less expected credit losses 38,345,960, less PLEDGED deposits 508,750,050 which sit in other financial investments. Audited consolidated FS, transition period 1-Jul-2025 to 31-Dec-2025, Crowe unqualified, 18-Feb-2026
A80: Deposits PLEDGED against facilities | B80: 508750050 | C80: Company | D80: 2025-12-31 | E80: Other financial investments at 31-Dec-2025 — deposits PLEDGED against credit facilities, so not free cash (note 9-E). Audited consolidated FS, transition period 1-Jul-2025 to 31-Dec-2025, Crowe unqualified, 18-Feb-2026
... A85: Non-controlling interest, carrying | B85: 34079000 | C85: Company | D85: 2025-12-31 | E85: Non-controlling interest carrying amount at 31-Dec-2025. Audited consolidated FS, transition period 1-Jul-2025 to 31-Dec-2025, Crowe unqualified, 18-Feb-2026
A86: DRIVERS
A87: Statutory tax rate — applied to operating profit | B87: 0.225 | C87: Country | D87: 2026 | E87: Egypt corporate income tax 22.5%. AMOC is a downstream processor and is taxed at the ordinary corporate rate, not the ~40.55% rate that applies to exploration and production concessions
A88: Feedstock pass-through factor | B88: 1 | C88: House | D88: 2026-08-06 | E88: Pass-through factor on the raw-material line: 1.0 means the feedstock charge moves one-for-one with realisation and volume, so the gross SPREAD per tonne is held flat in real terms and the margin neither widens nor narrows by assumption. Setting it below 1.0 is the way to express spread widening; the study leaves it at parity and sensitises it
A89: Terminal growth | B89: 0.05 | C89: House | D89: 2026-08-06 | E89: Terminal growth, 5% — the standing centre for established names in this market once currency turbulence has passed, sensitised 3-7%. An EGP-nominal rate struck against an EGP-nominal terminal risk-free rate
A90: Sustainable return on equity — book lens | B90: 0.28 | C90: House | D90: 2026-08-06 | E90: Sustainable return on equity for the book lens. Trailing return on average parent equity is about 33%; the sustainable rate is struck below it because the reported figure is flattered by a heavily written-down asset base that will have to be renewed
A91: Justified price/earnings — normalised lens | B91: 7.5 | C91: House | D91: 2026-08-06 | E91: Justified through-cycle price-to-earnings multiple on normalised earnings. Trailing is about 7.5x on the constructed 2025 base. A single-asset processor with a 20% state shareholder, an administered feedstock relationship and an Egyptian cost of equity near 28% does not earn a premium multiple. Bear 5.5x / bull 9.5x
A92: Re-rating on own trailing EV/EBITDA — relative lens | B92: 0 | C92: House | D92: 2026-08-06 | E92: Re-rating applied to the company's OWN trailing enterprise-value to EBITDA multiple in the relative lens. ZERO: the name is held at the multiple the market already pays it. The justified multiple is no longer a free number — it is DERIVED as the trailing multiple times one plus this figure, so it cannot drift away from the company's own pricing without the drift being visible. The previous edition set 4.5x by hand and justified it as 'holding the name at its own trailing level' against a stated trailing multiple of 'around 4.6x'; the model's own output was different, so the stated justification was false whichever way the multiple was struck. Holding at zero re-rating makes the lens a statement about the BRIDGE — what the disclosed claims on the cash are worth — rather than a disguised view on the multiple
A93: Processing intensity — Base and special oils | B93: 1 | C93: House | D93: 2026-08-06 | E93: Processing intensity by product line, relative weights, used to allocate the note 15-A conversion stack (salaries, supporting materials, other, depreciation) across the eight disclosed lines. Base oils are the reference at 1.00: they pass the full lube train — vacuum distillation, solvent extraction, dewaxing, hydrofinishing. Paraffin wax carries 1.15 for the additional deoiling and sweating steps. Gas oil, naphtha and LPG are light ends drawn off the front of the process and carry 0.25/0.20/0.15. Fuel oil and heavy fuel oil are the residue, sold substantially as produced, at 0.05. THIS IS THE ONLY OPERATING INPUT IN THE MODEL THAT IS NOT READ OFF A FILING, and it exists because note 15-A discloses the cost stack for the company and not by line. It is stated here rather than hidden in a formula, and the valuation is sensitised to it
A94: Processing intensity — Paraffin wax | B94: 1.15 | C94: House | D94: 2026-08-06 | E94: Processing intensity by product line, relative weights, used to allocate the note 15-A conversion stack (salaries, supporting materials, other, depreciation) across the eight disclosed lines. Base oils are the reference at 1.00: they pass the full lube train — vacuum distillation, solvent extraction, dewaxing, hydrofinishing. Paraffin wax carries 1.15 for the additional deoiling and sweating steps. Gas oil, naphtha and LPG are light ends drawn off the front of the process and carry 0.25/0.20/0.15. Fuel oil and heavy fuel oil are the residue, sold substantially as produced, at 0.05. THIS IS THE ONLY OPERATING INPUT IN THE MODEL THAT IS NOT READ OFF A FILING, and it exists because note 15-A discloses the cost stack for the company and not by line. It is stated here rather than hidden in a formula, and the valuation is sensitised to it
A95: Processing intensity — Gas oil | B95: 0.25 | C95: House | D95: 2026-08-06 | E95: Processing intensity by product line, relative weights, used to allocate the note 15-A conversion stack (salaries, supporting materials, other, depreciation) across the eight disclosed lines. Base oils are the reference at 1.00: they pass the full lube train — vacuum distillation, solvent extraction, dewaxing, hydrofinishing. Paraffin wax carries 1.15 for the additional deoiling and sweating steps. Gas oil, naphtha and LPG are light ends drawn off the front of the process and carry 0.25/0.20/0.15. Fuel oil and heavy fuel oil are the residue, sold substantially as produced, at 0.05. THIS IS THE ONLY OPERATING INPUT IN THE MODEL THAT IS NOT READ OFF A FILING, and it exists because note 15-A discloses the cost stack for the company and not by line. It is stated here rather than hidden in a formula, and the valuation is sensitised to it
A96: Processing intensity — Naphtha | B96: 0.2 | C96: House | D96: 2026-08-06 | E96: Processing intensity by product line, relative weights, used to allocate the note 15-A conversion stack (salaries, supporting materials, other, depreciation) across the eight disclosed lines. Base oils are the reference at 1.00: they pass the full lube train — vacuum distillation, solvent extraction, dewaxing, hydrofinishing. Paraffin wax carries 1.15 for the additional deoiling and sweating steps. Gas oil, naphtha and LPG are light ends drawn off the front of the process and carry 0.25/0.20/0.15. Fuel oil and heavy fuel oil are the residue, sold substantially as produced, at 0.05. THIS IS THE ONLY OPERATING INPUT IN THE MODEL THAT IS NOT READ OFF A FILING, and it exists because note 15-A discloses the cost stack for the company and not by line. It is stated here rather than hidden in a formula, and the valuation is sensitised to it
A97: Processing intensity — Liquefied petroleum gas | B97: 0.15 | C97: House | D97: 2026-08-06 | E97: Processing intensity by product line, relative weights, used to allocate the note 15-A conversion stack (salaries, supporting materials, other, depreciation) across the eight disclosed lines. Base oils are the reference at 1.00: they pass the full lube train — vacuum distillation, solvent extraction, dewaxing, hydrofinishing. Paraffin wax carries 1.15 for the additional deoiling and sweating steps. Gas oil, naphtha and LPG are light ends drawn off the front of the process and carry 0.25/0.20/0.15. Fuel oil and heavy fuel oil are the residue, sold substantially as produced, at 0.05. THIS IS THE ONLY OPERATING INPUT IN THE MODEL THAT IS NOT READ OFF A FILING, and it exists because note 15-A discloses the cost stack for the company and not by line. It is stated here rather than hidden in a formula, and the valuation is sensitised to it
A98: Processing intensity — Fuel oil (mix) | B98: 0.05 | C98: House | D98: 2026-08-06 | E98: Processing intensity by product line, relative weights, used to allocate the note 15-A conversion stack (salaries, supporting materials, other, depreciation) across the eight disclosed lines. Base oils are the reference at 1.00: they pass the full lube train — vacuum distillation, solvent extraction, dewaxing, hydrofinishing. Paraffin wax carries 1.15 for the additional deoiling and sweating steps. Gas oil, naphtha and LPG are light ends drawn off the front of the process and carry 0.25/0.20/0.15. Fuel oil and heavy fuel oil are the residue, sold substantially as produced, at 0.05. THIS IS THE ONLY OPERATING INPUT IN THE MODEL THAT IS NOT READ OFF A FILING, and it exists because note 15-A discloses the cost stack for the company and not by line. It is stated here rather than hidden in a formula, and the valuation is sensitised to it
... A150: Egyptian inflation factor, 2030E | B150: 1.095 | C150: Country | D150: 2026-08-06 | E150: Cumulative-year Egyptian inflation factors applied to the pound-denominated cost legs — salaries inside cost of sales, the other line, administrative and marketing expense, and capital expenditure. Historical years as printed, easing toward the central bank's published target thereafter
A151: COST OF CAPITAL
A152: Risk-free rate, Egypt 10-year local currency | B152: 0.2231 | C152: Country | D152: 2026-07-21 | E152: Egypt 10-year local-currency government bond yield, 22.31% (house cost-of-capital reference, cached 21-Jul-2026 print, re-verified 06-Aug-2026)
A153: Sovereign default spread, CDS basis | B153: 0.034 | C153: Country | D153: 2026-01-05 | E153: Egypt credit-default-swap-implied sovereign default spread, Damodaran January-2026 country-premium file, CDS column. Netted out of the local-currency risk-free rate so sovereign default risk is not charged twice
A154: Equity risk premium, CDS basis | B154: 0.0941 | C154: Country | D154: 2026-01-05 | E154: Damodaran original country-premium file, Egypt row, CDS column, last updated 5 January 2026 — total equity risk premium
A155: Beta | B155: 0.9405 | C155: House | D155: 2026-08-06 | E155: Own-stock tier-1 regression: AMOC weekly log-returns against a 33-name equal-weight Egyptian Exchange composite built from the full covered library, five-year window. R-squared 0.312, n = 257, standard error 0.087, 90% confidence interval [0.797, 1.084]. Passes the usability gate comfortably and is NOT a weak instrument: the interval spans 0.29x the point estimate, well inside the 2x flag
A156: Yield on cash | B156: 0.17 | C156: House | D156: 2026-08-06 | E156: Yield earned on the cash pile. Egyptian treasury bills and corporate deposits price a few points under the 19.50% policy rate net of the 20% withholding on interest
A157: Cost of debt | B157: 0.22 | C157: House | D157: 2026-08-06 | E157: Marginal cost of debt. The gross book is EGP 25mn — 0.06% of revenue — of short-dated Egyptian-pound facilities, so the rate is taken at the corridor lending rate of 20.00% plus a 200bp corporate spread rather than pretended to be observable. The integrity gate below computes what this input is actually WORTH to the answer
A158: CBE inflation target IN FORCE for the terminal horizon | B158: 0.07 | C158: Country | D158: 2026-08-06 | E158: The central bank's own stated inflation target, 7% (+/-2pp) on average for the fourth quarter of 2026, falling to 5% (+/-2pp) for the fourth quarter of 2028
A159: Terminal real risk-free rate | B159: 0.055 | C159: House | D159: 2026-08-06 | E159: Terminal real risk-free rate, the standard emerging-market convention. The terminal NOMINAL risk-free rate is not an input: it is DERIVED as this real rate plus the central bank's inflation target IN FORCE for the terminal horizon (`cbe_target`), so the single most terminal-value-sensitive number in the model cannot be set by hand. The previous edition hardcoded 10.50% by adding 5.5pp to the 5% target dated Q4-2028 while describing it as 'the' medium-term target; the target in force is 7% for Q4-2026 and the July-2026 rate decision pushed even that to H2-2027
A160: Terminal equity risk premium | B160: 0.07 | C160: House | D160: 2026-08-06 | E160: Terminal equity risk premium, normalised below the currently elevated crisis-era level toward the rating-class norm; never held flat into perpetuity
A161: Terminal cost of debt | B161: 0.15 | C161: House | D161: 2026-08-06 | E161: Terminal cost of debt: the midpoint of the 14-16% long-run Egyptian corporate-borrowing norm, with no name-specific reason to deviate
A162: Terminal debt weight | B162: 0.1 | C162: House | D162: 2026-08-06 | E162: Terminal debt weight, normalised. The company is net cash today and has been for years; a terminal structure carrying a tenth of capital in debt is already generous to the valuation and avoids capitalising the current zero-leverage position into perpetuity
A163: Cost-of-debt path, 2026E | B163: 0.22 | C163: House | D163: 2026-08-06 | E163: Forward cost-of-debt path 2026E-2030E, following the central bank's own disinflation path toward the long-run Egyptian corporate-borrowing norm. This path is what sets the SHAPE of the cost-of-capital glide; it is not a second free parameter
... A171: Lens weight — book | B171: 0.15 | C171: House | D171: 2026-08-06 | E171: Discounted cash flow primary for a single-asset operating processor with a visible volume ramp; the relative and normalised-earnings lenses carry equal secondary weight; the book lens least, because a substantially depreciated plant makes book value a poor proxy for replacement cost

Sheet Base Year
A1: Base year — twelve contiguous months to 30 June 2026
A2: The gross profit of the reported half is NOT taken as released. It is solved from the release's own profit line, and the released figure is shown beside it with the profit it would have implied. Every cell below is a formula.
B5: EGP | C5: Check
A6: Administrative + selling + other, 3M to 31-Mar-2026 | B6: =Assumptions!$B$17+Assumptions!$B$18+Assumptions!$B$19 -> 427863212
A7: Scaled to the half (x2) | B7: =B6*2 -> 855726424
A8: Other revenue, half | B8: =Assumptions!$B$20*2 -> 451113018
A9: Provisions and expected credit losses, half | B9: =(Assumptions!$B$21+Assumptions!$B$22)*2 -> 100646246
A10: Finance cost, half | B10: =Assumptions!$B$23*2 -> 1964438
A11: Effective tax rate, nine months (for the solve only) | B11: =(Assumptions!$B$38-Assumptions!$B$39+Assumptions!$B$40-Assumptions!$B$41)/((Assumptions!$B$38-Assumptions!$B$39+Assumptions!$B$40-Assumptions!$B$41)/0.22118761296853667) -> 0.22118761
A13: GROSS PROFIT, 6M to 30-Jun-2026 — SOLVED from the profit | B13: =Assumptions!$B$13/(1-B11)+B7-B8+B9+B10 -> 2.9506881e+09
A14: Gross profit AS RELEASED — rejected | B14: =Assumptions!$B$14 -> 3258000000
A15: Profit the released gross profit would imply | B15: =(B14-B7+B8-B9-B10)*(1-B11) -> 2.1423384e+09
A16: against the profit the same release reports | B16: =Assumptions!$B$13 -> 1903000000
A17: Overstatement in the released gross-profit line | B17: =B15/B16-1 -> 0.12576897
A19: BASE-YEAR REVENUE — twelve months to 30-Jun-2026 | B19: =(Assumptions!$B$10+Assumptions!$B$12)/10^6 -> 46958.726
A20: BASE-YEAR GROSS PROFIT | B20: =(Assumptions!$B$10-Assumptions!$B$11+B13)/10^6 -> 4224.8631
A21: BASE-YEAR COST OF SALES | B21: =B19-B20 -> 42733.863
A22: BASE-YEAR GROSS MARGIN | B22: =B20/B19 -> 0.089969714
A24: Alternative base: nine audited months x 4/3 | B24: =(Assumptions!$B$10+Assumptions!$B$15)/10^6*4/3 -> 41662.007
A25: its gross margin | B25: =(Assumptions!$B$10+Assumptions!$B$15-Assumptions!$B$11-Assumptions!$B$16)/(Assumptions!$B$10+Assumptions!$B$15) -> 0.075055115
A27: Operating lines, SAME twelve months
A28: Administrative expense | B28: =(Assumptions!$B$24+Assumptions!$B$17*2)/10^6 -> 1317.5406
A29: Selling expense | B29: =(Assumptions!$B$25+Assumptions!$B$18*2)/10^6 -> 215.39115
A30: Other operating expense | B30: =(Assumptions!$B$26+Assumptions!$B$19*2)/10^6 -> 110.94131
A31: Provisions and credit losses | B31: =(Assumptions!$B$27+(Assumptions!$B$21+Assumptions!$B$22)*2)/10^6 -> 103.11401
A32: Depreciation | B32: =(Assumptions!$B$28+Assumptions!$B$29*2)/10^6 -> 151.32049
A33: Cash capital expenditure | B33: =(Assumptions!$B$30+Assumptions!$B$31*2)/10^6 -> 160.32626
A34: Credit interest | B34: =(Assumptions!$B$32+Assumptions!$B$33*2)/10^6 -> 301.42477
A35: Employees' profit share | B35: =(Assumptions!$B$34*2)/10^6 -> 134.93574
A37: Every operating line is struck on the SAME twelve months as revenue and gross profit. The previous edition built revenue from the six-month product table doubled while taking cost of sales from the nine months scaled by four thirds, so its base-year gross margin of 7.081% corresponded to no filed period at all. One period, both sides, or the margin is an artefact of the scalars.
A39: RATES — solved, not assumed
A40: Employees' profit share, % of profit after tax | B40: =B35/((Assumptions!$B$35+Assumptions!$B$13)/10^6) -> 0.052721039
A41: Minority interest, % of OPERATING profit, whole base year | B41: =((Assumptions!$B$36+Assumptions!$B$37*2)/10^6)/((Assumptions!$B$35+Assumptions!$B$13)/10^6-B34*(1-0.22118761296853667)) -> 0.032582443
A42: Implied asset life, years = fixed assets at cost / depreciation | B42: =Assumptions!$B$70/10^6/B32 -> 18.112621
A43: Maintenance capital expenditure at cost over that life | B43: =Assumptions!$B$70/10^6/B42 -> 151.32049
A44: Inventory days of cost of sales | B44: =Assumptions!$B$72/10^6/B21*365 -> 24.320251
A45: Receivable days of revenue | B45: =(Assumptions!$B$73+Assumptions!$B$74)/10^6/B19*365 -> 7.2998005
A46: Operating payable days of cost of sales — dividends payable REMOVED | B46: =(Assumptions!$B$75+Assumptions!$B$76-Assumptions!$B$77)/10^6/B21*365 -> 13.111985

Sheet Product and Cost
A1: The eight disclosed product lines — revenue AND cost, per line
A2: Note 14-A gives tonnes and value per line. Note 15-A gives the cost stack for the company and NOT by line, so conversion is allocated on the registered processing-intensity weights and feedstock is then allocated on NET REALISABLE VALUE — the standard joint-product method. Every cell here is a formula.
A5: Line | B5: Tonnes, 6M | C5: Value, EGP 6M | D5: Realisation EGP/t | E5: Base tonnes mn | F5: Base realisation | G5: Conversion EGP/t | H5: Feedstock EGP/t | I5: Spread EGP/t
A6: Base and special oils | B6: =Assumptions!$B$46 -> 54968.98 | C6: =Assumptions!$B$54 -> 2597280264 | D6: =C6/B6 -> 47249.926 | E6: =B6*2/10^6 -> 0.10993796 | F6: =D6*$B$16 -> 53501.777 | G6: =$B$22*H6/$B$23 -> 10957.495 | H6: =Assumptions!$B$93 -> 1 | I6: =F6-G6 -> 42544.282
A7: Paraffin wax | B7: =Assumptions!$B$47 -> 41774.2 | C7: =Assumptions!$B$55 -> 2041969329 | D7: =C7/B7 -> 48881.112 | E7: =B7*2/10^6 -> 0.0835484 | F7: =D7*$B$16 -> 55348.791 | G7: =$B$22*H7/$B$23 -> 12601.119 | H7: =Assumptions!$B$94 -> 1.15 | I7: =F7-G7 -> 42747.672
A8: Gas oil | B8: =Assumptions!$B$48 -> 171684.88 | C8: =Assumptions!$B$56 -> 5121703599 | D8: =C8/B8 -> 29832.001 | E8: =B8*2/10^6 -> 0.34336976 | F8: =D8*$B$16 -> 33779.208 | G8: =$B$22*H8/$B$23 -> 2739.3737 | H8: =Assumptions!$B$95 -> 0.25 | I8: =F8-G8 -> 31039.834
A9: Naphtha | B9: =Assumptions!$B$49 -> 41430.857 | C9: =Assumptions!$B$57 -> 958746631 | D9: =C9/B9 -> 23140.883 | E9: =B9*2/10^6 -> 0.082861714 | F9: =D9*$B$16 -> 26202.758 | G9: =$B$22*H9/$B$23 -> 2191.4989 | H9: =Assumptions!$B$96 -> 0.2 | I9: =F9-G9 -> 24011.259
A10: Liquefied petroleum gas | B10: =Assumptions!$B$50 -> 23735.778 | C10: =Assumptions!$B$58 -> 816258520 | D10: =C10/B10 -> 34389.373 | E10: =B10*2/10^6 -> 0.047471556 | F10: =D10*$B$16 -> 38939.585 | G10: =$B$22*H10/$B$23 -> 1643.6242 | H10: =Assumptions!$B$97 -> 0.15 | I10: =F10-G10 -> 37295.961
A11: Fuel oil (mix) | B11: =Assumptions!$B$51 -> 460153.6 | C11: =Assumptions!$B$59 -> 8975569716 | D11: =C11/B11 -> 19505.595 | E11: =B11*2/10^6 -> 0.9203072 | F11: =D11*$B$16 -> 22086.468 | G11: =$B$22*H11/$B$23 -> 547.87473 | H11: =Assumptions!$B$98 -> 0.05 | I11: =F11-G11 -> 21538.593
A12: Heavy fuel oil | B12: =Assumptions!$B$52 -> 14327.52 | C12: =Assumptions!$B$60 -> 224110353 | D12: =C12/B12 -> 15641.95 | E12: =B12*2/10^6 -> 0.02865504 | F12: =D12*$B$16 -> 17711.607 | G12: =$B$22*H12/$B$23 -> 547.87473 | H12: =Assumptions!$B$99 -> 0.05 | I12: =F12-G12 -> 17163.732
A13: Waste | B13: =Assumptions!$B$53 -> 7.82 | C13: =Assumptions!$B$61 -> 87400 | D13: =C13/B13 -> 11176.471 | E13: =B13*2/10^6 -> 1.564e-05 | F13: =D13*$B$16 -> 12655.28 | G13: =$B$22*H13/$B$23 -> 0 | H13: =Assumptions!$B$100 -> 0 | I13: =F13-G13 -> 12655.28
A14: TOTAL | B14: =SUM(B6:B13) -> 808083.64 | C14: =SUM(C6:C13) -> 20735725812 | E14: =SUM(E6:E13) -> 1.6161673 | F14: =SUMPRODUCT(E6:E13,F6:F13) -> 46958.726
A15: Revenue at the disclosed realisations, annualised | B15: =SUMPRODUCT(E6:E13,D6:D13) -> 41471.452
A16: REALISATION INDEX — solved so the base year foots | B16: ='Base Year'!B19/B15 -> 1.1323145
A18: COST ALLOCATION
A19: Cost of sales, base year | B19: ='Base Year'!B21 -> 42733.863
A20: Feedstock share of cost (note 15-A) | B20: =Assumptions!$B$63/(Assumptions!$B$63+Assumptions!$B$64+Assumptions!$B$65+Assumptions!$B$66+Assumptions!$B$67) -> 0.9069217
A21: Feedstock total | B21: =B19*B20 -> 38756.267
A22: Conversion total | B22: =B19-B21 -> 3977.5952
A23: Processing-weighted tonnage | B23: =SUMPRODUCT(E6:E13,H6:H13) -> 0.36300225
A24: Net realisable value weighted tonnage | B24: =SUMPRODUCT(E6:E13,I6:I13) -> 42981.131
A26: Line | B26: Conversion EGP/t | C26: Net realisable EGP/t | D26: Feedstock EGP/t | E26: Total cost EGP/t | F26: Realisation EGP/t | G26: Spread EGP/t | H26: Gross margin
A27: Base and special oils | B27: =G6 -> 10957.495 | C27: =I6 -> 42544.282 | D27: =$B$21*I6/$B$24 -> 38362.359 | E27: =D27+B27 -> 49319.854 | F27: =F6 -> 53501.777 | G27: =F27-E27 -> 4181.9227 | H27: =G27/F27 -> 0.078164185
A28: Paraffin wax | B28: =G7 -> 12601.119 | C28: =I7 -> 42747.672 | D28: =$B$21*I7/$B$24 -> 38545.757 | E28: =D28+B28 -> 51146.876 | F28: =F7 -> 55348.791 | G28: =F28-E28 -> 4201.9151 | H28: =G28/F28 -> 0.075917018
A29: Gas oil | B29: =G8 -> 2739.3737 | C29: =I8 -> 31039.834 | D29: =$B$21*I8/$B$24 -> 27988.75 | E29: =D29+B29 -> 30728.123 | F29: =F8 -> 33779.208 | G29: =F29-E29 -> 3051.0842 | H29: =G29/F29 -> 0.090324328
A30: Naphtha | B30: =G9 -> 2191.4989 | C30: =I9 -> 24011.259 | D30: =$B$21*I9/$B$24 -> 21651.054 | E30: =D30+B30 -> 23842.553 | F30: =F9 -> 26202.758 | G30: =F30-E30 -> 2360.2051 | H30: =G30/F30 -> 0.090074681
A31: Liquefied petroleum gas | B31: =G10 -> 1643.6242 | C31: =I10 -> 37295.961 | D31: =$B$21*I10/$B$24 -> 33629.926 | E31: =D31+B31 -> 35273.55 | F31: =F10 -> 38939.585 | G31: =F31-E31 -> 3666.035 | H31: =G31/F31 -> 0.09414674
A32: Fuel oil (mix) | B32: =G11 -> 547.87473 | C32: =I11 -> 21538.593 | D32: =$B$21*I11/$B$24 -> 19421.441 | E32: =D32+B32 -> 19969.315 | F32: =F11 -> 22086.468 | G32: =F32-E32 -> 2117.1525 | H32: =G32/F32 -> 0.09585745
A33: Heavy fuel oil | B33: =G12 -> 547.87473 | C33: =I12 -> 17163.732 | D33: =$B$21*I12/$B$24 -> 15476.61 | E33: =D33+B33 -> 16024.485 | F33: =F12 -> 17711.607 | G33: =F33-E33 -> 1687.1222 | H33: =G33/F33 -> 0.095255173
A34: Waste | B34: =G13 -> 0 | C34: =I13 -> 12655.28 | D34: =$B$21*I13/$B$24 -> 11411.319 | E34: =D34+B34 -> 11411.319 | F34: =F13 -> 12655.28 | G34: =F34-E34 -> 1243.9604 | H34: =G34/F34 -> 0.098295765
A35: Cost of sales rebuilt from the per-line allocation | B35: =SUMPRODUCT(E6:E13,E27:E34) -> 42733.863
A36: must equal the base-year cost of sales — difference | B36: =B35-'Base Year'!B21 -> 0
A38: Row 36 is the footing test: the eight per-line costs must rebuild the disclosed cost of sales exactly. Feedstock allocated flat per tonne would make fuel oil sell below the cost of its own feed; feedstock allocated on relative sales value would make base oils and paraffin wax — the products this plant exists for — loss-making. Net realisable value is the standard joint-product method and the only one of the three that leaves every disclosed line with a positive spread.

Sheet Forecast
A1: Forecast engine — eight lines by five years, all formulas
A2: This is the block the Sensitivity sheet replicates twenty-five times, once per grid point, so that every sensitivity cell in this workbook is a live re-run rather than a pasted number.
A5: Levers for this block — the base case sets them all neutral
A6: Growth-path multiplier | B6: 1
A7: Gross-margin shift | B7: 0
A8: Realisation-path multiplier | B8: 1
A9: Working-capital cycle multiplier | B9: 1
A10: Explicit cost of capital | B10: =Assumptions!$B$152-Assumptions!$B$153+Assumptions!$B$155*Assumptions!$B$154 -> 0.27760105
A11: Equity weight | B11: =Assumptions!$B$7*Assumptions!$B$8/(Assumptions!$B$7*Assumptions!$B$8+(Assumptions!$B$82+Assumptions!$B$83-Assumptions!$B$79)/10^6) -> 1.2623542
A12: Debt weight | B12: =1-B11 -> -0.26235417
A13: After-tax cost of net debt | B13: =(Assumptions!$B$157*(Assumptions!$B$82+Assumptions!$B$83)/10^6-Assumptions!$B$156*Assumptions!$B$79/10^6)/((Assumptions!$B$82+Assumptions!$B$83-Assumptions!$B$79)/10^6)*(1-0.22118761296853667) -> 0.13206367
A14: WACC — explicit window | B14: =B11*B10+B12*B13 -> 0.31578339
A15: Terminal risk-free — DERIVED from the target in force | B15: =Assumptions!$B$158+Assumptions!$B$159 -> 0.125
A16: Terminal cost of equity | B16: =B15+Assumptions!$B$155*Assumptions!$B$160 -> 0.190835
A17: WACC — terminal | B17: =(1-Assumptions!$B$162)*B16+Assumptions!$B$162*Assumptions!$B$161*(1-0.22118761296853667) -> 0.18343369
A19: BASE CASE | B19: 2026E | C19: 2027E | D19: 2028E | E19: 2029E | F19: 2030E
A20: Inflation index, cumulative | C20: =Assumptions!$B$146 -> 1.145 | D20: =C20*Assumptions!$B$147 -> 1.29385 | E20: =D20*Assumptions!$B$148 -> 1.4426428 | F20: =E20*Assumptions!$B$149 -> 1.586907 | G20: =F20*Assumptions!$B$150 -> 1.7376632
A21: Realisation index, cumulative | C21: =(1+Assumptions!$B$101*$B$8) -> 1.09 | D21: =C21*(1+Assumptions!$B$102*$B$8) -> 1.17175 | E21: =D21*(1+Assumptions!$B$103*$B$8) -> 1.2479137 | F21: =E21*(1+Assumptions!$B$104*$B$8) -> 1.3202927 | G21: =F21*(1+Assumptions!$B$105*$B$8) -> 1.388948
A22: Volume — Base and special oils, mn t | C22: ='Product and Cost'!E6*(1+Assumptions!$B$106*$B$6) -> 0.11488517 | D22: =C22*(1+Assumptions!$B$107*$B$6) -> 0.11948057 | E22: =D22*(1+Assumptions!$B$108*$B$6) -> 0.1236624 | F22: =E22*(1+Assumptions!$B$109*$B$6) -> 0.12737227 | G22: =F22*(1+Assumptions!$B$110*$B$6) -> 0.13093869
A23: Volume — Paraffin wax, mn t | C23: ='Product and Cost'!E7*(1+Assumptions!$B$111*$B$6) -> 0.089396788 | D23: =C23*(1+Assumptions!$B$112*$B$6) -> 0.094313611 | E23: =D23*(1+Assumptions!$B$113*$B$6) -> 0.098557724 | F23: =E23*(1+Assumptions!$B$114*$B$6) -> 0.10230292 | G23: =F23*(1+Assumptions!$B$115*$B$6) -> 0.10557661
A24: Volume — Gas oil, mn t | C24: ='Product and Cost'!E8*(1+Assumptions!$B$116*$B$6) -> 0.35023716 | D24: =C24*(1+Assumptions!$B$117*$B$6) -> 0.3572419 | E24: =D24*(1+Assumptions!$B$118*$B$6) -> 0.36367225 | F24: =E24*(1+Assumptions!$B$119*$B$6) -> 0.36949101 | G24: =F24*(1+Assumptions!$B$120*$B$6) -> 0.37503338
A25: Volume — Naphtha, mn t | C25: ='Product and Cost'!E9*(1+Assumptions!$B$121*$B$6) -> 0.08410464 | D25: =C25*(1+Assumptions!$B$122*$B$6) -> 0.085618523 | E25: =D25*(1+Assumptions!$B$123*$B$6) -> 0.087159657 | F25: =E25*(1+Assumptions!$B$124*$B$6) -> 0.088554211 | G25: =F25*(1+Assumptions!$B$125*$B$6) -> 0.089882524
A26: Volume — Liquefied petroleum gas, mn t | C26: ='Product and Cost'!E10*(1+Assumptions!$B$126*$B$6) -> 0.048658345 | D26: =C26*(1+Assumptions!$B$127*$B$6) -> 0.049728828 | E26: =D26*(1+Assumptions!$B$128*$B$6) -> 0.050723405 | F26: =E26*(1+Assumptions!$B$129*$B$6) -> 0.051636426 | G26: =F26*(1+Assumptions!$B$130*$B$6) -> 0.052462609
A27: Volume — Fuel oil (mix), mn t | C27: ='Product and Cost'!E11*(1+Assumptions!$B$131*$B$6) -> 0.94791642 | D27: =C27*(1+Assumptions!$B$132*$B$6) -> 0.97256224 | E27: =D27*(1+Assumptions!$B$133*$B$6) -> 0.99395861 | F27: =E27*(1+Assumptions!$B$134*$B$6) -> 1.0138378 | G27: =F27*(1+Assumptions!$B$135*$B$6) -> 1.0320869
A28: Volume — Heavy fuel oil, mn t | C28: ='Product and Cost'!E12*(1+Assumptions!$B$136*$B$6) -> 0.029228141 | D28: =C28*(1+Assumptions!$B$137*$B$6) -> 0.029754247 | E28: =D28*(1+Assumptions!$B$138*$B$6) -> 0.030230315 | F28: =E28*(1+Assumptions!$B$139*$B$6) -> 0.03068377 | G28: =F28*(1+Assumptions!$B$140*$B$6) -> 0.031113343
A29: Volume — Waste, mn t | C29: ='Product and Cost'!E13*(1+Assumptions!$B$141*$B$6) -> 1.564e-05 | D29: =C29*(1+Assumptions!$B$142*$B$6) -> 1.564e-05 | E29: =D29*(1+Assumptions!$B$143*$B$6) -> 1.564e-05 | F29: =E29*(1+Assumptions!$B$144*$B$6) -> 1.564e-05 | G29: =F29*(1+Assumptions!$B$145*$B$6) -> 1.564e-05
A30: Total volume, mn t | C30: =SUM(C22:C29) -> 1.6644423 | D30: =SUM(D22:D29) -> 1.7087156 | E30: =SUM(E22:E29) -> 1.74798 | F30: =SUM(F22:F29) -> 1.783894 | G30: =SUM(G22:G29) -> 1.8171097
A31: REVENUE | C31: =C22*'Product and Cost'!$F$6*C21+C23*'Product and Cost'!$F$7*C21+C24*'Product and Cost'!$F$8*C21+C25*'Product and Cost'!$F$9*C21+C26*'Product and Cost'!$F$10*C21+C27*'Product and Cost'!$F$11*C21+C28*'Product and Cost'!$F$12*C21+C29*'Product and Cost'!$F$13*C21 -> 52840.811 | D31: =D22*'Product and Cost'!$F$6*D21+D23*'Product and Cost'!$F$7*D21+D24*'Product and Cost'!$F$8*D21+D25*'Product and Cost'!$F$9*D21+D26*'Product and Cost'!$F$10*D21+D27*'Product and Cost'!$F$11*D21+D28*'Product and Cost'!$F$12*D21+D29*'Product and Cost'!$F$13*D21 -> 58432.167 | E31: =E22*'Product and Cost'!$F$6*E21+E23*'Product and Cost'!$F$7*E21+E24*'Product and Cost'!$F$8*E21+E25*'Product and Cost'!$F$9*E21+E26*'Product and Cost'!$F$10*E21+E27*'Product and Cost'!$F$11*E21+E28*'Product and Cost'!$F$12*E21+E29*'Product and Cost'!$F$13*E21 -> 63772.637 | F31: =F22*'Product and Cost'!$F$6*F21+F23*'Product and Cost'!$F$7*F21+F24*'Product and Cost'!$F$8*F21+F25*'Product and Cost'!$F$9*F21+F26*'Product and Cost'!$F$10*F21+F27*'Product and Cost'!$F$11*F21+F28*'Product and Cost'!$F$12*F21+F29*'Product and Cost'!$F$13*F21 -> 68952.179 | G31: =G22*'Product and Cost'!$F$6*G21+G23*'Product and Cost'!$F$7*G21+G24*'Product and Cost'!$F$8*G21+G25*'Product and Cost'!$F$9*G21+G26*'Product and Cost'!$F$10*G21+G27*'Product and Cost'!$F$11*G21+G28*'Product and Cost'!$F$12*G21+G29*'Product and Cost'!$F$13*G21 -> 73977.843
A32: Cost of sales | C32: =C22*('Product and Cost'!$D$27*C21*Assumptions!$B$88+'Product and Cost'!$B$27*(0.4863620081*C20+0.4455809638*C20+0.0356254898*C21+0.0324315384))+C23*('Product and Cost'!$D$28*C21*Assumptions!$B$88+'Product and Cost'!$B$28*(0.4863620081*C20+0.4455809638*C20+0.0356254898*C21+0.0324315384))+C24*('Product and Cost'!$D$29*C21*Assumptions!$B$88+'Product and Cost'!$B$29*(0.4863620081*C20+0.4455809638*C20+0.0356254898*C21+0.0324315384))+C25*('Product and Cost'!$D$30*C21*Assumptions!$B$88+'Product and Cost'!$B$30*(0.4863620081*C20+0.4455809638*C20+0.0356254898*C21+0.0324315384))+C26*('Product and Cost'!$D$31*C21*Assumptions!$B$88+'Product and Cost'!$B$31*(0.4863620081*C20+0.4455809638*C20+0.0356254898*C21+0.0324315384))+C27*('Product and Cost'!$D$32*C21*Assumptions!$B$88+'Product and Cost'!$B$32*(0.4863620081*C20+0.4455809638*C20+0.0356254898*C21+0.0324315384))+C28*('Product and Cost'!$D$33*C21*Assumptions!$B$88+'Product and Cost'!$B$33*(0.4863620081*C20+0.4455809638*C20+0.0356254898*C21+0.0324315384))+C29*('Product and Cost'!$D$34*C21*Assumptions!$B$88+'Product and Cost'!$B$34*(0.4863620081*C20+0.4455809638*C20+0.0356254898*C21+0.0324315384)) -> 48291.16 | D32: =D22*('Product and Cost'!$D$27*D21*Assumptions!$B$88+'Product and Cost'!$B$27*(0.4863620081*D20+0.4455809638*D20+0.0356254898*D21+0.0324315384))+D23*('Product and Cost'!$D$28*D21*Assumptions!$B$88+'Product and Cost'!$B$28*(0.4863620081*D20+0.4455809638*D20+0.0356254898*D21+0.0324315384))+D24*('Product and Cost'!$D$29*D21*Assumptions!$B$88+'Product and Cost'!$B$29*(0.4863620081*D20+0.4455809638*D20+0.0356254898*D21+0.0324315384))+D25*('Product and Cost'!$D$30*D21*Assumptions!$B$88+'Product and Cost'!$B$30*(0.4863620081*D20+0.4455809638*D20+0.0356254898*D21+0.0324315384))+D26*('Product and Cost'!$D$31*D21*Assumptions!$B$88+'Product and Cost'!$B$31*(0.4863620081*D20+0.4455809638*D20+0.0356254898*D21+0.0324315384))+D27*('Product and Cost'!$D$32*D21*Assumptions!$B$88+'Product and Cost'!$B$32*(0.4863620081*D20+0.4455809638*D20+0.0356254898*D21+0.0324315384))+D28*('Product and Cost'!$D$33*D21*Assumptions!$B$88+'Product and Cost'!$B$33*(0.4863620081*D20+0.4455809638*D20+0.0356254898*D21+0.0324315384))+D29*('Product and Cost'!$D$34*D21*Assumptions!$B$88+'Product and Cost'!$B$34*(0.4863620081*D20+0.4455809638*D20+0.0356254898*D21+0.0324315384)) -> 53647.982 | E32: =E22*('Product and Cost'!$D$27*E21*Assumptions!$B$88+'Product and Cost'!$B$27*(0.4863620081*E20+0.4455809638*E20+0.0356254898*E21+0.0324315384))+E23*('Product and Cost'!$D$28*E21*Assumptions!$B$88+'Product and Cost'!$B$28*(0.4863620081*E20+0.4455809638*E20+0.0356254898*E21+0.0324315384))+E24*('Product and Cost'!$D$29*E21*Assumptions!$B$88+'Product and Cost'!$B$29*(0.4863620081*E20+0.4455809638*E20+0.0356254898*E21+0.0324315384))+E25*('Product and Cost'!$D$30*E21*Assumptions!$B$88+'Product and Cost'!$B$30*(0.4863620081*E20+0.4455809638*E20+0.0356254898*E21+0.0324315384))+E26*('Product and Cost'!$D$31*E21*Assumptions!$B$88+'Product and Cost'!$B$31*(0.4863620081*E20+0.4455809638*E20+0.0356254898*E21+0.0324315384))+E27*('Product and Cost'!$D$32*E21*Assumptions!$B$88+'Product and Cost'!$B$32*(0.4863620081*E20+0.4455809638*E20+0.0356254898*E21+0.0324315384))+E28*('Product and Cost'!$D$33*E21*Assumptions!$B$88+'Product and Cost'!$B$33*(0.4863620081*E20+0.4455809638*E20+0.0356254898*E21+0.0324315384))+E29*('Product and Cost'!$D$34*E21*Assumptions!$B$88+'Product and Cost'!$B$34*(0.4863620081*E20+0.4455809638*E20+0.0356254898*E21+0.0324315384)) -> 58815.401 | F32: =F22*('Product and Cost'!$D$27*F21*Assumptions!$B$88+'Product and Cost'!$B$27*(0.4863620081*F20+0.4455809638*F20+0.0356254898*F21+0.0324315384))+F23*('Product and Cost'!$D$28*F21*Assumptions!$B$88+'Product and Cost'!$B$28*(0.4863620081*F20+0.4455809638*F20+0.0356254898*F21+0.0324315384))+F24*('Product and Cost'!$D$29*F21*Assumptions!$B$88+'Product and Cost'!$B$29*(0.4863620081*F20+0.4455809638*F20+0.0356254898*F21+0.0324315384))+F25*('Product and Cost'!$D$30*F21*Assumptions!$B$88+'Product and Cost'!$B$30*(0.4863620081*F20+0.4455809638*F20+0.0356254898*F21+0.0324315384))+F26*('Product and Cost'!$D$31*F21*Assumptions!$B$88+'Product and Cost'!$B$31*(0.4863620081*F20+0.4455809638*F20+0.0356254898*F21+0.0324315384))+F27*('Product and Cost'!$D$32*F21*Assumptions!$B$88+'Product and Cost'!$B$32*(0.4863620081*F20+0.4455809638*F20+0.0356254898*F21+0.0324315384))+F28*('Product and Cost'!$D$33*F21*Assumptions!$B$88+'Product and Cost'!$B$33*(0.4863620081*F20+0.4455809638*F20+0.0356254898*F21+0.0324315384))+F29*('Product and Cost'!$D$34*F21*Assumptions!$B$88+'Product and Cost'!$B$34*(0.4863620081*F20+0.4455809638*F20+0.0356254898*F21+0.0324315384)) -> 63847.573 | G32: =G22*('Product and Cost'!$D$27*G21*Assumptions!$B$88+'Product and Cost'!$B$27*(0.4863620081*G20+0.4455809638*G20+0.0356254898*G21+0.0324315384))+G23*('Product and Cost'!$D$28*G21*Assumptions!$B$88+'Product and Cost'!$B$28*(0.4863620081*G20+0.4455809638*G20+0.0356254898*G21+0.0324315384))+G24*('Product and Cost'!$D$29*G21*Assumptions!$B$88+'Product and Cost'!$B$29*(0.4863620081*G20+0.4455809638*G20+0.0356254898*G21+0.0324315384))+G25*('Product and Cost'!$D$30*G21*Assumptions!$B$88+'Product and Cost'!$B$30*(0.4863620081*G20+0.4455809638*G20+0.0356254898*G21+0.0324315384))+G26*('Product and Cost'!$D$31*G21*Assumptions!$B$88+'Product and Cost'!$B$31*(0.4863620081*G20+0.4455809638*G20+0.0356254898*G21+0.0324315384))+G27*('Product and Cost'!$D$32*G21*Assumptions!$B$88+'Product and Cost'!$B$32*(0.4863620081*G20+0.4455809638*G20+0.0356254898*G21+0.0324315384))+G28*('Product and Cost'!$D$33*G21*Assumptions!$B$88+'Product and Cost'!$B$33*(0.4863620081*G20+0.4455809638*G20+0.0356254898*G21+0.0324315384))+G29*('Product and Cost'!$D$34*G21*Assumptions!$B$88+'Product and Cost'!$B$34*(0.4863620081*G20+0.4455809638*G20+0.0356254898*G21+0.0324315384)) -> 68797.186
A33: GROSS PROFIT | C33: =C31-C32+$B$7*C31 -> 4549.6506 | D33: =D31-D32+$B$7*D31 -> 4784.1849 | E33: =E31-E32+$B$7*E31 -> 4957.236 | F33: =F31-F32+$B$7*F31 -> 5104.6058 | G33: =G31-G32+$B$7*G31 -> 5180.6573
A34: Gross margin | C34: =C33/C31 -> 0.086101075 | D34: =D33/D31 -> 0.081875877 | E34: =E33/E31 -> 0.077732962 | F34: =F33/F31 -> 0.074031102 | G34: =G33/G31 -> 0.07002985
A35: Operating expense | C35: =('Base Year'!$B$28*C20)+('Base Year'!$B$29*C20*C30/'Product and Cost'!$E$14)+('Base Year'!$B$30*C20)+('Base Year'!$B$31*C20) -> 2007.6668 | D35: =('Base Year'!$B$28*D20)+('Base Year'!$B$29*D20*D30/'Product and Cost'!$E$14)+('Base Year'!$B$30*D20)+('Base Year'!$B$31*D20) -> 2276.2978 | E35: =('Base Year'!$B$28*E20)+('Base Year'!$B$29*E20*E30/'Product and Cost'!$E$14)+('Base Year'!$B$30*E20)+('Base Year'!$B$31*E20) -> 2545.6212 | F35: =('Base Year'!$B$28*F20)+('Base Year'!$B$29*F20*F30/'Product and Cost'!$E$14)+('Base Year'!$B$30*F20)+('Base Year'!$B$31*F20) -> 2807.7788 | G35: =('Base Year'!$B$28*G20)+('Base Year'!$B$29*G20*G30/'Product and Cost'!$E$14)+('Base Year'!$B$30*G20)+('Base Year'!$B$31*G20) -> 3082.21
A36: EBITDA | C36: =C33-C35 -> 2541.9838 | D36: =D33-D35 -> 2507.8872 | E36: =E33-E35 -> 2411.6148 | F36: =F33-F35 -> 2296.827 | G36: =G33-G35 -> 2098.4473
A37: Capital expenditure — maintenance + growth | C37: ='Base Year'!$B$43*C20+MAX(C30-'Product and Cost'!$E$14,0)*1947.901031*C20 -> 280.932 | D37: ='Base Year'!$B$43*D20+MAX(D30-C30,0)*1947.901031*D20 -> 307.36758 | E37: ='Base Year'!$B$43*E20+MAX(E30-D30,0)*1947.901031*E20 -> 328.63939 | F37: ='Base Year'!$B$43*F20+MAX(F30-E30,0)*1947.901031*F20 -> 351.14675 | G37: ='Base Year'!$B$43*G20+MAX(G30-F30,0)*1947.901031*G20 -> 375.37218
A38: Fixed assets at cost, closing | C38: =(Assumptions!$B$70+Assumptions!$B$71)/10^6+C37 -> 3429.0659 | D38: =C38+D37 -> 3736.4335 | E38: =D38+E37 -> 4065.0729 | F38: =E38+F37 -> 4416.2196 | G38: =F38+G37 -> 4791.5918
A39: Depreciation — rolls off the asset register | C39: =(Assumptions!$B$70+Assumptions!$B$71)/10^6/'Base Year'!$B$42 -> 173.80885 | D39: =C38/'Base Year'!$B$42 -> 189.31914 | E39: =D38/'Base Year'!$B$42 -> 206.28895 | F39: =E38/'Base Year'!$B$42 -> 224.43317 | G39: =F38/'Base Year'!$B$42 -> 243.82002
A40: Fixed assets, net book, closing | C40: =(Assumptions!$B$69+Assumptions!$B$71)/10^6+C37-C39 -> 1407.4626 | D40: =C40+D37-D39 -> 1525.5111 | E40: =D40+E37-E39 -> 1647.8615 | F40: =E40+F37-F39 -> 1774.5751 | G40: =F40+G37-G39 -> 1906.1272
A41: EBIT | C41: =C36-C39 -> 2368.175 | D41: =D36-D39 -> 2318.568 | E41: =E36-E39 -> 2205.3259 | F41: =F36-F39 -> 2072.3938 | G41: =G36-G39 -> 1854.6273
A42: NOPAT before the profit share | C42: =C41*(1-Assumptions!$B$87) -> 1835.3356 | D42: =D41*(1-Assumptions!$B$87) -> 1796.8902 | E42: =E41*(1-Assumptions!$B$87) -> 1709.1276 | F42: =F41*(1-Assumptions!$B$87) -> 1606.1052 | G42: =G41*(1-Assumptions!$B$87) -> 1437.3361
A43: less employees' profit share and board bonuses | C43: =MAX(C42,0)*'Base Year'!$B$40 -> 96.760801 | D43: =MAX(D42,0)*'Base Year'!$B$40 -> 94.73392 | E43: =MAX(E42,0)*'Base Year'!$B$40 -> 90.106981 | F43: =MAX(F42,0)*'Base Year'!$B$40 -> 84.675535 | G43: =MAX(G42,0)*'Base Year'!$B$40 -> 75.777855
A44: NOPAT | C44: =C42-C43 -> 1738.5748 | D44: =D42-D43 -> 1702.1563 | E44: =E42-E43 -> 1619.0206 | F44: =F42-F43 -> 1521.4297 | G44: =G42-G43 -> 1361.5583
A45: Net working capital — on days | C45: ='Base Year'!$B$44*$B$9/365*C32+'Base Year'!$B$45*$B$9/365*C31-'Base Year'!$B$46*$B$9/365*C32 -> 2539.6919 | D45: ='Base Year'!$B$44*$B$9/365*D32+'Base Year'!$B$45*$B$9/365*D31-'Base Year'!$B$46*$B$9/365*D32 -> 2816.011 | E45: ='Base Year'!$B$44*$B$9/365*E32+'Base Year'!$B$45*$B$9/365*E31-'Base Year'!$B$46*$B$9/365*E32 -> 3081.4964 | F45: ='Base Year'!$B$44*$B$9/365*F32+'Base Year'!$B$45*$B$9/365*F31-'Base Year'!$B$46*$B$9/365*F32 -> 3339.6103 | G45: ='Base Year'!$B$44*$B$9/365*G32+'Base Year'!$B$45*$B$9/365*G31-'Base Year'!$B$46*$B$9/365*G32 -> 3592.1114
A46: change in working capital | C46: =C45-('Base Year'!$B$44/365*'Base Year'!$B$21+'Base Year'!$B$45/365*'Base Year'!$B$19-'Base Year'!$B$46/365*'Base Year'!$B$21) -> 288.28965 | D46: =D45-C45 -> 276.31909 | E46: =E45-D45 -> 265.4854 | F46: =F45-E45 -> 258.11383 | G46: =G45-F45 -> 252.50115
A47: FREE CASH FLOW TO THE FIRM | C47: =C44+C39-C37-C46 -> 1343.162 | D47: =D44+D39-D37-D46 -> 1307.7888 | E47: =E44+E39-E37-E46 -> 1231.1847 | F47: =F44+F39-F37-F46 -> 1136.6022 | G47: =G44+G39-G37-G46 -> 977.50496
A48: Glide fraction | C48: =0.0000000000 -> 0 | D48: =0.3571428571 -> 0.35714286 | E48: =0.6428571429 -> 0.64285714 | F48: =0.8571428571 -> 0.85714286 | G48: =1.0000000000 -> 1
A49: Forward cost of capital | C49: =$B$14-($B$14-$B$17)*C48 -> 0.31578339 | D49: =$B$14-($B$14-$B$17)*D48 -> 0.26851564 | E49: =$B$14-($B$14-$B$17)*E48 -> 0.23070144 | F49: =$B$14-($B$14-$B$17)*F48 -> 0.20234079 | G49: =$B$14-($B$14-$B$17)*G48 -> 0.18343369
A50: Cumulative discount factor | C50: =1/(1+C49) -> 0.76000351 | D50: =C50/(1+D49) -> 0.59912822 | E50: =D50/(1+E49) -> 0.48681849 | F50: =E50/(1+F49) -> 0.40489227 | G50: =F50/(1+G49) -> 0.34213347
A51: Present value | C51: =C47*C50 -> 1020.8079 | D51: =D47*D50 -> 783.53316 | E51: =E47*E50 -> 599.36349 | F51: =F47*F50 -> 460.20146 | G51: =G47*G50 -> 334.43716
A52: PV of the explicit window | B52: =SUM(C51:G51) -> 3198.3431 | C52: =C45+C38 -> 5968.7578 | D52: =D45+D38 -> 6552.4445 | E52: =E45+E38 -> 7146.5693 | F52: =F45+F38 -> 7755.8299 | G52: =G45+G38 -> 8383.7032
A53: Terminal return on invested capital, at REPLACEMENT cost | B53: =G44*(1+Assumptions!$B$89)/G52 -> 0.17052562
A54: Required reinvestment = growth / return | B54: =MIN(Assumptions!$B$89/B53,0.95) -> 0.29321107
A55: Terminal value | B55: =G44*(1+Assumptions!$B$89)*(1-B54)/MAX($B$17-Assumptions!$B$89,0.02) -> 7572.6832
A56: PV of the terminal block | B56: =B55*G50 -> 2590.8684
A57: ENTERPRISE VALUE | B57: =B52+B56 -> 5789.2115
A58: plus net cash | B58: =(Assumptions!$B$79-Assumptions!$B$82-Assumptions!$B$83)/10^6 -> 2442.5449
A59: Enterprise value including cash | B59: =B57+B58 -> 8231.7564
A60: less minority — on the WHOLE enterprise, cash included | B60: =B59*'Base Year'!$B$41 -> 268.21073
A61: less the tax-disputes provision | B61: =Assumptions!$B$78/10^6 -> 921.44035
A62: less dividends payable — declared, out of working capital | B62: =Assumptions!$B$77/10^6 -> 517.25
A63: plus non-operating investments and pledged deposits | B63: =(Assumptions!$B$81+Assumptions!$B$80)/10^6 -> 578.35875
A64: EQUITY ATTRIBUTABLE | B64: =B59-B60-B61-B62+B63 -> 7103.2141
A65: VALUE PER SHARE, EGP | B65: =B64/Assumptions!$B$8 -> 5.4999722

Sheet Sensitivity
A1: Sensitivity — every grid point is the whole engine, again, in formulas
A2: The previous edition pasted these rows because each point is a whole-model re-run and its builder could not express a re-run inside a grid. Three of the pasted rows turned out not to reproduce: a working-capital row whose grid was never sorted, a beta row whose centre did not return the base case, and a volume row whose label described a different scenario from the one it ran. None of that can happen here, because there is nothing to paste.
A4: Summary — every cell points at its own live block below
A5: Gross margin, shifted on every forecast year
A6: grid point 1: -1.0% | C6: -0.01 | I6: =B95 -> 3.5279033
A7: grid point 2: -0.5% | C7: -0.005 | I7: =B144 -> 4.5139377
A8: grid point 3: +0.0% | C8: 0 | I8: =B193 -> 5.4999722 | J8: =B193-Forecast!B65 -> 0
A9: grid point 4: +0.5% | C9: 0.005 | I9: =B242 -> 6.4860066
A10: grid point 5: +1.0% | C10: 0.01 | I10: =B291 -> 7.4720411
A12: Volume growth path, as a multiple of the assumed path
A13: grid point 1: 0.00x | B13: 0 | I13: =B340 -> 4.827847
A14: grid point 2: 0.50x | B14: 0.5 | I14: =B389 -> 5.1577708
A15: grid point 3: 1.00x | B15: 1 | I15: =B438 -> 5.4999722 | J15: =B438-Forecast!B65 -> 0
A16: grid point 4: 1.50x | B16: 1.5 | I16: =B487 -> 5.8548333
A17: grid point 5: 2.00x | B17: 2 | I17: =B536 -> 6.222745
A19: Realisation path, as a multiple of the assumed path
A20: grid point 1: 0.90x | D20: 0.9 | I20: =B585 -> 4.661187
A21: grid point 2: 0.95x | D21: 0.95 | I21: =B634 -> 5.0782512
A22: grid point 3: 1.00x | D22: 1 | I22: =B683 -> 5.4999722 | J22: =B683-Forecast!B65 -> 0
A23: grid point 4: 1.05x | D23: 1.05 | I23: =B732 -> 5.9263909
A24: grid point 5: 1.10x | D24: 1.1 | I24: =B781 -> 6.3575484
A26: Beta
A27: grid point 1: 0.6000 | F27: 0.27533624 | G27: 0.16198219 | I27: =B830 -> 6.3325863
A28: grid point 2: 0.8000 | F28: 0.29909374 | G28: 0.17458219 | I28: =B879 -> 5.8089209
A29: grid point 3: 0.9405 | F29: 0.31578339 | G29: 0.18343369 | I29: =B928 -> 5.4999722 | J29: =B928-Forecast!B65 -> -8.8817842e-16
A30: grid point 4: 1.1500 | F30: 0.34066938 | G30: 0.19663219 | I30: =B977 -> 5.1083087
A31: grid point 5: 1.3000 | F31: 0.35848751 | G31: 0.20608219 | I31: =B1026 -> 4.8684118
A33: Working-capital cycle, as a multiple of the solved days
A34: grid point 1: 0.50x | E34: 0.5 | I34: =B1075 -> 6.5772729
A35: grid point 2: 0.75x | E35: 0.75 | I35: =B1124 -> 6.0386225
A36: grid point 3: 1.00x | E36: 1 | I36: =B1173 -> 5.4999722 | J36: =B1173-Forecast!B65 -> 0
A37: grid point 4: 1.25x | E37: 1.25 | I37: =B1222 -> 4.9613218
A38: grid point 5: 1.50x | E38: 1.5 | I38: =B1271 -> 4.4226715
A40: Terminal growth
A41: grid point 1: 3.0% | H41: 0.03 | I41: =B1320 -> 5.4815809
A42: grid point 2: 4.0% | H42: 0.04 | I42: =B1369 -> 5.4901354
A43: grid point 3: 5.0% | H43: 0.05 | I43: =B1418 -> 5.4999722 | J43: =B1418-Forecast!B65 -> 0
A44: grid point 4: 6.0% | H44: 0.06 | I44: =B1467 -> 5.5114028
A45: grid point 5: 7.0% | H45: 0.07 | I45: =B1516 -> 5.5248488
A47: GATE — every row must return the base case at its own base point
A49: Gross margin, shifted on every forecast year — -1.0% | B49: 2026E | C49: 2027E | D49: 2028E | E49: 2029E | F49: 2030E
A50: Inflation index, cumulative | C50: =Assumptions!$B$146 -> 1.145 | D50: =C50*Assumptions!$B$147 -> 1.29385 | E50: =D50*Assumptions!$B$148 -> 1.4426428 | F50: =E50*Assumptions!$B$149 -> 1.586907 | G50: =F50*Assumptions!$B$150 -> 1.7376632
A51: Realisation index, cumulative | C51: =(1+Assumptions!$B$101*Forecast!$B$8) -> 1.09 | D51: =C51*(1+Assumptions!$B$102*Forecast!$B$8) -> 1.17175 | E51: =D51*(1+Assumptions!$B$103*Forecast!$B$8) -> 1.2479137 | F51: =E51*(1+Assumptions!$B$104*Forecast!$B$8) -> 1.3202927 | G51: =F51*(1+Assumptions!$B$105*Forecast!$B$8) -> 1.388948
A52: Volume — Base and special oils, mn t | C52: ='Product and Cost'!E6*(1+Assumptions!$B$106*Forecast!$B$6) -> 0.11488517 | D52: =C52*(1+Assumptions!$B$107*Forecast!$B$6) -> 0.11948057 | E52: =D52*(1+Assumptions!$B$108*Forecast!$B$6) -> 0.1236624 | F52: =E52*(1+Assumptions!$B$109*Forecast!$B$6) -> 0.12737227 | G52: =F52*(1+Assumptions!$B$110*Forecast!$B$6) -> 0.13093869
A53: Volume — Paraffin wax, mn t | C53: ='Product and Cost'!E7*(1+Assumptions!$B$111*Forecast!$B$6) -> 0.089396788 | D53: =C53*(1+Assumptions!$B$112*Forecast!$B$6) -> 0.094313611 | E53: =D53*(1+Assumptions!$B$113*Forecast!$B$6) -> 0.098557724 | F53: =E53*(1+Assumptions!$B$114*Forecast!$B$6) -> 0.10230292 | G53: =F53*(1+Assumptions!$B$115*Forecast!$B$6) -> 0.10557661
A54: Volume — Gas oil, mn t | C54: ='Product and Cost'!E8*(1+Assumptions!$B$116*Forecast!$B$6) -> 0.35023716 | D54: =C54*(1+Assumptions!$B$117*Forecast!$B$6) -> 0.3572419 | E54: =D54*(1+Assumptions!$B$118*Forecast!$B$6) -> 0.36367225 | F54: =E54*(1+Assumptions!$B$119*Forecast!$B$6) -> 0.36949101 | G54: =F54*(1+Assumptions!$B$120*Forecast!$B$6) -> 0.37503338
A55: Volume — Naphtha, mn t | C55: ='Product and Cost'!E9*(1+Assumptions!$B$121*Forecast!$B$6) -> 0.08410464 | D55: =C55*(1+Assumptions!$B$122*Forecast!$B$6) -> 0.085618523 | E55: =D55*(1+Assumptions!$B$123*Forecast!$B$6) -> 0.087159657 | F55: =E55*(1+Assumptions!$B$124*Forecast!$B$6) -> 0.088554211 | G55: =F55*(1+Assumptions!$B$125*Forecast!$B$6) -> 0.089882524
A56: Volume — Liquefied petroleum gas, mn t | C56: ='Product and Cost'!E10*(1+Assumptions!$B$126*Forecast!$B$6) -> 0.048658345 | D56: =C56*(1+Assumptions!$B$127*Forecast!$B$6) -> 0.049728828 | E56: =D56*(1+Assumptions!$B$128*Forecast!$B$6) -> 0.050723405 | F56: =E56*(1+Assumptions!$B$129*Forecast!$B$6) -> 0.051636426 | G56: =F56*(1+Assumptions!$B$130*Forecast!$B$6) -> 0.052462609
A57: Volume — Fuel oil (mix), mn t | C57: ='Product and Cost'!E11*(1+Assumptions!$B$131*Forecast!$B$6) -> 0.94791642 | D57: =C57*(1+Assumptions!$B$132*Forecast!$B$6) -> 0.97256224 | E57: =D57*(1+Assumptions!$B$133*Forecast!$B$6) -> 0.99395861 | F57: =E57*(1+Assumptions!$B$134*Forecast!$B$6) -> 1.0138378 | G57: =F57*(1+Assumptions!$B$135*Forecast!$B$6) -> 1.0320869
A58: Volume — Heavy fuel oil, mn t | C58: ='Product and Cost'!E12*(1+Assumptions!$B$136*Forecast!$B$6) -> 0.029228141 | D58: =C58*(1+Assumptions!$B$137*Forecast!$B$6) -> 0.029754247 | E58: =D58*(1+Assumptions!$B$138*Forecast!$B$6) -> 0.030230315 | F58: =E58*(1+Assumptions!$B$139*Forecast!$B$6) -> 0.03068377 | G58: =F58*(1+Assumptions!$B$140*Forecast!$B$6) -> 0.031113343
A59: Volume — Waste, mn t | C59: ='Product and Cost'!E13*(1+Assumptions!$B$141*Forecast!$B$6) -> 1.564e-05 | D59: =C59*(1+Assumptions!$B$142*Forecast!$B$6) -> 1.564e-05 | E59: =D59*(1+Assumptions!$B$143*Forecast!$B$6) -> 1.564e-05 | F59: =E59*(1+Assumptions!$B$144*Forecast!$B$6) -> 1.564e-05 | G59: =F59*(1+Assumptions!$B$145*Forecast!$B$6) -> 1.564e-05
A60: Total volume, mn t | C60: =SUM(C52:C59) -> 1.6644423 | D60: =SUM(D52:D59) -> 1.7087156 | E60: =SUM(E52:E59) -> 1.74798 | F60: =SUM(F52:F59) -> 1.783894 | G60: =SUM(G52:G59) -> 1.8171097
A61: REVENUE | C61: =C52*'Product and Cost'!$F$6*C51+C53*'Product and Cost'!$F$7*C51+C54*'Product and Cost'!$F$8*C51+C55*'Product and Cost'!$F$9*C51+C56*'Product and Cost'!$F$10*C51+C57*'Product and Cost'!$F$11*C51+C58*'Product and Cost'!$F$12*C51+C59*'Product and Cost'!$F$13*C51 -> 52840.811 | D61: =D52*'Product and Cost'!$F$6*D51+D53*'Product and Cost'!$F$7*D51+D54*'Product and Cost'!$F$8*D51+D55*'Product and Cost'!$F$9*D51+D56*'Product and Cost'!$F$10*D51+D57*'Product and Cost'!$F$11*D51+D58*'Product and Cost'!$F$12*D51+D59*'Product and Cost'!$F$13*D51 -> 58432.167 | E61: =E52*'Product and Cost'!$F$6*E51+E53*'Product and Cost'!$F$7*E51+E54*'Product and Cost'!$F$8*E51+E55*'Product and Cost'!$F$9*E51+E56*'Product and Cost'!$F$10*E51+E57*'Product and Cost'!$F$11*E51+E58*'Product and Cost'!$F$12*E51+E59*'Product and Cost'!$F$13*E51 -> 63772.637 | F61: =F52*'Product and Cost'!$F$6*F51+F53*'Product and Cost'!$F$7*F51+F54*'Product and Cost'!$F$8*F51+F55*'Product and Cost'!$F$9*F51+F56*'Product and Cost'!$F$10*F51+F57*'Product and Cost'!$F$11*F51+F58*'Product and Cost'!$F$12*F51+F59*'Product and Cost'!$F$13*F51 -> 68952.179 | G61: =G52*'Product and Cost'!$F$6*G51+G53*'Product and Cost'!$F$7*G51+G54*'Product and Cost'!$F$8*G51+G55*'Product and Cost'!$F$9*G51+G56*'Product and Cost'!$F$10*G51+G57*'Product and Cost'!$F$11*G51+G58*'Product and Cost'!$F$12*G51+G59*'Product and Cost'!$F$13*G51 -> 73977.843
A62: Cost of sales | C62: =C52*('Product and Cost'!$D$27*C51*Assumptions!$B$88+'Product and Cost'!$B$27*(0.4863620081*C50+0.4455809638*C50+0.0356254898*C51+0.0324315384))+C53*('Product and Cost'!$D$28*C51*Assumptions!$B$88+'Product and Cost'!$B$28*(0.4863620081*C50+0.4455809638*C50+0.0356254898*C51+0.0324315384))+C54*('Product and Cost'!$D$29*C51*Assumptions!$B$88+'Product and Cost'!$B$29*(0.4863620081*C50+0.4455809638*C50+0.0356254898*C51+0.0324315384))+C55*('Product and Cost'!$D$30*C51*Assumptions!$B$88+'Product and Cost'!$B$30*(0.4863620081*C50+0.4455809638*C50+0.0356254898*C51+0.0324315384))+C56*('Product and Cost'!$D$31*C51*Assumptions!$B$88+'Product and Cost'!$B$31*(0.4863620081*C50+0.4455809638*C50+0.0356254898*C51+0.0324315384))+C57*('Product and Cost'!$D$32*C51*Assumptions!$B$88+'Product and Cost'!$B$32*(0.4863620081*C50+0.4455809638*C50+0.0356254898*C51+0.0324315384))+C58*('Product and Cost'!$D$33*C51*Assumptions!$B$88+'Product and Cost'!$B$33*(0.4863620081*C50+0.4455809638*C50+0.0356254898*C51+0.0324315384))+C59*('Product and Cost'!$D$34*C51*Assumptions!$B$88+'Product and Cost'!$B$34*(0.4863620081*C50+0.4455809638*C50+0.0356254898*C51+0.0324315384)) -> 48291.16 | D62: =D52*('Product and Cost'!$D$27*D51*Assumptions!$B$88+'Product and Cost'!$B$27*(0.4863620081*D50+0.4455809638*D50+0.0356254898*D51+0.0324315384))+D53*('Product and Cost'!$D$28*D51*Assumptions!$B$88+'Product and Cost'!$B$28*(0.4863620081*D50+0.4455809638*D50+0.0356254898*D51+0.0324315384))+D54*('Product and Cost'!$D$29*D51*Assumptions!$B$88+'Product and Cost'!$B$29*(0.4863620081*D50+0.4455809638*D50+0.0356254898*D51+0.0324315384))+D55*('Product and Cost'!$D$30*D51*Assumptions!$B$88+'Product and Cost'!$B$30*(0.4863620081*D50+0.4455809638*D50+0.0356254898*D51+0.0324315384))+D56*('Product and Cost'!$D$31*D51*Assumptions!$B$88+'Product and Cost'!$B$31*(0.4863620081*D50+0.4455809638*D50+0.0356254898*D51+0.0324315384))+D57*('Product and Cost'!$D$32*D51*Assumptions!$B$88+'Product and Cost'!$B$32*(0.4863620081*D50+0.4455809638*D50+0.0356254898*D51+0.0324315384))+D58*('Product and Cost'!$D$33*D51*Assumptions!$B$88+'Product and Cost'!$B$33*(0.4863620081*D50+0.4455809638*D50+0.0356254898*D51+0.0324315384))+D59*('Product and Cost'!$D$34*D51*Assumptions!$B$88+'Product and Cost'!$B$34*(0.4863620081*D50+0.4455809638*D50+0.0356254898*D51+0.0324315384)) -> 53647.982 | E62: =E52*('Product and Cost'!$D$27*E51*Assumptions!$B$88+'Product and Cost'!$B$27*(0.4863620081*E50+0.4455809638*E50+0.0356254898*E51+0.0324315384))+E53*('Product and Cost'!$D$28*E51*Assumptions!$B$88+'Product and Cost'!$B$28*(0.4863620081*E50+0.4455809638*E50+0.0356254898*E51+0.0324315384))+E54*('Product and Cost'!$D$29*E51*Assumptions!$B$88+'Product and Cost'!$B$29*(0.4863620081*E50+0.4455809638*E50+0.0356254898*E51+0.0324315384))+E55*('Product and Cost'!$D$30*E51*Assumptions!$B$88+'Product and Cost'!$B$30*(0.4863620081*E50+0.4455809638*E50+0.0356254898*E51+0.0324315384))+E56*('Product and Cost'!$D$31*E51*Assumptions!$B$88+'Product and Cost'!$B$31*(0.4863620081*E50+0.4455809638*E50+0.0356254898*E51+0.0324315384))+E57*('Product and Cost'!$D$32*E51*Assumptions!$B$88+'Product and Cost'!$B$32*(0.4863620081*E50+0.4455809638*E50+0.0356254898*E51+0.0324315384))+E58*('Product and Cost'!$D$33*E51*Assumptions!$B$88+'Product and Cost'!$B$33*(0.4863620081*E50+0.4455809638*E50+0.0356254898*E51+0.0324315384))+E59*('Product and Cost'!$D$34*E51*Assumptions!$B$88+'Product and Cost'!$B$34*(0.4863620081*E50+0.4455809638*E50+0.0356254898*E51+0.0324315384)) -> 58815.401 | F62: =F52*('Product and Cost'!$D$27*F51*Assumptions!$B$88+'Product and Cost'!$B$27*(0.4863620081*F50+0.4455809638*F50+0.0356254898*F51+0.0324315384))+F53*('Product and Cost'!$D$28*F51*Assumptions!$B$88+'Product and Cost'!$B$28*(0.4863620081*F50+0.4455809638*F50+0.0356254898*F51+0.0324315384))+F54*('Product and Cost'!$D$29*F51*Assumptions!$B$88+'Product and Cost'!$B$29*(0.4863620081*F50+0.4455809638*F50+0.0356254898*F51+0.0324315384))+F55*('Product and Cost'!$D$30*F51*Assumptions!$B$88+'Product and Cost'!$B$30*(0.4863620081*F50+0.4455809638*F50+0.0356254898*F51+0.0324315384))+F56*('Product and Cost'!$D$31*F51*Assumptions!$B$88+'Product and Cost'!$B$31*(0.4863620081*F50+0.4455809638*F50+0.0356254898*F51+0.0324315384))+F57*('Product and Cost'!$D$32*F51*Assumptions!$B$88+'Product and Cost'!$B$32*(0.4863620081*F50+0.4455809638*F50+0.0356254898*F51+0.0324315384))+F58*('Product and Cost'!$D$33*F51*Assumptions!$B$88+'Product and Cost'!$B$33*(0.4863620081*F50+0.4455809638*F50+0.0356254898*F51+0.0324315384))+F59*('Product and Cost'!$D$34*F51*Assumptions!$B$88+'Product and Cost'!$B$34*(0.4863620081*F50+0.4455809638*F50+0.0356254898*F51+0.0324315384)) -> 63847.573 | G62: =G52*('Product and Cost'!$D$27*G51*Assumptions!$B$88+'Product and Cost'!$B$27*(0.4863620081*G50+0.4455809638*G50+0.0356254898*G51+0.0324315384))+G53*('Product and Cost'!$D$28*G51*Assumptions!$B$88+'Product and Cost'!$B$28*(0.4863620081*G50+0.4455809638*G50+0.0356254898*G51+0.0324315384))+G54*('Product and Cost'!$D$29*G51*Assumptions!$B$88+'Product and Cost'!$B$29*(0.4863620081*G50+0.4455809638*G50+0.0356254898*G51+0.0324315384))+G55*('Product and Cost'!$D$30*G51*Assumptions!$B$88+'Product and Cost'!$B$30*(0.4863620081*G50+0.4455809638*G50+0.0356254898*G51+0.0324315384))+G56*('Product and Cost'!$D$31*G51*Assumptions!$B$88+'Product and Cost'!$B$31*(0.4863620081*G50+0.4455809638*G50+0.0356254898*G51+0.0324315384))+G57*('Product and Cost'!$D$32*G51*Assumptions!$B$88+'Product and Cost'!$B$32*(0.4863620081*G50+0.4455809638*G50+0.0356254898*G51+0.0324315384))+G58*('Product and Cost'!$D$33*G51*Assumptions!$B$88+'Product and Cost'!$B$33*(0.4863620081*G50+0.4455809638*G50+0.0356254898*G51+0.0324315384))+G59*('Product and Cost'!$D$34*G51*Assumptions!$B$88+'Product and Cost'!$B$34*(0.4863620081*G50+0.4455809638*G50+0.0356254898*G51+0.0324315384)) -> 68797.186
A63: GROSS PROFIT | C63: =C61-C62+$C$6*C61 -> 4021.2425 | D63: =D61-D62+$C$6*D61 -> 4199.8633 | E63: =E61-E62+$C$6*E61 -> 4319.5096 | F63: =F61-F62+$C$6*F61 -> 4415.084 | G63: =G61-G62+$C$6*G61 -> 4440.8788
A64: Gross margin | C64: =C63/C61 -> 0.076101075 | D64: =D63/D61 -> 0.071875877 | E64: =E63/E61 -> 0.067732962 | F64: =F63/F61 -> 0.064031102 | G64: =G63/G61 -> 0.06002985
A65: Operating expense | C65: =('Base Year'!$B$28*C50)+('Base Year'!$B$29*C50*C60/'Product and Cost'!$E$14)+('Base Year'!$B$30*C50)+('Base Year'!$B$31*C50) -> 2007.6668 | D65: =('Base Year'!$B$28*D50)+('Base Year'!$B$29*D50*D60/'Product and Cost'!$E$14)+('Base Year'!$B$30*D50)+('Base Year'!$B$31*D50) -> 2276.2978 | E65: =('Base Year'!$B$28*E50)+('Base Year'!$B$29*E50*E60/'Product and Cost'!$E$14)+('Base Year'!$B$30*E50)+('Base Year'!$B$31*E50) -> 2545.6212 | F65: =('Base Year'!$B$28*F50)+('Base Year'!$B$29*F50*F60/'Product and Cost'!$E$14)+('Base Year'!$B$30*F50)+('Base Year'!$B$31*F50) -> 2807.7788 | G65: =('Base Year'!$B$28*G50)+('Base Year'!$B$29*G50*G60/'Product and Cost'!$E$14)+('Base Year'!$B$30*G50)+('Base Year'!$B$31*G50) -> 3082.21
A66: EBITDA | C66: =C63-C65 -> 2013.5757 | D66: =D63-D65 -> 1923.5655 | E66: =E63-E65 -> 1773.8884 | F66: =F63-F65 -> 1607.3052 | G66: =G63-G65 -> 1358.6689
A67: Capital expenditure — maintenance + growth | C67: ='Base Year'!$B$43*C50+MAX(C60-'Product and Cost'!$E$14,0)*1947.901031*C50 -> 280.932 | D67: ='Base Year'!$B$43*D50+MAX(D60-C60,0)*1947.901031*D50 -> 307.36758 | E67: ='Base Year'!$B$43*E50+MAX(E60-D60,0)*1947.901031*E50 -> 328.63939 | F67: ='Base Year'!$B$43*F50+MAX(F60-E60,0)*1947.901031*F50 -> 351.14675 | G67: ='Base Year'!$B$43*G50+MAX(G60-F60,0)*1947.901031*G50 -> 375.37218
A68: Fixed assets at cost, closing | C68: =(Assumptions!$B$70+Assumptions!$B$71)/10^6+C67 -> 3429.0659 | D68: =C68+D67 -> 3736.4335 | E68: =D68+E67 -> 4065.0729 | F68: =E68+F67 -> 4416.2196 | G68: =F68+G67 -> 4791.5918
A69: Depreciation — rolls off the asset register | C69: =(Assumptions!$B$70+Assumptions!$B$71)/10^6/'Base Year'!$B$42 -> 173.80885 | D69: =C68/'Base Year'!$B$42 -> 189.31914 | E69: =D68/'Base Year'!$B$42 -> 206.28895 | F69: =E68/'Base Year'!$B$42 -> 224.43317 | G69: =F68/'Base Year'!$B$42 -> 243.82002
A70: Fixed assets, net book, closing | C70: =(Assumptions!$B$69+Assumptions!$B$71)/10^6+C67-C69 -> 1407.4626 | D70: =C70+D67-D69 -> 1525.5111 | E70: =D70+E67-E69 -> 1647.8615 | F70: =E70+F67-F69 -> 1774.5751 | G70: =F70+G67-G69 -> 1906.1272
A71: EBIT | C71: =C66-C69 -> 1839.7669 | D71: =D66-D69 -> 1734.2464 | E71: =E66-E69 -> 1567.5995 | F71: =F66-F69 -> 1382.872 | G71: =G66-G69 -> 1114.8488
A72: NOPAT before the profit share | C72: =C71*(1-Assumptions!$B$87) -> 1425.8193 | D72: =D71*(1-Assumptions!$B$87) -> 1344.0409 | E72: =E71*(1-Assumptions!$B$87) -> 1214.8896 | F72: =F71*(1-Assumptions!$B$87) -> 1071.7258 | G72: =G71*(1-Assumptions!$B$87) -> 864.00784
A73: less employees' profit share and board bonuses | C73: =MAX(C72,0)*'Base Year'!$B$40 -> 75.170677 | D73: =MAX(D72,0)*'Base Year'!$B$40 -> 70.859235 | E73: =MAX(E72,0)*'Base Year'!$B$40 -> 64.050243 | F73: =MAX(F72,0)*'Base Year'!$B$40 -> 56.502498 | G73: =MAX(G72,0)*'Base Year'!$B$40 -> 45.551392
A74: NOPAT | C74: =C72-C73 -> 1350.6486 | D74: =D72-D73 -> 1273.1817 | E74: =E72-E73 -> 1150.8394 | F74: =F72-F73 -> 1015.2233 | G74: =G72-G73 -> 818.45645
A75: Net working capital — on days | C75: ='Base Year'!$B$44*Forecast!$B$9/365*C62+'Base Year'!$B$45*Forecast!$B$9/365*C61-'Base Year'!$B$46*Forecast!$B$9/365*C62 -> 2539.6919 | D75: ='Base Year'!$B$44*Forecast!$B$9/365*D62+'Base Year'!$B$45*Forecast!$B$9/365*D61-'Base Year'!$B$46*Forecast!$B$9/365*D62 -> 2816.011 | E75: ='Base Year'!$B$44*Forecast!$B$9/365*E62+'Base Year'!$B$45*Forecast!$B$9/365*E61-'Base Year'!$B$46*Forecast!$B$9/365*E62 -> 3081.4964 | F75: ='Base Year'!$B$44*Forecast!$B$9/365*F62+'Base Year'!$B$45*Forecast!$B$9/365*F61-'Base Year'!$B$46*Forecast!$B$9/365*F62 -> 3339.6103 | G75: ='Base Year'!$B$44*Forecast!$B$9/365*G62+'Base Year'!$B$45*Forecast!$B$9/365*G61-'Base Year'!$B$46*Forecast!$B$9/365*G62 -> 3592.1114
A76: change in working capital | C76: =C75-('Base Year'!$B$44/365*'Base Year'!$B$21+'Base Year'!$B$45/365*'Base Year'!$B$19-'Base Year'!$B$46/365*'Base Year'!$B$21) -> 288.28965 | D76: =D75-C75 -> 276.31909 | E76: =E75-D75 -> 265.4854 | F76: =F75-E75 -> 258.11383 | G76: =G75-F75 -> 252.50115
A77: FREE CASH FLOW TO THE FIRM | C77: =C74+C69-C67-C76 -> 955.23585 | D77: =D74+D69-D67-D76 -> 878.81416 | E77: =E74+E69-E67-E76 -> 763.00353 | F77: =F74+F69-F67-F76 -> 630.39589 | G77: =G74+G69-G67-G76 -> 434.40314
A78: Glide fraction | C78: =0.0000000000 -> 0 | D78: =0.3571428571 -> 0.35714286 | E78: =0.6428571429 -> 0.64285714 | F78: =0.8571428571 -> 0.85714286 | G78: =1.0000000000 -> 1
A79: Forward cost of capital | C79: =Forecast!$B$14-(Forecast!$B$14-Forecast!$B$17)*C78 -> 0.31578339 | D79: =Forecast!$B$14-(Forecast!$B$14-Forecast!$B$17)*D78 -> 0.26851564 | E79: =Forecast!$B$14-(Forecast!$B$14-Forecast!$B$17)*E78 -> 0.23070144 | F79: =Forecast!$B$14-(Forecast!$B$14-Forecast!$B$17)*F78 -> 0.20234079 | G79: =Forecast!$B$14-(Forecast!$B$14-Forecast!$B$17)*G78 -> 0.18343369
A80: Cumulative discount factor | C80: =1/(1+C79) -> 0.76000351 | D80: =C80/(1+D79) -> 0.59912822 | E80: =D80/(1+E79) -> 0.48681849 | F80: =E80/(1+F79) -> 0.40489227 | G80: =F80/(1+G79) -> 0.34213347
A81: Present value | C81: =C77*C80 -> 725.9826 | D81: =D77*D80 -> 526.52236 | E81: =E77*E80 -> 371.44423 | F81: =F77*F80 -> 255.24243 | G81: =G77*G80 -> 148.62385
A82: PV of the explicit window | B82: =SUM(C81:G81) -> 2027.8155 | C82: =C75+C68 -> 5968.7578 | D82: =D75+D68 -> 6552.4445 | E82: =E75+E68 -> 7146.5693 | F82: =F75+F68 -> 7755.8299 | G82: =G75+G68 -> 8383.7032
A83: Terminal return on invested capital, at REPLACEMENT cost | B83: =G74*(1+Assumptions!$B$89)/G82 -> 0.10250593
A84: Required reinvestment = growth / return | B84: =MIN(Assumptions!$B$89/B83,0.95) -> 0.48777667
A85: Terminal value | B85: =G74*(1+Assumptions!$B$89)*(1-B84)/MAX(Forecast!$B$17-Assumptions!$B$89,0.02) -> 3298.9729
A86: PV of the terminal block | B86: =B85*G80 -> 1128.689
A87: ENTERPRISE VALUE | B87: =B82+B86 -> 3156.5045
A88: plus net cash | B88: =(Assumptions!$B$79-Assumptions!$B$82-Assumptions!$B$83)/10^6 -> 2442.5449
A89: Enterprise value including cash | B89: =B87+B88 -> 5599.0494
A90: less minority — on the WHOLE enterprise, cash included | B90: =B89*'Base Year'!$B$41 -> 182.43071
A91: less the tax-disputes provision | B91: =Assumptions!$B$78/10^6 -> 921.44035
A92: less dividends payable — declared, out of working capital | B92: =Assumptions!$B$77/10^6 -> 517.25
A93: plus non-operating investments and pledged deposits | B93: =(Assumptions!$B$81+Assumptions!$B$80)/10^6 -> 578.35875
A94: EQUITY ATTRIBUTABLE | B94: =B89-B90-B91-B92+B93 -> 4556.2871
A95: VALUE PER SHARE, EGP | B95: =B94/Assumptions!$B$8 -> 3.5279033
A98: Gross margin, shifted on every forecast year — -0.5% | B98: 2026E | C98: 2027E | D98: 2028E | E98: 2029E | F98: 2030E
A99: Inflation index, cumulative | C99: =Assumptions!$B$146 -> 1.145 | D99: =C99*Assumptions!$B$147 -> 1.29385 | E99: =D99*Assumptions!$B$148 -> 1.4426428 | F99: =E99*Assumptions!$B$149 -> 1.586907 | G99: =F99*Assumptions!$B$150 -> 1.7376632
A100: Realisation index, cumulative | C100: =(1+Assumptions!$B$101*Forecast!$B$8) -> 1.09 | D100: =C100*(1+Assumptions!$B$102*Forecast!$B$8) -> 1.17175 | E100: =D100*(1+Assumptions!$B$103*Forecast!$B$8) -> 1.2479137 | F100: =E100*(1+Assumptions!$B$104*Forecast!$B$8) -> 1.3202927 | G100: =F100*(1+Assumptions!$B$105*Forecast!$B$8) -> 1.388948
A101: Volume — Base and special oils, mn t | C101: ='Product and Cost'!E6*(1+Assumptions!$B$106*Forecast!$B$6) -> 0.11488517 | D101: =C101*(1+Assumptions!$B$107*Forecast!$B$6) -> 0.11948057 | E101: =D101*(1+Assumptions!$B$108*Forecast!$B$6) -> 0.1236624 | F101: =E101*(1+Assumptions!$B$109*Forecast!$B$6) -> 0.12737227 | G101: =F101*(1+Assumptions!$B$110*Forecast!$B$6) -> 0.13093869
A102: Volume — Paraffin wax, mn t | C102: ='Product and Cost'!E7*(1+Assumptions!$B$111*Forecast!$B$6) -> 0.089396788 | D102: =C102*(1+Assumptions!$B$112*Forecast!$B$6) -> 0.094313611 | E102: =D102*(1+Assumptions!$B$113*Forecast!$B$6) -> 0.098557724 | F102: =E102*(1+Assumptions!$B$114*Forecast!$B$6) -> 0.10230292 | G102: =F102*(1+Assumptions!$B$115*Forecast!$B$6) -> 0.10557661
A103: Volume — Gas oil, mn t | C103: ='Product and Cost'!E8*(1+Assumptions!$B$116*Forecast!$B$6) -> 0.35023716 | D103: =C103*(1+Assumptions!$B$117*Forecast!$B$6) -> 0.3572419 | E103: =D103*(1+Assumptions!$B$118*Forecast!$B$6) -> 0.36367225 | F103: =E103*(1+Assumptions!$B$119*Forecast!$B$6) -> 0.36949101 | G103: =F103*(1+Assumptions!$B$120*Forecast!$B$6) -> 0.37503338
A104: Volume — Naphtha, mn t | C104: ='Product and Cost'!E9*(1+Assumptions!$B$121*Forecast!$B$6) -> 0.08410464 | D104: =C104*(1+Assumptions!$B$122*Forecast!$B$6) -> 0.085618523 | E104: =D104*(1+Assumptions!$B$123*Forecast!$B$6) -> 0.087159657 | F104: =E104*(1+Assumptions!$B$124*Forecast!$B$6) -> 0.088554211 | G104: =F104*(1+Assumptions!$B$125*Forecast!$B$6) -> 0.089882524
A105: Volume — Liquefied petroleum gas, mn t | C105: ='Product and Cost'!E10*(1+Assumptions!$B$126*Forecast!$B$6) -> 0.048658345 | D105: =C105*(1+Assumptions!$B$127*Forecast!$B$6) -> 0.049728828 | E105: =D105*(1+Assumptions!$B$128*Forecast!$B$6) -> 0.050723405 | F105: =E105*(1+Assumptions!$B$129*Forecast!$B$6) -> 0.051636426 | G105: =F105*(1+Assumptions!$B$130*Forecast!$B$6) -> 0.052462609
A106: Volume — Fuel oil (mix), mn t | C106: ='Product and Cost'!E11*(1+Assumptions!$B$131*Forecast!$B$6) -> 0.94791642 | D106: =C106*(1+Assumptions!$B$132*Forecast!$B$6) -> 0.97256224 | E106: =D106*(1+Assumptions!$B$133*Forecast!$B$6) -> 0.99395861 | F106: =E106*(1+Assumptions!$B$134*Forecast!$B$6) -> 1.0138378 | G106: =F106*(1+Assumptions!$B$135*Forecast!$B$6) -> 1.0320869
A107: Volume — Heavy fuel oil, mn t | C107: ='Product and Cost'!E12*(1+Assumptions!$B$136*Forecast!$B$6) -> 0.029228141 | D107: =C107*(1+Assumptions!$B$137*Forecast!$B$6) -> 0.029754247 | E107: =D107*(1+Assumptions!$B$138*Forecast!$B$6) -> 0.030230315 | F107: =E107*(1+Assumptions!$B$139*Forecast!$B$6) -> 0.03068377 | G107: =F107*(1+Assumptions!$B$140*Forecast!$B$6) -> 0.031113343
A108: Volume — Waste, mn t | C108: ='Product and Cost'!E13*(1+Assumptions!$B$141*Forecast!$B$6) -> 1.564e-05 | D108: =C108*(1+Assumptions!$B$142*Forecast!$B$6) -> 1.564e-05 | E108: =D108*(1+Assumptions!$B$143*Forecast!$B$6) -> 1.564e-05 | F108: =E108*(1+Assumptions!$B$144*Forecast!$B$6) -> 1.564e-05 | G108: =F108*(1+Assumptions!$B$145*Forecast!$B$6) -> 1.564e-05
A109: Total volume, mn t | C109: =SUM(C101:C108) -> 1.6644423 | D109: =SUM(D101:D108) -> 1.7087156 | E109: =SUM(E101:E108) -> 1.74798 | F109: =SUM(F101:F108) -> 1.783894 | G109: =SUM(G101:G108) -> 1.8171097
A110: REVENUE | C110: =C101*'Product and Cost'!$F$6*C100+C102*'Product and Cost'!$F$7*C100+C103*'Product and Cost'!$F$8*C100+C104*'Product and Cost'!$F$9*C100+C105*'Product and Cost'!$F$10*C100+C106*'Product and Cost'!$F$11*C100+C107*'Product and Cost'!$F$12*C100+C108*'Product and Cost'!$F$13*C100 -> 52840.811 | D110: =D101*'Product and Cost'!$F$6*D100+D102*'Product and Cost'!$F$7*D100+D103*'Product and Cost'!$F$8*D100+D104*'Product and Cost'!$F$9*D100+D105*'Product and Cost'!$F$10*D100+D106*'Product and Cost'!$F$11*D100+D107*'Product and Cost'!$F$12*D100+D108*'Product and Cost'!$F$13*D100 -> 58432.167 | E110: =E101*'Product and Cost'!$F$6*E100+E102*'Product and Cost'!$F$7*E100+E103*'Product and Cost'!$F$8*E100+E104*'Product and Cost'!$F$9*E100+E105*'Product and Cost'!$F$10*E100+E106*'Product and Cost'!$F$11*E100+E107*'Product and Cost'!$F$12*E100+E108*'Product and Cost'!$F$13*E100 -> 63772.637 | F110: =F101*'Product and Cost'!$F$6*F100+F102*'Product and Cost'!$F$7*F100+F103*'Product and Cost'!$F$8*F100+F104*'Product and Cost'!$F$9*F100+F105*'Product and Cost'!$F$10*F100+F106*'Product and Cost'!$F$11*F100+F107*'Product and Cost'!$F$12*F100+F108*'Product and Cost'!$F$13*F100 -> 68952.179 | G110: =G101*'Product and Cost'!$F$6*G100+G102*'Product and Cost'!$F$7*G100+G103*'Product and Cost'!$F$8*G100+G104*'Product and Cost'!$F$9*G100+G105*'Product and Cost'!$F$10*G100+G106*'Product and Cost'!$F$11*G100+G107*'Product and Cost'!$F$12*G100+G108*'Product and Cost'!$F$13*G100 -> 73977.843
...

Sheet Lenses
A1: Four lenses, one bridge, one valuation date
A2: Lens 2 is on the TRAILING metric so it borrows no discount factor from lens 1. Lens 3 is forward-dated and is therefore DISCOUNTED to the valuation date at the cost of equity, with net cash added at face outside the multiple. Lens 4 uses the same cost-of-equity glide lens 1 uses. All formulas.
A5: Base-year EBITDA | B5: ='Base Year'!B20-'Base Year'!B28-'Base Year'!B29-'Base Year'!B30-'Base Year'!B31+'Base Year'!B32 -> 2629.1966
A6: Enterprise value at spot | B6: =Assumptions!$B$7*Assumptions!$B$8+(Assumptions!$B$82+Assumptions!$B$83-Assumptions!$B$79)/10^6 -> 9310.1051
A7: The company's OWN trailing EV/EBITDA | B7: =B6/B5 -> 3.5410457
A8: Justified multiple = trailing x (1 + re-rating) | B8: =B7*(1+Assumptions!$B$92) -> 3.5410457
A10: LENS 1 — discounted cash flow | B10: =Forecast!B65 -> 5.4999722
A11: LENS 2 — relative multiples, on the trailing metric | B11: =(B8*B5-(Assumptions!$B$82+Assumptions!$B$83-Assumptions!$B$79)/10^6)*(1-'Base Year'!B41)-(Assumptions!$B$78+Assumptions!$B$77-Assumptions!$B$81-Assumptions!$B$80)/10^6 -> 10509.388 | C11: =B11/Assumptions!$B$8 -> 8.1373506
A12: LENS 3 — normalised earnings power, DISCOUNTED | B12: =Forecast!E41 -> 2205.3259 | C12: =B12*(1-Assumptions!$B$87)*(1-'Base Year'!B40)*(1-'Base Year'!B41)/Assumptions!$B$8 -> 1.2127518 | D12: =C12*Assumptions!$B$91/(1+Forecast!B10)^2.4+((Assumptions!$B$79-Assumptions!$B$82-Assumptions!$B$83-Assumptions!$B$78-Assumptions!$B$77)/10^6)/Assumptions!$B$8 -> 5.8295249
A13: LENS 4 — book value and sustainable return | B13: =Assumptions!$B$84/10^6/Assumptions!$B$8 -> 3.7094045 | C13: =0.2366443942 -> 0.23664439 | D13: =(Assumptions!$B$90-Assumptions!$B$89)/(C13-Assumptions!$B$89) -> 1.2322899 | E13: =B13*D13 -> 4.5710617
A15: WEIGHTED CENTRAL | B15: =B10*Assumptions!$B$168+C11*Assumptions!$B$169+D12*Assumptions!$B$170+E13*Assumptions!$B$171 -> 5.9540218
A16: against spot | B16: =B15/Assumptions!$B$7-1 -> -0.34571189
A18: The weighted range on the Summary sheet is the bear and bull columns weighted with these same weights. The previous edition labelled a row "weighted central" and then took the minimum and maximum across the four lenses — both of which came from the cash-flow lens alone — so the word "weighted" applied to the centre and not to the ends, and the published spread was about two and a half times too wide.
