Workbook

Sheet READ FIRST
A1: Read this first
A5: THE RULE
A6: IT CALCULATES. IT DOES NOT STORE.
A8: Exactly ONE class of cell is pasted in this workbook: a figure read off an audited or disclosed filing, or a stated house judgement. Those are the blue cells on Assumptions, and the blue lever cells that define each sensitivity grid point. Everything else is a live formula.
A10: The previous edition also pasted its sensitivity grids, its beta sweep and its bear and bull columns, on the grounds that each is a whole-model re-run and a re-run cannot be written inside a grid. That was 27.6% of the file, and it was the part a reader would most want to interrogate. Three of those pasted rows turned out not to reproduce.
A12: The Sensitivity sheet now writes the entire forecast engine out again, in formulas, once for every grid point. Change any driver on Assumptions and every sensitivity cell in the file moves with it.
A14: WHAT IS AUDITED AND WHAT IS NOT
A15: The base year is the twelve months to 30 June 2026. The first half of it — July to December 2025 — is AUDITED by Crowe with an unqualified opinion. The second half — January to June 2026 — is REPORTED: a disclosure to the Egyptian Exchange dated 29-30 July 2026, not a filing. Half of this base year is a press release and the study says so wherever it uses it.
A17: The gross profit of that reported half is NOT used as released. Run through the company's own first-quarter expense run rates the released figure implies a profit after tax about 12.6% above the profit the same release reports. The gross profit used here is solved from the profit line, which passes two independent coherence tests. Base Year rows 13 to 17 show the whole test.
A19: THE ONE OPERATING INPUT THAT IS NOT READ OFF A FILING
A20: Note 15-A discloses the cost stack for the company and not by line. The processing-intensity weights on Assumptions are therefore a judgement, and the per-line margins depend on them. They are registered, dated and sensitised like every other input rather than hidden inside a formula.

Sheet Assumptions
A1: Assumptions — every driver, with the filing it was read from
A2: Blue cells are the ONLY pasted values in this workbook. Every one is a figure read off an audited or disclosed filing, or a stated house judgement. There is no third class: the previous edition also pasted its sensitivity grids and its bear and bull columns because each is a whole-model re-run; those re-runs are now written out as live formula blocks on the Sensitivity sheet, so a reader can change a driver here and watch every one of them move.
A5: Driver | B5: Value | C5: Ring | D5: Date | E5: Source
A6: MARKET AND CAPITAL
A7: Spot price, EGP | B7: 9.1 | C7: Company | D7: 2026-08-06 | E7: AMOC closing price on the Egyptian Exchange, 6 August 2026
A8: Shares outstanding, mn | B8: 1291.5 | C8: Company | D8: 2025-12-31 | E8: Issued and paid-up capital EGP 1,291,500,000 at EGP 1 par = 1,291,500,000 shares (note 18-L, share split to EGP 1 par recorded in the Commercial Register 24-Jan-2018)
A9: THE TWELVE MONTHS TO 30 JUNE 2026 — the base year
A10: Net sales, 6M to 31-Dec-2025 (AUDITED) | B10: 20735725812 | C10: Company | D10: 2025-12-31 | E10: Net sales, six months to 31-Dec-2025. Audited consolidated FS, transition period 1-Jul-2025 to 31-Dec-2025, Crowe unqualified, 18-Feb-2026
A11: Cost of sales, 6M to 31-Dec-2025 (AUDITED) | B11: 19461550746 | C11: Company | D11: 2025-12-31 | E11: Cost of sales, six months to 31-Dec-2025. Audited consolidated FS, transition period 1-Jul-2025 to 31-Dec-2025, Crowe unqualified, 18-Feb-2026
A12: Net sales, 6M to 30-Jun-2026 (REPORTED) | B12: 26223000000 | C12: Company | D12: 2026-06-30 | E12: Net sales, six months to 30-Jun-2026. Half-year results for 1-Jan to 30-Jun-2026, disclosed to the Egyptian Exchange 29-30 July 2026. REPORTED, NOT AUDITED — a press release, not a filing
A13: Profit after tax, 6M to 30-Jun-2026 (REPORTED) | B13: 1903000000 | C13: Company | D13: 2026-06-30 | E13: Net profit after tax, six months to 30-Jun-2026. Half-year results for 1-Jan to 30-Jun-2026, disclosed to the Egyptian Exchange 29-30 July 2026. REPORTED, NOT AUDITED — a press release, not a filing
A14: Gross profit as RELEASED — rejected, see coherence test | B14: 3258000000 | C14: Company | D14: 2026-06-30 | E14: Gross profit, six months to 30-Jun-2026, AS RELEASED. This study does NOT use this figure: run through the company's own Q1-2026 expense run rates it implies a profit after tax about 12.6% above the profit the same release reports. The gross profit actually used is SOLVED from the release's own profit line, which two independent coherence tests confirm. Half-year results for 1-Jan to 30-Jun-2026, disclosed to the Egyptian Exchange 29-30 July 2026. REPORTED, NOT AUDITED — a press release, not a filing
A15: Net sales, 3M to 31-Mar-2026 (reviewed) | B15: 10510779160 | C15: Company | D15: 2026-03-31 | E15: Net sales, three months to 31-Mar-2026. Reviewed consolidated FS, three months to 31-Mar-2026
A16: Cost of sales, 3M to 31-Mar-2026 (reviewed) | B16: 9439744195 | C16: Company | D16: 2026-03-31 | E16: Cost of sales, three months to 31-Mar-2026. Reviewed consolidated FS, three months to 31-Mar-2026
A17: Administrative expense, 3M to 31-Mar-2026 | B17: 365952237 | C17: Company | D17: 2026-03-31 | E17: General and administrative expenses, three months to 31-Mar-2026. Reviewed consolidated FS, three months to 31-Mar-2026
A18: Selling expense, 3M to 31-Mar-2026 | B18: 60830975 | C18: Company | D18: 2026-03-31 | E18: Marketing and selling expenses, three months to 31-Mar-2026. Reviewed consolidated FS, three months to 31-Mar-2026
A19: Other operating expense, 3M to 31-Mar-2026 | B19: 1080000 | C19: Company | D19: 2026-03-31 | E19: Other operating expenses, three months to 31-Mar-2026. Reviewed consolidated FS, three months to 31-Mar-2026
A20: Other revenue, 3M to 31-Mar-2026 | B20: 225556509 | C20: Company | D20: 2026-03-31 | E20: Other revenue, three months to 31-Mar-2026. Reviewed consolidated FS, three months to 31-Mar-2026
A21: Formed provisions, 3M to 31-Mar-2026 | B21: 30000000 | C21: Company | D21: 2026-03-31 | E21: Formed provisions, three months to 31-Mar-2026. Reviewed consolidated FS, three months to 31-Mar-2026
... A44: Finance cost, 6M to 31-Dec-2025 | B44: 1892108 | C44: Company | D44: 2025-12-31 | E44: Finance expenses, six months to 31-Dec-2025 (note 15-E): loan interest and charges 1,130,556, lease interest 761,552. Audited consolidated FS, transition period 1-Jul-2025 to 31-Dec-2025, Crowe unqualified, 18-Feb-2026
A45: NOTE 14-A — the audited product table, 6M to 31-Dec-2025
A46: Base and special oils — tonnes sold | B46: 54968.98 | C46: Company | D46: 2025-12-31 | E46: Tonnes sold by product line, six months to 31-Dec-2025 (note 14-A). Audited consolidated FS, transition period 1-Jul-2025 to 31-Dec-2025, Crowe unqualified, 18-Feb-2026
A47: Paraffin wax — tonnes sold | B47: 41774.2 | C47: Company | D47: 2025-12-31 | E47: Tonnes sold by product line, six months to 31-Dec-2025 (note 14-A). Audited consolidated FS, transition period 1-Jul-2025 to 31-Dec-2025, Crowe unqualified, 18-Feb-2026
A48: Gas oil — tonnes sold | B48: 171684.88 | C48: Company | D48: 2025-12-31 | E48: Tonnes sold by product line, six months to 31-Dec-2025 (note 14-A). Audited consolidated FS, transition period 1-Jul-2025 to 31-Dec-2025, Crowe unqualified, 18-Feb-2026
A49: Naphtha — tonnes sold | B49: 41430.857 | C49: Company | D49: 2025-12-31 | E49: Tonnes sold by product line, six months to 31-Dec-2025 (note 14-A). Audited consolidated FS, transition period 1-Jul-2025 to 31-Dec-2025, Crowe unqualified, 18-Feb-2026
A50: Liquefied petroleum gas — tonnes sold | B50: 23735.778 | C50: Company | D50: 2025-12-31 | E50: Tonnes sold by product line, six months to 31-Dec-2025 (note 14-A). Audited consolidated FS, transition period 1-Jul-2025 to 31-Dec-2025, Crowe unqualified, 18-Feb-2026
A51: Fuel oil (mix) — tonnes sold | B51: 460153.6 | C51: Company | D51: 2025-12-31 | E51: Tonnes sold by product line, six months to 31-Dec-2025 (note 14-A). Audited consolidated FS, transition period 1-Jul-2025 to 31-Dec-2025, Crowe unqualified, 18-Feb-2026
A52: Heavy fuel oil — tonnes sold | B52: 14327.52 | C52: Company | D52: 2025-12-31 | E52: Tonnes sold by product line, six months to 31-Dec-2025 (note 14-A). Audited consolidated FS, transition period 1-Jul-2025 to 31-Dec-2025, Crowe unqualified, 18-Feb-2026
A53: Waste — tonnes sold | B53: 7.82 | C53: Company | D53: 2025-12-31 | E53: Tonnes sold by product line, six months to 31-Dec-2025 (note 14-A). Audited consolidated FS, transition period 1-Jul-2025 to 31-Dec-2025, Crowe unqualified, 18-Feb-2026
A54: Base and special oils — sales value, EGP | B54: 2597280264 | C54: Company | D54: 2025-12-31 | E54: Sales value by product line, EGP, six months to 31-Dec-2025 (note 14-A). Audited consolidated FS, transition period 1-Jul-2025 to 31-Dec-2025, Crowe unqualified, 18-Feb-2026
A55: Paraffin wax — sales value, EGP | B55: 2041969329 | C55: Company | D55: 2025-12-31 | E55: Sales value by product line, EGP, six months to 31-Dec-2025 (note 14-A). Audited consolidated FS, transition period 1-Jul-2025 to 31-Dec-2025, Crowe unqualified, 18-Feb-2026
A56: Gas oil — sales value, EGP | B56: 5121703599 | C56: Company | D56: 2025-12-31 | E56: Sales value by product line, EGP, six months to 31-Dec-2025 (note 14-A). Audited consolidated FS, transition period 1-Jul-2025 to 31-Dec-2025, Crowe unqualified, 18-Feb-2026
A57: Naphtha — sales value, EGP | B57: 958746631 | C57: Company | D57: 2025-12-31 | E57: Sales value by product line, EGP, six months to 31-Dec-2025 (note 14-A). Audited consolidated FS, transition period 1-Jul-2025 to 31-Dec-2025, Crowe unqualified, 18-Feb-2026
... A61: Waste — sales value, EGP | B61: 87400 | C61: Company | D61: 2025-12-31 | E61: Sales value by product line, EGP, six months to 31-Dec-2025 (note 14-A). Audited consolidated FS, transition period 1-Jul-2025 to 31-Dec-2025, Crowe unqualified, 18-Feb-2026
A62: NOTE 15-A — the audited cost stack, 6M to 31-Dec-2025
A63: Raw materials | B63: 17650102725 | C63: Company | D63: 2025-12-31 | E63: Cost of sales — RAW MATERIALS, six months to 31-Dec-2025 (note 15-A). 90.7% of cost of sales and 85.1% of revenue: this single line is what the company is. Audited consolidated FS, transition period 1-Jul-2025 to 31-Dec-2025, Crowe unqualified, 18-Feb-2026
A64: Salaries | B64: 881019497 | C64: Company | D64: 2025-12-31 | E64: Cost of sales — salaries, six months to 31-Dec-2025 (note 15-A). Audited consolidated FS, transition period 1-Jul-2025 to 31-Dec-2025, Crowe unqualified, 18-Feb-2026
A65: Other expenses | B65: 807146755 | C65: Company | D65: 2025-12-31 | E65: Cost of sales — other expenses, six months to 31-Dec-2025 (note 15-A): natural gas, operating electricity, operating water, spare parts, maintenance, and the operating management and technical support contract with the Egyptian Projects Operations & Maintenance Company (EPROM). Audited consolidated FS, transition period 1-Jul-2025 to 31-Dec-2025, Crowe unqualified, 18-Feb-2026
A66: Supporting materials (chemicals and additives) | B66: 64533723 | C66: Company | D66: 2025-12-31 | E66: Cost of sales — supporting materials (chemicals and additives), six months to 31-Dec-2025 (note 15-A). The previous edition estimated this charge at roughly five times the disclosed figure
A67: Depreciation | B67: 58748046 | C67: Company | D67: 2025-12-31 | E67: Cost of sales — depreciation, six months to 31-Dec-2025 (note 15-A). Audited consolidated FS, transition period 1-Jul-2025 to 31-Dec-2025, Crowe unqualified, 18-Feb-2026
A68: BALANCE SHEET AT 31 DECEMBER 2025 (AUDITED)
A69: Fixed assets, net | B69: 893016274 | C69: Company | D69: 2025-12-31 | E69: Fixed assets net of accumulated depreciation at 31-Dec-2025 (note 6). Cost 2,740,810,692 less accumulated depreciation 1,847,794,418 — the plant is 67% written down, and 273,466,121 of it is fully depreciated and still in use. Audited consolidated FS, transition period 1-Jul-2025 to 31-Dec-2025, Crowe unqualified, 18-Feb-2026
A70: Fixed assets, at COST | B70: 2740810692 | C70: Company | D70: 2025-12-31 | E70: Fixed assets at COST at 31-Dec-2025 (note 6), before accumulated depreciation of 1,847,794,418. The gross figure is what a replacement-capex line has to be built on; the net figure is what the terminal return is flattered by. Audited consolidated FS, transition period 1-Jul-2025 to 31-Dec-2025, Crowe unqualified, 18-Feb-2026
A71: Projects under construction | B71: 407323203 | C71: Company | D71: 2025-12-31 | E71: Projects under construction at 31-Dec-2025 (note 7): assets in development 376,746,526 (administrative building, warehouses, civil projects, ERP system) plus investment expenditure 30,576,677. Audited consolidated FS, transition period 1-Jul-2025 to 31-Dec-2025, Crowe unqualified, 18-Feb-2026
A72: Inventory | B72: 2847392506 | C72: Company | D72: 2025-12-31 | E72: Inventory net of impairment at 31-Dec-2025 (note 9-A): work in process 792,134,042, finished goods 1,166,168,582, spare parts 309,298,239, supporting materials 283,470,554, raw materials 118,754,225, goods for resale 155,793,361. Audited consolidated FS, transition period 1-Jul-2025 to 31-Dec-2025, Crowe unqualified, 18-Feb-2026
A73: Trade receivables | B73: 573136185 | C73: Company | D73: 2025-12-31 | E73: Accounts receivable net at 31-Dec-2025 (note 9-B). 100% undue and unimpaired on the ageing analysis. Counterparties include Shell, ExxonMobil, Chevron, Total, TAQA/Castrol, Emarat Misr, OLA Energy and Petromine alongside the state companies. Audited consolidated FS, transition period 1-Jul-2025 to 31-Dec-2025, Crowe unqualified, 18-Feb-2026
A74: Debtors and other debit balances | B74: 366012664 | C74: Company | D74: 2025-12-31 | E74: Debtors and other debit balances net at 31-Dec-2025 (notes 9-C, 9-D). Audited consolidated FS, transition period 1-Jul-2025 to 31-Dec-2025, Crowe unqualified, 18-Feb-2026
A75: Accounts and notes payable | B75: 7942650 | C75: Company | D75: 2025-12-31 | E75: Accounts and notes payable at 31-Dec-2025 (note 10-3). The previous edition modelled a trade payable of about 2.5bn funding the working capital cycle; the actual trade payable is under 8mn and the funding sits in the EGPC current account instead. Audited consolidated FS, transition period 1-Jul-2025 to 31-Dec-2025, Crowe unqualified, 18-Feb-2026
A76: Creditors and other credit balances | B76: 2044446416 | C76: Company | D76: 2025-12-31 | E76: Creditors and other credit balances at 31-Dec-2025 (note 11): EGPC current account 1,132,353,505, deposits 70,891,867, miscellaneous taxes 47,021,719, dividends payable 517,250,000, miscellaneous creditors 148,226,091, customer advances 60,028,880. Audited consolidated FS, transition period 1-Jul-2025 to 31-Dec-2025, Crowe unqualified, 18-Feb-2026
A77: of which DIVIDENDS PAYABLE — a financing claim | B77: 517250000 | C77: Company | D77: 2025-12-31 | E77: Dividends payable at 31-Dec-2025 (note 11, other credit balances) — declared and not yet paid at the reporting date. Audited consolidated FS, transition period 1-Jul-2025 to 31-Dec-2025, Crowe unqualified, 18-Feb-2026
A78: Provisions — tax disputes and claims | B78: 921440353 | C78: Company | D78: 2025-12-31 | E78: Provisions at 31-Dec-2025 (note 10-1): tax disputes 904,609,345 and claims and disputes 16,831,008. A contingent liability worth EGP 0.71 a share that the previous edition never carried at all
A79: Cash at banks and on hand, free | B79: 2463522365 | C79: Company | D79: 2025-12-31 | E79: Cash at banks and on hand at 31-Dec-2025 (note 9-E): time deposits 883,351,250 plus current accounts 2,127,100,720 plus cash on hand 166,405, less expected credit losses 38,345,960, less PLEDGED deposits 508,750,050 which sit in other financial investments. Audited consolidated FS, transition period 1-Jul-2025 to 31-Dec-2025, Crowe unqualified, 18-Feb-2026
A80: Deposits PLEDGED against facilities | B80: 508750050 | C80: Company | D80: 2025-12-31 | E80: Other financial investments at 31-Dec-2025 — deposits PLEDGED against credit facilities, so not free cash (note 9-E). Audited consolidated FS, transition period 1-Jul-2025 to 31-Dec-2025, Crowe unqualified, 18-Feb-2026
... A85: Non-controlling interest, carrying | B85: 34079000 | C85: Company | D85: 2025-12-31 | E85: Non-controlling interest carrying amount at 31-Dec-2025. Audited consolidated FS, transition period 1-Jul-2025 to 31-Dec-2025, Crowe unqualified, 18-Feb-2026
A86: DRIVERS
A87: Statutory tax rate — applied to operating profit | B87: 0.225 | C87: Country | D87: 2026 | E87: Egypt corporate income tax 22.5%. AMOC is a downstream processor and is taxed at the ordinary corporate rate, not the ~40.55% rate that applies to exploration and production concessions
A88: Feedstock pass-through factor | B88: 1 | C88: House | D88: 2026-08-06 | E88: Pass-through factor on the raw-material line: 1.0 means the feedstock charge moves one-for-one with realisation and volume, so the gross SPREAD per tonne is held flat in real terms and the margin neither widens nor narrows by assumption. Setting it below 1.0 is the way to express spread widening; the study leaves it at parity and sensitises it
A89: Terminal growth | B89: 0.05 | C89: House | D89: 2026-08-06 | E89: Terminal growth, 5% — the standing centre for established names in this market once currency turbulence has passed, sensitised 3-7%. An EGP-nominal rate struck against an EGP-nominal terminal risk-free rate
A90: Sustainable return on equity — book lens | B90: 0.28 | C90: House | D90: 2026-08-06 | E90: Sustainable return on equity for the book lens. Trailing return on average parent equity is about 33%; the sustainable rate is struck below it because the reported figure is flattered by a heavily written-down asset base that will have to be renewed
A91: Justified price/earnings — normalised lens | B91: 7.5 | C91: House | D91: 2026-08-06 | E91: Justified through-cycle price-to-earnings multiple on normalised earnings. Trailing is about 7.5x on the constructed 2025 base. A single-asset processor with a 20% state shareholder, an administered feedstock relationship and an Egyptian cost of equity near 28% does not earn a premium multiple. Bear 5.5x / bull 9.5x
A92: Re-rating on own trailing EV/EBITDA — relative lens | B92: 0 | C92: House | D92: 2026-08-06 | E92: Re-rating applied to the company's OWN trailing enterprise-value to EBITDA multiple in the relative lens. ZERO: the name is held at the multiple the market already pays it. The justified multiple is no longer a free number — it is DERIVED as the trailing multiple times one plus this figure, so it cannot drift away from the company's own pricing without the drift being visible. The previous edition set 4.5x by hand and justified it as 'holding the name at its own trailing level' against a stated trailing multiple of 'around 4.6x'; the model's own output was different, so the stated justification was false whichever way the multiple was struck. Holding at zero re-rating makes the lens a statement about the BRIDGE — what the disclosed claims on the cash are worth — rather than a disguised view on the multiple
A93: Processing intensity — Base and special oils | B93: 1 | C93: House | D93: 2026-08-06 | E93: Processing intensity by product line, relative weights, used to allocate the note 15-A conversion stack (salaries, supporting materials, other, depreciation) across the eight disclosed lines. Base oils are the reference at 1.00: they pass the full lube train — vacuum distillation, solvent extraction, dewaxing, hydrofinishing. Paraffin wax carries 1.15 for the additional deoiling and sweating steps. Gas oil, naphtha and LPG are light ends drawn off the front of the process and carry 0.25/0.20/0.15. Fuel oil and heavy fuel oil are the residue, sold substantially as produced, at 0.05. THIS IS THE ONLY OPERATING INPUT IN THE MODEL THAT IS NOT READ OFF A FILING, and it exists because note 15-A discloses the cost stack for the company and not by line. It is stated here rather than hidden in a formula, and the valuation is sensitised to it
A94: Processing intensity — Paraffin wax | B94: 1.15 | C94: House | D94: 2026-08-06 | E94: Processing intensity by product line, relative weights, used to allocate the note 15-A conversion stack (salaries, supporting materials, other, depreciation) across the eight disclosed lines. Base oils are the reference at 1.00: they pass the full lube train — vacuum distillation, solvent extraction, dewaxing, hydrofinishing. Paraffin wax carries 1.15 for the additional deoiling and sweating steps. Gas oil, naphtha and LPG are light ends drawn off the front of the process and carry 0.25/0.20/0.15. Fuel oil and heavy fuel oil are the residue, sold substantially as produced, at 0.05. THIS IS THE ONLY OPERATING INPUT IN THE MODEL THAT IS NOT READ OFF A FILING, and it exists because note 15-A discloses the cost stack for the company and not by line. It is stated here rather than hidden in a formula, and the valuation is sensitised to it
A95: Processing intensity — Gas oil | B95: 0.25 | C95: House | D95: 2026-08-06 | E95: Processing intensity by product line, relative weights, used to allocate the note 15-A conversion stack (salaries, supporting materials, other, depreciation) across the eight disclosed lines. Base oils are the reference at 1.00: they pass the full lube train — vacuum distillation, solvent extraction, dewaxing, hydrofinishing. Paraffin wax carries 1.15 for the additional deoiling and sweating steps. Gas oil, naphtha and LPG are light ends drawn off the front of the process and carry 0.25/0.20/0.15. Fuel oil and heavy fuel oil are the residue, sold substantially as produced, at 0.05. THIS IS THE ONLY OPERATING INPUT IN THE MODEL THAT IS NOT READ OFF A FILING, and it exists because note 15-A discloses the cost stack for the company and not by line. It is stated here rather than hidden in a formula, and the valuation is sensitised to it
A96: Processing intensity — Naphtha | B96: 0.2 | C96: House | D96: 2026-08-06 | E96: Processing intensity by product line, relative weights, used to allocate the note 15-A conversion stack (salaries, supporting materials, other, depreciation) across the eight disclosed lines. Base oils are the reference at 1.00: they pass the full lube train — vacuum distillation, solvent extraction, dewaxing, hydrofinishing. Paraffin wax carries 1.15 for the additional deoiling and sweating steps. Gas oil, naphtha and LPG are light ends drawn off the front of the process and carry 0.25/0.20/0.15. Fuel oil and heavy fuel oil are the residue, sold substantially as produced, at 0.05. THIS IS THE ONLY OPERATING INPUT IN THE MODEL THAT IS NOT READ OFF A FILING, and it exists because note 15-A discloses the cost stack for the company and not by line. It is stated here rather than hidden in a formula, and the valuation is sensitised to it
A97: Processing intensity — Liquefied petroleum gas | B97: 0.15 | C97: House | D97: 2026-08-06 | E97: Processing intensity by product line, relative weights, used to allocate the note 15-A conversion stack (salaries, supporting materials, other, depreciation) across the eight disclosed lines. Base oils are the reference at 1.00: they pass the full lube train — vacuum distillation, solvent extraction, dewaxing, hydrofinishing. Paraffin wax carries 1.15 for the additional deoiling and sweating steps. Gas oil, naphtha and LPG are light ends drawn off the front of the process and carry 0.25/0.20/0.15. Fuel oil and heavy fuel oil are the residue, sold substantially as produced, at 0.05. THIS IS THE ONLY OPERATING INPUT IN THE MODEL THAT IS NOT READ OFF A FILING, and it exists because note 15-A discloses the cost stack for the company and not by line. It is stated here rather than hidden in a formula, and the valuation is sensitised to it
A98: Processing intensity — Fuel oil (mix) | B98: 0.05 | C98: House | D98: 2026-08-06 | E98: Processing intensity by product line, relative weights, used to allocate the note 15-A conversion stack (salaries, supporting materials, other, depreciation) across the eight disclosed lines. Base oils are the reference at 1.00: they pass the full lube train — vacuum distillation, solvent extraction, dewaxing, hydrofinishing. Paraffin wax carries 1.15 for the additional deoiling and sweating steps. Gas oil, naphtha and LPG are light ends drawn off the front of the process and carry 0.25/0.20/0.15. Fuel oil and heavy fuel oil are the residue, sold substantially as produced, at 0.05. THIS IS THE ONLY OPERATING INPUT IN THE MODEL THAT IS NOT READ OFF A FILING, and it exists because note 15-A discloses the cost stack for the company and not by line. It is stated here rather than hidden in a formula, and the valuation is sensitised to it
... A150: Egyptian inflation factor, 2030E | B150: 1.095 | C150: Country | D150: 2026-08-06 | E150: Cumulative-year Egyptian inflation factors applied to the pound-denominated cost legs — salaries inside cost of sales, the other line, administrative and marketing expense, and capital expenditure. Historical years as printed, easing toward the central bank's published target thereafter
A151: COST OF CAPITAL
A152: Risk-free rate, Egypt 10-year local currency | B152: 0.2231 | C152: Country | D152: 2026-07-21 | E152: Egypt 10-year local-currency government bond yield, 22.31% (house cost-of-capital reference, cached 21-Jul-2026 print, re-verified 06-Aug-2026)
A153: Sovereign default spread, CDS basis | B153: 0.034 | C153: Country | D153: 2026-01-05 | E153: Egypt credit-default-swap-implied sovereign default spread, Damodaran January-2026 country-premium file, CDS column. Netted out of the local-currency risk-free rate so sovereign default risk is not charged twice
A154: Equity risk premium, CDS basis | B154: 0.0941 | C154: Country | D154: 2026-01-05 | E154: Damodaran original country-premium file, Egypt row, CDS column, last updated 5 January 2026 — total equity risk premium
A155: Beta | B155: 0.908 | C155: Company | D155: 2026-07-22 | E155: Own-stock tier-1 regression, AMOC weekly log-returns against the EGX30 — the PUBLISHED index of the exchange AMOC is listed on, read from engine/raw_indices/EG/EGX30.csv (as of 22-Jul-2026) and resolved through beta_regression.own_stock_beta(). R-squared 0.259, n = 253, standard error 0.165, 90% confidence interval [0.637, 1.179], Blume cross-check 0.939. Passes the usability gate. THIS REPLACES the previous edition's 0.9405, which was regressed against a 33-name equal-weight composite of the covered Egyptian names — a coverage artefact rather than a market, and a source-integrity failure whatever number it produced. The correction is small on this name, -3.5% on beta and under a percent on fair value; it is made because the provenance was wrong, not because the answer was
A156: Yield on cash | B156: 0.17 | C156: House | D156: 2026-08-06 | E156: Yield earned on the cash pile. Egyptian treasury bills and corporate deposits price a few points under the 19.50% policy rate net of the 20% withholding on interest
A157: Cost of debt | B157: 0.22 | C157: House | D157: 2026-08-06 | E157: Marginal cost of debt. The gross book is EGP 25mn — 0.06% of revenue — of short-dated Egyptian-pound facilities, so the rate is taken at the corridor lending rate of 20.00% plus a 200bp corporate spread rather than pretended to be observable. The integrity gate below computes what this input is actually WORTH to the answer
A158: CBE inflation target IN FORCE for the terminal horizon | B158: 0.07 | C158: Country | D158: 2026-08-06 | E158: The central bank's own stated inflation target, 7% (+/-2pp) on average for the fourth quarter of 2026, falling to 5% (+/-2pp) for the fourth quarter of 2028
A159: Terminal real risk-free rate | B159: 0.055 | C159: House | D159: 2026-08-06 | E159: Terminal real risk-free rate, the standard emerging-market convention. The terminal NOMINAL risk-free rate is not an input: it is DERIVED as this real rate plus the central bank's inflation target IN FORCE for the terminal horizon (`cbe_target`), so the single most terminal-value-sensitive number in the model cannot be set by hand. The previous edition hardcoded 10.50% by adding 5.5pp to the 5% target dated Q4-2028 while describing it as 'the' medium-term target; the target in force is 7% for Q4-2026 and the July-2026 rate decision pushed even that to H2-2027
A160: Terminal equity risk premium | B160: 0.07 | C160: House | D160: 2026-08-06 | E160: Terminal equity risk premium, normalised below the currently elevated crisis-era level toward the rating-class norm; never held flat into perpetuity
A161: Terminal cost of debt | B161: 0.15 | C161: House | D161: 2026-08-06 | E161: Terminal cost of debt: the midpoint of the 14-16% long-run Egyptian corporate-borrowing norm, with no name-specific reason to deviate
A162: Terminal debt weight | B162: 0.1 | C162: House | D162: 2026-08-06 | E162: Terminal debt weight, normalised. The company is net cash today and has been for years; a terminal structure carrying a tenth of capital in debt is already generous to the valuation and avoids capitalising the current zero-leverage position into perpetuity
A163: Cost-of-debt path, 2026E | B163: 0.22 | C163: House | D163: 2026-08-06 | E163: Forward cost-of-debt path 2026E-2030E, following the central bank's own disinflation path toward the long-run Egyptian corporate-borrowing norm. This path is what sets the SHAPE of the cost-of-capital glide; it is not a second free parameter
... A171: Lens weight — book | B171: 0.15 | C171: House | D171: 2026-08-06 | E171: Discounted cash flow primary for a single-asset operating processor with a visible volume ramp; the relative and normalised-earnings lenses carry equal secondary weight; the book lens least, because a substantially depreciated plant makes book value a poor proxy for replacement cost

Sheet Base Year
A1: Base year — twelve contiguous months to 30 June 2026
A2: The gross profit of the reported half is NOT taken as released. It is solved from the release's own profit line, and the released figure is shown beside it with the profit it would have implied. Every cell below is a formula.
B5: EGP | C5: Check
A6: Administrative + selling + other, 3M to 31-Mar-2026 | B6: =Assumptions!$B$17+Assumptions!$B$18+Assumptions!$B$19
A7: Scaled to the half (x2) | B7: =B6*2
A8: Other revenue, half | B8: =Assumptions!$B$20*2
A9: Provisions and expected credit losses, half | B9: =(Assumptions!$B$21+Assumptions!$B$22)*2
A10: Finance cost, half | B10: =Assumptions!$B$23*2
A11: Effective tax rate, nine months (for the solve only) | B11: =(Assumptions!$B$38-Assumptions!$B$39+Assumptions!$B$40-Assumptions!$B$41)/((Assumptions!$B$38-Assumptions!$B$39+Assumptions!$B$40-Assumptions!$B$41)/0.22118761296853667)
A13: GROSS PROFIT, 6M to 30-Jun-2026 — SOLVED from the profit | B13: =Assumptions!$B$13/(1-B11)+B7-B8+B9+B10
A14: Gross profit AS RELEASED — rejected | B14: =Assumptions!$B$14
A15: Profit the released gross profit would imply | B15: =(B14-B7+B8-B9-B10)*(1-B11)
A16: against the profit the same release reports | B16: =Assumptions!$B$13
A17: Overstatement in the released gross-profit line | B17: =B15/B16-1
A19: BASE-YEAR REVENUE — twelve months to 30-Jun-2026 | B19: =(Assumptions!$B$10+Assumptions!$B$12)/10^6
A20: BASE-YEAR GROSS PROFIT | B20: =(Assumptions!$B$10-Assumptions!$B$11+B13)/10^6
A21: BASE-YEAR COST OF SALES | B21: =B19-B20
A22: BASE-YEAR GROSS MARGIN | B22: =B20/B19
A24: Alternative base: nine audited months x 4/3 | B24: =(Assumptions!$B$10+Assumptions!$B$15)/10^6*4/3
A25: its gross margin | B25: =(Assumptions!$B$10+Assumptions!$B$15-Assumptions!$B$11-Assumptions!$B$16)/(Assumptions!$B$10+Assumptions!$B$15)
A27: Operating lines, SAME twelve months
A28: Administrative expense | B28: =(Assumptions!$B$24+Assumptions!$B$17*2)/10^6
A29: Selling expense | B29: =(Assumptions!$B$25+Assumptions!$B$18*2)/10^6
A30: Other operating expense | B30: =(Assumptions!$B$26+Assumptions!$B$19*2)/10^6
A31: Provisions and credit losses | B31: =(Assumptions!$B$27+(Assumptions!$B$21+Assumptions!$B$22)*2)/10^6
A32: Depreciation | B32: =(Assumptions!$B$28+Assumptions!$B$29*2)/10^6
A33: Cash capital expenditure | B33: =(Assumptions!$B$30+Assumptions!$B$31*2)/10^6
A34: Credit interest | B34: =(Assumptions!$B$32+Assumptions!$B$33*2)/10^6
A35: Employees' profit share | B35: =(Assumptions!$B$34*2)/10^6
A37: Every operating line is struck on the SAME twelve months as revenue and gross profit. The previous edition built revenue from the six-month product table doubled while taking cost of sales from the nine months scaled by four thirds, so its base-year gross margin of 7.081% corresponded to no filed period at all. One period, both sides, or the margin is an artefact of the scalars.
A39: RATES — solved, not assumed
A40: Employees' profit share, % of profit after tax | B40: =B35/((Assumptions!$B$35+Assumptions!$B$13)/10^6)
A41: Minority interest, % of OPERATING profit, whole base year | B41: =((Assumptions!$B$36+Assumptions!$B$37*2)/10^6)/((Assumptions!$B$35+Assumptions!$B$13)/10^6-B34*(1-0.22118761296853667))
A42: Implied asset life, years = fixed assets at cost / depreciation | B42: =Assumptions!$B$70/10^6/B32
A43: Maintenance capital expenditure at cost over that life | B43: =Assumptions!$B$70/10^6/B42
A44: Inventory days of cost of sales | B44: =Assumptions!$B$72/10^6/B21*365
A45: Receivable days of revenue | B45: =(Assumptions!$B$73+Assumptions!$B$74)/10^6/B19*365
A46: Operating payable days of cost of sales — dividends payable REMOVED | B46: =(Assumptions!$B$75+Assumptions!$B$76-Assumptions!$B$77)/10^6/B21*365

Sheet Product and Cost
A1: The eight disclosed product lines — revenue AND cost, per line
A2: Note 14-A gives tonnes and value per line. Note 15-A gives the cost stack for the company and NOT by line, so conversion is allocated on the registered processing-intensity weights and feedstock is then allocated on NET REALISABLE VALUE — the standard joint-product method. Every cell here is a formula.
A5: Line | B5: Tonnes, 6M | C5: Value, EGP 6M | D5: Realisation EGP/t | E5: Base tonnes mn | F5: Base realisation | G5: Conversion EGP/t | H5: Feedstock EGP/t | I5: Spread EGP/t
A6: Base and special oils | B6: =Assumptions!$B$46 | C6: =Assumptions!$B$54 | D6: =C6/B6 | E6: =B6*2/10^6 | F6: =D6*$B$16 | G6: =$B$22*H6/$B$23 | H6: =Assumptions!$B$93 | I6: =F6-G6
A7: Paraffin wax | B7: =Assumptions!$B$47 | C7: =Assumptions!$B$55 | D7: =C7/B7 | E7: =B7*2/10^6 | F7: =D7*$B$16 | G7: =$B$22*H7/$B$23 | H7: =Assumptions!$B$94 | I7: =F7-G7
A8: Gas oil | B8: =Assumptions!$B$48 | C8: =Assumptions!$B$56 | D8: =C8/B8 | E8: =B8*2/10^6 | F8: =D8*$B$16 | G8: =$B$22*H8/$B$23 | H8: =Assumptions!$B$95 | I8: =F8-G8
A9: Naphtha | B9: =Assumptions!$B$49 | C9: =Assumptions!$B$57 | D9: =C9/B9 | E9: =B9*2/10^6 | F9: =D9*$B$16 | G9: =$B$22*H9/$B$23 | H9: =Assumptions!$B$96 | I9: =F9-G9
A10: Liquefied petroleum gas | B10: =Assumptions!$B$50 | C10: =Assumptions!$B$58 | D10: =C10/B10 | E10: =B10*2/10^6 | F10: =D10*$B$16 | G10: =$B$22*H10/$B$23 | H10: =Assumptions!$B$97 | I10: =F10-G10
A11: Fuel oil (mix) | B11: =Assumptions!$B$51 | C11: =Assumptions!$B$59 | D11: =C11/B11 | E11: =B11*2/10^6 | F11: =D11*$B$16 | G11: =$B$22*H11/$B$23 | H11: =Assumptions!$B$98 | I11: =F11-G11
A12: Heavy fuel oil | B12: =Assumptions!$B$52 | C12: =Assumptions!$B$60 | D12: =C12/B12 | E12: =B12*2/10^6 | F12: =D12*$B$16 | G12: =$B$22*H12/$B$23 | H12: =Assumptions!$B$99 | I12: =F12-G12
A13: Waste | B13: =Assumptions!$B$53 | C13: =Assumptions!$B$61 | D13: =C13/B13 | E13: =B13*2/10^6 | F13: =D13*$B$16 | G13: =$B$22*H13/$B$23 | H13: =Assumptions!$B$100 | I13: =F13-G13
A14: TOTAL | B14: =SUM(B6:B13) | C14: =SUM(C6:C13) | E14: =SUM(E6:E13) | F14: =SUMPRODUCT(E6:E13,F6:F13)
A15: Revenue at the disclosed realisations, annualised | B15: =SUMPRODUCT(E6:E13,D6:D13)
A16: REALISATION INDEX — solved so the base year foots | B16: ='Base Year'!B19/B15
A18: COST ALLOCATION
A19: Cost of sales, base year | B19: ='Base Year'!B21
A20: Feedstock share of cost (note 15-A) | B20: =Assumptions!$B$63/(Assumptions!$B$63+Assumptions!$B$64+Assumptions!$B$65+Assumptions!$B$66+Assumptions!$B$67)
A21: Feedstock total | B21: =B19*B20
A22: Conversion total | B22: =B19-B21
A23: Processing-weighted tonnage | B23: =SUMPRODUCT(E6:E13,H6:H13)
A24: Net realisable value weighted tonnage | B24: =SUMPRODUCT(E6:E13,I6:I13)
A26: Line | B26: Conversion EGP/t | C26: Net realisable EGP/t | D26: Feedstock EGP/t | E26: Total cost EGP/t | F26: Realisation EGP/t | G26: Spread EGP/t | H26: Gross margin
A27: Base and special oils | B27: =G6 | C27: =I6 | D27: =$B$21*I6/$B$24 | E27: =D27+B27 | F27: =F6 | G27: =F27-E27 | H27: =G27/F27
A28: Paraffin wax | B28: =G7 | C28: =I7 | D28: =$B$21*I7/$B$24 | E28: =D28+B28 | F28: =F7 | G28: =F28-E28 | H28: =G28/F28
A29: Gas oil | B29: =G8 | C29: =I8 | D29: =$B$21*I8/$B$24 | E29: =D29+B29 | F29: =F8 | G29: =F29-E29 | H29: =G29/F29
A30: Naphtha | B30: =G9 | C30: =I9 | D30: =$B$21*I9/$B$24 | E30: =D30+B30 | F30: =F9 | G30: =F30-E30 | H30: =G30/F30
A31: Liquefied petroleum gas | B31: =G10 | C31: =I10 | D31: =$B$21*I10/$B$24 | E31: =D31+B31 | F31: =F10 | G31: =F31-E31 | H31: =G31/F31
A32: Fuel oil (mix) | B32: =G11 | C32: =I11 | D32: =$B$21*I11/$B$24 | E32: =D32+B32 | F32: =F11 | G32: =F32-E32 | H32: =G32/F32
A33: Heavy fuel oil | B33: =G12 | C33: =I12 | D33: =$B$21*I12/$B$24 | E33: =D33+B33 | F33: =F12 | G33: =F33-E33 | H33: =G33/F33
A34: Waste | B34: =G13 | C34: =I13 | D34: =$B$21*I13/$B$24 | E34: =D34+B34 | F34: =F13 | G34: =F34-E34 | H34: =G34/F34
A35: Cost of sales rebuilt from the per-line allocation | B35: =SUMPRODUCT(E6:E13,E27:E34)
A36: must equal the base-year cost of sales — difference | B36: =B35-'Base Year'!B21
A38: Row 36 is the footing test: the eight per-line costs must rebuild the disclosed cost of sales exactly. Feedstock allocated flat per tonne would make fuel oil sell below the cost of its own feed; feedstock allocated on relative sales value would make base oils and paraffin wax — the products this plant exists for — loss-making. Net realisable value is the standard joint-product method and the only one of the three that leaves every disclosed line with a positive spread.

Sheet Forecast
A1: Forecast engine — eight lines by five years, all formulas
A2: This is the block the Sensitivity sheet replicates twenty-five times, once per grid point, so that every sensitivity cell in this workbook is a live re-run rather than a pasted number.
A5: Levers for this block — the base case sets them all neutral
A6: Volume growth added a year | B6: 0
A7: Gross-margin shift | B7: 0
A8: Realisation-path multiplier | B8: 1
A9: Working-capital cycle multiplier | B9: 1
A10: Explicit cost of capital | B10: =Assumptions!$B$152-Assumptions!$B$153+Assumptions!$B$155*Assumptions!$B$154
A11: Equity weight | B11: =Assumptions!$B$7*Assumptions!$B$8/(Assumptions!$B$7*Assumptions!$B$8+(Assumptions!$B$82+Assumptions!$B$83-Assumptions!$B$79)/10^6)
A12: Debt weight | B12: =1-B11
A13: After-tax cost of net debt | B13: =(Assumptions!$B$157*(Assumptions!$B$82+Assumptions!$B$83)/10^6-Assumptions!$B$156*Assumptions!$B$79/10^6)/((Assumptions!$B$82+Assumptions!$B$83-Assumptions!$B$79)/10^6)*(1-0.22118761296853667)
A14: WACC — explicit window | B14: =B11*B10+B12*B13
A15: Terminal risk-free — DERIVED from the target in force | B15: =Assumptions!$B$158+Assumptions!$B$159
A16: Terminal cost of equity | B16: =B15+Assumptions!$B$155*Assumptions!$B$160
A17: WACC — terminal | B17: =(1-Assumptions!$B$162)*B16+Assumptions!$B$162*Assumptions!$B$161*(1-0.22118761296853667)
A19: BASE CASE | B19: 2026E | C19: 2027E | D19: 2028E | E19: 2029E | F19: 2030E
A20: Inflation index, cumulative | C20: =Assumptions!$B$146 | D20: =C20*Assumptions!$B$147 | E20: =D20*Assumptions!$B$148 | F20: =E20*Assumptions!$B$149 | G20: =F20*Assumptions!$B$150
A21: Realisation index, cumulative | C21: =(1+Assumptions!$B$101*$B$8) | D21: =C21*(1+Assumptions!$B$102*$B$8) | E21: =D21*(1+Assumptions!$B$103*$B$8) | F21: =E21*(1+Assumptions!$B$104*$B$8) | G21: =F21*(1+Assumptions!$B$105*$B$8)
A22: Volume — Base and special oils, mn t | C22: ='Product and Cost'!E6*(1+Assumptions!$B$106+$B$6) | D22: =C22*(1+Assumptions!$B$107+$B$6) | E22: =D22*(1+Assumptions!$B$108+$B$6) | F22: =E22*(1+Assumptions!$B$109+$B$6) | G22: =F22*(1+Assumptions!$B$110+$B$6)
A23: Volume — Paraffin wax, mn t | C23: ='Product and Cost'!E7*(1+Assumptions!$B$111+$B$6) | D23: =C23*(1+Assumptions!$B$112+$B$6) | E23: =D23*(1+Assumptions!$B$113+$B$6) | F23: =E23*(1+Assumptions!$B$114+$B$6) | G23: =F23*(1+Assumptions!$B$115+$B$6)
A24: Volume — Gas oil, mn t | C24: ='Product and Cost'!E8*(1+Assumptions!$B$116+$B$6) | D24: =C24*(1+Assumptions!$B$117+$B$6) | E24: =D24*(1+Assumptions!$B$118+$B$6) | F24: =E24*(1+Assumptions!$B$119+$B$6) | G24: =F24*(1+Assumptions!$B$120+$B$6)
A25: Volume — Naphtha, mn t | C25: ='Product and Cost'!E9*(1+Assumptions!$B$121+$B$6) | D25: =C25*(1+Assumptions!$B$122+$B$6) | E25: =D25*(1+Assumptions!$B$123+$B$6) | F25: =E25*(1+Assumptions!$B$124+$B$6) | G25: =F25*(1+Assumptions!$B$125+$B$6)
A26: Volume — Liquefied petroleum gas, mn t | C26: ='Product and Cost'!E10*(1+Assumptions!$B$126+$B$6) | D26: =C26*(1+Assumptions!$B$127+$B$6) | E26: =D26*(1+Assumptions!$B$128+$B$6) | F26: =E26*(1+Assumptions!$B$129+$B$6) | G26: =F26*(1+Assumptions!$B$130+$B$6)
A27: Volume — Fuel oil (mix), mn t | C27: ='Product and Cost'!E11*(1+Assumptions!$B$131+$B$6) | D27: =C27*(1+Assumptions!$B$132+$B$6) | E27: =D27*(1+Assumptions!$B$133+$B$6) | F27: =E27*(1+Assumptions!$B$134+$B$6) | G27: =F27*(1+Assumptions!$B$135+$B$6)
A28: Volume — Heavy fuel oil, mn t | C28: ='Product and Cost'!E12*(1+Assumptions!$B$136+$B$6) | D28: =C28*(1+Assumptions!$B$137+$B$6) | E28: =D28*(1+Assumptions!$B$138+$B$6) | F28: =E28*(1+Assumptions!$B$139+$B$6) | G28: =F28*(1+Assumptions!$B$140+$B$6)
A29: Volume — Waste, mn t | C29: ='Product and Cost'!E13*(1+Assumptions!$B$141+$B$6) | D29: =C29*(1+Assumptions!$B$142+$B$6) | E29: =D29*(1+Assumptions!$B$143+$B$6) | F29: =E29*(1+Assumptions!$B$144+$B$6) | G29: =F29*(1+Assumptions!$B$145+$B$6)
A30: Total volume, mn t | C30: =SUM(C22:C29) | D30: =SUM(D22:D29) | E30: =SUM(E22:E29) | F30: =SUM(F22:F29) | G30: =SUM(G22:G29)
A31: REVENUE | C31: =C22*'Product and Cost'!$F$6*C21+C23*'Product and Cost'!$F$7*C21+C24*'Product and Cost'!$F$8*C21+C25*'Product and Cost'!$F$9*C21+C26*'Product and Cost'!$F$10*C21+C27*'Product and Cost'!$F$11*C21+C28*'Product and Cost'!$F$12*C21+C29*'Product and Cost'!$F$13*C21 | D31: =D22*'Product and Cost'!$F$6*D21+D23*'Product and Cost'!$F$7*D21+D24*'Product and Cost'!$F$8*D21+D25*'Product and Cost'!$F$9*D21+D26*'Product and Cost'!$F$10*D21+D27*'Product and Cost'!$F$11*D21+D28*'Product and Cost'!$F$12*D21+D29*'Product and Cost'!$F$13*D21 | E31: =E22*'Product and Cost'!$F$6*E21+E23*'Product and Cost'!$F$7*E21+E24*'Product and Cost'!$F$8*E21+E25*'Product and Cost'!$F$9*E21+E26*'Product and Cost'!$F$10*E21+E27*'Product and Cost'!$F$11*E21+E28*'Product and Cost'!$F$12*E21+E29*'Product and Cost'!$F$13*E21 | F31: =F22*'Product and Cost'!$F$6*F21+F23*'Product and Cost'!$F$7*F21+F24*'Product and Cost'!$F$8*F21+F25*'Product and Cost'!$F$9*F21+F26*'Product and Cost'!$F$10*F21+F27*'Product and Cost'!$F$11*F21+F28*'Product and Cost'!$F$12*F21+F29*'Product and Cost'!$F$13*F21 | G31: =G22*'Product and Cost'!$F$6*G21+G23*'Product and Cost'!$F$7*G21+G24*'Product and Cost'!$F$8*G21+G25*'Product and Cost'!$F$9*G21+G26*'Product and Cost'!$F$10*G21+G27*'Product and Cost'!$F$11*G21+G28*'Product and Cost'!$F$12*G21+G29*'Product and Cost'!$F$13*G21
A32: Cost of sales | C32: =C22*('Product and Cost'!$D$27*C21*Assumptions!$B$88+'Product and Cost'!$B$27*(0.4863620081*C20+0.4455809638*C20+0.0356254898*C21+0.0324315384))+C23*('Product and Cost'!$D$28*C21*Assumptions!$B$88+'Product and Cost'!$B$28*(0.4863620081*C20+0.4455809638*C20+0.0356254898*C21+0.0324315384))+C24*('Product and Cost'!$D$29*C21*Assumptions!$B$88+'Product and Cost'!$B$29*(0.4863620081*C20+0.4455809638*C20+0.0356254898*C21+0.0324315384))+C25*('Product and Cost'!$D$30*C21*Assumptions!$B$88+'Product and Cost'!$B$30*(0.4863620081*C20+0.4455809638*C20+0.0356254898*C21+0.0324315384))+C26*('Product and Cost'!$D$31*C21*Assumptions!$B$88+'Product and Cost'!$B$31*(0.4863620081*C20+0.4455809638*C20+0.0356254898*C21+0.0324315384))+C27*('Product and Cost'!$D$32*C21*Assumptions!$B$88+'Product and Cost'!$B$32*(0.4863620081*C20+0.4455809638*C20+0.0356254898*C21+0.0324315384))+C28*('Product and Cost'!$D$33*C21*Assumptions!$B$88+'Product and Cost'!$B$33*(0.4863620081*C20+0.4455809638*C20+0.0356254898*C21+0.0324315384))+C29*('Product and Cost'!$D$34*C21*Assumptions!$B$88+'Product and Cost'!$B$34*(0.4863620081*C20+0.4455809638*C20+0.0356254898*C21+0.0324315384)) | D32: =D22*('Product and Cost'!$D$27*D21*Assumptions!$B$88+'Product and Cost'!$B$27*(0.4863620081*D20+0.4455809638*D20+0.0356254898*D21+0.0324315384))+D23*('Product and Cost'!$D$28*D21*Assumptions!$B$88+'Product and Cost'!$B$28*(0.4863620081*D20+0.4455809638*D20+0.0356254898*D21+0.0324315384))+D24*('Product and Cost'!$D$29*D21*Assumptions!$B$88+'Product and Cost'!$B$29*(0.4863620081*D20+0.4455809638*D20+0.0356254898*D21+0.0324315384))+D25*('Product and Cost'!$D$30*D21*Assumptions!$B$88+'Product and Cost'!$B$30*(0.4863620081*D20+0.4455809638*D20+0.0356254898*D21+0.0324315384))+D26*('Product and Cost'!$D$31*D21*Assumptions!$B$88+'Product and Cost'!$B$31*(0.4863620081*D20+0.4455809638*D20+0.0356254898*D21+0.0324315384))+D27*('Product and Cost'!$D$32*D21*Assumptions!$B$88+'Product and Cost'!$B$32*(0.4863620081*D20+0.4455809638*D20+0.0356254898*D21+0.0324315384))+D28*('Product and Cost'!$D$33*D21*Assumptions!$B$88+'Product and Cost'!$B$33*(0.4863620081*D20+0.4455809638*D20+0.0356254898*D21+0.0324315384))+D29*('Product and Cost'!$D$34*D21*Assumptions!$B$88+'Product and Cost'!$B$34*(0.4863620081*D20+0.4455809638*D20+0.0356254898*D21+0.0324315384)) | E32: =E22*('Product and Cost'!$D$27*E21*Assumptions!$B$88+'Product and Cost'!$B$27*(0.4863620081*E20+0.4455809638*E20+0.0356254898*E21+0.0324315384))+E23*('Product and Cost'!$D$28*E21*Assumptions!$B$88+'Product and Cost'!$B$28*(0.4863620081*E20+0.4455809638*E20+0.0356254898*E21+0.0324315384))+E24*('Product and Cost'!$D$29*E21*Assumptions!$B$88+'Product and Cost'!$B$29*(0.4863620081*E20+0.4455809638*E20+0.0356254898*E21+0.0324315384))+E25*('Product and Cost'!$D$30*E21*Assumptions!$B$88+'Product and Cost'!$B$30*(0.4863620081*E20+0.4455809638*E20+0.0356254898*E21+0.0324315384))+E26*('Product and Cost'!$D$31*E21*Assumptions!$B$88+'Product and Cost'!$B$31*(0.4863620081*E20+0.4455809638*E20+0.0356254898*E21+0.0324315384))+E27*('Product and Cost'!$D$32*E21*Assumptions!$B$88+'Product and Cost'!$B$32*(0.4863620081*E20+0.4455809638*E20+0.0356254898*E21+0.0324315384))+E28*('Product and Cost'!$D$33*E21*Assumptions!$B$88+'Product and Cost'!$B$33*(0.4863620081*E20+0.4455809638*E20+0.0356254898*E21+0.0324315384))+E29*('Product and Cost'!$D$34*E21*Assumptions!$B$88+'Product and Cost'!$B$34*(0.4863620081*E20+0.4455809638*E20+0.0356254898*E21+0.0324315384)) | F32: =F22*('Product and Cost'!$D$27*F21*Assumptions!$B$88+'Product and Cost'!$B$27*(0.4863620081*F20+0.4455809638*F20+0.0356254898*F21+0.0324315384))+F23*('Product and Cost'!$D$28*F21*Assumptions!$B$88+'Product and Cost'!$B$28*(0.4863620081*F20+0.4455809638*F20+0.0356254898*F21+0.0324315384))+F24*('Product and Cost'!$D$29*F21*Assumptions!$B$88+'Product and Cost'!$B$29*(0.4863620081*F20+0.4455809638*F20+0.0356254898*F21+0.0324315384))+F25*('Product and Cost'!$D$30*F21*Assumptions!$B$88+'Product and Cost'!$B$30*(0.4863620081*F20+0.4455809638*F20+0.0356254898*F21+0.0324315384))+F26*('Product and Cost'!$D$31*F21*Assumptions!$B$88+'Product and Cost'!$B$31*(0.4863620081*F20+0.4455809638*F20+0.0356254898*F21+0.0324315384))+F27*('Product and Cost'!$D$32*F21*Assumptions!$B$88+'Product and Cost'!$B$32*(0.4863620081*F20+0.4455809638*F20+0.0356254898*F21+0.0324315384))+F28*('Product and Cost'!$D$33*F21*Assumptions!$B$88+'Product and Cost'!$B$33*(0.4863620081*F20+0.4455809638*F20+0.0356254898*F21+0.0324315384))+F29*('Product and Cost'!$D$34*F21*Assumptions!$B$88+'Product and Cost'!$B$34*(0.4863620081*F20+0.4455809638*F20+0.0356254898*F21+0.0324315384)) | G32: =G22*('Product and Cost'!$D$27*G21*Assumptions!$B$88+'Product and Cost'!$B$27*(0.4863620081*G20+0.4455809638*G20+0.0356254898*G21+0.0324315384))+G23*('Product and Cost'!$D$28*G21*Assumptions!$B$88+'Product and Cost'!$B$28*(0.4863620081*G20+0.4455809638*G20+0.0356254898*G21+0.0324315384))+G24*('Product and Cost'!$D$29*G21*Assumptions!$B$88+'Product and Cost'!$B$29*(0.4863620081*G20+0.4455809638*G20+0.0356254898*G21+0.0324315384))+G25*('Product and Cost'!$D$30*G21*Assumptions!$B$88+'Product and Cost'!$B$30*(0.4863620081*G20+0.4455809638*G20+0.0356254898*G21+0.0324315384))+G26*('Product and Cost'!$D$31*G21*Assumptions!$B$88+'Product and Cost'!$B$31*(0.4863620081*G20+0.4455809638*G20+0.0356254898*G21+0.0324315384))+G27*('Product and Cost'!$D$32*G21*Assumptions!$B$88+'Product and Cost'!$B$32*(0.4863620081*G20+0.4455809638*G20+0.0356254898*G21+0.0324315384))+G28*('Product and Cost'!$D$33*G21*Assumptions!$B$88+'Product and Cost'!$B$33*(0.4863620081*G20+0.4455809638*G20+0.0356254898*G21+0.0324315384))+G29*('Product and Cost'!$D$34*G21*Assumptions!$B$88+'Product and Cost'!$B$34*(0.4863620081*G20+0.4455809638*G20+0.0356254898*G21+0.0324315384))
A33: GROSS PROFIT | C33: =C31-C32+$B$7*C31 | D33: =D31-D32+$B$7*D31 | E33: =E31-E32+$B$7*E31 | F33: =F31-F32+$B$7*F31 | G33: =G31-G32+$B$7*G31
A34: Gross margin | C34: =C33/C31 | D34: =D33/D31 | E34: =E33/E31 | F34: =F33/F31 | G34: =G33/G31
A35: Operating expense | C35: =('Base Year'!$B$28*C20)+('Base Year'!$B$29*C20*C30/'Product and Cost'!$E$14)+('Base Year'!$B$30*C20)+('Base Year'!$B$31*C20) | D35: =('Base Year'!$B$28*D20)+('Base Year'!$B$29*D20*D30/'Product and Cost'!$E$14)+('Base Year'!$B$30*D20)+('Base Year'!$B$31*D20) | E35: =('Base Year'!$B$28*E20)+('Base Year'!$B$29*E20*E30/'Product and Cost'!$E$14)+('Base Year'!$B$30*E20)+('Base Year'!$B$31*E20) | F35: =('Base Year'!$B$28*F20)+('Base Year'!$B$29*F20*F30/'Product and Cost'!$E$14)+('Base Year'!$B$30*F20)+('Base Year'!$B$31*F20) | G35: =('Base Year'!$B$28*G20)+('Base Year'!$B$29*G20*G30/'Product and Cost'!$E$14)+('Base Year'!$B$30*G20)+('Base Year'!$B$31*G20)
A36: EBITDA | C36: =C33-C35 | D36: =D33-D35 | E36: =E33-E35 | F36: =F33-F35 | G36: =G33-G35
A37: Capital expenditure — maintenance + growth | C37: ='Base Year'!$B$43*C20+MAX(C30-'Product and Cost'!$E$14,0)*1947.901031*C20 | D37: ='Base Year'!$B$43*D20+MAX(D30-C30,0)*1947.901031*D20 | E37: ='Base Year'!$B$43*E20+MAX(E30-D30,0)*1947.901031*E20 | F37: ='Base Year'!$B$43*F20+MAX(F30-E30,0)*1947.901031*F20 | G37: ='Base Year'!$B$43*G20+MAX(G30-F30,0)*1947.901031*G20
A38: Fixed assets at cost, closing | C38: =(Assumptions!$B$70+Assumptions!$B$71)/10^6+C37 | D38: =C38+D37 | E38: =D38+E37 | F38: =E38+F37 | G38: =F38+G37
A39: Depreciation — rolls off the asset register | C39: =(Assumptions!$B$70+Assumptions!$B$71)/10^6/'Base Year'!$B$42 | D39: =C38/'Base Year'!$B$42 | E39: =D38/'Base Year'!$B$42 | F39: =E38/'Base Year'!$B$42 | G39: =F38/'Base Year'!$B$42
A40: Fixed assets, net book, closing | C40: =(Assumptions!$B$69+Assumptions!$B$71)/10^6+C37-C39 | D40: =C40+D37-D39 | E40: =D40+E37-E39 | F40: =E40+F37-F39 | G40: =F40+G37-G39
A41: EBIT | C41: =C36-C39 | D41: =D36-D39 | E41: =E36-E39 | F41: =F36-F39 | G41: =G36-G39
A42: NOPAT before the profit share | C42: =C41*(1-Assumptions!$B$87) | D42: =D41*(1-Assumptions!$B$87) | E42: =E41*(1-Assumptions!$B$87) | F42: =F41*(1-Assumptions!$B$87) | G42: =G41*(1-Assumptions!$B$87)
A43: less employees' profit share and board bonuses | C43: =MAX(C42,0)*'Base Year'!$B$40 | D43: =MAX(D42,0)*'Base Year'!$B$40 | E43: =MAX(E42,0)*'Base Year'!$B$40 | F43: =MAX(F42,0)*'Base Year'!$B$40 | G43: =MAX(G42,0)*'Base Year'!$B$40
A44: NOPAT | C44: =C42-C43 | D44: =D42-D43 | E44: =E42-E43 | F44: =F42-F43 | G44: =G42-G43
A45: Net working capital — on days | C45: ='Base Year'!$B$44*$B$9/365*C32+'Base Year'!$B$45*$B$9/365*C31-'Base Year'!$B$46*$B$9/365*C32 | D45: ='Base Year'!$B$44*$B$9/365*D32+'Base Year'!$B$45*$B$9/365*D31-'Base Year'!$B$46*$B$9/365*D32 | E45: ='Base Year'!$B$44*$B$9/365*E32+'Base Year'!$B$45*$B$9/365*E31-'Base Year'!$B$46*$B$9/365*E32 | F45: ='Base Year'!$B$44*$B$9/365*F32+'Base Year'!$B$45*$B$9/365*F31-'Base Year'!$B$46*$B$9/365*F32 | G45: ='Base Year'!$B$44*$B$9/365*G32+'Base Year'!$B$45*$B$9/365*G31-'Base Year'!$B$46*$B$9/365*G32
A46: change in working capital | C46: =C45-('Base Year'!$B$44/365*'Base Year'!$B$21+'Base Year'!$B$45/365*'Base Year'!$B$19-'Base Year'!$B$46/365*'Base Year'!$B$21) | D46: =D45-C45 | E46: =E45-D45 | F46: =F45-E45 | G46: =G45-F45
A47: FREE CASH FLOW TO THE FIRM | C47: =C44+C39-C37-C46 | D47: =D44+D39-D37-D46 | E47: =E44+E39-E37-E46 | F47: =F44+F39-F37-F46 | G47: =G44+G39-G37-G46
A48: Glide fraction | C48: =0.0000000000 | D48: =0.3571428571 | E48: =0.6428571429 | F48: =0.8571428571 | G48: =1.0000000000
A49: Forward cost of capital | C49: =$B$14-($B$14-$B$17)*C48 | D49: =$B$14-($B$14-$B$17)*D48 | E49: =$B$14-($B$14-$B$17)*E48 | F49: =$B$14-($B$14-$B$17)*F48 | G49: =$B$14-($B$14-$B$17)*G48
A50: Cumulative discount factor | C50: =1/(1+C49) | D50: =C50/(1+D49) | E50: =D50/(1+E49) | F50: =E50/(1+F49) | G50: =F50/(1+G49)
A51: Present value | C51: =C47*C50 | D51: =D47*D50 | E51: =E47*E50 | F51: =F47*F50 | G51: =G47*G50
A52: PV of the explicit window | B52: =SUM(C51:G51) | C52: =C45+C38 | D52: =D45+D38 | E52: =E45+E38 | F52: =F45+F38 | G52: =G45+G38
A53: Terminal return on invested capital, at REPLACEMENT cost | B53: =G44*(1+Assumptions!$B$89)/G52
A54: Required reinvestment = growth / return | B54: =MIN(Assumptions!$B$89/B53,0.95)
A55: Terminal value | B55: =G44*(1+Assumptions!$B$89)*(1-B54)/MAX($B$17-Assumptions!$B$89,0.02)
A56: PV of the terminal block | B56: =B55*G50
A57: ENTERPRISE VALUE | B57: =B52+B56
A58: plus net cash | B58: =(Assumptions!$B$79-Assumptions!$B$82-Assumptions!$B$83)/10^6
A59: Enterprise value including cash | B59: =B57+B58
A60: less minority — on the WHOLE enterprise, cash included | B60: =B59*'Base Year'!$B$41
A61: less the tax-disputes provision | B61: =Assumptions!$B$78/10^6
A62: less dividends payable — declared, out of working capital | B62: =Assumptions!$B$77/10^6
A63: plus non-operating investments and pledged deposits | B63: =(Assumptions!$B$81+Assumptions!$B$80)/10^6
A64: EQUITY ATTRIBUTABLE | B64: =B59-B60-B61-B62+B63
A65: VALUE PER SHARE, EGP | B65: =B64/Assumptions!$B$8

Sheet Sensitivity
A1: Sensitivity — every grid point is the whole engine, again, in formulas
A2: The previous edition pasted these rows because each point is a whole-model re-run and its builder could not express a re-run inside a grid. Three of the pasted rows turned out not to reproduce: a working-capital row whose grid was never sorted, a beta row whose centre did not return the base case, and a volume row whose label described a different scenario from the one it ran. None of that can happen here, because there is nothing to paste.
A4: Summary — every cell points at its own live block below
A5: Gross margin, shifted on every forecast year
A6: grid point 1: -1.0% | C6: -0.01 | I6: =B95
A7: grid point 2: -0.5% | C7: -0.005 | I7: =B144
A8: grid point 3: +0.0% | C8: 0 | I8: =B193 | J8: =B193-Forecast!B65
A9: grid point 4: +0.5% | C9: 0.005 | I9: =B242
A10: grid point 5: +1.0% | C10: 0.01 | I10: =B291
A12: Volume growth path, as a multiple of the assumed path
A13: grid point 1: -6.0% | B13: -0.06 | I13: =B340
A14: grid point 2: -3.0% | B14: -0.03 | I14: =B389
A15: grid point 3: +0.0% | B15: 0 | I15: =B438 | J15: =B438-Forecast!B65
A16: grid point 4: +3.0% | B16: 0.03 | I16: =B487
A17: grid point 5: +6.0% | B17: 0.06 | I17: =B536
A19: Realisation path, as a multiple of the assumed path
A20: grid point 1: 0.90x | D20: 0.9 | I20: =B585
A21: grid point 2: 0.95x | D21: 0.95 | I21: =B634
A22: grid point 3: 1.00x | D22: 1 | I22: =B683 | J22: =B683-Forecast!B65
A23: grid point 4: 1.05x | D23: 1.05 | I23: =B732
A24: grid point 5: 1.10x | D24: 1.1 | I24: =B781
A26: Beta
A27: grid point 1: 0.6000 | F27: 0.27533624 | G27: 0.16198219 | I27: =B830
A28: grid point 2: 0.8000 | F28: 0.29909374 | G28: 0.17458219 | I28: =B879
A29: grid point 3: 0.9080 | F29: 0.31192279 | G29: 0.18138619 | I29: =B928 | J29: =B928-Forecast!B65
A30: grid point 4: 1.1500 | F30: 0.34066938 | G30: 0.19663219 | I30: =B977
A31: grid point 5: 1.3000 | F31: 0.35848751 | G31: 0.20608219 | I31: =B1026
A33: Working-capital cycle, as a multiple of the solved days
A34: grid point 1: 0.50x | E34: 0.5 | I34: =B1075
A35: grid point 2: 0.75x | E35: 0.75 | I35: =B1124
A36: grid point 3: 1.00x | E36: 1 | I36: =B1173 | J36: =B1173-Forecast!B65
A37: grid point 4: 1.25x | E37: 1.25 | I37: =B1222
A38: grid point 5: 1.50x | E38: 1.5 | I38: =B1271
A40: Terminal growth
A41: grid point 1: 3.0% | H41: 0.03 | I41: =B1320
A42: grid point 2: 4.0% | H42: 0.04 | I42: =B1369
A43: grid point 3: 5.0% | H43: 0.05 | I43: =B1418 | J43: =B1418-Forecast!B65
A44: grid point 4: 6.0% | H44: 0.06 | I44: =B1467
A45: grid point 5: 7.0% | H45: 0.07 | I45: =B1516
A47: GATE — every row must return the base case at its own base point
A49: Gross margin, shifted on every forecast year — -1.0% | B49: 2026E | C49: 2027E | D49: 2028E | E49: 2029E | F49: 2030E
A50: Inflation index, cumulative | C50: =Assumptions!$B$146 | D50: =C50*Assumptions!$B$147 | E50: =D50*Assumptions!$B$148 | F50: =E50*Assumptions!$B$149 | G50: =F50*Assumptions!$B$150
A51: Realisation index, cumulative | C51: =(1+Assumptions!$B$101*Forecast!$B$8) | D51: =C51*(1+Assumptions!$B$102*Forecast!$B$8) | E51: =D51*(1+Assumptions!$B$103*Forecast!$B$8) | F51: =E51*(1+Assumptions!$B$104*Forecast!$B$8) | G51: =F51*(1+Assumptions!$B$105*Forecast!$B$8)
A52: Volume — Base and special oils, mn t | C52: ='Product and Cost'!E6*(1+Assumptions!$B$106+Forecast!$B$6) | D52: =C52*(1+Assumptions!$B$107+Forecast!$B$6) | E52: =D52*(1+Assumptions!$B$108+Forecast!$B$6) | F52: =E52*(1+Assumptions!$B$109+Forecast!$B$6) | G52: =F52*(1+Assumptions!$B$110+Forecast!$B$6)
A53: Volume — Paraffin wax, mn t | C53: ='Product and Cost'!E7*(1+Assumptions!$B$111+Forecast!$B$6) | D53: =C53*(1+Assumptions!$B$112+Forecast!$B$6) | E53: =D53*(1+Assumptions!$B$113+Forecast!$B$6) | F53: =E53*(1+Assumptions!$B$114+Forecast!$B$6) | G53: =F53*(1+Assumptions!$B$115+Forecast!$B$6)
A54: Volume — Gas oil, mn t | C54: ='Product and Cost'!E8*(1+Assumptions!$B$116+Forecast!$B$6) | D54: =C54*(1+Assumptions!$B$117+Forecast!$B$6) | E54: =D54*(1+Assumptions!$B$118+Forecast!$B$6) | F54: =E54*(1+Assumptions!$B$119+Forecast!$B$6) | G54: =F54*(1+Assumptions!$B$120+Forecast!$B$6)
A55: Volume — Naphtha, mn t | C55: ='Product and Cost'!E9*(1+Assumptions!$B$121+Forecast!$B$6) | D55: =C55*(1+Assumptions!$B$122+Forecast!$B$6) | E55: =D55*(1+Assumptions!$B$123+Forecast!$B$6) | F55: =E55*(1+Assumptions!$B$124+Forecast!$B$6) | G55: =F55*(1+Assumptions!$B$125+Forecast!$B$6)
A56: Volume — Liquefied petroleum gas, mn t | C56: ='Product and Cost'!E10*(1+Assumptions!$B$126+Forecast!$B$6) | D56: =C56*(1+Assumptions!$B$127+Forecast!$B$6) | E56: =D56*(1+Assumptions!$B$128+Forecast!$B$6) | F56: =E56*(1+Assumptions!$B$129+Forecast!$B$6) | G56: =F56*(1+Assumptions!$B$130+Forecast!$B$6)
A57: Volume — Fuel oil (mix), mn t | C57: ='Product and Cost'!E11*(1+Assumptions!$B$131+Forecast!$B$6) | D57: =C57*(1+Assumptions!$B$132+Forecast!$B$6) | E57: =D57*(1+Assumptions!$B$133+Forecast!$B$6) | F57: =E57*(1+Assumptions!$B$134+Forecast!$B$6) | G57: =F57*(1+Assumptions!$B$135+Forecast!$B$6)
A58: Volume — Heavy fuel oil, mn t | C58: ='Product and Cost'!E12*(1+Assumptions!$B$136+Forecast!$B$6) | D58: =C58*(1+Assumptions!$B$137+Forecast!$B$6) | E58: =D58*(1+Assumptions!$B$138+Forecast!$B$6) | F58: =E58*(1+Assumptions!$B$139+Forecast!$B$6) | G58: =F58*(1+Assumptions!$B$140+Forecast!$B$6)
A59: Volume — Waste, mn t | C59: ='Product and Cost'!E13*(1+Assumptions!$B$141+Forecast!$B$6) | D59: =C59*(1+Assumptions!$B$142+Forecast!$B$6) | E59: =D59*(1+Assumptions!$B$143+Forecast!$B$6) | F59: =E59*(1+Assumptions!$B$144+Forecast!$B$6) | G59: =F59*(1+Assumptions!$B$145+Forecast!$B$6)
A60: Total volume, mn t | C60: =SUM(C52:C59) | D60: =SUM(D52:D59) | E60: =SUM(E52:E59) | F60: =SUM(F52:F59) | G60: =SUM(G52:G59)
A61: REVENUE | C61: =C52*'Product and Cost'!$F$6*C51+C53*'Product and Cost'!$F$7*C51+C54*'Product and Cost'!$F$8*C51+C55*'Product and Cost'!$F$9*C51+C56*'Product and Cost'!$F$10*C51+C57*'Product and Cost'!$F$11*C51+C58*'Product and Cost'!$F$12*C51+C59*'Product and Cost'!$F$13*C51 | D61: =D52*'Product and Cost'!$F$6*D51+D53*'Product and Cost'!$F$7*D51+D54*'Product and Cost'!$F$8*D51+D55*'Product and Cost'!$F$9*D51+D56*'Product and Cost'!$F$10*D51+D57*'Product and Cost'!$F$11*D51+D58*'Product and Cost'!$F$12*D51+D59*'Product and Cost'!$F$13*D51 | E61: =E52*'Product and Cost'!$F$6*E51+E53*'Product and Cost'!$F$7*E51+E54*'Product and Cost'!$F$8*E51+E55*'Product and Cost'!$F$9*E51+E56*'Product and Cost'!$F$10*E51+E57*'Product and Cost'!$F$11*E51+E58*'Product and Cost'!$F$12*E51+E59*'Product and Cost'!$F$13*E51 | F61: =F52*'Product and Cost'!$F$6*F51+F53*'Product and Cost'!$F$7*F51+F54*'Product and Cost'!$F$8*F51+F55*'Product and Cost'!$F$9*F51+F56*'Product and Cost'!$F$10*F51+F57*'Product and Cost'!$F$11*F51+F58*'Product and Cost'!$F$12*F51+F59*'Product and Cost'!$F$13*F51 | G61: =G52*'Product and Cost'!$F$6*G51+G53*'Product and Cost'!$F$7*G51+G54*'Product and Cost'!$F$8*G51+G55*'Product and Cost'!$F$9*G51+G56*'Product and Cost'!$F$10*G51+G57*'Product and Cost'!$F$11*G51+G58*'Product and Cost'!$F$12*G51+G59*'Product and Cost'!$F$13*G51
A62: Cost of sales | C62: =C52*('Product and Cost'!$D$27*C51*Assumptions!$B$88+'Product and Cost'!$B$27*(0.4863620081*C50+0.4455809638*C50+0.0356254898*C51+0.0324315384))+C53*('Product and Cost'!$D$28*C51*Assumptions!$B$88+'Product and Cost'!$B$28*(0.4863620081*C50+0.4455809638*C50+0.0356254898*C51+0.0324315384))+C54*('Product and Cost'!$D$29*C51*Assumptions!$B$88+'Product and Cost'!$B$29*(0.4863620081*C50+0.4455809638*C50+0.0356254898*C51+0.0324315384))+C55*('Product and Cost'!$D$30*C51*Assumptions!$B$88+'Product and Cost'!$B$30*(0.4863620081*C50+0.4455809638*C50+0.0356254898*C51+0.0324315384))+C56*('Product and Cost'!$D$31*C51*Assumptions!$B$88+'Product and Cost'!$B$31*(0.4863620081*C50+0.4455809638*C50+0.0356254898*C51+0.0324315384))+C57*('Product and Cost'!$D$32*C51*Assumptions!$B$88+'Product and Cost'!$B$32*(0.4863620081*C50+0.4455809638*C50+0.0356254898*C51+0.0324315384))+C58*('Product and Cost'!$D$33*C51*Assumptions!$B$88+'Product and Cost'!$B$33*(0.4863620081*C50+0.4455809638*C50+0.0356254898*C51+0.0324315384))+C59*('Product and Cost'!$D$34*C51*Assumptions!$B$88+'Product and Cost'!$B$34*(0.4863620081*C50+0.4455809638*C50+0.0356254898*C51+0.0324315384)) | D62: =D52*('Product and Cost'!$D$27*D51*Assumptions!$B$88+'Product and Cost'!$B$27*(0.4863620081*D50+0.4455809638*D50+0.0356254898*D51+0.0324315384))+D53*('Product and Cost'!$D$28*D51*Assumptions!$B$88+'Product and Cost'!$B$28*(0.4863620081*D50+0.4455809638*D50+0.0356254898*D51+0.0324315384))+D54*('Product and Cost'!$D$29*D51*Assumptions!$B$88+'Product and Cost'!$B$29*(0.4863620081*D50+0.4455809638*D50+0.0356254898*D51+0.0324315384))+D55*('Product and Cost'!$D$30*D51*Assumptions!$B$88+'Product and Cost'!$B$30*(0.4863620081*D50+0.4455809638*D50+0.0356254898*D51+0.0324315384))+D56*('Product and Cost'!$D$31*D51*Assumptions!$B$88+'Product and Cost'!$B$31*(0.4863620081*D50+0.4455809638*D50+0.0356254898*D51+0.0324315384))+D57*('Product and Cost'!$D$32*D51*Assumptions!$B$88+'Product and Cost'!$B$32*(0.4863620081*D50+0.4455809638*D50+0.0356254898*D51+0.0324315384))+D58*('Product and Cost'!$D$33*D51*Assumptions!$B$88+'Product and Cost'!$B$33*(0.4863620081*D50+0.4455809638*D50+0.0356254898*D51+0.0324315384))+D59*('Product and Cost'!$D$34*D51*Assumptions!$B$88+'Product and Cost'!$B$34*(0.4863620081*D50+0.4455809638*D50+0.0356254898*D51+0.0324315384)) | E62: =E52*('Product and Cost'!$D$27*E51*Assumptions!$B$88+'Product and Cost'!$B$27*(0.4863620081*E50+0.4455809638*E50+0.0356254898*E51+0.0324315384))+E53*('Product and Cost'!$D$28*E51*Assumptions!$B$88+'Product and Cost'!$B$28*(0.4863620081*E50+0.4455809638*E50+0.0356254898*E51+0.0324315384))+E54*('Product and Cost'!$D$29*E51*Assumptions!$B$88+'Product and Cost'!$B$29*(0.4863620081*E50+0.4455809638*E50+0.0356254898*E51+0.0324315384))+E55*('Product and Cost'!$D$30*E51*Assumptions!$B$88+'Product and Cost'!$B$30*(0.4863620081*E50+0.4455809638*E50+0.0356254898*E51+0.0324315384))+E56*('Product and Cost'!$D$31*E51*Assumptions!$B$88+'Product and Cost'!$B$31*(0.4863620081*E50+0.4455809638*E50+0.0356254898*E51+0.0324315384))+E57*('Product and Cost'!$D$32*E51*Assumptions!$B$88+'Product and Cost'!$B$32*(0.4863620081*E50+0.4455809638*E50+0.0356254898*E51+0.0324315384))+E58*('Product and Cost'!$D$33*E51*Assumptions!$B$88+'Product and Cost'!$B$33*(0.4863620081*E50+0.4455809638*E50+0.0356254898*E51+0.0324315384))+E59*('Product and Cost'!$D$34*E51*Assumptions!$B$88+'Product and Cost'!$B$34*(0.4863620081*E50+0.4455809638*E50+0.0356254898*E51+0.0324315384)) | F62: =F52*('Product and Cost'!$D$27*F51*Assumptions!$B$88+'Product and Cost'!$B$27*(0.4863620081*F50+0.4455809638*F50+0.0356254898*F51+0.0324315384))+F53*('Product and Cost'!$D$28*F51*Assumptions!$B$88+'Product and Cost'!$B$28*(0.4863620081*F50+0.4455809638*F50+0.0356254898*F51+0.0324315384))+F54*('Product and Cost'!$D$29*F51*Assumptions!$B$88+'Product and Cost'!$B$29*(0.4863620081*F50+0.4455809638*F50+0.0356254898*F51+0.0324315384))+F55*('Product and Cost'!$D$30*F51*Assumptions!$B$88+'Product and Cost'!$B$30*(0.4863620081*F50+0.4455809638*F50+0.0356254898*F51+0.0324315384))+F56*('Product and Cost'!$D$31*F51*Assumptions!$B$88+'Product and Cost'!$B$31*(0.4863620081*F50+0.4455809638*F50+0.0356254898*F51+0.0324315384))+F57*('Product and Cost'!$D$32*F51*Assumptions!$B$88+'Product and Cost'!$B$32*(0.4863620081*F50+0.4455809638*F50+0.0356254898*F51+0.0324315384))+F58*('Product and Cost'!$D$33*F51*Assumptions!$B$88+'Product and Cost'!$B$33*(0.4863620081*F50+0.4455809638*F50+0.0356254898*F51+0.0324315384))+F59*('Product and Cost'!$D$34*F51*Assumptions!$B$88+'Product and Cost'!$B$34*(0.4863620081*F50+0.4455809638*F50+0.0356254898*F51+0.0324315384)) | G62: =G52*('Product and Cost'!$D$27*G51*Assumptions!$B$88+'Product and Cost'!$B$27*(0.4863620081*G50+0.4455809638*G50+0.0356254898*G51+0.0324315384))+G53*('Product and Cost'!$D$28*G51*Assumptions!$B$88+'Product and Cost'!$B$28*(0.4863620081*G50+0.4455809638*G50+0.0356254898*G51+0.0324315384))+G54*('Product and Cost'!$D$29*G51*Assumptions!$B$88+'Product and Cost'!$B$29*(0.4863620081*G50+0.4455809638*G50+0.0356254898*G51+0.0324315384))+G55*('Product and Cost'!$D$30*G51*Assumptions!$B$88+'Product and Cost'!$B$30*(0.4863620081*G50+0.4455809638*G50+0.0356254898*G51+0.0324315384))+G56*('Product and Cost'!$D$31*G51*Assumptions!$B$88+'Product and Cost'!$B$31*(0.4863620081*G50+0.4455809638*G50+0.0356254898*G51+0.0324315384))+G57*('Product and Cost'!$D$32*G51*Assumptions!$B$88+'Product and Cost'!$B$32*(0.4863620081*G50+0.4455809638*G50+0.0356254898*G51+0.0324315384))+G58*('Product and Cost'!$D$33*G51*Assumptions!$B$88+'Product and Cost'!$B$33*(0.4863620081*G50+0.4455809638*G50+0.0356254898*G51+0.0324315384))+G59*('Product and Cost'!$D$34*G51*Assumptions!$B$88+'Product and Cost'!$B$34*(0.4863620081*G50+0.4455809638*G50+0.0356254898*G51+0.0324315384))
A63: GROSS PROFIT | C63: =C61-C62+$C$6*C61 | D63: =D61-D62+$C$6*D61 | E63: =E61-E62+$C$6*E61 | F63: =F61-F62+$C$6*F61 | G63: =G61-G62+$C$6*G61
A64: Gross margin | C64: =C63/C61 | D64: =D63/D61 | E64: =E63/E61 | F64: =F63/F61 | G64: =G63/G61
A65: Operating expense | C65: =('Base Year'!$B$28*C50)+('Base Year'!$B$29*C50*C60/'Product and Cost'!$E$14)+('Base Year'!$B$30*C50)+('Base Year'!$B$31*C50) | D65: =('Base Year'!$B$28*D50)+('Base Year'!$B$29*D50*D60/'Product and Cost'!$E$14)+('Base Year'!$B$30*D50)+('Base Year'!$B$31*D50) | E65: =('Base Year'!$B$28*E50)+('Base Year'!$B$29*E50*E60/'Product and Cost'!$E$14)+('Base Year'!$B$30*E50)+('Base Year'!$B$31*E50) | F65: =('Base Year'!$B$28*F50)+('Base Year'!$B$29*F50*F60/'Product and Cost'!$E$14)+('Base Year'!$B$30*F50)+('Base Year'!$B$31*F50) | G65: =('Base Year'!$B$28*G50)+('Base Year'!$B$29*G50*G60/'Product and Cost'!$E$14)+('Base Year'!$B$30*G50)+('Base Year'!$B$31*G50)
A66: EBITDA | C66: =C63-C65 | D66: =D63-D65 | E66: =E63-E65 | F66: =F63-F65 | G66: =G63-G65
A67: Capital expenditure — maintenance + growth | C67: ='Base Year'!$B$43*C50+MAX(C60-'Product and Cost'!$E$14,0)*1947.901031*C50 | D67: ='Base Year'!$B$43*D50+MAX(D60-C60,0)*1947.901031*D50 | E67: ='Base Year'!$B$43*E50+MAX(E60-D60,0)*1947.901031*E50 | F67: ='Base Year'!$B$43*F50+MAX(F60-E60,0)*1947.901031*F50 | G67: ='Base Year'!$B$43*G50+MAX(G60-F60,0)*1947.901031*G50
A68: Fixed assets at cost, closing | C68: =(Assumptions!$B$70+Assumptions!$B$71)/10^6+C67 | D68: =C68+D67 | E68: =D68+E67 | F68: =E68+F67 | G68: =F68+G67
A69: Depreciation — rolls off the asset register | C69: =(Assumptions!$B$70+Assumptions!$B$71)/10^6/'Base Year'!$B$42 | D69: =C68/'Base Year'!$B$42 | E69: =D68/'Base Year'!$B$42 | F69: =E68/'Base Year'!$B$42 | G69: =F68/'Base Year'!$B$42
A70: Fixed assets, net book, closing | C70: =(Assumptions!$B$69+Assumptions!$B$71)/10^6+C67-C69 | D70: =C70+D67-D69 | E70: =D70+E67-E69 | F70: =E70+F67-F69 | G70: =F70+G67-G69
A71: EBIT | C71: =C66-C69 | D71: =D66-D69 | E71: =E66-E69 | F71: =F66-F69 | G71: =G66-G69
A72: NOPAT before the profit share | C72: =C71*(1-Assumptions!$B$87) | D72: =D71*(1-Assumptions!$B$87) | E72: =E71*(1-Assumptions!$B$87) | F72: =F71*(1-Assumptions!$B$87) | G72: =G71*(1-Assumptions!$B$87)
A73: less employees' profit share and board bonuses | C73: =MAX(C72,0)*'Base Year'!$B$40 | D73: =MAX(D72,0)*'Base Year'!$B$40 | E73: =MAX(E72,0)*'Base Year'!$B$40 | F73: =MAX(F72,0)*'Base Year'!$B$40 | G73: =MAX(G72,0)*'Base Year'!$B$40
A74: NOPAT | C74: =C72-C73 | D74: =D72-D73 | E74: =E72-E73 | F74: =F72-F73 | G74: =G72-G73
A75: Net working capital — on days | C75: ='Base Year'!$B$44*Forecast!$B$9/365*C62+'Base Year'!$B$45*Forecast!$B$9/365*C61-'Base Year'!$B$46*Forecast!$B$9/365*C62 | D75: ='Base Year'!$B$44*Forecast!$B$9/365*D62+'Base Year'!$B$45*Forecast!$B$9/365*D61-'Base Year'!$B$46*Forecast!$B$9/365*D62 | E75: ='Base Year'!$B$44*Forecast!$B$9/365*E62+'Base Year'!$B$45*Forecast!$B$9/365*E61-'Base Year'!$B$46*Forecast!$B$9/365*E62 | F75: ='Base Year'!$B$44*Forecast!$B$9/365*F62+'Base Year'!$B$45*Forecast!$B$9/365*F61-'Base Year'!$B$46*Forecast!$B$9/365*F62 | G75: ='Base Year'!$B$44*Forecast!$B$9/365*G62+'Base Year'!$B$45*Forecast!$B$9/365*G61-'Base Year'!$B$46*Forecast!$B$9/365*G62
A76: change in working capital | C76: =C75-('Base Year'!$B$44/365*'Base Year'!$B$21+'Base Year'!$B$45/365*'Base Year'!$B$19-'Base Year'!$B$46/365*'Base Year'!$B$21) | D76: =D75-C75 | E76: =E75-D75 | F76: =F75-E75 | G76: =G75-F75
A77: FREE CASH FLOW TO THE FIRM | C77: =C74+C69-C67-C76 | D77: =D74+D69-D67-D76 | E77: =E74+E69-E67-E76 | F77: =F74+F69-F67-F76 | G77: =G74+G69-G67-G76
A78: Glide fraction | C78: =0.0000000000 | D78: =0.3571428571 | E78: =0.6428571429 | F78: =0.8571428571 | G78: =1.0000000000
A79: Forward cost of capital | C79: =Forecast!$B$14-(Forecast!$B$14-Forecast!$B$17)*C78 | D79: =Forecast!$B$14-(Forecast!$B$14-Forecast!$B$17)*D78 | E79: =Forecast!$B$14-(Forecast!$B$14-Forecast!$B$17)*E78 | F79: =Forecast!$B$14-(Forecast!$B$14-Forecast!$B$17)*F78 | G79: =Forecast!$B$14-(Forecast!$B$14-Forecast!$B$17)*G78
A80: Cumulative discount factor | C80: =1/(1+C79) | D80: =C80/(1+D79) | E80: =D80/(1+E79) | F80: =E80/(1+F79) | G80: =F80/(1+G79)
A81: Present value | C81: =C77*C80 | D81: =D77*D80 | E81: =E77*E80 | F81: =F77*F80 | G81: =G77*G80
A82: PV of the explicit window | B82: =SUM(C81:G81) | C82: =C75+C68 | D82: =D75+D68 | E82: =E75+E68 | F82: =F75+F68 | G82: =G75+G68
A83: Terminal return on invested capital, at REPLACEMENT cost | B83: =G74*(1+Assumptions!$B$89)/G82
A84: Required reinvestment = growth / return | B84: =MIN(Assumptions!$B$89/B83,0.95)
A85: Terminal value | B85: =G74*(1+Assumptions!$B$89)*(1-B84)/MAX(Forecast!$B$17-Assumptions!$B$89,0.02)
A86: PV of the terminal block | B86: =B85*G80
A87: ENTERPRISE VALUE | B87: =B82+B86
A88: plus net cash | B88: =(Assumptions!$B$79-Assumptions!$B$82-Assumptions!$B$83)/10^6
A89: Enterprise value including cash | B89: =B87+B88
A90: less minority — on the WHOLE enterprise, cash included | B90: =B89*'Base Year'!$B$41
A91: less the tax-disputes provision | B91: =Assumptions!$B$78/10^6
A92: less dividends payable — declared, out of working capital | B92: =Assumptions!$B$77/10^6
A93: plus non-operating investments and pledged deposits | B93: =(Assumptions!$B$81+Assumptions!$B$80)/10^6
A94: EQUITY ATTRIBUTABLE | B94: =B89-B90-B91-B92+B93
A95: VALUE PER SHARE, EGP | B95: =B94/Assumptions!$B$8
A98: Gross margin, shifted on every forecast year — -0.5% | B98: 2026E | C98: 2027E | D98: 2028E | E98: 2029E | F98: 2030E
A99: Inflation index, cumulative | C99: =Assumptions!$B$146 | D99: =C99*Assumptions!$B$147 | E99: =D99*Assumptions!$B$148 | F99: =E99*Assumptions!$B$149 | G99: =F99*Assumptions!$B$150
A100: Realisation index, cumulative | C100: =(1+Assumptions!$B$101*Forecast!$B$8) | D100: =C100*(1+Assumptions!$B$102*Forecast!$B$8) | E100: =D100*(1+Assumptions!$B$103*Forecast!$B$8) | F100: =E100*(1+Assumptions!$B$104*Forecast!$B$8) | G100: =F100*(1+Assumptions!$B$105*Forecast!$B$8)
A101: Volume — Base and special oils, mn t | C101: ='Product and Cost'!E6*(1+Assumptions!$B$106+Forecast!$B$6) | D101: =C101*(1+Assumptions!$B$107+Forecast!$B$6) | E101: =D101*(1+Assumptions!$B$108+Forecast!$B$6) | F101: =E101*(1+Assumptions!$B$109+Forecast!$B$6) | G101: =F101*(1+Assumptions!$B$110+Forecast!$B$6)
A102: Volume — Paraffin wax, mn t | C102: ='Product and Cost'!E7*(1+Assumptions!$B$111+Forecast!$B$6) | D102: =C102*(1+Assumptions!$B$112+Forecast!$B$6) | E102: =D102*(1+Assumptions!$B$113+Forecast!$B$6) | F102: =E102*(1+Assumptions!$B$114+Forecast!$B$6) | G102: =F102*(1+Assumptions!$B$115+Forecast!$B$6)
A103: Volume — Gas oil, mn t | C103: ='Product and Cost'!E8*(1+Assumptions!$B$116+Forecast!$B$6) | D103: =C103*(1+Assumptions!$B$117+Forecast!$B$6) | E103: =D103*(1+Assumptions!$B$118+Forecast!$B$6) | F103: =E103*(1+Assumptions!$B$119+Forecast!$B$6) | G103: =F103*(1+Assumptions!$B$120+Forecast!$B$6)
A104: Volume — Naphtha, mn t | C104: ='Product and Cost'!E9*(1+Assumptions!$B$121+Forecast!$B$6) | D104: =C104*(1+Assumptions!$B$122+Forecast!$B$6) | E104: =D104*(1+Assumptions!$B$123+Forecast!$B$6) | F104: =E104*(1+Assumptions!$B$124+Forecast!$B$6) | G104: =F104*(1+Assumptions!$B$125+Forecast!$B$6)
A105: Volume — Liquefied petroleum gas, mn t | C105: ='Product and Cost'!E10*(1+Assumptions!$B$126+Forecast!$B$6) | D105: =C105*(1+Assumptions!$B$127+Forecast!$B$6) | E105: =D105*(1+Assumptions!$B$128+Forecast!$B$6) | F105: =E105*(1+Assumptions!$B$129+Forecast!$B$6) | G105: =F105*(1+Assumptions!$B$130+Forecast!$B$6)
A106: Volume — Fuel oil (mix), mn t | C106: ='Product and Cost'!E11*(1+Assumptions!$B$131+Forecast!$B$6) | D106: =C106*(1+Assumptions!$B$132+Forecast!$B$6) | E106: =D106*(1+Assumptions!$B$133+Forecast!$B$6) | F106: =E106*(1+Assumptions!$B$134+Forecast!$B$6) | G106: =F106*(1+Assumptions!$B$135+Forecast!$B$6)
A107: Volume — Heavy fuel oil, mn t | C107: ='Product and Cost'!E12*(1+Assumptions!$B$136+Forecast!$B$6) | D107: =C107*(1+Assumptions!$B$137+Forecast!$B$6) | E107: =D107*(1+Assumptions!$B$138+Forecast!$B$6) | F107: =E107*(1+Assumptions!$B$139+Forecast!$B$6) | G107: =F107*(1+Assumptions!$B$140+Forecast!$B$6)
A108: Volume — Waste, mn t | C108: ='Product and Cost'!E13*(1+Assumptions!$B$141+Forecast!$B$6) | D108: =C108*(1+Assumptions!$B$142+Forecast!$B$6) | E108: =D108*(1+Assumptions!$B$143+Forecast!$B$6) | F108: =E108*(1+Assumptions!$B$144+Forecast!$B$6) | G108: =F108*(1+Assumptions!$B$145+Forecast!$B$6)
A109: Total volume, mn t | C109: =SUM(C101:C108) | D109: =SUM(D101:D108) | E109: =SUM(E101:E108) | F109: =SUM(F101:F108) | G109: =SUM(G101:G108)
A110: REVENUE | C110: =C101*'Product and Cost'!$F$6*C100+C102*'Product and Cost'!$F$7*C100+C103*'Product and Cost'!$F$8*C100+C104*'Product and Cost'!$F$9*C100+C105*'Product and Cost'!$F$10*C100+C106*'Product and Cost'!$F$11*C100+C107*'Product and Cost'!$F$12*C100+C108*'Product and Cost'!$F$13*C100 | D110: =D101*'Product and Cost'!$F$6*D100+D102*'Product and Cost'!$F$7*D100+D103*'Product and Cost'!$F$8*D100+D104*'Product and Cost'!$F$9*D100+D105*'Product and Cost'!$F$10*D100+D106*'Product and Cost'!$F$11*D100+D107*'Product and Cost'!$F$12*D100+D108*'Product and Cost'!$F$13*D100 | E110: =E101*'Product and Cost'!$F$6*E100+E102*'Product and Cost'!$F$7*E100+E103*'Product and Cost'!$F$8*E100+E104*'Product and Cost'!$F$9*E100+E105*'Product and Cost'!$F$10*E100+E106*'Product and Cost'!$F$11*E100+E107*'Product and Cost'!$F$12*E100+E108*'Product and Cost'!$F$13*E100 | F110: =F101*'Product and Cost'!$F$6*F100+F102*'Product and Cost'!$F$7*F100+F103*'Product and Cost'!$F$8*F100+F104*'Product and Cost'!$F$9*F100+F105*'Product and Cost'!$F$10*F100+F106*'Product and Cost'!$F$11*F100+F107*'Product and Cost'!$F$12*F100+F108*'Product and Cost'!$F$13*F100 | G110: =G101*'Product and Cost'!$F$6*G100+G102*'Product and Cost'!$F$7*G100+G103*'Product and Cost'!$F$8*G100+G104*'Product and Cost'!$F$9*G100+G105*'Product and Cost'!$F$10*G100+G106*'Product and Cost'!$F$11*G100+G107*'Product and Cost'!$F$12*G100+G108*'Product and Cost'!$F$13*G100
...

Sheet Lenses
A1: Four lenses, one bridge, one valuation date
A2: Lens 2 is on the TRAILING metric so it borrows no discount factor from lens 1. Lens 3 is forward-dated and is therefore DISCOUNTED to the valuation date at the cost of equity, with net cash added at face outside the multiple. Lens 4 uses the same cost-of-equity glide lens 1 uses. All formulas.
A5: Base-year EBITDA | B5: ='Base Year'!B20-'Base Year'!B28-'Base Year'!B29-'Base Year'!B30-'Base Year'!B31+'Base Year'!B32
A6: Enterprise value at spot | B6: =Assumptions!$B$7*Assumptions!$B$8+(Assumptions!$B$82+Assumptions!$B$83-Assumptions!$B$79)/10^6
A7: The company's OWN trailing EV/EBITDA | B7: =B6/B5
A8: Justified multiple = trailing x (1 + re-rating) | B8: =B7*(1+Assumptions!$B$92)
A10: LENS 1 — discounted cash flow | B10: =Forecast!B65
A11: LENS 2 — relative multiples, on the trailing metric | B11: =(B8*B5-(Assumptions!$B$82+Assumptions!$B$83-Assumptions!$B$79)/10^6)*(1-'Base Year'!B41)-(Assumptions!$B$78+Assumptions!$B$77-Assumptions!$B$81-Assumptions!$B$80)/10^6 | C11: =B11/Assumptions!$B$8
A12: LENS 3 — normalised earnings power, DISCOUNTED | B12: =Forecast!E41 | C12: =B12*(1-Assumptions!$B$87)*(1-'Base Year'!B40)*(1-'Base Year'!B41)/Assumptions!$B$8 | D12: =C12*Assumptions!$B$91/(1+Forecast!B10)^2.4+((Assumptions!$B$79-Assumptions!$B$82-Assumptions!$B$83-Assumptions!$B$78-Assumptions!$B$77)/10^6)/Assumptions!$B$8
A13: LENS 4 — book value and sustainable return | B13: =Assumptions!$B$84/10^6/Assumptions!$B$8 | C13: =0.2338665864 | D13: =(Assumptions!$B$90-Assumptions!$B$89)/(C13-Assumptions!$B$89) | E13: =B13*D13
A15: WEIGHTED CENTRAL | B15: =B10*Assumptions!$B$168+C11*Assumptions!$B$169+D12*Assumptions!$B$170+E13*Assumptions!$B$171
A16: against spot | B16: =B15/Assumptions!$B$7-1
A18: The weighted range on the Summary sheet is the bear and bull columns weighted with these same weights. The previous edition labelled a row "weighted central" and then took the minimum and maximum across the four lenses — both of which came from the cash-flow lens alone — so the word "weighted" applied to the centre and not to the ends, and the published spread was about two and a half times too wide.
