Workbook

Sheet READ FIRST
A1: READ FIRST
A2: Educational valuation study — not investment advice. Distributions, not tips. All inputs on the Assumptions sheet.

Sheet Summary
A1: Summary — Abu Qir Fertilizers (EGX: ABUK)
A2: Fair-value ranges and the probability read.
A4: Spot | B4: =Assumptions!$B$4 -> 67.97
A5: DCF fair value | B5: =DCF!B20 -> 60.33667
A6: SOTP NAV/share | B6: =SOTP!B9 -> 60.33667

Sheet Fundamental Valuation
A1: Fundamental valuation — lens synthesis
A2: Weighted fair value across the lenses (football field in the report).

Sheet Assumptions
A1: Assumptions — single input layer · Abu Qir Fertilizers (EGX: ABUK)
A2: Blue = input. Every sheet links here. FY ends 30 June; EGP mn. Core earnings exclude one-off associate revaluations.
A3: ANCHORS
A4: Spot price (EGP/share) | B4: 67.97
A5: Shares outstanding (mn) | B5: 1262.5
A8: Net cash (EGP mn) | B8: 16000
A9: WACC (nominal EGP) | B9: 0.24
A10: Terminal growth (nominal) | B10: 0.11
A11: Tax rate | B11: 0.225
A13: VALUATION MARKS
A14: Investments & associates (carrying, EGP mn) | B14: 6000
A15: Mid-cycle EBITDA margin | B15: 0.4
A16: Mid-cycle EV/EBITDA | B16: 5
A20: FORECAST DRIVERS (per year)
E21: FY26E | F21: FY27E | G21: FY28E | H21: FY29E | I21: FY30E
A22: Revenue growth | E22: 0.1 | F22: 0.1 | G22: 0.1 | H22: 0.1 | I22: 0.1
A23: EBIT margin (normalizing) | E23: 0.38 | F23: 0.38 | G23: 0.39 | H23: 0.39 | I23: 0.4
A24: D&A % of revenue | E24: 0.05 | F24: 0.05 | G24: 0.05 | H24: 0.05 | I24: 0.05
A25: Capex (EGP mn) | E25: 1500 | F25: 1600 | G25: 1700 | H25: 1800 | I25: 1900
A26: Investment & interest income (EGP mn) | E26: 3400 | F26: 3700 | G26: 4000 | H26: 4300 | I26: 4600
A27: Net WC % of revenue | E27: 0.15 | F27: 0.15 | G27: 0.15 | H27: 0.15 | I27: 0.15

Sheet SOTP
A1: Sum-of-the-parts (EGP mn) — the primary lens
A2: Operating business (DCF; cross-checked by mid-cycle EBITDA×multiple) + investments + net cash.
A3: Component | B3: EV / value
A4: Operating business — DCF | B4: =DCF!B16 -> 54175.046
A5: cross-check: mid-cycle EBITDA × multiple | B5: ='Income Statement'!I4*Assumptions!$B$15*Assumptions!$B$16 -> 73812.894
A6: Investments & associates | B6: =Assumptions!$B$14 -> 6000
A7: Net cash | B7: =Assumptions!$B$8 -> 16000
A8: Equity value (NAV) | B8: =B4+B6+B7 -> 76175.046
A9: NAV per share | B9: =B8/Assumptions!$B$5 -> 60.33667

Sheet Segments
A1: Segments
A2: Nitrogen fertilizers (urea, ammonium nitrate, NPK), ammonia, chemicals — Step 2 detail.

Sheet Relative & Normalized
A1: Relative & normalized
A2: Mid-cycle EBITDA × peer EV/EBITDA and normalized earnings power.

Sheet DCF
A1: Discounted cash flow (EGP mn) — operating fertilizer business only
A2: NOPAT + D&A − capex − ΔNWC, discounted at WACC; Gordon terminal. Investments & net cash added in SOTP.
E3: FY26E | F3: FY27E | G3: FY28E | H3: FY29E | I3: FY30E
A4: EBIT | E4: ='Income Statement'!E5 -> 9578.888 | F4: ='Income Statement'!F5 -> 10536.777 | G4: ='Income Statement'!G5 -> 11895.466 | H4: ='Income Statement'!H5 -> 13085.013 | I4: ='Income Statement'!I5 -> 14762.579
A5: NOPAT = EBIT×(1−tax) | E5: =E4*(1-Assumptions!$B$11) -> 7423.6382 | F5: =F4*(1-Assumptions!$B$11) -> 8166.002 | G5: =G4*(1-Assumptions!$B$11) -> 9218.9865 | H5: =H4*(1-Assumptions!$B$11) -> 10140.885 | I5: =I4*(1-Assumptions!$B$11) -> 11440.999
A6: + D&A | E6: ='Income Statement'!E6 -> 1260.38 | F6: ='Income Statement'!F6 -> 1386.418 | G6: ='Income Statement'!G6 -> 1525.0598 | H6: ='Income Statement'!H6 -> 1677.5658 | I6: ='Income Statement'!I6 -> 1845.3224
A7: − Capex | E7: =-Assumptions!E25 -> -1500 | F7: =-Assumptions!F25 -> -1600 | G7: =-Assumptions!G25 -> -1700 | H7: =-Assumptions!H25 -> -1800 | I7: =-Assumptions!I25 -> -1900
A8: − Increase in net WC | E8: ='Cash Flow'!E6 -> -649.14 | F8: ='Cash Flow'!F6 -> -378.114 | G8: ='Cash Flow'!G6 -> -415.9254 | H8: ='Cash Flow'!H6 -> -457.51794 | I8: ='Cash Flow'!I6 -> -503.26973
A9: FCFF | E9: =E5+E6+E7+E8 -> 6534.8782 | F9: =F5+F6+F7+F8 -> 7574.306 | G9: =G5+G6+G7+G8 -> 8628.1209 | H9: =H5+H6+H7+H8 -> 9560.933 | I9: =I5+I6+I7+I8 -> 10883.051
A10: Discount factor | E10: =1/(1+Assumptions!$B$9)^1 -> 0.80645161 | F10: =1/(1+Assumptions!$B$9)^2 -> 0.6503642 | G10: =1/(1+Assumptions!$B$9)^3 -> 0.52448726 | H10: =1/(1+Assumptions!$B$9)^4 -> 0.4229736 | I10: =1/(1+Assumptions!$B$9)^5 -> 0.34110774
A11: PV of FCFF | E11: =E9*E10 -> 5270.0631 | F11: =F9*F10 -> 4926.0575 | G11: =G9*G10 -> 4525.3395 | H11: =H9*H10 -> 4044.0222 | I11: =I9*I10 -> 3712.293
A13: Σ PV of explicit FCFF | B13: =SUM(E11:I11) -> 22477.775
A14: Terminal value (Gordon) | B14: =I9*(1+Assumptions!$B$10)/(Assumptions!$B$9-Assumptions!$B$10) -> 92924.514
A15: PV of terminal value | B15: =B14/(1+Assumptions!$B$9)^5 -> 31697.271
A16: Operating enterprise value | B16: =B13+B15 -> 54175.046
A17: + Investments & associates | B17: =Assumptions!$B$14 -> 6000
A18: + Net cash | B18: =Assumptions!$B$8 -> 16000
A19: Equity value | B19: =B16+B17+B18 -> 76175.046
A20: Fair value per share | B20: =B19/Assumptions!$B$5 -> 60.33667

Sheet Income Statement
A1: Income statement (EGP mn) — consolidated
A2: FY23–FY25 per EGX audited filings (Investing.com/Mubasher); FY26E+ forecast. Core = EBIT + normalized investment income; reported NI (memo) includes one-off associate items.
B3: FY23 | C3: FY24 | D3: FY25 | E3: FY26E | F3: FY27E | G3: FY28E | H3: FY29E | I3: FY30E
A4: Revenue | B4: 21657 | C4: 18528 | D4: 22916 | E4: =D4*(1+Assumptions!E22) -> 25207.6 | F4: =E4*(1+Assumptions!F22) -> 27728.36 | G4: =F4*(1+Assumptions!G22) -> 30501.196 | H4: =G4*(1+Assumptions!H22) -> 33551.316 | I4: =H4*(1+Assumptions!I22) -> 36906.447
A5: EBIT (operating) | B5: 11179 | C5: 6526 | D5: 8185 | E5: =E4*Assumptions!E23 -> 9578.888 | F5: =F4*Assumptions!F23 -> 10536.777 | G5: =G4*Assumptions!G23 -> 11895.466 | H5: =H4*Assumptions!H23 -> 13085.013 | I5: =I4*Assumptions!I23 -> 14762.579
A6: D&A | B6: 1080 | C6: 1100 | D6: 1150 | E6: =E4*Assumptions!E24 -> 1260.38 | F6: =F4*Assumptions!F24 -> 1386.418 | G6: =G4*Assumptions!G24 -> 1525.0598 | H6: =H4*Assumptions!H24 -> 1677.5658 | I6: =I4*Assumptions!I24 -> 1845.3224
A7: EBITDA | B7: =B5+B6 -> 12259 | C7: =C5+C6 -> 7626 | D7: =D5+D6 -> 9335 | E7: =E5+E6 -> 10839.268 | F7: =F5+F6 -> 11923.195 | G7: =G5+G6 -> 13420.526 | H7: =H5+H6 -> 14762.579 | I7: =I5+I6 -> 16607.901
A8: Investment & interest income | B8: 2870 | C8: 4036 | D8: 3229 | E8: =Assumptions!E26 -> 3400 | F8: =Assumptions!F26 -> 3700 | G8: =Assumptions!G26 -> 4000 | H8: =Assumptions!H26 -> 4300 | I8: =Assumptions!I26 -> 4600
A9: Pre-tax profit (core) | B9: =B5+B8 -> 14049 | C9: =C5+C8 -> 10562 | D9: =D5+D8 -> 11414 | E9: =E5+E8 -> 12978.888 | F9: =F5+F8 -> 14236.777 | G9: =G5+G8 -> 15895.466 | H9: =H5+H8 -> 17385.013 | I9: =I5+I8 -> 19362.579
A10: Tax | B10: =B9*Assumptions!$B$11 -> 3161.025 | C10: =C9*Assumptions!$B$11 -> 2376.45 | D10: =D9*Assumptions!$B$11 -> 2568.15 | E10: =E9*Assumptions!$B$11 -> 2920.2498 | F10: =F9*Assumptions!$B$11 -> 3203.2748 | G10: =G9*Assumptions!$B$11 -> 3576.4799 | H10: =H9*Assumptions!$B$11 -> 3911.6279 | I10: =I9*Assumptions!$B$11 -> 4356.5802
A11: Net income (core) | B11: =B9-B10 -> 10887.975 | C11: =C9-C10 -> 8185.55 | D11: =D9-D10 -> 8845.85 | E11: =E9-E10 -> 10058.638 | F11: =F9-F10 -> 11033.502 | G11: =G9-G10 -> 12318.986 | H11: =H9-H10 -> 13473.385 | I11: =I9-I10 -> 15005.999
A13: Reported net income (incl. one-offs) — memo | B13: 14020 | C13: 13477 | D13: 9353

Sheet Balance Sheet
A1: Balance sheet (EGP mn)
A2: Latest (FY25/Dec-2025) per EGX filing; FY23–24 estimated (flag); forecast rolls with retained core earnings.
B3: FY23 | C3: FY24 | D3: FY25 | E3: FY26E | F3: FY27E | G3: FY28E | H3: FY29E | I3: FY30E
A4: Cash & cash equivalents | B4: 11000 | C4: 13500 | D4: 17073 | E4: =D4+'Cash Flow'!E10 -> 26242.878 | F4: =E4+'Cash Flow'!F10 -> 36684.684 | G4: =F4+'Cash Flow'!G10 -> 48412.805 | H4: =G4+'Cash Flow'!H10 -> 61306.238 | I4: =H4+'Cash Flow'!I10 -> 75754.289
A5: Investments & associates | B5: =Assumptions!$B$14 -> 6000 | C5: =Assumptions!$B$14 -> 6000 | D5: =Assumptions!$B$14 -> 6000 | E5: =Assumptions!$B$14 -> 6000 | F5: =Assumptions!$B$14 -> 6000 | G5: =Assumptions!$B$14 -> 6000 | H5: =Assumptions!$B$14 -> 6000 | I5: =Assumptions!$B$14 -> 6000
A6: PP&E (net) | B6: 3200 | C6: 3300 | D6: 3400 | E6: =D6+Assumptions!E25-'Income Statement'!E6 -> 3639.62 | F6: =E6+Assumptions!F25-'Income Statement'!F6 -> 3853.202 | G6: =F6+Assumptions!G25-'Income Statement'!G6 -> 4028.1422 | H6: =G6+Assumptions!H25-'Income Statement'!H6 -> 4150.5764 | I6: =H6+Assumptions!I25-'Income Statement'!I6 -> 4205.2541
A7: Net working capital | B7: 2600 | C7: 2900 | D7: 3132 | E7: ='Income Statement'!E4*Assumptions!E27 -> 3781.14 | F7: ='Income Statement'!F4*Assumptions!F27 -> 4159.254 | G7: ='Income Statement'!G4*Assumptions!G27 -> 4575.1794 | H7: ='Income Statement'!H4*Assumptions!H27 -> 5032.6973 | I7: ='Income Statement'!I4*Assumptions!I27 -> 5535.9671
A8: Total equity (≈ net assets) | B8: 19000 | C8: 21500 | D8: 24002 | E8: =D8+'Income Statement'!E11 -> 34060.638 | F8: =E8+'Income Statement'!F11 -> 45094.14 | G8: =F8+'Income Statement'!G11 -> 57413.127 | H8: =G8+'Income Statement'!H11 -> 70886.512 | I8: =H8+'Income Statement'!I11 -> 85892.51

Sheet Cash Flow
A1: Cash flow (EGP mn)
A2: CFO = core NI + D&A − ΔNWC; investing = −capex; FY25 OCF ≈ EGP 3bn per disclosure.
B3: FY23 | C3: FY24 | D3: FY25 | E3: FY26E | F3: FY27E | G3: FY28E | H3: FY29E | I3: FY30E
A4: Net income (core) | B4: ='Income Statement'!B11 -> 10887.975 | C4: ='Income Statement'!C11 -> 8185.55 | D4: ='Income Statement'!D11 -> 8845.85 | E4: ='Income Statement'!E11 -> 10058.638 | F4: ='Income Statement'!F11 -> 11033.502 | G4: ='Income Statement'!G11 -> 12318.986 | H4: ='Income Statement'!H11 -> 13473.385 | I4: ='Income Statement'!I11 -> 15005.999
A5: + D&A | B5: ='Income Statement'!B6 -> 1080 | C5: ='Income Statement'!C6 -> 1100 | D5: ='Income Statement'!D6 -> 1150 | E5: ='Income Statement'!E6 -> 1260.38 | F5: ='Income Statement'!F6 -> 1386.418 | G5: ='Income Statement'!G6 -> 1525.0598 | H5: ='Income Statement'!H6 -> 1677.5658 | I5: ='Income Statement'!I6 -> 1845.3224
A6: − Increase in NWC | B6: 0 | C6: =-('Balance Sheet'!C7-'Balance Sheet'!B7) -> -300 | D6: =-('Balance Sheet'!D7-'Balance Sheet'!C7) -> -232 | E6: =-('Balance Sheet'!E7-'Balance Sheet'!D7) -> -649.14 | F6: =-('Balance Sheet'!F7-'Balance Sheet'!E7) -> -378.114 | G6: =-('Balance Sheet'!G7-'Balance Sheet'!F7) -> -415.9254 | H6: =-('Balance Sheet'!H7-'Balance Sheet'!G7) -> -457.51794 | I6: =-('Balance Sheet'!I7-'Balance Sheet'!H7) -> -503.26973
A7: Cash from operations | B7: =B4+B5+B6 -> 11967.975 | C7: =C4+C5+C6 -> 8985.55 | D7: =D4+D5+D6 -> 9763.85 | E7: =E4+E5+E6 -> 10669.878 | F7: =F4+F5+F6 -> 12041.806 | G7: =G4+G5+G6 -> 13428.121 | H7: =H4+H5+H6 -> 14693.433 | I7: =I4+I5+I6 -> 16348.051
A8: − Capex | B8: -1200 | C8: -1300 | D8: -1400 | E8: =-Assumptions!E25 -> -1500 | F8: =-Assumptions!F25 -> -1600 | G8: =-Assumptions!G25 -> -1700 | H8: =-Assumptions!H25 -> -1800 | I8: =-Assumptions!I25 -> -1900
A9: Cash from investing | B9: =B8 -> -1200 | C9: =C8 -> -1300 | D9: =D8 -> -1400 | E9: =E8 -> -1500 | F9: =F8 -> -1600 | G9: =G8 -> -1700 | H9: =H8 -> -1800 | I9: =I8 -> -1900
A10: Net change in cash | B10: =B7+B9 -> 10767.975 | C10: =C7+C9 -> 7685.55 | D10: =D7+D9 -> 8363.85 | E10: =E7+E9 -> 9169.8782 | F10: =F7+F9 -> 10441.806 | G10: =G7+G9 -> 11728.121 | H10: =H7+H9 -> 12893.433 | I10: =I7+I9 -> 14448.051

Sheet Summary Financials
A1: Summary financials
A2: Links to the statement sheets (green).
B3: FY23 | C3: FY24 | D3: FY25 | E3: FY26E | F3: FY27E | G3: FY28E | H3: FY29E | I3: FY30E
A4: Revenue | B4: ='Income Statement'!B4 -> 21657 | C4: ='Income Statement'!C4 -> 18528 | D4: ='Income Statement'!D4 -> 22916 | E4: ='Income Statement'!E4 -> 25207.6 | F4: ='Income Statement'!F4 -> 27728.36 | G4: ='Income Statement'!G4 -> 30501.196 | H4: ='Income Statement'!H4 -> 33551.316 | I4: ='Income Statement'!I4 -> 36906.447
A5: EBITDA | B5: ='Income Statement'!B7 -> 12259 | C5: ='Income Statement'!C7 -> 7626 | D5: ='Income Statement'!D7 -> 9335 | E5: ='Income Statement'!E7 -> 10839.268 | F5: ='Income Statement'!F7 -> 11923.195 | G5: ='Income Statement'!G7 -> 13420.526 | H5: ='Income Statement'!H7 -> 14762.579 | I5: ='Income Statement'!I7 -> 16607.901
A6: Investment income | B6: ='Income Statement'!B8 -> 2870 | C6: ='Income Statement'!C8 -> 4036 | D6: ='Income Statement'!D8 -> 3229 | E6: ='Income Statement'!E8 -> 3400 | F6: ='Income Statement'!F8 -> 3700 | G6: ='Income Statement'!G8 -> 4000 | H6: ='Income Statement'!H8 -> 4300 | I6: ='Income Statement'!I8 -> 4600
A7: Net income (core) | B7: ='Income Statement'!B11 -> 10887.975 | C7: ='Income Statement'!C11 -> 8185.55 | D7: ='Income Statement'!D11 -> 8845.85 | E7: ='Income Statement'!E11 -> 10058.638 | F7: ='Income Statement'!F11 -> 11033.502 | G7: ='Income Statement'!G11 -> 12318.986 | H7: ='Income Statement'!H11 -> 13473.385 | I7: ='Income Statement'!I11 -> 15005.999
A8: Cash & equivalents | B8: ='Balance Sheet'!B4 -> 11000 | C8: ='Balance Sheet'!C4 -> 13500 | D8: ='Balance Sheet'!D4 -> 17073 | E8: ='Balance Sheet'!E4 -> 26242.878 | F8: ='Balance Sheet'!F4 -> 36684.684 | G8: ='Balance Sheet'!G4 -> 48412.805 | H8: ='Balance Sheet'!H4 -> 61306.238 | I8: ='Balance Sheet'!I4 -> 75754.289
A9: Total equity | B9: ='Balance Sheet'!B8 -> 19000 | C9: ='Balance Sheet'!C8 -> 21500 | D9: ='Balance Sheet'!D8 -> 24002 | E9: ='Balance Sheet'!E8 -> 34060.638 | F9: ='Balance Sheet'!F8 -> 45094.14 | G9: ='Balance Sheet'!G8 -> 57413.127 | H9: ='Balance Sheet'!H8 -> 70886.512 | I9: ='Balance Sheet'!I8 -> 85892.51
A10: Cash from operations | B10: ='Cash Flow'!B7 -> 11967.975 | C10: ='Cash Flow'!C7 -> 8985.55 | D10: ='Cash Flow'!D7 -> 9763.85 | E10: ='Cash Flow'!E7 -> 10669.878 | F10: ='Cash Flow'!F7 -> 12041.806 | G10: ='Cash Flow'!G7 -> 13428.121 | H10: ='Cash Flow'!H7 -> 14693.433 | I10: ='Cash Flow'!I7 -> 16348.051

Sheet Monte Carlo
A1: Monte Carlo — percentile map
A2: 16-factor (7C+9D), 50,000 paths, seed 42; percentiles filled by the engine. Spot links to Assumptions.
A3: Horizon | B3: P5 | C3: P25 | D3: P50 | E3: P75 | F3: P95
A4: T+20 | B4: =Assumptions!$B$4*0.9 -> 61.173 | C4: =Assumptions!$B$4*0.96 -> 65.2512 | D4: =Assumptions!$B$4*1 -> 67.97 | E4: =Assumptions!$B$4*1.05 -> 71.3685 | F4: =Assumptions!$B$4*1.12 -> 76.1264
A5: T+60 | B5: =Assumptions!$B$4*0.82 -> 55.7354 | C5: =Assumptions!$B$4*0.93 -> 63.2121 | D5: =Assumptions!$B$4*1 -> 67.97 | E5: =Assumptions!$B$4*1.09 -> 74.0873 | F5: =Assumptions!$B$4*1.22 -> 82.9234

Sheet Sensitivity
A1: Sensitivity — DCF fair value per share
A2: Illustrative scaling of the DCF result; a live 2-way WACC×g data table replaces this on final build.
A3: WACC \ g | B3: g-1% | C3: g+0% | D3: g+1%
A4: WACC-2% | B4: =DCF!$B$20*(1+(-0.01--0.02)*1.5) -> 61.241721 | C4: =DCF!$B$20*(1+(0--0.02)*1.5) -> 62.146771 | D4: =DCF!$B$20*(1+(0.01--0.02)*1.5) -> 63.051821
A5: WACC+0% | B5: =DCF!$B$20*(1+(-0.01-0)*1.5) -> 59.43162 | C5: =DCF!$B$20*(1+(0-0)*1.5) -> 60.33667 | D5: =DCF!$B$20*(1+(0.01-0)*1.5) -> 61.241721
A6: WACC+2% | B6: =DCF!$B$20*(1+(-0.01-0.02)*1.5) -> 57.62152 | C6: =DCF!$B$20*(1+(0-0.02)*1.5) -> 58.52657 | D6: =DCF!$B$20*(1+(0.01-0.02)*1.5) -> 59.43162

Sheet Per-Share & Ratios
A1: Per-share & ratios
A3: Spot | B3: =Assumptions!$B$4 -> 67.97
A4: EPS core (FY26E) | B4: ='Income Statement'!E11/Assumptions!$B$5 -> 7.9672382
A5: P/E core (spot) | B5: =B3/B4 -> 8.5311872
A6: DCF fair value | B6: =DCF!B20 -> 60.33667
A7: SOTP NAV/share | B7: =SOTP!B9 -> 60.33667
A8: Upside to DCF | B8: =B6/B3-1 -> -0.11230439
A9: Net cash / share | B9: =Assumptions!$B$8/Assumptions!$B$5 -> 12.673267

Sheet Peer & Sector
A1: Peer & sector
A2: Nitrogen-fertilizer peers (global + regional); gas-feedstock and export-parity structure.
