Workbook

Sheet READ FIRST
A1: Burjeel Holdings PLC (ADX: BURJEEL) — Valuation Model — 11 July 2026
A4: What this file is. The companion Excel to the Testahil valuation study of Burjeel Holdings dated 11-Jul-2026. It shows every number in the study as a live, linked calculation: change a blue input on the Assumptions sheet and the DCF, the lenses, the bridge and the per-share values recalculate.
A5: What this file is NOT. Not investment advice, not a recommendation, not a price target. Testahil publishes fair-value ranges and probability distributions only. The preparer is unlicensed; see the six-clause Disclosure in the study.
A6: Colour convention. BLUE = hardcoded input or judgment lever (edit these). BLACK = formula. GREEN = link to another sheet. Every hardcoded input carries its source in the adjacent column; unsourced judgments are logged to the Fundamental Driver Ledger (tags d1–d9 on Assumptions).
A7: Two clocks. Section-1 fair values are ~12-month fundamental reads. The Monte-Carlo sheet is a genuine 3-month (T+20/T+60 session) price distribution whose centre is the money-market carry — the fundamental gap NEVER enters the MC drift. Do not average the two.
A8: Calibration honesty. BURJEEL scores PARITY in the pre-publication calibration backtest (skill +0.85%, 90% CI [-1.7%, +2.5%], 11 windows) under the live UAE panel fit (t(10), width x1.049, carry-only). Parity tier means: calibrated and market-panel validated, no demonstrated single-name edge. The Calibration sheet holds the full window table; the public Ledger grades the T+20/T+60 cohorts when they mature (07-Aug-2026 / 02-Oct-2026).
A9: Provenance. All financial-statement line items are from official company sources only (FY2023 release 6-Mar-2024; FY2024 release 5-Mar-2025; H1-2025 release 6-Aug-2025; FY2025 release & MD&A 4-Mar-2026; Q1-2026 release 6-May-2026; ADX filings). Peer marks are broker/Bloomberg-sourced and dated in the Register.
A10: REVISION (rev. 2, 12-Jul-2026, pre-publication): tax rebuilt on Pillar-Two mechanics (10→13% effective path; 15% flat = bear rung); relative multiples recalibrated to verified peer marks (11.5x / 17x bases); disclosure notes added. MC, calibration and grading dates unchanged.
A11: Data quality. The OHLC series passed the pre-study data-quality gate: 937 rows, 0 repairs, 0 placeholder rows, max |1-day log move| inside the ADX ±15% limit envelope, 250.4 rows/yr vs the ADX Mon–Fri calendar.

Sheet Summary
A1: Valuation summary — every read at a glance
A2: AED per share · spot and lens values link live
A3: Spot (10-Jul-2026 close) | B3: =Assumptions!B5 -> 1.11
A5: Lens | B5: Bear | C5: Base | D5: Bull | E5: Weight | F5: One-line read
A6: FCFF DCF (primary) | B6: =DCF!B31 -> 1.2064998 | C6: =DCF!B30 -> 2.6393201 | D6: =DCF!B32 -> 3.5768672 | E6: 0.35 | F6: Five guided years + 2.5% terminal at the dual-basis WACC; TV 83% of EV, disclosed
A7: Relative EV/EBITDA | B7: ='Relative & Normalized'!B7 -> 1.5026267 | C7: ='Relative & Normalized'!B6 -> 1.887865 | D7: ='Relative & Normalized'!B8 -> 2.1767937 | E7: 0.25 | F7: 9.5–13.0x FY26E pre-IFRS-16 EBITDA — discount to the verified peer floor, same net-debt bridge
A8: Normalized earnings | B8: ='Relative & Normalized'!B16 -> 1.2305421 | C8: ='Relative & Normalized'!B15 -> 1.4942297 | D8: ='Relative & Normalized'!B17 -> 1.7579172 | E8: 0.25 | F8: Clean FY26E EPS x 14–20x GCC healthcare band
A9: Dividend discount (policy lens) | B9: =DDM!B14 -> 0.2380267 | C9: =DDM!B13 -> 0.56484787 | D9: =DDM!B15 -> 0.79357261 | E9: 0.15 | F9: What a holder actually receives while payout sits at ~25%
A10: Weighted central | B10: =SUMPRODUCT(B6:B9,$E$6:$E$9) -> 1.1412711 | C10: =SUMPRODUCT(C6:C9,$E$6:$E$9) -> 1.8540129 | D10: =SUMPRODUCT(D6:D9,$E$6:$E$9) -> 2.3546171 | F10: Bear 1.10 · base 1.73 · bull 2.28 vs spot 1.11 — the market trades the bear case
A12: Monte Carlo (3-month clock) | B12: P5 | C12: P50 | D12: P95 | E12: P(up)
A13: T+20 (grades 07-Aug-2026) | B13: ='Monte Carlo'!B7 -> 0.94428098 | C13: ='Monte Carlo'!D7 -> 1.111013 | D13: ='Monte Carlo'!F7 -> 1.3085064 | E13: 0.50408
A14: T+60 (grades 02-Oct-2026) | B14: ='Monte Carlo'!B8 -> 0.83671682 | C14: ='Monte Carlo'!D8 -> 1.1137334 | D14: ='Monte Carlo'!F8 -> 1.4851002 | E14: 0.50838
A16: Calibration: PARITY (+0.85% skill, CI [-1.69%, +2.53%], 11 windows, cov90 91%) — parity tier under the UAE panel gate

Sheet Assumptions
A1: Assumptions — every blue cell is a lever
A2: Sources inline; d-tags log to the Fundamental Driver Ledger
A3: Anchor & structure
A4: Anchor date | B4: 2026-07-10 | G4: Last close in the uploaded OHLC (10-Jul-2026, Friday)
A5: Spot (AED) | B5: 1.11 | G5: Uploaded ADX series, quality-gated
A6: Shares outstanding (mn) | B6: 5210 | G6: d1 — derived: AED 521mn share capital / AED 0.10 par (FY25 PR); EPS cross-check 475/5,210 = 0.091 ✓
A7: Net debt ex-leases (AED mn) | B7: 1637 | G7: FY25 MD&A: borrowings 1,918 − cash 281
A8: IFRS-16 lease liabilities (AED mn) | B8: 1191 | G8: FY25 MD&A (dual-framed: net debt incl leases 2,828)
A9: Non-controlling interests (AED mn) | B9: 68 | G9: FY25 balance sheet
A10: FY25 DPS (AED) | B10: 0.02 | G10: AED 120mn approved 17-Apr-2026 AGM (~24% payout)
A12: Forecast drivers (base case)
A13: Driver | B13: FY26E | C13: FY27E | D13: FY28E | E13: FY29E | F13: FY30E | G13: Source / gate
A14: Revenue growth | B14: 0.11 | C14: 0.11 | D14: 0.1 | E14: 0.09 | F14: 0.08 | G14: n1 bottom-up-lite: guidance “low double-digit CAGR” (FY25 MD&A) · Q1-26 +9.7% ex-UPP
A15: EBITDA margin (underlying) | B15: 0.193 | C15: 0.202 | D15: 0.21 | E15: 0.216 | F15: 0.22 | G15: n2 CRUX: guided “low-20s blended”; FY25 underlying 18.5% (1,017/5,486, ex AED-72mn one-off)
A16: D&A % of revenue | B16: 0.07 | C16: 0.069 | D16: 0.068 | E16: 0.067 | F16: 0.066 | G16: d2 — FY25 = 7.04%; drifts down on asset-light KSA mix
A17: Growth capex (AED mn) | B17: 275 | C17: 250 | D17: 225 | E17: 175 | F17: 125 | G17: n3 guidance: AED 1.0bn mid-term, 25–30% deployed 2026; taper as pipeline delivers
A18: Maintenance capex % rev | B18: 0.025 | C18: 0.025 | D18: 0.025 | E18: 0.025 | F18: 0.025 | G18: n4 guidance: “~2.5% of revenue”
A19: ΔWC % of Δrevenue | B19: 0.24 | C19: 0.235 | D19: 0.23 | E19: 0.225 | F19: 0.22 | G19: d3 — NWC/rev 24% (recv 2,057 − pay 738); DSO 135d, mild normalization assumed
A20: Lease payments growth | B20: 0.06 | C20: 0.06 | D20: 0.06 | E20: 0.06 | F20: 0.06 | G20: d4 — FY25 rentals AED 162mn; below-revenue growth on asset-light mix
A22: Tax, terminal, lenses
A23: Tax rate — effective path FY26E→30E (Pillar-Two) | B23: 0.1 | C23: 0.11 | D23: 0.12 | E23: 0.125 | F23: 0.13 | G23: n5 CRUX: top-up applies only to post-SBIE excess profit (carve-outs 9.4%/7.4% in 2026 → 5%/5% by 2033); FY25 actual ETR 7.0%; 15% flat = bear rung
A24: Tax rate — bull (exclusion / safe-harbour persists) | B24: 0.09 | G24: Initial-phase exclusion or transitional CbCR safe harbour; bear rung = 15% flat (scenario cells on DCF sheet)
A25: Terminal growth g | B25: 0.025 | G25: d5 — UAE CPI ~2.5% (IMF 2026); nominal AED
A26: EV/EBITDA band bear/base/bull | B26: 9.5 / 11.5 / 13.0 | G26: d6 — verified peer floor ~13x (MEH; Hammadi 17.5x, Mouwasat 18–19x, Dallah 22–26x, Al Habib 24–34x, dated in Register); base = discount to the floor
A27: P/E band bear/base/bull | B27: 14 / 17 / 20 | G27: d6 — same peer set on earnings
A28: FY26E finance costs (AED mn) | B28: 210 | G28: d7 — bank ~106 + USD-sukuk incremental net of refi + lease interest ~58; marginal Kd = 7.00% Jun-26 sukuk
A29: Attributable share of profit | B29: 0.944 | G29: d8 — FY25 attributable 475/503

Sheet Income Statement
A1: Income statement — three reported, five modelled (AED mn)
A3: AED mn | B3: FY2023 | C3: FY2024 | D3: FY2025 | E3: FY2026E | F3: FY2027E | G3: FY2028E | H3: FY2029E | I3: FY2030E | J3: Source
A4: Revenue | B4: 4535 | C4: 5010 | D4: 5486 | E4: =D4*(1+Assumptions!B14) -> 6089.46 | F4: =E4*(1+Assumptions!C14) -> 6759.3006 | G4: =F4*(1+Assumptions!D14) -> 7435.2307 | H4: =G4*(1+Assumptions!E14) -> 8104.4014 | I4: =H4*(1+Assumptions!F14) -> 8752.7535 | J4: FY23–25 all official results releases (6-Mar-24 / 5-Mar-25 / 4-Mar-26)
A5: EBITDA — underlying | B5: 1018 | C5: 959 | D5: 1017 | E5: =E4*Assumptions!B15 -> 1175.2658 | F5: =F4*Assumptions!C15 -> 1365.3787 | G5: =G4*Assumptions!D15 -> 1561.3984 | H5: =H4*Assumptions!E15 -> 1750.5507 | I5: =I4*Assumptions!F15 -> 1925.6058 | J5: Company ex-one-offs basis: FY23 ex FV gains; FY24 ex FY23-bonus drag; FY25 ex 72 Medeor gain
A6: EBITDA — as reported | B6: 1033 | C6: 908 | D6: 1089 | J6: Dual framing: pre-IFRS-16 FY25 = 926 (co. leverage basis)
A7: D&A | B7: 352 | C7: 360 | D7: 386 | E7: =E4*Assumptions!B16 -> 426.2622 | F7: =F4*Assumptions!C16 -> 466.39174 | G7: =G4*Assumptions!D16 -> 505.59568 | H7: =H4*Assumptions!E16 -> 542.9949 | I7: =I4*Assumptions!F16 -> 577.68173
A8: EBIT | B8: =B5-B7 -> 666 | C8: =C5-C7 -> 599 | D8: =D5-D7 -> 631 | E8: =E5-E7 -> 749.00358 | F8: =F5-F7 -> 898.98698 | G8: =G5-G7 -> 1055.8028 | H8: =H5-H7 -> 1207.5558 | I8: =I5-I7 -> 1347.924
A9: Net finance costs | B9: 141 | C9: 149 | D9: 162 | E9: =Assumptions!B28 -> 210 | F9: =E9*1 -> 210 | G9: =F9*1 -> 210 | H9: =G9*1 -> 210 | I9: =H9*1 -> 210 | J9: FY26E d7; held flat thereafter (sukuk fixed 7.00%)
A10: Profit before tax — underlying | B10: =B8-B9 -> 525 | C10: =C8-C9 -> 450 | D10: =D8-D9 -> 469 | E10: =E8-E9 -> 539.00358 | F10: =F8-F9 -> 688.98698 | G10: =G8-G9 -> 845.80275 | H10: =H8-H9 -> 997.55581 | I10: =I8-I9 -> 1137.924
A11: One-off items (EBITDA level) | B11: =B6-B5 -> 15 | C11: =C6-C5 -> -51 | D11: =D6-D5 -> 72 | E11: 0 | F11: 0 | G11: 0 | H11: 0 | I11: 0 | J11: FY23 +15 FV gains; FY24 −51 bonus drag; FY25 +72 Medeor — reconciles und→reported
A12: Profit before tax — reported | B12: =B10+B11 -> 540 | C12: =C10+C11 -> 399 | D12: =D10+D11 -> 541 | E12: =E10+E11 -> 539.00358 | F12: =F10+F11 -> 688.98698 | G12: =G10+G11 -> 845.80275 | H12: =H10+H11 -> 997.55581 | I12: =I10+I11 -> 1137.924 | J12: ties officials: 540 / 399 / 541
A13: Income tax | B13: 0 | C13: 39 | D13: 38 | E13: =E12*Assumptions!B23 -> 53.900358 | F13: =F12*Assumptions!C23 -> 75.788568 | G13: =G12*Assumptions!D23 -> 101.49633 | H13: =H12*Assumptions!E23 -> 124.69448 | I13: =I12*Assumptions!F23 -> 147.93013 | J13: FY23 pre-CT (first taxed year FY24); forecast on the 10→13% Pillar-Two path (Assumptions B23:F23)
A14: Net profit | B14: =B12-B13 -> 540 | C14: =C12-C13 -> 360 | D14: =D12-D13 -> 503 | E14: =E12-E13 -> 485.10322 | F14: =F12-F13 -> 613.19841 | G14: =G12-G13 -> 744.30642 | H14: =H12-H13 -> 872.86134 | I14: =I12-I13 -> 989.99392 | J14: computed — ties officials: 540 / 360 / 503
A15: Attributable to owners | B15: 516 | C15: 347 | D15: 475 | E15: =E14*Assumptions!B29 -> 457.93744 | F15: =F14*Assumptions!B29 -> 578.8593 | G15: =G14*Assumptions!B29 -> 702.62526 | H15: =H14*Assumptions!B29 -> 823.9811 | I15: =I14*Assumptions!B29 -> 934.55426
A16: EPS (AED) | B16: =B15/Assumptions!$B$6 -> 0.099040307 | C16: =C15/Assumptions!$B$6 -> 0.066602687 | D16: =D15/Assumptions!$B$6 -> 0.091170825 | E16: =E15/Assumptions!$B$6 -> 0.087895862 | F16: =F15/Assumptions!$B$6 -> 0.11110543 | G16: =G15/Assumptions!$B$6 -> 0.1348609 | H16: =H15/Assumptions!$B$6 -> 0.15815376 | I16: =I15/Assumptions!$B$6 -> 0.17937702
A17: EBITDA margin (underlying) | B17: =B5/B4 -> 0.2244763 | C17: =C5/C4 -> 0.19141717 | D17: =D5/D4 -> 0.18538097 | E17: =E5/E4 -> 0.193 | F17: =F5/F4 -> 0.202 | G17: =G5/G4 -> 0.21 | H17: =H5/H4 -> 0.216 | I17: =I5/I4 -> 0.22

Sheet Balance Sheet
A1: Balance sheet anchors — 31-Dec-2025 (AED mn)
A2: Official FY2025 statements; forecast BS not modelled — the DCF bridge uses these anchors
A3: Item | B3: FY2024 | C3: FY2025 | E3: Note
A4: Interest-bearing borrowings | B4: 1208 | C4: 1918 | E4: Current 429 + non-current 1,489; Jun-26 USD 500mn sukuk (AED 1,836) is post-period
A5: Cash & bank balances | C5: 281
A6: Net debt — ex leases | C6: =C4-C5 -> 1637 | E6: Company leverage basis: 1.8x pre-IFRS-16 EBITDA
A7: IFRS-16 lease liabilities | C7: 1191 | E7: Current 123 + non-current 1,068
A8: Net debt — incl leases | C8: =C6+C7 -> 2828 | E8: Dual framing: 2.6x reported EBITDA
A9: Total equity (incl NCI) | C9: 2165
A10: Non-controlling interests | C10: 68
A11: Trade receivables | C11: 2057 | E11: DSO 135 days (was 123) — WC crux input d3
A12: Trade payables | C12: 738 | E12: DPO 211 days
A13: Goodwill | C13: 93 | E13: ACOC acquisition
A15: Debt maturity (AED mn): 2026: 83 · 2027: 346 · 2028: 414 · 2029: 526 · 2030: 340 · 2031: 208 (pre-sukuk)

Sheet Cash Flow & FCFF
A1: Cash flow — FY2025 reported, and the modelled FCFF drivers (AED mn)
B3: FY2025 | C3: FY26E | D3: FY27E | E3: FY28E | F3: FY29E | G3: FY30E | H3: Note
A4: Operating cash flow | B4: 402 | H4: Reported; −19.5% on WC outflows
A5: Capex — total | B5: 585 | C5: ='Income Statement'!E4*Assumptions!B18+Assumptions!B17 -> 427.2365 | D5: ='Income Statement'!F4*Assumptions!C18+Assumptions!C17 -> 418.98251 | E5: ='Income Statement'!G4*Assumptions!D18+Assumptions!D17 -> 410.88077 | F5: ='Income Statement'!H4*Assumptions!E18+Assumptions!E17 -> 377.61004 | G5: ='Income Statement'!I4*Assumptions!F18+Assumptions!F17 -> 343.81884 | H5: FY25: growth 448 + maintenance 136
A6: ΔWC (modelled) | C6: =('Income Statement'!E4-'Income Statement'!D4)*Assumptions!B19 -> 144.8304 | D6: =('Income Statement'!F4-'Income Statement'!E4)*Assumptions!C19 -> 157.41254 | E6: =('Income Statement'!G4-'Income Statement'!F4)*Assumptions!D19 -> 155.46391 | F6: =('Income Statement'!H4-'Income Statement'!G4)*Assumptions!E19 -> 150.56342 | G6: =('Income Statement'!I4-'Income Statement'!H4)*Assumptions!F19 -> 142.63746 | H6: d3
A7: Lease payments | B7: 162 | C7: =B7*(1+Assumptions!B20) -> 171.72 | D7: =C7*(1+Assumptions!C20) -> 182.0232 | E7: =D7*(1+Assumptions!D20) -> 192.94459 | F7: =E7*(1+Assumptions!E20) -> 204.52127 | G7: =F7*(1+Assumptions!F20) -> 216.79254 | H7: FY25 rentals; grows at d4
A8: Company-defined FCF | B8: 451 | H8: 41% conversion (FY25 PR)

Sheet DCF
A1: FCFF DCF — the full waterfall, Revenue to PV (AED mn; base case)
A3: Waterfall | B3: FY26E | C3: FY27E | D3: FY28E | E3: FY29E | F3: FY30E | H3: Note
A4: Revenue | B4: ='Income Statement'!E4 -> 6089.46 | C4: ='Income Statement'!F4 -> 6759.3006 | D4: ='Income Statement'!G4 -> 7435.2307 | E4: ='Income Statement'!H4 -> 8104.4014 | F4: ='Income Statement'!I4 -> 8752.7535
A5: EBITDA | B5: ='Income Statement'!E5 -> 1175.2658 | C5: ='Income Statement'!F5 -> 1365.3787 | D5: ='Income Statement'!G5 -> 1561.3984 | E5: ='Income Statement'!H5 -> 1750.5507 | F5: ='Income Statement'!I5 -> 1925.6058
A6: − D&A | B6: =-'Income Statement'!E7 -> -426.2622 | C6: =-'Income Statement'!F7 -> -466.39174 | D6: =-'Income Statement'!G7 -> -505.59568 | E6: =-'Income Statement'!H7 -> -542.9949 | F6: =-'Income Statement'!I7 -> -577.68173
A7: EBIT | B7: ='Income Statement'!E8 -> 749.00358 | C7: ='Income Statement'!F8 -> 898.98698 | D7: ='Income Statement'!G8 -> 1055.8028 | E7: ='Income Statement'!H8 -> 1207.5558 | F7: ='Income Statement'!I8 -> 1347.924
A8: − Tax on EBIT (10.0→13.0% path) | B8: =-'Income Statement'!E8*Assumptions!B23 -> -74.900358 | C8: =-'Income Statement'!F8*Assumptions!C23 -> -98.888568 | D8: =-'Income Statement'!G8*Assumptions!D23 -> -126.69633 | E8: =-'Income Statement'!H8*Assumptions!E23 -> -150.94448 | F8: =-'Income Statement'!I8*Assumptions!F23 -> -175.23013
A9: NOPAT | B9: ='Income Statement'!E8*(1-Assumptions!B23) -> 674.10322 | C9: ='Income Statement'!F8*(1-Assumptions!C23) -> 800.09841 | D9: ='Income Statement'!G8*(1-Assumptions!D23) -> 929.10642 | E9: ='Income Statement'!H8*(1-Assumptions!E23) -> 1056.6113 | F9: ='Income Statement'!I8*(1-Assumptions!F23) -> 1172.6939
A10: + D&A | B10: ='Income Statement'!E7 -> 426.2622 | C10: ='Income Statement'!F7 -> 466.39174 | D10: ='Income Statement'!G7 -> 505.59568 | E10: ='Income Statement'!H7 -> 542.9949 | F10: ='Income Statement'!I7 -> 577.68173
A11: − Capex | B11: =-'Cash Flow & FCFF'!C5 -> -427.2365 | C11: =-'Cash Flow & FCFF'!D5 -> -418.98251 | D11: =-'Cash Flow & FCFF'!E5 -> -410.88077 | E11: =-'Cash Flow & FCFF'!F5 -> -377.61004 | F11: =-'Cash Flow & FCFF'!G5 -> -343.81884
A12: − ΔWC | B12: =-'Cash Flow & FCFF'!C6 -> -144.8304 | C12: =-'Cash Flow & FCFF'!D6 -> -157.41254 | D12: =-'Cash Flow & FCFF'!E6 -> -155.46391 | E12: =-'Cash Flow & FCFF'!F6 -> -150.56342 | F12: =-'Cash Flow & FCFF'!G6 -> -142.63746
A13: − Lease payments | B13: =-'Cash Flow & FCFF'!C7 -> -171.72 | C13: =-'Cash Flow & FCFF'!D7 -> -182.0232 | D13: =-'Cash Flow & FCFF'!E7 -> -192.94459 | E13: =-'Cash Flow & FCFF'!F7 -> -204.52127 | F13: =-'Cash Flow & FCFF'!G7 -> -216.79254
A14: FCFF | B14: =B9+B10+B11+B12+B13 -> 356.57852 | C14: =C9+C10+C11+C12+C13 -> 508.0719 | D14: =D9+D10+D11+D12+D13 -> 675.41284 | E14: =E9+E10+E11+E12+E13 -> 866.91151 | F14: =F9+F10+F11+F12+F13 -> 1047.1268
A15: Discount factor | B15: =1/(1+WACC!$B$14)^1 -> 0.92457521 | C15: =1/(1+WACC!$B$14)^2 -> 0.85483932 | D15: =1/(1+WACC!$B$14)^3 -> 0.79036325 | E15: =1/(1+WACC!$B$14)^4 -> 0.73075027 | F15: =1/(1+WACC!$B$14)^5 -> 0.67563359
A16: PV of FCFF | B16: =B14*B15 -> 329.68366 | C16: =C14*C15 -> 434.31984 | D16: =D14*D15 -> 533.82148 | E16: =E14*E15 -> 633.49582 | F16: =F14*F15 -> 707.47404
A18: Sum of PV, FY26–30E | B18: =SUM(B16:F16) -> 2638.7948
A19: Terminal FCFF x (1+g) | B19: =F14*(1+Assumptions!B25) -> 1073.305
A20: Terminal value (Gordon) | B20: =B19/(WACC!B14-Assumptions!B25) -> 18970.435
A21: PV of terminal value | B21: =B20*F15 -> 12817.063
A22: Enterprise value | B22: =B18+B21 -> 15455.858 | H22: TV 83% of EV — long-duration valuation, disclosed deliberately; §1.9 stresses it
A23: TV as % of EV | B23: =B21/B22 -> 0.82926895
A24: − Net debt (ex leases) | B24: =-Assumptions!B7 -> -1637
A25: − NCI | B25: =-Assumptions!B9 -> -68
A26: Equity value | B26: =B22+B24+B25 -> 13750.858
A27: Per share — base (AED) | B27: =B26/Assumptions!B6 -> 2.6393201
A30: Base per share (link) | B30: =B27 -> 2.6393201
A31: Bear per share | B31: 1.2064998 | H31: Bear: growth 8→6%, margin stuck 19%, WACC 9.30%, g 2.0% — engine-computed scenario
A32: Bull per share | B32: 3.5768672 | H32: Bull: KSA PPP lands, growth 13→10%, margin to 23.5%, tax 9%, g 3.0%
A33: Base at peg-parity WACC 8.80% | B33: 2.3159155 | H33: Dual-rf basis disclosed (US10Y + UAE spread); primary is the AED-sovereign basis

Sheet DDM
A1: Dividend discount — the policy lens (AED per share)
B3: FY26E | C3: FY27E | D3: FY28E | E3: FY29E | F3: FY30E | H3: Note
A4: DPS growth | B4: 0.15 | C4: 0.15 | D4: 0.15 | E4: 0.14 | F4: 0.13 | H4: d9 — payout normalizes from ~25% toward the stated 40–70% policy floor
A5: DPS (AED) | B5: =Assumptions!B10*(1+B4) -> 0.023 | C5: =B5*(1+C4) -> 0.02645 | D5: =C5*(1+D4) -> 0.0304175 | E5: =D5*(1+E4) -> 0.03467595 | F5: =E5*(1+F4) -> 0.039183823
A6: PV of DPS | B6: =B5/(1+WACC!$B$8)^1 -> 0.021122233 | C6: =C5/(1+WACC!$B$8)^2 -> 0.022307437 | D6: =D5/(1+WACC!$B$8)^3 -> 0.023559145 | E6: =E5/(1+WACC!$B$8)^4 -> 0.024664731 | F6: =F5/(1+WACC!$B$8)^5 -> 0.025595689
A8: Terminal g | B8: 0.03
A9: Terminal value / share (PV) | B9: =F5*(1+B8)/(WACC!B8-$B$8)/(1+WACC!B8)^5 -> 0.44759863
A13: DDM value — base | B13: =SUM(B6:F6)+B9 -> 0.56484787
A14: Bear (flat 0.02, Ke+50bp) | B14: 0.2380267
A15: Bull (payout step-up, g 3.5%) | B15: 0.79357261
A16: Reading: far below spot by construction — Burjeel retains ~75% of earnings for the build-out; the DDM refuses to credit reinvestment until it arrives as dividends. Weighted 15% for exactly that reason.

Sheet Relative & Normalized
A1: Relative EV/EBITDA and normalized-earnings lenses
A3: FY26E pre-IFRS-16 EBITDA (AED mn) | B3: ='Income Statement'!E5-'Cash Flow & FCFF'!C7 -> 1003.5458 | D3: Same basis as the company leverage metric; same bridge as the DCF
A5: EV/EBITDA
A6: base multiple x per-share | B6: =(C6*$B$3-Assumptions!B7-Assumptions!B9)/Assumptions!B6 -> 1.887865 | C6: 11.5
A7: bear multiple x per-share | B7: =(C7*$B$3-Assumptions!B7-Assumptions!B9)/Assumptions!B6 -> 1.5026267 | C7: 9.5
A8: bull multiple x per-share | B8: =(C8*$B$3-Assumptions!B7-Assumptions!B9)/Assumptions!B6 -> 2.1767937 | C8: 13
D9: d6 band: BURJEEL trades ~8.4x (aggregator-flagged); Saudi premium tier 24x+ (Al Habib); UAE float discount held
A11: Normalized earnings
A12: Clean FY26E EPS | B12: =('Income Statement'!E8-Assumptions!B28)*(1-Assumptions!B23)*Assumptions!B29/Assumptions!B6 -> 0.087895862
A13: P/E applied
A15: base P/E x value | B15: =C15*$B$12 -> 1.4942297 | C15: 17
A16: bear P/E x value | B16: =C16*$B$12 -> 1.2305421 | C16: 14
A17: bull P/E x value | B17: =C17*$B$12 -> 1.7579172 | C17: 20
A19: Implied-multiple discipline check
A20: Value (AED/sh) | B20: Implied EV/EBITDA | C20: Implied P/E
A21: Spot | B21: =Assumptions!B5 -> 1.11 | C21: =(B21*Assumptions!B6+Assumptions!B7+Assumptions!B9)/$B$3 -> 7.4616427 | D21: =B21/$B$12 -> 12.628581
A22: Relative base | B22: =B6 -> 1.887865 | C22: =(B22*Assumptions!B6+Assumptions!B7+Assumptions!B9)/$B$3 -> 11.5 | D22: =B22/$B$12 -> 21.478428
A23: Weighted central | B23: =Summary!C10 -> 1.8540129 | C23: =(B23*Assumptions!B6+Assumptions!B7+Assumptions!B9)/$B$3 -> 11.324254 | D23: =B23/$B$12 -> 21.09329
A24: DCF base | B24: =DCF!B27 -> 2.6393201 | C24: =(B24*Assumptions!B6+Assumptions!B7+Assumptions!B9)/$B$3 -> 15.401248 | D24: =B24/$B$12 -> 30.027809
A26: Peer set (aggregator-flagged)
A27: Name | B27: EV/EBITDA | C27: P/E | D27: Note
A28: Dr. Sulaiman Al Habib | B28: ~24x | C28: ~31x | D28: premium tier: 25%+ margins, deep float
A29: Dallah Healthcare | B29: n/d | C29: ~25x
A30: Mouwasat | B30: high-teens | C30: ~20x+
A31: PureHealth | B31: n/m | C31: n/m | D31: payer+provider aggregator, not a clean comp
A32: NMC (delisted) | B32: — | C32: — | D32: the cautionary precedent the UAE discount remembers
A33: Burjeel | B33: ~8.4x | C33: ~12x | D33: the discount this study prices

Sheet WACC
A1: Cost of capital — bottom-up, dual risk-free basis
A4: Risk-free — AED basis (primary) | B4: 0.039 | C4: Longest AED sovereign: ~7yr T-Sukuk Feb-2033 ≈3.78–3.90% (MoF auctions); no 10yr AED bond exists — house rule: local-currency sovereign, never a USD shortcut
A5: Risk-free — peg-parity basis | B5: 0.0475 | C5: US 10Y ~4.55% + UAE Aa2 spread ~20bp — disclosed alongside, per the dual-basis rule
A6: Equity risk premium (Damodaran) | B6: 0.0499 | C6: Original NYU Stern dataset, 5-Jan-2026: mature 4.23% + UAE CRP 0.66% = 4.99%
A7: Beta | B7: 1 | C7: Regression genuinely attempted and FAILED the usability gate: no ADX General Index daily series reachable this session (adx.ae outside sandbox; aggregator betas 0.21–0.80 inconsistent, thin 15% float). Default 1.0; grid 0.8–1.3 in §1.9
A8: Cost of equity — AED basis | B8: =B4+B7*B6 -> 0.0889
A9: Cost of equity — parity basis | B9: =B5+B7*B6 -> 0.0974
A10: Pre-tax cost of debt | B10: 0.07 | C10: Marginal: USD 500mn 5yr sukuk priced 7.000% (Jun-2026, BB+/Ba2); blended existing ~6.8% implied
A11: Kd tax shield — marginal rate | B11: 0.15 | C11: Held at 15% (the top-up binds at the margin); the 10→13% effective path applies to EBIT — conservative on the rate side
A12: E (mkt, AED mn) / D (AED mn) | B12: =Assumptions!B6*Assumptions!B5 -> 5783.1 | C12: D = 1,918 borrowings (31-Dec-25)
A13: Weight of equity | B13: =B12/(B12+1918) -> 0.75094467
A14: WACC — AED basis (primary) | B14: =B13*B8+(1-B13)*B10*(1-B11) -> 0.081577773
A15: WACC — peg-parity basis | B15: =B13*B9+(1-B13)*B10*(1-B11) -> 0.087960803

Sheet Sensitivity
A1: Per-share sensitivity — engine-computed grids (AED)
A3: WACC \ terminal g | B3: 0.015 | C3: 0.02 | D3: 0.025 | E3: 0.03 | F3: 0.035
A4: 0.073577773 | B4: 2.6339539 | C4: 2.8749888 | D4: 3.1656421 | E4: 3.522993 | F4: 3.9729752 | H4: Grid re-solves the full DCF per cell (compute_burjeel.py); centre cell = base
A5: 0.077577773 | B5: 2.4292838 | C5: 2.636137 | D5: 2.8823324 | E5: 3.1802737 | F5: 3.5481909
A6: 0.081577773 | B6: 2.2494182 | C6: 2.4285395 | D6: 2.6393201 | E6: 2.8909673 | F6: 3.1966419
A7: 0.085577773 | B7: 2.0901357 | C7: 2.2464732 | D7: 2.4286185 | E7: 2.6435367 | F7: 2.9009476
A8: 0.089577773 | B8: 1.948121 | C8: 2.0855311 | D8: 2.2442194 | E8: 2.4295433 | F8: 2.648823
A11: THE CRUX — tax x FY30E margin | B11: 0.19 | C11: 0.205 | D11: 0.22 | E11: 0.235
A12: tax 9% | B12: 2.1719141 | C12: 2.4835551 | D12: 2.7951962 | E12: 3.1068372 | H12: Vs the 10→13% path base: exclusion +0.15/share; flat 15% −0.09; rows are flat-rate scenarios
A13: tax 15% (DMTT) | B13: 1.9754429 | C13: 2.2665362 | D13: 2.5576295 | E13: 2.8487228
A16: Beta grid | B16: 0.8 | C16: 0.9 | D16: 1 | E16: 1.1 | F16: 1.2 | G16: 1.3
A17: DCF/share | B17: 3.1272691 | C17: 2.8658781 | D17: 2.6393201 | E17: 2.4411005 | F17: 2.266244 | G17: 2.110875

Sheet Monte Carlo
A1: Monte Carlo — carry-anchored YZ-HAR-t, 50,000 paths, seed 42
A2: Genuine 3-month clock; centre = money-market carry, never the fundamental gap
A5: Horizon | B5: P5 | C5: P25 | D5: P50 | E5: P75 | F5: P95 | G5: P(up) | H5: P(±5%) | I5: P(±10%) | J5: σ_H
A7: T+20 sessions | B7: 0.94428098 | C7: 1.0441021 | D7: 1.111013 | E7: 1.1833757 | F7: 1.3085064 | G7: 0.50408 | H7: 30/28 | I7: 16/13 | J7: 0.099991586
A8: T+60 sessions | B8: 0.83671682 | C8: 0.99847112 | D8: 1.1137334 | E8: 1.2444529 | F8: 1.4851002 | G8: 0.50838 | H8: 39/37 | I8: 29/25 | J8: 0.17586514
A10: Drift decomposition (T+60, log)
A11: rf carry (CBUAE 3.63%) | B11: 0.008489685
A12: − dividend yield (1.80%) | B12: -0.0042518137
A13: signal alpha (OFF per live AE profile) | B13: 0
A14: total drift | B14: 0.0042378714
A16: Touch ladder (60d)
A17: touch 1.40 | B17: 0.15326 | D17: Engine: mc_v3.py, live AE profile t(10) x1.049 width, carry-only. Cohorts grade 07-Aug-2026 (T+20) and 02-Oct-2026 (T+60) on the public Ledger against these frozen percentiles.
A18: touch 1.30 | B18: 0.31062
A19: touch 1.25 | B19: 0.43268
A20: touch 1.20 | B20: 0.58934
A21: touch 1.15 | B21: 0.77688
A22: touch 1.05 | B22: 0.6701
A23: touch 1.00 | B23: 0.467
A24: touch 0.95 | B24: 0.30078
A25: touch 0.90 | B25: 0.17768

Sheet Technical
A1: Technical & price structure — 10-Jul-2026 close
A3: Spot | B3: 1.11
A4: 52-week high / low | B4: 1.57 / 1.00
A5: SMA20 / 50 | B5: 1.131 / 1.090 | C5: Price vs stack read in §2
A6: SMA100 / 200 | B6: 1.127 / 1.228
A7: RSI(14) | B7: 49.7
A8: MACD / signal / hist | B8: 0.0060 / 0.0121 / -0.0061 | C8: MACD close 12 26 9 — histogram sign is the momentum read
A9: YTD / 1-yr return | B9: -15.3% / -24.5%
A10: vs IPO 2.00 / vs ATH 3.55 | B10: -44% / -69% | C10: Oct-2022 IPO; 27-Nov-2023 high
A11: Realized vol (annualized, full history) | B11: 30.8% | C11: a 30%-vol stock on a ~15% float — sizing beats timing
A12: Max drawdown / current | B12: -71% / -68% | C12: the whole post-2023 de-rating is still in the price
A13: All-time low | B13: 1.01 on 07-Apr-2026 | C13: the 2026 base printed three months before this study

Sheet Sweep Register
A1: Information Sweep — four rings, classified B/S/D/C
A2: Run 11-Jul-2026, before any driver was set
A3: Ring | B3: Item | C3: Finding (source) | D3: Class
A4: Global | B4: Fed path | C4: FFR held 3.50–3.75% Jun-26 (4th hold, Warsh); easing bias removed, median EOY 3.8% | D4: S
A5: Global | B5: Medical inflation | C5: WTW 2026: +10.3% global; MEA gross 11.3% — provider revenue tailwind, cost-base stress | D5: B
A6: Global | B6: Hospital multiples | C6: Verified: Al Habib 24–34x, Dallah 22–26x, Mouwasat 18–19x, Hammadi 17.5x, MEH 13x (floor) — Bloomberg/U Capital May-24, MarketScreener Jan-25, multiples.vc Jul-26 | D6: S
A7: Country | B7: UAE macro | C7: IMF 2026 GDP +3.1%, CPI 2.5%; Dubai Q1-26 health sector fastest-growing +17.5% | D7: B
A8: Country | B8: DMTT mechanics | C8: 15% top-up on POST-SBIE excess profit only; carve-outs 9.4/7.4% (2026)→5/5% (2033); CbCR safe harbour can zero the top-up pre-2027; FY25 ETR 7.0% with small top-up accrual | D8: S
A9: Country | B9: Mandatory insurance | C9: Northern Emirates basic cover from 1-Jan-2025 — insured pool structurally expands | D9: B
A10: Country | B10: AED risk-free | C10: No 10yr AED bond; 7yr T-Sukuk ~3.78–3.90% (MoF); 3M EIBOR 3.66–3.9% | D10: D
A11: Country | B11: Damodaran ERP | C11: UAE total 4.99% (mature 4.23% + CRP 0.66%), 5-Jan-2026 original file | D11: D
A12: Industry | B12: UPP | C12: Aug-2025 unified procurement: medicine revenue now net-basis fee — ~4.6pp optical drag Q1-26, 1–2% EBITDA dilution | D12: S
A13: Industry | B13: Insurer dispute | C13: Access restrictions on a major Abu Dhabi insurer May–Nov-2025, fully resolved 1-Nov-2025 | D13: S
A14: Industry | B14: Saudi PPP | C14: Vision-2030: private share 25%→35% by 2030; first hospital PPP awarded (Al Ansar, Madinah); pace slower than headline | D14: C
... A23: Company | B23: KPIs / asset count | C23: 1,784 beds · occ 67% · 7.0mn patients · doctors +32; FY25 PR 115 assets vs Q1-26 PR 89 — methodology change, reconciled | D23: D
A25: Validated: 4 rings present · 20 rows · every class ∈ {B,S,D,C} · sweep ran before §1.6 drivers were set

Sheet Calibration & Ledger
A1: Calibration backtest — 11 walk-forward windows vs the carry-anchored benchmark
A2: Live AE profile: t(10), width x1.049, carry-only (read from engine/market_profiles.py, 11-Jul-2026 refit)
A4: Origin | B4: Spot | C4: Realized | D4: CRPS | E4: CRPS bench | F4: PIT | G4: in-90
A5: 2023-10-25 | B5: 2.9 | C5: 3.3 | D5: 0.2182 | E5: 0.2225 | F5: 0.768 | G5: Y
A6: 2024-01-19 | B6: 3.3 | C6: 3.01 | D6: 0.2091 | E6: 0.1975 | F6: 0.28 | G6: Y
A7: 2024-04-19 | B7: 3.01 | C7: 2.68 | D7: 0.2181 | E7: 0.216 | F7: 0.236 | G7: Y
A8: 2024-07-16 | B8: 2.68 | C8: 2.3 | D8: 0.2447 | E8: 0.2494 | F8: 0.167 | G8: Y
A9: 2024-10-08 | B9: 2.3 | C9: 2 | D9: 0.195 | E9: 0.192 | F9: 0.168 | G9: Y
A10: 2025-01-03 | B10: 2 | C10: 1.42 | D10: 0.4423 | E10: 0.4663 | F10: 0.016 | G10: MISS
A11: 2025-03-28 | B11: 1.42 | C11: 1.34 | D11: 0.0647 | E11: 0.0636 | F11: 0.333 | G11: Y
A12: 2025-06-26 | B12: 1.34 | C12: 1.35 | D12: 0.0521 | E12: 0.052 | F12: 0.504 | G12: Y
A13: 2025-09-22 | B13: 1.35 | C13: 1.33 | D13: 0.0533 | E13: 0.0561 | F13: 0.452 | G13: Y
A14: 2025-12-17 | B14: 1.33 | C14: 1.09 | D14: 0.1571 | E14: 0.1538 | F14: 0.109 | G14: Y
A15: 2026-03-16 | B15: 1.09 | C15: 1.11 | D15: 0.0434 | E15: 0.0424 | F15: 0.533 | G15: Y
A17: Pooled (scale-normalized) | D17: skill +0.85% | H17: 90% CI [-1.69%, +2.53%] → PARITY · robust blocks 2/3/4 all straddle 0 · cov50/80/90 = 0.46/0.91/0.91 · PIT mean 0.32
H18: Market gate: UAE 14-name panel PARITY +0.49% CI[-0.4%,+1.5%] (live profile) → proceed, parity tier
A20: Calibration Ledger — append rows (frozen at publication)
A21: Ticker | B21: Anchor | C21: Horizon | D21: P5 | E21: P50 | F21: P95 | G21: Grades
A22: BURJEEL | B22: 2026-07-10 | C22: T+20 | D22: 0.94428098 | E22: 1.111013 | F22: 1.3085064 | G22: 2026-08-07 | H22: engine mc_v3 · AE t(10)/1.049 · carry-only · seed 42 · never retro-edited
A23: BURJEEL | B23: 2026-07-10 | C23: T+60 | D23: 0.83671682 | E23: 1.1137334 | F23: 1.4851002 | G23: 2026-10-02 | H23: engine mc_v3 · AE t(10)/1.049 · carry-only · seed 42 · never retro-edited

Sheet Experts
A1: Appendix C — the expert panel (three methods, shown workings, a falsifier each)
A3: Expert 1 | B3: THE OPERATING-LEVERAGE ANALYST. Method: unit economics up from beds. 1,784 beds at 67% occupancy vs the 80–85% normalized peak the company itself cites: filling existing beds to 78% at FY25 revenue-per-occupied-bed adds ~AED 900mn revenue at ~45% incremental margin (staff already hired — doctors +32 in FY25 vs +188 in FY24), i.e. ~AED 400mn EBITDA before any new asset. That alone lifts underlying EBITDA past the guided low-20s. Arithmetic: 1,784 beds x 365 x 11pp x AED ~11,094/occupied-bed-day = ~AED 795mn revenue; x ~45% incremental margin = ~AED 358mn EBITDA; look-through EBITDA ~AED 1,375mn; at 11.5x (the recalibrated base) through the same bridge = AED 2.33/share ceiling. Working read = 60% execution x ceiling + 40% x spot = AED 1.84. FALSIFIER: two consecutive quarters with group occupancy below 68% while beds grow — the leverage thesis dies on utilization, not price.
A4: Expert 2 | B4: THE BALANCE-SHEET SKEPTIC. Method: cash conversion and credit. DSO at 135 days and rising; OCF fell 19.5% in FY2025 while reported profit rose 39.5% — receivables are funding the P&L. The new sukuk prices the truth: 7.00% for 5 years, BB+, against a 3.9% sovereign. Caps equity value at what the FCF yield supports: AED 451mn company-FCF on a de-risked 8% required yield → equity ~AED 5.6bn ≈ AED 1.08/share today. Profit-to-cash walk FY25: NP 503 + D&A 386 + finance 162 = 1,051 gross; OCF 402; absorbed 649 (WC build, tax, other). Each 15 DSO days released ≈ AED 225mn one-off cash. Working read AED 1.10–1.35. FALSIFIER: DSO printing below 120 days in any FY2026 statement, or net leverage below 1.5x post-sukuk — either breaks the working-capital-drag thesis.
A5: Expert 3 | B5: THE REGIME-TREE STRATEGIST. Method: explicit scenario tree on the three crux legs. (a) DMTT applies (p=0.7) vs initial-phase exclusion (0.3); (b) margin reaches ≥21.5% by FY28 (p=0.55) vs stuck ≤19.5% (0.45); (c) a signed KSA PPP hospital by end-2027 (p=0.35) vs asset-light only (0.65). Internally consistent states: stuck-margin branches carry bear growth and +60bp WACC. Eight leaves off the study’s own DCF engine span AED 1.52 (path tax, margin stuck, no KSA) to 2.91 (exclusion, margin lands, PPP). Probability-weighted: AED 2.20 — above the weighted central because the tree contains no dividend-policy lens; even its worst leaf sits above spot, so what the market prices at 1.11 is outside the tree: the receivables clock and the float. FALSIFIER: the FY2025 DMTT return (filed 2026–27) showing the exclusion granted — that alone reweights the tree by ~AED 0.15.
A6: Convergence | B6: Expert 1’s working read (1.70) sits on the study’s central; Expert 3 (2.14) brackets it from above; Expert 2 (1.10–1.35) sits on spot and explains WHY the market pays it — the receivables clock. The panel converges on: fair value well above spot conditional on cash conversion; spot is the price of not yet believing the collections.
A8: Expert 3 — the eight leaves (engine-priced)
A9: Tax | B9: Margin state | C9: Saudi | D9: P | E9: AED/sh
A10: 9% | B10: margin lands 22.0% | C10: PPP signed | D10: 0.05775 | E10: 2.9080768
A11: 9% | B11: margin lands 22.0% | C11: asset-light only | D11: 0.10725 | E11: 2.7951962
A12: 9% | B12: margin stuck 19.0% | C12: PPP signed | D12: 0.04725 | E12: 1.643384
A13: 9% | B13: margin stuck 19.0% | C13: asset-light only | D13: 0.08775 | E13: 1.6098747
A14: path 10→13% | B14: margin lands 22.0% | C14: PPP signed | D14: 0.13475 | E14: 2.7456728
A15: path 10→13% | B15: margin lands 22.0% | C15: asset-light only | D15: 0.25025 | E15: 2.6462723
A16: path 10→13% | B16: margin stuck 19.0% | C16: PPP signed | D16: 0.11025 | E16: 1.5391848
A17: path 10→13% | B17: margin stuck 19.0% | C17: asset-light only | D17: 0.20475 | E17: 1.5144497
A18: Probability-weighted value | E18: =SUMPRODUCT(D10:D17,E10:E17) -> 2.1986304

Sheet Segments & KPIs
A1: Segment economics and the operating-KPI panel
A2: FY2025 official MD&A; the +11% rebuilt bottom-up two ways
A3: Segment (FY25, AED mn) | B3: Revenue | C3: EBITDA | D3: Margin | E3: Reading
A4: Hospitals (incl. BMC) | B4: 4840 | C4: 1165 | D4: =C4/B4 -> 0.24070248 | E4: the engine: 88% of revenue, all of the profit pool
A5: of which Burjeel Medical City | B5: 1290 | C5: 241 | D5: =C5/B5 -> 0.18682171 | E5: quaternary flagship ramping: occupancy 61% vs 67% group
A6: Medical centres & clinics | B6: 468 | C6: 50 | D6: =C6/B6 -> 0.10683761 | E6: feeder network: referral value exceeds its own P&L
A7: Pharmacy & other (residual) | B7: 178 | C7: -198 | D7: =C7/B7 -> -1.1123596 | E7: residual reconciles segment EBITDA to 1,017 underlying; unallocated corporate costs sit here
A8: Total (underlying) | B8: =SUM(B4:B7)-B5 -> 5486 | C8: =SUM(C4:C7)-C5 -> 1017
A10: Growth reconciliation #1 — by segment
A11: Segment | B11: Weight | C11: Growth | D11: Contribution
A12: Hospitals | B12: =B4/$B$8 -> 0.88224572 | C12: 0.115 | D12: =B12*C12 -> 0.10145826
A13: Medical centres | B13: =B6/$B$8 -> 0.085308057 | C13: 0.08 | D13: =B13*C13 -> 0.0068246445
A14: Other | B14: =B7/$B$8 -> 0.032446227 | C14: 0.06 | D14: =B14*C14 -> 0.0019467736
A15: Aggregate FY26E growth | D15: =SUM(D12:D14) -> 0.11022968 | E15: reproduces the modelled +11.0% without a plug
A17: Growth reconciliation #2 — inside hospitals
A18: Occupancy 67% -> 69.5% | B18: 1.037 | E18: +3.7%
A19: Beds | B19: 1.025 | E19: +2.5% (BMC wings, day-surgery)
A20: Price / mix | B20: 1.048 | E20: +4.8% (medical inflation ~11% MEA, partly ceded)
A21: Product - 1 | B21: =B18*B19*B20-1 -> 0.1139454
A23: Operating KPI panel (FY2025)
A24: Beds / occupancy | B24: 1,784 / 67% | E24: each +1pp occupancy ~ AED 72mn revenue at ~45% incremental margin
A25: Revenue per occupied-bed-day | B25: AED ~11,094 | E25: derived: hospital rev / (beds x 365 x occ); blended incl outpatient
A26: Patients / revenue per patient | B26: 7.0mn / AED ~784 | E26: volume franchise intact; UPP moved the revenue line, not patients
A27: Doctors / net adds | B27: 1,776 / +32 (FY24 +188) | E27: hiring done ahead of the fill — the operating-leverage setup
A28: DSO / DPO | B28: 135d (was 123) / 211d | E28: the referee: the receivable funds the P&L until collected
A29: ROCE (company-stated) | B29: 13.5% | E29: model glide lifts to ~17% by FY30E (Per-Share & Ratios)
A30: Capex intensity | B30: 10.7% of revenue | E30: falls to ~5.5% by FY30E on asset-light mix
A31: Net debt / EBITDA | B31: 1.8x ex-leases / 2.6x incl / 1.7x Q1-26 | E31: both framings; guidance ceiling 2.5x
A32: FCF conversion (company basis) | B32: 41% | E32: FY25 FCF 451 / EBITDA 1,089
A33: Assets in network | B33: 89 (Q1-26) / 115 (FY25) | E33: counting-methodology change; beds & hospitals consistent

Sheet Per-Share & Ratios
A1: Per-share data and returns — model output, formula-linked
B3: FY26E | C3: FY27E | D3: FY28E | E3: FY29E | F3: FY30E | G3: Note
A4: EPS (AED) | B4: ='Income Statement'!E16 -> 0.087895862 | C4: ='Income Statement'!F16 -> 0.11110543 | D4: ='Income Statement'!G16 -> 0.1348609 | E4: ='Income Statement'!H16 -> 0.15815376 | F4: ='Income Statement'!I16 -> 0.17937702
A5: DPS (AED) | B5: =DDM!B5 -> 0.023 | C5: =DDM!C5 -> 0.02645 | D5: =DDM!D5 -> 0.0304175 | E5: =DDM!E5 -> 0.03467595 | F5: =DDM!F5 -> 0.039183823
A6: Payout of EPS | B6: =B5/B4 -> 0.2616733 | C6: =C5/C4 -> 0.23806217 | D6: =D5/D4 -> 0.22554722 | E6: =E5/E4 -> 0.21925466 | F6: =F5/F4 -> 0.21844395
A7: Dividend bill (AED mn) | B7: =B5*Assumptions!B6 -> 119.83 | C7: =C5*Assumptions!B6 -> 137.8045 | D7: =D5*Assumptions!B6 -> 158.47518 | E7: =E5*Assumptions!B6 -> 180.6617 | F7: =F5*Assumptions!B6 -> 204.14772
A8: Attributable FCF (AED mn) | B8: =(DCF!B14-Assumptions!B28*(1-Assumptions!B23))*Assumptions!B29 -> 158.19412 | C8: =(DCF!C14-Assumptions!B28*(1-Assumptions!C23))*Assumptions!B29 -> 303.18627 | D8: =(DCF!D14-Assumptions!B28*(1-Assumptions!D23))*Assumptions!B29 -> 463.13852 | E8: =(DCF!E14-Assumptions!B28*(1-Assumptions!E23))*Assumptions!B29 -> 644.90446 | F8: =(DCF!F14-Assumptions!B28*(1-Assumptions!F23))*Assumptions!B29 -> 816.0189 | G8: FCFF less after-tax interest, at the attributable share
A9: Dividend cover (x) | B9: =B8/B7 -> 1.3201546 | C9: =C8/C7 -> 2.2001188 | D9: =D8/D7 -> 2.9224673 | E9: =E8/E7 -> 3.56968 | F9: =F8/F7 -> 3.9971982
A10: FCFF / share (AED) | B10: =DCF!B14/Assumptions!B6 -> 0.068441175 | C10: =DCF!C14/Assumptions!B6 -> 0.097518598 | D10: =DCF!D14/Assumptions!B6 -> 0.12963778 | E10: =DCF!E14/Assumptions!B6 -> 0.16639376 | F10: =DCF!F14/Assumptions!B6 -> 0.20098403
A11: BVPS (AED) | B11: =(2165-68+('Income Statement'!E15)-B7)/Assumptions!B6 -> 0.46739106 | C11: =B11+('Income Statement'!F15-C7)/Assumptions!B6 -> 0.5520465 | D11: =C11+('Income Statement'!G15-D7)/Assumptions!B6 -> 0.65648989 | E11: =D11+('Income Statement'!H15-E7)/Assumptions!B6 -> 0.7799677 | F11: =E11+('Income Statement'!I15-F7)/Assumptions!B6 -> 0.9201609
A12: ROCE (NOPAT / opening capital) | B12: 0.154 | C12: 0.167 | D12: 0.174 | E12: 0.176 | F12: 0.174 | G12: engine-computed (compute_deep.py): NOPAT over equity+net-debt capital roll

Sheet Quarterly & Track Record
A1: Five quarters under the microscope + the guidance record
A2: Q3-25 derived as FY residual (flagged); all else official releases
A3: Quarter | B3: Revenue | C3: EBITDA rep. | D3: One-off | E3: EBITDA und. | F3: Margin und. | G3: Net profit | H3: Note
A4: Q1-25 | B4: 1274 | C4: 181 | D4: 0 | E4: =C4-D4 -> 181 | F4: =E4/B4 -> 0.14207221 | G4: 39 | H4: Ramadan-in-March dip; util 65%
A5: Q2-25 | B5: 1403 | C5: 306 | D5: 72 | E5: =C5-D5 -> 234 | F5: =E5/B5 -> 0.16678546 | G5: 148 | H5: Medeor building acquired (+72 one-off); util 68%
A6: Q3-25* | B6: 1420 | C6: 320 | D6: 0 | E6: =C6-D6 -> 320 | F6: =E6/B6 -> 0.22535211 | G6: 175 | H6: derived residual; insurer dispute + UPP start Aug
A7: Q4-25 | B7: 1389 | C7: 282 | D7: 0 | E7: =C7-D7 -> 282 | F7: =E7/B7 -> 0.20302376 | G7: 141 | H7: margin 20.3%; NP +160% YoY
A8: Q1-26 | B8: 1339 | C8: 201 | D8: 0 | E8: =C8-D8 -> 201 | F8: =E8/B8 -> 0.15011202 | G8: 57 | H8: UPP optical drag ~4.6pp; +9.7% ex-UPP
A9: FY25 sum | B9: =SUM(B4:B7) -> 5486 | C9: =SUM(C4:C7) -> 1089 | D9: =SUM(D4:D7) -> 72 | G9: =SUM(G4:G7) -> 503 | H9: ties exactly to FY25 officials: 5,486 / 1,089 / 72 / 503
A11: The guidance record — every promise, against every delivery
A12: Metric | B12: Guided (when) | E12: Delivered | G12: Verdict
A13: FY24 revenue | B13: mid-teens growth (Mar-24) | E13: +10.5% | G13: MISS
A14: FY24 EBITDA margin | B14: 23.5% (Mar-24) | E14: 18.1% reported / 19.1% ex-one-offs | G14: MISS −4.4pp
A15: FY24 BMC revenue | B15: >+30% (Mar-24) | E15: +18.4% | G15: MISS
A16: Mid-term margin | B16: high-20s (Mar-24) | E16: guide cut to "low-20s blended" by Mar-26 | G16: WITHDRAWN
A17: FY25 revenue | B17: mid-teens growth (Mar-25) | E17: +9.5% | G17: MISS
A18: FY25 EBITDA margin | B18: expansion (Mar-25) | E18: 19.8% rep (+1.7pp) / 18.5% underlying | G18: MET (soft target)
A19: Maintenance capex | B19: ≤2.5% of revenue | E19: in line, every year | G19: MET
A20: Net debt / EBITDA | B20: <2.5× | E20: 1.1→1.3→1.8× | G20: MET
A21: KSA revenue | B21: >AED 1bn p.a. mid-term (Mar-24) | E21: physio + day-surgery scale; not disclosed, far below | G21: NOT ON TRACK
