Workbook

Sheet READ FIRST
A1: Testahil · Independent Valuation Study — Educational Analysis · Egypt Aluminum (EGX: EGAL)
A3: This workbook is the companion model to the EGAL valuation study dated 03 Jul 2026. It is educational analysis, not investment advice, not a recommendation, and contains no price target or rating.
A5: HOW TO USE — every input lives on the Assumptions sheet (blue cells). Change any blue cell (e.g. the WACC, terminal growth, normalized LME, the EV/EBITDA multiple, the payout ratio) and the whole model — DCF, relative and normalized lenses, forecast statements, per-share output — reprices. No downstream sheet hard-codes a duplicate of an assumption.
A7: COLOR CODE — blue: hard-coded inputs & judgments · black: formulas · green: links from other sheets.
A9: SOURCES — historical figures are from company disclosure via EGX/Mubasher (FY22/23–FY24/25 results; 9M FY25/26 release) and are commented where hard-coded. Forward inputs are the preparer's judgments.
A11: DISCLOSURE — the preparer may hold, and may in the future take or dispose of, a position in the security discussed. The preparer is not licensed by any securities regulator (including the Egyptian FRA).

Sheet Summary
A1: Summary — every read at a glance (EGAL · 01 Jul 2026 spot EGP 285.88)
A2: Read | B2: Output | C2: vs spot / note
A3: Spot (EGP, 01 Jul 2026) | B3: =Assumptions!$B$3 -> 285.88 | C3: —
A4: Market cap (EGP m) | B4: =Assumptions!$B$3*Assumptions!$B$4 -> 117925.5 | C4: 412.5 m shares
A5: DCF (primary) | B5: =DCF!$B$18 -> 268.46944 | C5: =DCF!$B$18/Assumptions!$B$3-1 -> -0.060901634
A6: Relative multiples | B6: ='Relative & Normalized'!$C$8 -> 234.54545 | C6: ='Relative & Normalized'!$C$8/Assumptions!$B$3-1 -> -0.17956676
A7: Normalized earnings power | B7: ='Relative & Normalized'!$C$13 -> 264.84848 | C7: ='Relative & Normalized'!$C$13/Assumptions!$B$3-1 -> -0.073567634
A8: Replacement cost / EV per tonne | B8: ='Fundamental Valuation'!$B$8 -> 209.58448 | C8: ='Fundamental Valuation'!$B$8/Assumptions!$B$3-1 -> -0.26687951
A9: Weighted central | B9: ='Fundamental Valuation'!$D$16 -> 250.25046 | C9: ='Fundamental Valuation'!$D$16/Assumptions!$B$3-1 -> -0.1246311
A10: Monte Carlo T+60 median (paths from spot) | B10: 326.25054 | C10: 50k paths · seed 42
A11: Monte Carlo T+60 p5–p95 | B11: 232–452 | C11: engine: YZ-HAR · t5 · secular drift
A12: Step 0 CRPS skill vs RW benchmark | B12: 0.15059163 | C12: PASS (> 0)

Sheet Fundamental Valuation
A1: Fundamental valuation — four lenses, weights, and the central value
A2: Replacement-cost / EV-per-tonne lens
A3: Capacity (kt) × US$/t × EGP/USD (EGP m) | B3: =Assumptions!$B$16*1000*Assumptions!$B$15*Assumptions!$B$6/1000000 -> 86416
A4: × (1 − age/technology discount) | B4: =B3*(1-Assumptions!$B$17) -> 73453.6
A5: + Expansion option credit (Trafigura, part) | B5: =Assumptions!$B$18 -> 4000
A6: + Net cash | B6: =Assumptions!$B$5 -> 9000
A7: Equity value | B7: =B4+B5+B6 -> 86453.6
A8: Replacement value per share (EGP) | B8: =B7/Assumptions!$B$4 -> 209.58448
A10: Synthesis
A11: Lens | B11: Weight | C11: Bear | D11: Base | E11: Bull
A12: Discounted cash flow (primary) | B12: =Assumptions!$B$20 -> 0.35 | C12: 205 | D12: =DCF!$B$18 -> 268.46944 | E12: 385
A13: Relative multiples | B13: =Assumptions!$B$21 -> 0.25 | C13: ='Relative & Normalized'!B8 -> 167.27273 | D13: ='Relative & Normalized'!$C$8 -> 234.54545 | E13: ='Relative & Normalized'!D8 -> 312.72727
A14: Normalized earnings power | B14: =Assumptions!$B$22 -> 0.25 | C14: ='Relative & Normalized'!B13 -> 172.72727 | D14: ='Relative & Normalized'!$C$13 -> 264.84848 | E14: ='Relative & Normalized'!D13 -> 376.36364
A15: Replacement cost / EV per tonne | B15: =Assumptions!$B$23 -> 0.15 | C15: 178 | D15: ='Fundamental Valuation'!$B$8 -> 209.58448 | E15: 290
A16: Weighted central | C16: =SUMPRODUCT($B$12:$B$15,C12:C15) -> 183.45 | D16: =SUMPRODUCT($B$12:$B$15,D12:D15) -> 250.25046 | E16: =SUMPRODUCT($B$12:$B$15,E12:E15) -> 350.52273
A17: vs spot | D17: =D16/Assumptions!$B$3-1 -> -0.1246311

Sheet Assumptions
A1: Assumptions — the single blue-cell input layer (all judgments live here)
A2: Market & share data
A3: Spot price (EGP, 01 Jul 2026 close) | B3: 285.88
A4: Shares outstanding (m) | B4: 412.5
A5: Net cash, est. 30 Jun 2026 (EGP m) | B5: 9000
A6: EGP/USD (03 Jul 2026) | B6: 49.1
A7: Valuation core
A8: WACC (nominal EGP) | B8: 0.2
A9: Terminal growth (nominal EGP) | B9: 0.12
A10: Tax rate | B10: 0.225
A11: EV/EBITDA multiple (relative lens) | B11: 6.5
A12: Normalized EBITDA (EGP m, mid-cycle) | B12: 13500
A13: Justified P/E (normalized lens) | B13: 9.5
A14: Mid-cycle net profit (EGP m) | B14: 11500
A15: Replacement cost (US$/t capacity) | B15: 5500
A16: Capacity (kt/yr) | B16: 320
A17: Age/technology discount (replacement lens) | B17: 0.15
A18: Expansion option credit (EGP m) | B18: 4000
A19: Lens weights: DCF / Relative / Normalized / Replacement
A20: w DCF | B20: 0.35
A21: w Relative | B21: 0.25
A22: w Normalized | B22: 0.25
A23: w Replacement | B23: 0.15
A24: Operating drivers (forecast years F26E–F31E)
A25: Driver | B25: F26E | C25: F27E | D25: F28E | E25: F29E | F25: F30E | G25: F31E
A26: Revenue growth | B26: 0.142 | C26: 0.069 | D26: 0.099 | E26: 0.1 | F26: 0.1 | G26: 0.1
A27: Gross margin | B27: 0.351 | C27: 0.3 | D27: 0.302 | E27: 0.305 | F27: 0.305 | G27: 0.305
A28: SG&A % of revenue | B28: 0.047 | C28: 0.049 | D28: 0.049 | E28: 0.049 | F28: 0.049 | G28: 0.049
A29: D&A (EGP m) | B29: 850 | C29: 950 | D29: 1100 | E29: 1250 | F29: 1350 | G29: 1450
A30: Net interest income (EGP m) | B30: 2300 | C30: 2000 | D30: 1800 | E30: 1700 | F30: 1600 | G30: 1500
A31: Capex (EGP m) | B31: 1500 | C31: 2200 | D31: 2600 | E31: 2800 | F31: 3000 | G31: 3200
A32: Change in WC % of Δrevenue | B32: 0.12 | C32: 0.12 | D32: 0.12 | E32: 0.12 | F32: 0.12 | G32: 0.12
A33: Dividend payout (of prior-yr NP) | B33: 0.405 | C33: 0.45 | D33: 0.45 | E33: 0.45 | F33: 0.45 | G33: 0.45
A35: Sources: FY22/23–FY24/25 company results via EGX/Mubasher (24 Aug 2025 release for FY24/25); 9M FY25/26 EGP 10.4bn NP (May 2026); company FY25/26 target EGP 13.71bn and FY26/27 budget EGP 11.1bn; Trafigura partnership releases 6/10 May 2026; net cash anchored to Sep-2025 disclosed EGP 6.9bn rolled forward (derived).

Sheet Earnings Power
A1: Normalized earnings power — the mid-cycle build behind the DCF & normalized lens
A2: Driver | B2: Bear | C2: Base | D2: Bull
A3: LME aluminium (US$/t, mid-cycle) | B3: 2300 | C3: 2600 | D3: 2850
A4: Realized premium / product mix (%) | B4: 1.1 | C4: 1.14 | D4: 1.17
A5: Sales volume (kt) | B5: 258 | C5: 278 | D5: 292
A6: EGP/USD | B6: 47 | C6: 50 | D6: 53
A7: Revenue (EGP m) | B7: =B3*B4*B5*B6/1000 -> 30678.78 | C7: =C3*C4*C5*C6/1000 -> 41199.6 | D7: =D3*D4*D5*D6/1000 -> 51604.722
A8: EBITDA margin | B8: 0.27 | C8: 0.33 | D8: 0.36
A9: Normalized EBITDA (EGP m) | B9: =B7*B8 -> 8283.2706 | C9: =C7*C8 -> 13595.868 | D9: =D7*D8 -> 18577.7
A10: D&A (EGP m) | B10: 1000 | C10: 1000 | D10: 1000
A11: Tax rate | B11: 0.225 | C11: 0.225 | D11: 0.225
A12: Mid-cycle net profit ≈ (EBITDA−D&A)×(1−t)+int (EGP m) | B12: =(B9-B10)*(1-B11)+B13*(1-B11) -> 6807.0347 | C12: =(C9-C10)*(1-C11)+C13*(1-C11) -> 11311.798 | D12: =(D9-D10)*(1-D11)+D13*(1-D11) -> 15405.217
A13: Net interest income (EGP m) | B13: 1500 | C13: 2000 | D13: 2300
A14: Base build lands EBITDA ≈ 13.6bn and NP ≈ 11.3bn — the Assumptions inputs (13,500 / 11,500) sit on this build; reconcile after edits.

Sheet Segments
A1: Segments — export vs local, and the FY24/25 revenue mix
A2: Segment | B2: FY23/24 | C2: FY24/25 | D2: Share FY24/25 | E2: Note
A3: Export sales (EGP m) | B3: 19700 | C3: 26900 | D3: =C3/$C$5 -> 0.62293032 | E3: LME-linked, USD-denominated (~60% EU-bound)
A4: Local sales (EGP m) | B4: 13115 | C4: 16283 | D4: =C4/$C$5 -> 0.37706968 | E4: Domestic ingot/billet/rod demand
A5: Total revenue | B5: ='Income Statement'!C3 -> 32815 | C5: ='Income Statement'!D3 -> 43183 | E5: links to Income Statement
A6: Production (kt, est.) | B6: 265 | C6: 272 | E6: vs ~320 kt nameplate
A7: Implied realization (EGP k/t) | B7: =B5/B6 -> 123.83019 | C7: =C5/C6 -> 158.76103 | E7: Revenue / volume

Sheet Relative & Normalized
A1: Relative multiples & normalized earnings — two cross-check lenses
A2: Relative lens | B2: Bear | C2: Base | D2: Bull
A3: EBITDA basis (EGP m) | B3: 12000 | C3: =Assumptions!$B$12 -> 13500 | D3: 15000
A4: EV/EBITDA multiple | B4: 5 | C4: =Assumptions!$B$11 -> 6.5 | D4: 8
A5: Enterprise value | B5: =B3*B4 -> 60000 | C5: =C3*C4 -> 87750 | D5: =D3*D4 -> 120000
A6: + Net cash | B6: =Assumptions!$B$5 -> 9000 | C6: =Assumptions!$B$5 -> 9000 | D6: =Assumptions!$B$5 -> 9000
A7: Equity value | B7: =B5+B6 -> 69000 | C7: =C5+C6 -> 96750 | D7: =D5+D6 -> 129000
A8: Value per share (EGP) | B8: =B7/Assumptions!$B$4 -> 167.27273 | C8: =C7/Assumptions!$B$4 -> 234.54545 | D8: =D7/Assumptions!$B$4 -> 312.72727
A10: Normalized-earnings lens | B10: Bear | C10: Base | D10: Bull
A11: Mid-cycle net profit (EGP m) | B11: 9500 | C11: =Assumptions!$B$14 -> 11500 | D11: 13500
A12: Justified P/E | B12: 7.5 | C12: =Assumptions!$B$13 -> 9.5 | D12: 11.5
A13: Value per share (EGP) | B13: =B11*B12/Assumptions!$B$4 -> 172.72727 | C13: =C11*C12/Assumptions!$B$4 -> 264.84848 | D13: =D11*D12/Assumptions!$B$4 -> 376.36364

Sheet DCF
A1: Discounted cash flow — FCFF, primary lens (explicit F27E–F31E + terminal)
A2: EGP m | B2: F27E | C2: F28E | D2: F29E | E2: F30E | F2: F31E
A3: EBIT | B3: ='Income Statement'!F7 -> 13232.148 | C3: ='Income Statement'!G7 -> 14658.004 | D3: ='Income Statement'!H7 -> 16314.996 | E3: ='Income Statement'!I7 -> 17946.495 | F3: ='Income Statement'!J7 -> 19741.145
A4: NOPAT = EBIT × (1 − tax) | B4: =B3*(1-Assumptions!$B$10) -> 10254.914 | C4: =C3*(1-Assumptions!$B$10) -> 11359.953 | D4: =D3*(1-Assumptions!$B$10) -> 12644.122 | E4: =E3*(1-Assumptions!$B$10) -> 13908.534 | F4: =F3*(1-Assumptions!$B$10) -> 15299.387
A5: + D&A | B5: ='Income Statement'!F8 -> 950 | C5: ='Income Statement'!G8 -> 1100 | D5: ='Income Statement'!H8 -> 1250 | E5: ='Income Statement'!I8 -> 1350 | F5: ='Income Statement'!J8 -> 1450
A6: − Capex | B6: =-Assumptions!C$31 -> -2200 | C6: =-Assumptions!D$31 -> -2600 | D6: =-Assumptions!E$31 -> -2800 | E6: =-Assumptions!F$31 -> -3000 | F6: =-Assumptions!G$31 -> -3200
A7: − Change in WC | B7: ='Cash Flow'!F5 -> -408.32808 | C7: ='Cash Flow'!G5 -> -626.28651 | D7: ='Cash Flow'!H5 -> -695.24129 | E7: ='Cash Flow'!I5 -> -764.76542 | F7: ='Cash Flow'!J5 -> -841.24196
A8: FCFF | B8: =SUM(B4:B7) -> 8596.5864 | C8: =SUM(C4:C7) -> 9233.6665 | D8: =SUM(D4:D7) -> 10398.88 | E8: =SUM(E4:E7) -> 11493.768 | F8: =SUM(F4:F7) -> 12708.145
A9: Discount factor | B9: =1/(1+Assumptions!$B$8)^1 -> 0.83333333 | C9: =1/(1+Assumptions!$B$8)^2 -> 0.69444444 | D9: =1/(1+Assumptions!$B$8)^3 -> 0.5787037 | E9: =1/(1+Assumptions!$B$8)^4 -> 0.48225309 | F9: =1/(1+Assumptions!$B$8)^5 -> 0.40187757
A10: PV of FCFF | B10: =B8*B9 -> 7163.822 | C10: =C8*C9 -> 6412.2684 | D10: =D8*D9 -> 6017.8706 | E10: =E8*E9 -> 5542.9053 | F10: =F8*F9 -> 5107.1185
A12: Σ PV explicit FCFF | B12: =SUM(B10:F10) -> 30243.985
A13: Terminal value (Gordon, on F31E FCFF) | B13: =F8*(1+Assumptions!$B$9)/(Assumptions!$B$8-Assumptions!$B$9) -> 177914.03
A14: PV of terminal value | B14: =B13*F9 -> 71499.66
A15: Enterprise value | B15: =B12+B14 -> 101743.64
A16: + Net cash | B16: =Assumptions!$B$5 -> 9000
A17: Equity value | B17: =B15+B16 -> 110743.64
A18: DCF value per share (EGP) | B18: =B17/Assumptions!$B$4 -> 268.46944
A19: Upside / (downside) vs spot | B19: =B18/Assumptions!$B$3-1 -> -0.060901634

Sheet Income Statement
A1: Income statement — 3yr historical (reported/derived) + FY25/26E bridge + 5yr forecast
A2: EGP m | B2: FY22/23 | C2: FY23/24 | D2: FY24/25 | E2: F26E | F2: F27E | G2: F28E | H2: F29E | I2: F30E | J2: F31E
A3: Revenue | B3: 22045 | C3: 32815 | D3: 43183 | E3: =D3*(1+Assumptions!B$26) -> 49314.986 | F3: =E3*(1+Assumptions!C$26) -> 52717.72 | G3: =F3*(1+Assumptions!D$26) -> 57936.774 | H3: =G3*(1+Assumptions!E$26) -> 63730.452 | I3: =H3*(1+Assumptions!F$26) -> 70103.497 | J3: =I3*(1+Assumptions!G$26) -> 77113.847
A4: COGS | B4: -16200 | C4: -22600 | D4: -29950 | E4: =-E3*(1-Assumptions!B$27) -> -32005.426 | F4: =-F3*(1-Assumptions!C$27) -> -36902.404 | G4: =-G3*(1-Assumptions!D$27) -> -40439.868 | H4: =-H3*(1-Assumptions!E$27) -> -44292.664 | I4: =-I3*(1-Assumptions!F$27) -> -48721.93 | J4: =-J3*(1-Assumptions!G$27) -> -53594.123
A5: Gross profit | B5: 5845 | C5: 10215 | D5: 13233 | E5: =E3+E4 -> 17309.56 | F5: =F3+F4 -> 15815.316 | G5: =G3+G4 -> 17496.906 | H5: =H3+H4 -> 19437.788 | I5: =I3+I4 -> 21381.567 | J5: =J3+J4 -> 23519.723
A6: SG&A & other opex | B6: -1000 | C6: -1350 | D6: -2073 | E6: =-E3*Assumptions!B$28 -> -2317.8043 | F6: =-F3*Assumptions!C$28 -> -2583.1683 | G6: =-G3*Assumptions!D$28 -> -2838.9019 | H6: =-H3*Assumptions!E$28 -> -3122.7921 | I6: =-I3*Assumptions!F$28 -> -3435.0713 | J6: =-J3*Assumptions!G$28 -> -3778.5785
A7: EBIT | B7: 4845 | C7: 8865 | D7: 11160 | E7: =E5+E6 -> 14991.756 | F7: =F5+F6 -> 13232.148 | G7: =G5+G6 -> 14658.004 | H7: =H5+H6 -> 16314.996 | I7: =I5+I6 -> 17946.495 | J7: =J5+J6 -> 19741.145
A8: D&A (memo, in COGS/opex) | B8: 650 | C8: 700 | D8: 780 | E8: =Assumptions!B$29 -> 850 | F8: =Assumptions!C$29 -> 950 | G8: =Assumptions!D$29 -> 1100 | H8: =Assumptions!E$29 -> 1250 | I8: =Assumptions!F$29 -> 1350 | J8: =Assumptions!G$29 -> 1450
A9: EBITDA | B9: 5495 | C9: 9565 | D9: 11940 | E9: =E7+E8 -> 15841.756 | F9: =F7+F8 -> 14182.148 | G9: =G7+G8 -> 15758.004 | H9: =H7+H8 -> 17564.996 | I9: =I7+I8 -> 19296.495 | J9: =J7+J8 -> 21191.145
A10: Net interest income | B10: -15 | C10: 1000 | D10: 2000 | E10: =Assumptions!B$30 -> 2300 | F10: =Assumptions!C$30 -> 2000 | G10: =Assumptions!D$30 -> 1800 | H10: =Assumptions!E$30 -> 1700 | I10: =Assumptions!F$30 -> 1600 | J10: =Assumptions!G$30 -> 1500
A11: FX & one-off items | B11: 0 | C11: 2165 | D11: 0 | E11: =0 -> 0 | F11: =0 -> 0 | G11: =0 -> 0 | H11: =0 -> 0 | I11: =0 -> 0 | J11: =0 -> 0
A12: Profit before tax | B12: 4830 | C12: 12030 | D12: 13160 | E12: =E7+E10+E11 -> 17291.756 | F12: =F7+F10+F11 -> 15232.148 | G12: =G7+G10+G11 -> 16458.004 | H12: =H7+H10+H11 -> 18014.996 | I12: =I7+I10+I11 -> 19546.495 | J12: =J7+J10+J11 -> 21241.145
A13: Income tax | B13: -1138 | C13: -2706 | D13: -2980 | E13: =-E12*Assumptions!$B$10 -> -3890.645 | F13: =-F12*Assumptions!$B$10 -> -3427.2332 | G13: =-G12*Assumptions!$B$10 -> -3703.0509 | H13: =-H12*Assumptions!$B$10 -> -4053.374 | I13: =-I12*Assumptions!$B$10 -> -4397.9614 | J13: =-J12*Assumptions!$B$10 -> -4779.2576
A14: Net profit after tax | B14: 3692 | C14: 9324 | D14: 10180 | E14: =E12+E13 -> 13401.111 | F14: =F12+F13 -> 11804.914 | G14: =G12+G13 -> 12754.953 | H14: =H12+H13 -> 13961.622 | I14: =I12+I13 -> 15148.534 | J14: =J12+J13 -> 16461.887
A15: EPS (EGP) | B15: 8.95 | C15: 22.6 | D15: 24.68 | E15: =E14/Assumptions!$B$4 -> 32.487541 | F15: =F14/Assumptions!$B$4 -> 28.617975 | G15: =G14/Assumptions!$B$4 -> 30.921098 | H15: =H14/Assumptions!$B$4 -> 33.846355 | I15: =I14/Assumptions!$B$4 -> 36.723718 | J15: =J14/Assumptions!$B$4 -> 39.907605
A17: Sources: FY22/23–FY24/25 reported (EGX/Mubasher, FY24/25 release 24 Aug 2025); COGS/SG&A split, D&A and interest are derived from disclosed EBIT/tax anchors and flagged as estimates. FY25/26E bridges 9M actual EGP 10.4bn NP to ~EGP 13.4bn.

Sheet Balance Sheet
A1: Balance sheet — 3yr historical (anchored/derived) + forecast
A2: EGP m | B2: FY22/23 | C2: FY23/24 | D2: FY24/25 | E2: F26E | F2: F27E | G2: F28E | H2: F29E | I2: F30E | J2: F31E
A3: Cash & ST investments | B3: 3050 | C3: 6320 | D3: 9600 | E3: ='Cash Flow'!E13 -> 17492.372 | F3: ='Cash Flow'!F13 -> 21608.459 | G3: ='Cash Flow'!G13 -> 26924.914 | H3: ='Cash Flow'!H13 -> 32901.565 | I3: ='Cash Flow'!I13 -> 39352.604 | J3: ='Cash Flow'!J13 -> 46406.409
A4: Receivables | B4: 2100 | C4: 3050 | D4: 3900 | E4: ='Income Statement'!E3*3900/43183 -> 4453.8 | F4: ='Income Statement'!F3*3900/43183 -> 4761.1122 | G4: ='Income Statement'!G3*3900/43183 -> 5232.4623 | H4: ='Income Statement'!H3*3900/43183 -> 5755.7085 | I4: ='Income Statement'!I3*3900/43183 -> 6331.2794 | J4: ='Income Statement'!J3*3900/43183 -> 6964.4073
A5: Inventories | B5: 5300 | C5: 7200 | D5: 8600 | E5: =-'Income Statement'!E4*8600/29950 -> 9190.2058 | F5: =-'Income Statement'!F4*8600/29950 -> 10596.35 | G5: =-'Income Statement'!G4*8600/29950 -> 11612.116 | H5: =-'Income Statement'!H4*8600/29950 -> 12718.428 | I5: =-'Income Statement'!I4*8600/29950 -> 13990.27 | J5: =-'Income Statement'!J4*8600/29950 -> 15389.298
A6: PP&E, net | B6: 6200 | C6: 6650 | D6: 7200 | E6: =D6+Assumptions!B$31-'Income Statement'!E8 -> 7850 | F6: =E6+Assumptions!C$31-'Income Statement'!F8 -> 9100 | G6: =F6+Assumptions!D$31-'Income Statement'!G8 -> 10600 | H6: =G6+Assumptions!E$31-'Income Statement'!H8 -> 12150 | I6: =H6+Assumptions!F$31-'Income Statement'!I8 -> 13800 | J6: =I6+Assumptions!G$31-'Income Statement'!J8 -> 15550
A7: Other assets | B7: 1450 | C7: 1600 | D7: 1700 | E7: =D7 -> 1700 | F7: =E7 -> 1700 | G7: =F7 -> 1700 | H7: =G7 -> 1700 | I7: =H7 -> 1700 | J7: =I7 -> 1700
A8: Total assets | B8: 18100 | C8: 24820 | D8: 31000 | E8: =SUM(E3:E7) -> 40686.378 | F8: =SUM(F3:F7) -> 47765.921 | G8: =SUM(G3:G7) -> 56069.492 | H8: =SUM(H3:H7) -> 65225.702 | I8: =SUM(I3:I7) -> 75174.154 | J8: =SUM(J3:J7) -> 86010.114
A9: Payables & accruals | B9: 3300 | C9: 3900 | D9: 4200 | E9: =-'Income Statement'!E4*4200/29950 -> 4488.24 | F9: =-'Income Statement'!F4*4200/29950 -> 5174.9615 | G9: =-'Income Statement'!G4*4200/29950 -> 5671.0333 | H9: =-'Income Statement'!H4*4200/29950 -> 6211.3252 | I9: =-'Income Statement'!I4*4200/29950 -> 6832.4577 | J9: =-'Income Statement'!J4*4200/29950 -> 7515.7034
A10: Debt | B10: 750 | C10: 680 | D10: 600 | E10: =D10 -> 600 | F10: =E10 -> 600 | G10: =F10 -> 600 | H10: =G10 -> 600 | I10: =H10 -> 600 | J10: =I10 -> 600
A11: Shareholders equity | B11: 10400 | C11: 18486 | D11: 25366 | E11: =D11+'Income Statement'!E14+'Cash Flow'!E10 -> 34644.211 | F11: =E11+'Income Statement'!F14+'Cash Flow'!F10 -> 40418.625 | G11: =F11+'Income Statement'!G14+'Cash Flow'!G10 -> 47861.367 | H11: =G11+'Income Statement'!H14+'Cash Flow'!H10 -> 56083.26 | I11: =H11+'Income Statement'!I14+'Cash Flow'!I10 -> 64949.064 | J11: =I11+'Income Statement'!J14+'Cash Flow'!J10 -> 74594.111
A12: Provisions & other liabilities | B12: 3650 | C12: 1754 | D12: 834 | E12: =E8-E9-E10-E11 -> 953.92742 | F12: =F8-F9-F10-F11 -> 1572.334 | G12: =G8-G9-G10-G11 -> 1937.0919 | H12: =H8-H9-H10-H11 -> 2331.1169 | I12: =I8-I9-I10-I11 -> 2792.6326 | J12: =J8-J9-J10-J11 -> 3300.2998
A13: Total liabilities & equity | B13: 18100 | C13: 24820 | D13: 31000 | E13: =E9+E10+E12+E11 -> 40686.378 | F13: =F9+F10+F12+F11 -> 47765.921 | G13: =G9+G10+G12+G11 -> 56069.492 | H13: =H9+H10+H12+H11 -> 65225.702 | I13: =I9+I10+I12+I11 -> 75174.154 | J13: =J9+J10+J12+J11 -> 86010.114
A14: Check (TA − TL&E) | B14: 0 | C14: 0 | D14: 0 | E14: =E8-E13 -> 0 | F14: =F8-F13 -> 0 | G14: =G8-G13 -> 0 | H14: =H8-H13 -> 0 | I14: =I8-I13 -> 0 | J14: =J8-J13 -> 0
A15: Net cash | B15: 2300 | C15: 5640 | D15: 9000 | E15: =E3-E10 -> 16892.372 | F15: =F3-F10 -> 21008.459 | G15: =G3-G10 -> 26324.914 | H15: =H3-H10 -> 32301.565 | I15: =I3-I10 -> 38752.604 | J15: =J3-J10 -> 45806.409
A16: BVPS (EGP) | B16: 25.2 | C16: 44.8 | D16: 61.5 | E16: =E11/Assumptions!$B$4 -> 83.985965 | F16: =F11/Assumptions!$B$4 -> 97.984546 | G16: =G11/Assumptions!$B$4 -> 116.02756 | H16: =H11/Assumptions!$B$4 -> 135.95942 | I16: =I11/Assumptions!$B$4 -> 157.45228 | J16: =J11/Assumptions!$B$4 -> 180.83421
A18: Historical columns are anchored to disclosed items (cash/net cash, capital EGP 1,650m = 412.5m shares) with remaining lines derived to reconcile; forecast provisions line is the balancing item. Flagged as reconstruction, not audited statements.

Sheet Cash Flow
A1: Cash flow — derived historical + forecast
A2: EGP m | B2: FY22/23 | C2: FY23/24 | D2: FY24/25 | E2: F26E | F2: F27E | G2: F28E | H2: F29E | I2: F30E | J2: F31E
A3: Net profit | B3: 3692 | C3: 9324 | D3: 10180 | E3: ='Income Statement'!E14 -> 13401.111 | F3: ='Income Statement'!F14 -> 11804.914 | G3: ='Income Statement'!G14 -> 12754.953 | H3: ='Income Statement'!H14 -> 13961.622 | I3: ='Income Statement'!I14 -> 15148.534 | J3: ='Income Statement'!J14 -> 16461.887
A4: D&A | B4: 650 | C4: 700 | D4: 780 | E4: ='Income Statement'!E8 -> 850 | F4: ='Income Statement'!F8 -> 950 | G4: ='Income Statement'!G8 -> 1100 | H4: ='Income Statement'!H8 -> 1250 | I4: ='Income Statement'!I8 -> 1350 | J4: ='Income Statement'!J8 -> 1450
A5: Change in working capital | B5: -900 | C5: -1600 | D5: -1450 | E5: =-('Income Statement'!E3-'Income Statement'!D3)*Assumptions!B$32 -> -735.83832 | F5: =-('Income Statement'!F3-'Income Statement'!E3)*Assumptions!C$32 -> -408.32808 | G5: =-('Income Statement'!G3-'Income Statement'!F3)*Assumptions!D$32 -> -626.28651 | H5: =-('Income Statement'!H3-'Income Statement'!G3)*Assumptions!E$32 -> -695.24129 | I5: =-('Income Statement'!I3-'Income Statement'!H3)*Assumptions!F$32 -> -764.76542 | J5: =-('Income Statement'!J3-'Income Statement'!I3)*Assumptions!G$32 -> -841.24196
A6: Operating cash flow | B6: 3442 | C6: 8424 | D6: 9510 | E6: =SUM(E3:E5) -> 13515.272 | F6: =SUM(F3:F5) -> 12346.586 | G6: =SUM(G3:G5) -> 13228.667 | H6: =SUM(H3:H5) -> 14516.38 | I6: =SUM(I3:I5) -> 15733.768 | J6: =SUM(J3:J5) -> 17070.645
A7: Capex | B7: -500 | C7: -600 | D7: -900 | E7: =-Assumptions!B$31 -> -1500 | F7: =-Assumptions!C$31 -> -2200 | G7: =-Assumptions!D$31 -> -2600 | H7: =-Assumptions!E$31 -> -2800 | I7: =-Assumptions!F$31 -> -3000 | J7: =-Assumptions!G$31 -> -3200
A8: Free cash flow | B8: 2942 | C8: 7824 | D8: 8610 | E8: =E6+E7 -> 12015.272 | F8: =F6+F7 -> 10146.586 | G8: =G6+G7 -> 10628.667 | H8: =H6+H7 -> 11716.38 | I8: =I6+I7 -> 12733.768 | J8: =J6+J7 -> 13870.645
A9: Other / FX & adjustments (plug) | B9: -1200 | C9: -3316 | D9: -2030 | E9: =0 -> 0 | F9: =0 -> 0 | G9: =0 -> 0 | H9: =0 -> 0 | I9: =0 -> 0 | J9: =0 -> 0
A10: Dividends paid | B10: -1030 | C10: -1238 | D10: -3300 | E10: =-'Income Statement'!D14*Assumptions!B$33 -> -4122.9 | F10: =-'Income Statement'!E14*Assumptions!C$33 -> -6030.4998 | G10: =-'Income Statement'!F14*Assumptions!D$33 -> -5312.2115 | H10: =-'Income Statement'!G14*Assumptions!E$33 -> -5739.7289 | I10: =-'Income Statement'!H14*Assumptions!F$33 -> -6282.7297 | J10: =-'Income Statement'!I14*Assumptions!G$33 -> -6816.8402
A11: Net change in cash | B11: 712 | C11: 3270 | D11: 3280 | E11: =E8+E9+E10 -> 7892.3724 | F11: =F8+F9+F10 -> 4116.0866 | G11: =G8+G9+G10 -> 5316.455 | H11: =H8+H9+H10 -> 5976.6515 | I11: =I8+I9+I10 -> 6451.0386 | J11: =J8+J9+J10 -> 7053.805
A12: Opening cash | B12: 2338 | C12: 3050 | D12: 6320 | E12: =D13 -> 9600 | F12: =E13 -> 17492.372 | G12: =F13 -> 21608.459 | H12: =G13 -> 26924.914 | I12: =H13 -> 32901.565 | J12: =I13 -> 39352.604
A13: Closing cash | B13: 3050 | C13: 6320 | D13: 9600 | E13: =E12+E11 -> 17492.372 | F13: =F12+F11 -> 21608.459 | G13: =G12+G11 -> 26924.914 | H13: =H12+H11 -> 32901.565 | I13: =I12+I11 -> 39352.604 | J13: =J12+J11 -> 46406.409
A15: Historical CF is derived (plug reconciles to cash anchors); dividends: DPS 2.50 (FY23), 3.00 (FY24), 8.00 (FY25 pay), FY24/25 distribution of EGP 10.00/sh assumed paid in F26E.

Sheet Summary Financials
A1: Summary financials — every cell links to the statement sheets
A2: EGP m | B2: FY22/23 | C2: FY23/24 | D2: FY24/25 | E2: F26E | F2: F27E | G2: F28E | H2: F29E | I2: F30E | J2: F31E
A3: Revenue | B3: ='Income Statement'!B3 -> 22045 | C3: ='Income Statement'!C3 -> 32815 | D3: ='Income Statement'!D3 -> 43183 | E3: ='Income Statement'!E3 -> 49314.986 | F3: ='Income Statement'!F3 -> 52717.72 | G3: ='Income Statement'!G3 -> 57936.774 | H3: ='Income Statement'!H3 -> 63730.452 | I3: ='Income Statement'!I3 -> 70103.497 | J3: ='Income Statement'!J3 -> 77113.847
A4: EBITDA | B4: ='Income Statement'!B9 -> 5495 | C4: ='Income Statement'!C9 -> 9565 | D4: ='Income Statement'!D9 -> 11940 | E4: ='Income Statement'!E9 -> 15841.756 | F4: ='Income Statement'!F9 -> 14182.148 | G4: ='Income Statement'!G9 -> 15758.004 | H4: ='Income Statement'!H9 -> 17564.996 | I4: ='Income Statement'!I9 -> 19296.495 | J4: ='Income Statement'!J9 -> 21191.145
A5: EBIT | B5: ='Income Statement'!B7 -> 4845 | C5: ='Income Statement'!C7 -> 8865 | D5: ='Income Statement'!D7 -> 11160 | E5: ='Income Statement'!E7 -> 14991.756 | F5: ='Income Statement'!F7 -> 13232.148 | G5: ='Income Statement'!G7 -> 14658.004 | H5: ='Income Statement'!H7 -> 16314.996 | I5: ='Income Statement'!I7 -> 17946.495 | J5: ='Income Statement'!J7 -> 19741.145
A6: Net profit | B6: ='Income Statement'!B14 -> 3692 | C6: ='Income Statement'!C14 -> 9324 | D6: ='Income Statement'!D14 -> 10180 | E6: ='Income Statement'!E14 -> 13401.111 | F6: ='Income Statement'!F14 -> 11804.914 | G6: ='Income Statement'!G14 -> 12754.953 | H6: ='Income Statement'!H14 -> 13961.622 | I6: ='Income Statement'!I14 -> 15148.534 | J6: ='Income Statement'!J14 -> 16461.887
A7: EPS (EGP) | B7: ='Income Statement'!B15 -> 8.95 | C7: ='Income Statement'!C15 -> 22.6 | D7: ='Income Statement'!D15 -> 24.68 | E7: ='Income Statement'!E15 -> 32.487541 | F7: ='Income Statement'!F15 -> 28.617975 | G7: ='Income Statement'!G15 -> 30.921098 | H7: ='Income Statement'!H15 -> 33.846355 | I7: ='Income Statement'!I15 -> 36.723718 | J7: ='Income Statement'!J15 -> 39.907605
A8: Operating cash flow | B8: ='Cash Flow'!B6 -> 3442 | C8: ='Cash Flow'!C6 -> 8424 | D8: ='Cash Flow'!D6 -> 9510 | E8: ='Cash Flow'!E6 -> 13515.272 | F8: ='Cash Flow'!F6 -> 12346.586 | G8: ='Cash Flow'!G6 -> 13228.667 | H8: ='Cash Flow'!H6 -> 14516.38 | I8: ='Cash Flow'!I6 -> 15733.768 | J8: ='Cash Flow'!J6 -> 17070.645
A9: Free cash flow | B9: ='Cash Flow'!B8 -> 2942 | C9: ='Cash Flow'!C8 -> 7824 | D9: ='Cash Flow'!D8 -> 8610 | E9: ='Cash Flow'!E8 -> 12015.272 | F9: ='Cash Flow'!F8 -> 10146.586 | G9: ='Cash Flow'!G8 -> 10628.667 | H9: ='Cash Flow'!H8 -> 11716.38 | I9: ='Cash Flow'!I8 -> 12733.768 | J9: ='Cash Flow'!J8 -> 13870.645
A10: Net cash | B10: ='Balance Sheet'!B15 -> 2300 | C10: ='Balance Sheet'!C15 -> 5640 | D10: ='Balance Sheet'!D15 -> 9000 | E10: ='Balance Sheet'!E15 -> 16892.372 | F10: ='Balance Sheet'!F15 -> 21008.459 | G10: ='Balance Sheet'!G15 -> 26324.914 | H10: ='Balance Sheet'!H15 -> 32301.565 | I10: ='Balance Sheet'!I15 -> 38752.604 | J10: ='Balance Sheet'!J15 -> 45806.409
A11: Shareholders equity | B11: ='Balance Sheet'!B11 -> 10400 | C11: ='Balance Sheet'!C11 -> 18486 | D11: ='Balance Sheet'!D11 -> 25366 | E11: ='Balance Sheet'!E11 -> 34644.211 | F11: ='Balance Sheet'!F11 -> 40418.625 | G11: ='Balance Sheet'!G11 -> 47861.367 | H11: ='Balance Sheet'!H11 -> 56083.26 | I11: ='Balance Sheet'!I11 -> 64949.064 | J11: ='Balance Sheet'!J11 -> 74594.111
A12: BVPS (EGP) | B12: ='Balance Sheet'!B16 -> 25.2 | C12: ='Balance Sheet'!C16 -> 44.8 | D12: ='Balance Sheet'!D16 -> 61.5 | E12: ='Balance Sheet'!E16 -> 83.985965 | F12: ='Balance Sheet'!F16 -> 97.984546 | G12: ='Balance Sheet'!G16 -> 116.02756 | H12: ='Balance Sheet'!H16 -> 135.95942 | I12: ='Balance Sheet'!I16 -> 157.45228 | J12: ='Balance Sheet'!J16 -> 180.83421

Sheet Monte Carlo
A1: Monte Carlo — YZ-HAR width · Student-t(5) shape · secular drift · 16 factors · 50,000 paths · seed 42
A2: Percentile map (EGP)
A3: Horizon | B3: p5 | C3: p25 | D3: p50 | E3: p75 | F3: p95
A4: T+20 sessions | B4: 244.50161 | C4: 277.80009 | D4: 298.80022 | E4: 321.18444 | F4: 361.95755
A5: T+60 sessions | B5: 231.54102 | C5: 287.48603 | D5: 326.25054 | E5: 369.4468 | F5: 451.69421
A7: Engine: diffusion σ_daily = HAR forecast 2.52% (ann. ≈ 40.0%); drift = secular 0.242%/day (Step-0 validated) + net factor +0.5%; simulated path vol ≈ 44%.
A9: Level-touch ladder (probability of touching by horizon)
A10: Level (EGP) | B10: T+20 touch | C10: T+60 touch
A11: 340 | B11: 0.17268 | C11: 0.56842
A12: 320 | B12: 0.37326 | C12: 0.73502
A13: 300 | B13: 0.6911 | C13: 0.88896
A14: 270 | B14: 0.37468 | C14: 0.49898
A15: 250 | B15: 0.12234 | C15: 0.2418
A16: 230 | B16: 0.03802 | C16: 0.11312
A17: 210 | B17: 0.01186 | C17: 0.05212
A19: Probability zones at T+60
A20: < 220 (deep downside) | B20: 0.03354
A21: 220–260 (lower band) | B21: 0.08852
A22: 260–310 (around spot) | B22: 0.26906
A23: 310–360 (upper band) | B23: 0.31394
A24: > 360 (strong upside) | B24: 0.29494

Sheet Sensitivity
A1: DCF sensitivity — value per share across WACC × terminal growth (live formulas)
A2: WACC \ g | B2: 0.11 | C2: 0.115 | D2: 0.12 | E2: 0.125 | F2: 0.13
A3: 0.185 | B3: =(SUMPRODUCT(DCF!$B$8:$F$8,1/(1+$A3)^{1,2,3,4,5})+DCF!$F$8*(1+B$2)/($A3-B$2)/(1+$A3)^5+Assumptions!$B$5)/Assumptions!$B$4 -> 292.94279 | C3: =(SUMPRODUCT(DCF!$B$8:$F$8,1/(1+$A3)^{1,2,3,4,5})+DCF!$F$8*(1+C$2)/($A3-C$2)/(1+$A3)^5+Assumptions!$B$5)/Assumptions!$B$4 -> 307.82254 | D3: =(SUMPRODUCT(DCF!$B$8:$F$8,1/(1+$A3)^{1,2,3,4,5})+DCF!$F$8*(1+D$2)/($A3-D$2)/(1+$A3)^5+Assumptions!$B$5)/Assumptions!$B$4 -> 324.99148 | E3: =(SUMPRODUCT(DCF!$B$8:$F$8,1/(1+$A3)^{1,2,3,4,5})+DCF!$F$8*(1+E$2)/($A3-E$2)/(1+$A3)^5+Assumptions!$B$5)/Assumptions!$B$4 -> 345.0219 | F3: =(SUMPRODUCT(DCF!$B$8:$F$8,1/(1+$A3)^{1,2,3,4,5})+DCF!$F$8*(1+F$2)/($A3-F$2)/(1+$A3)^5+Assumptions!$B$5)/Assumptions!$B$4 -> 368.69423
A4: 0.2 | B4: =(SUMPRODUCT(DCF!$B$8:$F$8,1/(1+$A4)^{1,2,3,4,5})+DCF!$F$8*(1+B$2)/($A4-B$2)/(1+$A4)^5+Assumptions!$B$5)/Assumptions!$B$4 -> 247.83462 | C4: =(SUMPRODUCT(DCF!$B$8:$F$8,1/(1+$A4)^{1,2,3,4,5})+DCF!$F$8*(1+C$2)/($A4-C$2)/(1+$A4)^5+Assumptions!$B$5)/Assumptions!$B$4 -> 257.54512 | D4: =(SUMPRODUCT(DCF!$B$8:$F$8,1/(1+$A4)^{1,2,3,4,5})+DCF!$F$8*(1+D$2)/($A4-D$2)/(1+$A4)^5+Assumptions!$B$5)/Assumptions!$B$4 -> 268.46944 | E4: =(SUMPRODUCT(DCF!$B$8:$F$8,1/(1+$A4)^{1,2,3,4,5})+DCF!$F$8*(1+E$2)/($A4-E$2)/(1+$A4)^5+Assumptions!$B$5)/Assumptions!$B$4 -> 280.85033 | F4: =(SUMPRODUCT(DCF!$B$8:$F$8,1/(1+$A4)^{1,2,3,4,5})+DCF!$F$8*(1+F$2)/($A4-F$2)/(1+$A4)^5+Assumptions!$B$5)/Assumptions!$B$4 -> 294.99993
A5: 0.215 | B5: =(SUMPRODUCT(DCF!$B$8:$F$8,1/(1+$A5)^{1,2,3,4,5})+DCF!$F$8*(1+B$2)/($A5-B$2)/(1+$A5)^5+Assumptions!$B$5)/Assumptions!$B$4 -> 215.61192 | C5: =(SUMPRODUCT(DCF!$B$8:$F$8,1/(1+$A5)^{1,2,3,4,5})+DCF!$F$8*(1+C$2)/($A5-C$2)/(1+$A5)^5+Assumptions!$B$5)/Assumptions!$B$4 -> 222.34376 | D5: =(SUMPRODUCT(DCF!$B$8:$F$8,1/(1+$A5)^{1,2,3,4,5})+DCF!$F$8*(1+D$2)/($A5-D$2)/(1+$A5)^5+Assumptions!$B$5)/Assumptions!$B$4 -> 229.78421 | E5: =(SUMPRODUCT(DCF!$B$8:$F$8,1/(1+$A5)^{1,2,3,4,5})+DCF!$F$8*(1+E$2)/($A5-E$2)/(1+$A5)^5+Assumptions!$B$5)/Assumptions!$B$4 -> 238.05139 | F5: =(SUMPRODUCT(DCF!$B$8:$F$8,1/(1+$A5)^{1,2,3,4,5})+DCF!$F$8*(1+F$2)/($A5-F$2)/(1+$A5)^5+Assumptions!$B$5)/Assumptions!$B$4 -> 247.29117
A6: 0.23 | B6: =(SUMPRODUCT(DCF!$B$8:$F$8,1/(1+$A6)^{1,2,3,4,5})+DCF!$F$8*(1+B$2)/($A6-B$2)/(1+$A6)^5+Assumptions!$B$5)/Assumptions!$B$4 -> 191.44278 | C6: =(SUMPRODUCT(DCF!$B$8:$F$8,1/(1+$A6)^{1,2,3,4,5})+DCF!$F$8*(1+C$2)/($A6-C$2)/(1+$A6)^5+Assumptions!$B$5)/Assumptions!$B$4 -> 196.31951 | D6: =(SUMPRODUCT(DCF!$B$8:$F$8,1/(1+$A6)^{1,2,3,4,5})+DCF!$F$8*(1+D$2)/($A6-D$2)/(1+$A6)^5+Assumptions!$B$5)/Assumptions!$B$4 -> 201.63958 | E6: =(SUMPRODUCT(DCF!$B$8:$F$8,1/(1+$A6)^{1,2,3,4,5})+DCF!$F$8*(1+E$2)/($A6-E$2)/(1+$A6)^5+Assumptions!$B$5)/Assumptions!$B$4 -> 207.46632 | F6: =(SUMPRODUCT(DCF!$B$8:$F$8,1/(1+$A6)^{1,2,3,4,5})+DCF!$F$8*(1+F$2)/($A6-F$2)/(1+$A6)^5+Assumptions!$B$5)/Assumptions!$B$4 -> 213.87574
A8: Grid re-prices live off the DCF FCFF row and Assumptions net cash/share count; the study's Figure 2 mirrors it.

Sheet Per-Share & Ratios
A1: Per-share & ratios
A2: EGP m | B2: FY22/23 | C2: FY23/24 | D2: FY24/25 | E2: F26E | F2: F27E | G2: F28E | H2: F29E | I2: F30E | J2: F31E
A3: EPS (EGP) | B3: ='Income Statement'!B15 -> 8.95 | C3: ='Income Statement'!C15 -> 22.6 | D3: ='Income Statement'!D15 -> 24.68 | E3: ='Income Statement'!E15 -> 32.487541 | F3: ='Income Statement'!F15 -> 28.617975 | G3: ='Income Statement'!G15 -> 30.921098 | H3: ='Income Statement'!H15 -> 33.846355 | I3: ='Income Statement'!I15 -> 36.723718 | J3: ='Income Statement'!J15 -> 39.907605
A4: DPS declared for year (EGP) | B4: 2.5 | C4: 3 | D4: 8 | E4: 10
A5: P/E at spot | B5: =Assumptions!$B$3/'Income Statement'!B15 -> 31.941899 | C5: =Assumptions!$B$3/'Income Statement'!C15 -> 12.649558 | D5: =Assumptions!$B$3/'Income Statement'!D15 -> 11.583468 | E5: =Assumptions!$B$3/'Income Statement'!E15 -> 8.7996811 | F5: =Assumptions!$B$3/'Income Statement'!F15 -> 9.989526 | G5: =Assumptions!$B$3/'Income Statement'!G15 -> 9.2454672 | H5: =Assumptions!$B$3/'Income Statement'!H15 -> 8.4464042 | I5: =Assumptions!$B$3/'Income Statement'!I15 -> 7.7846148 | J5: =Assumptions!$B$3/'Income Statement'!J15 -> 7.1635469
A6: EV/EBITDA at spot | B6: =(Assumptions!$B$3*Assumptions!$B$4-'Balance Sheet'!B15)/'Income Statement'!B9 -> 21.041947 | C6: =(Assumptions!$B$3*Assumptions!$B$4-'Balance Sheet'!C15)/'Income Statement'!C9 -> 11.739205 | D6: =(Assumptions!$B$3*Assumptions!$B$4-'Balance Sheet'!D15)/'Income Statement'!D9 -> 9.1227387 | E6: =(Assumptions!$B$3*Assumptions!$B$4-'Balance Sheet'!E15)/'Income Statement'!E9 -> 6.3776471 | F6: =(Assumptions!$B$3*Assumptions!$B$4-'Balance Sheet'!F15)/'Income Statement'!F9 -> 6.8337351 | G6: =(Assumptions!$B$3*Assumptions!$B$4-'Balance Sheet'!G15)/'Income Statement'!G9 -> 5.8129562 | H6: =(Assumptions!$B$3*Assumptions!$B$4-'Balance Sheet'!H15)/'Income Statement'!H9 -> 4.8746915 | I6: =(Assumptions!$B$3*Assumptions!$B$4-'Balance Sheet'!I15)/'Income Statement'!I9 -> 4.1029677 | J6: =(Assumptions!$B$3*Assumptions!$B$4-'Balance Sheet'!J15)/'Income Statement'!J9 -> 3.4032655
A7: Dividend yield (declared/spot) | B7: =B4/Assumptions!$B$3 -> 0.0087449279 | C7: =C4/Assumptions!$B$3 -> 0.010493914 | D7: =D4/Assumptions!$B$3 -> 0.027983769 | E7: =E4/Assumptions!$B$3 -> 0.034979712
A8: ROE (avg equity) | C8: ='Income Statement'!C14/AVERAGE('Balance Sheet'!B11:C11) -> 0.64557225 | D8: ='Income Statement'!D14/AVERAGE('Balance Sheet'!C11:D11) -> 0.46428897 | E8: ='Income Statement'!E14/AVERAGE('Balance Sheet'!D11:E11) -> 0.44662768 | F8: ='Income Statement'!F14/AVERAGE('Balance Sheet'!E11:F11) -> 0.3145342 | G8: ='Income Statement'!G14/AVERAGE('Balance Sheet'!F11:G11) -> 0.28896588 | H8: ='Income Statement'!H14/AVERAGE('Balance Sheet'!G11:H11) -> 0.26863576 | I8: ='Income Statement'!I14/AVERAGE('Balance Sheet'!H11:I11) -> 0.25032212 | J8: ='Income Statement'!J14/AVERAGE('Balance Sheet'!I11:J11) -> 0.2359397
A9: Net margin | B9: ='Income Statement'!B14/'Income Statement'!B3 -> 0.16747562 | C9: ='Income Statement'!C14/'Income Statement'!C3 -> 0.28413835 | D9: ='Income Statement'!D14/'Income Statement'!D3 -> 0.23574092 | E9: ='Income Statement'!E14/'Income Statement'!E3 -> 0.2717452 | F9: ='Income Statement'!F14/'Income Statement'!F3 -> 0.22392688 | G9: ='Income Statement'!G14/'Income Statement'!G3 -> 0.22015297 | H9: ='Income Statement'!H14/'Income Statement'!H3 -> 0.21907301 | I9: ='Income Statement'!I14/'Income Statement'!I3 -> 0.21608813 | J9: ='Income Statement'!J14/'Income Statement'!J3 -> 0.21347511
A10: FCF yield at spot | B10: ='Cash Flow'!B8/(Assumptions!$B$3*Assumptions!$B$4) -> 0.024947954 | C10: ='Cash Flow'!C8/(Assumptions!$B$3*Assumptions!$B$4) -> 0.066346973 | D10: ='Cash Flow'!D8/(Assumptions!$B$3*Assumptions!$B$4) -> 0.073012198 | E10: ='Cash Flow'!E8/(Assumptions!$B$3*Assumptions!$B$4) -> 0.10188867 | F10: ='Cash Flow'!F8/(Assumptions!$B$3*Assumptions!$B$4) -> 0.086042344 | G10: ='Cash Flow'!G8/(Assumptions!$B$3*Assumptions!$B$4) -> 0.090130349 | H10: ='Cash Flow'!H8/(Assumptions!$B$3*Assumptions!$B$4) -> 0.099354087 | I10: ='Cash Flow'!I8/(Assumptions!$B$3*Assumptions!$B$4) -> 0.10798147 | J10: ='Cash Flow'!J8/(Assumptions!$B$3*Assumptions!$B$4) -> 0.1176221

Sheet Peer & Sector
A1: Peer set — global primary-aluminium producers (indicative, early Jul 2026)
A2: Producer | B2: Mkt cap (US$bn) | C2: P/E | D2: EV/EBITDA | E2: Capacity (kt) | F2: Note
A3: Alcoa (AA) | B3: 9.5 | C3: 13 | D3: 6 | E3: 2990 | F3: US/global; alumina-integrated
A4: Norsk Hydro (NHY) | B4: 14 | C4: 14.5 | D4: 6.5 | E4: 2300 | F4: Hydro-powered, EU CBAM-advantaged
A5: Century Aluminum (CENX) | B5: 2.3 | C5: 15 | D5: 7 | E5: 1020 | F5: US smelter; power-price levered
A6: Hindalco (HNDL) | B6: 18 | C6: 11 | D6: 6.5 | E6: 1300 | F6: India; Novelis downstream
A7: China Hongqiao (1378) | B7: 13.5 | C7: 7.5 | D7: 4.5 | E7: 6460 | F7: World's largest; coal-power
A8: Aluminium Bahrain (ALBA) | B8: 4.5 | C8: 11 | D8: 7 | E8: 1620 | F8: Gulf; gas-powered, closest analogue
A9: Ma'aden (1211) | B9: 45 | C9: 25 | D9: 12 | E9: 780 | F9: Saudi diversified miner
A10: Egypt Aluminum (EGAL) | B10: 2.4 | C10: =Assumptions!$B$3/'Income Statement'!D15 -> 11.583468 | D10: =(Assumptions!$B$3*Assumptions!$B$4-Assumptions!$B$5)/'Income Statement'!D9 -> 9.1227387 | E10: 320 | F10: State 89.8%; Nag Hammadi; Trafigura expansion to ~600 kt
A12: Peer figures are indicative public-source snapshots for context, not a pricing basis; the relative lens uses the Assumptions multiple.
