Workbook

Sheet READ FIRST
A1: Testahil · Independent Valuation Study — Educational Analysis · Not investment advice
A4: Emaar Development PJSC (DFM: EMAARDEV) — companion valuation model.
A6: This workbook is an educational valuation exercise, not investment advice, and contains no price target or rating.
A7: All blue cells on the Assumptions sheet are inputs; every other sheet links back to them, so changing one input reprices the model.
A9: Reported historical financials (FY2023–FY2025) are the company's own disclosure (EMAARDEV results releases; S&P/Yahoo tie-out).
A10: Balance-sheet lines and some splits are estimates flagged in the sheets. Forward-looking inputs — margins, the net-cash mark, the
A11: land-bank value, the multiples, the DCF and the Monte-Carlo factors — are the preparer's own judgments and are inherently uncertain.
A13: CALIBRATION NOTE (important): the Monte-Carlo lens for EMAARDEV is INDICATIVE. On a full 5-year walk-forward backtest it TIES the
A14: zero-drift random-walk benchmark on CRPS skill (does not distinguishably beat it) but produces a well-calibrated, roughly-uniform PIT
A15: under the name-specific drift-ON setting. It is NOT a failed/broken calibration; it simply has no demonstrated edge for this name.
A17: Primary lens: RNAV / split-NAV (development legs carry no terminal value). Currency: AED.
A19: The preparer may hold, and may in the future take or dispose of, a position in the security discussed in this report.

Sheet Summary
A1: Valuation summary — Emaar Development PJSC
A2: Four-lens fair value vs spot. Weighted central = SUMPRODUCT(base, weights).
A3: Lens | B3: Bear | C3: Base | D3: Bull | E3: Weight
A4: RNAV (primary) | B4: 13.798151 | C4: =SOTP!B11 -> 17.556176 | D4: 22.314202 | E4: =Assumptions!$B$31 -> 0.4
A5: Going-concern DCF | B5: 14.00479 | C5: =DCF!B24 -> 18.427355 | D5: 24.87693 | E5: =Assumptions!$B$32 -> 0.2
A6: Relative multiples | B6: 12.375 | C6: ='Relative & Normalized'!B7 -> 15.75 | D6: 20.25 | E6: =Assumptions!$B$33 -> 0.15
A7: Property-cycle earnings | B7: 10.8 | C7: ='Relative & Normalized'!B12 -> 16.875 | D7: 23.2875 | E7: =Assumptions!$B$34 -> 0.25
A8: Weighted central | B8: =SUMPRODUCT(B4:B7,$E4:$E7) -> 12.876468 | C8: =SUMPRODUCT(C4:C7,$E4:$E7) -> 17.289192 | D8: =SUMPRODUCT(D4:D7,$E4:$E7) -> 22.760442
A10: Spot price (AED) | C10: =Assumptions!$B$5 -> 14.26
A11: Upside to central base | C11: =C8/C10-1 -> 0.21242578
A13: Read: modestly-to-clearly undervalued (~+21%); RNAV-led; crux = Dubai property cycle + NAV discount. MC INDICATIVE (ties benchmark).

Sheet Fundamental Valuation
A1: Fundamental valuation — overview
A2: Anchor = RNAV; cross-checks = DCF, relative, property-cycle. See Summary for the weighted blend.
A4: Lens | B4: Base FV (AED)
A5: RNAV (primary) | B5: =SOTP!B11 -> 17.556176
A6: Going-concern DCF | B6: =DCF!B24 -> 18.427355
A7: Relative multiples | B7: ='Relative & Normalized'!B7 -> 15.75
A8: Property-cycle earnings | B8: ='Relative & Normalized'!B12 -> 16.875
A9: Weighted central | B9: =Summary!C8 -> 17.289192

Sheet Assumptions
A1: Assumptions — the single input layer
A2: All blue cells are inputs. Every downstream sheet links here; change one cell and the model reprices.
A4: ANCHORS
A5: Spot price (AED/share) | B5: 14.26
A6: Shares outstanding (mn) | B6: 4000
A7: Net cash mark (AED mn) | B7: 20000
A8: Sales backlog (AED mn) | B8: 125200
A9: WACC / discount rate | B9: 0.11
A10: Risk-free rate (rf) | B10: 0.045
A11: Beta (per-name, 0.8–1.3 band) | B11: 1.05
A12: Equity risk premium (ERP) | B12: 0.06
A13: Cost of equity Ke = rf + beta×ERP | B13: =Assumptions!$B$10+Assumptions!$B$11*Assumptions!$B$12 -> 0.108
A14: Terminal growth (disclosure only) | B14: 0.035
A15: Terminal exit EV/EBITDA (DCF) | B15: 2.5
A16: Corporate tax rate (UAE CT) | B16: 0.09
A17: RNAV — DEVELOPMENT (no terminal value on dev legs)
A18: Sustainable development net margin | B18: 0.35
A19: Backlog recognition yr1 weight | B19: 0.35
A20: yr2 | B20: 0.3
A21: yr3 | B21: 0.2
A22: yr4 | B22: 0.15
A23: Land-bank future launches (attrib, PV, haircut) | B23: 18000
A24: Central overhead PV (negative) | B24: -3000
A25: RELATIVE & CYCLE
A26: Mid-cycle attributable net profit (AED mn) | B26: 9000
A27: Through-cycle P/E (cycle lens) | B27: 7.5
A28: Justified P/E (relative lens) | B28: 7
A29: Normalized mid-cycle EPS (AED) | B29: 2.25
A30: LENS WEIGHTS
A31: RNAV weight | B31: 0.4
A32: DCF weight | B32: 0.2
A33: Relative weight | B33: 0.15
A34: Cycle weight | B34: 0.25
A35: FORECAST DRIVERS (DCF / IS) | C35: 2026E | D35: 2027E | E35: 2028E | F35: 2029E | G35: 2030E
A36: Revenue (AED mn) | C36: 30000 | D36: 32000 | E36: 31000 | F36: 29000 | G36: 28000
A37: EBITDA margin | C37: 0.51 | D37: 0.49 | E37: 0.475 | F37: 0.46 | G37: 0.45
A38: D&A % of revenue | C38: 0.03 | D38: 0.03 | E38: 0.03 | F38: 0.03 | G38: 0.03
A39: Capex % of revenue | C39: 0.02 | D39: 0.02 | E39: 0.02 | F39: 0.02 | G39: 0.02
A40: Land investment (AED mn) | C40: 4000 | D40: 3500 | E40: 3000 | F40: 3000 | G40: 3000
A41: Δ net working capital (AED mn) | C41: -1500 | D41: -1000 | E41: 0 | F41: 1000 | G41: 1500

Sheet SOTP
A1: RNAV / sum-of-the-parts (primary lens)
A2: Split-NAV: development legs carry NO terminal value; net cash + PV of backlog profit + haircut land bank − overhead.
A4: Component | B4: AED mn
A5: Backlog PV factor (4-yr, WACC) | B5: =Assumptions!$B$19/(1+Assumptions!$B$9)^1+Assumptions!$B$20/(1+Assumptions!$B$9)^2+Assumptions!$B$21/(1+Assumptions!$B$9)^3+Assumptions!$B$22/(1+Assumptions!$B$9)^4 -> 0.80384997
A6: Net cash | B6: =Assumptions!$B$7 -> 20000
A7: PV of backlog net profit (attrib.) | B7: =Assumptions!$B$8*Assumptions!$B$18*B5 -> 35224.706
A8: Land-bank future launches (attrib, PV, haircut) | B8: =Assumptions!$B$23 -> 18000
A9: Central overhead PV | B9: =Assumptions!$B$24 -> -3000
A10: RNAV (equity) | B10: =B6+B7+B8+B9 -> 70224.706
A11: RNAV per share (AED) | B11: =B10/Assumptions!$B$6 -> 17.556176
A13: Development legs carry no perpetual terminal value; only recurring legs would (EMAARDEV is ~pure build-to-sell).

Sheet Segments
A1: Segment / community view
A2: Pure build-to-sell developer; value engine = the master-planned pipeline.
A4: Community cluster | B4: Cyclicality | C4: Margin trend | D4: Capital int. | E4: Swing role
A5: Flagship established (Downtown, Marina, Hills) | B5: Moderate | C5: Steady ~45% | D5: Low | E5: Cash anchor
A6: New master-plans (Oasis, Grand Polo, Beachfront) | B6: High | C6: Peak → normalize | D6: Moderate | E6: Dominant swing
A7: Emaar South / The Valley (volume) | B7: Moderate | C7: Improving | D7: Moderate | E7: Volume base
A8: Land bank (305m sq ft incl. new 36m) | B8: High | C8: Optionality | D8: High (land) | E8: Long-dated upside

Sheet Relative & Normalized
A1: Relative multiples & property-cycle earnings
A2: Floor lens (relative) and cycle lens (property-cycle framing replaces normalized-earnings for developers).
A4: Relative (floor)
A5: Normalized mid-cycle EPS (AED) | B5: =Assumptions!$B$29 -> 2.25
A6: Justified P/E | B6: =Assumptions!$B$28 -> 7
A7: Relative fair value (AED) | B7: =B5*B6 -> 15.75
A9: Property-cycle (mid)
A10: Mid-cycle attrib. net profit (AED mn) | B10: =Assumptions!$B$26 -> 9000
A11: Through-cycle P/E | B11: =Assumptions!$B$27 -> 7.5
A12: Cycle fair value (AED) | B12: =(B10/Assumptions!$B$6)*B11 -> 16.875

Sheet DCF
A1: Discounted cash flow — exit-multiple terminal (no Gordon perpetuity on a finite development pipeline, §3.5-E)
A2: Revenue→EBITDA→D&A→EBIT→NOPAT→+D&A→−Capex→−Land→−ΔWC→FCFF→Discount factor→PV. TV = exit EV/EBITDA.
B3: 2026E | C3: 2027E | D3: 2028E | E3: 2029E | F3: 2030E
A4: Revenue | B4: ='Income Statement'!E4 -> 30000 | C4: ='Income Statement'!F4 -> 32000 | D4: ='Income Statement'!G4 -> 31000 | E4: ='Income Statement'!H4 -> 29000 | F4: ='Income Statement'!I4 -> 28000
A5: EBITDA | B5: ='Income Statement'!E8 -> 15300 | C5: ='Income Statement'!F8 -> 15680 | D5: ='Income Statement'!G8 -> 14725 | E5: ='Income Statement'!H8 -> 13340 | F5: ='Income Statement'!I8 -> 12600
A6: D&A | B6: ='Income Statement'!E9 -> 900 | C6: ='Income Statement'!F9 -> 960 | D6: ='Income Statement'!G9 -> 930 | E6: ='Income Statement'!H9 -> 870 | F6: ='Income Statement'!I9 -> 840
A7: EBIT | B7: =B5-B6 -> 14400 | C7: =C5-C6 -> 14720 | D7: =D5-D6 -> 13795 | E7: =E5-E6 -> 12470 | F7: =F5-F6 -> 11760
A8: NOPAT = EBIT×(1−tax) | B8: =B7*(1-Assumptions!$B$16) -> 13104 | C8: =C7*(1-Assumptions!$B$16) -> 13395.2 | D8: =D7*(1-Assumptions!$B$16) -> 12553.45 | E8: =E7*(1-Assumptions!$B$16) -> 11347.7 | F8: =F7*(1-Assumptions!$B$16) -> 10701.6
A9: + D&A | B9: =B6 -> 900 | C9: =C6 -> 960 | D9: =D6 -> 930 | E9: =E6 -> 870 | F9: =F6 -> 840
A10: − Capex | B10: =-B4*Assumptions!C$39 -> -600 | C10: =-C4*Assumptions!D$39 -> -640 | D10: =-D4*Assumptions!E$39 -> -620 | E10: =-E4*Assumptions!F$39 -> -580 | F10: =-F4*Assumptions!G$39 -> -560
A11: − Land investment | B11: =-Assumptions!C$40 -> -4000 | C11: =-Assumptions!D$40 -> -3500 | D11: =-Assumptions!E$40 -> -3000 | E11: =-Assumptions!F$40 -> -3000 | F11: =-Assumptions!G$40 -> -3000
A12: − Δ working capital | B12: =-Assumptions!C$41 -> 1500 | C12: =-Assumptions!D$41 -> 1000 | D12: =-Assumptions!E$41 -> 0 | E12: =-Assumptions!F$41 -> -1000 | F12: =-Assumptions!G$41 -> -1500
A13: Free cash flow to firm | B13: =B8+B9+B10+B11+B12 -> 10904 | C13: =C8+C9+C10+C11+C12 -> 11215.2 | D13: =D8+D9+D10+D11+D12 -> 9863.45 | E13: =E8+E9+E10+E11+E12 -> 7637.7 | F13: =F8+F9+F10+F11+F12 -> 6481.6
A14: Discount factor | B14: =1/(1+Assumptions!$B$9)^1 -> 0.9009009 | C14: =1/(1+Assumptions!$B$9)^2 -> 0.81162243 | D14: =1/(1+Assumptions!$B$9)^3 -> 0.73119138 | E14: =1/(1+Assumptions!$B$9)^4 -> 0.65873097 | F14: =1/(1+Assumptions!$B$9)^5 -> 0.59345133
A15: PV of FCFF | B15: =B13*B14 -> 9823.4234 | C15: =C13*C14 -> 9102.5079 | D15: =D13*D14 -> 7212.0696 | E15: =E13*E14 -> 5031.1896 | F15: =F13*F14 -> 3846.5141
A17: Σ PV of explicit FCFF | B17: =SUM(B15:F15) -> 35015.705
A18: Year-5 EBITDA | B18: =F5 -> 12600
A19: Terminal value (exit EV/EBITDA) | B19: =B18*Assumptions!$B$15 -> 31500
A20: PV of terminal value | B20: =B19/(1+Assumptions!$B$9)^5 -> 18693.717
A21: Enterprise value | B21: =B17+B20 -> 53709.421
A22: plus: net cash | B22: =Assumptions!$B$7 -> 20000
A23: Equity value | B23: =B21+B22 -> 73709.421
A24: Fair value per share (AED) | B24: =B23/Assumptions!$B$6 -> 18.427355
A25: % terminal of EV | B25: =B20/B21 -> 0.34805284
A26: Memo: Gordon-perpetuity FV (disclosure, device A-7) | B26: =(B17+(F13*(1+Assumptions!$B$14)/(Assumptions!$B$9-Assumptions!$B$14))/(1+Assumptions!$B$9)^5+Assumptions!$B$7)/Assumptions!$B$6 -> 27.0244
A28: A naive Gordon perpetuity overstates value by assuming perpetual high-margin land replenishment — hence the exit-multiple terminal.

Sheet Income Statement
A1: Income statement (AED mn)
A2: 3 years historical (company disclosure) + 5-year forecast (links to Assumptions drivers).
A3: Line | B3: 2023 | C3: 2024 | D3: 2025 | E3: 2026E | F3: 2027E | G3: 2028E | H3: 2029E | I3: 2030E
A4: Revenue | B4: 11921 | C4: 19147 | D4: 27486 | E4: =Assumptions!C$36 -> 30000 | F4: =Assumptions!D$36 -> 32000 | G4: =Assumptions!E$36 -> 31000 | H4: =Assumptions!F$36 -> 29000 | I4: =Assumptions!G$36 -> 28000
A5: COGS | B5: -3513 | C5: -8490 | D5: -11948 | E5: =-(E4-E6) -> -13050 | F5: =-(F4-F6) -> -13920 | G5: =-(G4-G6) -> -13485 | H5: =-(H4-H6) -> -12615 | I5: =-(I4-I6) -> -12180
A6: Gross profit | B6: 8408 | C6: 10657 | D6: 15537 | E6: =E4*0.565 -> 16950 | F6: =F4*0.565 -> 18080 | G6: =G4*0.565 -> 17515 | H6: =H4*0.565 -> 16385 | I6: =I4*0.565 -> 15820
A7: SG&A / opex | B7: -1183 | C7: -1609 | D7: -2119 | E7: =-(E6-E10-E9) -> -1650 | F7: =-(F6-F10-F9) -> -2400 | G7: =-(G6-G10-G9) -> -2790 | H7: =-(H6-H10-H9) -> -3045 | I7: =-(I6-I10-I9) -> -3220
A8: EBITDA | B8: 8000 | C8: 9600 | D8: 14300 | E8: =E4*Assumptions!C$37 -> 15300 | F8: =F4*Assumptions!D$37 -> 15680 | G8: =G4*Assumptions!E$37 -> 14725 | H8: =H4*Assumptions!F$37 -> 13340 | I8: =I4*Assumptions!G$37 -> 12600
A9: D&A | B9: 775 | C9: 553 | D9: 881 | E9: =E4*Assumptions!C$38 -> 900 | F9: =F4*Assumptions!D$38 -> 960 | G9: =G4*Assumptions!E$38 -> 930 | H9: =H4*Assumptions!F$38 -> 870 | I9: =I4*Assumptions!G$38 -> 840
A10: EBIT | B10: 7225 | C10: 9047 | D10: 13419 | E10: =E8-E9 -> 14400 | F10: =F8-F9 -> 14720 | G10: =G8-G9 -> 13795 | H10: =H8-H9 -> 12470 | I10: =I8-I9 -> 11760
A11: Net finance & other | B11: 564 | C11: 1175 | D11: 1300 | E11: 1300 | F11: 1300 | G11: 1300 | H11: 1300 | I11: 1300
A12: JV / associates | B12: 120 | C12: 300 | D12: 300 | E12: 300 | F12: 300 | G12: 300 | H12: 300 | I12: 300
A13: PBT | B13: 6980 | C13: 10190 | D13: 15537 | E13: =E10+E11+E12 -> 16000 | F13: =F10+F11+F12 -> 16320 | G13: =G10+G11+G12 -> 15395 | H13: =H10+H11+H12 -> 14070 | I13: =I10+I11+I12 -> 13360
A14: Tax | B14: -104 | C14: -990 | D14: -1400 | E14: =-E13*Assumptions!$B$16 -> -1440 | F14: =-F13*Assumptions!$B$16 -> -1468.8 | G14: =-G13*Assumptions!$B$16 -> -1385.55 | H14: =-H13*Assumptions!$B$16 -> -1266.3 | I14: =-I13*Assumptions!$B$16 -> -1202.4
A15: NCI | B15: -236 | C15: -1570 | D15: -2817 | E15: =-(E13+E14)*0.2 -> -2912 | F15: =-(F13+F14)*0.2 -> -2970.24 | G15: =-(G13+G14)*0.2 -> -2801.89 | H15: =-(H13+H14)*0.2 -> -2560.74 | I15: =-(I13+I14)*0.2 -> -2431.52
A16: Net profit (attrib.) | B16: 6640 | C16: 7630 | D16: 11320 | E16: =E13+E14+E15 -> 11648 | F16: =F13+F14+F15 -> 11880.96 | G16: =G13+G14+G15 -> 11207.56 | H16: =H13+H14+H15 -> 10242.96 | I16: =I13+I14+I15 -> 9726.08
A18: EPS (AED) | B18: =B16/Assumptions!$B$6 -> 1.66 | C18: =C16/Assumptions!$B$6 -> 1.9075 | D18: =D16/Assumptions!$B$6 -> 2.83 | E18: =E16/Assumptions!$B$6 -> 2.912 | F18: =F16/Assumptions!$B$6 -> 2.97024 | G18: =G16/Assumptions!$B$6 -> 2.80189 | H18: =H16/Assumptions!$B$6 -> 2.56074 | I18: =I16/Assumptions!$B$6 -> 2.43152
A20: Source: EMAARDEV FY23–FY25 results releases (S&P/Yahoo tie-out). Forecast: Assumptions drivers.

Sheet Balance Sheet
A1: Balance sheet (AED mn)
A2: Cash-rich BTS developer, ~zero debt. Historical estimated from disclosure/ratios (flagged); forecast rolls forward.
A3: Line | B3: 2023 | C3: 2024 | D3: 2025 | E3: 2026E | F3: 2027E | G3: 2028E | H3: 2029E | I3: 2030E
A4: Cash & bank (incl. escrow) | B4: 16000 | C4: 18000 | D4: 24000 | E4: =D4+'Cash Flow'!E18 -> 24000 | F4: =E4+'Cash Flow'!F18 -> 24000 | G4: =F4+'Cash Flow'!G18 -> 24000 | H4: =G4+'Cash Flow'!H18 -> 24000 | I4: =H4+'Cash Flow'!I18 -> 24000
A5: Development properties / WIP | B5: 22000 | C5: 26000 | D5: 30000 | E5: =D5*1.02 -> 30600 | F5: =E5*1.02 -> 31212 | G5: =F5*1.02 -> 31836.24 | H5: =G5*1.02 -> 32472.965 | I5: =H5*1.02 -> 33122.424
A6: Receivables & contract assets | B6: 9000 | C6: 12000 | D6: 15000 | E6: =D6*1.02 -> 15300 | F6: =E6*1.02 -> 15606 | G6: =F6*1.02 -> 15918.12 | H6: =G6*1.02 -> 16236.482 | I6: =H6*1.02 -> 16561.212
A7: Other assets | B7: 6000 | C7: 7000 | D7: 8000 | E7: =D7*1.02 -> 8160 | F7: =E7*1.02 -> 8323.2 | G7: =F7*1.02 -> 8489.664 | H7: =G7*1.02 -> 8659.4573 | I7: =H7*1.02 -> 8832.6464
A8: Total assets | B8: 53000 | C8: 63000 | D8: 77000 | E8: =SUM(E4:E7) -> 78060 | F8: =SUM(F4:F7) -> 79141.2 | G8: =SUM(G4:G7) -> 80244.024 | H8: =SUM(H4:H7) -> 81368.904 | I8: =SUM(I4:I7) -> 82516.283
A9: Customer advances / deferred rev | B9: 20000 | C9: 25000 | D9: 31000 | E9: =D9*1.02 -> 31620 | F9: =E9*1.02 -> 32252.4 | G9: =F9*1.02 -> 32897.448 | H9: =G9*1.02 -> 33555.397 | I9: =H9*1.02 -> 34226.505
A10: Payables & provisions | B10: 10000 | C10: 12000 | D10: 14000 | E10: =D10*1.02 -> 14280 | F10: =E10*1.02 -> 14565.6 | G10: =F10*1.02 -> 14856.912 | H10: =G10*1.02 -> 15154.05 | I10: =H10*1.02 -> 15457.131
A11: Debt | B11: 0 | C11: 0 | D11: 0 | E11: 0 | F11: 0 | G11: 0 | H11: 0 | I11: 0
A12: Total liabilities | B12: 30000 | C12: 37000 | D12: 45000 | E12: =E9+E10+E11 -> 45900 | F12: =F9+F10+F11 -> 46818 | G12: =G9+G10+G11 -> 47754.36 | H12: =H9+H10+H11 -> 48709.447 | I12: =I9+I10+I11 -> 49683.636
A13: NCI | B13: 3000 | C13: 4000 | D13: 5000 | E13: =D13*1.02 -> 5100 | F13: =E13*1.02 -> 5202 | G13: =F13*1.02 -> 5306.04 | H13: =G13*1.02 -> 5412.1608 | I13: =H13*1.02 -> 5520.404
A14: Equity (attrib.) | B14: 20000 | C14: 22000 | D14: 27000 | E14: =D14+'Income Statement'!E16-Assumptions!$B$6*1 -> 34648 | F14: =E14+'Income Statement'!F16-Assumptions!$B$6*1 -> 42528.96 | G14: =F14+'Income Statement'!G16-Assumptions!$B$6*1 -> 49736.52 | H14: =G14+'Income Statement'!H16-Assumptions!$B$6*1 -> 55979.48 | I14: =H14+'Income Statement'!I16-Assumptions!$B$6*1 -> 61705.56
A16: Net cash (cash − debt) | B16: =B4-B11 -> 16000 | C16: =C4-C11 -> 18000 | D16: =D4-D11 -> 24000 | E16: =E4-E11 -> 24000 | F16: =F4-F11 -> 24000 | G16: =G4-G11 -> 24000 | H16: =H4-H11 -> 24000 | I16: =I4-I11 -> 24000
A18: Balance-sheet lines are estimates from disclosure and ratios (ROE ~37.5%, D/E ~0); flagged, not audited tie-out.

Sheet Cash Flow
A1: Cash flow (AED mn)
A2: Indirect method; forecast links to IS and Assumptions. Strong operating cash from pre-sales.
A3: Line | B3: 2023 | C3: 2024 | D3: 2025 | E3: 2026E | F3: 2027E | G3: 2028E | H3: 2029E | I3: 2030E
A4: Net profit (attrib.) | E4: ='Income Statement'!E16 -> 11648 | F4: ='Income Statement'!F16 -> 11880.96 | G4: ='Income Statement'!G16 -> 11207.56 | H4: ='Income Statement'!H16 -> 10242.96 | I4: ='Income Statement'!I16 -> 9726.08
A5: + NCI | E5: =-'Income Statement'!E15 -> 2912 | F5: =-'Income Statement'!F15 -> 2970.24 | G5: =-'Income Statement'!G15 -> 2801.89 | H5: =-'Income Statement'!H15 -> 2560.74 | I5: =-'Income Statement'!I15 -> 2431.52
A6: + D&A | E6: ='Income Statement'!E9 -> 900 | F6: ='Income Statement'!F9 -> 960 | G6: ='Income Statement'!G9 -> 930 | H6: ='Income Statement'!H9 -> 870 | I6: ='Income Statement'!I9 -> 840
A7: ± Δ working capital | E7: =-Assumptions!C$41 -> 1500 | F7: =-Assumptions!D$41 -> 1000 | G7: =-Assumptions!E$41 -> 0 | H7: =-Assumptions!F$41 -> -1000 | I7: =-Assumptions!G$41 -> -1500
A8: Operating cash flow | B8: 7000 | C8: 9500 | D8: 14500 | E8: =SUM(E4:E7) -> 16960 | F8: =SUM(F4:F7) -> 16811.2 | G8: =SUM(G4:G7) -> 14939.45 | H8: =SUM(H4:H7) -> 12673.7 | I8: =SUM(I4:I7) -> 11497.6
A9: − Capex | B9: -400 | C9: -500 | D9: -600 | E9: =-'Income Statement'!E4*Assumptions!C$39 -> -600 | F9: =-'Income Statement'!F4*Assumptions!D$39 -> -640 | G9: =-'Income Statement'!G4*Assumptions!E$39 -> -620 | H9: =-'Income Statement'!H4*Assumptions!F$39 -> -580 | I9: =-'Income Statement'!I4*Assumptions!G$39 -> -560
A10: − Land investment | B10: -2000 | C10: -4000 | D10: -8000 | E10: =-Assumptions!C$40 -> -4000 | F10: =-Assumptions!D$40 -> -3500 | G10: =-Assumptions!E$40 -> -3000 | H10: =-Assumptions!F$40 -> -3000 | I10: =-Assumptions!G$40 -> -3000
A11: Investing cash flow | B11: =B9+B10 -> -2400 | C11: =C9+C10 -> -4500 | D11: =D9+D10 -> -8600 | E11: =E9+E10 -> -4600 | F11: =F9+F10 -> -4140 | G11: =G9+G10 -> -3620 | H11: =H9+H10 -> -3580 | I11: =I9+I10 -> -3560
A12: − Dividends paid | B12: -2082 | C12: -2720 | D12: -4000 | E12: =-Assumptions!$B$6*1 -> -4000 | F12: =-Assumptions!$B$6*1 -> -4000 | G12: =-Assumptions!$B$6*1 -> -4000 | H12: =-Assumptions!$B$6*1 -> -4000 | I12: =-Assumptions!$B$6*1 -> -4000
A13: Financing cash flow | B13: =B12 -> -2082 | C13: =C12 -> -2720 | D13: =D12 -> -4000 | E13: =E12 -> -4000 | F13: =F12 -> -4000 | G13: =G12 -> -4000 | H13: =H12 -> -4000 | I13: =I12 -> -4000
A14: Net change in cash | B14: =B8+B11+B13 -> 2518 | C14: =C8+C11+C13 -> 2280 | D14: =D8+D11+D13 -> 1900 | E14: =E8+E11+E13 -> 8360 | F14: =F8+F11+F13 -> 8671.2 | G14: =G8+G11+G13 -> 7319.45 | H14: =H8+H11+H13 -> 5093.7 | I14: =I8+I11+I13 -> 3937.6

Sheet Summary Financials
A1: Summary financials (links to statements)
A2: Every cell links to the statement sheets — no hard-coded duplicates.
A3: Line | B3: 2023 | C3: 2024 | D3: 2025 | E3: 2026E | F3: 2027E | G3: 2028E | H3: 2029E | I3: 2030E
A4: Revenue | B4: ='Income Statement'!B4 -> 11921 | C4: ='Income Statement'!C4 -> 19147 | D4: ='Income Statement'!D4 -> 27486 | E4: ='Income Statement'!E4 -> 30000 | F4: ='Income Statement'!F4 -> 32000 | G4: ='Income Statement'!G4 -> 31000 | H4: ='Income Statement'!H4 -> 29000 | I4: ='Income Statement'!I4 -> 28000
A5: EBITDA | B5: ='Income Statement'!B8 -> 8000 | C5: ='Income Statement'!C8 -> 9600 | D5: ='Income Statement'!D8 -> 14300 | E5: ='Income Statement'!E8 -> 15300 | F5: ='Income Statement'!F8 -> 15680 | G5: ='Income Statement'!G8 -> 14725 | H5: ='Income Statement'!H8 -> 13340 | I5: ='Income Statement'!I8 -> 12600
A6: EBIT | B6: ='Income Statement'!B10 -> 7225 | C6: ='Income Statement'!C10 -> 9047 | D6: ='Income Statement'!D10 -> 13419 | E6: ='Income Statement'!E10 -> 14400 | F6: ='Income Statement'!F10 -> 14720 | G6: ='Income Statement'!G10 -> 13795 | H6: ='Income Statement'!H10 -> 12470 | I6: ='Income Statement'!I10 -> 11760
A7: Net profit (attrib.) | B7: ='Income Statement'!B16 -> 6640 | C7: ='Income Statement'!C16 -> 7630 | D7: ='Income Statement'!D16 -> 11320 | E7: ='Income Statement'!E16 -> 11648 | F7: ='Income Statement'!F16 -> 11880.96 | G7: ='Income Statement'!G16 -> 11207.56 | H7: ='Income Statement'!H16 -> 10242.96 | I7: ='Income Statement'!I16 -> 9726.08
A9: Free cash flow to firm | E9: =DCF!B13 -> 10904 | F9: =DCF!C13 -> 11215.2 | G9: =DCF!D13 -> 9863.45 | H9: =DCF!E13 -> 7637.7 | I9: =DCF!F13 -> 6481.6

Sheet Monte Carlo
A1: Monte Carlo — engine output (drift-ON, name-specific)
A2: 50,000 paths · seed 42 · YZ-HAR width (c2c-leveled) · unit-variance t5 · secular drift ON. INDICATIVE: ties benchmark, PIT ~uniform.
A4: The probability read (from the same 50,000 paths)
A5: P(price above spot) at T+60 | B5: 0.68856
A6: P(+10%) vs P(−10%) | B6: 44% vs 13%
A7: Odds ratio (up:down) | B7: 3.4359134
A8: Median level / % move | B8: 15.34 (+7.6%)
A9: 50% band (25th–75th) | B9: 13.87 – 16.97
A10: Touch +10% / −10% by T+60 | B10: 64% / 30%
A12: Percentile map (AED/share)
A13: Horizon | B13: p5 | C13: p25 | D13: p50 | E13: p75 | F13: p95
A14: T+20 sessions | B14: 12.421333 | C14: 13.782153 | D14: 14.603918 | E14: 15.488223 | F14: 17.182699
A15: T+60 sessions | B15: 11.58936 | C15: 13.866028 | D15: 15.344005 | E15: 16.96628 | F15: 20.326334
A17: Engine inputs
A18: Annualized diffusion vol | B18: 0.36877763
A19: Secular drift (daily, ON) | B19: 0.0011961174
A20: Net 3-month drift | B20: 0.074405024
A21: Seed | B21: 42
A22: Paths | B22: 50000
A24: Level-touch ladder
A25: Level | B25: T+20 | C25: T+60
A26: 20 | B26: 0.00874 | C26: 0.0887
A27: 18 | B27: 0.03638 | C27: 0.23038
A28: 17 | B28: 0.08812 | C28: 0.36928
A29: 16 | B29: 0.2335 | C29: 0.5712
A30: 15 | B30: 0.57244 | C30: 0.808
A31: 14 | B31: 0.65372 | C31: 0.74698
A32: 13 | B32: 0.19042 | C32: 0.34524
A33: 12 | B33: 0.0495 | C33: 0.15014

Sheet Sensitivity
A1: Sensitivity — WACC × terminal exit multiple (DCF) and RNAV drivers
A2: DCF fair value across WACC and exit EV/EBITDA; RNAV across dev margin and net cash.
A4: DCF FV (AED) — WACC (down) × exit EV/EBITDA (across)
A5: WACC \ exit | B5: 2 | C5: 2.5 | D5: 3 | E5: 3.5
A6: 0.095 | B6: =(DCF!$B$13/(1+$A6)^1+DCF!$C$13/(1+$A6)^2+DCF!$D$13/(1+$A6)^3+DCF!$E$13/(1+$A6)^4+DCF!$F$13/(1+$A6)^5+DCF!$F$5*2/(1+$A6)^5+Assumptions!$B$7)/Assumptions!$B$6 -> 18.065435 | C6: =(DCF!$B$13/(1+$A6)^1+DCF!$C$13/(1+$A6)^2+DCF!$D$13/(1+$A6)^3+DCF!$E$13/(1+$A6)^4+DCF!$F$13/(1+$A6)^5+DCF!$F$5*2.5/(1+$A6)^5+Assumptions!$B$7)/Assumptions!$B$6 -> 19.065919 | D6: =(DCF!$B$13/(1+$A6)^1+DCF!$C$13/(1+$A6)^2+DCF!$D$13/(1+$A6)^3+DCF!$E$13/(1+$A6)^4+DCF!$F$13/(1+$A6)^5+DCF!$F$5*3/(1+$A6)^5+Assumptions!$B$7)/Assumptions!$B$6 -> 20.066403 | E6: =(DCF!$B$13/(1+$A6)^1+DCF!$C$13/(1+$A6)^2+DCF!$D$13/(1+$A6)^3+DCF!$E$13/(1+$A6)^4+DCF!$F$13/(1+$A6)^5+DCF!$F$5*3.5/(1+$A6)^5+Assumptions!$B$7)/Assumptions!$B$6 -> 21.066886
A7: 0.11 | B7: =(DCF!$B$13/(1+$A7)^1+DCF!$C$13/(1+$A7)^2+DCF!$D$13/(1+$A7)^3+DCF!$E$13/(1+$A7)^4+DCF!$F$13/(1+$A7)^5+DCF!$F$5*2/(1+$A7)^5+Assumptions!$B$7)/Assumptions!$B$6 -> 17.49267 | C7: =(DCF!$B$13/(1+$A7)^1+DCF!$C$13/(1+$A7)^2+DCF!$D$13/(1+$A7)^3+DCF!$E$13/(1+$A7)^4+DCF!$F$13/(1+$A7)^5+DCF!$F$5*2.5/(1+$A7)^5+Assumptions!$B$7)/Assumptions!$B$6 -> 18.427355 | D7: =(DCF!$B$13/(1+$A7)^1+DCF!$C$13/(1+$A7)^2+DCF!$D$13/(1+$A7)^3+DCF!$E$13/(1+$A7)^4+DCF!$F$13/(1+$A7)^5+DCF!$F$5*3/(1+$A7)^5+Assumptions!$B$7)/Assumptions!$B$6 -> 19.362041 | E7: =(DCF!$B$13/(1+$A7)^1+DCF!$C$13/(1+$A7)^2+DCF!$D$13/(1+$A7)^3+DCF!$E$13/(1+$A7)^4+DCF!$F$13/(1+$A7)^5+DCF!$F$5*3.5/(1+$A7)^5+Assumptions!$B$7)/Assumptions!$B$6 -> 20.296727
A8: 0.125 | B8: =(DCF!$B$13/(1+$A8)^1+DCF!$C$13/(1+$A8)^2+DCF!$D$13/(1+$A8)^3+DCF!$E$13/(1+$A8)^4+DCF!$F$13/(1+$A8)^5+DCF!$F$5*2/(1+$A8)^5+Assumptions!$B$7)/Assumptions!$B$6 -> 16.957617 | C8: =(DCF!$B$13/(1+$A8)^1+DCF!$C$13/(1+$A8)^2+DCF!$D$13/(1+$A8)^3+DCF!$E$13/(1+$A8)^4+DCF!$F$13/(1+$A8)^5+DCF!$F$5*2.5/(1+$A8)^5+Assumptions!$B$7)/Assumptions!$B$6 -> 17.83163 | D8: =(DCF!$B$13/(1+$A8)^1+DCF!$C$13/(1+$A8)^2+DCF!$D$13/(1+$A8)^3+DCF!$E$13/(1+$A8)^4+DCF!$F$13/(1+$A8)^5+DCF!$F$5*3/(1+$A8)^5+Assumptions!$B$7)/Assumptions!$B$6 -> 18.705643 | E8: =(DCF!$B$13/(1+$A8)^1+DCF!$C$13/(1+$A8)^2+DCF!$D$13/(1+$A8)^3+DCF!$E$13/(1+$A8)^4+DCF!$F$13/(1+$A8)^5+DCF!$F$5*3.5/(1+$A8)^5+Assumptions!$B$7)/Assumptions!$B$6 -> 19.579657
A9: 0.14 | B9: =(DCF!$B$13/(1+$A9)^1+DCF!$C$13/(1+$A9)^2+DCF!$D$13/(1+$A9)^3+DCF!$E$13/(1+$A9)^4+DCF!$F$13/(1+$A9)^5+DCF!$F$5*2/(1+$A9)^5+Assumptions!$B$7)/Assumptions!$B$6 -> 16.457189 | C9: =(DCF!$B$13/(1+$A9)^1+DCF!$C$13/(1+$A9)^2+DCF!$D$13/(1+$A9)^3+DCF!$E$13/(1+$A9)^4+DCF!$F$13/(1+$A9)^5+DCF!$F$5*2.5/(1+$A9)^5+Assumptions!$B$7)/Assumptions!$B$6 -> 17.275194 | D9: =(DCF!$B$13/(1+$A9)^1+DCF!$C$13/(1+$A9)^2+DCF!$D$13/(1+$A9)^3+DCF!$E$13/(1+$A9)^4+DCF!$F$13/(1+$A9)^5+DCF!$F$5*3/(1+$A9)^5+Assumptions!$B$7)/Assumptions!$B$6 -> 18.0932 | E9: =(DCF!$B$13/(1+$A9)^1+DCF!$C$13/(1+$A9)^2+DCF!$D$13/(1+$A9)^3+DCF!$E$13/(1+$A9)^4+DCF!$F$13/(1+$A9)^5+DCF!$F$5*3.5/(1+$A9)^5+Assumptions!$B$7)/Assumptions!$B$6 -> 18.911205
A11: RNAV FV (AED) — dev margin (down) × net cash (across, AED bn)
A12: margin \ cash | B12: 16 | C12: 20 | D12: 24 | E12: 28
A13: 0.3 | B13: =(16*1000+Assumptions!$B$8*$A13*SOTP!$B$5+Assumptions!$B$23+Assumptions!$B$24)/Assumptions!$B$6 -> 15.298151 | C13: =(20*1000+Assumptions!$B$8*$A13*SOTP!$B$5+Assumptions!$B$23+Assumptions!$B$24)/Assumptions!$B$6 -> 16.298151 | D13: =(24*1000+Assumptions!$B$8*$A13*SOTP!$B$5+Assumptions!$B$23+Assumptions!$B$24)/Assumptions!$B$6 -> 17.298151 | E13: =(28*1000+Assumptions!$B$8*$A13*SOTP!$B$5+Assumptions!$B$23+Assumptions!$B$24)/Assumptions!$B$6 -> 18.298151
A14: 0.35 | B14: =(16*1000+Assumptions!$B$8*$A14*SOTP!$B$5+Assumptions!$B$23+Assumptions!$B$24)/Assumptions!$B$6 -> 16.556176 | C14: =(20*1000+Assumptions!$B$8*$A14*SOTP!$B$5+Assumptions!$B$23+Assumptions!$B$24)/Assumptions!$B$6 -> 17.556176 | D14: =(24*1000+Assumptions!$B$8*$A14*SOTP!$B$5+Assumptions!$B$23+Assumptions!$B$24)/Assumptions!$B$6 -> 18.556176 | E14: =(28*1000+Assumptions!$B$8*$A14*SOTP!$B$5+Assumptions!$B$23+Assumptions!$B$24)/Assumptions!$B$6 -> 19.556176
A15: 0.4 | B15: =(16*1000+Assumptions!$B$8*$A15*SOTP!$B$5+Assumptions!$B$23+Assumptions!$B$24)/Assumptions!$B$6 -> 17.814202 | C15: =(20*1000+Assumptions!$B$8*$A15*SOTP!$B$5+Assumptions!$B$23+Assumptions!$B$24)/Assumptions!$B$6 -> 18.814202 | D15: =(24*1000+Assumptions!$B$8*$A15*SOTP!$B$5+Assumptions!$B$23+Assumptions!$B$24)/Assumptions!$B$6 -> 19.814202 | E15: =(28*1000+Assumptions!$B$8*$A15*SOTP!$B$5+Assumptions!$B$23+Assumptions!$B$24)/Assumptions!$B$6 -> 20.814202
A16: 0.45 | B16: =(16*1000+Assumptions!$B$8*$A16*SOTP!$B$5+Assumptions!$B$23+Assumptions!$B$24)/Assumptions!$B$6 -> 19.072227 | C16: =(20*1000+Assumptions!$B$8*$A16*SOTP!$B$5+Assumptions!$B$23+Assumptions!$B$24)/Assumptions!$B$6 -> 20.072227 | D16: =(24*1000+Assumptions!$B$8*$A16*SOTP!$B$5+Assumptions!$B$23+Assumptions!$B$24)/Assumptions!$B$6 -> 21.072227 | E16: =(28*1000+Assumptions!$B$8*$A16*SOTP!$B$5+Assumptions!$B$23+Assumptions!$B$24)/Assumptions!$B$6 -> 22.072227

Sheet Per-Share & Ratios
A1: Per-share & ratio dashboard
A2: Fixed panel, identical across studies (the 'Data Miner').
A3: Metric | B3: 2023 | C3: 2024 | D3: 2025
A4: EPS (AED) | B4: 1.66 | C4: 1.91 | D4: 2.83
A5: DPS (AED) | B5: 0.52 | C5: 0.68 | D5: 1
A6: BVPS (AED) | B6: 5 | C6: 5.5 | D6: 6.75
A7: P/E | B7: 8.6 | C7: 7.5 | D7: =Assumptions!$B$5/2.83 -> 5.0388693
A8: Dividend yield | B8: =0.52/Assumptions!$B$5 -> 0.036465638 | C8: =0.68/Assumptions!$B$5 -> 0.047685835 | D8: =1/Assumptions!$B$5 -> 0.070126227
A9: EV/EBITDA (2025) | D9: =(Assumptions!$B$5*Assumptions!$B$6-Assumptions!$B$7)/14300 -> 2.5902098
A10: Net margin (attrib.) | B10: 0.557 | C10: 0.398 | D10: 0.412
A11: ROE | B11: 0.33 | C11: 0.35 | D11: 0.375
A12: ROIC | D12: 0.21
A13: Net debt / EBITDA | B13: -2 | C13: -1.9 | D13: -1.4
A14: Backlog / revenue | B14: =57100/11921 -> 4.7898666 | C14: =90900/19147 -> 4.74748 | D14: =125200/27486 -> 4.5550462

Sheet Peer & Sector
A1: Peer set & sector structure
A2: Dubai / GCC residential developers; EMAARDEV screens cheap on P/E with a large backlog and net cash.
A4: Peer | B4: P/E | C4: EV/EBITDA | D4: Div yield | E4: Note
A5: Emaar Development (EMAARDEV) | B5: 5.0x | C5: 2.7x | D5: 7.0% | E5: This study; deep value + net cash
A6: Emaar Properties (EMAAR) | B6: ~9x | C6: ~6x | D6: ~5% | E6: Parent; diversified (malls/hotels)
A7: Aldar Properties (Abu Dhabi) | B7: ~12x | C7: ~11x | D7: ~3% | E7: Diversified dev + recurring
A8: DAMAC / Deyaar / Union Props | B8: 6–10x | C8: 4–8x | D8: 3–6% | E8: Smaller Dubai developers
A9: Sector | B9: — | C9: — | D9: — | E9: Dubai residential up-cycle; rising 2026-27 supply
