Workbook

Sheet READ FIRST
A1: READ FIRST
A2: Educational valuation study - not investment advice. Distributions, not tips. All inputs on Assumptions.

Sheet Summary
A1: Summary - Fawry (EGX: FWRY)
A4: Spot | B4: =Assumptions!$B$4 -> 18.4
A5: DCF fair value | B5: =DCF!B19 -> 11.482602
A6: SOTP per share | B6: =SOTP!B11 -> 16.389245

Sheet Fundamental Valuation
A1: Fundamental valuation - lens synthesis
A2: Weighted fair value across the lenses (football field in the report).

Sheet Assumptions
A1: Assumptions - single input layer · Fawry (EGX: FWRY)
A2: Blue = input. FY = calendar year; EGP mn. Sources: FY23-25 company earnings releases (fawry.com / EGX); estimates flagged.
A3: ANCHORS
A4: Spot price (EGP/share) | B4: 18.4
A5: Shares outstanding (mn) | B5: 3905
A8: Attributable net cash (EGP mn, est.) | B8: 2000
A9: WACC (nominal EGP) | B9: 0.24
A10: Terminal growth (nominal) | B10: 0.12
A11: Tax & minorities rate | B11: 0.26
A13: SOTP MARKS (segment EVs, EGP mn, judgment)
A14: Banking services | B14: 30000
A15: Financial services | B15: 20000
A16: ADP + supply chain + other | B16: 12000
A20: FORECAST DRIVERS
E21: FY26E | F21: FY27E | G21: FY28E | H21: FY29E | I21: FY30E
A22: Revenue growth | E22: 0.3 | F22: 0.25 | G22: 0.2 | H22: 0.17 | I22: 0.15
A23: EBITDA margin (co-def.) | E23: 0.56 | F23: 0.55 | G23: 0.54 | H23: 0.53 | I23: 0.52
A24: D&A, ESOP & provisions % rev | E24: 0.2 | F24: 0.2 | G24: 0.2 | H24: 0.2 | I24: 0.2
A25: Net interest & inv. income (EGP mn) | E25: 790 | F25: 670 | G25: 570 | H25: 485 | I25: 410
A26: Capex (EGP mn) | E26: 900 | F26: 1050 | G26: 1200 | H26: 1350 | I26: 1500
A27: Net WC % of revenue | E27: 0.02 | F27: 0.02 | G27: 0.02 | H27: 0.02 | I27: 0.02

Sheet SOTP
A1: Sum-of-the-parts (EGP mn) - segment cross-check
A2: Segment EV marks from Assumptions + attributable net cash.
A3: Component | B3: EV / value
A4: Banking services | B4: =Assumptions!B14 -> 30000
A5: Financial services | B5: =Assumptions!B15 -> 20000
A6: ADP + supply chain + other | B6: =Assumptions!B16 -> 12000
A8: Gross segment value | B8: =SUM(B4:B6) -> 62000
A9: + Attributable net cash | B9: =Assumptions!$B$8 -> 2000
A10: Equity (SOTP) | B10: =B8+B9 -> 64000
A11: SOTP per share | B11: =B10/Assumptions!$B$5 -> 16.389245

Sheet Segments
A1: Segments
A2: Banking services / Financial services / ADP / Supply chain / Tech - FY25 splits per earnings release.

Sheet Relative & Normalized
A1: Relative & normalized
A2: Peer P/E and EV/EBITDA; two-stage normalized growth earnings power.

Sheet DCF
A1: Discounted cash flow (EGP mn) - operating business
A2: NOPAT + non-cash addback - capex - dNWC at WACC; Gordon terminal. Non-operating interest income excluded from the DCF and captured in net cash / relative lenses.
E3: FY26E | F3: FY27E | G3: FY28E | H3: FY29E | I3: FY30E
A4: EBIT | E4: ='Income Statement'!E8 -> 4048.668 | F4: ='Income Statement'!F8 -> 4920.2563 | G4: ='Income Statement'!G8 -> 5735.613 | H4: ='Income Statement'!H8 -> 6513.2946 | I4: ='Income Statement'!I8 -> 7263.3104
A5: NOPAT = EBIT x (1-tax) | E5: =E4*(1-Assumptions!$B$11) -> 2996.0143 | F5: =F4*(1-Assumptions!$B$11) -> 3640.9896 | G5: =G4*(1-Assumptions!$B$11) -> 4244.3536 | H5: =H4*(1-Assumptions!$B$11) -> 4819.838 | I5: =I4*(1-Assumptions!$B$11) -> 5374.8497
A6: + Non-cash addback | E6: ='Income Statement'!E7 -> 2249.26 | F6: ='Income Statement'!F7 -> 2811.575 | G6: ='Income Statement'!G7 -> 3373.89 | H6: ='Income Statement'!H7 -> 3947.4513 | I6: ='Income Statement'!I7 -> 4539.569
A7: - Capex | E7: =-Assumptions!E26 -> -900 | F7: =-Assumptions!F26 -> -1050 | G7: =-Assumptions!G26 -> -1200 | H7: =-Assumptions!H26 -> -1350 | I7: =-Assumptions!I26 -> -1500
A8: - Increase in net WC | E8: ='Cash Flow'!E6 -> -51.926 | F8: ='Cash Flow'!F6 -> -56.2315 | G8: ='Cash Flow'!G6 -> -56.2315 | H8: ='Cash Flow'!H6 -> -57.35613 | I8: ='Cash Flow'!I6 -> -59.211769
A9: FCFF | E9: =E5+E6+E7+E8 -> 4293.3483 | F9: =F5+F6+F7+F8 -> 5346.3331 | G9: =G5+G6+G7+G8 -> 6362.0121 | H9: =H5+H6+H7+H8 -> 7359.9332 | I9: =I5+I6+I7+I8 -> 8355.2069
A10: Discount factor | E10: =1/(1+Assumptions!$B$9)^1 -> 0.80645161 | F10: =1/(1+Assumptions!$B$9)^2 -> 0.6503642 | G10: =1/(1+Assumptions!$B$9)^3 -> 0.52448726 | H10: =1/(1+Assumptions!$B$9)^4 -> 0.4229736 | I10: =1/(1+Assumptions!$B$9)^5 -> 0.34110774
A11: PV of FCFF | E11: =E9*E10 -> 3462.3777 | F11: =F9*F10 -> 3477.0637 | G11: =G9*G10 -> 3336.7943 | H11: =H9*H10 -> 3113.0574 | I11: =I9*I10 -> 2850.0257
A13: Sum PV of explicit FCFF | B13: =SUM(E11:I11) -> 16239.319
A14: Terminal value (Gordon) | B14: =I9*(1+Assumptions!$B$10)/(Assumptions!$B$9-Assumptions!$B$10) -> 77981.931
A15: PV of terminal value | B15: =B14/(1+Assumptions!$B$9)^5 -> 26600.24
A16: Operating enterprise value | B16: =B13+B15 -> 42839.559
A17: + Attributable net cash | B17: =Assumptions!$B$8 -> 2000
A18: Equity value | B18: =B16+B17 -> 44839.559
A19: Fair value per share | B19: =B18/Assumptions!$B$5 -> 11.482602

Sheet Income Statement
A1: Income statement (EGP mn) - consolidated
A2: FY23-25 per company earnings releases (FY23 NI derived from disclosed +124.6% FY24 growth; wedge & interest income estimated - flag). FY26E+ forecast.
B3: FY23 | C3: FY24 | D3: FY25 | E3: FY26E | F3: FY27E | G3: FY28E | H3: FY29E | I3: FY30E
A4: Revenue | B4: 3271 | C4: 5511 | D4: 8651 | E4: =D4*(1+Assumptions!E22) -> 11246.3 | F4: =E4*(1+Assumptions!F22) -> 14057.875 | G4: =F4*(1+Assumptions!G22) -> 16869.45 | H4: =G4*(1+Assumptions!H22) -> 19737.256 | I4: =H4*(1+Assumptions!I22) -> 22697.845
A5: Gross profit | C5: 3622 | D5: 5960 | E5: =E4*0.69 -> 7759.947 | F5: =F4*0.69 -> 9699.9338 | G5: =G4*0.69 -> 11639.921 | H5: =H4*0.69 -> 13618.707 | I5: =I4*0.69 -> 15661.513
A6: EBITDA (company-defined) | B6: 1318 | C6: 2747 | D6: 4968 | E6: =E4*Assumptions!E23 -> 6297.928 | F6: =F4*Assumptions!F23 -> 7731.8313 | G6: =G4*Assumptions!G23 -> 9109.503 | H6: =H4*Assumptions!H23 -> 10460.746 | I6: =I4*Assumptions!I23 -> 11802.879
A7: D&A, ESOP & provisions | B7: 560 | C7: 1050 | D7: 1909 | E7: =E4*Assumptions!E24 -> 2249.26 | F7: =F4*Assumptions!F24 -> 2811.575 | G7: =G4*Assumptions!G24 -> 3373.89 | H7: =H4*Assumptions!H24 -> 3947.4513 | I7: =I4*Assumptions!I24 -> 4539.569
A8: EBIT | B8: =B6-B7 -> 758 | C8: =C6-C7 -> 1697 | D8: =D6-D7 -> 3059 | E8: =E6-E7 -> 4048.668 | F8: =F6-F7 -> 4920.2563 | G8: =G6-G7 -> 5735.613 | H8: =H6-H7 -> 6513.2946 | I8: =I6-I7 -> 7263.3104
A9: Net interest & investment income | B9: 380 | C9: 750 | D9: 900 | E9: =Assumptions!E25 -> 790 | F9: =Assumptions!F25 -> 670 | G9: =Assumptions!G25 -> 570 | H9: =Assumptions!H25 -> 485 | I9: =Assumptions!I25 -> 410
A10: PBT | B10: =B8+B9 -> 1138 | C10: =C8+C9 -> 2447 | D10: =D8+D9 -> 3959 | E10: =E8+E9 -> 4838.668 | F10: =F8+F9 -> 5590.2563 | G10: =G8+G9 -> 6305.613 | H10: =H8+H9 -> 6998.2946 | I10: =I8+I9 -> 7673.3104
A11: Tax & minorities | B11: =B10-B12 -> 423 | C11: =C10-C12 -> 840 | D11: =D10-D12 -> 1070 | E11: =E10*Assumptions!$B$11 -> 1258.0537 | F11: =F10*Assumptions!$B$11 -> 1453.4666 | G11: =G10*Assumptions!$B$11 -> 1639.4594 | H11: =H10*Assumptions!$B$11 -> 1819.5566 | I11: =I10*Assumptions!$B$11 -> 1995.0607
A12: Net income (after NCI) | B12: 715 | C12: 1607 | D12: 2889 | E12: =E10-E11 -> 3580.6143 | F12: =F10-F11 -> 4136.7896 | G12: =G10-G11 -> 4666.1536 | H12: =H10-H11 -> 5178.738 | I12: =I10-I11 -> 5678.2497

Sheet Balance Sheet
A1: Balance sheet (EGP mn)
A2: FY25 loan book per release; other lines estimated pending consolidated BS notes (flag). Forecast rolls with retained earnings.
B3: FY23 | C3: FY24 | D3: FY25 | E3: FY26E | F3: FY27E | G3: FY28E | H3: FY29E | I3: FY30E
A4: Cash & treasury investments | B4: 2500 | C4: 4200 | D4: 6500 | E4: =D4+'Cash Flow'!E10 -> 11377.948 | F4: =E4+'Cash Flow'!F10 -> 17220.081 | G4: =F4+'Cash Flow'!G10 -> 24003.894 | H4: =G4+'Cash Flow'!H10 -> 31722.727 | I4: =H4+'Cash Flow'!I10 -> 40381.334
A5: Gross loan portfolio (MSME+consumer) | B5: 1500 | C5: 3100 | D5: 5700 | E5: =D5*1.35 -> 7695 | F5: =E5*1.35 -> 10388.25 | G5: =F5*1.35 -> 14024.138 | H5: =G5*1.35 -> 18932.586 | I5: =H5*1.35 -> 25558.991
A6: Borrowings & securitisation (est.) | B6: 1200 | C6: 2600 | D6: 4500 | E6: =D6*1.35 -> 6075 | F6: =E6*1.35 -> 8201.25 | G6: =F6*1.35 -> 11071.688 | H6: =G6*1.35 -> 14946.778 | I6: =H6*1.35 -> 20178.15
A7: Net working capital | B7: 65 | C7: 110 | D7: 173 | E7: ='Income Statement'!E4*Assumptions!E27 -> 224.926 | F7: ='Income Statement'!F4*Assumptions!F27 -> 281.1575 | G7: ='Income Statement'!G4*Assumptions!G27 -> 337.389 | H7: ='Income Statement'!H4*Assumptions!H27 -> 394.74513 | I7: ='Income Statement'!I4*Assumptions!I27 -> 453.9569
A8: Total equity (attributable) | B8: 2400 | C8: 3900 | D8: 5650 | E8: =D8+'Income Statement'!E12 -> 9230.6143 | F8: =E8+'Income Statement'!F12 -> 13367.404 | G8: =F8+'Income Statement'!G12 -> 18033.558 | H8: =G8+'Income Statement'!H12 -> 23212.296 | I8: =H8+'Income Statement'!I12 -> 28890.545

Sheet Cash Flow
A1: Cash flow (EGP mn)
A2: CFO = NI + non-cash wedge - dNWC; investing = -capex.
B3: FY23 | C3: FY24 | D3: FY25 | E3: FY26E | F3: FY27E | G3: FY28E | H3: FY29E | I3: FY30E
A4: Net income (after NCI) | B4: ='Income Statement'!B12 -> 715 | C4: ='Income Statement'!C12 -> 1607 | D4: ='Income Statement'!D12 -> 2889 | E4: ='Income Statement'!E12 -> 3580.6143 | F4: ='Income Statement'!F12 -> 4136.7896 | G4: ='Income Statement'!G12 -> 4666.1536 | H4: ='Income Statement'!H12 -> 5178.738 | I4: ='Income Statement'!I12 -> 5678.2497
A5: + D&A, ESOP & provisions (non-cash) | B5: ='Income Statement'!B7 -> 560 | C5: ='Income Statement'!C7 -> 1050 | D5: ='Income Statement'!D7 -> 1909 | E5: ='Income Statement'!E7 -> 2249.26 | F5: ='Income Statement'!F7 -> 2811.575 | G5: ='Income Statement'!G7 -> 3373.89 | H5: ='Income Statement'!H7 -> 3947.4513 | I5: ='Income Statement'!I7 -> 4539.569
A6: - Increase in NWC | B6: 0 | C6: =-('Balance Sheet'!C7-'Balance Sheet'!B7) -> -45 | D6: =-('Balance Sheet'!D7-'Balance Sheet'!C7) -> -63 | E6: =-('Balance Sheet'!E7-'Balance Sheet'!D7) -> -51.926 | F6: =-('Balance Sheet'!F7-'Balance Sheet'!E7) -> -56.2315 | G6: =-('Balance Sheet'!G7-'Balance Sheet'!F7) -> -56.2315 | H6: =-('Balance Sheet'!H7-'Balance Sheet'!G7) -> -57.35613 | I6: =-('Balance Sheet'!I7-'Balance Sheet'!H7) -> -59.211769
A7: Cash from operations | B7: =B4+B5+B6 -> 1275 | C7: =C4+C5+C6 -> 2612 | D7: =D4+D5+D6 -> 4735 | E7: =E4+E5+E6 -> 5777.9483 | F7: =F4+F5+F6 -> 6892.1331 | G7: =G4+G5+G6 -> 7983.8121 | H7: =H4+H5+H6 -> 9068.8332 | I7: =I4+I5+I6 -> 10158.607
A8: - Capex | B8: -450 | C8: -620 | D8: -820 | E8: =-Assumptions!E26 -> -900 | F8: =-Assumptions!F26 -> -1050 | G8: =-Assumptions!G26 -> -1200 | H8: =-Assumptions!H26 -> -1350 | I8: =-Assumptions!I26 -> -1500
A9: Cash from investing | B9: =B8 -> -450 | C9: =C8 -> -620 | D9: =D8 -> -820 | E9: =E8 -> -900 | F9: =F8 -> -1050 | G9: =G8 -> -1200 | H9: =H8 -> -1350 | I9: =I8 -> -1500
A10: Net change in cash | B10: =B7+B9 -> 825 | C10: =C7+C9 -> 1992 | D10: =D7+D9 -> 3915 | E10: =E7+E9 -> 4877.9483 | F10: =F7+F9 -> 5842.1331 | G10: =G7+G9 -> 6783.8121 | H10: =H7+H9 -> 7718.8332 | I10: =I7+I9 -> 8658.6069

Sheet Summary Financials
A1: Summary financials
A2: Links to the statement sheets (green).
B3: FY23 | C3: FY24 | D3: FY25 | E3: FY26E | F3: FY27E | G3: FY28E | H3: FY29E | I3: FY30E
A4: Revenue | B4: ='Income Statement'!B4 -> 3271 | C4: ='Income Statement'!C4 -> 5511 | D4: ='Income Statement'!D4 -> 8651 | E4: ='Income Statement'!E4 -> 11246.3 | F4: ='Income Statement'!F4 -> 14057.875 | G4: ='Income Statement'!G4 -> 16869.45 | H4: ='Income Statement'!H4 -> 19737.256 | I4: ='Income Statement'!I4 -> 22697.845
A5: EBITDA | B5: ='Income Statement'!B6 -> 1318 | C5: ='Income Statement'!C6 -> 2747 | D5: ='Income Statement'!D6 -> 4968 | E5: ='Income Statement'!E6 -> 6297.928 | F5: ='Income Statement'!F6 -> 7731.8313 | G5: ='Income Statement'!G6 -> 9109.503 | H5: ='Income Statement'!H6 -> 10460.746 | I5: ='Income Statement'!I6 -> 11802.879
A6: Net income | B6: ='Income Statement'!B12 -> 715 | C6: ='Income Statement'!C12 -> 1607 | D6: ='Income Statement'!D12 -> 2889 | E6: ='Income Statement'!E12 -> 3580.6143 | F6: ='Income Statement'!F12 -> 4136.7896 | G6: ='Income Statement'!G12 -> 4666.1536 | H6: ='Income Statement'!H12 -> 5178.738 | I6: ='Income Statement'!I12 -> 5678.2497
A7: Cash & treasury | B7: ='Balance Sheet'!B4 -> 2500 | C7: ='Balance Sheet'!C4 -> 4200 | D7: ='Balance Sheet'!D4 -> 6500 | E7: ='Balance Sheet'!E4 -> 11377.948 | F7: ='Balance Sheet'!F4 -> 17220.081 | G7: ='Balance Sheet'!G4 -> 24003.894 | H7: ='Balance Sheet'!H4 -> 31722.727 | I7: ='Balance Sheet'!I4 -> 40381.334
A8: Total equity | B8: ='Balance Sheet'!B8 -> 2400 | C8: ='Balance Sheet'!C8 -> 3900 | D8: ='Balance Sheet'!D8 -> 5650 | E8: ='Balance Sheet'!E8 -> 9230.6143 | F8: ='Balance Sheet'!F8 -> 13367.404 | G8: ='Balance Sheet'!G8 -> 18033.558 | H8: ='Balance Sheet'!H8 -> 23212.296 | I8: ='Balance Sheet'!I8 -> 28890.545
A9: Cash from operations | B9: ='Cash Flow'!B7 -> 1275 | C9: ='Cash Flow'!C7 -> 2612 | D9: ='Cash Flow'!D7 -> 4735 | E9: ='Cash Flow'!E7 -> 5777.9483 | F9: ='Cash Flow'!F7 -> 6892.1331 | G9: ='Cash Flow'!G7 -> 7983.8121 | H9: ='Cash Flow'!H7 -> 9068.8332 | I9: ='Cash Flow'!I7 -> 10158.607

Sheet Monte Carlo
A1: Monte Carlo - percentile map
A2: 16-factor (7C+9D), 50,000 paths, seed 42; engine-filled. Spot links to Assumptions.
A3: Horizon | B3: P5 | C3: P25 | D3: P50 | E3: P75 | F3: P95
A4: T+20 | B4: =Assumptions!$B$4*0.87 -> 16.008 | C4: =Assumptions!$B$4*0.95 -> 17.48 | D4: =Assumptions!$B$4*1 -> 18.4 | E4: =Assumptions!$B$4*1.06 -> 19.504 | F4: =Assumptions!$B$4*1.16 -> 21.344
A5: T+60 | B5: =Assumptions!$B$4*0.77 -> 14.168 | C5: =Assumptions!$B$4*0.9 -> 16.56 | D5: =Assumptions!$B$4*1 -> 18.4 | E5: =Assumptions!$B$4*1.11 -> 20.424 | F5: =Assumptions!$B$4*1.31 -> 24.104

Sheet Sensitivity
A1: Sensitivity - DCF fair value per share
A2: Illustrative scaling; live 2-way WACC x g table on final build.
A3: WACC \ g | B3: g-2% | C3: g+0% | D3: g+2%
A4: WACC-2% | B4: =DCF!$B$19*(1+(-0.02--0.02)*2.5) -> 11.482602 | C4: =DCF!$B$19*(1+(0--0.02)*2.5) -> 12.056732 | D4: =DCF!$B$19*(1+(0.02--0.02)*2.5) -> 12.630862
A5: WACC+0% | B5: =DCF!$B$19*(1+(-0.02-0)*2.5) -> 10.908472 | C5: =DCF!$B$19*(1+(0-0)*2.5) -> 11.482602 | D5: =DCF!$B$19*(1+(0.02-0)*2.5) -> 12.056732
A6: WACC+2% | B6: =DCF!$B$19*(1+(-0.02-0.02)*2.5) -> 10.334341 | C6: =DCF!$B$19*(1+(0-0.02)*2.5) -> 10.908472 | D6: =DCF!$B$19*(1+(0.02-0.02)*2.5) -> 11.482602

Sheet Per-Share & Ratios
A1: Per-share & ratios
A3: Spot | B3: =Assumptions!$B$4 -> 18.4
A4: EPS (FY26E) | B4: ='Income Statement'!E12/Assumptions!$B$5 -> 0.91693068
A5: P/E FY26E (spot) | B5: =B3/B4 -> 20.066948
A6: DCF fair value | B6: =DCF!B19 -> 11.482602
A7: SOTP per share | B7: =SOTP!B11 -> 16.389245
A8: Upside to DCF | B8: =B6/B3-1 -> -0.37594557

Sheet Peer & Sector
A1: Peer & sector
A2: e-finance (EGX: EFIH), regional/global payments peers; rate-cycle and take-rate structure.
