Workbook

Sheet READ FIRST
A1: Testahil · Industries Qatar (QSE: IQCD) — Valuation Model
A3: What this workbook is | B3: An educational valuation model for Industries Qatar Q.P.S.C. (QSE: IQCD). It is not investment advice, not a recommendation, and carries no rating or price target.
A4: Reporting currency | B4: Qatari riyal (QR), pegged at USD/QR 3.64. Figures in QR billion unless a cell header states otherwise.
A5: The one input layer | B5: Every number a reader might change lives on the Assumptions sheet in blue. Every other cell is a black formula or a green cross-sheet link. Change one blue input and the whole model reprices.
A6: Primary lens | B6: Holding-company sum-of-the-parts (SOTP): each segment valued on normalized mid-cycle earnings × a justified multiple, plus net cash, less a holdco discount. Cross-checked by a consolidated FCFF DCF, relative multiples, normalized earnings power and a dividend-discount model.
A7: Two clocks | B7: (1) risk-adjusted fair value — the ~12-month anchor the five lenses trıangulate; (2) full-execution value — a multi-year ceiling if petrochemical normalization and the Ammonia-7 / Ras Laffan pipeline all land. Only the Monte Carlo percentiles are genuine three-month figures.
A8: Anchor | B8: Spot QR 11.07 at close on 05 Jul 2026 · 6.05bn shares · market cap ≈ QR 67.0bn.
A9: Disclosure | B9: The preparer may hold, and may in the future take or dispose of, a position in the security discussed in this report. Full disclaimer in the Word study.

Sheet Summary
A1: Summary — Industries Qatar (QSE: IQCD)
A3: Spot (QR) | B3: =Assumptions!B4 -> 11.07
A4: Shares (bn) | B4: =Assumptions!B5 -> 6.05
A5: Market cap (QRbn) | B5: =Assumptions!B4*Assumptions!B5 -> 66.9735
A6: Net cash (QRbn) | B6: =Assumptions!B6 -> 8.5
A7: SOTP fair value (QR) | B7: =SOTP!D11/Assumptions!B5 -> 10.377521
A8: DCF fair value (QR) | B8: =DCF!B23 -> 11.393885
A9: Relative fair value (QR) | B9: =Assumptions!B36*Assumptions!B37/Assumptions!B5 -> 11.016529
A10: Dividend yield (FY25) | B10: ='Income Statement'!D13/Assumptions!B4 -> 0.064204499
A11: Projected 3m annualized vol | B11: ='Monte Carlo'!B5 -> 0.21777498
A12: Blended central fair value (QR) | B12: ='Fundamental Valuation'!F9 -> 10.876368
A13: Central vs spot | B13: ='Fundamental Valuation'!F9/Assumptions!B4-1 -> -0.017491612
A15: Fairly valued: five lenses cluster near spot; the swing is petrochemical normalization plus Ammonia-7 / Ras Laffan delivery.

Sheet Fundamental Valuation
A1: Fundamental valuation — five lenses and blended central
A3: Lens | B3: Bear | C3: Base | D3: Bull | E3: Weight | F3: Contribution
A4: Sum-of-the-parts | B4: 5.87 | C4: =SOTP!D11/Assumptions!B5 -> 10.377521 | D4: 15.96 | E4: 0.35 | F4: =C4*E4 -> 3.6321322
A5: Consolidated DCF | B5: 7.7 | C5: =DCF!B23 -> 11.393885 | D5: 14.86 | E5: 0.2 | F5: =C5*E5 -> 2.2787769
A6: Relative multiples | B6: 7.74 | C6: =Assumptions!B36*Assumptions!B37/Assumptions!B5 -> 11.016529 | D6: 13.49 | E6: 0.15 | F6: =C6*E6 -> 1.6524793
A7: Normalized earnings | B7: 7.36 | C7: =(Assumptions!B10+Assumptions!B11+Assumptions!B12)*Assumptions!B37/Assumptions!B5 -> 11.016529 | D7: 14.18 | E7: 0.15 | F7: =C7*E7 -> 1.6524793
A8: Dividend discount | B8: 7.15 | C8: 11.07 | D8: 15.39 | E8: 0.15 | F8: =C8*E8 -> 1.6605
A9: Blended central (base) | F9: =SUM(F4:F8) -> 10.876368
A10: Spot (QR) | F10: =Assumptions!B4 -> 11.07
A11: Central vs spot | F11: =F9/F10-1 -> -0.017491612
A13: Football-field, not a blended point: the range is shown; the weighted central is a reference, not a target (device A-8).

Sheet Assumptions
A1: Assumptions — the single blue-cell input layer
A3: Market & structure
A4: Spot price | B4: 11.07 | C4: QR/sh | D4: QSE close 05-Jul-2026
A5: Shares outstanding | B5: 6.05 | C5: bn | D5: IQ FY2025
A6: Net cash (debt-free) | B6: 8.5 | C6: QR bn | D6: Q1-2026, no LT debt
A7: Holdco discount (base) | B7: 0.04 | D7: clean 3-seg, 100% payout
A9: Segment normalized earnings (QR bn, proportionate)
A10: Fertilizers (QAFCO 100%) — norm. NI | B10: 2.5 | C10: QR bn | D10: mid-cycle urea/ammonia
A11: Petrochemicals (QAPCO/QAFAC) — norm. NI | B11: 1.3 | C11: QR bn | D11: recovery from trough
A12: Steel (100%) — norm. NI | B12: 0.5 | C12: QR bn | D12: ex one-off reversal
A13: Segment justified P/E (×)
A14: Fertilizers P/E | B14: 14.5 | C14: x
A15: Petrochemicals P/E | B15: 13 | C15: x
A16: Steel P/E | B16: 7.5 | C16: x
A18: Cost of equity & DCF
A19: Risk-free rate (QAR, pegged) | B19: 0.045 | D19: Qatar 10y
A20: Equity risk premium | B20: 0.055
A21: Beta | B21: 0.95 | D21: defensive quasi-sovereign
A22: Cost of equity Ke = rf + β×ERP | B22: =B19+B21*B20 -> 0.09725
A23: WACC (≈ Ke, net cash / unlevered) | B23: =B22 -> 0.09725
A24: Terminal growth g | B24: 0.03 | D24: mature + pipeline
A25: Effective tax rate | B25: 0.03 | D25: low Qatari tax
A26: Interest income on cash | B26: 0.04 | D26: on net cash
A28: DCF drivers — proportionate (QR bn), FY26E–FY30E
B29: FY26E | C29: FY27E | D29: FY28E | E29: FY29E | F29: FY30E
A30: EBITDA | B30: 5.7 | C30: 6.3 | D30: 6.6 | E30: 6.9 | F30: 7.1
A31: Depreciation & amortization | B31: 1.8 | C31: 1.9 | D31: 2 | E31: 2 | F31: 2.1
A32: Capital expenditure | B32: 2 | C32: 1.9 | D32: 1.9 | E32: 2 | F32: 2.1
A33: Change in working capital | B33: 0.3 | C33: 0.3 | D33: 0.2 | E33: 0.2 | F33: 0.2
A35: Relative & DDM
A36: Normalized group NI (relative lens) | B36: 4.3 | C36: QR bn
A37: Justified P/E (vs 16.3x history) | B37: 15.5 | C37: x
A38: Next-12m DPS (DDM) | B38: 0.68 | C38: QR/sh | D38: 100% payout
A39: DDM stage-1 growth (5y) | B39: 0.05 | D39: Ammonia-7/Ras Laffan
A40: DDM terminal growth | B40: 0.03
A42: Blue = input · black = formula · green (other sheets) = link to Assumptions

Sheet SOTP
A1: Sum-of-the-parts (primary lens) — base case
A3: Segment | B3: Norm. NI (QRbn) | C3: P/E (x) | D3: EV (QRbn) | E3: % of segment EV
A4: Fertilizers (QAFCO 100%) | B4: =Assumptions!B10 -> 2.5 | C4: =Assumptions!B14 -> 14.5 | D4: =B4*C4 -> 36.25 | E4: =D4/$D$7 -> 0.6370826
A5: Petrochemicals (QAPCO/QAFAC) | B5: =Assumptions!B11 -> 1.3 | C5: =Assumptions!B15 -> 13 | D5: =B5*C5 -> 16.9 | E5: =D5/$D$7 -> 0.2970123
A6: Steel (100%) | B6: =Assumptions!B12 -> 0.5 | C6: =Assumptions!B16 -> 7.5 | D6: =B6*C6 -> 3.75 | E6: =D6/$D$7 -> 0.065905097
A7: Segment EV (sum) | D7: =SUM(D4:D6) -> 56.9
A8: Add: net cash | D8: =Assumptions!B6 -> 8.5
A9: Gross asset value | D9: =D7+D8 -> 65.4
A10: Less: holdco discount | C10: =Assumptions!B7 -> 0.04 | D10: =-D9*C10 -> -2.616
A11: Equity value | D11: =D9+D10 -> 62.784
A12: Fair value per share (QR) | D12: =D11/Assumptions!B5 -> 10.377521
A14: Segment marks are normalized mid-cycle earnings; petrochemicals is the swing leg (FY2025 trough QR0.7bn, Q1-2026 ≈ QR4mn).

Sheet Segments
A1: Segment detail — FY2025 actual and normalization
A3: Segment | B3: FY25 NI | C3: FY25 EBITDA mgn | D3: Q1-26 NI | E3: Norm. NI | F3: Basis
A4: Fertilizers (QAFCO 100%) | B4: 2.7 | C4: 0.46 | D4: 0.495 | E4: =Assumptions!B10 -> 2.5 | F4: World-scale, low-cost gas; +Ammonia-7 Q2-26
A5: Petrochemicals (QAPCO 80% / QAFAC 50%) | B5: 0.7 | D5: 0.004 | E5: =Assumptions!B11 -> 1.3 | F5: Trough; China oversupply; Ras Laffan ramp
A6: Steel (100%) | B6: 0.713 | D6: 0.196 | E6: =Assumptions!B12 -> 0.5 | F6: Restarted DRI; ex QR0.222bn reversal
A7: Group | B7: =SUM(B4:B6) -> 4.113 | D7: =SUM(D4:D6) -> 0.695 | E7: =SUM(E4:E6) -> 4.3
A9: Source: IQ FY2025 annual report; Q1-2026 press release (30-Apr-2026). Segment revenue/EBITDA on IQ's proportionate basis.

Sheet Relative & Normalized
A1: Relative multiples & normalized earnings power
A3: Relative multiples
A5: Normalized group net income (QRbn) | B5: =Assumptions!B36 -> 4.3
A6: Justified P/E (vs 16.3x 10y median) (x) | B6: =Assumptions!B37 -> 15.5
A7: Implied equity value (QRbn) | B7: =B5*B6 -> 66.65
A8: Fair value per share (QR) | B8: =B7/Assumptions!B5 -> 11.016529
A10: Normalized earnings power
A12: Fertilizers norm. NI | B12: =Assumptions!B10 -> 2.5
A13: Petrochemicals norm. NI | B13: =Assumptions!B11 -> 1.3
A14: Steel norm. NI | B14: =Assumptions!B12 -> 0.5
A15: Mid-cycle group NI (QRbn) | B15: =B12+B13+B14 -> 4.3
A16: Justified P/E (x) | B16: =Assumptions!B37 -> 15.5
A17: Fair value per share (QR) | B17: =B15*B16/Assumptions!B5 -> 11.016529

Sheet DCF
A1: Consolidated DCF — proportionate FCFF, five-year explicit forecast
A3: QR bn | B3: FY26E | C3: FY27E | D3: FY28E | E3: FY29E | F3: FY30E
A4: EBITDA | B4: =Assumptions!B30 -> 5.7 | C4: =Assumptions!C30 -> 6.3 | D4: =Assumptions!D30 -> 6.6 | E4: =Assumptions!E30 -> 6.9 | F4: =Assumptions!F30 -> 7.1
A5: Less: D&A | B5: =-Assumptions!B31 -> -1.8 | C5: =-Assumptions!C31 -> -1.9 | D5: =-Assumptions!D31 -> -2 | E5: =-Assumptions!E31 -> -2 | F5: =-Assumptions!F31 -> -2.1
A6: EBIT | B6: =B4+B5 -> 3.9 | C6: =C4+C5 -> 4.4 | D6: =D4+D5 -> 4.6 | E6: =E4+E5 -> 4.9 | F6: =F4+F5 -> 5
A7: Less: tax on EBIT | B7: =-B6*Assumptions!$B$25 -> -0.117 | C7: =-C6*Assumptions!$B$25 -> -0.132 | D7: =-D6*Assumptions!$B$25 -> -0.138 | E7: =-E6*Assumptions!$B$25 -> -0.147 | F7: =-F6*Assumptions!$B$25 -> -0.15
A8: NOPAT (EBIT×(1−t)) | B8: =B6+B7 -> 3.783 | C8: =C6+C7 -> 4.268 | D8: =D6+D7 -> 4.462 | E8: =E6+E7 -> 4.753 | F8: =F6+F7 -> 4.85
A9: Add back: D&A | B9: =Assumptions!B31 -> 1.8 | C9: =Assumptions!C31 -> 1.9 | D9: =Assumptions!D31 -> 2 | E9: =Assumptions!E31 -> 2 | F9: =Assumptions!F31 -> 2.1
A10: Less: capex | B10: =-Assumptions!B32 -> -2 | C10: =-Assumptions!C32 -> -1.9 | D10: =-Assumptions!D32 -> -1.9 | E10: =-Assumptions!E32 -> -2 | F10: =-Assumptions!F32 -> -2.1
A11: Less: Δ working capital | B11: =-Assumptions!B33 -> -0.3 | C11: =-Assumptions!C33 -> -0.3 | D11: =-Assumptions!D33 -> -0.2 | E11: =-Assumptions!E33 -> -0.2 | F11: =-Assumptions!F33 -> -0.2
A12: Free cash flow to firm | B12: =B8+B9+B10+B11 -> 3.283 | C12: =C8+C9+C10+C11 -> 3.968 | D12: =D8+D9+D10+D11 -> 4.362 | E12: =E8+E9+E10+E11 -> 4.553 | F12: =F8+F9+F10+F11 -> 4.65
A13: Discount factor | B13: =1/(1+Assumptions!$B$23)^1 -> 0.91136933 | C13: =1/(1+Assumptions!$B$23)^2 -> 0.83059406 | D13: =1/(1+Assumptions!$B$23)^3 -> 0.75697795 | E13: =1/(1+Assumptions!$B$23)^4 -> 0.68988649 | F13: =1/(1+Assumptions!$B$23)^5 -> 0.62874139
A14: PV of FCFF | B14: =B12*B13 -> 2.9920255 | C14: =C12*C13 -> 3.2957972 | D14: =D12*D13 -> 3.3019378 | E14: =E12*E13 -> 3.1410532 | F14: =F12*F13 -> 2.9236475
A16: Sum of PV (explicit) | B16: =SUM(B14:F14) -> 15.654461
A17: Terminal value (Gordon) | B17: =F12*(1+Assumptions!$B$24)/(Assumptions!$B$23-Assumptions!$B$24) -> 71.219331
A18: PV of terminal value | B18: =B17/(1+Assumptions!$B$23)^5 -> 44.778541
A19: Enterprise value | B19: =B16+B18 -> 60.433002
A20: TV as % of EV | B20: =B18/B19 -> 0.74096172
A21: Add: net cash | B21: =Assumptions!B6 -> 8.5
A22: Equity value | B22: =B19+B21 -> 68.933002
A23: Fair value per share (QR) | B23: =B22/Assumptions!B5 -> 11.393885
A25: WACC = Ke = rf + β×ERP (Assumptions). TV disclosed as % of EV (device A-7) and sensitized on the Sensitivity sheet. FCFF terminal ≈ net income (maintenance capex ≈ D&A).

Sheet Income Statement
A1: Appendix A.1 — Income statement (proportionate basis)
A3: QR bn | B3: FY23 | C3: FY24 | D3: FY25 | E3: FY26E | F3: FY27E | G3: FY28E | H3: FY29E | I3: FY30E
A4: Revenue | B4: 17.9 | C4: 16.4 | D4: 16.5 | E4: 16 | F4: 17 | G4: 17.6 | H4: 18.1 | I4: 18.5
A5: EBITDA | B5: 7 | C5: 6.6 | D5: 6.4 | E5: =Assumptions!B30 -> 5.7 | F5: =Assumptions!C30 -> 6.3 | G5: =Assumptions!D30 -> 6.6 | H5: =Assumptions!E30 -> 6.9 | I5: =Assumptions!F30 -> 7.1
A6: EBITDA margin | B6: =B5/B4 -> 0.39106145 | C6: =C5/C4 -> 0.40243902 | D6: =D5/D4 -> 0.38787879 | E6: =E5/E4 -> 0.35625 | F6: =F5/F4 -> 0.37058824 | G6: =G5/G4 -> 0.375 | H6: =H5/H4 -> 0.38121547 | I6: =I5/I4 -> 0.38378378
A7: Less: D&A | B7: -1.7 | C7: -1.75 | D7: -1.8 | E7: =-Assumptions!B31 -> -1.8 | F7: =-Assumptions!C31 -> -1.9 | G7: =-Assumptions!D31 -> -2 | H7: =-Assumptions!E31 -> -2 | I7: =-Assumptions!F31 -> -2.1
A8: EBIT | B8: =B5+B7 -> 5.3 | C8: =C5+C7 -> 4.85 | D8: =D5+D7 -> 4.6 | E8: =E5+E7 -> 3.9 | F8: =F5+F7 -> 4.4 | G8: =G5+G7 -> 4.6 | H8: =H5+H7 -> 4.9 | I8: =I5+I7 -> 5
A9: Net interest income | B9: 0.3 | C9: 0.3 | D9: 0.3 | E9: =Assumptions!$B$6*Assumptions!$B$26 -> 0.34 | F9: =Assumptions!$B$6*Assumptions!$B$26 -> 0.34 | G9: =Assumptions!$B$6*Assumptions!$B$26 -> 0.34 | H9: =Assumptions!$B$6*Assumptions!$B$26 -> 0.34 | I9: =Assumptions!$B$6*Assumptions!$B$26 -> 0.34
A10: Pre-tax profit | B10: =B8+B9 -> 5.6 | C10: =C8+C9 -> 5.15 | D10: =D8+D9 -> 4.9 | E10: =E8+E9 -> 4.24 | F10: =F8+F9 -> 4.74 | G10: =G8+G9 -> 4.94 | H10: =H8+H9 -> 5.24 | I10: =I8+I9 -> 5.34
A11: Tax | B11: =-B10*Assumptions!$B$25 -> -0.168 | C11: =-C10*Assumptions!$B$25 -> -0.1545 | D11: =-D10*Assumptions!$B$25 -> -0.147 | E11: =-E10*Assumptions!$B$25 -> -0.1272 | F11: =-F10*Assumptions!$B$25 -> -0.1422 | G11: =-G10*Assumptions!$B$25 -> -0.1482 | H11: =-H10*Assumptions!$B$25 -> -0.1572 | I11: =-I10*Assumptions!$B$25 -> -0.1602
A12: Net profit | B12: 4.7 | C12: 4.5 | D12: 4.3 | E12: =E10+E11 -> 4.1128 | F12: =F10+F11 -> 4.5978 | G12: =G10+G11 -> 4.7918 | H12: =H10+H11 -> 5.0828 | I12: =I10+I11 -> 5.1798
A13: EPS (QR) | B13: =B12/Assumptions!$B$5 -> 0.7768595 | C13: =C12/Assumptions!$B$5 -> 0.74380165 | D13: =D12/Assumptions!$B$5 -> 0.7107438 | E13: =E12/Assumptions!$B$5 -> 0.67980165 | F13: =F12/Assumptions!$B$5 -> 0.75996694 | G13: =G12/Assumptions!$B$5 -> 0.79203306 | H13: =H12/Assumptions!$B$5 -> 0.84013223 | I13: =I12/Assumptions!$B$5 -> 0.85616529
A14: DPS (QR, 100% payout) | B14: =B13 -> 0.7768595 | C14: =C13 -> 0.74380165 | D14: =D13 -> 0.7107438 | E14: =E13 -> 0.67980165 | F14: =F13 -> 0.75996694 | G14: =G13 -> 0.79203306 | H14: =H13 -> 0.84013223 | I14: =I13 -> 0.85616529
A16: Historicals: IQ FY2023–FY2025 reported (proportionate). Forecast net profit computed from EBITDA→EBIT→pre-tax→tax; historicals shown as reported.

Sheet Balance Sheet
A1: Appendix A.2 — Balance sheet (summary, IFRS)
A3: QR bn | B3: FY23 | C3: FY24 | D3: FY25 | E3: FY26E | F3: FY27E | G3: FY28E | H3: FY29E | I3: FY30E
A4: Cash & bank balances | B4: 9.9 | C4: 9.2 | D4: 8.5 | E4: =D4 -> 8.5 | F4: =E4 -> 8.5 | G4: =F4 -> 8.5 | H4: =G4 -> 8.5 | I4: =H4 -> 8.5
A5: Other current assets | B5: 7.5 | C5: 7.6 | D5: 7.7 | E5: =D5 -> 7.7 | F5: =E5 -> 7.7 | G5: =F5 -> 7.7 | H5: =G5 -> 7.7 | I5: =H5 -> 7.7
A6: PP&E and projects | B6: 19.5 | C6: 19.8 | D6: 20 | E6: =D6 -> 20 | F6: =E6 -> 20 | G6: =F6 -> 20 | H6: =G6 -> 20 | I6: =H6 -> 20
A7: Investments & other | B7: 4.3 | C7: 4.4 | D7: 4.5 | E7: =D7 -> 4.5 | F7: =E7 -> 4.5 | G7: =F7 -> 4.5 | H7: =G7 -> 4.5 | I7: =H7 -> 4.5
A8: Total assets | B8: =SUM(B4:B7) -> 41.2 | C8: =SUM(C4:C7) -> 41 | D8: =SUM(D4:D7) -> 40.7 | E8: =SUM(E4:E7) -> 40.7 | F8: =SUM(F4:F7) -> 40.7 | G8: =SUM(G4:G7) -> 40.7 | H8: =SUM(H4:H7) -> 40.7 | I8: =SUM(I4:I7) -> 40.7
A9: Total liabilities (no LT debt) | B9: 2.1 | C9: 2 | D9: 2 | E9: 2 | F9: 2 | G9: 2 | H9: 2 | I9: 2
A10: Total equity | B10: =B8-B9 -> 39.1 | C10: =C8-C9 -> 39 | D10: =D8-D9 -> 38.7 | E10: =E8-E9 -> 38.7 | F10: =F8-F9 -> 38.7 | G10: =G8-G9 -> 38.7 | H10: =H8-H9 -> 38.7 | I10: =I8-I9 -> 38.7
A12: Source: IQ FY2025 annual report & Q1-2026 release. Debt-free; net cash ≈ QR8.5bn. Forecast balances held broadly flat (100% payout).

Sheet Cash Flow
A1: Appendix A.3 — Cash flow (summary)
A3: QR bn | B3: FY23 | C3: FY24 | D3: FY25 | E3: FY26E | F3: FY27E | G3: FY28E | H3: FY29E | I3: FY30E
A4: Operating cash flow | B4: 4.8 | C4: 4.6 | D4: 4.4 | E4: ='Income Statement'!E12+Assumptions!B31-Assumptions!B33 -> 5.6128 | F4: ='Income Statement'!F12+Assumptions!C31-Assumptions!C33 -> 6.1978 | G4: ='Income Statement'!G12+Assumptions!D31-Assumptions!D33 -> 6.5918 | H4: ='Income Statement'!H12+Assumptions!E31-Assumptions!E33 -> 6.8828 | I4: ='Income Statement'!I12+Assumptions!F31-Assumptions!F33 -> 7.0798
A5: Less: capex | B5: -2.4 | C5: -2.3 | D5: -2.2 | E5: =-Assumptions!B32 -> -2 | F5: =-Assumptions!C32 -> -1.9 | G5: =-Assumptions!D32 -> -1.9 | H5: =-Assumptions!E32 -> -2 | I5: =-Assumptions!F32 -> -2.1
A6: Free cash flow | B6: =B4+B5 -> 2.4 | C6: =C4+C5 -> 2.3 | D6: =D4+D5 -> 2.2 | E6: =E4+E5 -> 3.6128 | F6: =F4+F5 -> 4.2978 | G6: =G4+G5 -> 4.6918 | H6: =H4+H5 -> 4.8828 | I6: =I4+I5 -> 4.9798
A7: Dividends paid | B7: -4.7 | C7: -4.5 | D7: -4.3 | E7: =-'Income Statement'!E12 -> -4.1128 | F7: =-'Income Statement'!F12 -> -4.5978 | G7: =-'Income Statement'!G12 -> -4.7918 | H7: =-'Income Statement'!H12 -> -5.0828 | I7: =-'Income Statement'!I12 -> -5.1798
A9: 100% dividend payout; capex elevated in FY23–26 (Ammonia-7) then normalizing toward maintenance ≈ D&A.

Sheet Summary Financials
A1: Summary financials (every cell links to the statement sheets)
A3: QR bn | B3: FY23 | C3: FY24 | D3: FY25 | E3: FY26E | F3: FY27E | G3: FY28E | H3: FY29E | I3: FY30E
A4: Revenue | B4: ='Income Statement'!B4 -> 17.9 | C4: ='Income Statement'!C4 -> 16.4 | D4: ='Income Statement'!D4 -> 16.5 | E4: ='Income Statement'!E4 -> 16 | F4: ='Income Statement'!F4 -> 17 | G4: ='Income Statement'!G4 -> 17.6 | H4: ='Income Statement'!H4 -> 18.1 | I4: ='Income Statement'!I4 -> 18.5
A5: EBITDA | B5: ='Income Statement'!B5 -> 7 | C5: ='Income Statement'!C5 -> 6.6 | D5: ='Income Statement'!D5 -> 6.4 | E5: ='Income Statement'!E5 -> 5.7 | F5: ='Income Statement'!F5 -> 6.3 | G5: ='Income Statement'!G5 -> 6.6 | H5: ='Income Statement'!H5 -> 6.9 | I5: ='Income Statement'!I5 -> 7.1
A6: EBIT | B6: ='Income Statement'!B8 -> 5.3 | C6: ='Income Statement'!C8 -> 4.85 | D6: ='Income Statement'!D8 -> 4.6 | E6: ='Income Statement'!E8 -> 3.9 | F6: ='Income Statement'!F8 -> 4.4 | G6: ='Income Statement'!G8 -> 4.6 | H6: ='Income Statement'!H8 -> 4.9 | I6: ='Income Statement'!I8 -> 5
A7: Net profit | B7: ='Income Statement'!B12 -> 4.7 | C7: ='Income Statement'!C12 -> 4.5 | D7: ='Income Statement'!D12 -> 4.3 | E7: ='Income Statement'!E12 -> 4.1128 | F7: ='Income Statement'!F12 -> 4.5978 | G7: ='Income Statement'!G12 -> 4.7918 | H7: ='Income Statement'!H12 -> 5.0828 | I7: ='Income Statement'!I12 -> 5.1798
A8: EPS (QR) | B8: ='Income Statement'!B13 -> 0.7768595 | C8: ='Income Statement'!C13 -> 0.74380165 | D8: ='Income Statement'!D13 -> 0.7107438 | E8: ='Income Statement'!E13 -> 0.67980165 | F8: ='Income Statement'!F13 -> 0.75996694 | G8: ='Income Statement'!G13 -> 0.79203306 | H8: ='Income Statement'!H13 -> 0.84013223 | I8: ='Income Statement'!I13 -> 0.85616529
A9: Total assets | B9: ='Balance Sheet'!B8 -> 41.2 | C9: ='Balance Sheet'!C8 -> 41 | D9: ='Balance Sheet'!D8 -> 40.7 | E9: ='Balance Sheet'!E8 -> 40.7 | F9: ='Balance Sheet'!F8 -> 40.7 | G9: ='Balance Sheet'!G8 -> 40.7 | H9: ='Balance Sheet'!H8 -> 40.7 | I9: ='Balance Sheet'!I8 -> 40.7
A10: Total equity | B10: ='Balance Sheet'!B10 -> 39.1 | C10: ='Balance Sheet'!C10 -> 39 | D10: ='Balance Sheet'!D10 -> 38.7 | E10: ='Balance Sheet'!E10 -> 38.7 | F10: ='Balance Sheet'!F10 -> 38.7 | G10: ='Balance Sheet'!G10 -> 38.7 | H10: ='Balance Sheet'!H10 -> 38.7 | I10: ='Balance Sheet'!I10 -> 38.7
A11: Free cash flow | B11: ='Cash Flow'!B6 -> 2.4 | C11: ='Cash Flow'!C6 -> 2.3 | D11: ='Cash Flow'!D6 -> 2.2 | E11: ='Cash Flow'!E6 -> 3.6128 | F11: ='Cash Flow'!F6 -> 4.2978 | G11: ='Cash Flow'!G6 -> 4.6918 | H11: ='Cash Flow'!H6 -> 4.8828 | I11: ='Cash Flow'!I6 -> 4.9798

Sheet Monte Carlo
A1: Monte Carlo — YZ-HAR engine, Student-t(5), 50,000 paths, seed 42
A3: Engine diagnostics
A4: Spot (QR) | B4: 11.07
A5: Projected annualized vol | B5: 0.21777498
A6: Variance ratio (60d) | B6: 0.86495956
A7: HAR persistence (β1+β5+β22) | B7: 0.32258547
A8: Net factor drift (3m) | B8: 0.006
A9: Secular own-history drift | B9: OFF (non-EGX)
A11: Percentile table
A12: Horizon | B12: p5 | C12: p25 | D12: p50 | E12: p75 | F12: p95
A13: T+20 | B13: 9.6189875 | C13: 10.600008 | D13: 11.129458 | E13: 11.674913 | F13: 12.731707
A14: T+60 | B14: 8.8397534 | C14: 10.239233 | D14: 11.212674 | E14: 12.2463 | F14: 14.080795
A16: Touch-probability ladder (T+60)
A17: Level (QR) | B17: P(touch by T+60)
A18: 13 | B18: 0.29
A19: 12 | B19: 0.58
A20: 11.5 | B20: 0.77
A21: 10.5 | B21: 0.5
A22: 10 | B22: 0.29
A23: 9.5 | B23: 0.16
A25: Width from the YZ-HAR variance cascade; shape unit-variance t(5); drift OFF plus small net factor tilt. Value gap kept out of the drift.

Sheet Sensitivity
A1: Sensitivity — DCF fair value on WACC × terminal-g
A3: WACC \ g | B3: 0.02 | C3: 0.025 | D3: 0.03 | E3: 0.035 | F3: 0.04
A4: 0.09 | B4: =((SUMPRODUCT(DCF!$B$12:$F$12,1/(1+0.09)^{1,2,3,4,5}))+ (DCF!$F$12*(1+0.02)/(0.09-0.02))/(1+0.09)^5 + Assumptions!$B$6)/Assumptions!$B$5 -> 11.323159 | C4: =((SUMPRODUCT(DCF!$B$12:$F$12,1/(1+0.09)^{1,2,3,4,5}))+ (DCF!$F$12*(1+0.025)/(0.09-0.025))/(1+0.09)^5 + Assumptions!$B$6)/Assumptions!$B$5 -> 11.921502 | D4: =((SUMPRODUCT(DCF!$B$12:$F$12,1/(1+0.09)^{1,2,3,4,5}))+ (DCF!$F$12*(1+0.03)/(0.09-0.03))/(1+0.09)^5 + Assumptions!$B$6)/Assumptions!$B$5 -> 12.619569 | E4: =((SUMPRODUCT(DCF!$B$12:$F$12,1/(1+0.09)^{1,2,3,4,5}))+ (DCF!$F$12*(1+0.035)/(0.09-0.035))/(1+0.09)^5 + Assumptions!$B$6)/Assumptions!$B$5 -> 13.444557 | F4: =((SUMPRODUCT(DCF!$B$12:$F$12,1/(1+0.09)^{1,2,3,4,5}))+ (DCF!$F$12*(1+0.04)/(0.09-0.04))/(1+0.09)^5 + Assumptions!$B$6)/Assumptions!$B$5 -> 14.434542
A5: 0.095 | B5: =((SUMPRODUCT(DCF!$B$12:$F$12,1/(1+0.095)^{1,2,3,4,5}))+ (DCF!$F$12*(1+0.02)/(0.095-0.02))/(1+0.095)^5 + Assumptions!$B$6)/Assumptions!$B$5 -> 10.648334 | C5: =((SUMPRODUCT(DCF!$B$12:$F$12,1/(1+0.095)^{1,2,3,4,5}))+ (DCF!$F$12*(1+0.025)/(0.095-0.025))/(1+0.095)^5 + Assumptions!$B$6)/Assumptions!$B$5 -> 11.157491 | D5: =((SUMPRODUCT(DCF!$B$12:$F$12,1/(1+0.095)^{1,2,3,4,5}))+ (DCF!$F$12*(1+0.03)/(0.095-0.03))/(1+0.095)^5 + Assumptions!$B$6)/Assumptions!$B$5 -> 11.74498 | E5: =((SUMPRODUCT(DCF!$B$12:$F$12,1/(1+0.095)^{1,2,3,4,5}))+ (DCF!$F$12*(1+0.035)/(0.095-0.035))/(1+0.095)^5 + Assumptions!$B$6)/Assumptions!$B$5 -> 12.430384 | F5: =((SUMPRODUCT(DCF!$B$12:$F$12,1/(1+0.095)^{1,2,3,4,5}))+ (DCF!$F$12*(1+0.04)/(0.095-0.04))/(1+0.095)^5 + Assumptions!$B$6)/Assumptions!$B$5 -> 13.240406
A6: 0.1 | B6: =((SUMPRODUCT(DCF!$B$12:$F$12,1/(1+0.1)^{1,2,3,4,5}))+ (DCF!$F$12*(1+0.02)/(0.1-0.02))/(1+0.1)^5 + Assumptions!$B$6)/Assumptions!$B$5 -> 10.058023 | C6: =((SUMPRODUCT(DCF!$B$12:$F$12,1/(1+0.1)^{1,2,3,4,5}))+ (DCF!$F$12*(1+0.025)/(0.1-0.025))/(1+0.1)^5 + Assumptions!$B$6)/Assumptions!$B$5 -> 10.49549 | D6: =((SUMPRODUCT(DCF!$B$12:$F$12,1/(1+0.1)^{1,2,3,4,5}))+ (DCF!$F$12*(1+0.03)/(0.1-0.03))/(1+0.1)^5 + Assumptions!$B$6)/Assumptions!$B$5 -> 10.995453 | E6: =((SUMPRODUCT(DCF!$B$12:$F$12,1/(1+0.1)^{1,2,3,4,5}))+ (DCF!$F$12*(1+0.035)/(0.1-0.035))/(1+0.1)^5 + Assumptions!$B$6)/Assumptions!$B$5 -> 11.572332 | F6: =((SUMPRODUCT(DCF!$B$12:$F$12,1/(1+0.1)^{1,2,3,4,5}))+ (DCF!$F$12*(1+0.04)/(0.1-0.04))/(1+0.1)^5 + Assumptions!$B$6)/Assumptions!$B$5 -> 12.245359
A7: 0.105 | B7: =((SUMPRODUCT(DCF!$B$12:$F$12,1/(1+0.105)^{1,2,3,4,5}))+ (DCF!$F$12*(1+0.02)/(0.105-0.02))/(1+0.105)^5 + Assumptions!$B$6)/Assumptions!$B$5 -> 9.5373086 | C7: =((SUMPRODUCT(DCF!$B$12:$F$12,1/(1+0.105)^{1,2,3,4,5}))+ (DCF!$F$12*(1+0.025)/(0.105-0.025))/(1+0.105)^5 + Assumptions!$B$6)/Assumptions!$B$5 -> 9.91637 | D7: =((SUMPRODUCT(DCF!$B$12:$F$12,1/(1+0.105)^{1,2,3,4,5}))+ (DCF!$F$12*(1+0.03)/(0.105-0.03))/(1+0.105)^5 + Assumptions!$B$6)/Assumptions!$B$5 -> 10.345973 | E7: =((SUMPRODUCT(DCF!$B$12:$F$12,1/(1+0.105)^{1,2,3,4,5}))+ (DCF!$F$12*(1+0.035)/(0.105-0.035))/(1+0.105)^5 + Assumptions!$B$6)/Assumptions!$B$5 -> 10.836948 | F7: =((SUMPRODUCT(DCF!$B$12:$F$12,1/(1+0.105)^{1,2,3,4,5}))+ (DCF!$F$12*(1+0.04)/(0.105-0.04))/(1+0.105)^5 + Assumptions!$B$6)/Assumptions!$B$5 -> 11.403457
A8: 0.11 | B8: =((SUMPRODUCT(DCF!$B$12:$F$12,1/(1+0.11)^{1,2,3,4,5}))+ (DCF!$F$12*(1+0.02)/(0.11-0.02))/(1+0.11)^5 + Assumptions!$B$6)/Assumptions!$B$5 -> 9.0745898 | C8: =((SUMPRODUCT(DCF!$B$12:$F$12,1/(1+0.11)^{1,2,3,4,5}))+ (DCF!$F$12*(1+0.025)/(0.11-0.025))/(1+0.11)^5 + Assumptions!$B$6)/Assumptions!$B$5 -> 9.4055031 | D8: =((SUMPRODUCT(DCF!$B$12:$F$12,1/(1+0.11)^{1,2,3,4,5}))+ (DCF!$F$12*(1+0.03)/(0.11-0.03))/(1+0.11)^5 + Assumptions!$B$6)/Assumptions!$B$5 -> 9.7777805 | E8: =((SUMPRODUCT(DCF!$B$12:$F$12,1/(1+0.11)^{1,2,3,4,5}))+ (DCF!$F$12*(1+0.035)/(0.11-0.035))/(1+0.11)^5 + Assumptions!$B$6)/Assumptions!$B$5 -> 10.199695 | F8: =((SUMPRODUCT(DCF!$B$12:$F$12,1/(1+0.11)^{1,2,3,4,5}))+ (DCF!$F$12*(1+0.04)/(0.11-0.04))/(1+0.11)^5 + Assumptions!$B$6)/Assumptions!$B$5 -> 10.681883
A10: Grid reprices the DCF FCFF path (DCF sheet) at each WACC × g. Base case shaded on the DCF sheet; TV% of EV disclosed there.

Sheet Per-Share & Ratios
A1: Per-share & ratio dashboard
A3: Metric | B3: FY24 | C3: FY25 | D3: FY26E
A4: EPS (QR) | B4: ='Income Statement'!C13 -> 0.74380165 | C4: ='Income Statement'!D13 -> 0.7107438 | D4: ='Income Statement'!E13 -> 0.67980165
A5: DPS (QR) | B5: ='Income Statement'!C13 -> 0.74380165 | C5: ='Income Statement'!D13 -> 0.7107438 | D5: ='Income Statement'!E13 -> 0.67980165
A6: P/E (x) | B6: =Assumptions!$B$4/'Income Statement'!C13 -> 14.883 | C6: =Assumptions!$B$4/'Income Statement'!D13 -> 15.575233 | D6: =Assumptions!$B$4/'Income Statement'!E13 -> 16.284162
A7: Dividend yield | B7: ='Income Statement'!C13/Assumptions!$B$4 -> 0.067190755 | C7: ='Income Statement'!D13/Assumptions!$B$4 -> 0.064204499 | D7: ='Income Statement'!E13/Assumptions!$B$4 -> 0.061409363
A8: Net profit (QRbn) | B8: ='Income Statement'!C12 -> 4.5 | C8: ='Income Statement'!D12 -> 4.3 | D8: ='Income Statement'!E12 -> 4.1128
A9: EBITDA margin | B9: ='Income Statement'!C5/'Income Statement'!C4 -> 0.40243902 | C9: ='Income Statement'!D5/'Income Statement'!D4 -> 0.38787879 | D9: ='Income Statement'!E5/'Income Statement'!E4 -> 0.35625
A10: Net cash (QRbn) | B10: =Assumptions!$B$6 -> 8.5 | C10: =Assumptions!$B$6 -> 8.5 | D10: =Assumptions!$B$6 -> 8.5
A11: Payout ratio | B11: =1 -> 1 | C11: =1 -> 1 | D11: =1 -> 1
A13: Identical panel across every Testahil study (device A-5). Spot-based multiples use the anchor price.

Sheet Peer & Sector
A1: Peer set & sector structure
A3: Peer | B3: P/E (x) | C3: EV/EBITDA | D3: Div yield | E3: Note
A4: SABIC (Saudi) | B4: 18 | C4: 8.5 | D4: 0.045 | E4: Global chemicals bellwether
A5: Sipchem / Advanced (Saudi) | B5: 15 | C5: 7.5 | D5: 0.05 | E5: GCC petrochemicals
A6: CF Industries (US) | B6: 11 | C6: 6.5 | D6: 0.02 | E6: Pure-play nitrogen
A7: Nutrien / Yara | B7: 12 | C7: 6 | D7: 0.05 | E7: Global fertilizer majors
A8: QSE large-cap median | B8: 15.5 | C8: 9 | D8: 0.045 | E8: Local quasi-sovereign premium
A9: Industries Qatar (IQCD) | B9: 15.6 | D9: 0.059 | E9: Spot; ~16.3x 10y median
A11: Peer multiples indicative (regional/aggregator sources). On global sector peers the parts screen fairly-to-fully valued; the QSE quasi-sovereign premium supports the group multiple.
