Workbook

Sheet READ FIRST
A1: Testahil · Independent Valuation Study — Educational Analysis
B3: Lecico Egypt (S.A.E.) · EGX: LCSW
B5: This workbook is an educational valuation exercise and a personal analytical opinion, published free of charge.
B6: It is NOT investment advice, NOT a recommendation, and NOT a solicitation to buy, sell or hold any security.
B7: The preparer is not licensed by any securities regulator (incl. Egypt's FRA), manages no money, and takes no clients.
B8: All values are model outputs shown as ranges and distributions — no single number should be relied upon.
B9: Reported figures are Lecico's own disclosure (FY2025 results, 28 Feb 2026; Q1-2026 filing). Forward inputs are the
B10: preparer's judgments and are flagged throughout. Assumptions is the single blue-cell input layer: change an input and
B11: the whole model reprices. See the Disclosure & Disclaimer in the study. Consult a licensed advisor before investing.
B12: Colour key: BLUE = input you can change · BLACK = formula · GREEN = link to another sheet.
B14: Distributions, not tips — fair-value ranges and probabilities, never a target or rating.

Sheet Summary
A1: Valuation summary — every read at a glance
A3: Lens / read | B3: Output | C3: Takeaway
A4: FUNDAMENTAL — what the business is worth (anchor)
A5: FCFF DCF (primary) | B5: ='DCF — Primary Lens'!$B$26 -> 37.054814 | C5: see §1.1
A6: Weighted central (5 lenses) | B6: ='Fundamental Valuation'!$D$10 -> 37.266444 | C6: =B6/Assumptions!B4-1 -> 0.26541407
A7: TECHNICAL — what the tape is doing
A8: Trend vs 20/50/100/200-day | B8: Above all four | C8: Uptrend, RSI 61
A9: MONTE CARLO — 3-month price map (paths from spot)
A10: T+20 (p5 · p50 · p95) | B10: 24.3 · 30.0 · 37.0
A11: T+60 (p5 · p50 · p95) | B11: 21.7 · 31.0 · 44.4
A12: EXPERT PANEL — three methods (Appendix D)
A13: Expert 1 — Normalized earnings power + multiples | B13: 40
A14: Expert 2 — RNAV at realizable value + cash-conversion | B14: 31
A15: Expert 3 — DCF + ROIC vs WACC (economic profit) | B15: 35
A17: Bottom line: fair value ≈ EGP 37 (range 26–51), ~+26% vs spot 29.45; the swing is the EGP path and cash conversion.

Sheet Fundamental Valuation
A1: Fundamental valuation — five lenses
A2: Football-field synthesis; never a single blended point (device A-8).
A4: Lens | B4: Weight | C4: Bear | D4: Base | E4: Bull
A5: DCF (FCFF) | B5: 0.3 | C5: 21.72 | D5: ='DCF — Primary Lens'!$B$26 -> 37.054814 | E5: 61.25
A6: Relative multiples | B6: 0.2 | C6: 28 | D6: 39 | E6: 52
A7: Normalized earnings | B7: 0.25 | C7: 27 | D7: 39 | E7: 53
A8: FCFE / owner-earnings | B8: 0.1 | C8: 22 | D8: 32 | E8: 44
A9: Asset / reproduction | B9: 0.15 | C9: 30 | D9: 36 | E9: 44
A10: Weighted central | B10: =SUM(B5:B9) -> 1 | C10: =SUMPRODUCT($B$5:$B$9,C$5:C$9) -> 25.566 | D10: =SUMPRODUCT($B$5:$B$9,D$5:D$9) -> 37.266444 | E10: =SUMPRODUCT($B$5:$B$9,E$5:E$9) -> 53.025
A12: Central vs spot | B12: =D10/Assumptions!$B$4-1 -> 0.26541407
A14: Reads: modestly-to-meaningfully undervalued on fundamentals; held back by cash-conversion and EGP competitiveness.

Sheet Assumptions
A1: Assumptions — single blue-cell input layer
A3: Anchor & capital
A4: Spot price (EGP) | B4: 29.45 | G4: 6 Jul 2026 close (attached history)
A5: Shares outstanding (m) | B5: 80
A6: Net debt, reported Dec-2025 (EGP m) | B6: 1270 | G6: Bank facilities + current loans − cash
A7: Net debt incl. leases + LT notes (EGP m) | B7: 1660
A8: Tax rate (statutory) | B8: 0.225
A10: FY2025 base (actuals, EGP m)
A11: Revenue 2025 | B11: 7803.7
A12: EBITDA 2025 | B12: 980.8
A13: EBIT 2025 | B13: 742.6
A15: Forecast drivers (2026E–2030E)
B16: 2026E | C16: 2027E | D16: 2028E | E16: 2029E | F16: 2030E
A17: Revenue growth % | B17: 0.12 | C17: 0.13 | D17: 0.12 | E17: 0.11 | F17: 0.1
A18: EBITDA margin % | B18: 0.115 | C18: 0.125 | D18: 0.135 | E18: 0.14 | F18: 0.145
A19: D&A (EGP m) | B19: 265 | C19: 300 | D19: 340 | E19: 380 | F19: 420
A20: Capex (EGP m) | B20: 650 | C20: 500 | D20: 480 | E20: 500 | F20: 520
A21: Δ Working capital (EGP m) | B21: 250 | C21: 300 | D21: 310 | E21: 320 | F21: 320
A23: Cost of capital (Ke = rf + ERP)
A24: Risk-free (EGP 10-yr sovereign) | B24: 0.22
A25: Equity risk premium | B25: 0.06
A26: Beta (building materials) | B26: 1
A27: Ke — pure local | B27: =B24+B26*B25 -> 0.28
A28: Ke — export leg (USD-linked) | B28: 0.15
A29: Ke — blended (~55% export) | B29: =0.45*B27+0.55*B28 -> 0.2085
A30: WACC (base) | B30: 0.21
A31: Terminal growth g (nominal EGP) | B31: 0.11
A33: Normalization & multiples
A34: Normalized mid-cycle EBITDA (EGP m) | B34: 1100
A35: Normalized net income (EGP m) | B35: 460
A36: Fair EV/EBITDA (x) | B36: 4
A37: Fair P/E (x) | B37: 6.8
A38: Normalized EPS (EGP) | B38: 5.75
A39: Book value / share (EGP) | B39: 49.7

Sheet DCF — Primary Lens
A1: Primary lens — FCFF discounted cash flow (EGP m)
A2: Going-concern FCFF; nominal EGP; 5-yr explicit + Gordon terminal. Ke published as rf + ERP.
A4: FCFF build | B4: 2026E | C4: 2027E | D4: 2028E | E4: 2029E | F4: 2030E
A5: Revenue | B5: =Assumptions!$B$11*(1+Assumptions!B17) -> 8740.144 | C5: =B5*(1+Assumptions!C17) -> 9876.3627 | D5: =C5*(1+Assumptions!D17) -> 11061.526 | E5: =D5*(1+Assumptions!E17) -> 12278.294 | F5: =E5*(1+Assumptions!F17) -> 13506.124
A6: EBITDA margin % | B6: =Assumptions!B18 -> 0.115 | C6: =Assumptions!C18 -> 0.125 | D6: =Assumptions!D18 -> 0.135 | E6: =Assumptions!E18 -> 0.14 | F6: =Assumptions!F18 -> 0.145
A7: EBITDA | B7: =B5*B6 -> 1005.1166 | C7: =C5*C6 -> 1234.5453 | D7: =D5*D6 -> 1493.306 | E7: =E5*E6 -> 1718.9612 | F7: =F5*F6 -> 1958.3879
A8: less: D&A | B8: =-Assumptions!B19 -> -265 | C8: =-Assumptions!C19 -> -300 | D8: =-Assumptions!D19 -> -340 | E8: =-Assumptions!E19 -> -380 | F8: =-Assumptions!F19 -> -420
A9: EBIT | B9: =B7+B8 -> 740.11656 | C9: =C7+C8 -> 934.54534 | D9: =D7+D8 -> 1153.306 | E9: =E7+E8 -> 1338.9612 | F9: =F7+F8 -> 1538.3879
A10: NOPAT = EBIT×(1−t) | B10: =B9*(1-Assumptions!$B$8) -> 573.59033 | C10: =C9*(1-Assumptions!$B$8) -> 724.27264 | D10: =D9*(1-Assumptions!$B$8) -> 893.81218 | E10: =E9*(1-Assumptions!$B$8) -> 1037.6949 | F10: =F9*(1-Assumptions!$B$8) -> 1192.2506
A11: plus: D&A | B11: =Assumptions!B19 -> 265 | C11: =Assumptions!C19 -> 300 | D11: =Assumptions!D19 -> 340 | E11: =Assumptions!E19 -> 380 | F11: =Assumptions!F19 -> 420
A12: less: Capex | B12: =-Assumptions!B20 -> -650 | C12: =-Assumptions!C20 -> -500 | D12: =-Assumptions!D20 -> -480 | E12: =-Assumptions!E20 -> -500 | F12: =-Assumptions!F20 -> -520
A13: less: Δ working capital | B13: =-Assumptions!B21 -> -250 | C13: =-Assumptions!C21 -> -300 | D13: =-Assumptions!D21 -> -310 | E13: =-Assumptions!E21 -> -320 | F13: =-Assumptions!F21 -> -320
A14: Free cash flow to firm (FCFF) | B14: =B10+B11+B12+B13 -> -61.409666 | C14: =C10+C11+C12+C13 -> 224.27264 | D14: =D10+D11+D12+D13 -> 443.81218 | E14: =E10+E11+E12+E13 -> 597.69491 | F14: =F10+F11+F12+F13 -> 772.25063
A15: Discount factor @ WACC | B15: =1/(1+Assumptions!$B$30)^1 -> 0.82644628 | C15: =1/(1+Assumptions!$B$30)^2 -> 0.68301346 | D15: =1/(1+Assumptions!$B$30)^3 -> 0.56447393 | E15: =1/(1+Assumptions!$B$30)^4 -> 0.46650738 | F15: =1/(1+Assumptions!$B$30)^5 -> 0.38554329
A16: PV of FCFF | B16: =B14*B15 -> -50.75179 | C16: =C14*C15 -> 153.18123 | D16: =D14*D15 -> 250.52041 | E16: =E14*E15 -> 278.82909 | F16: =F14*F15 -> 297.73605
A18: Terminal value & equity bridge
A19: Sum PV of explicit FCFF | B19: =SUM(B16:F16) -> 929.51498
A20: Terminal value (Gordon) | B20: =F14*(1+Assumptions!$B$31)/(Assumptions!$B$30-Assumptions!$B$31) -> 8571.982
A21: PV of terminal value | B21: =B20*F15 -> 3304.8701
A22: Enterprise value | B22: =B19+B21 -> 4234.3851
A23: TV as % of EV | B23: =B21/B22 -> 0.78048407
A24: less: net debt (Dec-2025) | B24: =-Assumptions!$B$6 -> -1270
A25: Equity value | B25: =B22+B24 -> 2964.3851
A26: Fair value per share (EGP) | B26: =B25/Assumptions!$B$5 -> 37.054814
A28: Upside / (downside) vs spot | B28: =B26/Assumptions!$B$4-1 -> 0.25822799

Sheet Segments
A1: Segment build — FY2025 (EGP m)
A3: Segment | B3: Revenue | C3: % rev | D3: Export % | E3: Gross margin | F3: Gross profit
A4: Sanitary ware | B4: 5014.6 | C4: =B4/$B$7 -> 0.64258438 | D4: 0.814 | E4: 0.261 | F4: =B4*E4 -> 1308.8106
A5: Tiles | B5: 2488.8 | C5: =B5/$B$7 -> 0.31892155 | D5: 0.078 | E5: 0.138 | F5: =B5*E5 -> 343.4544
A6: Brassware | B6: 300.4 | C6: =B6/$B$7 -> 0.038494067 | D6: 0 | E6: 0.441 | F6: =B6*E6 -> 132.4764
A7: Total | B7: =SUM(B4:B6) -> 7803.8 | E7: =F7/B7 -> 0.22870158 | F7: =SUM(F4:F6) -> 1784.7414
A9: Export share of total revenue | B9: =SUMPRODUCT(B4:B6,D4:D6)/B7 -> 0.54793957
A11: Sanitary ware is 64% of revenue and 81% export — the hard-currency earner; tiles are domestic; brassware is small/high-margin.

Sheet Relative & Normalized
A1: Relative multiples & normalized earnings
A3: Current trading multiples
A4: Market cap (EGP m) | B4: =Assumptions!$B$4*Assumptions!$B$5 -> 2356
A5: + net debt | B5: =Assumptions!$B$6 -> 1270
A6: Enterprise value | B6: =B4+B5 -> 3626
A7: EV/EBITDA (2025A, 980.8) | B7: =B6/980.8 -> 3.6969821
A8: EV/EBITDA (normalized) | B8: =B6/Assumptions!$B$34 -> 3.2963636
A9: P/E (2025A EPS 3.05) | B9: =Assumptions!$B$4/3.05 -> 9.6557377
A10: P/B (BVPS 49.7) | B10: =Assumptions!$B$4/49.7 -> 0.59255533
A12: Lens A — relative multiples (fair value)
A13: Fair EV/EBITDA (x) × normalized EBITDA | B13: =Assumptions!$B$36*Assumptions!$B$34 -> 4400
A14: less net debt → equity | B14: =B13-Assumptions!$B$6 -> 3130
A15: Fair value / share (EGP) | B15: =B14/Assumptions!$B$5 -> 39.125
A17: Lens B — normalized earnings power
A18: Normalized net income (EGP m) | B18: =Assumptions!$B$35 -> 460
A19: Normalized EPS (EGP) | B19: =B18/Assumptions!$B$5 -> 5.75
A20: × justified P/E (x) | B20: =Assumptions!$B$37 -> 6.8
A21: Fair value / share (EGP) | B21: =B19*B20 -> 39.1
A23: Peak/mid-cycle: 2025 is a MARGIN TROUGH (EBIT 9.5% vs 2024 17.3%, 2023 19.4%). Normalized ~13% mid-cycle.

Sheet FCFE & Asset
A1: Lens C — FCFE / owner-earnings · Lens D — asset / reproduction
A3: FCFE / owner-earnings (conservative)
A4: Steady-state owner-earnings capacity (EGP m) | B4: 430
A5: Capitalization rate (Ke − g, local-heavy) | B5: 0.135
A6: Implied equity value (EGP m) | B6: =B4/B5 -> 3185.1852
A7: Haircut for near-term negative FCF / WC trap | B7: 0.2
A8: Fair value / share (EGP) | B8: =B6*(1-B7)/Assumptions!$B$5 -> 31.851852
A10: Asset / reproduction value (floor)
A11: Total assets (Dec-2025) | B11: 8537
A12: less: inventory haircut 20% | B12: -576
A13: less: receivables haircut 15% | B13: -249
A14: less: PP&E haircut 10% | B14: -359
A15: Realizable assets | B15: =SUM(B11:B14) -> 7353
A16: less: total liabilities | B16: -4431.2
A17: less: minority interest | B17: -128
A18: Realizable equity (EGP m) | B18: =B15+B16+B17 -> 2793.8
A19: Fair value / share (EGP) | B19: =B18/Assumptions!$B$5 -> 34.9225
A21: Stock trades at 0.59× book (BVPS 49.7) — the realizable-asset floor is itself a support.

Sheet Income Statement
A1: Appendix A.1 — Income statement (EGP m): 3-yr historical + 5-yr forecast
B3: 2023A | C3: 2024A | D3: 2025A | F3: 2026E | G3: 2027E | H3: 2028E | I3: 2029E | J3: 2030E
A4: Revenue | B4: 4844 | C4: 6644.7 | D4: 7803.7 | F4: =Assumptions!$B$11*(1+Assumptions!B17) -> 8740.144 | G4: =F4*(1+Assumptions!C17) -> 9876.3627 | H4: =G4*(1+Assumptions!D17) -> 11061.526 | I4: =H4*(1+Assumptions!E17) -> 12278.294 | J4: =I4*(1+Assumptions!F17) -> 13506.124
A5: EBITDA | C5: 1330.1 | D5: 980.8 | F5: =F4*Assumptions!B18 -> 1005.1166 | G5: =G4*Assumptions!C18 -> 1234.5453 | H5: =H4*Assumptions!D18 -> 1493.306 | I5: =I4*Assumptions!E18 -> 1718.9612 | J5: =J4*Assumptions!F18 -> 1958.3879
A6: D&A | C6: 179.1 | D6: 238.2 | F6: =Assumptions!B19 -> 265 | G6: =Assumptions!C19 -> 300 | H6: =Assumptions!D19 -> 340 | I6: =Assumptions!E19 -> 380 | J6: =Assumptions!F19 -> 420
A7: EBIT | B7: 941.1 | C7: 1151 | D7: 742.6 | F7: =F5-F6 -> 740.11656 | G7: =G5-G6 -> 934.54534 | H7: =H5-H6 -> 1153.306 | I7: =I5-I6 -> 1338.9612 | J7: =J5-J6 -> 1538.3879
A8: Net finance & other | C8: 78.9 | D8: -280.9 | F8: -260 | G8: -252 | H8: -244 | I8: -236 | J8: -228
A9: Profit before tax | C9: 1231.9 | D9: 461.7 | F9: =F7+F8 -> 480.11656 | G9: =G7+G8 -> 682.54534 | H9: =H7+H8 -> 909.30604 | I9: =I7+I8 -> 1102.9612 | J9: =J7+J8 -> 1310.3879
A10: Tax | C10: -312.5 | D10: -202.4 | F10: =-F9*Assumptions!$B$8 -> -108.02623 | G10: =-G9*Assumptions!$B$8 -> -153.5727 | H10: =-H9*Assumptions!$B$8 -> -204.59386 | I10: =-I9*Assumptions!$B$8 -> -248.16627 | J10: =-J9*Assumptions!$B$8 -> -294.83728
A11: Net profit after tax | C11: 919.4 | D11: 259.3 | F11: =F9+F10 -> 372.09033 | G11: =G9+G10 -> 528.97264 | H11: =H9+H10 -> 704.71218 | I11: =I9+I10 -> 854.79491 | J11: =J9+J10 -> 1015.5506
A12: Minority interest | C12: -29.1 | D12: -15.2 | F12: =-F11*0.05 -> -18.604517 | G12: =-G11*0.05 -> -26.448632 | H12: =-H11*0.05 -> -35.235609 | I12: =-I11*0.05 -> -42.739746 | J12: =-J11*0.05 -> -50.777532
A13: Net profit attributable | B13: 446.3 | C13: 890.3 | D13: 244.1 | F13: =F11+F12 -> 353.48582 | G13: =G11+G12 -> 502.52401 | H13: =H11+H12 -> 669.47657 | I13: =I11+I12 -> 812.05517 | J13: =J11+J12 -> 964.7731
A14: EPS (EGP) | B14: 5.58 | C14: 11.13 | D14: 3.05 | F14: =F13/Assumptions!$B$5 -> 4.4185727 | G14: =G13/Assumptions!$B$5 -> 6.2815501 | H14: =H13/Assumptions!$B$5 -> 8.3684572 | I14: =I13/Assumptions!$B$5 -> 10.15069 | J14: =J13/Assumptions!$B$5 -> 12.059664
A16: FY2024 net finance includes ~EGP 362m devaluation/FX gains; forecast below EBIT uses statutory 22.5% tax and ~5% minority.

Sheet Balance Sheet
A1: Appendix A.2 — Balance sheet (EGP m): 3-yr historical + 5-yr forecast
B3: 2023A | C3: 2024A | D3: 2025A | F3: 2026E | G3: 2027E | H3: 2028E | I3: 2029E | J3: 2030E
A4: Cash & equivalents | C4: 352.2 | D4: 314 | F4: 320 | G4: 360 | H4: 400 | I4: 440 | J4: 480
A5: Inventory | C5: 2543.4 | D5: 2880.3 | F5: =2880.3*(1+Assumptions!B17) -> 3225.936 | G5: =F5*(1+Assumptions!C17) -> 3645.3077 | H5: =G5*(1+Assumptions!D17) -> 4082.7446 | I5: =H5*(1+Assumptions!E17) -> 4531.8465 | J5: =I5*(1+Assumptions!F17) -> 4985.0312
A6: Receivables | C6: 1443.9 | D6: 1659.3 | F6: =1659.3*(1+Assumptions!B17) -> 1858.416 | G6: =F6*(1+Assumptions!C17) -> 2100.0101 | H6: =G6*(1+Assumptions!D17) -> 2352.0113 | I6: =H6*(1+Assumptions!E17) -> 2610.7325 | J6: =I6*(1+Assumptions!F17) -> 2871.8058
A7: Total current assets | C7: 4339.5 | D7: 4853.6 | F7: =F4+F5+F6 -> 5404.352 | G7: =G4+G5+G6 -> 6105.3178 | H7: =H4+H5+H6 -> 6834.7559 | I7: =I4+I5+I6 -> 7582.579 | J7: =J4+J5+J6 -> 8336.8369
A8: PP&E | C8: 3322.4 | D8: 3586 | F8: =3586+Assumptions!B20-Assumptions!B19 -> 3971 | G8: =F8+Assumptions!C20-Assumptions!C19 -> 4171 | H8: =G8+Assumptions!D20-Assumptions!D19 -> 4311 | I8: =H8+Assumptions!E20-Assumptions!E19 -> 4431 | J8: =I8+Assumptions!F20-Assumptions!F19 -> 4531
A9: Other non-current | C9: 85.5 | D9: 97.5 | F9: 97.5 | G9: 97.5 | H9: 97.5 | I9: 97.5 | J9: 97.5
A10: Total assets | C10: 7747.4 | D10: 8537 | F10: =F7+F8+F9 -> 9472.852 | G10: =G7+G8+G9 -> 10373.818 | H10: =H7+H8+H9 -> 11243.256 | I10: =I7+I8+I9 -> 12111.079 | J10: =J7+J8+J9 -> 12965.337
A11: Bank facilities + current loans | C11: 954.3 | D11: 1627.7 | F11: 1627.7 | G11: 1627.7 | H11: 1627.7 | I11: 1627.7 | J11: 1627.7
A12: Trade & other payables | C12: 1791.7 | D12: 1668.1 | F12: =1668.1*(1+Assumptions!B17*0.6) -> 1788.2032 | G12: =F12*(1+Assumptions!C17*0.6) -> 1927.683 | H12: =G12*(1+Assumptions!D17*0.6) -> 2066.4762 | I12: =H12*(1+Assumptions!E17*0.6) -> 2202.8637 | J12: =I12*(1+Assumptions!F17*0.6) -> 2335.0355
A13: Other current liabilities | C13: 160.9 | D13: 260.1 | F13: 260.1 | G13: 260.1 | H13: 260.1 | I13: 260.1 | J13: 260.1
A14: Total non-current liabilities | C14: 984 | D14: 875.2 | F14: 875.2 | G14: 875.2 | H14: 875.2 | I14: 875.2 | J14: 875.2
A15: Total liabilities | C15: 3890.8 | D15: 4431.2 | F15: =F11+F12+F13+F14 -> 4551.2032 | G15: =G11+G12+G13+G14 -> 4690.683 | H15: =H11+H12+H13+H14 -> 4829.4762 | I15: =I11+I12+I13+I14 -> 4965.8637 | J15: =J11+J12+J13+J14 -> 5098.0355
A16: Non-controlling interest | C16: 122 | D16: 128 | F16: 128 | G16: 128 | H16: 128 | I16: 128 | J16: 128
A17: Total equity (attributable) | B17: 3200 | C17: 3734.6 | D17: 3977.8 | F17: =3977.8+'Income Statement'!F13 -> 4331.2858 | G17: =F17+'Income Statement'!G13 -> 4833.8098 | H17: =G17+'Income Statement'!H13 -> 5503.2864 | I17: =H17+'Income Statement'!I13 -> 6315.3416 | J17: =I17+'Income Statement'!J13 -> 7280.1147
A19: Forecast is indicative (cash and debt held roughly flat as blue inputs; equity rolls forward with retained net income).

Sheet Cash Flow
A1: Appendix A.3 — Cash flow (EGP m): 2-yr historical + 5-yr forecast
B3: 2023A | C3: 2024A | D3: 2025A | F3: 2026E | G3: 2027E | H3: 2028E | I3: 2029E | J3: 2030E
A4: EBITDA | C4: 1330.1 | D4: 980.8 | F4: ='DCF — Primary Lens'!F7 -> 1958.3879 | G4: ='DCF — Primary Lens'!G7 -> 0 | H4: ='DCF — Primary Lens'!H7 -> 0 | I4: ='DCF — Primary Lens'!I7 -> 0 | J4: ='DCF — Primary Lens'!J7 -> 0
A5: Δ working capital | C5: -317.5 | D5: -706 | F5: =-Assumptions!B21 -> -250 | G5: =-Assumptions!C21 -> -300 | H5: =-Assumptions!D21 -> -310 | I5: =-Assumptions!E21 -> -320 | J5: =-Assumptions!F21 -> -320
A6: Tax paid | C6: -201.4 | D6: -328.4 | F6: =-'DCF — Primary Lens'!F9*Assumptions!$B$8 -> -346.13728 | G6: =-'DCF — Primary Lens'!G9*Assumptions!$B$8 -> 0 | H6: =-'DCF — Primary Lens'!H9*Assumptions!$B$8 -> 0 | I6: =-'DCF — Primary Lens'!I9*Assumptions!$B$8 -> 0 | J6: =-'DCF — Primary Lens'!J9*Assumptions!$B$8 -> 0
A7: Interest paid | C7: -281.9 | D7: -298.6 | F7: -260 | G7: -252 | H7: -244 | I7: -236 | J7: -228
A8: Operating cash flow | C8: 537.1 | D8: -196 | F8: =F4+F5+F6+F7 -> 1102.2506 | G8: =G4+G5+G6+G7 -> -552 | H8: =H4+H5+H6+H7 -> -554 | I8: =I4+I5+I6+I7 -> -556 | J8: =J4+J5+J6+J7 -> -548
A9: Capex | C9: -285 | D9: -466.8 | F9: =-Assumptions!B20 -> -650 | G9: =-Assumptions!C20 -> -500 | H9: =-Assumptions!D20 -> -480 | I9: =-Assumptions!E20 -> -500 | J9: =-Assumptions!F20 -> -520
A10: Free cash flow to firm | C10: 252.1 | D10: -662.8 | F10: ='DCF — Primary Lens'!F14 -> 772.25063 | G10: ='DCF — Primary Lens'!G14 -> 0 | H10: ='DCF — Primary Lens'!H14 -> 0 | I10: ='DCF — Primary Lens'!I14 -> 0 | J10: ='DCF — Primary Lens'!J14 -> 0
A12: 2025 operating cash flow was NEGATIVE (−196) on a EGP 706m working-capital absorption — the cash-conversion crux.

Sheet Summary Financials
A1: Summary financials — links to statement sheets
B3: 2023A | C3: 2024A | D3: 2025A | F3: 2026E | G3: 2027E | H3: 2028E | I3: 2029E | J3: 2030E
A4: Revenue | B4: ='Income Statement'!B4 -> 4844 | C4: ='Income Statement'!C4 -> 6644.7 | D4: ='Income Statement'!D4 -> 7803.7 | F4: ='Income Statement'!F4 -> 8740.144 | G4: ='Income Statement'!G4 -> 9876.3627 | H4: ='Income Statement'!H4 -> 11061.526 | I4: ='Income Statement'!I4 -> 12278.294
A5: EBITDA | B5: ='Income Statement'!B5 -> 0 | C5: ='Income Statement'!C5 -> 1330.1 | D5: ='Income Statement'!D5 -> 980.8 | F5: ='Income Statement'!F5 -> 1005.1166 | G5: ='Income Statement'!G5 -> 1234.5453 | H5: ='Income Statement'!H5 -> 1493.306 | I5: ='Income Statement'!I5 -> 1718.9612
A6: EBIT | B6: ='Income Statement'!B7 -> 941.1 | C6: ='Income Statement'!C7 -> 1151 | D6: ='Income Statement'!D7 -> 742.6 | F6: ='Income Statement'!F7 -> 740.11656 | G6: ='Income Statement'!G7 -> 934.54534 | H6: ='Income Statement'!H7 -> 1153.306 | I6: ='Income Statement'!I7 -> 1338.9612
A7: Net profit attributable | B7: ='Income Statement'!B13 -> 446.3 | C7: ='Income Statement'!C13 -> 890.3 | D7: ='Income Statement'!D13 -> 244.1 | F7: ='Income Statement'!F13 -> 353.48582 | G7: ='Income Statement'!G13 -> 502.52401 | H7: ='Income Statement'!H13 -> 669.47657 | I7: ='Income Statement'!I13 -> 812.05517
A8: EPS (EGP) | B8: ='Income Statement'!B14 -> 5.58 | C8: ='Income Statement'!C14 -> 11.13 | D8: ='Income Statement'!D14 -> 3.05 | F8: ='Income Statement'!F14 -> 4.4185727 | G8: ='Income Statement'!G14 -> 6.2815501 | H8: ='Income Statement'!H14 -> 8.3684572 | I8: ='Income Statement'!I14 -> 10.15069
A9: Total assets | B9: ='Balance Sheet'!B7 -> 0 | C9: ='Balance Sheet'!C7 -> 4339.5 | D9: ='Balance Sheet'!D7 -> 4853.6 | F9: ='Balance Sheet'!F7 -> 5404.352 | G9: ='Balance Sheet'!G7 -> 6105.3178 | H9: ='Balance Sheet'!H7 -> 6834.7559 | I9: ='Balance Sheet'!I7 -> 7582.579
A10: Total equity | B10: ='Balance Sheet'!B17 -> 3200 | C10: ='Balance Sheet'!C17 -> 3734.6 | D10: ='Balance Sheet'!D17 -> 3977.8 | F10: ='Balance Sheet'!F17 -> 4331.2858 | G10: ='Balance Sheet'!G17 -> 4833.8098 | H10: ='Balance Sheet'!H17 -> 5503.2864 | I10: ='Balance Sheet'!I17 -> 6315.3416
A11: Operating cash flow | B11: ='Cash Flow'!B8 -> 0 | C11: ='Cash Flow'!C8 -> 537.1 | D11: ='Cash Flow'!D8 -> -196 | F11: ='Cash Flow'!F8 -> 1102.2506 | G11: ='Cash Flow'!G8 -> -552 | H11: ='Cash Flow'!H8 -> -554 | I11: ='Cash Flow'!I8 -> -556
A12: FCFF | B12: ='Cash Flow'!B10 -> 0 | C12: ='Cash Flow'!C10 -> 252.1 | D12: ='Cash Flow'!D10 -> -662.8 | F12: ='Cash Flow'!F10 -> 772.25063 | G12: ='Cash Flow'!G10 -> 0 | H12: ='Cash Flow'!H10 -> 0 | I12: ='Cash Flow'!I10 -> 0

Sheet Monte Carlo
A1: Monte Carlo — YZ-HAR engine, 50,000 paths, seed 42
A3: Probability read (T+60, from the same 50,000 paths)
A4: P(price > spot) at T+60 | B4: 0.604
A5: P(+10%) vs P(−10%) | B5: 41% vs 22%
A6: Odds ratio (up:down) | B6: 1.9 : 1
A7: Median level / % move | B7: 31.0 (+5.3%)
A8: 50% band (25th–75th) | B8: 27.1 – 35.5 (29% of spot)
A9: Touch(+10%) / Touch(−10%) | B9: 66% / 46%
A11: Percentile map (EGP/share)
A12: Horizon | B12: p5 | C12: p25 | D12: p50 | E12: p75 | F12: p95
A13: T+20 sessions | B13: 24.285721 | C13: 27.757537 | D13: 29.992565 | E13: 32.383621 | F13: 36.981678
A14: T+60 sessions | B14: 21.691767 | C14: 27.072319 | D14: 31.011948 | E14: 35.537506 | F14: 44.370477
A16: Level-touch ladder
A17: Level (EGP) | B17: by T+20 | C17: by T+60
A18: 35.34 | B18: 0.13546 | C18: 0.413
A19: 32.98 | B19: 0.31802 | C19: 0.6084
A20: 30.92 | B20: 0.62022 | C20: 0.8043
A21: 28.86 | B21: 0.70218 | C21: 0.80218
A22: 26.5 | B22: 0.25788 | C22: 0.45626
A23: 24.44 | B23: 0.0895 | C23: 0.2516
A24: 22.09 | B24: 0.02324 | C24: 0.11262
A26: Width = YZ-HAR (ann. sigma 42%); Student-t(5) shape; secular drift +19%/yr (Step-0 calibrated).

Sheet Sensitivity
A1: DCF sensitivity — EGP/share by WACC × terminal g
A3: WACC \ g | B3: 0.09 | C3: 0.1 | D3: 0.11 | E3: 0.12 | F3: 0.13
A4: 0.19 | B4: 40.62 | C4: 45.97 | D4: 52.65 | E4: 61.25 | F4: 72.71
A5: 0.2 | B5: 34.57 | C5: 38.8 | D5: 43.97 | E5: 50.44 | F5: 58.75
A6: 0.21 | B6: 29.55 | C6: 32.96 | D6: 37.06 | E6: 42.06 | F6: 48.32
A7: 0.22 | B7: 25.33 | C7: 28.12 | D7: 31.42 | E7: 35.38 | F7: 40.23
A8: 0.23 | B8: 21.72 | C8: 24.04 | D8: 26.75 | E8: 29.94 | F8: 33.78
A10: Base case WACC 21% × g 11% → EGP 37. TV is ~78% of EV, so the value is terminal-assumption-sensitive (device A-7).

Sheet Per-Share & Ratios
A1: Per-Share & Ratios — standardized dashboard
B3: 2023A | C3: 2024A | D3: 2025A | F3: 2026E | G3: 2027E | H3: 2028E | I3: 2029E | J3: 2030E
A4: EPS (EGP) | B4: 5.58 | C4: 11.13 | D4: 3.05 | F4: ='Income Statement'!F14 -> 4.4185727 | G4: ='Income Statement'!G14 -> 6.2815501 | H4: ='Income Statement'!H14 -> 8.3684572 | I4: ='Income Statement'!I14 -> 10.15069 | J4: ='Income Statement'!J14 -> 12.059664
A5: BVPS (EGP) | B5: 40 | C5: 46.7 | D5: 49.7 | F5: ='Balance Sheet'!F17/Assumptions!$B$5 -> 54.141073 | G5: ='Balance Sheet'!G17/Assumptions!$B$5 -> 60.422623 | H5: ='Balance Sheet'!H17/Assumptions!$B$5 -> 68.79108 | I5: ='Balance Sheet'!I17/Assumptions!$B$5 -> 78.94177 | J5: ='Balance Sheet'!J17/Assumptions!$B$5 -> 91.001433
A6: P/E (x, at spot) | B6: =Assumptions!$B$4/B4 -> 5.2777778 | C6: =Assumptions!$B$4/C4 -> 2.6460018 | D6: =Assumptions!$B$4/D4 -> 9.6557377 | F6: =Assumptions!$B$4/F4 -> 6.6650482 | G6: =Assumptions!$B$4/G4 -> 4.6883332 | H6: =Assumptions!$B$4/H4 -> 3.5191672 | I6: =Assumptions!$B$4/I4 -> 2.9012807
A7: P/B (x, at spot) | B7: =Assumptions!$B$4/B5 -> 0.73625 | C7: =Assumptions!$B$4/C5 -> 0.63062099 | D7: =Assumptions!$B$4/D5 -> 0.59255533 | F7: =Assumptions!$B$4/F5 -> 0.54394933 | G7: =Assumptions!$B$4/G5 -> 0.48740023 | H7: =Assumptions!$B$4/H5 -> 0.42810783 | I7: =Assumptions!$B$4/I5 -> 0.37305979
A8: EBITDA margin % | B8: 0.282 | C8: 0.2 | D8: 0.126 | F8: =Assumptions!B18 -> 0.115 | G8: =Assumptions!C18 -> 0.125 | H8: =Assumptions!D18 -> 0.135 | I8: =Assumptions!E18 -> 0.14 | J8: =Assumptions!F18 -> 0.145
A9: Net debt / EBITDA (x) | D9: =Assumptions!$B$6/980.8 -> 1.2948613
A10: ROIC vs WACC | D10: 0.11 | F10: 0.145
A12: Dividend: none (stand-alone accumulated losses block distribution) — DPS/yield rows are N/A by disclosure.
A13: ROIC (11% in 2025) sits below WACC (21%) at the trough — value creation resumes only as margins normalize.

Sheet Peer & Sector
A1: Peer set & sector structure
A3: Peer | B3: Market | C3: EV/EBITDA | D3: P/E | E3: Note
A4: Lecico (LCSW) | B4: EGX | C4: 3.7x | D4: 9.7x | E4: Trough margins; 0.59x book
A5: RAK Ceramics | B5: Abu Dhabi (ADX) | C5: 5–6x | D5: 8–10x | E5: Regional ceramics leader
A6: Saudi Ceramics | B6: Tadawul | C6: 6–8x | D6: 12–16x | E6: Domestic KSA demand
A7: Cleopatra Ceramics | B7: Private / EGX | C7: n/a | D7: n/a | E7: Egypt tiles peer
A8: Kajaria Ceramics | B8: India (NSE) | C8: 20–28x | D8: 40–55x | E8: Structural-growth premium
A9: Cera Sanitaryware | B9: India (NSE) | C9: 18–24x | D9: 30–40x | E9: Sanitaryware growth
A10: Geberit / Villeroy&Boch | B10: SIX / XETRA | C10: 10–14x | D10: 18–25x | E10: High-end European
A12: Sector: cyclical building material; kilns are gas-intensive; export leg is FX-geared. Principal risks: EGP strength,
A13: energy-cost hikes, working-capital absorption / negative FCF, no dividend, and audit qualifications (hyperinflation/Lebanon).
