Workbook

Sheet READ FIRST
A1: READ FIRST — DISCLOSURE & DISCLAIMER (educational valuation study; not investment advice)
A3: WHAT THIS IS
A4: An independent, educational valuation model for LG Energy Solution, Ltd. (KRX: 373220) — an expression of personal analytical opinion, published free of charge. It is NOT investment advice, NOT a recommendation or solicitation to buy, sell or hold any security, and NOT directed at any reader's circumstances.
A6: NO LICENCE
A7: The preparer is not licensed or registered by any securities regulator in any jurisdiction, holds no brokerage authorisation, manages no money, solicits no clients, and accepts no fees. Consult a licensed financial advisor before any investment decision.
A9: HOW TO USE
A10: Blue cells are hardcoded inputs (edit to your own view); black cells are formulas; green cells link across sheets. The primary lens is a going-concern FCFF DCF, bridged from consolidated enterprise value to the PARENT's equity by subtracting net debt AND the large minority interest, then cross-checked with relative EV/EBITDA, normalised earnings and EV-per-GWh capacity. Currency KRW; valuation in KRW trillion, per share in KRW.
A12: THE CRUX
A13: Reported profit is carried by the US IRA production credit (AMPC), which accrues largely to joint-venture minorities — so the parent's owners were attributed a NET LOSS in 2024 (EPS -4,354) and 2025 (EPS -4,585). Trailing P/E is meaningless; the model values the inflection back to positive parent earnings as capex normalises and utilisation recovers.
A15: HOLDINGS
A16: The preparer may hold, and may in future take or dispose of, a position in the security discussed, and may transact at any time without notice.
A18: SOURCES
A19: Reported figures are from LG Energy Solution's audited consolidated financial statements (Deloitte Anjin, 5 Mar 2026) and IR disclosure; forward inputs are the preparer's judgments and are uncertain.

Sheet Summary
A1: LG Energy Solution (KRX: 373220) — Valuation Summary
A2: FCFF DCF (primary) + relative + normalised + capacity. Educational; not advice.
A4: Headline
A5: Weighted central fundamental value | B5: ='Fundamental Valuation'!B11 | D5: the four lenses, weighted
A6: Market price (26-Jun-2026) | B6: =Assumptions!B5 | D6: close
A7: Central vs spot | B7: =B5/B6-1 | D7: negative = looks expensive
A8: Bear case (AMPC cut + EV weak) | B8: =Assumptions!B35 | D8: low end
A9: Bull case (recovery + ESS/AI) | B9: =Assumptions!B36 | D9: high end
A10: Monte-Carlo median, T+60 | B10: =Assumptions!B39 | D10: near-term price, not value
A12: The four lenses
A13: Lens | B13: Value (KRW) | C13: Weight | D13: Note
A14: Going-concern DCF (FCFF, parent) | B14: =DCF!B25 | C14: =Assumptions!B28 | D14: net of debt & minorities
A15: Relative multiples (EV/EBITDA) | B15: ='Relative & Capacity'!B8 | C15: =Assumptions!B29 | D15: mid-cycle EBITDA x multiple
A16: Normalised through-cycle earnings | B16: ='Relative & Capacity'!B16 | C16: =Assumptions!B30 | D16: parent earnings, recovered
A17: EV / capacity (per GWh) | B17: ='Relative & Capacity'!B23 | C17: =Assumptions!B31 | D17: asset / replacement value
A18: Weighted central | B18: ='Fundamental Valuation'!B11 | C18: =SUM(C14:C17)
A20: Verdict — modestly expensive; the case is an EV-cycle and AMPC-policy bet. A buyer underwrites EV-demand stabilising, energy storage scaling, the credit retained, and parent earnings inflecting positive. Educational analysis, not investment advice.

Sheet Fundamental Valuation
A1: Fundamental Valuation — weighted lenses
A2: Spot sits ~25% above the weighted central. DCF and capacity below spot; relative and normalised straddle it.
A4: Method | B4: Value (KRW) | C4: vs spot | D4: Weight | E4: Note
A5: Going-concern DCF (FCFF, parent) | B5: =DCF!B25 | C5: =B5/Assumptions!$B$5-1 | D5: =Assumptions!B28 | E5: primary lens; full debt + minority bridge
A6: Relative multiples (EV/EBITDA) | B6: ='Relative & Capacity'!B8 | C6: =B6/Assumptions!$B$5-1 | D6: =Assumptions!B29 | E6: mid-cycle EBITDA vs CATL ~10.4x
A7: Normalised through-cycle earnings | B7: ='Relative & Capacity'!B16 | C7: =B7/Assumptions!$B$5-1 | D7: =Assumptions!B30 | E7: parent earnings once utilisation recovers
A8: EV / capacity (per GWh) | B8: ='Relative & Capacity'!B23 | C8: =B8/Assumptions!$B$5-1 | D8: =Assumptions!B31 | E8: asset / replacement cross-check
A11: WEIGHTED CENTRAL FUNDAMENTAL VALUE | B11: =SUMPRODUCT(B5:B8,D5:D8) | C11: =B11/Assumptions!$B$5-1 | D11: =SUM(D5:D8)
A12: Memo: spot price (26-Jun-2026) | B12: =Assumptions!B5
A13: Central vs spot | B13: =B11/B12-1 | E13: negative = market prices a growth premium
A15: Bear / AMPC-cut floor | B15: =Assumptions!B35
A16: Bull / recovery ceiling | B16: =Assumptions!B36
A18: The lenses do not cluster: anchor on near-term cash flow (DCF) or replacement cost (capacity) and the stock looks ~30-40% rich; grant mid-cycle EBITDA and a growth multiple (relative, normalised) and it looks roughly fair. The dispersion is the finding.

Sheet Assumptions
A1: Assumptions & inputs (blue = editable)
A2: Scalars used across the model; audited actuals sourced in cell comments.
A4: Market & capital structure
A5: Spot price (KRW, 26-Jun-26) | B5: 331500
A6: Shares outstanding | B6: 234000000
A7: Net debt (KRW tn) | B7: 18.73
A8: Minority interest / NCI (KRW tn) | B8: 9.11
A9: Market capitalisation (KRW tn) | B9: =B5*B6/10^12
A10: Enterprise value (KRW tn) | B10: =B9+B7
A11: Owner book value / BVPS (KRW) | B11: 86391.026
A12: P/B (x) | B12: =B5/B11
A14: DCF parameters
A15: WACC | B15: 0.09
A16: Terminal growth g | B16: 0.035
A17: Tax rate | B17: 0.22
A19: Cross-check inputs
A20: Mid-cycle EBITDA (KRW tn) | B20: 9.4
A21: EV/EBITDA multiple (x) | B21: 11
A22: Normalised parent net income (KRW tn) | B22: 2.93
A23: Normalised P/E multiple (x) | B23: 24
A24: Capacity (GWh, effective) | B24: 350
A25: Value per GWh (KRW bn) | B25: 205
A27: Lens weights
A28: DCF weight | B28: 0.25
A29: Relative weight | B29: 0.3
A30: Normalised weight | B30: 0.27
A31: Capacity weight | B31: 0.18
A32: sum of weights | B32: =SUM(B28:B31)
A34: Scenario anchors (per share, KRW)
A35: Bear case (AMPC cut + EV weak) | B35: 150000
A36: Bull case (recovery + ESS/AI super-cycle) | B36: 415000
A38: Monte-Carlo memo (see Monte Carlo sheet)
A39: T+60 median (KRW) | B39: 334200
A40: 3-month volatility | B40: 0.22590957
A41: Vol scale (Step-0 calibrated) | B41: 0.84

Sheet DCF
A1: Discounted cash flow (FCFF) — consolidated, bridged to parent
A2: Unlevered FCFF 2026e-2030e (KRW tn). EV less net debt AND minority interest = parent equity. Blue = editable.
A4: (KRW tn) | B4: 2026e | C4: 2027e | D4: 2028e | E4: 2029e | F4: 2030e
A5: Revenue | B5: 27.7 | C5: 31.4 | D5: 35.2 | E5: 38.7 | F5: 42.2
A6: growth YoY | B6: =B5/23.67-1 | C6: =C5/B5-1 | D6: =D5/C5-1 | E6: =E5/D5-1 | F6: =F5/E5-1
A7: Operating margin (incl. AMPC) | B7: 0.06 | C7: 0.07 | D7: 0.085 | E7: 0.105 | F7: 0.125
A8: EBIT | B8: =B5*B7 | C8: =C5*C7 | D8: =D5*D7 | E8: =E5*E7 | F8: =F5*F7
A9: NOPAT (EBIT x (1-tax)) | B9: =B8*(1-Assumptions!$B$17) | C9: =C8*(1-Assumptions!$B$17) | D9: =D8*(1-Assumptions!$B$17) | E9: =E8*(1-Assumptions!$B$17) | F9: =F8*(1-Assumptions!$B$17)
A10: Depreciation & amortisation | B10: 5 | C10: 5.3 | D10: 5.6 | E10: 5.9 | F10: 6.2
A11: Capital expenditure | B11: -6.5 | C11: -5.8 | D11: -5.5 | E11: -5.5 | F11: -5.5
A12: Change in net working capital | B12: -0.5 | C12: -0.45 | D12: -0.4 | E12: -0.35 | F12: -0.3
A13: Free cash flow to firm (FCFF) | B13: =B9+B10+B11+B12 | C13: =C9+C10+C11+C12 | D13: =D9+D10+D11+D12 | E13: =E9+E10+E11+E12 | F13: =F9+F10+F11+F12
A14: Discount factor | B14: =1/(1+Assumptions!$B$15)^1 | C14: =1/(1+Assumptions!$B$15)^2 | D14: =1/(1+Assumptions!$B$15)^3 | E14: =1/(1+Assumptions!$B$15)^4 | F14: =1/(1+Assumptions!$B$15)^5
A15: PV of FCFF | B15: =B13*B14 | C15: =C13*C14 | D15: =D13*D14 | E15: =E13*E14 | F15: =F13*F14
A17: Sum PV of explicit FCFF (2026-30) | B17: =SUM(B15:F15)
A18: Terminal value (Gordon) | B18: =F13*(1+Assumptions!$B$16)/(Assumptions!$B$15-Assumptions!$B$16)
A19: PV of terminal value | B19: =B18/(1+Assumptions!$B$15)^5
A20: Enterprise value | B20: =B17+B19
A21: (-) Net debt | B21: =-Assumptions!B7
A22: (-) Minority interest (NCI) | B22: =-Assumptions!B8
A23: Parent equity value | B23: =B20+B21+B22
A24: Shares outstanding | B24: =Assumptions!B6
A25: DCF value per share (KRW) | B25: =B23*10^12/B24
A26: vs spot | B26: =B25/Assumptions!B5-1
A28: The value is overwhelmingly terminal: explicit FCFF is only modestly positive (negative in 2026e), so the answer is highly sensitive to WACC, terminal growth and the margin recovery. Even crediting a recovery to a ~12.5% mid-cycle operating margin, parent equity nets to ~KRW 146,000/share after the net-debt and minority bridge — well below spot.

Sheet Relative & Capacity
A1: Relative, normalised & capacity cross-checks
A2: Three lenses that better capture a growth recovery; each bridges to the parent's equity per share.
A4: Relative — EV/EBITDA
A5: Mid-cycle EBITDA (KRW tn) | B5: =Assumptions!B20
A6: EV/EBITDA multiple (x) | B6: =Assumptions!B21
A7: Implied EV less net debt & NCI (tn) | B7: =B5*B6-Assumptions!B7-Assumptions!B8
A8: Value per share (KRW) | B8: =B7*10^12/Assumptions!B6
A9: vs spot | B9: =B8/Assumptions!B5-1
A12: Normalised through-cycle earnings
A13: Normalised parent net income (KRW tn) | B13: =Assumptions!B22
A14: Normalised EPS (KRW) | B14: =B13*10^12/Assumptions!B6
A15: Normalised P/E (x) | B15: =Assumptions!B23
A16: Value per share (KRW) | B16: =B14*B15
A17: vs spot | B17: =B16/Assumptions!B5-1
A20: EV per GWh — capacity / replacement
A21: Capacity (GWh) | B21: =Assumptions!B24
A22: Value per GWh (KRW bn) | B22: =Assumptions!B25
A23: Value per share (KRW) | B23: =(B21*B22/1000-Assumptions!B7-Assumptions!B8)*10^12/Assumptions!B6
A24: vs spot | B24: =B23/Assumptions!B5-1
A26: All multiples and marks are editable on Assumptions. The capacity lens (EV less net debt and NCI, over shares) values the asset base on a replacement-plus-premium basis.

Sheet Monte Carlo
A1: Monte Carlo — 3-month price map (16 factors, 50k paths, seed 42)
A2: Near-term PRICE process, not value. Vol scale 0.84x passed the Step-0 backtest. Drift built from factors, not trailing momentum.
A4: Engine parameters
A5: Spot (KRW) | B5: 331500
A6: 3-month drift (mu60) | B6: 0.008
A7: 3-month volatility (sig60) | B7: 0.22590957
A8: 1-month drift (mu20) | B8: 0.0026666667
A9: 1-month volatility (sig20) | B9: 0.13042895
A10: Vol scale (KVOL, calibrated) | B10: 0.84
A12: Percentiles of simulated price (KRW)
A13: Horizon | B13: 5th | C13: 25th | D13: Median | E13: 75th | F13: 95th
A14: T+20 (~1 month) | B14: 268200 | C14: 304400 | D14: 332400 | E14: 363000 | F14: 411900
A15: T+60 (~3 months) | B15: 230500 | C15: 286900 | D15: 334200 | E15: 389200 | F15: 484500
A17: Level-touch probabilities
A18: Level (KRW) | B18: Within T+20 | C18: Within T+60
A19: 370,000 ▲ | B19: 0.33 | C19: 0.59
A20: 410,000 ▲ | B20: 0.08 | C20: 0.32
A21: 450,000 ▲ | B21: 0.02 | C21: 0.16
A22: 300,000 ▼ | B22: 0.35 | C22: 0.59
A23: 270,000 ▼ | B23: 0.09 | C23: 0.31
A24: 240,000 ▼ | B24: 0.01 | C24: 0.13
A26: The paths diffuse from spot as a near-term price process and deliberately do not embed the fundamental valuation — the ~25% gap of the lenses is kept out of the drift, so the fundamental and probabilistic lenses stay independent.

Sheet Income Statement
A1: Consolidated income statement (KRW tn)
A2: FY2024-25 audited (Deloitte Anjin); FY2023 revenue & OP disclosed, other lines estimated; 2026e-30e illustrative, tie to DCF.
A4: Income statement | B4: 2023a | C4: 2024a | D4: 2025a | E4: 2026e | F4: 2027e | G4: 2028e | H4: 2029e | I4: 2030e
A5: Total revenue | B5: 33.75 | C5: 25.62 | D5: 23.67 | E5: 27.70 | F5: 31.40 | G5: 35.20 | H5: 38.70 | I5: 42.20
A6: growth YoY | B6: — | C6: (24%) | D6: (8%) | E6: +17% | F6: +13% | G6: +12% | H6: +10% | I6: +9%
A7: AMPC / other op. income | B7: 0.66 | C7: 1.48 | D7: 1.65 | E7: 1.55 | F7: 1.65 | G7: 1.75 | H7: 1.80 | I7: 1.90
A8: Operating profit (incl. AMPC) | B8: 2.16 | C8: 0.58 | D8: 1.35 | E8: 1.66 | F8: 2.20 | G8: 2.99 | H8: 4.06 | I8: 5.28
A9: OP margin | B9: 6.4% | C9: 2.2% | D9: 5.7% | E9: 6.0% | F9: 7.0% | G9: 8.5% | H9: 10.5% | I9: 12.5%
A10: Operating profit ex-AMPC | B10: 1.50 | C10: (0.91) | D10: (0.30) | E10: 0.11 | F10: 0.55 | G10: 1.24 | H10: 2.26 | I10: 3.38
A11: Pre-tax profit | B11: 1.80 | C11: 0.35 | D11: 0.41 | E11: 0.60 | F11: 1.30 | G11: 2.40 | H11: 3.40 | I11: 4.50
A12: Net profit — group total | B12: 1.40 | C12: 0.34 | D12: 0.08 | E12: 0.50 | F12: 1.10 | G12: 1.90 | H12: 2.70 | I12: 3.60
A13: of which non-controlling int. | B13: 0.60 | C13: 1.36 | D13: 1.15 | E13: 0.80 | F13: 0.70 | G13: 0.70 | H13: 0.70 | I13: 0.70
A14: Net profit — to owners | B14: 0.80 | C14: (1.02) | D14: (1.07) | E14: (0.30) | F14: 0.40 | G14: 1.20 | H14: 2.00 | I14: 2.90
A15: EPS — to owners (KRW) | B15: 3,400 | C15: (4,354) | D15: (4,585) | E15: (1,280) | F15: 1,710 | G15: 5,130 | H15: 8,550 | I15: 12,390
A17: The decisive feature is the owner / non-controlling split: in 2024-25 the production-credit profit accrued to JV minorities and the parent's owners were attributed a net loss; the projection shows parent earnings inflecting positive from 2027e. Margins align with the DCF sheet.

Sheet Balance Sheet
A1: Consolidated balance sheet (KRW tn)
A2: FY2024-25 audited; FY2023 partly estimated; 2026e-30e illustrative.
A4: Balance sheet | B4: 2023a | C4: 2024a | D4: 2025a | E4: 2026e | F4: 2027e | G4: 2028e | H4: 2029e | I4: 2030e
A5: Cash & cash equivalents | B5: 4.5 | C5: 3.90 | D5: 3.78 | E5: 4.5 | F5: 5.5 | G5: 6.5 | H5: 7.5 | I5: 9.0
A6: Property, plant & equipment | B6: 30.0 | C6: 38.35 | D6: 40.79 | E6: 42.0 | F6: 43.0 | G6: 44.0 | H6: 45.0 | I6: 46.0
A7: Total assets | B7: 47.5 | C7: 60.31 | D7: 67.15 | E7: 69.0 | F7: 71.0 | G7: 73.0 | H7: 76.0 | I7: 79.0
A8: Borrowings, bonds & leases | B8: 12.5 | C8: 15.39 | D8: 22.51 | E8: 22.0 | F8: 21.0 | G8: 20.0 | H8: 19.0 | I8: 18.0
A9: Total liabilities | B9: 23.1 | C9: 29.34 | D9: 37.83 | E9: 38.0 | F9: 38.0 | G9: 38.0 | H9: 38.5 | I9: 39.0
A10: Equity attributable to owners | B10: 20.20 | C10: 21.12 | D10: 20.22 | E10: 20.5 | F10: 21.0 | G10: 22.0 | H10: 23.5 | I10: 25.5
A11: Non-controlling interests | B11: 4.17 | C11: 9.85 | D11: 9.11 | E11: 9.5 | F11: 10.0 | G11: 10.5 | H11: 11.0 | I11: 11.5
A12: Total equity | B12: 24.37 | C12: 30.97 | D12: 29.32 | E12: 30.0 | F12: 31.0 | G12: 32.5 | H12: 34.5 | I12: 37.0
A13: BVPS — owners (KRW) | B13: 86,300 | C13: 90,250 | D13: 86,390 | E13: 87,600 | F13: 89,700 | G13: 94,000 | H13: 100,400 | I13: 109,000
A14: Net debt (debt - cash) | B14: 8.0 | C14: 11.49 | D14: 18.73 | E14: 17.5 | F14: 15.5 | G14: 13.5 | H14: 11.5 | I14: 9.0
A16: FY2024-25 totals are audited (total assets KRW 67.1tn, equity to owners KRW 20.2tn, NCI KRW 9.1tn, borrowings KRW 22.5tn end-2025). NCI jumped from KRW 4.2tn (end-2023) to KRW 9.9tn (end-2024) as the US JV build-out and credit accrual landed — the balance-sheet signature of the owner-loss attribution.

Sheet Cash Flow
A1: Consolidated cash flow (simplified, KRW tn)
A2: FY2024-25 audited; FY2023 estimated; 2026e-30e illustrative. Free cash flow inflects positive from 2027e on the capex cut.
A4: Cash flow | B4: 2023a | C4: 2024a | D4: 2025a | E4: 2026e | F4: 2027e | G4: 2028e | H4: 2029e | I4: 2030e
A5: Operating cash flow | B5: 4.0 | C5: 5.11 | D5: 4.43 | E5: 5.0 | F5: 6.0 | G5: 7.0 | H5: 7.8 | I5: 8.5
A6: Capital expenditure | B6: (10.0) | C6: (12.40) | D6: (10.83) | E6: (6.5) | F6: (5.8) | G6: (5.5) | H6: (5.5) | I6: (5.5)
A7: Free cash flow | B7: (6.0) | C7: (7.29) | D7: (6.40) | E7: (1.5) | F7: 0.2 | G7: 1.5 | H7: 2.3 | I7: 3.0
A9: The capex peak (KRW 12.4tn 2024, 10.8tn 2025) drove free cash flow deeply negative; the guided >40% cut for 2026 and the taper turn it positive from 2027e — the inflection the DCF discounts.

Sheet Per-Share & Ratios
A1: Per-share & ratios
A2: Market and valuation ratios at the 26-Jun-2026 close.
A4: Market
A5: Spot (KRW) | B5: =Assumptions!B5
A6: Shares (m) | B6: =Assumptions!B6/10^6
A7: Market cap (KRW tn) | B7: =Assumptions!B9
A8: Net debt (KRW tn) | B8: =Assumptions!B7
A9: Enterprise value (KRW tn) | B9: =Assumptions!B10
A11: Valuation ratios
A12: P/B (x) | B12: =Assumptions!B5/Assumptions!B11
A13: EV/EBITDA — trailing (x, depressed) | B13: =Assumptions!B10/5.9
A14: EV/EBITDA — mid-cycle (x) | B14: =Assumptions!B10/Assumptions!B20
A15: Net debt / mid-cycle EBITDA (x) | B15: =Assumptions!B7/Assumptions!B20
A16: Trailing P/E (owners) | B16: N/M — owner EPS negative
A17: BVPS — owners (KRW) | B17: =Assumptions!B11
A19: Valuation conclusion
A20: Weighted central (KRW) | B20: ='Fundamental Valuation'!B11
A21: Central vs spot | B21: =B20/Assumptions!B5-1
A23: Trailing EV/EBITDA screens high (~21x) because EBITDA is depressed; trailing P/E is not meaningful because owner-level EPS is negative. The mid-cycle EV/EBITDA (~11x at the central EBITDA) is the more useful gauge.
