Workbook

Sheet READ FIRST
A1: Testahil — Saudi Arabian Mining Company (Maaden) · Tadawul: 1211
A2: Companion model · Independent Valuation Study — Educational Analysis · Not investment advice
A4: What this workbook is. A transparent companion to the Maaden study. Blue cells on the Assumptions sheet are the only inputs; every
A5: other cell is a formula that links back to them, so changing one input (a commodity price, a segment multiple, the WACC) reprices the
A6: whole model. Black = formula; green = link to another sheet; blue = input you can change.
A8: What it is not. It is not investment advice, a recommendation, or a price target. Outputs are fair-value ranges and probability
A9: distributions, presented as ranges because no single number should be relied on. The preparer is not licensed by any securities
A10: regulator and may hold a position in the security. See the study's Disclosure & Disclaimer.
A12: Currency note. Maaden reports in Saudi riyals (SAR). The riyal is pegged to the US dollar at 3.75, so — unlike a rupee or pound
A13: name — there is no material FX-translation swing in this model; commodity prices (in USD) convert at the peg.
A15: Calibration note (see study Appendix B). The Monte-Carlo engine was backtested five years on Maaden and did NOT beat a plain
A16: zero-drift random-walk cone on CRPS skill. Section 3 is therefore presented as an honest regime-conditional probability map, not a
A17: skill-validated forecast. Coverage/PIT diagnostics are shown for completeness only.

Sheet Summary
A1: Valuation summary — Saudi Arabian Mining Company (Maaden)
A2: Four-lens fair value vs spot. Bear/base/bull; weighted central.
A3: Lens | B3: Bear | C3: Base | D3: Bull | E3: Weight
A4: Sum-of-the-parts | B4: 28 | C4: =SOTP!$C$11 -> 44.201031 | D4: 60 | E4: 0.4
A5: Consolidated DCF | B5: 30 | C5: =DCF!$E$20 -> 47.44634 | D5: 62 | E5: 0.2
A6: Relative multiples | B6: 20 | C6: ='Relative & Normalized'!$C$4 -> 25.708763 | D6: 38 | E6: 0.15
A7: Mid-cycle earnings | B7: 28 | C7: ='Relative & Normalized'!$C$6 -> 42.216495 | D7: 58 | E7: 0.25
A8: Weighted central | B8: =SUMPRODUCT(B4:B7,$E$4:$E$7) -> 27.2 | C8: =SUMPRODUCT(C4:C7,$E$4:$E$7) -> 41.580118 | D8: =SUMPRODUCT(D4:D7,$E$4:$E$7) -> 56.6
A9: Spot price (SAR) | C9: =Assumptions!$B$5 -> 58.8
A10: Central vs spot | C10: =C8/C9-1 -> -0.29285513
A12: Read: richly valued — spot embeds a large Vision-2030 growth/sovereign premium over fundamental central.

Sheet Fundamental Valuation
A1: Fundamental valuation — four lenses
A2: Bear/base/bull per lens (links to Summary).
A3: Lens | B3: Bear | C3: Base | D3: Bull
A4: Sum-of-the-parts | B4: =Summary!B4 -> 28 | C4: =Summary!C4 -> 44.201031 | D4: =Summary!D4 -> 60
A5: Consolidated DCF | B5: =Summary!B5 -> 30 | C5: =Summary!C5 -> 47.44634 | D5: =Summary!D5 -> 62
A6: Relative multiples | B6: =Summary!B6 -> 20 | C6: =Summary!C6 -> 25.708763 | D6: =Summary!D6 -> 38
A7: Mid-cycle earnings | B7: =Summary!B7 -> 28 | C7: =Summary!C7 -> 42.216495 | D7: =Summary!D7 -> 58
A8: Weighted central | B8: =Summary!B8 -> 27.2 | C8: =Summary!C8 -> 41.580118 | D8: =Summary!D8 -> 56.6
A9: Spot | C9: =Assumptions!$B$5 -> 58.8

Sheet Assumptions
A1: Assumptions — the single input layer
A2: All blue cells are inputs. Every other sheet links here. SAR bn unless noted.
A4: ANCHORS
A5: Spot price (SAR/share) | B5: 58.8
A6: Shares outstanding (bn) | B6: 3.88
A7: Consolidated net debt (SAR bn) | B7: 24
A8: WACC | B8: 0.093
A9: Risk-free rate (rf) | B9: 0.045 | C9: Saudi 10-yr / USD-pegged
A10: Equity risk premium (ERP) | B10: 0.055
A11: Beta (house band 0.8-1.3) | B11: 0.95 | C11: realized 0.46; floored to house band
A12: Cost of equity Ke = rf + beta*ERP | B12: =B9+B11*B10 -> 0.09725
A13: Terminal growth | B13: 0.035
A14: Effective tax / zakat rate | B14: 0.08 | C14: Saudi zakat + partial income tax
A15: SOTP — segment marks (base)
A16: Phosphate normalized EBITDA | B16: 11 | C16: FY27E mid-cycle, DAP ~$650/t
A17: Phosphate EV/EBITDA | B17: 10.5 | C17: premium: tier-1 gas-cost + Phosphate 3
A18: Aluminium normalized EBITDA | B18: 3 | C18: fully consolidated (Alba/Alcoa)
A19: Aluminium EV/EBITDA | B19: 7
A20: Base Metals & New Minerals EBITDA | B20: 4.5 | C20: gold + copper; Ar Rjum ramp
A21: Base Metals & New Minerals EV/EBITDA | B21: 10
A22: New minerals / exploration / Manara mark | B22: 14 | C22: option value; Vale/FQM stakes (Maaden share)
A23: RELATIVE & NORMALIZED
A24: Relative: normalized group EBITDA | B24: 16.5
A25: Relative: peer EV/EBITDA multiple | B25: 7.5 | C25: diversified-miner blend, quality premium
A26: Mid-cycle net income | B26: 6.3 | C26: mid-cycle commodity prices
A27: Mid-cycle justified P/E | B27: 26 | C27: through-cycle, growth + sovereign
A28: DCF drivers (FY26E-FY30E)
A29: Revenue growth FY26E-FY30E | C29: per-year below (row E..I)
A30: Revenue growth (%) | E30: 0.075 | F30: 0.096 | G30: 0.077 | H30: 0.071 | I30: 0.067
A31: EBITDA margin (%) | E31: 0.405 | F31: 0.415 | G31: 0.42 | H31: 0.425 | I31: 0.428
A32: D&A (% of revenue) | E32: 0.14 | F32: 0.14 | G32: 0.14 | H32: 0.14 | I32: 0.14
A33: Capex (SAR bn) | E33: 9 | F33: 9 | G33: 8 | H33: 7.5 | I33: 7
A34: Increase in net working capital (SAR bn) | E34: 1.2 | F34: 1.1 | G34: 1 | H34: 0.9 | I34: 0.8
A35: MONTE CARLO (from analytics)
A36: Realized vol 252d (annualized) | B36: 0.324
A37: Net 3-month factor drift | B37: 0.022
A38: Paths / seed | B38: 50,000 · seed 42

Sheet SOTP
A1: Sum-of-the-parts (primary lens)
A2: Each commodity segment marked on a normalized EBITDA × a peer-plus EV/EBITDA multiple; less net debt. Marks link to Assumptions.
A3: Part | B3: Basis | C3: Value (SAR bn)
A4: Phosphate | B4: Norm. EBITDA × EV/EBITDA | C4: =Assumptions!$B$16*Assumptions!$B$17 -> 115.5
A5: Aluminium | B5: Norm. EBITDA × EV/EBITDA | C5: =Assumptions!$B$18*Assumptions!$B$19 -> 21
A6: Base Metals & New Minerals (gold/copper) | B6: Norm. EBITDA × EV/EBITDA | C6: =Assumptions!$B$20*Assumptions!$B$21 -> 45
A7: New minerals / exploration / Manara | B7: Option-value mark | C7: =Assumptions!$B$22 -> 14
A8: Σ Enterprise value | C8: =SUM(C4:C7) -> 195.5
A9: less: consolidated net debt | C9: =-Assumptions!$B$7 -> -24
A10: Equity value | C10: =C8+C9 -> 171.5
A11: per share (SAR) | C11: =C10/Assumptions!$B$6 -> 44.201031

Sheet Segments
A1: Segment view (SAR bn)
A2: Revenue and EBITDA by business unit, FY25 disclosed. Source: Maaden FY25 results.
A3: Segment | B3: Revenue FY25 | C3: EBITDA FY25 | D3: EBITDA margin | E3: % of EBITDA
A4: Phosphate | B4: 20.77 | C4: 9.76 | D4: =IF(B4=0,"n/m",C4/B4) -> 0.46990852 | E4: =C4/$C$8 -> 0.61
A5: Aluminium | B5: 10.99 | C5: 2.6 | D5: =IF(B5=0,"n/m",C5/B5) -> 0.23657871 | E5: =C5/$C$8 -> 0.1625
A6: Base Metals & New Minerals | B6: 6.82 | C6: 3.54 | D6: =IF(B6=0,"n/m",C6/B6) -> 0.51906158 | E6: =C6/$C$8 -> 0.22125
A7: Corporate / other | B7: 0 | C7: 0.1 | D7: =IF(B7=0,"n/m",C7/B7) -> n/m | E7: =C7/$C$8 -> 0.00625
A8: Total | B8: =SUM(B4:B7) -> 38.58 | C8: =SUM(C4:C7) -> 16

Sheet Relative & Normalized
A1: Relative & normalized-earnings lenses
A2: Links to Assumptions.
A3: Lens | B3: Workings | C3: SAR/share
A4: Relative EV/EBITDA | B4: Norm EBITDA × mult − net debt, /sh | C4: =(Assumptions!$B$24*Assumptions!$B$25-Assumptions!$B$7)/Assumptions!$B$6 -> 25.708763
A5: implied EV (SAR bn) | C5: =Assumptions!$B$24*Assumptions!$B$25 -> 123.75
A6: Mid-cycle earnings | B6: Mid-cycle NI × justified P/E, /sh | C6: =Assumptions!$B$26*Assumptions!$B$27/Assumptions!$B$6 -> 42.216495
A7: mid-cycle EPS (SAR) | C7: =Assumptions!$B$26/Assumptions!$B$6 -> 1.6237113

Sheet DCF
A1: Discounted cash flow — explicit 5-year FCFF
A2: NOPAT + D&A − capex − ΔWC, discounted at WACC (Ke = rf + beta·ERP). Free cash flow to the firm, five-year explicit forecast. Every input links to Assumptions.
A3: Line | E3: FY26E | F3: FY27E | G3: FY28E | H3: FY29E | I3: FY30E
A4: EBIT | E4: ='Income Statement'!E$7 -> 10.990478 | F4: ='Income Statement'!F$7 -> 12.500113 | G4: ='Income Statement'!G$7 -> 13.707397 | H4: ='Income Statement'!H$7 -> 14.942776 | I4: ='Income Statement'!I$7 -> 16.111773
A5: NOPAT = EBIT × (1 − tax) | E5: =E4*(1-Assumptions!$B$14) -> 10.111239 | F5: =F4*(1-Assumptions!$B$14) -> 11.500104 | G5: =G4*(1-Assumptions!$B$14) -> 12.610805 | H5: =H4*(1-Assumptions!$B$14) -> 13.747354 | I5: =I4*(1-Assumptions!$B$14) -> 14.822831
A6: + D&A | E6: ='Income Statement'!E$6 -> 5.80629 | F6: ='Income Statement'!F$6 -> 6.3636938 | G6: ='Income Statement'!G$6 -> 6.8536983 | H6: ='Income Statement'!H$6 -> 7.3403108 | I6: ='Income Statement'!I$6 -> 7.8321117
A7: − Capex | E7: =-Assumptions!E$33 -> -9 | F7: =-Assumptions!F$33 -> -9 | G7: =-Assumptions!G$33 -> -8 | H7: =-Assumptions!H$33 -> -7.5 | I7: =-Assumptions!I$33 -> -7
A8: − Increase in net working capital | E8: =-Assumptions!E$34 -> -1.2 | F8: =-Assumptions!F$34 -> -1.1 | G8: =-Assumptions!G$34 -> -1 | H8: =-Assumptions!H$34 -> -0.9 | I8: =-Assumptions!I$34 -> -0.8
A9: Free cash flow to firm (FCFF) | E9: =E5+E6+E7+E8 -> 5.7175293 | F9: =F5+F6+F7+F8 -> 7.7637977 | G9: =G5+G6+G7+G8 -> 10.464503 | H9: =H5+H6+H7+H8 -> 12.687664 | I9: =I5+I6+I7+I8 -> 14.854942
A10: Discount factor | E10: =1/(1+Assumptions!$B$8)^1 -> 0.91491308 | F10: =1/(1+Assumptions!$B$8)^2 -> 0.83706595 | G10: =1/(1+Assumptions!$B$8)^3 -> 0.76584259 | H10: =1/(1+Assumptions!$B$8)^4 -> 0.7006794 | I10: =1/(1+Assumptions!$B$8)^5 -> 0.64106075
A11: PV of FCFF | E11: =E9*E10 -> 5.2310424 | F11: =F9*F10 -> 6.4988107 | G11: =G9*G10 -> 8.0141621 | H11: =H9*H10 -> 8.8899852 | I11: =I9*I10 -> 9.5229206
A13: Σ PV of explicit FCFF (FY26E-FY30E) | E13: =SUM(E11:I11) -> 38.156921
A14: Terminal value (Gordon) = FCFF_FY30 × (1+g)/(WACC−g) | E14: =I9*(1+Assumptions!$B$13)/(Assumptions!$B$8-Assumptions!$B$13) -> 265.08389
A15: PV of terminal value | E15: =E14*I10 -> 169.93488
A16: Enterprise value | E16: =E13+E15 -> 208.0918
A17: TV as % of EV (device A-7 disclosure) | E17: =E15/E16 -> 0.81663419
A18: less: net debt | E18: =-Assumptions!$B$7 -> -24
A19: Equity value | E19: =E16+E18 -> 184.0918
A20: DCF fair value per share (SAR) | E20: =E19/Assumptions!$B$6 -> 47.44634

Sheet Income Statement
A1: Income statement (SAR bn, consolidated)
A2: FY23-FY25 disclosed (blue); FY26E-FY30E forecast (formulas). Source: Maaden FY25 results (5 Mar 2026), quarterly filings.
A3: Line | B3: FY23 | C3: FY24 | D3: FY25 | E3: FY26E | F3: FY27E | G3: FY28E | H3: FY29E | I3: FY30E
A4: Total revenue | B4: 27.9 | C4: 32.55 | D4: 38.58 | E4: =D4*(1+Assumptions!E$30) -> 41.4735 | F4: =E4*(1+Assumptions!F$30) -> 45.454956 | G4: =F4*(1+Assumptions!G$30) -> 48.954988 | H4: =G4*(1+Assumptions!H$30) -> 52.430792 | I4: =H4*(1+Assumptions!I$30) -> 55.943655
A5: EBITDA | B5: 9.5 | C5: 12.3 | D5: 16.1 | E5: =E4*Assumptions!E$31 -> 16.796768 | F5: =F4*Assumptions!F$31 -> 18.863807 | G5: =G4*Assumptions!G$31 -> 20.561095 | H5: =H4*Assumptions!H$31 -> 22.283086 | I5: =I4*Assumptions!I$31 -> 23.943884
A6: Depreciation & amortization (D&A) | B6: 5.5 | C6: 6 | D6: 6.6 | E6: =E4*Assumptions!E$32 -> 5.80629 | F6: =F4*Assumptions!F$32 -> 6.3636938 | G6: =G4*Assumptions!G$32 -> 6.8536983 | H6: =H4*Assumptions!H$32 -> 7.3403108 | I6: =I4*Assumptions!I$32 -> 7.8321117
A7: EBIT | B7: =B5-B6 -> 4 | C7: =C5-C6 -> 6.3 | D7: =D5-D6 -> 9.5 | E7: =E5-E6 -> 10.990478 | F7: =F5-F6 -> 12.500113 | G7: =G5-G6 -> 13.707397 | H7: =H5-H6 -> 14.942776 | I7: =I5-I6 -> 16.111773
A8: Net finance cost | B8: -2.1 | C8: -1.9 | D8: -1.9 | E8: -1.5 | F8: -1.4 | G8: -1.3 | H8: -1.2 | I8: -1.1
A9: Share of JV/associates + other | B9: 0.3 | C9: 0.3 | D9: 0.7 | E9: 0.5 | F9: 0.5 | G9: 0.6 | H9: 0.6 | I9: 0.7
A10: Profit before zakat & tax | B10: =B7+B8+B9 -> 2.2 | C10: =C7+C8+C9 -> 4.7 | D10: =D7+D8+D9 -> 8.3 | E10: =E7+E8+E9 -> 9.9904775 | F10: =F7+F8+F9 -> 11.600113 | G10: =G7+G8+G9 -> 13.007397 | H10: =H7+H8+H9 -> 14.342776 | I10: =I7+I8+I9 -> 15.711773
A11: Zakat & income tax | B11: =-B10*Assumptions!$B$14 -> -0.176 | C11: =-C10*Assumptions!$B$14 -> -0.376 | D11: =-D10*Assumptions!$B$14 -> -0.664 | E11: =-E10*Assumptions!$B$14 -> -0.7992382 | F11: =-F10*Assumptions!$B$14 -> -0.92800903 | G11: =-G10*Assumptions!$B$14 -> -1.0405917 | H11: =-H10*Assumptions!$B$14 -> -1.1474221 | I11: =-I10*Assumptions!$B$14 -> -1.2569418
A12: Non-controlling interests | B12: -0.444 | C12: -1.454 | D12: -0.286 | E12: -0.6 | F12: -0.6 | G12: -0.7 | H12: -0.7 | I12: -0.8
A13: Net profit (attributable) | B13: =B10+B11+B12 -> 1.58 | C13: =C10+C11+C12 -> 2.87 | D13: =D10+D11+D12 -> 7.35 | E13: =E10+E11+E12 -> 8.5912393 | F13: =F10+F11+F12 -> 10.072104 | G13: =G10+G11+G12 -> 11.266805 | H13: =H10+H11+H12 -> 12.495354 | I13: =I10+I11+I12 -> 13.654831
A14: EBITDA margin | B14: =B5/B4 -> 0.34050179 | C14: =C5/C4 -> 0.37788018 | D14: =D5/D4 -> 0.41731467 | E14: =E5/E4 -> 0.405 | F14: =F5/F4 -> 0.415 | G14: =G5/G4 -> 0.42 | H14: =H5/H4 -> 0.425 | I14: =I5/I4 -> 0.428
A15: Net margin | B15: =B13/B4 -> 0.056630824 | C15: =C13/C4 -> 0.088172043 | D15: =D13/D4 -> 0.19051322 | E15: =E13/E4 -> 0.20715009 | F15: =F13/F4 -> 0.22158428 | G15: =G13/G4 -> 0.23014621 | H15: =H13/H4 -> 0.2383209 | I15: =I13/I4 -> 0.24408185
A17: Note: FY23 revenue and weak-year figures approximate (post-2022 peak). FY24/FY25 per company disclosure.

Sheet Balance Sheet
A1: Balance sheet (SAR bn, consolidated)
A2: FY23-FY25 anchored to disclosure; FY26E-FY30E rolled forward. Equity per company (FY25 SAR 61.6bn).
A3: Line | B3: FY23 | C3: FY24 | D3: FY25 | E3: FY26E | F3: FY27E | G3: FY28E | H3: FY29E | I3: FY30E
A4: PP&E + intangibles | B4: 92 | C4: 101 | D4: 108 | E4: =D4+Assumptions!E$33-'Income Statement'!E$6 -> 111.19371 | F4: =E4+Assumptions!F$33-'Income Statement'!F$6 -> 113.83002 | G4: =F4+Assumptions!G$33-'Income Statement'!G$6 -> 114.97632 | H4: =G4+Assumptions!H$33-'Income Statement'!H$6 -> 115.13601 | I4: =H4+Assumptions!I$33-'Income Statement'!I$6 -> 114.3039
A5: Inventory + receivables + other CA | B5: 18 | C5: 19.5 | D5: 21.5 | E5: ='Income Statement'!E$4*0.55 -> 22.810425 | F5: ='Income Statement'!F$4*0.55 -> 25.000226 | G5: ='Income Statement'!G$4*0.55 -> 26.925243 | H5: ='Income Statement'!H$4*0.55 -> 28.836935 | I5: ='Income Statement'!I$4*0.55 -> 30.76901
A6: Cash & equivalents | B6: 8.5 | C6: 9 | D6: 11 | E6: =D6+'Cash Flow'!E$12 -> 15.797529 | F6: =E6+'Cash Flow'!F$12 -> 22.733327 | G6: =F6+'Cash Flow'!G$12 -> 32.55383 | H6: =G6+'Cash Flow'!H$12 -> 44.689495 | I6: =H6+'Cash Flow'!I$12 -> 59.176437
A7: Total assets | B7: 118.5 | C7: 129.5 | D7: 140.5 | E7: =E4+E5+E6 -> 149.80166 | F7: =F4+F5+F6 -> 161.56357 | G7: =G4+G5+G6 -> 174.45539 | H7: =H4+H5+H6 -> 188.66244 | I7: =I4+I5+I6 -> 204.24934
A8: Borrowings (gross debt) | B8: 30 | C8: 31 | D8: 35 | E8: =D8 -> 35 | F8: =E8 -> 35 | G8: =F8 -> 35 | H8: =G8 -> 35 | I8: =H8 -> 35
A9: Payables + provisions + other | B9: 25.5 | C9: 30.6 | D9: 26.9 | E9: =D9*1.03 -> 27.707 | F9: =E9*1.03 -> 28.53821 | G9: =F9*1.03 -> 29.394356 | H9: =G9*1.03 -> 30.276187 | I9: =H9*1.03 -> 31.184473
A10: Non-controlling interests | B10: 15 | C10: 16 | D10: 17 | E10: =D10+'Income Statement'!E$12*-1 -> 17.6 | F10: =E10+'Income Statement'!F$12*-1 -> 18.2 | G10: =F10+'Income Statement'!G$12*-1 -> 18.9 | H10: =G10+'Income Statement'!H$12*-1 -> 19.6 | I10: =H10+'Income Statement'!I$12*-1 -> 20.4
A11: Equity (attributable) | B11: 48 | C11: 51.89 | D11: 61.59 | E11: =D11+'Income Statement'!E$13 -> 70.181239 | F11: =E11+'Income Statement'!F$13 -> 80.253343 | G11: =F11+'Income Statement'!G$13 -> 91.520148 | H11: =G11+'Income Statement'!H$13 -> 104.0155 | I11: =H11+'Income Statement'!I$13 -> 117.67033
A12: Net debt = borrowings − cash | B12: =B8-B6 -> 21.5 | C12: =C8-C6 -> 22 | D12: =D8-D6 -> 24 | E12: =E8-E6 -> 19.202471 | F12: =F8-F6 -> 12.266673 | G12: =G8-G6 -> 2.4461699 | H12: =H8-H6 -> -9.6894945 | I12: =I8-I6 -> -24.176437
A13: Check: assets − liabilities − equity − NCI (≈0) | B13: =B7-B8-B9-B11-B10 -> 0 | C13: =C7-C8-C9-C11-C10 -> 0.01 | D13: =D7-D8-D9-D11-D10 -> 0.01

Sheet Cash Flow
A1: Cash flow (SAR bn, forecast)
A2: Derived from the Income Statement and Assumptions. FY26E-FY30E.
A3: Line | E3: FY26E | F3: FY27E | G3: FY28E | H3: FY29E | I3: FY30E
A4: Net profit (attributable) | E4: ='Income Statement'!E$13 -> 8.5912393 | F4: ='Income Statement'!F$13 -> 10.072104 | G4: ='Income Statement'!G$13 -> 11.266805 | H4: ='Income Statement'!H$13 -> 12.495354 | I4: ='Income Statement'!I$13 -> 13.654831
A5: + Non-controlling interests | E5: =-'Income Statement'!E$12 -> 0.6 | F5: =-'Income Statement'!F$12 -> 0.6 | G5: =-'Income Statement'!G$12 -> 0.7 | H5: =-'Income Statement'!H$12 -> 0.7 | I5: =-'Income Statement'!I$12 -> 0.8
A6: + D&A | E6: ='Income Statement'!E$6 -> 5.80629 | F6: ='Income Statement'!F$6 -> 6.3636938 | G6: ='Income Statement'!G$6 -> 6.8536983 | H6: ='Income Statement'!H$6 -> 7.3403108 | I6: ='Income Statement'!I$6 -> 7.8321117
A7: − Increase in net working capital | E7: =-Assumptions!E$34 -> -1.2 | F7: =-Assumptions!F$34 -> -1.1 | G7: =-Assumptions!G$34 -> -1 | H7: =-Assumptions!H$34 -> -0.9 | I7: =-Assumptions!I$34 -> -0.8
A8: Operating cash flow | E8: =E4+E5+E6+E7 -> 13.797529 | F8: =F4+F5+F6+F7 -> 15.935798 | G8: =G4+G5+G6+G7 -> 17.820503 | H8: =H4+H5+H6+H7 -> 19.635664 | I8: =I4+I5+I6+I7 -> 21.486942
A9: − Capex | E9: =-Assumptions!E$33 -> -9 | F9: =-Assumptions!F$33 -> -9 | G9: =-Assumptions!G$33 -> -8 | H9: =-Assumptions!H$33 -> -7.5 | I9: =-Assumptions!I$33 -> -7
A10: Free cash flow (to equity, pre-financing) | E10: =E8+E9 -> 4.7975293 | F10: =F8+F9 -> 6.9357977 | G10: =G8+G9 -> 9.8205031 | H10: =H8+H9 -> 12.135664 | I10: =I8+I9 -> 14.486942
A11: − Net debt change / dividends (balancing) | E11: =0 -> 0 | F11: =0 -> 0 | G11: =0 -> 0 | H11: =0 -> 0 | I11: =0 -> 0
A12: Net change in cash | E12: =E10+E11 -> 4.7975293 | F12: =F10+F11 -> 6.9357977 | G12: =G10+G11 -> 9.8205031 | H12: =H10+H11 -> 12.135664 | I12: =I10+I11 -> 14.486942

Sheet Summary Financials
A1: Summary financials (SAR bn)
A2: Every cell links to the statement sheets.
A3: Line | B3: FY23 | C3: FY24 | D3: FY25 | E3: FY26E | F3: FY27E | G3: FY28E | H3: FY29E | I3: FY30E
A4: Revenue | B4: ='Income Statement'!B4 -> 27.9 | C4: ='Income Statement'!C4 -> 32.55 | D4: ='Income Statement'!D4 -> 38.58 | E4: ='Income Statement'!E4 -> 41.4735 | F4: ='Income Statement'!F4 -> 45.454956 | G4: ='Income Statement'!G4 -> 48.954988 | H4: ='Income Statement'!H4 -> 52.430792 | I4: ='Income Statement'!I4 -> 55.943655
A5: EBITDA | B5: ='Income Statement'!B5 -> 9.5 | C5: ='Income Statement'!C5 -> 12.3 | D5: ='Income Statement'!D5 -> 16.1 | E5: ='Income Statement'!E5 -> 16.796768 | F5: ='Income Statement'!F5 -> 18.863807 | G5: ='Income Statement'!G5 -> 20.561095 | H5: ='Income Statement'!H5 -> 22.283086 | I5: ='Income Statement'!I5 -> 23.943884
A6: EBIT | B6: ='Income Statement'!B7 -> 4 | C6: ='Income Statement'!C7 -> 6.3 | D6: ='Income Statement'!D7 -> 9.5 | E6: ='Income Statement'!E7 -> 10.990478 | F6: ='Income Statement'!F7 -> 12.500113 | G6: ='Income Statement'!G7 -> 13.707397 | H6: ='Income Statement'!H7 -> 14.942776 | I6: ='Income Statement'!I7 -> 16.111773
A7: Net profit (attributable) | B7: ='Income Statement'!B13 -> 1.58 | C7: ='Income Statement'!C13 -> 2.87 | D7: ='Income Statement'!D13 -> 7.35 | E7: ='Income Statement'!E13 -> 8.5912393 | F7: ='Income Statement'!F13 -> 10.072104 | G7: ='Income Statement'!G13 -> 11.266805 | H7: ='Income Statement'!H13 -> 12.495354 | I7: ='Income Statement'!I13 -> 13.654831
A8: Equity (attributable) | B8: ='Balance Sheet'!B11 -> 48 | C8: ='Balance Sheet'!C11 -> 51.89 | D8: ='Balance Sheet'!D11 -> 61.59 | E8: ='Balance Sheet'!E11 -> 70.181239 | F8: ='Balance Sheet'!F11 -> 80.253343 | G8: ='Balance Sheet'!G11 -> 91.520148 | H8: ='Balance Sheet'!H11 -> 104.0155 | I8: ='Balance Sheet'!I11 -> 117.67033
A9: Net debt | B9: ='Balance Sheet'!B12 -> 21.5 | C9: ='Balance Sheet'!C12 -> 22 | D9: ='Balance Sheet'!D12 -> 24 | E9: ='Balance Sheet'!E12 -> 19.202471 | F9: ='Balance Sheet'!F12 -> 12.266673 | G9: ='Balance Sheet'!G12 -> 2.4461699 | H9: ='Balance Sheet'!H12 -> -9.6894945 | I9: ='Balance Sheet'!I12 -> -24.176437
A10: Net debt / EBITDA | B10: ='Balance Sheet'!B12/'Income Statement'!B5 -> 2.2631579 | C10: ='Balance Sheet'!C12/'Income Statement'!C5 -> 1.7886179 | D10: ='Balance Sheet'!D12/'Income Statement'!D5 -> 1.4906832 | E10: ='Balance Sheet'!E12/'Income Statement'!E5 -> 1.1432242 | F10: ='Balance Sheet'!F12/'Income Statement'!F5 -> 0.65027559 | G10: ='Balance Sheet'!G12/'Income Statement'!G5 -> 0.1189708 | H10: ='Balance Sheet'!H12/'Income Statement'!H5 -> -0.43483628 | I10: ='Balance Sheet'!I12/'Income Statement'!I5 -> -1.0097124

Sheet Monte Carlo
A1: Monte Carlo — engine output
A2: 50,000 paths · 16 factors · seed 42. Honest regime-conditional cone (no CRPS skill vs RW; see Appendix B). SAR/share.
A4: Horizon | B4: p5 | C4: p25 | D4: p50 | E4: p75 | F4: p95
A5: T+20 sessions | B5: 50.7 | C5: 55.6 | D5: 59.2 | E5: 63.1 | F5: 69.1
A6: T+60 sessions | B6: 46.1 | C6: 53.9 | D6: 60.1 | E6: 67.1 | F6: 78.4
A8: Inputs (from Assumptions): | B8: =Assumptions!$B$36 -> 0.324
A9: net 3-month factor drift | B9: =Assumptions!$B$37 -> 0.022
A11: Level-touch ladder
A12: Level | B12: T+20 | C12: T+60
A13: 80 | B13: 0.001 | C13: 0.064
A14: 72 | B14: 0.028 | C14: 0.223
A15: 66 | B15: 0.199 | C15: 0.481
A16: 62 | B16: 0.516 | C16: 0.727
A17: 58 | B17: 0.76 | C17: 0.851
A18: 54 | B18: 0.279 | C18: 0.511
A19: 50 | B19: 0.058 | C19: 0.246
A20: 46 | B20: 0.006 | C20: 0.091

Sheet Sensitivity
A1: SOTP sensitivity — DAP price × phosphate multiple
A2: Fair value (SAR/share). Other segments held at base. DAP is 55% price-geared into phosphate EBITDA.
A3: mult \ DAP $/t | B3: 500 | C3: 575 | D3: 650 | E3: 725 | F3: 800
A4: 7.5 | B4: =((Assumptions!$B$16*(0.45+0.55*500/650)*$A4)+(Assumptions!$B$18*Assumptions!$B$19)+(Assumptions!$B$20*Assumptions!$B$21)+Assumptions!$B$22-Assumptions!$B$7)/Assumptions!$B$6 -> 32.997125 | C4: =((Assumptions!$B$16*(0.45+0.55*575/650)*$A4)+(Assumptions!$B$18*Assumptions!$B$19)+(Assumptions!$B$20*Assumptions!$B$21)+Assumptions!$B$22-Assumptions!$B$7)/Assumptions!$B$6 -> 34.346501 | D4: =((Assumptions!$B$16*(0.45+0.55*650/650)*$A4)+(Assumptions!$B$18*Assumptions!$B$19)+(Assumptions!$B$20*Assumptions!$B$21)+Assumptions!$B$22-Assumptions!$B$7)/Assumptions!$B$6 -> 35.695876 | E4: =((Assumptions!$B$16*(0.45+0.55*725/650)*$A4)+(Assumptions!$B$18*Assumptions!$B$19)+(Assumptions!$B$20*Assumptions!$B$21)+Assumptions!$B$22-Assumptions!$B$7)/Assumptions!$B$6 -> 37.045252 | F4: =((Assumptions!$B$16*(0.45+0.55*800/650)*$A4)+(Assumptions!$B$18*Assumptions!$B$19)+(Assumptions!$B$20*Assumptions!$B$21)+Assumptions!$B$22-Assumptions!$B$7)/Assumptions!$B$6 -> 38.394627
A5: 8.5 | B5: =((Assumptions!$B$16*(0.45+0.55*500/650)*$A5)+(Assumptions!$B$18*Assumptions!$B$19)+(Assumptions!$B$20*Assumptions!$B$21)+Assumptions!$B$22-Assumptions!$B$7)/Assumptions!$B$6 -> 35.472343 | C5: =((Assumptions!$B$16*(0.45+0.55*575/650)*$A5)+(Assumptions!$B$18*Assumptions!$B$19)+(Assumptions!$B$20*Assumptions!$B$21)+Assumptions!$B$22-Assumptions!$B$7)/Assumptions!$B$6 -> 37.001636 | D5: =((Assumptions!$B$16*(0.45+0.55*650/650)*$A5)+(Assumptions!$B$18*Assumptions!$B$19)+(Assumptions!$B$20*Assumptions!$B$21)+Assumptions!$B$22-Assumptions!$B$7)/Assumptions!$B$6 -> 38.530928 | E5: =((Assumptions!$B$16*(0.45+0.55*725/650)*$A5)+(Assumptions!$B$18*Assumptions!$B$19)+(Assumptions!$B$20*Assumptions!$B$21)+Assumptions!$B$22-Assumptions!$B$7)/Assumptions!$B$6 -> 40.06022 | F5: =((Assumptions!$B$16*(0.45+0.55*800/650)*$A5)+(Assumptions!$B$18*Assumptions!$B$19)+(Assumptions!$B$20*Assumptions!$B$21)+Assumptions!$B$22-Assumptions!$B$7)/Assumptions!$B$6 -> 41.589512
A6: 9.5 | B6: =((Assumptions!$B$16*(0.45+0.55*500/650)*$A6)+(Assumptions!$B$18*Assumptions!$B$19)+(Assumptions!$B$20*Assumptions!$B$21)+Assumptions!$B$22-Assumptions!$B$7)/Assumptions!$B$6 -> 37.947561 | C6: =((Assumptions!$B$16*(0.45+0.55*575/650)*$A6)+(Assumptions!$B$18*Assumptions!$B$19)+(Assumptions!$B$20*Assumptions!$B$21)+Assumptions!$B$22-Assumptions!$B$7)/Assumptions!$B$6 -> 39.65677 | D6: =((Assumptions!$B$16*(0.45+0.55*650/650)*$A6)+(Assumptions!$B$18*Assumptions!$B$19)+(Assumptions!$B$20*Assumptions!$B$21)+Assumptions!$B$22-Assumptions!$B$7)/Assumptions!$B$6 -> 41.365979 | E6: =((Assumptions!$B$16*(0.45+0.55*725/650)*$A6)+(Assumptions!$B$18*Assumptions!$B$19)+(Assumptions!$B$20*Assumptions!$B$21)+Assumptions!$B$22-Assumptions!$B$7)/Assumptions!$B$6 -> 43.075188 | F6: =((Assumptions!$B$16*(0.45+0.55*800/650)*$A6)+(Assumptions!$B$18*Assumptions!$B$19)+(Assumptions!$B$20*Assumptions!$B$21)+Assumptions!$B$22-Assumptions!$B$7)/Assumptions!$B$6 -> 44.784397
A7: 10.5 | B7: =((Assumptions!$B$16*(0.45+0.55*500/650)*$A7)+(Assumptions!$B$18*Assumptions!$B$19)+(Assumptions!$B$20*Assumptions!$B$21)+Assumptions!$B$22-Assumptions!$B$7)/Assumptions!$B$6 -> 40.42278 | C7: =((Assumptions!$B$16*(0.45+0.55*575/650)*$A7)+(Assumptions!$B$18*Assumptions!$B$19)+(Assumptions!$B$20*Assumptions!$B$21)+Assumptions!$B$22-Assumptions!$B$7)/Assumptions!$B$6 -> 42.311905 | D7: =((Assumptions!$B$16*(0.45+0.55*650/650)*$A7)+(Assumptions!$B$18*Assumptions!$B$19)+(Assumptions!$B$20*Assumptions!$B$21)+Assumptions!$B$22-Assumptions!$B$7)/Assumptions!$B$6 -> 44.201031 | E7: =((Assumptions!$B$16*(0.45+0.55*725/650)*$A7)+(Assumptions!$B$18*Assumptions!$B$19)+(Assumptions!$B$20*Assumptions!$B$21)+Assumptions!$B$22-Assumptions!$B$7)/Assumptions!$B$6 -> 46.090157 | F7: =((Assumptions!$B$16*(0.45+0.55*800/650)*$A7)+(Assumptions!$B$18*Assumptions!$B$19)+(Assumptions!$B$20*Assumptions!$B$21)+Assumptions!$B$22-Assumptions!$B$7)/Assumptions!$B$6 -> 47.979282
A8: 11.5 | B8: =((Assumptions!$B$16*(0.45+0.55*500/650)*$A8)+(Assumptions!$B$18*Assumptions!$B$19)+(Assumptions!$B$20*Assumptions!$B$21)+Assumptions!$B$22-Assumptions!$B$7)/Assumptions!$B$6 -> 42.897998 | C8: =((Assumptions!$B$16*(0.45+0.55*575/650)*$A8)+(Assumptions!$B$18*Assumptions!$B$19)+(Assumptions!$B$20*Assumptions!$B$21)+Assumptions!$B$22-Assumptions!$B$7)/Assumptions!$B$6 -> 44.96704 | D8: =((Assumptions!$B$16*(0.45+0.55*650/650)*$A8)+(Assumptions!$B$18*Assumptions!$B$19)+(Assumptions!$B$20*Assumptions!$B$21)+Assumptions!$B$22-Assumptions!$B$7)/Assumptions!$B$6 -> 47.036082 | E8: =((Assumptions!$B$16*(0.45+0.55*725/650)*$A8)+(Assumptions!$B$18*Assumptions!$B$19)+(Assumptions!$B$20*Assumptions!$B$21)+Assumptions!$B$22-Assumptions!$B$7)/Assumptions!$B$6 -> 49.105125 | F8: =((Assumptions!$B$16*(0.45+0.55*800/650)*$A8)+(Assumptions!$B$18*Assumptions!$B$19)+(Assumptions!$B$20*Assumptions!$B$21)+Assumptions!$B$22-Assumptions!$B$7)/Assumptions!$B$6 -> 51.174167
A10: Cells near spot (SAR 58.8) indicate the DAP/multiple the market is implying.

Sheet Per-Share & Ratios
A1: Per-share & ratios
A2: Links to statements / Assumptions. The standing ratio dashboard (device A-5).
A3: Metric | B3: FY23 | C3: FY24 | D3: FY25 | E3: FY26E | F3: FY27E | G3: FY28E | H3: FY29E | I3: FY30E
A4: EPS (SAR) | B4: ='Income Statement'!B13/Assumptions!$B$6 -> 0.40721649 | C4: ='Income Statement'!C13/Assumptions!$B$6 -> 0.73969072 | D4: ='Income Statement'!D13/Assumptions!$B$6 -> 1.8943299 | E4: ='Income Statement'!E13/Assumptions!$B$6 -> 2.2142369 | F4: ='Income Statement'!F13/Assumptions!$B$6 -> 2.5959031 | G4: ='Income Statement'!G13/Assumptions!$B$6 -> 2.9038157 | H4: ='Income Statement'!H13/Assumptions!$B$6 -> 3.220452 | I4: ='Income Statement'!I13/Assumptions!$B$6 -> 3.5192863
A5: Book value/share (SAR) | B5: ='Balance Sheet'!B11/Assumptions!$B$6 -> 12.371134 | C5: ='Balance Sheet'!C11/Assumptions!$B$6 -> 13.373711 | D5: ='Balance Sheet'!D11/Assumptions!$B$6 -> 15.873711 | E5: ='Balance Sheet'!E11/Assumptions!$B$6 -> 18.087948 | F5: ='Balance Sheet'!F11/Assumptions!$B$6 -> 20.683851 | G5: ='Balance Sheet'!G11/Assumptions!$B$6 -> 23.587667 | H5: ='Balance Sheet'!H11/Assumptions!$B$6 -> 26.808119 | I5: ='Balance Sheet'!I11/Assumptions!$B$6 -> 30.327405
A6: EBITDA margin | B6: ='Income Statement'!B5/'Income Statement'!B4 -> 0.34050179 | C6: ='Income Statement'!C5/'Income Statement'!C4 -> 0.37788018 | D6: ='Income Statement'!D5/'Income Statement'!D4 -> 0.41731467 | E6: ='Income Statement'!E5/'Income Statement'!E4 -> 0.405 | F6: ='Income Statement'!F5/'Income Statement'!F4 -> 0.415 | G6: ='Income Statement'!G5/'Income Statement'!G4 -> 0.42 | H6: ='Income Statement'!H5/'Income Statement'!H4 -> 0.425 | I6: ='Income Statement'!I5/'Income Statement'!I4 -> 0.428
A7: Net margin | B7: ='Income Statement'!B13/'Income Statement'!B4 -> 0.056630824 | C7: ='Income Statement'!C13/'Income Statement'!C4 -> 0.088172043 | D7: ='Income Statement'!D13/'Income Statement'!D4 -> 0.19051322 | E7: ='Income Statement'!E13/'Income Statement'!E4 -> 0.20715009 | F7: ='Income Statement'!F13/'Income Statement'!F4 -> 0.22158428 | G7: ='Income Statement'!G13/'Income Statement'!G4 -> 0.23014621 | H7: ='Income Statement'!H13/'Income Statement'!H4 -> 0.2383209 | I7: ='Income Statement'!I13/'Income Statement'!I4 -> 0.24408185
A8: Net debt / EBITDA | B8: ='Balance Sheet'!B12/'Income Statement'!B5 -> 2.2631579 | C8: ='Balance Sheet'!C12/'Income Statement'!C5 -> 1.7886179 | D8: ='Balance Sheet'!D12/'Income Statement'!D5 -> 1.4906832 | E8: ='Balance Sheet'!E12/'Income Statement'!E5 -> 1.1432242 | F8: ='Balance Sheet'!F12/'Income Statement'!F5 -> 0.65027559 | G8: ='Balance Sheet'!G12/'Income Statement'!G5 -> 0.1189708 | H8: ='Balance Sheet'!H12/'Income Statement'!H5 -> -0.43483628 | I8: ='Balance Sheet'!I12/'Income Statement'!I5 -> -1.0097124
A9: ROE (attributable) | B9: ='Income Statement'!B13/'Balance Sheet'!B11 -> 0.032916667 | C9: ='Income Statement'!C13/'Balance Sheet'!C11 -> 0.055309308 | D9: ='Income Statement'!D13/'Balance Sheet'!D11 -> 0.11933755 | E9: ='Income Statement'!E13/'Balance Sheet'!E11 -> 0.12241504 | F9: ='Income Statement'!F13/'Balance Sheet'!F11 -> 0.12550385 | G9: ='Income Statement'!G13/'Balance Sheet'!G11 -> 0.12310737 | H9: ='Income Statement'!H13/'Balance Sheet'!H11 -> 0.12012972 | I9: ='Income Statement'!I13/'Balance Sheet'!I11 -> 0.11604311
A10: P/E (on spot) | B10: =Assumptions!$B$5/('Income Statement'!B13/Assumptions!$B$6) -> 144.39494 | C10: =Assumptions!$B$5/('Income Statement'!C13/Assumptions!$B$6) -> 79.492683 | D10: =Assumptions!$B$5/('Income Statement'!D13/Assumptions!$B$6) -> 31.04 | E10: =Assumptions!$B$5/('Income Statement'!E13/Assumptions!$B$6) -> 26.555424 | F10: =Assumptions!$B$5/('Income Statement'!F13/Assumptions!$B$6) -> 22.651077 | G10: =Assumptions!$B$5/('Income Statement'!G13/Assumptions!$B$6) -> 20.249219 | H10: =Assumptions!$B$5/('Income Statement'!H13/Assumptions!$B$6) -> 18.258307 | I10: =Assumptions!$B$5/('Income Statement'!I13/Assumptions!$B$6) -> 16.707933
A11: EV/EBITDA (on spot mktcap+netdebt) | B11: =(Assumptions!$B$5*Assumptions!$B$6+'Balance Sheet'!B12)/'Income Statement'!B5 -> 26.278316 | C11: =(Assumptions!$B$5*Assumptions!$B$6+'Balance Sheet'!C12)/'Income Statement'!C5 -> 20.336911 | D11: =(Assumptions!$B$5*Assumptions!$B$6+'Balance Sheet'!D12)/'Income Statement'!D5 -> 15.661118 | E11: =(Assumptions!$B$5*Assumptions!$B$6+'Balance Sheet'!E12)/'Income Statement'!E5 -> 14.725838 | F11: =(Assumptions!$B$5*Assumptions!$B$6+'Balance Sheet'!F12)/'Income Statement'!F5 -> 12.744547 | G11: =(Assumptions!$B$5*Assumptions!$B$6+'Balance Sheet'!G12)/'Income Statement'!G5 -> 11.214878 | H11: =(Assumptions!$B$5*Assumptions!$B$6+'Balance Sheet'!H12)/'Income Statement'!H5 -> 9.8036017 | I11: =(Assumptions!$B$5*Assumptions!$B$6+'Balance Sheet'!I12)/'Income Statement'!I5 -> 8.5185662
A12: Dividend / share (SAR) | B12: =0 -> 0 | C12: =0 -> 0 | D12: =0 -> 0 | E12: =0 -> 0 | F12: =0 -> 0 | G12: =0 -> 0 | H12: =0 -> 0 | I12: =0 -> 0
A13: Note: Maaden pays no dividend (growth phase); capex-funded. Capital trajectory is the future-payout thesis.

Sheet Peer & Sector
A1: Peer set & sector
A2: No single clean comparable — split by commodity. Typical multiples are context, not targets.
A3: Segment | B3: Closest peers | C3: Typical valuation
A4: Phosphate / fertilizer | B4: Mosaic, Nutrien, OCP, ICL | C4: EV/EBITDA ~5–8x; cyclical
A5: Aluminium | B5: Alcoa, Norsk Hydro, Alba, EGA | C5: EV/EBITDA ~4–6x
A6: Gold / base metals | B6: Barrick, Newmont, AngloGold | C6: EV/EBITDA ~6–9x
A7: Diversified majors | B7: BHP, Rio Tinto, Vale, Anglo | C7: EV/EBITDA ~5–7x; P/E ~8–14x
A9: Maaden trades ~15x EV/EBITDA and ~31x P/E — a large premium to all peer groups; the premium is the Vision-2030 growth thesis.
