Workbook

Sheet READ FIRST
A1: READ FIRST
A2: Educational valuation study - not investment advice. Distributions, not tips. All inputs on Assumptions.

Sheet Summary
A1: Summary - Oriental Weavers (EGX: ORWE)
A4: Spot | B4: =Assumptions!$B$4 -> 22.34
A5: DCF (FCFE) fair value | B5: =DCF!B17 -> 17.300509
A6: Mid-cycle cross-check | B6: =SOTP!B9 -> 21.201301

Sheet Fundamental Valuation
A1: Fundamental valuation - lens synthesis
A2: Weighted fair value across the lenses (football field in the report).

Sheet Assumptions
A1: Assumptions - single input layer · Oriental Weavers (EGX: ORWE)
A2: Blue = input. FY = calendar year; EGP mn. Sources: 4Q23 earnings release, Mubasher FY24 results, AGM dividend disclosure Apr-2026; estimates flagged.
A3: ANCHORS
A4: Spot price (EGP/share) | B4: 22.34
A5: Shares outstanding (mn, per dividend arithmetic - confirm) | B5: 665.1
A8: Net debt (EGP mn, est.) | B8: 2000
A9: Cost of equity (nominal EGP) | B9: 0.24
A10: Terminal growth (nominal) | B10: 0.11
A11: Tax & minorities % of PBT | B11: 0.28
A13: MID-CYCLE CROSS-CHECK MARKS
A14: Mid-cycle EBITDA margin | B14: 0.12
A15: Mid-cycle EV/EBITDA | B15: 4.5
A20: FORECAST DRIVERS
E21: FY26E | F21: FY27E | G21: FY28E | H21: FY29E | I21: FY30E
A22: Revenue growth | E22: 0.12 | F22: 0.11 | G22: 0.1 | H22: 0.1 | I22: 0.09
A23: Gross margin | E23: 0.125 | F23: 0.128 | G23: 0.13 | H23: 0.132 | I23: 0.134
A24: SG&A % of revenue | E24: 0.04 | F24: 0.04 | G24: 0.04 | H24: 0.04 | I24: 0.04
A25: D&A % of revenue | E25: 0.03 | F25: 0.03 | G25: 0.03 | H25: 0.03 | I25: 0.03
A26: Net interest, FX & other income (EGP mn) | E26: 900 | F26: 850 | G26: 800 | H26: 800 | I26: 800
A27: Capex % of revenue | E27: 0.035 | F27: 0.035 | G27: 0.035 | H27: 0.035 | I27: 0.035
A28: Net WC % of revenue | E28: 0.28 | F28: 0.28 | G28: 0.28 | H28: 0.28 | I28: 0.28

Sheet SOTP
A1: Mid-cycle EBITDA cross-check (EGP mn)
A2: Enterprise view: mid-cycle EBITDA x multiple, less net debt - the lens that ignores the one-off other-income layer entirely.
A3: Component | B3: Value
A4: Mid-cycle EBITDA (FY26E rev x margin) | B4: ='Income Statement'!E4*Assumptions!$B$14 -> 3577.9968
A5: x EV/EBITDA | B5: =Assumptions!$B$15 -> 4.5
A6: Enterprise value | B6: =B4*B5 -> 16100.986
A7: - Net debt | B7: =-Assumptions!$B$8 -> -2000
A8: Equity value | B8: =B6+B7 -> 14100.986
A9: Per share | B9: =B8/Assumptions!$B$5 -> 21.201301

Sheet Segments
A1: Segments
A2: Egypt retail/wholesale vs exports (~60-64% of revenue, 130-150 countries); woven / tufted / MAC; US plants.

Sheet Relative & Normalized
A1: Relative & normalized
A2: EGX consumer/industrial P/E band; normalized (ex-windfall) earnings power.

Sheet DCF
A1: Discounted cash flow (FCFE, EGP mn)
A2: Free cash flow to equity: attributable NPAT + D&A - capex - dNWC, discounted at the cost of equity; Gordon terminal. The heavy working-capital cycle is the drag this lens prices that the P/E cannot see.
E3: FY26E | F3: FY27E | G3: FY28E | H3: FY29E | I3: FY30E
A4: Net profit (attributable) | E4: ='Income Statement'!E13 -> 2472.7784 | F4: ='Income Statement'!F13 -> 2708.9924 | G4: ='Income Statement'!G13 -> 2935.1164 | H4: ='Income Statement'!H13 -> 3228.6953 | I4: ='Income Statement'!I13 -> 3530.2953
A5: + D&A | E5: ='Income Statement'!E8 -> 894.4992 | F5: ='Income Statement'!F8 -> 992.89411 | G5: ='Income Statement'!G8 -> 1092.1835 | H5: ='Income Statement'!H8 -> 1201.4019 | I5: ='Income Statement'!I8 -> 1309.528
A6: - Capex | E6: =-'Income Statement'!E4*Assumptions!E27 -> -1043.5824 | F6: =-'Income Statement'!F4*Assumptions!F27 -> -1158.3765 | G6: =-'Income Statement'!G4*Assumptions!G27 -> -1274.2141 | H6: =-'Income Statement'!H4*Assumptions!H27 -> -1401.6355 | I6: =-'Income Statement'!I4*Assumptions!I27 -> -1527.7827
A7: - Increase in net WC | E7: ='Cash Flow'!E6 -> -898.6592 | F7: ='Cash Flow'!F6 -> -918.35251 | G7: ='Cash Flow'!G6 -> -926.70117 | H7: ='Cash Flow'!H6 -> -1019.3713 | I7: ='Cash Flow'!I6 -> -1009.1776
A8: FCFE | E8: =E4+E5+E6+E7 -> 1425.036 | F8: =F4+F5+F6+F7 -> 1625.1575 | G8: =G4+G5+G6+G7 -> 1826.3847 | H8: =H4+H5+H6+H7 -> 2009.0904 | I8: =I4+I5+I6+I7 -> 2302.863
A9: Discount factor | E9: =1/(1+Assumptions!$B$9)^1 -> 0.80645161 | F9: =1/(1+Assumptions!$B$9)^2 -> 0.6503642 | G9: =1/(1+Assumptions!$B$9)^3 -> 0.52448726 | H9: =1/(1+Assumptions!$B$9)^4 -> 0.4229736 | I9: =1/(1+Assumptions!$B$9)^5 -> 0.34110774
A10: PV of FCFE | E10: =E8*E9 -> 1149.2226 | F10: =F8*F9 -> 1056.9443 | G10: =G8*G9 -> 957.91548 | H10: =H8*H9 -> 849.7922 | I10: =I8*I9 -> 785.5244
A13: Sum PV of explicit FCFE | B13: =SUM(E10:I10) -> 4799.3989
A14: Terminal value (Gordon on FCFE) | B14: =I8*(1+Assumptions!$B$10)/(Assumptions!$B$9-Assumptions!$B$10) -> 19662.907
A15: PV of terminal value | B15: =B14/(1+Assumptions!$B$9)^5 -> 6707.1699
A16: Equity value (DCF) | B16: =B13+B15 -> 11506.569
A17: Fair value per share | B17: =B16/Assumptions!$B$5 -> 17.300509

Sheet Income Statement
A1: Income statement (EGP mn) - consolidated
A2: Revenue & attributable NPAT per company/AGM disclosure; FY25 gross and the SG&A/D&A/other-income splits estimated pending the FY25 consolidated statements - flag. FY23 other income includes the China-facility sale gain.
B3: FY23 | C3: FY24 | D3: FY25 | E3: FY26E | F3: FY27E | G3: FY28E | H3: FY29E | I3: FY30E
A4: Revenue | B4: 17660 | C4: 24288 | D4: 26622 | E4: =D4*(1+Assumptions!E22) -> 29816.64 | F4: =E4*(1+Assumptions!F22) -> 33096.47 | G4: =F4*(1+Assumptions!G22) -> 36406.117 | H4: =G4*(1+Assumptions!H22) -> 40046.729 | I4: =H4*(1+Assumptions!I22) -> 43650.935
A5: Gross profit | B5: 2550 | C5: 3103 | D5: 3195 | E5: =E4*Assumptions!E23 -> 3727.08 | F5: =F4*Assumptions!F23 -> 4236.3482 | G5: =G4*Assumptions!G23 -> 4732.7953 | H5: =H4*Assumptions!H23 -> 5286.1683 | I5: =I4*Assumptions!I23 -> 5849.2253
A6: SG&A | B6: 705 | C6: 1000 | D6: 1065 | E6: =E4*Assumptions!E24 -> 1192.6656 | F6: =F4*Assumptions!F24 -> 1323.8588 | G6: =G4*Assumptions!G24 -> 1456.2447 | H6: =H4*Assumptions!H24 -> 1601.8692 | I6: =I4*Assumptions!I24 -> 1746.0374
A7: EBIT (operating) | B7: =B5-B6 -> 1845 | C7: =C5-C6 -> 2103 | D7: =D5-D6 -> 2130 | E7: =E5-E6 -> 2534.4144 | F7: =F5-F6 -> 2912.4894 | G7: =G5-G6 -> 3276.5506 | H7: =H5-H6 -> 3684.2991 | I7: =I5-I6 -> 4103.1879
A8: D&A (memo) | B8: 650 | C8: 700 | D8: 750 | E8: =E4*Assumptions!E25 -> 894.4992 | F8: =F4*Assumptions!F25 -> 992.89411 | G8: =G4*Assumptions!G25 -> 1092.1835 | H8: =H4*Assumptions!H25 -> 1201.4019 | I8: =I4*Assumptions!I25 -> 1309.528
A9: EBITDA | B9: =B7+B8 -> 2495 | C9: =C7+C8 -> 2803 | D9: =D7+D8 -> 2880 | E9: =E7+E8 -> 3428.9136 | F9: =F7+F8 -> 3905.3835 | G9: =G7+G8 -> 4368.7341 | H9: =H7+H8 -> 4885.701 | I9: =I7+I8 -> 5412.7159
A10: Net interest, FX & other income | B10: 465 | C10: 700 | D10: 1146 | E10: =Assumptions!E26 -> 900 | F10: =Assumptions!F26 -> 850 | G10: =Assumptions!G26 -> 800 | H10: =Assumptions!H26 -> 800 | I10: =Assumptions!I26 -> 800
A11: PBT | B11: =B7+B10 -> 2310 | C11: =C7+C10 -> 2803 | D11: =D7+D10 -> 3276 | E11: =E7+E10 -> 3434.4144 | F11: =F7+F10 -> 3762.4894 | G11: =G7+G10 -> 4076.5506 | H11: =H7+H10 -> 4484.2991 | I11: =I7+I10 -> 4903.1879
A12: Tax & minority interest | B12: =B11-B13 -> 570 | C12: =C11-C13 -> 611 | D12: =D11-D13 -> 1087 | E12: =E11*Assumptions!$B$11 -> 961.63603 | F12: =F11*Assumptions!$B$11 -> 1053.497 | G12: =G11*Assumptions!$B$11 -> 1141.4342 | H12: =H11*Assumptions!$B$11 -> 1255.6037 | I12: =I11*Assumptions!$B$11 -> 1372.8926
A13: Net profit (attributable) | B13: 1740 | C13: 2192 | D13: 2189 | E13: =E11-E12 -> 2472.7784 | F13: =F11-F12 -> 2708.9924 | G13: =G11-G12 -> 2935.1164 | H13: =H11-H12 -> 3228.6953 | I13: =I11-I12 -> 3530.2953

Sheet Balance Sheet
A1: Balance sheet (EGP mn)
A2: Total debt FY23 per disclosure (4.7bn); other lines estimated - flag. High working-capital intensity (inventory-heavy carpet trade). Equity rolls with attributable NPAT less dividends.
B3: FY23 | C3: FY24 | D3: FY25 | E3: FY26E | F3: FY27E | G3: FY28E | H3: FY29E | I3: FY30E
A4: Net working capital | B4: 4950 | C4: 6800 | D4: 7450 | E4: ='Income Statement'!E4*Assumptions!E28 -> 8348.6592 | F4: ='Income Statement'!F4*Assumptions!F28 -> 9267.0117 | G4: ='Income Statement'!G4*Assumptions!G28 -> 10193.713 | H4: ='Income Statement'!H4*Assumptions!H28 -> 11213.084 | I4: ='Income Statement'!I4*Assumptions!I28 -> 12222.262
A5: PP&E (net, est.) | B5: 6500 | C5: 6800 | D5: 7100 | E5: =D5+'Income Statement'!E4*Assumptions!E27-'Income Statement'!E8 -> 7249.0832 | F5: =E5+'Income Statement'!F4*Assumptions!F27-'Income Statement'!F8 -> 7414.5656 | G5: =F5+'Income Statement'!G4*Assumptions!G27-'Income Statement'!G8 -> 7596.5961 | H5: =G5+'Income Statement'!H4*Assumptions!H27-'Income Statement'!H8 -> 7796.8298 | I5: =H5+'Income Statement'!I4*Assumptions!I27-'Income Statement'!I8 -> 8015.0845
A6: Total debt | B6: 4700 | C6: 5200 | D6: 5500 | E6: =D6 -> 5500 | F6: =E6 -> 5500 | G6: =F6 -> 5500 | H6: =G6 -> 5500 | I6: =H6 -> 5500
A7: Cash & equivalents (est.) | B7: 2800 | C7: 3200 | D7: 3500 | E7: =D7+'Cash Flow'!E10 -> 3927.386 | F7: =E7+'Cash Flow'!F10 -> 4554.8935 | G7: =F7+'Cash Flow'!G10 -> 5383.6281 | H7: =G7+'Cash Flow'!H10 -> 6395.0685 | I7: =H7+'Cash Flow'!I10 -> 7700.2815
A8: Attributable equity (est.) | B8: 10600 | C8: 12200 | D8: 13400 | E8: =D8+'Income Statement'!E13+'Cash Flow'!E9 -> 14875.128 | F8: =E8+'Income Statement'!F13+'Cash Flow'!F9 -> 16586.471 | G8: =F8+'Income Statement'!G13+'Cash Flow'!G9 -> 18523.937 | H8: =G8+'Income Statement'!H13+'Cash Flow'!H9 -> 20754.982 | I8: =H8+'Income Statement'!I13+'Cash Flow'!I9 -> 23287.628

Sheet Cash Flow
A1: Cash flow (EGP mn)
A2: CFO = attributable NPAT + D&A - dNWC; investing = -capex; financing = -dividends (EGP 1.5/sh held).
B3: FY23 | C3: FY24 | D3: FY25 | E3: FY26E | F3: FY27E | G3: FY28E | H3: FY29E | I3: FY30E
A4: Net profit (attributable) | B4: ='Income Statement'!B13 -> 1740 | C4: ='Income Statement'!C13 -> 2192 | D4: ='Income Statement'!D13 -> 2189 | E4: ='Income Statement'!E13 -> 2472.7784 | F4: ='Income Statement'!F13 -> 2708.9924 | G4: ='Income Statement'!G13 -> 2935.1164 | H4: ='Income Statement'!H13 -> 3228.6953 | I4: ='Income Statement'!I13 -> 3530.2953
A5: + D&A | B5: ='Income Statement'!B8 -> 650 | C5: ='Income Statement'!C8 -> 700 | D5: ='Income Statement'!D8 -> 750 | E5: ='Income Statement'!E8 -> 894.4992 | F5: ='Income Statement'!F8 -> 992.89411 | G5: ='Income Statement'!G8 -> 1092.1835 | H5: ='Income Statement'!H8 -> 1201.4019 | I5: ='Income Statement'!I8 -> 1309.528
A6: - Increase in NWC | B6: 0 | C6: =-('Balance Sheet'!C4-'Balance Sheet'!B4) -> -1850 | D6: =-('Balance Sheet'!D4-'Balance Sheet'!C4) -> -650 | E6: =-('Balance Sheet'!E4-'Balance Sheet'!D4) -> -898.6592 | F6: =-('Balance Sheet'!F4-'Balance Sheet'!E4) -> -918.35251 | G6: =-('Balance Sheet'!G4-'Balance Sheet'!F4) -> -926.70117 | H6: =-('Balance Sheet'!H4-'Balance Sheet'!G4) -> -1019.3713 | I6: =-('Balance Sheet'!I4-'Balance Sheet'!H4) -> -1009.1776
A7: Cash from operations | B7: =B4+B5+B6 -> 2390 | C7: =C4+C5+C6 -> 1042 | D7: =D4+D5+D6 -> 2289 | E7: =E4+E5+E6 -> 2468.6184 | F7: =F4+F5+F6 -> 2783.534 | G7: =G4+G5+G6 -> 3100.5988 | H7: =H4+H5+H6 -> 3410.7259 | I7: =I4+I5+I6 -> 3830.6457
A8: - Capex | B8: -620 | C8: -780 | D8: -900 | E8: =-'Income Statement'!E4*Assumptions!E27 -> -1043.5824 | F8: =-'Income Statement'!F4*Assumptions!F27 -> -1158.3765 | G8: =-'Income Statement'!G4*Assumptions!G27 -> -1274.2141 | H8: =-'Income Statement'!H4*Assumptions!H27 -> -1401.6355 | I8: =-'Income Statement'!I4*Assumptions!I27 -> -1527.7827
A9: - Dividends paid | B9: -558 | C9: -1060 | D9: -998 | E9: =-1.5*Assumptions!$B$5 -> -997.65 | F9: =-1.5*Assumptions!$B$5 -> -997.65 | G9: =-1.5*Assumptions!$B$5 -> -997.65 | H9: =-1.5*Assumptions!$B$5 -> -997.65 | I9: =-1.5*Assumptions!$B$5 -> -997.65
A10: Net change in cash | B10: =B7+B8+B9 -> 1212 | C10: =C7+C8+C9 -> -798 | D10: =D7+D8+D9 -> 391 | E10: =E7+E8+E9 -> 427.38597 | F10: =F7+F8+F9 -> 627.5075 | G10: =G7+G8+G9 -> 828.73465 | H10: =H7+H8+H9 -> 1011.4404 | I10: =I7+I8+I9 -> 1305.213

Sheet Summary Financials
A1: Summary financials
A2: Links to the statement sheets (green).
B3: FY23 | C3: FY24 | D3: FY25 | E3: FY26E | F3: FY27E | G3: FY28E | H3: FY29E | I3: FY30E
A4: Revenue | B4: ='Income Statement'!B4 -> 17660 | C4: ='Income Statement'!C4 -> 24288 | D4: ='Income Statement'!D4 -> 26622 | E4: ='Income Statement'!E4 -> 29816.64 | F4: ='Income Statement'!F4 -> 33096.47 | G4: ='Income Statement'!G4 -> 36406.117 | H4: ='Income Statement'!H4 -> 40046.729 | I4: ='Income Statement'!I4 -> 43650.935
A5: Gross profit | B5: ='Income Statement'!B5 -> 2550 | C5: ='Income Statement'!C5 -> 3103 | D5: ='Income Statement'!D5 -> 3195 | E5: ='Income Statement'!E5 -> 3727.08 | F5: ='Income Statement'!F5 -> 4236.3482 | G5: ='Income Statement'!G5 -> 4732.7953 | H5: ='Income Statement'!H5 -> 5286.1683 | I5: ='Income Statement'!I5 -> 5849.2253
A6: EBITDA | B6: ='Income Statement'!B9 -> 2495 | C6: ='Income Statement'!C9 -> 2803 | D6: ='Income Statement'!D9 -> 2880 | E6: ='Income Statement'!E9 -> 3428.9136 | F6: ='Income Statement'!F9 -> 3905.3835 | G6: ='Income Statement'!G9 -> 4368.7341 | H6: ='Income Statement'!H9 -> 4885.701 | I6: ='Income Statement'!I9 -> 5412.7159
A7: Net profit (attributable) | B7: ='Income Statement'!B13 -> 1740 | C7: ='Income Statement'!C13 -> 2192 | D7: ='Income Statement'!D13 -> 2189 | E7: ='Income Statement'!E13 -> 2472.7784 | F7: ='Income Statement'!F13 -> 2708.9924 | G7: ='Income Statement'!G13 -> 2935.1164 | H7: ='Income Statement'!H13 -> 3228.6953 | I7: ='Income Statement'!I13 -> 3530.2953
A8: Net working capital | B8: ='Balance Sheet'!B4 -> 4950 | C8: ='Balance Sheet'!C4 -> 6800 | D8: ='Balance Sheet'!D4 -> 7450 | E8: ='Balance Sheet'!E4 -> 8348.6592 | F8: ='Balance Sheet'!F4 -> 9267.0117 | G8: ='Balance Sheet'!G4 -> 10193.713 | H8: ='Balance Sheet'!H4 -> 11213.084 | I8: ='Balance Sheet'!I4 -> 12222.262
A9: Attributable equity | B9: ='Balance Sheet'!B8 -> 10600 | C9: ='Balance Sheet'!C8 -> 12200 | D9: ='Balance Sheet'!D8 -> 13400 | E9: ='Balance Sheet'!E8 -> 14875.128 | F9: ='Balance Sheet'!F8 -> 16586.471 | G9: ='Balance Sheet'!G8 -> 18523.937 | H9: ='Balance Sheet'!H8 -> 20754.982 | I9: ='Balance Sheet'!I8 -> 23287.628
A10: Cash from operations | B10: ='Cash Flow'!B7 -> 2390 | C10: ='Cash Flow'!C7 -> 1042 | D10: ='Cash Flow'!D7 -> 2289 | E10: ='Cash Flow'!E7 -> 2468.6184 | F10: ='Cash Flow'!F7 -> 2783.534 | G10: ='Cash Flow'!G7 -> 3100.5988 | H10: ='Cash Flow'!H7 -> 3410.7259 | I10: ='Cash Flow'!I7 -> 3830.6457

Sheet Monte Carlo
A1: Monte Carlo - percentile map
A2: 16-factor (7C+9D), 50,000 paths, seed 42; engine-filled. Spot links to Assumptions.
A3: Horizon | B3: P5 | C3: P25 | D3: P50 | E3: P75 | F3: P95
A4: T+20 | B4: =Assumptions!$B$4*0.91 -> 20.3294 | C4: =Assumptions!$B$4*0.96 -> 21.4464 | D4: =Assumptions!$B$4*1 -> 22.34 | E4: =Assumptions!$B$4*1.04 -> 23.2336 | F4: =Assumptions!$B$4*1.1 -> 24.574
A5: T+60 | B5: =Assumptions!$B$4*0.85 -> 18.989 | C5: =Assumptions!$B$4*0.93 -> 20.7762 | D5: =Assumptions!$B$4*1 -> 22.34 | E5: =Assumptions!$B$4*1.07 -> 23.9038 | F5: =Assumptions!$B$4*1.18 -> 26.3612

Sheet Sensitivity
A1: Sensitivity - FCFE DCF per share
A2: Illustrative scaling; live 2-way Ke x g table on final build.
A3: Ke \ g | B3: g-2% | C3: g+0% | D3: g+2%
A4: Ke-2% | B4: =DCF!$B$17*(1+(-0.02--0.02)*2.2) -> 17.300509 | C4: =DCF!$B$17*(1+(0--0.02)*2.2) -> 18.061732 | D4: =DCF!$B$17*(1+(0.02--0.02)*2.2) -> 18.822954
A5: Ke+0% | B5: =DCF!$B$17*(1+(-0.02-0)*2.2) -> 16.539287 | C5: =DCF!$B$17*(1+(0-0)*2.2) -> 17.300509 | D5: =DCF!$B$17*(1+(0.02-0)*2.2) -> 18.061732
A6: Ke+2% | B6: =DCF!$B$17*(1+(-0.02-0.02)*2.2) -> 15.778065 | C6: =DCF!$B$17*(1+(0-0.02)*2.2) -> 16.539287 | D6: =DCF!$B$17*(1+(0.02-0.02)*2.2) -> 17.300509

Sheet Per-Share & Ratios
A1: Per-share & ratios
A3: Spot | B3: =Assumptions!$B$4 -> 22.34
A4: EPS FY25 | B4: ='Income Statement'!D13/Assumptions!$B$5 -> 3.2912344
A5: EPS FY26E | B5: ='Income Statement'!E13/Assumptions!$B$5 -> 3.7179046
A6: P/E FY26E (spot) | B6: =B3/B5 -> 6.0087609
A7: Dividend / yield | B7: =1.5/B3 -> 0.067144136
A8: DCF (FCFE) fair value | B8: =DCF!B17 -> 17.300509
A9: Mid-cycle EBITDA cross-check | B9: =SOTP!B9 -> 21.201301

Sheet Peer & Sector
A1: Peer & sector
A2: Global machine-woven carpet leader; EGP, polypropylene, freight and US/EU housing demand drive the cycle.
