Workbook

Sheet READ FIRST
A1: READ FIRST — what this model is, and is not
A3: This workbook is the companion model to the Testahil QNB Group valuation study — educational analysis, NOT investment advice, NOT a recommendation, and NOT directed at any reader's circumstances. It contains no price target and no rating. The preparer is not licensed by any securities regulator, manages no money and accepts no clients. All outputs are ranges and distributions; no single number should be relied on. Blue cells are inputs — edit them and the model reprices. Reported financials are QNB Group's own disclosure (FY23/24/25); forward inputs (growth, payout, RWA, marks, Ke, factor probabilities) are the preparer's flagged judgments. The preparer may hold, and may in the future take or dispose of, a position in the security discussed. Consult a licensed professional before any decision. Currency: QAR (QAR mn or per-share). Spot & market data as of 05 Jul 2026 and change continuously.

Sheet Summary
A1: Valuation summary — every read at a glance
A3: Lens | B3: Bear | C3: Base | D3: Bull | E3: vs spot
A4: DDM (primary) | B4: 13.21 | C4: =DDM!$B$17 -> 18.677965 | D4: 29.25 | E4: =C4/Assumptions!$B$4-1 -> 0.064878291
A5: FCFE / capital DCF | B5: 14.91 | C5: =DCF!$B$21 -> 20.185486 | D5: 28.79 | E5: =C5/Assumptions!$B$4-1 -> 0.1508259
A6: Relative (P/B–RoTE) | B6: 14.42 | C6: ='Relative & Normalized'!$B$12 -> 18.174388 | D6: 24.53 | E6: =C6/Assumptions!$B$4-1 -> 0.036168069
A7: Normalized earnings | B7: 13.97 | C7: ='Relative & Normalized'!$B$18 -> 17.582287 | D7: 29.8 | E7: =C7/Assumptions!$B$4-1 -> 0.0024109179
A8: Weighted central | B8: 13.97 | C8: =DDM!$B$17*Assumptions!$B$30+DCF!$B$21*Assumptions!$B$31+'Relative & Normalized'!$B$12*Assumptions!$B$32+'Relative & Normalized'!$B$18*Assumptions!$B$33 -> 18.760173 | D8: 28.54 | E8: =C8/Assumptions!$B$4-1 -> 0.069565186
A10: Spot (QAR) | B10: =Assumptions!$B$4 -> 17.54
A11: MC median T+60 | B11: 17.24
A13: Fundamental central ≈ QAR 18.8 (~+7% vs spot); the Monte Carlo median sits at spot because §3 maps price, not value. Base column links live to the lens sheets.

Sheet Fundamental Valuation
A1: Fundamental valuation — lens roll-up
A3: Lens | B3: Weight | C3: Base value | D3: Contribution
A4: DDM | B4: =Assumptions!$B$30 -> 0.4 | C4: =DDM!$B$17 -> 18.677965 | D4: =B4*C4 -> 7.4711861
A5: FCFE/DCF | B5: =Assumptions!$B$31 -> 0.25 | C5: =DCF!$B$21 -> 20.185486 | D5: =B5*C5 -> 5.0463716
A6: Relative | B6: =Assumptions!$B$32 -> 0.15 | C6: ='Relative & Normalized'!$B$12 -> 18.174388 | D6: =B6*C6 -> 2.7261582
A7: Normalized | B7: =Assumptions!$B$33 -> 0.2 | C7: ='Relative & Normalized'!$B$18 -> 17.582287 | D7: =B7*C7 -> 3.5164575
A8: Weighted central fair value | D8: =SUM(D4:D7) -> 18.760173
A9: Upside vs spot | D9: =D8/Assumptions!$B$4-1 -> 0.069565186

Sheet Assumptions
A1: QNB Group (QSE: QNBK) — Assumptions · the single blue-cell input layer
A3: Market anchor (05 Jul 2026)
A4: Spot price (QAR/share) | B4: 17.54
A5: Shares outstanding (mn) | B5: 9113
A6: USD/QAR (peg) | B6: 3.64
A7: Cost of equity (Ke = rf + β·ERP)
A8: Risk-free rate rf | B8: 0.045
A9: Equity risk premium ERP | B9: 0.055
A10: Beta (EM-adjusted, 0.8–1.3 band) | B10: 1.1
A11: Cost of equity Ke | B11: =Assumptions!$B$8+Assumptions!$B$10*Assumptions!$B$9 -> 0.1055
A12: Terminal growth g | B12: 0.0475
A13: Through-cycle RoTE | B13: 0.145
A14: Terminal payout ratio | B14: 0.6
A15: FY25 actuals (base)
A16: EPS FY25 (QAR) | B16: 1.74
A17: DPS FY25 (QAR) | B17: 0.725
A18: Ordinary equity FY25 (QAR mn) | B18: 108000
A19: Tangible BVPS FY25 (QAR) | B19: 11.19
A20: Ordinary BVPS FY25 (QAR) | B20: 11.85
A21: RWA FY25 (QAR mn) | B21: 700000
A22: CET1 target on RWA | B22: 0.125
A23: Forecast drivers FY26E–FY30E | C23: FY26E | D23: FY27E | E23: FY28E | F23: FY29E | G23: FY30E
A24: EPS growth (FY26–30) | C24: 0.04 | D24: 0.055 | E24: 0.065 | F24: 0.07 | G24: 0.07
A25: Payout ratio (FY26–30) | C25: 0.43 | D25: 0.44 | E25: 0.45 | F25: 0.46 | G25: 0.47
A26: RWA growth (FY26–30) | C26: 0.075 | D26: 0.07 | E26: 0.065 | F26: 0.06 | G26: 0.055
A27: Relative & weights
A28: Peer / market P/B (dated, indicative) | B28: 1.48
A29: Peer P/E (dated, indicative) | B29: 10.5
A30: Weight — DDM | B30: 0.4
A31: Weight — FCFE/DCF | B31: 0.25
A32: Weight — Relative | B32: 0.15
A33: Weight — Normalized | B33: 0.2
A34: Blue = input (edit these). Black = formula. Green = cross-sheet link. Every other sheet references this layer; change one cell here and the model reprices. Source: QNB Group FY23/24/25 disclosures (qnb.com); forward inputs are the preparer's flagged judgments.

Sheet DDM
A1: Primary lens — Two-stage Dividend Discount Model
A3: Cost of equity Ke | B3: =Assumptions!$B$11 -> 0.1055
A4: Terminal growth g | B4: =Assumptions!$B$12 -> 0.0475
A5: Terminal payout | B5: =Assumptions!$B$14 -> 0.6
A7: Line | B7: FY25 | C7: FY26E | D7: FY27E | E7: FY28E | F7: FY29E | G7: FY30E
A8: EPS (QAR) | B8: =Assumptions!$B$16 -> 1.74 | C8: =B8*(1+Assumptions!$C$24) -> 1.8096 | D8: =C8*(1+Assumptions!$D$24) -> 1.909128 | E8: =D8*(1+Assumptions!$E$24) -> 2.0332213 | F8: =E8*(1+Assumptions!$F$24) -> 2.1755468 | G8: =F8*(1+Assumptions!$G$24) -> 2.3278351
A9: Payout ratio | C9: =Assumptions!$C$25 -> 0.43 | D9: =Assumptions!$D$25 -> 0.44 | E9: =Assumptions!$E$25 -> 0.45 | F9: =Assumptions!$F$25 -> 0.46 | G9: =Assumptions!$G$25 -> 0.47
A10: DPS (QAR) | C10: =C8*C9 -> 0.778128 | D10: =D8*D9 -> 0.84001632 | E10: =E8*E9 -> 0.91494959 | F10: =F8*F9 -> 1.0007515 | G10: =G8*G9 -> 1.0940825
A11: Discount factor 1/(1+Ke)^t | C11: =1/(1+$B$3)^1 -> 0.90456807 | D11: =1/(1+$B$3)^2 -> 0.81824339 | E11: =1/(1+$B$3)^3 -> 0.74015684 | F11: =1/(1+$B$3)^4 -> 0.66952225 | G11: =1/(1+$B$3)^5 -> 0.60562845
A12: PV of dividend | C12: =C10*C11 -> 0.70386974 | D12: =D10*D11 -> 0.6873378 | E12: =E10*E11 -> 0.6772062 | F12: =F10*F11 -> 0.67002542 | G12: =G10*G11 -> 0.66260748
A14: Σ PV of explicit dividends (FY26–30) | B14: =SUM(C12:G12) -> 3.4010466
A15: Terminal value = EPS30·(1+g)·payout/(Ke−g) | B15: =G8*(1+$B$4)*$B$5/($B$3-$B$4) -> 25.224903
A16: PV of terminal value | B16: =B15*G11 -> 15.276919
A17: DDM fair value (QAR/share) | B17: =B14+B16 -> 18.677965
A18: TV as % of value (disclose — high-terminal) | B18: =B16/B17 -> 0.81791129
A19: Implied upside vs spot | B19: =B17/Assumptions!$B$4-1 -> 0.064878291
A21: Two clocks kept separate: this is the ~12-month risk-adjusted anchor on the ACTUAL dividend policy. The gap to full distributable capacity (the excess-capital return case) is on the DCF sheet and in §1.7. Ke published as rf+ERP; sensitized on the Sensitivity sheet.

Sheet Segments
A1: Segments — earnings contribution by geography (indicative)
A3: Segment | B3: Net profit share | C3: Assets share | D3: RoTE | E3: Note
A4: Qatar (domestic) | B4: 0.62 | C4: 0.58 | D4: 0.18 | E4: Core; sovereign & corporate
A5: Türkiye (QNB Finansbank) | B5: 0.14 | C5: 0.16 | D5: 0.14 | E5: Hyperinflation accounting; lira drag
A6: Egypt (QNB Alahli) | B6: 0.1 | C6: 0.07 | D6: 0.28 | E6: High nominal RoE, EGP translation
A7: Other intl network | B7: 0.14 | C7: 0.19 | D7: 0.12 | E7: GCC, Asia, Europe branches
A8: Total | B8: =SUM(B4:B7) -> 1 | C8: =SUM(C4:C7) -> 1
A10: Shares are the preparer's estimates from segment disclosure; Egypt/Türkiye reported under hyperinflation (IAS 29) so nominal RoE overstates real returns. Group RoTE is the blend, tax-adjusted for Pillar Two.

Sheet Relative & Normalized
A1: Relative multiples & normalized earnings power
A3: P/B–RoTE (Gordon justified) + peer
A4: Through-cycle RoTE | B4: =Assumptions!$B$13 -> 0.145
A5: Ke | B5: =Assumptions!$B$11 -> 0.1055
A6: g | B6: =Assumptions!$B$12 -> 0.0475
A7: Justified P/B = (RoTE−g)/(Ke−g) | B7: =(B4-B6)/(B5-B6) -> 1.6810345
A8: Tangible BVPS (QAR) | B8: =Assumptions!$B$19 -> 11.19
A9: Gordon fair value = justified P/B · TBVPS | B9: =B7*B8 -> 18.810776
A10: Peer / market P/B | B10: =Assumptions!$B$28 -> 1.48
A11: Peer-based value = peer P/B · ordinary BVPS | B11: =B10*Assumptions!$B$20 -> 17.538
A12: Relative fair value (50/50 blend) | B12: =0.5*B9+0.5*B11 -> 18.174388
A14: Normalized earnings power (through-cycle)
A15: Normalized EPS = RoTE · TBVPS | B15: =B4*B8 -> 1.62255
A16: RoE-consistent payout = 1 − g/RoTE | B16: =1-B6/B4 -> 0.67241379
A17: Justified P/E (on terminal payout) | B17: =Assumptions!$B$14*(1+B6)/(B5-B6) -> 10.836207
A18: Normalized fair value = EPS · justified P/E | B18: =B15*B17 -> 17.582287
A19: Peer P/E cross-read · EPS FY25 | B19: =Assumptions!$B$29*Assumptions!$B$16 -> 18.27
A21: For banks the P/B–RoTE lens dominates a raw P/E because low payout understates value (retained earnings compound at RoTE>Ke). Justified P/E shown on the conservative terminal payout for coherence with the DDM.

Sheet DCF
A1: Cash-flow cross-check — FCFE / distributable-capital DCF (bank equity DCF)
A3: Ke | B3: =Assumptions!$B$11 -> 0.1055
A4: g | B4: =Assumptions!$B$12 -> 0.0475
A5: CET1 target on RWA | B5: =Assumptions!$B$22 -> 0.125
A7: Line (QAR mn) | B7: FY25 | C7: FY26E | D7: FY27E | E7: FY28E | F7: FY29E | G7: FY30E
A8: Net income (EPS·shares) | B8: =Assumptions!$B$16*Assumptions!$B$5 -> 15856.62 | C8: =DDM!C8*Assumptions!$B$5 -> 16490.885 | D8: =DDM!D8*Assumptions!$B$5 -> 17397.883 | E8: =DDM!E8*Assumptions!$B$5 -> 18528.746 | F8: =DDM!F8*Assumptions!$B$5 -> 19825.758 | G8: =DDM!G8*Assumptions!$B$5 -> 21213.561
A9: Risk-weighted assets (RWA) | B9: =Assumptions!$B$21 -> 700000 | C9: =B9*(1+Assumptions!$C$26) -> 752500 | D9: =C9*(1+Assumptions!$D$26) -> 805175 | E9: =D9*(1+Assumptions!$E$26) -> 857511.38 | F9: =E9*(1+Assumptions!$F$26) -> 908962.06 | G9: =F9*(1+Assumptions!$G$26) -> 958954.97
A10: Required CET1 capital = RWA·target | B10: =B9*$B$5 -> 87500 | C10: =C9*$B$5 -> 94062.5 | D10: =D9*$B$5 -> 100646.88 | E10: =E9*$B$5 -> 107188.92 | F10: =F9*$B$5 -> 113620.26 | G10: =G9*$B$5 -> 119869.37
A11: Δ required capital | C11: =C10-B10 -> 6562.5 | D11: =D10-C10 -> 6584.375 | E11: =E10-D10 -> 6542.0469 | F11: =F10-E10 -> 6431.3353 | G11: =G10-F10 -> 6249.1141
A12: FCFE = NI − Δ required capital | C12: =C8-C11 -> 9928.3848 | D12: =D8-D11 -> 10813.508 | E12: =E8-E11 -> 11986.699 | F12: =F8-F11 -> 13394.423 | G12: =G8-G11 -> 14964.447
A13: FCFE per share (QAR) | C13: =C12/Assumptions!$B$5 -> 1.0894749 | D13: =D12/Assumptions!$B$5 -> 1.1866025 | E13: =E12/Assumptions!$B$5 -> 1.3153406 | F13: =F12/Assumptions!$B$5 -> 1.4698149 | G13: =G12/Assumptions!$B$5 -> 1.6420989
A14: Discount factor | C14: =1/(1+$B$3)^1 -> 0.90456807 | D14: =1/(1+$B$3)^2 -> 0.81824339 | E14: =1/(1+$B$3)^3 -> 0.74015684 | F14: =1/(1+$B$3)^4 -> 0.66952225 | G14: =1/(1+$B$3)^5 -> 0.60562845
A15: PV of FCFE per share | C15: =C13*C14 -> 0.98550421 | D15: =D13*D14 -> 0.97092964 | E15: =E13*E14 -> 0.97355836 | F15: =F13*F14 -> 0.98407375 | G15: =G13*G14 -> 0.99450179
A17: Σ PV explicit FCFE/sh | B17: =SUM(C15:G15) -> 4.9085677
A18: Terminal FCFE/sh = EPS30·(1+g)·term-payout | B18: =DDM!G8*(1+$B$4)*Assumptions!$B$14 -> 1.4630444
A19: Terminal value/sh = /(Ke−g) | B19: =B18/($B$3-$B$4) -> 25.224903
A20: PV of terminal value/sh | B20: =B19*G14 -> 15.276919
A21: FCFE-DCF fair value (QAR/share) | B21: =B17+B20 -> 20.185486
A22: TV as % of value (disclose) | B22: =B20/B21 -> 0.75682688
A24: Bank equity-DCF: free cash flow to equity = earnings less the capital that must be retained to fund RWA growth at the CET1 target. Above the actual-policy DDM because it distributes full capacity. The excess-capital ceiling (RoE-consistent payout) is reported in §1.7 as the crux upper bound.

Sheet Income Statement
A1: Appendix A.1 — Income statement (consolidated, QAR mn) · 3y actual + 5y forecast
A3: QAR mn | B3: FY23 | C3: FY24 | D3: FY25 | E3: FY26E | F3: FY27E | G3: FY28E | H3: FY29E | I3: FY30E
A4: Operating income | B4: 38960 | C4: 41300 | D4: 44800 | E4: =D4*(1+Assumptions!$C$24+0.01) -> 47040 | F4: =E4*(1+Assumptions!$D$24+0.01) -> 50097.6 | G4: =F4*(1+Assumptions!$E$24+0.01) -> 53854.92 | H4: =G4*(1+Assumptions!$F$24+0.01) -> 58163.314 | I4: =H4*(1+Assumptions!$G$24+0.01) -> 62816.379
A5: Operating expenses (= −C/I·OpInc) | B5: -8804.96 | C5: -9209.9 | D5: -10438.4 | E5: =-E4*0.24 -> -11289.6 | F5: =-F4*0.24 -> -12023.424 | G5: =-G4*0.24 -> -12925.181 | H5: =-H4*0.24 -> -13959.195 | I5: =-I4*0.24 -> -15075.931
A6: Pre-provision operating profit | B6: =B4+B5 -> 30155.04 | C6: =C4+C5 -> 32090.1 | D6: =D4+D5 -> 34361.6 | E6: =E4+E5 -> 35750.4 | F6: =F4+F5 -> 38074.176 | G6: =G4+G5 -> 40929.739 | H6: =H4+H5 -> 44204.118 | I6: =I4+I5 -> 47740.448
A7: Net loan-loss / ECL charge | B7: -8600 | C7: -8100 | D7: -8500 | E7: =-E4*0.19 -> -8937.6 | F7: =-F4*0.19 -> -9518.544 | G7: =-G4*0.19 -> -10232.435 | H7: =-H4*0.19 -> -11051.03 | I7: =-I4*0.19 -> -11935.112
A8: Profit before tax | B8: =B6+B7 -> 21555.04 | C8: =C6+C7 -> 23990.1 | D8: =D6+D7 -> 25861.6 | E8: =E6+E7 -> 26812.8 | F8: =F6+F7 -> 28555.632 | G8: =G6+G7 -> 30697.304 | H8: =H6+H7 -> 33153.089 | I8: =I6+I7 -> 35805.336
A9: Tax (incl. Pillar Two from FY25) | B9: =-B8*0.03 -> -646.6512 | C9: =-C8*0.03 -> -719.703 | D9: =-D8*0.135 -> -3491.316 | E9: =-E8*0.15 -> -4021.92 | F9: =-F8*0.15 -> -4283.3448 | G9: =-G8*0.15 -> -4604.5957 | H9: =-H8*0.15 -> -4972.9633 | I9: =-I8*0.15 -> -5370.8004
A10: Net profit (incl. NCI & AT1) | B10: 15500 | C10: 16720 | D10: 17000 | E10: =DDM!C8*Assumptions!$B$5/0.91 -> 18121.851 | F10: =DDM!D8*Assumptions!$B$5/0.91 -> 19118.553 | G10: =DDM!E8*Assumptions!$B$5/0.91 -> 20361.259 | H10: =DDM!F8*Assumptions!$B$5/0.91 -> 21786.547 | I10: =DDM!G8*Assumptions!$B$5/0.91 -> 23311.606
A11: Attributable EPS (QAR) | B11: 1.55 | C11: 1.69 | D11: 1.74 | E11: =DDM!C8 -> 1.8096 | F11: =DDM!D8 -> 1.909128 | G11: =DDM!E8 -> 2.0332213 | H11: =DDM!F8 -> 2.1755468 | I11: =DDM!G8 -> 2.3278351
A13: Actuals from QNB Group FY23/24/25 results (qnb.com). FY25 net profit +1.7% vs +10% pre-tax reflects Pillar Two (15% global minimum tax). Forecast opex modelled at ~24% C/I and ECL at ~19% of operating income; every forecast EPS links to the DDM sheet.

Sheet Balance Sheet
A1: Appendix A.2 — Balance sheet (consolidated, QAR mn) · 3y actual + 5y forecast
A3: QAR mn | B3: FY23 | C3: FY24 | D3: FY25 | E3: FY26E | F3: FY27E | G3: FY28E | H3: FY29E | I3: FY30E
A4: Loans & advances | B4: 851000 | C4: 911000 | D4: 1018000 | E4: =D4*(1+Assumptions!$C$26+0.02) -> 1114710 | F4: =E4*(1+Assumptions!$D$26+0.02) -> 1215033.9 | G4: =F4*(1+Assumptions!$E$26+0.02) -> 1318311.8 | H4: =G4*(1+Assumptions!$F$26+0.02) -> 1423776.7 | I4: =H4*(1+Assumptions!$G$26+0.02) -> 1530560
A5: Investment & other assets | B5: 385000 | C5: 387000 | D5: 373000 | E5: =D5*(1+Assumptions!$C$26) -> 400975 | F5: =E5*(1+Assumptions!$D$26) -> 429043.25 | G5: =F5*(1+Assumptions!$E$26) -> 456931.06 | H5: =G5*(1+Assumptions!$F$26) -> 484346.92 | I5: =H5*(1+Assumptions!$G$26) -> 510986.01
A6: Total assets | B6: =B4+B5 -> 1236000 | C6: =C4+C5 -> 1298000 | D6: =D4+D5 -> 1391000 | E6: =E4+E5 -> 1515685 | F6: =F4+F5 -> 1644077.1 | G6: =G4+G5 -> 1775242.8 | H6: =H4+H5 -> 1908123.6 | I6: =I4+I5 -> 2041546
A7: Customer deposits | B7: 861000 | C7: 887000 | D7: 955000 | E7: =D7*(1+Assumptions!$C$26) -> 1026625 | F7: =E7*(1+Assumptions!$D$26) -> 1098488.8 | G7: =F7*(1+Assumptions!$E$26) -> 1169890.5 | H7: =G7*(1+Assumptions!$F$26) -> 1240083.9 | I7: =H7*(1+Assumptions!$G$26) -> 1308288.6
A8: Other liabilities & debt (plug) | B8: 264000 | C8: 297000 | D8: 311000 | E8: =E6-E7-E9 -> 353730.54 | F8: =F6-F7-F9 -> 399552.55 | G8: =G6-G7-G9 -> 448117.79 | H8: =H6-H7-H9 -> 499040.43 | I8: =I6-I7-I9 -> 551902.99
A9: Total equity | B9: 111000 | C9: 114000 | D9: 125000 | E9: =D9+'Income Statement'!E10*(1-DDM!C9) -> 135329.46 | F9: =E9+'Income Statement'!F10*(1-DDM!D9) -> 146035.85 | G9: =F9+'Income Statement'!G10*(1-DDM!E9) -> 157234.54 | H9: =G9+'Income Statement'!H10*(1-DDM!F9) -> 168999.27 | I9: =H9+'Income Statement'!I10*(1-DDM!G9) -> 181354.42
A10: Check: A = L + E | B10: =B6-B7-B8-B9 -> 0 | C10: =C6-C7-C8-C9 -> 0 | D10: =D6-D7-D8-D9 -> 0 | E10: =E6-E7-E8-E9 -> 0 | F10: =F6-F7-F8-F9 -> 0 | G10: =G6-G7-G8-G9 -> 0 | H10: =H6-H7-H8-H9 -> 0 | I10: =I6-I7-I8-I9 -> 0
A11: CET1 / CAR (%) | B11: 0.194 | C11: 0.192 | D11: 0.193 | E11: 0.194 | F11: 0.195 | G11: 0.196 | H11: 0.197 | I11: 0.198
A13: Total assets = loans + investments; equity rolls forward as prior equity + retained earnings (net profit × [1 − payout]). Deposits/assets grow with the RWA-growth driver on Assumptions. FY25: assets QAR 1,391bn, loans 1,018bn, deposits 955bn, equity 125bn.

Sheet Cash Flow
A1: Appendix A.3 — Capital generation & distribution (QAR mn) · 3y actual + 5y forecast
A3: QAR mn | B3: FY23 | C3: FY24 | D3: FY25 | E3: FY26E | F3: FY27E | G3: FY28E | H3: FY29E | I3: FY30E
A4: Net profit | B4: 15500 | C4: 16720 | D4: 17000 | E4: ='Income Statement'!E10 -> 18121.851 | F4: ='Income Statement'!F10 -> 19118.553 | G4: ='Income Statement'!G10 -> 20361.259 | H4: ='Income Statement'!H10 -> 21786.547 | I4: ='Income Statement'!I10 -> 23311.606
A5: Less: capital retained for RWA growth | B5: -8525 | C5: -9196 | D5: -9350 | E5: =-DCF!C11 -> -6562.5 | F5: =-DCF!D11 -> -6584.375 | G5: =-DCF!E11 -> -6542.0469 | H5: =-DCF!F11 -> -6431.3353 | I5: =-DCF!G11 -> -6249.1141
A6: Distributable capital (FCFE) | B6: =B4+B5 -> 6975 | C6: =C4+C5 -> 7524 | D6: =D4+D5 -> 7650 | E6: =E4+E5 -> 11559.351 | F6: =F4+F5 -> 12534.178 | G6: =G4+G5 -> 13819.212 | H6: =H4+H5 -> 15355.212 | I6: =I4+I5 -> 17062.492
A7: Cash dividends paid | B7: =-0.65*Assumptions!$B$5 -> -5923.45 | C7: =-0.7*Assumptions!$B$5 -> -6379.1 | D7: =-0.725*Assumptions!$B$5 -> -6606.925 | E7: =-DDM!C10*Assumptions!$B$5 -> -7091.0805 | F7: =-DDM!D10*Assumptions!$B$5 -> -7655.0687 | G7: =-DDM!E10*Assumptions!$B$5 -> -8337.9357 | H7: =-DDM!F10*Assumptions!$B$5 -> -9119.8487 | I7: =-DDM!G10*Assumptions!$B$5 -> -9970.3737
A8: Share buyback (actual FY25) | D8: -2100
A9: Retained / excess capital build | B9: =B6+B7+IF(B8="",0,B8) -> 1051.55 | C9: =C6+C7+IF(C8="",0,C8) -> 1144.9 | D9: =D6+D7+IF(D8="",0,D8) -> -1056.925 | E9: =E6+E7+IF(E8="",0,E8) -> 4468.271 | F9: =F6+F7+IF(F8="",0,F8) -> 4879.1095 | G9: =G6+G7+IF(G8="",0,G8) -> 5481.2767 | H9: =H6+H7+IF(H8="",0,H8) -> 6235.3633 | I9: =I6+I7+IF(I8="",0,I8) -> 7092.1178
A11: Bank cash-flow analogue: distributable capital = net profit less the capital retained to fund RWA growth at the CET1 target. FY25 buyback QAR 2.1bn (123.1mn shares). The gap between FCFE and dividends is the excess-capital build — the crux for the DDM-vs-FCFE spread.

Sheet Summary Financials
A1: Summary financials (every cell links to the statement sheets)
A3: QAR mn | B3: FY23 | C3: FY24 | D3: FY25 | E3: FY26E | F3: FY27E | G3: FY28E | H3: FY29E | I3: FY30E
A4: Operating income | B4: ='Income Statement'!B4 -> 38960 | C4: ='Income Statement'!C4 -> 41300 | D4: ='Income Statement'!D4 -> 44800 | E4: ='Income Statement'!E4 -> 47040 | F4: ='Income Statement'!F4 -> 50097.6 | G4: ='Income Statement'!G4 -> 53854.92 | H4: ='Income Statement'!H4 -> 58163.314 | I4: ='Income Statement'!I4 -> 62816.379
A5: Pre-provision profit | B5: ='Income Statement'!B6 -> 30155.04 | C5: ='Income Statement'!C6 -> 32090.1 | D5: ='Income Statement'!D6 -> 34361.6 | E5: ='Income Statement'!E6 -> 35750.4 | F5: ='Income Statement'!F6 -> 38074.176 | G5: ='Income Statement'!G6 -> 40929.739 | H5: ='Income Statement'!H6 -> 44204.118 | I5: ='Income Statement'!I6 -> 47740.448
A6: Net profit | B6: ='Income Statement'!B10 -> 15500 | C6: ='Income Statement'!C10 -> 16720 | D6: ='Income Statement'!D10 -> 17000 | E6: ='Income Statement'!E10 -> 18121.851 | F6: ='Income Statement'!F10 -> 19118.553 | G6: ='Income Statement'!G10 -> 20361.259 | H6: ='Income Statement'!H10 -> 21786.547 | I6: ='Income Statement'!I10 -> 23311.606
A7: EPS (QAR) | B7: ='Income Statement'!B11 -> 1.55 | C7: ='Income Statement'!C11 -> 1.69 | D7: ='Income Statement'!D11 -> 1.74 | E7: ='Income Statement'!E11 -> 1.8096 | F7: ='Income Statement'!F11 -> 1.909128 | G7: ='Income Statement'!G11 -> 2.0332213 | H7: ='Income Statement'!H11 -> 2.1755468 | I7: ='Income Statement'!I11 -> 2.3278351
A8: Total assets | B8: ='Balance Sheet'!B6 -> 1236000 | C8: ='Balance Sheet'!C6 -> 1298000 | D8: ='Balance Sheet'!D6 -> 1391000 | E8: ='Balance Sheet'!E6 -> 1515685 | F8: ='Balance Sheet'!F6 -> 1644077.1 | G8: ='Balance Sheet'!G6 -> 1775242.8 | H8: ='Balance Sheet'!H6 -> 1908123.6 | I8: ='Balance Sheet'!I6 -> 2041546
A9: Loans & advances | B9: ='Balance Sheet'!B4 -> 851000 | C9: ='Balance Sheet'!C4 -> 911000 | D9: ='Balance Sheet'!D4 -> 1018000 | E9: ='Balance Sheet'!E4 -> 1114710 | F9: ='Balance Sheet'!F4 -> 1215033.9 | G9: ='Balance Sheet'!G4 -> 1318311.8 | H9: ='Balance Sheet'!H4 -> 1423776.7 | I9: ='Balance Sheet'!I4 -> 1530560
A10: Customer deposits | B10: ='Balance Sheet'!B7 -> 861000 | C10: ='Balance Sheet'!C7 -> 887000 | D10: ='Balance Sheet'!D7 -> 955000 | E10: ='Balance Sheet'!E7 -> 1026625 | F10: ='Balance Sheet'!F7 -> 1098488.8 | G10: ='Balance Sheet'!G7 -> 1169890.5 | H10: ='Balance Sheet'!H7 -> 1240083.9 | I10: ='Balance Sheet'!I7 -> 1308288.6
A11: Total equity | B11: ='Balance Sheet'!B9 -> 111000 | C11: ='Balance Sheet'!C9 -> 114000 | D11: ='Balance Sheet'!D9 -> 125000 | E11: ='Balance Sheet'!E9 -> 135329.46 | F11: ='Balance Sheet'!F9 -> 146035.85 | G11: ='Balance Sheet'!G9 -> 157234.54 | H11: ='Balance Sheet'!H9 -> 168999.27 | I11: ='Balance Sheet'!I9 -> 181354.42
A12: Distributable capital (FCFE) | B12: ='Cash Flow'!B6 -> 6975 | C12: ='Cash Flow'!C6 -> 7524 | D12: ='Cash Flow'!D6 -> 7650 | E12: ='Cash Flow'!E6 -> 11559.351 | F12: ='Cash Flow'!F6 -> 12534.178 | G12: ='Cash Flow'!G6 -> 13819.212 | H12: ='Cash Flow'!H6 -> 15355.212 | I12: ='Cash Flow'!I6 -> 17062.492
A13: Dividends paid | B13: ='Cash Flow'!B7 -> -5923.45 | C13: ='Cash Flow'!C7 -> -6379.1 | D13: ='Cash Flow'!D7 -> -6606.925 | E13: ='Cash Flow'!E7 -> -7091.0805 | F13: ='Cash Flow'!F7 -> -7655.0687 | G13: ='Cash Flow'!G7 -> -8337.9357 | H13: ='Cash Flow'!H7 -> -9119.8487 | I13: ='Cash Flow'!I7 -> -9970.3737
A15: All green — pure cross-sheet links to the Income Statement, Balance Sheet and Cash Flow sheets. No hard-coded duplicates.

Sheet Monte Carlo
A1: Monte Carlo — YZ-HAR width · t5 shape · zero secular drift (non-EGX) · 16 factors
A3: Engine
A4: Anchor spot (QAR) | B4: 17.54
A5: Forecast ann. vol (HAR) | B5: 0.1805
A6: Paths | B6: 50000
A7: Seed | B7: 42
A8: Secular drift (non-EGX) | B8: 0
A9: Net continuous drift (3m) | B9: 0.003
A10: Net event contribution (3m) | B10: -0.0155
A11: Net total 3m contribution | B11: -0.0125
A13: Percentile map (QAR/share)
A14: Horizon | B14: p5 | C14: p25 | D14: p50 | E14: p75 | F14: p95
A15: T+20 sessions | B15: 15.35 | C15: 16.74 | D15: 17.48 | E15: 18.19 | F15: 19.55
A16: T+60 sessions | B16: 13.96 | C16: 15.91 | D16: 17.24 | E16: 18.6 | F16: 20.91
A19: Factor stack (7 continuous + 9 discrete)
A20: Continuous factor | B20: Dir. | D20: Discrete event | E20: Prob. | F20: Mean
A21: QCB policy-rate path (Fed-linked) | B21: - | D21: Regional geopolitical / Gulf-security shock | E21: 0.25 | F21: -0.08
A22: Hydrocarbon / Qatar sovereign liquidity | B22: + | D22: Oil-price regime shift (Brent) | E22: 0.3 | F22: 0.02
A23: QAR peg stability (USD peg) | B23: 0 | D23: Sovereign rating / QAR-peg action | E23: 0.2 | F23: 0.01
A24: QE Index & foreign / MSCI flows | B24: + | D24: Global rate-path surprise (Fed pivot) | E24: 0.3 | F24: 0.01
A25: Regional private-sector credit growth | B25: + | D25: Quarterly earnings surprise (NIM/fees/tax) | E25: 0.5 | F25: 0.01
A26: Turkey / Egypt EM translation | B26: - | D26: Asset-quality / ECL shift (EM exposure) | E26: 0.25 | F26: -0.05
A27: Global-minimum-tax (Pillar Two) drift | B27: - | D27: Capital action / dividend-policy change | E27: 0.3 | F27: 0.02
D28: MSCI / index reweighting or large flow | E28: 0.25 | F28: 0.01
D29: Pillar-Two / tax-regime step | E29: 0.25 | F29: -0.03
A31: Paths diffuse from spot; the §1 value gap is kept out of the drift (lens independence). Width from the pooled log-HAR cascade on a gap-aware Yang-Zhang proxy; shape unit-variance Student-t(5) via a per-path chi-square mixture; zero secular drift for a non-EGX name.

Sheet Sensitivity
A1: Sensitivity — DDM fair value across Ke × terminal-g (§3.5-G grid)
A3: Ke \ g | B3: 0.04 | C3: 0.045 | D3: 0.0475 | E3: 0.05 | F3: 0.0525
A4: 0.095 | B4: 20.28 | C4: 22.04 | D4: 23.06 | E4: 24.2 | F4: 25.47
A5: 0.1 | B5: 18.48 | C5: 19.93 | D5: 20.76 | E5: 21.66 | F5: 22.67
A6: 0.105 | B6: 16.97 | C6: 18.17 | D6: 18.85 | E6: 19.59 | F6: 20.4
A7: 0.11 | B7: 15.68 | C7: 16.69 | D7: 17.25 | E7: 17.87 | F7: 18.53
A8: 0.115 | B8: 14.55 | C8: 15.41 | D8: 15.89 | E8: 16.41 | F8: 16.96
A10: Two-stage DDM re-priced across cost of equity and terminal growth. Base = Ke 10.5% / g 4.75% (shaded band near spot). The high terminal-value share makes the valuation a Ke-minus-g bet — this grid is the disclosure (device A-7 / §3.5-G).

Sheet Per-Share & Ratios
A1: Per-share & ratios — the standardized dashboard
B3: FY23 | C3: FY24 | D3: FY25 | E3: FY26E | F3: FY27E | G3: FY28E | H3: FY29E | I3: FY30E
A4: EPS (QAR) | B4: 1.55 | C4: 1.69 | D4: 1.74 | E4: 1.81 | F4: 1.909 | G4: 2.033 | H4: 2.176 | I4: 2.328
A5: DPS (QAR) | B5: 0.65 | C5: 0.7 | D5: 0.725 | E5: 0.778 | F5: 0.84 | G5: 0.915 | H5: 1.001 | I5: 1.094
A6: Payout ratio | B6: =B5/B4 -> 0.41935484 | C6: =C5/C4 -> 0.41420118 | D6: =D5/D4 -> 0.41666667 | E6: =E5/E4 -> 0.42983425 | F6: =F5/F4 -> 0.44002095 | G6: =G5/G4 -> 0.45007378 | H6: =H5/H4 -> 0.46001838 | I6: =I5/I4 -> 0.46993127
A7: P/E (× on spot) | B7: =Assumptions!$B$4/B4 -> 11.316129 | C7: =Assumptions!$B$4/C4 -> 10.378698 | D7: =Assumptions!$B$4/D4 -> 10.08046 | E7: =Assumptions!$B$4/E4 -> 9.6906077 | F7: =Assumptions!$B$4/F4 -> 9.1880566 | G7: =Assumptions!$B$4/G4 -> 8.6276439 | H7: =Assumptions!$B$4/H4 -> 8.0606618 | I7: =Assumptions!$B$4/I4 -> 7.5343643
A8: Dividend yield (on spot) | B8: =B5/Assumptions!$B$4 -> 0.037058153 | C8: =C5/Assumptions!$B$4 -> 0.03990878 | D8: =D5/Assumptions!$B$4 -> 0.041334094 | E8: =E5/Assumptions!$B$4 -> 0.044355758 | F8: =F5/Assumptions!$B$4 -> 0.047890536 | G8: =G5/Assumptions!$B$4 -> 0.052166477 | H8: =H5/Assumptions!$B$4 -> 0.057069555 | I8: =I5/Assumptions!$B$4 -> 0.062371722
A9: BVPS (ordinary, QAR) | B9: 9.9 | C9: 10.9 | D9: 11.85 | E9: 12.92 | F9: 14.08 | G9: 15.35 | H9: 16.73 | I9: 18.23
A10: P/B (× on spot) | B10: =Assumptions!$B$4/B9 -> 1.7717172 | C10: =Assumptions!$B$4/C9 -> 1.6091743 | D10: =Assumptions!$B$4/D9 -> 1.4801688 | E10: =Assumptions!$B$4/E9 -> 1.3575851 | F10: =Assumptions!$B$4/F9 -> 1.2457386 | G10: =Assumptions!$B$4/G9 -> 1.142671 | H10: =Assumptions!$B$4/H9 -> 1.048416 | I10: =Assumptions!$B$4/I9 -> 0.9621503
A11: RoTE | B11: 0.159 | C11: 0.157 | D11: 0.155 | E11: 0.148 | F11: 0.146 | G11: 0.147 | H11: 0.149 | I11: 0.15
A12: Net interest margin | B12: 0.027 | C12: 0.0265 | D12: 0.0262 | E12: 0.0258 | F12: 0.0255 | G12: 0.0258 | H12: 0.026 | I12: 0.0262
A13: Cost/income | B13: 0.226 | C13: 0.223 | D13: 0.233 | E13: 0.235 | F13: 0.235 | G13: 0.234 | H13: 0.233 | I13: 0.232
A14: NPL ratio | B14: 0.03 | C14: 0.028 | D14: 0.026 | E14: 0.026 | F14: 0.026 | G14: 0.025 | H14: 0.025 | I14: 0.024
A15: Cost of risk | B15: 0.009 | C15: 0.0085 | D15: 0.009 | E15: 0.0088 | F15: 0.0085 | G15: 0.0083 | H15: 0.008 | I15: 0.008
A16: CAR | B16: 0.194 | C16: 0.192 | D16: 0.193 | E16: 0.194 | F16: 0.195 | G16: 0.196 | H16: 0.197 | I16: 0.198
A18: The fixed per-name panel (EFG 'Data Miner' analogue). Ratios on spot QAR 17.54. NIM, cost-of-risk and CAR forecasts are the preparer's flagged estimates consistent with FY25 guidance (NIM 260–265bps, CoR 85–90bps).

Sheet Peer & Sector
A1: Peer set & sector — GCC banks (dated, indicative)
A3: Bank | B3: P/B (×) | C3: P/E (×) | D3: RoE | E3: Div yld | F3: Note
A4: QNB Group (QNBK) | B4: 1.48 | C4: 10.1 | D4: 0.15 | E4: 0.041 | F4: This study
A5: Al Rajhi (1120) | B5: 4 | C5: 19 | D5: 0.2 | E5: 0.021 | F5: Islamic premium
A6: First Abu Dhabi (FAB) | B6: 1.5 | C6: 10.5 | D6: 0.16 | E6: 0.045 | F6: Largest UAE
A7: Emirates NBD | B7: 1.3 | C7: 7 | D7: 0.19 | E7: 0.04 | F7: Turkey/EM drag
A8: Saudi National Bank | B8: 1.4 | C8: 11.5 | D8: 0.13 | E8: 0.035 | F8: Biggest by equity
A9: Commercial Bank of Qatar | B9: 0.7 | C9: 7.5 | D9: 0.11 | E9: 0.045 | F9: Cheapest Qatari
A10: Qatar Islamic Bank | B10: 1.8 | C10: 11 | D10: 0.17 | E10: 0.037 | F10: Qatar Islamic
A12: Peer median (ex-Rajhi) | B12: =MEDIAN(B5:B10) -> 1.45 | C12: =MEDIAN(C5:C10) -> 10.75 | D12: =MEDIAN(D5:D10) -> 0.165
A14: Multiples are indicative and dated (mid-2025 to mid-2026 range); they move continuously. QNB at ~1.48× P/B on ~15% RoE sits a premium to CBQ/SAB (0.7–0.9×) and far below Al Rajhi (~4×). Source: AGBI, Bloomberg Intelligence, exchange data.
