Workbook

Sheet READ FIRST
A1: Riyad Bank (Tadawul: 1010) — Valuation Model
B3: Testahil · Independent Valuation Study — Educational Analysis · Not investment advice
B5: This workbook is the companion model to the RIBL valuation study (edition 09-07-2026).
B6: Blue cells = inputs you can change (all on the Assumptions sheet). Black = formulas. Green = links across sheets.
B8: Reading order: Assumptions → Driver Build → the five valuation lenses (DDM, FCFE, Residual Income,
B9: Relative & Normalized) → Summary. Financial statements (IS/BS/CF) and Monte Carlo sit behind.
B11: Read: moderately undervalued (~SAR 26.6 vs spot SAR 20.23, ~+32%), conditional on RIBL
B12: defending a mid-teens ROE. Cost of equity is built bottom-up on the local SAR curve (no USD shortcut).
B14: Every valuation output on every sheet traces to the single blue-cell Assumptions layer — change an
B15: assumption once and the whole model re-prices. Monte Carlo percentiles are simulation outputs (flagged).
B17: Some balance-sheet sub-lines are estimated to disclosed totals (Tier-1 sukuk, common-equity split, RWA proxy).

Sheet Summary
A1: Valuation summary — every lens
A3: Lens | B3: Fair value (SAR) | C3: Weight | D3: Note
A4: DDM | B4: =DDM!$B$15 -> 23.612199 | C4: =Assumptions!$B$43 -> 0.3 | D4: Cash actually distributed
A5: Residual income | B5: ='Residual Income'!$B$17 -> 33.238177 | C5: =Assumptions!$B$44 -> 0.2 | D5: Excess return over Ke
A6: FCFE (equity DCF) | B6: =FCFE!$B$15 -> 32.18062 | C6: =Assumptions!$B$45 -> 0.15 | D6: Distributable capital
A7: Relative multiples | B7: ='Relative & Normalized'!$B$10 -> 24.62241 | C7: =Assumptions!$B$46 -> 0.2 | D7: Peer P/B & fwd P/E
A8: Normalized earnings power | B8: ='Relative & Normalized'!$B$15 -> 20.853 | C8: =Assumptions!$B$47 -> 0.15 | D8: Through-cycle floor
A9: Weighted central | B9: =SUMPRODUCT(B4:B8,C4:C8) -> 26.61082 | C9: =SUM(C4:C8) -> 1
A10: Spot | B10: =Assumptions!$B$4 -> 20.23
A11: Upside vs spot | B11: =B9/B10-1 -> 0.31541374
A13: P/B (spot) | B13: =Assumptions!$B$4/Assumptions!$B$35 -> 1.2223565
A14: Dividend yield (spot) | B14: =DDM!B6/Assumptions!$B$4 -> 0.058340519
A16: Sell-side consensus PT (cross-check) | B16: 26.98

Sheet Assumptions
A1: Assumptions — the single blue-cell input layer
A3: Assumption | B3: Value | C3: Unit | D3: Basis
A4: Spot price | B4: 20.23 | C4: SAR | D4: 07 Jul 2026 close
A5: Shares outstanding (post-bonus) | B5: 3988 | C5: mn | D5: 1-for-3 bonus Q2-2026
A6: Tier-1 sukuk | B6: 8000 | C6: SAR mn | D6: estimated
A7: Tier-1 sukuk coupon | B7: 350 | C7: SAR mn | D7: estimated
A8: Risk-free rate (SAR 10Y sukuk) | B8: 0.053 | C8: % | D8: same-week Saudi anchor
A9: Equity risk premium (Saudi) | B9: 0.05 | C9: % | D9: Damodaran Jan-2026
A10: Beta | B10: 1 | C10: x | D10: assumed (no TASI regression)
A11: Terminal growth g | B11: 0.045 | C11: % | D11: Saudi nominal GDP proxy
A12: FY25 net income (base) | B12: 10411 | C12: SAR mn | D12: disclosed
A13: NI growth FY26E | B13: 0.085 | C13: % | D13: house view
A14: NI growth FY27E | B14: 0.075 | C14: % | D14: house view
A15: NI growth FY28E | B15: 0.065 | C15: % | D15: house view
... A47: Weight — Normalized earnings po | B47: 0.15 | C47: % | D47: synthesis

Sheet Driver Build
A1: Bank driver build — NIM, DuPont, capital
A3: Driver | B3: FY23 | C3: FY24 | D3: FY25 | E3: FY26E | F3: FY27E | G3: FY28E | H3: FY29E | I3: FY30E
A4: Net income (SAR mn) | B4: 8036 | C4: 9322 | D4: 10411 | E4: =D4*(1+Assumptions!$B$13) -> 11295.935 | F4: =E4*(1+Assumptions!$B$14) -> 12143.13 | G4: =F4*(1+Assumptions!$B$15) -> 12932.434 | H4: =G4*(1+Assumptions!$B$16) -> 13708.38 | I4: =H4*(1+Assumptions!$B$17) -> 14462.34
A5: NIM (%) | B5: 0.029 | C5: 0.0285 | D5: 0.0288 | E5: =Assumptions!$B$23 -> 0.028 | F5: =Assumptions!$B$24 -> 0.0275 | G5: =Assumptions!$B$25 -> 0.027 | H5: =Assumptions!$B$26 -> 0.0268 | I5: =Assumptions!$B$27 -> 0.0265
A6: Cost-to-income (%) | B6: 0.33 | C6: 0.31 | D6: 0.296 | E6: 0.3 | F6: 0.3 | G6: 0.3 | H6: 0.3 | I6: 0.3
A7: Cost of risk (bps) | B7: 55 | C7: 51 | D7: 37 | E7: 42 | F7: 44 | G7: 45 | H7: 45 | I7: 45
A8: Loans (SAR mn) | B8: 282000 | C8: 320090 | D8: 373305 | E8: =D8*(1+Assumptions!$B$38) -> 406902.45 | F8: =E8*(1+Assumptions!$B$39) -> 441489.16 | G8: =F8*(1+Assumptions!$B$40) -> 476808.29 | H8: =G8*(1+Assumptions!$B$41) -> 512568.91 | I8: =H8*(1+Assumptions!$B$42) -> 548448.74
A9: Total assets (SAR mn) | B9: 386849 | C9: 450379 | D9: 519481 | E9: =D9*(1+Assumptions!$B$38*0.95) -> 563896.63 | F9: =E9*(1+Assumptions!$B$39*0.95) -> 609431.28 | G9: =F9*(1+Assumptions!$B$40*0.95) -> 655748.06 | H9: =G9*(1+Assumptions!$B$41*0.95) -> 702470.1 | I9: =H9*(1+Assumptions!$B$42*0.95) -> 749184.37
A10: RWA (SAR mn) | B10: =B9*Assumptions!$B$28 -> 278531.28 | C10: =C9*Assumptions!$B$28 -> 324272.88 | D10: =D9*Assumptions!$B$28 -> 374026.32 | E10: =E9*Assumptions!$B$28 -> 406005.57 | F10: =F9*Assumptions!$B$28 -> 438790.52 | G10: =G9*Assumptions!$B$28 -> 472138.6 | H10: =H9*Assumptions!$B$28 -> 505778.47 | I10: =I9*Assumptions!$B$28 -> 539412.74
A11: Common equity (SAR mn) | B11: 52258 | C11: 59942 | D11: 66000 | E11: =D11+(E4-Assumptions!$B$7)*(1-Assumptions!$B$18) -> 72239.183 | F11: =E11+(F4-Assumptions!$B$7)*(1-Assumptions!$B$19) -> 78843.336 | G11: =F11+(G4-Assumptions!$B$7)*(1-Assumptions!$B$20) -> 85763.674 | H11: =G11+(H4-Assumptions!$B$7)*(1-Assumptions!$B$21) -> 92977.199 | I11: =H11+(I4-Assumptions!$B$7)*(1-Assumptions!$B$22) -> 100456.74
A12: Dividends paid (SAR mn) | E12: =(E4-Assumptions!$B$7)*Assumptions!$B$18 -> 4706.7521 | F12: =(F4-Assumptions!$B$7)*Assumptions!$B$19 -> 5188.9773 | G12: =(G4-Assumptions!$B$7)*Assumptions!$B$20 -> 5662.0951 | H12: =(H4-Assumptions!$B$7)*Assumptions!$B$21 -> 6144.8546 | I12: =(I4-Assumptions!$B$7)*Assumptions!$B$22 -> 6632.8
A13: ROAE (%) | E13: =(E4-Assumptions!$B$7)/((E11+D11)/2) -> 0.15836226 | F13: =(F4-Assumptions!$B$7)/((F11+E11)/2) -> 0.15611508 | G13: =(G4-Assumptions!$B$7)/((G11+F11)/2) -> 0.15287847 | H13: =(H4-Assumptions!$B$7)/((H11+G11)/2) -> 0.14947202 | I13: =(I4-Assumptions!$B$7)/((I11+H11)/2) -> 0.1459138
A14: Common equity / RWA (%) | B14: =B11/B10 -> 0.18761986 | C14: =C11/C10 -> 0.18485049 | D14: =D11/D10 -> 0.17645817 | E14: =E11/E10 -> 0.17792658 | F14: =F11/F10 -> 0.17968332 | G14: =G11/G10 -> 0.18164936 | H14: =H11/H10 -> 0.18382989 | I14: =I11/I10 -> 0.18623353
A16: Historical NI/NIM/CIR/CoR/loans/assets/equity disclosed or estimated to totals (blue). Forward = formulas off Assumptions.

Sheet DDM
A1: Dividend discount model — primary lens
A3: DDM build | B3: FY26E | C3: FY27E | D3: FY28E | E3: FY29E | F3: FY30E
A4: EPS (SAR) | B4: =('Driver Build'!E4-Assumptions!$B$7)/Assumptions!$B$5 -> 2.7447179 | C4: =('Driver Build'!F4-Assumptions!$B$7)/Assumptions!$B$5 -> 2.957154 | D4: =('Driver Build'!G4-Assumptions!$B$7)/Assumptions!$B$5 -> 3.1550736 | E4: =('Driver Build'!H4-Assumptions!$B$7)/Assumptions!$B$5 -> 3.3496438 | F4: =('Driver Build'!I4-Assumptions!$B$7)/Assumptions!$B$5 -> 3.5387012
A5: Payout ratio | B5: =Assumptions!$B$18 -> 0.43 | C5: =Assumptions!$B$19 -> 0.44 | D5: =Assumptions!$B$20 -> 0.45 | E5: =Assumptions!$B$21 -> 0.46 | F5: =Assumptions!$B$22 -> 0.47
A6: DPS (SAR) | B6: =B4*B5 -> 1.1802287 | C6: =C4*C5 -> 1.3011478 | D6: =D4*D5 -> 1.4197831 | E6: =E4*E5 -> 1.5408362 | F6: =F4*F5 -> 1.6631896
A7: Discount factor @ Ke | B7: =1/(1+(Assumptions!$B$8+Assumptions!$B$10*Assumptions!$B$9))^1 -> 0.90661831 | C7: =1/(1+(Assumptions!$B$8+Assumptions!$B$10*Assumptions!$B$9))^2 -> 0.82195677 | D7: =1/(1+(Assumptions!$B$8+Assumptions!$B$10*Assumptions!$B$9))^3 -> 0.74520106 | E7: =1/(1+(Assumptions!$B$8+Assumptions!$B$10*Assumptions!$B$9))^4 -> 0.67561293 | F7: =1/(1+(Assumptions!$B$8+Assumptions!$B$10*Assumptions!$B$9))^5 -> 0.61252305
A8: PV of DPS | B8: =B6*B7 -> 1.070017 | C8: =C6*C7 -> 1.0694872 | D8: =D6*D7 -> 1.0580239 | E8: =E6*E7 -> 1.0410088 | F8: =F6*F7 -> 1.018742
A10: Σ PV explicit dividends | B10: =SUM(B8:F8) -> 5.2572788
A11: Ke = rf + beta*ERP | B11: =Assumptions!$B$8+Assumptions!$B$10*Assumptions!$B$9 -> 0.103
A12: Terminal DPS (FY31) | B12: =F6*(1+Assumptions!$B$11) -> 1.7380331
A13: Terminal value | B13: =B12/(B11-Assumptions!$B$11) -> 29.966088
A14: PV terminal value | B14: =B13*F7 -> 18.35492
A15: DDM fair value (SAR) | B15: =B10+B14 -> 23.612199
A16: TV as % of value | B16: =B14/B15 -> 0.77734903

Sheet FCFE
A1: Equity DCF — free cash flow to equity
A3: FCFE build (SAR mn) | B3: FY26E | C3: FY27E | D3: FY28E | E3: FY29E | F3: FY30E
A4: Net income | B4: ='Driver Build'!E4 -> 11295.935 | C4: ='Driver Build'!F4 -> 12143.13 | D4: ='Driver Build'!G4 -> 12932.434 | E4: ='Driver Build'!H4 -> 13708.38 | F4: ='Driver Build'!I4 -> 14462.34
A5: ΔRWA | B5: ='Driver Build'!E10-'Driver Build'!D10 -> 31979.25 | C5: ='Driver Build'!F10-'Driver Build'!E10 -> 32784.95 | D5: ='Driver Build'!G10-'Driver Build'!F10 -> 33348.08 | E5: ='Driver Build'!H10-'Driver Build'!G10 -> 33639.875 | F5: ='Driver Build'!I10-'Driver Build'!H10 -> 33634.269
A6: − capital retained (ΔRWA×CET1) | B6: =B5*Assumptions!$B$29 -> 5116.6801 | C6: =C5*Assumptions!$B$29 -> 5245.592 | D6: =D5*Assumptions!$B$29 -> 5335.6927 | E6: =E5*Assumptions!$B$29 -> 5382.38 | F6: =F5*Assumptions!$B$29 -> 5381.483
A7: FCFE | B7: =B4-B6 -> 6179.2549 | C7: =C4-C6 -> 6897.5382 | D7: =D4-D6 -> 7596.7409 | E7: =E4-E6 -> 8325.9996 | F7: =F4-F6 -> 9080.8575
A8: Discount factor | B8: =DDM!B7 -> 0.90661831 | C8: =DDM!C7 -> 0.82195677 | D8: =DDM!D7 -> 0.74520106 | E8: =DDM!E7 -> 0.67561293 | F8: =DDM!F7 -> 0.61252305
A9: PV of FCFE | B9: =B7*B8 -> 5602.2257 | C9: =C7*C8 -> 5669.4782 | D9: =D7*D8 -> 5661.0993 | E9: =E7*E8 -> 5625.1529 | F9: =F7*F8 -> 5562.2346
A11: Σ PV explicit FCFE | B11: =SUM(B9:F9) -> 28120.191
A12: Terminal FCFE (FY31) | B12: =F7*(1+Assumptions!$B$11) -> 9489.4961
A13: PV terminal FCFE | B13: =B12/(DDM!B11-Assumptions!$B$11)*F8 -> 100216.12
A14: Equity value (SAR mn) | B14: =B11+B13 -> 128336.31
A15: FCFE value / share (SAR) | B15: =B14/Assumptions!$B$5 -> 32.18062

Sheet Residual Income
A1: Residual income valuation (EFG-style multi-period build)
A3: Residual income build (SAR mn) | B3: FY26E | C3: FY27E | D3: FY28E | E3: FY29E | F3: FY30E
A4: Opening book value (common eq) | B4: ='Driver Build'!D11 -> 66000 | C4: ='Driver Build'!E11 -> 72239.183 | D4: ='Driver Build'!F11 -> 78843.336 | E4: ='Driver Build'!G11 -> 85763.674 | F4: ='Driver Build'!H11 -> 92977.199
A5: Net income to common | B5: ='Driver Build'!E4-Assumptions!$B$7 -> 10945.935 | C5: ='Driver Build'!F4-Assumptions!$B$7 -> 11793.13 | D5: ='Driver Build'!G4-Assumptions!$B$7 -> 12582.434 | E5: ='Driver Build'!H4-Assumptions!$B$7 -> 13358.38 | F5: ='Driver Build'!I4-Assumptions!$B$7 -> 14112.34
A6: − equity charge (Ke × opening BV) | B6: =DDM!B11*B4 -> 6798 | C6: =DDM!B11*C4 -> 7440.6358 | D6: =DDM!B11*D4 -> 8120.8636 | E6: =DDM!B11*E4 -> 8833.6585 | F6: =DDM!B11*F4 -> 9576.6515
A7: Residual income | B7: =B5-B6 -> 4147.935 | C7: =C5-C6 -> 4352.4943 | D7: =D5-D6 -> 4461.57 | E7: =E5-E6 -> 4524.7211 | F7: =F5-F6 -> 4535.689
A8: Discount factor | B8: =DDM!B7 -> 0.90661831 | C8: =DDM!C7 -> 0.82195677 | D8: =DDM!D7 -> 0.74520106 | E8: =DDM!E7 -> 0.67561293 | F8: =DDM!F7 -> 0.61252305
A9: PV of residual income | B9: =B7*B8 -> 3760.5938 | C9: =C7*C8 -> 3577.5621 | D9: =D7*D8 -> 3324.7667 | E9: =E7*E8 -> 3056.9601 | F9: =F7*F8 -> 2778.214
A11: Book value FY25 (B0) | B11: ='Driver Build'!D11 -> 66000
A12: Σ PV explicit RI | B12: =SUM(B9:F9) -> 16498.097
A13: Terminal RI (FY31) | B13: =F7*(1+Assumptions!$B$11) -> 4739.795
A14: Terminal value | B14: =B13/(DDM!B11-Assumptions!$B$11) -> 81720.603
A15: PV terminal value | B15: =B14*F8 -> 50055.753
A16: Equity value | B16: =B11+B12+B15 -> 132553.85
A17: RI value / share (SAR) | B17: =B16/Assumptions!$B$5 -> 33.238177
A18: Implied exit P/B on FY25 book | B18: =B16/B11 -> 2.0083917
A20: Justified P/B cross-check (through-cycle)
A21: Through-cycle ROE | B21: =Assumptions!$B$30 -> 0.145
A22: Cost of equity Ke | B22: =DDM!B11 -> 0.103
A23: Terminal growth g | B23: =Assumptions!$B$11 -> 0.045
A24: Justified P/B = (ROE−g)/(Ke−g) | B24: =ROUND((B21-B23)/(B22-B23),2) -> 1.72
A25: BVPS FY25 (common) | B25: =Assumptions!$B$35 -> 16.55
A26: Justified fair value (SAR) | B26: =B24*B25 -> 28.466
A28: Multi-period build feeds the Summary; the through-cycle justified P/B is Expert 1's more conservative reading.

Sheet Relative & Normalized
A1: Relative multiples & normalized earnings floor
A3: Item | B3: Value | C3: Basis
A4: Sector P/B | B4: =Assumptions!$B$33 -> 1.4
A5: BVPS FY25 | B5: =Assumptions!$B$35 -> 16.55
A6: P/B fair value | B6: =B4*B5 -> 23.17
A7: Forward P/E | B7: =Assumptions!$B$34 -> 9.5
A8: FY26E EPS | B8: =DDM!B4 -> 2.7447179
A9: P/E fair value | B9: =B7*B8 -> 26.07482
A10: Relative blend (SAR) | B10: =AVERAGE(B6,B9) -> 24.62241
A12: Normalized ROE | B12: =Assumptions!$B$31 -> 0.14
A13: Normalized EPS = ROE×BVPS | B13: =B12*Assumptions!$B$35 -> 2.317
A14: Normalized P/E | B14: =Assumptions!$B$32 -> 9
A15: Normalized fair value (SAR) | B15: =B13*B14 -> 20.853

Sheet Income Statement
A1: Income statement — 3yr historical + 5yr forecast (SAR mn)
A3: Line | B3: FY23 | C3: FY24 | D3: FY25 | E3: FY26E | F3: FY27E | G3: FY28E | H3: FY29E | I3: FY30E
A4: Net special commission income | B4: 8300 | C4: 8900 | D4: 9700 | E4: 10400 | F4: 11000 | G4: 11600 | H4: 12200 | I4: 12800
A5: Fee & commission income, net | B5: 2400 | C5: 2700 | D5: 3200 | E5: 3650 | F5: 4050 | G5: 4400 | H5: 4750 | I5: 5050
A6: Trading & other income | B6: 1500 | C6: 1700 | D6: 2000 | E6: 2100 | F6: 2200 | G6: 2300 | H6: 2400 | I6: 2500
A7: Total operating income | B7: =SUM(B4:B6) -> 12200 | C7: =SUM(C4:C6) -> 13300 | D7: =SUM(D4:D6) -> 14900 | E7: =E4+E5+E6 -> 16150 | F7: =F4+F5+F6 -> 17250 | G7: =G4+G5+G6 -> 18300 | H7: =H4+H5+H6 -> 19350 | I7: =I4+I5+I6 -> 20350
A8: Net income (disclosed/model) | B8: 8036 | C8: 9322 | D8: 10411 | E8: ='Driver Build'!E4 -> 11295.935 | F8: ='Driver Build'!F4 -> 12143.13 | G8: ='Driver Build'!G4 -> 12932.434 | H8: ='Driver Build'!H4 -> 13708.38 | I8: ='Driver Build'!I4 -> 14462.34
A9: EPS (post-bonus, SAR) | B9: 1.927 | C9: 2.25 | D9: 2.523 | E9: =DDM!B4 -> 2.7447179 | F9: =DDM!C4 -> 2.957154 | G9: =DDM!D4 -> 3.1550736 | H9: =DDM!E4 -> 3.3496438 | I9: =DDM!F4 -> 3.5387012
A11: FY23–25 net income disclosed; operating sub-lines estimated to totals (blue). Forecast net income links to Driver Build.

Sheet Balance Sheet
A1: Balance sheet — 3yr historical + 5yr forecast (SAR mn)
A3: Line | B3: FY23 | C3: FY24 | D3: FY25 | E3: FY26E | F3: FY27E | G3: FY28E | H3: FY29E | I3: FY30E
A4: Loans & advances, net | B4: 282000 | C4: 320090 | D4: 373305 | E4: ='Driver Build'!E8 -> 406902.45 | F4: ='Driver Build'!F8 -> 441489.16 | G4: ='Driver Build'!G8 -> 476808.29 | H4: ='Driver Build'!H8 -> 512568.91 | I4: ='Driver Build'!I8 -> 548448.74
A5: Total assets | B5: 386849 | C5: 450379 | D5: 519481 | E5: ='Driver Build'!E9 -> 563896.63 | F5: ='Driver Build'!F9 -> 609431.28 | G5: ='Driver Build'!G9 -> 655748.06 | H5: ='Driver Build'!H9 -> 702470.1 | I5: ='Driver Build'!I9 -> 749184.37
A6: Client deposits | B6: 275000 | C6: 306412 | D6: 331721 | E6: 358259 | F6: 385128 | G6: 412087 | H6: 440933 | I6: 469594
A7: Common equity | B7: 52258 | C7: 59942 | D7: 66000 | E7: ='Driver Build'!E11 -> 72239.183 | F7: ='Driver Build'!F11 -> 78843.336 | G7: ='Driver Build'!G11 -> 85763.674 | H7: ='Driver Build'!H11 -> 92977.199 | I7: ='Driver Build'!I11 -> 100456.74
A8: Tier-1 sukuk | B8: =Assumptions!$B$6 -> 8000 | C8: =Assumptions!$B$6 -> 8000 | D8: =Assumptions!$B$6 -> 8000 | E8: =Assumptions!$B$6 -> 8000 | F8: =Assumptions!$B$6 -> 8000 | G8: =Assumptions!$B$6 -> 8000 | H8: =Assumptions!$B$6 -> 8000 | I8: =Assumptions!$B$6 -> 8000
A9: Total equity | B9: =B7+B8 -> 60258 | C9: =C7+C8 -> 67942 | D9: =D7+D8 -> 74000 | E9: =E7+E8 -> 80239.183 | F9: =F7+F8 -> 86843.336 | G9: =G7+G8 -> 93763.674 | H9: =H7+H8 -> 100977.2 | I9: =I7+I8 -> 108456.74
A10: RWA (proxy) | B10: ='Driver Build'!B10 -> 278531.28 | C10: ='Driver Build'!C10 -> 324272.88 | D10: ='Driver Build'!D10 -> 374026.32 | E10: ='Driver Build'!E10 -> 406005.57 | F10: ='Driver Build'!F10 -> 438790.52 | G10: ='Driver Build'!G10 -> 472138.6 | H10: ='Driver Build'!H10 -> 505778.47 | I10: ='Driver Build'!I10 -> 539412.74
A11: Common equity / RWA (%) | B11: =B7/B10 -> 0.18761986 | C11: =C7/C10 -> 0.18485049 | D11: =D7/D10 -> 0.17645817 | E11: =E7/E10 -> 0.17792658 | F11: =F7/F10 -> 0.17968332 | G11: =G7/G10 -> 0.18164936 | H11: =H7/H10 -> 0.18382989 | I11: =I7/I10 -> 0.18623353
A12: BVPS (post-bonus, SAR) | B12: =B7/Assumptions!$B$5 -> 13.103811 | C12: =C7/Assumptions!$B$5 -> 15.030592 | D12: =D7/Assumptions!$B$5 -> 16.549649 | E12: =E7/Assumptions!$B$5 -> 18.114138 | F12: =F7/Assumptions!$B$5 -> 19.770144 | G12: =G7/Assumptions!$B$5 -> 21.505435 | H12: =H7/Assumptions!$B$5 -> 23.314243 | I12: =I7/Assumptions!$B$5 -> 25.189754
A14: FY23–25 totals disclosed; Tier-1 sukuk & common-equity split estimated; RWA is a 72%-of-assets proxy.

Sheet Cash Flow
A1: Cash flow — sources & uses of equity capital (SAR mn)
A3: Line | B3: FY26E | C3: FY27E | D3: FY28E | E3: FY29E | F3: FY30E
A4: Net income | B4: ='Driver Build'!E4 -> 11295.935 | C4: ='Driver Build'!F4 -> 12143.13 | D4: ='Driver Build'!G4 -> 12932.434 | E4: ='Driver Build'!H4 -> 13708.38 | F4: ='Driver Build'!I4 -> 14462.34
A5: − dividends paid | B5: =-'Driver Build'!E12 -> -4706.7521 | C5: =-'Driver Build'!F12 -> -5188.9773 | D5: =-'Driver Build'!G12 -> -5662.0951 | E5: =-'Driver Build'!H12 -> -6144.8546 | F5: =-'Driver Build'!I12 -> -6632.8
A6: − capital retained for RWA growth | B6: =-FCFE!B6 -> -5116.6801 | C6: =-FCFE!C6 -> -5245.592 | D6: =-FCFE!D6 -> -5335.6927 | E6: =-FCFE!E6 -> -5382.38 | F6: =-FCFE!F6 -> -5381.483
A7: Retained surplus (buffer) | B7: =B4+B5+B6 -> 1472.5029 | C7: =C4+C5+C6 -> 1708.5609 | D7: =D4+D5+D6 -> 1934.6457 | E7: =E4+E5+E6 -> 2181.1449 | F7: =F4+F5+F6 -> 2448.0575
A8: Memo: FCFE | B8: =FCFE!B7 -> 6179.2549 | C8: =FCFE!C7 -> 6897.5382 | D8: =FCFE!D7 -> 7596.7409 | E8: =FCFE!E7 -> 8325.9996 | F8: =FCFE!F7 -> 9080.8575

Sheet Monte Carlo
A1: Monte Carlo — YZ-HAR, 50,000 paths, zero drift
A3: Horizon | B3: p5 | C3: p25 | D3: p50 | E3: p75 | F3: p95
A4: T+20 | B4: 18.27 | C4: 19.49 | D4: 20.22 | E4: 20.99 | F4: 22.43
A5: T+60 | B5: 16.95 | C5: 18.97 | D5: 20.22 | E5: 21.57 | F5: 24.19
A7: 50% band T+60 | B7: =C5 -> 18.97 | C7: to | D7: =E5 -> 21.57
A8: 90% band T+60 | B8: =B5 -> 16.95 | C8: to | D8: =F5 -> 24.19
A10: Anchor vol (YZ-HAR, ann.) | B10: 0.233
A14: Percentiles are simulation outputs (YZ-HAR engine, 50k paths, seed 42), not formulas — flagged per house convention.
A16: Level | B16: Touch T+20 | C16: Touch T+60
A17: 17.2 | B17: 0.019 | C17: 0.109
A18: 18.21 | B18: 0.075 | C18: 0.252
A19: 19.22 | B19: 0.298 | C19: 0.536
A20: 20.23 | B20: 1 | C20: 1
A21: 21.24 | B21: 0.322 | C21: 0.552
A22: 22.25 | B22: 0.097 | C22: 0.293
A23: 23.26 | B23: 0.032 | C23: 0.153

Sheet Sensitivity
A1: DDM fair value — Ke × terminal growth
A3: Ke \ g | B3: 4.0% | C3: 4.5% | D3: 5.0% | E3: 5.5%
A4: 9.5% | B4: =DDM!B6/(1+0.095)^1+DDM!C6/(1+0.095)^2+DDM!D6/(1+0.095)^3+DDM!E6/(1+0.095)^4+DDM!F6/(1+0.095)^5+DDM!F6*(1+0.04)/(0.095-0.04)/(1+0.095)^5 -> 25.35019 | C4: =DDM!B6/(1+0.095)^1+DDM!C6/(1+0.095)^2+DDM!D6/(1+0.095)^3+DDM!E6/(1+0.095)^4+DDM!F6/(1+0.095)^5+DDM!F6*(1+0.045)/(0.095-0.045)/(1+0.095)^5 -> 27.453594 | D4: =DDM!B6/(1+0.095)^1+DDM!C6/(1+0.095)^2+DDM!D6/(1+0.095)^3+DDM!E6/(1+0.095)^4+DDM!F6/(1+0.095)^5+DDM!F6*(1+0.05)/(0.095-0.05)/(1+0.095)^5 -> 30.02442 | E4: =DDM!B6/(1+0.095)^1+DDM!C6/(1+0.095)^2+DDM!D6/(1+0.095)^3+DDM!E6/(1+0.095)^4+DDM!F6/(1+0.095)^5+DDM!F6*(1+0.055)/(0.095-0.055)/(1+0.095)^5 -> 33.237953
A5: 10.3% | B5: =DDM!B6/(1+0.103)^1+DDM!C6/(1+0.103)^2+DDM!D6/(1+0.103)^3+DDM!E6/(1+0.103)^4+DDM!F6/(1+0.103)^5+DDM!F6*(1+0.04)/(0.103-0.04)/(1+0.103)^5 -> 22.074606 | C5: =DDM!B6/(1+0.103)^1+DDM!C6/(1+0.103)^2+DDM!D6/(1+0.103)^3+DDM!E6/(1+0.103)^4+DDM!F6/(1+0.103)^5+DDM!F6*(1+0.045)/(0.103-0.045)/(1+0.103)^5 -> 23.612199 | D5: =DDM!B6/(1+0.103)^1+DDM!C6/(1+0.103)^2+DDM!D6/(1+0.103)^3+DDM!E6/(1+0.103)^4+DDM!F6/(1+0.103)^5+DDM!F6*(1+0.05)/(0.103-0.05)/(1+0.103)^5 -> 25.439902 | E5: =DDM!B6/(1+0.103)^1+DDM!C6/(1+0.103)^2+DDM!D6/(1+0.103)^3+DDM!E6/(1+0.103)^4+DDM!F6/(1+0.103)^5+DDM!F6*(1+0.055)/(0.103-0.055)/(1+0.103)^5 -> 27.648378
A6: 11.0% | B6: =DDM!B6/(1+0.11)^1+DDM!C6/(1+0.11)^2+DDM!D6/(1+0.11)^3+DDM!E6/(1+0.11)^4+DDM!F6/(1+0.11)^5+DDM!F6*(1+0.04)/(0.11-0.04)/(1+0.11)^5 -> 19.823789 | C6: =DDM!B6/(1+0.11)^1+DDM!C6/(1+0.11)^2+DDM!D6/(1+0.11)^3+DDM!E6/(1+0.11)^4+DDM!F6/(1+0.11)^5+DDM!F6*(1+0.045)/(0.11-0.045)/(1+0.11)^5 -> 21.027739 | D6: =DDM!B6/(1+0.11)^1+DDM!C6/(1+0.11)^2+DDM!D6/(1+0.11)^3+DDM!E6/(1+0.11)^4+DDM!F6/(1+0.11)^5+DDM!F6*(1+0.05)/(0.11-0.05)/(1+0.11)^5 -> 22.432348 | E6: =DDM!B6/(1+0.11)^1+DDM!C6/(1+0.11)^2+DDM!D6/(1+0.11)^3+DDM!E6/(1+0.11)^4+DDM!F6/(1+0.11)^5+DDM!F6*(1+0.055)/(0.11-0.055)/(1+0.11)^5 -> 24.092339
A8: Centre cell (Ke 10.3%, g 4.5%) = DDM base; blends with 4 other lenses to the weighted central.

Sheet Per-Share & Ratios
A1: Per-share & ratio summary
A3: Metric | B3: FY23 | C3: FY24 | D3: FY25 | E3: FY26E | F3: FY27E | G3: FY28E | H3: FY29E | I3: FY30E
A4: EPS (SAR) | B4: ='Income Statement'!B9 -> 1.927 | C4: ='Income Statement'!C9 -> 2.25 | D4: ='Income Statement'!D9 -> 2.523 | E4: =DDM!B4 -> 2.7447179 | F4: =DDM!C4 -> 2.957154 | G4: =DDM!D4 -> 3.1550736 | H4: =DDM!E4 -> 3.3496438 | I4: =DDM!F4 -> 3.5387012
A5: DPS (SAR) | B5: 0.79 | C5: 0.9 | D5: 1.05 | E5: =DDM!B6 -> 1.1802287 | F5: =DDM!C6 -> 1.3011478 | G5: =DDM!D6 -> 1.4197831 | H5: =DDM!E6 -> 1.5408362 | I5: =DDM!F6 -> 1.6631896
A6: BVPS (SAR) | B6: ='Balance Sheet'!B12 -> 13.103811 | C6: ='Balance Sheet'!C12 -> 15.030592 | D6: ='Balance Sheet'!D12 -> 16.549649 | E6: ='Balance Sheet'!E12 -> 18.114138 | F6: ='Balance Sheet'!F12 -> 19.770144 | G6: ='Balance Sheet'!G12 -> 21.505435 | H6: ='Balance Sheet'!H12 -> 23.314243 | I6: ='Balance Sheet'!I12 -> 25.189754
A7: ROAE (%) | E7: ='Driver Build'!E13 -> 0.15836226 | F7: ='Driver Build'!F13 -> 0.15611508 | G7: ='Driver Build'!G13 -> 0.15287847 | H7: ='Driver Build'!H13 -> 0.14947202 | I7: ='Driver Build'!I13 -> 0.1459138
A8: Payout (%) | E8: =DDM!B5 -> 0.43 | F8: =DDM!C5 -> 0.44 | G8: =DDM!D5 -> 0.45 | H8: =DDM!E5 -> 0.46 | I8: =DDM!F5 -> 0.47
A9: P/E @ spot (x) | B9: =Assumptions!$B$4/B4 -> 10.498184 | C9: =Assumptions!$B$4/C4 -> 8.9911111 | D9: =Assumptions!$B$4/D4 -> 8.0182323 | E9: =Assumptions!$B$4/E4 -> 7.3705207 | F9: =Assumptions!$B$4/F4 -> 6.841037 | G9: =Assumptions!$B$4/G4 -> 6.4118948 | H9: =Assumptions!$B$4/H4 -> 6.0394481 | I9: =Assumptions!$B$4/I4 -> 5.7167867
A10: P/B @ spot (x) | B10: =Assumptions!$B$4/B6 -> 1.5438256 | C10: =Assumptions!$B$4/C6 -> 1.3459217 | D10: =Assumptions!$B$4/D6 -> 1.2223824 | E10: =Assumptions!$B$4/E6 -> 1.1168072 | F10: =Assumptions!$B$4/F6 -> 1.0232601 | G10: =Assumptions!$B$4/G6 -> 0.94069244 | H10: =Assumptions!$B$4/H6 -> 0.86770994 | I10: =Assumptions!$B$4/I6 -> 0.8031043

Sheet Peer & Sector
A1: Peer set & sector context
A3: Bank | B3: P/B | C3: P/E | D3: ROE | E3: Note
A4: Al Rajhi | B4: 3.5 | C4: 16 | D4: 0.23 | E4: Premium Islamic compounder
A5: SNB | B5: 1.4 | C5: 10 | D5: 0.13 | E5: Largest by assets, PIF-majority
A6: Riyad Bank | B6: 1.2 | C6: 8 | D6: 0.16 | E6: This study — cheap for the ROE
A7: Alinma | B7: 1.6 | C7: 11 | D7: 0.15 | E7: Faster-growing mid-tier
A8: Banque Saudi Fransi | B8: 1.1 | C8: 9 | D8: 0.12 | E8: Corporate-tilted
A9: Arab National Bank | B9: 1 | C9: 8 | D9: 0.12 | E9: Value end
A10: Al Bilad | B10: 2 | C10: 14 | D10: 0.16 | E10: Retail/Islamic growth
A11: Saudi Investment Bank | B11: 0.9 | C11: 8 | D11: 0.11 | E11: Deepest discount
A12: Emirates NBD (UAE) | B12: 1 | C12: 6 | D12: 0.18 | E12: GCC reference
A13: QNB (Qatar) | B13: 1.4 | C13: 9 | D13: 0.18 | E13: GCC reference
A15: Multiples approximate, for context; not independently verified. RIBL screens cheap for its ROE.

Sheet Earnings Drivers
A1: Key earnings drivers (2yr back / 2yr forward)
A3: Driver | B3: FY23 a | C3: FY24 a | D3: FY25 a | E3: FY26 e | F3: FY27 e
A4: Loan growth | B4: n/a | C4: ='Balance Sheet'!C4/'Balance Sheet'!B4-1 -> 0.13507092 | D4: ='Balance Sheet'!D4/'Balance Sheet'!C4-1 -> 0.16625012 | E4: ='Balance Sheet'!E4/'Balance Sheet'!D4-1 -> 0.09 | F4: ='Balance Sheet'!F4/'Balance Sheet'!E4-1 -> 0.085
A5: Deposit growth | B5: n/a | C5: ='Balance Sheet'!C6/'Balance Sheet'!B6-1 -> 0.11422545 | D5: ='Balance Sheet'!D6/'Balance Sheet'!C6-1 -> 0.08259794 | E5: ='Balance Sheet'!E6/'Balance Sheet'!D6-1 -> 0.080000965 | F5: ='Balance Sheet'!F6/'Balance Sheet'!E6-1 -> 0.074998814
A6: NIM | B6: ='Driver Build'!B5 -> 0.029 | C6: ='Driver Build'!C5 -> 0.0285 | D6: ='Driver Build'!D5 -> 0.0288 | E6: ='Driver Build'!E5 -> 0.028 | F6: ='Driver Build'!F5 -> 0.0275
A7: Net interest income growth | B7: n/a | C7: ='Income Statement'!C4/'Income Statement'!B4-1 -> 0.072289157 | D7: ='Income Statement'!D4/'Income Statement'!C4-1 -> 0.08988764 | E7: ='Income Statement'!E4/'Income Statement'!D4-1 -> 0.072164948 | F7: ='Income Statement'!F4/'Income Statement'!E4-1 -> 0.057692308
A8: Fee income growth | B8: n/a | C8: ='Income Statement'!C5/'Income Statement'!B5-1 -> 0.125 | D8: ='Income Statement'!D5/'Income Statement'!C5-1 -> 0.18518519 | E8: ='Income Statement'!E5/'Income Statement'!D5-1 -> 0.140625 | F8: ='Income Statement'!F5/'Income Statement'!E5-1 -> 0.10958904
A9: Revenue growth | B9: n/a | C9: ='Income Statement'!C7/'Income Statement'!B7-1 -> 0.090163934 | D9: ='Income Statement'!D7/'Income Statement'!C7-1 -> 0.12030075 | E9: ='Income Statement'!E7/'Income Statement'!D7-1 -> 0.083892617 | F9: ='Income Statement'!F7/'Income Statement'!E7-1 -> 0.068111455
A10: Opex growth | B10: n/a | C10: 0.023 | D10: 0.02 | E10: 0.103 | F10: 0.065
A11: Cost-to-income | B11: ='Driver Build'!B6 -> 0.33 | C11: ='Driver Build'!C6 -> 0.31 | D11: ='Driver Build'!D6 -> 0.296 | E11: ='Driver Build'!E6 -> 0.3 | F11: ='Driver Build'!F6 -> 0.3
A12: Cost of risk (bps) | B12: ='Driver Build'!B7 -> 55 | C12: ='Driver Build'!C7 -> 51 | D12: ='Driver Build'!D7 -> 37 | E12: ='Driver Build'!E7 -> 42 | F12: ='Driver Build'!F7 -> 44
A13: Earnings growth | B13: n/a | C13: ='Driver Build'!C4/'Driver Build'!B4-1 -> 0.16002987 | D13: ='Driver Build'!D4/'Driver Build'!C4-1 -> 0.11682042 | E13: ='Driver Build'!E4/'Driver Build'!D4-1 -> 0.085 | F13: ='Driver Build'!F4/'Driver Build'!E4-1 -> 0.075
A14: ROAE | B14: n/a | C14: 0.16 | D14: 0.16 | E14: ='Driver Build'!E13 -> 0.15836226 | F14: ='Driver Build'!F13 -> 0.15611508
A15: ROAA | B15: n/a | C15: ='Driver Build'!C4/(('Balance Sheet'!C5+'Balance Sheet'!B5)/2) -> 0.022268725 | D15: ='Driver Build'!D4/(('Balance Sheet'!D5+'Balance Sheet'!C5)/2) -> 0.021469078 | E15: ='Driver Build'!E4/(('Balance Sheet'!E5+'Balance Sheet'!D5)/2) -> 0.020853181 | F15: ='Driver Build'!F4/(('Balance Sheet'!F5+'Balance Sheet'!E5)/2) -> 0.020698613
A16: Net profit — reported (SAR mn) | B16: ='Driver Build'!B4 -> 8036 | C16: ='Driver Build'!C4 -> 9322 | D16: ='Driver Build'!D4 -> 10411 | E16: ='Driver Build'!E4 -> 11295.935 | F16: ='Driver Build'!F4 -> 12143.13
A17: Net profit — attributable (SAR mn) | B17: ='Driver Build'!B4-Assumptions!$B$7 -> 7686 | C17: ='Driver Build'!C4-Assumptions!$B$7 -> 8972 | D17: ='Driver Build'!D4-Assumptions!$B$7 -> 10061 | E17: ='Driver Build'!E4-Assumptions!$B$7 -> 10945.935 | F17: ='Driver Build'!F4-Assumptions!$B$7 -> 11793.13
A19: Growth rows link to statements; opex growth & FY24-25 ROAE are estimates (blue). Mirrors the EFG house driver table.

Sheet Summary Financials
A1: Summary financials (links to statements)
A3: Line | B3: FY23 | C3: FY24 | D3: FY25 | E3: FY26E | F3: FY27E | G3: FY28E | H3: FY29E | I3: FY30E
A4: Total operating income | B4: ='Income Statement'!B7 -> 12200 | C4: ='Income Statement'!C7 -> 13300 | D4: ='Income Statement'!D7 -> 14900 | E4: ='Income Statement'!E7 -> 16150 | F4: ='Income Statement'!F7 -> 17250 | G4: ='Income Statement'!G7 -> 18300 | H4: ='Income Statement'!H7 -> 19350 | I4: ='Income Statement'!I7 -> 20350
A5: Net income | B5: ='Income Statement'!B8 -> 8036 | C5: ='Income Statement'!C8 -> 9322 | D5: ='Income Statement'!D8 -> 10411 | E5: ='Income Statement'!E8 -> 11295.935 | F5: ='Income Statement'!F8 -> 12143.13 | G5: ='Income Statement'!G8 -> 12932.434 | H5: ='Income Statement'!H8 -> 13708.38 | I5: ='Income Statement'!I8 -> 14462.34
A6: Total assets | B6: ='Balance Sheet'!B5 -> 386849 | C6: ='Balance Sheet'!C5 -> 450379 | D6: ='Balance Sheet'!D5 -> 519481 | E6: ='Balance Sheet'!E5 -> 563896.63 | F6: ='Balance Sheet'!F5 -> 609431.28 | G6: ='Balance Sheet'!G5 -> 655748.06 | H6: ='Balance Sheet'!H5 -> 702470.1 | I6: ='Balance Sheet'!I5 -> 749184.37
A7: Loans | B7: ='Balance Sheet'!B4 -> 282000 | C7: ='Balance Sheet'!C4 -> 320090 | D7: ='Balance Sheet'!D4 -> 373305 | E7: ='Balance Sheet'!E4 -> 406902.45 | F7: ='Balance Sheet'!F4 -> 441489.16 | G7: ='Balance Sheet'!G4 -> 476808.29 | H7: ='Balance Sheet'!H4 -> 512568.91 | I7: ='Balance Sheet'!I4 -> 548448.74
A8: Deposits | B8: ='Balance Sheet'!B6 -> 275000 | C8: ='Balance Sheet'!C6 -> 306412 | D8: ='Balance Sheet'!D6 -> 331721 | E8: ='Balance Sheet'!E6 -> 358259 | F8: ='Balance Sheet'!F6 -> 385128 | G8: ='Balance Sheet'!G6 -> 412087 | H8: ='Balance Sheet'!H6 -> 440933 | I8: ='Balance Sheet'!I6 -> 469594
A9: Common equity | B9: ='Balance Sheet'!B7 -> 52258 | C9: ='Balance Sheet'!C7 -> 59942 | D9: ='Balance Sheet'!D7 -> 66000 | E9: ='Balance Sheet'!E7 -> 72239.183 | F9: ='Balance Sheet'!F7 -> 78843.336 | G9: ='Balance Sheet'!G7 -> 85763.674 | H9: ='Balance Sheet'!H7 -> 92977.199 | I9: ='Balance Sheet'!I7 -> 100456.74
