Workbook

Sheet READ FIRST
A1: Testahil · Independent Valuation Study — SABIC (Tadawul: 2010)
A2: Educational analysis · Not investment advice · distributions, not tips
A5: This workbook is the companion model to the SABIC valuation study. It is educational and
A6: informational only — NOT investment advice, NOT a recommendation, and contains no price target
A7: and no rating. The preparer is not licensed by any securities regulator and holds no advisory mandate.
A9: Architecture: every downstream sheet links back to the Assumptions tab (the single blue-cell input
A10: layer). Change one input there — e.g. the terminal EBITDA margin, WACC, or terminal growth — and the
A11: whole model reprices. Blue = input; black = formula; green = cross-sheet link.
A13: Primary lens: normalized mid-cycle DCF (petrochemical — the product-feedstock spread cycle is the
A14: swing factor). Cross-checks: EV/EBITDA & P/B relative, and a normalized-dividend-yield read.
A16: Currency: SAR billion unless noted; per-share in SAR. Shares 3,000 mn. Spot SAR 51.80 (7 Jul 2026).
A17: SABIC reports adjusted metrics (ex one-offs) from Q2-2025; the 2025 reported net loss of SAR 25.8 bn
... A22: security discussed. Sources: SABIC FY2025 earnings release & integrated report, Tadawul disclosures.

Sheet Summary
A1: Summary — SABIC (Tadawul: 2010)
A2: Modestly undervalued at a cyclical trough; the petchem margin cycle is the swing.
A4: Lens / read | B4: Output (SAR) | C4: vs spot | D4: Takeaway
A5: DCF (mid-cycle, primary) | B5: =DCF!B26 | C5: =B5/Assumptions!$B$5-1 | D5: Anchor
A6: EV/EBITDA relative (blend) | B6: =Assumptions!$B$46*Assumptions!$B$45/(Assumptions!$B$6/1000)*0.93 | C6: =B6/Assumptions!$B$5-1 | D6: ≈ floor
A7: P/B (asset / replacement) | B7: =Assumptions!$B$8*Assumptions!$B$47 | C7: =B7/Assumptions!$B$5-1 | D7: Book anchor
A8: Dividend yield (normalized) | B8: =Assumptions!$B$48/Assumptions!$B$49 | C8: =B8/Assumptions!$B$5-1 | D8: Income anchor
A9: Weighted central (40/20/15/25) | B9: =0.40*B5+0.20*B6+0.15*B7+0.25*B8 | C9: =B9/Assumptions!$B$5-1 | D9: Modestly undervalued
A11: MONTE CARLO (3-month, from spot — value gap kept out of drift)
A12: Horizon | B12: p5 | C12: p25 | D12: p50 | E12: p75 | F12: p95
A13: T+20 | B13: 45.16 | C13: 49.46 | D13: 51.85 | E13: 54.26 | F13: 58.79
A14: T+60 | B14: 41.26 | C14: 47.42 | D14: 51.74 | E14: 56.35 | F14: 64.22
A16: P(above spot) T+60 50% · P(+10%) 22% vs P(−10%) 21% · median 51.7 (-0.1%)

Sheet Fundamental Valuation
A1: Fundamental valuation — five reads & weights
A2: Football-field inputs; primary = normalized DCF.
A4: Lens | B4: Bear | C4: Base | D4: Bull | E4: Weight
A5: DCF (mid-cycle, primary) | B5: 36.215239 | C5: =DCF!B26 | D5: 96.156877 | E5: 0.4
A6: EV/EBITDA relative | B6: 41.72 | C6: 47.833333 | D6: 51.333333 | E6: 0.2
A7: P/B (asset / replacement) | B7: 42.906667 | C7: 51.488 | D7: 57.924 | E7: 0.15
A8: Dividend yield (normalized) | B8: 51.666667 | C8: 56.363636 | D8: 62 | E8: 0.25
A9: Weighted central | B9: =SUMPRODUCT(B5:B8,E5:E8) | C9: =SUMPRODUCT(C5:C8,E5:E8) | D9: =SUMPRODUCT(D5:D8,E5:E8)

Sheet Assumptions
A1: Assumptions — the single blue-cell input layer
A2: Every downstream cell links here. Edit blue cells only.
A4: MARKET & SHARE DATA
A5: Spot price (SAR) | B5: 51.8
A6: Shares outstanding (mn) | B6: 3000
A7: Net debt (SAR bn; +debt / −cash) | B7: 0
A8: Book value / share 2025A (SAR) | B8: 42.9
A10: DCF — REVENUE & MARGIN
A11: 2025A revenue (SAR bn) | B11: 116.53
A12: Revenue growth 2026 | B12: 0.02
A13: Revenue growth 2027 | B13: 0.03
A14: Revenue growth 2028 | B14: 0.035
A15: Revenue growth 2029 | B15: 0.03
A16: Revenue growth 2030 | B16: 0.025
A17: EBITDA margin 2026 (start) | B17: 0.155
A18: EBITDA margin 2030 (mid-cycle) | B18: 0.19
A19: D&A 2026 (SAR bn) | B19: 12
A20: D&A 2027 (SAR bn) | B20: 12.3
A21: D&A 2028 (SAR bn) | B21: 12.6
A22: D&A 2029 (SAR bn) | B22: 12.9
... A33: Δ working capital 2030 (SAR bn) | B33: 0.6
A35: DISCOUNTING (Ke = rf + β·ERP)
A36: Risk-free rate (rf) | B36: 0.045
A37: Beta (0.8–1.3 band) | B37: 1.05
A38: Equity risk premium (ERP) | B38: 0.055
A39: Cost of equity Ke = rf + β·ERP | B39: =B36+B37*B38
A40: WACC (base) | B40: 0.0975
A41: Effective tax / Zakat rate | B41: 0.12
A42: Terminal growth g | B42: 0.025
A44: RELATIVE / DIVIDEND
A45: EV/EBITDA multiple (peer) | B45: 7
A46: Normalized mid-cycle EBITDA (SAR bn) | B46: 22
A47: P/B multiple (mid-cycle) | B47: 1.2
A48: Normalized DPS (SAR) | B48: 3.1
A49: Target dividend yield | B49: 0.055

Sheet Primary Lens (DCF)
A1: Primary lens — DCF bear/base/bull
A2: Same waterfall, three margin/discount scenarios. See DCF sheet for the full build.
A4: Scenario | B4: EV (SAR bn) | C4: Equity (SAR bn) | D4: Per share | E4: TV % of EV
A5: Bear | B5: 108.6 | C5: 108.6 | D5: 36.22 | E5: 0.69049043
A6: Base (=DCF sheet) | B6: =DCF!B22 | C6: =DCF!B25 | D6: =DCF!B26 | E6: =DCF!B23
A7: Bull | B7: 288.5 | C7: 288.5 | D7: 96.16 | E7: 0.80332537
A9: Swing (device A-1): the product–feedstock spread ($/t) drives the mid-cycle EBITDA margin (bear 16.5% → bull 21.0%). Sensitized in the Sensitivity sheet.

Sheet Segments
A1: Segments — SABIC business mix (indicative)
A2: SABIC does not disclose clean segment EBITDA splits → top-down (data-discipline gate).
A4: Segment | B4: % of revenue (approx) | C4: Note
A5: Petrochemicals & polymers | B5: ~70% | C5: Ethylene/PE/MEG/PP — core; margin = product-feedstock spread
A6: Agri-Nutrients (SABIC AN, listed) | B6: ~12% | C6: Urea/ammonia; supported by 2025 urea supply limits
A7: Specialties | B7: ~10% | C7: Engineering plastics retained post-ET divestiture
A8: Metals (Hadeed) — divested 2024 | B8: — | C8: Sold to PIF; removed from continuing ops
A9: Europe petchem / Americas ET — divesting | B9: — | C9: Held for sale; 2025 one-off writedowns SAR 15.2 bn

Sheet Relative & Normalized
A1: Relative & normalized — EV/EBITDA, P/B, dividend
A2: Peer multiples vs global petchem; normalized mid-cycle.
A4: Metric | B4: Value | C4: Implied SAR/sh | D4: Note
A5: EV/EBITDA multiple (peer) | B5: =Assumptions!$B$45 | C5: =17.88*B5/(Assumptions!$B$6/1000) | D5: trough EBITDA → floor
A6: EV/EBITDA on mid-cycle (22.0) | B6: =Assumptions!$B$45 | C6: =Assumptions!$B$46*B6/(Assumptions!$B$6/1000) | D6: normalized
A7: P/B multiple | B7: =Assumptions!$B$47 | C7: =Assumptions!$B$8*B7 | D7: BVPS 42.9; spot P/B 1.21x
A8: Dividend yield (normalized DPS 3.10) | B8: =Assumptions!$B$49 | C8: =Assumptions!$B$48/B8 | D8: income anchor; 5.8% yield at spot
A9: Normalized earnings → petchem-cycle framing | B9: see §1.4 | D9: Each cycle is finite; state cycle position (trough) not a single 'normalized EPS'

Sheet DCF
A1: DCF — normalized mid-cycle (primary lens)
A2: Full FCFF waterfall, 5-yr explicit. Every driver links to Assumptions. TV disclosed as % of EV.
A4: SAR bn | B4: 2026 | C4: 2027 | D4: 2028 | E4: 2029 | F4: 2030
A5: Revenue | B5: =Assumptions!$B$11*(1+Assumptions!$B$12) | C5: =B5*(1+Assumptions!$B$13) | D5: =C5*(1+Assumptions!$B$14) | E5: =D5*(1+Assumptions!$B$15) | F5: =E5*(1+Assumptions!$B$16) | G5: =F5*(1+Assumptions!$B$16)
A6: EBITDA margin | B6: =Assumptions!$B$17+(Assumptions!$B$18-Assumptions!$B$17)*1/5 | C6: =Assumptions!$B$17+(Assumptions!$B$18-Assumptions!$B$17)*2/5 | D6: =Assumptions!$B$17+(Assumptions!$B$18-Assumptions!$B$17)*3/5 | E6: =Assumptions!$B$17+(Assumptions!$B$18-Assumptions!$B$17)*4/5 | F6: =Assumptions!$B$17+(Assumptions!$B$18-Assumptions!$B$17)*5/5 | G6: =Assumptions!$B$17+(Assumptions!$B$18-Assumptions!$B$17)*5/5
A7: EBITDA | B7: =B5*B6 | C7: =C5*C6 | D7: =D5*D6 | E7: =E5*E6 | F7: =F5*F6
A8: less: D&A | B8: =-Assumptions!$B$19 | C8: =-Assumptions!$B$20 | D8: =-Assumptions!$B$21 | E8: =-Assumptions!$B$22 | F8: =-Assumptions!$B$23 | G8: =-Assumptions!$B$23
A9: EBIT | B9: =B7+B8 | C9: =C7+C8 | D9: =D7+D8 | E9: =E7+E8 | F9: =F7+F8
A10: NOPAT = EBIT×(1−t) | B10: =B9*(1-Assumptions!$B$41) | C10: =C9*(1-Assumptions!$B$41) | D10: =D9*(1-Assumptions!$B$41) | E10: =E9*(1-Assumptions!$B$41) | F10: =F9*(1-Assumptions!$B$41)
A11: add back: D&A | B11: =Assumptions!$B$19 | C11: =Assumptions!$B$20 | D11: =Assumptions!$B$21 | E11: =Assumptions!$B$22 | F11: =Assumptions!$B$23
A12: less: Capex | B12: =-Assumptions!$B$24 | C12: =-Assumptions!$B$25 | D12: =-Assumptions!$B$26 | E12: =-Assumptions!$B$27 | F12: =-Assumptions!$B$28
A13: less: Δ working capital | B13: =-Assumptions!$B$29 | C13: =-Assumptions!$B$30 | D13: =-Assumptions!$B$31 | E13: =-Assumptions!$B$32 | F13: =-Assumptions!$B$33
A14: Free cash flow to firm (FCFF) | B14: =B10+B11+B12+B13 | C14: =C10+C11+C12+C13 | D14: =D10+D11+D12+D13 | E14: =E10+E11+E12+E13 | F14: =F10+F11+F12+F13
A15: Discount factor @ WACC | B15: =1/(1+Assumptions!$B$40)^1 | C15: =1/(1+Assumptions!$B$40)^2 | D15: =1/(1+Assumptions!$B$40)^3 | E15: =1/(1+Assumptions!$B$40)^4 | F15: =1/(1+Assumptions!$B$40)^5 | G15: =1/(1+Assumptions!$B$40)^5
A16: PV of FCFF | B16: =B14*B15 | C16: =C14*C15 | D16: =D14*D15 | E16: =E14*E15 | F16: =F14*F15
A18: VALUATION BRIDGE
A19: Σ PV of explicit FCFF (2026–30) | B19: =SUM(B16:F16)
A20: Terminal value = FCFF₂₀₃₀×(1+g)/(WACC−g) | B20: =F14*(1+Assumptions!$B$42)/(Assumptions!$B$40-Assumptions!$B$42)
A21: PV of terminal value | B21: =B20*F15
A22: Enterprise value (EV) | B22: =B19+B21
A23: TV as % of EV | B23: =B21/B22
A24: less: net debt | B24: =-Assumptions!$B$7
A25: Equity value | B25: =B22+B24
A26: Per share (SAR) | B26: =B25/(Assumptions!$B$6/1000)
A27: vs spot | B27: =B26/Assumptions!$B$5-1
A28: Note: high-terminal DCF (device A-7) — TV≈75% of EV; sensitized on the WACC × g grid (Sensitivity) and the margin × EV/EBITDA grid.

Sheet Income Statement
A1: Income statement — 3y historical + 5y forecast (SAR bn)
A2: Historicals on continuing/adjusted basis; forecast links to DCF drivers. Source: SABIC FY23–25 disclosures.
A4: SAR bn | B4: 2023A | C4: 2024A | D4: 2025A | E4: 2026E | F4: 2027E | G4: 2028E | H4: 2029E | I4: 2030E
A5: Revenue | B5: 141.9 | C5: 117.74 | D5: 116.53 | E5: =DCF!B5 | F5: =DCF!C5 | G5: =DCF!D5 | H5: =DCF!E5 | I5: =DCF!F5 | J5: =DCF!G5
A6: EBITDA (adjusted) | B6: 17.4 | C6: 21 | D6: 17.88 | E6: =DCF!B7 | F6: =DCF!C7 | G6: =DCF!D7 | H6: =DCF!E7 | I6: =DCF!F7 | J6: =DCF!G7
A7: EBITDA margin | B7: =B6/B5 | C7: =C6/C5 | D7: =D6/D5 | E7: =E6/E5 | F7: =F6/F5 | G7: =G6/G5 | H7: =H6/H5 | I7: =I6/I5
A8: less: D&A | B8: -13.7 | C8: -11.6 | D8: -12.1 | E8: =DCF!B8 | F8: =DCF!C8 | G8: =DCF!D8 | H8: =DCF!E8 | I8: =DCF!F8 | J8: =DCF!G8
A9: EBIT | B9: =B6+B8 | C9: =C6+C8 | D9: =D6+D8 | E9: =E6+E8 | F9: =F6+F8 | G9: =G6+G8 | H9: =H6+H8 | I9: =I6+I8
A10: Net income (reported, attrib.) | B10: -2.77 | C10: 1.54 | D10: -25.78
A11: Net income (adjusted) | C11: 5.88 | D11: 2.07 | E11: =DCF!B10 | F11: =DCF!C10 | G11: =DCF!D10 | H11: =DCF!E10 | I11: =DCF!F10 | J11: =J9*(1-Assumptions!$B$41)
A12: 2025 reported net loss (SAR −25.8 bn) reflects one-off non-cash writedowns on European petchem / ET divestitures; adjusted basis used for the cycle.

Sheet Balance Sheet
A1: Balance sheet — key lines, 3y historical + 5y forecast (SAR bn)
A2: Source: SABIC FY23–25. Net-cash-to-neutral balance sheet; A+/A1 rated.
A4: SAR bn | B4: 2023A | C4: 2024A | D4: 2025A | E4: 2026E | F4: 2027E | G4: 2028E | H4: 2029E | I4: 2030E
A5: Total assets | B5: 294.38 | C5: 277.54 | D5: 244.29 | E5: 250 | F5: 258 | G5: 266 | H5: 274 | I5: 282
A6: of which PP&E (approx) | B6: 150 | C6: 145 | D6: 140 | E6: 138 | F6: 137 | G6: 136 | H6: 136 | I6: 136
A7: Total liabilities | B7: 99.1 | C7: 94.1 | D7: 89.47 | E7: 88 | F7: 88 | G7: 89 | H7: 90 | I7: 91
A8: Total debt (borrowings+leases) | B8: 35 | C8: 34 | D8: 33.8 | E8: 33 | F8: 33 | G8: 33 | H8: 33 | I8: 33
A9: Cash + short-term investments | B9: 43.8 | C9: 40 | D9: 38 | E9: 40 | F9: 44 | G9: 50 | H9: 57 | I9: 64
A10: Net debt (+)/ net cash (−) | B10: -8.76 | C10: -6 | D10: 0 | E10: -7 | F10: -11 | G10: -17 | H10: -24 | I10: -31
A11: Equity (attrib. to Parent) | B11: 167.43 | C11: 156.36 | D11: 128.72 | E11: 131 | F11: 135 | G11: 141 | H11: 148 | I11: 157
A13: Forward cash build assumes dividend ≈ FCF with modest net-cash accumulation as mid-cycle FCF recovers; illustrative, flagged estimate.

Sheet Cash Flow
A1: Cash flow — 3y historical + 5y forecast (SAR bn)
A2: Forecast FCFF links to DCF. Source: SABIC FY23–25.
A4: SAR bn | B4: 2023A | C4: 2024A | D4: 2025A | E4: 2026E | F4: 2027E | G4: 2028E | H4: 2029E | I4: 2030E
A5: Cash from operations | B5: 24.45 | C5: 16.36 | D5: 15.96 | E5: =DCF!B10+DCF!B11+DCF!B13 | F5: =DCF!C10+DCF!C11+DCF!C13 | G5: =DCF!D10+DCF!D11+DCF!D13 | H5: =DCF!E10+DCF!E11+DCF!E13 | I5: =DCF!F10+DCF!F11+DCF!F13 | J5: =DCF!G10+DCF!G11-DCF!G13
A6: less: Capex | B6: -11.76 | C6: -7.99 | D6: -7.72 | E6: =DCF!B12 | F6: =DCF!C12 | G6: =DCF!D12 | H6: =DCF!E12 | I6: =DCF!F12 | J6: =DCF!G12
A7: Free cash flow | B7: =B5+B6 | C7: =C5+C6 | D7: =D5+D6 | E7: =E5+E6 | F7: =F5+F6 | G7: =G5+G6 | H7: =H5+H6 | I7: =I5+I6
A8: Dividends paid | B8: -9.6 | C8: -10.2 | D8: -9 | E8: -9.3 | F8: -9.3 | G8: -9.6 | H8: -9.9 | I8: -9.9

Sheet Summary Financials
A1: Summary financials — every cell links to the statement sheets
A4: SAR bn | B4: 2023A | C4: 2024A | D4: 2025A | E4: 2026E | F4: 2027E | G4: 2028E | H4: 2029E | I4: 2030E
A5: Revenue | B5: ='Income Statement'!B5 | C5: ='Income Statement'!C5 | D5: ='Income Statement'!D5 | E5: ='Income Statement'!E5 | F5: ='Income Statement'!F5 | G5: ='Income Statement'!G5 | H5: ='Income Statement'!H5 | I5: ='Income Statement'!I5
A6: EBITDA (adj) | B6: ='Income Statement'!B6 | C6: ='Income Statement'!C6 | D6: ='Income Statement'!D6 | E6: ='Income Statement'!E6 | F6: ='Income Statement'!F6 | G6: ='Income Statement'!G6 | H6: ='Income Statement'!H6 | I6: ='Income Statement'!I6
A7: EBIT | B7: ='Income Statement'!B9 | C7: ='Income Statement'!C9 | D7: ='Income Statement'!D9 | E7: ='Income Statement'!E9 | F7: ='Income Statement'!F9 | G7: ='Income Statement'!G9 | H7: ='Income Statement'!H9 | I7: ='Income Statement'!I9
A8: Net income (adj) | B8: ='Income Statement'!B11 | C8: ='Income Statement'!C11 | D8: ='Income Statement'!D11 | E8: ='Income Statement'!E11 | F8: ='Income Statement'!F11 | G8: ='Income Statement'!G11 | H8: ='Income Statement'!H11 | I8: ='Income Statement'!I11
A9: Free cash flow | B9: ='Cash Flow'!B7 | C9: ='Cash Flow'!C7 | D9: ='Cash Flow'!D7 | E9: ='Cash Flow'!E7 | F9: ='Cash Flow'!F7 | G9: ='Cash Flow'!G7 | H9: ='Cash Flow'!H7 | I9: ='Cash Flow'!I7
A10: Equity (Parent) | B10: ='Balance Sheet'!B11 | C10: ='Balance Sheet'!C11 | D10: ='Balance Sheet'!D11 | E10: ='Balance Sheet'!E11 | F10: ='Balance Sheet'!F11 | G10: ='Balance Sheet'!G11 | H10: ='Balance Sheet'!H11 | I10: ='Balance Sheet'!I11

Sheet Monte Carlo
A1: Monte Carlo — YZ-HAR engine, 50,000 paths, seed 42
A2: Zero drift (international); unit-variance t7; 16-factor overlay. Presentation-only prob read.
A4: Probability read (T+60) | B4: Value
A5: P(above spot) | B5: 49.6%
A6: P(+10%) vs P(−10%) | B6: 22.3% vs 21.2%
A7: Odds ratio (up:down 10%) | B7: 1.05 : 1
A8: Median level / move | B8: 51.74 (-0.1%)
A9: 50% band (25–75) | B9: 47.42 – 56.35
A10: Touch +10% / −10% | B10: 39% / 36%
A12: Percentile map (SAR) | B12: p5 | C12: p25 | D12: p50 | E12: p75 | F12: p95
A13: T+20 | B13: 45.16 | C13: 49.46 | D13: 51.85 | E13: 54.26 | F13: 58.79
A14: T+60 | B14: 41.26 | C14: 47.42 | D14: 51.74 | E14: 56.35 | F14: 64.22
A16: Diffusion vol (annualized, YZ-HAR): 19.3%. Step 0 CRPS skill +0.28% vs zero-drift RW benchmark (marginal pass); see Peer & Sector / Appendix B.

Sheet Sensitivity
A1: Sensitivity — DCF fair value (SAR/sh)
A2: WACC × terminal g, and mid-cycle EBITDA margin × EV/EBITDA (the real-unit swing).
A4: WACC (rows) × terminal g (cols)
A5: WACC \ g | B5: 1.5% | C5: 2.0% | D5: 2.5% | E5: 3.0% | F5: 3.5%
A6: 8.75% | B6: 62.4 | C6: 66.1 | D6: 70.4 | E6: 75.5 | F6: 81.5
A7: 9.25% | B7: 58.1 | C7: 61.3 | D7: 65 | E7: 69.2 | F7: 74.2
A8: 9.75% | B8: 54.4 | C8: 57.1 | D8: 60.3 | E8: 63.9 | F8: 68
A9: 10.25% | B9: 51.1 | C9: 53.5 | D9: 56.2 | E9: 59.3 | F9: 62.8
A10: 10.75% | B10: 48.1 | C10: 50.2 | D10: 52.6 | E10: 55.2 | F10: 58.3
A12: Mid-cycle EBITDA margin (rows) × EV/EBITDA (cols) — device A-1 swing in real units
A13: margin \ x | B13: 6.0x | C13: 6.5x | D13: 7.0x | E13: 7.5x | F13: 8.0x
A14: 16.0% | B14: 42.8 | C14: 46.4 | D14: 50 | E14: 53.5 | F14: 57.1
A15: 17.5% | B15: 46.8 | C15: 50.7 | D15: 54.6 | E15: 58.5 | F15: 62.4
A16: 19.0% | B16: 50.8 | C16: 55.1 | D16: 59.3 | E16: 63.6 | F16: 67.8
A17: 20.5% | B17: 54.9 | C17: 59.4 | D17: 64 | E17: 68.6 | F17: 73.1
A18: 22.0% | B18: 58.9 | C18: 63.8 | D18: 68.7 | E18: 73.6 | F18: 78.5

Sheet Per-Share & Ratios
A1: Per-share & ratios dashboard
A2: Fixed panel (the 'Data Miner'). Source: SABIC FY23–25 + model.
A4: Metric | B4: 2023A | C4: 2024A | D4: 2025A | E4: At spot / fwd
A5: EPS reported (SAR) | B5: -0.92 | C5: 0.51 | D5: -8.59
A6: EPS adjusted (SAR) | C6: 1.96 | D6: 0.69
A7: DPS (SAR) | B7: 3.2 | C7: 3.4 | D7: 3
A8: BVPS (SAR) | B8: 55.8 | C8: 52.1 | D8: 42.9
A9: Dividend yield @ spot
A10: P/B @ spot
A11: EV/EBITDA (2025A adj)
A12: EBITDA margin (%) | B12: 0.123 | C12: 0.178 | D12: 0.153
A13: FCF (SAR bn) | C13: 6.15 | D13: 7.2
A14: Net debt / EBITDA

Sheet Peer & Sector
A1: Peer set, sector structure & Step 0 calibration
A2: Global petchem peers + backtest result.
A4: Peer | B4: Market | C4: EV/EBITDA (indic.) | D4: Note
A5: SABIC | B5: Tadawul | C5: ~8.4x (2025A adj) | D5: Aramco-owned 70%; net cash; A+/A1
A6: Dow | B6: NYSE | C6: ~7–8x | D6: US integrated
A7: LyondellBasell | B7: NYSE | C7: ~6–7x | D7: PO/PE
A8: Westlake | B8: NYSE | C8: ~6–7x | D8: PVC/PE
A9: Formosa Plastics | B9: TWSE | C9: ~7–9x | D9: Asia integrated
A10: SABIC Agri-Nutrients | B10: Tadawul | C10: listed sub | D10: urea/ammonia
A13: STEP 0 — CALIBRATION BACKTEST (5-yr, h=60, zero-drift international)
A14: Origins scored (step 3, block-bootstrap) | B14: 346
A15: CRPS skill (1−engine/benchmark) | B15: +0.28% (marginal pass; 90% CI straddles 0)
A16: Interval coverage 50/80/90 | B16: 0.41 / 0.80 / 0.91
A17: PIT mean / std | B17: 0.35 / 0.26 (left-tilt = secular decline, shared with benchmark)
A18: Recalibration applied | B18: t5 → t7 (AAPL calibration-panel fix)
A19: Verdict | B19: PASS (marginal) — width & shape beat the RW benchmark
