Workbook

Sheet READ FIRST
A1: Testahil · Independent Valuation Study — Silver (XAG/USD)
A2: Combined 1 / 3 / 12-month edition · educational analysis · not investment advice
A4: • This workbook is an educational valuation model, not investment advice, and not a recommendation to buy, sell or hold silver or any related instrument.
A5: • The preparer is not licensed by any securities or commodities regulator, manages no money, and accepts no clients or fees.
A6: • A commodity has no income statement, balance sheet or cash flows, so the company-style sheets of the standard template are a justified N/A here and are replaced by their metal analogues: Fair-Value Anchors, the Gold-Silver Ratio, and the Silver Balance (supply/demand) sheet, which is the metal's 'financial statements'.
A7: • The Assumptions sheet is the single blue-cell input layer. Every downstream figure links to it, so changing one input (spot, gold, a target ratio, the deficit) reprices the whole model.
A8: • Blue = input; black = formula; green = link from another sheet.
A9: • Monte Carlo percentiles are computed by the YZ-HAR engine (mc_v2.py, 50,000 paths, seed 42) and pasted as values on the Monte Carlo sheet, with the engine parameters documented on Assumptions.
A10: • All figures are model outputs presented as ranges and distributions. Sources: World Silver Survey 2026 (Silver Institute / Metals Focus), LBMA, published analyst research, exchange data.
A11: • The preparer may hold, and may in the future take or dispose of, a position in the instrument discussed.

Sheet Summary
A1: Summary — every read at a glance (1 / 3 / 12 month)
A3: Read | B3: 1 month | C3: 3 months | D3: 12 months
A4: MC median | B4: ='Monte Carlo'!D4 | C4: ='Monte Carlo'!D5 | D4: ='Monte Carlo'!D6
A5: MC 5th percentile | B5: ='Monte Carlo'!B4 | C5: ='Monte Carlo'!B5 | D5: ='Monte Carlo'!B6
A6: MC 95th percentile | B6: ='Monte Carlo'!F4 | C6: ='Monte Carlo'!F5 | D6: ='Monte Carlo'!F6
A7: Spot | B7: =Assumptions!$B$4
A8: Gold-silver ratio | B8: =Assumptions!$B$5/Assumptions!$B$4
A9: Fair-value zone | B9: =Assumptions!$B$30 | C9: =Assumptions!$B$31 | D9: =Assumptions!$B$32
A11: Fundamental fair value neither cheap nor dear; MC centred near spot near-term, tilting up over 12m.

Sheet Fundamental Valuation
A1: Fundamental Valuation — anchor synthesis
A3: Anchor | B3: Weight | C3: Contribution
A4: Gold-silver ratio (neutral) | B4: 0.35 | C4: ='Fair-Value Anchors'!B5
A5: Analyst consensus (median) | B5: 0.25 | C5: ='Fair-Value Anchors'!B8
A6: Supply/demand deficit | B6: 0.2 | C6: 60
A7: Real-rate carry | B7: 0.12 | C7: — (tilt)
A8: Cost floor | B8: 0.08 | C8: ='Fair-Value Anchors'!B10
A9: Weighted fair-value centre | B9: =SUM(B4:B8) | C9: =Assumptions!$B$31

Sheet Assumptions
A1: Assumptions — single input layer (blue = input)
A3: Input | B3: Value | C3: Source / note
A4: Spot silver (US$/oz) | B4: 62.425 | C4: 03 Jul 2026 close, attached history
A5: Gold spot (US$/oz) | B5: 4020 | C5: current level (Q2-26), for the ratio
A6: — Gold-silver ratio anchors —
A7: Bull-compression ratio | B7: 50 | C7: BofA/Citi thesis
A8: Long-run average ratio | B8: 62 | C8: multi-decade neutral
A9: 2-year average ratio | B9: 80 | C9: recent window / UBS drift-to
A10: — Consensus targets (2026) — | C10: set when silver traded $78–90
A11: Consensus low (World Bank) | B11: 70
A12: Consensus median (Reuters) | B12: 79.5 | C12: 30-analyst poll
A13: Consensus high (Citi) | B13: 110 | C13: acute-shortage thesis
A14: — Supply / demand (Moz) — | C14: WSS 2026
A15: 2026e total demand | B15: 1116
A16: 2026e mine supply | B16: 850 | C16: ~70% by-product
A17: 2026e recycling | B17: 196 | C17: 13-yr high
A18: 2026e PV/solar demand | B18: 151 | C18: −19% YoY (thrifting)
A19: Cumulative deficit since 2021 | B19: 808
A20: — Cost & carry —
A21: Primary AISC low (US$/oz) | B21: 25
A22: Primary AISC high (US$/oz) | B22: 31
A23: — Monte Carlo engine — | C23: mc_v2.py YZ-HAR
A24: Forward vol, 3-month (ann) | B24: 0.474 | C24: YZ-HAR, Step-0 validated
A25: Forward vol, 12-month (ann) | B25: 0.443 | C25: YZ-HAR
A26: Net factor drift, 3-month | B26: 0.017 | C26: near-flat
A27: Net factor drift, 12-month | B27: 0.07 | C27: deficit + 2027 easing
A28: Paths / seed | B28: 50000 | C28: seed 42
A29: — Fair-value zone — | C29: synthesis (§1.5)
A30: Fair-value low | B30: 58
A31: Fair-value centre | B31: 68
A32: Fair-value high | B32: 78

Sheet Fair-Value Anchors
A1: Fair-Value Anchors — five lenses (links to Assumptions)
A3: Anchor / scenario | B3: Implied silver | C3: Basis | D3: Note
A4: Gold-silver ratio @ bull 50× | B4: =Assumptions!$B$5/Assumptions!$B$7 | C4: gold ÷ ratio | D4: silver re-rated vs gold
A5: Gold-silver ratio @ long-run 62× | B5: =Assumptions!$B$5/Assumptions!$B$8 | C5: gold ÷ ratio | D5: neutral anchor ≈ spot
A6: Gold-silver ratio @ 2y-avg 80× | B6: =Assumptions!$B$5/Assumptions!$B$9 | C6: gold ÷ ratio | D6: silver lags gold
A7: Consensus — low | B7: =Assumptions!$B$11 | C7: 2026 target | D7: World Bank / cautious
A8: Consensus — median | B8: =Assumptions!$B$12 | C8: 2026 target | D8: Reuters 30-analyst
A9: Consensus — high | B9: =Assumptions!$B$13 | C9: 2026 target | D9: Citi acute-shortage
A10: Cost floor — AISC low | B10: =Assumptions!$B$21 | C10: marginal cost | D10: non-binding
A11: Cost floor — AISC high | B11: =Assumptions!$B$22 | C11: marginal cost | D11: deep-bear boundary
A12: Weighted fair-value zone | B12: =Assumptions!$B$30&" – "&Assumptions!$B$32 | C12: synthesis | D12: centre = fair-value centre input

Sheet Gold-Silver Ratio
A1: Gold-Silver Ratio — silver’s primary lens
A3: Item | B3: Value | C3: Note
A4: Current ratio (gold ÷ silver) | B4: =Assumptions!$B$5/Assumptions!$B$4 | C4: live from Assumptions
A5: Long-run average | B5: 62 | C5: neutral anchor
A6: 2-year average | B6: 80 | C6: silver cheap on this window
A7: April 2025 peak | B7: 107 | C7: silver historically cheapest
A8: December 2025 trough | B8: 55 | C8: silver historically dearest
A9: Implied silver @ current gold, long-run ratio | B9: =Assumptions!$B$5/62 | C9: the neutral fair value
A10: Implied silver if gold $4,600 @ 60× | B10: =4600/60 | C10: gold reversion drags silver up

Sheet Silver Balance
A1: Silver Balance — the commodity’s financial statements (Moz)
A2: World Silver Survey 2026 (Silver Institute / Metals Focus). 3 years historical + current-year forecast.
A3: Line (Moz) | B3: 2024 | C3: 2025 | D3: 2026e
A4: Mine production | B4: 820 | C4: 819 | D4: 850
A5: Recycling | B5: 193 | C5: 198 | D5: 196
A6: Total supply | B6: =B4+B5 | C6: =C4+C5 | D6: =D4+D5
A7: Industrial (total) | B7: 681 | C7: 657 | D7: 640
A8: of which photovoltaics | B8: 198 | C8: 187 | D8: 151
A9: Investment | B9: 168 | C9: 169 | D9: 171
A10: Jewellery | B10: 203 | C10: 196 | D10: 178
A11: Silverware + other | B11: 110 | C11: 113 | D11: 127
A12: Total demand | B12: =B7+B9+B10+B11 | C12: =C7+C9+C10+C11 | D12: =D7+D9+D10+D11
A13: Balance (deficit) | B13: =B6-B12 | C13: =C6-C12 | D13: =D6-D12
A15: Cumulative deficit since 2021 (Moz) | B15: =Assumptions!$B$19

Sheet Demand Segments
A1: Demand Segments — silver’s dual identity
A3: Segment | B3: Share | C3: 2026e (Moz) | D3: Driver
A4: Industrial ex-PV | B4: ~44% | C4: =('Silver Balance'!D7-'Silver Balance'!D8) | D4: electronics, EVs, AI/data-centre
A5: Solar / photovoltaics | B5: ~14% | C5: ='Silver Balance'!D8 | D5: THE swing — thrifting (grams/watt)
A6: Investment | B6: ~25% | C6: ='Silver Balance'!D9 | D6: price-sensitive; the mania’s marginal buyer
A7: Jewellery | B7: ~16% | C7: ='Silver Balance'!D10 | D7: falling on high prices
A8: Silverware + other | B8: ~11% | C8: ='Silver Balance'!D11 | D8: multi-year lows

Sheet Technical
A1: Technical indicators
A2: Computed from XAG/USD daily history to 03 Jul 2026
A3: Indicator | B3: Reading | C3: Signal
A4: Close | B4: 62.425 | C4: —
A5: SMA 20 | B5: 63.15 | C5: price -12.1% vs SMA50
A6: SMA 50 | B6: 71.04 | C6: declining
A7: SMA 100 | B7: 74.78
A8: SMA 200 | B8: 70.33 | C8: price -11.2% vs SMA200
A9: MACD line | B9: -3.373 | C9: negative
A10: MACD signal | B10: -3.671
A11: MACD histogram | B11: 0.298 | C11: just turned up
A12: RSI-14 | B12: 43.6 | C12: neutral, off oversold
A13: ATR-14 | B13: 3.484 | C13: 5.6% — wide range
A14: 52-week high | B14: 116.61 | C14: intraday ATH ~$121–122
A15: 52-week low | B15: 36.77

Sheet Monte Carlo
A1: Monte Carlo — YZ-HAR engine, 50k paths, seed 42 (percentiles pasted as values)
A2: Width: gap-aware Yang-Zhang + log-HAR. Shape: Student-t(5). Diffusion drift OFF; +7%/12-mo factor tilt.
A3: Horizon | B3: p5 | C3: p25 | D3: p50 | E3: p75 | F3: p95 | G3: mean
A4: T+21 (1 month) | B4: 49.85 | C4: 57.82 | D4: 62.77 | E4: 68.21 | F4: 78.95 | G4: 63.44
A5: T+63 (3 months) | B5: 43.8 | C5: 55.64 | D5: 63.46 | E5: 72.49 | F5: 91.79 | G5: 65.3
A6: T+252 (12 months) | B6: 33.52 | C6: 52.1 | D6: 66.83 | E6: 85.72 | F6: 134.67 | G6: 74.34
A8: Engine parameters
A9: Forward vol 3m (ann) | B9: =Assumptions!$B$24
A10: Forward vol 12m (ann) | B10: =Assumptions!$B$25
A11: Net drift 3m | B11: =Assumptions!$B$26
A12: Net drift 12m | B12: =Assumptions!$B$27
A14: Zone vs spot | B14: T+63 | C14: T+252
A15: < -20% | B15: 0.124 | C15: 0.218
A16: -20..-10% | B16: 0.142 | C16: 0.1
A17: -10..-5% | B17: 0.097 | C17: 0.054
A18: -5..+5% | B18: 0.204 | C18: 0.107
A19: +5..+10% | B19: 0.09 | C19: 0.052
A20: +10..+20% | B20: 0.141 | C20: 0.094
A21: > +20% | B21: 0.203 | C21: 0.376
A23: Touch level | B23: T+63 | C23: T+252
A24: $85 | B24: 0.148 | C24: 0.448
A25: $78 | B25: 0.271 | C25: 0.579
A26: $72 | B26: 0.459 | C26: 0.718
A27: $68 | B27: 0.637 | C27: 0.822
A28: $55 | B28: 0.449 | C28: 0.649
A29: $50 | B29: 0.232 | C29: 0.465
A30: $45 | B30: 0.11 | C30: 0.316
A31: $40 | B31: 0.049 | C31: 0.201

Sheet Sensitivity
A1: Sensitivity — silver fair value = gold ÷ ratio (US$/oz)
A2: Rows: gold-silver ratio. Columns: gold price. Live formulas.
A3: ratio \ gold | B3: 3500 | C3: 3800 | D3: 4020 | E3: 4300 | F3: 4600 | G3: 5000
A4: 50 | B4: =B$3/$A4 | C4: =C$3/$A4 | D4: =D$3/$A4 | E4: =E$3/$A4 | F4: =F$3/$A4 | G4: =G$3/$A4
A5: 55 | B5: =B$3/$A5 | C5: =C$3/$A5 | D5: =D$3/$A5 | E5: =E$3/$A5 | F5: =F$3/$A5 | G5: =G$3/$A5
A6: 62 | B6: =B$3/$A6 | C6: =C$3/$A6 | D6: =D$3/$A6 | E6: =E$3/$A6 | F6: =F$3/$A6 | G6: =G$3/$A6
A7: 70 | B7: =B$3/$A7 | C7: =C$3/$A7 | D7: =D$3/$A7 | E7: =E$3/$A7 | F7: =F$3/$A7 | G7: =G$3/$A7
A8: 80 | B8: =B$3/$A8 | C8: =C$3/$A8 | D8: =D$3/$A8 | E8: =E$3/$A8 | F8: =F$3/$A8 | G8: =G$3/$A8
A9: 90 | B9: =B$3/$A9 | C9: =C$3/$A9 | D9: =D$3/$A9 | E9: =E$3/$A9 | F9: =F$3/$A9 | G9: =G$3/$A9
A11: Today: gold ~$4,020, ratio ~64× → silver ≈ spot. Upside is a joint move (gold up + ratio compressing).

Sheet Step 0 Calibration
A1: Step 0 — calibration backtest (gate: CRPS skill > 0)
A2: Rolling h=60 backtest, YZ-HAR engine, diffusion drift OFF, scored vs a zero-drift random-walk cone.
A3: Metric | B3: Result
A4: CRPS skill vs RW (non-overlap, mean across phasings) | B4: +0.0153 (pass, >0)
A5: CRPS skill (dense origins, n=1,072) | B5: +0.0150 · 95% CI [+0.002, +0.025]
A6: Fraction of phasings with skill > 0 | B6: 93%
A7: Winkler interval skill (90% PI) | B7: +0.067
A8: Coverage 50 / 80 / 90% (diagnostic) | B8: 0.50 / 0.83 / 0.89
A9: PIT mean / std (diagnostic) | B9: 0.60 / 0.29 (mild right-skew)
A10: Secular-drift test | B10: drift degrades skill (0.0150→0.0071) — zero-drift confirmed
A11: Sample span | B11: 2021-01-01 to 2026-07-03 (origins to 2026-04-13)
A12: Verdict | B12: PASS — engine beats the benchmark; proceed

Sheet Peer & Sector
A1: Peer & Sector — the investable silver complex
A3: Cohort | B3: Names | C3: Character
A4: Primary miners | B4: Fresnillo, Pan American, Hecla, First Majestic, Endeavour | C4: levered to spot; AISC ~$25–31
A5: Diversified / by-product | B5: Glencore, BHP, Newmont, KGHM | C5: silver a minor by-product
A6: Streamers / royalty | B6: Wheaton, Franco-Nevada | C6: fixed-cost streams; lower risk
A7: Physical ETFs | B7: SLV, SIVR, PSLV | C7: direct bullion
A8: Silver (this study) | B8: — | C8: the metal itself — no leverage, no counterparty

Sheet Sources
A1: Sources & about
A3: • World Silver Survey 2026 — Silver Institute / Metals Focus (15 April 2026): supply/demand balance, deficit, PV.
A4: • LBMA precious-metals forecasts and the gold-silver ratio history.
A5: • Published analyst research (Reuters poll, J.P. Morgan, BofA, Citi, UBS, ING, World Bank) for the consensus anchor.
A6: • Company reports for primary-producer AISC (Endeavour, Pan American, Hecla, First Majestic).
A7: • Attached XAG/USD daily OHLC history (01 Jan 2021 – 03 Jul 2026) for technicals and the Monte Carlo engine.
A8: • Monte Carlo: mc_v2.py YZ-HAR engine (gap-aware Yang-Zhang variance + log-HAR; Student-t(5); 50,000 paths, seed 42).
A9: • Educational analysis under the Testahil brand. Not investment advice. The preparer may hold a position.
