Workbook

Sheet READ FIRST
A1: Testahil · Independent Valuation Study — Educational Analysis · Platinum (XPT/USD) · Not investment advice
A2: Combined 1 / 3 / 12-month edition · anchor 20 Jul 2026 close $1,608.37/oz
A3: • This workbook is an educational valuation exercise and an expression of personal analytical opinion — not investment advice, not a recommendation, not directed at any reader's objectives or needs.
A4: • The preparer is not licensed by any securities or commodities regulator, provides no consultancy, manages no money, solicits no funds and accepts no clients.
A5: • A commodity has no income statement, balance sheet, cash-flow statement, per-share metrics or WACC, so the standard template's company sheets are a justified N/A here; their metal analogues are the Platinum Balance, Supply & Cost Curve and Demand Segments sheets.
A6: • The Assumptions sheet is the single input layer: blue = input; black = formula; green = cross-sheet link. Change an input and the linked sheets recalculate.
A7: • Monte Carlo percentiles are computed engine outputs (mc_v3 carry-anchored YZ-HAR-t: 50,000 paths, seed 42, ν = Gaussian, width_cal = 0.853 — a PROVISIONAL single-instrument self-fit, flagged) pasted as values and labelled as such; they are not spreadsheet formulas.
A8: • Step 0 verdict is PARITY under the scale-normalized carry-anchored gate — the engine ties, and does not beat, the carry-anchored random walk on platinum's history; metals remain the weakest calibration in the system (gold self-fit; silver borrows gold's).
A9: • All figures are model outputs presented as ranges and probability distributions; no single number is a forecast or a price target.
A10: • The preparer may hold, and may in the future take or dispose of, a position in the instrument discussed.

Sheet Summary
A1: Summary — every read at a glance (US$/oz)
A2: Read | B2: 1 month | C2: 3 months | D2: 12 months | E2: Note
A3: MC median (predicted) | B3: ='Monte Carlo'!D4 -> 1613.09 | C3: ='Monte Carlo'!D5 -> 1624.63 | D3: ='Monte Carlo'!D6 -> 1668.58
A4: MC p5 | B4: ='Monte Carlo'!B4 -> 1376.57 | C4: ='Monte Carlo'!B5 -> 1228.74 | D4: ='Monte Carlo'!B6 -> 961.14
A5: MC p95 | B5: ='Monte Carlo'!F4 -> 1890.7 | C5: ='Monte Carlo'!F5 -> 2152.39 | D5: ='Monte Carlo'!F6 -> 2896.85
A6: Spot | B6: =Assumptions!$B$3 -> 1608.37
A7: Pt/Au ratio | B7: =Assumptions!$B$3/Assumptions!$B$4 -> 0.40492699
A8: Pt/Pd ratio | B8: =Assumptions!$B$3/Assumptions!$B$5 -> 1.2981195
A9: Fair-value zone (lo / centre / hi) | B9: =Assumptions!$B$28 -> 1310 | C9: =Assumptions!$B$29 -> 1634.33 | D9: =Assumptions!$B$30 -> 2138.6
A10: Verdict | B10: Fairly valued — spot ~1.6% below the weighted centre; two-sided cone; 12-mo drift = carry only

Sheet Fundamental Valuation
A1: Fundamental Valuation — anchor synthesis (fair value NOW, undated)
A2: Anchor | B2: Weight | C2: Base (US$/oz) | D2: Note
A3: Pt/Au ratio (5y mean × gold) | B3: 0.3 | C3: ='Fair-Value Anchors'!B5 -> 1831.092 | D3: primary relative lens; still cheap vs gold
A4: Analyst consensus (fresh vintage) | B4: 0.3 | C4: ='Fair-Value Anchors'!B8 -> 1750 | D4: UBS 1,700–1,800; stale 2,222 excluded from base
A5: Supply/demand balance | B5: 0.2 | C5: 1500 | D5: floor-builder: 4th deficit, 11 weeks cover
A6: Cost curve (AISC + margin) | B6: 0.2 | C6: 1300 | D6: AISC 1,006; incentive 2,300–2,500
A7: Real-rate carry | B7: 0 | C7: — (tilt) | D7: timing switch, not a level
A8: Weighted fair-value centre | B8: =SUM(B3:B7) -> 1 | C8: =SUMPRODUCT(B3:B6,C3:C6) -> 1634.3276 | D8: ties to Assumptions zone centre (rounding)

Sheet Assumptions
A1: Assumptions — single input layer (blue = input)
A2: Input | B2: Value | C2: Source / note
A3: Spot platinum (US$/oz) | B3: 1608.37 | C3: 20 Jul 2026 close, attached daily history (post data-quality gate)
A4: Gold spot (US$/oz) | B4: 3972 | C4: Fri 17 Jul 2026 close — one-session mismatch vs the Mon 20 Jul anchor, stated; 20-Jul vendor prints ~4,000–4,030 → centre +0.3%
A5: Palladium spot (US$/oz) | B5: 1239 | C5: spot 17 Jul 2026
A6: — Pt/Au ratio anchors — | C6: attached 2011–26 series; post-2016 = modern regime
A7: 2-year average ratio | B7: 0.3883 | C7: recent regime — maps to ~spot
A8: 5-year average ratio | B8: 0.461 | C8: the mean-reversion case
A9: Post-2016 average ratio | B9: 0.5697 | C9: full modern regime — bull anchor
A10: — Consensus targets — | C10: two vintages, $500 apart
A11: UBS end-2026 | B11: 1700 | C11: 29 Jun 2026, post-crash (spot $1,618)
A12: UBS mid-2027 | B12: 1800 | C12: 29 Jun 2026
A13: LBMA 2026 survey average | B13: 2222 | C13: 20 Jan 2026 — set at the record; stale-high
A14: Valterra LT planning low | B14: 2300 | C14: Feb 2026 — greenfield incentive, excluded from base
A15: Valterra LT planning high | B15: 2500 | C15: Feb 2026
A16: — Supply / demand (koz, WPIC Q1-26) — | C16: WPIC Platinum Quarterly, 18 May 2026 (Metals Focus)
A17: 2026f total supply | B17: 7377 | C17: +2% YoY
A18: 2026f mine supply | B18: 5551 | C18: South Africa 4,005 (~72%)
A19: 2026f recycling | B19: 1826 | C19: +9% — the elastic leg
A20: 2026f total demand | B20: 7674 | C20: −9% YoY
A21: 2026f balance (deficit) | B21: -297 | C21: 4th consecutive deficit
A22: Above-ground stocks end-26f (koz) | B22: 1747 | C22: ≈ 11 weeks of demand cover — thinnest on record
A23: — Cost & carry —
A24: AISC 2026f (US$/oz) | B24: 1006 | C24: S&P Global, +7.7% YoY
A25: Real 10Y TIPS (%) | B25: 2.31 | C25: 18-Jul-2026 close (Treasury est. via TipsWatch) — ~18-yr high; path 1.99 (12-May, FRED) → 2.07 (3-Jun, TE) → 2.31
A26: MC carry rf (%) | B26: 3.63 | C26: Fed funds midpoint held; FOMC 16–17 Jun 2026, statement 17 Jun; q = 0
A27: — Fair-value zone (computed §1.5) — | C27: weights 30/30/20/20 ratio/consensus/balance/cost — house judgment, Driver Ledger
A28: Zone low | B28: 1310 | C28: weighted bear
A29: Zone centre | B29: 1634.33 | C29: weighted base
A30: Zone high | B30: 2138.6 | C30: weighted bull

Sheet Fair-Value Anchors
A1: Fair-Value Anchors — five lenses (US$/oz)
A2: Anchor / scenario | B2: Implied Pt | C2: Basis | D2: Note
A3: Pt/Au @ 2-year mean | B3: =Assumptions!$B$4*Assumptions!$B$7 -> 1542.3276 | C3: gold × ratio | D3: recent regime ≈ spot
A4: Pt/Au @ today | B4: =Assumptions!$B$3 -> 1608.37 | C4: spot | D4: 12th pctile of post-2016
A5: Pt/Au @ 5-year mean | B5: =Assumptions!$B$4*Assumptions!$B$8 -> 1831.092 | C5: gold × ratio | D5: the mean-reversion case — BASE
A6: Pt/Au @ post-2016 mean | B6: =Assumptions!$B$4*Assumptions!$B$9 -> 2262.8484 | C6: gold × ratio | D6: bull anchor
A7: Consensus — UBS end-26 | B7: =Assumptions!$B$11 -> 1700 | C7: 2026 target | D7: fresh, post-crash
A8: Consensus — blend (BASE) | B8: =(Assumptions!$B$11+Assumptions!$B$12)/2 -> 1750 | C8: fresh vintage | D8: base consensus anchor 1,750
A9: Consensus — LBMA survey | B9: =Assumptions!$B$13 -> 2222 | C9: 2026 survey | D9: stale-high (set at record)
A10: Cost floor — AISC | B10: =Assumptions!$B$24 -> 1006 | C10: marginal cost | D10: deep-bear bound; tested 2018–24
A11: Incentive price — Valterra | B11: =(Assumptions!$B$14+Assumptions!$B$15)/2 -> 2400 | C11: greenfield sanction | D11: long-run ceiling logic
A12: Weighted fair-value zone | B12: =Assumptions!$B$28&" – "&Assumptions!$B$30 -> 1310 – 2138.6 | C12: synthesis | D12: centre = Assumptions!B29

Sheet Pt-Gold Ratio
A1: Pt/Au Ratio — platinum's primary relative lens
A2: Item | B2: Value | C2: Note
A3: Current ratio (Pt ÷ Au) | B3: =Assumptions!$B$3/Assumptions!$B$4 -> 0.40492699 | C3: live from Assumptions
A4: 2-year average | B4: 0.3883 | C4: recent regime
A5: 5-year average | B5: 0.461 | C5: mean-reversion anchor
A6: Post-2016 average | B6: 0.5697 | C6: modern regime
A7: Full-history average (2011–26) | B7: 0.7133 | C7: a fossil — pre-2015 premium era
A8: April 2025 trough | B8: 0.2808 | C8: platinum cheapest ever vs gold
A9: 2011 peak | B9: 1.3701 | C9: the old premium world
A10: Percentile of today (post-2016) | B10: 0.128 | C10: still historically cheap
A11: Pt/Pd cross | B11: =Assumptions!$B$3/Assumptions!$B$5 -> 1.2981195 | C11: first premium since 2017 — the crux driver
A12: Implied Pt @ current gold, 5y mean | B12: =Assumptions!$B$4*Assumptions!$B$8 -> 1831.092 | C12: +14% vs spot
A13: Implied Pt if gold $4,742 @ 5y mean | B13: =4742*Assumptions!$B$8 -> 2186.062 | C13: LBMA gold consensus × ratio held

Sheet Platinum Balance
A1: Platinum Balance — the commodity's financial statements (koz)
A2: WPIC Platinum Quarterly Q1 2026 (18 May 2026; research by Metals Focus)
A3: Line (koz) | B3: 2023 | C3: 2024 | D3: 2025 | E3: 2026f
A4: South Africa | B4: 3957 | C4: 4133 | D4: 3957 | E4: 4005
A5: Zimbabwe | B5: 507 | C5: 512 | D5: 516 | E5: 508
A6: Russia | B6: 674 | C6: 677 | D6: 677 | E6: 646
A7: North America | B7: 278 | C7: 265 | D7: 212 | E7: 201
A8: Other | B8: 190 | C8: 191 | D8: 196 | E8: 192
A9: Rounding / unallocated (ties to WPIC print) | B9: 14 | C9: 9 | D9: 3 | E9: -1
A10: Total mine supply | B10: =SUM(B4:B9) -> 5620 | C10: =SUM(C4:C9) -> 5787 | D10: =SUM(D4:D9) -> 5561 | E10: =SUM(E4:E9) -> 5551
A11: Recycling | B11: 1515 | C11: 1536 | D11: 1679 | E11: 1826
A12: TOTAL SUPPLY | B12: =B10+B11 -> 7135 | C12: =C10+C11 -> 7323 | D12: =D10+D11 -> 7240 | E12: =E10+E11 -> 7377
A13: Automotive | B13: 3204 | C13: 3108 | D13: 3031 | E13: 2959
A14: Jewellery | B14: 1849 | C14: 2008 | D14: 2214 | E14: 1958
A15: Industrial | B15: 2491 | C15: 2526 | D15: 2049 | E15: 2238
A16: of which hydrogen (memo) | B16: 22 | C16: 40 | D16: 65 | E16: 69
A17: Investment | B17: 388 | C17: 713 | D17: 1136 | E17: 519
A18: Rounding / unallocated (ties to WPIC print) | B18: 1 | C18: 0 | D18: 1 | E18: 0
A19: TOTAL DEMAND | B19: =B13+B14+B15+B17+B18 -> 7933 | C19: =C13+C14+C15+C17+C18 -> 8355 | D19: =D13+D14+D15+D17+D18 -> 8431 | E19: =E13+E14+E15+E17+E18 -> 7674
A20: BALANCE (supply − demand) | B20: =B12-B19 -> -798 | C20: =C12-C19 -> -1032 | D20: =D12-D19 -> -1191 | E20: =E12-E19 -> -297
A21: Above-ground stocks (year-end) | B21: 4268 | C21: 3235 | D21: 2044 | E21: 1747
A22: Weeks of demand cover (WPIC-stated) | B22: 34 | C22: 20 | D22: 12 | E22: 11
A24: Four consecutive deficits ≈ 3.3 Moz drawn from stocks; cover 34 → 11 weeks (WPIC-stated; simple AGS ÷ same-year demand × 52 gives ~28/20/13/12 — definitional difference stated, dual-framing rule). Computed balances −798/−1,032 (2023/24) vs WPIC-printed −799/−1,033: 1 koz of print rounding, stated. Hydrogen is a memo line inside Industrial (not double-counted).

Sheet Supply & Cost Curve
A1: Supply structure & the cost curve
A2: Item | B2: Value | C2: Note
A3: South Africa share of mine supply | B3: =4005/5551 -> 0.72149162 | C3: 72% — the most concentrated major metal
A4: AISC 2026f (US$/oz) | B4: =Assumptions!$B$24 -> 1006 | C4: S&P Global, +7.7% YoY
A5: Spot ÷ AISC | B5: =Assumptions!$B$3/Assumptions!$B$24 -> 1.5987773 | C5: first sustained margin in a decade (2018–24 ≈ 1×)
A6: Incentive price (greenfield) | B6: =(Assumptions!$B$14+Assumptions!$B$15)/2 -> 2400 | C6: Valterra planning range 2,300–2,500
A7: SA electricity cost since 2008 | B7: >+900% | C7: structural cost inflation (Reuters/MarketScreener, Feb-2026)
A8: Projects surviving from the 2005–10 boom | B8: 2 of 20 | C8: why supply cannot respond for years
A9: Valterra 2026 guidance (PGM M&C) | B9: 3.0–3.4 Moz | C9: unchanged at Q2-26; Amandelbult +116% post-flood
A10: Recycling 2026f (koz) | B10: =Assumptions!$B$19 -> 1826 | C10: the only elastic supply leg

Sheet Demand Segments
A1: Demand Segments — platinum's four legs (2026f)
A2: Segment | B2: 2026f (koz) | C2: Share | D2: YoY | E2: Driver / swing
A3: Automotive | B3: ='Platinum Balance'!E13 -> 2959 | C3: =B3/'Platinum Balance'!E19 -> 0.3855877 | D3: −2% | E3: ICE+hybrid volumes; reverse Pt-for-Pd substitution — THE crux
A4: Jewellery | B4: ='Platinum Balance'!E14 -> 1958 | C4: =B4/'Platinum Balance'!E19 -> 0.25514725 | D4: −12% | E4: China fabrication −42% Q1-26; VAT-rebate removal 1-Nov-25
A5: Industrial | B5: ='Platinum Balance'!E15 -> 2238 | C5: =B5/'Platinum Balance'!E19 -> 0.29163409 | D5: +9% | E5: chem 612 · glass 377 · medical 332 · H2 69 — the quiet grower
A6: Investment | B6: ='Platinum Balance'!E17 -> 519 | C6: =B6/'Platinum Balance'!E19 -> 0.067630962 | D6: −54% | E6: bars +27% (China 13t vs <1t 2019) vs ETF −100, exchange −100

Sheet Technical
A1: Technical indicators
A2: Computed from XPT/USD daily history (04 Jan 2011 – 20 Jul 2026, 4,032 sessions post-clean)
A3: Indicator | B3: Reading | C3: Signal
A4: Close | B4: 1608.37 | C4: —
A5: SMA 20 | B5: 1610.97 | C5: price -0.2% vs SMA20 — reclaimed
A6: SMA 50 | B6: 1758.02 | C6: price -8.5% vs SMA50 — falling
A7: SMA 200 | B7: 1926 | C7: price -16.5% vs SMA200
A8: 50/200 stack | B8: death-cross | C8: both falling — post-halving structure
A9: RSI(14) | B9: 53.52 | C9: neutral, off the June oversold
A10: MACD line / signal | B10: -37 / -46 | C10: negative
A11: MACD histogram | B11: 9.1 | C11: positive but fading (was +17)
A12: Avg daily range (30d) | B12: 0.0407 | C12: high-volatility tape
A13: 52-week high (close) | B13: 2772.45 | C13: 23 Jan 2026 record
A14: 52-week low (close) | B14: 1293 | C14: 31 Jul 2025
A15: Support | B15: 1,540 → 1,500 → 1,348 | C15: June–July floor → round → Feb-2021 shelf
A16: Resistance | B16: 1,758 → 1,990 | C16: SMA50 → May-2026 recovery high

Sheet Monte Carlo
A1: Monte Carlo — mc_v3 carry-anchored YZ-HAR-t, 50k paths, seed 42 (engine outputs pasted as values)
A2: Width: gap-aware Yang-Zhang + log-HAR(1/5/22), bias-corrected, 0.8 shrink; drift = ln(1+3.63%)·h/252, q=0; ν=Gaussian, width_cal=0.853 (PROVISIONAL self-fit); no signal, no factor drift.
A3: Horizon | B3: p5 | C3: p25 | D3: p50 | E3: p75 | F3: p95 | G3: mean
A4: T+21 (1 month) | B4: 1376.57 | C4: 1511.11 | D4: 1613.09 | E4: 1722.92 | F4: 1890.7 | G4: 1620.83
A5: T+63 (3 months) | B5: 1228.74 | C5: 1450.35 | D5: 1624.63 | E5: 1818.31 | F5: 2152.39 | G5: 1648.11
A6: T+252 (12 months) | B6: 961.14 | C6: 1332.64 | D6: 1668.58 | E6: 2085.84 | F6: 2896.85 | G6: 1763.11
A8: Ledger-convention cohorts (graded rows)
A9: Horizon | B9: p5 | C9: p25 | D9: p50 | E9: p75 | F9: p95 | G9: ann. fwd vol
A10: T+20 (grade 17 Aug 26) | B10: 1381.97 | C10: 1514.01 | D10: 1612.84 | E10: 1718.44 | F10: 1881.84 | G10: 0.3356
A11: T+60 (grade 12 Oct 26) | B11: 1238.91 | C11: 1452.81 | D11: 1623.02 | E11: 1813.36 | F11: 2128.49 | G11: 0.3395
A13: Zone vs spot | B13: T+63 | C13: T+252
A14: below −20% | B14: 0.0836 | C14: 0.2184
A15: −20…−10% | B15: 0.1626 | C15: 0.1161
A16: −10…−5% | B16: 0.1109 | C16: 0.0618
A17: ±5% | B17: 0.2328 | C17: 0.1186
A18: +5…+10% | B18: 0.1052 | C18: 0.0572
A19: +10…+20% | B19: 0.1511 | C19: 0.0991
A20: above +20% | B20: 0.1538 | C20: 0.3288
A22: Touch (level hit at least once) | B22: by T+20 | C22: by T+60 | D22: by T+252
A23: $1,750 | B23: 0.3175 | C23: 0.5784 | D23: 0.7967
A24: $1,990 (May high) | B24: 0.0183 | C24: 0.1858 | D24: 0.5342
A25: $2,222 (stale consensus) | B25: 0.0003 | C25: 0.0472 | D25: 0.3488
A26: $2,925 (record) | B26: 0 | C26: 0.0003 | D26: 0.0822
A27: $1,540 (floor) | B27: 0.5463 | C27: 0.722 | D27: 0.851
A28: $1,348 (2021 shelf) | B28: 0.043 | C28: 0.2368 | D28: 0.5361
A29: $1,006 (AISC) | B29: 0 | C29: 0.0032 | D29: 0.1277
A31: Sensitivity (stated, not adopted): under the gold+silver-trained LONO shape (ν=20, width 1.035) the T+63 90% band widens to 1,161–2,278.
A33: Ledger cohort fields (anchored at publication; graded later; append-only)
A34: instrument / cycle_no | B34: XPTUSD / 1
A35: anchor_date / anchor_price | B35: 2026-07-20 / 1,608.37
A36: grade_date T+20 / T+60 (projected) | B36: 2026-08-17 / 2026-10-12 | F36: Mon–Fri weekmask; actual grading counts real trading rows
A37: touch T+20 +5/+10/−5/−10% | B37: 53% / 26% / 49% / 21%
A38: touch T+60 +5/+10/−5/−10% | B38: 73% / 53% / 69% / 46%
A39: anchor_vol (ann., HAR) T+20 / T+60 | B39: 33.6% / 34.0% | F39: forward, width_cal applied
A40: status | B40: NOT anchored to the live site — publication is a separate, explicitly-requested step (house rule).

Sheet Sensitivity
A1: Sensitivity — platinum fair value = gold × Pt/Au ratio (US$/oz)
A2: Rows: Pt/Au ratio. Columns: gold price.
A3: ratio \ gold | B3: 3600 | C3: 3972 | D3: 4400 | E3: 4800
A4: 0.32 | B4: =B$3*$A4 -> 1152 | C4: =C$3*$A4 -> 1271.04 | D4: =D$3*$A4 -> 1408 | E4: =E$3*$A4 -> 1536
A5: 0.36 | B5: =B$3*$A5 -> 1296 | C5: =C$3*$A5 -> 1429.92 | D5: =D$3*$A5 -> 1584 | E5: =E$3*$A5 -> 1728
A6: 0.405 | B6: =B$3*$A6 -> 1458 | C6: =C$3*$A6 -> 1608.66 | D6: =D$3*$A6 -> 1782 | E6: =E$3*$A6 -> 1944
A7: 0.45 | B7: =B$3*$A7 -> 1620 | C7: =C$3*$A7 -> 1787.4 | D7: =D$3*$A7 -> 1980 | E7: =E$3*$A7 -> 2160
A8: 0.5 | B8: =B$3*$A8 -> 1800 | C8: =C$3*$A8 -> 1986 | D8: =D$3*$A8 -> 2200 | E8: =E$3*$A8 -> 2400
A10: Today: gold ~$3,972, ratio 0.405× → ≈ spot. Bull = joint move (gold up + ratio re-rates); the two dimensions are NOT independent — reverse substitution pins the ratio (§1.7 of the study).

Sheet Step 0 Calibration
A1: Step 0 — calibration gate (current house basis)
A2: Walk-forward h=60, non-overlapping, scale-normalized CRPS vs a CARRY-ANCHORED lognormal RW; robust verdict across bootstrap blocks {2,3,4}; production chain (reproduction check passed against the live gold registry).
A3: Windows (full history / last-5y) | B3: 62 (2012–2026) / 20
A4: ADOPTED config (provisional self-fit) | B4: ν = Gaussian (sentinel 250), width_cal = 0.853 (MLE scale 0.790, clip floor 0.85 active)
A5: Self-fit skill & CI (block 2) | B5: -0.0004 [-0.009, +0.009] — PARITY
A6: De-circularized LONO (gold+silver-trained) | B6: -0.0114 [-0.032, +0.009] — PARITY
A7: Borrowed live METALS (Gaussian/1.0) | B7: -0.0094 [-0.030, +0.010] — PARITY
A8: Coverage 50/80/90 (self-fit) | B8: 48% / 81% / 93.5% vs 50/80/90 — mildly over-covered
A9: PIT mean | B9: 0.489 — centred; no drift blemish under the carry anchor
A10: Reproduction check (gold, live registry) | B10: EXACT: 67 windows, +0.0035, CI[−0.005,+0.013], PARITY
A11: Verdict | B11: PARITY — the engine ties the carry-anchored RW; platinum does NOT arrive failing. PROVISIONAL single-name fit, flagged circular; pooled 3-metal fit (ν≈20, 0.965, 148 windows) is the likely future config.

Sheet Peer & Sector
A1: Peer & Sector — the investable platinum complex
A2: Cohort | B2: Names | C2: Character
A3: SA primary producers | B3: Valterra (ex-Amplats), Impala, Sibanye-Stillwater, Northam | C3: levered to spot & ZAR; AISC ~$1,000; payouts over projects
A4: Zimbabwe / other | B4: Zimplats, Tharisa | C4: expansion optionality, political discount
A5: Russian by-product | B5: Norilsk Nickel | C5: ~12% of supply; sanctions-shadowed
A6: Physical ETFs | B6: PPLT (~$1.8bn AUM), PLTM | C6: direct bullion; 2026f ETF line −100 koz
A7: New venue | B7: GFEX platinum futures (Guangzhou) | C7: China's first PGM derivatives; published stockpiles
A8: Platinum (this study) | B8: — | C8: the metal itself — no leverage, no balance sheet, no counterparty

Sheet Sweep Register
A1: Step 2A Information Sweep — four metal rings, validated (engine/research_sweep.py: 0 errors)
A2: ID | B2: Ring | C2: Category | D2: Class | E2: Headline | F2: Date
A3: F01 | B3: GLOBAL_MACRO | C3: real rates & USD | D3: S | E3: 10Y TIPS real yield ~2.31% at the 18-Jul-2026 close (Treasury estimate via TipsWatch) — the highest 10-year real yield in ~18 years; rising path 1.99% (12-May, FRED) -> 2.07% (3-Jun, TE) -> 2.31%; firm dollar; hawkish 2026 repricing after hot CPI | F3: 2026-07-18
A4: F02 | B4: GLOBAL_MACRO | C4: central-bank policy path | D4: S | E4: Fed funds midpoint 3.63% held at the 16–17-Jun-2026 FOMC (statement 17 Jun; 3.50–3.75%); market pricing leans to hikes near-term, easing expected 2027 | F4: 2026-06-17
A5: F03 | B5: GLOBAL_MACRO | C5: official-sector behavior | D5: S | E5: WPIC reports PGMs 'fundamentally key' to China's 15th Five-Year Plan (AI/hydrogen) and frames platinum as a strategic metal — an INDUSTRY-COUNCIL characterization: China's official strategic-minerals catalogue is undisclosed and its reconstructed 2016/2021 lists carry NO PGMs; no central bank holds platinum reserves in size | F5: 2026-07-17
A6: F04 | B6: SUPPLY | C6: mine production | D6: D | E6: WPIC Q1-2026 Quarterly: 2026f mine supply 5,551 koz flat (SA 4,005, Zim 508, Ru 646, NA 201, other 192); total supply 7,377 koz (+2%) | F6: 2026-05-18
A7: F05 | B7: SUPPLY | C7: recycling | D7: D | E7: Recycling 1,826 koz 2026f (+9%): autocat 1,365, jewellery 373, industrial 88; recyclers working-capital-constrained at higher prices | F7: 2026-05-18
A8: F06 | B8: SUPPLY | C8: disruptions | D8: D | E8: Valterra Q2-2026: PGM M&C +1% YoY, Amandelbult +116% post-flood recovery, FY guidance unchanged 3.0–3.4 Moz; miners favour payouts over projects (S&P AISC 2026f $1,006/oz, +7.7%; SA electricity +900% since 2008); Valterra long-term planning $2,300–2,500 | F8: 2026-07-17
A9: F07 | B9: DEMAND | C9: industrial demand | D9: D | E9: Industrial 2,238 koz 2026f (+9%): chemical 612, glass 377, medical 332, electrical 119, petroleum 132, hydrogen 69 (from 22 in 2023; WPIC sees PEM electrolyser demand >500 koz p.a. within 10 years) | F9: 2026-05-18
A10: F08 | B10: DEMAND | C10: industrial demand | D10: S | E10: Automotive 2,959 koz 2026f (−2%); Pt-for-Pd substitution (~700 koz embedded) flips: Pt now at a ~1.30× PREMIUM to Pd — reverse-substitution incentive live, but platform lock-in (~15% of models/yr, ~7-yr cycles) makes it slow | F10: 2026-05-18
A11: F09 | B11: DEMAND | C11: jewelry / consumer demand | D11: S | E11: Jewellery 1,958 koz 2026f (−12%); China fabrication −42% YoY in Q1-2026 on price shock, weak sentiment, destocking and the 1-Nov-2025 removal of the 13% VAT rebate | F11: 2026-05-18
A12: F10 | B12: DEMAND | C12: investment / ETF flows | D12: D | E12: Investment 519 koz 2026f: bars & coins 533 (+27%), China ≥500g bars 185, ETF −100, exchange stocks −100; China bar market grew <1t (2019) → ~13t (2025) | F12: 2026-05-18
A13: F11 | B13: DEMAND | C13: official-sector purchases | D13: NEG | E13: Negative search — nothing found (searched 'central bank platinum reserves purchases 2026', 'Gokhran platinum purchases 2026'; only China strategic-mineral classification and the historic Russian palladium precedent surfaced — no quantified official platinum buying) | F13: 2026-07-20
... A20: F18 | B20: DEMAND | C20: investment / ETF flows | D20: NEG | E20: Negative search — nothing found (searched 'market-implied weighting of commodity fair-value anchors' — none exists; weights are a stated house judgment) | F20: 2026-07-20
A21: Driver gate:
A22: BOTTOM_UP | B22: 2026 supply/demand balance (deficit 297 koz; AGS 1,747 koz ≈ 11 weeks) | F22: F04,F05,F07,F08,F09,F10
A23: BOTTOM_UP | B23: Analyst-consensus forward anchor ($1,700–1,800 fresh; $2,222 stale-high) | F23: F15
A24: BOTTOM_UP | B24: AISC cost floor $1,006/oz; incentive range $2,300–2,500 | F24: F06
A25: TOP_DOWN | B25: Pt/Au neutral-ratio band (0.36–0.46, base = 5y mean 0.461… computed 0.461→base 1,831) | F25: F16,F15
A26: TOP_DOWN | B26: q_annual = 0 (no holder yield; METALS-profile precedent) | F26: F17,F02
A27: TOP_DOWN | B27: Anchor weights 30/30/20/20 (ratio/consensus/balance/cost; carry = tilt) | F27: F18

Sheet Sources
A1: Sources & about
A2: • WPIC Platinum Quarterly Q1 2026 (18 May 2026; research by Metals Focus) — supply/demand balance, above-ground stocks, lease-rate & China commentary. platinuminvestment.com
A3: • WPIC/Mining Weekly (17 Jul 2026) — China 15th Five-Year Plan (WPIC characterization; the official strategic-minerals catalogue is undisclosed and reconstructed lists carry no PGMs — Swedish National China Centre, 2026), GFEX, China bar market <1t (2019) → ~13t (2025).
A4: • UBS platinum note via Yahoo Finance (29 Jun 2026) — $1,700 Sep/Dec-26, $1,800 Mar/Jun-27; surplus risk; falling lease rates.
A5: • LBMA 2026 Precious Metals Forecast Survey via Kitco (20 Jan 2026) — platinum average $2,222 (stale-high, set at the record); gold $4,742.
A6: • Valterra Platinum Q2-2026 production report via Reuters/TradingView (17 Jul 2026) — output, guidance, realized prices ($1,966 Q2 avg).
A7: • Reuters via MarketScreener (11 Feb 2026) — payouts over projects; S&P Global AISC 2026f $1,006/oz (+7.7%); $2,300–2,500 planning range; SA electricity +900% since 2008.
A8: • WPIC Perspectives (24 Jan 2024) — Pt-for-Pd substitution ~700 koz embedded; ~15% of models/yr; ~7-year platform lock-in.
A9: • CFTC COT via metalcharts.org (14 Jul 2026) — managed money net long +8.3k (Pt), −6.2k (Pd).
A10: • 10Y TIPS real yield 2.31% at the 18-Jul-2026 close (US Treasury estimate via TipsWatch, 19-Jul-2026); rising path 1.99% (FRED DFII10, 12-May) → 2.07% (TradingEconomics, 3-Jun) → 2.31% — an ~18-year high. Fed funds midpoint 3.63%; FOMC 16–17 Jun 2026, statement 17 Jun (federalreserve.gov).
A11: • Spot cross-section Fri 17 Jul 2026 (Fortune/quote pages): gold $3,972, palladium $1,239, silver $55 — one-session mismatch vs the Mon 20 Jul platinum anchor, stated. 30-Jan-2026 crash catalyst: the surprise Warsh Fed-chair nomination (Fortune/NBC, 31-Jan-2026 — gold −11.4% settle basis, silver −31.4%); the Strait of Hormuz war began 28-Feb-2026 (Brent to $126) — it POST-dates the crash and supported Q1 prices (Wikipedia timeline).
A12: • Attached XPT/USD daily OHLC history (Investing.com export), 04 Jan 2011 – 20 Jul 2026; Step 0.0 data-quality gate applied (9 placeholder rows dropped; no corporate-action repairs; 260.0 rows/yr = metals Mon–Fri calendar).
... A14: • Educational analysis under the Testahil Standing Research Protocol; not investment advice; no ratings, no price targets — fair-value ranges and distributions only.
