Workbook

Sheet READ FIRST
A1: TALAAT MOUSTAFA GROUP HOLDING — valuation workbook
A2: Egyptian Exchange · TMGH · Egyptian pounds · 2026-09-01
A4: BLUE cells are inputs. BLACK cells are formulas. Change a blue cell and the value per share on the Summary sheet recomputes.
A6: This workbook contains no recommendation, no target price and no rating.
A8: The four cases on the Summary sheet are alternatives, not a distribution. They are two ways of measuring Egypt's equity risk premium crossed with two readings of how fast the order book converts. They are never averaged.
A10: Sheet order: READ FIRST · Summary · Fundamental Valuation · Assumptions · SOTP Bridge · Segments · Relative & Normalized · DCF · Income Statement · Balance Sheet · Cash Flow · Summary Financials · Monte Carlo · Sensitivity · Per-Share & Ratios · Peer & Sector

Sheet Summary
A1: Summary | B1: Value | C1: Note
A2: Last close, EGP | B2: 97.8 | C2: Egyptian Exchange close, 23 August 2026, from the same cleaned price history the probability distribution is fitted to
A3: Shares in issue, million | B3: 2060.6538
A4: Market capitalisation, EGP mn | B4: =B2*B3
A6: Case | B6: Enterprise value | C6: Equity value | D6: Per share, minority at book | E6: Per share, minority proportional | F6: Against last close
A7: Rating premium, slower conversion | B7: 78902.729 | C7: 90543.829 | D7: =C7/$B$3 | E7: 44.186642 | F7: =D7/$B$2-1
A8: Rating premium, faster conversion | B8: 99795.051 | C8: 111436.15 | D8: =C8/$B$3 | E8: 49.741277 | F8: =D8/$B$2-1
A9: Swap premium, slower conversion | B9: 100442.15 | C9: 112083.25 | D9: =C9/$B$3 | E9: 49.91332 | F9: =D9/$B$2-1
A10: Swap premium, faster conversion | B10: 132506.28 | C10: 144147.38 | D10: =C10/$B$3 | E10: 58.438199 | F10: =D10/$B$2-1
A12: Lowest published case, EGP/share | B12: =MIN(D7:E10)
A13: Highest published case, EGP/share | B13: =MAX(D7:E10)
A15: Discount rate the last close implies, slower conversion | B15: 0.26528369
A16: Discount rate the last close implies, faster conversion | B16: 0.29072154
A17: Discount rate this workbook uses | B17: 0.3579341

Sheet Fundamental Valuation
A1: Lens | B1: Low, EGP/share | C1: High, EGP/share | D1: What it measures
A2: Cash flow, sum of the parts | B2: 43.939369 | C2: 69.952253 | D2: the order book, hotels and recurring businesses, discounted
A3: Book value and sustainable return | B3: 3.3262713 | C3: 12.632516 | D3: return on equity of 16.7% against a cost of equity of 37.1%
A4: Normalised earnings power | B4: 15.44113 | C4: 23.76577 | D4: three years of profit with revaluation gains removed, capitalised
A5: Its own history of multiples | B5: 34.040011 | C5: 57.999136 | D5: the multiples these shares have actually carried, on normalised earnings

Sheet Assumptions
A1: Assumption | B1: Value | C1: Where it comes from
A2: Development gross margin, first half 2026 | B2: 0.26578929 | C2: an output of the disclosed cost line, not an input
A3: Hospitality gross margin, first half 2026 | B3: 0.45371295 | C3: an output of the disclosed cost line
A4: Other recurring gross margin, first half 2026 | B4: 0.31910573 | C4: an output of the disclosed cost line
A5: Overhead as a share of revenue, 2025 | B5: 0.067510893 | C5: general and administrative, marketing and government charges over revenue
A6: Collections on the order book, a year | B6: 0.075697294 | C6: from the movement in customer advances in the first half of 2026
A7: Work in progress, years of cost | B7: 4 | C7: the company's own position at 30 June 2026
A8: Marginal borrowing rate | B8: 0.255 | C8: sovereign yield plus a 250 basis-point corporate spread; TMG does not disclose its own facility pricing
A9: Hospitality revenue growth | B9: 0.2 | C9: stated
A10: Other recurring revenue growth | B10: 0.22 | C10: stated
A11: Order book converts over, years — slower | B11: 14 | C11: the crux, read one way
A12: Order book converts over, years — faster | B12: 10 | C12: the crux, read the other way
A13: Annual contracted sales, EGP mn | B13: 382200 | C13: FY2025 as reported, held flat in nominal terms
... A17: Dividend payout | B17: 0.3 | C17: the company's recent behaviour

Sheet SOTP Bridge
A1: Bridge, slower-conversion case | B1: EGP mn
A2: Present value of the explicit ten years | B2: 72255.833
A3: Present value of the order book beyond it | B3: 0
A4: Present value of the recurring businesses beyond it | B4: 6646.8961
A5: Enterprise value | B5: =SUM(B2:B4)
A6: Cash, deposits and amortised-cost assets | B6: 75773.4
A7: Borrowings | B7: -16493
A8: Lease liabilities | B8: -513.9
A9: Investment property | B9: 25228
A10: Associates and other financial assets | B10: 3299.4
A11: Value of the whole group's equity | B11: =B5+SUM(B6:B10)
A12: Non-controlling interests, at book | B12: -75652.8
A13: Equity attributable to TMG's shareholders | B13: =B11+B12
A14: Shares in issue, million | B14: 2060.6538
A15: Value per share, EGP | B15: =B13/B14

Sheet Segments
A1: Segment | B1: FY2025 revenue | C1: FY2025 cost | D1: Gross profit | E1: Gross margin | F1: 1H2026 revenue | G1: 1H2026 cost | H1: 1H2026 margin
A2: Real-estate development | B2: 36705.7 | C2: 26645.4 | D2: =B2-C2 | E2: =D2/B2 | F2: 16967.2 | G2: 12457.5 | H2: =(F2-G2)/F2
A3: Hospitality | B3: 14889.7 | C3: 7800.6 | D3: =B3-C3 | E3: =D3/B3 | F3: 7512.9 | G3: 4104.2 | H3: =(F3-G3)/F3
A4: Other recurring income | B4: 10899.7 | C4: 7193.7 | D4: =B4-C4 | E4: =D4/B4 | F4: 5711.9 | G4: 3889.2 | H4: =(F4-G4)/F4
A5: Total | B5: =SUM(B2:B4) | C5: =SUM(C2:C4) | D5: =SUM(D2:D4) | E5: =D5/B5 | F5: =SUM(F2:F4) | G5: =SUM(G2:G4) | H5: =(F5-G5)/F5

Sheet Relative & Normalized
A1: Year end | B1: Close, EGP | C1: Earnings per share | D1: Price to earnings | E1: Book value per share | F1: Price to book
A2: 2011 | B2: 2.96
A3: 2012 | B3: 4.43
A4: 2013 | B4: 6.18
A5: 2014 | B5: 9.86
A6: 2015 | B6: 6.47
A7: 2016 | B7: 9.13
A8: 2017 | B8: 9.8 | C8: 0.64387332 | D8: =B8/C8
A9: 2018 | B9: 9.89 | C9: 0.82731024 | D9: =B9/C9
A10: 2019 | B10: 8.17 | C10: 0.9085466 | D10: =B10/C10
A11: 2020 | B11: 6.57
A12: 2021 | B12: 9.07 | C12: 0.85492284 | D12: =B12/C12
A13: 2022 | B13: 9.99 | C13: 1.1183344 | D13: =B13/C13
A14: 2023 | B14: 24.15 | C14: 1.6079075 | D14: =B14/C14 | E14: 18.610022 | F14: =B14/E14
A15: 2024 | B15: 56 | C15: 5.2037368 | D15: =B15/C15
A16: 2025 | B16: 80 | C16: 6.9802556 | D16: =B16/C16 | E16: 39.331001 | F16: =B16/E16
A18: Normalised earnings | B18: EGP mn
A19: Attributable profit 2023, cleaned | B19: 3313.3
A20: Attributable profit 2024, cleaned | B20: 8025.3563
A21: Attributable profit 2025, cleaned | B21: 12218.462
A22: Average | B22: 7852.3729
A23: Average per share, EGP | B23: =B22/'Summary'!$B$3

Sheet DCF
A1: Discounted cash flow, slower conversion | B1: 2026 | C1: 2027 | D1: 2028 | E1: 2029 | F1: 2030 | G1: 2031 | H1: 2032 | I1: 2033 | J1: 2034 | K1: 2035 | L1: 2036 | M1: 2037 | N1: 2038 | O1: 2039 | P1: 2040 | Q1: 2041 | R1: 2042 | S1: 2043 | T1: 2044 | U1: 2045
A2: Revenue | B2: 80502.498 | C2: 96868.95 | D2: 116567.2 | E2: 140276.49 | F2: 168814.71 | G2: 203166.83 | H2: 244518.99 | I2: 294299.72 | J2: 354229.51 | K2: 426380.63 | L2: 513249.12 | M2: 617841.63 | N2: 743780.03 | O2: 895427.54 | P2: 1078040.7 | Q2: 1297952.5 | R2: 1562793.5 | S2: 1881757.8 | T2: 2265924.3 | U2: 2728643.3
A3: Cost of revenue | B3: 55039.062 | C3: 66227.96 | D3: 79694.476 | E3: 95902.899 | F3: 115412.3 | G3: 138895.93 | H3: 167164.54 | I3: 201194.54 | J3: 242161.9 | K3: 291483 | L3: 350863.83 | M3: 422359.36 | N3: 508445 | O3: 612102.81 | P3: 736925.3 | Q3: 887240.73 | R3: 1068263.9 | S3: 1286278.3 | T3: 1548855 | U3: 1865117.8
A4: Gross profit | B4: 25463.436 | C4: 30640.991 | D4: 36872.727 | E4: 44373.588 | F4: 53402.411 | G4: 64270.902 | H4: 77354.454 | I4: 93105.177 | J4: 112067.61 | K4: 134897.63 | L4: 162385.29 | M4: 195482.27 | N4: 235335.03 | O4: 283324.73 | P4: 341115.36 | Q4: 410711.77 | R4: 494529.59 | S4: 595479.58 | T4: 717069.27 | U4: 863525.52
A5: Overheads | B5: 5434.7955 | C5: 6539.7093 | D5: 7869.5559 | E5: 9470.1909 | F5: 11396.832 | G5: 13715.974 | H5: 16507.695 | I5: 19868.437 | J5: 23914.35 | K5: 28785.337 | L5: 34649.906 | M5: 41711.04 | N5: 50213.254 | O5: 60451.112 | P5: 72779.488 | Q5: 87625.932 | R5: 105505.59 | S5: 127039.15 | T5: 152974.57 | U5: 184213.14
A6: Depreciation | B6: 1142.6904 | C6: 1156.8021 | D6: 1176.437 | E6: 1202.6953 | F6: 1236.9036 | G6: 1280.6614 | H6: 1335.8969 | I6: 1404.9354 | J6: 1490.5802 | K6: 1596.2115 | L6: 1725.9055 | M6: 1884.5772 | N6: 2078.1538 | O6: 2313.7834 | P6: 2600.0869 | Q6: 2947.4617 | R6: 3368.4491 | S6: 3878.1762 | T6: 4494.891 | U6: 5240.6069
A7: Operating profit | B7: 18885.95 | C7: 22944.479 | D7: 27826.734 | E7: 33700.702 | F7: 40768.676 | G7: 49274.267 | H7: 59510.861 | I7: 71831.805 | J7: 86662.677 | K7: 104516.08 | L7: 126009.48 | M7: 151886.65 | N7: 183043.62 | O7: 220559.83 | P7: 265735.79 | Q7: 320138.37 | R7: 385655.56 | S7: 464562.25 | T7: 559599.8 | U7: 674071.77
A8: Free cash flow to the firm | B8: 13543.19 | C8: 15508.047 | D8: 18059.74 | E8: 21271.582 | F8: 25243.503 | G8: 30104.588 | H8: 36016.872 | I8: 43180.449 | J8: 51840.054 | K8: 62293.288 | L8: 74900.772 | M8: 90098.562 | N8: 108413.23 | O8: 130480.18 | P8: 157065.75 | Q8: 189093.94 | R8: 227678.72 | S8: 274162.98 | T8: 330165.47 | U8: 397637.59
A9: Discount factor | B9: =1/(1+'Summary'!$B$14)^1 | C9: =1/(1+'Summary'!$B$14)^2 | D9: =1/(1+'Summary'!$B$14)^3 | E9: =1/(1+'Summary'!$B$14)^4 | F9: =1/(1+'Summary'!$B$14)^5 | G9: =1/(1+'Summary'!$B$14)^6 | H9: =1/(1+'Summary'!$B$14)^7 | I9: =1/(1+'Summary'!$B$14)^8 | J9: =1/(1+'Summary'!$B$14)^9 | K9: =1/(1+'Summary'!$B$14)^10 | L9: =1/(1+'Summary'!$B$14)^11 | M9: =1/(1+'Summary'!$B$14)^12 | N9: =1/(1+'Summary'!$B$14)^13 | O9: =1/(1+'Summary'!$B$14)^14 | P9: =1/(1+'Summary'!$B$14)^15 | Q9: =1/(1+'Summary'!$B$14)^16 | R9: =1/(1+'Summary'!$B$14)^17 | S9: =1/(1+'Summary'!$B$14)^18 | T9: =1/(1+'Summary'!$B$14)^19 | U9: =1/(1+'Summary'!$B$14)^20
A10: Present value | B10: =B8*B9 | C10: =C8*C9 | D10: =D8*D9 | E10: =E8*E9 | F10: =F8*F9 | G10: =G8*G9 | H10: =H8*H9 | I10: =I8*I9 | ... U10: =U8*U9
A12: Sum of the explicit years | B12: =SUM(B10:U10)
A13: Order book still unconverted, present value | B13: 0
A14: Recurring businesses beyond the window, present value | B14: 6646.8961
A15: Enterprise value | B15: =B12+B13+B14

Sheet Income Statement
A1: EGP mn | B1: 2023 | C1: 2024 | D1: 2025 | E1: 2026 | F1: 2027 | G1: 2028 | H1: 2029 | I1: 2030 | J1: 2031 | K1: 2032 | L1: 2033 | M1: 2034 | N1: 2035 | O1: 2036 | P1: 2037 | Q1: 2038 | R1: 2039 | S1: 2040 | T1: 2041 | U1: 2042 | V1: 2043 | W1: 2044 | X1: 2045
A2: Development revenue | B2: 21578.7 | C2: 24518.3 | D2: 36705.7 | E2: 49337.224 | F2: 59204.669 | G2: 71045.603 | H2: 85254.723 | I2: 102305.67 | J2: 122766.8 | K2: 147320.16 | L2: 176784.19 | M2: 212141.03 | N2: 254569.24 | O2: 305483.09 | P2: 366579.71 | Q2: 439895.65 | R2: 527874.78 | S2: 633449.73 | T2: 760139.68 | U2: 912167.61 | V2: 1094601.1 | W2: 1313521.4 | X2: 1576225.6
A3: Hospitality revenue | B3: 3540.9 | C3: 11496.5 | D3: 14889.7 | E3: 17867.64 | F3: 21441.168 | G3: 25729.402 | H3: 30875.282 | I3: 37050.338 | J3: 44460.406 | K3: 53352.487 | L3: 64022.985 | M3: 76827.582 | N3: 92193.098 | O3: 110631.72 | P3: 132758.06 | Q3: 159309.67 | R3: 191171.61 | S3: 229405.93 | T3: 275287.11 | U3: 330344.54 | V3: 396413.45 | W3: 475696.13 | X3: 570835.36
A4: Other recurring revenue | B4: 3311.7 | C4: 6655.5 | D4: 10899.7 | E4: 13297.634 | F4: 16223.113 | G4: 19792.198 | H4: 24146.482 | I4: 29458.708 | J4: 35939.624 | K4: 43846.341 | L4: 53492.536 | M4: 65260.894 | N4: 79618.291 | O4: 97134.315 | P4: 118503.86 | Q4: 144574.71 | R4: 176381.15 | S4: 215185.01 | T4: 262525.71 | U4: 320281.36 | V4: 390743.26 | W4: 476706.78 | X4: 581582.27
A5: Gross profit | B5: 8637.3 | C5: 15300.2 | D5: 20855.4 | E5: 25463.436 | F5: 30640.991 | G5: 36872.727 | H5: 44373.588 | I5: 53402.411 | J5: 64270.902 | K5: 77354.454 | L5: 93105.177 | M5: 112067.61 | N5: 134897.63 | O5: 162385.29 | P5: 195482.27 | Q5: 235335.03 | R5: 283324.73 | S5: 341115.36 | T5: 410711.77 | U5: 494529.59 | V5: 595479.58 | W5: 717069.27 | X5: 863525.52
A6: Net profit | B6: 3347.3 | C6: 14467.5 | D6: 18202 | E6: 23122.06 | F6: 29092.806 | G6: 36292.319 | H6: 45001.953 | I6: 55557.275 | J6: 68360.529 | K6: 83895.376 | L6: 102744.47 | M6: 125610.46 | N6: 153341.31 | O6: 186960.58 | P6: 227704.05 | Q6: 277063.78 | R6: 336841.26 | S6: 409211.42 | T6: 496799.9 | U6: 602776.29 | V6: 730966.46 | W6: 885988.16 | X6: 1073414.6
A7: Attributable profit | B7: 3313.3 | C7: 10723.1 | D7: 14383.9 | E7: 12667.781 | F7: 15938.948 | G7: 19883.313 | H7: 24655.022 | I7: 30437.92 | J7: 37452.382 | K7: 45963.391 | L7: 56290.159 | M7: 68817.653 | N7: 84010.43 | O7: 102429.27 | P7: 124751.21 | Q7: 151793.72 | R7: 184543.74 | S7: 224192.86 | T7: 272179.58 | U7: 330240.4 | V7: 400471.38 | W7: 485402.44 | X7: 588086.94
A8: Earnings per share, EGP | B8: 1.6078877 | C8: 5.2037368 | D8: 6.9802603 | E8: 6.1474572 | F8: 7.7348985 | G8: 9.6490315 | H8: 11.96466 | I8: 14.771001 | J8: 18.175 | K8: 22.305246 | L8: 27.31665 | M8: 33.396029 | N8: 40.768823 | O8: 49.70717 | P8: 60.539628 | Q8: 73.662892 | R8: 89.555918 | S8: 108.79696 | T8: 132.08409 | U8: 160.26001 | V8: 194.3419 | W8: 235.55749 | X8: 285.38852

Sheet Balance Sheet
A1: EGP mn | B1: 30 Jun 2026 reported | C1: 2026 | D1: 2027 | E1: 2028 | F1: 2029 | G1: 2030 | H1: 2031 | I1: 2032 | J1: 2033 | K1: 2034 | L1: 2035 | M1: 2036 | N1: 2037 | O1: 2038 | P1: 2039 | Q1: 2040 | R1: 2041 | S1: 2042 | T1: 2043 | U1: 2044 | V1: 2045
A2: Cash and deposits | C2: 94001.704 | D2: 116038.9 | E2: 142860.25 | F2: 175619.23 | G2: 215692.91 | H2: 264734.76 | I2: 324737.07 | J2: 398105.29 | K2: 487746.94 | L2: 597178.44 | M2: 730653.66 | N2: 893318.75 | O2: 1091398.8 | P2: 1332423.3 | Q2: 1625497.4 | R2: 1981630.1 | S2: 2414129.9 | T2: 2939082.2 | U2: 3575925.3 | V2: 4348145.8
A3: Properties under development | B3: 148315.4 | C3: 147460.47 | D3: 154064.05 | E3: 167710.48 | F3: 188377.79 | G3: 216397.26 | H3: 252434.65 | I3: 297490.03 | J3: 352914.37 | K3: 420442 | L3: 502238.96 | M3: 600968.18 | N3: 719872.88 | O3: 862880.75 | P3: 1034731.9 | Q3: 1241134.5 | R3: 1488953.6 | S3: 1786438.4 | T3: 2143496.7 | U3: 2572024 | V3: 3086299.7
A4: Property, plant and equipment | B4: 73322.7 | C4: 96400.179 | D4: 98036.418 | E4: 100224.61 | F4: 103075.3 | G4: 106721.78 | H4: 111324.74 | I4: 117077.95 | J4: 124215.01 | K4: 133017.63 | L4: 143825.46 | M4: 157048.1 | N4: 173179.48 | O4: 192815.28 | P4: 216673.91 | Q4: 245621.81 | R4: 280704.09 | S4: 323181.35 | T4: 374574.25 | U4: 436717.24 | V4: 511823.46
A5: Investment property | B5: 25228 | C5: 25228 | D5: 25228 | E5: 25228 | F5: 25228 | G5: 25228 | H5: 25228 | I5: 25228 | J5: 25228 | K5: 25228 | L5: 25228 | M5: 25228 | N5: 25228 | O5: 25228 | P5: 25228 | Q5: 25228 | R5: 25228 | S5: 25228 | T5: 25228 | U5: 25228 | V5: 25228
A6: Total assets | B6: 477897.9 | C6: 496447.25 | D6: 526724.27 | E6: 569380.24 | F6: 625657.23 | G6: 697396.85 | H6: 787079.05 | I6: 897889.95 | J6: 1033819.6 | K6: 1199791.5 | L6: 1401827.8 | M6: 1647254.8 | N6: 1944956 | O6: 2305679.8 | P6: 2742414 | Q6: 3270838.6 | R6: 3909872.6 | S6: 4682334.6 | T6: 5615738 | U6: 6743251.4 | V6: 8104853.8
A7: Customer advances | B7: 133993.1 | C7: 133220.73 | D7: 139186.63 | E7: 151515.27 | F7: 170186.81 | G7: 195500.53 | H7: 228057.92 | I7: 268762.45 | J7: 318834.66 | K7: 379841.38 | L7: 453739.5 | M7: 542934.78 | N7: 650357.27 | O7: 779555.37 | P7: 934811.44 | Q7: 1121282.5 | R7: 1345170.5 | S7: 1613928.3 | T7: 1936506.7 | U7: 2323652.6 | V7: 2788266.5
A8: Borrowings | C8: 16493 | D8: 16493 | E8: 16493 | F8: 16493 | G8: 16493 | H8: 16493 | I8: 16493 | J8: 16493 | K8: 16493 | L8: 16493 | M8: 16493 | N8: 16493 | O8: 16493 | P8: 16493 | Q8: 16493 | R8: 16493 | S8: 16493 | T8: 16493 | U8: 16493 | V8: 16493
A9: Total liabilities | B9: 310574.2 | C9: 309801.83 | D9: 315767.73 | E9: 328096.37 | F9: 346767.91 | G9: 372081.63 | H9: 404639.02 | I9: 445343.55 | J9: 495415.76 | K9: 556422.48 | L9: 630320.6 | M9: 719515.88 | N9: 826938.37 | O9: 956136.47 | P9: 1111392.5 | Q9: 1297863.6 | R9: 1521751.6 | S9: 1790509.4 | T9: 2113087.8 | U9: 2500233.7 | V9: 2964847.6
A10: Equity attributable to TMG | B10: 91670.9 | C10: 100538.35 | D10: 111695.61 | E10: 125613.93 | F10: 142872.45 | G10: 164178.99 | H10: 190395.66 | I10: 222570.03 | J10: 261973.14 | K10: 310145.5 | L10: 368952.8 | M10: 440653.29 | N10: 527979.14 | O10: 634234.74 | P10: 763415.36 | Q10: 920350.36 | R10: 1110876.1 | S10: 1342044.3 | T10: 1622374.3 | U10: 1962156 | V10: 2373816.9
A11: Non-controlling interests | B11: 75652.8 | C11: 86107.078 | D11: 99260.937 | E11: 115669.94 | F11: 136016.87 | G11: 161136.23 | H11: 192044.38 | I11: 229976.36 | J11: 276430.67 | K11: 333223.48 | L11: 402554.36 | M11: 487085.67 | N11: 590038.5 | O11: 715308.56 | P11: 867606.08 | Q11: 1052624.6 | R11: 1277245 | S11: 1549780.9 | T11: 1880275.9 | U11: 2280861.7 | V11: 2766189.3
A12: Total equity | B12: 167323.6 | C12: 186645.43 | D12: 210956.55 | E12: 241283.87 | F12: 278889.32 | G12: 325315.22 | H12: 382440.03 | I12: 452546.39 | J12: 538403.81 | K12: 643368.98 | L12: 771507.16 | M12: 927738.95 | N12: 1118017.6 | O12: 1349543.3 | P12: 1631021.4 | Q12: 1972975 | R12: 2388121 | S12: 2891825.2 | T12: 3502650.2 | U12: 4243017.7 | V12: 5140006.2
A13: Assets less liabilities less equity | C13: -5.8207661e-11 | D13: -2.910383e-11 | E13: 0 | F13: -5.8207661e-11 | G13: 1.1641532e-10 | H13: 5.8207661e-11 | I13: 5.8207661e-11 | J13: 1.1641532e-10 | K13: 3.4924597e-10 | L13: 1.1641532e-10 | M13: 1.1641532e-10 | N13: 0 | O13: 2.3283064e-10 | P13: -4.6566129e-10 | Q13: -4.6566129e-10 | R13: -9.3132257e-10 | S13: -9.3132257e-10 | T13: -4.6566129e-10 | U13: -9.3132257e-10 | V13: 1.8626451e-09

Sheet Cash Flow
A1: EGP mn | B1: 2026 | C1: 2027 | D1: 2028 | E1: 2029 | F1: 2030 | G1: 2031 | H1: 2032 | I1: 2033 | J1: 2034 | K1: 2035 | L1: 2036 | M1: 2037 | N1: 2038 | O1: 2039 | P1: 2040 | Q1: 2041 | R1: 2042 | S1: 2043 | T1: 2044 | U1: 2045
A2: Operating cash flow | B2: 24347.308 | C2: 29611.923 | D2: 36150.968 | E2: 44208.879 | F2: 54088.437 | G2: 66161.186 | H2: 80880.432 | I2: 98797.266 | J2: 120580.14 | K2: 147038.67 | L2: 179152.55 | M2: 218106.41 | N2: 265332.17 | O2: 322559.98 | P2: 391879.92 | Q2: 475816.34 | R2: 577417.67 | S2: 700364.76 | T2: 849101.67 | U2: 1028993.4
A3: Capital spend | B3: -2318.6694 | C3: -2793.0413 | D3: -3364.6281 | E3: -4053.3875 | F3: -4883.3822 | G3: -5883.6256 | H3: -7089.1024 | I3: -8541.9999 | J3: -10293.194 | K3: -12404.041 | L3: -14948.544 | M3: -18015.961 | N3: -21713.956 | O3: -26172.407 | P3: -31547.993 | Q3: -38029.74 | R3: -45845.708 | S3: -55271.075 | T3: -66637.885 | U3: -80346.827
A4: Dividends | B4: -3800.3343 | C4: -4781.6844 | D4: -5964.994 | E4: -7396.5067 | F4: -9131.3761 | G4: -11235.715 | H4: -13789.017 | I4: -16887.048 | J4: -20645.296 | K4: -25203.129 | L4: -30728.781 | M4: -37425.364 | N4: -45538.115 | O4: -55363.123 | P4: -67257.858 | Q4: -81653.874 | R4: -99072.119 | S4: -120141.41 | T4: -145620.73 | U4: -176426.08
A5: Movement in customer advances | B5: -772.37375 | C5: 5965.8999 | D5: 12328.641 | E5: 18671.54 | F5: 25313.727 | G5: 32557.381 | H5: 40704.539 | I5: 50072.207 | J5: 61006.72 | K5: 73898.117 | L5: 89195.28 | M5: 107422.49 | N5: 129198.11 | O5: 155256.06 | P5: 186471.03 | Q5: 223888.05 | R5: 268757.77 | S5: 322578.41 | T5: 387145.9 | U5: 464613.94
A6: Movement in work in progress | B6: 854.9315 | C6: -6603.5851 | D6: -13646.429 | E6: -20667.31 | F6: -28019.469 | G6: -36037.385 | H6: -45055.379 | I6: -55424.343 | J6: -67527.627 | K6: -81796.964 | L6: -98729.216 | M6: -118904.7 | N6: -143007.88 | O6: -171851.13 | P6: -206402.61 | Q6: -247819.07 | R6: -297484.84 | S6: -357058.28 | T6: -428527.28 | U6: -514275.75
A7: Free cash flow to the firm | B7: 13543.19 | C7: 15508.047 | D7: 18059.74 | E7: 21271.582 | F7: 25243.503 | G7: 30104.588 | H7: 36016.872 | I7: 43180.449 | J7: 51840.054 | K7: 62293.288 | L7: 74900.772 | M7: 90098.562 | N7: 108413.23 | O7: 130480.18 | P7: 157065.75 | Q7: 189093.94 | R7: 227678.72 | S7: 274162.98 | T7: 330165.47 | U7: 397637.59
A8: Closing cash and deposits | B8: 94001.704 | C8: 116038.9 | D8: 142860.25 | E8: 175619.23 | F8: 215692.91 | G8: 264734.76 | H8: 324737.07 | I8: 398105.29 | J8: 487746.94 | K8: 597178.44 | L8: 730653.66 | M8: 893318.75 | N8: 1091398.8 | O8: 1332423.3 | P8: 1625497.4 | Q8: 1981630.1 | R8: 2414129.9 | S8: 2939082.2 | T8: 3575925.3 | U8: 4348145.8

Sheet Summary Financials
A1: EGP mn | B1: 2026 | C1: 2027 | D1: 2028 | E1: 2029 | F1: 2030 | G1: 2031 | H1: 2032 | I1: 2033 | J1: 2034 | K1: 2035 | L1: 2036 | M1: 2037 | N1: 2038 | O1: 2039 | P1: 2040 | Q1: 2041 | R1: 2042 | S1: 2043 | T1: 2044 | U1: 2045
A2: Revenue | B2: 80502.498 | C2: 96868.95 | D2: 116567.2 | E2: 140276.49 | F2: 168814.71 | G2: 203166.83 | H2: 244518.99 | I2: 294299.72 | J2: 354229.51 | K2: 426380.63 | L2: 513249.12 | M2: 617841.63 | N2: 743780.03 | O2: 895427.54 | P2: 1078040.7 | Q2: 1297952.5 | R2: 1562793.5 | S2: 1881757.8 | T2: 2265924.3 | U2: 2728643.3
A3: Gross margin | B3: 0.31630616 | C3: 0.31631385 | D3: 0.31632162 | E3: 0.31632948 | F3: 0.31633742 | G3: 0.31634545 | H3: 0.31635356 | I3: 0.31636176 | J3: 0.31637005 | K3: 0.31637842 | L3: 0.31638689 | M3: 0.31639544 | N3: 0.31640407 | O3: 0.3164128 | P3: 0.31642161 | Q3: 0.31643051 | R3: 0.3164395 | S3: 0.31644857 | T3: 0.31645774 | U3: 0.31646699
A4: Operating margin | B4: 0.2346008 | C4: 0.23686103 | D4: 0.23871838 | E4: 0.24024484 | F4: 0.24149954 | G4: 0.24253106 | H4: 0.2433793 | I4: 0.24407704 | J4: 0.24465121 | K4: 0.2451239 | L4: 0.24551329 | M4: 0.24583428 | N4: 0.24609914 | O4: 0.2463179 | P4: 0.24649885 | Q4: 0.24664876 | R4: 0.2467732 | S4: 0.24687675 | T4: 0.24696315 | U4: 0.2470355
A5: Net profit | B5: 23122.06 | C5: 29092.806 | D5: 36292.319 | E5: 45001.953 | F5: 55557.275 | G5: 68360.529 | H5: 83895.376 | I5: 102744.47 | J5: 125610.46 | K5: 153341.31 | L5: 186960.58 | M5: 227704.05 | N5: 277063.78 | O5: 336841.26 | P5: 409211.42 | Q5: 496799.9 | R5: 602776.29 | S5: 730966.46 | T5: 885988.16 | U5: 1073414.6
A6: Attributable profit | B6: 12667.781 | C6: 15938.948 | D6: 19883.313 | E6: 24655.022 | F6: 30437.92 | G6: 37452.382 | H6: 45963.391 | I6: 56290.159 | J6: 68817.653 | K6: 84010.43 | L6: 102429.27 | M6: 124751.21 | N6: 151793.72 | O6: 184543.74 | P6: 224192.86 | Q6: 272179.58 | R6: 330240.4 | S6: 400471.38 | T6: 485402.44 | U6: 588086.94
A7: Earnings per share, EGP | B7: 6.1474572 | C7: 7.7348985 | D7: 9.6490315 | E7: 11.96466 | F7: 14.771001 | G7: 18.175 | H7: 22.305246 | I7: 27.31665 | J7: 33.396029 | K7: 40.768823 | L7: 49.70717 | M7: 60.539628 | N7: 73.662892 | O7: 89.555918 | P7: 108.79696 | Q7: 132.08409 | R7: 160.26001 | S7: 194.3419 | T7: 235.55749 | U7: 285.38852
A8: New contracted sales | B8: 49732.598 | C8: 75979.888 | D8: 104759.84 | E8: 137031.79 | F8: 173871.46 | G8: 216506.86 | H8: 266359.14 | I8: 325090.06 | J8: 394657.32 | K8: 477379.83 | L8: 576014.99 | M8: 693850.65 | N8: 834814.67 | O8: 1003605.8 | P8: 1205850.5 | Q8: 1448290.3 | R8: 1739006.3 | S8: 2087689.3 | T8: 2505961.9 | U8: 3007766.5
A9: Order book, closing | B9: 491395.37 | C9: 508170.59 | D9: 541884.83 | E9: 593661.9 | F9: 665227.7 | G9: 758967.75 | H9: 878006.73 | I9: 1026312.6 | J9: 1208828.9 | K9: 1431639.5 | L9: 1702171.4 | M9: 2029442.3 | N9: 2424361.3 | O9: 2900092.4 | P9: 3472493.2 | Q9: 4160643.8 | R9: 4987482.5 | S9: 5980570.7 | T9: 7173011.2 | U9: 8604552
A10: Order book, years of deliveries | B10: 9.9599315 | C10: 8.5832858 | D10: 7.6272818 | E10: 6.9633901 | F10: 6.5023543 | G10: 6.1821905 | H10: 5.9598545 | I10: 5.8054545 | J10: 5.6982323 | K10: 5.6237724 | L10: 5.5720642 | M10: 5.5361557 | N10: 5.5112192 | O10: 5.4939022 | P10: 5.4818766 | Q10: 5.4735254 | R10: 5.467726 | S10: 5.4636986 | T10: 5.4609018 | U10: 5.4589596

Sheet Monte Carlo
A1: Horizon | B1: 5th | C1: 25th | D1: 50th | E1: 75th | F1: 95th | G1: Resolves
A2: 1 month | B2: 86.73 | C2: 95 | D2: 99.95 | E2: 105.22 | F2: 115.25 | G2: 2026-09-23
A3: 3 months | B3: 80.5 | C3: 94.74 | D3: 103.82 | E3: 113.76 | F3: 133.71 | G3: 2026-11-23
A5: These describe the PRICE, not the business. They are produced independently of the valuation and are shown beside it so that agreement is information rather than repetition.

Sheet Sensitivity
A1: Discount rate | B1: Slower conversion, EGP/share | C1: Faster conversion, EGP/share | D1: Against last close
A2: 0.24 | B2: 156.08381 | C2: 237.82173 | D2: =B2/'Summary'!$B$2-1
A3: 0.26 | B3: 105.91034 | C3: 153.40611 | D3: =B3/'Summary'!$B$2-1
A4: 0.28 | B4: 80.874091 | C4: 112.14566 | D4: =B4/'Summary'!$B$2-1
A5: 0.3157 | B5: 57.755268 | C5: 75.179534 | D5: =B5/'Summary'!$B$2-1
A6: 0.3237 | B6: 54.411057 | C6: 69.981606 | D6: =B6/'Summary'!$B$2-1
A7: 0.3579 | B7: 43.947533 | C7: 54.090193 | D7: =B7/'Summary'!$B$2-1
A8: 0.4 | B8: 35.992405 | C8: 42.511381 | D8: =B8/'Summary'!$B$2-1
A10: Years to convert the order book | B10: EGP per share
A11: 8 | B11: 43.939369
A12: 10 | B12: 43.939369
A13: 12 | B13: 43.939369
A14: 14 | B14: 43.939369
A15: 16 | B15: 43.939369
A16: 20 | B16: 43.939369

Sheet Per-Share & Ratios
A1: Measure | B1: Value | C1: Note
A2: Book value per share, EGP | B2: 44.486318
A3: Earnings per share 2025, EGP | B3: 6.98
A4: Price to earnings at last close | B4: ='Summary'!B2/B3
A5: Price to book at last close | B5: ='Summary'!B2/B2
A6: Return on equity 2025 | B6: 0.16655888
A7: Cost of equity, rating basis | B7: 0.37146228
A8: Cost of equity, swap basis | B8: 0.3343919
A9: Net cash, EGP mn | B9: 58766.5
A10: Order book, EGP mn | B10: 491000
A11: Order book per share, EGP | B11: =B10/'Summary'!$B$3
A12: Minority share of consolidated equity | B12: 0.45213467

Sheet Peer & Sector
A1: Company | B1: Last close, EGP | C1: As at | D1: Why it is a comparator
A2: Emaar Misr for Development | B2: 11.53 | C2: 2026-07-28 | D2: off-plan developer, comparable payment plans and handover clock
A3: Sixth of October Development & Investment (SODIC) | B3: 27.48 | C3: 2026-07-27 | D3: integrated-community developer, similar product mix
A4: Palm Hills Developments | B4: 15.2 | C4: 2026-08-23 | D4: closest listed comparator by scale and by land position; note it recognises revenue on PERCENTAGE OF COMPLETION, not handover, so its margin and revenue timing are not directly comparable
A5: Heliopolis Housing & Development | B5: 7.75 | C5: 2026-08-23 | D5: land-rich developer with a comparable legacy landbank
A6: Orascom Development Egypt | B6: 40.16 | C6: 2026-07-27 | D6: developer with a substantial hospitality leg — the nearest listed analogue for TMG's three-segment shape
A8: Emaar Properties (DFM: EMAAR) | C8: UAE | D8: the regional template for a developer with a large recurring-income and hospitality platform alongside a development book
A9: Aldar Properties (ADX: ALDAR) | C9: UAE | D9: development plus investment-property and management legs, with a disclosed backlog the market prices explicitly
A10: Dar Al Arkan (Tadawul: 4300) | C10: Saudi Arabia | D10: the market TMG has just entered with Banan; a reference for how a Saudi development book is priced
A12: Peer MULTIPLES are not tabulated here. This study holds committed price libraries for the Egyptian names but has not sourced their financial statements, and a peer multiple built on an unsourced denominator is a number wearing a decimal point. The relative lens is therefore built on TMGH's OWN history of multiples, which is sourced end to end, and the peer set is carried as context with its sourcing stated.
