Workbook

Sheet READ FIRST
A1: TALAAT MOUSTAFA GROUP HOLDING — valuation workbook
A2: Egyptian Exchange · TMGH · Egyptian pounds · 2026-09-10
A4: BLUE cells are inputs. BLACK cells are formulas. Change a blue cell and the value per share on the Summary sheet recomputes.
A6: This workbook contains no recommendation, no target price and no rating.
A8: The four cases on the Summary sheet are alternatives, not a distribution. They are two ways of measuring Egypt's equity risk premium crossed with two readings of how fast the order book converts. They are never averaged.
A10: Sheet order: READ FIRST · Summary · Fundamental Valuation · Assumptions · SOTP Bridge · Segments · Relative & Normalized · DCF · Income Statement · Balance Sheet · Cash Flow · Summary Financials · Monte Carlo · Sensitivity · Per-Share & Ratios · Peer & Sector

Sheet Summary
A1: Summary | B1: Value | C1: Note
A2: Last close, EGP | B2: 96.6 | C2: Egyptian Exchange close for 2 September 2026, the latest price this repository holds for this name, read from the committed supplied price file through gap_today.latest_price_per_ticker(). SUPERSEDES the 23 August 2026 close of 97.80 the study was struck at: a fair value put against a price ten days old is a comparison a reader cannot use, however good the fair value is.
A3: Shares in issue, million | B3: 2060.6538
A4: Market capitalisation, EGP mn | B4: =B2*B3
A6: Case | B6: Enterprise value | C6: Equity value (adopted basis) | D6: Per share, minority at value share (adopted) | E6: Per share, minority at book | F6: Against last close
A7: Rating premium, slower conversion | B7: 294735.93 | C7: 301894.24 | D7: =C7/$B$3 | E7: 148.67953 | F7: =D7/$B$2-1
A8: Rating premium, faster conversion | B8: 133147.97 | C8: 174201.39 | D8: =C8/$B$3 | E8: 70.263655 | F8: =D8/$B$2-1
A9: Swap premium, slower conversion | B9: 301876.89 | C9: 307537.29 | D9: =C9/$B$3 | E9: 152.14491 | F9: =D9/$B$2-1
A10: Swap premium, faster conversion | B10: 136359.33 | C10: 176739.13 | D10: =C10/$B$3 | E10: 71.822075 | F10: =D10/$B$2-1
A12: Lowest published case, EGP/share | B12: =MIN(D7:D10)
A13: Highest published case, EGP/share | B13: =MAX(D7:D10)
A15: Discount rate the last close implies, slower conversion | B15: 0.32319862
A16: Discount rate the last close implies, faster conversion | B16: 0.1757914
A17: Cost of capital, first year | B17: 0.31557656
A18: Cost of capital, once normalised | B18: 0.1748067

Sheet Fundamental Valuation
A1: Lens | B1: Low, EGP/share | C1: High, EGP/share | D1: What it measures
A2: Cash flow, sum of the parts | B2: 70.263655 | C2: 152.14491 | D2: the order book, hotels and recurring businesses, discounted
A3: Book value and sustainable return | B3: 4.1937215 | C3: 14.112605 | D3: return on equity of 16.7% against a cost of equity of 32.6%
A4: Normalised earnings power | B4: 18.575721 | C4: 27.421483 | D4: three years of profit with revaluation gains removed, capitalised
A5: Its own history of multiples | B5: 34.040011 | C5: 57.999136 | D5: the multiples these shares have actually carried, on normalised earnings

Sheet Assumptions
A1: Assumption | B1: Value | C1: Where it comes from
A2: Development gross margin, first half 2026 | B2: 0.26578929 | C2: an output of the disclosed cost line, not an input
A3: Hospitality gross margin, first half 2026 | B3: 0.45371295 | C3: an output of the disclosed cost line
A4: Other recurring gross margin, first half 2026 | B4: 0.31910573 | C4: an output of the disclosed cost line
A5: Overhead as a share of revenue, 2025 | B5: 0.067510893 | C5: general and administrative, marketing and government charges over revenue
A6: Collections on the order book, a year | B6: 0.075697294 | C6: from the movement in customer advances in the first half of 2026
A7: Work in progress, years of cost | B7: 4 | C7: the company's own position at 30 June 2026
A8: Marginal borrowing rate | B8: 0.255 | C8: sovereign yield plus a 250 basis-point corporate spread; TMG does not disclose its own facility pricing
A9: Hospitality revenue growth | B9: 0.2 | C9: stated
A10: Other recurring revenue growth | B10: 0.22 | C10: stated
A11: Order book converts over, years — slower | B11: 14 | C11: the crux, read one way
A12: Order book converts over, years — faster | B12: 10 | C12: the crux, read the other way
A13: Normalised annual contracted sales, EGP mn | B13: 300000 | C13: below the 2025 figure and far below 2024's launch year
... A17: Dividend payout | B17: 0.3 | C17: the company's recent behaviour

Sheet SOTP Bridge
A1: Bridge, slower-conversion case | B1: EGP mn
A2: Present value of the explicit ten years | B2: 221850.04
A3: Present value of the order book beyond it | B3: 24044.061
A4: Present value of the recurring businesses beyond it | B4: 48841.829
A5: Enterprise value | B5: =SUM(B2:B4)
A6: Cash, deposits and amortised-cost assets | B6: 75773.4
A7: Borrowings | B7: -16493
A8: Lease liabilities | B8: -513.9
A9: Investment property | B9: 25228
A10: Associates and other financial assets | B10: 3299.4
A11: Value of the whole group's equity | B11: =B5+SUM(B6:B10)
A12: Non-controlling interests at their share of value (adopted) | B12: -80135.595
A13: reference: minority at book — NOT deducted below | B13: -75652.8
A14: Equity attributable to TMG's shareholders | B14: =B11+B12
A15: Shares in issue, million | B15: 2060.6538
A16: Value per share, EGP | B16: =B14/B15

Sheet Segments
A1: Segment | B1: FY2025 revenue | C1: FY2025 cost | D1: Gross profit | E1: Gross margin | F1: 1H2026 revenue | G1: 1H2026 cost | H1: 1H2026 margin
A2: Real-estate development | B2: 36705.7 | C2: 26645.4 | D2: =B2-C2 | E2: =D2/B2 | F2: 16967.2 | G2: 12457.5 | H2: =(F2-G2)/F2
A3: Hospitality | B3: 14889.7 | C3: 7800.6 | D3: =B3-C3 | E3: =D3/B3 | F3: 7512.9 | G3: 4104.2 | H3: =(F3-G3)/F3
A4: Other recurring income | B4: 10899.7 | C4: 7193.7 | D4: =B4-C4 | E4: =D4/B4 | F4: 5711.9 | G4: 3889.2 | H4: =(F4-G4)/F4
A5: Total | B5: =SUM(B2:B4) | C5: =SUM(C2:C4) | D5: =SUM(D2:D4) | E5: =D5/B5 | F5: =SUM(F2:F4) | G5: =SUM(G2:G4) | H5: =(F5-G5)/F5

Sheet Relative & Normalized
A1: Year end | B1: Close, EGP | C1: Earnings per share | D1: Price to earnings | E1: Book value per share | F1: Price to book
A2: 2011 | B2: 2.96
A3: 2012 | B3: 4.43
A4: 2013 | B4: 6.18
A5: 2014 | B5: 9.86
A6: 2015 | B6: 6.47
A7: 2016 | B7: 9.13
A8: 2017 | B8: 9.8 | C8: 0.64387332 | D8: =B8/C8
A9: 2018 | B9: 9.89 | C9: 0.82731024 | D9: =B9/C9
A10: 2019 | B10: 8.17 | C10: 0.9085466 | D10: =B10/C10
A11: 2020 | B11: 6.57
A12: 2021 | B12: 9.07 | C12: 0.85492284 | D12: =B12/C12
A13: 2022 | B13: 9.99 | C13: 1.1183344 | D13: =B13/C13
A14: 2023 | B14: 24.15 | C14: 1.6079075 | D14: =B14/C14 | E14: 18.610022 | F14: =B14/E14
A15: 2024 | B15: 56 | C15: 5.2037368 | D15: =B15/C15
A16: 2025 | B16: 80 | C16: 6.9802556 | D16: =B16/C16 | E16: 39.331001 | F16: =B16/E16
A18: Normalised earnings | B18: EGP mn
A19: Attributable profit 2023, cleaned | B19: 3313.3
A20: Attributable profit 2024, cleaned | B20: 8025.3563
A21: Attributable profit 2025, cleaned | B21: 12218.462
A22: Average | B22: 7852.3729
A23: Average per share, EGP | B23: =B22/'Summary'!$B$3

Sheet DCF
A1: Discounted cash flow, slower conversion | B1: 2026 | C1: 2027 | D1: 2028 | E1: 2029 | F1: 2030 | G1: 2031 | H1: 2032 | I1: 2033 | J1: 2034 | K1: 2035
A2: Revenue | B2: 80502.498 | C2: 94071.892 | D2: 113309.54 | E2: 138282 | F2: 169256.39 | G2: 206703.06 | H2: 251304.61 | I2: 303971.58 | J2: 365865.29 | K2: 438428.53
A3: Cost of revenue | B3: 55039.062 | C3: 64174.329 | D3: 77302.667 | E3: 94438.527 | F3: 115736.59 | G3: 141492.27 | H3: 172146.61 | I3: 208295.72 | J3: 250705.02 | K3: 300328.69
A4: Gross profit | B4: 25463.436 | C4: 29897.563 | D4: 36006.876 | E4: 43843.475 | F4: 53519.804 | G4: 65210.794 | H4: 79157.998 | I4: 95675.855 | J4: 115160.27 | K4: 138099.83
A5: Overheads | B5: 5434.7955 | C5: 6350.8774 | D5: 7649.6284 | E5: 9335.5414 | F5: 11426.65 | G5: 13954.708 | H5: 16965.798 | I5: 20521.393 | J5: 24699.893 | K5: 29598.701
A6: Depreciation | B6: 1142.6904 | C6: 1156.8021 | D6: 1176.437 | E6: 1202.6953 | F6: 1236.9036 | G6: 1280.6614 | H6: 1335.8969 | I6: 1404.9354 | J6: 1490.5802 | K6: 1596.2115
A7: Operating profit | B7: 18885.95 | C7: 22389.883 | D7: 27180.81 | E7: 33305.238 | F7: 40856.251 | G7: 49975.425 | H7: 60856.303 | I7: 73749.527 | J7: 88969.802 | K7: 106904.92
A8: Free cash flow to the firm | B8: 24854.899 | C8: 37015.786 | D8: 47341.395 | E8: 56941.585 | F8: 66665.506 | G8: 77186.228 | H8: 89064.818 | I8: 102799.56 | J8: 118864.63 | K8: 137741.58
A9: Cost of capital, this year's forward rate | B9: 0.31557656 | C9: 0.26534911 | D9: 0.22516714 | E9: 0.19503067 | F9: 0.17493968 | G9: 0.17493968 | H9: 0.17493968 | I9: 0.17493968 | J9: 0.17493968 | K9: 0.17493968
A10: Discount factor | B10: =1/(1+B9) | C10: =B10/(1+C9) | D10: =C10/(1+D9) | E10: =D10/(1+E9) | F10: =E10/(1+F9) | G10: =F10/(1+G9) | H10: =G10/(1+H9) | I10: =H10/(1+I9) | J10: =I10/(1+J9) | K10: =J10/(1+K9)
A11: Present value | B11: =B8*B10 | C11: =C8*C10 | D11: =D8*D10 | E11: =E8*E10 | F11: =F8*F10 | G11: =G8*G10 | H11: =H8*H10 | I11: =I8*I10 | ... K11: =K8*K10
A13: Sum of the explicit years | B13: =SUM(B11:K11)
A14: Order book still unconverted, present value | B14: 24044.061
A15: Recurring businesses beyond the window, present value | B15: 48841.829
A16: Enterprise value | B16: =B13+B14+B15

Sheet Income Statement
A1: EGP mn | B1: 2023 | C1: 2024 | D1: 2025 | E1: 2026 | F1: 2027 | G1: 2028 | H1: 2029 | I1: 2030 | J1: 2031 | K1: 2032 | L1: 2033 | M1: 2034 | N1: 2035
A2: Development revenue | B2: 21578.7 | C2: 24518.3 | D2: 36705.7 | E2: 49337.224 | F2: 56407.611 | G2: 67787.943 | H2: 83260.238 | I2: 102747.35 | J2: 126303.03 | K2: 154105.78 | L2: 186456.06 | M2: 223776.82 | N2: 266617.14
A3: Hospitality revenue | B3: 3540.9 | C3: 11496.5 | D3: 14889.7 | E3: 17867.64 | F3: 21441.168 | G3: 25729.402 | H3: 30875.282 | I3: 37050.338 | J3: 44460.406 | K3: 53352.487 | L3: 64022.985 | M3: 76827.582 | N3: 92193.098
A4: Other recurring revenue | B4: 3311.7 | C4: 6655.5 | D4: 10899.7 | E4: 13297.634 | F4: 16223.113 | G4: 19792.198 | H4: 24146.482 | I4: 29458.708 | J4: 35939.624 | K4: 43846.341 | L4: 53492.536 | M4: 65260.894 | N4: 79618.291
A5: Gross profit | B5: 8637.3 | C5: 15300.2 | D5: 20855.4 | E5: 25463.436 | F5: 29897.563 | G5: 36006.876 | H5: 43843.475 | I5: 53519.804 | J5: 65210.794 | K5: 79157.998 | L5: 95675.855 | M5: 115160.27 | N5: 138099.83
A6: Net profit | B6: 3347.3 | C6: 14467.5 | D6: 18202 | E6: 23122.06 | F6: 30416.309 | G6: 41116.789 | H6: 55261.664 | I6: 73096.578 | J6: 95057.014 | K6: 121762.45 | L6: 154020.57 | M6: 192840.45 | N6: 239454.21
A7: Attributable profit | B7: 3313.3 | C7: 10723.1 | D7: 14383.9 | E7: 12667.781 | F7: 16664.05 | G7: 22526.475 | H7: 30275.965 | I7: 40047.101 | J7: 52078.468 | K7: 66709.458 | L7: 84382.574 | M7: 105650.65 | N7: 131188.72
A8: Earnings per share, EGP | B8: 1.6078877 | C8: 5.2037368 | D8: 6.9802603 | E8: 6.1474572 | F8: 8.0867779 | G8: 10.931712 | H8: 14.692407 | I8: 19.434172 | J8: 25.272789 | K8: 32.372958 | L8: 40.949418 | M8: 51.270452 | N8: 63.663641

Sheet Balance Sheet
A1: EGP mn | B1: 30 Jun 2026 reported | C1: 2026 | D1: 2027 | E1: 2028 | F1: 2029 | G1: 2030 | H1: 2031 | I1: 2032 | J1: 2033 | K1: 2034 | L1: 2035
A2: Cash and deposits | C2: 105313.41 | D2: 150394.13 | E2: 211029.25 | F2: 288338.15 | G2: 384422.51 | H2: 502311.26 | I2: 645962.05 | J2: 820311.52 | K2: 1031369.8 | L2: 1286357.7
A3: Properties under development | B3: 148315.4 | C3: 147460.47 | D3: 152010.42 | E3: 163778.45 | F3: 183964.4 | G3: 213411.5 | H3: 252791.66 | I3: 302739.86 | J3: 363952.93 | K3: 437264.04 | L3: 523701.19
A4: Property, plant and equipment | B4: 73322.7 | C4: 96400.179 | D4: 98036.418 | E4: 100224.61 | F4: 103075.3 | G4: 106721.78 | H4: 111324.74 | I4: 117077.95 | J4: 124215.01 | K4: 133017.63 | L4: 143825.46
A5: Investment property | B5: 25228 | C5: 25228 | D5: 25228 | E5: 25228 | F5: 25228 | G5: 25228 | H5: 25228 | I5: 25228 | J5: 25228 | K5: 25228 | L5: 25228
A6: Total assets | B6: 477897.9 | C6: 507758.96 | D6: 559025.88 | E6: 633617.21 | F6: 733962.75 | G6: 863140.69 | H6: 1025012.6 | I6: 1224364.8 | J6: 1467064.4 | K6: 1760236.4 | L6: 2112469.2
A7: Customer advances | B7: 133993.1 | C7: 144532.44 | D7: 170382.26 | E7: 210614.74 | F7: 264781.41 | G7: 332876.9 | H7: 415315.3 | I7: 512917.89 | J7: 626911.7 | K7: 758938.45 | L7: 911073.7
A8: Borrowings | C8: 16493 | D8: 16493 | E8: 16493 | F8: 16493 | G8: 16493 | H8: 16493 | I8: 16493 | J8: 16493 | K8: 16493 | L8: 16493
A9: Total liabilities | B9: 310574.2 | C9: 321113.54 | D9: 346963.36 | E9: 387195.84 | F9: 441362.51 | G9: 509458 | H9: 591896.4 | I9: 689498.99 | J9: 803492.8 | K9: 935519.55 | L9: 1087654.8
A10: Equity attributable to TMG | B10: 91670.9 | C10: 100538.35 | D10: 112203.18 | E10: 127971.71 | F10: 149164.89 | G10: 177197.86 | H10: 213652.79 | I10: 260349.41 | J10: 319417.21 | K10: 393372.67 | L10: 485204.77
A11: Non-controlling interests | B11: 75652.8 | C11: 86107.078 | D11: 99859.338 | E11: 118449.65 | F11: 143435.35 | G11: 176484.83 | H11: 219463.37 | I11: 274516.37 | J11: 344154.36 | K11: 431344.17 | L11: 539609.65
A12: Total equity | B12: 167323.6 | C12: 186645.43 | D12: 212062.52 | E12: 246421.37 | F12: 292600.24 | G12: 353682.69 | H12: 433116.16 | I12: 534865.77 | J12: 663571.57 | K12: 824716.83 | L12: 1024814.4
A13: Assets less liabilities less equity | C13: -5.8207661e-11 | D13: -5.8207661e-11 | E13: 5.8207661e-11 | F13: -1.1641532e-10 | G13: 5.8207661e-11 | H13: 0 | I13: -2.3283064e-10 | J13: 2.3283064e-10 | K13: 1.1641532e-10 | L13: 0

Sheet Cash Flow
A1: EGP mn | B1: 2026 | C1: 2027 | D1: 2028 | E1: 2029 | F1: 2030 | G1: 2031 | H1: 2032 | I1: 2033 | J1: 2034 | K1: 2035
A2: Operating cash flow | B2: 35659.016 | C2: 52872.977 | D2: 70757.684 | E2: 90445.077 | F2: 112981.87 | G2: 139395.91 | H2: 170752.74 | I2: 208206.25 | J2: 253046.69 | K2: 306748.52
A3: Capital spend | B3: -2318.6694 | C3: -2793.0413 | D3: -3364.6281 | E3: -4053.3875 | F3: -4883.3822 | G3: -5883.6256 | H3: -7089.1024 | I3: -8541.9999 | J3: -10293.194 | K3: -12404.041
A4: Dividends | B4: -3800.3343 | C4: -4999.2149 | D4: -6757.9424 | E4: -9082.7895 | F4: -12014.13 | G4: -15623.54 | H4: -20012.837 | I4: -25314.772 | J4: -31695.195 | K4: -39356.617
A5: Movement in customer advances | B5: 10539.335 | C5: 25849.821 | D5: 40232.486 | E5: 54166.664 | F5: 68095.493 | G5: 82438.401 | H5: 97602.587 | I5: 113993.81 | J5: 132026.76 | K5: 152135.25
A6: Movement in work in progress | B6: 854.9315 | C6: -4549.9548 | D6: -11768.028 | E6: -20185.946 | F6: -29447.103 | G6: -39380.163 | H6: -49948.198 | I6: -61213.07 | J6: -73311.104 | K6: -86437.151
A7: Free cash flow to the firm | B7: 24854.899 | C7: 37015.786 | D7: 47341.395 | E7: 56941.585 | F7: 66665.506 | G7: 77186.228 | H7: 89064.818 | I7: 102799.56 | J7: 118864.63 | K7: 137741.58
A8: Closing cash and deposits | B8: 105313.41 | C8: 150394.13 | D8: 211029.25 | E8: 288338.15 | F8: 384422.51 | G8: 502311.26 | H8: 645962.05 | I8: 820311.52 | J8: 1031369.8 | K8: 1286357.7

Sheet Summary Financials
A1: EGP mn | B1: 2026 | C1: 2027 | D1: 2028 | E1: 2029 | F1: 2030 | G1: 2031 | H1: 2032 | I1: 2033 | J1: 2034 | K1: 2035
A2: Revenue | B2: 80502.498 | C2: 94071.892 | D2: 113309.54 | E2: 138282 | F2: 169256.39 | G2: 206703.06 | H2: 251304.61 | I2: 303971.58 | J2: 365865.29 | K2: 438428.53
A3: Gross margin | B3: 0.31630616 | C3: 0.31781611 | D3: 0.31777443 | E3: 0.31705844 | F3: 0.31620551 | G3: 0.31548054 | H3: 0.31498825 | I3: 0.31475263 | J3: 0.31476141 | K3: 0.31498825
A4: Operating margin | B4: 0.2346008 | C4: 0.23800821 | D4: 0.23988103 | E4: 0.24085013 | F4: 0.24138675 | G4: 0.24177399 | H4: 0.24216151 | I4: 0.24261981 | J4: 0.24317639 | K4: 0.2438366
A5: Net profit | B5: 23122.06 | C5: 30416.309 | D5: 41116.789 | E5: 55261.664 | F5: 73096.578 | G5: 95057.014 | H5: 121762.45 | I5: 154020.57 | J5: 192840.45 | K5: 239454.21
A6: Attributable profit | B6: 12667.781 | C6: 16664.05 | D6: 22526.475 | E6: 30275.965 | F6: 40047.101 | G6: 52078.468 | H6: 66709.458 | I6: 84382.574 | J6: 105650.65 | K6: 131188.72
A7: Earnings per share, EGP | B7: 6.1474572 | C7: 8.0867779 | D7: 10.931712 | E7: 14.692407 | F7: 19.434172 | G7: 25.272789 | H7: 32.372958 | I7: 40.949418 | J7: 51.270452 | K7: 63.663641
A8: New contracted sales | B8: 300000 | C8: 345000 | D8: 396750 | E8: 456262.5 | F8: 524701.87 | G8: 603407.16 | H8: 693918.23 | I8: 798005.96 | J8: 917706.86 | K8: 1055362.9
A9: Order book, closing | B9: 741662.78 | C9: 1030255.2 | D9: 1359217.2 | E9: 1732219.5 | F9: 2154174 | G9: 2631278.1 | H9: 3171090.6 | I9: 3782640.5 | J9: 4476570.5 | K9: 5265316.3
A10: Order book, years of deliveries | B10: 15.032519 | C10: 18.264471 | D10: 20.051017 | E10: 20.804883 | F10: 20.965739 | G10: 20.833056 | H10: 20.577363 | I10: 20.287035 | J10: 20.004621 | K10: 19.748604

Sheet Monte Carlo
A1: Horizon | B1: 5th | C1: 25th | D1: 50th | E1: 75th | F1: 95th | G1: Resolves
A2: 1 month | B2: 86.73 | C2: 95 | D2: 99.95 | E2: 105.22 | F2: 115.25 | G2: 2026-09-23
A3: 3 months | B3: 80.5 | C3: 94.74 | D3: 103.82 | E3: 113.76 | F3: 133.71 | G3: 2026-11-23
A5: These describe the PRICE, not the business. They are produced independently of the valuation and are shown beside it so that agreement is information rather than repetition.

Sheet Sensitivity
A1: Discount rate | B1: Slower conversion, EGP/share (minority at value share, adopted) | C1: Faster conversion, EGP/share (minority at value share, adopted) | D1: Against last close
A2: 0.22097935 | B2: 352.66928 | C2: 282.86961 | D2: =B2/'Summary'!$B$2-1
A3: 0.26097935 | B3: 198.32981 | C3: 129.45889 | D3: =B3/'Summary'!$B$2-1
A4: 0.28097935 | B4: 169.36905 | C4: 102.88407 | D4: =B4/'Summary'!$B$2-1
A5: 0.30097935 | B5: 149.24258 | C5: 85.768475 | D5: =B5/'Summary'!$B$2-1
A6: 0.32097935 | B6: 134.19487 | C6: 74.057508 | D6: =B6/'Summary'!$B$2-1
A7: 0.34097935 | B7: 122.42504 | C7: 65.749908 | D7: =B7/'Summary'!$B$2-1
A8: 0.38097935 | B8: 105.10747 | C8: 55.252963 | D8: =B8/'Summary'!$B$2-1
A10: Years to convert the order book | B10: EGP per share
A11: 8 | B11: 79.50601
A12: 10 | B12: 108.10588
A13: 12 | B13: 129.59655
A14: 14 | B14: 146.5041
A15: 16 | B15: 160.22788
A16: 20 | B16: 181.24716

Sheet Per-Share & Ratios
A1: Measure | B1: Value | C1: Note
A2: Book value per share, EGP | B2: 44.486318
A3: Earnings per share 2025, EGP | B3: 6.98
A4: Price to earnings at last close | B4: ='Summary'!B2/B3
A5: Price to book at last close | B5: ='Summary'!B2/B2
A6: Return on equity 2025 | B6: 0.16655888
A7: Cost of equity, rating basis | B7: 0.32565392
A8: Cost of equity, swap basis | B8: 0.30980957
A9: Net cash, EGP mn | B9: 58766.5
A10: Order book, EGP mn | B10: 491000
A11: Order book per share, EGP | B11: =B10/'Summary'!$B$3
A12: Minority share of consolidated equity | B12: 0.45213467

Sheet Peer & Sector
A1: Company | B1: Last close, EGP | C1: As at | D1: Why it is a comparator
A2: Emaar Misr for Development | B2: 13.7 | C2: 2026-09-01 | D2: off-plan developer, comparable payment plans and handover clock
A3: Sixth of October Development & Investment (SODIC) | B3: 31.01 | C3: 2026-09-01 | D3: integrated-community developer, similar product mix
A4: Palm Hills Developments | B4: 15.2 | C4: 2026-08-23 | D4: closest listed comparator by scale and by land position; note it recognises revenue on PERCENTAGE OF COMPLETION, not handover, so its margin and revenue timing are not directly comparable
A5: Heliopolis Housing & Development | B5: 7.75 | C5: 2026-08-23 | D5: land-rich developer with a comparable legacy landbank
A6: Orascom Development Egypt | B6: 41.5 | C6: 2026-09-01 | D6: developer with a substantial hospitality leg — the nearest listed analogue for TMG's three-segment shape
A8: Emaar Properties (DFM: EMAAR) | C8: UAE | D8: the regional template for a developer with a large recurring-income and hospitality platform alongside a development book
A9: Aldar Properties (ADX: ALDAR) | C9: UAE | D9: development plus investment-property and management legs, with a disclosed backlog the market prices explicitly
A10: Dar Al Arkan (Tadawul: 4300) | C10: Saudi Arabia | D10: the market TMG has just entered with Banan; a reference for how a Saudi development book is priced
A12: Peer MULTIPLES are not tabulated here. This study holds committed price libraries for the Egyptian names but has not sourced their financial statements, and a peer multiple built on an unsourced denominator is a number wearing a decimal point. The relative lens is therefore built on TMGH's OWN history of multiples, which is sourced end to end, and the peer set is carried as context with its sourcing stated.
