Workbook

Sheet READ FIRST
A1: Palm Hills Developments — valuation workbook
A2: Edition of 30 August 2026. Supersedes 11 June 2026.
A4: This workbook is for information and education. It is not investment advice and carries no rating and no price target.
A6: BLUE cells are inputs and live on the Assumptions sheet. BLACK cells are formulas. Change a blue cell and the statements, the discounted cash flow and the value per share all recompute.
A8: Reported history comes only from the company's own audited statements and its own results releases. Where a figure the valuation needs is not disclosed, it is absent and named on the Assumptions sheet rather than estimated.
A10: The single most important number in this workbook is cash conversion — the share of revenue that reaches operating cash flow. The company does not disclose its collection terms, so it is measured from the three published cash-flow statements and it spans 3.9% to 17.9%. The Sensitivity sheet shows what that does to the answer.

Sheet Summary
A1: Summary
A2: Every figure recomputes from Assumptions.
A4: Lens | B4: Bear | C4: Base | D4: Full value | E4: Weight
A5: Discounted cash flow | B5: 2.85 | C5: 14.86 | D5: 38.75 | E5: 0.45
A6: Book value of equity | B6: 5.91 | C6: 6.56 | D6: 8.53 | E6: 0.15
A7: Earnings multiple on own history | B7: 7.45 | C7: 11.17 | D7: 17.37 | E7: 0.2
A8: Normalised earnings power | B8: 4.72 | C8: 5.17 | D8: 5.72 | E8: 0.2
A9: Weighted central | B9: 4.6 | C9: 10.94 | D9: 23.33 | E9: 1
A11: Valuation | B11: Per share (EGP) | C11: Equity (EGP mn) | D11: Enterprise value
A12: Weak cash conversion (3.9%) | B12: 9.17 | C12: 26215 | D12: 45704
A13: Average cash conversion (8.7%) | B13: 19.3 | C13: 55208 | D13: 74697
A14: Strong cash conversion (17.9%) | B14: 38.74 | C14: 110792 | D14: 130281
A15: Average, alternative country-risk basis | B15: 21.44 | C15: 61314 | D15: 80803
A17: Market price, 23 Aug 2026 | B17: 15.2
A18: Book value of equity per share | B18: 6.56
A19: Cash conversion implied by the market price | B19: 0.0678
A21: Cost of capital
A22: Weighted average, rating basis | B22: 0.26250009
A23: Weighted average, swap basis | B23: 0.25237862
A24: Previous edition used | B24: 0.18

Sheet Fundamental Valuation
A1: Fundamental valuation — bridge to equity
A2: All formulas; drivers live on Assumptions.
A4: Present value of the explicit ten years | B4: 49459.8
A5: Present value of the terminal value | B5: 25237.2
A6: Enterprise value | B6: =B4+B5
A7: less net debt | B7: =-Assumptions!B13
A8: plus investments in associates | B8: =Assumptions!B14
A9: plus investment property | B9: =Assumptions!B15
A10: Equity value | B10: =B6+B7+B8+B9
A11: Shares outstanding (mn) | B11: =Assumptions!B16
A12: Value per share (EGP) | B12: =B10/B11
A14: Terminal value as a share of enterprise value | B14: =B5/B6

Sheet Assumptions
A1: Assumptions — every blue cell is an input
A2: Change one and the whole workbook recomputes.
A4: Driver | B4: Value | C4: Source
A5: Cash conversion — central | B5: 0.087136637 | C5: mean of the three published cash-flow statements
A6: Cash conversion — weak | B6: 0.039375935 | C6: 2023 and 2025 outcome
A7: Cash conversion — strong | B7: 0.17870013 | C7: 2024 outcome
A8: Gross margin | B8: 0.38322372 | C8: average of FY2025 and 1Q2026 as reported
A9: Overheads as a share of revenue | B9: 0.17599456 | C9: FY2025 as reported
A10: Delivery capacity growth | B10: 0.252 | C10: Egyptian consumer price inflation, three-year mean
A11: Terminal growth | B11: 0.12 | C11: below nominal growth, stated
A12: Cost of capital | B12: 0.26250009 | C12: built on the Fundamental Valuation and Peer sheets
A13: Net debt (EGP mn) | B13: 24133.2 | C13: gross borrowings less cash, FY2025 audited
A14: Investments in associates (EGP mn) | B14: 3611.6 | C14: FY2025 audited
A15: Investment property (EGP mn) | B15: 1032.5 | C15: FY2025 audited
A16: Shares outstanding (mn) | B16: 2859.92 | C16: FY2025
... A19: Order book target multiple of revenue | B19: 5.4109168 | C19: the 2024 level, to which the model converges
A21: NOT DISCLOSED — absent by design, never estimated
A22: fy2025 results release | C22: PHD has published FY2025 consolidated statements but NO FY2025 full-year results release. The release is where units sold, new sales, deliveries and construction spend are disclose
A23: h1 2026 results | C23: As at this build date (30-Aug-2026) no 2Q/H1-2026 statements or release are posted to the result centre; the newest disclosure of any kind is 1Q2026 (posted 25-Jun-2026). The study
A24: securitisation pricing | C24: The EGP 2.015bn securitisation of 4-Feb-2026 discloses tranche sizes, tenors and national-scale ratings but NO coupon on any tranche, so the company's own marginal cost of debt can
A25: per project pricing | C25: The company does not disclose per-project unit mix, average unit area, price per square metre or construction cost per square metre. The 11-Jun-2026 edition carried a full per-proj
A26: backlog cost to complete | C26: Remaining construction cost against the EGP 263bn backlog is not disclosed as a single figure. It is inferred in the model from the realised gross margin and flagged where used.

Sheet SOTP Bridge
A1: Bridge from enterprise value to equity
A2: A developer is one business; the bridge is the parts that sit outside the operating cash flows.
A4: Operating business, discounted cash flow | B4: 74697
A5: Investments in associates | B5: 3611.6
A6: Investment property | B6: 1032.5
A7: Cash | B7: 9419.5
A8: Gross borrowings | B8: -33552.7
A9: Equity value | B9: =B4+B5+B6+B7+B8
A10: Per share (EGP) | B10: =B9/Assumptions!B16

Sheet Segments
A1: Units and prices by region — the forecast's drivers
A2: New sales value and unit counts are both disclosed per region; the price per unit is one divided by the other.
A4: North Coast & Alexandria
A5: Year | B5: 2020 | C5: 2021 | D5: 2022 | E5: 2023 | F5: 2024
A6: New sales (EGP mn) | B6: 4205 | C6: 7139 | D6: 5627 | E6: 13900 | F6: 95082
A7: Units sold | B7: 726 | C7: 1552 | D7: 800 | E7: 1231 | F7: 4192
A8: Price per unit (EGP mn) | B8: 5.792011 | C8: 4.5998711 | D8: 7.03375 | E8: 11.291633 | F8: 22.681775
A9: carried forward at 2074 units, price 22.68, escalated
A11: West Cairo & Badya
A12: Year | B12: 2020 | C12: 2021 | D12: 2022 | E12: 2023 | F12: 2024
A13: New sales (EGP mn) | B13: 6627 | C13: 7258 | D13: 13118 | E13: 32332 | F13: 44570
A14: Units sold | B14: 858 | C14: 1416 | D14: 2039 | E14: 2950 | F14: 2839
A15: Price per unit (EGP mn) | B15: 7.7237762 | C15: 5.1257062 | D15: 6.4335459 | E15: 10.96 | F15: 15.69919
A16: carried forward at 2609 units, price 15.70, escalated
A18: East Cairo
A19: Year | B19: 2020 | C19: 2021 | D19: 2022 | E19: 2023 | F19: 2024
A20: New sales (EGP mn) | B20: 1947 | C20: 2892 | D20: 7265 | E20: 13270 | F20: 11364
A21: Units sold | B21: 256 | C21: 382 | D21: 1194 | E21: 1200 | F21: 453
A22: Price per unit (EGP mn) | B22: 7.6054688 | C22: 7.5706806 | D22: 6.0845896 | E22: 11.058333 | F22: 25.086093
A23: carried forward at 949 units, price 25.09, escalated
A25: Disclosed group drivers
A26: Disclosed driver | B26: Value | C26: Note
A27: New sales, 1Q2026 (EGP mn) | B27: 52000 | C27: includes EGP 24,000mn from one land-plot launch
A28: New sales, FY2024 (EGP mn) | B28: 151016 | C28: chart series
A29: Order book, 31 Mar 2026 (EGP mn) | B29: 263000 | C29: units sold and not yet delivered
A30: Order book, FY2024 (EGP mn) | B30: 147000
A31: Units sold, FY2023 | B31: 5300 | C31: the last year the company disclosed a unit count
A32: Units delivered, FY2023 | B32: 1500
A33: Construction spend, FY2024 (EGP mn) | B33: 8500
A34: Cash collections, FY2024 (EGP mn) | B34: 25400
A35: Land bank (mn sqm) | B35: 33
A37: Build level: SEGMENT, not unit.
A38: The company discloses no per-project unit mix, unit area, price per square metre or construction cost per square metre. The forecast is built at the finest level the disclosure supports and the limit is stated rather than filled.

Sheet Relative & Normalized
A1: Relative and normalised measures
B4: 2023 | C4: 2024 | D4: 2025
A5: Revenue | B5: 17462.1 | C5: 27167.3 | D5: 36169.3
A6: Cash from operations | B6: 756.7 | C6: 4854.8 | D6: 1424.2
A7: Cash conversion | B7: =B6/B5 | C7: =C6/C5 | D7: =D6/D5
A9: Price to book (market) | B9: =15.2000/6.5617
A10: Book value per share (EGP) | B10: 6.56
A11: Return on equity, 2025 | B11: =4216.7/((18765.8+14624.7)/2)

Sheet DCF
A1: Discounted cash flow — central case
A2: Every row a formula off Assumptions; change a blue cell there.
A4: EGP million | B4: 2026 | C4: 2027 | D4: 2028 | E4: 2029 | F4: 2030 | G4: 2031 | H4: 2032 | I4: 2033 | J4: 2034 | K4: 2035
A5: Delivery capacity | B5: =Assumptions!B17*(1+Assumptions!B10) | C5: =B5*(1+Assumptions!$B$10) | D5: =C5*(1+Assumptions!$B$10) | E5: =D5*(1+Assumptions!$B$10) | F5: =E5*(1+Assumptions!$B$10) | G5: =F5*(1+Assumptions!$B$10) | H5: =G5*(1+Assumptions!$B$10) | I5: =H5*(1+Assumptions!$B$10) | J5: =I5*(1+Assumptions!$B$10) | K5: =J5*(1+Assumptions!$B$10)
A6: Revenue | B6: =B5 | C6: =C5 | D6: =D5 | E6: =E5 | F6: =F5 | G6: =G5 | H6: =H5 | I6: =I5 | ... K6: =K5
A7: Gross profit | B7: =B6*Assumptions!$B$8 | C7: =C6*Assumptions!$B$8 | D7: =D6*Assumptions!$B$8 | E7: =E6*Assumptions!$B$8 | F7: =F6*Assumptions!$B$8 | G7: =G6*Assumptions!$B$8 | H7: =H6*Assumptions!$B$8 | I7: =I6*Assumptions!$B$8 | ... K7: =K6*Assumptions!$B$8
A8: Overheads | B8: =-B6*Assumptions!$B$9 | C8: =-C6*Assumptions!$B$9 | D8: =-D6*Assumptions!$B$9 | E8: =-E6*Assumptions!$B$9 | F8: =-F6*Assumptions!$B$9 | G8: =-G6*Assumptions!$B$9 | H8: =-H6*Assumptions!$B$9 | I8: =-I6*Assumptions!$B$9 | ... K8: =-K6*Assumptions!$B$9
A9: Operating cash flow | B9: =B6*Assumptions!$B$5 | C9: =C6*Assumptions!$B$5 | D9: =D6*Assumptions!$B$5 | E9: =E6*Assumptions!$B$5 | F9: =F6*Assumptions!$B$5 | G9: =G6*Assumptions!$B$5 | H9: =H6*Assumptions!$B$5 | I9: =I6*Assumptions!$B$5 | ... K9: =K6*Assumptions!$B$5
A10: Free cash flow to the firm | B10: 10123.9 | C10: 11004.2 | D10: 12106.2 | E10: 13486 | F10: 15213.5 | G10: 17376.4 | H10: 20084.2 | I10: 23474.5 | J10: 27719.1 | K10: 33033.3
A11: Discount factor | B11: =1/(1+Assumptions!$B$12)^1 | C11: =1/(1+Assumptions!$B$12)^2 | D11: =1/(1+Assumptions!$B$12)^3 | E11: =1/(1+Assumptions!$B$12)^4 | F11: =1/(1+Assumptions!$B$12)^5 | G11: =1/(1+Assumptions!$B$12)^6 | H11: =1/(1+Assumptions!$B$12)^7 | I11: =1/(1+Assumptions!$B$12)^8 | J11: =1/(1+Assumptions!$B$12)^9 | K11: =1/(1+Assumptions!$B$12)^10
A12: Present value | B12: =B10*B11 | C12: =C10*C11 | D12: =D10*D11 | E12: =E10*E11 | F12: =F10*F11 | G12: =G10*G11 | H12: =H10*H11 | I12: =I10*I11 | ... K12: =K10*K11
A14: Sum of the explicit years | B14: =SUM(B12:K12)
A15: Terminal value, discounted | B15: 25237.2
A16: Enterprise value | B16: =B14+B15

Sheet Income Statement
A1: Income statement — built from units and prices
A2: Gross margin is an OUTPUT of price per unit against cost per unit.
A4: EGP mn unless stated | B4: 2026 | C4: 2027 | D4: 2028 | E4: 2029 | F4: 2030
A5: Units sold | B5: 5632.6667 | C5: 5632.6667 | D5: 5632.6667 | E5: 5632.6667 | F5: 5632.6667
A6: New sales | B6: 139999.49 | C6: 175279.37 | D6: 219449.77 | E6: 274751.11 | F6: 343988.39
A7: Units delivered | B7: 1885.5495 | C7: 2168.3819 | D7: 2493.6392 | E7: 2867.6851 | F7: 3297.8379
A8: Revenue per delivered unit | B8: 21.2924 | C8: 26.6581 | D8: 33.376 | E8: 41.7867 | F8: 52.317
A9: Revenue | B9: 40147.923 | C9: 57804.98 | D9: 83227.61 | E9: 119831.11 | F9: 172532.84
A10: Cost per delivered unit | B10: 13.1327 | C10: 16.4421 | D10: 20.5855 | E10: 25.773 | F10: 32.2679
A11: Cost of revenue | B11: 24762.286 | C11: 35652.74 | D11: 51332.815 | E11: 73908.987 | F11: 106414.16
A12: Gross profit | B12: 15385.637 | C12: 22152.24 | D12: 31894.794 | E12: 45922.125 | F12: 66118.676
A13: Gross margin | B13: 0.3832 | C13: 0.3832 | D13: 0.3832 | E13: 0.3832 | F13: 0.3832
A14: Overheads | B14: 7065.816 | C14: 10173.362 | D14: 14647.606 | E14: 21089.624 | F14: 30364.84
A15: Operating profit | B15: 7927.2136 | C15: 11413.602 | D15: 16433.304 | E15: 23660.672 | F15: 34066.635
... A20: Order book, closing | B20: 362851.57 | C20: 480325.96 | D20: 616548.12 | E20: 771468.12 | F20: 942923.67

Sheet Balance Sheet
A1: Balance sheet — as reported
A2: EGP million.
B4: 2025 | C4: 2024
A5: Non-current assets | B5: 65900.2 | C5: 54166.4
A6: Current assets | B6: 106229.6 | C6: 69270.9
A7: Total assets | B7: 172129.8 | C7: 123437.3
A8: Current liabilities | B8: 105099 | C8: 74496.9
A9: Non-current liabilities | B9: 48265.1 | C9: 34315.7
A10: Total liabilities | B10: 153364.1 | C10: 108812.6
A11: Shareholders' funds | B11: 18765.8 | C11: 14624.7
A12: Check: assets less liabilities and equity | B12: =B7-B10-B11 | C12: =C7-C10-C11

Sheet Cash Flow
A1: Cash flow — forecast
A2: Central case. EGP million.
A4: EGP million | B4: 2026 | C4: 2027 | D4: 2028 | E4: 2029 | F4: 2030 | G4: 2031 | H4: 2032 | I4: 2033 | J4: 2034 | K4: 2035
A5: Operating cash flow | B5: 3945.9 | C5: 4940.3 | D5: 6185.2 | E5: 7743.9 | F5: 9695.3 | G5: 12138.6 | H5: 15197.5 | I5: 19027.2 | J5: 23822.1 | K5: 29825.3
A6: Free cash flow to the firm | B6: 10123.9 | C6: 11004.2 | D6: 12106.2 | E6: 13486 | F6: 15213.5 | G6: 17376.4 | H6: 20084.2 | I6: 23474.5 | J6: 27719.1 | K6: 33033.3

Sheet Summary Financials
A1: Summary financials, as reported
A4: EGP million | B4: 2023 | C4: 2024 | D4: 2025
A5: Revenue | B5: 17462.1 | C5: 27167.3 | D5: 36169.3
A6: Gross profit | B6: 5507.6 | C6: 9330.1 | D6: 14887.6
A7: Pre-tax profit | B7: 2300.7 | C7: 4320.6 | D7: 6251.1
A8: Profit after tax and minority | B8: 1581.5 | C8: 3254.9 | D8: 4216.7
A9: Cash from operations | B9: 756.7 | C9: 4854.8 | D9: 1424.2

Sheet Monte Carlo
A1: Price distribution — published output, reproduced not re-derived
A2: This is the price engine's distribution, independent of the valuation.
A4: Percentile | B4: One month | C4: Three months
A5: 5th | B5: 13.08 | C5: 11.98
A6: 25th | B6: 14.67 | C6: 14.61
A7: 50th | B7: 15.64 | C7: 16.34
A8: 75th | B8: 16.68 | C8: 18.27
A9: 95th | B9: 18.71 | C9: 22.26
A11: Resolved three-month tests | B11: 57
A12: Inside the 90% band | B12: 0.9123
A13: Inside the middle band | B13: 0.5088
A14: Band width vs a random walk | B14: 1.469

Sheet Sensitivity
A1: Value per share against the two things that move it
A2: Read down a column: cash conversion moves value more than the discount rate does.
A4: Cash conversion | B4: 0.22250009 | C4: 0.24250009 | D4: 0.26250009 | E4: 0.28250009 | F4: 0.30250009
A5: 0.039375935 | B5: 15 | C5: 11.61 | D5: 9.17 | E5: 7.31 | F5: 5.86
A6: 0.06 | B6: 21.6 | C6: 16.91 | D6: 13.54 | E6: 11.02 | F6: 9.05
A7: 0.087136637 | B7: 30.28 | C7: 23.87 | D7: 19.3 | E7: 15.89 | F7: 13.25
A8: 0.12 | B8: 40.8 | C8: 32.31 | D8: 26.28 | E8: 21.79 | F8: 18.33
A9: 0.17870013 | B9: 59.58 | C9: 47.38 | D9: 38.74 | E9: 32.33 | F9: 27.41

Sheet Per-Share & Ratios
A1: Per share and ratios
A4: Shares outstanding (mn) | B4: 2859.92
A5: Market price (EGP) | B5: 15.2
A6: Book value per share (EGP) | B6: 6.5617
A7: Price to book | B7: 2.3165
A8: Earnings per share, 2025 (EGP) | B8: 1.4744
A9: Net debt per share (EGP) | B9: 8.4384
A10: Order book per share (EGP) | B10: 91.9606
A11: Gross margin, 2025 | B11: 0.4116
A12: Cash conversion, 2025 | B12: 0.0394

Sheet Peer & Sector
A1: Egyptian listed developers
A2: Every measure on the same window, the same cleaning and the same index.
A4: Code | B4: Company | C4: Beta | D4: R-squared | E4: Std error | F4: Volatility | G4: Worst fall
A5: TMGH | B5: Talaat Moustafa Group Holding | C5: 1.4718 | D5: 0.3261 | E5: 0.1848 | F5: 0.4394 | G5: -0.4419
A6: PHDC | B6: Palm Hills Developments | C6: 1.0493 | D6: 0.2988 | E6: 0.1823 | F6: 0.4391 | G6: -0.4866
A7: ORHD | B7: Orascom Development Egypt | C7: 0.8837 | D7: 0.321 | E7: 0.173 | F7: 0.4636 | G7: -0.4293
A8: HELI | B8: Heliopolis Housing and Development | C8: 0.7653 | D8: 0.2884 | E8: 0.1815 | F8: 0.444 | G8: -0.3958
A9: EMFD | B9: Emaar Misr for Development | C9: 0.7388 | D9: 0.2441 | E9: 0.1692 | F9: 0.4106 | G9: -0.4712
A10: PRDC | B10: Pioneers Properties for Urban Development | C10: 0.7067 | D10: 0.2576 | E10: 0.1864 | F10: 0.4217 | G10: -0.5199
A11: OCDI | B11: Sixth of October Development & Investment (SODIC) | C11: 0.4938 | D11: 0.1033 | E11: 0.2237 | F11: 0.4713 | G11: -0.4658
A13: Earnings and book multiples are not published for the peer group: no peer discloses statements this study can obtain on a consistent basis, and an inconsistent multiple would mislead.
