Workbook

Sheet READ FIRST
A1: Read this first
A5: THE RULE
A6: IT CALCULATES. IT DOES NOT STORE.
A8: Exactly ONE class of cell is pasted in this workbook: a figure read off an audited or disclosed filing, or a stated house judgement. Those are the blue cells on Assumptions, and the blue lever cells that define each sensitivity grid point. Everything else is a live formula.
A10: The previous edition also pasted its sensitivity grids, its beta sweep and its bear and bull columns, on the grounds that each is a whole-model re-run and a re-run cannot be written inside a grid. That was 27.6% of the file, and it was the part a reader would most want to interrogate. Three of those pasted rows turned out not to reproduce.
A12: The Sensitivity sheet now writes the entire forecast engine out again, in formulas, once for every grid point. Change any driver on Assumptions and every sensitivity cell in the file moves with it.
A14: WHAT IS AUDITED AND WHAT IS NOT
A15: The base year is the twelve months to 30 June 2026. The first half of it — July to December 2025 — is AUDITED by Crowe with an unqualified opinion. The second half — January to June 2026 — is REPORTED: a disclosure to the Egyptian Exchange dated 29-30 July 2026, not a filing. Half of this base year is a press release and the study says so wherever it uses it.
A17: The gross profit of that reported half is NOT used as released. Run through the company's own first-quarter expense run rates the released figure implies a profit after tax about 12.6% above the profit the same release reports. The gross profit used here is solved from the profit line, which passes two independent coherence tests. Base Year rows 13 to 17 show the whole test.
A19: THE ONE OPERATING INPUT THAT IS NOT READ OFF A FILING
A20: Note 15-A discloses the cost stack for the company and not by line. The processing-intensity weights on Assumptions are therefore a judgement, and the per-line margins depend on them. They are registered, dated and sensitised like every other input rather than hidden inside a formula.

Sheet Summary
A1: Summary — the answer, and every lens behind it
A2: Nothing on this sheet is typed. Every figure points at the sheet that computed it, so a driver changed on Assumptions moves this page too.
B5: Bear | C5: Base | D5: Bull | E5: Weight
A6: Discounted cash flow | B6: 1.6731381 | C6: ='Fundamental Valuation'!B10 | D6: 23.927095 | E6: =Assumptions!$B$189
A7: Relative multiples | B7: 9.8774947 | C7: ='Fundamental Valuation'!C11 | D7: 15.299898 | E7: =Assumptions!$B$190
A8: Normalised earnings power | B8: 9.8828031 | C8: ='Fundamental Valuation'!D12 | D8: 16.086867 | E8: =Assumptions!$B$191
A9: Book value and sustainable return | B9: 4.7388314 | C9: ='Fundamental Valuation'!E13 | D9: 7.1228739 | E9: =Assumptions!$B$192
A10: CENTRAL — the cash-flow lens | B10: =B6 | C10: =C6 | D10: =D6
A12: Market price at the valuation date | B12: =Assumptions!$B$7
A13: Central against price | B13: =C10/B12-1
A14: Shares in issue, millions | B14: =Assumptions!$B$8
A15: Market capitalisation at the valuation date | B15: =B14*Assumptions!$B$7
A17: WHERE THE VALUE SITS
A18: Present value of the explicit five years | B18: =DCF!B52
A19: Present value of the terminal block | B19: =DCF!B56
A20: Terminal share of enterprise value | B20: =B19/(B18+B19)
A21: Net cash added in the bridge | B21: =DCF!B58
A23: The bear and bull columns of each lens are the blue cells here and the only pasted figures on the sheet: each is a complete re-run of the model at that scenario, computed in compute.py and reproduced in formulas on the Sensitivity sheet. The central row is a live formula across them, because the defect being closed was a sheet that labelled a row weighted and then took the minimum and maximum across four lenses.

Sheet Fundamental Valuation
A1: Four lenses, one bridge, one valuation date
A2: Lens 2 is on the TRAILING metric so it borrows no discount factor from lens 1. Lens 3 is forward-dated and is therefore DISCOUNTED to the valuation date at the cost of equity, with net cash added at face outside the multiple. Lens 4 uses the same cost-of-equity glide lens 1 uses. All formulas.
A5: Base-year EBITDA | B5: ='Income Statement'!B20-'Income Statement'!B28-'Income Statement'!B29-'Income Statement'!B30-'Income Statement'!B31+'Income Statement'!B32
A6: Enterprise value at spot | B6: =Assumptions!$B$7*Assumptions!$B$8+(Assumptions!$B$103+Assumptions!$B$104-Assumptions!$B$100)/10^6
A7: The company's OWN trailing EV/EBITDA | B7: =B6/B5
A8: Justified multiple = trailing x (1 + re-rating) | B8: =B7*(1+Assumptions!$B$113)
A10: LENS 1 — discounted cash flow | B10: =DCF!B65
A11: LENS 2 — relative multiples, on the trailing metric | B11: =(B8*B5-(Assumptions!$B$103+Assumptions!$B$104-Assumptions!$B$100)/10^6)*(1-'Income Statement'!B41)-(Assumptions!$B$99+Assumptions!$B$98-Assumptions!$B$102-Assumptions!$B$101)/10^6 | C11: =B11/Assumptions!$B$8
A12: LENS 3 — normalised earnings power, DISCOUNTED | B12: =DCF!E41 | C12: =B12*(1-Assumptions!$B$108)*(1-'Income Statement'!B40)*(1-'Income Statement'!B41)/Assumptions!$B$8 | D12: =C12*Assumptions!$B$112/(1+DCF!B10)^2.4+((Assumptions!$B$100-Assumptions!$B$103-Assumptions!$B$104-Assumptions!$B$99-Assumptions!$B$98)/10^6)/Assumptions!$B$8
A13: LENS 4 — book value and sustainable return | B13: =Assumptions!$B$105/10^6/Assumptions!$B$8 | C13: =0.2283705826 | D13: =(Assumptions!$B$111-Assumptions!$B$110)/(C13-Assumptions!$B$110) | E13: =B13*D13
A15: CENTRAL — the cash-flow lens | B15: =B10
A16: against spot | B16: =B15/Assumptions!$B$7-1
A17: the retired 45/20/20/15 blend, published beside the answer and unused | B17: =B10*Assumptions!$B$189+C11*Assumptions!$B$190+D12*Assumptions!$B$191+E13*Assumptions!$B$192
A19: ONE CLASS PRIMARY IS THE CENTRAL. The cash-flow lens is the answer; the relative, normalised-earnings and book rows are cross-checks and the range across them is an ENVELOPE, not a spread around a weighted estimate. The blend on the row above is kept visible and unused: three of the four lenses value a refiner on reported earnings and historical-cost book, and averaging them into the answer imports every weakness of the weakest at a weight nobody tested out of sample. An earlier edition labelled a row "weighted central" and then took the minimum and maximum across all four lenses, both of which came from the cash-flow lens alone, so the word "weighted" applied to the centre and not to the ends and the published spread was about two and a half times too wide.

Sheet Assumptions
A1: Assumptions — every driver, with the filing it was read from
A2: Blue cells are the ONLY pasted values in this workbook. Every one is a figure read off an audited or disclosed filing, or a stated house judgement. There is no third class: the previous edition also pasted its sensitivity grids and its bear and bull columns because each is a whole-model re-run; those re-runs are now written out as live formula blocks on the Sensitivity sheet, so a reader can change a driver here and watch every one of them move.
A5: Driver | B5: Value | C5: Ring | D5: Date | E5: Source
A6: MARKET AND CAPITAL
A7: Spot price, EGP | B7: 13.5 | C7: Company | D7: 2026-09-03 | E7: AMOC closing price on the Egyptian Exchange, 3 September 2026
A8: Shares outstanding, mn | B8: 1291.5 | C8: Company | D8: 2025-12-31 | E8: Issued and paid-up capital EGP 1,291,500,000 at EGP 1 par = 1,291,500,000 shares (note 18-L, share split to EGP 1 par recorded in the Commercial Register 24-Jan-2018)
A9: THE TWELVE MONTHS TO 30 JUNE 2026 — the base year
A10: Net sales, 6M to 31-Dec-2025 (AUDITED) | B10: 20735725812 | C10: Company | D10: 2025-12-31 | E10: Net sales, six months to 31-Dec-2025. Audited consolidated FS, transition period 1-Jul-2025 to 31-Dec-2025, Crowe unqualified, 18-Feb-2026
A11: Cost of sales, 6M to 31-Dec-2025 (AUDITED) | B11: 19461550746 | C11: Company | D11: 2025-12-31 | E11: Cost of sales, six months to 31-Dec-2025. Audited consolidated FS, transition period 1-Jul-2025 to 31-Dec-2025, Crowe unqualified, 18-Feb-2026
A12: Net sales, 6M to 30-Jun-2026 (FILED) | B12: 26223032454 | C12: Company | D12: 2026-06-30 | E12: Net sales, six months to 30-Jun-2026. Reviewed consolidated financial statements, six months to 30-Jun-2026, limited review report attached (note 14-A / 15-A)
A13: Cost of sales, 6M to 30-Jun-2026 (FILED) | B13: 22964084821 | C13: Company | D13: 2026-06-30 | E13: Cost of sales, six months to 30-Jun-2026. Reviewed consolidated financial statements, six months to 30-Jun-2026, limited review report attached (note 14-A / 15-A)
A14: Gross profit, 6M to 30-Jun-2026 (FILED) | B14: 3258947633 | C14: Company | D14: 2026-06-30 | E14: Gross profit, six months to 30-Jun-2026 — 12.43% of net sales. Reviewed consolidated financial statements, six months to 30-Jun-2026, limited review report attached (note 14-A / 15-A)
A15: General and administrative, 6M to 30-Jun-2026 (FILED) | B15: 675083735 | C15: Company | D15: 2026-06-30 | E15: General and administrative expenses, six months to 30-Jun-2026. Reviewed consolidated financial statements, six months to 30-Jun-2026, limited review report attached (note 14-A / 15-A)
A16: Marketing and selling, 6M to 30-Jun-2026 (FILED) | B16: 125019700 | C16: Company | D16: 2026-06-30 | E16: Marketing and selling expenses, six months to 30-Jun-2026. Reviewed consolidated financial statements, six months to 30-Jun-2026, limited review report attached (note 14-A / 15-A)
A17: Other expenses, 6M to 30-Jun-2026 (FILED) | B17: 2599294 | C17: Company | D17: 2026-06-30 | E17: Other expenses, six months to 30-Jun-2026. Reviewed consolidated financial statements, six months to 30-Jun-2026, limited review report attached (note 14-A / 15-A)
A18: Formed provisions, 6M to 30-Jun-2026 (FILED) | B18: 96672167 | C18: Company | D18: 2026-06-30 | E18: Formed provisions, six months to 30-Jun-2026. Reviewed consolidated financial statements, six months to 30-Jun-2026, limited review report attached (note 14-A / 15-A)
A19: Expected credit losses, 6M to 30-Jun-2026 (FILED) | B19: 48692230 | C19: Company | D19: 2026-06-30 | E19: Expected credit losses formed, six months to 30-Jun-2026. Reviewed consolidated financial statements, six months to 30-Jun-2026, limited review report attached (note 14-A / 15-A)
A20: Finance expenses, 6M to 30-Jun-2026 (FILED) | B20: 1938539 | C20: Company | D20: 2026-06-30 | E20: Finance expenses, six months to 30-Jun-2026. Reviewed consolidated financial statements, six months to 30-Jun-2026, limited review report attached (note 14-A / 15-A)
A21: Other income, 6M to 30-Jun-2026 (FILED) | B21: 196526615 | C21: Company | D21: 2026-06-30 | E21: Other operating income, six months to 30-Jun-2026, of which credit interest 134,944,385. Reviewed consolidated financial statements, six months to 30-Jun-2026, limited review report attached (note 14-A / 15-A)
... A65: Finance cost, 6M to 31-Dec-2025 | B65: 1892108 | C65: Company | D65: 2025-12-31 | E65: Finance expenses, six months to 31-Dec-2025 (note 15-E): loan interest and charges 1,130,556, lease interest 761,552. Audited consolidated FS, transition period 1-Jul-2025 to 31-Dec-2025, Crowe unqualified, 18-Feb-2026
A66: NOTE 14-A — the audited product table, 6M to 31-Dec-2025
A67: Base and special oils — tonnes sold | B67: 118475.64 | C67: Company | D67: 2026-06-30 | E67: Tonnes sold by product line, TWELVE months to 30-Jun-2026 — the audited transition half (note 14-A, Audited consolidated FS, transition period 1-Jul-2025 to 31-Dec-2025, Crowe unqualified, 18-Feb-2026) plus the reviewed half (Reviewed consolidated financial statements, six months to 30-Jun-2026, limited review report attached (note 14-A / 15-A)). Both halves are filed; nothing is annualised.
A68: Paraffin wax — tonnes sold | B68: 82805.74 | C68: Company | D68: 2026-06-30 | E68: Tonnes sold by product line, TWELVE months to 30-Jun-2026 — the audited transition half (note 14-A, Audited consolidated FS, transition period 1-Jul-2025 to 31-Dec-2025, Crowe unqualified, 18-Feb-2026) plus the reviewed half (Reviewed consolidated financial statements, six months to 30-Jun-2026, limited review report attached (note 14-A / 15-A)). Both halves are filed; nothing is annualised.
A69: Gas oil — tonnes sold | B69: 346720.79 | C69: Company | D69: 2026-06-30 | E69: Tonnes sold by product line, TWELVE months to 30-Jun-2026 — the audited transition half (note 14-A, Audited consolidated FS, transition period 1-Jul-2025 to 31-Dec-2025, Crowe unqualified, 18-Feb-2026) plus the reviewed half (Reviewed consolidated financial statements, six months to 30-Jun-2026, limited review report attached (note 14-A / 15-A)). Both halves are filed; nothing is annualised.
A70: Naphtha — tonnes sold | B70: 80543.106 | C70: Company | D70: 2026-06-30 | E70: Tonnes sold by product line, TWELVE months to 30-Jun-2026 — the audited transition half (note 14-A, Audited consolidated FS, transition period 1-Jul-2025 to 31-Dec-2025, Crowe unqualified, 18-Feb-2026) plus the reviewed half (Reviewed consolidated financial statements, six months to 30-Jun-2026, limited review report attached (note 14-A / 15-A)). Both halves are filed; nothing is annualised.
A71: Liquefied petroleum gas — tonnes sold | B71: 47938.789 | C71: Company | D71: 2026-06-30 | E71: Tonnes sold by product line, TWELVE months to 30-Jun-2026 — the audited transition half (note 14-A, Audited consolidated FS, transition period 1-Jul-2025 to 31-Dec-2025, Crowe unqualified, 18-Feb-2026) plus the reviewed half (Reviewed consolidated financial statements, six months to 30-Jun-2026, limited review report attached (note 14-A / 15-A)). Both halves are filed; nothing is annualised.
A72: Fuel oil (mix) — tonnes sold | B72: 799642.26 | C72: Company | D72: 2026-06-30 | E72: Tonnes sold by product line, TWELVE months to 30-Jun-2026 — the audited transition half (note 14-A, Audited consolidated FS, transition period 1-Jul-2025 to 31-Dec-2025, Crowe unqualified, 18-Feb-2026) plus the reviewed half (Reviewed consolidated financial statements, six months to 30-Jun-2026, limited review report attached (note 14-A / 15-A)). Both halves are filed; nothing is annualised.
A73: Heavy fuel oil — tonnes sold | B73: 26181.62 | C73: Company | D73: 2026-06-30 | E73: Tonnes sold by product line, TWELVE months to 30-Jun-2026 — the audited transition half (note 14-A, Audited consolidated FS, transition period 1-Jul-2025 to 31-Dec-2025, Crowe unqualified, 18-Feb-2026) plus the reviewed half (Reviewed consolidated financial statements, six months to 30-Jun-2026, limited review report attached (note 14-A / 15-A)). Both halves are filed; nothing is annualised.
A74: Waste — tonnes sold | B74: 16.66 | C74: Company | D74: 2026-06-30 | E74: Tonnes sold by product line, TWELVE months to 30-Jun-2026 — the audited transition half (note 14-A, Audited consolidated FS, transition period 1-Jul-2025 to 31-Dec-2025, Crowe unqualified, 18-Feb-2026) plus the reviewed half (Reviewed consolidated financial statements, six months to 30-Jun-2026, limited review report attached (note 14-A / 15-A)). Both halves are filed; nothing is annualised.
A75: Base and special oils — sales value, EGP | B75: 6910344291 | C75: Company | D75: 2026-06-30 | E75: Sales value by product line, EGP, TWELVE months to 30-Jun-2026 — the audited transition half (note 14-A, Audited consolidated FS, transition period 1-Jul-2025 to 31-Dec-2025, Crowe unqualified, 18-Feb-2026) plus the reviewed half (Reviewed consolidated financial statements, six months to 30-Jun-2026, limited review report attached (note 14-A / 15-A)). Foots to disclosed twelve-month net sales with no scalar.
A76: Paraffin wax — sales value, EGP | B76: 4652865956 | C76: Company | D76: 2026-06-30 | E76: Sales value by product line, EGP, TWELVE months to 30-Jun-2026 — the audited transition half (note 14-A, Audited consolidated FS, transition period 1-Jul-2025 to 31-Dec-2025, Crowe unqualified, 18-Feb-2026) plus the reviewed half (Reviewed consolidated financial statements, six months to 30-Jun-2026, limited review report attached (note 14-A / 15-A)). Foots to disclosed twelve-month net sales with no scalar.
A77: Gas oil — sales value, EGP | B77: 13032962579 | C77: Company | D77: 2026-06-30 | E77: Sales value by product line, EGP, TWELVE months to 30-Jun-2026 — the audited transition half (note 14-A, Audited consolidated FS, transition period 1-Jul-2025 to 31-Dec-2025, Crowe unqualified, 18-Feb-2026) plus the reviewed half (Reviewed consolidated financial statements, six months to 30-Jun-2026, limited review report attached (note 14-A / 15-A)). Foots to disclosed twelve-month net sales with no scalar.
A78: Naphtha — sales value, EGP | B78: 2237624310 | C78: Company | D78: 2026-06-30 | E78: Sales value by product line, EGP, TWELVE months to 30-Jun-2026 — the audited transition half (note 14-A, Audited consolidated FS, transition period 1-Jul-2025 to 31-Dec-2025, Crowe unqualified, 18-Feb-2026) plus the reviewed half (Reviewed consolidated financial statements, six months to 30-Jun-2026, limited review report attached (note 14-A / 15-A)). Foots to disclosed twelve-month net sales with no scalar.
... A82: Waste — sales value, EGP | B82: 192200 | C82: Company | D82: 2026-06-30 | E82: Sales value by product line, EGP, TWELVE months to 30-Jun-2026 — the audited transition half (note 14-A, Audited consolidated FS, transition period 1-Jul-2025 to 31-Dec-2025, Crowe unqualified, 18-Feb-2026) plus the reviewed half (Reviewed consolidated financial statements, six months to 30-Jun-2026, limited review report attached (note 14-A / 15-A)). Foots to disclosed twelve-month net sales with no scalar.
A83: NOTE 15-A — the audited cost stack, 6M to 31-Dec-2025
A84: Raw materials | B84: 17650102725 | C84: Company | D84: 2025-12-31 | E84: Cost of sales — RAW MATERIALS, six months to 31-Dec-2025 (note 15-A). 90.7% of cost of sales and 85.1% of revenue: this single line is what the company is. Audited consolidated FS, transition period 1-Jul-2025 to 31-Dec-2025, Crowe unqualified, 18-Feb-2026
A85: Salaries | B85: 881019497 | C85: Company | D85: 2025-12-31 | E85: Cost of sales — salaries, six months to 31-Dec-2025 (note 15-A). Audited consolidated FS, transition period 1-Jul-2025 to 31-Dec-2025, Crowe unqualified, 18-Feb-2026
A86: Other expenses | B86: 807146755 | C86: Company | D86: 2025-12-31 | E86: Cost of sales — other expenses, six months to 31-Dec-2025 (note 15-A): natural gas, operating electricity, operating water, spare parts, maintenance, and the operating management and technical support contract with the Egyptian Projects Operations & Maintenance Company (EPROM). Audited consolidated FS, transition period 1-Jul-2025 to 31-Dec-2025, Crowe unqualified, 18-Feb-2026
A87: Supporting materials (chemicals and additives) | B87: 64533723 | C87: Company | D87: 2025-12-31 | E87: Cost of sales — supporting materials (chemicals and additives), six months to 31-Dec-2025 (note 15-A). The previous edition estimated this charge at roughly five times the disclosed figure
A88: Depreciation | B88: 58748046 | C88: Company | D88: 2025-12-31 | E88: Cost of sales — depreciation, six months to 31-Dec-2025 (note 15-A). Audited consolidated FS, transition period 1-Jul-2025 to 31-Dec-2025, Crowe unqualified, 18-Feb-2026
A89: BALANCE SHEET AT 31 DECEMBER 2025 (AUDITED)
A90: Fixed assets, net | B90: 873010517 | C90: Company | D90: 2026-06-30 | E90: Fixed assets net of accumulated depreciation at 30-Jun-2026 (note 6). Reviewed consolidated FS, six months to 30-Jun-2026, limited review
A91: Fixed assets, at COST | B91: 2740810692 | C91: Company | D91: 2025-12-31 | E91: Fixed assets at COST at 31-Dec-2025 (note 6), before accumulated depreciation of 1,847,794,418. The gross figure is what a replacement-capex line has to be built on; the net figure is what the terminal return is flattered by. Audited consolidated FS, transition period 1-Jul-2025 to 31-Dec-2025, Crowe unqualified, 18-Feb-2026
A92: Projects under construction | B92: 414641768 | C92: Company | D92: 2026-06-30 | E92: Projects under construction at 30-Jun-2026 (note 7). Reviewed consolidated FS, six months to 30-Jun-2026, limited review
A93: Inventory | B93: 3764066490 | C93: Company | D93: 2026-06-30 | E93: Inventory net of impairment at 30-Jun-2026 (note 9-A). Reviewed consolidated FS, six months to 30-Jun-2026, limited review
A94: Trade receivables | B94: 2035100729 | C94: Company | D94: 2026-06-30 | E94: Accounts receivable net at 30-Jun-2026 (note 9-B). Reviewed consolidated FS, six months to 30-Jun-2026, limited review
A95: Debtors and other debit balances | B95: 632115619 | C95: Company | D95: 2026-06-30 | E95: Debtors and other debit balances net at 30-Jun-2026 (notes 9-C, 9-D). Reviewed consolidated FS, six months to 30-Jun-2026, limited review
A96: Accounts and notes payable | B96: 14015841 | C96: Company | D96: 2026-06-30 | E96: Accounts and notes payable at 30-Jun-2026 (note 10-3). Reviewed consolidated FS, six months to 30-Jun-2026, limited review
A97: Creditors and other credit balances | B97: 3286150065 | C97: Company | D97: 2026-06-30 | E97: Creditors and other credit balances at 30-Jun-2026 (note 11). Reviewed consolidated FS, six months to 30-Jun-2026, limited review
A98: of which DIVIDENDS PAYABLE — a financing claim | B98: 258300000 | C98: Company | D98: 2026-06-30 | E98: Dividends payable at 30-Jun-2026 (note 11) — HALF the 517,250,000 standing six months earlier, because the declared dividend was largely paid. Reviewed consolidated FS, six months to 30-Jun-2026, limited review
A99: Provisions — tax disputes and claims | B99: 996857074 | C99: Company | D99: 2026-06-30 | E99: Provisions at 30-Jun-2026 (note 10-1) — a recognised liability, carried in full in the bridge. Reviewed consolidated FS, six months to 30-Jun-2026, limited review
A100: Cash at banks and on hand, free | B100: 3018394920 | C100: Company | D100: 2026-06-30 | E100: Cash and cash equivalents at 30-Jun-2026 (note 9-E). UP from 2,463,522,365 six months earlier AFTER paying 861,257,265 of dividends. Reviewed consolidated FS, six months to 30-Jun-2026, limited review
A101: Deposits PLEDGED against facilities | B101: 525170000 | C101: Company | D101: 2026-06-30 | E101: Other financial investments at 30-Jun-2026 — deposits PLEDGED against facilities, not free cash. Reviewed consolidated FS, six months to 30-Jun-2026, limited review
... A106: Non-controlling interest, carrying | B106: 72835277 | C106: Company | D106: 2026-06-30 | E106: Non-controlling interest carrying amount at 30-Jun-2026. Reviewed consolidated FS, six months to 30-Jun-2026, limited review
A107: DRIVERS
A108: Statutory tax rate — applied to operating profit | B108: 0.225 | C108: Country | D108: 2026 | E108: Egypt corporate income tax 22.5%. AMOC is a downstream processor and is taxed at the ordinary corporate rate, not the ~40.55% rate that applies to exploration and production concessions
A109: Feedstock pass-through factor | B109: 1 | C109: House | D109: 2026-08-06 | E109: Pass-through factor on the raw-material line: 1.0 means the feedstock charge moves one-for-one with realisation and volume, so the gross SPREAD per tonne is held flat in real terms and the margin neither widens nor narrows by assumption. Setting it below 1.0 is the way to express spread widening; the study leaves it at parity and sensitises it
A110: Terminal growth | B110: 0.07 | C110: Country | D110: 2026-08-06 | E110: Terminal growth, 7% — INFLATION ONLY, and no real growth at all. It is set equal to the central bank's published inflation target, which is the same 7% embedded in this study's own terminal risk-free rate. The previous edition used 5% against that identical 12.5% nominal rate, which is a business shrinking about 2% a year in real terms for ever — an assumption never stated as one, on a plant serving a population growing 1.6% a year. Zero real growth is still the conservative end: it assumes AMOC never again grows a tonne
A111: Sustainable return on equity — book lens | B111: 0.28 | C111: House | D111: 2026-08-06 | E111: Sustainable return on equity for the book lens. Trailing return on average parent equity is about 33%; the sustainable rate is struck below it because the reported figure is flattered by a heavily written-down asset base that will have to be renewed
A112: Justified price/earnings — normalised lens | B112: 7.5 | C112: House | D112: 2026-08-06 | E112: Justified through-cycle price-to-earnings multiple on normalised earnings. Trailing is about 7.5x on the constructed 2025 base. A single-asset processor with a 20% state shareholder, an administered feedstock relationship and an Egyptian cost of equity near 28% does not earn a premium multiple. Bear 5.5x / bull 9.5x
A113: Re-rating on own trailing EV/EBITDA — relative lens | B113: 0 | C113: House | D113: 2026-08-06 | E113: Re-rating applied to the company's OWN trailing enterprise-value to EBITDA multiple in the relative lens. ZERO: the name is held at the multiple the market already pays it. The justified multiple is no longer a free number — it is DERIVED as the trailing multiple times one plus this figure, so it cannot drift away from the company's own pricing without the drift being visible. The previous edition set 4.5x by hand and justified it as 'holding the name at its own trailing level' against a stated trailing multiple of 'around 4.6x'; the model's own output was different, so the stated justification was false whichever way the multiple was struck. Holding at zero re-rating makes the lens a statement about the BRIDGE — what the disclosed claims on the cash are worth — rather than a disguised view on the multiple
A114: Processing intensity — Base and special oils | B114: 1 | C114: House | D114: 2026-08-06 | E114: Processing intensity by product line, relative weights, used to allocate the note 15-A conversion stack (salaries, supporting materials, other, depreciation) across the eight disclosed lines. Base oils are the reference at 1.00: they pass the full lube train — vacuum distillation, solvent extraction, dewaxing, hydrofinishing. Paraffin wax carries 1.15 for the additional deoiling and sweating steps. Gas oil, naphtha and LPG are light ends drawn off the front of the process and carry 0.25/0.20/0.15. Fuel oil and heavy fuel oil are the residue, sold substantially as produced, at 0.05. THIS IS THE ONLY OPERATING INPUT IN THE MODEL THAT IS NOT READ OFF A FILING, and it exists because note 15-A discloses the cost stack for the company and not by line. It is stated here rather than hidden in a formula, and the valuation is sensitised to it
A115: Processing intensity — Paraffin wax | B115: 1.15 | C115: House | D115: 2026-08-06 | E115: Processing intensity by product line, relative weights, used to allocate the note 15-A conversion stack (salaries, supporting materials, other, depreciation) across the eight disclosed lines. Base oils are the reference at 1.00: they pass the full lube train — vacuum distillation, solvent extraction, dewaxing, hydrofinishing. Paraffin wax carries 1.15 for the additional deoiling and sweating steps. Gas oil, naphtha and LPG are light ends drawn off the front of the process and carry 0.25/0.20/0.15. Fuel oil and heavy fuel oil are the residue, sold substantially as produced, at 0.05. THIS IS THE ONLY OPERATING INPUT IN THE MODEL THAT IS NOT READ OFF A FILING, and it exists because note 15-A discloses the cost stack for the company and not by line. It is stated here rather than hidden in a formula, and the valuation is sensitised to it
A116: Processing intensity — Gas oil | B116: 0.25 | C116: House | D116: 2026-08-06 | E116: Processing intensity by product line, relative weights, used to allocate the note 15-A conversion stack (salaries, supporting materials, other, depreciation) across the eight disclosed lines. Base oils are the reference at 1.00: they pass the full lube train — vacuum distillation, solvent extraction, dewaxing, hydrofinishing. Paraffin wax carries 1.15 for the additional deoiling and sweating steps. Gas oil, naphtha and LPG are light ends drawn off the front of the process and carry 0.25/0.20/0.15. Fuel oil and heavy fuel oil are the residue, sold substantially as produced, at 0.05. THIS IS THE ONLY OPERATING INPUT IN THE MODEL THAT IS NOT READ OFF A FILING, and it exists because note 15-A discloses the cost stack for the company and not by line. It is stated here rather than hidden in a formula, and the valuation is sensitised to it
A117: Processing intensity — Naphtha | B117: 0.2 | C117: House | D117: 2026-08-06 | E117: Processing intensity by product line, relative weights, used to allocate the note 15-A conversion stack (salaries, supporting materials, other, depreciation) across the eight disclosed lines. Base oils are the reference at 1.00: they pass the full lube train — vacuum distillation, solvent extraction, dewaxing, hydrofinishing. Paraffin wax carries 1.15 for the additional deoiling and sweating steps. Gas oil, naphtha and LPG are light ends drawn off the front of the process and carry 0.25/0.20/0.15. Fuel oil and heavy fuel oil are the residue, sold substantially as produced, at 0.05. THIS IS THE ONLY OPERATING INPUT IN THE MODEL THAT IS NOT READ OFF A FILING, and it exists because note 15-A discloses the cost stack for the company and not by line. It is stated here rather than hidden in a formula, and the valuation is sensitised to it
A118: Processing intensity — Liquefied petroleum gas | B118: 0.15 | C118: House | D118: 2026-08-06 | E118: Processing intensity by product line, relative weights, used to allocate the note 15-A conversion stack (salaries, supporting materials, other, depreciation) across the eight disclosed lines. Base oils are the reference at 1.00: they pass the full lube train — vacuum distillation, solvent extraction, dewaxing, hydrofinishing. Paraffin wax carries 1.15 for the additional deoiling and sweating steps. Gas oil, naphtha and LPG are light ends drawn off the front of the process and carry 0.25/0.20/0.15. Fuel oil and heavy fuel oil are the residue, sold substantially as produced, at 0.05. THIS IS THE ONLY OPERATING INPUT IN THE MODEL THAT IS NOT READ OFF A FILING, and it exists because note 15-A discloses the cost stack for the company and not by line. It is stated here rather than hidden in a formula, and the valuation is sensitised to it
A119: Processing intensity — Fuel oil (mix) | B119: 0.05 | C119: House | D119: 2026-08-06 | E119: Processing intensity by product line, relative weights, used to allocate the note 15-A conversion stack (salaries, supporting materials, other, depreciation) across the eight disclosed lines. Base oils are the reference at 1.00: they pass the full lube train — vacuum distillation, solvent extraction, dewaxing, hydrofinishing. Paraffin wax carries 1.15 for the additional deoiling and sweating steps. Gas oil, naphtha and LPG are light ends drawn off the front of the process and carry 0.25/0.20/0.15. Fuel oil and heavy fuel oil are the residue, sold substantially as produced, at 0.05. THIS IS THE ONLY OPERATING INPUT IN THE MODEL THAT IS NOT READ OFF A FILING, and it exists because note 15-A discloses the cost stack for the company and not by line. It is stated here rather than hidden in a formula, and the valuation is sensitised to it
... A171: Egyptian inflation factor, 2030E | B171: 1.07 | C171: Country | D171: 2026-09-02 | E171: Cumulative-year Egyptian inflation factors applied to the pound-denominated cost legs — salaries inside cost of sales, the other line, administrative and marketing expense, and capital expenditure. The three HISTORICAL years are as printed. The five FORECAST years are the single Egyptian inflation path this series uses for every Egyptian company it values, read from that path rather than set for this study: no valuation here sets an inflation rate of its own, because a company cannot be valued in an economy the study beside it does not recognise. The path is the central bank's published disinflation ladder, and the years between published points are labelled as interpolated where they are
A172: COST OF CAPITAL
A173: Risk-free rate, Egypt 10-year local currency | B173: 0.2231 | C173: Country | D173: 2026-07-21 | E173: Egypt 10-year local-currency government bond yield, 22.31% (house cost-of-capital reference, cached 21-Jul-2026 print, re-verified 06-Aug-2026)
A174: Sovereign default spread, CDS basis | B174: 0.034 | C174: Country | D174: 2026-01-05 | E174: Egypt credit-default-swap-implied sovereign default spread, Damodaran January-2026 country-premium file, CDS column. Netted out of the local-currency risk-free rate so sovereign default risk is not charged twice
A175: Equity risk premium, CDS basis | B175: 0.0941 | C175: Country | D175: 2026-01-05 | E175: Damodaran original country-premium file, Egypt row, CDS column, last updated 5 January 2026 — total equity risk premium
A176: Beta | B176: 0.90634649 | C176: Company | D176: 2026-09-08 | E176: Own-stock tier-1 regression, AMOC weekly log-returns against raw_indices/EG/EGX30.csv — the published index of the exchange AMOC is listed on, series as of 2026-09-08, resolved by beta_regression.own_stock_beta() rather than hand-rolled. R-squared 0.236, n = 256, standard error 0.175, 90% confidence interval [0.619, 1.193]. Passes the usability gate. THIS REPLACES the previous edition's 0.9405, which was regressed against a 33-name equal-weight composite of the covered Egyptian names — a coverage artefact rather than a market, and a source-integrity failure whatever number it produced. The correction is small on this name and it is made because the provenance was wrong, not because the answer was.
A177: Yield on cash | B177: 0.17 | C177: House | D177: 2026-08-06 | E177: Yield earned on the cash pile. Egyptian treasury bills and corporate deposits price a few points under the 19.50% policy rate net of the 20% withholding on interest
A178: Cost of debt | B178: 0.2431 | C178: House | D178: 2026-09-02 | E178: Marginal cost of debt: the Egyptian ten-year sovereign yield this study discounts with, plus a 200bp corporate spread. The gross book is EGP 25mn — 0.06% of revenue — of short-dated Egyptian-pound facilities, so no observable marginal rate exists and the rate is built rather than pretended to be observed. It replaces a build off the 20.00% corridor lending rate, which produced 22.00% — below the sovereign, which a same-currency corporate cannot be. The integrity gate below computes what this input is actually WORTH to the answer
A179: CBE inflation target IN FORCE for the terminal horizon | B179: 0.07 | C179: Country | D179: 2026-08-06 | E179: The central bank's own stated inflation target, 7% (+/-2pp) on average for the fourth quarter of 2026, falling to 5% (+/-2pp) for the fourth quarter of 2028
A180: Terminal real risk-free rate | B180: 0.055 | C180: House | D180: 2026-08-06 | E180: Terminal real risk-free rate, the standard emerging-market convention. The terminal NOMINAL risk-free rate is not an input: it is DERIVED as this real rate plus the central bank's inflation target IN FORCE for the terminal horizon (`cbe_target`), so the single most terminal-value-sensitive number in the model cannot be set by hand. The previous edition hardcoded 10.50% by adding 5.5pp to the 5% target dated Q4-2028 while describing it as 'the' medium-term target; the target in force is 7% for Q4-2026 and the July-2026 rate decision pushed even that to H2-2027
A181: Terminal equity risk premium | B181: 0.07 | C181: House | D181: 2026-08-06 | E181: Terminal equity risk premium, normalised below the currently elevated crisis-era level toward the rating-class norm; never held flat into perpetuity
A182: Terminal cost of debt | B182: 0.15 | C182: House | D182: 2026-08-06 | E182: Terminal cost of debt: the midpoint of the 14-16% long-run Egyptian corporate-borrowing norm, with no name-specific reason to deviate
A183: Terminal debt weight | B183: 0.1 | C183: House | D183: 2026-08-06 | E183: Terminal debt weight, normalised. The company is net cash today and has been for years; a terminal structure carrying a tenth of capital in debt is already generous to the valuation and avoids capitalising the current zero-leverage position into perpetuity
A184: Cost-of-debt path, 2026E | B184: 0.2431 | C184: House | D184: 2026-08-06 | E184: Forward cost-of-debt path 2026E-2030E, following the central bank's own disinflation path toward the long-run Egyptian corporate-borrowing norm. This path is what sets the SHAPE of the cost-of-capital glide; it is not a second free parameter
... A192: Lens weight — book | B192: 0.15 | C192: House | D192: 2026-08-06 | E192: Discounted cash flow primary for a single-asset operating processor with a visible volume ramp; the relative and normalised-earnings lenses carry equal secondary weight; the book lens least, because a substantially depreciated plant makes book value a poor proxy for replacement cost

Sheet SOTP Bridge
A1: Enterprise value to equity — every step
A2: AMOC is a single operating company: one refinery, eight product lines off one crude slate, no stakes to sum. There are no parts to break out, so this sheet is the full enterprise-to-equity walk rather than a sum of pieces, and it says so rather than inventing segments to fill the shape.
A5: Present value of the explicit window | B5: =DCF!B52
A6: Terminal value | B6: =DCF!B55
A7: Present value of the terminal block | B7: =DCF!B56
A8: ENTERPRISE VALUE | B8: =DCF!B57
A9: plus net cash | B9: =DCF!B58
A10: Enterprise value including cash | B10: =DCF!B59
A11: less minority interest, on the whole enterprise | B11: =DCF!B60
A12: less the tax-disputes provision | B12: =DCF!B61
A13: less dividends declared and payable | B13: =DCF!B62
A14: plus non-operating investments and pledged deposits | B14: =DCF!B63
A15: EQUITY ATTRIBUTABLE TO THE PARENT | B15: =DCF!B64
A16: VALUE PER SHARE, EGP | B16: =B15/Assumptions!$B$8
A18: THE SAME WALK, PER SHARE
A19: Enterprise value | B19: =DCF!B57/Assumptions!$B$8
A20: Net cash | B20: =DCF!B58/Assumptions!$B$8
A21: Minority interest | B21: =DCF!B60/Assumptions!$B$8*-1
A22: Provisions, dividends payable and investments | B22: =(DCF!B63-DCF!B61-DCF!B62)/Assumptions!$B$8
A23: VALUE PER SHARE, EGP | B23: =SUM(B19:B22)
A25: The minority is taken on the WHOLE enterprise, cash included, because the subsidiary that carries it holds its share of the cash as well as of the plant. Taking it on the operating enterprise alone and then adding the group cash at face would credit the parent with cash it does not wholly own.

Sheet Segments
A1: The eight disclosed product lines — revenue AND cost, per line
A2: Note 14-A gives tonnes and value per line. Note 15-A gives the cost stack for the company and NOT by line, so conversion is allocated on the registered processing-intensity weights and feedstock is then allocated on NET REALISABLE VALUE — the standard joint-product method. Every cell here is a formula.
A5: Line | B5: Tonnes, 6M | C5: Value, EGP 6M | D5: Realisation EGP/t | E5: Base tonnes mn | F5: Base realisation | G5: Conversion EGP/t | H5: Feedstock EGP/t | I5: Spread EGP/t
A6: Base and special oils | B6: =Assumptions!$B$67 | C6: =Assumptions!$B$75 | D6: =C6/B6 | E6: =B6/10^6 | F6: =D6*$B$16 | G6: =$B$22*H6/$B$23 | H6: =Assumptions!$B$114 | I6: =F6-G6
A7: Paraffin wax | B7: =Assumptions!$B$68 | C7: =Assumptions!$B$76 | D7: =C7/B7 | E7: =B7/10^6 | F7: =D7*$B$16 | G7: =$B$22*H7/$B$23 | H7: =Assumptions!$B$115 | I7: =F7-G7
A8: Gas oil | B8: =Assumptions!$B$69 | C8: =Assumptions!$B$77 | D8: =C8/B8 | E8: =B8/10^6 | F8: =D8*$B$16 | G8: =$B$22*H8/$B$23 | H8: =Assumptions!$B$116 | I8: =F8-G8
A9: Naphtha | B9: =Assumptions!$B$70 | C9: =Assumptions!$B$78 | D9: =C9/B9 | E9: =B9/10^6 | F9: =D9*$B$16 | G9: =$B$22*H9/$B$23 | H9: =Assumptions!$B$117 | I9: =F9-G9
A10: Liquefied petroleum gas | B10: =Assumptions!$B$71 | C10: =Assumptions!$B$79 | D10: =C10/B10 | E10: =B10/10^6 | F10: =D10*$B$16 | G10: =$B$22*H10/$B$23 | H10: =Assumptions!$B$118 | I10: =F10-G10
A11: Fuel oil (mix) | B11: =Assumptions!$B$72 | C11: =Assumptions!$B$80 | D11: =C11/B11 | E11: =B11/10^6 | F11: =D11*$B$16 | G11: =$B$22*H11/$B$23 | H11: =Assumptions!$B$119 | I11: =F11-G11
A12: Heavy fuel oil | B12: =Assumptions!$B$73 | C12: =Assumptions!$B$81 | D12: =C12/B12 | E12: =B12/10^6 | F12: =D12*$B$16 | G12: =$B$22*H12/$B$23 | H12: =Assumptions!$B$120 | I12: =F12-G12
A13: Waste | B13: =Assumptions!$B$74 | C13: =Assumptions!$B$82 | D13: =C13/B13 | E13: =B13/10^6 | F13: =D13*$B$16 | G13: =$B$22*H13/$B$23 | H13: =Assumptions!$B$121 | I13: =F13-G13
A14: TOTAL | B14: =SUM(B6:B13) | C14: =SUM(C6:C13) | E14: =SUM(E6:E13) | F14: =SUMPRODUCT(E6:E13,F6:F13)
A15: Revenue at the disclosed realisations, twelve months as filed | B15: =SUMPRODUCT(E6:E13,D6:D13)
A16: REALISATION INDEX — solved so the base year foots | B16: ='Income Statement'!B19/B15
A18: COST ALLOCATION
A19: Cost of sales, base year | B19: ='Income Statement'!B21
A20: Feedstock share of cost (note 15-A) | B20: =Assumptions!$B$26/(Assumptions!$B$26+Assumptions!$B$25+Assumptions!$B$29+Assumptions!$B$27+Assumptions!$B$28)
A21: Feedstock total | B21: =B19*B20
A22: Conversion total | B22: =B19-B21
A23: Processing-weighted tonnage | B23: =SUMPRODUCT(E6:E13,H6:H13)
A24: Net realisable value weighted tonnage | B24: =SUMPRODUCT(E6:E13,I6:I13)
A26: Line | B26: Conversion EGP/t | C26: Net realisable EGP/t | D26: Feedstock EGP/t | E26: Total cost EGP/t | F26: Realisation EGP/t | G26: Spread EGP/t | H26: Gross margin
A27: Base and special oils | B27: =G6 | C27: =I6 | D27: =$B$21*I6/$B$24 | E27: =D27+B27 | F27: =F6 | G27: =F27-E27 | H27: =G27/F27
A28: Paraffin wax | B28: =G7 | C28: =I7 | D28: =$B$21*I7/$B$24 | E28: =D28+B28 | F28: =F7 | G28: =F28-E28 | H28: =G28/F28
A29: Gas oil | B29: =G8 | C29: =I8 | D29: =$B$21*I8/$B$24 | E29: =D29+B29 | F29: =F8 | G29: =F29-E29 | H29: =G29/F29
A30: Naphtha | B30: =G9 | C30: =I9 | D30: =$B$21*I9/$B$24 | E30: =D30+B30 | F30: =F9 | G30: =F30-E30 | H30: =G30/F30
A31: Liquefied petroleum gas | B31: =G10 | C31: =I10 | D31: =$B$21*I10/$B$24 | E31: =D31+B31 | F31: =F10 | G31: =F31-E31 | H31: =G31/F31
A32: Fuel oil (mix) | B32: =G11 | C32: =I11 | D32: =$B$21*I11/$B$24 | E32: =D32+B32 | F32: =F11 | G32: =F32-E32 | H32: =G32/F32
A33: Heavy fuel oil | B33: =G12 | C33: =I12 | D33: =$B$21*I12/$B$24 | E33: =D33+B33 | F33: =F12 | G33: =F33-E33 | H33: =G33/F33
A34: Waste | B34: =G13 | C34: =I13 | D34: =$B$21*I13/$B$24 | E34: =D34+B34 | F34: =F13 | G34: =F34-E34 | H34: =G34/F34
A35: Cost of sales rebuilt from the per-line allocation | B35: =SUMPRODUCT(E6:E13,E27:E34)
A36: must equal the base-year cost of sales — difference | B36: =B35-'Income Statement'!B21
A38: Row 36 is the footing test: the eight per-line costs must rebuild the disclosed cost of sales exactly. Feedstock allocated flat per tonne would make fuel oil sell below the cost of its own feed; feedstock allocated on relative sales value would make base oils and paraffin wax — the products this plant exists for — loss-making. Net realisable value is the standard joint-product method and the only one of the three that leaves every disclosed line with a positive spread.

Sheet Relative & Normalized
A1: Lens 2 and lens 3, in full
A2: Lens 2 is struck on the TRAILING metric so it borrows no discount factor from the cash-flow lens. Lens 3 is forward-dated and is therefore discounted back to the valuation date, with net cash added at face outside the multiple.
A5: LENS 2 — RELATIVE MULTIPLES
A6: Base-year EBITDA | B6: ='Fundamental Valuation'!B5
A7: Enterprise value at the market price | B7: ='Fundamental Valuation'!B6
A8: The company's own trailing enterprise value / EBITDA | B8: ='Fundamental Valuation'!B7
A9: Re-rating applied | B9: =Assumptions!$B$113
A10: Justified multiple | B10: ='Fundamental Valuation'!B8
A11: Equity on that multiple | B11: ='Fundamental Valuation'!B11
A12: LENS 2, EGP PER SHARE | B12: ='Fundamental Valuation'!C11
A14: LENS 3 — NORMALISED EARNINGS POWER
A15: Normalised EBIT, 2028E | B15: ='Fundamental Valuation'!B12
A16: Normalised earnings per share | B16: ='Fundamental Valuation'!C12
A17: Justified price / earnings | B17: =Assumptions!$B$112
A18: Discounted back at the explicit cost of equity | B18: =(1+DCF!B10)^2.4
A19: LENS 3, EGP PER SHARE | B19: ='Fundamental Valuation'!D12
A21: LENS 4 — BOOK VALUE AND SUSTAINABLE RETURN
A22: Book value per share attributable to the parent | B22: ='Fundamental Valuation'!B13
A23: Sustainable return on equity | B23: =Assumptions!$B$111
A24: Cost of equity used | B24: ='Fundamental Valuation'!C13
A25: Justified price / book | B25: ='Fundamental Valuation'!D13
A26: LENS 4, EGP PER SHARE | B26: ='Fundamental Valuation'!E13

Sheet DCF
A1: Discounted cash flow — the forecast engine — eight lines by five years, all formulas
A2: This is the block the Sensitivity sheet replicates twenty-five times, once per grid point, so that every sensitivity cell in this workbook is a live re-run rather than a pasted number.
A5: Levers for this block — the base case sets them all neutral
A6: Volume growth added a year | B6: 0
A7: Gross-margin shift | B7: 0
A8: Realisation-path multiplier | B8: 1
A9: Working-capital cycle multiplier | B9: 1
A10: Explicit cost of capital | B10: =Assumptions!$B$173-Assumptions!$B$174+Assumptions!$B$176*Assumptions!$B$175
A11: Gross borrowings as a share of the capital structure | B11: =(Assumptions!$B$103+Assumptions!$B$104)/10^6/(Assumptions!$B$7*Assumptions!$B$8)
A12: Equity weight — unlevered | B12: =1-B11
A13: After-tax cost of net debt (shown; not used to discount operations) | B13: =(Assumptions!$B$178*(Assumptions!$B$103+Assumptions!$B$104)/10^6-Assumptions!$B$177*Assumptions!$B$100/10^6)/((Assumptions!$B$103+Assumptions!$B$104-Assumptions!$B$100)/10^6)*(1-0.22118761296853667)
A14: OPERATING DISCOUNT RATE — unlevered; the cash is added in the bridge | B14: =B10
A15: Terminal risk-free — DERIVED from the target in force | B15: =Assumptions!$B$179+Assumptions!$B$180
A16: Terminal cost of equity | B16: =B15+Assumptions!$B$176*Assumptions!$B$181
A17: WACC — terminal | B17: =(1-Assumptions!$B$183)*B16+Assumptions!$B$183*Assumptions!$B$182*(1-0.22118761296853667)
A19: BASE CASE | B19: 2026E | C19: 2027E | D19: 2028E | E19: 2029E | F19: 2030E
A20: Inflation index, cumulative | C20: =Assumptions!$B$167 | D20: =C20*Assumptions!$B$168 | E20: =D20*Assumptions!$B$169 | F20: =E20*Assumptions!$B$170 | G20: =F20*Assumptions!$B$171
A21: Realisation index, cumulative | C21: =(1+Assumptions!$B$122*$B$8) | D21: =C21*(1+Assumptions!$B$123*$B$8) | E21: =D21*(1+Assumptions!$B$124*$B$8) | F21: =E21*(1+Assumptions!$B$125*$B$8) | G21: =F21*(1+Assumptions!$B$126*$B$8)
A22: Volume — Base and special oils, mn t | C22: ='Segments'!E6*(1+Assumptions!$B$127+$B$6) | D22: =C22*(1+Assumptions!$B$128+$B$6) | E22: =D22*(1+Assumptions!$B$129+$B$6) | F22: =E22*(1+Assumptions!$B$130+$B$6) | G22: =F22*(1+Assumptions!$B$131+$B$6)
A23: Volume — Paraffin wax, mn t | C23: ='Segments'!E7*(1+Assumptions!$B$132+$B$6) | D23: =C23*(1+Assumptions!$B$133+$B$6) | E23: =D23*(1+Assumptions!$B$134+$B$6) | F23: =E23*(1+Assumptions!$B$135+$B$6) | G23: =F23*(1+Assumptions!$B$136+$B$6)
A24: Volume — Gas oil, mn t | C24: ='Segments'!E8*(1+Assumptions!$B$137+$B$6) | D24: =C24*(1+Assumptions!$B$138+$B$6) | E24: =D24*(1+Assumptions!$B$139+$B$6) | F24: =E24*(1+Assumptions!$B$140+$B$6) | G24: =F24*(1+Assumptions!$B$141+$B$6)
A25: Volume — Naphtha, mn t | C25: ='Segments'!E9*(1+Assumptions!$B$142+$B$6) | D25: =C25*(1+Assumptions!$B$143+$B$6) | E25: =D25*(1+Assumptions!$B$144+$B$6) | F25: =E25*(1+Assumptions!$B$145+$B$6) | G25: =F25*(1+Assumptions!$B$146+$B$6)
A26: Volume — Liquefied petroleum gas, mn t | C26: ='Segments'!E10*(1+Assumptions!$B$147+$B$6) | D26: =C26*(1+Assumptions!$B$148+$B$6) | E26: =D26*(1+Assumptions!$B$149+$B$6) | F26: =E26*(1+Assumptions!$B$150+$B$6) | G26: =F26*(1+Assumptions!$B$151+$B$6)
A27: Volume — Fuel oil (mix), mn t | C27: ='Segments'!E11*(1+Assumptions!$B$152+$B$6) | D27: =C27*(1+Assumptions!$B$153+$B$6) | E27: =D27*(1+Assumptions!$B$154+$B$6) | F27: =E27*(1+Assumptions!$B$155+$B$6) | G27: =F27*(1+Assumptions!$B$156+$B$6)
A28: Volume — Heavy fuel oil, mn t | C28: ='Segments'!E12*(1+Assumptions!$B$157+$B$6) | D28: =C28*(1+Assumptions!$B$158+$B$6) | E28: =D28*(1+Assumptions!$B$159+$B$6) | F28: =E28*(1+Assumptions!$B$160+$B$6) | G28: =F28*(1+Assumptions!$B$161+$B$6)
A29: Volume — Waste, mn t | C29: ='Segments'!E13*(1+Assumptions!$B$162+$B$6) | D29: =C29*(1+Assumptions!$B$163+$B$6) | E29: =D29*(1+Assumptions!$B$164+$B$6) | F29: =E29*(1+Assumptions!$B$165+$B$6) | G29: =F29*(1+Assumptions!$B$166+$B$6)
A30: Total volume, mn t | C30: =SUM(C22:C29) | D30: =SUM(D22:D29) | E30: =SUM(E22:E29) | F30: =SUM(F22:F29) | G30: =SUM(G22:G29)
A31: REVENUE | C31: =C22*'Segments'!$F$6*C21+C23*'Segments'!$F$7*C21+C24*'Segments'!$F$8*C21+C25*'Segments'!$F$9*C21+C26*'Segments'!$F$10*C21+C27*'Segments'!$F$11*C21+C28*'Segments'!$F$12*C21+C29*'Segments'!$F$13*C21 | D31: =D22*'Segments'!$F$6*D21+D23*'Segments'!$F$7*D21+D24*'Segments'!$F$8*D21+D25*'Segments'!$F$9*D21+D26*'Segments'!$F$10*D21+D27*'Segments'!$F$11*D21+D28*'Segments'!$F$12*D21+D29*'Segments'!$F$13*D21 | E31: =E22*'Segments'!$F$6*E21+E23*'Segments'!$F$7*E21+E24*'Segments'!$F$8*E21+E25*'Segments'!$F$9*E21+E26*'Segments'!$F$10*E21+E27*'Segments'!$F$11*E21+E28*'Segments'!$F$12*E21+E29*'Segments'!$F$13*E21 | F31: =F22*'Segments'!$F$6*F21+F23*'Segments'!$F$7*F21+F24*'Segments'!$F$8*F21+F25*'Segments'!$F$9*F21+F26*'Segments'!$F$10*F21+F27*'Segments'!$F$11*F21+F28*'Segments'!$F$12*F21+F29*'Segments'!$F$13*F21 | G31: =G22*'Segments'!$F$6*G21+G23*'Segments'!$F$7*G21+G24*'Segments'!$F$8*G21+G25*'Segments'!$F$9*G21+G26*'Segments'!$F$10*G21+G27*'Segments'!$F$11*G21+G28*'Segments'!$F$12*G21+G29*'Segments'!$F$13*G21
A32: Cost of sales | C32: =C22*('Segments'!$D$27*C21*Assumptions!$B$109+'Segments'!$B$27*(0.4983251709*C21+0.4357405005*C21+0.0330936548*C21+0.0328406739))+C23*('Segments'!$D$28*C21*Assumptions!$B$109+'Segments'!$B$28*(0.4983251709*C21+0.4357405005*C21+0.0330936548*C21+0.0328406739))+C24*('Segments'!$D$29*C21*Assumptions!$B$109+'Segments'!$B$29*(0.4983251709*C21+0.4357405005*C21+0.0330936548*C21+0.0328406739))+C25*('Segments'!$D$30*C21*Assumptions!$B$109+'Segments'!$B$30*(0.4983251709*C21+0.4357405005*C21+0.0330936548*C21+0.0328406739))+C26*('Segments'!$D$31*C21*Assumptions!$B$109+'Segments'!$B$31*(0.4983251709*C21+0.4357405005*C21+0.0330936548*C21+0.0328406739))+C27*('Segments'!$D$32*C21*Assumptions!$B$109+'Segments'!$B$32*(0.4983251709*C21+0.4357405005*C21+0.0330936548*C21+0.0328406739))+C28*('Segments'!$D$33*C21*Assumptions!$B$109+'Segments'!$B$33*(0.4983251709*C21+0.4357405005*C21+0.0330936548*C21+0.0328406739))+C29*('Segments'!$D$34*C21*Assumptions!$B$109+'Segments'!$B$34*(0.4983251709*C21+0.4357405005*C21+0.0330936548*C21+0.0328406739)) | D32: =D22*('Segments'!$D$27*D21*Assumptions!$B$109+'Segments'!$B$27*(0.4983251709*D21+0.4357405005*D21+0.0330936548*D21+0.0328406739))+D23*('Segments'!$D$28*D21*Assumptions!$B$109+'Segments'!$B$28*(0.4983251709*D21+0.4357405005*D21+0.0330936548*D21+0.0328406739))+D24*('Segments'!$D$29*D21*Assumptions!$B$109+'Segments'!$B$29*(0.4983251709*D21+0.4357405005*D21+0.0330936548*D21+0.0328406739))+D25*('Segments'!$D$30*D21*Assumptions!$B$109+'Segments'!$B$30*(0.4983251709*D21+0.4357405005*D21+0.0330936548*D21+0.0328406739))+D26*('Segments'!$D$31*D21*Assumptions!$B$109+'Segments'!$B$31*(0.4983251709*D21+0.4357405005*D21+0.0330936548*D21+0.0328406739))+D27*('Segments'!$D$32*D21*Assumptions!$B$109+'Segments'!$B$32*(0.4983251709*D21+0.4357405005*D21+0.0330936548*D21+0.0328406739))+D28*('Segments'!$D$33*D21*Assumptions!$B$109+'Segments'!$B$33*(0.4983251709*D21+0.4357405005*D21+0.0330936548*D21+0.0328406739))+D29*('Segments'!$D$34*D21*Assumptions!$B$109+'Segments'!$B$34*(0.4983251709*D21+0.4357405005*D21+0.0330936548*D21+0.0328406739)) | E32: =E22*('Segments'!$D$27*E21*Assumptions!$B$109+'Segments'!$B$27*(0.4983251709*E21+0.4357405005*E21+0.0330936548*E21+0.0328406739))+E23*('Segments'!$D$28*E21*Assumptions!$B$109+'Segments'!$B$28*(0.4983251709*E21+0.4357405005*E21+0.0330936548*E21+0.0328406739))+E24*('Segments'!$D$29*E21*Assumptions!$B$109+'Segments'!$B$29*(0.4983251709*E21+0.4357405005*E21+0.0330936548*E21+0.0328406739))+E25*('Segments'!$D$30*E21*Assumptions!$B$109+'Segments'!$B$30*(0.4983251709*E21+0.4357405005*E21+0.0330936548*E21+0.0328406739))+E26*('Segments'!$D$31*E21*Assumptions!$B$109+'Segments'!$B$31*(0.4983251709*E21+0.4357405005*E21+0.0330936548*E21+0.0328406739))+E27*('Segments'!$D$32*E21*Assumptions!$B$109+'Segments'!$B$32*(0.4983251709*E21+0.4357405005*E21+0.0330936548*E21+0.0328406739))+E28*('Segments'!$D$33*E21*Assumptions!$B$109+'Segments'!$B$33*(0.4983251709*E21+0.4357405005*E21+0.0330936548*E21+0.0328406739))+E29*('Segments'!$D$34*E21*Assumptions!$B$109+'Segments'!$B$34*(0.4983251709*E21+0.4357405005*E21+0.0330936548*E21+0.0328406739)) | F32: =F22*('Segments'!$D$27*F21*Assumptions!$B$109+'Segments'!$B$27*(0.4983251709*F21+0.4357405005*F21+0.0330936548*F21+0.0328406739))+F23*('Segments'!$D$28*F21*Assumptions!$B$109+'Segments'!$B$28*(0.4983251709*F21+0.4357405005*F21+0.0330936548*F21+0.0328406739))+F24*('Segments'!$D$29*F21*Assumptions!$B$109+'Segments'!$B$29*(0.4983251709*F21+0.4357405005*F21+0.0330936548*F21+0.0328406739))+F25*('Segments'!$D$30*F21*Assumptions!$B$109+'Segments'!$B$30*(0.4983251709*F21+0.4357405005*F21+0.0330936548*F21+0.0328406739))+F26*('Segments'!$D$31*F21*Assumptions!$B$109+'Segments'!$B$31*(0.4983251709*F21+0.4357405005*F21+0.0330936548*F21+0.0328406739))+F27*('Segments'!$D$32*F21*Assumptions!$B$109+'Segments'!$B$32*(0.4983251709*F21+0.4357405005*F21+0.0330936548*F21+0.0328406739))+F28*('Segments'!$D$33*F21*Assumptions!$B$109+'Segments'!$B$33*(0.4983251709*F21+0.4357405005*F21+0.0330936548*F21+0.0328406739))+F29*('Segments'!$D$34*F21*Assumptions!$B$109+'Segments'!$B$34*(0.4983251709*F21+0.4357405005*F21+0.0330936548*F21+0.0328406739)) | G32: =G22*('Segments'!$D$27*G21*Assumptions!$B$109+'Segments'!$B$27*(0.4983251709*G21+0.4357405005*G21+0.0330936548*G21+0.0328406739))+G23*('Segments'!$D$28*G21*Assumptions!$B$109+'Segments'!$B$28*(0.4983251709*G21+0.4357405005*G21+0.0330936548*G21+0.0328406739))+G24*('Segments'!$D$29*G21*Assumptions!$B$109+'Segments'!$B$29*(0.4983251709*G21+0.4357405005*G21+0.0330936548*G21+0.0328406739))+G25*('Segments'!$D$30*G21*Assumptions!$B$109+'Segments'!$B$30*(0.4983251709*G21+0.4357405005*G21+0.0330936548*G21+0.0328406739))+G26*('Segments'!$D$31*G21*Assumptions!$B$109+'Segments'!$B$31*(0.4983251709*G21+0.4357405005*G21+0.0330936548*G21+0.0328406739))+G27*('Segments'!$D$32*G21*Assumptions!$B$109+'Segments'!$B$32*(0.4983251709*G21+0.4357405005*G21+0.0330936548*G21+0.0328406739))+G28*('Segments'!$D$33*G21*Assumptions!$B$109+'Segments'!$B$33*(0.4983251709*G21+0.4357405005*G21+0.0330936548*G21+0.0328406739))+G29*('Segments'!$D$34*G21*Assumptions!$B$109+'Segments'!$B$34*(0.4983251709*G21+0.4357405005*G21+0.0330936548*G21+0.0328406739))
A33: GROSS PROFIT | C33: =C31-C32+$B$7*C31 | D33: =D31-D32+$B$7*D31 | E33: =E31-E32+$B$7*E31 | F33: =F31-F32+$B$7*F31 | G33: =G31-G32+$B$7*G31
A34: Gross margin | C34: =C33/C31 | D34: =D33/D31 | E34: =E33/E31 | F34: =F33/F31 | G34: =G33/G31
A35: Operating expense | C35: =('Income Statement'!$B$28*C20)+('Income Statement'!$B$29*C20*C30/'Segments'!$E$14)+('Income Statement'!$B$30*C20)+('Income Statement'!$B$31*C20) | D35: =('Income Statement'!$B$28*D20)+('Income Statement'!$B$29*D20*D30/'Segments'!$E$14)+('Income Statement'!$B$30*D20)+('Income Statement'!$B$31*D20) | E35: =('Income Statement'!$B$28*E20)+('Income Statement'!$B$29*E20*E30/'Segments'!$E$14)+('Income Statement'!$B$30*E20)+('Income Statement'!$B$31*E20) | F35: =('Income Statement'!$B$28*F20)+('Income Statement'!$B$29*F20*F30/'Segments'!$E$14)+('Income Statement'!$B$30*F20)+('Income Statement'!$B$31*F20) | G35: =('Income Statement'!$B$28*G20)+('Income Statement'!$B$29*G20*G30/'Segments'!$E$14)+('Income Statement'!$B$30*G20)+('Income Statement'!$B$31*G20)
A36: EBITDA | C36: =C33-C35 | D36: =D33-D35 | E36: =E33-E35 | F36: =F33-F35 | G36: =G33-G35
A37: Capital expenditure — maintenance + growth | C37: ='Income Statement'!$B$43*C20+MAX(C30-'Segments'!$E$14,0)*2100.379938*C20 | D37: ='Income Statement'!$B$43*D20+MAX(D30-C30,0)*2100.379938*D20 | E37: ='Income Statement'!$B$43*E20+MAX(E30-D30,0)*2100.379938*E20 | F37: ='Income Statement'!$B$43*F20+MAX(F30-E30,0)*2100.379938*F20 | G37: ='Income Statement'!$B$43*G20+MAX(G30-F30,0)*2100.379938*G20
A38: Fixed assets at cost, closing | C38: =(Assumptions!$B$91+Assumptions!$B$92)/10^6+C37 | D38: =C38+D37 | E38: =D38+E37 | F38: =E38+F37 | G38: =F38+G37
A39: Depreciation — rolls off the asset register | C39: =(Assumptions!$B$91+Assumptions!$B$92)/10^6/'Income Statement'!$B$42 | D39: =C38/'Income Statement'!$B$42 | E39: =D38/'Income Statement'!$B$42 | F39: =E38/'Income Statement'!$B$42 | G39: =F38/'Income Statement'!$B$42
A40: Fixed assets, net book, closing | C40: =(Assumptions!$B$90+Assumptions!$B$92)/10^6+C37-C39 | D40: =C40+D37-D39 | E40: =D40+E37-E39 | F40: =E40+F37-F39 | G40: =F40+G37-G39
A41: EBIT | C41: =C36-C39 | D41: =D36-D39 | E41: =E36-E39 | F41: =F36-F39 | G41: =G36-G39
A42: NOPAT before the profit share | C42: =C41*(1-Assumptions!$B$108) | D42: =D41*(1-Assumptions!$B$108) | E42: =E41*(1-Assumptions!$B$108) | F42: =F41*(1-Assumptions!$B$108) | G42: =G41*(1-Assumptions!$B$108)
A43: less employees' profit share and board bonuses | C43: =MAX(C42,0)*'Income Statement'!$B$40 | D43: =MAX(D42,0)*'Income Statement'!$B$40 | E43: =MAX(E42,0)*'Income Statement'!$B$40 | F43: =MAX(F42,0)*'Income Statement'!$B$40 | G43: =MAX(G42,0)*'Income Statement'!$B$40
A44: NOPAT | C44: =C42-C43 | D44: =D42-D43 | E44: =E42-E43 | F44: =F42-F43 | G44: =G42-G43
A45: Net working capital — on days | C45: ='Income Statement'!$B$44*$B$9/365*C32+'Income Statement'!$B$45*$B$9/365*C31-'Income Statement'!$B$46*$B$9/365*C32 | D45: ='Income Statement'!$B$44*$B$9/365*D32+'Income Statement'!$B$45*$B$9/365*D31-'Income Statement'!$B$46*$B$9/365*D32 | E45: ='Income Statement'!$B$44*$B$9/365*E32+'Income Statement'!$B$45*$B$9/365*E31-'Income Statement'!$B$46*$B$9/365*E32 | F45: ='Income Statement'!$B$44*$B$9/365*F32+'Income Statement'!$B$45*$B$9/365*F31-'Income Statement'!$B$46*$B$9/365*F32 | G45: ='Income Statement'!$B$44*$B$9/365*G32+'Income Statement'!$B$45*$B$9/365*G31-'Income Statement'!$B$46*$B$9/365*G32
A46: change in working capital | C46: =C45-('Income Statement'!$B$44/365*'Income Statement'!$B$21+'Income Statement'!$B$45/365*'Income Statement'!$B$19-'Income Statement'!$B$46/365*'Income Statement'!$B$21) | D46: =D45-C45 | E46: =E45-D45 | F46: =F45-E45 | G46: =G45-F45
A47: FREE CASH FLOW TO THE FIRM | C47: =C44+C39-C37-C46 | D47: =D44+D39-D37-D46 | E47: =E44+E39-E37-E46 | F47: =F44+F39-F37-F46 | G47: =G44+G39-G37-G46
A48: Glide fraction | C48: =0.0000000000 | D48: =0.5166487648 | E48: =0.7314715360 | F48: =0.8925886144 | G48: =1.0000000000
A49: Forward cost of capital | C49: =$B$14-($B$14-$B$17)*C48 | D49: =$B$14-($B$14-$B$17)*D48 | E49: =$B$14-($B$14-$B$17)*E48 | F49: =$B$14-($B$14-$B$17)*F48 | G49: =$B$14-($B$14-$B$17)*G48
A50: Cumulative discount factor | C50: =1/(1+C49) | D50: =C50/(1+D49) | E50: =D50/(1+E49) | F50: =E50/(1+F49) | G50: =F50/(1+G49)
A51: Present value | C51: =C47*C50 | D51: =D47*D50 | E51: =E47*E50 | F51: =F47*F50 | G51: =G47*G50
A52: PV of the explicit window | B52: =SUM(C51:G51) | C52: =C45+C38 | D52: =D45+D38 | E52: =E45+E38 | F52: =F45+F38 | G52: =G45+G38
A53: Terminal return on invested capital, at REPLACEMENT cost | B53: =G44*(1+Assumptions!$B$110)/G52
A54: Required reinvestment = growth / return | B54: =MIN(Assumptions!$B$110/B53,0.95)
A55: Terminal value | B55: =G44*(1+Assumptions!$B$110)*(1-B54)/MAX($B$17-Assumptions!$B$110,0.02)
A56: PV of the terminal block | B56: =B55*G50
A57: ENTERPRISE VALUE | B57: =B52+B56
A58: plus net cash | B58: =(Assumptions!$B$100-Assumptions!$B$103-Assumptions!$B$104)/10^6
A59: Enterprise value including cash | B59: =B57+B58
A60: less minority — on the WHOLE enterprise, cash included | B60: =B59*'Income Statement'!$B$41
A61: less the tax-disputes provision | B61: =Assumptions!$B$99/10^6
A62: less dividends payable — declared, out of working capital | B62: =Assumptions!$B$98/10^6
A63: plus non-operating investments and pledged deposits | B63: =(Assumptions!$B$102+Assumptions!$B$101)/10^6
A64: EQUITY ATTRIBUTABLE | B64: =B59-B60-B61-B62+B63
A65: VALUE PER SHARE, EGP | B65: =B64/Assumptions!$B$8

Sheet Income Statement
A1: Base year — twelve contiguous months to 30 June 2026
A2: The gross profit of the reported half is NOT taken as released. It is solved from the release's own profit line, and the released figure is shown beside it with the profit it would have implied. Every cell below is a formula.
B5: EGP | C5: Check
A6: Administrative + selling + other, 3M to 31-Mar-2026 | B6: =Assumptions!$B$38+Assumptions!$B$39+Assumptions!$B$40
A7: Scaled to the half (x2) | B7: =B6*2
A8: Other revenue, half | B8: =Assumptions!$B$41*2
A9: Provisions and expected credit losses, half | B9: =(Assumptions!$B$42+Assumptions!$B$43)*2
A10: Finance cost, half | B10: =Assumptions!$B$44*2
A11: Effective tax rate, nine months (for the solve only) | B11: =(Assumptions!$B$59-Assumptions!$B$60+Assumptions!$B$61-Assumptions!$B$62)/((Assumptions!$B$59-Assumptions!$B$60+Assumptions!$B$61-Assumptions!$B$62)/0.22118761296853667)
A13: GROSS PROFIT, 6M to 30-Jun-2026 — AS FILED | B13: =Assumptions!$B$14
A14: Gross profit as the press release stated it | B14: =Assumptions!$B$35
A15: Profit after tax, 6M to 30-Jun-2026 — AS FILED | B15: =Assumptions!$B$22
A16: against the profit the press release reported | B16: =Assumptions!$B$34
A17: Release against filing, gross profit | B17: =B13/B14-1
A19: BASE-YEAR REVENUE — twelve months to 30-Jun-2026 | B19: =(Assumptions!$B$10+Assumptions!$B$12)/10^6
A20: BASE-YEAR GROSS PROFIT | B20: =(Assumptions!$B$10-Assumptions!$B$11+B13)/10^6
A21: BASE-YEAR COST OF SALES | B21: =B19-B20
A22: BASE-YEAR GROSS MARGIN | B22: =B20/B19
A24: Alternative base: nine audited months x 4/3 | B24: =(Assumptions!$B$10+Assumptions!$B$36)/10^6*4/3
A25: its gross margin | B25: =(Assumptions!$B$10+Assumptions!$B$36-Assumptions!$B$11-Assumptions!$B$37)/(Assumptions!$B$10+Assumptions!$B$36)
A27: Operating lines, SAME twelve months
A28: Administrative expense | B28: =(Assumptions!$B$45+Assumptions!$B$15)/10^6
A29: Selling expense | B29: =(Assumptions!$B$46+Assumptions!$B$16)/10^6
A30: Other operating expense | B30: =(Assumptions!$B$47+Assumptions!$B$17)/10^6
A31: Provisions and credit losses | B31: =(Assumptions!$B$48+Assumptions!$B$18+Assumptions!$B$19)/10^6
A32: Depreciation | B32: =(Assumptions!$B$30)/10^6
A33: Cash capital expenditure | B33: =(Assumptions!$B$31)/10^6
A34: Credit interest | B34: =(Assumptions!$B$53+Assumptions!$B$32)/10^6
A35: Employees' profit share | B35: =(Assumptions!$B$55*2)/10^6
A37: Every operating line is struck on the SAME twelve months as revenue and gross profit. The previous edition built revenue from the six-month product table doubled while taking cost of sales from the nine months scaled by four thirds, so its base-year gross margin of 7.081% corresponded to no filed period at all. One period, both sides, or the margin is an artefact of the scalars.
A39: RATES — solved, not assumed
A40: Employees' profit share, % of profit after tax | B40: =B35/((Assumptions!$B$56+Assumptions!$B$22)/10^6)
A41: Minority interest, % of OPERATING profit, whole base year | B41: =((Assumptions!$B$57+Assumptions!$B$23)/10^6)/((Assumptions!$B$56+Assumptions!$B$22)/10^6-B34*(1-0.22118761296853667))
A42: Implied asset life, years = fixed assets at cost / depreciation | B42: =Assumptions!$B$91/10^6/B32
A43: Maintenance capital expenditure at cost over that life | B43: =Assumptions!$B$91/10^6/B42
A44: Inventory days of cost of sales | B44: =Assumptions!$B$93/10^6/B21*365
A45: Receivable days of revenue | B45: =(Assumptions!$B$94+Assumptions!$B$95)/10^6/B19*365
A46: Operating payable days of cost of sales — dividends payable REMOVED | B46: =(Assumptions!$B$96+Assumptions!$B$97-Assumptions!$B$98)/10^6/B21*365

Sheet Balance Sheet
A1: Balance sheet — as filed, and the lines the forecast projects
A2: The filed column is the blue class: figures read off the statement. Everything to the right is projected from the working-capital days and the asset register on the Income Statement sheet, through the same engine the cash flow runs on.
A5: EGP mn | B5: As filed | C5: 2026E | D5: 2027E | E5: 2028E | F5: 2029E | G5: 2030E
A6: Fixed assets at cost | B6: =(Assumptions!$B$91+Assumptions!$B$92)/10^6 | C6: =DCF!C38 | D6: =DCF!D38 | E6: =DCF!E38 | F6: =DCF!F38 | G6: =DCF!G38
A7: Accumulated depreciation | B7: =-(Assumptions!$B$91-Assumptions!$B$90)/10^6
A8: Fixed assets, net book | B8: =(Assumptions!$B$90+Assumptions!$B$92)/10^6 | C8: =DCF!C40 | D8: =DCF!D40 | E8: =DCF!E40 | F8: =DCF!F40 | G8: =DCF!G40
A9: Inventory | B9: =Assumptions!$B$93/10^6
A10: Trade and other receivables | B10: =(Assumptions!$B$94+Assumptions!$B$95)/10^6
A11: Cash and bank | B11: =Assumptions!$B$100/10^6
A12: Financial investments and pledged deposits | B12: =(Assumptions!$B$102+Assumptions!$B$101)/10^6
A13: Trade and other payables | B13: =-(Assumptions!$B$96+Assumptions!$B$97)/10^6
A14: Dividends declared and payable | B14: =-Assumptions!$B$98/10^6
A15: Borrowings | B15: =-(Assumptions!$B$103+Assumptions!$B$104)/10^6
A16: Provisions | B16: =-Assumptions!$B$99/10^6
A17: Equity attributable to the parent, as filed | B17: =Assumptions!$B$105/10^6
A18: Minority interest, as filed | B18: =Assumptions!$B$106/10^6
A20: PROJECTED WORKING CAPITAL AND INVESTED CAPITAL
A21: Net working capital — on the filed days | C21: =DCF!C45 | D21: =DCF!D45 | E21: =DCF!E45 | F21: =DCF!F45 | G21: =DCF!G45
A22: change in the year | C22: =DCF!C46 | D22: =DCF!D46 | E22: =DCF!E46 | F22: =DCF!F46 | G22: =DCF!G46
A23: Invested capital at replacement cost | C23: =DCF!C52 | D23: =DCF!D52 | E23: =DCF!E52 | F23: =DCF!F52 | G23: =DCF!G52
A25: Working capital is projected on inventory, receivable and payable DAYS solved off the filed balance sheet, with dividends declared removed from payables first — leaving them in would have the company financing itself out of a distribution it has already committed to pay.

Sheet Cash Flow
A1: Free cash flow to the firm — the full waterfall, year by year
A2: This is the flow the discounted cash flow discounts, taken line by line from the engine on the DCF sheet. It stops at present value, not at free cash flow.
A5: EGP mn | B5: 2026E | C5: 2027E | D5: 2028E | E5: 2029E | F5: 2030E
A6: Revenue | C6: =DCF!C31 | D6: =DCF!D31 | E6: =DCF!E31 | F6: =DCF!F31 | G6: =DCF!G31
A7: Cost of sales | C7: =DCF!C32 | D7: =DCF!D32 | E7: =DCF!E32 | F7: =DCF!F32 | G7: =DCF!G32
A8: GROSS PROFIT | C8: =DCF!C33 | D8: =DCF!D33 | E8: =DCF!E33 | F8: =DCF!F33 | G8: =DCF!G33
A9: Operating expense | C9: =DCF!C35 | D9: =DCF!D35 | E9: =DCF!E35 | F9: =DCF!F35 | G9: =DCF!G35
A10: EBITDA | C10: =DCF!C36 | D10: =DCF!D36 | E10: =DCF!E36 | F10: =DCF!F36 | G10: =DCF!G36
A11: Depreciation | C11: =DCF!C39 | D11: =DCF!D39 | E11: =DCF!E39 | F11: =DCF!F39 | G11: =DCF!G39
A12: EBIT | C12: =DCF!C41 | D12: =DCF!D41 | E12: =DCF!E41 | F12: =DCF!F41 | G12: =DCF!G41
A13: NOPAT before the profit share | C13: =DCF!C42 | D13: =DCF!D42 | E13: =DCF!E42 | F13: =DCF!F42 | G13: =DCF!G42
A14: Employees' profit share and board bonuses | C14: =DCF!C43 | D14: =DCF!D43 | E14: =DCF!E43 | F14: =DCF!F43 | G14: =DCF!G43
A15: NOPAT | C15: =DCF!C44 | D15: =DCF!D44 | E15: =DCF!E44 | F15: =DCF!F44 | G15: =DCF!G44
A16: add back depreciation | C16: =DCF!C39 | D16: =DCF!D39 | E16: =DCF!E39 | F16: =DCF!F39 | G16: =DCF!G39
A17: less capital expenditure | C17: =DCF!C37 | D17: =DCF!D37 | E17: =DCF!E37 | F17: =DCF!F37 | G17: =DCF!G37
A18: less the change in working capital | C18: =DCF!C46 | D18: =DCF!D46 | E18: =DCF!E46 | F18: =DCF!F46 | G18: =DCF!G46
A19: FREE CASH FLOW TO THE FIRM | C19: =DCF!C47 | D19: =DCF!D47 | E19: =DCF!E47 | F19: =DCF!F47 | G19: =DCF!G47
A20: Forward cost of capital | C20: =DCF!C49 | D20: =DCF!D49 | E20: =DCF!E49 | F20: =DCF!F49 | G20: =DCF!G49
A21: Cumulative discount factor | C21: =DCF!C50 | D21: =DCF!D50 | E21: =DCF!E50 | F21: =DCF!F50 | G21: =DCF!G50
A22: PRESENT VALUE | C22: =DCF!C51 | D22: =DCF!D51 | E22: =DCF!E51 | F22: =DCF!F51 | G22: =DCF!G51
A24: PV of the explicit window | B24: =DCF!B52
A25: PV of the terminal block | B25: =DCF!B56
A27: Two lines are shown as they are computed rather than as a conventional waterfall would order them: tax is struck on EBIT at the statutory rate before the profit share, and the employees' share is then taken off the taxed figure, which is the order the company's own statements follow.

Sheet Summary Financials
A1: Summary financials — the base year and the five forecast years
A2: The base column is the twelve months to 30 June 2026 built on the Income Statement sheet; the five forecast columns are the engine. Margins are outputs of the volume, price and cost-per-unit build, never inputs.
A5: EGP mn | B5: Base year | C5: 2026E | D5: 2027E | E5: 2028E | F5: 2029E | G5: 2030E
A6: Revenue | B6: ='Income Statement'!B19 | C6: =DCF!C31 | D6: =DCF!D31 | E6: =DCF!E31 | F6: =DCF!F31 | G6: =DCF!G31
A7: Gross profit | B7: ='Income Statement'!B20 | C7: =DCF!C33 | D7: =DCF!D33 | E7: =DCF!E33 | F7: =DCF!F33 | G7: =DCF!G33
A8: Gross margin | B8: ='Income Statement'!B22 | C8: =DCF!C34 | D8: =DCF!D34 | E8: =DCF!E34 | F8: =DCF!F34 | G8: =DCF!G34
A9: EBITDA | B9: ='Fundamental Valuation'!B5 | C9: =DCF!C36 | D9: =DCF!D36 | E9: =DCF!E36 | F9: =DCF!F36 | G9: =DCF!G36
A10: EBIT | B10: ='Fundamental Valuation'!B5-'Income Statement'!B32 | C10: =DCF!C41 | D10: =DCF!D41 | E10: =DCF!E41 | F10: =DCF!F41 | G10: =DCF!G41
A11: NOPAT | C11: =DCF!C44 | D11: =DCF!D44 | E11: =DCF!E44 | F11: =DCF!F44 | G11: =DCF!G44
A12: Capital expenditure | B12: ='Income Statement'!B33 | C12: =DCF!C37 | D12: =DCF!D37 | E12: =DCF!E37 | F12: =DCF!F37 | G12: =DCF!G37
A13: Free cash flow to the firm | C13: =DCF!C47 | D13: =DCF!D47 | E13: =DCF!E47 | F13: =DCF!F47 | G13: =DCF!G47
A15: PER TONNE, EGP — the unit the plant actually runs on
A16: Volume, million tonnes | C16: =DCF!C30 | D16: =DCF!D30 | E16: =DCF!E30 | F16: =DCF!F30 | G16: =DCF!G30
A17: Revenue per tonne | C17: =DCF!C31/DCF!C30 | D17: =DCF!D31/DCF!D30 | E17: =DCF!E31/DCF!E30 | F17: =DCF!F31/DCF!F30 | G17: =DCF!G31/DCF!G30
A18: Gross profit per tonne | C18: =DCF!C33/DCF!C30 | D18: =DCF!D33/DCF!D30 | E18: =DCF!E33/DCF!E30 | F18: =DCF!F33/DCF!F30 | G18: =DCF!G33/DCF!G30
A19: EBITDA per tonne | C19: =DCF!C36/DCF!C30 | D19: =DCF!D36/DCF!D30 | E19: =DCF!E36/DCF!E30 | F19: =DCF!F36/DCF!F30 | G19: =DCF!G36/DCF!G30

Sheet Monte Carlo
A1: The price distribution, and how often its bands have held
A2: This is the price engine, not the valuation: an independent lens, shown beside the fundamental answer and never fed into it. The percentiles are produced by the engine and are read in here, like a figure off a filing.
A5: Anchor date | B5: 2026-08-06
A6: Anchor price, EGP | B6: 9.1
A7: Live risk-free used by the engine | B7: 0.195
A8: Dividend yield used by the engine | B8: 0.0879
A9: Tail parameter and width calibration (per-market fit) | B9: 6 | C9: 0.951
A10: Per-name width overlay applied | B10: 0.98772961
A12: THE DISTRIBUTION, EGP PER SHARE
A13: Horizon | B13: p5 | C13: p25 | D13: p50 | E13: p75 | F13: p95
A14: 1M — grade date 2026-09-06 | B14: 7.7095612 | C14: 8.598973 | D14: 9.1709726 | E14: 9.785587 | F14: 10.913622
A15: 3M — grade date 2026-11-08 | B15: 6.9017095 | C15: 8.3442309 | D15: 9.3294301 | E15: 10.41935 | F15: 12.604538
A17: HOW OFTEN THE BANDS HAVE HELD, ON THIS NAME
A18: Resolved three-month windows scored | B18: 17
A19: First origin | B19: 2022-04-05
A20: Last origin | B20: 2026-04-12
A21: Inside the 50 per cent band | B21: 0.52941176
A22: Inside the 80 per cent band | B22: 0.88235294
A23: Inside the 90 per cent band | B23: 0.94117647
A24: Mean probability-integral transform (0.5 is centred) | B24: 0.4612
A26: These bands are a record of what happened, not a forecast of the fundamental value. The fundamental study, this price distribution and the technical read are independent lenses: no output of one is an input to another, and they are shown side by side so that agreement between them is information rather than an echo.

Sheet Sensitivity
A1: Sensitivity — every grid point is the whole engine, again, in formulas
A2: The previous edition pasted these rows because each point is a whole-model re-run and its builder could not express a re-run inside a grid. Three of the pasted rows turned out not to reproduce: a working-capital row whose grid was never sorted, a beta row whose centre did not return the base case, and a volume row whose label described a different scenario from the one it ran. None of that can happen here, because there is nothing to paste.
A4: Summary — every cell points at its own live block below
A5: Gross margin, shifted on every forecast year
A6: grid point 1: -1.0% | C6: -0.01 | I6: =B95
A7: grid point 2: -0.5% | C7: -0.005 | I7: =B144
A8: grid point 3: +0.0% | C8: 0 | I8: =B193 | J8: =B193-DCF!B65
A9: grid point 4: +0.5% | C9: 0.005 | I9: =B242
A10: grid point 5: +1.0% | C10: 0.01 | I10: =B291
A12: Volume growth path, as a multiple of the assumed path
A13: grid point 1: -6.0% | B13: -0.06 | I13: =B340
A14: grid point 2: -3.0% | B14: -0.03 | I14: =B389
A15: grid point 3: +0.0% | B15: 0 | I15: =B438 | J15: =B438-DCF!B65
A16: grid point 4: +3.0% | B16: 0.03 | I16: =B487
A17: grid point 5: +6.0% | B17: 0.06 | I17: =B536
A19: Realisation path, as a multiple of the assumed path
A20: grid point 1: 0.90x | D20: 0.9 | I20: =B585
A21: grid point 2: 0.95x | D21: 0.95 | I21: =B634
A22: grid point 3: 1.00x | D22: 1 | I22: =B683 | J22: =B683-DCF!B65
A23: grid point 4: 1.05x | D23: 1.05 | I23: =B732
A24: grid point 5: 1.10x | D24: 1.1 | I24: =B781
A26: Beta
A27: grid point 1: 0.6000 | F27: 0.24556 | G27: 0.16198219 | I27: =B830
A28: grid point 2: 0.8000 | F28: 0.26438 | G28: 0.17458219 | I28: =B879
A29: grid point 3: 0.9063 | F29: 0.2743872 | G29: 0.18128201 | I29: =B928 | J29: =B928-DCF!B65
A30: grid point 4: 1.1500 | F30: 0.297315 | G30: 0.19663219 | I30: =B977
A31: grid point 5: 1.3000 | F31: 0.31143 | G31: 0.20608219 | I31: =B1026
A33: Working-capital cycle, as a multiple of the solved days
A34: grid point 1: 0.50x | E34: 0.5 | I34: =B1075
A35: grid point 2: 0.75x | E35: 0.75 | I35: =B1124
A36: grid point 3: 1.00x | E36: 1 | I36: =B1173 | J36: =B1173-DCF!B65
A37: grid point 4: 1.25x | E37: 1.25 | I37: =B1222
A38: grid point 5: 1.50x | E38: 1.5 | I38: =B1271
A40: Terminal growth
A41: grid point 1: 3.0% | H41: 0.03 | I41: =B1320
A42: grid point 2: 4.0% | H42: 0.04 | I42: =B1369
A43: grid point 3: 5.0% | H43: 0.05 | I43: =B1418
A44: grid point 4: 6.0% | H44: 0.06 | I44: =B1467
A45: grid point 5: 7.0% | H45: 0.07 | I45: =B1516 | J45: =B1516-DCF!B65
A47: GATE — every row must return the base case at its own base point
A49: Gross margin, shifted on every forecast year — -1.0% | B49: 2026E | C49: 2027E | D49: 2028E | E49: 2029E | F49: 2030E
A50: Inflation index, cumulative | C50: =Assumptions!$B$167 | D50: =C50*Assumptions!$B$168 | E50: =D50*Assumptions!$B$169 | F50: =E50*Assumptions!$B$170 | G50: =F50*Assumptions!$B$171
A51: Realisation index, cumulative | C51: =(1+Assumptions!$B$122*DCF!$B$8) | D51: =C51*(1+Assumptions!$B$123*DCF!$B$8) | E51: =D51*(1+Assumptions!$B$124*DCF!$B$8) | F51: =E51*(1+Assumptions!$B$125*DCF!$B$8) | G51: =F51*(1+Assumptions!$B$126*DCF!$B$8)
A52: Volume — Base and special oils, mn t | C52: ='Segments'!E6*(1+Assumptions!$B$127+DCF!$B$6) | D52: =C52*(1+Assumptions!$B$128+DCF!$B$6) | E52: =D52*(1+Assumptions!$B$129+DCF!$B$6) | F52: =E52*(1+Assumptions!$B$130+DCF!$B$6) | G52: =F52*(1+Assumptions!$B$131+DCF!$B$6)
A53: Volume — Paraffin wax, mn t | C53: ='Segments'!E7*(1+Assumptions!$B$132+DCF!$B$6) | D53: =C53*(1+Assumptions!$B$133+DCF!$B$6) | E53: =D53*(1+Assumptions!$B$134+DCF!$B$6) | F53: =E53*(1+Assumptions!$B$135+DCF!$B$6) | G53: =F53*(1+Assumptions!$B$136+DCF!$B$6)
A54: Volume — Gas oil, mn t | C54: ='Segments'!E8*(1+Assumptions!$B$137+DCF!$B$6) | D54: =C54*(1+Assumptions!$B$138+DCF!$B$6) | E54: =D54*(1+Assumptions!$B$139+DCF!$B$6) | F54: =E54*(1+Assumptions!$B$140+DCF!$B$6) | G54: =F54*(1+Assumptions!$B$141+DCF!$B$6)
A55: Volume — Naphtha, mn t | C55: ='Segments'!E9*(1+Assumptions!$B$142+DCF!$B$6) | D55: =C55*(1+Assumptions!$B$143+DCF!$B$6) | E55: =D55*(1+Assumptions!$B$144+DCF!$B$6) | F55: =E55*(1+Assumptions!$B$145+DCF!$B$6) | G55: =F55*(1+Assumptions!$B$146+DCF!$B$6)
A56: Volume — Liquefied petroleum gas, mn t | C56: ='Segments'!E10*(1+Assumptions!$B$147+DCF!$B$6) | D56: =C56*(1+Assumptions!$B$148+DCF!$B$6) | E56: =D56*(1+Assumptions!$B$149+DCF!$B$6) | F56: =E56*(1+Assumptions!$B$150+DCF!$B$6) | G56: =F56*(1+Assumptions!$B$151+DCF!$B$6)
A57: Volume — Fuel oil (mix), mn t | C57: ='Segments'!E11*(1+Assumptions!$B$152+DCF!$B$6) | D57: =C57*(1+Assumptions!$B$153+DCF!$B$6) | E57: =D57*(1+Assumptions!$B$154+DCF!$B$6) | F57: =E57*(1+Assumptions!$B$155+DCF!$B$6) | G57: =F57*(1+Assumptions!$B$156+DCF!$B$6)
A58: Volume — Heavy fuel oil, mn t | C58: ='Segments'!E12*(1+Assumptions!$B$157+DCF!$B$6) | D58: =C58*(1+Assumptions!$B$158+DCF!$B$6) | E58: =D58*(1+Assumptions!$B$159+DCF!$B$6) | F58: =E58*(1+Assumptions!$B$160+DCF!$B$6) | G58: =F58*(1+Assumptions!$B$161+DCF!$B$6)
A59: Volume — Waste, mn t | C59: ='Segments'!E13*(1+Assumptions!$B$162+DCF!$B$6) | D59: =C59*(1+Assumptions!$B$163+DCF!$B$6) | E59: =D59*(1+Assumptions!$B$164+DCF!$B$6) | F59: =E59*(1+Assumptions!$B$165+DCF!$B$6) | G59: =F59*(1+Assumptions!$B$166+DCF!$B$6)
A60: Total volume, mn t | C60: =SUM(C52:C59) | D60: =SUM(D52:D59) | E60: =SUM(E52:E59) | F60: =SUM(F52:F59) | G60: =SUM(G52:G59)
A61: REVENUE | C61: =C52*'Segments'!$F$6*C51+C53*'Segments'!$F$7*C51+C54*'Segments'!$F$8*C51+C55*'Segments'!$F$9*C51+C56*'Segments'!$F$10*C51+C57*'Segments'!$F$11*C51+C58*'Segments'!$F$12*C51+C59*'Segments'!$F$13*C51 | D61: =D52*'Segments'!$F$6*D51+D53*'Segments'!$F$7*D51+D54*'Segments'!$F$8*D51+D55*'Segments'!$F$9*D51+D56*'Segments'!$F$10*D51+D57*'Segments'!$F$11*D51+D58*'Segments'!$F$12*D51+D59*'Segments'!$F$13*D51 | E61: =E52*'Segments'!$F$6*E51+E53*'Segments'!$F$7*E51+E54*'Segments'!$F$8*E51+E55*'Segments'!$F$9*E51+E56*'Segments'!$F$10*E51+E57*'Segments'!$F$11*E51+E58*'Segments'!$F$12*E51+E59*'Segments'!$F$13*E51 | F61: =F52*'Segments'!$F$6*F51+F53*'Segments'!$F$7*F51+F54*'Segments'!$F$8*F51+F55*'Segments'!$F$9*F51+F56*'Segments'!$F$10*F51+F57*'Segments'!$F$11*F51+F58*'Segments'!$F$12*F51+F59*'Segments'!$F$13*F51 | G61: =G52*'Segments'!$F$6*G51+G53*'Segments'!$F$7*G51+G54*'Segments'!$F$8*G51+G55*'Segments'!$F$9*G51+G56*'Segments'!$F$10*G51+G57*'Segments'!$F$11*G51+G58*'Segments'!$F$12*G51+G59*'Segments'!$F$13*G51
A62: Cost of sales | C62: =C52*('Segments'!$D$27*C51*Assumptions!$B$109+'Segments'!$B$27*(0.4983251709*C51+0.4357405005*C51+0.0330936548*C51+0.0328406739))+C53*('Segments'!$D$28*C51*Assumptions!$B$109+'Segments'!$B$28*(0.4983251709*C51+0.4357405005*C51+0.0330936548*C51+0.0328406739))+C54*('Segments'!$D$29*C51*Assumptions!$B$109+'Segments'!$B$29*(0.4983251709*C51+0.4357405005*C51+0.0330936548*C51+0.0328406739))+C55*('Segments'!$D$30*C51*Assumptions!$B$109+'Segments'!$B$30*(0.4983251709*C51+0.4357405005*C51+0.0330936548*C51+0.0328406739))+C56*('Segments'!$D$31*C51*Assumptions!$B$109+'Segments'!$B$31*(0.4983251709*C51+0.4357405005*C51+0.0330936548*C51+0.0328406739))+C57*('Segments'!$D$32*C51*Assumptions!$B$109+'Segments'!$B$32*(0.4983251709*C51+0.4357405005*C51+0.0330936548*C51+0.0328406739))+C58*('Segments'!$D$33*C51*Assumptions!$B$109+'Segments'!$B$33*(0.4983251709*C51+0.4357405005*C51+0.0330936548*C51+0.0328406739))+C59*('Segments'!$D$34*C51*Assumptions!$B$109+'Segments'!$B$34*(0.4983251709*C51+0.4357405005*C51+0.0330936548*C51+0.0328406739)) | D62: =D52*('Segments'!$D$27*D51*Assumptions!$B$109+'Segments'!$B$27*(0.4983251709*D51+0.4357405005*D51+0.0330936548*D51+0.0328406739))+D53*('Segments'!$D$28*D51*Assumptions!$B$109+'Segments'!$B$28*(0.4983251709*D51+0.4357405005*D51+0.0330936548*D51+0.0328406739))+D54*('Segments'!$D$29*D51*Assumptions!$B$109+'Segments'!$B$29*(0.4983251709*D51+0.4357405005*D51+0.0330936548*D51+0.0328406739))+D55*('Segments'!$D$30*D51*Assumptions!$B$109+'Segments'!$B$30*(0.4983251709*D51+0.4357405005*D51+0.0330936548*D51+0.0328406739))+D56*('Segments'!$D$31*D51*Assumptions!$B$109+'Segments'!$B$31*(0.4983251709*D51+0.4357405005*D51+0.0330936548*D51+0.0328406739))+D57*('Segments'!$D$32*D51*Assumptions!$B$109+'Segments'!$B$32*(0.4983251709*D51+0.4357405005*D51+0.0330936548*D51+0.0328406739))+D58*('Segments'!$D$33*D51*Assumptions!$B$109+'Segments'!$B$33*(0.4983251709*D51+0.4357405005*D51+0.0330936548*D51+0.0328406739))+D59*('Segments'!$D$34*D51*Assumptions!$B$109+'Segments'!$B$34*(0.4983251709*D51+0.4357405005*D51+0.0330936548*D51+0.0328406739)) | E62: =E52*('Segments'!$D$27*E51*Assumptions!$B$109+'Segments'!$B$27*(0.4983251709*E51+0.4357405005*E51+0.0330936548*E51+0.0328406739))+E53*('Segments'!$D$28*E51*Assumptions!$B$109+'Segments'!$B$28*(0.4983251709*E51+0.4357405005*E51+0.0330936548*E51+0.0328406739))+E54*('Segments'!$D$29*E51*Assumptions!$B$109+'Segments'!$B$29*(0.4983251709*E51+0.4357405005*E51+0.0330936548*E51+0.0328406739))+E55*('Segments'!$D$30*E51*Assumptions!$B$109+'Segments'!$B$30*(0.4983251709*E51+0.4357405005*E51+0.0330936548*E51+0.0328406739))+E56*('Segments'!$D$31*E51*Assumptions!$B$109+'Segments'!$B$31*(0.4983251709*E51+0.4357405005*E51+0.0330936548*E51+0.0328406739))+E57*('Segments'!$D$32*E51*Assumptions!$B$109+'Segments'!$B$32*(0.4983251709*E51+0.4357405005*E51+0.0330936548*E51+0.0328406739))+E58*('Segments'!$D$33*E51*Assumptions!$B$109+'Segments'!$B$33*(0.4983251709*E51+0.4357405005*E51+0.0330936548*E51+0.0328406739))+E59*('Segments'!$D$34*E51*Assumptions!$B$109+'Segments'!$B$34*(0.4983251709*E51+0.4357405005*E51+0.0330936548*E51+0.0328406739)) | F62: =F52*('Segments'!$D$27*F51*Assumptions!$B$109+'Segments'!$B$27*(0.4983251709*F51+0.4357405005*F51+0.0330936548*F51+0.0328406739))+F53*('Segments'!$D$28*F51*Assumptions!$B$109+'Segments'!$B$28*(0.4983251709*F51+0.4357405005*F51+0.0330936548*F51+0.0328406739))+F54*('Segments'!$D$29*F51*Assumptions!$B$109+'Segments'!$B$29*(0.4983251709*F51+0.4357405005*F51+0.0330936548*F51+0.0328406739))+F55*('Segments'!$D$30*F51*Assumptions!$B$109+'Segments'!$B$30*(0.4983251709*F51+0.4357405005*F51+0.0330936548*F51+0.0328406739))+F56*('Segments'!$D$31*F51*Assumptions!$B$109+'Segments'!$B$31*(0.4983251709*F51+0.4357405005*F51+0.0330936548*F51+0.0328406739))+F57*('Segments'!$D$32*F51*Assumptions!$B$109+'Segments'!$B$32*(0.4983251709*F51+0.4357405005*F51+0.0330936548*F51+0.0328406739))+F58*('Segments'!$D$33*F51*Assumptions!$B$109+'Segments'!$B$33*(0.4983251709*F51+0.4357405005*F51+0.0330936548*F51+0.0328406739))+F59*('Segments'!$D$34*F51*Assumptions!$B$109+'Segments'!$B$34*(0.4983251709*F51+0.4357405005*F51+0.0330936548*F51+0.0328406739)) | G62: =G52*('Segments'!$D$27*G51*Assumptions!$B$109+'Segments'!$B$27*(0.4983251709*G51+0.4357405005*G51+0.0330936548*G51+0.0328406739))+G53*('Segments'!$D$28*G51*Assumptions!$B$109+'Segments'!$B$28*(0.4983251709*G51+0.4357405005*G51+0.0330936548*G51+0.0328406739))+G54*('Segments'!$D$29*G51*Assumptions!$B$109+'Segments'!$B$29*(0.4983251709*G51+0.4357405005*G51+0.0330936548*G51+0.0328406739))+G55*('Segments'!$D$30*G51*Assumptions!$B$109+'Segments'!$B$30*(0.4983251709*G51+0.4357405005*G51+0.0330936548*G51+0.0328406739))+G56*('Segments'!$D$31*G51*Assumptions!$B$109+'Segments'!$B$31*(0.4983251709*G51+0.4357405005*G51+0.0330936548*G51+0.0328406739))+G57*('Segments'!$D$32*G51*Assumptions!$B$109+'Segments'!$B$32*(0.4983251709*G51+0.4357405005*G51+0.0330936548*G51+0.0328406739))+G58*('Segments'!$D$33*G51*Assumptions!$B$109+'Segments'!$B$33*(0.4983251709*G51+0.4357405005*G51+0.0330936548*G51+0.0328406739))+G59*('Segments'!$D$34*G51*Assumptions!$B$109+'Segments'!$B$34*(0.4983251709*G51+0.4357405005*G51+0.0330936548*G51+0.0328406739))
A63: GROSS PROFIT | C63: =C61-C62+$C$6*C61 | D63: =D61-D62+$C$6*D61 | E63: =E61-E62+$C$6*E61 | F63: =F61-F62+$C$6*F61 | G63: =G61-G62+$C$6*G61
A64: Gross margin | C64: =C63/C61 | D64: =D63/D61 | E64: =E63/E61 | F64: =F63/F61 | G64: =G63/G61
A65: Operating expense | C65: =('Income Statement'!$B$28*C50)+('Income Statement'!$B$29*C50*C60/'Segments'!$E$14)+('Income Statement'!$B$30*C50)+('Income Statement'!$B$31*C50) | D65: =('Income Statement'!$B$28*D50)+('Income Statement'!$B$29*D50*D60/'Segments'!$E$14)+('Income Statement'!$B$30*D50)+('Income Statement'!$B$31*D50) | E65: =('Income Statement'!$B$28*E50)+('Income Statement'!$B$29*E50*E60/'Segments'!$E$14)+('Income Statement'!$B$30*E50)+('Income Statement'!$B$31*E50) | F65: =('Income Statement'!$B$28*F50)+('Income Statement'!$B$29*F50*F60/'Segments'!$E$14)+('Income Statement'!$B$30*F50)+('Income Statement'!$B$31*F50) | G65: =('Income Statement'!$B$28*G50)+('Income Statement'!$B$29*G50*G60/'Segments'!$E$14)+('Income Statement'!$B$30*G50)+('Income Statement'!$B$31*G50)
A66: EBITDA | C66: =C63-C65 | D66: =D63-D65 | E66: =E63-E65 | F66: =F63-F65 | G66: =G63-G65
A67: Capital expenditure — maintenance + growth | C67: ='Income Statement'!$B$43*C50+MAX(C60-'Segments'!$E$14,0)*2100.379938*C50 | D67: ='Income Statement'!$B$43*D50+MAX(D60-C60,0)*2100.379938*D50 | E67: ='Income Statement'!$B$43*E50+MAX(E60-D60,0)*2100.379938*E50 | F67: ='Income Statement'!$B$43*F50+MAX(F60-E60,0)*2100.379938*F50 | G67: ='Income Statement'!$B$43*G50+MAX(G60-F60,0)*2100.379938*G50
A68: Fixed assets at cost, closing | C68: =(Assumptions!$B$91+Assumptions!$B$92)/10^6+C67 | D68: =C68+D67 | E68: =D68+E67 | F68: =E68+F67 | G68: =F68+G67
A69: Depreciation — rolls off the asset register | C69: =(Assumptions!$B$91+Assumptions!$B$92)/10^6/'Income Statement'!$B$42 | D69: =C68/'Income Statement'!$B$42 | E69: =D68/'Income Statement'!$B$42 | F69: =E68/'Income Statement'!$B$42 | G69: =F68/'Income Statement'!$B$42
A70: Fixed assets, net book, closing | C70: =(Assumptions!$B$90+Assumptions!$B$92)/10^6+C67-C69 | D70: =C70+D67-D69 | E70: =D70+E67-E69 | F70: =E70+F67-F69 | G70: =F70+G67-G69
A71: EBIT | C71: =C66-C69 | D71: =D66-D69 | E71: =E66-E69 | F71: =F66-F69 | G71: =G66-G69
A72: NOPAT before the profit share | C72: =C71*(1-Assumptions!$B$108) | D72: =D71*(1-Assumptions!$B$108) | E72: =E71*(1-Assumptions!$B$108) | F72: =F71*(1-Assumptions!$B$108) | G72: =G71*(1-Assumptions!$B$108)
A73: less employees' profit share and board bonuses | C73: =MAX(C72,0)*'Income Statement'!$B$40 | D73: =MAX(D72,0)*'Income Statement'!$B$40 | E73: =MAX(E72,0)*'Income Statement'!$B$40 | F73: =MAX(F72,0)*'Income Statement'!$B$40 | G73: =MAX(G72,0)*'Income Statement'!$B$40
A74: NOPAT | C74: =C72-C73 | D74: =D72-D73 | E74: =E72-E73 | F74: =F72-F73 | G74: =G72-G73
A75: Net working capital — on days | C75: ='Income Statement'!$B$44*DCF!$B$9/365*C62+'Income Statement'!$B$45*DCF!$B$9/365*C61-'Income Statement'!$B$46*DCF!$B$9/365*C62 | D75: ='Income Statement'!$B$44*DCF!$B$9/365*D62+'Income Statement'!$B$45*DCF!$B$9/365*D61-'Income Statement'!$B$46*DCF!$B$9/365*D62 | E75: ='Income Statement'!$B$44*DCF!$B$9/365*E62+'Income Statement'!$B$45*DCF!$B$9/365*E61-'Income Statement'!$B$46*DCF!$B$9/365*E62 | F75: ='Income Statement'!$B$44*DCF!$B$9/365*F62+'Income Statement'!$B$45*DCF!$B$9/365*F61-'Income Statement'!$B$46*DCF!$B$9/365*F62 | G75: ='Income Statement'!$B$44*DCF!$B$9/365*G62+'Income Statement'!$B$45*DCF!$B$9/365*G61-'Income Statement'!$B$46*DCF!$B$9/365*G62
A76: change in working capital | C76: =C75-('Income Statement'!$B$44/365*'Income Statement'!$B$21+'Income Statement'!$B$45/365*'Income Statement'!$B$19-'Income Statement'!$B$46/365*'Income Statement'!$B$21) | D76: =D75-C75 | E76: =E75-D75 | F76: =F75-E75 | G76: =G75-F75
A77: FREE CASH FLOW TO THE FIRM | C77: =C74+C69-C67-C76 | D77: =D74+D69-D67-D76 | E77: =E74+E69-E67-E76 | F77: =F74+F69-F67-F76 | G77: =G74+G69-G67-G76
A78: Glide fraction | C78: =0.0000000000 | D78: =0.5166487648 | E78: =0.7314715360 | F78: =0.8925886144 | G78: =1.0000000000
A79: Forward cost of capital | C79: =DCF!$B$14-(DCF!$B$14-DCF!$B$17)*C78 | D79: =DCF!$B$14-(DCF!$B$14-DCF!$B$17)*D78 | E79: =DCF!$B$14-(DCF!$B$14-DCF!$B$17)*E78 | F79: =DCF!$B$14-(DCF!$B$14-DCF!$B$17)*F78 | G79: =DCF!$B$14-(DCF!$B$14-DCF!$B$17)*G78
A80: Cumulative discount factor | C80: =1/(1+C79) | D80: =C80/(1+D79) | E80: =D80/(1+E79) | F80: =E80/(1+F79) | G80: =F80/(1+G79)
A81: Present value | C81: =C77*C80 | D81: =D77*D80 | E81: =E77*E80 | F81: =F77*F80 | G81: =G77*G80
A82: PV of the explicit window | B82: =SUM(C81:G81) | C82: =C75+C68 | D82: =D75+D68 | E82: =E75+E68 | F82: =F75+F68 | G82: =G75+G68
A83: Terminal return on invested capital, at REPLACEMENT cost | B83: =G74*(1+Assumptions!$B$110)/G82
A84: Required reinvestment = growth / return | B84: =MIN(Assumptions!$B$110/B83,0.95)
A85: Terminal value | B85: =G74*(1+Assumptions!$B$110)*(1-B84)/MAX(DCF!$B$17-Assumptions!$B$110,0.02)
A86: PV of the terminal block | B86: =B85*G80
A87: ENTERPRISE VALUE | B87: =B82+B86
A88: plus net cash | B88: =(Assumptions!$B$100-Assumptions!$B$103-Assumptions!$B$104)/10^6
A89: Enterprise value including cash | B89: =B87+B88
A90: less minority — on the WHOLE enterprise, cash included | B90: =B89*'Income Statement'!$B$41
A91: less the tax-disputes provision | B91: =Assumptions!$B$99/10^6
A92: less dividends payable — declared, out of working capital | B92: =Assumptions!$B$98/10^6
A93: plus non-operating investments and pledged deposits | B93: =(Assumptions!$B$102+Assumptions!$B$101)/10^6
A94: EQUITY ATTRIBUTABLE | B94: =B89-B90-B91-B92+B93
A95: VALUE PER SHARE, EGP | B95: =B94/Assumptions!$B$8
A98: Gross margin, shifted on every forecast year — -0.5% | B98: 2026E | C98: 2027E | D98: 2028E | E98: 2029E | F98: 2030E
A99: Inflation index, cumulative | C99: =Assumptions!$B$167 | D99: =C99*Assumptions!$B$168 | E99: =D99*Assumptions!$B$169 | F99: =E99*Assumptions!$B$170 | G99: =F99*Assumptions!$B$171
A100: Realisation index, cumulative | C100: =(1+Assumptions!$B$122*DCF!$B$8) | D100: =C100*(1+Assumptions!$B$123*DCF!$B$8) | E100: =D100*(1+Assumptions!$B$124*DCF!$B$8) | F100: =E100*(1+Assumptions!$B$125*DCF!$B$8) | G100: =F100*(1+Assumptions!$B$126*DCF!$B$8)
A101: Volume — Base and special oils, mn t | C101: ='Segments'!E6*(1+Assumptions!$B$127+DCF!$B$6) | D101: =C101*(1+Assumptions!$B$128+DCF!$B$6) | E101: =D101*(1+Assumptions!$B$129+DCF!$B$6) | F101: =E101*(1+Assumptions!$B$130+DCF!$B$6) | G101: =F101*(1+Assumptions!$B$131+DCF!$B$6)
A102: Volume — Paraffin wax, mn t | C102: ='Segments'!E7*(1+Assumptions!$B$132+DCF!$B$6) | D102: =C102*(1+Assumptions!$B$133+DCF!$B$6) | E102: =D102*(1+Assumptions!$B$134+DCF!$B$6) | F102: =E102*(1+Assumptions!$B$135+DCF!$B$6) | G102: =F102*(1+Assumptions!$B$136+DCF!$B$6)
A103: Volume — Gas oil, mn t | C103: ='Segments'!E8*(1+Assumptions!$B$137+DCF!$B$6) | D103: =C103*(1+Assumptions!$B$138+DCF!$B$6) | E103: =D103*(1+Assumptions!$B$139+DCF!$B$6) | F103: =E103*(1+Assumptions!$B$140+DCF!$B$6) | G103: =F103*(1+Assumptions!$B$141+DCF!$B$6)
A104: Volume — Naphtha, mn t | C104: ='Segments'!E9*(1+Assumptions!$B$142+DCF!$B$6) | D104: =C104*(1+Assumptions!$B$143+DCF!$B$6) | E104: =D104*(1+Assumptions!$B$144+DCF!$B$6) | F104: =E104*(1+Assumptions!$B$145+DCF!$B$6) | G104: =F104*(1+Assumptions!$B$146+DCF!$B$6)
A105: Volume — Liquefied petroleum gas, mn t | C105: ='Segments'!E10*(1+Assumptions!$B$147+DCF!$B$6) | D105: =C105*(1+Assumptions!$B$148+DCF!$B$6) | E105: =D105*(1+Assumptions!$B$149+DCF!$B$6) | F105: =E105*(1+Assumptions!$B$150+DCF!$B$6) | G105: =F105*(1+Assumptions!$B$151+DCF!$B$6)
A106: Volume — Fuel oil (mix), mn t | C106: ='Segments'!E11*(1+Assumptions!$B$152+DCF!$B$6) | D106: =C106*(1+Assumptions!$B$153+DCF!$B$6) | E106: =D106*(1+Assumptions!$B$154+DCF!$B$6) | F106: =E106*(1+Assumptions!$B$155+DCF!$B$6) | G106: =F106*(1+Assumptions!$B$156+DCF!$B$6)
A107: Volume — Heavy fuel oil, mn t | C107: ='Segments'!E12*(1+Assumptions!$B$157+DCF!$B$6) | D107: =C107*(1+Assumptions!$B$158+DCF!$B$6) | E107: =D107*(1+Assumptions!$B$159+DCF!$B$6) | F107: =E107*(1+Assumptions!$B$160+DCF!$B$6) | G107: =F107*(1+Assumptions!$B$161+DCF!$B$6)
A108: Volume — Waste, mn t | C108: ='Segments'!E13*(1+Assumptions!$B$162+DCF!$B$6) | D108: =C108*(1+Assumptions!$B$163+DCF!$B$6) | E108: =D108*(1+Assumptions!$B$164+DCF!$B$6) | F108: =E108*(1+Assumptions!$B$165+DCF!$B$6) | G108: =F108*(1+Assumptions!$B$166+DCF!$B$6)
A109: Total volume, mn t | C109: =SUM(C101:C108) | D109: =SUM(D101:D108) | E109: =SUM(E101:E108) | F109: =SUM(F101:F108) | G109: =SUM(G101:G108)
A110: REVENUE | C110: =C101*'Segments'!$F$6*C100+C102*'Segments'!$F$7*C100+C103*'Segments'!$F$8*C100+C104*'Segments'!$F$9*C100+C105*'Segments'!$F$10*C100+C106*'Segments'!$F$11*C100+C107*'Segments'!$F$12*C100+C108*'Segments'!$F$13*C100 | D110: =D101*'Segments'!$F$6*D100+D102*'Segments'!$F$7*D100+D103*'Segments'!$F$8*D100+D104*'Segments'!$F$9*D100+D105*'Segments'!$F$10*D100+D106*'Segments'!$F$11*D100+D107*'Segments'!$F$12*D100+D108*'Segments'!$F$13*D100 | E110: =E101*'Segments'!$F$6*E100+E102*'Segments'!$F$7*E100+E103*'Segments'!$F$8*E100+E104*'Segments'!$F$9*E100+E105*'Segments'!$F$10*E100+E106*'Segments'!$F$11*E100+E107*'Segments'!$F$12*E100+E108*'Segments'!$F$13*E100 | F110: =F101*'Segments'!$F$6*F100+F102*'Segments'!$F$7*F100+F103*'Segments'!$F$8*F100+F104*'Segments'!$F$9*F100+F105*'Segments'!$F$10*F100+F106*'Segments'!$F$11*F100+F107*'Segments'!$F$12*F100+F108*'Segments'!$F$13*F100 | G110: =G101*'Segments'!$F$6*G100+G102*'Segments'!$F$7*G100+G103*'Segments'!$F$8*G100+G104*'Segments'!$F$9*G100+G105*'Segments'!$F$10*G100+G106*'Segments'!$F$11*G100+G107*'Segments'!$F$12*G100+G108*'Segments'!$F$13*G100
...

Sheet Per-Share & Ratios
A1: Per share, and the multiples the answer implies
A2: What the central and the market price each imply, on the same base-year figures. Every cell is a formula off the Summary and Income Statement sheets.
A5: Central, EGP | B5: =Summary!C10
A6: Market price, EGP | B6: =Assumptions!$B$7
A7: Book value per share, EGP | B7: ='Fundamental Valuation'!B13
A8: Base-year revenue per share, EGP | B8: ='Income Statement'!B19/Assumptions!$B$8
A9: Base-year EBITDA per share, EGP | B9: ='Fundamental Valuation'!B5/Assumptions!$B$8
A10: Dividend declared and payable, per share, EGP | B10: =Assumptions!$B$98/10^6/Assumptions!$B$8
A12: Multiple | B12: At the central | C12: At the market price
A13: Price / book | B13: =B$5/'Fundamental Valuation'!B13 | C13: =Assumptions!$B$7/'Fundamental Valuation'!B13
A14: Enterprise value / base-year EBITDA | B14: =(B$5*Assumptions!$B$8+(Assumptions!$B$103+Assumptions!$B$104-Assumptions!$B$100)/10^6)/'Fundamental Valuation'!B5 | C14: ='Fundamental Valuation'!B6/'Fundamental Valuation'!B5
A15: Enterprise value / base-year revenue | B15: =(B$5*Assumptions!$B$8+(Assumptions!$B$103+Assumptions!$B$104-Assumptions!$B$100)/10^6)/'Income Statement'!B19 | C15: ='Fundamental Valuation'!B6/'Income Statement'!B19
A16: Yield on the dividend already declared and payable | B16: =Assumptions!$B$98/10^6/Assumptions!$B$8/B$5 | C16: =Assumptions!$B$98/10^6/Assumptions!$B$8/Assumptions!$B$7
A18: RETURNS
A19: Trailing return on equity | B19: =Assumptions!$B$111
A20: Terminal return on invested capital, at replacement cost | B20: =DCF!B53
A21: Required reinvestment rate in the terminal year | B21: =DCF!B54
A22: Terminal growth | B22: =Assumptions!$B$110

Sheet Peer & Sector
A1: Sector context — a refiner and lubricant base-oil producer
A2: The comparator basis is the company's OWN traded multiple and a stated re-rating, not a peer set: no Egyptian listed refiner discloses a comparable base-oil split, and importing a foreign multiple into an EGP valuation would price a different cost of capital. That is a gap and it is named as one rather than filled.
A5: Comparator basis | B5: Multiple | C5: Applied to (EGP mn) | D5: Implied EGP/share
A6: The company's own trailing enterprise value / EBITDA | B6: ='Fundamental Valuation'!B7 | C6: ='Fundamental Valuation'!B5 | D6: =(B6*C6-(Assumptions!$B$103+Assumptions!$B$104-Assumptions!$B$100)/10^6)*(1-'Income Statement'!B41)/Assumptions!$B$8
A7: Justified multiple, after the stated re-rating | B7: ='Fundamental Valuation'!B8 | C7: ='Fundamental Valuation'!B5 | D7: =(B7*C7-(Assumptions!$B$103+Assumptions!$B$104-Assumptions!$B$100)/10^6)*(1-'Income Statement'!B41)/Assumptions!$B$8
A9: WHAT ACTUALLY DRIVES A PROCESSOR
A10: Indicator | B10: 2026E | C10: 2027E | D10: 2028E | E10: 2029E | F10: 2030E
A11: Throughput, million tonnes | C11: =DCF!C30 | D11: =DCF!D30 | E11: =DCF!E30 | F11: =DCF!F30 | G11: =DCF!G30
A12: Gross profit per tonne, EGP | C12: =DCF!C33/DCF!C30 | D12: =DCF!D33/DCF!D30 | E12: =DCF!E33/DCF!E30 | F12: =DCF!F33/DCF!F30 | G12: =DCF!G33/DCF!G30
A13: EBITDA per tonne, EGP | C13: =DCF!C36/DCF!C30 | D13: =DCF!D36/DCF!D30 | E13: =DCF!E36/DCF!E30 | F13: =DCF!F36/DCF!F30 | G13: =DCF!G36/DCF!G30
A14: Gross margin | C14: =DCF!C34 | D14: =DCF!D34 | E14: =DCF!E34 | F14: =DCF!F34 | G14: =DCF!G34
A15: Capital expenditure as a share of revenue | C15: =DCF!C37/DCF!C31 | D15: =DCF!D37/DCF!D31 | E15: =DCF!E37/DCF!E31 | F15: =DCF!F37/DCF!F31 | G15: =DCF!G37/DCF!G31
A17: The crude slate is bought from a single counterparty at a disclosed formula and the refined product is sold into a market whose price is set outside the company, so what a reader can actually compare across the sector is the spread per tonne and how much of the plant is running — not a price/earnings ratio struck on a different tax regime and a different currency.
