Workbook

Sheet READ FIRST
A1: ADIB-Egypt (EGX: ADIB) — valuation model, 2026-09-10
A3: WHICH COMPANY. Abu Dhabi Islamic Bank – Egypt S.A.E., listed in Cairo, reporting in Egyptian pounds. NOT Abu Dhabi Islamic Bank PJSC (ADX: ADIB), its Abu Dhabi parent, which is a different company covered separately.
A5: HOW TO USE THIS FILE. Every BLUE cell on the Assumptions sheet is an input you may change. Everything downstream of one is a formula. Change the cost of risk, or the asset yield, or the growth path, and the value per share on Summary recomputes.
A7: THERE IS NO ENTERPRISE VALUE AND NO WACC IN THIS MODEL, and that is deliberate. A bank's deposits are its raw material rather than its financing, so subtracting them as though they were debt produces a number with no meaning. Everything here is built on equity and discounted at the cost of equity.
A9: MARGINS ARE OUTPUTS. The asset yield and the cost of funds are inputs; the net interest margin, the cost-to-income ratio and the returns on assets and equity are computed from them. None of those four is typed anywhere in this file.
A11: ONE LENS IS THE ANSWER. The dividend discount is the central. Residual income, the relative multiple and book value are cross-checks published beside it. They are not averaged, and there are no weights in this workbook.
A13: NOT INVESTMENT ADVICE. No rating, no price target. An educational valuation exercise.

Sheet Summary
A1: ADIB-Egypt — summary
A4: Share price (3 Sep 2026) | B4: 52.05
A5: Shares in issue, million | B5: 1500
A6: Market capitalisation, EGP million | B6: =B4*B5
A8: THE LENSES — the dividend discount is the central; the rest are cross-checks
A9: Dividend discount (PRIMARY = the central) | B9: ='Fundamental Valuation'!B30
A10: Free cash flow to equity | B10: ='Fundamental Valuation'!B31
A11: Residual income | B11: ='Fundamental Valuation'!B32
A12: Relative multiples | B12: ='Relative & Normalized'!B12
A13: Book value and sustainable return | B13: ='Relative & Normalized'!B20
A14: Normalised earnings power | B14: ='Relative & Normalized'!B28
A16: THE ENVELOPE — the range of the three present-value reads, nothing invented
A17: Low (free cash flow to equity) | B17: =MIN('Fundamental Valuation'!B30:B32) | C17: =B17/$B$4-1
A18: CENTRAL (dividend discount) | B18: ='Fundamental Valuation'!B30 | C18: =B18/$B$4-1
A19: High (residual income) | B19: =MAX('Fundamental Valuation'!B30:B32) | C19: =B19/$B$4-1 | D19: against the share price
A21: WHAT THE FORECAST SAYS
A22: EGP million | B22: 2026 | C22: 2027 | D22: 2028 | E22: 2029 | F22: 2030
A23: Attributable profit | B23: ='Income Statement'!E14 | C23: ='Income Statement'!F14 | D23: ='Income Statement'!G14 | E23: ='Income Statement'!H14 | F23: ='Income Statement'!I14
A24: Earnings per share | B24: ='Income Statement'!E21 | C24: ='Income Statement'!F21 | D24: ='Income Statement'!G21 | E24: ='Income Statement'!H21 | F24: ='Income Statement'!I21
A25: Dividend per share | B25: ='Income Statement'!E22 | C25: ='Income Statement'!F22 | D25: ='Income Statement'!G22 | E25: ='Income Statement'!H22 | F25: ='Income Statement'!I22
A26: Book value per share | B26: ='Income Statement'!E23 | C26: ='Income Statement'!F23 | D26: ='Income Statement'!G23 | E26: ='Income Statement'!H23 | F26: ='Income Statement'!I23

Sheet Fundamental Valuation
A1: ADIB-Egypt — the three present-value lenses | B1: Value | D1: 2026E | E1: 2027E | F1: 2028E | G1: 2029E | H1: 2030E
A3: LENS 1 — DIVIDEND DISCOUNT (the PRIMARY; this is the central)
A4: Dividend, EGP million | D4: ='Balance Sheet'!C13 | E4: ='Balance Sheet'!D13 | F4: ='Balance Sheet'!E13 | G4: ='Balance Sheet'!F13 | H4: ='Balance Sheet'!G13
A5: Discount factor | D5: ='Assumptions'!B36 | E5: ='Assumptions'!C36 | F5: ='Assumptions'!D36 | G5: ='Assumptions'!E36 | H5: ='Assumptions'!F36
A6: Present value of the dividend | D6: =D4*D5 | E6: =E4*E5 | F6: =F4*F5 | G6: =G4*G5 | H6: =H4*H5
A7: Sum of the explicit years | B7: =SUM(D6:H6)
A8: Terminal return on equity | B8: ='Income Statement'!I20
A9: Terminal payout (DERIVED as 1 − g / return, never typed) | B9: =1-'Assumptions'!$B$31/B8
A10: Terminal value | B10: ='Income Statement'!I14*(1+'Assumptions'!$B$31)*B9/('Assumptions'!$B$34-'Assumptions'!$B$31)
A11: Present value of the terminal | B11: =B10*H5
A12: Equity value | B12: =B7+B11
A14: LENS 2 — FREE CASH FLOW TO EQUITY (cross-check)
A15: Net flow to shareholders | D15: ='Balance Sheet'!C15 | E15: ='Balance Sheet'!D15 | F15: ='Balance Sheet'!E15 | G15: ='Balance Sheet'!F15 | H15: ='Balance Sheet'!G15
A16: Present value | D16: =D15*D5 | E16: =E15*E5 | F16: =F15*F5 | G16: =G15*G5 | H16: =H15*H5
A17: Terminal value | B17: =('Income Statement'!I14*(1+'Assumptions'!$B$31)-'Assumptions'!$B$19*'Balance Sheet'!G4*'Assumptions'!$B$31)/('Assumptions'!$B$34-'Assumptions'!$B$31)
A18: Equity value | B18: =SUM(D16:H16)+B17*H5
A20: LENS 3 — RESIDUAL INCOME (cross-check)
A21: Residual income (profit less a charge for the equity used) | D21: ='Income Statement'!E14-'Assumptions'!B35*'Balance Sheet'!C10 | E21: ='Income Statement'!F14-'Assumptions'!C35*'Balance Sheet'!D10 | F21: ='Income Statement'!G14-'Assumptions'!D35*'Balance Sheet'!E10 | G21: ='Income Statement'!H14-'Assumptions'!E35*'Balance Sheet'!F10 | H21: ='Income Statement'!I14-'Assumptions'!F35*'Balance Sheet'!G10
A22: Present value | D22: =D21*D5 | E22: =E21*E5 | F22: =F21*F5 | G22: =G21*G5 | H22: =H21*H5
A23: Opening book value plus capital paid in | B23: ='Balance Sheet'!B11+'Assumptions'!$B$20
A24: Terminal residual income, discounted | B24: =(('Income Statement'!I14-'Assumptions'!$B$34*'Balance Sheet'!G10)*(1+'Assumptions'!$B$31)/('Assumptions'!$B$34-'Assumptions'!$B$31))*H5
A25: Equity value | B25: =B23+SUM(D22:H22)+B24
A30: DIVIDEND DISCOUNT — value per share (THE CENTRAL) | B30: =B12/'Summary'!$B$5
A31: Free cash flow to equity — value per share | B31: =B18/'Summary'!$B$5
A32: Residual income — value per share | B32: =B25/'Summary'!$B$5

Sheet Assumptions
A1: Driver (BLUE cells are inputs — change them) | B1: 2026 | C1: 2027 | D1: 2028 | E1: 2029 | F1: 2030 | G1: Source / basis
A3: VOLUME
A4: Financing to customers, growth | B4: 0.48 | C4: 0.26 | D4: 0.19 | E4: 0.15 | F4: 0.12 | G4: Net financing to customers, year-on-year. FY2026 +48% takes the FY2025 close of EGP 147,226 million to EGP 217,895 million — and the bank was ALREADY at EGP 190,427 million on 30 June, so this asks for only +14.4% in the second half against +29.3% in the first. The path then decays toward nominal GDP. IT IS NOT A FLAT SHARE OF SYSTEM CREDIT, and that is the walk-forward's doing: a flat-share rule under-forecast this name at every one of eleven origins, by a median 0.29 in logs at three years, because ADIB has taken share at about 8.7% a year for a decade. The share path this implies is disclosed in the macro-coherence table and it decelerates to zero drift by FY2030.
A5: Financing / total assets | B5: 0.47 | C5: 0.485 | D5: 0.5 | E5: 0.51 | F5: 0.52 | G5: Financing to customers over total assets. FY2025 actual 42.46%; 30 June 2026 actual 45.96%. The bank is rotating out of treasury bills into customer financing as policy rates fall and bill yields compress, and the path continues that observed rotation at a decelerating pace. Every point is above both observations, which is the assumption, and it is sensitised.
A6: RATES — inputs. The margin is an OUTPUT of these two rows.
A7: Asset yield on average assets | B7: 0.15 | C7: 0.134 | D7: 0.121 | E7: 0.113 | F7: 0.108 | G7: Income from Murabaha, Musharaka, Mudaraba and similar income over AVERAGE total assets. FY2025 actual 16.23%; the six months to June 2026 annualise to 15.30%. The path falls with the CBE's published policy glide (19.00 -> 12.00) at an asset beta of about 0.75, which is what an Egyptian bank holding treasury bills and floating-rate corporate paper reprices at. IT IS AN INPUT; net interest margin is not.
A8: Cost of funds on average interest-bearing liabilities | B8: 0.106 | C8: 0.092 | D8: 0.081 | E8: 0.074 | F8: 0.07 | G8: Cost of deposits and similar costs over AVERAGE INTEREST-BEARING LIABILITIES — customers' deposits plus due to banks plus subordinated financing, and nothing else. FY2025 actual 11.22%. Total liabilities is NOT the denominator: at FY2025 it would add EGP 17.9 billion of other liabilities, current tax and provisions that pay nothing, and understate the funding rate by about a sixth of itself. The path falls at a deposit beta of about 0.80 to the policy glide, slower than the asset side, which is why the margin compresses.
A9: Interest-bearing liabilities / total assets | B9: 0.855 | G9: Average interest-bearing liabilities over average total assets, held at the FY2025 observed 85.5%. The bank funds itself with deposits and that ratio has moved within two points across the whole panel.
A10: OTHER INCOME AND COST
A11: Net fees / average assets | B11: 0.008 | C11: 0.0082 | D11: 0.0084 | E11: 0.0085 | F11: 0.0085 | G11: Net fees and commissions over average total assets. FY2025 actual 0.899%; the June 2026 half annualises to 0.797%. The path opens at the reviewed half's level and recovers slowly as trade finance and card income grow with the branch network.
A12: Other non-interest income / average assets | B12: 0.0028 | C12: 0.0026 | D12: 0.0024 | E12: 0.0023 | F12: 0.0022 | G12: Dividends, net trading, share of associates and gains on investments, as one block, over average total assets. FY2025 actual 0.238%; the June 2026 half annualises to 0.372%, flattered by trading gains on a moving currency. The path normalises DOWN toward the FY2022-FY2024 average as the pound settles.
A13: Other operating expenses / average assets | B13: -0.0075 | C13: -0.007 | D13: -0.0065 | E13: -0.006 | F13: -0.0055 | G13: Other operating expenses over average total assets — deposit insurance, central-bank charges and the operating-provision line. FY2025 actual -0.387%; the June 2026 half annualises to -0.797%, more than double. The path opens at the reviewed level and decays, which is the conservative reading of a line that has doubled.
A14: Administrative expenses, growth | B14: 0.34 | C14: 0.18 | D14: 0.15 | E14: 0.135 | F14: 0.13 | G14: Administrative expenses, year-on-year. FY2026 +34% on FY2025 takes EGP 3,431 million to EGP 4,598 million; the June half already spent EGP 2,239 million, so this asks for EGP 2,359 million in the second. Thereafter inflation plus about six points, because a bank adding branches and systems does not hold headcount flat. Cost-to-income is an OUTPUT of this and of the revenue lines; it is not typed anywhere.
A15: Cost of risk on average financing | B15: 0.01 | C15: 0.013 | D15: 0.013 | E15: 0.013 | F15: 0.013 | G15: Expected credit losses over AVERAGE net financing to customers. The observed series is 1.64% (FY2022), 2.73% (FY2023), 2.73% (FY2024), 1.25% (FY2025) and effectively ZERO in the June 2026 half — EGP 2.176 million on a EGP 190 billion book. FY2026 is set at 1.00%, above the half-year run rate and below the four-year mean of 2.09%; the outer years at 1.30% sit between the two. ANNUALISING THE JUNE HALF WOULD HAVE ADDED ABOUT EGP 1.8 BILLION TO FY2026 PRE-TAX PROFIT and it is not done. Sensitised +/-50 basis points in 1.9.
A16: TAX, CAPITAL AND THE SHAREHOLDER
A17: Effective tax rate | B17: 0.285 | G17: Effective tax rate. FY2025 actual 27.92%, FY2024 26.64%, the June 2026 half 29.57%. The Egyptian statutory corporate rate is 22.5%; an Egyptian bank pays materially more because the 20% withholding on treasury-bill income is not creditable and part of its cost base is disallowed. 28.5% sits inside the observed range and above the statutory rate for that reason.
A18: Non-controlling interests, share of profit | B18: 0.001 | G18: Non-controlling interests take 0.10% of net profit — EGP 12.4 million of EGP 12,601.0 million in FY2025. Held at that level; it is immaterial and is carried rather than dropped so the bridge to attributable profit closes.
A19: Target equity / total assets | B19: 0.105 | G19: Attributable equity to total assets, held at 10.5% — the level ADIB-Egypt actually stood at on 30 June 2026 after its EGP 3 billion cash increase, against 9.98% at the FY2025 year end. THIS IS THE BINDING CONSTRAINT ON A GROWING BANK and the model pins the RATIO, not the increment: equity each year is 10.5% of that year's assets and the dividend is whatever profit is left after getting there. A bank growing its balance sheet 34% cannot also distribute, and the arithmetic says so rather than a sentence saying so beside a typed payout.
A20: Capital raised in 2026, EGP million | B20: 3000 | G20: The EGP 3,000 million cash capital increase completed in the first half of 2026, taking issued capital from EGP 12 billion to EGP 15 billion — 300 million new shares at the LE 10 par. IT WAS ISSUED AT PAR, far below book: attributable book value per share was EGP 28.83 at 31 December 2025 on 1,200 million shares and EGP 29.04 at 30 June 2026 on 1,500 million, so a half-year at a 38.6% return on equity bought existing holders 0.7% of book value per share and the rest went to the new shares. This is the study's crux and it is in 1.7.
A21: COST OF EQUITY
A22: Egyptian ten-year local-currency yield | B22: 0.23 | G22: Egypt ten-year EGP government bond yield, 23.00%, the quote of 6 August 2026 held in the house macroeconomic path and already used by the PHDC, EGCH and PHAR cost-of-capital records. IT IS 34 DAYS OLD AGAINST THIS STUDY'S PRICING DATE AND THE HOUSE PATH'S OWN 14-DAY STALENESS RULE FLAGS IT AS STALE. A live re-source was attempted on 9 September 2026 down four routes and all four failed: the central bank's treasury-bond auction pages return 404, its auction API returns the site shell, the market-data pages render their yield tables in JavaScript, and the investing.com bond page returns 403. The level is carried, the staleness is declared here rather than buried, and the rate is sensitised by +/-200 basis points in section 1.9.
A23: less the sovereign default spread | B23: 0.0342 | G23: Egypt sovereign credit-default-swap spread, 3.42%, mid-year (July 2026) vintage of the country default-spread dataset, Egypt row, "Sovereign CDS net of Swiss CDS". Netted out of the local-currency risk-free rate so that sovereign default risk is charged ONCE, inside the equity risk premium, and not twice. The house macroeconomic path carries 3.41% for the same field from the same file; the one-basis-point difference is a rounding artefact and is immaterial.
A24: Beta against the EGX30 index | B24: 1.0746933 | G24: Own-stock first-tier weekly regression against EGX30 — THE PUBLISHED INDEX OF THE EXCHANGE THIS STOCK IS LISTED ON — resolved by beta_regression.own_stock_beta() rather than hand-rolled. Beta 1.0747, R-squared 0.248, n = 256 weekly observations over 4.94 years to 2026-08-20, standard error 0.1634, 90% confidence interval [0.806, 1.344], Dimson-corrected and matched to the exchange's own trading week (W-THU). The coefficient is 6.6 times its own standard error. Blume cross-check 1.0498.
A25: Egyptian total equity risk premium | B25: 0.095164 | G25: Egypt TOTAL equity risk premium on the sovereign-CDS basis, 9.5164%, same mid-year vintage. This is the dataset's TOTAL premium column, not its country premium column — the total is what multiplies beta. The country risk premium alone on this basis is 5.3164% and is NOT added on top.
A26: Terminal risk-free rate | B26: 0.105 | G26: Terminal risk-free rate, DERIVED and never quoted: terminal inflation of 7.00% (the CBE target-band midpoint in force) plus the 5.50% emerging-market terminal real convention. It cannot disagree with the inflation the rest of the model runs on because it is computed from it.
A27: Terminal equity risk premium | B27: 0.07 | G27: Terminal equity risk premium, 7.00%, normalised below today's crisis-era level toward the rating-class norm; never held flat into perpetuity.
A28: of which the MATURE premium — beta applies to this leg only | B28: 0.04318 | G28: Damodaran identity: total premium less the country leg
A29: Egypt country premium — charged FLAT, once, never multiplied by beta | B29: 0.051984 | G29: sovereign default spread x the equity-to-bond scaling
A30: Terminal country premium — charged FLAT and once | B30: 0.02682 | G30: terminal total premium less the SAME mature leg: what normalises is country risk
A31: Terminal growth | B31: 0.07 | G31: Terminal growth 7.00% = terminal inflation, ZERO REAL. For a bank in an economy whose private credit is 26% of GDP that is deliberately conservative: it assumes ADIB-Egypt stops taking share and stops participating in credit deepening the moment the explicit window closes. It sits BELOW the 12.50% terminal risk-free rate and equals the inflation inside it, so the terminal cannot grow faster than the money it is discounted in.
A33: Cost of equity (= rf − sovereign spread + beta × MATURE premium + country premium, flat) | B33: =B22-B23+B24*B28+B29
A34: Terminal cost of equity | B34: =B26+B24*B28+B30
A35: Cost of equity by year (glide) | B35: =$B$33+($B$34-$B$33)*1/6 | C35: =$B$33+($B$34-$B$33)*2/6 | D35: =$B$33+($B$34-$B$33)*3/6 | E35: =$B$33+($B$34-$B$33)*4/6 | F35: =$B$33+($B$34-$B$33)*5/6
A36: Discount factor | B36: =1/(1+B35) | C36: =B36/(1+C35) | D36: =C36/(1+D35) | E36: =D36/(1+E35) | F36: =E36/(1+F35)

Sheet SOTP Bridge
A1: SUM-OF-THE-PARTS BRIDGE — NOT APPLICABLE, AND THE REASON IS NOT AN OMISSION.
A3: ADIB-Egypt is one bank. It consolidates a small leasing and micro-finance operation whose contribution is inside the numbers everywhere in this model: non-controlling interests take 0.10% of net profit (EGP 12.4 million of EGP 12601.0 million in FY2025) and the associates line contributed EGP 161.3 million. There are no separable parts to value apart, and inventing a sum-of-the-parts here would be presentation rather than analysis.
A5: FOR A BANK THE EQUIVALENT BRIDGE IS THE CAPITAL ACCOUNT, and it is on the Balance Sheet tab: opening equity, the profit earned, the capital raised, the equity the balance sheet consumed, and the dividend that is what is left. That is the bridge between what the bank earns and what a shareholder receives, and it is the one that matters here.
A7: THIS SHEET IS PRESENT BECAUSE THE STANDARD SHEET LIST REQUIRES IT. A sheet deleted because it did not apply would read to a checker exactly like a sheet nobody built.

Sheet Segments
A1: What the filings disclose | B1: FY2025 | C1: H1-2026 | D1: Used as a driver?
A3: Income from Murabaha, Musharaka, Mudaraba and similar | B3: 49262.5 | C3: 29117.9 | D3: yes — the yield x average assets build
A4: Cost of deposits and similar costs | B4: -29110.1 | C4: -16864 | D4: yes — the funding rate x average interest-bearing liabilities
A5: Net fees and commissions | B5: 2729.8 | C5: 1516.6 | D5: yes — a rate on average assets
A6: Financing to customers, net | B6: 147226.1 | C6: 190427.1 | D6: yes — the volume driver
A7: Customers' deposits | B7: 277564.4 | C7: — | D7: yes — via the assets-to-deposits ratio
A8: Total assets | B8: 346711.2 | C8: 414302.1 | D8: yes
A10: WHAT IS NOT DISCLOSED, AND SO IS NOT MODELLED
A11: · No split of financing between retail, corporate and small business.
A12: · No split of deposits between current, savings and investment accounts, so the low-cost funding share cannot be measured and no assumption is made about it.
A13: · No geographic or product segment note.
A14: · No disclosed non-performing ratio or coverage in the statements parsed.
A16: A driver this study cannot see is a driver this study does not model. The alternative is inventing a segmentation the issuer does not publish.

Sheet Relative & Normalized
A1: Cross-check lenses (BLUE cells are inputs) | B1: Value | C1: Note
A3: RELATIVE MULTIPLES
A4: Forecast 2026 book value per share | B4: ='Income Statement'!E23
A5: Forecast 2026 earnings per share | B5: ='Income Statement'!E21
A6: Price-to-book, low | B6: 1.4
A7: Price-to-book, high | B7: 2.2
A8: Price-to-earnings, low | B8: 5.5
A9: Price-to-earnings, high | B9: 8.5
A10: Book-based midpoint | B10: =B4*AVERAGE(B6:B7)
A11: Earnings-based midpoint | B11: =B5*AVERAGE(B8:B9)
A12: RELATIVE MULTIPLES — value per share | B12: =AVERAGE(B10,B11) | C12: The price-to-book band Egyptian large-cap banks trade in. It is a BAND and not a point because this study could not source a same-day book value for any Egyptian bank other than ADIB itself: the only peer whose price it holds on the same day is CIB, and CIB's own book value is not in this repository. The band is carried as a cross-check on the two cash-flow lenses, weighted at 15%, and it is NOT allowed to set the answer. Where a multiple cannot be sourced it is said so rather than filled in.
A14: BOOK VALUE AND THE RETURN IT SUSTAINS
A15: Attributable book value per share, 30 June 2026 (filed) | B15: 29.0386
A16: Terminal return on equity | B16: ='Fundamental Valuation'!B8
A17: Sustainable price-to-book (= (return − g) / (cost of equity − g)) | B17: =(B16-'Assumptions'!$B$31)/('Assumptions'!$B$34-'Assumptions'!$B$31)
A18: Book-value floor (what is owned if compounding stops) | B18: =B15
A20: BOOK VALUE AND SUSTAINABLE RETURN — value per share | B20: =B15*B17
A22: NORMALISED EARNINGS POWER (reported, carries no weight)
A23: Normalised net interest margin | B23: 0.055
A24: Normalised cost of risk | B24: 0.015
A25: Normalised attributable profit, EGP million | B25: =(B23*'Balance Sheet'!C6+'Assumptions'!$B$11*'Balance Sheet'!C6+'Assumptions'!$B$12*'Balance Sheet'!C6+'Assumptions'!$B$13*'Balance Sheet'!C6+'Income Statement'!E8-B24*'Balance Sheet'!C7)*(1-'Assumptions'!$B$17)*(1-'Assumptions'!$B$18)
A28: NORMALISED EARNINGS POWER — value per share | B28: =B25/('Assumptions'!$B$33-'Assumptions'!$B$31)/'Summary'!$B$5 | C28: the normalised profit capitalised at the current cost of equity less terminal growth. A check on whether the cycle is being capitalised, not a valuation.

Sheet DCF
A1: THERE IS NO FREE-CASH-FLOW-TO-THE-FIRM DISCOUNTED CASH FLOW IN THIS MODEL.
A3: A bank's deposits are its raw material, not its financing. An enterprise-value discounted cash flow subtracts them as though they were borrowings, which for ADIB-Egypt would mean subtracting EGP 277,564 million of customer money the bank exists to gather. There is no weighted average cost of capital here and no enterprise-to-equity bridge.
A5: THE EQUIVALENT IS ON THE FUNDAMENTAL VALUATION TAB and it is a discounted cash flow in every sense that matters: a flow to the shareholder, projected five years, discounted at a cost of equity that glides with the central bank's published path, with a terminal value on a growth rate equal to terminal inflation.
A7: The discounting mechanics are repeated here so a reader looking for them finds them.
B10: 2026 | C10: 2027 | D10: 2028 | E10: 2029 | F10: 2030 | G10: terminal
A11: Flow to shareholders | B11: ='Balance Sheet'!C15 | C11: ='Balance Sheet'!D15 | D11: ='Balance Sheet'!E15 | E11: ='Balance Sheet'!F15 | F11: ='Balance Sheet'!G15
A12: Cost of equity | B12: ='Assumptions'!B35 | C12: ='Assumptions'!C35 | D12: ='Assumptions'!D35 | E12: ='Assumptions'!E35 | F12: ='Assumptions'!F35
A13: Discount factor | B13: ='Assumptions'!B36 | C13: ='Assumptions'!C36 | D13: ='Assumptions'!D36 | E13: ='Assumptions'!E36 | F13: ='Assumptions'!F36
A14: Present value | B14: =B11*B13 | C14: =C11*C13 | D14: =D11*D13 | E14: =E11*E13 | F14: =F11*F13
A15: Terminal value, discounted | B15: ='Fundamental Valuation'!B17*'Fundamental Valuation'!H5
A16: Equity value | B16: =SUM(B14:F14)+B15
A17: Value per share | B17: =B16/'Summary'!$B$5

Sheet Income Statement
A1: EGP million | B1: FY2023A | C1: FY2024A | D1: FY2025A | E1: 2026E | F1: 2027E | G1: 2028E | H1: 2029E | I1: 2030E
A3: Financing income | B3: 19533.7 | C3: 36944.5 | D3: 49262.5 | E3: ='Balance Sheet'!C6*'Assumptions'!B7 | F3: ='Balance Sheet'!D6*'Assumptions'!C7 | G3: ='Balance Sheet'!E6*'Assumptions'!D7 | H3: ='Balance Sheet'!F6*'Assumptions'!E7 | I3: ='Balance Sheet'!G6*'Assumptions'!F7
A4: Cost of deposits | B4: -10609.5 | C4: -21691.8 | D4: -29110.1 | E4: =-'Balance Sheet'!C8*'Assumptions'!B8 | F4: =-'Balance Sheet'!D8*'Assumptions'!C8 | G4: =-'Balance Sheet'!E8*'Assumptions'!D8 | H4: =-'Balance Sheet'!F8*'Assumptions'!E8 | I4: =-'Balance Sheet'!G8*'Assumptions'!F8
A5: Net income from funds | B5: 8924.2 | C5: 15252.6 | D5: 20152.3 | E5: =E3+E4 | F5: =F3+F4 | G5: =G3+G4 | H5: =H3+H4 | I5: =I3+I4
A6: Net fees and commissions | B6: 1558.5 | C6: 1895.1 | D6: 2729.8 | E6: ='Balance Sheet'!C6*'Assumptions'!B11 | F6: ='Balance Sheet'!D6*'Assumptions'!C11 | G6: ='Balance Sheet'!E6*'Assumptions'!D11 | H6: ='Balance Sheet'!F6*'Assumptions'!E11 | I6: ='Balance Sheet'!G6*'Assumptions'!F11
A7: Other non-interest income | B7: 380.9 | C7: 854.5 | D7: 721.3 | E7: ='Balance Sheet'!C6*'Assumptions'!B12 | F7: ='Balance Sheet'!D6*'Assumptions'!C12 | G7: ='Balance Sheet'!E6*'Assumptions'!D12 | H7: ='Balance Sheet'!F6*'Assumptions'!E12 | I7: ='Balance Sheet'!G6*'Assumptions'!F12
A8: Administrative expenses | B8: -1921.9 | C8: -2614.5 | D8: -3431.2 | E8: =-(3431.217)*(1+'Assumptions'!B14) | F8: =-(-E8)*(1+'Assumptions'!C14) | G8: =-(-F8)*(1+'Assumptions'!D14) | H8: =-(-G8)*(1+'Assumptions'!E14) | I8: =-(-H8)*(1+'Assumptions'!F14)
A9: Other operating expenses | B9: -772.5 | C9: -927 | D9: -1176 | E9: ='Balance Sheet'!C6*'Assumptions'!B13 | F9: ='Balance Sheet'!D6*'Assumptions'!C13 | G9: ='Balance Sheet'!E6*'Assumptions'!D13 | H9: ='Balance Sheet'!F6*'Assumptions'!E13 | I9: ='Balance Sheet'!G6*'Assumptions'!F13
A10: Expected credit losses | B10: -1633.8 | C10: -2170.6 | D10: -1514.1 | E10: =-'Balance Sheet'!C7*'Assumptions'!B15 | F10: =-'Balance Sheet'!D7*'Assumptions'!C15 | G10: =-'Balance Sheet'!E7*'Assumptions'!D15 | H10: =-'Balance Sheet'!F7*'Assumptions'!E15 | I10: =-'Balance Sheet'!G7*'Assumptions'!F15
A11: Profit before tax | B11: 6535.4 | C11: 12290.2 | D11: 17482.1 | E11: =E5+E6+E7+E8+E9+E10 | F11: =F5+F6+F7+F8+F9+F10 | G11: =G5+G6+G7+G8+G9+G10 | H11: =H5+H6+H7+H8+H9+H10 | I11: =I5+I6+I7+I8+I9+I10
A12: Tax | B12: -1861.5 | C12: -3274.2 | D12: -4881.2 | E12: =-E11*'Assumptions'!$B$17 | F12: =-F11*'Assumptions'!$B$17 | G12: =-G11*'Assumptions'!$B$17 | H12: =-H11*'Assumptions'!$B$17 | I12: =-I11*'Assumptions'!$B$17
A13: Net profit | B13: 4673.8 | C13: 9015.9 | D13: 12601 | E13: =E11+E12 | F13: =F11+F12 | G13: =G11+G12 | H13: =H11+H12 | I13: =I11+I12
A14: Attributable to the bank | B14: 4670.7 | C14: 9008.9 | D14: 12588.6 | E14: =E13*(1-'Assumptions'!$B$18) | F14: =F13*(1-'Assumptions'!$B$18) | G14: =G13*(1-'Assumptions'!$B$18) | H14: =H13*(1-'Assumptions'!$B$18) | I14: =I13*(1-'Assumptions'!$B$18)
A16: THE RATIOS — every one an OUTPUT of the rows above
A17: Net interest margin | E17: =E5/'Balance Sheet'!C6 | F17: =F5/'Balance Sheet'!D6 | G17: =G5/'Balance Sheet'!E6 | H17: =H5/'Balance Sheet'!F6 | I17: =I5/'Balance Sheet'!G6
A18: Cost-to-income | E18: =-E8/(E5+E6+E7) | F18: =-F8/(F5+F6+F7) | G18: =-G8/(G5+G6+G7) | H18: =-H8/(H5+H6+H7) | I18: =-I8/(I5+I6+I7)
A19: Return on average assets | E19: =E13/'Balance Sheet'!C6 | F19: =F13/'Balance Sheet'!D6 | G19: =G13/'Balance Sheet'!E6 | H19: =H13/'Balance Sheet'!F6 | I19: =I13/'Balance Sheet'!G6
A20: Return on average equity | E20: =E14/AVERAGE('Balance Sheet'!C10,'Balance Sheet'!C11) | F20: =F14/AVERAGE('Balance Sheet'!D10,'Balance Sheet'!D11) | G20: =G14/AVERAGE('Balance Sheet'!E10,'Balance Sheet'!E11) | H20: =H14/AVERAGE('Balance Sheet'!F10,'Balance Sheet'!F11) | I20: =I14/AVERAGE('Balance Sheet'!G10,'Balance Sheet'!G11)
A21: Earnings per share | E21: =E14/'Summary'!$B$5 | F21: =F14/'Summary'!$B$5 | G21: =G14/'Summary'!$B$5 | H21: =H14/'Summary'!$B$5 | I21: =I14/'Summary'!$B$5
A22: Dividend per share | E22: ='Balance Sheet'!C13/'Summary'!$B$5 | F22: ='Balance Sheet'!D13/'Summary'!$B$5 | G22: ='Balance Sheet'!E13/'Summary'!$B$5 | H22: ='Balance Sheet'!F13/'Summary'!$B$5 | I22: ='Balance Sheet'!G13/'Summary'!$B$5
A23: Book value per share | E23: ='Balance Sheet'!C11/'Summary'!$B$5 | F23: ='Balance Sheet'!D11/'Summary'!$B$5 | G23: ='Balance Sheet'!E11/'Summary'!$B$5 | H23: ='Balance Sheet'!F11/'Summary'!$B$5 | I23: ='Balance Sheet'!G11/'Summary'!$B$5

Sheet Balance Sheet
A1: EGP million | B1: FY2025A | C1: 2026E | D1: 2027E | E1: 2028E | F1: 2029E | G1: 2030E | H1: note
A2: THE BALANCE SHEET DRIVES THE INCOME STATEMENT, NOT THE OTHER WAY ROUND.
A3: Financing to customers, closing | B3: 147226.1 | C3: =B3*(1+'Assumptions'!B4) | D3: =C3*(1+'Assumptions'!C4) | E3: =D3*(1+'Assumptions'!D4) | F3: =E3*(1+'Assumptions'!E4) | G3: =F3*(1+'Assumptions'!F4) | H3: grows at the input rate on Assumptions
A4: Total assets, closing | B4: 346711.2 | C4: =C3/'Assumptions'!B5 | D4: =D3/'Assumptions'!C5 | E4: =E3/'Assumptions'!D5 | F4: =F3/'Assumptions'!E5 | G4: =G3/'Assumptions'!F5
A5: Customers' deposits, closing | B5: 277564.4 | C5: =C4/1.24912 | D5: =D4/1.24912 | E5: =E4/1.24912 | F5: =F4/1.24912 | G5: =G4/1.24912
A6: Average total assets | C6: =AVERAGE(B4,C4) | D6: =AVERAGE(C4,D4) | E6: =AVERAGE(D4,E4) | F6: =AVERAGE(E4,F4) | G6: =AVERAGE(F4,G4)
A7: Average financing | C7: =AVERAGE(B3,C3) | D7: =AVERAGE(C3,D3) | E7: =AVERAGE(D3,E3) | F7: =AVERAGE(E3,F3) | G7: =AVERAGE(F3,G3)
A8: Average interest-bearing liabilities | C8: =C6*'Assumptions'!$B$9 | D8: =D6*'Assumptions'!$B$9 | E8: =E6*'Assumptions'!$B$9 | F8: =F6*'Assumptions'!$B$9 | G8: =G6*'Assumptions'!$B$9
A10: Attributable equity, opening | C10: =B11 | D10: =C11 | E10: =D11 | F10: =E11 | G10: =F11
A11: Attributable equity, closing | B11: 34596.3 | C11: =C4*'Assumptions'!$B$19 | D11: =D4*'Assumptions'!$B$19 | E11: =E4*'Assumptions'!$B$19 | F11: =F4*'Assumptions'!$B$19 | G11: =G4*'Assumptions'!$B$19 | H11: PINNED at the target ratio — the capital a bank must hold
A12: Equity build required | C12: =C11-C10 | D12: =D11-D10 | E12: =E11-E10 | F12: =F11-F10 | G12: =G11-G10
A13: Dividend | C13: ='Income Statement'!E14+C14-C12 | D13: ='Income Statement'!F14+D14-D12 | E13: ='Income Statement'!G14+E14-E12 | F13: ='Income Statement'!H14+F14-F12 | G13: ='Income Statement'!I14+G14-G12 | H13: DERIVED: profit plus new shares, less the equity build. Never typed.
A14: Capital raised | C14: ='Assumptions'!$B$20 | D14: 0 | E14: 0 | F14: 0 | G14: 0
A15: Net flow to shareholders | C15: =C13-C14 | D15: =D13-D14 | E15: =E13-E14 | F15: =F13-F14 | G15: =G13-G14 | H15: negative in 2026 because that is the year shareholders paid in
A16: Equity / total assets | B16: =B11/B4 | C16: =C11/C4 | D16: =D11/D4 | E16: =E11/E4 | F16: =F11/F4 | G16: =G11/G4

Sheet Cash Flow
A1: EGP million | B1: FY2025A | C1: 2026E | D1: 2027E | E1: 2028E | F1: 2029E | G1: 2030E
A3: WHAT THE BANK EARNS AND WHERE IT GOES
A4: Attributable profit | B4: 12588.6 | C4: ='Income Statement'!E14 | D4: ='Income Statement'!F14 | E4: ='Income Statement'!G14 | F4: ='Income Statement'!H14 | G4: ='Income Statement'!I14
A5: less the equity the balance sheet consumes | C5: =-'Balance Sheet'!C12 | D5: =-'Balance Sheet'!D12 | E5: =-'Balance Sheet'!E12 | F5: =-'Balance Sheet'!F12 | G5: =-'Balance Sheet'!G12
A6: plus capital raised from shareholders | C6: ='Balance Sheet'!C14 | D6: ='Balance Sheet'!D14 | E6: ='Balance Sheet'!E14 | F6: ='Balance Sheet'!F14 | G6: ='Balance Sheet'!G14
A7: equals the Dividend | C7: ='Balance Sheet'!C13 | D7: ='Balance Sheet'!D13 | E7: ='Balance Sheet'!E13 | F7: ='Balance Sheet'!F13 | G7: ='Balance Sheet'!G13
A8: less what shareholders paid in | C8: =-'Balance Sheet'!C14 | D8: =-'Balance Sheet'!D14 | E8: =-'Balance Sheet'!E14 | F8: =-'Balance Sheet'!F14 | G8: =-'Balance Sheet'!G14
A9: equals the NET FLOW TO SHAREHOLDERS | C9: ='Balance Sheet'!C15 | D9: ='Balance Sheet'!D15 | E9: ='Balance Sheet'!E15 | F9: ='Balance Sheet'!F15 | G9: ='Balance Sheet'!G15
A11: FILED, FOR COMPARISON — dividends actually paid, FY2025 cash-flow statement | B11: 1055.866
A12: the same, as a share of FY2024 attributable profit | B12: =B11/9008.926
A13: This is the external check on the derived payout: the model gives 18.2% for FY2026 against the 11.7% the bank actually paid.

Sheet Summary Financials
A1: EGP million | B1: FY2023A | C1: FY2024A | D1: FY2025A | E1: H1-2026A | F1: 2026E | G1: 2027E | H1: 2028E | I1: 2029E | J1: 2030E
A3: Net income from funds | B3: 8924.2 | C3: 15252.6 | D3: 20152.3 | E3: 12253.9 | F3: ='Income Statement'!E5 | G3: ='Income Statement'!F5 | H3: ='Income Statement'!G5 | I3: ='Income Statement'!H5 | J3: ='Income Statement'!I5
A4: Profit before tax | B4: 6535.4 | C4: 12290.2 | D4: 17482.1 | E4: 10721.8 | F4: ='Income Statement'!E11 | G4: ='Income Statement'!F11 | H4: ='Income Statement'!G11 | I4: ='Income Statement'!H11 | J4: ='Income Statement'!I11
A5: Attributable profit | B5: 4670.7 | C5: 9008.9 | D5: 12588.6 | E5: 7536.8 | F5: ='Income Statement'!E14 | G5: ='Income Statement'!F14 | H5: ='Income Statement'!G14 | I5: ='Income Statement'!H14 | J5: ='Income Statement'!I14
A6: Financing to customers | B6: 63099.8 | C6: 95691.1 | D6: 147226.1 | E6: 190427.1 | F6: ='Balance Sheet'!C3 | G6: ='Balance Sheet'!D3 | H6: ='Balance Sheet'!E3 | I6: ='Balance Sheet'!F3 | J6: ='Balance Sheet'!G3
A7: Total assets | B7: 162254.7 | C7: 260467.1 | D7: 346711.2 | E7: 414302.1 | F7: ='Balance Sheet'!C4 | G7: ='Balance Sheet'!D4 | H7: ='Balance Sheet'!E4 | I7: ='Balance Sheet'!F4 | J7: ='Balance Sheet'!G4
A8: Attributable equity | B8: 14344.8 | C8: 22958.7 | D8: 34596.3 | E8: 43557.9 | F8: ='Balance Sheet'!C11 | G8: ='Balance Sheet'!D11 | H8: ='Balance Sheet'!E11 | I8: ='Balance Sheet'!F11 | J8: ='Balance Sheet'!G11
A10: THE RATIOS — outputs
A11: Net interest margin | D11: 0.06638 | F11: ='Income Statement'!E17 | G11: ='Income Statement'!F17 | H11: ='Income Statement'!G17 | I11: ='Income Statement'!H17 | J11: ='Income Statement'!I17
A12: Cost-to-income | D12: 0.14537 | F12: ='Income Statement'!E18 | G12: ='Income Statement'!F18 | H12: ='Income Statement'!G18 | I12: ='Income Statement'!H18 | J12: ='Income Statement'!I18
A13: Return on average equity | D13: 0.43745 | F13: ='Income Statement'!E20 | G13: ='Income Statement'!F20 | H13: ='Income Statement'!G20 | I13: ='Income Statement'!H20 | J13: ='Income Statement'!I20

Sheet Monte Carlo
A1: The probability map — the price engine, not the valuation
A3: Anchor price | B3: 54.4 | C3: close of 2026-08-23
A4: Clean sessions in the history | B4: 3762
A5: Shape parameter (degrees of freedom) | B5: 5 | C5: read live from the engine registry, fitted on the Egyptian panel — not chosen here
A6: Width calibration | B6: 0.951
A7: Per-stock width overlay | B7: 0.99090358
A8: Risk-free carry / dividend yield | B8: 0.195 | C8: 0.01352374
A10: Horizon | B10: Resolves | C10: 5th | D10: 25th | E10: Median | F10: 75th | G10: 95th
A11: 1 month | B11: 2026-09-23 | C11: 46.98 | D11: 52.4 | E11: 55.69 | F11: 59.23 | G11: 66.06
A12: 3 months | B12: 2026-11-23 | C12: 42.27 | D12: 51.66 | E12: 57.83 | F12: 64.72 | G12: 78.98
A14: THIS IS A DIFFERENT LENS FROM THE VALUATION AND IT IS NOT COMBINED WITH IT. It is a 50,000-path simulation of where the price goes, with a drift equal to the Egyptian carry and no view of direction beyond that. It is anchored on the 23 August close because that is the last session in the price history; the fair value is struck against the 3 September close. Two clocks.

Sheet Sensitivity
A1: What moves the answer | B1: Central | C1: Change
A3: cost of risk +50bp | B3: 39.4647 | C3: -0.112375
A4: cost of risk -50bp | B4: 49.4573 | C4: 0.112375
A5: asset yield -50bp | B5: 34.569 | C5: -0.222486
A6: asset yield +50bp | B6: 54.3529 | C6: 0.222486
A7: cost of funds +50bp | B7: 36.0034 | C7: -0.190225
A8: cost of funds -50bp | B8: 52.9186 | C8: 0.190225
A9: financing growth -5pp/yr | B9: 38.7004 | C9: -0.129564
A10: financing growth +5pp/yr | B10: 50.9691 | C10: 0.146378
A11: risk-free +200bp | B11: 36.6044 | C11: -0.176707
A12: risk-free -200bp | B12: 55.9735 | C12: 0.258936
A13: terminal growth +100bp | B13: 46.0776 | C13: 0.036361
A14: terminal growth -100bp | B14: 43.0861 | C14: -0.030924
A16: THE SENSITIVITIES MOVE THE PRIMARY LENS, not a blend. Change any blue cell on Assumptions to reproduce one of these rows live.
A18: TWO-WAY: value per share against the cost of risk and the asset yield
A19: cost of risk (2027-30) → | B19: 0.008 | C19: 0.011 | D19: 0.013 | E19: 0.015 | F19: 0.018
A20: asset yield -1.00%
A21: asset yield -0.50%
A22: asset yield +0.00%
A23: asset yield +0.50%
A24: asset yield +1.00%
A25: The grid is left for the reader to fill by changing the two blue rows on Assumptions: a pre-computed grid would be a picture of a model rather than the model.

Sheet Per-Share & Ratios
A1: Per share, EGP | B1: FY2025A | C1: 2026E | D1: 2027E | E1: 2028E | F1: 2029E | G1: 2030E
A3: Earnings | B3: 8.392 | C3: ='Income Statement'!E21 | D3: ='Income Statement'!F21 | E3: ='Income Statement'!G21 | F3: ='Income Statement'!H21 | G3: ='Income Statement'!I21
A4: Dividend | B4: 0.704 | C4: ='Income Statement'!E22 | D4: ='Income Statement'!F22 | E4: ='Income Statement'!G22 | F4: ='Income Statement'!H22 | G4: ='Income Statement'!I22
A5: Book value | B5: 23.064 | C5: ='Income Statement'!E23 | D5: ='Income Statement'!F23 | E5: ='Income Statement'!G23 | F5: ='Income Statement'!H23 | G5: ='Income Statement'!I23
A7: AT THE CENTRAL, AND AT THE MARKET
A8: Price / forecast 2026 book | B8: ='Summary'!B18/'Income Statement'!E23 | C8: ='Summary'!B4/'Income Statement'!E23 | D8: at the central | at the market
A9: Price / forecast 2026 earnings | B9: ='Summary'!B18/'Income Statement'!E21 | C9: ='Summary'!B4/'Income Statement'!E21
A10: Gordon price-to-book at the 2026 return and first-year cost of equity | B10: =('Income Statement'!E20-'Assumptions'!$B$31)/('Assumptions'!B35-'Assumptions'!$B$31) | D10: the multiple the model's own arithmetic supports
A12: YEARS THREE TO FIVE AS RANGES — from the walk-forward's own error spread
A13: Attributable profit, EGP million | B13: Low | C13: Point | D13: High | E13: Cells measured
A14: 2028 | B14: 4986 | C14: 17161 | D14: 25394 | E14: 8
A15: 2029 | B15: 7747 | C15: 18753 | D15: 43995 | E15: 7
A16: 2030 | B16: 10762 | C16: 20042 | D16: 49448 | E16: 6
A17: engine/adib_walkforward/forward_ranges.json — the FUNDAMENTAL walk-forward's own attributable-profit error dispersion, centred on its own median. Not the price-engine walk-forward and not the technical one.

Sheet Peer & Sector
A1: Peer | B1: Price | C1: Date | D1: What is held | E1: What is NOT
A3: ADIB-Egypt (EGX: ADIB) | B3: 52.05 | C3: 2026-09-03 | D3: price, and sixteen years of audited statements | E3: —
A4: Commercial International Bank (COMI) | B4: 138.98 | C4: 2026-09-03 | D4: price only, same file and same day | E4: book value, earnings, capital — none sourced on the study date
A5: Every other listed Egyptian bank | B5: — | C5: — | D5: nothing on the study date | E5: not sourced, and not substituted from memory
A7: THE BAND USED, AND WHY IT IS A BAND
A8: The price-to-book band Egyptian large-cap banks trade in. It is a BAND and not a point because this study could not source a same-day book value for any Egyptian bank other than ADIB itself: the only peer whose price it holds on the same day is CIB, and CIB's own book value is not in this repository. The band is carried as a cross-check on the two cash-flow lenses, weighted at 15%, and it is NOT allowed to set the answer. Where a multiple cannot be sourced it is said so rather than filled in.
A10: THE SECTOR FRAME
A11: Egyptian private-sector credit is about 26% of GDP, down from 36% in 2009: the banking system has shrunk relative to the economy for fifteen years while the government absorbed the savings.
A12: ADIB-Egypt is about 3.14% of that system credit and rising. The forecast takes it to about 4.42% by 2030, at a rate that decays to zero.
A13: A reader who believes credit deepening resumes should read the growth path as conservative; a reader who believes the crowding-out continues should read it the other way.
