Workbook

Sheet READ FIRST
A1: Testahil — ADNOC Logistics & Services plc (ADX: ADNOCLS)
A3: Companion model · Independent Valuation Study · Educational analysis · Not investment advice
A5: What this workbook is. A transparent companion to the ADNOC L&S valuation study. Every blue cell is an
A6: input; every black cell is a formula; green cells link across sheets.
A8: IT IS FORMULA-DRIVEN. Every figure that can be derived arithmetically from a driver is a live formula, so
A9: you can change a blue cell on Assumptions and watch the model reprice. The cost of equity is built from the
A10: normalised risk-free rate, the beta and the equity risk premium — and the normalised rate is itself a
A11: formula, the observed government bond yield less the sovereign default spread. The cost of debt is built
A12: three separate ways on the sheet — the parent facility at the overnight financing rate plus its margin, a
A13: weighted blend of the instruments the company actually has outstanding, and the disclosed third-party
A14: bank-loan midpoint — and the three are averaged in a cell. The discount factors compound year on year off
A15: the cost-of-capital glide, with a three-quarter stub for 2026 because the valuation date is 31 March 2026.
... A115: Sensitivity · Per-Share & Ratios · Peer & Sector.

Sheet Summary
A1: Summary — valuation at a glance
A2: All values link live to their source sheets. AED per share unless stated.
A4: Lens | B4: Bear | C4: Base | D4: Bull | E4: Weight | F4: Contribution | G4: vs spot | H4: Terminal value share
A5: Discounted cash flow (own regressed beta) | B5: ='Fundamental Valuation'!$C$6 | C5: =DCF!$C$62 | D5: ='Fundamental Valuation'!$C$7 | E5: =Assumptions!$C$170 | F5: =C5*E5 | G5: =C5/$C$16-1 | H5: =DCF!$C$48
A6: Relative multiples | B6: ='Relative & Normalized'!$C$26 | C6: ='Relative & Normalized'!$C$21 | D6: ='Relative & Normalized'!$D$26 | E6: =Assumptions!$C$171 | F6: =C6*E6 | G6: =C6/$C$16-1
A7: Normalised earnings power | B7: ='Relative & Normalized'!$C$58 | C7: ='Relative & Normalized'!$C$53 | D7: ='Relative & Normalized'!$D$58 | E7: =Assumptions!$C$172 | F7: =C7*E7 | G7: =C7/$C$16-1
A8: Book value and sustainable return | B8: ='Relative & Normalized'!$C$102 | C8: ='Relative & Normalized'!$C$80 | D8: ='Relative & Normalized'!$D$102 | E8: =Assumptions!$C$173 | F8: =C8*E8 | G8: =C8/$C$16-1
A9: WEIGHTED CENTRAL | B9: =B5*E5+B6*E6+B7*E7+B8*E8 | C9: =SUM(F5:F8) | D9: =D5*E5+D6*E6+D7*E7+D8*E8 | E9: =SUM(E5:E8) | G9: =C9/$C$16-1
A11: THE CONTESTED JUDGEMENT — PUBLISHED BOTH WAYS, NEVER AVERAGED
A12: Discounted cash flow (composite-index beta of 0.705) | B12: =B5 | C12: =DCF!$C$141 | D12: =D5 | E12: =E5 | F12: =C12*E12 | G12: =C12/$C$16-1 | H12: =DCF!$C$136
A13: Weighted central on the composite-index beta | C13: =F12+F6+F7+F8 | G13: =C13/$C$16-1
A15: Expert panel average | C15: ='Fundamental Valuation'!$C$34 | G15: =C15/$C$16-1
A16: Market price (AED, anchor) | C16: =Assumptions!$C$5
A18: Key figure | C18: Value
A19: Shares outstanding (mn) | C19: =Assumptions!$C$6
A20: Market capitalisation (USD 000) | C20: =DCF!$C$97
A21: Enterprise value at the anchor price (USD 000) | C21: ='Relative & Normalized'!$C$32
A22: Net debt at 31 March 2026, including the deferred consideration and the eleven vessels bought on 7 August 2026 (USD 000) | C22: ='Relative & Normalized'!$C$31
A23: The eleven vessels bought on 7 August 2026, at the announced price (USD 000) | C23: =Assumptions!$C$82
A24: FY2025 revenue (USD 000) | C24: ='Income Statement'!D5
A25: FY2025 EBITDA as reported (USD 000) | C25: ='Income Statement'!D16
A26: FY2025 profit attributable to shareholders (USD 000) | C26: ='Income Statement'!D28
A27: Cost of equity — published-index beta (primary) | C27: =DCF!$C$69
A28: Cost of equity — composite-index beta (alternative) | C28: =DCF!$C$115
A29: Cost of equity at the lower 90% confidence bound on the primary beta | C29: =DCF!$C$123
A30: Cost of equity at the upper 90% confidence bound on the primary beta | C30: =DCF!$C$124
A31: Cost of debt — the three constructions averaged (a simple average, not a weighted figure) | C31: =DCF!$C$92
A32: Cost of debt — the balance-weighted construction alone, published beside the average rather than in place of it | C32: =DCF!$C$93
A33: Cost of capital — explicit window | C33: =DCF!$C$105
A34: Cost of capital — terminal | C34: =DCF!$C$111
A35: Terminal growth | C35: =DCF!$C$39
A36: Sum-of-the-parts cross-check (AED per share) | C36: ='SOTP Bridge'!$C$43
A38: The terminal value share beside the discounted-cash-flow row is a live formula — the present value of the terminal value over the enterprise value of operations — and it is shown again in the equity bridge on the SOTP Bridge sheet. It is high, as it is for any long-lived asset owner whose fleet outlives the forecast window, and it is the reason the terminal cost of capital and the terminal growth rate carry more of this valuation than any single trading year.

Sheet Fundamental Valuation
A1: Fundamental valuation — the four lenses and the contested judgement
A4: Lens / step | B4: Basis | C4: AED per share
A5: Discounted cash flow (own regressed beta) | B5: links to the DCF sheet — five explicit years plus a capitalised terminal value | C5: =DCF!$C$62
A6: bear | B6: beta 1.412 — the TOP of the regression's own 90% confidence interval, not a round number picked by hand — with the rate anchor at 0.85x and capital expenditure at 1.10x. A whole-model re-run | C6: 4.0250073
A7: bull | B7: beta 0.758 — the BOTTOM of the same interval — with the rate anchor at 1.15x and capital expenditure at 0.95x. Taking both bounds from the interval means the published range is the range the estimate itself supports. A whole-model re-run | C7: 10.132159
A8: Relative multiples | B8: blended enterprise and earnings multiples on 2026 earnings | C8: ='Relative & Normalized'!$C$21
A9: Normalised earnings power | B9: the same multiples on the five-year average of the forecast | C9: ='Relative & Normalized'!$C$53
A10: Book value and sustainable return | B10: the book the company already has, plus the present value of earning more than the cost of equity on it while that lasts, plus a fading remainder — a residual income build, not a justified multiple | C10: ='Relative & Normalized'!$C$80
A12: Weighted central | C12: =Summary!$C$9
A14: THE CONTESTED JUDGEMENT — TWO INDEX CONSTRUCTIONS, BOTH CARRIED THROUGH IN FULL
A15: Beta — weekly regression against the published index of its own exchange (primary) | B15: 161 weekly observations, R-squared 15.8%, standard error 0.199, 90% confidence interval 0.758 to 1.412 — the usability gate is passed, and this is the index the method asks for | C15: =Assumptions!$C$14
A16: Cost of equity on the published-index beta | B16: normalised risk-free rate plus beta times the equity risk premium | C16: =DCF!$C$69
A17: Cost of capital on the published-index beta | B17: explicit window, market-value weights | C17: =DCF!$C$105
A18: Fair value per share — published-index beta (AED) | B18: the primary reading | C18: =DCF!$C$62
A19: Weighted central — published-index beta (AED) | B19: all four lenses | C19: =Summary!$C$9
A20: Beta — the same regression against an equal-weight composite of the same exchange's names (alternative) | B20: the published index is weighted by size and is dominated by the same large-capitalisation group this company belongs to; the composite gives the exchange's smallest names the same say as its largest. Only the measure of the market changes | C20: =Assumptions!$C$15
A21: Cost of equity on the composite-index beta | B21: the same construction, the same premium, the composite beta | C21: =DCF!$C$115
A22: Cost of capital on the composite-index beta | B22: explicit window, market-value weights | C22: =DCF!$C$117
A23: Fair value per share — composite-index beta (AED) | B23: the alternative reading | C23: =DCF!$C$141
A24: Weighted central — composite-index beta (AED) | B24: all four lenses, the discounted-cash-flow leg swapped | C24: =Summary!$C$13
A25: Beta — lower bound of the 90% confidence interval on the primary regression | B25: the bull-case beta; the bear and bull cases take the two ends of this interval rather than round numbers picked by hand | C25: =Assumptions!$C$16
A26: Beta — upper bound of the 90% confidence interval on the primary regression | B26: the bear-case beta; the published range is therefore the range the estimate itself supports | C26: =Assumptions!$C$17
A27: These two readings are published side by side and are never averaged into a single number. They are the same regression of the same weekly returns; what differs is how the market itself is measured. The published index of the exchange is what the beta method asks for and is the primary reading. The equal-weight composite is what an earlier construction of this study used, and it is kept in view because a difference of this size is a property of index construction rather than a fact about the company. The regression passes its usability gate, but the history is only three years long and the 90% interval shown above spans more than half the point estimate, so the alternative is not a stress case — it is a second legitimate answer to the same question.
A29: EXPERT PANEL — THREE METHODS, WORKED INDEPENDENTLY
A30: Expert | B30: Method | C30: Base (AED per share) | D30: Low | E30: High
A31: Expert 1 | B31: mid-cycle earnings power | C31: 7.3089016 | D31: 5.4816762 | E31: 9.136127
A32: Expert 2 | B32: owner cash earnings | C32: 6.3021038 | D32: 4.6121737 | E32: 8.8564341
A33: Expert 3 | B33: cash returns against the cost of capital | C33: 4.8929387 | D33: 3.4814178 | E33: 5.9965206
A34: Panel average | C34: =AVERAGE(C31:C33)

Sheet Assumptions
A1: Assumptions — every input in the model
A2: Blue cells are inputs. Change one and the model reprices: everything downstream is a formula.
A4: Market and share anchors
A5: Share price (AED, Abu Dhabi Securities Exchange close) | C5: 6.16
A6: Shares outstanding (mn) | C6: 7398.4988
A7: Dirhams per US dollar (fixed parity, unchanged since 1997) | C7: 3.6725
A8: Stub year fraction — 31 March 2026 valuation date to 31 December 2026 | C8: 0.75
A9: First-quarter 2026 free cash flow, already inside net debt at the valuation date (USD 000) | C9: 130000
A11: Cost of capital
A12: Observed government bond yield (dirham tranche maturing January 2031) | C12: 0.0448
A13: Sovereign default spread (netted out of the risk-free rate) | C13: 0.0042
A14: Beta — own-stock weekly regression against the published index of its own exchange | C14: 1.085
A15: Beta — the same regression against an equal-weight composite of that exchange's names (the disclosed alternative) | C15: 0.705
A16: Beta — lower bound of the regression's 90% confidence interval (the bull-case beta) | C16: 0.758
A17: Beta — upper bound of the regression's 90% confidence interval (the bear-case beta) | C17: 1.412
A18: Beta — lead-lag sum beta from the same series, one lead and two lags | C18: 1.164
A19: Equity risk premium (mature premium plus country risk) | C19: 0.0487 | H19: No sovereign credit-default-swap entry exists for the United Arab Emirates in the country risk file, so the alternative rating-versus-swap premium basis cannot be built for this country; one basis is published rather than two.
A20: Terminal risk-free rate | C20: 0.0325
A21: Statutory corporate tax rate | C21: 0.09
A23: Cost of debt — the evidence behind the three constructions
A24: Secured overnight financing rate | C24: 0.0365 | H24: The Central Bank base rate of 3.65% was maintained at the 29 July 2026 decision; the last change was a 25 basis point cut from 3.90% on 10 December 2025.
A25: Parent revolving credit facility margin | C25: 0.008
A26: Third-party bank loans — low end of the disclosed range | C26: 0.0711
A27: Third-party bank loans — high end of the disclosed range | C27: 0.0755
A28: Other third-party borrowings — low end of the disclosed range | C28: 0.0436
A29: Other third-party borrowings — high end of the disclosed range | C29: 0.0831
A30: Lease interest charged in 2025 (USD 000) | C30: 12719
A31: Lease liabilities, opening balance 2025 (USD 000) | C31: 170274
A32: Lease liabilities, closing balance 2025 (USD 000) | C32: 223153
A33: Shareholder loan at 31 March 2026 (USD 000) | C33: 500000
A34: Third-party borrowings at 31 March 2026 (USD 000) | C34: 402763
A35: Lease liabilities at 31 March 2026 (USD 000) | C35: 212449
A37: Tanker fleet — vessel counts by class | B37: Handysize | C37: Medium range | D37: Long range 1 | E37: Long range 2 | F37: Very large crude carrier
A38: Vessels owned at 31 December 2025 | B38: 2 | C38: 16 | D38: 9 | E38: 17 | F38: 9
A39: Less vessels sold between the year end and the valuation date | B39: 0 | C39: 0 | D39: 0 | E39: 0 | F39: 1
A41: Tanker rates — the published blended rate by class and quarter (USD per day). It is a BLEND across the whole class, charters out included; the spot rate is solved out of it on the Segments sheet, never read off it | B41: First quarter | C41: Second quarter | D41: Third quarter | E41: Fourth quarter
A42: Long range 1 — 2024 | B42: 51645 | C42: 49424 | D42: 31911 | E42: 27640
A43: Long range 2 — 2024 | B43: 60038 | C43: 63734 | D43: 36237 | E43: 32034
A44: Very large crude carrier — 2024 | B44: 54580 | C44: 46097 | D44: 39681 | E44: 33167
A45: Medium range — 2025 | B45: 23459 | C45: 25161 | D45: 23391 | E45: 24547 | H45: The handysize class is not broken out in the disclosure, so the medium-range rate stands in for it — SCALED by the disclosed relative move, because the company said handysize rates fell 21% while medium range rose 29%, and an unadjusted substitution therefore had the sign wrong. The gap is still flagged. The 2024 quarterly rates for the medium-range class are not disclosed either, so its 2025 average stands in on both sides of the mid-cycle average.
A46: Long range 1 — 2025 | B46: 21546 | C46: 24225 | D46: 24452 | E46: 26574
A47: Long range 2 — 2025 | B47: 31033 | C47: 35533 | D47: 34410 | E47: 41973
A48: Very large crude carrier — 2025 | B48: 39245 | C48: 44350 | D48: 40996 | E48: 85273
A50: Tanker rates — the published blended rate by class, the two disclosed quarters of 2026 (USD per day) | B50: First quarter 2026 | C50: Second quarter 2026
A51: Medium range | B51: 30000 | C51: 44000
A52: Long range 1 | B52: 36000 | C52: 55000
A53: Long range 2 | B53: 58000 | C53: 95000
A54: Very large crude carrier | B54: 145000 | C54: 260000
A56: The smallest tankers, which the rate disclosure does not break out
A57: Handysize rate as a proportion of the medium-range rate — the company disclosed Handysize DOWN 21% against medium range UP 29%, so the two smallest classes moved in OPPOSITE directions and the medium-range rate cannot stand in for the smallest unadjusted. It scales the medium-range rate in every window and on both sides of the mid-cycle average | C57: 0.79
A59: Tanker charters out — the twelve fixtures as disclosed, each at its own rate for exactly the days its own contract runs | B59: Rate (USD per day) | C59: Contract begins | D59: Contract ends
A60: Navig8 Macallister — long range 1, fixed for 20 months | B60: 19750 | C60: 45866 | D60: 46474
A61: Navig8 Martinez — long range 1, fixed for 32 months | B61: 19750 | C61: 45866 | D61: 46840
A62: Navig8 Prosperity — long range 2, fixed for 36 months | B62: 30561 | C62: 45050 | D62: 46146
A63: Navig8 Promise — long range 2, fixed for 12 months | B63: 32125 | C63: 45840 | D63: 46205
A64: Navig8 Pride — long range 2, fixed for 12 months | B64: 32125 | C64: 45847 | D64: 46212
A65: Navig8 Prestige — long range 2, fixed for 12 months | B65: 36850 | C65: 45938 | D65: 46303
A66: Navig8 Providence — long range 2, fixed for 12 months | B66: 42000 | C66: 46053 | D66: 46418
A67: Navig8 Passion — long range 2, fixed for 12 months | B67: 42000 | C67: 46059 | D67: 46424
A68: Zakum — very large crude carrier, fixed for 22 months | B68: 50633 | C68: 45963 | D68: 46632
A69: Hili — very large crude carrier, fixed for 22 months | B69: 50633 | C69: 45977 | D69: 46646
A70: Arzanah — very large crude carrier, fixed for 12 months | B70: 70000 | C70: 46054 | D70: 46419
A71: Habshan — very large crude carrier, fixed for 12 months | B71: 72500 | C71: 46074 | D71: 46439
A73: Rate windows and forecast years — the calendar the fleet build runs on (dates) | B73: Q1 2025 | C73: Q2 2025 | D73: Q3 2025 | E73: Q4 2025 | F73: Q1 2026 | G73: Q2 2026
A74: Rate window begins | B74: 45658 | C74: 45748 | D74: 45839 | E74: 45931 | F74: 46023 | G74: 46113
A75: Rate window ends — each window closes where the next one opens; the last is the disclosed quarter end | B75: =C74 | C75: =D74 | D75: =E74 | E75: =F74 | F75: =G74 | G75: 46204
A77: Forecast years (dates) | B77: FY2026 | C77: FY2027 | D77: FY2028 | E77: FY2029 | F77: FY2030
A78: Forecast year begins | B78: =F74 | C78: 46388 | D78: 46753 | E78: 47119 | F78: 47484
A79: Forecast year ends — each year closes where the next one opens | B79: =C78 | C79: =D78 | D79: =E78 | E79: =F78 | F79: 47849
A81: THE FLEET PURCHASE ANNOUNCED 7 AUGUST 2026 — eleven vessels for about USD 1.3 billion, announced on the anchor date of this study and therefore already inside the market price the valuation is compared against | B81: Vessels | C81: Delivery date
A82: Purchase price — added BOTH to net debt, because it is committed and funded, and to the opening asset base, so it depreciates and shields tax (USD 000) | C82: 1300000
A83: Very large crude carriers bought secondhand — they join the spot fleet on delivery and earn at the implied spot rate from that date | B83: 6 | C83: 46266
A84: Gas carriers acquired in total — they add contracted vessel-years to the gas fleet | B84: 5
A85: Of which bought secondhand, delivering in the third quarter | B85: 3 | C85: 46266
A86: Of which newbuildings resold from the yard, delivering in the fourth quarter | B86: =B84-B85 | C86: 46341
A87: Vessels acquired in total | B87: =B83+B84
A89: Tanker fleet — rate path and running cost
A90: Weight on the 2025 implied spot rate in setting the second half of 2026 | C90: 0.5
A91: All-in running cost per vessel per day (USD) | C91: =Segments!B142 | H91: GREEN, NOT BLUE. The running cost per vessel-day is not an assumption: it is solved on the Segments sheet so that the same construction reproduces the tanker earnings the company actually reported for 2025. The same is true of the gas-carrier day rate, the three days ratios and the opening net working capital immediately below.
A92: Running-cost escalation (services and wages) | C92: 0.02
A93: Gross-up from time-charter-equivalent revenue to reported revenue | C93: 1.6
A95: Gas carriers
A96: Consolidated gas vessels in service through 2025 (vessel-years) | C96: 8
A97: Gas carriers — implied revenue per vessel-day (USD) | C97: =Segments!B153
A98: Gas carriers — earnings margin | C98: 0.7
A99: Share of joint-venture profit carried in the disclosed 2025 Gas Carriers earnings (USD 000) | C99: 21313
A100: Share of joint-venture profit carried in the disclosed 2025 Services earnings (USD 000) | C100: 16079
A102: Gas-carrier contract table — the vessel-years the fleet is contracted for, before and after the August 2026 purchase | B102: FY2026 | C102: FY2027 | D102: FY2028 | E102: FY2029 | F102: FY2030
A103: Contracted vessel-years before that purchase — the disclosed contract table | B103: 10.739726 | C103: 13 | D103: 21.25 | E103: 25 | F103: 25
A104: Vessel-years the gas carriers bought in August 2026 add — each tranche from its own delivery date | B104: =(Assumptions!$B$85*MAX(Assumptions!$B$79-MAX(Assumptions!$B$78,Assumptions!$C$85),0)+Assumptions!$B$86*MAX(Assumptions!$B$79-MAX(Assumptions!$B$78,Assumptions!$C$86),0))/(Assumptions!$B$79-Assumptions!$B$78) | C104: =(Assumptions!$B$85*MAX(Assumptions!$C$79-MAX(Assumptions!$C$78,Assumptions!$C$85),0)+Assumptions!$B$86*MAX(Assumptions!$C$79-MAX(Assumptions!$C$78,Assumptions!$C$86),0))/(Assumptions!$C$79-Assumptions!$C$78) | D104: =(Assumptions!$B$85*MAX(Assumptions!$D$79-MAX(Assumptions!$D$78,Assumptions!$C$85),0)+Assumptions!$B$86*MAX(Assumptions!$D$79-MAX(Assumptions!$D$78,Assumptions!$C$86),0))/(Assumptions!$D$79-Assumptions!$D$78) | E104: =(Assumptions!$B$85*MAX(Assumptions!$E$79-MAX(Assumptions!$E$78,Assumptions!$C$85),0)+Assumptions!$B$86*MAX(Assumptions!$E$79-MAX(Assumptions!$E$78,Assumptions!$C$86),0))/(Assumptions!$E$79-Assumptions!$E$78) | F104: =(Assumptions!$B$85*MAX(Assumptions!$F$79-MAX(Assumptions!$F$78,Assumptions!$C$85),0)+Assumptions!$B$86*MAX(Assumptions!$F$79-MAX(Assumptions!$F$78,Assumptions!$C$86),0))/(Assumptions!$F$79-Assumptions!$F$78)
A105: Gas carriers — contracted vessel-years | B105: =B103+B104 | C105: =C103+C104 | D105: =D103+D104 | E105: =E103+E104 | F105: =F103+F104
A107: The remaining five units — revenue and margin drivers | B107: FY2026 | C107: FY2027 | D107: FY2028 | E107: FY2029 | F107: FY2030
A108: Offshore Contracting — revenue (USD 000) | B108: 1248192 | C108: 1298120 | D108: 1350044 | E108: 1404046 | F108: 1460208
A109: Offshore Contracting — earnings margin | B109: 0.385 | C109: 0.415 | D109: 0.43 | E109: 0.43 | F109: 0.43
A110: Offshore Services — revenue (USD 000) | B110: 662856 | C110: 696000 | D110: 730800 | E110: 767340 | F110: 805707
A111: Offshore Services — earnings margin | B111: 0.287 | C111: 0.29 | D111: 0.29 | E111: 0.29 | F111: 0.29
A112: Offshore Projects — revenue (USD 000) | B112: 125000 | C112: 200000 | D112: 250000 | E112: 275000 | F112: 300000
A113: Offshore Projects — earnings margin | B113: -0.02 | C113: 0.06 | D113: 0.065 | E113: 0.065 | F113: 0.065
A114: Dry-Bulk and Containers — revenue (USD 000) | B114: 197164 | C114: 201107 | D114: 205129 | E114: 209232 | F114: 213417
A115: Dry-Bulk and Containers — earnings margin | B115: 0.184 | C115: 0.184 | D115: 0.184 | E115: 0.184 | F115: 0.184
...

Sheet SOTP Bridge
A1: Enterprise value to equity — the bridge, and the sum-of-the-parts cross-check
A2: USD thousand unless stated. Per-share figures in dirhams at the fixed parity.
A4: Step | C4: USD 000 | D4: AED per share
A5: Present value of the five forecast years | C5: =DCF!$C$45 | D5: =C5/Assumptions!$C$6/1000*Assumptions!$C$7
A6: Present value of the terminal value | C6: =DCF!$C$46 | D6: =C6/Assumptions!$C$6/1000*Assumptions!$C$7
A7: Enterprise value of operations | C7: =C5+C6 | D7: =C7/Assumptions!$C$6/1000*Assumptions!$C$7
A8: Terminal value as a share of enterprise value | C8: =C6/C7
A9: Plus joint ventures and associates at carrying value | C9: =Assumptions!$C$157 | D9: =C9/Assumptions!$C$6/1000*Assumptions!$C$7
A10: Enterprise value | C10: =C7+C9 | D10: =C10/Assumptions!$C$6/1000*Assumptions!$C$7
A11: Less net debt at 31 March 2026 | C11: =-Assumptions!$C$150 | D11: =C11/Assumptions!$C$6/1000*Assumptions!$C$7
A12: Less deferred consideration on acquisitions | C12: =-Assumptions!$C$151 | D12: =C12/Assumptions!$C$6/1000*Assumptions!$C$7
A13: Less the eleven vessels bought on 7 August 2026, at the announced price | C13: =-Assumptions!$C$82 | D13: =C13/Assumptions!$C$6/1000*Assumptions!$C$7
A14: Less perpetual capital securities at carrying value | C14: =-Assumptions!$C$152 | D14: =C14/Assumptions!$C$6/1000*Assumptions!$C$7
A15: Equity value before the minorities | C15: =C10+C11+C12+C13+C14 | D15: =C15/Assumptions!$C$6/1000*Assumptions!$C$7
A16: Less non-controlling interests — the contracted slice at its contracted price, the rest at the greater of book and value | C16: =DCF!$C$59 | D16: =C16/Assumptions!$C$6/1000*Assumptions!$C$7
A17: Equity attributable to ordinary shareholders | C17: =C15+C16 | D17: =C17/Assumptions!$C$6/1000*Assumptions!$C$7
A18: Fair value per share (USD) | C18: =C17/Assumptions!$C$6/1000
A19: Fair value per share (AED) | C19: =C18*Assumptions!$C$7
A21: THE SUM-OF-THE-PARTS CROSS-CHECK — EACH LEG ON ITS OWN MULTIPLE | C21: 2026E EBITDA | D21: Multiple | E21: Enterprise value | F21: Basis
A22: Integrated Logistics | B22: =Segments!B204 | C22: =C28 | D22: =B22*C22 | E22: a contracted-fleet multiple, because this leg earns under long-term contracts
A23: Shipping | B23: =Segments!B205 | C23: =C31 | D23: =B23*C23 | E23: a blend of the contracted and spot multiples, weighted by the company's own disclosed share of earnings exposed to spot rates
A24: Services | B24: =Segments!B206 | C24: =C28 | D24: =B24*C24 | E24: a contracted-fleet multiple, because this leg earns under long-term contracts
A25: Enterprise value of the operating legs | D25: =SUM(D22:D24)
A27: THE SHIPPING MULTIPLE, BUILT — NOT PASTED
A28: Contracted-fleet multiple (long-term contracted gas shipping peer) | C28: ='Peer & Sector'!$C$10
A29: Spot-tanker multiple (average of the two spot-tanker peers) | C29: ='Peer & Sector'!$C$11
A30: Share of 2026 earnings exposed to spot rates, as disclosed | C30: =Assumptions!$C$167
A31: Shipping multiple — the two weighted by that share | C31: =(1-C30)*C28+C30*C29
A33: THE SUM-OF-THE-PARTS BRIDGE TO EQUITY
A34: Enterprise value of the operating legs | C34: =D25
A35: Plus joint ventures and associates at carrying value | C35: =Assumptions!$C$157
A36: Enterprise value | C36: =C34+C35
A37: Less net debt at 31 March 2026 | C37: =-Assumptions!$C$150
A38: Less deferred consideration on acquisitions | C38: =-Assumptions!$C$151
A39: Less the eleven vessels bought on 7 August 2026, at the announced price | C39: =-Assumptions!$C$82
A40: Less perpetual capital securities at carrying value | C40: =-Assumptions!$C$152
A41: Less non-controlling interests at carrying value | C41: =-Assumptions!$C$154
A42: Equity attributable to ordinary shareholders | C42: =C36+C37+C38+C39+C40+C41
A43: Sum-of-the-parts fair value per share (AED) | C43: =C42/Assumptions!$C$6/1000*Assumptions!$C$7
A45: The sum-of-the-parts is a cross-check on the discounted cash flow, not a fifth lens: it prices each business unit's 2026 earnings on the multiple the market is paying for that kind of earnings stream, and the Shipping leg is the only one that carries spot exposure, which is why its multiple is a weighted blend rather than a single peer figure.

Sheet Segments
A1: Segments — the disclosed record and the unit build
A2: USD thousand unless stated. The tanker fleet is built vessel by vessel; every forecast figure below is a formula.
A4: Segment revenue — as disclosed (USD 000) | B4: FY2023 | C4: FY2024 | D4: FY2025
A5: Offshore Contracting | B5: 974525 | C5: 1108200 | D5: 1368875
A6: Offshore Services | B6: 500751 | C6: 552790 | D6: 628915
A7: Offshore Projects | B7: 157146 | C7: 619930 | D7: 531333
A8: Tankers | B8: 407370 | C8: 516530 | D8: 1719714
A9: Gas Carriers | B9: 173550 | C9: 152650 | D9: 179794
A10: Dry-Bulk and Containers | B10: 257900 | C10: 286820 | D10: 225048
A11: Services | B11: 283910 | C11: 312410 | D11: 362433
A12: Total revenue | B12: =SUM(B5:B11) | C12: =SUM(C5:C11) | D12: =SUM(D5:D11)
A14: Segment EBITDA — as disclosed (USD 000) | B14: FY2023 | C14: FY2024 | D14: FY2025
A15: Offshore Contracting | B15: 424419 | C15: 497703 | D15: 623065
A16: Offshore Services | B16: 92741 | C16: 134880 | D16: 178369
A17: Offshore Projects | B17: 10439 | C17: 54240 | D17: 28024
A18: Tankers | B18: 159260 | C18: 239700 | D18: 451220
A19: Gas Carriers | B19: 101022 | C19: 87308 | D19: 129547
A20: Dry-Bulk and Containers | B20: 60280 | C20: 69440 | D20: 37862
A21: Services | B21: 44488 | C21: 56000 | D21: 60273
A22: Total segment EBITDA | B22: =SUM(B15:B21) | C22: =SUM(C15:C21) | D22: =SUM(D15:D21)
A23: Segment EBITDA margin | B23: =B22/B12 | C23: =C22/C12 | D23: =D22/D12
A25: TANKERS — THE UNIT BUILD, VESSEL BY VESSEL | B25: Handysize | C25: Medium range | D25: Long range 1 | E25: Long range 2 | F25: Very large crude carrier
A26: Vessels owned at 31 December 2025 | B26: =Assumptions!$B$38 | C26: =Assumptions!$C$38 | D26: =Assumptions!$D$38 | E26: =Assumptions!$E$38 | F26: =Assumptions!$F$38
A27: Less vessels sold between the year end and the valuation date | B27: =Assumptions!$B$39 | C27: =Assumptions!$C$39 | D27: =Assumptions!$D$39 | E27: =Assumptions!$E$39 | F27: =Assumptions!$F$39
A28: Vessels owned at the 31 March 2026 valuation date | B28: =B26-B27 | C28: =C26-C27 | D28: =D26-D27 | E28: =E26-E27 | F28: =F26-F27
A29: Vessels bought in the purchase announced 7 August 2026 | B29: =0 | C29: =0 | D29: =0 | E29: =0 | F29: =Assumptions!$B$83
A30: Their delivery date — they earn nothing before it and at the implied spot rate after it | B30: =0 | C30: =0 | D30: =0 | E30: =0 | F30: =Assumptions!$C$83
A32: THE PUBLISHED BLEND, CONVERTED TO A SPOT RATE — WINDOW BY WINDOW. The company publishes ONE rate per class and states it is a blend across the whole class, charters out included, so the spot rate is SOLVED out of it here | B32: Q1 2025 | C32: Q2 2025 | D32: Q3 2025 | E32: Q4 2025 | F32: Q1 2026 | G32: Q2 2026 | H32: Mid-cycle anchor
A33: Window begins | B33: =Assumptions!$B$74 | C33: =Assumptions!$C$74 | D33: =Assumptions!$D$74 | E33: =Assumptions!$E$74 | F33: =Assumptions!$F$74 | G33: =Assumptions!$G$74 | H33: =B33
A34: Window ends | B34: =Assumptions!$B$75 | C34: =Assumptions!$C$75 | D34: =Assumptions!$D$75 | E34: =Assumptions!$E$75 | F34: =Assumptions!$F$75 | G34: =Assumptions!$G$75 | H34: =B34
A35: Days in the window | B35: =B34-B33 | C35: =C34-C33 | D35: =D34-D33 | E35: =E34-E33 | F35: =F34-F33 | G35: =G34-G33 | H35: =H34-H33
A37: Published blended rate by class (USD per day)
A38: Handysize | B38: =AVERAGE(Assumptions!$B$45:$E$45)*Assumptions!$C$57 | C38: =AVERAGE(Assumptions!$B$45:$E$45)*Assumptions!$C$57 | D38: =AVERAGE(Assumptions!$B$45:$E$45)*Assumptions!$C$57 | E38: =AVERAGE(Assumptions!$B$45:$E$45)*Assumptions!$C$57 | F38: =Assumptions!$B$51*Assumptions!$C$57 | G38: =Assumptions!$C$51*Assumptions!$C$57 | H38: =AVERAGE(Assumptions!$B$45:$E$45)*Assumptions!$C$57
A39: Medium range | B39: =Assumptions!$B$45 | C39: =Assumptions!$C$45 | D39: =Assumptions!$D$45 | E39: =Assumptions!$E$45 | F39: =Assumptions!$B$51 | G39: =Assumptions!$C$51 | H39: =AVERAGE(Assumptions!$B$45:$E$45)
A40: Long range 1 | B40: =Assumptions!$B$46 | C40: =Assumptions!$C$46 | D40: =Assumptions!$D$46 | E40: =Assumptions!$E$46 | F40: =Assumptions!$B$52 | G40: =Assumptions!$C$52 | H40: =(AVERAGE(Assumptions!$B$42:$E$42)+AVERAGE(Assumptions!$B$46:$E$46))/2
A41: Long range 2 | B41: =Assumptions!$B$47 | C41: =Assumptions!$C$47 | D41: =Assumptions!$D$47 | E41: =Assumptions!$E$47 | F41: =Assumptions!$B$53 | G41: =Assumptions!$C$53 | H41: =(AVERAGE(Assumptions!$B$43:$E$43)+AVERAGE(Assumptions!$B$47:$E$47))/2
A42: Very large crude carrier | B42: =Assumptions!$B$48 | C42: =Assumptions!$C$48 | D42: =Assumptions!$D$48 | E42: =Assumptions!$E$48 | F42: =Assumptions!$B$54 | G42: =Assumptions!$C$54 | H42: =(AVERAGE(Assumptions!$B$44:$E$44)+AVERAGE(Assumptions!$B$48:$E$48))/2
A44: Class vessel-days in the window — vessels owned x days
A45: Handysize | B45: =$B$26*B$35 | C45: =$B$26*C$35 | D45: =$B$26*D$35 | E45: =$B$26*E$35 | F45: =$B$28*F$35 | G45: =$B$28*G$35 | H45: =$B$26*H$35
A46: Medium range | B46: =$C$26*B$35 | C46: =$C$26*C$35 | D46: =$C$26*D$35 | E46: =$C$26*E$35 | F46: =$C$28*F$35 | G46: =$C$28*G$35 | H46: =$C$26*H$35
A47: Long range 1 | B47: =$D$26*B$35 | C47: =$D$26*C$35 | D47: =$D$26*D$35 | E47: =$D$26*E$35 | F47: =$D$28*F$35 | G47: =$D$28*G$35 | H47: =$D$26*H$35
A48: Long range 2 | B48: =$E$26*B$35 | C48: =$E$26*C$35 | D48: =$E$26*D$35 | E48: =$E$26*E$35 | F48: =$E$28*F$35 | G48: =$E$28*G$35 | H48: =$E$26*H$35
A49: Very large crude carrier | B49: =$F$26*B$35 | C49: =$F$26*C$35 | D49: =$F$26*D$35 | E49: =$F$26*E$35 | F49: =$F$28*F$35 | G49: =$F$28*G$35 | H49: =$F$26*H$35
A51: Charter vessel-days in the window — each fixture for exactly the days its own contract runs
A52: Handysize | B52: =0 | C52: =0 | D52: =0 | E52: =0 | F52: =0 | G52: =0 | H52: =0
A53: Medium range | B53: =0 | C53: =0 | D53: =0 | E53: =0 | F53: =0 | G53: =0 | H53: =0
A54: Long range 1 | B54: =MAX(MIN(Assumptions!$D$60,B$34)-MAX(Assumptions!$C$60,B$33),0)+MAX(MIN(Assumptions!$D$61,B$34)-MAX(Assumptions!$C$61,B$33),0) | C54: =MAX(MIN(Assumptions!$D$60,C$34)-MAX(Assumptions!$C$60,C$33),0)+MAX(MIN(Assumptions!$D$61,C$34)-MAX(Assumptions!$C$61,C$33),0) | D54: =MAX(MIN(Assumptions!$D$60,D$34)-MAX(Assumptions!$C$60,D$33),0)+MAX(MIN(Assumptions!$D$61,D$34)-MAX(Assumptions!$C$61,D$33),0) | E54: =MAX(MIN(Assumptions!$D$60,E$34)-MAX(Assumptions!$C$60,E$33),0)+MAX(MIN(Assumptions!$D$61,E$34)-MAX(Assumptions!$C$61,E$33),0) | F54: =MAX(MIN(Assumptions!$D$60,F$34)-MAX(Assumptions!$C$60,F$33),0)+MAX(MIN(Assumptions!$D$61,F$34)-MAX(Assumptions!$C$61,F$33),0) | G54: =MAX(MIN(Assumptions!$D$60,G$34)-MAX(Assumptions!$C$60,G$33),0)+MAX(MIN(Assumptions!$D$61,G$34)-MAX(Assumptions!$C$61,G$33),0) | H54: =MAX(MIN(Assumptions!$D$60,H$34)-MAX(Assumptions!$C$60,H$33),0)+MAX(MIN(Assumptions!$D$61,H$34)-MAX(Assumptions!$C$61,H$33),0)
A55: Long range 2 | B55: =MAX(MIN(Assumptions!$D$62,B$34)-MAX(Assumptions!$C$62,B$33),0)+MAX(MIN(Assumptions!$D$63,B$34)-MAX(Assumptions!$C$63,B$33),0)+MAX(MIN(Assumptions!$D$64,B$34)-MAX(Assumptions!$C$64,B$33),0)+MAX(MIN(Assumptions!$D$65,B$34)-MAX(Assumptions!$C$65,B$33),0)+MAX(MIN(Assumptions!$D$66,B$34)-MAX(Assumptions!$C$66,B$33),0)+MAX(MIN(Assumptions!$D$67,B$34)-MAX(Assumptions!$C$67,B$33),0) | C55: =MAX(MIN(Assumptions!$D$62,C$34)-MAX(Assumptions!$C$62,C$33),0)+MAX(MIN(Assumptions!$D$63,C$34)-MAX(Assumptions!$C$63,C$33),0)+MAX(MIN(Assumptions!$D$64,C$34)-MAX(Assumptions!$C$64,C$33),0)+MAX(MIN(Assumptions!$D$65,C$34)-MAX(Assumptions!$C$65,C$33),0)+MAX(MIN(Assumptions!$D$66,C$34)-MAX(Assumptions!$C$66,C$33),0)+MAX(MIN(Assumptions!$D$67,C$34)-MAX(Assumptions!$C$67,C$33),0) | D55: =MAX(MIN(Assumptions!$D$62,D$34)-MAX(Assumptions!$C$62,D$33),0)+MAX(MIN(Assumptions!$D$63,D$34)-MAX(Assumptions!$C$63,D$33),0)+MAX(MIN(Assumptions!$D$64,D$34)-MAX(Assumptions!$C$64,D$33),0)+MAX(MIN(Assumptions!$D$65,D$34)-MAX(Assumptions!$C$65,D$33),0)+MAX(MIN(Assumptions!$D$66,D$34)-MAX(Assumptions!$C$66,D$33),0)+MAX(MIN(Assumptions!$D$67,D$34)-MAX(Assumptions!$C$67,D$33),0) | E55: =MAX(MIN(Assumptions!$D$62,E$34)-MAX(Assumptions!$C$62,E$33),0)+MAX(MIN(Assumptions!$D$63,E$34)-MAX(Assumptions!$C$63,E$33),0)+MAX(MIN(Assumptions!$D$64,E$34)-MAX(Assumptions!$C$64,E$33),0)+MAX(MIN(Assumptions!$D$65,E$34)-MAX(Assumptions!$C$65,E$33),0)+MAX(MIN(Assumptions!$D$66,E$34)-MAX(Assumptions!$C$66,E$33),0)+MAX(MIN(Assumptions!$D$67,E$34)-MAX(Assumptions!$C$67,E$33),0) | F55: =MAX(MIN(Assumptions!$D$62,F$34)-MAX(Assumptions!$C$62,F$33),0)+MAX(MIN(Assumptions!$D$63,F$34)-MAX(Assumptions!$C$63,F$33),0)+MAX(MIN(Assumptions!$D$64,F$34)-MAX(Assumptions!$C$64,F$33),0)+MAX(MIN(Assumptions!$D$65,F$34)-MAX(Assumptions!$C$65,F$33),0)+MAX(MIN(Assumptions!$D$66,F$34)-MAX(Assumptions!$C$66,F$33),0)+MAX(MIN(Assumptions!$D$67,F$34)-MAX(Assumptions!$C$67,F$33),0) | G55: =MAX(MIN(Assumptions!$D$62,G$34)-MAX(Assumptions!$C$62,G$33),0)+MAX(MIN(Assumptions!$D$63,G$34)-MAX(Assumptions!$C$63,G$33),0)+MAX(MIN(Assumptions!$D$64,G$34)-MAX(Assumptions!$C$64,G$33),0)+MAX(MIN(Assumptions!$D$65,G$34)-MAX(Assumptions!$C$65,G$33),0)+MAX(MIN(Assumptions!$D$66,G$34)-MAX(Assumptions!$C$66,G$33),0)+MAX(MIN(Assumptions!$D$67,G$34)-MAX(Assumptions!$C$67,G$33),0) | H55: =MAX(MIN(Assumptions!$D$62,H$34)-MAX(Assumptions!$C$62,H$33),0)+MAX(MIN(Assumptions!$D$63,H$34)-MAX(Assumptions!$C$63,H$33),0)+MAX(MIN(Assumptions!$D$64,H$34)-MAX(Assumptions!$C$64,H$33),0)+MAX(MIN(Assumptions!$D$65,H$34)-MAX(Assumptions!$C$65,H$33),0)+MAX(MIN(Assumptions!$D$66,H$34)-MAX(Assumptions!$C$66,H$33),0)+MAX(MIN(Assumptions!$D$67,H$34)-MAX(Assumptions!$C$67,H$33),0)
A56: Very large crude carrier | B56: =MAX(MIN(Assumptions!$D$68,B$34)-MAX(Assumptions!$C$68,B$33),0)+MAX(MIN(Assumptions!$D$69,B$34)-MAX(Assumptions!$C$69,B$33),0)+MAX(MIN(Assumptions!$D$70,B$34)-MAX(Assumptions!$C$70,B$33),0)+MAX(MIN(Assumptions!$D$71,B$34)-MAX(Assumptions!$C$71,B$33),0) | C56: =MAX(MIN(Assumptions!$D$68,C$34)-MAX(Assumptions!$C$68,C$33),0)+MAX(MIN(Assumptions!$D$69,C$34)-MAX(Assumptions!$C$69,C$33),0)+MAX(MIN(Assumptions!$D$70,C$34)-MAX(Assumptions!$C$70,C$33),0)+MAX(MIN(Assumptions!$D$71,C$34)-MAX(Assumptions!$C$71,C$33),0) | D56: =MAX(MIN(Assumptions!$D$68,D$34)-MAX(Assumptions!$C$68,D$33),0)+MAX(MIN(Assumptions!$D$69,D$34)-MAX(Assumptions!$C$69,D$33),0)+MAX(MIN(Assumptions!$D$70,D$34)-MAX(Assumptions!$C$70,D$33),0)+MAX(MIN(Assumptions!$D$71,D$34)-MAX(Assumptions!$C$71,D$33),0) | E56: =MAX(MIN(Assumptions!$D$68,E$34)-MAX(Assumptions!$C$68,E$33),0)+MAX(MIN(Assumptions!$D$69,E$34)-MAX(Assumptions!$C$69,E$33),0)+MAX(MIN(Assumptions!$D$70,E$34)-MAX(Assumptions!$C$70,E$33),0)+MAX(MIN(Assumptions!$D$71,E$34)-MAX(Assumptions!$C$71,E$33),0) | F56: =MAX(MIN(Assumptions!$D$68,F$34)-MAX(Assumptions!$C$68,F$33),0)+MAX(MIN(Assumptions!$D$69,F$34)-MAX(Assumptions!$C$69,F$33),0)+MAX(MIN(Assumptions!$D$70,F$34)-MAX(Assumptions!$C$70,F$33),0)+MAX(MIN(Assumptions!$D$71,F$34)-MAX(Assumptions!$C$71,F$33),0) | G56: =MAX(MIN(Assumptions!$D$68,G$34)-MAX(Assumptions!$C$68,G$33),0)+MAX(MIN(Assumptions!$D$69,G$34)-MAX(Assumptions!$C$69,G$33),0)+MAX(MIN(Assumptions!$D$70,G$34)-MAX(Assumptions!$C$70,G$33),0)+MAX(MIN(Assumptions!$D$71,G$34)-MAX(Assumptions!$C$71,G$33),0) | H56: =MAX(MIN(Assumptions!$D$68,H$34)-MAX(Assumptions!$C$68,H$33),0)+MAX(MIN(Assumptions!$D$69,H$34)-MAX(Assumptions!$C$69,H$33),0)+MAX(MIN(Assumptions!$D$70,H$34)-MAX(Assumptions!$C$70,H$33),0)+MAX(MIN(Assumptions!$D$71,H$34)-MAX(Assumptions!$C$71,H$33),0)
A58: Charter revenue in the window (USD) — each fixture at its own contracted rate
A59: Handysize | B59: =0 | C59: =0 | D59: =0 | E59: =0 | F59: =0 | G59: =0 | H59: =0
A60: Medium range | B60: =0 | C60: =0 | D60: =0 | E60: =0 | F60: =0 | G60: =0 | H60: =0
A61: Long range 1 | B61: =Assumptions!$B$60*MAX(MIN(Assumptions!$D$60,B$34)-MAX(Assumptions!$C$60,B$33),0)+Assumptions!$B$61*MAX(MIN(Assumptions!$D$61,B$34)-MAX(Assumptions!$C$61,B$33),0) | C61: =Assumptions!$B$60*MAX(MIN(Assumptions!$D$60,C$34)-MAX(Assumptions!$C$60,C$33),0)+Assumptions!$B$61*MAX(MIN(Assumptions!$D$61,C$34)-MAX(Assumptions!$C$61,C$33),0) | D61: =Assumptions!$B$60*MAX(MIN(Assumptions!$D$60,D$34)-MAX(Assumptions!$C$60,D$33),0)+Assumptions!$B$61*MAX(MIN(Assumptions!$D$61,D$34)-MAX(Assumptions!$C$61,D$33),0) | E61: =Assumptions!$B$60*MAX(MIN(Assumptions!$D$60,E$34)-MAX(Assumptions!$C$60,E$33),0)+Assumptions!$B$61*MAX(MIN(Assumptions!$D$61,E$34)-MAX(Assumptions!$C$61,E$33),0) | F61: =Assumptions!$B$60*MAX(MIN(Assumptions!$D$60,F$34)-MAX(Assumptions!$C$60,F$33),0)+Assumptions!$B$61*MAX(MIN(Assumptions!$D$61,F$34)-MAX(Assumptions!$C$61,F$33),0) | G61: =Assumptions!$B$60*MAX(MIN(Assumptions!$D$60,G$34)-MAX(Assumptions!$C$60,G$33),0)+Assumptions!$B$61*MAX(MIN(Assumptions!$D$61,G$34)-MAX(Assumptions!$C$61,G$33),0) | H61: =Assumptions!$B$60*MAX(MIN(Assumptions!$D$60,H$34)-MAX(Assumptions!$C$60,H$33),0)+Assumptions!$B$61*MAX(MIN(Assumptions!$D$61,H$34)-MAX(Assumptions!$C$61,H$33),0)
A62: Long range 2 | B62: =Assumptions!$B$62*MAX(MIN(Assumptions!$D$62,B$34)-MAX(Assumptions!$C$62,B$33),0)+Assumptions!$B$63*MAX(MIN(Assumptions!$D$63,B$34)-MAX(Assumptions!$C$63,B$33),0)+Assumptions!$B$64*MAX(MIN(Assumptions!$D$64,B$34)-MAX(Assumptions!$C$64,B$33),0)+Assumptions!$B$65*MAX(MIN(Assumptions!$D$65,B$34)-MAX(Assumptions!$C$65,B$33),0)+Assumptions!$B$66*MAX(MIN(Assumptions!$D$66,B$34)-MAX(Assumptions!$C$66,B$33),0)+Assumptions!$B$67*MAX(MIN(Assumptions!$D$67,B$34)-MAX(Assumptions!$C$67,B$33),0) | C62: =Assumptions!$B$62*MAX(MIN(Assumptions!$D$62,C$34)-MAX(Assumptions!$C$62,C$33),0)+Assumptions!$B$63*MAX(MIN(Assumptions!$D$63,C$34)-MAX(Assumptions!$C$63,C$33),0)+Assumptions!$B$64*MAX(MIN(Assumptions!$D$64,C$34)-MAX(Assumptions!$C$64,C$33),0)+Assumptions!$B$65*MAX(MIN(Assumptions!$D$65,C$34)-MAX(Assumptions!$C$65,C$33),0)+Assumptions!$B$66*MAX(MIN(Assumptions!$D$66,C$34)-MAX(Assumptions!$C$66,C$33),0)+Assumptions!$B$67*MAX(MIN(Assumptions!$D$67,C$34)-MAX(Assumptions!$C$67,C$33),0) | D62: =Assumptions!$B$62*MAX(MIN(Assumptions!$D$62,D$34)-MAX(Assumptions!$C$62,D$33),0)+Assumptions!$B$63*MAX(MIN(Assumptions!$D$63,D$34)-MAX(Assumptions!$C$63,D$33),0)+Assumptions!$B$64*MAX(MIN(Assumptions!$D$64,D$34)-MAX(Assumptions!$C$64,D$33),0)+Assumptions!$B$65*MAX(MIN(Assumptions!$D$65,D$34)-MAX(Assumptions!$C$65,D$33),0)+Assumptions!$B$66*MAX(MIN(Assumptions!$D$66,D$34)-MAX(Assumptions!$C$66,D$33),0)+Assumptions!$B$67*MAX(MIN(Assumptions!$D$67,D$34)-MAX(Assumptions!$C$67,D$33),0) | E62: =Assumptions!$B$62*MAX(MIN(Assumptions!$D$62,E$34)-MAX(Assumptions!$C$62,E$33),0)+Assumptions!$B$63*MAX(MIN(Assumptions!$D$63,E$34)-MAX(Assumptions!$C$63,E$33),0)+Assumptions!$B$64*MAX(MIN(Assumptions!$D$64,E$34)-MAX(Assumptions!$C$64,E$33),0)+Assumptions!$B$65*MAX(MIN(Assumptions!$D$65,E$34)-MAX(Assumptions!$C$65,E$33),0)+Assumptions!$B$66*MAX(MIN(Assumptions!$D$66,E$34)-MAX(Assumptions!$C$66,E$33),0)+Assumptions!$B$67*MAX(MIN(Assumptions!$D$67,E$34)-MAX(Assumptions!$C$67,E$33),0) | F62: =Assumptions!$B$62*MAX(MIN(Assumptions!$D$62,F$34)-MAX(Assumptions!$C$62,F$33),0)+Assumptions!$B$63*MAX(MIN(Assumptions!$D$63,F$34)-MAX(Assumptions!$C$63,F$33),0)+Assumptions!$B$64*MAX(MIN(Assumptions!$D$64,F$34)-MAX(Assumptions!$C$64,F$33),0)+Assumptions!$B$65*MAX(MIN(Assumptions!$D$65,F$34)-MAX(Assumptions!$C$65,F$33),0)+Assumptions!$B$66*MAX(MIN(Assumptions!$D$66,F$34)-MAX(Assumptions!$C$66,F$33),0)+Assumptions!$B$67*MAX(MIN(Assumptions!$D$67,F$34)-MAX(Assumptions!$C$67,F$33),0) | G62: =Assumptions!$B$62*MAX(MIN(Assumptions!$D$62,G$34)-MAX(Assumptions!$C$62,G$33),0)+Assumptions!$B$63*MAX(MIN(Assumptions!$D$63,G$34)-MAX(Assumptions!$C$63,G$33),0)+Assumptions!$B$64*MAX(MIN(Assumptions!$D$64,G$34)-MAX(Assumptions!$C$64,G$33),0)+Assumptions!$B$65*MAX(MIN(Assumptions!$D$65,G$34)-MAX(Assumptions!$C$65,G$33),0)+Assumptions!$B$66*MAX(MIN(Assumptions!$D$66,G$34)-MAX(Assumptions!$C$66,G$33),0)+Assumptions!$B$67*MAX(MIN(Assumptions!$D$67,G$34)-MAX(Assumptions!$C$67,G$33),0) | H62: =Assumptions!$B$62*MAX(MIN(Assumptions!$D$62,H$34)-MAX(Assumptions!$C$62,H$33),0)+Assumptions!$B$63*MAX(MIN(Assumptions!$D$63,H$34)-MAX(Assumptions!$C$63,H$33),0)+Assumptions!$B$64*MAX(MIN(Assumptions!$D$64,H$34)-MAX(Assumptions!$C$64,H$33),0)+Assumptions!$B$65*MAX(MIN(Assumptions!$D$65,H$34)-MAX(Assumptions!$C$65,H$33),0)+Assumptions!$B$66*MAX(MIN(Assumptions!$D$66,H$34)-MAX(Assumptions!$C$66,H$33),0)+Assumptions!$B$67*MAX(MIN(Assumptions!$D$67,H$34)-MAX(Assumptions!$C$67,H$33),0)
A63: Very large crude carrier | B63: =Assumptions!$B$68*MAX(MIN(Assumptions!$D$68,B$34)-MAX(Assumptions!$C$68,B$33),0)+Assumptions!$B$69*MAX(MIN(Assumptions!$D$69,B$34)-MAX(Assumptions!$C$69,B$33),0)+Assumptions!$B$70*MAX(MIN(Assumptions!$D$70,B$34)-MAX(Assumptions!$C$70,B$33),0)+Assumptions!$B$71*MAX(MIN(Assumptions!$D$71,B$34)-MAX(Assumptions!$C$71,B$33),0) | C63: =Assumptions!$B$68*MAX(MIN(Assumptions!$D$68,C$34)-MAX(Assumptions!$C$68,C$33),0)+Assumptions!$B$69*MAX(MIN(Assumptions!$D$69,C$34)-MAX(Assumptions!$C$69,C$33),0)+Assumptions!$B$70*MAX(MIN(Assumptions!$D$70,C$34)-MAX(Assumptions!$C$70,C$33),0)+Assumptions!$B$71*MAX(MIN(Assumptions!$D$71,C$34)-MAX(Assumptions!$C$71,C$33),0) | D63: =Assumptions!$B$68*MAX(MIN(Assumptions!$D$68,D$34)-MAX(Assumptions!$C$68,D$33),0)+Assumptions!$B$69*MAX(MIN(Assumptions!$D$69,D$34)-MAX(Assumptions!$C$69,D$33),0)+Assumptions!$B$70*MAX(MIN(Assumptions!$D$70,D$34)-MAX(Assumptions!$C$70,D$33),0)+Assumptions!$B$71*MAX(MIN(Assumptions!$D$71,D$34)-MAX(Assumptions!$C$71,D$33),0) | E63: =Assumptions!$B$68*MAX(MIN(Assumptions!$D$68,E$34)-MAX(Assumptions!$C$68,E$33),0)+Assumptions!$B$69*MAX(MIN(Assumptions!$D$69,E$34)-MAX(Assumptions!$C$69,E$33),0)+Assumptions!$B$70*MAX(MIN(Assumptions!$D$70,E$34)-MAX(Assumptions!$C$70,E$33),0)+Assumptions!$B$71*MAX(MIN(Assumptions!$D$71,E$34)-MAX(Assumptions!$C$71,E$33),0) | F63: =Assumptions!$B$68*MAX(MIN(Assumptions!$D$68,F$34)-MAX(Assumptions!$C$68,F$33),0)+Assumptions!$B$69*MAX(MIN(Assumptions!$D$69,F$34)-MAX(Assumptions!$C$69,F$33),0)+Assumptions!$B$70*MAX(MIN(Assumptions!$D$70,F$34)-MAX(Assumptions!$C$70,F$33),0)+Assumptions!$B$71*MAX(MIN(Assumptions!$D$71,F$34)-MAX(Assumptions!$C$71,F$33),0) | G63: =Assumptions!$B$68*MAX(MIN(Assumptions!$D$68,G$34)-MAX(Assumptions!$C$68,G$33),0)+Assumptions!$B$69*MAX(MIN(Assumptions!$D$69,G$34)-MAX(Assumptions!$C$69,G$33),0)+Assumptions!$B$70*MAX(MIN(Assumptions!$D$70,G$34)-MAX(Assumptions!$C$70,G$33),0)+Assumptions!$B$71*MAX(MIN(Assumptions!$D$71,G$34)-MAX(Assumptions!$C$71,G$33),0) | H63: =Assumptions!$B$68*MAX(MIN(Assumptions!$D$68,H$34)-MAX(Assumptions!$C$68,H$33),0)+Assumptions!$B$69*MAX(MIN(Assumptions!$D$69,H$34)-MAX(Assumptions!$C$69,H$33),0)+Assumptions!$B$70*MAX(MIN(Assumptions!$D$70,H$34)-MAX(Assumptions!$C$70,H$33),0)+Assumptions!$B$71*MAX(MIN(Assumptions!$D$71,H$34)-MAX(Assumptions!$C$71,H$33),0)
A65: Spot vessel-days — class days less charter days
A66: Handysize | B66: =B45-B52 | C66: =C45-C52 | D66: =D45-D52 | E66: =E45-E52 | F66: =F45-F52 | G66: =G45-G52 | H66: =H45-H52
A67: Medium range | B67: =B46-B53 | C67: =C46-C53 | D67: =D46-D53 | E67: =E46-E53 | F67: =F46-F53 | G67: =G46-G53 | H67: =H46-H53
A68: Long range 1 | B68: =B47-B54 | C68: =C47-C54 | D68: =D47-D54 | E68: =E47-E54 | F68: =F47-F54 | G68: =G47-G54 | H68: =H47-H54
A69: Long range 2 | B69: =B48-B55 | C69: =C48-C55 | D69: =D48-D55 | E69: =E48-E55 | F69: =F48-F55 | G69: =G48-G55 | H69: =H48-H55
A70: Very large crude carrier | B70: =B49-B56 | C70: =C49-C56 | D70: =D49-D56 | E70: =E49-E56 | F70: =F49-F56 | G70: =G49-G56 | H70: =H49-H56
A72: IMPLIED SPOT RATE — the blend with the chartered vessels removed (USD per day)
A73: Handysize | B73: =(B38*B45-B59)/B66 | C73: =(C38*C45-C59)/C66 | D73: =(D38*D45-D59)/D66 | E73: =(E38*E45-E59)/E66 | F73: =(F38*F45-F59)/F66 | G73: =(G38*G45-G59)/G66 | H73: =(H38*H45-H59)/H66
A74: Medium range | B74: =(B39*B46-B60)/B67 | C74: =(C39*C46-C60)/C67 | D74: =(D39*D46-D60)/D67 | E74: =(E39*E46-E60)/E67 | F74: =(F39*F46-F60)/F67 | G74: =(G39*G46-G60)/G67 | H74: =(H39*H46-H60)/H67
A75: Long range 1 | B75: =(B40*B47-B61)/B68 | C75: =(C40*C47-C61)/C68 | D75: =(D40*D47-D61)/D68 | E75: =(E40*E47-E61)/E68 | F75: =(F40*F47-F61)/F68 | G75: =(G40*G47-G61)/G68 | H75: =(H40*H47-H61)/H68
A76: Long range 2 | B76: =(B41*B48-B62)/B69 | C76: =(C41*C48-C62)/C69 | D76: =(D41*D48-D62)/D69 | E76: =(E41*E48-E62)/E69 | F76: =(F41*F48-F62)/F69 | G76: =(G41*G48-G62)/G69 | H76: =(H41*H48-H62)/H69
A77: Very large crude carrier | B77: =(B42*B49-B63)/B70 | C77: =(C42*C49-C63)/C70 | D77: =(D42*D49-D63)/D70 | E77: =(E42*E49-E63)/E70 | F77: =(F42*F49-F63)/F70 | G77: =(G42*G49-G63)/G70 | H77: =(H42*H49-H63)/H70
A79: THE IMPLIED SPOT RATE PATH — NEVER THE PUBLISHED BLEND | B79: Handysize | C79: Medium range | D79: Long range 1 | E79: Long range 2 | F79: Very large crude carrier
A80: 2025 implied spot rate — the four quarters averaged (USD per day) | B80: =AVERAGE(B73:E73) | C80: =AVERAGE(B74:E74) | D80: =AVERAGE(B75:E75) | E80: =AVERAGE(B76:E76) | F80: =AVERAGE(B77:E77)
A81: Mid-cycle implied spot anchor (USD per day) | B81: =H73 | C81: =H74 | D81: =H75 | E81: =H76 | F81: =H77
A82: First-quarter 2026 implied spot rate (USD per day) | B82: =F73 | C82: =F74 | D82: =F75 | E82: =F76 | F82: =F77
A83: Second-quarter 2026 implied spot rate (USD per day) | B83: =G73 | C83: =G74 | D83: =G75 | E83: =G76 | F83: =G77
A84: Second half of 2026 — the first quarter stepped back toward the 2025 implied spot rate (USD per day) | B84: =B82*(1-Assumptions!$C$90)+B80*Assumptions!$C$90 | C84: =C82*(1-Assumptions!$C$90)+C80*Assumptions!$C$90 | D84: =D82*(1-Assumptions!$C$90)+D80*Assumptions!$C$90 | E84: =E82*(1-Assumptions!$C$90)+E80*Assumptions!$C$90 | F84: =F82*(1-Assumptions!$C$90)+F80*Assumptions!$C$90
A85: FY2026 implied spot rate — the four quarters averaged (USD per day) | B85: =(B82+B83+2*B84)/4 | C85: =(C82+C83+2*C84)/4 | D85: =(D82+D83+2*D84)/4 | E85: =(E82+E83+2*E84)/4 | F85: =(F82+F83+2*F84)/4
A87: Implied spot rate by class, gliding to the mid-cycle anchor (USD per day) | B87: FY2026 | C87: FY2027 | D87: FY2028 | E87: FY2029 | F87: FY2030
A88: Handysize | B88: =$B$85 | C88: =$B$85+($B$81-$B$85)*1/4 | D88: =$B$85+($B$81-$B$85)*2/4 | E88: =$B$85+($B$81-$B$85)*3/4 | F88: =$B$85+($B$81-$B$85)*4/4
A89: Medium range | B89: =$C$85 | C89: =$C$85+($C$81-$C$85)*1/4 | D89: =$C$85+($C$81-$C$85)*2/4 | E89: =$C$85+($C$81-$C$85)*3/4 | F89: =$C$85+($C$81-$C$85)*4/4
A90: Long range 1 | B90: =$D$85 | C90: =$D$85+($D$81-$D$85)*1/4 | D90: =$D$85+($D$81-$D$85)*2/4 | E90: =$D$85+($D$81-$D$85)*3/4 | F90: =$D$85+($D$81-$D$85)*4/4
A91: Long range 2 | B91: =$E$85 | C91: =$E$85+($E$81-$E$85)*1/4 | D91: =$E$85+($E$81-$E$85)*2/4 | E91: =$E$85+($E$81-$E$85)*3/4 | F91: =$E$85+($E$81-$E$85)*4/4
A92: Very large crude carrier | B92: =$F$85 | C92: =$F$85+($F$81-$F$85)*1/4 | D92: =$F$85+($F$81-$F$85)*2/4 | E92: =$F$85+($F$81-$F$85)*3/4 | F92: =$F$85+($F$81-$F$85)*4/4
A94: THE FORECAST YEARS — EVERY VESSEL PRICED ON ITS OWN TERMS | B94: FY2026 | C94: FY2027 | D94: FY2028 | E94: FY2029 | F94: FY2030
A95: Year begins | B95: =Assumptions!$B$78 | C95: =Assumptions!$C$78 | D95: =Assumptions!$D$78 | E95: =Assumptions!$E$78 | F95: =Assumptions!$F$78
A96: Year ends | B96: =Assumptions!$B$79 | C96: =Assumptions!$C$79 | D96: =Assumptions!$D$79 | E96: =Assumptions!$E$79 | F96: =Assumptions!$F$79
A97: Days in the year | B97: =B96-B95 | C97: =C96-C95 | D97: =D96-D95 | E97: =E96-E95 | F97: =F96-F95
A99: Charter vessel-days by class | B99: FY2026 | C99: FY2027 | D99: FY2028 | E99: FY2029 | F99: FY2030
A100: Handysize | B100: =0 | C100: =0 | D100: =0 | E100: =0 | F100: =0
A101: Medium range | B101: =0 | C101: =0 | D101: =0 | E101: =0 | F101: =0
A102: Long range 1 | B102: =MAX(MIN(Assumptions!$D$60,B$96)-MAX(Assumptions!$C$60,B$95),0)+MAX(MIN(Assumptions!$D$61,B$96)-MAX(Assumptions!$C$61,B$95),0) | C102: =MAX(MIN(Assumptions!$D$60,C$96)-MAX(Assumptions!$C$60,C$95),0)+MAX(MIN(Assumptions!$D$61,C$96)-MAX(Assumptions!$C$61,C$95),0) | D102: =MAX(MIN(Assumptions!$D$60,D$96)-MAX(Assumptions!$C$60,D$95),0)+MAX(MIN(Assumptions!$D$61,D$96)-MAX(Assumptions!$C$61,D$95),0) | E102: =MAX(MIN(Assumptions!$D$60,E$96)-MAX(Assumptions!$C$60,E$95),0)+MAX(MIN(Assumptions!$D$61,E$96)-MAX(Assumptions!$C$61,E$95),0) | F102: =MAX(MIN(Assumptions!$D$60,F$96)-MAX(Assumptions!$C$60,F$95),0)+MAX(MIN(Assumptions!$D$61,F$96)-MAX(Assumptions!$C$61,F$95),0)
A103: Long range 2 | B103: =MAX(MIN(Assumptions!$D$62,B$96)-MAX(Assumptions!$C$62,B$95),0)+MAX(MIN(Assumptions!$D$63,B$96)-MAX(Assumptions!$C$63,B$95),0)+MAX(MIN(Assumptions!$D$64,B$96)-MAX(Assumptions!$C$64,B$95),0)+MAX(MIN(Assumptions!$D$65,B$96)-MAX(Assumptions!$C$65,B$95),0)+MAX(MIN(Assumptions!$D$66,B$96)-MAX(Assumptions!$C$66,B$95),0)+MAX(MIN(Assumptions!$D$67,B$96)-MAX(Assumptions!$C$67,B$95),0) | C103: =MAX(MIN(Assumptions!$D$62,C$96)-MAX(Assumptions!$C$62,C$95),0)+MAX(MIN(Assumptions!$D$63,C$96)-MAX(Assumptions!$C$63,C$95),0)+MAX(MIN(Assumptions!$D$64,C$96)-MAX(Assumptions!$C$64,C$95),0)+MAX(MIN(Assumptions!$D$65,C$96)-MAX(Assumptions!$C$65,C$95),0)+MAX(MIN(Assumptions!$D$66,C$96)-MAX(Assumptions!$C$66,C$95),0)+MAX(MIN(Assumptions!$D$67,C$96)-MAX(Assumptions!$C$67,C$95),0) | D103: =MAX(MIN(Assumptions!$D$62,D$96)-MAX(Assumptions!$C$62,D$95),0)+MAX(MIN(Assumptions!$D$63,D$96)-MAX(Assumptions!$C$63,D$95),0)+MAX(MIN(Assumptions!$D$64,D$96)-MAX(Assumptions!$C$64,D$95),0)+MAX(MIN(Assumptions!$D$65,D$96)-MAX(Assumptions!$C$65,D$95),0)+MAX(MIN(Assumptions!$D$66,D$96)-MAX(Assumptions!$C$66,D$95),0)+MAX(MIN(Assumptions!$D$67,D$96)-MAX(Assumptions!$C$67,D$95),0) | E103: =MAX(MIN(Assumptions!$D$62,E$96)-MAX(Assumptions!$C$62,E$95),0)+MAX(MIN(Assumptions!$D$63,E$96)-MAX(Assumptions!$C$63,E$95),0)+MAX(MIN(Assumptions!$D$64,E$96)-MAX(Assumptions!$C$64,E$95),0)+MAX(MIN(Assumptions!$D$65,E$96)-MAX(Assumptions!$C$65,E$95),0)+MAX(MIN(Assumptions!$D$66,E$96)-MAX(Assumptions!$C$66,E$95),0)+MAX(MIN(Assumptions!$D$67,E$96)-MAX(Assumptions!$C$67,E$95),0) | F103: =MAX(MIN(Assumptions!$D$62,F$96)-MAX(Assumptions!$C$62,F$95),0)+MAX(MIN(Assumptions!$D$63,F$96)-MAX(Assumptions!$C$63,F$95),0)+MAX(MIN(Assumptions!$D$64,F$96)-MAX(Assumptions!$C$64,F$95),0)+MAX(MIN(Assumptions!$D$65,F$96)-MAX(Assumptions!$C$65,F$95),0)+MAX(MIN(Assumptions!$D$66,F$96)-MAX(Assumptions!$C$66,F$95),0)+MAX(MIN(Assumptions!$D$67,F$96)-MAX(Assumptions!$C$67,F$95),0)
A104: Very large crude carrier | B104: =MAX(MIN(Assumptions!$D$68,B$96)-MAX(Assumptions!$C$68,B$95),0)+MAX(MIN(Assumptions!$D$69,B$96)-MAX(Assumptions!$C$69,B$95),0)+MAX(MIN(Assumptions!$D$70,B$96)-MAX(Assumptions!$C$70,B$95),0)+MAX(MIN(Assumptions!$D$71,B$96)-MAX(Assumptions!$C$71,B$95),0) | C104: =MAX(MIN(Assumptions!$D$68,C$96)-MAX(Assumptions!$C$68,C$95),0)+MAX(MIN(Assumptions!$D$69,C$96)-MAX(Assumptions!$C$69,C$95),0)+MAX(MIN(Assumptions!$D$70,C$96)-MAX(Assumptions!$C$70,C$95),0)+MAX(MIN(Assumptions!$D$71,C$96)-MAX(Assumptions!$C$71,C$95),0) | D104: =MAX(MIN(Assumptions!$D$68,D$96)-MAX(Assumptions!$C$68,D$95),0)+MAX(MIN(Assumptions!$D$69,D$96)-MAX(Assumptions!$C$69,D$95),0)+MAX(MIN(Assumptions!$D$70,D$96)-MAX(Assumptions!$C$70,D$95),0)+MAX(MIN(Assumptions!$D$71,D$96)-MAX(Assumptions!$C$71,D$95),0) | E104: =MAX(MIN(Assumptions!$D$68,E$96)-MAX(Assumptions!$C$68,E$95),0)+MAX(MIN(Assumptions!$D$69,E$96)-MAX(Assumptions!$C$69,E$95),0)+MAX(MIN(Assumptions!$D$70,E$96)-MAX(Assumptions!$C$70,E$95),0)+MAX(MIN(Assumptions!$D$71,E$96)-MAX(Assumptions!$C$71,E$95),0) | F104: =MAX(MIN(Assumptions!$D$68,F$96)-MAX(Assumptions!$C$68,F$95),0)+MAX(MIN(Assumptions!$D$69,F$96)-MAX(Assumptions!$C$69,F$95),0)+MAX(MIN(Assumptions!$D$70,F$96)-MAX(Assumptions!$C$70,F$95),0)+MAX(MIN(Assumptions!$D$71,F$96)-MAX(Assumptions!$C$71,F$95),0)
A106: Charter revenue by class (USD 000) | B106: FY2026 | C106: FY2027 | D106: FY2028 | E106: FY2029 | F106: FY2030
A107: Handysize | B107: =0 | C107: =0 | D107: =0 | E107: =0 | F107: =0
A108: Medium range | B108: =0 | C108: =0 | D108: =0 | E108: =0 | F108: =0
A109: Long range 1 | B109: =(Assumptions!$B$60*MAX(MIN(Assumptions!$D$60,B$96)-MAX(Assumptions!$C$60,B$95),0)+Assumptions!$B$61*MAX(MIN(Assumptions!$D$61,B$96)-MAX(Assumptions!$C$61,B$95),0))/1000 | C109: =(Assumptions!$B$60*MAX(MIN(Assumptions!$D$60,C$96)-MAX(Assumptions!$C$60,C$95),0)+Assumptions!$B$61*MAX(MIN(Assumptions!$D$61,C$96)-MAX(Assumptions!$C$61,C$95),0))/1000 | D109: =(Assumptions!$B$60*MAX(MIN(Assumptions!$D$60,D$96)-MAX(Assumptions!$C$60,D$95),0)+Assumptions!$B$61*MAX(MIN(Assumptions!$D$61,D$96)-MAX(Assumptions!$C$61,D$95),0))/1000 | E109: =(Assumptions!$B$60*MAX(MIN(Assumptions!$D$60,E$96)-MAX(Assumptions!$C$60,E$95),0)+Assumptions!$B$61*MAX(MIN(Assumptions!$D$61,E$96)-MAX(Assumptions!$C$61,E$95),0))/1000 | F109: =(Assumptions!$B$60*MAX(MIN(Assumptions!$D$60,F$96)-MAX(Assumptions!$C$60,F$95),0)+Assumptions!$B$61*MAX(MIN(Assumptions!$D$61,F$96)-MAX(Assumptions!$C$61,F$95),0))/1000
A110: Long range 2 | B110: =(Assumptions!$B$62*MAX(MIN(Assumptions!$D$62,B$96)-MAX(Assumptions!$C$62,B$95),0)+Assumptions!$B$63*MAX(MIN(Assumptions!$D$63,B$96)-MAX(Assumptions!$C$63,B$95),0)+Assumptions!$B$64*MAX(MIN(Assumptions!$D$64,B$96)-MAX(Assumptions!$C$64,B$95),0)+Assumptions!$B$65*MAX(MIN(Assumptions!$D$65,B$96)-MAX(Assumptions!$C$65,B$95),0)+Assumptions!$B$66*MAX(MIN(Assumptions!$D$66,B$96)-MAX(Assumptions!$C$66,B$95),0)+Assumptions!$B$67*MAX(MIN(Assumptions!$D$67,B$96)-MAX(Assumptions!$C$67,B$95),0))/1000 | C110: =(Assumptions!$B$62*MAX(MIN(Assumptions!$D$62,C$96)-MAX(Assumptions!$C$62,C$95),0)+Assumptions!$B$63*MAX(MIN(Assumptions!$D$63,C$96)-MAX(Assumptions!$C$63,C$95),0)+Assumptions!$B$64*MAX(MIN(Assumptions!$D$64,C$96)-MAX(Assumptions!$C$64,C$95),0)+Assumptions!$B$65*MAX(MIN(Assumptions!$D$65,C$96)-MAX(Assumptions!$C$65,C$95),0)+Assumptions!$B$66*MAX(MIN(Assumptions!$D$66,C$96)-MAX(Assumptions!$C$66,C$95),0)+Assumptions!$B$67*MAX(MIN(Assumptions!$D$67,C$96)-MAX(Assumptions!$C$67,C$95),0))/1000 | D110: =(Assumptions!$B$62*MAX(MIN(Assumptions!$D$62,D$96)-MAX(Assumptions!$C$62,D$95),0)+Assumptions!$B$63*MAX(MIN(Assumptions!$D$63,D$96)-MAX(Assumptions!$C$63,D$95),0)+Assumptions!$B$64*MAX(MIN(Assumptions!$D$64,D$96)-MAX(Assumptions!$C$64,D$95),0)+Assumptions!$B$65*MAX(MIN(Assumptions!$D$65,D$96)-MAX(Assumptions!$C$65,D$95),0)+Assumptions!$B$66*MAX(MIN(Assumptions!$D$66,D$96)-MAX(Assumptions!$C$66,D$95),0)+Assumptions!$B$67*MAX(MIN(Assumptions!$D$67,D$96)-MAX(Assumptions!$C$67,D$95),0))/1000 | E110: =(Assumptions!$B$62*MAX(MIN(Assumptions!$D$62,E$96)-MAX(Assumptions!$C$62,E$95),0)+Assumptions!$B$63*MAX(MIN(Assumptions!$D$63,E$96)-MAX(Assumptions!$C$63,E$95),0)+Assumptions!$B$64*MAX(MIN(Assumptions!$D$64,E$96)-MAX(Assumptions!$C$64,E$95),0)+Assumptions!$B$65*MAX(MIN(Assumptions!$D$65,E$96)-MAX(Assumptions!$C$65,E$95),0)+Assumptions!$B$66*MAX(MIN(Assumptions!$D$66,E$96)-MAX(Assumptions!$C$66,E$95),0)+Assumptions!$B$67*MAX(MIN(Assumptions!$D$67,E$96)-MAX(Assumptions!$C$67,E$95),0))/1000 | F110: =(Assumptions!$B$62*MAX(MIN(Assumptions!$D$62,F$96)-MAX(Assumptions!$C$62,F$95),0)+Assumptions!$B$63*MAX(MIN(Assumptions!$D$63,F$96)-MAX(Assumptions!$C$63,F$95),0)+Assumptions!$B$64*MAX(MIN(Assumptions!$D$64,F$96)-MAX(Assumptions!$C$64,F$95),0)+Assumptions!$B$65*MAX(MIN(Assumptions!$D$65,F$96)-MAX(Assumptions!$C$65,F$95),0)+Assumptions!$B$66*MAX(MIN(Assumptions!$D$66,F$96)-MAX(Assumptions!$C$66,F$95),0)+Assumptions!$B$67*MAX(MIN(Assumptions!$D$67,F$96)-MAX(Assumptions!$C$67,F$95),0))/1000
A111: Very large crude carrier | B111: =(Assumptions!$B$68*MAX(MIN(Assumptions!$D$68,B$96)-MAX(Assumptions!$C$68,B$95),0)+Assumptions!$B$69*MAX(MIN(Assumptions!$D$69,B$96)-MAX(Assumptions!$C$69,B$95),0)+Assumptions!$B$70*MAX(MIN(Assumptions!$D$70,B$96)-MAX(Assumptions!$C$70,B$95),0)+Assumptions!$B$71*MAX(MIN(Assumptions!$D$71,B$96)-MAX(Assumptions!$C$71,B$95),0))/1000 | C111: =(Assumptions!$B$68*MAX(MIN(Assumptions!$D$68,C$96)-MAX(Assumptions!$C$68,C$95),0)+Assumptions!$B$69*MAX(MIN(Assumptions!$D$69,C$96)-MAX(Assumptions!$C$69,C$95),0)+Assumptions!$B$70*MAX(MIN(Assumptions!$D$70,C$96)-MAX(Assumptions!$C$70,C$95),0)+Assumptions!$B$71*MAX(MIN(Assumptions!$D$71,C$96)-MAX(Assumptions!$C$71,C$95),0))/1000 | D111: =(Assumptions!$B$68*MAX(MIN(Assumptions!$D$68,D$96)-MAX(Assumptions!$C$68,D$95),0)+Assumptions!$B$69*MAX(MIN(Assumptions!$D$69,D$96)-MAX(Assumptions!$C$69,D$95),0)+Assumptions!$B$70*MAX(MIN(Assumptions!$D$70,D$96)-MAX(Assumptions!$C$70,D$95),0)+Assumptions!$B$71*MAX(MIN(Assumptions!$D$71,D$96)-MAX(Assumptions!$C$71,D$95),0))/1000 | E111: =(Assumptions!$B$68*MAX(MIN(Assumptions!$D$68,E$96)-MAX(Assumptions!$C$68,E$95),0)+Assumptions!$B$69*MAX(MIN(Assumptions!$D$69,E$96)-MAX(Assumptions!$C$69,E$95),0)+Assumptions!$B$70*MAX(MIN(Assumptions!$D$70,E$96)-MAX(Assumptions!$C$70,E$95),0)+Assumptions!$B$71*MAX(MIN(Assumptions!$D$71,E$96)-MAX(Assumptions!$C$71,E$95),0))/1000 | F111: =(Assumptions!$B$68*MAX(MIN(Assumptions!$D$68,F$96)-MAX(Assumptions!$C$68,F$95),0)+Assumptions!$B$69*MAX(MIN(Assumptions!$D$69,F$96)-MAX(Assumptions!$C$69,F$95),0)+Assumptions!$B$70*MAX(MIN(Assumptions!$D$70,F$96)-MAX(Assumptions!$C$70,F$95),0)+Assumptions!$B$71*MAX(MIN(Assumptions!$D$71,F$96)-MAX(Assumptions!$C$71,F$95),0))/1000
A113: Acquired vessel-days by class — the vessels bought on 7 August 2026, counted from their own delivery date | B113: FY2026 | C113: FY2027 | D113: FY2028 | E113: FY2029 | F113: FY2030
A114: Handysize | B114: =$B$29*MAX(B$96-MAX(B$95,$B$30),0) | C114: =$B$29*MAX(C$96-MAX(C$95,$B$30),0) | D114: =$B$29*MAX(D$96-MAX(D$95,$B$30),0) | E114: =$B$29*MAX(E$96-MAX(E$95,$B$30),0) | F114: =$B$29*MAX(F$96-MAX(F$95,$B$30),0)
A115: Medium range | B115: =$C$29*MAX(B$96-MAX(B$95,$C$30),0) | C115: =$C$29*MAX(C$96-MAX(C$95,$C$30),0) | D115: =$C$29*MAX(D$96-MAX(D$95,$C$30),0) | E115: =$C$29*MAX(E$96-MAX(E$95,$C$30),0) | F115: =$C$29*MAX(F$96-MAX(F$95,$C$30),0)
A116: Long range 1 | B116: =$D$29*MAX(B$96-MAX(B$95,$D$30),0) | C116: =$D$29*MAX(C$96-MAX(C$95,$D$30),0) | D116: =$D$29*MAX(D$96-MAX(D$95,$D$30),0) | E116: =$D$29*MAX(E$96-MAX(E$95,$D$30),0) | F116: =$D$29*MAX(F$96-MAX(F$95,$D$30),0)
...

Sheet Relative & Normalized
A1: Relative multiples, normalised earnings power and the book lens
A2: USD thousand unless stated. Per-share figures in dirhams.
A4: Relative lens | C4: Value
A5: FY2026E group EBITDA | C5: =DCF!B6
A6: Blended enterprise multiple | C6: ='Peer & Sector'!$C$13
A7: Implied enterprise value | C7: =C5*C6
A8: Plus joint ventures and associates at carrying value | C8: =Assumptions!$C$157
A9: Less net debt at 31 March 2026 | C9: =-Assumptions!$C$150
A10: Less deferred consideration on acquisitions | C10: =-Assumptions!$C$151
A11: Less the eleven vessels bought on 7 August 2026, at the announced price | C11: =-Assumptions!$C$82
A12: Less perpetual capital securities at carrying value | C12: =-Assumptions!$C$152
A13: Implied equity value before the minorities | C13: =C7+C8+C9+C10+C11+C12
A14: Less non-controlling interests — the contracted slice at its contracted price, the rest at the greater of book and value | C14: =-(DCF!$C$56+MAX(DCF!$C$57,C13*DCF!$C$58))
A15: Implied equity attributable to ordinary shareholders | C15: =C13+C14
A16: Value per share on the enterprise multiple (AED) | C16: =C15/Assumptions!$C$6/1000*Assumptions!$C$7
A17: Blended FORWARD price/earnings — applied to forward earnings below, so the multiple and the earnings are on the same basis | C17: ='Peer & Sector'!$C$16
A18: FY2026E earnings attributable to ordinary shareholders | C18: ='Income Statement'!E30
A19: Value per share on the earnings multiple (AED) | C19: =C18*C17/Assumptions!$C$6/1000*Assumptions!$C$7
A20: Weight on the enterprise multiple | C20: =Assumptions!$C$169
A21: RELATIVE LENS — value per share (AED) | C21: =C20*C16+(1-C20)*C19
A22: Bear and bull — enterprise value on the spot-tanker multiple (C) / on the contracted multiple (D) | C22: =C5*'Peer & Sector'!$C$11 | D22: =C5*'Peer & Sector'!$C$10
A23: Equity value before the minorities | C23: =C22+Assumptions!$C$157-Assumptions!$C$150-Assumptions!$C$151-Assumptions!$C$82-Assumptions!$C$152 | D23: =D22+Assumptions!$C$157-Assumptions!$C$150-Assumptions!$C$151-Assumptions!$C$82-Assumptions!$C$152
A24: Less non-controlling interests — the same two-part deduction | C24: =-(DCF!$C$56+MAX(DCF!$C$57,C23*DCF!$C$58)) | D24: =-(DCF!$C$56+MAX(DCF!$C$57,D23*DCF!$C$58))
A25: Equity attributable to ordinary shareholders | C25: =C23+C24 | D25: =D23+D24
A26: Bear on the spot multiple (C) / bull on the contracted multiple (D), same construction | C26: =C25/Assumptions!$C$6/1000*Assumptions!$C$7 | D26: =D25/Assumptions!$C$6/1000*Assumptions!$C$7
A28: THE COMPANY'S OWN MULTIPLES AT THE ANCHOR PRICE
A29: Share price (USD) | C29: =Assumptions!$C$5/Assumptions!$C$7
A30: Market capitalisation (USD 000) | C30: =C29*Assumptions!$C$6*1000
A31: Net debt including the deferred consideration and the vessels bought on 7 August 2026 (USD 000) | C31: =Assumptions!$C$150+Assumptions!$C$151+Assumptions!$C$82
A32: Enterprise value (USD 000) | C32: =C30+C31
A33: Enterprise value / 2025 reported EBITDA | C33: =C32/'Income Statement'!D16
A34: Enterprise value / FY2026E EBITDA | C34: =C32/C5
A35: Price / 2025 earnings attributable to ordinary shareholders — the TRAILING basis | C35: =C30/'Income Statement'!D30
A36: Price / FY2026E earnings attributable to ordinary shareholders — the FORWARD basis, the one the peer multiples are quoted on | C36: =C30/C18
A37: Price / book at 31 March 2026 | C37: =C30/(Assumptions!$C$158+Assumptions!$C$152)
A38: Dividend yield on the 2026 distribution | C38: =Assumptions!$C$162/C30
A39: Enterprise value on the equity bridge's own convention — adding the perpetual capital securities and the minorities (USD 000) | C39: =C32+Assumptions!$C$152+Assumptions!$C$154
A40: Enterprise value / 2025 reported EBITDA — bridge convention | C40: =C39/'Income Statement'!D16
A41: Enterprise value / FY2026E EBITDA — bridge convention | C41: =C39/C5
A42: The two multiples immediately above are the company's own on the SAME enterprise value the equity bridge uses. The three rows before them use the narrower market-capitalisation-plus-net-debt convention, because that is the convention the peer figures are published on and the comparison has to be like for like. Both are shown rather than one chosen.
A43: Normalised earnings lens — the five-year average of the model's own forecast | C43: Value
A44: Mid-cycle EBITDA — five-year average | C44: =AVERAGE(DCF!B6:F6)
A45: Implied enterprise value | C45: =C44*C6
A46: Implied equity value before the minorities | C46: =C45+Assumptions!$C$157-Assumptions!$C$150-Assumptions!$C$151-Assumptions!$C$82-Assumptions!$C$152
A47: Less non-controlling interests — the same two-part deduction | C47: =-(DCF!$C$56+MAX(DCF!$C$57,C46*DCF!$C$58))
A48: Implied equity attributable to ordinary shareholders | C48: =C46+C47
A49: Value per share on the enterprise multiple (AED) | C49: =C48/Assumptions!$C$6/1000*Assumptions!$C$7
A50: Mid-cycle earnings attributable to ordinary shareholders — five-year average | C50: =AVERAGE('Income Statement'!E30:I30)
A51: Mid-cycle earnings per share (USD) | C51: =C50/Assumptions!$C$6/1000
A52: Value per share on the earnings multiple (AED) | C52: =C51*C17*Assumptions!$C$7
A53: NORMALISED LENS — value per share (AED) | C53: =(C49+C52)/2
A54: Bear and bull — enterprise value on the spot-tanker multiple (C) / on the contracted multiple (D) | C54: =C44*'Peer & Sector'!$C$11 | D54: =C44*'Peer & Sector'!$C$10
A55: Equity value before the minorities | C55: =C54+Assumptions!$C$157-Assumptions!$C$150-Assumptions!$C$151-Assumptions!$C$82-Assumptions!$C$152 | D55: =D54+Assumptions!$C$157-Assumptions!$C$150-Assumptions!$C$151-Assumptions!$C$82-Assumptions!$C$152
A56: Less non-controlling interests — the same two-part deduction | C56: =-(DCF!$C$56+MAX(DCF!$C$57,C55*DCF!$C$58)) | D56: =-(DCF!$C$56+MAX(DCF!$C$57,D55*DCF!$C$58))
A57: Equity attributable to ordinary shareholders | C57: =C55+C56 | D57: =D55+D56
A58: Bear on the spot multiple (C) / bull on the contracted multiple (D), same construction | C58: =C57/Assumptions!$C$6/1000*Assumptions!$C$7 | D58: =D57/Assumptions!$C$6/1000*Assumptions!$C$7
A60: Book value and sustainable return — a RESIDUAL INCOME build | C60: Value
A61: Equity attributable to shareholders at 31 March 2026 (USD 000) | C61: =Assumptions!$C$158
A62: Book value per share (USD) | C62: =C61/Assumptions!$C$6/1000
A63: Book value per share (AED) | C63: =C62*Assumptions!$C$7
A64: Sustainable return on equity — five-year forecast average | C64: =AVERAGE('Balance Sheet'!E28:I28)
A65: Cost of equity | C65: =DCF!$C$69
A66: Terminal growth | C66: =Assumptions!$C$164
A67: Rate at which the return above the cost of equity fades beyond the forecast | C67: =Assumptions!$C$168
A68: THE RESIDUAL-INCOME LADDER — BASE | B68: FY2026 | C68: FY2027 | D68: FY2028 | E68: FY2029 | F68: FY2030
A69: Opening ordinary book value (USD mn) — the balance sheet's own roll-forward | B69: =C61/1000 | C69: ='Balance Sheet'!B69/1000 | D69: ='Balance Sheet'!C69/1000 | E69: ='Balance Sheet'!D69/1000 | F69: ='Balance Sheet'!E69/1000
A70: Return on ordinary equity — profit after the perpetual coupon, over closing ordinary book | B70: ='Income Statement'!E30/'Balance Sheet'!B69 | C70: ='Income Statement'!F30/'Balance Sheet'!C69 | D70: ='Income Statement'!G30/'Balance Sheet'!D69 | E70: ='Income Statement'!H30/'Balance Sheet'!E69 | F70: ='Income Statement'!I30/'Balance Sheet'!F69
A71: Residual income — (return less cost of equity) x opening book (USD mn) | B71: =(B70-C65)*B69 | C71: =(C70-C65)*C69 | D71: =(D70-C65)*D69 | E71: =(E70-C65)*E69 | F71: =(F70-C65)*F69
A72: Discount factor at the cost of equity | B72: =1/(1+C65)^1 | C72: =1/(1+C65)^2 | D72: =1/(1+C65)^3 | E72: =1/(1+C65)^4 | F72: =1/(1+C65)^5
A73: Present value of the residual income (USD mn) | B73: =B71*B72 | C73: =C71*C72 | D73: =D71*D72 | E73: =E71*E72 | F73: =F71*F72
A74: Present value of the five forecast years (USD mn) | C74: =SUM(B73:F73)
A75: Terminal residual income — the final year's excess return on the closing book (USD mn) | C75: =(F70-C65)*'Balance Sheet'!F69/1000
A76: Terminal value — that excess fading toward the cost of equity (USD mn) | C76: =C75/(C65+C67-C66)
A77: Present value of the terminal value (USD mn) | C77: =C76/(1+C65)^5
A78: Equity value — opening book plus the residual income it earns (USD mn) | C78: =C61/1000+C74+C77
A79: Implied price / book — the equity value over the book it starts from | C79: =C78/(C61/1000)
A80: BOOK LENS — value per share (AED) | C80: =C78/Assumptions!$C$6*Assumptions!$C$7
A82: THE SAME LADDER — BEAR: the return 15% lower, discounted at the cost of equity built on the TOP of the beta's 90% confidence interval | B82: FY2026 | C82: FY2027 | D82: FY2028 | E82: FY2029 | F82: FY2030
A83: Return on ordinary equity — profit after the perpetual coupon, over closing ordinary book (scaled 0.85x) | B83: ='Income Statement'!E30/'Balance Sheet'!B69*0.85 | C83: ='Income Statement'!F30/'Balance Sheet'!C69*0.85 | D83: ='Income Statement'!G30/'Balance Sheet'!D69*0.85 | E83: ='Income Statement'!H30/'Balance Sheet'!E69*0.85 | F83: ='Income Statement'!I30/'Balance Sheet'!F69*0.85
A84: Residual income — (return less cost of equity) x opening book (USD mn) | B84: =(B83-DCF!$C$124)*B69 | C84: =(C83-DCF!$C$124)*C69 | D84: =(D83-DCF!$C$124)*D69 | E84: =(E83-DCF!$C$124)*E69 | F84: =(F83-DCF!$C$124)*F69
A85: Discount factor at the cost of equity | B85: =1/(1+DCF!$C$124)^1 | C85: =1/(1+DCF!$C$124)^2 | D85: =1/(1+DCF!$C$124)^3 | E85: =1/(1+DCF!$C$124)^4 | F85: =1/(1+DCF!$C$124)^5
A86: Present value of the residual income (USD mn) | B86: =B84*B85 | C86: =C84*C85 | D86: =D84*D85 | E86: =E84*E85 | F86: =F84*F85
A87: Present value of the five forecast years (USD mn) | C87: =SUM(B86:F86)
A88: Terminal residual income — the final year's excess return on the closing book (USD mn) | C88: =(F83-DCF!$C$124)*'Balance Sheet'!F69/1000
A89: Terminal value — that excess fading toward the cost of equity (USD mn) | C89: =C88/(DCF!$C$124+C67-C66)
A90: Present value of the terminal value (USD mn) | C90: =C89/(1+DCF!$C$124)^5
A91: Equity value — opening book plus the residual income it earns (USD mn) | C91: =C61/1000+C87+C90
A92: THE SAME LADDER — BULL: the return 15% higher, discounted at the cost of equity built on the BOTTOM of the same interval | B92: FY2026 | C92: FY2027 | D92: FY2028 | E92: FY2029 | F92: FY2030
A93: Return on ordinary equity — profit after the perpetual coupon, over closing ordinary book (scaled 1.15x) | B93: ='Income Statement'!E30/'Balance Sheet'!B69*1.15 | C93: ='Income Statement'!F30/'Balance Sheet'!C69*1.15 | D93: ='Income Statement'!G30/'Balance Sheet'!D69*1.15 | E93: ='Income Statement'!H30/'Balance Sheet'!E69*1.15 | F93: ='Income Statement'!I30/'Balance Sheet'!F69*1.15
A94: Residual income — (return less cost of equity) x opening book (USD mn) | B94: =(B93-DCF!$C$123)*B69 | C94: =(C93-DCF!$C$123)*C69 | D94: =(D93-DCF!$C$123)*D69 | E94: =(E93-DCF!$C$123)*E69 | F94: =(F93-DCF!$C$123)*F69
A95: Discount factor at the cost of equity | B95: =1/(1+DCF!$C$123)^1 | C95: =1/(1+DCF!$C$123)^2 | D95: =1/(1+DCF!$C$123)^3 | E95: =1/(1+DCF!$C$123)^4 | F95: =1/(1+DCF!$C$123)^5
A96: Present value of the residual income (USD mn) | B96: =B94*B95 | C96: =C94*C95 | D96: =D94*D95 | E96: =E94*E95 | F96: =F94*F95
A97: Present value of the five forecast years (USD mn) | C97: =SUM(B96:F96)
A98: Terminal residual income — the final year's excess return on the closing book (USD mn) | C98: =(F93-DCF!$C$123)*'Balance Sheet'!F69/1000
A99: Terminal value — that excess fading toward the cost of equity (USD mn) | C99: =C98/(DCF!$C$123+C67-C66)
A100: Present value of the terminal value (USD mn) | C100: =C99/(1+DCF!$C$123)^5
A101: Equity value — opening book plus the residual income it earns (USD mn) | C101: =C61/1000+C97+C100
A102: Bear — return 15% lower, discounted at the cost of equity built on the TOP of the beta's 90% confidence interval (C) / bull — return 15% higher, discounted at the cost of equity built on the BOTTOM of the same interval (D) | C102: =C91/Assumptions!$C$6*Assumptions!$C$7 | D102: =C101/Assumptions!$C$6*Assumptions!$C$7
A104: THE REALISED VESSEL SALE — DIRECT EVIDENCE ON CARRYING VALUES
A105: Carrying value of the very large crude carrier sold (USD 000) | C105: 83000
...

Sheet DCF
A1: Discounted cash flow — the full waterfall
A2: USD thousand. Every line is a live formula: the cost of capital is built below from its own components, the discount factors compound year on year off the glide, and 2026 is a three-quarter stub because the valuation date is 31 March 2026.
A4: USD 000 | B4: FY2026E | C4: FY2027E | D4: FY2028E | E4: FY2029E | F4: FY2030E
A5: Revenue | B5: =Segments!B187 | C5: =Segments!C187 | D5: =Segments!D187 | E5: =Segments!E187 | F5: =Segments!F187
A6: EBITDA | B6: =Segments!B197 | C6: =Segments!C197 | D6: =Segments!D197 | E6: =Segments!E197 | F6: =Segments!F197
A7: EBITDA margin | B7: =B6/B5 | C7: =C6/C5 | D7: =D6/D5 | E7: =E6/E5 | F7: =F6/F5
A8: Less depreciation and amortisation | B8: =-'Balance Sheet'!B39 | C8: =-'Balance Sheet'!C39 | D8: =-'Balance Sheet'!D39 | E8: =-'Balance Sheet'!E39 | F8: =-'Balance Sheet'!F39
A9: EBIT | B9: =B6+B8 | C9: =C6+C8 | D9: =D6+D8 | E9: =E6+E8 | F9: =F6+F8
A10: Less tax on operating profit — the business-unit mix below | B10: =-B35 | C10: =-C35 | D10: =-D35 | E10: =-E35 | F10: =-F35
A11: NOPAT | B11: =B9+B10 | C11: =C9+C10 | D11: =D9+D10 | E11: =E9+E10 | F11: =F9+F10
A12: Add back depreciation and amortisation | B12: =-B8 | C12: =-C8 | D12: =-D8 | E12: =-E8 | F12: =-F8
A13: Less capital expenditure | B13: =-Assumptions!$B$120 | C13: =-Assumptions!$C$120 | D13: =-Assumptions!$D$120 | E13: =-Assumptions!$E$120 | F13: =-Assumptions!$F$120
A14: Less change in working capital | B14: =-'Balance Sheet'!B50 | C14: =-'Balance Sheet'!C50 | D14: =-'Balance Sheet'!D50 | E14: =-'Balance Sheet'!E50 | F14: =-'Balance Sheet'!F50
A15: Free cash flow to the firm | B15: =B11+B12+B13+B14 | C15: =C11+C12+C13+C14 | D15: =D11+D12+D13+D14 | E15: =E11+E12+E13+E14 | F15: =F11+F12+F13+F14
A16: Less first-quarter 2026 free cash flow, already inside net debt at the valuation date | B16: =-Assumptions!$C$9 | C16: =0 | D16: =0 | E16: =0 | F16: =0
A17: Free cash flow discounted from 31 March 2026 | B17: =B15+B16 | C17: =C15+C16 | D17: =D15+D16 | E17: =E15+E16 | F17: =F15+F16
A18: Forward cost of capital — the glide from current to terminal | B18: =$C$105+($C$111-$C$105)*1/5 | C18: =$C$105+($C$111-$C$105)*2/5 | D18: =$C$105+($C$111-$C$105)*3/5 | E18: =$C$105+($C$111-$C$105)*4/5 | F18: =$C$105+($C$111-$C$105)*5/5
A19: Discount factor — each year compounded onto the last | B19: =1/(1+B18)^Assumptions!$C$8 | C19: =B19/(1+C18) | D19: =C19/(1+D18) | E19: =D19/(1+E18) | F19: =E19/(1+F18)
A20: Present value of free cash flow | B20: =B17*B19 | C20: =C17*C19 | D20: =D17*D19 | E20: =E17*E19 | F20: =F17*F19
A22: THE TAX MIX — EACH BUSINESS UNIT AT ITS OWN DISCLOSED RATE | B22: FY2026E | C22: FY2027E | D22: FY2028E | E22: FY2029E | F22: FY2030E
A23: Integrated Logistics — EBITDA | B23: =Segments!B204 | C23: =Segments!C204 | D23: =Segments!D204 | E23: =Segments!E204 | F23: =Segments!F204
A24: Shipping — EBITDA | B24: =Segments!B205 | C24: =Segments!C205 | D24: =Segments!D205 | E24: =Segments!E205 | F24: =Segments!F205
A25: Services — EBITDA | B25: =Segments!B206 | C25: =Segments!C206 | D25: =Segments!D206 | E25: =Segments!E206 | F25: =Segments!F206
A26: Integrated Logistics — share of depreciation and amortisation | B26: =-B8*(Assumptions!$C$141+Assumptions!$C$142+Assumptions!$C$143)/(Assumptions!$C$141+Assumptions!$C$142+Assumptions!$C$143+Assumptions!$C$144+Assumptions!$C$145+Assumptions!$C$146+Assumptions!$C$147) | C26: =-C8*(Assumptions!$C$141+Assumptions!$C$142+Assumptions!$C$143)/(Assumptions!$C$141+Assumptions!$C$142+Assumptions!$C$143+Assumptions!$C$144+Assumptions!$C$145+Assumptions!$C$146+Assumptions!$C$147) | D26: =-D8*(Assumptions!$C$141+Assumptions!$C$142+Assumptions!$C$143)/(Assumptions!$C$141+Assumptions!$C$142+Assumptions!$C$143+Assumptions!$C$144+Assumptions!$C$145+Assumptions!$C$146+Assumptions!$C$147) | E26: =-E8*(Assumptions!$C$141+Assumptions!$C$142+Assumptions!$C$143)/(Assumptions!$C$141+Assumptions!$C$142+Assumptions!$C$143+Assumptions!$C$144+Assumptions!$C$145+Assumptions!$C$146+Assumptions!$C$147) | F26: =-F8*(Assumptions!$C$141+Assumptions!$C$142+Assumptions!$C$143)/(Assumptions!$C$141+Assumptions!$C$142+Assumptions!$C$143+Assumptions!$C$144+Assumptions!$C$145+Assumptions!$C$146+Assumptions!$C$147)
A27: Shipping — share of depreciation and amortisation | B27: =-B8*(Assumptions!$C$144+Assumptions!$C$145+Assumptions!$C$146)/(Assumptions!$C$141+Assumptions!$C$142+Assumptions!$C$143+Assumptions!$C$144+Assumptions!$C$145+Assumptions!$C$146+Assumptions!$C$147) | C27: =-C8*(Assumptions!$C$144+Assumptions!$C$145+Assumptions!$C$146)/(Assumptions!$C$141+Assumptions!$C$142+Assumptions!$C$143+Assumptions!$C$144+Assumptions!$C$145+Assumptions!$C$146+Assumptions!$C$147) | D27: =-D8*(Assumptions!$C$144+Assumptions!$C$145+Assumptions!$C$146)/(Assumptions!$C$141+Assumptions!$C$142+Assumptions!$C$143+Assumptions!$C$144+Assumptions!$C$145+Assumptions!$C$146+Assumptions!$C$147) | E27: =-E8*(Assumptions!$C$144+Assumptions!$C$145+Assumptions!$C$146)/(Assumptions!$C$141+Assumptions!$C$142+Assumptions!$C$143+Assumptions!$C$144+Assumptions!$C$145+Assumptions!$C$146+Assumptions!$C$147) | F27: =-F8*(Assumptions!$C$144+Assumptions!$C$145+Assumptions!$C$146)/(Assumptions!$C$141+Assumptions!$C$142+Assumptions!$C$143+Assumptions!$C$144+Assumptions!$C$145+Assumptions!$C$146+Assumptions!$C$147)
A28: Services — share of depreciation and amortisation | B28: =-B8*(Assumptions!$C$147)/(Assumptions!$C$141+Assumptions!$C$142+Assumptions!$C$143+Assumptions!$C$144+Assumptions!$C$145+Assumptions!$C$146+Assumptions!$C$147) | C28: =-C8*(Assumptions!$C$147)/(Assumptions!$C$141+Assumptions!$C$142+Assumptions!$C$143+Assumptions!$C$144+Assumptions!$C$145+Assumptions!$C$146+Assumptions!$C$147) | D28: =-D8*(Assumptions!$C$147)/(Assumptions!$C$141+Assumptions!$C$142+Assumptions!$C$143+Assumptions!$C$144+Assumptions!$C$145+Assumptions!$C$146+Assumptions!$C$147) | E28: =-E8*(Assumptions!$C$147)/(Assumptions!$C$141+Assumptions!$C$142+Assumptions!$C$143+Assumptions!$C$144+Assumptions!$C$145+Assumptions!$C$146+Assumptions!$C$147) | F28: =-F8*(Assumptions!$C$147)/(Assumptions!$C$141+Assumptions!$C$142+Assumptions!$C$143+Assumptions!$C$144+Assumptions!$C$145+Assumptions!$C$146+Assumptions!$C$147)
A29: Integrated Logistics — taxable profit | B29: =MAX(B23-B26,0) | C29: =MAX(C23-C26,0) | D29: =MAX(D23-D26,0) | E29: =MAX(E23-E26,0) | F29: =MAX(F23-F26,0)
A30: Shipping — taxable profit | B30: =MAX(B24-B27,0) | C30: =MAX(C24-C27,0) | D30: =MAX(D24-D27,0) | E30: =MAX(E24-E27,0) | F30: =MAX(F24-F27,0)
A31: Services — taxable profit | B31: =MAX(B25-B28,0) | C31: =MAX(C25-C28,0) | D31: =MAX(D25-D28,0) | E31: =MAX(E25-E28,0) | F31: =MAX(F25-F28,0)
A32: Integrated Logistics — tax charge at 9% | B32: =B29*Assumptions!$C$138 | C32: =C29*Assumptions!$C$138 | D32: =D29*Assumptions!$C$138 | E32: =E29*Assumptions!$C$138 | F32: =F29*Assumptions!$C$138
A33: Shipping — tax charge at 1% | B33: =B30*Assumptions!$C$139 | C33: =C30*Assumptions!$C$139 | D33: =D30*Assumptions!$C$139 | E33: =E30*Assumptions!$C$139 | F33: =F30*Assumptions!$C$139
A34: Services — tax charge at 4% | B34: =B31*Assumptions!$C$140 | C34: =C31*Assumptions!$C$140 | D34: =D31*Assumptions!$C$140 | E34: =E31*Assumptions!$C$140 | F34: =F31*Assumptions!$C$140
A35: Tax on operating profit | B35: =SUM(B32:B34) | C35: =SUM(C32:C34) | D35: =SUM(D32:D34) | E35: =SUM(E32:E34) | F35: =SUM(F32:F34)
A36: Effective tax rate on operating profit | B36: =B35/B9 | C36: =C35/C9 | D36: =D35/D9 | E36: =E35/E9 | F36: =F35/F9
A38: TERMINAL VALUE AND THE BRIDGE TO EQUITY
A39: Terminal growth | C39: =Assumptions!$C$164
A40: Terminal invested capital | C40: ='Balance Sheet'!I26
A41: Terminal return on invested capital | C41: =F11/C40
A42: Required reinvestment rate — terminal growth over the return on invested capital | C42: =C39/C41
A43: Terminal-year NOPAT grown one year | C43: =F11*(1+C39)
A44: Terminal value — grown NOPAT net of reinvestment, capitalised at the terminal rate | C44: =C43*(1-C42)/(C111-C39)
A45: Present value of the five forecast years | C45: =SUM(B20:F20)
A46: Present value of the terminal value | C46: =C44*F19
A47: Enterprise value of operations | C47: =C45+C46
A48: Terminal value as a share of enterprise value | C48: =C46/C47
A49: Plus joint ventures and associates at carrying value | C49: =Assumptions!$C$157
A50: Enterprise value | C50: =C47+C49
A51: Less net debt at 31 March 2026 | C51: =-Assumptions!$C$150
A52: Less deferred consideration on acquisitions | C52: =-Assumptions!$C$151
A53: Less the eleven vessels bought on 7 August 2026 — committed and funded, so their price is carried here and their earnings are in the forecast above | C53: =-Assumptions!$C$82
A54: Less perpetual capital securities at carrying value | C54: =-Assumptions!$C$152
A55: Equity value before the minorities | C55: =C50+C51+C52+C53+C54
A56: Minorities arising on the tanker combination — 20% CONTRACTED for purchase in mid-2027, whose price already sits in the bridge above as deferred consideration, so it is deducted at that contracted price, not at a share of value | C56: =Assumptions!$C$155
A57: The remaining minorities at carrying value | C57: =Assumptions!$C$154-C56
A58: Their share of profit — the profit share scaled to their share of the carried minority balance | C58: =Assumptions!$C$156*C57/Assumptions!$C$154
A59: Less non-controlling interests — the contracted slice at its contracted price, the rest at the greater of book and value | C59: =-(C56+MAX(C57,C55*C58))
A60: Equity attributable to ordinary shareholders | C60: =C55+C59
A61: Fair value per share (USD) | C61: =C60/Assumptions!$C$6/1000
A62: Fair value per share (AED) | C62: =C61*Assumptions!$C$7
A63: COST OF EQUITY — BUILT HERE, NOT ASSUMED
A64: Observed government bond yield (dirham tranche, January 2031) | C64: =Assumptions!$C$12
A65: Less sovereign default spread — country risk enters once, through the premium | C65: =Assumptions!$C$13
A66: Normalised risk-free rate | C66: =C64-C65
A67: Beta — own-stock weekly regression against its local index | C67: =Assumptions!$C$14
A68: Equity risk premium | C68: =Assumptions!$C$19
A69: Cost of equity | C69: =C66+C67*C68
A71: COST OF DEBT — THREE CONSTRUCTIONS, AVERAGED HERE
A72: Secured overnight financing rate | C72: =Assumptions!$C$24
A73: Parent revolving credit facility margin | C73: =Assumptions!$C$25
A74: METHOD 1 — parent revolving facility rate drawn January 2026 | C74: =C72+C73
A75: Third-party bank loans — low end of the disclosed range | C75: =Assumptions!$C$26
A76: Third-party bank loans — high end of the disclosed range | C76: =Assumptions!$C$27
A77: Bank-loan midpoint | C77: =(C75+C76)/2
A78: Other third-party borrowings — low end of the disclosed range | C78: =Assumptions!$C$28
A79: Other third-party borrowings — high end of the disclosed range | C79: =Assumptions!$C$29
A80: Other-borrowings midpoint | C80: =(C78+C79)/2
A81: Third-party blended rate — the two midpoints averaged | C81: =(C77+C80)/2
A82: Lease interest charged in 2025 (USD 000) | C82: =Assumptions!$C$30
A83: Lease liabilities, opening balance (USD 000) | C83: =Assumptions!$C$31
A84: Lease liabilities, closing balance (USD 000) | C84: =Assumptions!$C$32
A85: Implied lease borrowing rate — interest over the average balance | C85: =C82/((C83+C84)/2)
A86: Shareholder loan at 31 March 2026 (USD 000) | C86: =Assumptions!$C$33
A87: Third-party borrowings at 31 March 2026 (USD 000) | C87: =Assumptions!$C$34
A88: Lease liabilities at 31 March 2026 (USD 000) | C88: =Assumptions!$C$35
A89: Borrowings at 31 March 2026 (USD 000) | C89: =C86+C87+C88
A90: METHOD 2 — the instruments actually outstanding, weighted by balance | C90: =(C86*C74+C87*C81+C88*C85)/C89
A91: METHOD 3 — the disclosed third-party bank-loan midpoint | C91: =C77
A92: Cost of debt — the three constructions averaged. This is a simple average of three independent readings, NOT a figure weighted by what is drawn; the weighted one is the line below | C92: =AVERAGE(C74,C90,C91)
A93: Memorandum — cost of debt on the balance-weighted construction alone (method 2), the only one of the three that is weighted by the instruments actually outstanding | C93: =C90
A94: Statutory corporate tax rate | C94: =Assumptions!$C$21
A95: Cost of debt after tax | C95: =C92*(1-C94)
A96: WEIGHTS AND THE COST OF CAPITAL — EQUITY, DEBT AND THE PERPETUAL SECURITIES
A97: Market capitalisation (USD 000) | C97: =Assumptions!$C$5/Assumptions!$C$7*Assumptions!$C$6*1000
A98: Borrowings at 31 March 2026 (USD 000) | C98: =C89
A99: Perpetual capital securities at carrying value (USD 000) | C99: =Assumptions!$C$152
A100: Total capital (USD 000) | C100: =C97+C98+C99
A101: Equity weight — market capitalisation over the total | C101: =C97/C100
A102: Debt weight | C102: =C98/C100
A103: Perpetual capital securities weight | C103: =C99/C100
A104: Cost of the perpetual capital securities — their own coupon. It is not tax-deductible, because it is an equity distribution, so it is not taxed down | C104: =C72+Assumptions!$C$153
...

Sheet Income Statement
A1: Income statement — three years audited, five years forecast
A2: USD thousand, consolidated. History is the audited record; every forecast line is a formula.
A4: USD 000 | B4: FY2023 | C4: FY2024 | D4: FY2025 | E4: FY2026E | F4: FY2027E | G4: FY2028E | H4: FY2029E | I4: FY2030E
A5: Revenue | B5: =Segments!B12 | C5: =Segments!C12 | D5: =Segments!D12 | E5: =DCF!B5 | F5: =DCF!C5 | G5: =DCF!D5 | H5: =DCF!E5 | I5: =DCF!F5
A6: Direct costs | B6: -2003225 | C6: -2608784 | D6: -3908236 | E6: - | F6: - | G6: - | H6: - | I6: -
A7: Gross profit | B7: =B5+B6 | C7: =C5+C6 | D7: =D5+D6 | E7: - | F7: - | G7: - | H7: - | I7: -
A8: General and administrative expenses | B8: -146436 | C8: -141522 | D8: -204983 | E8: - | F8: - | G8: - | H8: - | I8: -
A9: Expected credit losses | B9: -2672 | C9: 2649 | D9: -9590 | E9: - | F9: - | G9: - | H9: - | I9: -
A10: Other income | B10: 10865 | C10: 19896 | D10: 50459 | E10: - | F10: - | G10: - | H10: - | I10: -
A11: Other expenses | B11: 0 | C11: -4310 | D11: 0 | E11: - | F11: - | G11: - | H11: - | I11: -
A12: Operating profit | B12: =B7+B8+B9+B10+B11 | C12: =C7+C8+C9+C10+C11 | D12: =D7+D8+D9+D10+D11 | E12: =E14-E13 | F12: =F14-F13 | G12: =G14-G13 | H12: =H14-H13 | I12: =I14-I13
A13: Depreciation and amortisation | B13: 248526 | C13: 317339 | D13: 524809 | E13: ='Balance Sheet'!B39 | F13: ='Balance Sheet'!C39 | G13: ='Balance Sheet'!D39 | H13: ='Balance Sheet'!E39 | I13: ='Balance Sheet'!F39
A14: EBITDA (operating) | B14: =B12+B13 | C14: =C12+C13 | D14: =D12+D13 | E14: =DCF!B6 | F14: =DCF!C6 | G14: =DCF!D6 | H14: =DCF!E6 | I14: =DCF!F6
A15: Add share of joint ventures and one-off gains carried in reported EBITDA | B15: =B19+B20+B21 | C15: =C19+C20+C21 | D15: =D19+D20+D21 | E15: - | F15: - | G15: - | H15: - | I15: -
A16: EBITDA as reported | B16: =B14+B15 | C16: =C14+C15 | D16: =D14+D15 | E16: =E14 | F16: =F14 | G16: =G14 | H16: =H14 | I16: =I14
A17: Total operating costs | B17: =B5-B14 | C17: =C5-C14 | D17: =D5-D14 | E17: =E5-E14 | F17: =F5-F14 | G17: =G5-G14 | H17: =H5-H14 | I17: =I5-I14
A18: EBITDA margin (operating) | B18: =B14/B5 | C18: =C14/C5 | D18: =D14/D5 | E18: =E14/E5 | F18: =F14/F5 | G18: =G14/G5 | H18: =H14/H5 | I18: =I14/I5
A19: Share of joint ventures and associates | B19: 14071 | C19: 14198 | D19: 37392 | E19: - | F19: - | G19: - | H19: - | I19: -
A20: Gain on bargain purchase | B20: 0 | C20: 0 | D20: 12056 | E20: - | F20: - | G20: - | H20: - | I20: -
A21: Loss on the previously held interest | B21: 0 | C21: 0 | D21: -3398 | E21: - | F21: - | G21: - | H21: - | I21: -
A22: Finance income | B22: 9785 | C22: 15594 | D22: 18959 | E22: =Assumptions!$C$24*Assumptions!$C$159 | F22: =Assumptions!$C$24*Assumptions!$C$159 | G22: =Assumptions!$C$24*Assumptions!$C$159 | H22: =Assumptions!$C$24*Assumptions!$C$159 | I22: =Assumptions!$C$24*Assumptions!$C$159
A23: Finance costs | B23: -15098 | C23: -18034 | D23: -87143 | E23: =-DCF!$C$92*'Balance Sheet'!B54 | F23: =-DCF!$C$92*'Balance Sheet'!C54 | G23: =-DCF!$C$92*'Balance Sheet'!D54 | H23: =-DCF!$C$92*'Balance Sheet'!E54 | I23: =-DCF!$C$92*'Balance Sheet'!F54
A24: Profit before tax | B24: =B12+B19+B20+B21+B22+B23 | C24: =C12+C19+C20+C21+C22+C23 | D24: =D12+D19+D20+D21+D22+D23 | E24: =E12+E22+E23 | F24: =F12+F22+F23 | G24: =G12+G22+G23 | H24: =H12+H22+H23 | I24: =I12+I22+I23
A25: Income tax | B25: -2283 | C25: -72847 | D25: -58781 | E25: =-E24*DCF!B36 | F25: =-F24*DCF!C36 | G25: =-G24*DCF!D36 | H25: =-H24*DCF!E36 | I25: =-I24*DCF!F36
A26: Profit for the year | B26: =B24+B25 | C26: =C24+C25 | D26: =D24+D25 | E26: =E24+E25 | F26: =F24+F25 | G26: =G24+G25 | H26: =H24+H25 | I26: =I24+I25
A27: Non-controlling interests | B27: 0 | C27: 0 | D27: -24306 | E27: =-E26*Assumptions!$C$156 | F27: =-F26*Assumptions!$C$156 | G27: =-G26*Assumptions!$C$156 | H27: =-H26*Assumptions!$C$156 | I27: =-I26*Assumptions!$C$156
A28: Profit attributable to shareholders | B28: =B26+B27 | C28: =C26+C27 | D28: =D26+D27 | E28: =E26+E27 | F28: =F26+F27 | G28: =G26+G27 | H28: =H26+H27 | I28: =I26+I27
A29: Perpetual capital securities coupon | B29: 0 | C29: 0 | D29: -61333 | E29: =-Assumptions!$C$152*(Assumptions!$C$24+Assumptions!$C$153) | F29: =-Assumptions!$C$152*(Assumptions!$C$24+Assumptions!$C$153) | G29: =-Assumptions!$C$152*(Assumptions!$C$24+Assumptions!$C$153) | H29: =-Assumptions!$C$152*(Assumptions!$C$24+Assumptions!$C$153) | I29: =-Assumptions!$C$152*(Assumptions!$C$24+Assumptions!$C$153)
A30: Earnings attributable to ordinary shareholders, AFTER the perpetual capital securities coupon | B30: =B28+B29 | C30: =C28+C29 | D30: =D28+D29 | E30: =E28+E29 | F30: =F28+F29 | G30: =G28+G29 | H30: =H28+H29 | I30: =I28+I29
A31: Earnings per ordinary share, AFTER the perpetual coupon (USD) — the coupon ranks ahead of the ordinary shares, so it comes out of the numerator | B31: =B30/Assumptions!$C$6/1000 | C31: =C30/Assumptions!$C$6/1000 | D31: =D30/Assumptions!$C$6/1000 | E31: =E30/Assumptions!$C$6/1000 | F31: =F30/Assumptions!$C$6/1000 | G31: =G30/Assumptions!$C$6/1000 | H31: =H30/Assumptions!$C$6/1000 | I31: =I30/Assumptions!$C$6/1000
A32: Earnings per ordinary share, AFTER the perpetual coupon (AED) | B32: =B31*Assumptions!$C$7 | C32: =C31*Assumptions!$C$7 | D32: =D31*Assumptions!$C$7 | E32: =E31*Assumptions!$C$7 | F32: =F31*Assumptions!$C$7 | G32: =G31*Assumptions!$C$7 | H32: =H31*Assumptions!$C$7 | I32: =I31*Assumptions!$C$7
A33: Memorandum — earnings per share BEFORE the perpetual coupon (USD), on attributable profit; shown so the two are never confused | B33: =B28/Assumptions!$C$6/1000 | C33: =C28/Assumptions!$C$6/1000 | D33: =D28/Assumptions!$C$6/1000 | E33: =E28/Assumptions!$C$6/1000 | F33: =F28/Assumptions!$C$6/1000 | G33: =G28/Assumptions!$C$6/1000 | H33: =H28/Assumptions!$C$6/1000 | I33: =I28/Assumptions!$C$6/1000
A35: Every FY2023-25 line above is the audited figure. In the forecast the company's own disclosure-only lines — direct costs, gross profit, the general and administrative split, the share of joint ventures and the two 2025 acquisition items — are not projected, because the forecast is built at the business-unit level on earnings before depreciation rather than on a cost-line split the filings do not support forward. The finance charge is computed on gross borrowings, which move with the net-debt roll, so profit is struck after interest and differs from the pre-financing discounted-cash-flow waterfall by construction.

Sheet Balance Sheet
A1: Balance sheet — condensed, and the rolls that drive it
A2: USD thousand, consolidated. Every FY2023-25 line is the audited closing figure; every forecast line is rolled forward from a driver.
A4: USD 000 | B4: FY2023 | C4: FY2024 | D4: FY2025 | E4: FY2026E | F4: FY2027E | G4: FY2028E | H4: FY2029E | I4: FY2030E
A5: Property, plant and equipment | B5: 3806543 | C5: 4543335 | D5: 6884178 | E5: =B37 | F5: =C37 | G5: =D37 | H5: =E37 | I5: =F37
A6: Right-of-use assets | B6: 148146 | C6: 161691 | D6: 225292 | E6: - | F6: - | G6: - | H6: - | I6: -
A7: Intangible assets | B7: 11440 | C7: 11078 | D7: 19434 | E7: =Assumptions!$C$160 | F7: =Assumptions!$C$160 | G7: =Assumptions!$C$160 | H7: =Assumptions!$C$160 | I7: =Assumptions!$C$160
A8: Goodwill | B8: 51368 | C8: 51368 | D8: 51368 | E8: =Assumptions!$C$161 | F8: =Assumptions!$C$161 | G8: =Assumptions!$C$161 | H8: =Assumptions!$C$161 | I8: =Assumptions!$C$161
A9: Investment properties | B9: 95269 | C9: 92501 | D9: 89154 | E9: - | F9: - | G9: - | H9: - | I9: -
A10: Investments in joint ventures and associates | B10: 76712 | C10: 267775 | D10: 577769 | E10: =Assumptions!$C$157 | F10: =Assumptions!$C$157 | G10: =Assumptions!$C$157 | H10: =Assumptions!$C$157 | I10: =Assumptions!$C$157
A11: Inventories | B11: 120720 | C11: 132687 | D11: 137108 | E11: =B47 | F11: =C47 | G11: =D47 | H11: =E47 | I11: =F47
A12: Trade and other receivables, including amounts due from related parties | B12: 1131167 | C12: 1284889 | D12: 1489668 | E12: =B46 | F12: =C46 | G12: =D46 | H12: =E46 | I12: =F46
A13: Cash and cash equivalents | B13: 215709 | C13: 198919 | D13: 337794 | E13: =Assumptions!$C$159 | F13: =Assumptions!$C$159 | G13: =Assumptions!$C$159 | H13: =Assumptions!$C$159 | I13: =Assumptions!$C$159
A14: Total assets | B14: 5745668 | C14: 7003326 | D14: 9965153 | E14: - | F14: - | G14: - | H14: - | I14: -
A15: Trade and other payables, including amounts due to related parties | B15: 962048 | C15: 1227680 | D15: 1280361 | E15: =B48 | F15: =C48 | G15: =D48 | H15: =E48 | I15: =F48
A16: Net working capital | B16: =B12+B11-B15 | C16: =C12+C11-C15 | D16: =D12+D11-D15 | E16: =E12+E11-E15 | F16: =F12+F11-F15 | G16: =G12+G11-G15 | H16: =H12+H11-H15 | I16: =I12+I11-I15
A17: Gross borrowings | B17: 289554 | C17: 739301 | D17: 1031879 | E17: =B54 | F17: =C54 | G17: =D54 | H17: =E54 | I17: =F54
A18: Net debt | B18: =B17-B13 | C18: =C17-C13 | D18: =D17-D13 | E18: =B62 | F18: =C62 | G18: =D62 | H18: =E62 | I18: =F62
A19: Perpetual capital securities | B19: 0 | C19: 0 | D19: 1978619 | E19: =Assumptions!$C$152 | F19: =Assumptions!$C$152 | G19: =Assumptions!$C$152 | H19: =Assumptions!$C$152 | I19: =Assumptions!$C$152
A20: Non-controlling interests | B20: 0 | C20: 0 | D20: 264512 | E20: =Assumptions!$C$154 | F20: =Assumptions!$C$154 | G20: =Assumptions!$C$154 | H20: =Assumptions!$C$154 | I20: =Assumptions!$C$154
A21: Equity attributable to shareholders | B21: 4405982 | C21: 4894627 | D21: 4981987 | E21: =B69 | F21: =C69 | G21: =D69 | H21: =E69 | I21: =F69
A22: Total equity | B22: =B21+B19+B20 | C22: =C21+C19+C20 | D22: =D21+D19+D20 | E22: =E21+E19+E20 | F22: =F21+F19+F20 | G22: =G21+G19+G20 | H22: =H21+H19+H20 | I22: =I21+I19+I20
A23: Net debt / EBITDA | B23: =B18/'Income Statement'!B14 | C23: =C18/'Income Statement'!C14 | D23: =D18/'Income Statement'!D14 | E23: =E18/'Income Statement'!E14 | F23: =F18/'Income Statement'!F14 | G23: =G18/'Income Statement'!G14 | H23: =H18/'Income Statement'!H14 | I23: =I18/'Income Statement'!I14
A24: Book value per share (USD) | B24: =B21/Assumptions!$C$6/1000 | C24: =C21/Assumptions!$C$6/1000 | D24: =D21/Assumptions!$C$6/1000 | E24: =E21/Assumptions!$C$6/1000 | F24: =F21/Assumptions!$C$6/1000 | G24: =G21/Assumptions!$C$6/1000 | H24: =H21/Assumptions!$C$6/1000 | I24: =I21/Assumptions!$C$6/1000
A25: Book value per share (AED) | B25: =B24*Assumptions!$C$7 | C25: =C24*Assumptions!$C$7 | D25: =D24*Assumptions!$C$7 | E25: =E24*Assumptions!$C$7 | F25: =F24*Assumptions!$C$7 | G25: =G24*Assumptions!$C$7 | H25: =H24*Assumptions!$C$7 | I25: =I24*Assumptions!$C$7
A26: Invested capital | B26: =B5+B16+B7+B8 | C26: =C5+C16+C7+C8 | D26: =D5+D16+D7+D8 | E26: =E5+E16+E7+E8 | F26: =F5+F16+F7+F8 | G26: =G5+G16+G7+G8 | H26: =H5+H16+H7+H8 | I26: =I5+I16+I7+I8
A27: Return on invested capital | B27: - | C27: - | D27: - | E27: =DCF!B11/E26 | F27: =DCF!C11/F26 | G27: =DCF!D11/G26 | H27: =DCF!E11/H26 | I27: =DCF!F11/I26
A28: Return on equity (profit over average equity) | B28: - | C28: ='Income Statement'!C28/((B21+C21)/2) | D28: ='Income Statement'!D28/((C21+D21)/2) | E28: ='Income Statement'!E28/((Assumptions!$C$158+E21)/2) | F28: ='Income Statement'!F28/((E21+F21)/2) | G28: ='Income Statement'!G28/((F21+G21)/2) | H28: ='Income Statement'!H28/((G21+H21)/2) | I28: ='Income Statement'!I28/((H21+I21)/2)
A30: THE PROPERTY, PLANT AND EQUIPMENT ROLL | B30: FY2026E | C30: FY2027E | D30: FY2028E | E30: FY2029E | F30: FY2030E
A31: Opening property, plant and equipment | B31: =D5 | C31: =B37 | D31: =C37 | E31: =D37 | F31: =E37
A32: Capital expenditure | B32: =Assumptions!$B$120 | C32: =Assumptions!$C$120 | D32: =Assumptions!$D$120 | E32: =Assumptions!$E$120 | F32: =Assumptions!$F$120
A33: Vessels acquired in the purchase announced 7 August 2026 — the same price that is carried in net debt below | B33: =Assumptions!$C$82 | C33: =0 | D33: =0 | E33: =0 | F33: =0
A34: Depreciation rate on property, plant and equipment | B34: =Assumptions!$C$121 | C34: =Assumptions!$C$121 | D34: =Assumptions!$C$121 | E34: =Assumptions!$C$121 | F34: =Assumptions!$C$121
A35: First-pass depreciation, on the opening balance plus the full additions | B35: =B34*(B31+(B31+B32+B33))/2 | C35: =C34*(C31+(C31+C32+C33))/2 | D35: =D34*(D31+(D31+D32+D33))/2 | E35: =E34*(E31+(E31+E32+E33))/2 | F35: =F34*(F31+(F31+F32+F33))/2
A36: Depreciation on property, plant and equipment — on the average of opening and closing | B36: =B34*(B31+(B31+B32+B33-B35))/2 | C36: =C34*(C31+(C31+C32+C33-C35))/2 | D36: =D34*(D31+(D31+D32+D33-D35))/2 | E36: =E34*(E31+(E31+E32+E33-E35))/2 | F36: =F34*(F31+(F31+F32+F33-F35))/2
A37: Closing property, plant and equipment | B37: =B31+B32+B33-B36 | C37: =C31+C32+C33-C36 | D37: =D31+D32+D33-D36 | E37: =E31+E32+E33-E36 | F37: =F31+F32+F33-F36
A38: Other depreciation and amortisation, escalated | B38: =Assumptions!$C$122*(1+Assumptions!$C$92)^1 | C38: =Assumptions!$C$122*(1+Assumptions!$C$92)^2 | D38: =Assumptions!$C$122*(1+Assumptions!$C$92)^3 | E38: =Assumptions!$C$122*(1+Assumptions!$C$92)^4 | F38: =Assumptions!$C$122*(1+Assumptions!$C$92)^5
A39: Total depreciation and amortisation | B39: =B36+B38 | C39: =C36+C38 | D39: =D36+D38 | E39: =E36+E38 | F39: =F36+F38
A40: THE WORKING-CAPITAL ROLL FROM THE DAYS RATIOS | B40: FY2026E | C40: FY2027E | D40: FY2028E | E40: FY2029E | F40: FY2030E
A41: Revenue | B41: =DCF!B5 | C41: =DCF!C5 | D41: =DCF!D5 | E41: =DCF!E5 | F41: =DCF!F5
A42: Total operating costs | B42: =B41-DCF!B6 | C42: =C41-DCF!C6 | D42: =D41-DCF!D6 | E42: =E41-DCF!E6 | F42: =F41-DCF!F6
A43: Days sales outstanding | B43: =Assumptions!$C$126 | C43: =Assumptions!$C$126 | D43: =Assumptions!$C$126 | E43: =Assumptions!$C$126 | F43: =Assumptions!$C$126
A44: Days inventory outstanding | B44: =Assumptions!$C$127 | C44: =Assumptions!$C$127 | D44: =Assumptions!$C$127 | E44: =Assumptions!$C$127 | F44: =Assumptions!$C$127
A45: Days payable outstanding | B45: =Assumptions!$C$128 | C45: =Assumptions!$C$128 | D45: =Assumptions!$C$128 | E45: =Assumptions!$C$128 | F45: =Assumptions!$C$128
A46: Trade and other receivables — revenue x days / 365 | B46: =B41*B43/365 | C46: =C41*C43/365 | D46: =D41*D43/365 | E46: =E41*E43/365 | F46: =F41*F43/365
A47: Inventories — operating cost x days / 365 | B47: =B42*B44/365 | C47: =C42*C44/365 | D47: =D42*D44/365 | E47: =E42*E44/365 | F47: =F42*F44/365
A48: Trade and other payables — operating cost x days / 365 | B48: =B42*B45/365 | C48: =C42*C45/365 | D48: =D42*D45/365 | E48: =E42*E45/365 | F48: =F42*F45/365
A49: Net working capital | B49: =B46+B47-B48 | C49: =C46+C47-C48 | D49: =D46+D47-D48 | E49: =E46+E47-E48 | F49: =F46+F47-F48
A50: Change in net working capital | B50: =B49-Assumptions!$C$129 | C50: =C49-B49 | D50: =D49-C49 | E50: =E49-D49 | F50: =F49-E49
A52: THE NET-DEBT ROLL | B52: FY2026E | C52: FY2027E | D52: FY2028E | E52: FY2029E | F52: FY2030E
A53: Opening net debt — including the deferred consideration and the price of the vessels bought on 7 August 2026 | B53: =Assumptions!$C$150+Assumptions!$C$151+Assumptions!$C$82 | C53: =B62 | D53: =C62 | E53: =D62 | F53: =E62
A54: Gross borrowings — opening net debt plus the cash held | B54: =B53+Assumptions!$C$159 | C54: =C53+Assumptions!$C$159 | D54: =D53+Assumptions!$C$159 | E54: =E53+Assumptions!$C$159 | F54: =F53+Assumptions!$C$159
A55: Interest charge on gross borrowings | B55: =DCF!$C$92*B54 | C55: =DCF!$C$92*C54 | D55: =DCF!$C$92*D54 | E55: =DCF!$C$92*E54 | F55: =DCF!$C$92*F54
A56: Free cash flow to the firm | B56: =DCF!B15 | C56: =DCF!C15 | D56: =DCF!D15 | E56: =DCF!E15 | F56: =DCF!F15
A57: Less interest after tax | B57: =-B55*(1-Assumptions!$C$21) | C57: =-C55*(1-Assumptions!$C$21) | D57: =-D55*(1-Assumptions!$C$21) | E57: =-E55*(1-Assumptions!$C$21) | F57: =-F55*(1-Assumptions!$C$21)
A58: Plus finance income after tax | B58: =Assumptions!$C$24*Assumptions!$C$159*(1-Assumptions!$C$21) | C58: =Assumptions!$C$24*Assumptions!$C$159*(1-Assumptions!$C$21) | D58: =Assumptions!$C$24*Assumptions!$C$159*(1-Assumptions!$C$21) | E58: =Assumptions!$C$24*Assumptions!$C$159*(1-Assumptions!$C$21) | F58: =Assumptions!$C$24*Assumptions!$C$159*(1-Assumptions!$C$21)
A59: Less perpetual capital securities coupon | B59: =-Assumptions!$C$152*(Assumptions!$C$24+Assumptions!$C$153) | C59: =-Assumptions!$C$152*(Assumptions!$C$24+Assumptions!$C$153) | D59: =-Assumptions!$C$152*(Assumptions!$C$24+Assumptions!$C$153) | E59: =-Assumptions!$C$152*(Assumptions!$C$24+Assumptions!$C$153) | F59: =-Assumptions!$C$152*(Assumptions!$C$24+Assumptions!$C$153)
A60: Free cash flow to equity | B60: =B56+B57+B58+B59 | C60: =C56+C57+C58+C59 | D60: =D56+D57+D58+D59 | E60: =E56+E57+E58+E59 | F60: =F56+F57+F58+F59
A61: Less ordinary dividends | B61: =-Assumptions!$C$162*(1+Assumptions!$C$163)^0 | C61: =-Assumptions!$C$162*(1+Assumptions!$C$163)^1 | D61: =-Assumptions!$C$162*(1+Assumptions!$C$163)^2 | E61: =-Assumptions!$C$162*(1+Assumptions!$C$163)^3 | F61: =-Assumptions!$C$162*(1+Assumptions!$C$163)^4
A62: Closing net debt | B62: =B53-B60-B61 | C62: =C53-C60-C61 | D62: =D53-D60-D61 | E62: =E53-E60-E61 | F62: =F53-F60-F61
A64: THE EQUITY ROLL | B64: FY2026E | C64: FY2027E | D64: FY2028E | E64: FY2029E | F64: FY2030E
A65: Opening equity attributable to shareholders | B65: =Assumptions!$C$158 | C65: =B69 | D65: =C69 | E65: =D69 | F65: =E69
A66: Add profit attributable to shareholders | B66: ='Income Statement'!E28 | C66: ='Income Statement'!F28 | D66: ='Income Statement'!G28 | E66: ='Income Statement'!H28 | F66: ='Income Statement'!I28
A67: Less ordinary dividends | B67: =B61 | C67: =C61 | D67: =D61 | E67: =E61 | F67: =F61
A68: Less perpetual capital securities coupon | B68: =B59 | C68: =C59 | D68: =D59 | E68: =E59 | F68: =F59
A69: Closing equity attributable to shareholders | B69: =B65+B66+B67+B68 | C69: =C65+C66+C67+C68 | D69: =D65+D66+D67+D68 | E69: =E65+E66+E67+E68 | F69: =F65+F66+F67+F68
A70: Ordinary dividend per share (USD) | B70: =-B67/Assumptions!$C$6/1000 | C70: =-C67/Assumptions!$C$6/1000 | D70: =-D67/Assumptions!$C$6/1000 | E70: =-E67/Assumptions!$C$6/1000 | F70: =-F67/Assumptions!$C$6/1000
A72: The condensed layout above does not foot to zero: right-of-use assets, investment properties, provisions, deferred tax and the other liabilities not shown separately are omitted from the forecast columns because they are not driven by anything in this model. The audited FY2023-25 columns carry every line as reported.

Sheet Cash Flow
A1: Cash flow — the audited record and the forecast waterfall
A2: USD thousand.
A4: USD 000 | B4: FY2023 | C4: FY2024 | D4: FY2025 | E4: FY2026E | F4: FY2027E | G4: FY2028E | H4: FY2029E | I4: FY2030E
A5: EBITDA (operating) | B5: ='Income Statement'!B14 | C5: ='Income Statement'!C14 | D5: ='Income Statement'!D14 | E5: ='Income Statement'!E14 | F5: ='Income Statement'!F14 | G5: ='Income Statement'!G14 | H5: ='Income Statement'!H14 | I5: ='Income Statement'!I14
A6: Operating cash flow, as reported | B6: 822648 | C6: 1068865 | D6: 1370729 | E6: - | F6: - | G6: - | H6: - | I6: -
A7: Capital expenditure | B7: -774015 | C7: -810851 | D7: -1106529 | E7: =DCF!B13 | F7: =DCF!C13 | G7: =DCF!D13 | H7: =DCF!E13 | I7: =DCF!F13
A8: Free cash flow, as reported | B8: =B6+B7 | C8: =C6+C7 | D8: =D6+D7 | E8: - | F8: - | G8: - | H8: - | I8: -
A10: THE FORECAST WATERFALL — LINKED TO THE DISCOUNTED-CASH-FLOW SHEET | E10: FY2026E | F10: FY2027E | G10: FY2028E | H10: FY2029E | I10: FY2030E
A11: NOPAT | B11: - | C11: - | D11: - | E11: =DCF!B11 | F11: =DCF!C11 | G11: =DCF!D11 | H11: =DCF!E11 | I11: =DCF!F11
A12: Add back depreciation and amortisation | B12: - | C12: - | D12: - | E12: =DCF!B12 | F12: =DCF!C12 | G12: =DCF!D12 | H12: =DCF!E12 | I12: =DCF!F12
A13: Less capital expenditure | B13: - | C13: - | D13: - | E13: =DCF!B13 | F13: =DCF!C13 | G13: =DCF!D13 | H13: =DCF!E13 | I13: =DCF!F13
A14: Less change in working capital | B14: - | C14: - | D14: - | E14: =DCF!B14 | F14: =DCF!C14 | G14: =DCF!D14 | H14: =DCF!E14 | I14: =DCF!F14
A15: Free cash flow to the firm | B15: - | C15: - | D15: - | E15: =E11+E12+E13+E14 | F15: =F11+F12+F13+F14 | G15: =G11+G12+G13+G14 | H15: =H11+H12+H13+H14 | I15: =I11+I12+I13+I14
A16: Less interest after tax | B16: - | C16: - | D16: - | E16: ='Balance Sheet'!B57 | F16: ='Balance Sheet'!C57 | G16: ='Balance Sheet'!D57 | H16: ='Balance Sheet'!E57 | I16: ='Balance Sheet'!F57
A17: Plus finance income after tax | B17: - | C17: - | D17: - | E17: ='Balance Sheet'!B58 | F17: ='Balance Sheet'!C58 | G17: ='Balance Sheet'!D58 | H17: ='Balance Sheet'!E58 | I17: ='Balance Sheet'!F58
A18: Less perpetual capital securities coupon | B18: - | C18: - | D18: - | E18: ='Balance Sheet'!B59 | F18: ='Balance Sheet'!C59 | G18: ='Balance Sheet'!D59 | H18: ='Balance Sheet'!E59 | I18: ='Balance Sheet'!F59
A19: Free cash flow to equity | B19: - | C19: - | D19: - | E19: =E15+E16+E17+E18 | F19: =F15+F16+F17+F18 | G19: =G15+G16+G17+G18 | H19: =H15+H16+H17+H18 | I19: =I15+I16+I17+I18
A20: Less ordinary dividends | B20: - | C20: - | D20: - | E20: ='Balance Sheet'!B61 | F20: ='Balance Sheet'!C61 | G20: ='Balance Sheet'!D61 | H20: ='Balance Sheet'!E61 | I20: ='Balance Sheet'!F61
A21: Movement in net debt (a fall is a negative) | B21: - | C21: - | D21: - | E21: =-E19-E20 | F21: =-F19-F20 | G21: =-G19-G20 | H21: =-H19-H20 | I21: =-I19-I20
A22: Cash conversion — free cash flow to the firm over EBITDA | B22: - | C22: - | D22: - | E22: =E15/E5 | F22: =F15/F5 | G22: =G15/G5 | H22: =H15/H5 | I22: =I15/I5
A24: Cash conversion is the crux of an asset-heavy fleet owner: in 2026 the newbuild programme absorbs more than the whole of the operating cash the business generates, and only as that programme delivers does free cash flow to the firm turn materially positive.

Sheet Summary Financials
A1: Summary financials — the eight-year picture
A2: USD thousand unless stated. Every cell on this sheet is a link or a ratio; nothing is typed twice.
A4: USD 000 | B4: FY2023 | C4: FY2024 | D4: FY2025 | E4: FY2026E | F4: FY2027E | G4: FY2028E | H4: FY2029E | I4: FY2030E
A5: Revenue | B5: ='Income Statement'!B5 | C5: ='Income Statement'!C5 | D5: ='Income Statement'!D5 | E5: ='Income Statement'!E5 | F5: ='Income Statement'!F5 | G5: ='Income Statement'!G5 | H5: ='Income Statement'!H5 | I5: ='Income Statement'!I5
A6: Revenue growth | B6: - | C6: =C5/B5-1 | D6: =D5/C5-1 | E6: =E5/D5-1 | F6: =F5/E5-1 | G6: =G5/F5-1 | H6: =H5/G5-1 | I6: =I5/H5-1
A7: EBITDA (operating) | B7: ='Income Statement'!B14 | C7: ='Income Statement'!C14 | D7: ='Income Statement'!D14 | E7: ='Income Statement'!E14 | F7: ='Income Statement'!F14 | G7: ='Income Statement'!G14 | H7: ='Income Statement'!H14 | I7: ='Income Statement'!I14
A8: EBITDA margin | B8: ='Income Statement'!B18 | C8: ='Income Statement'!C18 | D8: ='Income Statement'!D18 | E8: ='Income Statement'!E18 | F8: ='Income Statement'!F18 | G8: ='Income Statement'!G18 | H8: ='Income Statement'!H18 | I8: ='Income Statement'!I18
A9: EBIT | B9: ='Income Statement'!B12 | C9: ='Income Statement'!C12 | D9: ='Income Statement'!D12 | E9: ='Income Statement'!E12 | F9: ='Income Statement'!F12 | G9: ='Income Statement'!G12 | H9: ='Income Statement'!H12 | I9: ='Income Statement'!I12
A10: Depreciation and amortisation | B10: ='Income Statement'!B13 | C10: ='Income Statement'!C13 | D10: ='Income Statement'!D13 | E10: ='Income Statement'!E13 | F10: ='Income Statement'!F13 | G10: ='Income Statement'!G13 | H10: ='Income Statement'!H13 | I10: ='Income Statement'!I13
A11: Profit attributable to shareholders | B11: ='Income Statement'!B28 | C11: ='Income Statement'!C28 | D11: ='Income Statement'!D28 | E11: ='Income Statement'!E28 | F11: ='Income Statement'!F28 | G11: ='Income Statement'!G28 | H11: ='Income Statement'!H28 | I11: ='Income Statement'!I28
A12: Earnings attributable to ordinary shareholders | B12: ='Income Statement'!B30 | C12: ='Income Statement'!C30 | D12: ='Income Statement'!D30 | E12: ='Income Statement'!E30 | F12: ='Income Statement'!F30 | G12: ='Income Statement'!G30 | H12: ='Income Statement'!H30 | I12: ='Income Statement'!I30
A13: Earnings per ordinary share (AED) | B13: ='Income Statement'!B32 | C13: ='Income Statement'!C32 | D13: ='Income Statement'!D32 | E13: ='Income Statement'!E32 | F13: ='Income Statement'!F32 | G13: ='Income Statement'!G32 | H13: ='Income Statement'!H32 | I13: ='Income Statement'!I32
A14: Free cash flow to the firm | B14: - | C14: - | D14: - | E14: ='Cash Flow'!E15 | F14: ='Cash Flow'!F15 | G14: ='Cash Flow'!G15 | H14: ='Cash Flow'!H15 | I14: ='Cash Flow'!I15
A15: Capital expenditure | B15: ='Cash Flow'!B7 | C15: ='Cash Flow'!C7 | D15: ='Cash Flow'!D7 | E15: ='Cash Flow'!E7 | F15: ='Cash Flow'!F7 | G15: ='Cash Flow'!G7 | H15: ='Cash Flow'!H7 | I15: ='Cash Flow'!I7
A16: Capital expenditure / revenue | B16: =-B15/B5 | C16: =-C15/C5 | D16: =-D15/D5 | E16: =-E15/E5 | F16: =-F15/F5 | G16: =-G15/G5 | H16: =-H15/H5 | I16: =-I15/I5
A17: Net working capital | B17: ='Balance Sheet'!B16 | C17: ='Balance Sheet'!C16 | D17: ='Balance Sheet'!D16 | E17: ='Balance Sheet'!E16 | F17: ='Balance Sheet'!F16 | G17: ='Balance Sheet'!G16 | H17: ='Balance Sheet'!H16 | I17: ='Balance Sheet'!I16
A18: Net working capital / revenue | B18: =B17/B5 | C18: =C17/C5 | D18: =D17/D5 | E18: =E17/E5 | F18: =F17/F5 | G18: =G17/G5 | H18: =H17/H5 | I18: =I17/I5
A19: Net debt | B19: ='Balance Sheet'!B18 | C19: ='Balance Sheet'!C18 | D19: ='Balance Sheet'!D18 | E19: ='Balance Sheet'!E18 | F19: ='Balance Sheet'!F18 | G19: ='Balance Sheet'!G18 | H19: ='Balance Sheet'!H18 | I19: ='Balance Sheet'!I18
A20: Net debt / EBITDA | B20: ='Balance Sheet'!B23 | C20: ='Balance Sheet'!C23 | D20: ='Balance Sheet'!D23 | E20: ='Balance Sheet'!E23 | F20: ='Balance Sheet'!F23 | G20: ='Balance Sheet'!G23 | H20: ='Balance Sheet'!H23 | I20: ='Balance Sheet'!I23
A21: Equity attributable to shareholders | B21: ='Balance Sheet'!B21 | C21: ='Balance Sheet'!C21 | D21: ='Balance Sheet'!D21 | E21: ='Balance Sheet'!E21 | F21: ='Balance Sheet'!F21 | G21: ='Balance Sheet'!G21 | H21: ='Balance Sheet'!H21 | I21: ='Balance Sheet'!I21
A22: Invested capital | B22: ='Balance Sheet'!B26 | C22: ='Balance Sheet'!C26 | D22: ='Balance Sheet'!D26 | E22: ='Balance Sheet'!E26 | F22: ='Balance Sheet'!F26 | G22: ='Balance Sheet'!G26 | H22: ='Balance Sheet'!H26 | I22: ='Balance Sheet'!I26
A23: Return on invested capital | B23: - | C23: - | D23: - | E23: ='Balance Sheet'!E27 | F23: ='Balance Sheet'!F27 | G23: ='Balance Sheet'!G27 | H23: ='Balance Sheet'!H27 | I23: ='Balance Sheet'!I27
A24: Return on equity | B24: - | C24: ='Balance Sheet'!C28 | D24: ='Balance Sheet'!D28 | E24: ='Balance Sheet'!E28 | F24: ='Balance Sheet'!F28 | G24: ='Balance Sheet'!G28 | H24: ='Balance Sheet'!H28 | I24: ='Balance Sheet'!I28
A26: Return on invested capital is the discounted-cash-flow sheet's NOPAT over the same year's invested capital, which is why the audited years carry capital but no return: their tax charge is struck on a post-financing basis and is not comparable with the pre-financing NOPAT the forecast uses.

Sheet Monte Carlo
A1: Probabilistic price map
A2: A map of price dispersion over the next one and three months. It carries no view on value and is never blended with the valuation. Each figure is a complete engine re-run, so it is a pasted value and does NOT redraw when a driver is changed.
A4: Horizon (AED) | B4: 5th | C4: 25th | D4: Median | E4: 75th | F4: 95th | G4: Probability above spot
A5: One month — graded 2026-09-07 | B5: 5.4740089 | C5: 5.8893332 | D5: 6.164121 | E5: 6.4532251 | F5: 6.9280856 | G5: 0.50406
A6: Three months — graded 2026-11-09 | B6: 4.945078 | C6: 5.6724641 | D6: 6.1784801 | E6: 6.7276859 | F6: 7.7283701 | G6: 0.5092
A8: Level event | B8: One month | C8: Three months
A9: Finishes 10% or more above spot | B9: 0.08632 | C9: 0.23286
A10: Finishes 10% or more below spot | B10: 0.06752 | C10: 0.19752
A11: Touches 10% above spot at any point | B11: 0.14278 | C11: 0.42208
A12: Touches 10% below spot at any point | B12: 0.11002 | C12: 0.3644
A14: Engine setting | C14: Value
A15: Simulated paths | C15: 50000
A16: Annualised volatility (three-month anchor) | C16: 0.28173247
A17: Spot price (AED) | C17: =Summary!$C$16
A18: Anchor date | C18: 2026-08-07
A19: Calibration verdict on the five-year walk-forward | C19: PARITY
A21: The price map is a dispersion forecast from the price series alone. It is deliberately not reconciled to the valuation lenses: one is a statement about what a price could do over weeks, the other about what a business is worth.

Sheet Sensitivity
A1: Sensitivity — what the valuation needs the world to do
A2: AED per share. Each cell is a complete re-run of the whole model, including the fleet build, so these grids are engine outputs rather than formulas and do NOT redraw when a driver is changed.
A4: Beta (rows) x terminal growth (columns)
A5: Beta | B5: 1.0% | C5: 1.5% | D5: 2.0% | E5: 2.5%
A6: 0.705 | B6: 8.3749443 | C6: 8.8225319 | D6: 9.3704688 | E6: 10.058871
A7: 0.900 | B7: 7.0705809 | C7: 7.3541289 | D7: 7.6902194 | E7: 8.0963184
A8: 1.085 | B8: 6.1042118 | C8: 6.2903658 | D8: 6.505577 | E8: 6.7581734
A9: 1.250 | B9: 5.4009352 | C9: 5.5286387 | D9: 5.6733875 | E9: 5.8395323
A10: 1.412 | B10: 4.8197249 | C10: 4.906776 | D10: 5.0036095 | E10: 5.1124798
A11: The beta rows are not evenly spaced round numbers. They span the two index constructions and the interval around the adopted one: 0.705 is the equal-weight composite of the exchange's own names, 1.085 is the adopted regression against the exchange's published index, and 1.412 is the top of that regression's own 90% confidence interval (its bottom, 0.758, sits just above the composite reading). The terminal growth column at 2.0% is the one the model runs on, so the cell where that column meets the 1.085 row is the published cash-flow value of AED 6.51 — every cell here is a complete re-run of the model discounted at the same three tranches of capital the valuation itself uses, equity, debt and the perpetual securities, so the grid is centred on the figure it brackets.
A12: Mid-cycle tanker rate anchor, as a multiple of the base anchor
B13: 0.80x | C13: 0.90x | D13: 1.00x | E13: 1.10x | F13: 1.20x
A14: Fair value per share (AED) | B14: 5.4668954 | C14: 5.9862362 | D14: 6.505577 | E14: 7.0249178 | F14: 7.5442585
A15: Swing across the grid | C15: =MAX(B14:F14)-MIN(B14:F14)
A16: This row and the one below it are re-runs of the whole model at the same 8.49% cost of capital the valuation uses, so the 1.00x cell reproduces the published AED 6.51 exactly and the swing across the row is a clean read of what that single driver is worth.
A17: Capital expenditure, as a multiple of the guided path
B18: 0.90x | C18: 1.00x | D18: 1.10x | E18: 1.20x
A19: Fair value per share (AED) | B19: 6.9149404 | C19: 6.505577 | D19: 6.0962135 | E19: 5.68685
A20: Swing across the grid | C20: =MAX(B19:E19)-MIN(B19:E19)
A22: A uniform group tax rate — the global-minimum-tax case
B23: 5% | C23: 9% | D23: 15%
A24: Fair value per share (AED) | B24: 6.4152247 | C24: 5.9631304 | D24: 5.2849888
A25: The shipping units currently bear under one per cent, because international shipping income is relieved under the corporate tax law; the group's blended charge on operating profit is therefore only a few per cent. A fifteen per cent rate reaching that income — a global minimum tax applied without the shipping relief — is the downside case, and it is a whole-model re-run rather than a formula because the mix itself changes.
A27: THE RATE PATH AGAINST WHAT THE FORWARD MARKET WAS ACTUALLY PAYING
A28: One-year time charter fixed in early 2026, very large crude carrier (USD per day) | C28: 76900
A29: Broker spot print for the same vessel class (USD per day) | C29: 102897
A30: This study's own path for the same vessel class (USD per day) | B30: FY2026E | C30: FY2027E | D30: FY2028E | E30: FY2029E | F30: FY2030E
A31: Very large crude carrier — spot time-charter equivalent | B31: =Segments!B92 | C31: =Segments!C92 | D31: =Segments!D92 | E31: =Segments!E92 | F31: =Segments!F92
A32: The study's 2027 path over the one-year time charter | C32: =C31/C28
A33: Crude tanker order book as a share of the trading fleet | C33: 0.27
A34: An independent one-year time charter fixed in early 2026 priced a very large crude carrier at USD 76,900 a day, well below the spot rate of the moment. A forward market that will not pay spot for a year of time is telling the reader it does not expect spot to hold, and a crude tanker order book near 27% of the trading fleet is the supply reason why. Both point the same way as the reversion path this study uses as its base, and both are reasons the sustained-strength path is published as an alternative rather than adopted.

Sheet Per-Share & Ratios
A1: Per-share and ratio analysis
A2: The indicator set for an asset-heavy marine logistics operator. Every ratio is a formula off the statements; per-share figures convert to dirhams at the fixed parity.
A4: Measure | B4: FY2023 | C4: FY2024 | D4: FY2025 | E4: FY2026E | F4: FY2027E | G4: FY2028E | H4: FY2029E | I4: FY2030E
A5: Earnings per ordinary share (USD) | B5: ='Income Statement'!B31 | C5: ='Income Statement'!C31 | D5: ='Income Statement'!D31 | E5: ='Income Statement'!E31 | F5: ='Income Statement'!F31 | G5: ='Income Statement'!G31 | H5: ='Income Statement'!H31 | I5: ='Income Statement'!I31
A6: Earnings per ordinary share (AED) | B6: ='Income Statement'!B32 | C6: ='Income Statement'!C32 | D6: ='Income Statement'!D32 | E6: ='Income Statement'!E32 | F6: ='Income Statement'!F32 | G6: ='Income Statement'!G32 | H6: ='Income Statement'!H32 | I6: ='Income Statement'!I32
A7: Attributable profit per share (AED, before the perpetual coupon) | B7: ='Income Statement'!B28/Assumptions!$C$6/1000*Assumptions!$C$7 | C7: ='Income Statement'!C28/Assumptions!$C$6/1000*Assumptions!$C$7 | D7: ='Income Statement'!D28/Assumptions!$C$6/1000*Assumptions!$C$7 | E7: ='Income Statement'!E28/Assumptions!$C$6/1000*Assumptions!$C$7 | F7: ='Income Statement'!F28/Assumptions!$C$6/1000*Assumptions!$C$7 | G7: ='Income Statement'!G28/Assumptions!$C$6/1000*Assumptions!$C$7 | H7: ='Income Statement'!H28/Assumptions!$C$6/1000*Assumptions!$C$7 | I7: ='Income Statement'!I28/Assumptions!$C$6/1000*Assumptions!$C$7
A8: Book value per share (AED) | B8: ='Balance Sheet'!B25 | C8: ='Balance Sheet'!C25 | D8: ='Balance Sheet'!D25 | E8: ='Balance Sheet'!E25 | F8: ='Balance Sheet'!F25 | G8: ='Balance Sheet'!G25 | H8: ='Balance Sheet'!H25 | I8: ='Balance Sheet'!I25
A9: Free cash flow to the firm per share (AED) | B9: - | C9: - | D9: - | E9: ='Cash Flow'!E15/Assumptions!$C$6/1000*Assumptions!$C$7 | F9: ='Cash Flow'!F15/Assumptions!$C$6/1000*Assumptions!$C$7 | G9: ='Cash Flow'!G15/Assumptions!$C$6/1000*Assumptions!$C$7 | H9: ='Cash Flow'!H15/Assumptions!$C$6/1000*Assumptions!$C$7 | I9: ='Cash Flow'!I15/Assumptions!$C$6/1000*Assumptions!$C$7
A10: Ordinary dividend per share (AED) | B10: - | C10: - | D10: - | E10: ='Balance Sheet'!B70*Assumptions!$C$7 | F10: ='Balance Sheet'!C70*Assumptions!$C$7 | G10: ='Balance Sheet'!D70*Assumptions!$C$7 | H10: ='Balance Sheet'!E70*Assumptions!$C$7 | I10: ='Balance Sheet'!F70*Assumptions!$C$7
A11: Ordinary dividend payout ratio | B11: - | C11: - | D11: - | E11: =-'Balance Sheet'!B67/'Income Statement'!E28 | F11: =-'Balance Sheet'!C67/'Income Statement'!F28 | G11: =-'Balance Sheet'!D67/'Income Statement'!G28 | H11: =-'Balance Sheet'!E67/'Income Statement'!H28 | I11: =-'Balance Sheet'!F67/'Income Statement'!I28
A12: Gross margin | B12: ='Income Statement'!B7/'Income Statement'!B5 | C12: ='Income Statement'!C7/'Income Statement'!C5 | D12: ='Income Statement'!D7/'Income Statement'!D5 | E12: - | F12: - | G12: - | H12: - | I12: -
A13: EBITDA margin | B13: ='Income Statement'!B18 | C13: ='Income Statement'!C18 | D13: ='Income Statement'!D18 | E13: ='Income Statement'!E18 | F13: ='Income Statement'!F18 | G13: ='Income Statement'!G18 | H13: ='Income Statement'!H18 | I13: ='Income Statement'!I18
A14: EBIT margin | B14: ='Income Statement'!B12/'Income Statement'!B5 | C14: ='Income Statement'!C12/'Income Statement'!C5 | D14: ='Income Statement'!D12/'Income Statement'!D5 | E14: ='Income Statement'!E12/'Income Statement'!E5 | F14: ='Income Statement'!F12/'Income Statement'!F5 | G14: ='Income Statement'!G12/'Income Statement'!G5 | H14: ='Income Statement'!H12/'Income Statement'!H5 | I14: ='Income Statement'!I12/'Income Statement'!I5
A15: Net margin (attributable) | B15: ='Income Statement'!B28/'Income Statement'!B5 | C15: ='Income Statement'!C28/'Income Statement'!C5 | D15: ='Income Statement'!D28/'Income Statement'!D5 | E15: ='Income Statement'!E28/'Income Statement'!E5 | F15: ='Income Statement'!F28/'Income Statement'!F5 | G15: ='Income Statement'!G28/'Income Statement'!G5 | H15: ='Income Statement'!H28/'Income Statement'!H5 | I15: ='Income Statement'!I28/'Income Statement'!I5
A16: Return on equity | B16: - | C16: ='Balance Sheet'!C28 | D16: ='Balance Sheet'!D28 | E16: ='Balance Sheet'!E28 | F16: ='Balance Sheet'!F28 | G16: ='Balance Sheet'!G28 | H16: ='Balance Sheet'!H28 | I16: ='Balance Sheet'!I28
A17: Return on invested capital | B17: - | C17: - | D17: - | E17: ='Balance Sheet'!E27 | F17: ='Balance Sheet'!F27 | G17: ='Balance Sheet'!G27 | H17: ='Balance Sheet'!H27 | I17: ='Balance Sheet'!I27
A18: Net debt / EBITDA | B18: ='Balance Sheet'!B23 | C18: ='Balance Sheet'!C23 | D18: ='Balance Sheet'!D23 | E18: ='Balance Sheet'!E23 | F18: ='Balance Sheet'!F23 | G18: ='Balance Sheet'!G23 | H18: ='Balance Sheet'!H23 | I18: ='Balance Sheet'!I23
A19: Interest cover (EBIT over finance costs) | B19: =-'Income Statement'!B12/'Income Statement'!B23 | C19: =-'Income Statement'!C12/'Income Statement'!C23 | D19: =-'Income Statement'!D12/'Income Statement'!D23 | E19: =-'Income Statement'!E12/'Income Statement'!E23 | F19: =-'Income Statement'!F12/'Income Statement'!F23 | G19: =-'Income Statement'!G12/'Income Statement'!G23 | H19: =-'Income Statement'!H12/'Income Statement'!H23 | I19: =-'Income Statement'!I12/'Income Statement'!I23
A20: Days sales outstanding | B20: ='Balance Sheet'!B12/'Income Statement'!B5*365 | C20: ='Balance Sheet'!C12/'Income Statement'!C5*365 | D20: ='Balance Sheet'!D12/'Income Statement'!D5*365 | E20: ='Balance Sheet'!E12/'Income Statement'!E5*365 | F20: ='Balance Sheet'!F12/'Income Statement'!F5*365 | G20: ='Balance Sheet'!G12/'Income Statement'!G5*365 | H20: ='Balance Sheet'!H12/'Income Statement'!H5*365 | I20: ='Balance Sheet'!I12/'Income Statement'!I5*365
A21: Days inventory outstanding | B21: ='Balance Sheet'!B11/'Income Statement'!B17*365 | C21: ='Balance Sheet'!C11/'Income Statement'!C17*365 | D21: ='Balance Sheet'!D11/'Income Statement'!D17*365 | E21: ='Balance Sheet'!E11/'Income Statement'!E17*365 | F21: ='Balance Sheet'!F11/'Income Statement'!F17*365 | G21: ='Balance Sheet'!G11/'Income Statement'!G17*365 | H21: ='Balance Sheet'!H11/'Income Statement'!H17*365 | I21: ='Balance Sheet'!I11/'Income Statement'!I17*365
A22: Days payable outstanding | B22: ='Balance Sheet'!B15/'Income Statement'!B17*365 | C22: ='Balance Sheet'!C15/'Income Statement'!C17*365 | D22: ='Balance Sheet'!D15/'Income Statement'!D17*365 | E22: ='Balance Sheet'!E15/'Income Statement'!E17*365 | F22: ='Balance Sheet'!F15/'Income Statement'!F17*365 | G22: ='Balance Sheet'!G15/'Income Statement'!G17*365 | H22: ='Balance Sheet'!H15/'Income Statement'!H17*365 | I22: ='Balance Sheet'!I15/'Income Statement'!I17*365
A23: Cash conversion cycle (days) | B23: =B20+B21-B22 | C23: =C20+C21-C22 | D23: =D20+D21-D22 | E23: =E20+E21-E22 | F23: =F20+F21-F22 | G23: =G20+G21-G22 | H23: =H20+H21-H22 | I23: =I20+I21-I22
A24: Capital expenditure / revenue | B24: =-'Cash Flow'!B7/'Income Statement'!B5 | C24: =-'Cash Flow'!C7/'Income Statement'!C5 | D24: =-'Cash Flow'!D7/'Income Statement'!D5 | E24: =-'Cash Flow'!E7/'Income Statement'!E5 | F24: =-'Cash Flow'!F7/'Income Statement'!F5 | G24: =-'Cash Flow'!G7/'Income Statement'!G5 | H24: =-'Cash Flow'!H7/'Income Statement'!H5 | I24: =-'Cash Flow'!I7/'Income Statement'!I5
A26: MULTIPLES AT THE ANCHOR PRICE
A27: Share price (AED) | C27: =Summary!$C$16
A28: Share price (USD) | C28: ='Relative & Normalized'!$C$29
A29: Market capitalisation (USD 000) | C29: ='Relative & Normalized'!$C$30
A30: Enterprise value (USD 000) | C30: ='Relative & Normalized'!$C$32
A31: Enterprise value / 2025 reported EBITDA | C31: ='Relative & Normalized'!$C$33
A32: Enterprise value / FY2026E EBITDA | C32: ='Relative & Normalized'!$C$34
A33: Price / 2025 ordinary earnings | C33: ='Relative & Normalized'!$C$35
A34: Price / book at 31 March 2026 | C34: ='Relative & Normalized'!$C$37
A35: Dividend yield on the 2026 distribution | C35: ='Relative & Normalized'!$C$38

Sheet Peer & Sector
A1: Peer frame and sector context
A2: No single clean comparable exists: the company is part contracted marine logistics and part spot tanker owner, so the frame is built from both ends and blended on the company's own disclosed exposure.
A4: Company | B4: Market | C4: Business model | D4: EV/EBITDA | E4: Forward P/E | F4: Trailing P/E | G4: Price / book | H4: Dividend yield | I4: Source | J4: As at
A5: Qatar Gas Transport (Nakilat) | B5: Qatar | C5: long-term contracted gas shipping | D5: 12.26 | E5: 13.97 | F5: 14.15 | G5: 1.65 | H5: 0.0336 | I5: stockanalysis.com company statistics page | J5: 2026-08-09
A6: Frontline plc | B6: Oslo / New York | C6: spot crude tankers | D6: 8.96 | E6: 6.44 | F6: 9.98 | G6: n/a | H6: n/a | I6: stockanalysis.com company statistics page | J6: 2026-08-09
A7: International Seaways | B7: New York | C7: spot crude and product tankers | D7: 8.1 | E7: n/a | F7: n/a | G7: n/a | H7: n/a | I7: valueinvesting.io enterprise-value-to-earnings page | J7: 2026-07-26
A9: THE MULTIPLES USED IN THE RELATIVE LENS
A10: Contracted-shipping multiple | C10: =D5
A11: Spot-tanker multiple — the two spot owners averaged | C11: =(D6+D7)/2
A12: Share of 2026 earnings exposed to spot rates, as disclosed | C12: =Assumptions!$C$167
A13: Blended enterprise multiple | C13: =(1-C12)*C10+C12*C11
A14: Contracted-shipping forward price/earnings | C14: =E5
A15: Spot-tanker forward price/earnings | C15: =E6
A16: Blended forward price/earnings — the multiple the relative lens applies to forward earnings | C16: =(1-C12)*C14+C12*C15
A17: Contracted-shipping trailing price/earnings | C17: =F5
A18: Spot-tanker trailing price/earnings | C18: =F6
A19: Blended trailing price/earnings — the same blend on the trailing basis, so the company can be compared with the peers on either basis rather than one against the other | C19: =(1-C12)*C17+C12*C18
A21: THE COMPANY'S OWN MULTIPLES AT THE ANCHOR PRICE
A22: Enterprise value / 2025 reported EBITDA | C22: ='Relative & Normalized'!$C$33
A23: Enterprise value / FY2026E EBITDA | C23: ='Relative & Normalized'!$C$34
A24: Price / 2025 ordinary earnings — trailing, against the blended trailing multiple above | C24: ='Relative & Normalized'!$C$35
A25: Price / FY2026E ordinary earnings — forward, against the blended forward multiple above | C25: ='Relative & Normalized'!$C$36
A26: Price / book at 31 March 2026 | C26: ='Relative & Normalized'!$C$37
A27: Dividend yield on the 2026 distribution | C27: ='Relative & Normalized'!$C$38
A28: The contracted peer is a long-term contracted gas shipping company whose earnings look nothing like a spot tanker owner's; the two spot owners carry the opposite exposure. Neither is a comparable on its own, which is why the multiple applied is a blend weighted by the share of earnings the company itself discloses as spot-exposed, and why the relative lens is a cross-check rather than an independent valuation.
