Workbook

Sheet READ FIRST
A1: Alinma Bank (Tadawul: 1150) — Valuation model — Testahil · Educational analysis · Not investment advice
A3: READ FIRST — what this model is and is not
A4: This is an educational valuation model, not investment advice and not a recommendation. It presents fair-value
A5: ranges and probability distributions only — never a rating or target price. Every downstream cell links to the
A6: single blue-cell Assumptions sheet: change one input and the whole model reprices.
A8: Two clocks. The fundamental fair value (~12-month anchor) and the Monte Carlo T+20/T+60 distributions are
A9: separate horizons and are never blended. Only the MC percentiles are genuine 3-month figures.
A10: Lens independence. The MC drift never embeds the fundamental value gap; the value gap lives in the
A11: fundamental sheets only. The MC drift is the carry anchor ln(1+rf)-ln(1+q) — Alinma's dividend yield ~= the
A12: Saudi risk-free, so the price carry is ~zero and the expected total return arrives as dividends.
A13: Flagged inputs (Fundamental Driver Ledger rows): SAR 10Y rf is CONSTRUCTED (UST 4.46% + Saudi Aa3/CDS spread,
A14: Damodaran Jan-2026) pending a real SAGBI/iBoxx quote; Tier-1 sukuk ~SAR 13.75bn from the three known issuances,
... A22: discussed in this report.

Sheet Summary
A1: Valuation summary — every read at a glance | B1: Fair value (SAR/sh) | C1: vs spot | D1: Weight
A2: FUNDAMENTAL — DDM (primary) | B2: =DDM!G9 | C2: =B2/Assumptions!$B$2-1 | D2: 0.35
A3: FUNDAMENTAL — Residual income | B3: ='Residual Income'!G9 | C3: =B3/Assumptions!$B$2-1 | D3: 0.2
A4: FUNDAMENTAL — Equity DCF (FCFE) | B4: =FCFE!G9 | C4: =B4/Assumptions!$B$2-1 | D4: 0.15
A5: FUNDAMENTAL — Relative multiples | B5: =('Relative & Normalized'!D2+'Relative & Normalized'!D3)/2 | C5: =B5/Assumptions!$B$2-1 | D5: 0.2
A6: FUNDAMENTAL — Normalized floor | B6: ='Relative & Normalized'!D5 | C6: =B6/Assumptions!$B$2-1 | D6: 0.1
A7: WEIGHTED CENTRAL (fundamental clock, ~12m) | B7: =SUMPRODUCT(B2:B6,D2:D6) | C7: =B7/Assumptions!$B$2-1
A9: TECHNICAL — MA-stack / RSI read | B9: Below MA20/50/100; RSI 11; support 23.3
A10: MONTE CARLO — T+60 median (3-month clock) | B10: 23.997139
A11: MC 50% band / 90% band | B11: 22.82–25.24 / 20.76–27.70

Sheet Assumptions
A1: Input | B1: Value | C1: Unit / note
A2: Spot (SAR) | B2: 24 | C2: 07 Jul 2026 close (investing.com OHLC)
A3: Shares out (mn) | B3: 2987.2 | C3: 3,000mn issued less 12.8mn treasury (Tadawul FY25 announcement)
A4: rf — SAR 10Y | B4: 0.048 | C4: CONSTRUCTED: UST 4.46% + Aa3/CDS spread — FLAGGED, replace with SAGBI/iBoxx at publish
A5: ERP rating-based | B5: 0.0501 | C5: Damodaran ORIGINAL ctryprem.html, Saudi Aa3 row, 'Last updated Jan 5 2026'
A6: ERP CDS-based | B6: 0.0572 | C6: Same file, Saudi CDS column (0.98% CDS)
A7: Beta (regressed) | B7: 0.736 | C7: vs TASI daily n=40 R2=0.29 SE=0.185 — passes gate; SHORT window, grid mandatory
A8: Terminal growth g | B8: 0.03 | C8: Nominal LT; sensitized 2.0-4.0%
A9: Through-cycle ROE | B9: 0.16 | C9: Terminal fade target (18.7% FY25 actual)
A10: Dividend yield q | B10: 0.0417 | C10: SAR 1.00/yr run-rate on 24.00 (0.25/qtr post-bonus)
A11: Zakat effective | B11: 0.102 | C11: FY25 actual 10.2% of pre-zakat profit
A12: Tier-1 sukuk (SAR mn) | B12: 13750 | C12: SAR 5bn + SAR 5bn + USD 1bn known issuances — FLAGGED, tie to FS note 11
A13: T1 cost FY26e (SAR mn) | B13: 520 | C13: Implied FY25 503mn (NI - EPSxWtd shares), grown
... A15: RWA density | B15: 0.75 | C15: RWA / total assets (CAR 18.0% context)
A16: Forecast drivers FY26-30
A17: Financing growth | B17: 0.13 | C17: 0.12 | D17: 0.1 | E17: 0.09 | F17: 0.08 | H17: FY26e … FY30e
A18: NIM | B18: 0.0345 | C18: 0.034 | D18: 0.034 | E18: 0.034 | F18: 0.034 | H18: FY26e … FY30e
A19: Non-funded income growth | B19: 0.09 | C19: 0.09 | D19: 0.08 | E19: 0.08 | F19: 0.07 | H19: FY26e … FY30e
A20: Cost-to-income | B20: 0.315 | C20: 0.312 | D20: 0.31 | E20: 0.308 | F20: 0.305 | H20: FY26e … FY30e
A21: Cost of risk | B21: 0.005 | C21: 0.005 | D21: 0.005 | E21: 0.005 | F21: 0.005 | H21: FY26e … FY30e
A22: Payout ratio | B22: 0.47 | C22: 0.48 | D22: 0.49 | E22: 0.5 | F22: 0.5 | H22: FY26e … FY30e
A23: Investments growth | B23: 0.1 | C23: 0.09 | D23: 0.08 | E23: 0.08 | F23: 0.07 | H23: FY26e … FY30e
A24: Ke — four-corner mean | B24: =($B$4+$B$7*$B$5+$B$4+$B$7*$B$6+$B$4+$B$5+$B$4+$B$6)/4 | C24: mean of {rating,CDS} x {beta regressed, beta=1.0} — the published grid center

Sheet Driver Build
A1: Driver | B1: FY23 | C1: FY24 | D1: FY25 | E1: FY26e | F1: FY27e | G1: FY28e | H1: FY29e | I1: FY30e
A2: Financing growth (%) | C2: 15.6 | D2: 13.6 | E2: =Assumptions!B$17*100 | F2: =Assumptions!C$17*100 | G2: =Assumptions!D$17*100 | H2: =Assumptions!E$17*100 | I2: =Assumptions!F$17*100
A3: NIM (%) | B3: 3.81 | C3: 3.7 | D3: 3.55 | E3: =Assumptions!B$18*100 | F3: =Assumptions!C$18*100 | G3: =Assumptions!D$18*100 | H3: =Assumptions!E$18*100 | I3: =Assumptions!F$18*100
A4: DuPont: NI/opinc (%) | B4: 49.8 | C4: 53.3 | D4: 53.7 | E4: ='Income Statement'!E12/'Income Statement'!E7*100 | F4: ='Income Statement'!F12/'Income Statement'!F7*100 | G4: ='Income Statement'!G12/'Income Statement'!G7*100 | H4: ='Income Statement'!H12/'Income Statement'!H7*100 | I4: ='Income Statement'!I12/'Income Statement'!I7*100
A5: DuPont: opinc/assets (%) | B5: 4.42 | C5: 4.26 | D5: 4.05 | E5: ='Income Statement'!E7/'Balance Sheet'!E4*100 | F5: ='Income Statement'!F7/'Balance Sheet'!F4*100 | G5: ='Income Statement'!G7/'Balance Sheet'!G4*100 | H5: ='Income Statement'!H7/'Balance Sheet'!H4*100 | I5: ='Income Statement'!I7/'Balance Sheet'!I4*100
A6: DuPont: assets/common equity (x) | B6: 8.6 | C6: 9 | D6: 9.4 | E6: ='Balance Sheet'!E4/'Balance Sheet'!E7 | F6: ='Balance Sheet'!F4/'Balance Sheet'!F7 | G6: ='Balance Sheet'!G4/'Balance Sheet'!G7 | H6: ='Balance Sheet'!H4/'Balance Sheet'!H7 | I6: ='Balance Sheet'!I4/'Balance Sheet'!I7
A7: CET1 ratio (%) | B7: 15.8 | C7: 15.7 | D7: 14.8 | E7: ='Balance Sheet'!E9 | F7: ='Balance Sheet'!F9 | G7: ='Balance Sheet'!G9 | H7: ='Balance Sheet'!H9 | I7: ='Balance Sheet'!I9
A8: CAR total (%) | B8: 17.5 | C8: 17.7 | D8: 18 | E8: 18 | F8: 18 | G8: 18 | H8: 18.1 | I8: 18.2
A9: NPL (%) | B9: 1.61 | C9: 1.4 | D9: 1.45 | E9: 1.45 | F9: 1.45 | G9: 1.45 | H9: 1.45 | I9: 1.45
A10: NPL coverage (%) | B10: 154.9 | C10: 172.3 | D10: 150.3 | E10: 150 | F10: 150 | G10: 150 | H10: 150 | I10: 150
A11: Reg. LDR (%) | B11: 80.5 | C11: 83.3 | D11: 84 | E11: 85 | F11: 85 | G11: 85 | H11: 85 | I11: 85

Sheet DDM
A1: Dividend discount model | B1: FY26e | C1: FY27e | D1: FY28e | E1: FY29e | F1: FY30e | G1: Terminal
A2: DPS (SAR) | B2: ='Per-Share & Ratios'!E5 | C2: ='Per-Share & Ratios'!F5 | D2: ='Per-Share & Ratios'!G5 | E2: ='Per-Share & Ratios'!H5 | F2: ='Per-Share & Ratios'!I5
A3: Discount factor @ Ke | B3: =1/(1+Assumptions!$B$24)^1 | C3: =1/(1+Assumptions!$B$24)^2 | D3: =1/(1+Assumptions!$B$24)^3 | E3: =1/(1+Assumptions!$B$24)^4 | F3: =1/(1+Assumptions!$B$24)^5
A4: PV of DPS | B4: =B2*B3 | C4: =C2*C3 | D4: =D2*D3 | E4: =E2*E3 | F4: =F2*F3
A5: Terminal payout = 1 − g/ROE_t | G5: =1-Assumptions!$B$8/Assumptions!$B$9
A6: Terminal DPS = EPS30×(1+g)×payout_t | G6: ='Per-Share & Ratios'!I3*(1+Assumptions!$B$8)*G5
A7: TV = DPS_t/(Ke−g) | G7: =G6/(Assumptions!$B$24-Assumptions!$B$8)
A8: PV of TV | G8: =G7*F3
A9: DDM fair value (SAR/sh) | G9: =SUM(B4:F4)+G8

Sheet FCFE
A1: Equity DCF (FCFE, bank form) | B1: FY26e | C1: FY27e | D1: FY28e | E1: FY29e | F1: FY30e | G1: Terminal
A2: NI to common (SAR mn) | B2: ='Income Statement'!E14 | C2: ='Income Statement'!F14 | D2: ='Income Statement'!G14 | E2: ='Income Statement'!H14 | F2: ='Income Statement'!I14
A3: Δ RWA (SAR mn) | B3: ='Balance Sheet'!E8-'Balance Sheet'!D8 | C3: ='Balance Sheet'!F8-'Balance Sheet'!E8 | D3: ='Balance Sheet'!G8-'Balance Sheet'!F8 | E3: ='Balance Sheet'!H8-'Balance Sheet'!G8 | F3: ='Balance Sheet'!I8-'Balance Sheet'!H8
A4: Capital charge = CET1 tgt × ΔRWA | B4: =Assumptions!$B$14*B3 | C4: =Assumptions!$B$14*C3 | D4: =Assumptions!$B$14*D3 | E4: =Assumptions!$B$14*E3 | F4: =Assumptions!$B$14*F3
A5: FCFE (SAR mn) | B5: =B2-B4 | C5: =C2-C4 | D5: =D2-D4 | E5: =E2-E4 | F5: =F2-F4
A6: PV of FCFE | B6: =B5/(1+Assumptions!$B$24)^1 | C6: =C5/(1+Assumptions!$B$24)^2 | D6: =D5/(1+Assumptions!$B$24)^3 | E6: =E5/(1+Assumptions!$B$24)^4 | F6: =F5/(1+Assumptions!$B$24)^5
A7: TV = FCFE30×(1+g)/(Ke−g) | G7: =F5*(1+Assumptions!$B$8)/(Assumptions!$B$24-Assumptions!$B$8)
A8: PV of TV | G8: =G7/(1+Assumptions!$B$24)^5
A9: Equity value (SAR mn) / per share | F9: =SUM(B6:F6)+G8 | G9: =F9/'Per-Share & Ratios'!B2

Sheet Residual Income
A1: Residual income build | B1: FY26e | C1: FY27e | D1: FY28e | E1: FY29e | F1: FY30e | G1: Terminal
A2: Opening BVPS | B2: =11.4970 | C2: ='Per-Share & Ratios'!E6 | D2: ='Per-Share & Ratios'!F6 | E2: ='Per-Share & Ratios'!G6 | F2: ='Per-Share & Ratios'!H6
A3: EPS | B3: ='Per-Share & Ratios'!E3 | C3: ='Per-Share & Ratios'!F3 | D3: ='Per-Share & Ratios'!G3 | E3: ='Per-Share & Ratios'!H3 | F3: ='Per-Share & Ratios'!I3
A4: Equity charge = Ke × opening BV | B4: =Assumptions!$B$24*B2 | C4: =Assumptions!$B$24*C2 | D4: =Assumptions!$B$24*D2 | E4: =Assumptions!$B$24*E2 | F4: =Assumptions!$B$24*F2
A5: Residual income | B5: =B3-B4 | C5: =C3-C4 | D5: =D3-D4 | E5: =E3-E4 | F5: =F3-F4
A6: PV of RI | B6: =B5/(1+Assumptions!$B$24)^1 | C6: =C5/(1+Assumptions!$B$24)^2 | D6: =D5/(1+Assumptions!$B$24)^3 | E6: =E5/(1+Assumptions!$B$24)^4 | F6: =F5/(1+Assumptions!$B$24)^5
A7: Terminal: [justified P/B − 1] × BV30 | G7: =((Assumptions!$B$9-Assumptions!$B$8)/(Assumptions!$B$24-Assumptions!$B$8)-1)*'Per-Share & Ratios'!I6
A8: PV of terminal | G8: =G7/(1+Assumptions!$B$24)^5
A9: RI fair value = BV0 + ΣPV(RI) + PV(terminal) | G9: =B2+SUM(B6:F6)+G8

Sheet Relative & Normalized
A1: Lens | B1: Multiple | C1: Applied to | D1: Fair value (SAR/sh)
A2: Peer P/B–ROE read | B2: 2.30x | C2: BVPS25 (common) | D2: =2.30*11.4970
A3: Peer P/E (fwd) | B3: 11.5x | C3: EPS FY26e | D3: =11.5*'Per-Share & Ratios'!E3
A4: Justified P/B (Ke base, ROE_t, g) | B4: =(Assumptions!$B$9-Assumptions!$B$8)/(Assumptions!$B$24-Assumptions!$B$8) | C4: BVPS25 | D4: =B4*11.4970
A5: Normalized floor (beta=1, CDS ERP) | B5: =(Assumptions!$B$9-Assumptions!$B$8)/((Assumptions!$B$4+Assumptions!$B$6)-Assumptions!$B$8) | C5: BVPS25 | D5: =B5*11.4970

Sheet Income Statement
A1: SAR mn | B1: FY23 | C1: FY24 | D1: FY25 | E1: FY26e | F1: FY27e | G1: FY28e | H1: FY29e | I1: FY30e
A2: Financing, net | B2: 175032 | C2: 202308.1 | D2: 229746.8 | E2: =D2*(1+Assumptions!B$17) | F2: =E2*(1+Assumptions!C$17) | G2: =F2*(1+Assumptions!D$17) | H2: =G2*(1+Assumptions!E$17) | I2: =H2*(1+Assumptions!F$17)
A3: Investments | B3: 43236 | C3: 48625.2 | D3: 56622.6 | E3: =D3*(1+Assumptions!B$23) | F3: =E3*(1+Assumptions!C$23) | G3: =F3*(1+Assumptions!D$23) | H3: =G3*(1+Assumptions!E$23) | I3: =H3*(1+Assumptions!F$23)
A4: Avg earning assets | E4: =(D2+D3+E2+E3)/2 | F4: =(E2+E3+F2+F3)/2 | G4: =(F2+F3+G2+G3)/2 | H4: =(G2+G3+H2+H3)/2 | I4: =(H2+H3+I2+I3)/2
A5: Net financing & investment income | B5: 7655 | C5: 8648.6 | D5: 9376.7 | E5: =Assumptions!B$18*E4 | F5: =Assumptions!C$18*F4 | G5: =Assumptions!D$18*G4 | H5: =Assumptions!E$18*H4 | I5: =Assumptions!F$18*I4
A6: Non-funded income | B6: 2071 | C6: 2291.5 | D6: 2528.6 | E6: =D6*(1+Assumptions!B$19) | F6: =E6*(1+Assumptions!C$19) | G6: =F6*(1+Assumptions!D$19) | H6: =G6*(1+Assumptions!E$19) | I6: =H6*(1+Assumptions!F$19)
A7: Total operating income | B7: 9726 | C7: 10940.1 | D7: 11905.3 | E7: =E5+E6 | F7: =F5+F6 | G7: =G5+G6 | H7: =H5+H6 | I7: =I5+I6
A8: Operating expenses | B8: 3044 | C8: 3383.6 | D8: 3714.6 | E8: =Assumptions!B$20*E7 | F8: =Assumptions!C$20*F7 | G8: =Assumptions!D$20*G7 | H8: =Assumptions!E$20*H7 | I8: =Assumptions!F$20*I7
A9: Impairment (ECL), net | B9: 1300 | C9: 1049.3 | D9: 1060.1 | E9: =Assumptions!B$21*(D2+E2)/2 | F9: =Assumptions!C$21*(E2+F2)/2 | G9: =Assumptions!D$21*(F2+G2)/2 | H9: =Assumptions!E$21*(G2+H2)/2 | I9: =Assumptions!F$21*(H2+I2)/2
A10: Pre-zakat profit | B10: 5382 | C10: 6502.1 | D10: 7126 | E10: =E7-E8-E9 | F10: =F7-F8-F9 | G10: =G7-G8-G9 | H10: =H7-H8-H9 | I10: =I7-I8-I9
A11: Zakat | B11: 543 | C11: 670.4 | D11: 728.9 | E11: =Assumptions!$B$11*E10 | F11: =Assumptions!$B$11*F10 | G11: =Assumptions!$B$11*G10 | H11: =Assumptions!$B$11*H10 | I11: =Assumptions!$B$11*I10
A12: Net income (after zakat) | B12: 4839 | C12: 5831.7 | D12: 6397.1 | E12: =E10-E11 | F12: =F10-F11 | G12: =G10-G11 | H12: =H10-H11 | I12: =I10-I11
A13: Tier-1 sukuk costs | B13: 350 | C13: 430 | D13: 503 | E13: 520 | F13: 540 | G13: 560 | H13: 570 | I13: 580
A14: NI attributable to common | B14: 4489 | C14: 5401.7 | D14: 5894.1 | E14: =E12-E13 | F14: =F12-F13 | G14: =G12-G13 | H14: =H12-H13 | I14: =I12-I13

Sheet Balance Sheet
A1: SAR mn | B1: FY23 | C1: FY24 | D1: FY25 | E1: FY26e | F1: FY27e | G1: FY28e | H1: FY29e | I1: FY30e
A2: Financing, net | B2: 175032 | C2: 202308.1 | D2: 229746.8 | E2: ='Income Statement'!E2 | F2: ='Income Statement'!F2 | G2: ='Income Statement'!G2 | H2: ='Income Statement'!H2 | I2: ='Income Statement'!I2
A3: Investments | B3: 43236 | C3: 48625.2 | D3: 56622.6 | E3: ='Income Statement'!E3 | F3: ='Income Statement'!F3 | G3: ='Income Statement'!G3 | H3: ='Income Statement'!H3 | I3: ='Income Statement'!I3
A4: Total assets | B4: 236600 | C4: 276827.5 | D4: 311067.1 | E4: =D4*(1+0.9*Assumptions!B$17) | F4: =E4*(1+0.9*Assumptions!C$17) | G4: =F4*(1+0.9*Assumptions!D$17) | H4: =G4*(1+0.9*Assumptions!E$17) | I4: =H4*(1+0.9*Assumptions!F$17)
A5: Customer deposits | B5: 187901 | C5: 210544.7 | D5: 227373.9 | E5: =D5*(1+0.85*Assumptions!B$17) | F5: =E5*(1+0.85*Assumptions!C$17) | G5: =F5*(1+0.85*Assumptions!D$17) | H5: =G5*(1+0.85*Assumptions!E$17) | I5: =H5*(1+0.85*Assumptions!F$17)
A6: Total equity (incl. Tier-1 sukuk) | B6: 36700 | C6: 41441.8 | D6: 48241.1 | E6: =E7+Assumptions!$B$12 | F6: =F7+Assumptions!$B$12 | G6: =G7+Assumptions!$B$12 | H6: =H7+Assumptions!$B$12 | I6: =I7+Assumptions!$B$12
A7: Common equity (ex T1) | B7: 27950 | C7: 32690 | D7: 34491.1 | E7: =D7+'Income Statement'!E14-'Per-Share & Ratios'!E5*'Per-Share & Ratios'!E2 | F7: =E7+'Income Statement'!F14-'Per-Share & Ratios'!F5*'Per-Share & Ratios'!F2 | G7: =F7+'Income Statement'!G14-'Per-Share & Ratios'!G5*'Per-Share & Ratios'!G2 | H7: =G7+'Income Statement'!H14-'Per-Share & Ratios'!H5*'Per-Share & Ratios'!H2 | I7: =H7+'Income Statement'!I14-'Per-Share & Ratios'!I5*'Per-Share & Ratios'!I2
A8: RWA (75% of assets) | B8: 177450 | C8: 207620.6 | D8: 233300.3 | E8: =Assumptions!$B$15*E4 | F8: =Assumptions!$B$15*F4 | G8: =Assumptions!$B$15*G4 | H8: =Assumptions!$B$15*H4 | I8: =Assumptions!$B$15*I4
A9: CET1 ratio (common/RWA) | B9: 15.8 | C9: 15.7 | D9: 14.8 | E9: =E7/E8*100 | F9: =F7/F8*100 | G9: =G7/G8*100 | H9: =H7/H8*100 | I9: =I7/I8*100

Sheet Cash Flow
A1: SAR mn — equity capital walk | B1: FY23 | C1: FY24 | D1: FY25 | E1: FY26e | F1: FY27e | G1: FY28e | H1: FY29e | I1: FY30e
A2: Opening common equity | B2: 26210 | C2: 27950 | D2: 32690 | E2: ='Balance Sheet'!D7 | F2: ='Balance Sheet'!E7 | G2: ='Balance Sheet'!F7 | H2: ='Balance Sheet'!G7 | I2: ='Balance Sheet'!H7
A3: + NI attributable to common | B3: 4489 | C3: 5401.7 | D3: 5894.1 | E3: ='Income Statement'!E14 | F3: ='Income Statement'!F14 | G3: ='Income Statement'!G14 | H3: ='Income Statement'!H14 | I3: ='Income Statement'!I14
A4: − Dividends paid | B4: 2500 | C4: 2750 | D4: 3000 | E4: ='Per-Share & Ratios'!E5*'Per-Share & Ratios'!E2 | F4: ='Per-Share & Ratios'!F5*'Per-Share & Ratios'!F2 | G4: ='Per-Share & Ratios'!G5*'Per-Share & Ratios'!G2 | H4: ='Per-Share & Ratios'!H5*'Per-Share & Ratios'!H2 | I4: ='Per-Share & Ratios'!I5*'Per-Share & Ratios'!I2
A5: ± Other (OCI, treasury, T1 moves) | B5: -249 | C5: 2088.3 | D5: -1093 | E5: 0 | F5: 0 | G5: 0 | H5: 0 | I5: 0
A6: Closing common equity | B6: 27950 | C6: 32690 | D6: 34491.1 | E6: =E2+E3-E4+E5 | F6: =F2+F3-F4+F5 | G6: =G2+G3-G4+G5 | H6: =H2+H3-H4+H5 | I6: =I2+I3-I4+I5

Sheet Monte Carlo
A1: v3 engine output (carry-anchored YZ-HAR-t) | B1: T+20 | C1: T+60
A2: Median | B2: 23.996406 | C2: 23.997139
A3: P5 | B3: 22.100616 | C3: 20.763281
A4: P25 | B4: 23.314376 | C4: 22.822707
A5: P75 | B5: 24.701784 | C5: 25.236231
A6: P95 | B6: 26.094692 | C6: 27.702861
A7: P(above spot) | B7: 0.49854 | C7: 0.49948
A8: P(+10%) | B8: 0.03582 | C8: 0.117
A9: P(−10%) | B9: 0.02684 | C9: 0.09736
A10: Drift = carry ln(1+rf)−ln(1+q) (log, over horizon) | B10: -0.00012962546 | C10: -0.00038887639
A11: σ_H (log) | B11: 0.055778513 | C11: 0.096611219
A12: Note: the §1 value gap is deliberately NOT in the drift (lens independence). Step-0 verdict: PARITY — market-panel validated, no single-name edge claimed.

Sheet Sensitivity
A1: DDM fair value — Ke × terminal g | B1: g=2.0% | C1: 2.5% | D1: 3.0% | E1: 3.5% | F1: 4.0%
A2: Ke=8.00% | B2: 37.4 | C2: 39.3 | D2: 41.5 | E2: 44.1 | F2: 47.4
A3: Ke=8.75% | B3: 32.7 | C3: 34 | D3: 35.5 | E3: 37.3 | F3: 39.4
A4: Ke=9.46% | B4: 29.2 | C4: 30.1 | D4: 31.2 | E4: 32.5 | F4: 33.9
A5: Ke=10.17% | B5: 26.3 | C5: 27 | D5: 27.8 | E5: 28.6 | F5: 29.7
A6: Ke=11.00% | B6: 23.5 | C6: 24 | D6: 24.5 | E6: 25.1 | F6: 25.8

Sheet Per-Share & Ratios
A1: SAR mn | B1: FY23 | C1: FY24 | D1: FY25 | E1: FY26e | F1: FY27e | G1: FY28e | H1: FY29e | I1: FY30e
A2: Shares (mn, post-bonus basis) | B2: 3000 | C2: 3000 | D2: 3000 | E2: 3000 | F2: 3000 | G2: 3000 | H2: 3000 | I2: 3000
A3: EPS (common, SAR) | B3: 1.5 | C3: 1.8 | D3: 1.96 | E3: ='Income Statement'!E14/E2 | F3: ='Income Statement'!F14/F2 | G3: ='Income Statement'!G14/G2 | H3: ='Income Statement'!H14/H2 | I3: ='Income Statement'!I14/I2
A4: EPS as reported (pre-bonus wtd) | B4: 1.81 | C4: 2.22 | D4: 2.37
A5: DPS (SAR) | B5: 0.83 | C5: 0.92 | D5: 1 | E5: =ROUND(Assumptions!B$22*E3,2) | F5: =ROUND(Assumptions!C$22*F3,2) | G5: =ROUND(Assumptions!D$22*G3,2) | H5: =ROUND(Assumptions!E$22*H3,2) | I5: =ROUND(Assumptions!F$22*I3,2)
A6: BVPS (common, SAR) | B6: 9.32 | C6: 10.9 | D6: 11.497033 | E6: ='Balance Sheet'!E7/E2 | F6: ='Balance Sheet'!F7/F2 | G6: ='Balance Sheet'!G7/G2 | H6: ='Balance Sheet'!H7/H2 | I6: ='Balance Sheet'!I7/I2
A7: ROE (%, common) | B7: 17.2 | C7: 18.8 | D7: 18.7 | E7: ='Income Statement'!E14/(('Balance Sheet'!D7+'Balance Sheet'!E7)/2)*100 | F7: ='Income Statement'!F14/(('Balance Sheet'!E7+'Balance Sheet'!F7)/2)*100 | G7: ='Income Statement'!G14/(('Balance Sheet'!F7+'Balance Sheet'!G7)/2)*100 | H7: ='Income Statement'!H14/(('Balance Sheet'!G7+'Balance Sheet'!H7)/2)*100 | I7: ='Income Statement'!I14/(('Balance Sheet'!H7+'Balance Sheet'!I7)/2)*100
A8: ROA (%) | B8: 2.2 | C8: 2.27 | D8: 2.18 | E8: ='Income Statement'!E12/(('Balance Sheet'!D4+'Balance Sheet'!E4)/2)*100 | F8: ='Income Statement'!F12/(('Balance Sheet'!E4+'Balance Sheet'!F4)/2)*100 | G8: ='Income Statement'!G12/(('Balance Sheet'!F4+'Balance Sheet'!G4)/2)*100 | H8: ='Income Statement'!H12/(('Balance Sheet'!G4+'Balance Sheet'!H4)/2)*100 | I8: ='Income Statement'!I12/(('Balance Sheet'!H4+'Balance Sheet'!I4)/2)*100
A9: NIM (%) | B9: 3.81 | C9: 3.7 | D9: 3.55 | E9: ='Income Statement'!E5/'Income Statement'!E4*100 | F9: ='Income Statement'!F5/'Income Statement'!F4*100 | G9: ='Income Statement'!G5/'Income Statement'!G4*100 | H9: ='Income Statement'!H5/'Income Statement'!H4*100 | I9: ='Income Statement'!I5/'Income Statement'!I4*100
A10: Cost-to-income (%) | B10: 31.3 | C10: 30.9 | D10: 31.2 | E10: ='Income Statement'!E8/'Income Statement'!E7*100 | F10: ='Income Statement'!F8/'Income Statement'!F7*100 | G10: ='Income Statement'!G8/'Income Statement'!G7*100 | H10: ='Income Statement'!H8/'Income Statement'!H7*100 | I10: ='Income Statement'!I8/'Income Statement'!I7*100
A11: Cost of risk (bp) | B11: 77 | C11: 55 | D11: 49 | E11: =Assumptions!B$21*10000 | F11: =Assumptions!C$21*10000 | G11: =Assumptions!D$21*10000 | H11: =Assumptions!E$21*10000 | I11: =Assumptions!F$21*10000
A12: P/E at spot | D12: =Assumptions!$B$2/D3 | E12: =Assumptions!$B$2/E3 | F12: =Assumptions!$B$2/F3 | G12: =Assumptions!$B$2/G3 | H12: =Assumptions!$B$2/H3 | I12: =Assumptions!$B$2/I3
A13: P/B at spot | D13: =Assumptions!$B$2/D6 | E13: =Assumptions!$B$2/E6 | F13: =Assumptions!$B$2/F6 | G13: =Assumptions!$B$2/G6 | H13: =Assumptions!$B$2/H6 | I13: =Assumptions!$B$2/I6
A14: Dividend yield at spot (%) | D14: =D5/Assumptions!$B$2*100 | E14: =E5/Assumptions!$B$2*100 | F14: =F5/Assumptions!$B$2*100 | G14: =G5/Assumptions!$B$2*100 | H14: =H5/Assumptions!$B$2*100 | I14: =I5/Assumptions!$B$2*100

Sheet Peer & Sector
A1: Bank | B1: P/B | C1: P/E | D1: ROE | E1: Note
A2: Al Rajhi | B2: ~3.5x | C2: ~16x | D2: ~23% | E2: Premium Islamic franchise; the sector ceiling
A3: SNB | B3: ~1.4x | C3: ~10x | D3: ~13% | E3: Largest by assets
A4: Riyad Bank | B4: ~1.2x | C4: ~8x | D4: ~16% | E4: Testahil coverage 09-Jul-2026
A5: Alinma (this study) | B5: ~2.1x | C5: ~11x | D5: ~18.7% | E5: Fastest-growing large Islamic bank; premium for growth
A6: Banque Saudi Fransi | B6: ~1.1x | C6: ~9x | D6: ~12% | E6: Corporate-tilted
A7: Arab National Bank | B7: ~1.0x | C7: ~8x | D7: ~12% | E7: Value end
A8: Al Bilad | B8: ~2.0x | C8: ~14x | D8: ~16% | E8: Retail/Islamic growth comp
A9: Saudi Investment Bank | B9: ~0.9x | C9: ~8x | D9: ~11% | E9: Smallest, deepest discount
A10: GCC — Emirates NBD | B10: ~1.0x | C10: ~6x | D10: ~18% | E10: UAE large-cap context
A11: GCC — QNB | B11: ~1.4x | C11: ~9x | D11: ~18% | E11: Qatar large-cap context

Sheet Earnings Drivers
A1: Key earnings drivers | B1: FY24 | C1: FY25 | D1: FY26e | E1: FY27e
A2: Financing growth (%) | B2: 15.6 | C2: 13.6 | D2: =Assumptions!B17*100 | E2: =Assumptions!C17*100
A3: Deposit growth (%) | B3: 12.1 | C3: 8 | D3: 11.1 | E3: 10.2
A4: NIM (%) | B4: 3.7 | C4: 3.55 | D4: =Assumptions!B18*100 | E4: =Assumptions!C18*100
A5: NII growth (%) | B5: 13 | C5: 8.4 | D5: ='Income Statement'!E5/'Income Statement'!D5*100-100 | E5: ='Income Statement'!F5/'Income Statement'!E5*100-100
A6: Fee/non-funded growth (%) | B6: 10.6 | C6: 10.3 | D6: 9 | E6: 9
A7: Revenue growth (%) | B7: 12.5 | C7: 8.8 | D7: ='Income Statement'!E7/'Income Statement'!D7*100-100 | E7: ='Income Statement'!F7/'Income Statement'!E7*100-100
A8: Opex growth (%) | B8: 11.2 | C8: 9.8 | D8: ='Income Statement'!E8/'Income Statement'!D8*100-100 | E8: ='Income Statement'!F8/'Income Statement'!E8*100-100
A9: Cost-to-income (%) | B9: 30.9 | C9: 31.2 | D9: =Assumptions!B20*100 | E9: =Assumptions!C20*100
A10: Cost of risk (bp) | B10: 55 | C10: 49 | D10: 50 | E10: 50
A11: Earnings growth (%) | B11: 20.5 | C11: 9.7 | D11: ='Income Statement'!E12/'Income Statement'!D12*100-100 | E11: ='Income Statement'!F12/'Income Statement'!E12*100-100
A12: ROAE (%) | B12: 18.8 | C12: 18.7 | D12: ='Per-Share & Ratios'!E7 | E12: ='Per-Share & Ratios'!F7
A13: ROAA (%) | B13: 2.27 | C13: 2.18 | D13: ='Per-Share & Ratios'!E8 | E13: ='Per-Share & Ratios'!F8
A14: Net profit, reported (SAR mn) | B14: 5831.7 | C14: 6397.1 | D14: ='Income Statement'!E12 | E14: ='Income Statement'!F12
A15: Net profit, attributable (SAR mn) | B15: 5401.7 | C15: 5894.1 | D15: ='Income Statement'!E14 | E15: ='Income Statement'!F14

Sheet Summary Financials
A1: SAR mn | B1: FY23 | C1: FY24 | D1: FY25 | E1: FY26e | F1: FY27e | G1: FY28e | H1: FY29e | I1: FY30e
A2: Total operating income | B2: ='Income Statement'!B7 | C2: ='Income Statement'!C7 | D2: ='Income Statement'!D7 | E2: ='Income Statement'!E7 | F2: ='Income Statement'!F7 | G2: ='Income Statement'!G7 | H2: ='Income Statement'!H7 | I2: ='Income Statement'!I7
A3: Net income | B3: ='Income Statement'!B12 | C3: ='Income Statement'!C12 | D3: ='Income Statement'!D12 | E3: ='Income Statement'!E12 | F3: ='Income Statement'!F12 | G3: ='Income Statement'!G12 | H3: ='Income Statement'!H12 | I3: ='Income Statement'!I12
A4: Financing, net | B4: ='Balance Sheet'!B2 | C4: ='Balance Sheet'!C2 | D4: ='Balance Sheet'!D2 | E4: ='Balance Sheet'!E2 | F4: ='Balance Sheet'!F2 | G4: ='Balance Sheet'!G2 | H4: ='Balance Sheet'!H2 | I4: ='Balance Sheet'!I2
A5: Deposits | B5: ='Balance Sheet'!B5 | C5: ='Balance Sheet'!C5 | D5: ='Balance Sheet'!D5 | E5: ='Balance Sheet'!E5 | F5: ='Balance Sheet'!F5 | G5: ='Balance Sheet'!G5 | H5: ='Balance Sheet'!H5 | I5: ='Balance Sheet'!I5
A6: Common equity | B6: ='Balance Sheet'!B7 | C6: ='Balance Sheet'!C7 | D6: ='Balance Sheet'!D7 | E6: ='Balance Sheet'!E7 | F6: ='Balance Sheet'!F7 | G6: ='Balance Sheet'!G7 | H6: ='Balance Sheet'!H7 | I6: ='Balance Sheet'!I7
A7: EPS (common) | B7: ='Per-Share & Ratios'!B3 | C7: ='Per-Share & Ratios'!C3 | D7: ='Per-Share & Ratios'!D3 | E7: ='Per-Share & Ratios'!E3 | F7: ='Per-Share & Ratios'!F3 | G7: ='Per-Share & Ratios'!G3 | H7: ='Per-Share & Ratios'!H3 | I7: ='Per-Share & Ratios'!I3
A8: DPS | B8: ='Per-Share & Ratios'!B5 | C8: ='Per-Share & Ratios'!C5 | D8: ='Per-Share & Ratios'!D5 | E8: ='Per-Share & Ratios'!E5 | F8: ='Per-Share & Ratios'!F5 | G8: ='Per-Share & Ratios'!G5 | H8: ='Per-Share & Ratios'!H5 | I8: ='Per-Share & Ratios'!I5
A9: BVPS | B9: ='Per-Share & Ratios'!B6 | C9: ='Per-Share & Ratios'!C6 | D9: ='Per-Share & Ratios'!D6 | E9: ='Per-Share & Ratios'!E6 | F9: ='Per-Share & Ratios'!F6 | G9: ='Per-Share & Ratios'!G6 | H9: ='Per-Share & Ratios'!H6 | I9: ='Per-Share & Ratios'!I6
A10: ROE % | B10: ='Per-Share & Ratios'!B7 | C10: ='Per-Share & Ratios'!C7 | D10: ='Per-Share & Ratios'!D7 | E10: ='Per-Share & Ratios'!E7 | F10: ='Per-Share & Ratios'!F7 | G10: ='Per-Share & Ratios'!G7 | H10: ='Per-Share & Ratios'!H7 | I10: ='Per-Share & Ratios'!I7
