Workbook

Sheet READ FIRST
A1: Elm Company (Tadawul: 7203) — Valuation Model
A2: Testahil · Independent Valuation Study — Educational Analysis · Not investment advice
A5: This workbook is an educational valuation model. It is not investment advice and contains no rating, target price, or recommendation.
A6: Every downstream cell links back to the Assumptions sheet (blue cells). Change one blue input and the DCF, Sensitivity and Summary reprice.
A7: Fundamental fair value is a ~12-month anchor. Only the Monte Carlo percentiles are genuine 3-month figures. The two are kept on separate clocks.
A8: The discount rate is the dominant swing factor (77% of DCF value is terminal); it is deliberately shown across a wide sensitivity band, not as a point.
A9: The preparer may hold, and may in future take or dispose of, a position in the security discussed.
A11: Sheets: Summary · Assumptions (inputs) · DCF · Income Statement · Balance Sheet · Cash Flow · Segments · Relative & Normalized · Monte Carlo · Sensitivity · Per-Share & Ratios

Sheet Summary
A1: Valuation summary — every read
A2: Spot SAR 658; weighted central fair value ~SAR 620 (range ~530–720).
A4: Lens | B4: Method | C4: Fair value (SAR) | D4: Weight
A5: DCF (primary) | B5: 5-yr FCFF, β1.0, WACC 10.5%, g4% | C5: =DCF!B24 -> 576.15201 | D5: 40%
A6: Relative EV/EBITDA | B6: 18–20× 2025e EBITDA | C6: 593–656 | D6: 25%
A7: Relative P/E | B7: 24× 2025e EPS | C7: 686 | D7: 30%
A8: Monte Carlo T+60 | B8: median (3-month) | C8: 662 | D8: —
A9: Weighted central | C9: ≈ 620 (530–720) | D9: 100%
A11: Fair value is a ~12-month anchor; Monte Carlo is the 3-month path. Never a rating or target — ranges and probabilities only.

Sheet Assumptions
A1: Assumptions — single input layer
A2: Blue cells are inputs. All other sheets reference these.
A4: Market & share data
A5: Spot price | B5: 658.5 | C5: SAR
A6: Shares outstanding | B6: 80 | C6: m
A7: Dividend per share | B7: 8.5 | C7: SAR
A9: Cost of capital
A10: Risk-free rate (SAR 10Y) | B10: 0.055
A11: Equity risk premium (rating) | B11: 0.0501
A12: Beta (anchor) | B12: 1
A13: WACC = rf + beta×ERP | B13: =Assumptions!B10+Assumptions!B12*Assumptions!B11 -> 0.1051
A14: Terminal growth | B14: 0.04
A15: Effective zakat rate | B15: 0.07
A16: Net cash (net of leases) | B16: 1900 | C16: SAR mn
A18: Operating forecast (FY25e–29e)
A19: Base revenue FY24a | B19: 7407 | C19: SAR mn
A20: Revenue growth | B20: 0.303 | C20: 0.171 | D20: 0.142 | E20: 0.12 | F20: 0.1
A21: EBIT margin | B21: 0.232 | C21: 0.235 | D21: 0.237 | E21: 0.24 | F21: 0.24
A22: D&A % of revenue | B22: 0.03 | C22: 0.03 | D22: 0.03 | E22: 0.03 | F22: 0.03
A23: Capex % of revenue | B23: 0.032 | C23: 0.031 | D23: 0.03 | E23: 0.03 | F23: 0.03
A24: ΔWC % of revenue growth | B24: 0.025

Sheet DCF
A1: Discounted cash flow — FCFF
A2: All rows compute from Assumptions. TV = Gordon growth. Fair value = (EV + net cash) / shares.
A4: SAR mn | B4: 2025e | C4: 2026e | D4: 2027e | E4: 2028e | F4: 2029e
A5: Revenue | B5: =Assumptions!B19*(1+Assumptions!B20) -> 9651.321 | C5: =B5*(1+Assumptions!C20) -> 11301.697 | D5: =C5*(1+Assumptions!D20) -> 12906.538 | E5: =D5*(1+Assumptions!E20) -> 14455.322 | F5: =E5*(1+Assumptions!F20) -> 15900.855
A6: EBITDA | B6: =B5*Assumptions!B21+B5*Assumptions!B22 -> 2528.6461 | C6: =C5*Assumptions!C21+C5*Assumptions!C22 -> 2994.9497 | D6: =D5*Assumptions!D21+D5*Assumptions!D22 -> 3446.0456 | E6: =E5*Assumptions!E21+E5*Assumptions!E22 -> 3902.937 | F6: =F5*Assumptions!F21+F5*Assumptions!F22 -> 4293.2308
A7: − D&A | B7: =-B5*Assumptions!B22 -> -289.53963 | C7: =-C5*Assumptions!C22 -> -339.05091 | D7: =-D5*Assumptions!D22 -> -387.19614 | E7: =-E5*Assumptions!E22 -> -433.65967 | F7: =-F5*Assumptions!F22 -> -477.02564
A8: EBIT | B8: =B6+B7 -> 2239.1065 | C8: =C6+C7 -> 2655.8988 | D8: =D6+D7 -> 3058.8495 | E8: =E6+E7 -> 3469.2774 | F8: =F6+F7 -> 3816.2051
A9: NOPAT (EBIT×(1−zakat)) | B9: =B8*(1-Assumptions!B15) -> 2082.369 | C9: =C8*(1-Assumptions!B15) -> 2469.9859 | D9: =D8*(1-Assumptions!B15) -> 2844.73 | E9: =E8*(1-Assumptions!B15) -> 3226.428 | F9: =F8*(1-Assumptions!B15) -> 3549.0708
A10: + D&A | B10: =B5*Assumptions!B22 -> 289.53963 | C10: =C5*Assumptions!C22 -> 339.05091 | D10: =D5*Assumptions!D22 -> 387.19614 | E10: =E5*Assumptions!E22 -> 433.65967 | F10: =F5*Assumptions!F22 -> 477.02564
A11: − Capex | B11: =-B5*Assumptions!B23 -> -308.84227 | C11: =-C5*Assumptions!C23 -> -350.3526 | D11: =-D5*Assumptions!D23 -> -387.19614 | E11: =-E5*Assumptions!E23 -> -433.65967 | F11: =-F5*Assumptions!F23 -> -477.02564
A12: − Δ working capital | B12: =-(B5-Assumptions!B19)*Assumptions!B24 -> -56.108025 | C12: =-(C5-B5)*Assumptions!B24 -> -41.259397 | D12: =-(D5-C5)*Assumptions!B24 -> -40.121024 | E12: =-(E5-D5)*Assumptions!B24 -> -38.719614 | F12: =-(F5-E5)*Assumptions!B24 -> -36.138306
A13: Free cash flow to firm | B13: =B9+B10+B11+B12 -> 2006.9584 | C13: =C9+C10+C11+C12 -> 2417.4248 | D13: =D9+D10+D11+D12 -> 2804.609 | E13: =E9+E10+E11+E12 -> 3187.7083 | F13: =F9+F10+F11+F12 -> 3512.9324
A14: Discount factor | B14: =1/(1+Assumptions!B13)^1 -> 0.90489548 | C14: =1/(1+Assumptions!B13)^2 -> 0.81883584 | D14: =1/(1+Assumptions!B13)^3 -> 0.74096085 | E14: =1/(1+Assumptions!B13)^4 -> 0.67049213 | F14: =1/(1+Assumptions!B13)^5 -> 0.6067253
A15: PV of FCFF | B15: =B13*B14 -> 1816.0876 | C15: =C13*C14 -> 1979.474 | D15: =D13*D14 -> 2078.1055 | E15: =E13*E14 -> 2137.3334 | F15: =F13*F14 -> 2131.385
A17: Sum PV of explicit FCFF | B17: =SUM(B15:F15) -> 10142.385
A18: Terminal value (Gordon) | B18: =F13*(1+Assumptions!B14)/(Assumptions!B13-Assumptions!B14) -> 56120.58
A19: PV of terminal value | B19: =B18*F14 -> 34049.776
A20: Enterprise value | B20: =B17+B19 -> 44192.161
A21: + Net cash | B21: =Assumptions!B16 -> 1900
A22: Equity value | B22: =B20+B21 -> 46092.161
A23: ÷ shares (m) | B23: =Assumptions!B6 -> 80
A24: Fair value per share (SAR) | B24: =B22/B23 -> 576.15201
A25: TV as % of EV | B25: =B19/B20 -> 0.77049356

Sheet Income Statement
A1: Income statement (SAR mn)
A2: Three actual (FY22–24), five forecast (FY25e–29e). Actuals: Elm IR / Argaam.
A4: SAR mn | B4: 2022a | C4: 2023a | D4: 2024a | E4: 2025e | F4: 2026e | G4: 2027e | H4: 2028e | I4: 2029e
A5: Revenue | B5: 4606 | C5: 5898 | D5: 7407 | E5: 9651 | F5: 11302 | G5: 12907 | H5: 14455 | I5: 15901
A6: Cost of revenue | B6: -2736 | C6: -3563 | D6: -4378 | E6: -5704 | F6: -6634 | G6: -7525 | H6: -8369 | I6: -9143
A7: Gross profit | B7: 1870 | C7: 2335 | D7: 3029 | E7: 3947 | F7: 4668 | G7: 5382 | H7: 6086 | I7: 6758
A8: Operating expenses | B8: -894 | C8: -981 | D8: -1326 | E8: -1708 | F8: -2012 | G8: -2323 | H8: -2617 | I8: -2942
A9: EBIT | B9: 976 | C9: 1354 | D9: 1703 | E9: 2239 | F9: 2656 | G9: 3059 | H9: 3469 | I9: 3816
A10: Other income (net) | B10: 37 | C10: 119 | D10: 251 | E10: 220 | F10: 228 | G10: 236 | H10: 244 | I10: 252
A11: Profit before zakat | B11: 1013 | C11: 1473 | D11: 1954 | E11: 2459 | F11: 2884 | G11: 3295 | H11: 3713 | I11: 4068
A12: Zakat | B12: -83 | C12: -124 | D12: -130 | E12: -172 | F12: -202 | G12: -231 | H12: -260 | I12: -285
A13: Net profit | B13: 930 | C13: 1349 | D13: 1824 | E13: 2287 | F13: 2682 | G13: 3064 | H13: 3453 | I13: 3783
A14: EPS (SAR) | B14: 11.99 | C14: 17.46 | D14: 23.51 | E14: 28.6 | F14: 33.5 | G14: 38.3 | H14: 43.2 | I14: 47.3

Sheet Balance Sheet
A1: Balance sheet (SAR mn) — summary
A2: Elm carries no meaningful financial debt; liabilities are leases, income-sharing payables, zakat.
A4: SAR mn | B4: 2022a | C4: 2023a | D4: 2024a | E4: 2025e | F4: 2026e | G4: 2027e | H4: 2028e | I4: 2029e
A5: Cash & short-term investments | B5: 2900 | C5: 3500 | D5: 4200 | E5: 5000 | F5: 5900 | G5: 6900 | H5: 8000 | I5: 9200
A6: Other assets | B6: 3126 | C6: 4597 | D6: 5354 | E6: 6300 | F6: 7300 | G6: 8300 | H6: 9300 | I6: 10300
A7: Total assets | B7: 6026 | C7: 8097 | D7: 9554
A8: Total liabilities | B8: 2979 | C8: 4102 | D8: 4261 | E8: 4500 | F8: 4800 | G8: 5100 | H8: 5400 | I8: 5700
A9: Total equity | B9: 3047 | C9: 3994 | D9: 5293 | E9: 6802 | F9: 8572 | G9: 10594 | H9: 12873 | I9: 15370

Sheet Cash Flow
A1: Cash flow (SAR mn) — summary
A2: High FCF conversion; cash capex ~3% of revenue. Dividends ~33% payout.
A4: SAR mn | B4: 2022a | C4: 2023a | D4: 2024a | E4: 2025e | F4: 2026e | G4: 2027e | H4: 2028e | I4: 2029e
A5: Operating cash flow | B5: 1706 | C5: 1559 | D5: 1662 | E5: 2521 | F5: 2980 | G5: 3411 | H5: 3848 | I5: 4224
A6: Capex | D6: -228 | E6: -309 | F6: -350 | G6: -387 | H6: -434 | I6: -477
A7: Free cash flow | C7: 1027 | D7: 1434 | E7: 2212 | F7: 2630 | G7: 3024 | H7: 3414 | I7: 3747
A8: Dividends paid | B8: -441 | C8: -532 | D8: -583 | E8: -620 | F8: -700 | G8: -800 | H8: -910 | I8: -1030

Sheet Segments
A1: Segment scorecard (FY2024)
A2: BPO / Professional Services split estimated from disclosed growth + the Digital Business figure.
A4: Segment | B4: Revenue (SAR mn) | C4: % of total | D4: Growth | E4: Gross margin
A5: Digital Business | B5: 5469 | C5: 73.8% | D5: +28.5% | E5: ~46%
A6: Business Process Outsourcing | B6: 1300 | C6: ~18% | D6: +20.7% | E6: ~25%
A7: Professional Services | B7: 638 | C7: ~9% | D7: −6.7% | E7: declining
A8: Total | B8: 7407 | C8: 100% | D8: +25.6% | E8: 40.9%

Sheet Relative & Normalized
A1: Relative valuation — cross-check
A2: On 2025e EBITDA SAR 2,529 and 2025e EPS SAR 28.6.
A4: EV/EBITDA multiple | B4: 16× | C4: 18× | D4: 20× | E4: 22×
A5: → per share (SAR) | B5: 529 | C5: 593 | D5: 656 | E5: 719
A7: Forward P/E multiple | B7: 20× | C7: 24× | D7: 28× | E7: 32×
A8: → per share (SAR) | B8: 572 | C8: 686 | D8: 800 | E8: 915
A10: Elm history ~42× P/E; current ~24×; TASI ~17.5×. Premium justified by ROIC & moat if durable.

Sheet Monte Carlo
A1: Monte Carlo — 3-month distribution
A2: Saudi-fitted engine: ν=5, width_cal 1.28, carry-anchored, 50,000 paths, seed 42. Values from the engine.
A4: Percentile | B4: 5th | C4: 10th | D4: 25th | E4: 50th | F4: 75th | G4: 90th | H4: 95th
A5: T+20 (SAR) | B5: 547 | C5: 575 | D5: 616 | E5: 660 | F5: 706 | G5: 758 | H5: 798
A6: T+60 (SAR) | B6: 480 | C6: 522 | D6: 589 | E6: 662 | F6: 746 | G6: 843 | H6: 920
A8: Probability read (T+60) | B8: Value
A9: P(above spot) | B9: 51%
A10: P(+10%) vs P(−10%) | B10: 30% / 26%
A11: Median (SAR / move) | B11: 662 (+0.6%)
A12: 50% band (SAR) | B12: 589–746
A13: Touch +10% / −10% | B13: 55% / 48%
A15: Calibration: PARITY under the Saudi-fitted panel (calibrated, market-panel validated, no single-name edge).

Sheet Sensitivity
A1: Sensitivity — fair value (SAR) vs WACC × terminal g
A2: Recomputed from the DCF FCFF row. Base = Assumptions WACC × terminal g.
A4: WACC ＼ g | B4: 3.0% | C4: 3.5% | D4: 4.0% | E4: 4.5% | F4: 5.0%
A5: 7.50% | B5: =((DCF!B13/(1+0.075)^1+DCF!C13/(1+0.075)^2+DCF!D13/(1+0.075)^3+DCF!E13/(1+0.075)^4+DCF!F13/(1+0.075)^5)+DCF!F13*(1+0.03)/(0.075-0.03)/(1+0.075)^5+Assumptions!B16)/Assumptions!B6 -> 861.98261 | C5: =((DCF!B13/(1+0.075)^1+DCF!C13/(1+0.075)^2+DCF!D13/(1+0.075)^3+DCF!E13/(1+0.075)^4+DCF!F13/(1+0.075)^5)+DCF!F13*(1+0.035)/(0.075-0.035)/(1+0.075)^5+Assumptions!B16)/Assumptions!B6 -> 953.31892 | D5: =((DCF!B13/(1+0.075)^1+DCF!C13/(1+0.075)^2+DCF!D13/(1+0.075)^3+DCF!E13/(1+0.075)^4+DCF!F13/(1+0.075)^5)+DCF!F13*(1+0.04)/(0.075-0.04)/(1+0.075)^5+Assumptions!B16)/Assumptions!B6 -> 1070.7513 | E5: =((DCF!B13/(1+0.075)^1+DCF!C13/(1+0.075)^2+DCF!D13/(1+0.075)^3+DCF!E13/(1+0.075)^4+DCF!F13/(1+0.075)^5)+DCF!F13*(1+0.045)/(0.075-0.045)/(1+0.075)^5+Assumptions!B16)/Assumptions!B6 -> 1227.3278 | F5: =((DCF!B13/(1+0.075)^1+DCF!C13/(1+0.075)^2+DCF!D13/(1+0.075)^3+DCF!E13/(1+0.075)^4+DCF!F13/(1+0.075)^5)+DCF!F13*(1+0.05)/(0.075-0.05)/(1+0.075)^5+Assumptions!B16)/Assumptions!B6 -> 1446.535
A6: 9.00% | B6: =((DCF!B13/(1+0.09)^1+DCF!C13/(1+0.09)^2+DCF!D13/(1+0.09)^3+DCF!E13/(1+0.09)^4+DCF!F13/(1+0.09)^5)+DCF!F13*(1+0.03)/(0.09-0.03)/(1+0.09)^5+Assumptions!B16)/Assumptions!B6 -> 645.96711 | C6: =((DCF!B13/(1+0.09)^1+DCF!C13/(1+0.09)^2+DCF!D13/(1+0.09)^3+DCF!E13/(1+0.09)^4+DCF!F13/(1+0.09)^5)+DCF!F13*(1+0.035)/(0.09-0.035)/(1+0.09)^5+Assumptions!B16)/Assumptions!B6 -> 693.10063 | D6: =((DCF!B13/(1+0.09)^1+DCF!C13/(1+0.09)^2+DCF!D13/(1+0.09)^3+DCF!E13/(1+0.09)^4+DCF!F13/(1+0.09)^5)+DCF!F13*(1+0.04)/(0.09-0.04)/(1+0.09)^5+Assumptions!B16)/Assumptions!B6 -> 749.66085 | E6: =((DCF!B13/(1+0.09)^1+DCF!C13/(1+0.09)^2+DCF!D13/(1+0.09)^3+DCF!E13/(1+0.09)^4+DCF!F13/(1+0.09)^5)+DCF!F13*(1+0.045)/(0.09-0.045)/(1+0.09)^5+Assumptions!B16)/Assumptions!B6 -> 818.79002 | F6: =((DCF!B13/(1+0.09)^1+DCF!C13/(1+0.09)^2+DCF!D13/(1+0.09)^3+DCF!E13/(1+0.09)^4+DCF!F13/(1+0.09)^5)+DCF!F13*(1+0.05)/(0.09-0.05)/(1+0.09)^5+Assumptions!B16)/Assumptions!B6 -> 905.20147
A7: 10.51% | B7: =((DCF!B13/(1+0.1051)^1+DCF!C13/(1+0.1051)^2+DCF!D13/(1+0.1051)^3+DCF!E13/(1+0.1051)^4+DCF!F13/(1+0.1051)^5)+DCF!F13*(1+0.03)/(0.1051-0.03)/(1+0.1051)^5+Assumptions!B16)/Assumptions!B6 -> 515.93037 | C7: =((DCF!B13/(1+0.1051)^1+DCF!C13/(1+0.1051)^2+DCF!D13/(1+0.1051)^3+DCF!E13/(1+0.1051)^4+DCF!F13/(1+0.1051)^5)+DCF!F13*(1+0.035)/(0.1051-0.035)/(1+0.1051)^5+Assumptions!B16)/Assumptions!B6 -> 543.89349 | D7: =((DCF!B13/(1+0.1051)^1+DCF!C13/(1+0.1051)^2+DCF!D13/(1+0.1051)^3+DCF!E13/(1+0.1051)^4+DCF!F13/(1+0.1051)^5)+DCF!F13*(1+0.04)/(0.1051-0.04)/(1+0.1051)^5+Assumptions!B16)/Assumptions!B6 -> 576.15201 | E7: =((DCF!B13/(1+0.1051)^1+DCF!C13/(1+0.1051)^2+DCF!D13/(1+0.1051)^3+DCF!E13/(1+0.1051)^4+DCF!F13/(1+0.1051)^5)+DCF!F13*(1+0.045)/(0.1051-0.045)/(1+0.1051)^5+Assumptions!B16)/Assumptions!B6 -> 613.77801 | F7: =((DCF!B13/(1+0.1051)^1+DCF!C13/(1+0.1051)^2+DCF!D13/(1+0.1051)^3+DCF!E13/(1+0.1051)^4+DCF!F13/(1+0.1051)^5)+DCF!F13*(1+0.05)/(0.1051-0.05)/(1+0.1051)^5+Assumptions!B16)/Assumptions!B6 -> 658.23269
A8: 12.00% | B8: =((DCF!B13/(1+0.12)^1+DCF!C13/(1+0.12)^2+DCF!D13/(1+0.12)^3+DCF!E13/(1+0.12)^4+DCF!F13/(1+0.12)^5)+DCF!F13*(1+0.03)/(0.12-0.03)/(1+0.12)^5+Assumptions!B16)/Assumptions!B6 -> 430.58884 | C8: =((DCF!B13/(1+0.12)^1+DCF!C13/(1+0.12)^2+DCF!D13/(1+0.12)^3+DCF!E13/(1+0.12)^4+DCF!F13/(1+0.12)^5)+DCF!F13*(1+0.035)/(0.12-0.035)/(1+0.12)^5+Assumptions!B16)/Assumptions!B6 -> 448.82848 | D8: =((DCF!B13/(1+0.12)^1+DCF!C13/(1+0.12)^2+DCF!D13/(1+0.12)^3+DCF!E13/(1+0.12)^4+DCF!F13/(1+0.12)^5)+DCF!F13*(1+0.04)/(0.12-0.04)/(1+0.12)^5+Assumptions!B16)/Assumptions!B6 -> 469.34807 | E8: =((DCF!B13/(1+0.12)^1+DCF!C13/(1+0.12)^2+DCF!D13/(1+0.12)^3+DCF!E13/(1+0.12)^4+DCF!F13/(1+0.12)^5)+DCF!F13*(1+0.045)/(0.12-0.045)/(1+0.12)^5+Assumptions!B16)/Assumptions!B6 -> 492.60362 | F8: =((DCF!B13/(1+0.12)^1+DCF!C13/(1+0.12)^2+DCF!D13/(1+0.12)^3+DCF!E13/(1+0.12)^4+DCF!F13/(1+0.12)^5)+DCF!F13*(1+0.05)/(0.12-0.05)/(1+0.12)^5+Assumptions!B16)/Assumptions!B6 -> 519.18138
A9: 13.50% | B9: =((DCF!B13/(1+0.135)^1+DCF!C13/(1+0.135)^2+DCF!D13/(1+0.135)^3+DCF!E13/(1+0.135)^4+DCF!F13/(1+0.135)^5)+DCF!F13*(1+0.03)/(0.135-0.03)/(1+0.135)^5+Assumptions!B16)/Assumptions!B6 -> 369.3015 | C9: =((DCF!B13/(1+0.135)^1+DCF!C13/(1+0.135)^2+DCF!D13/(1+0.135)^3+DCF!E13/(1+0.135)^4+DCF!F13/(1+0.135)^5)+DCF!F13*(1+0.035)/(0.135-0.035)/(1+0.135)^5+Assumptions!B16)/Assumptions!B6 -> 381.90169 | D9: =((DCF!B13/(1+0.135)^1+DCF!C13/(1+0.135)^2+DCF!D13/(1+0.135)^3+DCF!E13/(1+0.135)^4+DCF!F13/(1+0.135)^5)+DCF!F13*(1+0.04)/(0.135-0.04)/(1+0.135)^5+Assumptions!B16)/Assumptions!B6 -> 395.82821 | E9: =((DCF!B13/(1+0.135)^1+DCF!C13/(1+0.135)^2+DCF!D13/(1+0.135)^3+DCF!E13/(1+0.135)^4+DCF!F13/(1+0.135)^5)+DCF!F13*(1+0.045)/(0.135-0.045)/(1+0.135)^5+Assumptions!B16)/Assumptions!B6 -> 411.30213 | F9: =((DCF!B13/(1+0.135)^1+DCF!C13/(1+0.135)^2+DCF!D13/(1+0.135)^3+DCF!E13/(1+0.135)^4+DCF!F13/(1+0.135)^5)+DCF!F13*(1+0.05)/(0.135-0.05)/(1+0.135)^5+Assumptions!B16)/Assumptions!B6 -> 428.59651

Sheet Per-Share & Ratios
A1: Per-share & ratio dashboard
A2: Identical shape across Testahil studies.
A4: Metric | B4: 2022a | C4: 2023a | D4: 2024a | E4: 2025e
A5: EPS (SAR) | B5: 11.99 | C5: 17.46 | D5: 23.51 | E5: 28.6
A6: DPS (SAR) | B6: 5.5 | C6: 6.65 | D6: 7.29 | E6: 7.75
A7: BVPS (SAR) | B7: 38.1 | C7: 49.9 | D7: 66.2 | E7: 85
A8: Gross margin | B8: 40.6% | C8: 39.6% | D8: 40.9% | E8: ~41.3%
A9: EBIT margin | B9: 21.2% | C9: 23.0% | D9: 23.0% | E9: 23.2%
A10: Net margin | B10: 20.2% | C10: 22.9% | D10: 24.6% | E10: ~23.7%
A11: ROE (avg equity) | B11: — | C11: 38% | D11: 39% | E11: 38%
A12: ROIC | B12: ~80% | C12: ~85% | D12: ~88% | E12: ~85%
A14: Valuation at spot | B14: Trailing 2024a | C14: Forward 2025e
A15: P/E | B15: 28.0× | C15: 23.0×
A16: P/B | B16: 9.9× | C16: —
A17: EV/EBITDA | B17: 26.7× | C17: 20.1×
A18: Dividend yield | B18: 1.3% | C18: —
