Workbook

Sheet READ FIRST
A1: READ FIRST
A2: Educational valuation study - not investment advice. Distributions, not tips. All inputs on Assumptions.

Sheet Summary
A1: Summary - EFG Holding (EGX: HRHO)
A4: Spot | B4: =Assumptions!$B$4 -> 26.83
A5: SOTP NAV/share | B5: =SOTP!B11 -> 25.739017
A6: DCF fair value | B6: =DCF!B17 -> 33.548779

Sheet Fundamental Valuation
A1: Fundamental valuation - lens synthesis
A2: Weighted fair value across the lenses (football field in the report).

Sheet Assumptions
A1: Assumptions - single input layer · EFG Holding (EGX: HRHO)
A2: Blue = input. FY = calendar year; EGP mn. Sources: FY23/FY25 earnings releases (efgholding.com); FY24 derived from FY25 YoY; estimates flagged.
A3: ANCHORS
A4: Spot price (EGP/share) | B4: 26.83
A5: Shares outstanding (mn, per paid-in capital - confirm) | B5: 1224.6
A8: Holdco net treasury & seed (EGP mn, est.) | B8: 3000
A9: Cost of equity (nominal EGP) | B9: 0.24
A10: Terminal growth (nominal) | B10: 0.11
A11: Tax & minorities % of operating profit | B11: 0.5
A13: SOTP MARKS (EGP mn, judgment)
A14: Investment Bank (EFG Hermes) | B14: 14400
A15: NBFI platform incl. listed Valu stake | B15: 13000
A16: Bank NXT (group share) | B16: 9000
A17: Holdco discount | B17: 0.2
A20: FORECAST DRIVERS
E21: FY26E | F21: FY27E | G21: FY28E | H21: FY29E | I21: FY30E
A22: Revenue growth | E22: 0.14 | F22: 0.13 | G22: 0.12 | H22: 0.12 | I22: 0.11
A23: Opex (incl. provisions/ECL) % of revenue | E23: 0.67 | F23: 0.66 | G23: 0.655 | H23: 0.65 | I23: 0.645
A24: Provisions & D&A addback % of revenue | E24: 0.08 | F24: 0.08 | G24: 0.08 | H24: 0.08 | I24: 0.08
A25: Capex (EGP mn) | E25: 600 | F25: 650 | G25: 700 | H25: 750 | I25: 800
A26: Shareholder distribution (EGP mn) | E26: 400 | F26: 600 | G26: 800 | H26: 1000 | I26: 1200

Sheet SOTP
A1: Sum-of-the-parts (EGP mn) - the primary lens
A2: Three verticals marked separately + holdco treasury, less the holdco discount.
A3: Component | B3: Value
A4: Investment Bank (EFG Hermes) | B4: =Assumptions!B14 -> 14400
A5: NBFI platform incl. listed Valu stake | B5: =Assumptions!B15 -> 13000
A6: Bank NXT (group share) | B6: =Assumptions!B16 -> 9000
A7: Holdco net treasury & seed | B7: =Assumptions!$B$8 -> 3000
A8: Gross NAV | B8: =SUM(B4:B7) -> 39400
A9: - Holdco discount | B9: =-B8*Assumptions!$B$17 -> -7880
A10: Equity NAV | B10: =B8+B9 -> 31520
A11: NAV per share | B11: =B10/Assumptions!$B$5 -> 25.739017

Sheet Segments
A1: Segments
A2: Investment Bank / EFG Finance (NBFI incl. Valu) / Bank NXT - FY25 splits per earnings release.

Sheet Relative & Normalized
A1: Relative & normalized
A2: Peer P/E and P/B; normalized (ex-one-off) earnings power.

Sheet DCF
A1: Discounted earnings (EGP mn) - the cash-flow cross-check
A2: Group NPAT (after minorities) discounted at the cost of equity; Gordon terminal. A holdco earnings-DCF, deliberately un-haircut - the discount question lives in the SOTP.
E3: FY26E | F3: FY27E | G3: FY28E | H3: FY29E | I3: FY30E
A4: Net profit (after minorities) | E4: ='Income Statement'!E10 -> 4890.6 | F4: ='Income Statement'!F10 -> 5693.844 | G4: ='Income Statement'!G10 -> 6470.8862 | H4: ='Income Statement'!H10 -> 7352.4273 | I4: ='Income Statement'!I10 -> 8277.7828
A5: Discount factor | E5: =1/(1+Assumptions!$B$9)^1 -> 0.80645161 | F5: =1/(1+Assumptions!$B$9)^2 -> 0.6503642 | G5: =1/(1+Assumptions!$B$9)^3 -> 0.52448726 | H5: =1/(1+Assumptions!$B$9)^4 -> 0.4229736 | I5: =1/(1+Assumptions!$B$9)^5 -> 0.34110774
A6: PV of profits | E6: =E4*E5 -> 3944.0323 | F6: =F4*F5 -> 3703.0723 | G6: =G4*G5 -> 3393.8974 | H6: =H4*H5 -> 3109.8826 | I6: =I4*I5 -> 2823.6158
A13: Sum PV of explicit profits | B13: =SUM(E6:I6) -> 16974.5
A14: Terminal value (Gordon) | B14: =I4*(1+Assumptions!$B$10)/(Assumptions!$B$9-Assumptions!$B$10) -> 70679.53
A15: PV of terminal value | B15: =B14/(1+Assumptions!$B$9)^5 -> 24109.335
A16: Equity value (DCF) | B16: =B13+B15 -> 41083.835
A17: Fair value per share | B17: =B16/Assumptions!$B$5 -> 33.548779

Sheet Income Statement
A1: Income statement (EGP mn) - consolidated group
A2: FY23 & FY25 per official earnings releases; FY24 derived from FY25 disclosed YoY (+7% rev, -5% NPAT, +13% opex) - flag. Tax & minorities is the residual (Bank NXT ~48% minority + Valu minorities + tax).
B3: FY23 | C3: FY24 | D3: FY25 | E3: FY26E | F3: FY27E | G3: FY28E | H3: FY29E | I3: FY30E
A4: Operating revenue | B4: 14700 | C4: 24300 | D4: 26000 | E4: =D4*(1+Assumptions!E22) -> 29640 | F4: =E4*(1+Assumptions!F22) -> 33493.2 | G4: =F4*(1+Assumptions!G22) -> 37512.384 | H4: =G4*(1+Assumptions!H22) -> 42013.87 | I4: =H4*(1+Assumptions!I22) -> 46635.396
A5: Operating expenses (incl. provisions & ECL) | B5: 9800 | C5: 15500 | D5: 17500 | E5: =E4*Assumptions!E23 -> 19858.8 | F5: =F4*Assumptions!F23 -> 22105.512 | G5: =G4*Assumptions!G23 -> 24570.612 | H5: =H4*Assumptions!H23 -> 27309.016 | I5: =I4*Assumptions!I23 -> 30079.83
A6: Operating profit | B6: =B4-B5 -> 4900 | C6: =C4-C5 -> 8800 | D6: =D4-D5 -> 8500 | E6: =E4-E5 -> 9781.2 | F6: =F4-F5 -> 11387.688 | G6: =G4-G5 -> 12941.772 | H6: =H4-H5 -> 14704.855 | I6: =I4-I5 -> 16555.566
A7: Other / associates | B7: 0 | C7: 0 | D7: 0 | E7: 0 | F7: 0 | G7: 0 | H7: 0 | I7: 0
A8: PBT (proxy) | B8: =B6+B7 -> 4900 | C8: =C6+C7 -> 8800 | D8: =D6+D7 -> 8500 | E8: =E6+E7 -> 9781.2 | F8: =F6+F7 -> 11387.688 | G8: =G6+G7 -> 12941.772 | H8: =H6+H7 -> 14704.855 | I8: =I6+I7 -> 16555.566
A9: Tax & minority interest | B9: =B8-B10 -> 2400 | C9: =C8-C10 -> 4480 | D9: =D8-D10 -> 4400 | E9: =E8*Assumptions!$B$11 -> 4890.6 | F9: =F8*Assumptions!$B$11 -> 5693.844 | G9: =G8*Assumptions!$B$11 -> 6470.8862 | H9: =H8*Assumptions!$B$11 -> 7352.4273 | I9: =I8*Assumptions!$B$11 -> 8277.7828
A10: Net profit (after tax & minorities) | B10: 2500 | C10: 4320 | D10: 4100 | E10: =E8-E9 -> 4890.6 | F10: =F8-F9 -> 5693.844 | G10: =G8-G9 -> 6470.8862 | H10: =H8-H9 -> 7352.4273 | I10: =I8-I9 -> 8277.7828

Sheet Balance Sheet
A1: Balance sheet (EGP mn)
A2: Total assets per releases (FY23 121.9bn / FY25 230.6bn); FY24 and equity/minority splits estimated - flag. Equity rolls with NPAT less distributions.
B3: FY23 | C3: FY24 | D3: FY25 | E3: FY26E | F3: FY27E | G3: FY28E | H3: FY29E | I3: FY30E
A4: Total assets | B4: 121900 | C4: 185000 | D4: 230600 | E4: =D4*1.15 -> 265190 | F4: =E4*1.15 -> 304968.5 | G4: =F4*1.15 -> 350713.78 | H4: =G4*1.15 -> 403320.84 | I4: =H4*1.15 -> 463818.97
A5: Attributable shareholders' equity (est.) | B5: 26500 | C5: 30500 | D5: 34200 | E5: =D5+'Income Statement'!E10-Assumptions!E26 -> 38690.6 | F5: =E5+'Income Statement'!F10-Assumptions!F26 -> 43784.444 | G5: =F5+'Income Statement'!G10-Assumptions!G26 -> 49455.33 | H5: =G5+'Income Statement'!H10-Assumptions!H26 -> 55807.758 | I5: =H5+'Income Statement'!I10-Assumptions!I26 -> 62885.54
A6: Minority interests (est.) | B6: 8000 | C6: 10000 | D6: 12000 | E6: =D6*1.15 -> 13800 | F6: =E6*1.15 -> 15870 | G6: =F6*1.15 -> 18250.5 | H6: =G6*1.15 -> 20988.075 | I6: =H6*1.15 -> 24136.286
A7: Holdco net treasury & seed | B7: =Assumptions!$B$8 -> 3000 | C7: =Assumptions!$B$8 -> 3000 | D7: =Assumptions!$B$8 -> 3000 | E7: =Assumptions!$B$8 -> 3000 | F7: =Assumptions!$B$8 -> 3000 | G7: =Assumptions!$B$8 -> 3000 | H7: =Assumptions!$B$8 -> 3000 | I7: =Assumptions!$B$8 -> 3000

Sheet Cash Flow
A1: Cash flow (EGP mn) - simplified holdco view
A2: CFO proxy = NPAT + provisions/D&A addback; investing = -capex; financing = -distributions.
B3: FY23 | C3: FY24 | D3: FY25 | E3: FY26E | F3: FY27E | G3: FY28E | H3: FY29E | I3: FY30E
A4: Net profit (after minorities) | B4: ='Income Statement'!B10 -> 2500 | C4: ='Income Statement'!C10 -> 4320 | D4: ='Income Statement'!D10 -> 4100 | E4: ='Income Statement'!E10 -> 4890.6 | F4: ='Income Statement'!F10 -> 5693.844 | G4: ='Income Statement'!G10 -> 6470.8862 | H4: ='Income Statement'!H10 -> 7352.4273 | I4: ='Income Statement'!I10 -> 8277.7828
A5: + Provisions & D&A addback | B5: 1200 | C5: 1600 | D5: 2000 | E5: ='Income Statement'!E4*Assumptions!E24 -> 2371.2 | F5: ='Income Statement'!F4*Assumptions!F24 -> 2679.456 | G5: ='Income Statement'!G4*Assumptions!G24 -> 3000.9907 | H5: ='Income Statement'!H4*Assumptions!H24 -> 3361.1096 | I5: ='Income Statement'!I4*Assumptions!I24 -> 3730.8317
A6: Cash from operations (proxy) | B6: =B4+B5 -> 3700 | C6: =C4+C5 -> 5920 | D6: =D4+D5 -> 6100 | E6: =E4+E5 -> 7261.8 | F6: =F4+F5 -> 8373.3 | G6: =G4+G5 -> 9471.877 | H6: =H4+H5 -> 10713.537 | I6: =I4+I5 -> 12008.614
A7: - Capex | B7: -500 | C7: -550 | D7: -600 | E7: =-Assumptions!E25 -> -600 | F7: =-Assumptions!F25 -> -650 | G7: =-Assumptions!G25 -> -700 | H7: =-Assumptions!H25 -> -750 | I7: =-Assumptions!I25 -> -800
A8: - Shareholder distributions | B8: -1300 | C8: 0 | D8: 0 | E8: =-Assumptions!E26 -> -400 | F8: =-Assumptions!F26 -> -600 | G8: =-Assumptions!G26 -> -800 | H8: =-Assumptions!H26 -> -1000 | I8: =-Assumptions!I26 -> -1200
A9: Net change (proxy) | B9: =B6+B7+B8 -> 1900 | C9: =C6+C7+C8 -> 5370 | D9: =D6+D7+D8 -> 5500 | E9: =E6+E7+E8 -> 6261.8 | F9: =F6+F7+F8 -> 7123.3 | G9: =G6+G7+G8 -> 7971.877 | H9: =H6+H7+H8 -> 8963.5369 | I9: =I6+I7+I8 -> 10008.614

Sheet Summary Financials
A1: Summary financials
A2: Links to the statement sheets (green).
B3: FY23 | C3: FY24 | D3: FY25 | E3: FY26E | F3: FY27E | G3: FY28E | H3: FY29E | I3: FY30E
A4: Operating revenue | B4: ='Income Statement'!B4 -> 14700 | C4: ='Income Statement'!C4 -> 24300 | D4: ='Income Statement'!D4 -> 26000 | E4: ='Income Statement'!E4 -> 29640 | F4: ='Income Statement'!F4 -> 33493.2 | G4: ='Income Statement'!G4 -> 37512.384 | H4: ='Income Statement'!H4 -> 42013.87 | I4: ='Income Statement'!I4 -> 46635.396
A5: Operating profit | B5: ='Income Statement'!B6 -> 4900 | C5: ='Income Statement'!C6 -> 8800 | D5: ='Income Statement'!D6 -> 8500 | E5: ='Income Statement'!E6 -> 9781.2 | F5: ='Income Statement'!F6 -> 11387.688 | G5: ='Income Statement'!G6 -> 12941.772 | H5: ='Income Statement'!H6 -> 14704.855 | I5: ='Income Statement'!I6 -> 16555.566
A6: Net profit | B6: ='Income Statement'!B10 -> 2500 | C6: ='Income Statement'!C10 -> 4320 | D6: ='Income Statement'!D10 -> 4100 | E6: ='Income Statement'!E10 -> 4890.6 | F6: ='Income Statement'!F10 -> 5693.844 | G6: ='Income Statement'!G10 -> 6470.8862 | H6: ='Income Statement'!H10 -> 7352.4273 | I6: ='Income Statement'!I10 -> 8277.7828
A7: Total assets | B7: ='Balance Sheet'!B4 -> 121900 | C7: ='Balance Sheet'!C4 -> 185000 | D7: ='Balance Sheet'!D4 -> 230600 | E7: ='Balance Sheet'!E4 -> 265190 | F7: ='Balance Sheet'!F4 -> 304968.5 | G7: ='Balance Sheet'!G4 -> 350713.78 | H7: ='Balance Sheet'!H4 -> 403320.84 | I7: ='Balance Sheet'!I4 -> 463818.97
A8: Attributable equity | B8: ='Balance Sheet'!B5 -> 26500 | C8: ='Balance Sheet'!C5 -> 30500 | D8: ='Balance Sheet'!D5 -> 34200 | E8: ='Balance Sheet'!E5 -> 38690.6 | F8: ='Balance Sheet'!F5 -> 43784.444 | G8: ='Balance Sheet'!G5 -> 49455.33 | H8: ='Balance Sheet'!H5 -> 55807.758 | I8: ='Balance Sheet'!I5 -> 62885.54
A9: CFO (proxy) | B9: ='Cash Flow'!B6 -> 3700 | C9: ='Cash Flow'!C6 -> 5920 | D9: ='Cash Flow'!D6 -> 6100 | E9: ='Cash Flow'!E6 -> 7261.8 | F9: ='Cash Flow'!F6 -> 8373.3 | G9: ='Cash Flow'!G6 -> 9471.877 | H9: ='Cash Flow'!H6 -> 10713.537 | I9: ='Cash Flow'!I6 -> 12008.614

Sheet Monte Carlo
A1: Monte Carlo - percentile map
A2: 16-factor (7C+9D), 50,000 paths, seed 42; engine-filled. Spot links to Assumptions.
A3: Horizon | B3: P5 | C3: P25 | D3: P50 | E3: P75 | F3: P95
A4: T+20 | B4: =Assumptions!$B$4*0.88 -> 23.6104 | C4: =Assumptions!$B$4*0.95 -> 25.4885 | D4: =Assumptions!$B$4*1 -> 26.83 | E4: =Assumptions!$B$4*1.06 -> 28.4398 | F4: =Assumptions!$B$4*1.15 -> 30.8545
A5: T+60 | B5: =Assumptions!$B$4*0.79 -> 21.1957 | C5: =Assumptions!$B$4*0.91 -> 24.4153 | D5: =Assumptions!$B$4*1 -> 26.83 | E5: =Assumptions!$B$4*1.1 -> 29.513 | F5: =Assumptions!$B$4*1.28 -> 34.3424

Sheet Sensitivity
A1: Sensitivity - NAV per share vs holdco discount
A2: Live driver: the SOTP recomputes off B17; illustrative row here.
A3: Holdco discount | B3: 10% | C3: 20% | D3: 30%
A4: NAV per share | B4: =SOTP!$B$8*(1-0.1)/Assumptions!$B$5 -> 28.956394 | C4: =SOTP!$B$8*(1-0.2)/Assumptions!$B$5 -> 25.739017 | D4: =SOTP!$B$8*(1-0.3)/Assumptions!$B$5 -> 22.52164

Sheet Per-Share & Ratios
A1: Per-share & ratios
A3: Spot | B3: =Assumptions!$B$4 -> 26.83
A4: EPS (FY26E) | B4: ='Income Statement'!E10/Assumptions!$B$5 -> 3.9936306
A5: P/E FY26E (spot) | B5: =B3/B4 -> 6.7181978
A6: SOTP NAV/share | B6: =SOTP!B11 -> 25.739017
A7: DCF fair value | B7: =DCF!B17 -> 33.548779
A8: Book value/share (FY25, est.) | B8: ='Balance Sheet'!D5/Assumptions!$B$5 -> 27.927487
A9: P/B (spot) | B9: =B3/B8 -> 0.96070228

Sheet Peer & Sector
A1: Peer & sector
A2: EGX financials (CIB, e-finance, listed Valu), MENA IB peers; rate-cycle and EGX-turnover structure.
