Workbook

Sheet READ FIRST
A1: Testahil — NVIDIA Corporation (NASDAQ: NVDA)
A2: Companion model · Independent Valuation Study · Educational analysis · Not investment advice
A5: What this workbook is. A transparent companion to the NVDA valuation study. Every blue cell is an input; every
A6: black cell is a formula; green cells link across sheets. All inputs live on the Assumptions sheet — change one
A7: (a growth rate, the WACC, a multiple) and the whole model reprices.
A9: What it is not. It is not investment advice, a recommendation, or a price target. Values are model outputs shown
A10: as ranges. The preparer is not licensed by any securities regulator and may hold a position in the security.
A12: Primary lens. NVDA is valued on a discounted-cash-flow basis (DCF), cross-checked with forward relative multiples,
A13: a forward-earnings-power read, and a reverse-DCF. Data Center is ~90% of revenue and is the whole thesis.
A15: Currency & fiscal year. US$ millions unless stated; fiscal year ends late January (FY26 ended 25 Jan 2026).
A16: Spot $196.44 (6 Jul 2026). ~24.3bn diluted shares → market cap ~$4.77tn. Net cash ~$54bn; strategic equity ~$22bn.
A17: Historicals are company disclosure (FY26 10-K, 25 Feb 2026); some balance-sheet lines plug to disclosed totals.
... A21: Sensitivity · Per-Share & Ratios · Peer & Sector.

Sheet Summary
A1: Valuation summary — NVIDIA Corporation (NASDAQ: NVDA)
A2: Three-lens fair value vs spot. Base links live; bear/bull are scenario outputs (see study §1.5).
B3: Bear | C3: Base | D3: Bull | E3: Weight
A4: DCF (primary) | B4: 146 | C4: ='DCF (Primary)'!B21 | D4: 291 | E4: =Assumptions!$B$40
A5: Relative multiples | B5: 129 | C5: ='Relative & Normalized'!C4 | D5: 256 | E5: =Assumptions!$B$41
A6: Forward earnings | B6: 164 | C6: ='Relative & Normalized'!C7 | D6: 306 | E6: =Assumptions!$B$42
A7: Weighted central | B7: =SUMPRODUCT(B4:B6,E4:E6) | C7: =SUMPRODUCT(C4:C6,E4:E6) | D7: =SUMPRODUCT(D4:D6,E4:E6)
A9: Spot price ($) | C9: =Assumptions!$B$4
A10: Upside to central base | C10: =C7/C9-1
A12: Read: roughly fairly valued; the swing factor is the durability of the AI data-center compute cycle.

Sheet Fundamental Valuation
A1: Fundamental valuation — football-field data
A2: Bear/base/bull per lens (links to Summary).
A3: Lens | B3: Bear | C3: Base | D3: Bull
A4: DCF (primary) | B4: =Summary!B4 | C4: =Summary!C4 | D4: =Summary!D4
A5: Relative multiples | B5: =Summary!B5 | C5: =Summary!C5 | D5: =Summary!D5
A6: Forward earnings | B6: =Summary!B6 | C6: =Summary!C6 | D6: =Summary!D6
A7: Weighted central | B7: =Summary!B7 | C7: =Summary!C7 | D7: =Summary!D7
A8: Spot | C8: =Assumptions!$B$4

Sheet Assumptions
A1: Assumptions — the single input layer
A2: All blue cells are inputs. Every other sheet links here.
A3: ANCHORS
A4: Spot price ($/share) | B4: 196.44
A5: Diluted shares (mn) | B5: 24300
A6: Net cash (cash+securities − debt, $m) | B6: 54093
A7: Strategic equity investments ($m) | B7: 22251
A8: Risk-free rate (rf) | B8: 0.043
A9: Equity risk premium (ERP) | B9: 0.048
A10: Beta (house band 0.8–1.3) | B10: 1.3
A11: WACC = rf + beta×ERP (net cash → =Ke) | B11: =B8+B10*B9
A12: Terminal growth | B12: 0.045
A13: Tax rate | B13: 0.16
A15: RELATIVE & NORMALIZED
A16: Forward EV/EBITDA multiple (FY27E) | B16: 20
A17: Forward P/E multiple (FY27E) | B17: 24
A18: Forward-earnings P/E (FY28E) | B18: 21
A20: SYNTHESIS WEIGHTS
A22: WORKING CAPITAL (% of revenue, forecast)
A23: Accounts receivable | B23: 0.178
A24: Inventories | B24: 0.099
A25: Accounts payable | B25: 0.03
A27: MONTE CARLO
A28: Diffusion volatility σ (YZ-HAR, ann.) | B28: 0.451
A29: Net continuous factor drift (3m) | B29: 0
A30: Paths / seed | B30: 50000 | C30: seed 42
A40: DCF weight | B40: 0.45
A41: Relative weight | B41: 0.25
A42: Forward-earnings weight | B42: 0.3
A44: FORECAST DRIVERS (FY27E–FY31E) | E44: FY27E | F44: FY28E | G44: FY29E | H44: FY30E | I44: FY31E
A45: Data-center revenue growth | E45: 0.73 | F45: 0.34 | G45: 0.23 | H45: 0.15 | I45: 0.09
A46: Non-DC revenue growth | E46: 0.17 | F46: 0.12 | G46: 0.1 | H46: 0.08 | I46: 0.06
A47: Gross margin | E47: 0.745 | F47: 0.74 | G47: 0.73 | H47: 0.72 | I47: 0.71
A48: Opex % of revenue | E48: 0.1 | F48: 0.1 | G48: 0.105 | H48: 0.11 | I48: 0.115
A49: D&A % of revenue | E49: 0.015 | F49: 0.015 | G49: 0.015 | H49: 0.016 | I49: 0.016
A50: Capex % of revenue | E50: 0.025 | F50: 0.025 | G50: 0.026 | H50: 0.027 | I50: 0.028
A51: Other income (net, $m) | E51: 10000 | F51: 10500 | G51: 11000 | H51: 11500 | I51: 12000
A52: Dividends ($m) | E52: 6100 | F52: 7500 | G52: 9000 | H52: 11000 | I52: 13000
A53: Net buybacks ($m) | E53: 70000 | F53: 75000 | G53: 80000 | H53: 85000 | I53: 90000

Sheet DCF (Primary)
A1: Discounted cash flow — primary lens (explicit 5-year FCFF)
A2: NOPAT + D&A − capex − ΔWC, discounted at WACC (=Ke, net cash). Links to Income Statement / Balance Sheet / Assumptions.
E3: FY27E | F3: FY28E | G3: FY29E | H3: FY30E | I3: FY31E
A4: Revenue | E4: ='Income Statement'!E6 | F4: ='Income Statement'!F6 | G4: ='Income Statement'!G6 | H4: ='Income Statement'!H6 | I4: ='Income Statement'!I6
A5: EBITDA | E5: ='Income Statement'!E14 | F5: ='Income Statement'!F14 | G5: ='Income Statement'!G14 | H5: ='Income Statement'!H14 | I5: ='Income Statement'!I14
A6: − D&A | E6: =-'Income Statement'!E13 | F6: =-'Income Statement'!F13 | G6: =-'Income Statement'!G13 | H6: =-'Income Statement'!H13 | I6: =-'Income Statement'!I13
A7: EBIT | E7: ='Income Statement'!E11 | F7: ='Income Statement'!F11 | G7: ='Income Statement'!G11 | H7: ='Income Statement'!H11 | I7: ='Income Statement'!I11
A8: NOPAT = EBIT×(1−tax) | E8: =E7*(1-Assumptions!$B$13) | F8: =F7*(1-Assumptions!$B$13) | G8: =G7*(1-Assumptions!$B$13) | H8: =H7*(1-Assumptions!$B$13) | I8: =I7*(1-Assumptions!$B$13)
A9: + D&A | E9: ='Income Statement'!E13 | F9: ='Income Statement'!F13 | G9: ='Income Statement'!G13 | H9: ='Income Statement'!H13 | I9: ='Income Statement'!I13
A10: − Capex | E10: =-Assumptions!E50*'Income Statement'!E6 | F10: =-Assumptions!F50*'Income Statement'!F6 | G10: =-Assumptions!G50*'Income Statement'!G6 | H10: =-Assumptions!H50*'Income Statement'!H6 | I10: =-Assumptions!I50*'Income Statement'!I6
A11: − Increase in net working capital | E11: =-(('Balance Sheet'!E5+'Balance Sheet'!E6-'Balance Sheet'!E14)-('Balance Sheet'!D5+'Balance Sheet'!D6-'Balance Sheet'!D14)) | F11: =-(('Balance Sheet'!F5+'Balance Sheet'!F6-'Balance Sheet'!F14)-('Balance Sheet'!E5+'Balance Sheet'!E6-'Balance Sheet'!E14)) | G11: =-(('Balance Sheet'!G5+'Balance Sheet'!G6-'Balance Sheet'!G14)-('Balance Sheet'!F5+'Balance Sheet'!F6-'Balance Sheet'!F14)) | H11: =-(('Balance Sheet'!H5+'Balance Sheet'!H6-'Balance Sheet'!H14)-('Balance Sheet'!G5+'Balance Sheet'!G6-'Balance Sheet'!G14)) | I11: =-(('Balance Sheet'!I5+'Balance Sheet'!I6-'Balance Sheet'!I14)-('Balance Sheet'!H5+'Balance Sheet'!H6-'Balance Sheet'!H14))
A12: Free cash flow to firm (FCFF) | E12: =E8+E9+E10+E11 | F12: =F8+F9+F10+F11 | G12: =G8+G9+G10+G11 | H12: =H8+H9+H10+H11 | I12: =I8+I9+I10+I11
A13: Discount factor | E13: =1/(1+Assumptions!$B$11)^1 | F13: =1/(1+Assumptions!$B$11)^2 | G13: =1/(1+Assumptions!$B$11)^3 | H13: =1/(1+Assumptions!$B$11)^4 | I13: =1/(1+Assumptions!$B$11)^5
A14: PV of FCFF | E14: =E12*E13 | F14: =F12*F13 | G14: =G12*G13 | H14: =H12*H13 | I14: =I12*I13
A16: Σ PV of explicit FCFF (FY27–31) | B16: =SUM(E14:I14)
A17: Terminal value (Gordon, on FY31 FCFF) | B17: =I12*(1+Assumptions!$B$12)/(Assumptions!$B$11-Assumptions!$B$12)
A18: PV of terminal value | B18: =B17/(1+Assumptions!$B$11)^5
A19: Enterprise value | B19: =B16+B18
A20: + Net cash + strategic investments | B20: =Assumptions!$B$6+Assumptions!$B$7
A21: Equity value → per share ($) | B21: =(B19+B20)/Assumptions!$B$5
A22: Terminal value as % of EV | B22: =B18/B19
A23: Implied EV / FY27E EBITDA | B23: =B19/'Income Statement'!E14

Sheet Segments
A1: Segment view
A2: Revenue and mix by segment, FY24–FY31 (links to Income Statement).
B3: FY24 | C3: FY25 | D3: FY26 | E3: FY27E | F3: FY28E | G3: FY29E | H3: FY30E | I3: FY31E
A4: Data Center revenue | B4: ='Income Statement'!B4 | C4: ='Income Statement'!C4 | D4: ='Income Statement'!D4 | E4: ='Income Statement'!E4 | F4: ='Income Statement'!F4 | G4: ='Income Statement'!G4 | H4: ='Income Statement'!H4 | I4: ='Income Statement'!I4
A5: Non-DC revenue | B5: ='Income Statement'!B5 | C5: ='Income Statement'!C5 | D5: ='Income Statement'!D5 | E5: ='Income Statement'!E5 | F5: ='Income Statement'!F5 | G5: ='Income Statement'!G5 | H5: ='Income Statement'!H5 | I5: ='Income Statement'!I5
A6: Total revenue | B6: =B4+B5 | C6: =C4+C5 | D6: =D4+D5 | E6: =E4+E5 | F6: =F4+F5 | G6: =G4+G5 | H6: =H4+H5 | I6: =I4+I5
A7: Data Center % of revenue | B7: =B4/B6 | C7: =C4/C6 | D7: =D4/D6 | E7: =E4/E6 | F7: =F4/F6 | G7: =G4/G6 | H7: =H4/H6 | I7: =I4/I6
A8: Data Center YoY growth | C8: =C4/B4-1 | D8: =D4/C4-1 | E8: =E4/D4-1 | F8: =F4/E4-1 | G8: =G4/F4-1 | H8: =H4/G4-1 | I8: =I4/H4-1
A9: Total revenue YoY growth | C9: =C6/B6-1 | D9: =D6/C6-1 | E9: =E6/D6-1 | F9: =F6/E6-1 | G9: =G6/F6-1 | H9: =H6/G6-1 | I9: =I6/H6-1

Sheet Relative & Normalized
A1: Relative & forward-earnings lenses
A2: Market-consistent forward multiples. Links to Assumptions / Income Statement.
A3: Lens | B3: Workings | C3: $/share
A4: Relative (blend) | B4: 0.5×EV/EBITDA + 0.5×P/E, FY27E | C4: =0.5*(('Income Statement'!E14*Assumptions!$B$16+Assumptions!$B$6+Assumptions!$B$7)/Assumptions!$B$5)+0.5*('Income Statement'!E20*Assumptions!$B$17)
A5: EV/EBITDA value | C5: =('Income Statement'!E14*Assumptions!$B$16+Assumptions!$B$6+Assumptions!$B$7)/Assumptions!$B$5
A6: P/E value | C6: ='Income Statement'!E20*Assumptions!$B$17
A7: Forward earnings power | B7: FY28E EPS × justified P/E | C7: ='Income Statement'!F20*Assumptions!$B$18
A8: FY28E EPS ($) | C8: ='Income Statement'!F20

Sheet DCF Scenarios & ROIC
A1: DCF scenarios & economic-profit (ROIC vs WACC)
A2: Bear/base/bull DCF outputs and the return-on-capital check (supports the cash-returns expert).
A3: Scenario | B3: WACC | C3: Term. g | D3: $/share
A4: Bull | B4: 0.09 | C4: 0.05 | D4: 291
A5: Base (live) | B5: =Assumptions!$B$11 | C5: =Assumptions!$B$12 | D5: ='DCF (Primary)'!B21
A6: Bear | B6: 0.125 | C6: 0.035 | D6: 146
A8: Economic-profit / return-on-capital check
A9: NOPAT (FY26 actual = EBIT×(1−t), $m) | B9: ='Income Statement'!D11*(1-Assumptions!$B$13)
A10: Capital employed (equity + debt, FY26, $m) | B10: ='Balance Sheet'!D12+'Balance Sheet'!D13
A11: Return on capital employed (NOPAT / capital) | B11: =B9/B10
A12: WACC (= Ke, net cash) | B12: =Assumptions!$B$11
A13: Economic-profit spread (ROCE − WACC) | B13: =B11-B12
A15: Capital employed uses the full balance-sheet base (equity + debt), so the ~$62bn net cash conservatively depresses the ratio; netting excess cash lifts it materially higher. Either way the return runs many multiples of the 10.5% cost of capital — the cash-returns expert's core point.
A16: Reverse-DCF: FCF CAGR implied by spot ≈ 12% (see study §1.2). The market pays for a longer super-normal runway than the 5-yr explicit window.

Sheet Income Statement
A1: Income statement ($m, GAAP, fiscal year ends late Jan)
A2: FY24–FY26 disclosed (blue); FY27–FY31 forecast (formulas linking to Assumptions).
B3: FY24 | C3: FY25 | D3: FY26 | E3: FY27E | F3: FY28E | G3: FY29E | H3: FY30E | I3: FY31E
A4: Data Center revenue | B4: 47525 | C4: 115186 | D4: 193737 | E4: =D4*(1+Assumptions!E45) | F4: =E4*(1+Assumptions!F45) | G4: =F4*(1+Assumptions!G45) | H4: =G4*(1+Assumptions!H45) | I4: =H4*(1+Assumptions!I45)
A5: Non-DC revenue (Gaming/ProViz/Auto/OEM) | B5: 13397 | C5: 15311 | D5: 22201 | E5: =D5*(1+Assumptions!E46) | F5: =E5*(1+Assumptions!F46) | G5: =F5*(1+Assumptions!G46) | H5: =G5*(1+Assumptions!H46) | I5: =H5*(1+Assumptions!I46)
A6: Total revenue | B6: =B4+B5 | C6: =C4+C5 | D6: =D4+D5 | E6: =E4+E5 | F6: =F4+F5 | G6: =G4+G5 | H6: =H4+H5 | I6: =I4+I5
A8: Gross profit | B8: 44290 | C8: 97873 | D8: 153532 | E8: =E6*Assumptions!E47 | F8: =F6*Assumptions!F47 | G8: =G6*Assumptions!G47 | H8: =H6*Assumptions!H47 | I8: =I6*Assumptions!I47
A9: Gross margin | B9: =B8/B6 | C9: =C8/C6 | D9: =D8/D6 | E9: =E8/E6 | F9: =F8/F6 | G9: =G8/G6 | H9: =H8/H6 | I9: =I8/I6
A10: Operating expenses (R&D + SG&A) | B10: 11318 | C10: 16420 | D10: 23132 | E10: =E6*Assumptions!E48 | F10: =F6*Assumptions!F48 | G10: =G6*Assumptions!G48 | H10: =H6*Assumptions!H48 | I10: =I6*Assumptions!I48
A11: Operating income (EBIT) | B11: =B8-B10 | C11: =C8-C10 | D11: =D8-D10 | E11: =E8-E10 | F11: =F8-F10 | G11: =G8-G10 | H11: =H8-H10 | I11: =I8-I10
A12: Operating margin | B12: =B11/B6 | C12: =C11/C6 | D12: =D11/D6 | E12: =E11/E6 | F12: =F11/F6 | G12: =G11/G6 | H12: =H11/H6 | I12: =I11/I6
A13: Depreciation & amortization | B13: 1508 | C13: 1864 | D13: 3000 | E13: =E6*Assumptions!E49 | F13: =F6*Assumptions!F49 | G13: =G6*Assumptions!G49 | H13: =H6*Assumptions!H49 | I13: =I6*Assumptions!I49
A14: EBITDA | B14: =B11+B13 | C14: =C11+C13 | D14: =D11+D13 | E14: =E11+E13 | F14: =F11+F13 | G14: =G11+G13 | H14: =H11+H13 | I14: =I11+I13
A15: EBITDA margin | B15: =B14/B6 | C15: =C14/C6 | D15: =D14/D6 | E15: =E14/E6 | F15: =F14/F6 | G15: =G14/G6 | H15: =H14/H6 | I15: =I14/I6
A16: Other income (net int.+investments) | B16: 848 | C16: 2607 | D16: 9200 | E16: =Assumptions!E51 | F16: =Assumptions!F51 | G16: =Assumptions!G51 | H16: =Assumptions!H51 | I16: =Assumptions!I51
A17: Pre-tax income (PBT) | B17: =B11+B16 | C17: =C11+C16 | D17: =D11+D16 | E17: =E11+E16 | F17: =F11+F16 | G17: =G11+G16 | H17: =H11+H16 | I17: =I11+I16
A18: Tax | B18: 4062 | C18: 11180 | D18: 19533 | E18: =E17*Assumptions!$B$13 | F18: =F17*Assumptions!$B$13 | G18: =G17*Assumptions!$B$13 | H18: =H17*Assumptions!$B$13 | I18: =I17*Assumptions!$B$13
A19: Net income (GAAP) | B19: =B17-B18 | C19: =C17-C18 | D19: =D17-D18 | E19: =E17-E18 | F19: =F17-F18 | G19: =G17-G18 | H19: =H17-H18 | I19: =I17-I18
A20: Diluted EPS ($) | B20: 1.19 | C20: 2.94 | D20: 4.9 | E20: =E19/Assumptions!$B$5 | F20: =F19/Assumptions!$B$5 | G20: =G19/Assumptions!$B$5 | H20: =H19/Assumptions!$B$5 | I20: =I19/Assumptions!$B$5
A22: Source: NVDA FY26 10-K (25 Feb 2026); Q1 FY27 print $81.6bn and Q2 guide $91bn frame the forecast. Forecast = formulas.

Sheet Balance Sheet
A1: Balance sheet ($m)
A2: Historicals anchored to disclosed lines; PP&E/goodwill plugs to disclosed totals; forecast rolls forward.
B3: FY24 | C3: FY25 | D3: FY26 | E3: FY27E | F3: FY28E | G3: FY29E | H3: FY30E | I3: FY31E
A4: Cash & equivalents + marketable securities | B4: 25984 | C4: 43210 | D4: 62556 | E4: =D4+('Cash Flow'!E9)-Assumptions!E52-Assumptions!E53 | F4: =E4+('Cash Flow'!F9)-Assumptions!F52-Assumptions!F53 | G4: =F4+('Cash Flow'!G9)-Assumptions!G52-Assumptions!G53 | H4: =G4+('Cash Flow'!H9)-Assumptions!H52-Assumptions!H53 | I4: =H4+('Cash Flow'!I9)-Assumptions!I52-Assumptions!I53
A5: Accounts receivable | B5: 9999 | C5: 23065 | D5: 38466 | E5: ='Income Statement'!E6*Assumptions!$B$23 | F5: ='Income Statement'!F6*Assumptions!$B$23 | G5: ='Income Statement'!G6*Assumptions!$B$23 | H5: ='Income Statement'!H6*Assumptions!$B$23 | I5: ='Income Statement'!I6*Assumptions!$B$23
A6: Inventories | B6: 5282 | C6: 10080 | D6: 21403 | E6: ='Income Statement'!E6*Assumptions!$B$24 | F6: ='Income Statement'!F6*Assumptions!$B$24 | G6: ='Income Statement'!G6*Assumptions!$B$24 | H6: ='Income Statement'!H6*Assumptions!$B$24 | I6: ='Income Statement'!I6*Assumptions!$B$24
A7: Strategic & other assets | B7: 6000 | C7: 17000 | D7: 44000 | E7: =D7 | F7: =E7 | G7: =F7 | H7: =G7 | I7: =H7
A8: PP&E, goodwill & intangibles (plug) | B8: =(B12+B13+B14+B15+B16)-(B4+B5+B6+B7) | C8: =(C12+C13+C14+C15+C16)-(C4+C5+C6+C7) | D8: =(D12+D13+D14+D15+D16)-(D4+D5+D6+D7) | E8: =D8+Assumptions!E50*'Income Statement'!E6-'Income Statement'!E13 | F8: =E8+Assumptions!F50*'Income Statement'!F6-'Income Statement'!F13 | G8: =F8+Assumptions!G50*'Income Statement'!G6-'Income Statement'!G13 | H8: =G8+Assumptions!H50*'Income Statement'!H6-'Income Statement'!H13 | I8: =H8+Assumptions!I50*'Income Statement'!I6-'Income Statement'!I13
A9: Total assets | B9: =SUM(B4:B8) | C9: =SUM(C4:C8) | D9: =SUM(D4:D8) | E9: =SUM(E4:E8) | F9: =SUM(F4:F8) | G9: =SUM(G4:G8) | H9: =SUM(H4:H8) | I9: =SUM(I4:I8)
A12: Shareholders' equity | B12: 42978 | C12: 79327 | D12: 168540 | E12: =D12+'Income Statement'!E19-Assumptions!E52-Assumptions!E53 | F12: =E12+'Income Statement'!F19-Assumptions!F52-Assumptions!F53 | G12: =F12+'Income Statement'!G19-Assumptions!G52-Assumptions!G53 | H12: =G12+'Income Statement'!H19-Assumptions!H52-Assumptions!H53 | I12: =H12+'Income Statement'!I19-Assumptions!I52-Assumptions!I53
A13: Debt (notes payable) | B13: 9709 | C13: 8463 | D13: 8463 | E13: =D13 | F13: =E13 | G13: =F13 | H13: =G13 | I13: =H13
A14: Accounts payable | B14: 2699 | C14: 3466 | D14: 6300 | E14: ='Income Statement'!E6*Assumptions!$B$25 | F14: ='Income Statement'!F6*Assumptions!$B$25 | G14: ='Income Statement'!G6*Assumptions!$B$25 | H14: ='Income Statement'!H6*Assumptions!$B$25 | I14: ='Income Statement'!I6*Assumptions!$B$25
A15: Accrued & other current liabilities | B15: 6000 | C15: 12000 | D15: 18000 | E15: =D15 | F15: =E15 | G15: =F15 | H15: =G15 | I15: =H15
A16: Other long-term liabilities | B16: 4342 | C16: 8345 | D16: 5000 | E16: =D16 | F16: =E16 | G16: =F16 | H16: =G16 | I16: =H16
A17: Total liabilities & equity | B17: =B12+B13+B14+B15+B16 | C17: =C12+C13+C14+C15+C16 | D17: =D12+D13+D14+D15+D16 | E17: =E12+E13+E14+E15+E16 | F17: =F12+F13+F14+F15+F16 | G17: =G12+G13+G14+G15+G16 | H17: =H12+H13+H14+H15+H16 | I17: =I12+I13+I14+I15+I16
A19: Balance check (assets − L&E) | B19: =B9-B17 | C19: =C9-C17 | D19: =D9-D17 | E19: =E9-E17 | F19: =F9-F17 | G19: =G9-G17 | H19: =H9-H17 | I19: =I9-I17
A20: Net cash / (debt) | B20: =B4-B13 | C20: =C4-C13 | D20: =D4-D13 | E20: =E4-E13 | F20: =F4-F13 | G20: =G4-G13 | H20: =H4-H13 | I20: =I4-I13
A22: Note: PP&E/goodwill/intangibles plugs to disclosed total assets; forecast rolls +capex −D&A. Cash rolls via the Cash Flow.

Sheet Cash Flow
A1: Cash flow ($m, forecast)
A2: Derived from the Income Statement and Balance Sheet. Closing cash ties to the Balance Sheet.
E3: FY27E | F3: FY28E | G3: FY29E | H3: FY30E | I3: FY31E
A4: Net income | E4: ='Income Statement'!E19 | F4: ='Income Statement'!F19 | G4: ='Income Statement'!G19 | H4: ='Income Statement'!H19 | I4: ='Income Statement'!I19
A5: + D&A | E5: ='Income Statement'!E13 | F5: ='Income Statement'!F13 | G5: ='Income Statement'!G13 | H5: ='Income Statement'!H13 | I5: ='Income Statement'!I13
A6: − Increase in net working capital | E6: =-(('Balance Sheet'!E5+'Balance Sheet'!E6-'Balance Sheet'!E14)-('Balance Sheet'!D5+'Balance Sheet'!D6-'Balance Sheet'!D14)) | F6: =-(('Balance Sheet'!F5+'Balance Sheet'!F6-'Balance Sheet'!F14)-('Balance Sheet'!E5+'Balance Sheet'!E6-'Balance Sheet'!E14)) | G6: =-(('Balance Sheet'!G5+'Balance Sheet'!G6-'Balance Sheet'!G14)-('Balance Sheet'!F5+'Balance Sheet'!F6-'Balance Sheet'!F14)) | H6: =-(('Balance Sheet'!H5+'Balance Sheet'!H6-'Balance Sheet'!H14)-('Balance Sheet'!G5+'Balance Sheet'!G6-'Balance Sheet'!G14)) | I6: =-(('Balance Sheet'!I5+'Balance Sheet'!I6-'Balance Sheet'!I14)-('Balance Sheet'!H5+'Balance Sheet'!H6-'Balance Sheet'!H14))
A7: Operating cash flow | E7: =E4+E5+E6 | F7: =F4+F5+F6 | G7: =G4+G5+G6 | H7: =H4+H5+H6 | I7: =I4+I5+I6
A8: − Capex | E8: =-Assumptions!E50*'Income Statement'!E6 | F8: =-Assumptions!F50*'Income Statement'!F6 | G8: =-Assumptions!G50*'Income Statement'!G6 | H8: =-Assumptions!H50*'Income Statement'!H6 | I8: =-Assumptions!I50*'Income Statement'!I6
A9: Free cash flow | E9: =E7+E8 | F9: =F7+F8 | G9: =G7+G8 | H9: =H7+H8 | I9: =I7+I8
A10: − Dividends | E10: =-Assumptions!E52 | F10: =-Assumptions!F52 | G10: =-Assumptions!G52 | H10: =-Assumptions!H52 | I10: =-Assumptions!I52
A11: − Net buybacks | E11: =-Assumptions!E53 | F11: =-Assumptions!F53 | G11: =-Assumptions!G53 | H11: =-Assumptions!H53 | I11: =-Assumptions!I53
A12: Net change in cash | E12: =E9+E10+E11 | F12: =F9+F10+F11 | G12: =G9+G10+G11 | H12: =H9+H10+H11 | I12: =I9+I10+I11
A13: Opening cash+securities | E13: ='Balance Sheet'!D4 | F13: ='Balance Sheet'!E4 | G13: ='Balance Sheet'!F4 | H13: ='Balance Sheet'!G4 | I13: ='Balance Sheet'!H4
A14: Closing cash+securities | E14: =E13+E12 | F14: =F13+F12 | G14: =G13+G12 | H14: =H13+H12 | I14: =I13+I12

Sheet Summary Financials
A1: Summary financials ($m)
A2: Every cell links to the statement sheets.
B3: FY24 | C3: FY25 | D3: FY26 | E3: FY27E | F3: FY28E | G3: FY29E | H3: FY30E | I3: FY31E
A4: Revenue | B4: ='Income Statement'!B6 | C4: ='Income Statement'!C6 | D4: ='Income Statement'!D6 | E4: ='Income Statement'!E6 | F4: ='Income Statement'!F6 | G4: ='Income Statement'!G6 | H4: ='Income Statement'!H6 | I4: ='Income Statement'!I6
A5: EBITDA | B5: ='Income Statement'!B14 | C5: ='Income Statement'!C14 | D5: ='Income Statement'!D14 | E5: ='Income Statement'!E14 | F5: ='Income Statement'!F14 | G5: ='Income Statement'!G14 | H5: ='Income Statement'!H14 | I5: ='Income Statement'!I14
A6: EBIT | B6: ='Income Statement'!B11 | C6: ='Income Statement'!C11 | D6: ='Income Statement'!D11 | E6: ='Income Statement'!E11 | F6: ='Income Statement'!F11 | G6: ='Income Statement'!G11 | H6: ='Income Statement'!H11 | I6: ='Income Statement'!I11
A7: Net income | B7: ='Income Statement'!B19 | C7: ='Income Statement'!C19 | D7: ='Income Statement'!D19 | E7: ='Income Statement'!E19 | F7: ='Income Statement'!F19 | G7: ='Income Statement'!G19 | H7: ='Income Statement'!H19 | I7: ='Income Statement'!I19
A8: Total assets | B8: ='Balance Sheet'!B9 | C8: ='Balance Sheet'!C9 | D8: ='Balance Sheet'!D9 | E8: ='Balance Sheet'!E9 | F8: ='Balance Sheet'!F9 | G8: ='Balance Sheet'!G9 | H8: ='Balance Sheet'!H9 | I8: ='Balance Sheet'!I9
A9: Equity | B9: ='Balance Sheet'!B12 | C9: ='Balance Sheet'!C12 | D9: ='Balance Sheet'!D12 | E9: ='Balance Sheet'!E12 | F9: ='Balance Sheet'!F12 | G9: ='Balance Sheet'!G12 | H9: ='Balance Sheet'!H12 | I9: ='Balance Sheet'!I12
A10: Net cash | B10: ='Balance Sheet'!B20 | C10: ='Balance Sheet'!C20 | D10: ='Balance Sheet'!D20 | E10: ='Balance Sheet'!E20 | F10: ='Balance Sheet'!F20 | G10: ='Balance Sheet'!G20 | H10: ='Balance Sheet'!H20 | I10: ='Balance Sheet'!I20
A11: Free cash flow | E11: ='Cash Flow'!E9 | F11: ='Cash Flow'!F9 | G11: ='Cash Flow'!G9 | H11: ='Cash Flow'!H9 | I11: ='Cash Flow'!I9

Sheet Monte Carlo
A1: Monte Carlo — engine outputs
A2: 50,000 paths · 16 factors · seed 42 · zero drift (international) · YZ-HAR width · Student-t(5). Values, not a sheet simulation.
A3: Probability read (T+60, from the same 50,000 paths)
A4: P(price above spot) | C4: 47%
A5: P(+10%) vs P(−10%) | C5: 30% vs 34% (odds 0.89)
A6: Median level / move | C6: $193 (−1.6%)
A7: 50% band (25th–75th) | C7: $167 – $223 (−15% / +14%)
A8: Touch +10% / −10% | C8: 57% / 59%
A10: Percentile map ($/share)
A11: Horizon | B11: p5 | C11: p25 | D11: p50 | E11: p75 | F11: p95
A12: T+20 sessions | B12: 156 | C12: 180 | D12: 195 | E12: 212 | F12: 244
A13: T+60 sessions | B13: 132 | C13: 167 | D13: 193 | E13: 223 | F13: 283
A15: Inputs (from Assumptions): σ | C15: =Assumptions!$B$28
A16: net continuous factor drift | C16: =Assumptions!$B$29
A18: Level-touch ladder
A19: Level | B19: T+20 | C19: T+60
A20: 240 | B20: 0.098 | C20: 0.295
A21: 230 | B21: 0.169 | C21: 0.392
A22: 220 | B22: 0.289 | C22: 0.517
A23: 210 | B23: 0.476 | C23: 0.666
A24: 200 | B24: 0.758 | C24: 0.852
A25: 190 | B25: 0.691 | C25: 0.825
A26: 180 | B26: 0.414 | C26: 0.644
A27: 170 | B27: 0.217 | C27: 0.478
A28: 160 | B28: 0.105 | C28: 0.335

Sheet Sensitivity
A1: DCF sensitivity — WACC × terminal growth
A2: Fair value ($/share) live off the DCF engine. Cells near spot show how much AI-compute durability is priced.
A4: WACC \ g | B4: 0.03 | C4: 0.035 | D4: 0.04 | E4: 0.045 | F4: 0.05
A5: 0.095 | B5: 189 | C5: 202 | D5: 217 | E5: 235 | F5: 257
A6: 0.105 | B6: 163 | C6: 172 | D6: 183 | E6: 195 | F6: 210
A7: 0.11 | B7: 153 | C7: 160 | D7: ='DCF (Primary)'!B21 | E7: 180 | F7: 192
A8: 0.115 | B8: 143 | C8: 150 | D8: 158 | E8: 167 | F8: 177
A9: 0.125 | B9: 128 | C9: 133 | D9: 139 | E9: 145 | F9: 153
A11: Base cell (10.5% × 4.5%) links live to the DCF; other cells are engine outputs at the labelled WACC/g. TV = 79% of EV.

Sheet Per-Share & Ratios
A1: Per-share & ratios
A2: Links to statements / Assumptions.
B3: FY24 | C3: FY25 | D3: FY26 | E3: FY27E | F3: FY28E | G3: FY29E | H3: FY30E | I3: FY31E
A4: Diluted EPS ($) | B4: ='Income Statement'!B20 | C4: ='Income Statement'!C20 | D4: ='Income Statement'!D20 | E4: ='Income Statement'!E20 | F4: ='Income Statement'!F20 | G4: ='Income Statement'!G20 | H4: ='Income Statement'!H20 | I4: ='Income Statement'!I20
A5: Book value / share ($) | B5: ='Balance Sheet'!B12/Assumptions!$B$5 | C5: ='Balance Sheet'!C12/Assumptions!$B$5 | D5: ='Balance Sheet'!D12/Assumptions!$B$5 | E5: ='Balance Sheet'!E12/Assumptions!$B$5 | F5: ='Balance Sheet'!F12/Assumptions!$B$5 | G5: ='Balance Sheet'!G12/Assumptions!$B$5 | H5: ='Balance Sheet'!H12/Assumptions!$B$5 | I5: ='Balance Sheet'!I12/Assumptions!$B$5
A6: Gross margin | B6: ='Income Statement'!B9 | C6: ='Income Statement'!C9 | D6: ='Income Statement'!D9 | E6: ='Income Statement'!E9 | F6: ='Income Statement'!F9 | G6: ='Income Statement'!G9 | H6: ='Income Statement'!H9 | I6: ='Income Statement'!I9
A7: Operating margin | B7: ='Income Statement'!B12 | C7: ='Income Statement'!C12 | D7: ='Income Statement'!D12 | E7: ='Income Statement'!E12 | F7: ='Income Statement'!F12 | G7: ='Income Statement'!G12 | H7: ='Income Statement'!H12 | I7: ='Income Statement'!I12
A8: Net margin | B8: ='Income Statement'!B19/'Income Statement'!B6 | C8: ='Income Statement'!C19/'Income Statement'!C6 | D8: ='Income Statement'!D19/'Income Statement'!D6 | E8: ='Income Statement'!E19/'Income Statement'!E6 | F8: ='Income Statement'!F19/'Income Statement'!F6 | G8: ='Income Statement'!G19/'Income Statement'!G6 | H8: ='Income Statement'!H19/'Income Statement'!H6 | I8: ='Income Statement'!I19/'Income Statement'!I6
A9: Revenue YoY | C9: ='Income Statement'!C6/'Income Statement'!B6-1 | D9: ='Income Statement'!D6/'Income Statement'!C6-1 | E9: ='Income Statement'!E6/'Income Statement'!D6-1 | F9: ='Income Statement'!F6/'Income Statement'!E6-1 | G9: ='Income Statement'!G6/'Income Statement'!F6-1 | H9: ='Income Statement'!H6/'Income Statement'!G6-1 | I9: ='Income Statement'!I6/'Income Statement'!H6-1
A10: ROE (NI / equity) | B10: ='Income Statement'!B19/'Balance Sheet'!B12 | C10: ='Income Statement'!C19/'Balance Sheet'!C12 | D10: ='Income Statement'!D19/'Balance Sheet'!D12 | E10: ='Income Statement'!E19/'Balance Sheet'!E12 | F10: ='Income Statement'!F19/'Balance Sheet'!F12 | G10: ='Income Statement'!G19/'Balance Sheet'!G12 | H10: ='Income Statement'!H19/'Balance Sheet'!H12 | I10: ='Income Statement'!I19/'Balance Sheet'!I12
A11: P/E on spot (×) | B11: =Assumptions!$B$4/'Income Statement'!B20 | C11: =Assumptions!$B$4/'Income Statement'!C20 | D11: =Assumptions!$B$4/'Income Statement'!D20 | E11: =Assumptions!$B$4/'Income Statement'!E20 | F11: =Assumptions!$B$4/'Income Statement'!F20 | G11: =Assumptions!$B$4/'Income Statement'!G20 | H11: =Assumptions!$B$4/'Income Statement'!H20 | I11: =Assumptions!$B$4/'Income Statement'!I20

Sheet Peer & Sector
A1: Peer set & sector
A2: AI-accelerator / semiconductor peers and context.
A3: Peer | B3: Note | C3: Typical valuation
A4: AMD | B4: AI-GPU challenger (MI300/MI450) | C4: ~35–40× fwd P/E
A5: Broadcom | B5: Custom-ASIC / networking | C5: ~30–35× fwd P/E
A6: TSMC | B6: Foundry (supply constraint) | C6: ~20–25× fwd P/E
A7: Marvell / hyperscaler ASIC | B7: Custom silicon supplements GPUs | C7: growth / strategic
A9: Context: ~81% AI-accelerator share; CUDA moat; hyperscaler capex ~$650–700bn (2026) → ~$1tn (2027, NVDA est). Not model inputs.
