Workbook

Sheet READ FIRST
A1: READ FIRST — DISCLOSURE, DISCLAIMER AND HOW TO USE THIS MODEL
A3: NATURE OF THIS WORKBOOK
A4: This workbook is an educational valuation model and an expression of the preparer's personal analytical opinion, built exclusively from documents Palm Hills Developments itself issued and from assumptions stated on the Assumptions sheet. It is shared free of charge so that its methodology can be examined, stress-tested and critiqued — you are invited to change the assumptions and see how the outputs respond.
A6: NO ADVICE, NO RECOMMENDATION, NO SOLICITATION
A7: Nothing in this workbook constitutes investment advice, financial consultancy, securities analysis services, a research recommendation, a rating, a price target, an offer, or a solicitation to buy, sell, hold or otherwise deal in any security.
A9: NO LICENSED ACTIVITY
A10: The preparer is not licensed or registered with the Egyptian Financial Regulatory Authority or any other securities regulator, does not manage money, and does not accept clients, fees or funds of any kind.
A12: ESTIMATES AND UNCERTAINTY
A13: All values are model outputs resting on explicit, subjective assumptions; they are illustrative, highly uncertain, and likely to prove wrong in material respects. Outputs are ranges and distributions because no single number should be relied on.
A15: NO LIABILITY
A16: To the maximum extent permitted by applicable law, the preparer accepts no liability for any decision made or action taken or not taken, or for any loss or damage of any kind incurred, by any person in reliance on any part of this workbook.
A18: HOW TO USE THIS MODEL
... A22: The company holds EGP 34,337 mn of customers' maintenance money for residents' associations that have not been legally constituted. Whether that float is permanent operating funding or restricted third-party money is worth more than any other assumption in this model. Cell B43 on Assumptions switches between the two. The two answers are never averaged.

Sheet Summary
A1: PALM HILLS DEVELOPMENTS (EGX:PHDC) — VALUATION SUMMARY
A2: Fundamental refresh, 19 August 2026. Fundamentals as of the 30 June 2026 reviewed statements; price sections carried forward from 22 July 2026.
A4: HEADLINE — VALUE PER SHARE (EGP) | B4: Framing A | C4: Framing B | D4: Note
A5: Cash-flow lens, normalised cost of capital | B5: ='Fundamental Valuation'!B12 | C5: ='Fundamental Valuation'!C12 | D5: discount path glides to the terminal rate
A6: Cash-flow lens, spot cost of capital held constant | B6: 11.67095 | C6: -4.8247151 | D6: the other end of the cost-of-capital range
A7: Book value and sustainable return | B7: 7.1865825 | C7: 7.1865825 | D7: independent of the contested judgement
A8: Relative multiples | B8: 10.914478 | C8: 10.914478 | D8: independent of the contested judgement
A9: Normalised earnings power | B9: 11.951543 | C9: 11.951543 | D9: independent of the contested judgement
A11: WEIGHTED CENTRE | B11: 15.815329 | C11: 5.7914208 | D11: the two are published side by side, never averaged
A12: Weighted low | B12: 9.8126304 | C12: 2.389581
A13: Weighted high | B13: 21.818027 | C13: 9.1932606
A15: Market price (close 22-Jul-2026) | B15: =Assumptions!B4
A16: Base against market | B16: =B11/B15-1 | C16: =C11/B15-1
A18: WHAT THE NUMBER RESTS ON | B18: Value | D18: Source
A19: Weighted cost of capital, spot, credit-swap basis | B19: 0.25889012 | D19: built on the Assumptions sheet from the central bank auction and the country file
A20: Weighted cost of capital, terminal | B20: 0.14794324 | D20: normalised on the central bank inflation target for the fourth quarter of 2028
A21: Beta | B21: 1.0555271 | D21: own-stock weekly regression against the exchange index
A22: Revenue per EGP of build cost (the crux) | B22: 3.1186188 | D22: measured on the reviewed half-year
A23: Residents' Association float, EGP mn | B23: 34337.385 | D23: note 63 of the reviewed statements
A24: Net debt, company definition, EGP mn | B24: 5659.6364 | D24: note 34 less cash and treasury bills
A25: Return on invested capital | B25: 0.11261427 | D25: computed from the model's own capital
A26: Shares outstanding after treasury, mn | B26: 2824.4702 | D26: note 62

Sheet Fundamental Valuation
A1: FUNDAMENTAL VALUATION — THE BRIDGE FROM FIRM TO EQUITY
A2: Both framings of the contested judgement, computed in full. Column B is framing A; column C is framing B.
A4: EGP mn | B4: Framing A — float is operating funding | C4: Framing B — float restricted | D4: Note
A5: Present value of the explicit forecast | B5: 27110.814 | C5: 5423.7314 | D5: sum of the discounted free cash flows on the DCF sheet
A6: Present value of the terminal value | B6: 77890.85 | C6: 39660.703 | D6: reinvestment-consistent, so growth is charged for
A7: ENTERPRISE VALUE | B7: =B5+B6 | C7: =C5+C6
A8: Less net debt | B8: -5659.6364 | C8: -24983.021 | D8: company definition in A; restricted definition in B
A9: Less non-controlling interests | B9: -1723.0488 | C9: -1723.0488
A10: EQUITY VALUE | B10: =SUM(B7:B9) | C10: =SUM(C7:C9)
A11: Shares outstanding after treasury, mn | B11: =Assumptions!B5 | C11: =Assumptions!B5
A12: VALUE PER SHARE, EGP | B12: =B10/B11 | C12: =C10/C11
A14: THE FOUR LENSES | B14: Low | C14: High | D14: Weight
A15: Cash flow, framing A | B15: 11.67095 | C15: 34.561873 | D15: 0.45
A16: Book value and sustainable return | B16: 4.349429 | C16: 10.023736 | D16: 0.2
A17: Relative multiples | B17: 9.6838885 | C17: 12.145068 | D17: 0.2
A18: Normalised earnings power | B18: 11.693596 | C18: 12.20949 | D18: 0.15

Sheet Assumptions
A1: ASSUMPTIONS — every blue cell is an input you can overwrite
A2: Layer, date and source for each. The model recomputes off these.
A3: Input | B3: Value | C3: Date | D3: Source and construction
A4: Market price, EGP | B4: 15.01 | C4: 22-Jul-2026 | D4: assets/data.js, TICKERS.PHDC — published cone and technical read carried forward unchanged by this fundamentals-only refresh — published spot, close of 22-Jul-2026. This refresh does not touch it
A5: Shares outstanding after treasury, mn | B5: 2824.4702 | C5: 30-Jun-2026 | D5: Interim consolidated financial statements as of 30 June 2026, Palm Hills Developments Company S.A.E — limited review report, Forvis Mazars Mostafa Shawki, Cairo 17-Aug-2026 (COMPANY_OFFICIAL) — note 62: outstanding shares after treasury
A6: rf obs | B6: 0.23269 | C6: 17-Aug-2026 | D6: Central Bank of Egypt, EGP Treasury Fixed Coupon Bonds auction result, auction date 17-Aug-2026, issue 18-Aug-2026 — accepted weighted-average yields (PRIMARY_MARKET_DATA) — three-year bond, accepted weighted-average yield 23.269% (22 accepted bids, EGP 18.881bn accepted of EGP 39.684bn submitted: the deepest accepted print in the auction). The two-year cleared at 22.691% on a single accepted bid and the five-year at 19.700% on a single accepted bid; neither is a usable clearing level
A7: ds rating | B7: 0.05970183 | C7: 30-Jun-2026 | D7: Damodaran country default spreads and risk premiums, ORIGINAL file ctrypremJuly26.xlsx sheet 'ERPs by country', Egypt row — CDS spreads as of 30-Jun-2026, rating default spreads updated 30-Jun-2026 (PRIMARY_MARKET_DATA) — rating-based adjusted default spread, Moody's Caa1
A8: ds cds | B8: 0.0342 | C8: 30-Jun-2026 | D8: Damodaran country default spreads and risk premiums, ORIGINAL file ctrypremJuly26.xlsx sheet 'ERPs by country', Egypt row — CDS spreads as of 30-Jun-2026, rating default spreads updated 30-Jun-2026 (PRIMARY_MARKET_DATA) — sovereign CDS net of Swiss CDS (gross 3.55%)
A9: erp rating | B9: 0.13480623 | C9: 30-Jun-2026 | D9: Damodaran country default spreads and risk premiums, ORIGINAL file ctrypremJuly26.xlsx sheet 'ERPs by country', Egypt row — CDS spreads as of 30-Jun-2026, rating default spreads updated 30-Jun-2026 (PRIMARY_MARKET_DATA) — total equity risk premium, rating basis
A10: erp cds | B10: 0.09516375 | C10: 30-Jun-2026 | D10: Damodaran country default spreads and risk premiums, ORIGINAL file ctrypremJuly26.xlsx sheet 'ERPs by country', Egypt row — CDS spreads as of 30-Jun-2026, rating default spreads updated 30-Jun-2026 (PRIMARY_MARKET_DATA) — total equity risk premium, CDS basis
A11: beta val | B11: 1.0555271 | C11: 22-Jul-2026 | D11: engine/beta_regression.own_stock_beta('PHDC','EG','EGX') — Dimson-adjusted weekly own-stock regression against EGX30 read from engine/raw_indices/EG/EGX30.csv (PRIMARY_MARKET_DATA) — Dimson-adjusted weekly beta, 255 observations over 4.93 years to 16-Jul-2026, R-squared 29.8%, standard error 0.182, passes the usability gate
A12: taxrate stat | B12: 0.225 | C12: 30-Jun-2026 | D12: Interim consolidated financial statements as of 30 June 2026, Palm Hills Developments Company S.A.E — limited review report, Forvis Mazars Mostafa Shawki, Cairo 17-Aug-2026 (COMPANY_OFFICIAL) — note 70a, tax at 22.5%; Damodaran corporate tax rate for Egypt agrees
A13: rf term | B13: 0.105 | C13: 06-Aug-2026 | D13: Terminal risk-free rate, normalised from the Central Bank of Egypt's longest published inflation target (5% for Q4-2028) plus a standard emerging-market real-rate convention. Same construction and same value as the ARCC study of 06-Aug-2026 (input rf_term) — the house prior for Egypt
A14: erp term | B14: 0.07 | C14: 06-Aug-2026 | D14: Terminal equity risk premium, normalised below the currently elevated Egypt level. Same value and construction as the ARCC study of 06-Aug-2026 (input erp_term)
A15: term g | B15: 0.08 | C15: 19-Aug-2026 | D15: Terminal nominal growth: the central bank's 5% long-run inflation target plus about 3% real. Held below the terminal weighted cost of capital under both cost-of-capital framings and made reinvestment-consistent through the return on capital the model itself computes
... A25: FLOAT TREATMENT — 1 = framing A, 0 = framing B | B25: 1 | C25: switch | D25: the contested judgement. Setting this to 0 removes the float from the cash flows and moves the net-debt definition to the restricted one
A27: Path | B27: FY2027 | C27: FY2028 | D27: FY2029 | E27: FY2030 | F27: FY2031
A28: Real construction volume growth | B28: 0.12 | C28: 0.09 | D28: 0.06 | E28: 0.04 | F28: 0.03
A29: Selling-price escalation | B29: 0.09 | C29: 0.08 | D29: 0.075 | E29: 0.07 | F29: 0.065
A30: Steel escalator | B30: 0.06 | C30: 0.06 | D30: 0.055 | E30: 0.05 | F30: 0.045
A31: Cement escalator | B31: 0.09 | C31: 0.08 | D31: 0.07 | E31: 0.065 | F31: 0.06
A32: Finishing escalator | B32: 0.115 | C32: 0.1 | D32: 0.09 | E32: 0.08 | F32: 0.07
A33: Site labour escalator | B33: 0.135 | C33: 0.12 | D33: 0.11 | E33: 0.1 | F33: 0.09
A34: Weighted build-cost escalator | B34: 0.10225 | C34: 0.092 | D34: 0.08325 | E34: 0.0755 | F34: 0.06775
A35: Cost-class weights: steel / cement / finishing / labour | B35: 0.25 | C35: 0.2 | D35: 0.25 | E35: 0.3

Sheet SOTP Bridge
A1: BRIDGE — WHAT IS AND IS NOT INSIDE THE ENTERPRISE
A2: The three definitions of net debt, and the float that separates them.
A4: EGP mn | B4: Amount | C4: In the enterprise? | D4: Note
A5: Credit facilities (overdrafts) | B5: 13922.423 | C5: debt | D5: note 50
A6: Loans, long and short term | B6: 10886.432 | C6: debt | D6: note 51
A7: Banks — credit balances | B7: 1529.8425 | C7: debt | D7: note 49
A8: Lease obligations | B8: 141.59347 | C8: debt | D8: note 55
A9: INTEREST-BEARING OBLIGATIONS | B9: 26480.291 | C9: debt | D9: note 34 — the company's own schedule
A10: Notes payable to the land authority and under sale-and-leaseback | B10: 8795.1761 | C10: debt-like | D10: note 52 — carried only in the broad definition
A11: Land purchase liabilities | B11: 76.747274 | C11: debt-like | D11: note 56
A12: Cash and cash equivalents | B12: -7804.2469 | C12: asset | D12: note 48
A13: Treasury bills and bonds at amortised cost | B13: -13016.407 | C13: asset | D13: note 47, average return 19.10%
A14: Residents' Association balance | B14: 34337.385 | C14: the contested judgement | D14: note 63 — matched by maintenance-deposit notes receivable of EGP 15,014 mn and by the invested proceeds
A15: Non-controlling interests | B15: 1723.0488 | C15: deducted | D15: balance sheet
A17: Net debt on each definition | B17: EGP mn | C17: EGP per share | D17: Used where
A18: Company definition — interest-bearing less cash and treasury bills | B18: 5659.6364 | C18: =B18/Assumptions!$B$5 | D18: framing A
A19: Broad — also carrying notes payable and land liabilities | B19: 14531.56 | C19: =B19/Assumptions!$B$5 | D19: disclosed only
A20: Restricted — the invested residents' money is not the enterprise's | B20: 24983.021 | C20: =B20/Assumptions!$B$5 | D20: framing B

Sheet Segments
A1: SEGMENTS — REVENUE AND COST BY ACTIVITY
A2: Notes 64 and 65 of the reviewed statements. The two foot exactly to the face of the income statement, which the model asserts.
A4: Activity | B4: Revenue H1-2026 | C4: Revenue H1-2025 | D4: Cost H1-2026 | E4: Cost H1-2025 | F4: Margin H1-2026 | G4: Margin H1-2025
A5: Real estate development | B5: 17546.53 | C5: 13857.585 | D5: 12132.983 | E5: 8530.8386 | F5: =1-D5/B5 | G5: =1-E5/C5
A6: Commercial and service activities | B6: 767.49322 | C6: 286.77763 | D6: 250.32095 | E6: 203.99495 | F6: =1-D6/B6 | G6: =1-E6/C6
A7: Owners' share, hotels | B7: 128.14275 | C7: 92.024925 | D7: 0 | E7: 0 | F7: =1-D7/B7 | G7: =1-E7/C7
A8: Palm Hills club | B8: 384.67109 | C8: 307.67566 | D8: 145.38546 | E8: 118.66988 | F8: =1-D8/B8 | G8: =1-E8/C8
A9: Other activities | B9: 701.28032 | C9: 1035.0665 | D9: 0 | E9: 0 | F9: =1-D9/B9 | G9: =1-E9/C9
A10: Depreciation of fixed assets, Macor | B10: 0 | C10: 0 | D10: 10.583017 | E10: 6.390921 | F10: no revenue line | G10: no revenue line
A11: TOTAL | B11: =SUM(B5:B10) | C11: =SUM(C5:C10) | D11: =SUM(D5:D10) | E11: =SUM(E5:E10) | F11: =1-D11/B11 | G11: =1-E11/C11
A13: THE DEVELOPMENT COST BLOCK, DECOMPOSED
A14: Construction cost charged to the income statement | B14: 5626.3787 | H14: note 43: the movement in the cumulative charge
A15: Land and partners' share, together | B15: 6506.6041 | H15: the residual — not separable from anything the company publishes
A16: Cost of real estate development | B16: 12132.983 | H16: note 65
A17: Real-estate revenue | B17: 17546.53 | H17: note 64
A18: Revenue per EGP of build cost (the crux) | B18: 3.1186188 | H18: the ratio the study sensitises
A19: Real-estate gross margin — AN OUTPUT | B19: 0.30852525 | H19: one less the two cost rates

Sheet Relative & Normalized
A1: RELATIVE MULTIPLES AND NORMALISED EARNINGS POWER
A4: Relative lens | B4: Multiple | C4: Value per share, EGP | D4: Note
A5: Median Egyptian peer, price to earnings | B5: 6.8 | C5: 9.6838885 | D5: five listed Egyptian developers
A6: Median Gulf peer, price to earnings | B6: 7.1 | C6: 10.111119 | D6: Emaar Properties and Aldar
A7: All peers, price to earnings | B7: 7 | C7: 9.9687087 | D7: inside and outside the country
A8: Gulf peer, enterprise value to EBITDA | B8: 5.1 | C8: 12.145068 | D8: bridged to equity at the company net-debt definition
A9: Palm Hills, trailing price to earnings | B9: 10.539981
A11: Normalised earnings power | B11: Value | D11: Note
A12: Revenue base, trailing twelve months, EGP mn | B12: 40144.989 | D12: the current scale, not a forecast year
A13: Mid-cycle margin | B13: 0.20697435 | D13: average of 2023, 2024 and the reviewed half of 2026
A14: Earnings before interest, tax and depreciation, EGP mn | B14: 8308.9829
A15: Depreciation and amortisation, EGP mn | B15: -558.35782
A16: Discount unwinding on instalment receivables, EGP mn | B16: 1046.3879 | D16: real income on the customer financing the balance sheet already carries
A17: Return on the treasury-bill book, EGP mn | B17: 911.21213
A18: Interest, EGP mn | B18: -3060.3308 | D18: at the measured all-in rate, net of the capitalised share
A19: Profit before tax, EGP mn | B19: 6647.8943
A20: Profit after tax, EGP mn | B20: 4857.09
A21: Earnings per share, EGP | B21: 1.7196464
A22: Value at the peer range, EGP | B22: 11.693596 | D22: low end
A23: Value at the peer range, EGP | B23: 12.20949 | D23: high end

Sheet DCF
A1: DISCOUNTED CASH FLOW — FRAMING A
A2: The full waterfall to free cash flow to the firm. Column H totals. Interest is excluded because this is a pre-financing measure.
A4: EGP mn | B4: H2-2026E | C4: FY2027E | D4: FY2028E | E4: FY2029E | F4: FY2030E | G4: FY2031E | H4: Total
A5: Revenue | B5: 21414.432 | C5: 47321.534 | D5: 55706.91 | E5: 63478.023 | F5: 70638.344 | G5: 77486.732 | H5: =SUM(B5:G5)
A6: Earnings before interest, tax and depreciation | B6: 5008.3001 | C6: 10927.207 | D6: 12756.533 | E6: 14420.393 | F6: 15931.561 | G6: 17388.979 | H6: =SUM(B6:G6)
A7: margin | B7: 0.23387499 | C7: 0.23091404 | D7: 0.22899373 | E7: 0.22717143 | F7: 0.22553701 | G7: 0.22441235
A8: Depreciation and amortisation | B8: -306.14613 | C8: -676.52061 | D8: -796.40006 | E8: -907.49787 | F8: -1009.8636 | G8: -1107.7699 | H8: =SUM(B8:G8)
A9: Operating profit | B9: 5775.5009 | C9: 12622.564 | D9: 14752.308 | E9: 16694.579 | F9: 18462.275 | G9: 20165.046 | H9: =SUM(B9:G9)
A10: Tax at the measured effective rate | B10: -1555.7997 | C10: -3400.256 | D10: -3973.9647 | E10: -4497.172 | F10: -4973.3525 | G10: -5432.0435 | H10: =SUM(B10:G10)
A11: Operating profit after tax | B11: 4219.7012 | C11: 9222.3082 | D11: 10778.344 | E11: 12197.407 | F11: 13488.922 | G11: 14733.002 | H11: =SUM(B11:G11)
A12: Add back depreciation and amortisation | B12: 306.14613 | C12: 676.52061 | D12: 796.40006 | E12: 907.49787 | F12: 1009.8636 | G12: 1107.7699 | H12: =SUM(B12:G12)
A13: Capital expenditure | B13: -364.47708 | C13: -805.42014 | D13: -948.14058 | E13: -1080.4062 | F13: -1202.276 | G13: -1318.8367 | H13: =SUM(B13:G13)
A14: Change in working capital | B14: -6323.8892 | C14: -7276.8308 | D14: -13711.662 | E14: -12711.185 | F14: -11690.914 | G14: -11097.059 | H14: =SUM(B14:G14)
A15: Residents' Association float | B15: 4179.2564 | C15: 4993.2391 | D15: 8831.7204 | E15: 8579.9098 | F15: 8294.3902 | G15: 8270.8313 | H15: =SUM(B15:G15)
A16: FREE CASH FLOW TO THE FIRM | B16: 2016.7375 | C16: 6809.817 | D16: 5746.6619 | E16: 7893.2231 | F16: 9899.9859 | G16: 11695.707 | H16: =SUM(B16:G16)
A17: Discount factor | B17: 0.94406749 | C17: 0.80860306 | D17: 0.6779487 | E17: 0.58995561 | F17: 0.53340817 | G17: 0.50164667
A18: Present value | B18: =B16*B17 | C18: =C16*C17 | D18: =D16*D17 | E18: =E16*E17 | F18: =F16*F17 | G18: =G16*G17 | H18: =SUM(B18:G18)
A20: TERMINAL VALUE
A21: Return on invested capital, from the model's own year-five capital | B21: 0.11261427
A22: Terminal growth | B22: 0.08
A23: Implied reinvestment rate | B23: 0.71038953
A24: Terminal free cash flow, EGP mn | B24: 11303.032
A25: Terminal cost of capital | B25: 0.14794324
A26: Terminal value, EGP mn | B26: 166359.93
A27: Terminal discount factor | B27: 0.46820681
A28: Present value of the terminal value, EGP mn | H28: =B26*B27
A29: ENTERPRISE VALUE, EGP mn | H29: =H18+H28

Sheet Income Statement
A1: CONSOLIDATED INCOME STATEMENT — HISTORY AND FORECAST
A2: History from the company's own statements. Forecast columns are the model, stated before financing. Blanks are figures no obtained official document carries.
A4: EGP mn | B4: FY2023 | C4: FY2024 | D4: FY2025 | E4: H1-2025 | F4: H1-2026 | G4: FY2027E | H4: FY2028E | I4: FY2029E | J4: FY2030E | K4: FY2031E
A5: Revenue | B5: 17462.108 | C5: 27167.304 | D5: 36196 | E5: 15579.129 | F5: 19528.118 | G5: 47321.534 | H5: 55706.91 | I5: 63478.023 | J5: 70638.344 | K5: 77486.732
A6: Cost of revenues | B6: -11907.224 | C6: -17739.914 | E6: -8859.8944 | F6: -12539.272 | G6: -30920.003 | H6: -36578.743 | I6: -41824.644 | J6: -46650.037 | K6: -51232.044
A7: Gross profit | B7: 5507.6353 | C7: 9330.0964 | E7: 6664.6885 | F7: 6926.0221 | G7: 16401.531 | H7: 19128.166 | I7: 21653.379 | J7: 23988.308 | K7: 26254.688
A8: gross margin | B8: 0.31540494 | C8: 0.34343107 | E8: 0.42779596 | F8: 0.35466921 | G8: 0.34659762 | H8: 0.34337152 | I8: 0.34111615 | J8: 0.33959329 | K8: 0.33882818
A9: Administrative, selling and marketing | B9: -2060.4617 | C9: -3435.755 | E9: -2206.1714 | F9: -2845.8516 | G9: -6823.0542 | H9: -7977.4423 | I9: -9077.1973 | J9: -10119.795 | K9: -11134.756
A10: Earnings before interest, tax and depreciation | B10: 3433.0695 | C10: 5870.8628 | D10: 8552 | E10: 4444.438 | F10: 4066.1769 | G10: 10927.207 | H10: 12756.533 | I10: 14420.393 | J10: 15931.561 | K10: 17388.979
A11: margin | B11: 0.19660109 | C11: 0.21610031 | D11: 0.2362692 | E11: 0.28528155 | F11: 0.20822165 | G11: 0.23091404 | H11: 0.22899373 | I11: 0.22717143 | J11: 0.22553701 | K11: 0.22441235
A12: Depreciation and amortisation | G12: -676.52061 | H12: -796.40006 | I12: -907.49787 | J12: -1009.8636 | K12: -1107.7699
A13: Finance costs and interest | B13: -1503.5637 | C13: -2311.3955 | E13: -1337.7813 | F13: -1676.5432
A14: Profit before tax | B14: 2300.7038 | C14: 4320.5984 | E14: 3587.6063 | F14: 3137.7785
A15: Attributable profit | B15: 1581.5117 | C15: 3254.9454 | D15: 4216.6577 | E15: 2443.3809 | F15: 2264.8227

Sheet Balance Sheet
A1: CONSOLIDATED BALANCE SHEET
A2: Read from the face of the reviewed statements. The identity holds in both columns, which the model asserts before it will emit a number.
A4: EGP mn | B4: 30 Jun 2026 | C4: 31 Dec 2025 | D4: Note
A5: Investments in associates | B5: 3898.4778 | C5: 3611.6197
A6: Investment property | B6: 1008.4196 | C6: 1032.5302
A7: Fixed assets, net | B7: 5637.3739 | C7: 4521.9709
A8: Notes receivable, long term | B8: 55707.502 | C8: 54801.316 | D8: note 41
A9: Notes receivable, long term, undelivered units | B9: 1033.5602 | C9: 1518.4902 | D9: note 42
A10: TOTAL NON-CURRENT ASSETS | B10: 67800.794 | C10: 65900.163
A11: Work in progress | B11: 23915.931 | C11: 17570.909 | D11: note 43
A12: Accounts receivable | B12: 35055.008 | C12: 28118.116 | D12: note 44
A13: Debtors and other debit balances | B13: 14932.336 | C13: 12921.979 | D13: note 45
A14: Suppliers — advance payments | B14: 10490.853 | C14: 9056.2447
A15: Treasury bills and bonds at amortised cost | B15: 13016.407 | C15: 9581.5284 | D15: note 47
A16: Notes receivable, short term | B16: 20530.518 | C16: 18137.719 | D16: note 41
A17: Cash and cash equivalents | B17: 7804.2469 | C17: 9419.5262 | D17: note 48
A18: TOTAL ASSETS | B18: 194767.29 | C18: 172129.81
A19: Controlling equity | B19: 18910.859 | C19: 17431.42
A20: Non-controlling interests | B20: 1723.0488 | C20: 1334.3321
A21: Loans, long term | B21: 10236.28 | C21: 10543.12 | D21: note 51
A22: Notes payable, long term | B22: 4016.7146 | C22: 4505.0249 | D22: note 52
A23: Residents' Association | B23: 34337.385 | C23: 29122.77 | D23: note 63 — the contested judgement
A24: Joint arrangement, partners' share, long term | B24: 3530.9907 | C24: 3991.8653 | D24: note 58
A25: Banks — credit balances | B25: 1529.8425 | C25: 938.7709 | D25: note 49
A26: Credit facilities | B26: 13922.423 | C26: 11337.532 | D26: note 50
A27: Notes payable, short term | B27: 4778.4615 | C27: 4875.6736 | D27: note 52
A28: Advances from customers | B28: 83483.291 | C28: 69354.084 | D28: note 53
A29: Creditors and other credit balances | B29: 6608.4273 | C29: 5121.7124 | D29: note 59
A30: Suppliers and contractors | B30: 5740.1304 | C30: 3807.0429
A31: TOTAL LIABILITIES | B31: 174133.38 | C31: 153364.06
A32: CHECK: total liabilities plus equity less total assets | B32: =B31+B19+B20-B18 | C32: =C31+C19+C20-C18

Sheet Cash Flow
A1: CASH FLOW — WHAT THE FLOAT DOES
A2: The single most important table in this workbook. Strip the movement in the Residents' Association balance out of reported operating cash flow and it is negative in every period the company has disclosed.
A4: EGP mn | B4: Reported operating cash flow | C4: Residents' Association movement | D4: Operating cash flow without it
A5: H1-2026 | B5: 1499.0682 | C5: 5214.6149 | D5: =B5-C5
A6: H1-2025 | B6: 494.41146 | C6: 6086.7108 | D6: =B6-C6
A7: FY2024 | B7: 3084.3785 | C7: 10047.698 | D7: =B7-C7
A8: FY2023 | B8: 753.22401 | C8: 3777.4925 | D8: =B8-C8
A10: RECONCILIATION OF THE MODEL TO THE LAST REPORTED PERIOD
A11: Reported unlevered cash flow, H1-2026 | B11: 3821.6797 | D11: operating cash flow plus interest paid plus capitalised interest, less capital expenditure
A12: Add back: income-tax payable unwound in the period | B12: 990.08794 | D12: the balance fell from EGP 1,977 mn to EGP 986 mn — not a run-rate item
A13: Add back: partners' share paid down in the period | B13: 1611.0418 | D13: note 58 balance fell over the half
A14: Like-for-like reported unlevered cash flow | B14: 6422.8094
A15: Model, second half of 2026, framing A | B15: 2016.7375
A16: Residual | B16: 4406.0719 | D16: disclosed rather than tuned away: the difference between a ratio-driven roll and one actual half-year of a working-capital-driven developer
A17: Income-statement reconciliation gap | B17: -0.012759876 | D17: where the model should be tight, and is

Sheet Summary Financials
A1: SUMMARY FINANCIALS — THE FORECAST IN ONE PLACE
A4: EGP mn | B4: H2-2026E | C4: FY2027E | D4: FY2028E | E4: FY2029E | F4: FY2030E | G4: FY2031E
A5: Revenue | B5: 21414.432 | C5: 47321.534 | D5: 55706.91 | E5: 63478.023 | F5: 70638.344 | G5: 77486.732
A6: Real-estate revenue | B6: 19387.13 | C6: 42841.608 | D6: 50433.142 | E6: 57468.565 | F6: 63951.019 | G6: 70151.07
A7: Construction cost charged to income | B7: 6251.4106 | C7: 13891.754 | D7: 16535.077 | E7: 18986.319 | F7: 21236.578 | G7: 23355.617
A8: Land and partners' share | B8: 7189.135 | C8: 15886.524 | D8: 18701.617 | E8: 21310.492 | F8: 23714.316 | G8: 26013.419
A9: Gross margin | B9: 0.34820761 | C9: 0.34659762 | D9: 0.34337152 | E9: 0.34111615 | F9: 0.33959329 | G9: 0.33882818
A10: Real-estate gross margin | B10: 0.30672844 | C10: 0.30492156 | D10: 0.30131869 | E10: 0.29880254 | F10: 0.29710434 | G10: 0.29624687
A11: Earnings before interest, tax and depreciation | B11: 5008.3001 | C11: 10927.207 | D11: 12756.533 | E11: 14420.393 | F11: 15931.561 | G11: 17388.979
A12: Operating profit after tax | B12: 4219.7012 | C12: 9222.3082 | D12: 10778.344 | E12: 12197.407 | F12: 13488.922 | G12: 14733.002
A13: Working capital employed | B13: 67490.473 | C13: 74767.303 | D13: 88478.965 | E13: 101190.15 | F13: 112881.06 | G13: 123978.12
A14: Residents' Association movement | B14: 4179.2564 | C14: 4993.2391 | D14: 8831.7204 | E14: 8579.9098 | F14: 8294.3902 | G14: 8270.8313
A15: Free cash flow to the firm | B15: 2016.7375 | C15: 6809.817 | D15: 5746.6619 | E15: 7893.2231 | F15: 9899.9859 | G15: 11695.707

Sheet Monte Carlo
A1: PROBABILITY MAP — CARRIED FORWARD UNCHANGED
A2: This is a fundamentals-only refresh. The rows below are the last published price cone and they do not recalculate. Data as of 2026-07-22, computed on 2026-07-28.
A4: Horizon | B4: 5% | C4: 25% | D4: Median | E4: 75% | F4: 95% | G4: Resolves
A5: One month | B5: 12.89 | C5: 14.32 | D5: 15.23 | E5: 16.22 | F5: 18.01 | G5: 2026-08-23
A6: Three months | B6: 11.52 | C6: 14.01 | D6: 15.72 | E6: 17.59 | F6: 21.39 | G6: 2026-10-22
A8: Level, EGP | B8: Touch within one month | C8: Touch within three months
A9: 20 | B9: 0.01 | C9: 0.15
A10: 18.5 | B10: 0.05 | C10: 0.28
A11: 17.5 | B11: 0.12 | C11: 0.42
A12: 16.5 | B12: 0.31 | C12: 0.62
A13: 15.55 | B13: 0.66 | C13: 0.83
A15: Anchor price, EGP | B15: 15.01
A16: Fundamental base from this refresh, EGP | B16: ='Fundamental Valuation'!B12
A17: Technical read, data as of | B17: 2026-07-22
A18: Technical read, computed on | B18: 2026-08-17

Sheet Sensitivity
A1: SENSITIVITY — FAIR VALUE PER SHARE, EGP
A2: The crux against the cost of capital, computed separately under each framing.
A4: FRAMING A — float is operating funding
A5: Cost-of-capital shift | B5: 2.81x | C5: 2.96x | D5: 3.12x | E5: 3.27x | F5: 3.43x
A6: -200 bp | B6: 37.74176 | C6: 44.469224 | D6: 50.523942 | E6: 56.00202 | F6: 60.982091
A7: -100 bp | B7: 30.381775 | C7: 36.0524 | D7: 41.155963 | E7: 45.773473 | F7: 49.971209
A8: +0 bp | B8: 25.202884 | C8: 30.128668 | D8: 34.561873 | E8: 38.572868 | F8: 42.219228
A9: +100 bp | B9: 21.36475 | C9: 25.737508 | D9: 29.672991 | E9: 33.233666 | F9: 36.470643
A10: +200 bp | B10: 18.409312 | C10: 22.355351 | D10: 25.906786 | E10: 29.119989 | F10: 32.041083
A12: FRAMING B — float restricted
A13: Cost-of-capital shift | B13: 2.81x | C13: 2.96x | D13: 3.12x | E13: 3.27x | F13: 3.43x
A14: -200 bp | B14: 1.7399503 | C14: 8.4674143 | D14: 14.522132 | E14: 20.00021 | F14: 24.980281
A15: -100 bp | B15: -0.96490989 | C15: 4.7057157 | D15: 9.8092788 | E15: 14.426788 | F15: 18.624524
A16: +0 bp | B16: -2.8521533 | C16: 2.0736306 | D16: 6.5068361 | E16: 10.517832 | F16: 14.164191
A17: +100 bp | B17: -4.2374979 | C17: 0.13526056 | D17: 4.0707432 | E17: 7.6314179 | F17: 10.868395
A18: +200 bp | B18: -5.2930016 | C18: -1.3469625 | D18: 2.2044727 | E18: 5.417676 | F18: 8.33877
A20: SINGLE-DRIVER RANGES
A21: Driver | B21: Low | C21: High | G21: Note
A22: Real volume growth | B22: 25.045385 | C22: 40.190694 | G22: low is no real growth at all, high is half again the base path. More volume is worth more because most of the capital funding it is customer money, not shareholder money
A23: Build-cost escalation | B23: 27.512958 | C23: 41.135973 | G23: two hundred basis points either way on all four classes together
A24: Cost of capital | B24: 18.409312 | C24: 60.982091 | G24: two hundred basis points either way on the whole path
A25: The contested judgement | B25: 5.7914208 | C25: 15.815329 | G25: the largest single item in the model

Sheet Per-Share & Ratios
A1: PER-SHARE FIGURES, RATIOS AND THE WORKING-CAPITAL CYCLE
A4: Measure | B4: Value | C4: Construction
A5: Market price, EGP | B5: 15.01 | C5: close of 22-Jul-2026
A6: Shares outstanding after treasury, mn | B6: 2824.4702 | C6: note 62
A7: Market value, EGP mn | B7: 42395.297 | C7: price times shares
A8: Book value per share, EGP | B8: 6.6953653 | C8: controlling equity over shares
A9: Trailing earnings per share, EGP | B9: 1.4241012 | C9: trailing twelve months over the weighted average share count
A10: Price to book | B10: 2.2418493
A11: Price to earnings | B11: 10.539981
A12: Price to sales | B12: 1.0560545
A13: Enterprise value to EBITDA, company net-debt basis | B13: 5.8791863
A14: Enterprise value to EBITDA, broad net-debt basis | B14: 6.9646043
A15: Return on equity, trailing | B15: 0.22222599 | C15: on average controlling equity
A16: Debt to equity, interest-bearing | B16: 1.400269
A17: Debt to equity, broad | B17: 1.8694134
A18: Dividend yield | B18: 0.032366422 | C18: EGP 686 mn paid in the half, annualised
A19: Days sales outstanding | B19: 1056.247 | C19: all receivables over annualised revenue
A20: Days inventory outstanding | B20: 348.079 | C20: work in progress over annualised cost
A21: Days payables outstanding | B21: 211.55083 | C21: contractors and notes payable
A22: Gross cash conversion cycle, days | B22: 1192.7752
A23: Customer advances, days | B23: 1215.0387
A24: NET CASH CONVERSION CYCLE, days | B24: -22.263457 | C24: negative: the customer funds the build. This is the whole financial architecture
A25: Realised all-in cost of debt | B25: 0.20966308 | C25: interest paid and capitalised over average interest-bearing obligations, annualised
A26: Measured corporate credit spread | B26: 0.018630079 | C26: the company's own borrowing cost less the return on its own treasury-bill book
A27: Share of interest capitalised into work in progress | B27: 0.44878166

Sheet Peer & Sector
A1: PEERS AND THE SECTOR
A2: Peer multiples are market-data quotes and are used to price other companies only. No aggregator figure enters any Palm Hills historical.
A4: Company | B4: Listing | C4: Market value, EGP mn | D4: Price to earnings | E4: EV to EBITDA | F4: Note
A5: Talaat Moustafa Group Holding | B5: EGX:TMGH | C5: 156630 | D5: 10.2 | F5: Egypt
A6: Emaar Misr for Development | B6: EGX:EMFD | C6: 54600 | D6: 6.1 | F6: Egypt
A7: SODIC | B7: EGX:OCDI | C7: 24100 | D7: 6.1 | F7: Egypt
A8: Heliopolis Housing | B8: EGX:HELI | C8: 22670 | D8: 7.5 | F8: Egypt
A9: Madinet Masr | B9: EGX:MASR | C9: 16500 | F9: Egypt
A10: Emaar Properties | B10: DFM:EMAAR | D10: 6.5 | E10: 3.6 | F10: United Arab Emirates
A11: Aldar Properties | B11: ADX:ALDAR | D11: 7.7 | E11: 6.6 | F11: United Arab Emirates
A12: Palm Hills Developments | B12: EGX:PHDC | C12: 42395.297 | D12: 10.539981 | E12: 5.8791863 | F12: computed from the statements at the published price
A14: THE EGYPTIAN MARKET IN THE FIRST HALF OF 2026
A15: Sales of the ten largest developers, EGP mn | B15: 670000 | F15: H1-2026
A16: Same measure a year earlier, EGP mn | B16: 651000 | F16: H1-2025
A17: Change in value | B17: 0.029185868
A18: Change in units | B18: -0.05 | F18: about 39,000 units
A19: Implied change in the average ticket | B19: 0.083353545 | F19: the dated anchor for the selling-price escalator
A20: Palm Hills H1-2026 sales, EGP mn | B20: 94000 | F20: SECONDARY AND UNVERIFIED — the company release could not be obtained; no driver reads it
A21: Palm Hills share of the top ten | B21: 0.14029851
