Workbook

Sheet READ FIRST
A1: Testahil — Independent Valuation Study — Educational Analysis
A2: Tesla, Inc. (NASDAQ: TSLA) · companion model · edition 30-06-2026 · reporting currency USD
A4: READ FIRST — what this workbook is, and is not.
A6: This workbook is the companion model to the Tesla valuation study. It is an educational exercise in transparent valuation: every assumption is a blue input on the Assumptions sheet, and every downstream figure links back to it, so you can change any input and reprice the whole model.
A8: It is NOT investment advice, NOT a recommendation or solicitation to buy, sell or hold any security, and NOT directed at the circumstances of any reader. The preparer is not licensed by any securities regulator, holds no brokerage authorisation, manages no money and accepts no clients.
A10: Reported financials are Tesla's own disclosure (SEC filings, ir.tesla.com). Forward-looking inputs — the autonomy/AI optionality value, the segment marks, operating margins, multiples, the DCF and the Monte-Carlo factor probabilities — are the preparer's judgments and are flagged blue.
A12: Colour key: BLUE = input you can change (Assumptions). BLACK = formula. GREEN = link pulling from another sheet.
A14: The Monte Carlo is a price model, not a forecast; it encodes subjective probabilities for events that have not happened and says nothing about value. Spot and market data are as of 30 June 2026 and change continuously. The preparer may hold, and may in future take or dispose of, a position in the security discussed. Consult a licensed professional before any decision.

Sheet Summary
A1: Summary — Tesla, Inc. (NASDAQ: TSLA)
A2: 30 Jun 2026 · reporting currency USD · educational valuation study
A4: Spot price (USD) | B4: =Assumptions!B5 -> 420.6
A5: Shares (bn) | B5: =Assumptions!B6 -> 3.23
A6: Market cap (USD bn) | B6: =B4*B5 -> 1358.538
A8: Weighted central fair value (USD) | B8: ='Fundamental Valuation'!B9 -> 174.12029
A9: vs spot | B9: =B8/B4-1 -> -0.58601928
A11: Valuation range (USD/sh)
A12: SOTP — base (primary) | B12: =SOTP!C15 -> 230.92
A13: DCF — cross-check | B13: =DCF!B26 -> 89.876
A14: Relative (blended) | B14: ='Relative & Normalized'!D8 -> 172.34262
A15: Normalized earnings | B15: ='Relative & Normalized'!B13 -> 151.70279
A16: Autonomy-at-scale (SOTP bull) | B16: =SOTP!C16 -> 560
A18: Monte Carlo (3-month, 50k paths, seed 42)
A19: T+60 median (USD) | B19: ='Monte Carlo'!C19 -> 0.46
A20: T+60 5%–95% band (USD) | B20: ='Monte Carlo'!B19&" – "&'Monte Carlo'!F19 -> 0.21 – 647
A22: Read: richly valued on fundamentals; the case is an autonomy/AI optionality bet. This is a valuation, not advice.

Sheet Fundamental Valuation
A1: Fundamental valuation — four lenses
A2: DCF is the primary anchor; SOTP isolates the autonomy option. All values link from their sheets.
A4: Method | B4: USD / sh | C4: vs spot | D4: Weight
A5: SOTP — segments + option (primary) | B5: =SOTP!C15 -> 230.92 | C5: =B5/Assumptions!B5-1 -> -0.4509748 | D5: =Assumptions!B38 -> 0.4
A6: Consolidated DCF (cross-check) | B6: =DCF!B26 -> 89.876 | C6: =B6/Assumptions!B5-1 -> -0.78631479 | D6: =Assumptions!B39 -> 0.2
A7: Relative multiples (blended) | B7: ='Relative & Normalized'!D8 -> 172.34262 | C7: =B7/Assumptions!B5-1 -> -0.59024579 | D7: =Assumptions!B40 -> 0.15
A8: Normalized earnings power | B8: ='Relative & Normalized'!B13 -> 151.70279 | C8: =B8/Assumptions!B5-1 -> -0.63931815 | D8: =Assumptions!B41 -> 0.25
A9: WEIGHTED CENTRAL | B9: =SUMPRODUCT(B5:B8,D5:D8) -> 174.12029 | C9: =B9/Assumptions!B5-1 -> -0.58601928 | D9: =SUM(D5:D8) -> 1
A11: Memo: autonomy-at-scale (SOTP bull) | B11: =SOTP!C16 -> 560
A12: Memo: spot (USD) | B12: =Assumptions!B5 -> 420.6
A13: Memo: Monte Carlo T+60 median (USD) | B13: ='Monte Carlo'!C19 -> 0.46
A15: All four operating lenses sit below spot; only the autonomy-at-scale case exceeds it. The dispersion is the widest in coverage.

Sheet Assumptions
A1: Assumptions — single input layer
A2: All blue cells are inputs. Every other sheet links to this sheet.
A4: Market
A5: Spot price (USD, 30 Jun 2026 close) | B5: 420.6
A6: Shares outstanding (bn) | B6: 3.23
A7: Net cash & investments (USD bn) | B7: 40
A9: DCF — operating forecast
A10: Year | B10: 2026e | C10: 2027e | D10: 2028e | E10: 2029e | F10: 2030e
A11: Revenue (USD bn) | C11: 108 | D11: 130 | E11: 154 | F11: 182 | G11: 215
A12: EBIT margin | C12: 0.065 | D12: 0.09 | E12: 0.115 | F12: 0.135 | G12: 0.155
A13: D&A (USD bn) | C13: 6.5 | D13: 7.5 | E13: 8.5 | F13: 9.5 | G13: 11
A14: Capex (USD bn) | C14: 25 | D14: 22 | E14: 20 | F14: 18 | G14: 17
A15: Δ working capital (USD bn) | C15: 1 | D15: 1.5 | E15: 1.5 | F15: 1.5 | G15: 1.5
A17: Tax rate | B17: 0.15
A18: WACC | B18: 0.1
A19: Terminal growth | B19: 0.045
A21: SOTP — segment & optionality (per share)
A22: Automotive value / sh | B22: 70
A23: Energy gen. & storage / sh | B23: 35
A24: Services & other / sh | B24: 10
A25: Net cash & investments / sh | B25: 12
A26: Autonomy option — full-scale value / sh | B26: 433
A27: Autonomy option — base probability weight | B27: 0.24
A29: Relative & normalized multiples
A30: EV / Sales multiple | B30: 5
A31: EV / EBITDA multiple | B31: 30
A32: P / E multiple (relative) | B32: 45
A33: Normalized EBITDA (USD bn) | B33: 17
A34: Normalized net earnings (USD bn) | B34: 12
A35: Normalized P/E multiple | B35: 35
A36: Normalized earnings — power lens (USD bn) | B36: 14
A37: Lens weights (synthesis — four lenses)
A38: SOTP — base (primary) | B38: 0.4
A39: DCF — cross-check | B39: 0.2
A40: Relative multiples | B40: 0.15
A41: Normalized earnings | B41: 0.25
A42: Weights total | B42: =SUM(B38:B41) -> 1
A44: Memo: autonomy-at-scale (SOTP bull, not weighted) | B44: =SOTP!C16 -> 560

Sheet SOTP
A1: Segment sum-of-the-parts — isolating the optionality
A2: Cross-check that separates the operating businesses from the autonomy option. Marks link to Assumptions.
A4: Component (per share) | B4: Basis | C4: USD / sh
A5: Automotive | B5: normalized EBIT multiple | C5: =Assumptions!B22 -> 70
A6: Energy generation & storage | B6: growth multiple | C6: =Assumptions!B23 -> 35
A7: Services & other | B7: modest multiple | C7: =Assumptions!B24 -> 10
A8: Net cash & investments | B8: balance sheet | C8: =Assumptions!B25 -> 12
A9: Operating businesses subtotal | C9: =SUM(C5:C8) -> 127
A11: Autonomy option — full-scale value | B11: Robotaxi + FSD + Optimus | C11: =Assumptions!B26 -> 433
A12: Base probability weight | C12: =Assumptions!B27 -> 0.24
A13: Autonomy option (risk-weighted, base) | C13: =C11*C12 -> 103.92
A15: SOTP — base (opt. risk-weighted) | C15: =C9+C13 -> 230.92
A16: SOTP — autonomy bull (opt. at full scale) | C16: =C9+C11 -> 560
A17: SOTP — core-only bear (opt. → 0) | C17: =C9 -> 127
A19: vs spot — base | C19: =C15/Assumptions!B5-1 -> -0.4509748
A20: vs spot — bull | C20: =C16/Assumptions!B5-1 -> 0.33143129
A21: vs spot — bear | C21: =C17/Assumptions!B5-1 -> -0.6980504
A23: The autonomy option is the swing factor: the entire gap to spot is a probability weight on an outcome that has not happened.

Sheet Segments
A1: Segments — operating revenue build
A2: Segment revenue links to the Income Statement; used by the SOTP.
A4: Segment revenue (USD bn) | B4: 2025a | C4: 2026e | D4: 2027e | E4: 2028e | F4: 2029e | G4: 2030e
A5: Automotive | B5: ='Income Statement'!C5 -> 77.1 | D5: ='Income Statement'!E5 -> 87.4 | E5: ='Income Statement'!F5 -> 104.7 | F5: ='Income Statement'!G5 -> 124 | G5: ='Income Statement'!H5 -> 146 | H5: ='Income Statement'!I5 -> 173
A6: Energy generation & storage | B6: ='Income Statement'!C6 -> 10.1 | D6: ='Income Statement'!E6 -> 16 | E6: ='Income Statement'!F6 -> 20 | F6: ='Income Statement'!G6 -> 24 | G6: ='Income Statement'!H6 -> 28 | H6: ='Income Statement'!I6 -> 32
A7: Services & other | B7: ='Income Statement'!C7 -> 10.5 | D7: ='Income Statement'!E7 -> 14 | E7: ='Income Statement'!F7 -> 16 | F7: ='Income Statement'!G7 -> 18 | G7: ='Income Statement'!H7 -> 20 | H7: ='Income Statement'!I7 -> 22
A8: Total revenue | B8: =SUM(B5:B7) -> 97.7 | D8: =SUM(D5:D7) -> 117.4 | E8: =SUM(E5:E7) -> 140.7 | F8: =SUM(F5:F7) -> 166 | G8: =SUM(G5:G7) -> 194 | H8: =SUM(H5:H7) -> 227
A10: Segment mix (2030e)
A11: Automotive % | B11: =G5/G8 -> 0.75257732
A12: Energy % | B12: =G6/G8 -> 0.1443299
A13: Services % | B13: =G7/G8 -> 0.10309278

Sheet Relative & Normalized
A1: Relative multiples & normalized earnings
A2: Multiples and metrics link to Assumptions and the Income Statement.
A4: Relative lens | B4: Metric (USD bn) | C4: Multiple | D4: Implied / sh
A5: EV / Sales | B5: =Assumptions!C11 -> 108 | C5: =Assumptions!B30 -> 5 | D5: =(B5*C5+Assumptions!B7)/Assumptions!B6 -> 179.56656
A6: EV / EBITDA | B6: =Assumptions!B33 -> 17 | C6: =Assumptions!B31 -> 30 | D6: =(B6*C6+Assumptions!B7)/Assumptions!B6 -> 170.27864
A7: P / E | B7: =Assumptions!B34 -> 12 | C7: =Assumptions!B32 -> 45 | D7: =(B7*C7)/Assumptions!B6 -> 167.18266
A8: Blended relative value | D8: =AVERAGE(D5:D7) -> 172.34262
A10: Normalized earnings power
A11: Normalized net earnings (USD bn) | B11: =Assumptions!B36 -> 14
A12: Normalized P/E | B12: =Assumptions!B35 -> 35
A13: Normalized value / sh (USD) | B13: =B11*B12/Assumptions!B6 -> 151.70279
A15: No clean peer set exists; the relative lens is the least informative and is a discipline, not the anchor.

Sheet DCF
A1: DCF — going-concern (primary lens)
A2: Unlevered FCFF on the operating business. Drivers link to Assumptions.
A4: FCFF build (USD bn) | B4: 2026e | C4: 2027e | D4: 2028e | E4: 2029e | F4: 2030e
A5: Revenue | C5: =Assumptions!C11 -> 108 | D5: =Assumptions!D11 -> 130 | E5: =Assumptions!E11 -> 154 | F5: =Assumptions!F11 -> 182 | G5: =Assumptions!G11 -> 215
A6: EBIT margin | C6: =Assumptions!C12 -> 0.065 | D6: =Assumptions!D12 -> 0.09 | E6: =Assumptions!E12 -> 0.115 | F6: =Assumptions!F12 -> 0.135 | G6: =Assumptions!G12 -> 0.155
A7: EBIT | C7: =C5*C6 -> 7.02 | D7: =D5*D6 -> 11.7 | E7: =E5*E6 -> 17.71 | F7: =F5*F6 -> 24.57 | G7: =G5*G6 -> 33.325
A8: NOPAT (after tax) | C8: =C7*(1-Assumptions!$B$17) -> 5.967 | D8: =D7*(1-Assumptions!$B$17) -> 9.945 | E8: =E7*(1-Assumptions!$B$17) -> 15.0535 | F8: =F7*(1-Assumptions!$B$17) -> 20.8845 | G8: =G7*(1-Assumptions!$B$17) -> 28.32625
A9: (+) D&A | C9: =Assumptions!C13 -> 6.5 | D9: =Assumptions!D13 -> 7.5 | E9: =Assumptions!E13 -> 8.5 | F9: =Assumptions!F13 -> 9.5 | G9: =Assumptions!G13 -> 11
A10: (−) Capex | C10: =-Assumptions!C14 -> -25 | D10: =-Assumptions!D14 -> -22 | E10: =-Assumptions!E14 -> -20 | F10: =-Assumptions!F14 -> -18 | G10: =-Assumptions!G14 -> -17
A11: (−) Δ working capital | C11: =-Assumptions!C15 -> -1 | D11: =-Assumptions!D15 -> -1.5 | E11: =-Assumptions!E15 -> -1.5 | F11: =-Assumptions!F15 -> -1.5 | G11: =-Assumptions!G15 -> -1.5
A12: Unlevered FCFF | C12: =C8+C9+C10+C11 -> -13.533 | D12: =D8+D9+D10+D11 -> -6.055 | E12: =E8+E9+E10+E11 -> 2.0535 | F12: =F8+F9+F10+F11 -> 10.8845 | G12: =G8+G9+G10+G11 -> 20.82625
A13: Discount period (t) | C13: 1 | D13: 2 | E13: 3 | F13: 4 | G13: 5
A14: Discount factor | C14: =1/(1+Assumptions!$B$18)^C13 -> 0.90909091 | D14: =1/(1+Assumptions!$B$18)^D13 -> 0.82644628 | E14: =1/(1+Assumptions!$B$18)^E13 -> 0.7513148 | F14: =1/(1+Assumptions!$B$18)^F13 -> 0.68301346 | G14: =1/(1+Assumptions!$B$18)^G13 -> 0.62092132
A15: PV of FCFF | C15: =C12*C14 -> -12.302727 | D15: =D12*D14 -> -5.0041322 | E15: =E12*E14 -> 1.5428249 | F15: =F12*F14 -> 7.43426 | G15: =G12*G14 -> 12.931463
A18: DCF bridge to value
A19: PV of explicit FCFF (2026e–2030e) | B19: =SUM(C15:G15) -> 4.6016881
A20: Terminal value (Gordon, on 2030e FCFF) | B20: =G12*(1+Assumptions!$B$19)/(Assumptions!$B$18-Assumptions!$B$19) -> 395.69875
A21: PV of terminal value | B21: =B20*G14 -> 245.69779
A22: Enterprise value | B22: =B19+B21 -> 250.29948
A23: (+) Net cash & investments | B23: =Assumptions!B7 -> 40
A24: Equity value | B24: =B22+B23 -> 290.29948
A25: Shares (bn) | B25: =Assumptions!B6 -> 3.23
A26: DCF value / share (USD) | B26: =B24/B25 -> 89.876
A27: vs spot | B27: =B26/Assumptions!B5-1 -> -0.78631479
A29: Note: value is dominated by the terminal year; see Sensitivity for the WACC×g grid.

Sheet Income Statement
A1: Consolidated income statement (USD bn)
A2: Actuals: Tesla Q4/FY2025 Update & FY2025 10-K (SEC). Forecast drivers link to Assumptions.
A4: Income statement | B4: 2023a | C4: 2024a | D4: 2025a | E4: 2026e | F4: 2027e | G4: 2028e | H4: 2029e | I4: 2030e
A5: Automotive revenue | B5: 82.4 | C5: 77.1 | D5: 69.5 | E5: =Assumptions!C11-C6-C7 -> 87.4 | F5: =Assumptions!D11-D6-D7 -> 104.7 | G5: =Assumptions!E11-E6-E7 -> 124 | H5: =Assumptions!F11-F6-F7 -> 146 | I5: =Assumptions!G11-G6-G7 -> 173
A6: Energy gen. & storage | B6: 6 | C6: 10.1 | D6: 12.8 | E6: 16 | F6: 20 | G6: 24 | H6: 28 | I6: 32
A7: Services & other | B7: 8.3 | C7: 10.5 | D7: 12.5 | E7: 14 | F7: 16 | G7: 18 | H7: 20 | I7: 22
A8: Total revenue | B8: 96.8 | C8: 97.7 | D8: 94.8 | E8: =Assumptions!C11 -> 108 | F8: =Assumptions!D11 -> 130 | G8: =Assumptions!E11 -> 154 | H8: =Assumptions!F11 -> 182 | I8: =Assumptions!G11 -> 215
A9: growth YoY | C9: =C8/B8-1 -> 0.0092975207 | D9: =D8/C8-1 -> -0.029682702 | E9: =E8/D8-1 -> 0.13924051 | F9: =F8/E8-1 -> 0.2037037 | G9: =G8/F8-1 -> 0.18461538 | H9: =H8/G8-1 -> 0.18181818 | I9: =I8/H8-1 -> 0.18131868
A10: (Cost & opex) | B10: =-(B8-B12) -> -87.8944 | C10: =-(C8-C12) -> -90.5679 | D10: =-(D8-D12) -> -90.534 | E10: =-(E8-E12) -> -100.98 | F10: =-(F8-F12) -> -118.3 | G10: =-(G8-G12) -> -136.29 | H10: =-(H8-H12) -> -157.43 | I10: =-(I8-I12) -> -181.675
A11: EBIT margin | B11: 0.092 | C11: 0.073 | D11: 0.045 | E11: =Assumptions!C12 -> 0.065 | F11: =Assumptions!D12 -> 0.09 | G11: =Assumptions!E12 -> 0.115 | H11: =Assumptions!F12 -> 0.135 | I11: =Assumptions!G12 -> 0.155
A12: Operating profit | B12: =B8*B11 -> 8.9056 | C12: =C8*C11 -> 7.1321 | D12: =D8*D11 -> 4.266 | E12: =E8*E11 -> 7.02 | F12: =F8*F11 -> 11.7 | G12: =G8*G11 -> 17.71 | H12: =H8*H11 -> 24.57 | I12: =I8*I11 -> 33.325
A13: Net interest & other | B13: 1 | C13: 1.6 | D13: 1.6 | E13: 1.5 | F13: 1.6 | G13: 1.7 | H13: 1.8 | I13: 1.9
A14: Pre-tax profit | B14: =B12+B13 -> 9.9056 | C14: =C12+C13 -> 8.7321 | D14: =D12+D13 -> 5.866 | E14: =E12+E13 -> 8.52 | F14: =F12+F13 -> 13.3 | G14: =G12+G13 -> 19.41 | H14: =H12+H13 -> 26.37 | I14: =I12+I13 -> 35.225
A15: Tax & minorities | B15: 5.1 | C15: -1.6 | D15: -2.1 | E15: =-E14*Assumptions!$B$17 -> -1.278 | F15: =-F14*Assumptions!$B$17 -> -1.995 | G15: =-G14*Assumptions!$B$17 -> -2.9115 | H15: =-H14*Assumptions!$B$17 -> -3.9555 | I15: =-I14*Assumptions!$B$17 -> -5.28375
A16: Net profit attributable | B16: =B14+B15 -> 15.0056 | C16: =C14+C15 -> 7.1321 | D16: =D14+D15 -> 3.766 | E16: =E14+E15 -> 7.242 | F16: =F14+F15 -> 11.305 | G16: =G14+G15 -> 16.4985 | H16: =H14+H15 -> 22.4145 | I16: =I14+I15 -> 29.94125
A17: EPS (USD) | B17: =B16/Assumptions!$B$6 -> 4.6456966 | C17: =C16/Assumptions!$B$6 -> 2.2080805 | D17: =D16/Assumptions!$B$6 -> 1.1659443 | E17: =E16/Assumptions!$B$6 -> 2.2421053 | F17: =F16/Assumptions!$B$6 -> 3.5 | G17: =G16/Assumptions!$B$6 -> 5.1078947 | H17: =H16/Assumptions!$B$6 -> 6.9394737 | I17: =I16/Assumptions!$B$6 -> 9.2697368
A19: FY2023 net income includes a ~USD 5.9bn one-time deferred-tax benefit. FY2025 was the first annual revenue decline in Tesla's history.

Sheet Balance Sheet
A1: Consolidated balance sheet (USD bn)
A2: Anchored to Tesla's reported totals; sub-lines are approximate allocations.
A4: Balance sheet | B4: 2023a | C4: 2024a | D4: 2025a | E4: 2026e | F4: 2027e | G4: 2028e | H4: 2029e | I4: 2030e
A5: Cash & equivalents | B5: 16.4 | C5: 16.1 | D5: 16.5 | E5: 14 | F5: 16 | G5: 20 | H5: 26 | I5: 34
A6: Short/long-term investments | B6: 12.7 | C6: 20.4 | D6: 28.2 | E6: 28 | F6: 28 | G6: 28 | H6: 28 | I6: 28
A7: Receivables & other | B7: 3.5 | C7: 4.4 | D7: 4.5 | E7: 5 | F7: 6 | G7: 7 | H7: 8 | I7: 9
A8: Inventory | B8: 13.6 | C8: 12 | D8: 12.5 | E8: 14 | F8: 16 | G8: 18 | H8: 20 | I8: 22
A9: Total current assets | B9: =SUM(B5:B8) -> 46.2 | C9: =SUM(C5:C8) -> 52.9 | D9: =SUM(D5:D8) -> 61.7 | E9: =SUM(E5:E8) -> 61 | F9: =SUM(F5:F8) -> 66 | G9: =SUM(G5:G8) -> 73 | H9: =SUM(H5:H8) -> 82 | I9: =SUM(I5:I8) -> 93
A10: Property, plant & equipment | B10: 29.7 | C10: 35.8 | D10: 40 | E10: 52 | F10: 62 | G10: 70 | H10: 76 | I10: 80
A11: Other non-current assets | B11: 30.9 | C11: 33.5 | D11: 33.3 | E11: 34 | F11: 35 | G11: 36 | H11: 37 | I11: 38
A12: Total assets | B12: =B9+B10+B11 -> 106.8 | C12: =C9+C10+C11 -> 122.2 | D12: =D9+D10+D11 -> 135 | E12: =E9+E10+E11 -> 147 | F12: =F9+F10+F11 -> 163 | G12: =G9+G10+G11 -> 179 | H12: =H9+H10+H11 -> 195 | I12: =I9+I10+I11 -> 211
A13: Payables & accrued | B13: 23.8 | C13: 26.6 | D13: 28 | E13: 30 | F13: 33 | G13: 36 | H13: 39 | I13: 42
A14: Debt & finance leases | B14: 9.6 | C14: 7.3 | D14: 6.5 | E14: 6.5 | F14: 6.5 | G14: 6.5 | H14: 6.5 | I14: 6.5
A15: Other liabilities | B15: 10.5 | C15: 13.6 | D15: 14.5 | E15: 15 | F15: 15.5 | G15: 16 | H15: 16.5 | I15: 17
A16: Total liabilities | B16: =B13+B14+B15 -> 43.9 | C16: =C13+C14+C15 -> 47.5 | D16: =D13+D14+D15 -> 49 | E16: =E13+E14+E15 -> 51.5 | F16: =F13+F14+F15 -> 55 | G16: =G13+G14+G15 -> 58.5 | H16: =H13+H14+H15 -> 62 | I16: =I13+I14+I15 -> 65.5
A17: Total equity | B17: =B12-B16 -> 62.9 | C17: =C12-C16 -> 74.7 | D17: =D12-D16 -> 86 | E17: =E12-E16 -> 95.5 | F17: =F12-F16 -> 108 | G17: =G12-G16 -> 120.5 | H17: =H12-H16 -> 133 | I17: =I12-I16 -> 145.5
A18: Net cash (cash+inv − debt) | B18: =B5+B6-B14 -> 19.5 | C18: =C5+C6-C14 -> 29.2 | D18: =D5+D6-D14 -> 38.2 | E18: =E5+E6-E14 -> 35.5 | F18: =F5+F6-F14 -> 37.5 | G18: =G5+G6-G14 -> 41.5 | H18: =H5+H6-H14 -> 47.5 | I18: =I5+I6-I14 -> 55.5
A20: Net cash of ~USD 38bn is a real asset in the SOTP.

Sheet Cash Flow
A1: Consolidated cash flow (simplified, USD bn)
A2: 2026 capex step-up (>USD 25bn) turns FCF sharply negative before recovery.
A4: Cash flow | B4: 2023a | C4: 2024a | D4: 2025a | E4: 2026e | F4: 2027e | G4: 2028e | H4: 2029e | I4: 2030e
A5: Operating cash flow | B5: 13.3 | C5: 14.9 | D5: 16.8 | E5: 11.5 | F5: 15.9 | G5: 22.1 | H5: 28.9 | I5: 37.8
A6: Capex (investing) | B6: -8.9 | C6: -11.3 | D6: -8.6 | E6: =-Assumptions!C14 -> -25 | F6: =-Assumptions!D14 -> -22 | G6: =-Assumptions!E14 -> -20 | H6: =-Assumptions!F14 -> -18 | I6: =-Assumptions!G14 -> -17
A7: Free cash flow | B7: =B5+B6 -> 4.4 | C7: =C5+C6 -> 3.6 | D7: =D5+D6 -> 8.2 | E7: =E5+E6 -> -13.5 | F7: =F5+F6 -> -6.1 | G7: =G5+G6 -> 2.1 | H7: =H5+H6 -> 10.9 | I7: =I5+I6 -> 20.8
A9: Forecast FCF ties to the unlevered FCFF on the DCF sheet (differences are financing/interest).

Sheet Summary Financials
A1: Summary financials
A2: Every cell links to the statement sheets.
A4: USD bn | B4: 2023a | C4: 2024a | D4: 2025a | E4: 2026e | F4: 2027e | G4: 2028e | H4: 2029e | I4: 2030e
A5: Total revenue | B5: ='Income Statement'!B8 -> 96.8 | C5: ='Income Statement'!C8 -> 97.7 | D5: ='Income Statement'!D8 -> 94.8 | E5: ='Income Statement'!E8 -> 108 | F5: ='Income Statement'!F8 -> 130 | G5: ='Income Statement'!G8 -> 154 | H5: ='Income Statement'!H8 -> 182 | I5: ='Income Statement'!I8 -> 215
A6: Operating profit | B6: ='Income Statement'!B12 -> 8.9056 | C6: ='Income Statement'!C12 -> 7.1321 | D6: ='Income Statement'!D12 -> 4.266 | E6: ='Income Statement'!E12 -> 7.02 | F6: ='Income Statement'!F12 -> 11.7 | G6: ='Income Statement'!G12 -> 17.71 | H6: ='Income Statement'!H12 -> 24.57 | I6: ='Income Statement'!I12 -> 33.325
A7: Operating margin | B7: ='Income Statement'!B12/'Income Statement'!B8 -> 0.092 | C7: ='Income Statement'!C12/'Income Statement'!C8 -> 0.073 | D7: ='Income Statement'!D12/'Income Statement'!D8 -> 0.045 | E7: ='Income Statement'!E12/'Income Statement'!E8 -> 0.065 | F7: ='Income Statement'!F12/'Income Statement'!F8 -> 0.09 | G7: ='Income Statement'!G12/'Income Statement'!G8 -> 0.115 | H7: ='Income Statement'!H12/'Income Statement'!H8 -> 0.135 | I7: ='Income Statement'!I12/'Income Statement'!I8 -> 0.155
A8: Net profit | B8: ='Income Statement'!B16 -> 15.0056 | C8: ='Income Statement'!C16 -> 7.1321 | D8: ='Income Statement'!D16 -> 3.766 | E8: ='Income Statement'!E16 -> 7.242 | F8: ='Income Statement'!F16 -> 11.305 | G8: ='Income Statement'!G16 -> 16.4985 | H8: ='Income Statement'!H16 -> 22.4145 | I8: ='Income Statement'!I16 -> 29.94125
A9: EPS (USD) | B9: ='Income Statement'!B17 -> 4.6456966 | C9: ='Income Statement'!C17 -> 2.2080805 | D9: ='Income Statement'!D17 -> 1.1659443 | E9: ='Income Statement'!E17 -> 2.2421053 | F9: ='Income Statement'!F17 -> 3.5 | G9: ='Income Statement'!G17 -> 5.1078947 | H9: ='Income Statement'!H17 -> 6.9394737 | I9: ='Income Statement'!I17 -> 9.2697368
A10: Total assets | B10: ='Balance Sheet'!B12 -> 106.8 | C10: ='Balance Sheet'!C12 -> 122.2 | D10: ='Balance Sheet'!D12 -> 135 | E10: ='Balance Sheet'!E12 -> 147 | F10: ='Balance Sheet'!F12 -> 163 | G10: ='Balance Sheet'!G12 -> 179 | H10: ='Balance Sheet'!H12 -> 195 | I10: ='Balance Sheet'!I12 -> 211
A11: Total equity | B11: ='Balance Sheet'!B17 -> 62.9 | C11: ='Balance Sheet'!C17 -> 74.7 | D11: ='Balance Sheet'!D17 -> 86 | E11: ='Balance Sheet'!E17 -> 95.5 | F11: ='Balance Sheet'!F17 -> 108 | G11: ='Balance Sheet'!G17 -> 120.5 | H11: ='Balance Sheet'!H17 -> 133 | I11: ='Balance Sheet'!I17 -> 145.5
A12: Net cash | B12: ='Balance Sheet'!B18 -> 19.5 | C12: ='Balance Sheet'!C18 -> 29.2 | D12: ='Balance Sheet'!D18 -> 38.2 | E12: ='Balance Sheet'!E18 -> 35.5 | F12: ='Balance Sheet'!F18 -> 37.5 | G12: ='Balance Sheet'!G18 -> 41.5 | H12: ='Balance Sheet'!H18 -> 47.5 | I12: ='Balance Sheet'!I18 -> 55.5
A13: Operating cash flow | B13: ='Cash Flow'!B5 -> 13.3 | C13: ='Cash Flow'!C5 -> 14.9 | D13: ='Cash Flow'!D5 -> 16.8 | E13: ='Cash Flow'!E5 -> 11.5 | F13: ='Cash Flow'!F5 -> 15.9 | G13: ='Cash Flow'!G5 -> 22.1 | H13: ='Cash Flow'!H5 -> 28.9 | I13: ='Cash Flow'!I5 -> 37.8
A14: Free cash flow | B14: ='Cash Flow'!B7 -> 4.4 | C14: ='Cash Flow'!C7 -> 3.6 | D14: ='Cash Flow'!D7 -> 8.2 | E14: ='Cash Flow'!E7 -> -13.5 | F14: ='Cash Flow'!F7 -> -6.1 | G14: ='Cash Flow'!G7 -> 2.1 | H14: ='Cash Flow'!H7 -> 10.9 | I14: ='Cash Flow'!I7 -> 20.8

Sheet Monte Carlo
A1: Monte Carlo — 3-month price map
A2: 16 factors (7 continuous + 9 discrete) · 50,000 paths · seed 42 · realized vol 48%. Outputs from the companion engine.
A4: Engine parameters
A5: Anchor / spot (USD) | B5: =Assumptions!B5 -> 420.6
A6: Realized volatility (annualized) | B6: 0.48
A7: Net 3-month factor drift | B7: 0.029
A8: Annualized path volatility (with events) | B8: 0.554
A10: Percentile table (USD)
A11: Horizon | B11: 5% | C11: 25% | D11: Median | E11: 75% | F11: 95%
A12: T+20 (~1 month) | B12: 325 | C12: 379 | D12: 420 | E12: 466 | F12: 541
A13: T+60 (~3 months) | B13: 270 | C13: 350 | D13: 419 | E13: 501 | F13: 647
A15: Touch probabilities (chance price reaches level in window)
A16: Level (USD) | B16: by T+20 | C16: by T+60 | D16: Note
A17: 460 | B17: 0.47 | C17: 0.68 | D17: toward recent highs
A18: 485 | B18: 0.29 | C18: 0.54 | D18: toward 52-wk high
A19: 500 | B19: 0.21 | C19: 0.46 | D19: above 52-wk high | E19: 501 | F19: 647
A20: 540 | B20: 0.08 | C20: 0.3 | D20: new-high extension
A21: 380 | B21: 0.42 | C21: 0.65 | D21: support (MA cluster)
A22: 360 | B22: 0.25 | C22: 0.51 | D22: below MAs
A23: 320 | B23: 0.06 | C23: 0.28 | D23: deeper pullback
A24: 290 | B24: 0.01 | C24: 0.15 | D24: range low / SOTP zone
A26: Factor structure (drift = 3-month, price-space; discrete = probability × impact)
A27: Factor | B27: Tier | C27: Drift / impact | D27: Prob.
A28: Auto ASP / gross-margin trajectory | B28: C | C28: -0.005 | D28: —
A29: Delivery-volume trajectory | B29: C | C29: 0.01 | D29: —
A30: Nasdaq / high-beta growth flows | B30: C | C30: 0.01 | D30: —
A31: US real-rate / discount-rate path | B31: C | C31: -0.006 | D31: —
A32: FSD / Robotaxi monetization ramp | B32: C | C32: 0.014 | D32: —
A33: Energy-storage & services growth | B33: C | C33: 0.006 | D33: —
A34: Input cost / FX | B34: C | C34: 0 | D34: —
A35: Robotaxi / unsupervised-FSD milestone | B35: E | C35: 0.08 | D35: 0.35
A36: Quarterly delivery beat/miss | B36: E | C36: 0.01 | D36: 0.45
A37: Quarterly earnings/margin surprise | B37: E | C37: 0 | D37: 0.5
A38: Optimus / new-product progress | B38: E | C38: 0.06 | D38: 0.3
A39: China demand / price-war shock | B39: E | C39: -0.07 | D39: 0.3
A40: EV-credit / tariff / FSD-probe policy | B40: E | C40: -0.06 | D40: 0.35
A41: Key-person / governance / attention | B41: E | C41: -0.01 | D41: 0.3
A42: Broad Nasdaq risk-off | B42: M | C42: -0.06 | D42: 0.25
A43: Energy megadeal / margin inflection | B43: E | C43: 0.04 | D43: 0.3
A45: The paths diffuse from spot and deliberately do not embed the §1 value gap, so the fundamental and probabilistic lenses stay independent.

Sheet Sensitivity
A1: DCF sensitivity — value/share by WACC × terminal g
A2: Recomputes the DCF value for each WACC/g pairing off the FCFF stream. Base cell highlighted.
A4: WACC \ g | B4: 0.03 | C4: 0.035 | D4: 0.04 | E4: 0.045 | F4: 0.05
A5: 0.085 | B5: =(SUMPRODUCT(DCF!$C$12:$G$12,1/(1+0.085)^DCF!$C$13:$G$13)+(DCF!$G$12*(1+0.03)/(0.085-0.03))/(1+0.085)^5+Assumptions!$B$7)/Assumptions!$B$6 -> 94.450798 | C5: =(SUMPRODUCT(DCF!$C$12:$G$12,1/(1+0.085)^DCF!$C$13:$G$13)+(DCF!$G$12*(1+0.035)/(0.085-0.035))/(1+0.085)^5+Assumptions!$B$7)/Assumptions!$B$6 -> 102.90995 | D5: =(SUMPRODUCT(DCF!$C$12:$G$12,1/(1+0.085)^DCF!$C$13:$G$13)+(DCF!$G$12*(1+0.04)/(0.085-0.04))/(1+0.085)^5+Assumptions!$B$7)/Assumptions!$B$6 -> 113.24892 | E5: =(SUMPRODUCT(DCF!$C$12:$G$12,1/(1+0.085)^DCF!$C$13:$G$13)+(DCF!$G$12*(1+0.045)/(0.085-0.045))/(1+0.085)^5+Assumptions!$B$7)/Assumptions!$B$6 -> 126.17262 | F5: =(SUMPRODUCT(DCF!$C$12:$G$12,1/(1+0.085)^DCF!$C$13:$G$13)+(DCF!$G$12*(1+0.05)/(0.085-0.05))/(1+0.085)^5+Assumptions!$B$7)/Assumptions!$B$6 -> 142.78882
A6: 0.09 | B6: =(SUMPRODUCT(DCF!$C$12:$G$12,1/(1+0.09)^DCF!$C$13:$G$13)+(DCF!$G$12*(1+0.03)/(0.09-0.03))/(1+0.09)^5+Assumptions!$B$7)/Assumptions!$B$6 -> 85.969631 | C6: =(SUMPRODUCT(DCF!$C$12:$G$12,1/(1+0.09)^DCF!$C$13:$G$13)+(DCF!$G$12*(1+0.035)/(0.09-0.035))/(1+0.09)^5+Assumptions!$B$7)/Assumptions!$B$6 -> 92.890468 | D6: =(SUMPRODUCT(DCF!$C$12:$G$12,1/(1+0.09)^DCF!$C$13:$G$13)+(DCF!$G$12*(1+0.04)/(0.09-0.04))/(1+0.09)^5+Assumptions!$B$7)/Assumptions!$B$6 -> 101.19547 | E6: =(SUMPRODUCT(DCF!$C$12:$G$12,1/(1+0.09)^DCF!$C$13:$G$13)+(DCF!$G$12*(1+0.045)/(0.09-0.045))/(1+0.09)^5+Assumptions!$B$7)/Assumptions!$B$6 -> 111.34603 | F6: =(SUMPRODUCT(DCF!$C$12:$G$12,1/(1+0.09)^DCF!$C$13:$G$13)+(DCF!$G$12*(1+0.05)/(0.09-0.05))/(1+0.09)^5+Assumptions!$B$7)/Assumptions!$B$6 -> 124.03423
A7: 0.095 | B7: =(SUMPRODUCT(DCF!$C$12:$G$12,1/(1+0.095)^DCF!$C$13:$G$13)+(DCF!$G$12*(1+0.03)/(0.095-0.03))/(1+0.095)^5+Assumptions!$B$7)/Assumptions!$B$6 -> 78.820704 | C7: =(SUMPRODUCT(DCF!$C$12:$G$12,1/(1+0.095)^DCF!$C$13:$G$13)+(DCF!$G$12*(1+0.035)/(0.095-0.035))/(1+0.095)^5+Assumptions!$B$7)/Assumptions!$B$6 -> 84.570566 | D7: =(SUMPRODUCT(DCF!$C$12:$G$12,1/(1+0.095)^DCF!$C$13:$G$13)+(DCF!$G$12*(1+0.04)/(0.095-0.04))/(1+0.095)^5+Assumptions!$B$7)/Assumptions!$B$6 -> 91.365859 | E7: =(SUMPRODUCT(DCF!$C$12:$G$12,1/(1+0.095)^DCF!$C$13:$G$13)+(DCF!$G$12*(1+0.045)/(0.095-0.045))/(1+0.095)^5+Assumptions!$B$7)/Assumptions!$B$6 -> 99.520209 | F7: =(SUMPRODUCT(DCF!$C$12:$G$12,1/(1+0.095)^DCF!$C$13:$G$13)+(DCF!$G$12*(1+0.05)/(0.095-0.05))/(1+0.095)^5+Assumptions!$B$7)/Assumptions!$B$6 -> 109.48664
A8: 0.1 | B8: =(SUMPRODUCT(DCF!$C$12:$G$12,1/(1+0.1)^DCF!$C$13:$G$13)+(DCF!$G$12*(1+0.03)/(0.1-0.03))/(1+0.1)^5+Assumptions!$B$7)/Assumptions!$B$6 -> 72.717933 | C8: =(SUMPRODUCT(DCF!$C$12:$G$12,1/(1+0.1)^DCF!$C$13:$G$13)+(DCF!$G$12*(1+0.035)/(0.1-0.035))/(1+0.1)^5+Assumptions!$B$7)/Assumptions!$B$6 -> 77.557388 | D8: =(SUMPRODUCT(DCF!$C$12:$G$12,1/(1+0.1)^DCF!$C$13:$G$13)+(DCF!$G$12*(1+0.04)/(0.1-0.04))/(1+0.1)^5+Assumptions!$B$7)/Assumptions!$B$6 -> 83.203418 | E8: =(SUMPRODUCT(DCF!$C$12:$G$12,1/(1+0.1)^DCF!$C$13:$G$13)+(DCF!$G$12*(1+0.045)/(0.1-0.045))/(1+0.1)^5+Assumptions!$B$7)/Assumptions!$B$6 -> 89.876 | F8: =(SUMPRODUCT(DCF!$C$12:$G$12,1/(1+0.1)^DCF!$C$13:$G$13)+(DCF!$G$12*(1+0.05)/(0.1-0.05))/(1+0.1)^5+Assumptions!$B$7)/Assumptions!$B$6 -> 97.883097
A9: 0.105 | B9: =(SUMPRODUCT(DCF!$C$12:$G$12,1/(1+0.105)^DCF!$C$13:$G$13)+(DCF!$G$12*(1+0.03)/(0.105-0.03))/(1+0.105)^5+Assumptions!$B$7)/Assumptions!$B$6 -> 67.451541 | C9: =(SUMPRODUCT(DCF!$C$12:$G$12,1/(1+0.105)^DCF!$C$13:$G$13)+(DCF!$G$12*(1+0.035)/(0.105-0.035))/(1+0.105)^5+Assumptions!$B$7)/Assumptions!$B$6 -> 71.570336 | D9: =(SUMPRODUCT(DCF!$C$12:$G$12,1/(1+0.105)^DCF!$C$13:$G$13)+(DCF!$G$12*(1+0.04)/(0.105-0.04))/(1+0.105)^5+Assumptions!$B$7)/Assumptions!$B$6 -> 76.322791 | E9: =(SUMPRODUCT(DCF!$C$12:$G$12,1/(1+0.105)^DCF!$C$13:$G$13)+(DCF!$G$12*(1+0.045)/(0.105-0.045))/(1+0.105)^5+Assumptions!$B$7)/Assumptions!$B$6 -> 81.867323 | F9: =(SUMPRODUCT(DCF!$C$12:$G$12,1/(1+0.105)^DCF!$C$13:$G$13)+(DCF!$G$12*(1+0.05)/(0.105-0.05))/(1+0.105)^5+Assumptions!$B$7)/Assumptions!$B$6 -> 88.419951
A11: Even the most generous corner stays far below spot: the operating business cannot reach the price on cash flows under any reasonable pairing.

Sheet Per-Share & Ratios
A1: Per-share & ratios
A2: Trailing and forward multiples on the model.
A4: Spot (USD) | B4: =Assumptions!B5 -> 420.6
A5: Shares (bn) | B5: =Assumptions!B6 -> 3.23
A6: Market cap (USD bn) | B6: =B4*B5 -> 1358.538
A7: Net cash (USD bn) | B7: =Assumptions!B7 -> 40
A8: Enterprise value (USD bn) | B8: =B6-B7 -> 1318.538
A10: On FY2025a
A11: EPS (USD) | B11: ='Income Statement'!D17 -> 1.1659443
A12: P/E (×) | B12: =B4/B11 -> 360.73765
A13: Revenue (USD bn) | B13: ='Income Statement'!D8 -> 94.8
A14: EV/Sales (×) | B14: =B8/B13 -> 13.908629
A16: On 2027e
A17: EPS (USD) | B17: ='Income Statement'!F17 -> 3.5
A18: Forward P/E (×) | B18: =B4/B17 -> 120.17143
A19: Revenue (USD bn) | B19: ='Income Statement'!F8 -> 130
A20: Forward EV/Sales (×) | B20: =B8/B19 -> 10.1426
A22: Valuation
A23: Weighted central (USD) | B23: ='Fundamental Valuation'!B9 -> 174.12029
A24: Implied P/E on central (2027e) | B24: =B23/B17 -> 49.748654
A26: At ~360× trailing earnings the multiple itself is a risk; a de-rating toward peer multiples is a large downside.

Sheet Peer & Sector
A1: Peer set, sector structure, and risks
A2: Competitive map and principal risks.
A4: Arena | B4: Leaders | C4: Tesla | D4: Note
A5: EV manufacturing | B5: BYD / Tesla / legacy OEMs | C5: co-leader | D5: BYD leads on volume/price
A6: Energy storage | B6: Tesla / CATL / Fluence | C6: top tier | D6: Megapack scaling fast
A7: Robotaxi / autonomy | B7: Waymo / Tesla | C7: challenger | D7: Waymo live in more cities
A8: Humanoid robotics | B8: Tesla / Figure / others | C8: early | D8: Optimus pre-revenue
A9: FSD / ADAS software | B9: Tesla / Mobileye | C9: leader (data) | D9: unproven at L4 scale
A10: Charging network | B10: Tesla (NACS) / others | C10: #1 | D10: opened to other OEMs
A12: Principal risks
A13: Autonomy optionality — the dominant factor; a stall removes support for most of the price.
A14: Auto-margin compression — Chinese competition and price/incentive pressure erode the operating core.
A15: Policy and rates — EV-credit removal, tariffs, an adverse FSD probe, or higher-for-longer rates.
A16: Valuation / multiple — at ~360× trailing earnings a de-rating is a large, operations-independent downside.
A17: Key-person / governance — dependence on the founder's vision and attention, two-sided.
A18: Competition in every arena — Waymo, BYD, and multiple humanoid/storage firms.
