Workbook

Sheet READ FIRST
A1: ADNOC Drilling Company P.J.S.C. — valuation model, 9 August 2026
B3: THIS WORKBOOK CALCULATES.
B4: Everything arithmetically derivable from a driver is a live formula. Change a blue cell on the Assumptions sheet and the workbook reprices: the cost of capital is built in the sheet from the risk-free rate net of the sovereign default spread, the equity beta and the equity risk premium; the cost of debt is built from the five-year Treasury yield and the company's own borrowing margin and then taxed; the weights come from net debt and market capitalisation; the discount factors compound; the waterfall chains EBITDA to EBIT to NOPAT to free cash flow to present value; the terminal block derives its reinvestment rate from growth over return on capital; the statements roll forward; and every ratio and per-share figure is a formula.
B6: THREE CLASSES OF CELL ARE PASTED, AND ONLY THREE.
B7: 1. Audited and disclosed history. The three years of income statement, balance sheet and cash flow come from the company's own signed consolidated financial statements. Where a line is both disclosed and derivable, the DISCLOSED figure is carried — the model does not overwrite an audited number with its own arithmetic.
B9: 2. The output of the unit build. The rig delivery schedule on the Assumptions sheet is a fleet plan, not arithmetic: it says how many rigs of each class are expected in service in each year. Everything downstream of it — average deployed rigs, revenue per class, the cost stack that serves them — is a formula.
B11: 3. Whole-model re-runs. The Monte Carlo sheet, the three grids on the Sensitivity sheet, and the Bear and Bull columns on the Summary and Fundamental Valuation sheets are pasted, because each cell in them is a complete revaluation at a different set of inputs. THESE CELLS DO NOT REDRAW WHEN A DRIVER CHANGES. Everything else does — including both discounted-cash-flow cases, which are each built live from their own fleet schedule, their own capital-expenditure plan and the same cost stack.
B13: One sheet is other companies' data.
B14: The Peer and Sector sheet carries thirteen other listed drillers and oilfield-service companies. Their prices, earnings and balance sheets are theirs, not ADNOC Drilling's, and are pasted as observations. The only formulas on that sheet are the enterprise values and multiples computed from them. Nothing on it enters ADNOC Drilling's own statements.
B16: BLUE MEANS INPUT, BLACK MEANS FORMULA.
B17: Every blue cell is on the Assumptions sheet, and every one of them carries its source and the construction behind it in the right-hand column.
B19: WHERE THE NUMBERS COME FROM.
B20: Every historical figure traces to ADNOC Drilling's own issued financial statements: the audited consolidated statements for 2023, 2024 and 2025 and the reviewed interim statements for the first quarter and first half of 2026, each downloaded from the company's investor-relations site. Operating units — rig counts, wells drilled, integrated-services rig counts, unconventional revenue — come from the company's own quarterly management discussion and analysis, which is the only published source that carries them. The Peer and Sector sheet is the one place third-party data appears; it is other companies' data, used for cross-check and for the relative lens, and none of it enters ADNOC Drilling's own statements.
... B26: This workbook contains no rating and no price target. It produces a fair-value range and a distribution of outcomes.

Sheet Summary
A1: Summary valuation table
B3: AED per share | C3: Weight | D3: Bear | E3: Bull | F3: Note
A4: Discounted cash flow — continued expansion | B4: ='Fundamental Valuation'!B4 | C4: ='Fundamental Valuation'!C4 | D4: ='Fundamental Valuation'!D4 | E4: ='Fundamental Valuation'!E4 | F4: =DCF!$C$54
A5: Discounted cash flow — capacity plateau | B5: ='Fundamental Valuation'!B5 | C5: ='Fundamental Valuation'!C5 | D5: ='Fundamental Valuation'!D5 | E5: ='Fundamental Valuation'!E5 | F5: =DCF!$C$76
A6: Relative multiples | B6: ='Fundamental Valuation'!B6 | C6: ='Fundamental Valuation'!C6 | D6: ='Fundamental Valuation'!D6 | E6: ='Fundamental Valuation'!E6
A7: Book value and sustainable return | B7: ='Fundamental Valuation'!B7 | C7: ='Fundamental Valuation'!C7 | D7: ='Fundamental Valuation'!D7 | E7: ='Fundamental Valuation'!E7
A8: Normalised earnings power | B8: ='Fundamental Valuation'!B8 | C8: ='Fundamental Valuation'!C8 | D8: ='Fundamental Valuation'!D8 | E8: ='Fundamental Valuation'!E8
A9: Weighted central fair value | B9: ='Fundamental Valuation'!B9 | D9: ='Fundamental Valuation'!D9 | E9: ='Fundamental Valuation'!E9
A10: Market price, 07-Aug-2026 | B10: =Assumptions!$C$5
A11: Central against the market price | B11: =B9/B10-1
A13: MEMO
A14: Terminal value as a share of enterprise value — continued expansion | B14: =DCF!$C$54
A15: Terminal value as a share of enterprise value — capacity plateau | B15: =DCF!$C$76
A16: Weighted average cost of capital — rating basis | B16: =DCF!$C$24
A17: Weighted average cost of capital — credit-default-swap basis | B17: =DCF!$C$25
A18: Market capitalisation (USD thousands) | B18: =DCF!$C$19
A19: Enterprise value at the market price (USD thousands) | B19: =DCF!$C$19+DCF!$C$20
A20: Enterprise value / FY2026 guided EBITDA at the market price | B20: ='Relative & Normalized'!C16
A21: Segment-weighted peer enterprise value / EBITDA | B21: ='Relative & Normalized'!C10

Sheet Fundamental Valuation
A1: Fundamental valuation — the five lenses and the weighted central
A3: Lens | B3: Value (AED/sh) | C3: Weight | D3: Bear | E3: Bull | F3: What the lens is measuring
A4: Discounted cash flow — continued expansion | B4: ='SOTP Bridge'!B19 | C4: =Assumptions!$C$258 | D4: 5.670418 | E4: 6.8716804 | F4: Free cash flow to the firm over five explicit years plus a terminal value, on a fleet plan that keeps building
A5: Discounted cash flow — capacity plateau | B5: ='SOTP Bridge'!C19 | C5: =Assumptions!$C$259 | D5: 4.9928756 | E5: 5.8815927 | F5: The same waterfall on a fleet that stops growing once the capacity target is met
A6: Relative multiples | B6: ='Relative & Normalized'!C15 | C6: =Assumptions!$C$260 | D6: 2.989651 | E6: 4.6374079 | F6: What the listed drilling and oilfield-services universe pays for a dollar of EBITDA, weighted to this company's own segment mix
A7: Book value and sustainable return | B7: ='Relative & Normalized'!C37 | C7: =Assumptions!$C$261 | D7: 4.3540915 | E7: 5.1657746 | F7: The multiple of book a franchise earning this return on equity justifies
A8: Normalised earnings power | B8: ='Relative & Normalized'!C28 | C8: =Assumptions!$C$262 | D8: 3.2330988 | E8: 3.6993926 | F8: What the fleet already installed earns at the guided margin, with no growth credited
A9: Weighted central | B9: =(B4*C4+B5*C5+B6*C6+B7*C7+B8*C8)/(C4+C5+C6+C7+C8) | C9: =C4+C5+C6+C7+C8 | D9: =(D4*C4+D5*C5+D6*C6+D7*C7+D8*C8)/(C4+C5+C6+C7+C8) | E9: =(E4*C4+E5*C5+E6*C6+E7*C7+E8*C8)/(C4+C5+C6+C7+C8)
A11: Market price | B11: =Assumptions!$C$5
A12: Central against the market price | B12: =B9/B11-1
A13: Terminal value as a share of enterprise value (continued expansion) | B13: =DCF!$C$54

Sheet Assumptions
A1: Assumptions — every blue cell is an input; change one and the workbook reprices
A3: Driver | B3: Unit | C3: Value | D3: Source and construction
A4: MARKET AND SHARE COUNT
A5: Market price | B5: AED/sh | C5: 5.8 | D5: Uploaded ADX daily price history for ADNOCDRILL, last close 03-Sep-2026 — the latest price supplied to this repository (SUPPLIED_03-09-2026.json). Superseded: AED 5.94 of 7 August 2026, on which every edition before this one was struck
A6: AED per USD | B6: AED/USD | C6: 3.6725 | D6: AED/USD central-bank peg, unchanged since 1997; the rate at which the company itself translates its AED-declared dividends into the USD amounts disclosed in Note 24 of the audited statements
A7: Shares issued | B7: '000 | C7: 16000000 | D7: Share capital note 13, FY2025 audited statements: 16,000,000 thousand shares of AED 0.10 each, unchanged since listing
A8: Treasury shares held by the market maker | B8: '000 | C8: 7349 | D8: Note 14, 1H-2026 interim: the appointed market maker held 7,349 thousand shares on the company's behalf at 30 June 2026, classified as treasury shares in equity (31 Dec 2025: 9,279 thousand)
A9: COST OF CAPITAL
A10: US 10-year Treasury yield (observed) | B10: % | C10: 0.0469 | D10: US 10-year constant-maturity Treasury yield, Federal Reserve H.15 via the St. Louis Fed (series DGS10), 06-Aug-2026 close
A11: US adjusted default spread | B11: % | C11: 0.0023 | D11: Adjusted default spread for the United States (Moody's Aa1), Damodaran country default spreads and risk premiums, original ctryprem file, last updated 5 January 2026
A12: Equity beta | B12: x | C12: 0.795 | D12: Own-stock 5-year weekly regression against the FTSE ADX General Index — the headline index of the exchange the stock actually trades on, held at engine/raw_indices/AE/ADXGENERAL.csv (3,884 sessions, 02-Jan-2011 to 24-Jul-2026, screened for blanks, duplicate dates, limit-exceeding single-session moves and trading-day density before use). n=247 weekly observations, R-squared 0.128, standard error 0.133, 90% interval 0.58 to 1.01. Clears the regression usability gate (n>=24, R-squared>=5%, standard error below the absolute beta), so the first tier of the beta hierarchy applies and no peer beta is needed. SUPERSEDES a prior 0.664 measured against an equal-weight composite of the 18-name UAE price library; that composite under-weights the large-capitalisation names the published index is concentrated in, and it is retained as a robustness check rather than as the regressor. The index series ends 24-Jul-2026 against a 07-Aug-2026 price anchor, a 14-day gap that costs the regression two of roughly 250 weekly observations. Source: engine/adnocdrill_study/beta_reg.py
A13: Equity risk premium — rating basis | B13: % | C13: 0.0487 | D13: Equity risk premium for the Emirate of Abu Dhabi on the rating basis (mature-market premium plus the Abu Dhabi country risk premium), Damodaran ctryprem file, 5 January 2026. The United Arab Emirates federal row carries the identical Aa2 / 0.42% / 0.64% / 4.87% set
A14: Equity risk premium — credit-default-swap basis | B14: % | C14: 0.0493 | D14: Equity risk premium for the Emirate of Abu Dhabi on the credit-default-swap basis, Damodaran ctryprem file, 5 January 2026
A15: US 5-year Treasury yield | B15: % | C15: 0.044 | D15: US 5-year constant-maturity Treasury yield, Federal Reserve H.15 via the St. Louis Fed (series DGS5), 06-Aug-2026 close
A16: Borrowing margin over Term SOFR on the latest facility | B16: % | C16: 0.0075 | D16: Borrowings note 15, FY2025 audited consolidated financial statements (Deloitte & Touche (M.E.), unqualified) — the Facility E and F term loan and revolving facility signed 16 October 2025, USD 2.0 billion committed, 5-year initial maturity, priced at Term SOFR plus 0.75%. This is the company's own latest and longest-dated debt issue and therefore its marginal borrowing margin
A17: Secured Overnight Financing Rate, spot | B17: % | C17: 0.0365 | D17: Secured Overnight Financing Rate, New York Fed via the St. Louis Fed (series SOFR), 06-Aug-2026
A18: Abu Dhabi sovereign credit-default-swap spread | B18: % | C18: 0.0046 | D18: Sovereign credit-default-swap spread for the Emirate of Abu Dhabi, Damodaran ctryprem file
A19: Corporate income tax rate | B19: % | C19: 0.09 | D19: Income tax note 30, FY2025 audited consolidated financial statements (Deloitte & Touche (M.E.), unqualified): 'The Group is subject to income tax at 9% on its taxable profits in accordance with the fiscal arrangement with Abu Dhabi Supreme Council for Financial and Economic Affairs effective 1 January 2024.' The same 9% is the UAE statutory corporate rate in the Damodaran country file
A20: FLEET PLAN — CONTINUED-EXPANSION CASE (a delivery schedule, not arithmetic)
A21: Abu Dhabi onshore rigs, year end — 2026 | B21: rigs | C21: 92 | D21: Abu Dhabi onshore fleet held at the FY2025 disclosed 92 rigs and grown two a year thereafter under the continued-expansion case
A22: Abu Dhabi onshore rigs, year end — 2027 | B22: rigs | C22: 94 | D22: Abu Dhabi onshore fleet held at the FY2025 disclosed 92 rigs and grown two a year thereafter under the continued-expansion case
A23: Abu Dhabi onshore rigs, year end — 2028 | B23: rigs | C23: 96 | D23: Abu Dhabi onshore fleet held at the FY2025 disclosed 92 rigs and grown two a year thereafter under the continued-expansion case
A24: Abu Dhabi onshore rigs, year end — 2029 | B24: rigs | C24: 98 | D24: Abu Dhabi onshore fleet held at the FY2025 disclosed 92 rigs and grown two a year thereafter under the continued-expansion case
A25: Abu Dhabi onshore rigs, year end — 2030 | B25: rigs | C25: 100 | D25: Abu Dhabi onshore fleet held at the FY2025 disclosed 92 rigs and grown two a year thereafter under the continued-expansion case
A26: Regional onshore rigs, year end — 2026 | B26: rigs | C26: 30 | D26: Opens at the 30 regional rigs disclosed at 30 June 2026 (8 from the SLDC joint venture with SLB, 22 from MBPS) and adds two a year
A27: Regional onshore rigs, year end — 2027 | B27: rigs | C27: 32 | D27: Opens at the 30 regional rigs disclosed at 30 June 2026 (8 from the SLDC joint venture with SLB, 22 from MBPS) and adds two a year
A28: Regional onshore rigs, year end — 2028 | B28: rigs | C28: 34 | D28: Opens at the 30 regional rigs disclosed at 30 June 2026 (8 from the SLDC joint venture with SLB, 22 from MBPS) and adds two a year
A29: Regional onshore rigs, year end — 2029 | B29: rigs | C29: 36 | D29: Opens at the 30 regional rigs disclosed at 30 June 2026 (8 from the SLDC joint venture with SLB, 22 from MBPS) and adds two a year
A30: Regional onshore rigs, year end — 2030 | B30: rigs | C30: 38 | D30: Opens at the 30 regional rigs disclosed at 30 June 2026 (8 from the SLDC joint venture with SLB, 22 from MBPS) and adds two a year
A31: Jack-up rigs, year end — 2026 | B31: rigs | C31: 36 | D31: Held flat at the FY2025 disclosed 36; no jack-ups are on order
A32: Jack-up rigs, year end — 2027 | B32: rigs | C32: 36 | D32: Held flat at the FY2025 disclosed 36; no jack-ups are on order
... A50: Rigs given at least one discrete service, year end — 2030 | B50: rigs | C50: 64 | D50: The second rig population Oilfield Services serves and the company discloses separately: 48 at end-2024, 58 at end-2025, 53 at 30 June 2026. Held broadly flat, because it has not grown as the integrated fleet has
A51: FLEET PLAN — CAPACITY-PLATEAU CASE (a delivery schedule, not arithmetic)
A52: Abu Dhabi onshore rigs, year end (plateau) — 2026 | B52: rigs | C52: 92 | D52: Held flat at the FY2025 disclosed 92 rigs: the domestic fleet stops growing once the production-capacity target is met
A53: Abu Dhabi onshore rigs, year end (plateau) — 2027 | B53: rigs | C53: 92 | D53: Held flat at the FY2025 disclosed 92 rigs: the domestic fleet stops growing once the production-capacity target is met
A54: Abu Dhabi onshore rigs, year end (plateau) — 2028 | B54: rigs | C54: 92 | D54: Held flat at the FY2025 disclosed 92 rigs: the domestic fleet stops growing once the production-capacity target is met
A55: Abu Dhabi onshore rigs, year end (plateau) — 2029 | B55: rigs | C55: 92 | D55: Held flat at the FY2025 disclosed 92 rigs: the domestic fleet stops growing once the production-capacity target is met
A56: Abu Dhabi onshore rigs, year end (plateau) — 2030 | B56: rigs | C56: 92 | D56: Held flat at the FY2025 disclosed 92 rigs: the domestic fleet stops growing once the production-capacity target is met
A57: Regional onshore rigs, year end (plateau) — 2026 | B57: rigs | C57: 30 | D57: Held flat at the 30 regional rigs disclosed at 30 June 2026
A58: Regional onshore rigs, year end (plateau) — 2027 | B58: rigs | C58: 30 | D58: Held flat at the 30 regional rigs disclosed at 30 June 2026
A59: Regional onshore rigs, year end (plateau) — 2028 | B59: rigs | C59: 30 | D59: Held flat at the 30 regional rigs disclosed at 30 June 2026
A60: Regional onshore rigs, year end (plateau) — 2029 | B60: rigs | C60: 30 | D60: Held flat at the 30 regional rigs disclosed at 30 June 2026
A61: Regional onshore rigs, year end (plateau) — 2030 | B61: rigs | C61: 30 | D61: Held flat at the 30 regional rigs disclosed at 30 June 2026
A62: Jack-up rigs, year end (plateau) — 2026 | B62: rigs | C62: 36 | D62: Held flat at the FY2025 disclosed 36
A63: Jack-up rigs, year end (plateau) — 2027 | B63: rigs | C63: 36 | D63: Held flat at the FY2025 disclosed 36
... A81: Rigs given at least one discrete service, year end (plateau) — 2030 | B81: rigs | C81: 56 | D81: Held flat at the disclosed count on the same reasoning as the expansion case: this population is not growing
A82: DISCLOSED BASE FOR THE UNIT RATES (reported figures, nothing derived)
A83: Onshore segment revenue — FY2025 | B83: USD '000 | C83: 2037025 | D83: Segment note 28, FY2025 audited consolidated financial statements (Deloitte & Touche (M.E.), unqualified) — Onshore
A84: Offshore segment revenue — FY2025 | B84: USD '000 | C84: 1403893 | D84: Segment note 28, FY2025 audited consolidated financial statements (Deloitte & Touche (M.E.), unqualified) — Offshore
A85: Oilfield Services segment revenue — FY2024 | B85: USD '000 | C85: 813116 | D85: Segment note 28, FY2025 audited consolidated financial statements (Deloitte & Touche (M.E.), unqualified) comparative column — Oilfield Services
A86: Oilfield Services segment revenue — FY2025 | B86: USD '000 | C86: 1461968 | D86: Segment note 28, FY2025 audited consolidated financial statements (Deloitte & Touche (M.E.), unqualified) — Oilfield Services
A87: Offshore Island revenue — FY2023 | B87: USD '000 | C87: 209079 | D87: FY2023 audited consolidated financial statements (KPMG Lower Gulf Limited, unqualified) segment note — Offshore Island revenue for FY2023, the last year the island and jack-up businesses were reported as separate segments; from 1Q-2025 they are presented as one Offshore segment
A88: Offshore Jack-up revenue — FY2023 | B88: USD '000 | C88: 799726 | D88: FY2023 audited consolidated financial statements (KPMG Lower Gulf Limited, unqualified) segment note — Offshore Jack-up revenue for FY2023
A89: Unconventional revenue — FY2025 | B89: USD '000 | C89: 692000 | D89: FY2025 management discussion and analysis: unconventional revenue of $692 million in full year 2025, split $534 million in Oilfield Services and $158 million in Onshore land drilling
A90: Unconventional booked to Oilfield Services — FY2024 | B90: USD '000 | C90: 95000 | D90: FY2025 management discussion and analysis Oilfield Services commentary, prior-year comparative — the unconventional contribution inside Oilfield Services was $95 million in 2024
A91: Unconventional booked to Oilfield Services — FY2025 | B91: USD '000 | C91: 534000 | D91: FY2025 management discussion and analysis Oilfield Services commentary — unconventional contribution rose from $95 million in 2024 to $534 million in 2025
A92: Abu Dhabi onshore rigs — FY2024 year end | B92: rigs | C92: 95 | D92: FY2024 MD&A operational highlights — onshore rigs at year end
A93: Abu Dhabi onshore rigs — FY2025 year end | B93: rigs | C93: 92 | D93: FY2025 management discussion and analysis operational highlights — Abu Dhabi onshore rigs at year end
A94: Jack-up rigs — FY2022 year end | B94: rigs | C94: 31 | D94: FY2023 MD&A, FY22 comparative — offshore jack-up rigs
... A108: Rigs given at least one discrete service — 30 June 2026 | B108: rigs | C108: 53 | D108: 1H-2026 management discussion and analysis: 'at least one discrete service was delivered across an additional 53 rigs... resulting in OFS coverage across a total of 114 rigs'
A109: UNIT REVENUE RATES (every one derived from the block above)
A110: Revenue per Abu Dhabi onshore rig-year | B110: USD '000 | C110: =(Assumptions!$C$83-(Assumptions!$C$89-Assumptions!$C$91))/((Assumptions!$C$92+Assumptions!$C$93)/2) | D110: FY2025 reported Onshore segment revenue less the unconventional land-drilling revenue inside it, over the average of the FY2024 and FY2025 reported rig counts
A111: Revenue per regional onshore rig-year | B111: USD '000 | C111: 8000 | D111: Revenue per regional land rig-year, USD thousands. Derived, not assumed: 1H-2026 Onshore revenue of $1,031 million less roughly $35 million of unconventional land drilling leaves $996 million; the Abu Dhabi conventional fleet at its disclosed FY2025 realised rate accounts for approximately $920 million of that, leaving about $76 million earned across an average of roughly 19 regional rigs in the half (8 SLDC rigs from January, 22 MBPS rigs part-period). That is about $8.0 million per rig-year, roughly 40% of the Abu Dhabi rate, consistent with smaller land rigs on Oman and Kuwait terms
A112: Island-to-jack-up revenue ratio | B112: x | C112: =(Assumptions!$C$87/Assumptions!$C$98)/(Assumptions!$C$88/((Assumptions!$C$94+Assumptions!$C$95)/2)) | D112: FY2023 is the last year the island and jack-up businesses were reported separately, so it is the only year that can fix the ratio between them. Revenue per island rig-year over revenue per jack-up rig-year, both on that year
A113: Revenue per jack-up rig-year | B113: USD '000 | C113: =Assumptions!$C$84/(((Assumptions!$C$96+Assumptions!$C$97)/2)+Assumptions!$C$112*((Assumptions!$C$99+Assumptions!$C$100)/2)) | D113: FY2025 reported Offshore segment revenue divided across jack-up-equivalent rig-years, island rigs counted at the ratio above
A114: Revenue per island rig-year | B114: USD '000 | C114: =Assumptions!$C$113*Assumptions!$C$112 | D114: The jack-up rate at the FY2023 island-to-jack-up ratio
A115: Rigs served by Oilfield Services — FY2024 | B115: rigs | C115: =Assumptions!$C$101+Assumptions!$C$103 | D115: Oilfield Services serves TWO rig populations, and the company discloses both: the integrated-services fleet and, separately, the rigs given at least one discrete service. The first edition of this model recognised only the first
A116: Rigs served by Oilfield Services — FY2025 | B116: rigs | C116: =Assumptions!$C$102+Assumptions!$C$104 | D116: The same two populations a year later
A117: Revenue per rig served — FY2024 | B117: USD '000 | C117: =(Assumptions!$C$85-Assumptions!$C$90)/Assumptions!$C$115 | D117: FY2024 reported Oilfield Services revenue less the unconventional revenue inside it, over the rigs served
A118: Revenue per rig served — FY2025 | B118: USD '000 | C118: =(Assumptions!$C$86-Assumptions!$C$91)/Assumptions!$C$116 | D118: The same construction a year later
A119: Realised growth in revenue per rig served | B119: % | C119: =Assumptions!$C$118/Assumptions!$C$117-1 | D119: Measured, not assumed: what the company actually achieved between the two disclosed years. It fades to the contract escalator across the forecast, because a gain of this size in revenue per rig served is a mix and efficiency effect that cannot compound indefinitely
A120: ESCALATORS — ONE PER DRIVER CLASS
A121: Contract day-rate escalation | B121: % | C121: 0.015 | D121: Contract day-rate escalator applied to the conventional revenue-per-rig price line. The customer is a single national oil company on multi-year contracts, so realised day rates track a negotiated escalation rather than a spot market. Realised Abu Dhabi onshore revenue per average deployed rig moved from $18.9 million in FY2023 to $20.9 million in FY2024 to $20.1 million in FY2025 (this model's own unit arithmetic on disclosed segment revenue and disclosed rig counts) — a three-year path that is up but not monotone. 1.5% is set at domestic inflation rather than extrapolating the FY2024 step
A122: Wage escalation (domestic labour only) | B122: % | C122: 0.02 | D122: Staff-cost escalator. United Arab Emirates consumer price inflation ran 1.63% in 2023, 1.66% in 2024 and 1.25% in 2025 (World Bank via the St. Louis Fed, series FPCPITOTLZGARE); 2.0% carries a modest real-wage drift above that for a business competing for skilled rig crews in a tight regional labour market. Applies ONLY to the domestic labour line
A123: Oilfield-services cost escalation | B123: % | C123: 0.015 | D123: Oilfield-services cost escalator, applied to repairs and maintenance, major maintenance and hire of equipment. US producer price index for drilling oil and gas wells (series PCU213111213111) stood at 396.978 in June 2026, down 1.63% year on year with a three-year compound rate of +0.29%. 1.5% sits above the flat recent print and below general inflation, on the view that the recent softness reflects the US land downturn rather than the Gulf market these costs are actually incurred in — the gap is flagged rather than smoothed away
A124: Fuel escalation (own commodity path) | B124: % | C124: 0 | D124: Fuel and lubricants escalator. This is a globally traded input and is escalated on its own commodity path, NOT on a domestic inflation proxy: Brent closed at $88.90 on 03-Aug-2026 against a one-year average of $79.69 and a three-year average of $79.48 (US Energy Information Administration via the St. Louis Fed, series DCOILBRENTEU). Spot sits roughly 12% above the three-year mean, so a flat nominal path embeds mean reversion in real terms. The company's onshore contracts carry an explicit fuel-escalation pass-through — the 1H-2026 MD&A attributes part of the onshore revenue increase to 'higher fuel escalation' — so this line is close to margin-neutral either way
A125: General escalation | B125: % | C125: 0.015 | D125: Escalator for other direct cost and for general and administrative expenses, anchored on United Arab Emirates consumer price inflation (1.25% in 2025, 1.66% in 2024) rounded to 1.5%
A126: Unconventional EBITDA margin | B126: % | C126: 0.065 | D126: EBITDA margin on unconventional revenue, triangulated three ways in the workbook rather than asserted: (i) the FY2025 disclosed conventional EBITDA margin of 51% applied to conventional revenue implies $50 million of EBITDA on $692 million of unconventional revenue, a 7.3% margin; (ii) the same arithmetic on FY2024's disclosed 52% implies a negative margin, but on a $117 million revenue base a half-point of rounding in the disclosed margin swings the answer by more than the answer itself, so it is reported and discarded; (iii) the FY2024-to-FY2025 incremental bridge — group EBITDA up $183 million on revenue up $869 million, of which $294 million of conventional revenue at 51% explains $150 million — leaves $33 million on $575 million of incremental unconventional revenue, a 5.8% margin. The average of the two usable estimates is 6.5%. This is the single most consequential fact about the unconventional programme: it is a large revenue line that carries almost no profit
A127: FY2025 DIRECT COST — AS REPORTED IN THE COST NOTE
A128: Repairs and maintenance — as reported | B128: USD '000 | C128: 904937 | D128: Direct cost note 20, FY2025 audited consolidated financial statements (Deloitte & Touche (M.E.), unqualified) — repairs and maintenance
A129: Staff costs — as reported | B129: USD '000 | C129: 802536 | D129: Direct cost note 20, FY2025 audited consolidated financial statements (Deloitte & Touche (M.E.), unqualified) — staff costs
A130: Hire of equipment — as reported | B130: USD '000 | C130: 303652 | D130: Direct cost note 20, FY2025 audited consolidated financial statements (Deloitte & Touche (M.E.), unqualified) — hire of equipment
A131: Chemicals — as reported | B131: USD '000 | C131: 254535 | D131: Direct cost note 20, FY2025 audited consolidated financial statements (Deloitte & Touche (M.E.), unqualified) — chemicals
A132: Fuel and lubricants — as reported | B132: USD '000 | C132: 170776 | D132: Direct cost note 20, FY2025 audited consolidated financial statements (Deloitte & Touche (M.E.), unqualified) — fuel and lubricants
A133: Major maintenance charges — as reported | B133: USD '000 | C133: 53151 | D133: Direct cost note 20, FY2025 audited consolidated financial statements (Deloitte & Touche (M.E.), unqualified) — major maintenance charges
A134: Other direct cost — as reported | B134: USD '000 | C134: 123312 | D134: Direct cost note 20, FY2025 audited consolidated financial statements (Deloitte & Touche (M.E.), unqualified) — other direct cost
A135: General and administrative expenses — as reported | B135: USD '000 | C135: 167197 | D135: General and administrative expenses, FY2025 audited consolidated financial statements (Deloitte & Touche (M.E.), unqualified)
A136: Depreciation inside general and administrative expenses | B136: USD '000 | C136: 19255 | D136: Segment note 28, FY2025 audited consolidated financial statements (Deloitte & Touche (M.E.), unqualified) — depreciation and amortisation included in general and administrative expenses. Ties to note 21: property and equipment 4,020 plus right-of-use 11,042 plus intangibles 4,193
A137: Direct cost carried by the unconventional programme | B137: USD '000 | C137: =Assumptions!$C$89*(1-Assumptions!$C$126) | D137: FY2025 unconventional revenue at one minus the unconventional EBITDA margin — the cash cost the unconventional programme carried, which has to come out of the reported direct cost before the remainder can be escalated on conventional volume drivers
A138: FY2025 CONVENTIONAL COST STACK (reported cost less the unconventional share)
A139: Repairs and maintenance — conventional base | B139: USD '000 | C139: =Assumptions!$C$128*(1-Assumptions!$C$137/SUM(Assumptions!$C$128:$C$134)) | D139: The reported line less its pro-rata share of the direct cost the unconventional programme carried
A140: Staff costs — conventional base | B140: USD '000 | C140: =Assumptions!$C$129*(1-Assumptions!$C$137/SUM(Assumptions!$C$128:$C$134)) | D140: The reported line less its pro-rata share of the direct cost the unconventional programme carried
A141: Hire of equipment — conventional base | B141: USD '000 | C141: =Assumptions!$C$130*(1-Assumptions!$C$137/SUM(Assumptions!$C$128:$C$134)) | D141: The reported line less its pro-rata share of the direct cost the unconventional programme carried
A142: Chemicals — conventional base | B142: USD '000 | C142: =Assumptions!$C$131*(1-Assumptions!$C$137/SUM(Assumptions!$C$128:$C$134)) | D142: The reported line less its pro-rata share of the direct cost the unconventional programme carried
A143: Fuel and lubricants — conventional base | B143: USD '000 | C143: =Assumptions!$C$132*(1-Assumptions!$C$137/SUM(Assumptions!$C$128:$C$134)) | D143: The reported line less its pro-rata share of the direct cost the unconventional programme carried
A144: Major maintenance charges — conventional base | B144: USD '000 | C144: =Assumptions!$C$133*(1-Assumptions!$C$137/SUM(Assumptions!$C$128:$C$134)) | D144: The reported line less its pro-rata share of the direct cost the unconventional programme carried
A145: Other direct cost — conventional base | B145: USD '000 | C145: =Assumptions!$C$134*(1-Assumptions!$C$137/SUM(Assumptions!$C$128:$C$134)) | D145: The reported line less its pro-rata share of the direct cost the unconventional programme carried
A146: General and administrative expenses excluding depreciation | B146: USD '000 | C146: =Assumptions!$C$135-Assumptions!$C$136 | D146: FY2025 reported general and administrative expenses less the depreciation and amortisation inside them, which is charged separately in the model
A147: Other income, FY2025 base | B147: USD '000 | C147: 26991 | D147: Other income - net, FY2025 audited consolidated financial statements (Deloitte & Touche (M.E.), unqualified)
A148: Share of joint-venture results, FY2025 base | B148: USD '000 | C148: 29000 | D148: Share of results of joint ventures, FY2025 audited consolidated financial statements (Deloitte & Touche (M.E.), unqualified)
...

Sheet SOTP Bridge
A1: Enterprise value to equity — the bridge, struck on the 30 June 2026 capital structure
B3: Continued expansion | C3: Capacity plateau | D3: Note
A4: Enterprise value at 31 December 2025 | B4: =DCF!$C$53 | C4: =DCF!$C$75 | D4: Present value of the explicit five years plus the discounted terminal value. Discounting FY2026 cash flow by a full year places the answer at the START of FY2026, which is 31 December 2025 — six months before the balance sheet the deductions below come from
A5: of which terminal value | B5: =DCF!$C$54 | C5: =DCF!$C$76 | D5: The share of the answer that rests on the period beyond 2030 — read this before the valuation
A6: carried forward half a year at the cost of capital | B6: =B4*((1+DCF!$C$24)^0.5-1) | C6: =C4*((1+DCF!$C$24)^0.5-1) | D6: An enterprise compounds at its own cost of capital. Closing the six-month gap rather than ignoring it is what puts both sides of this bridge on one date
A7: less the free cash flow the business actually generated over that half year | B7: =-(Assumptions!$C$234-Assumptions!$C$235)*(1+DCF!$C$24)^0.25 | C7: =-(Assumptions!$C$234-Assumptions!$C$235)*(1+DCF!$C$24)^0.25 | D7: Reported, not forecast. Cash the enterprise has already handed out is no longer inside it. Acquisition consideration is deliberately NOT deducted here: it bought assets that sit inside the same enterprise, so it nets out of an enterprise-value roll-forward
A8: Enterprise value at 30 June 2026 | B8: =B4+B6+B7 | C8: =C4+C6+C7 | D8: Now on the same date as every line beneath it
A9: add investment in joint ventures | B9: =Assumptions!$C$228 | C9: =Assumptions!$C$228 | D9: Enersol and Turnwell at carrying value; their earnings are excluded from the discounted EBITDA, so the stake is added here instead
A10: add cash and cash equivalents | B10: =Assumptions!$C$229 | C10: =Assumptions!$C$229 | D10: Balance sheet at 30 June 2026
A11: less borrowings | B11: =-Assumptions!$C$230 | C11: =-Assumptions!$C$230 | D11: Current and non-current term loans
A12: less lease liabilities | B12: =-Assumptions!$C$231 | C12: =-Assumptions!$C$231
A13: less the financial liability over the acquired minorities | B13: =-Assumptions!$C$232 | C13: =-Assumptions!$C$232 | D13: The present value of the price at which the parent may be required to buy the 30% of SLDC and the 20% of MBPS it does not own. The minority interests reported at 30 June 2026 are NOT deducted as well: that is the same claim under another name, and the company has already charged a matching investment reserve against owners equity for it
A14: Equity value at 30 June 2026 | B14: =B8+SUM(B9:B13) | C14: =C8+SUM(C9:C13)
A15: accreted to the price anchor at the cost of equity | B15: =B14*((1+DCF!$C$9)^(Assumptions!$C$236/365)-1) | C15: =C14*((1+DCF!$C$9)^(Assumptions!$C$236/365)-1) | D15: The remaining 38 days from the balance-sheet date to the share price this value is compared against
A16: Equity value at the price anchor | B16: =B14+B15 | C16: =C14+C15
A17: Shares outstanding (thousands) | B17: =Assumptions!$C$7-Assumptions!$C$8 | C17: =Assumptions!$C$7-Assumptions!$C$8 | D17: Issued shares less the shares the appointed market maker holds on the company's behalf
A18: Value per share (USD) | B18: =B16/B17 | C18: =C16/C17
A19: Value per share (AED) | B19: =B18*Assumptions!$C$6 | C19: =C18*Assumptions!$C$6 | D19: Converted at the peg

Sheet Segments
A1: Segments — the unit build: rigs times revenue per rig, and the cost stack that serves them
A3: USD thousands unless stated | B3: FY2023 | C3: FY2024 | D3: FY2025 | E3: FY2026E | F3: FY2027E | G3: FY2028E | H3: FY2029E | I3: FY2030E
A4: OPERATING UNITS (average deployed over the year)
A5: Average Abu Dhabi onshore rigs | B5: 79 | C5: 89.5 | D5: 93.5 | E5: =(Assumptions!$C$93+Assumptions!$C$21)/2 | F5: =(Assumptions!$C$21+Assumptions!$C$22)/2 | G5: =(Assumptions!$C$22+Assumptions!$C$23)/2 | H5: =(Assumptions!$C$23+Assumptions!$C$24)/2 | I5: =(Assumptions!$C$24+Assumptions!$C$25)/2
A6: Average regional onshore rigs | B6: 0 | C6: 0 | D6: 0 | E6: =(Assumptions!$C$105+Assumptions!$C$26)/2 | F6: =(Assumptions!$C$26+Assumptions!$C$27)/2 | G6: =(Assumptions!$C$27+Assumptions!$C$28)/2 | H6: =(Assumptions!$C$28+Assumptions!$C$29)/2 | I6: =(Assumptions!$C$29+Assumptions!$C$30)/2
A7: Average jack-up rigs | B7: 33 | C7: 36 | D7: 36.5 | E7: =(Assumptions!$C$97+Assumptions!$C$31)/2 | F7: =(Assumptions!$C$31+Assumptions!$C$32)/2 | G7: =(Assumptions!$C$32+Assumptions!$C$33)/2 | H7: =(Assumptions!$C$33+Assumptions!$C$34)/2 | I7: =(Assumptions!$C$34+Assumptions!$C$35)/2
A8: Average island rigs | B8: 10 | C8: 10 | D8: 11 | E8: =(Assumptions!$C$100+Assumptions!$C$36)/2 | F8: =(Assumptions!$C$36+Assumptions!$C$37)/2 | G8: =(Assumptions!$C$37+Assumptions!$C$38)/2 | H8: =(Assumptions!$C$38+Assumptions!$C$39)/2 | I8: =(Assumptions!$C$39+Assumptions!$C$40)/2
A9: Average integrated-services rigs | B9: 44 | C9: 52.5 | D9: 58.5 | E9: =(Assumptions!$C$102+Assumptions!$C$41)/2 | F9: =(Assumptions!$C$41+Assumptions!$C$42)/2 | G9: =(Assumptions!$C$42+Assumptions!$C$43)/2 | H9: =(Assumptions!$C$43+Assumptions!$C$44)/2 | I9: =(Assumptions!$C$44+Assumptions!$C$45)/2
A10: Average rigs given at least one discrete service | C10: 48 | D10: 58 | E10: =(Assumptions!$C$104+Assumptions!$C$46)/2 | F10: =(Assumptions!$C$46+Assumptions!$C$47)/2 | G10: =(Assumptions!$C$47+Assumptions!$C$48)/2 | H10: =(Assumptions!$C$48+Assumptions!$C$49)/2 | I10: =(Assumptions!$C$49+Assumptions!$C$50)/2
A11: Day-rate escalation index (2025 = 1.00) | B11: 1 | C11: 1 | D11: 1 | E11: =(1+Assumptions!$C$121)^1 | F11: =(1+Assumptions!$C$121)^2 | G11: =(1+Assumptions!$C$121)^3 | H11: =(1+Assumptions!$C$121)^4 | I11: =(1+Assumptions!$C$121)^5
A13: Rigs served by Oilfield Services (integrated plus discrete) | B13: 44 | C13: 52.5 | D13: 58.5 | E13: =E9+E10 | F13: =F9+F10 | G13: =G9+G10 | H13: =H9+H10 | I13: =I9+I10
A14: Oilfield-services revenue-per-rig-served index (2025 = 1.00) | E14: =1*(1+(Assumptions!$C$119*1.000000+Assumptions!$C$121*0.000000)) | F14: =E14*(1+(Assumptions!$C$119*0.750000+Assumptions!$C$121*0.250000)) | G14: =F14*(1+(Assumptions!$C$119*0.500000+Assumptions!$C$121*0.500000)) | H14: =G14*(1+(Assumptions!$C$119*0.250000+Assumptions!$C$121*0.750000)) | I14: =H14*(1+(Assumptions!$C$119*0.000000+Assumptions!$C$121*1.000000))
A16: REVENUE BY UNIT — BEFORE RECONCILIATION TO FY2026 GUIDANCE
A17: Onshore conventional — Abu Dhabi | E17: =E5*Assumptions!$C$110*E11 | F17: =F5*Assumptions!$C$110*F11 | G17: =G5*Assumptions!$C$110*G11 | H17: =H5*Assumptions!$C$110*H11 | I17: =I5*Assumptions!$C$110*I11
A18: Onshore conventional — regional | E18: =E6*Assumptions!$C$111*E11 | F18: =F6*Assumptions!$C$111*F11 | G18: =G6*Assumptions!$C$111*G11 | H18: =H6*Assumptions!$C$111*H11 | I18: =I6*Assumptions!$C$111*I11
A19: Offshore — jack-up | E19: =E7*Assumptions!$C$113*E11 | F19: =F7*Assumptions!$C$113*F11 | G19: =G7*Assumptions!$C$113*G11 | H19: =H7*Assumptions!$C$113*H11 | I19: =I7*Assumptions!$C$113*I11
A20: Offshore — island | E20: =E8*Assumptions!$C$114*E11 | F20: =F8*Assumptions!$C$114*F11 | G20: =G8*Assumptions!$C$114*G11 | H20: =H8*Assumptions!$C$114*H11 | I20: =I8*Assumptions!$C$114*I11
A21: Oilfield Services — rigs served | E21: =E13*Assumptions!$C$118*E14 | F21: =F13*Assumptions!$C$118*F14 | G21: =G13*Assumptions!$C$118*G14 | H21: =H13*Assumptions!$C$118*H14 | I21: =I13*Assumptions!$C$118*I14
A23: RECONCILIATION TO THE FY2026 SEGMENT GUIDANCE
A24: Onshore — factor on the conventional unit build | E24: =(Assumptions!$C$187-E28)/(E17+E18)
A25: Offshore — factor on the conventional unit build | E25: =Assumptions!$C$188/(E19+E20)
A26: Oilfield Services — factor on the conventional unit build | E26: =(Assumptions!$C$189-E29)/E21
A28: Unconventional — Onshore land drilling | B28: 0 | C28: 22000 | D28: 158000 | E28: =Assumptions!$C$150*Assumptions!$C$160 | F28: =Assumptions!$C$151*Assumptions!$C$160 | G28: =Assumptions!$C$152*Assumptions!$C$160 | H28: =Assumptions!$C$153*Assumptions!$C$160 | I28: =Assumptions!$C$154*Assumptions!$C$160
A29: Unconventional — Oilfield Services | B29: 0 | C29: 95000 | D29: 534000 | E29: =Assumptions!$C$150*(1-Assumptions!$C$160) | F29: =Assumptions!$C$151*(1-Assumptions!$C$160) | G29: =Assumptions!$C$152*(1-Assumptions!$C$160) | H29: =Assumptions!$C$153*(1-Assumptions!$C$160) | I29: =Assumptions!$C$154*(1-Assumptions!$C$160)
A31: REVENUE BY REPORTED SEGMENT
A32: Onshore conventional — Abu Dhabi (reconciled) | E32: =E17*$E$24 | F32: =F17*$E$24 | G32: =G17*$E$24 | H32: =H17*$E$24 | I32: =I17*$E$24
A33: Onshore conventional — regional (reconciled) | E33: =E18*$E$24 | F33: =F18*$E$24 | G33: =G18*$E$24 | H33: =H18*$E$24 | I33: =I18*$E$24
A34: Offshore — jack-up (reconciled) | E34: =E19*$E$25 | F34: =F19*$E$25 | G34: =G19*$E$25 | H34: =H19*$E$25 | I34: =I19*$E$25
A35: Offshore — island (reconciled) | E35: =E20*$E$25 | F35: =F20*$E$25 | G35: =G20*$E$25 | H35: =H20*$E$25 | I35: =I20*$E$25
A36: Oilfield Services — rigs served (reconciled) | E36: =E21*$E$26 | F36: =F21*$E$26 | G36: =G21*$E$26 | H36: =H21*$E$26 | I36: =I21*$E$26
A38: Onshore | B38: 1495057 | C38: 1892670 | D38: 2037025 | E38: =E32+E33+E28 | F38: =F32+F33+F28 | G38: =G32+G33+G28 | H38: =H32+H33+H28 | I38: =I32+I33+I28
A39: Offshore | B39: 1008805 | C39: 1328436 | D39: 1403893 | E39: =E34+E35 | F39: =F34+F35 | G39: =G34+G35 | H39: =H34+H35 | I39: =I34+I35
A40: Oilfield Services | B40: 553003 | C40: 813116 | D40: 1461968 | E40: =E36+E29 | F40: =F36+F29 | G40: =G36+G29 | H40: =H36+H29 | I40: =I36+I29
A41: Total revenue | B41: =B38+B39+B40 | C41: =C38+C39+C40 | D41: =D38+D39+D40 | E41: =E38+E39+E40 | F41: =F38+F39+F40 | G41: =G38+G39+G40 | H41: =H38+H39+H40 | I41: =I38+I39+I40
A42: of which conventional | B42: =B41-B28-B29 | C42: =C41-C28-C29 | D42: =D41-D28-D29 | E42: =E41-E28-E29 | F42: =F41-F28-F29 | G42: =G41-G28-G29 | H42: =H41-H28-H29 | I42: =I41-I28-I29
A44: COST STACK — EACH LINE ON ITS OWN VOLUME DRIVER AND ITS OWN ESCALATOR
A45: Total rig-years (all classes, including integrated services) | B45: 166 | C45: 188 | D45: 199.5 | E45: =E5+E6+E7+E8+E9 | F45: =F5+F6+F7+F8+F9 | G45: =G5+G6+G7+G8+G9 | H45: =H5+H6+H7+H8+H9 | I45: =I5+I6+I7+I8+I9
A46: Offshore rig-years | B46: 43 | C46: 46 | D46: 47.5 | E46: =E7+E8 | F46: =F7+F8 | G46: =G7+G8 | H46: =H7+H8 | I46: =I7+I8
A47: Wells drilled (drilling rig-years scaled off the FY2025 disclosed 836) | B47: 613 | C47: 676 | D47: 836 | E47: =836.0*(E5+E6+E7+E8)/141.0 | F47: =836.0*(F5+F6+F7+F8)/141.0 | G47: =836.0*(G5+G6+G7+G8)/141.0 | H47: =836.0*(H5+H6+H7+H8)/141.0 | I47: =836.0*(I5+I6+I7+I8)/141.0
A48: Repairs and maintenance (rig years) | E48: =Assumptions!$C$139*E45/199.5*(1+Assumptions!$C$123)^1 | F48: =Assumptions!$C$139*F45/199.5*(1+Assumptions!$C$123)^2 | G48: =Assumptions!$C$139*G45/199.5*(1+Assumptions!$C$123)^3 | H48: =Assumptions!$C$139*H45/199.5*(1+Assumptions!$C$123)^4 | I48: =Assumptions!$C$139*I45/199.5*(1+Assumptions!$C$123)^5
A49: Staff costs (rig years) | E49: =Assumptions!$C$140*E45/199.5*(1+Assumptions!$C$122)^1 | F49: =Assumptions!$C$140*F45/199.5*(1+Assumptions!$C$122)^2 | G49: =Assumptions!$C$140*G45/199.5*(1+Assumptions!$C$122)^3 | H49: =Assumptions!$C$140*H45/199.5*(1+Assumptions!$C$122)^4 | I49: =Assumptions!$C$140*I45/199.5*(1+Assumptions!$C$122)^5
A50: Hire of equipment (conv revenue) | E50: =Assumptions!$C$141*E42/4210886.0*(1+Assumptions!$C$123)^1 | F50: =Assumptions!$C$141*F42/4210886.0*(1+Assumptions!$C$123)^2 | G50: =Assumptions!$C$141*G42/4210886.0*(1+Assumptions!$C$123)^3 | H50: =Assumptions!$C$141*H42/4210886.0*(1+Assumptions!$C$123)^4 | I50: =Assumptions!$C$141*I42/4210886.0*(1+Assumptions!$C$123)^5
A51: Chemicals (wells) | E51: =Assumptions!$C$142*E47/836.0*(1+Assumptions!$C$123)^1 | F51: =Assumptions!$C$142*F47/836.0*(1+Assumptions!$C$123)^2 | G51: =Assumptions!$C$142*G47/836.0*(1+Assumptions!$C$123)^3 | H51: =Assumptions!$C$142*H47/836.0*(1+Assumptions!$C$123)^4 | I51: =Assumptions!$C$142*I47/836.0*(1+Assumptions!$C$123)^5
A52: Fuel and lubricants (rig years) | E52: =Assumptions!$C$143*E45/199.5*(1+Assumptions!$C$124)^1 | F52: =Assumptions!$C$143*F45/199.5*(1+Assumptions!$C$124)^2 | G52: =Assumptions!$C$143*G45/199.5*(1+Assumptions!$C$124)^3 | H52: =Assumptions!$C$143*H45/199.5*(1+Assumptions!$C$124)^4 | I52: =Assumptions!$C$143*I45/199.5*(1+Assumptions!$C$124)^5
A53: Major maintenance charges (offshore rig years) | E53: =Assumptions!$C$144*E46/47.5*(1+Assumptions!$C$123)^1 | F53: =Assumptions!$C$144*F46/47.5*(1+Assumptions!$C$123)^2 | G53: =Assumptions!$C$144*G46/47.5*(1+Assumptions!$C$123)^3 | H53: =Assumptions!$C$144*H46/47.5*(1+Assumptions!$C$123)^4 | I53: =Assumptions!$C$144*I46/47.5*(1+Assumptions!$C$123)^5
A54: Other direct cost (conv revenue) | E54: =Assumptions!$C$145*E42/4210886.0*(1+Assumptions!$C$125)^1 | F54: =Assumptions!$C$145*F42/4210886.0*(1+Assumptions!$C$125)^2 | G54: =Assumptions!$C$145*G42/4210886.0*(1+Assumptions!$C$125)^3 | H54: =Assumptions!$C$145*H42/4210886.0*(1+Assumptions!$C$125)^4 | I54: =Assumptions!$C$145*I42/4210886.0*(1+Assumptions!$C$125)^5
A55: Conventional cash cost | E55: =SUM(E48:E54) | F55: =SUM(F48:F54) | G55: =SUM(G48:G54) | H55: =SUM(H48:H54) | I55: =SUM(I48:I54)
A56: Unconventional cash cost | E56: =(E28+E29)*(1-Assumptions!$C$126) | F56: =(F28+F29)*(1-Assumptions!$C$126) | G56: =(G28+G29)*(1-Assumptions!$C$126) | H56: =(H28+H29)*(1-Assumptions!$C$126) | I56: =(I28+I29)*(1-Assumptions!$C$126)
A57: General and administrative expenses excluding depreciation | E57: =Assumptions!$C$146*E42/4210886.0*(1+Assumptions!$C$125)^1 | F57: =Assumptions!$C$146*F42/4210886.0*(1+Assumptions!$C$125)^2 | G57: =Assumptions!$C$146*G42/4210886.0*(1+Assumptions!$C$125)^3 | H57: =Assumptions!$C$146*H42/4210886.0*(1+Assumptions!$C$125)^4 | I57: =Assumptions!$C$146*I42/4210886.0*(1+Assumptions!$C$125)^5
A58: Other income | E58: =Assumptions!$C$147*(1+Assumptions!$C$125)^1 | F58: =Assumptions!$C$147*(1+Assumptions!$C$125)^2 | G58: =Assumptions!$C$147*(1+Assumptions!$C$125)^3 | H58: =Assumptions!$C$147*(1+Assumptions!$C$125)^4 | I58: =Assumptions!$C$147*(1+Assumptions!$C$125)^5
A59: Share of joint-venture results | E59: =Assumptions!$C$148*(1+Assumptions!$C$125)^1 | F59: =Assumptions!$C$148*(1+Assumptions!$C$125)^2 | G59: =Assumptions!$C$148*(1+Assumptions!$C$125)^3 | H59: =Assumptions!$C$148*(1+Assumptions!$C$125)^4 | I59: =Assumptions!$C$148*(1+Assumptions!$C$125)^5
A61: EBITDA | B61: 1482896 | C61: 2014787 | D61: 2198036 | E61: =E41-E55-E56-E57+E58+E59 | F61: =F41-F55-F56-F57+F58+F59 | G61: =G41-G55-G56-G57+G58+G59 | H61: =H41-H55-H56-H57+H58+H59 | I61: =I41-I55-I56-I57+I58+I59
A62: EBITDA margin | B62: =B61/B41 | C62: =C61/C41 | D62: =D61/D41 | E62: =E61/E41 | F62: =F61/F41 | G62: =G61/G41 | H62: =H61/H41 | I62: =I61/I41
A63: EBITDA excluding joint-venture results | B63: 1482896 | C63: 2006297 | D63: 2169036 | E63: =E61-E59 | F63: =F61-F59 | G63: =G61-G59 | H63: =H61-H59 | I63: =I61-I59
A66: CAPACITY-PLATEAU CASE — OPERATING UNITS
A67: Average Abu Dhabi onshore rigs | E67: =(Assumptions!$C$93+Assumptions!$C$52)/2 | F67: =(Assumptions!$C$52+Assumptions!$C$53)/2 | G67: =(Assumptions!$C$53+Assumptions!$C$54)/2 | H67: =(Assumptions!$C$54+Assumptions!$C$55)/2 | I67: =(Assumptions!$C$55+Assumptions!$C$56)/2
A68: Average regional onshore rigs | E68: =(Assumptions!$C$105+Assumptions!$C$57)/2 | F68: =(Assumptions!$C$57+Assumptions!$C$58)/2 | G68: =(Assumptions!$C$58+Assumptions!$C$59)/2 | H68: =(Assumptions!$C$59+Assumptions!$C$60)/2 | I68: =(Assumptions!$C$60+Assumptions!$C$61)/2
A69: Average jack-up rigs | E69: =(Assumptions!$C$97+Assumptions!$C$62)/2 | F69: =(Assumptions!$C$62+Assumptions!$C$63)/2 | G69: =(Assumptions!$C$63+Assumptions!$C$64)/2 | H69: =(Assumptions!$C$64+Assumptions!$C$65)/2 | I69: =(Assumptions!$C$65+Assumptions!$C$66)/2
A70: Average island rigs | E70: =(Assumptions!$C$100+Assumptions!$C$67)/2 | F70: =(Assumptions!$C$67+Assumptions!$C$68)/2 | G70: =(Assumptions!$C$68+Assumptions!$C$69)/2 | H70: =(Assumptions!$C$69+Assumptions!$C$70)/2 | I70: =(Assumptions!$C$70+Assumptions!$C$71)/2
A71: Average integrated-services rigs | E71: =(Assumptions!$C$102+Assumptions!$C$72)/2 | F71: =(Assumptions!$C$72+Assumptions!$C$73)/2 | G71: =(Assumptions!$C$73+Assumptions!$C$74)/2 | H71: =(Assumptions!$C$74+Assumptions!$C$75)/2 | I71: =(Assumptions!$C$75+Assumptions!$C$76)/2
A72: Average rigs given at least one discrete service | E72: =(Assumptions!$C$104+Assumptions!$C$77)/2 | F72: =(Assumptions!$C$77+Assumptions!$C$78)/2 | G72: =(Assumptions!$C$78+Assumptions!$C$79)/2 | H72: =(Assumptions!$C$79+Assumptions!$C$80)/2 | I72: =(Assumptions!$C$80+Assumptions!$C$81)/2
A73: Day-rate escalation index (2025 = 1.00) | E73: =(1+Assumptions!$C$121)^1 | F73: =(1+Assumptions!$C$121)^2 | G73: =(1+Assumptions!$C$121)^3 | H73: =(1+Assumptions!$C$121)^4 | I73: =(1+Assumptions!$C$121)^5
A75: Rigs served by Oilfield Services (integrated plus discrete) | E75: =E71+E72 | F75: =F71+F72 | G75: =G71+G72 | H75: =H71+H72 | I75: =I71+I72
A76: Oilfield-services revenue-per-rig-served index (2025 = 1.00) | E76: =1*(1+(Assumptions!$C$119*1.000000+Assumptions!$C$121*0.000000)) | F76: =E76*(1+(Assumptions!$C$119*0.750000+Assumptions!$C$121*0.250000)) | G76: =F76*(1+(Assumptions!$C$119*0.500000+Assumptions!$C$121*0.500000)) | H76: =G76*(1+(Assumptions!$C$119*0.250000+Assumptions!$C$121*0.750000)) | I76: =H76*(1+(Assumptions!$C$119*0.000000+Assumptions!$C$121*1.000000))
A78: REVENUE BY UNIT — BEFORE RECONCILIATION TO FY2026 GUIDANCE
A79: Onshore conventional — Abu Dhabi | E79: =E67*Assumptions!$C$110*E73 | F79: =F67*Assumptions!$C$110*F73 | G79: =G67*Assumptions!$C$110*G73 | H79: =H67*Assumptions!$C$110*H73 | I79: =I67*Assumptions!$C$110*I73
A80: Onshore conventional — regional | E80: =E68*Assumptions!$C$111*E73 | F80: =F68*Assumptions!$C$111*F73 | G80: =G68*Assumptions!$C$111*G73 | H80: =H68*Assumptions!$C$111*H73 | I80: =I68*Assumptions!$C$111*I73
A81: Offshore — jack-up | E81: =E69*Assumptions!$C$113*E73 | F81: =F69*Assumptions!$C$113*F73 | G81: =G69*Assumptions!$C$113*G73 | H81: =H69*Assumptions!$C$113*H73 | I81: =I69*Assumptions!$C$113*I73
A82: Offshore — island | E82: =E70*Assumptions!$C$114*E73 | F82: =F70*Assumptions!$C$114*F73 | G82: =G70*Assumptions!$C$114*G73 | H82: =H70*Assumptions!$C$114*H73 | I82: =I70*Assumptions!$C$114*I73
A83: Oilfield Services — rigs served | E83: =E75*Assumptions!$C$118*E76 | F83: =F75*Assumptions!$C$118*F76 | G83: =G75*Assumptions!$C$118*G76 | H83: =H75*Assumptions!$C$118*H76 | I83: =I75*Assumptions!$C$118*I76
A85: RECONCILIATION TO THE FY2026 SEGMENT GUIDANCE
A86: Onshore — factor on the conventional unit build | E86: =(Assumptions!$C$187-E90)/(E79+E80)
A87: Offshore — factor on the conventional unit build | E87: =Assumptions!$C$188/(E81+E82)
A88: Oilfield Services — factor on the conventional unit build | E88: =(Assumptions!$C$189-E91)/E83
A90: Unconventional — Onshore land drilling | E90: =Assumptions!$C$155*Assumptions!$C$160 | F90: =Assumptions!$C$156*Assumptions!$C$160 | G90: =Assumptions!$C$157*Assumptions!$C$160 | H90: =Assumptions!$C$158*Assumptions!$C$160 | I90: =Assumptions!$C$159*Assumptions!$C$160
A91: Unconventional — Oilfield Services | E91: =Assumptions!$C$155*(1-Assumptions!$C$160) | F91: =Assumptions!$C$156*(1-Assumptions!$C$160) | G91: =Assumptions!$C$157*(1-Assumptions!$C$160) | H91: =Assumptions!$C$158*(1-Assumptions!$C$160) | I91: =Assumptions!$C$159*(1-Assumptions!$C$160)
A93: REVENUE BY REPORTED SEGMENT
A94: Onshore conventional — Abu Dhabi (reconciled) | E94: =E79*$E$86 | F94: =F79*$E$86 | G94: =G79*$E$86 | H94: =H79*$E$86 | I94: =I79*$E$86
A95: Onshore conventional — regional (reconciled) | E95: =E80*$E$86 | F95: =F80*$E$86 | G95: =G80*$E$86 | H95: =H80*$E$86 | I95: =I80*$E$86
A96: Offshore — jack-up (reconciled) | E96: =E81*$E$87 | F96: =F81*$E$87 | G96: =G81*$E$87 | H96: =H81*$E$87 | I96: =I81*$E$87
A97: Offshore — island (reconciled) | E97: =E82*$E$87 | F97: =F82*$E$87 | G97: =G82*$E$87 | H97: =H82*$E$87 | I97: =I82*$E$87
A98: Oilfield Services — rigs served (reconciled) | E98: =E83*$E$88 | F98: =F83*$E$88 | G98: =G83*$E$88 | H98: =H83*$E$88 | I98: =I83*$E$88
A100: Onshore | E100: =E94+E95+E90 | F100: =F94+F95+F90 | G100: =G94+G95+G90 | H100: =H94+H95+H90 | I100: =I94+I95+I90
A101: Offshore | E101: =E96+E97 | F101: =F96+F97 | G101: =G96+G97 | H101: =H96+H97 | I101: =I96+I97
A102: Oilfield Services | E102: =E98+E91 | F102: =F98+F91 | G102: =G98+G91 | H102: =H98+H91 | I102: =I98+I91
A103: Total revenue | E103: =E100+E101+E102 | F103: =F100+F101+F102 | G103: =G100+G101+G102 | H103: =H100+H101+H102 | I103: =I100+I101+I102
A104: of which conventional | E104: =E103-E90-E91 | F104: =F103-F90-F91 | G104: =G103-G90-G91 | H104: =H103-H90-H91 | I104: =I103-I90-I91
A106: COST STACK — EACH LINE ON ITS OWN VOLUME DRIVER AND ITS OWN ESCALATOR
A107: Total rig-years (all classes, including integrated services) | E107: =E67+E68+E69+E70+E71 | F107: =F67+F68+F69+F70+F71 | G107: =G67+G68+G69+G70+G71 | H107: =H67+H68+H69+H70+H71 | I107: =I67+I68+I69+I70+I71
A108: Offshore rig-years | E108: =E69+E70 | F108: =F69+F70 | G108: =G69+G70 | H108: =H69+H70 | I108: =I69+I70
A109: Wells drilled (drilling rig-years scaled off the FY2025 disclosed 836) | E109: =836.0*(E67+E68+E69+E70)/141.0 | F109: =836.0*(F67+F68+F69+F70)/141.0 | G109: =836.0*(G67+G68+G69+G70)/141.0 | H109: =836.0*(H67+H68+H69+H70)/141.0 | I109: =836.0*(I67+I68+I69+I70)/141.0
A110: Repairs and maintenance (rig years) | E110: =Assumptions!$C$139*E107/199.5*(1+Assumptions!$C$123)^1 | F110: =Assumptions!$C$139*F107/199.5*(1+Assumptions!$C$123)^2 | G110: =Assumptions!$C$139*G107/199.5*(1+Assumptions!$C$123)^3 | H110: =Assumptions!$C$139*H107/199.5*(1+Assumptions!$C$123)^4 | I110: =Assumptions!$C$139*I107/199.5*(1+Assumptions!$C$123)^5
A111: Staff costs (rig years) | E111: =Assumptions!$C$140*E107/199.5*(1+Assumptions!$C$122)^1 | F111: =Assumptions!$C$140*F107/199.5*(1+Assumptions!$C$122)^2 | G111: =Assumptions!$C$140*G107/199.5*(1+Assumptions!$C$122)^3 | H111: =Assumptions!$C$140*H107/199.5*(1+Assumptions!$C$122)^4 | I111: =Assumptions!$C$140*I107/199.5*(1+Assumptions!$C$122)^5
A112: Hire of equipment (conv revenue) | E112: =Assumptions!$C$141*E104/4210886.0*(1+Assumptions!$C$123)^1 | F112: =Assumptions!$C$141*F104/4210886.0*(1+Assumptions!$C$123)^2 | G112: =Assumptions!$C$141*G104/4210886.0*(1+Assumptions!$C$123)^3 | H112: =Assumptions!$C$141*H104/4210886.0*(1+Assumptions!$C$123)^4 | I112: =Assumptions!$C$141*I104/4210886.0*(1+Assumptions!$C$123)^5
A113: Chemicals (wells) | E113: =Assumptions!$C$142*E109/836.0*(1+Assumptions!$C$123)^1 | F113: =Assumptions!$C$142*F109/836.0*(1+Assumptions!$C$123)^2 | G113: =Assumptions!$C$142*G109/836.0*(1+Assumptions!$C$123)^3 | H113: =Assumptions!$C$142*H109/836.0*(1+Assumptions!$C$123)^4 | I113: =Assumptions!$C$142*I109/836.0*(1+Assumptions!$C$123)^5
A114: Fuel and lubricants (rig years) | E114: =Assumptions!$C$143*E107/199.5*(1+Assumptions!$C$124)^1 | F114: =Assumptions!$C$143*F107/199.5*(1+Assumptions!$C$124)^2 | G114: =Assumptions!$C$143*G107/199.5*(1+Assumptions!$C$124)^3 | H114: =Assumptions!$C$143*H107/199.5*(1+Assumptions!$C$124)^4 | I114: =Assumptions!$C$143*I107/199.5*(1+Assumptions!$C$124)^5
A115: Major maintenance charges (offshore rig years) | E115: =Assumptions!$C$144*E108/47.5*(1+Assumptions!$C$123)^1 | F115: =Assumptions!$C$144*F108/47.5*(1+Assumptions!$C$123)^2 | G115: =Assumptions!$C$144*G108/47.5*(1+Assumptions!$C$123)^3 | H115: =Assumptions!$C$144*H108/47.5*(1+Assumptions!$C$123)^4 | I115: =Assumptions!$C$144*I108/47.5*(1+Assumptions!$C$123)^5
A116: Other direct cost (conv revenue) | E116: =Assumptions!$C$145*E104/4210886.0*(1+Assumptions!$C$125)^1 | F116: =Assumptions!$C$145*F104/4210886.0*(1+Assumptions!$C$125)^2 | G116: =Assumptions!$C$145*G104/4210886.0*(1+Assumptions!$C$125)^3 | H116: =Assumptions!$C$145*H104/4210886.0*(1+Assumptions!$C$125)^4 | I116: =Assumptions!$C$145*I104/4210886.0*(1+Assumptions!$C$125)^5
A117: Conventional cash cost | E117: =SUM(E110:E116) | F117: =SUM(F110:F116) | G117: =SUM(G110:G116) | H117: =SUM(H110:H116) | I117: =SUM(I110:I116)
A118: Unconventional cash cost | E118: =(E90+E91)*(1-Assumptions!$C$126) | F118: =(F90+F91)*(1-Assumptions!$C$126) | G118: =(G90+G91)*(1-Assumptions!$C$126) | H118: =(H90+H91)*(1-Assumptions!$C$126) | I118: =(I90+I91)*(1-Assumptions!$C$126)
...

Sheet Relative & Normalized
A1: Relative multiples, normalised earnings power, and the book-value lens
A3: RELATIVE MULTIPLES — segment-weighted, applied to the company's own guided EBITDA
A4: Onshore share of FY2025 segment EBITDA | C4: =994477.0/(994477.0+952523.0+251036.0) | D4: From the FY2025 segment note
A5: Offshore share of FY2025 segment EBITDA | C5: =952523.0/(994477.0+952523.0+251036.0)
A6: Oilfield Services share of FY2025 segment EBITDA | C6: =1-C4-C5
A7: Multiple applied to Onshore | C7: =(Assumptions!$C$253+Assumptions!$C$254)/2 | D7: Average of the MENA national-oil-company drillers and the global land drillers
A8: Multiple applied to Offshore | C8: =(Assumptions!$C$253+Assumptions!$C$255)/2
A9: Multiple applied to Oilfield Services | C9: =Assumptions!$C$256
A10: Segment-weighted multiple | C10: =C4*C7+C5*C8+C6*C9
A11: Last-twelve-month EBITDA excluding joint ventures | C11: =Assumptions!$C$252 | D11: The multiple and the earnings it multiplies are on the same footing: every peer multiple above is an enterprise value struck today over that peer's last twelve months, and the joint-venture earnings are taken out here because the joint-venture carrying value is added back on the bridge below
A12: Implied enterprise value | C12: =C10*C11
A13: Implied equity value at 30 June 2026 | C13: =C12+Assumptions!$C$228+Assumptions!$C$229-Assumptions!$C$230-Assumptions!$C$231-Assumptions!$C$232 | D13: The same bridge the cash-flow lenses use, and the minority is deducted once
A14: Accreted to the price anchor at the cost of equity | C14: =C13*(1+DCF!$C$9)^(Assumptions!$C$236/365)
A15: Implied value per share (AED) | C15: =C14/(Assumptions!$C$7-Assumptions!$C$8)*Assumptions!$C$6
A16: The company's own enterprise value / last-twelve-month EBITDA | C16: =(DCF!$C$19+DCF!$C$20)/C11 | D16: The gap between this and the segment-weighted peer multiple is the whole of the relative lens
A18: NORMALISED EARNINGS POWER — the installed fleet, no growth credited
A19: Normalised revenue on the fleet installed at 30 June 2026 | C19: =Assumptions!$C$93*Assumptions!$C$110+Assumptions!$C$105*Assumptions!$C$111+Assumptions!$C$97*Assumptions!$C$113+Assumptions!$C$106*Assumptions!$C$114+(Assumptions!$C$107+Assumptions!$C$108)*Assumptions!$C$118 | D19: The rigs the company has ALREADY taken delivery of, at FY2025 realised rates. The first edition carried 14 island rigs and the 70 integrated rigs the company TARGETS for the end of 2026; the reported counts at 30 June 2026 are 13 and 61. A target is growth, and this lens is the one that credits none
A20: Normalised EBITDA | C20: =C19*Assumptions!$C$248
A21: Normalised depreciation and amortisation | C21: =Assumptions!$C$249 | D21: The charge the fleet being priced actually carries, annualised off the first half of 2026
A22: Normalised EBIT | C22: =C20-C21
A23: Normalised NOPAT | C23: =C22*(1-Assumptions!$C$19)
A24: Capitalisation rate — the cost of capital, with no growth deducted from it | C24: =DCF!$C$24 | D24: The first edition divided by the cost of capital LESS a terminal growth rate while the text beside it said no growth was credited. A denominator of cost-of-capital-minus-growth IS the growth credit; there is no other reason for the growth rate to appear in it
A25: Implied enterprise value | C25: =C23/C24
A26: Implied equity value at 30 June 2026 | C26: =C25+Assumptions!$C$228+Assumptions!$C$229-Assumptions!$C$230-Assumptions!$C$231-Assumptions!$C$232
A27: Accreted to the price anchor at the cost of equity | C27: =C26*(1+DCF!$C$9)^(Assumptions!$C$236/365)
A28: Implied value per share (AED) | C28: =C27/(Assumptions!$C$7-Assumptions!$C$8)*Assumptions!$C$6
A30: BOOK VALUE AND SUSTAINABLE RETURN
A31: Sustainable return on equity | C31: =Assumptions!$C$251
A32: Cost of equity | C32: =DCF!$C$9
A33: Growth | C33: =Assumptions!$C$193
A34: Justified price / book = (return on equity - growth) / (cost of equity - growth) | C34: =(C31-C33)/(C32-C33) | D34: Highly geared to the denominator: with a cost of equity this close to the growth rate, a small move in either coordinate moves the multiple a long way. Read the sensitivity, not the point estimate
A35: Book equity attributable to owners | C35: =Assumptions!$C$239
A36: Book value per share (AED) | C36: =C35/(Assumptions!$C$7-Assumptions!$C$8)*Assumptions!$C$6
A37: Implied value per share (AED) | C37: =C34*C36*(1+C32)^(Assumptions!$C$236/365)
A38: The company's own price / book | C38: =Assumptions!$C$5/C36

Sheet DCF
A1: Discounted cash flow — the cost of capital and the waterfall, both built here
A3: COST OF CAPITAL — BUILT, NOT PASTED
A4: US 10-year Treasury yield (observed) | C4: =Assumptions!$C$10
A5: less the US adjusted default spread | C5: =Assumptions!$C$11
A6: Normalised risk-free rate | C6: =C4-C5
A7: Equity beta | C7: =Assumptions!$C$12
A8: Equity risk premium — rating basis | C8: =Assumptions!$C$13
A9: Cost of equity — rating basis | C9: =C6+C7*C8
A10: Equity risk premium — credit-default-swap basis | C10: =Assumptions!$C$14
A11: Cost of equity — credit-default-swap basis | C11: =C6+C7*C10
A12: US 5-year Treasury yield | C12: =Assumptions!$C$15
A13: Borrowing margin on the latest facility | C13: =Assumptions!$C$16
A14: Marginal cost of debt, pre-tax (term-matched) | C14: =C12+C13
A15: Cross-check: spot floating all-in cost | C15: =Assumptions!$C$17+C13
A16: Cross-check: trailing effective rate on average gross debt | C16: 0.047696771
A17: Sovereign floor — 5-year Treasury plus the Abu Dhabi credit-default-swap spread | C17: =C12+Assumptions!$C$18
A18: Cost of debt after tax | C18: =C14*(1-Assumptions!$C$19)
A19: Market capitalisation | C19: =(Assumptions!$C$7-Assumptions!$C$8)*Assumptions!$C$5/Assumptions!$C$6
A20: Net debt at 30 June 2026 | C20: =Assumptions!$C$230+Assumptions!$C$231-Assumptions!$C$229
A21: Gross interest-bearing debt at 30 June 2026 | C21: =Assumptions!$C$230+Assumptions!$C$231 | D21: The weights are struck on GROSS debt. Interest is paid on the gross balance, and cash is bridged separately in the enterprise-value-to-equity step; netting it off here as well would take credit for the same cash twice
A22: Weight of equity | C22: =C19/(C19+C21)
A23: Weight of debt | C23: =1-C22
A24: Weighted average cost of capital — rating basis | C24: =C22*C9+C23*C18
A25: Weighted average cost of capital — credit-default-swap basis | C25: =C22*C11+C23*C18
A27: FREE-CASH-FLOW WATERFALL — CONTINUED-EXPANSION CASE
B28: FY2026E | C28: FY2027E | D28: FY2028E | E28: FY2029E | F28: FY2030E
A29: Revenue | B29: =Segments!E41 | C29: =Segments!F41 | D29: =Segments!G41 | E29: =Segments!H41 | F29: =Segments!I41
A30: EBITDA | B30: =Segments!E63 | C30: =Segments!F63 | D30: =Segments!G63 | E30: =Segments!H63 | F30: =Segments!I63
A31: EBITDA margin | B31: =B30/B29 | C31: =C30/C29 | D31: =D30/D29 | E31: =E30/E29 | F31: =F30/F29
A32: less depreciation and amortisation | B32: =-'Balance Sheet'!E8 | C32: =-'Balance Sheet'!F8 | D32: =-'Balance Sheet'!G8 | E32: =-'Balance Sheet'!H8 | F32: =-'Balance Sheet'!I8
A33: EBIT | B33: =B30+B32 | C33: =C30+C32 | D33: =D30+D32 | E33: =E30+E32 | F33: =F30+F32
A34: Tax rate | B34: =Assumptions!$C$19 | C34: =Assumptions!$C$19 | D34: =Assumptions!$C$19 | E34: =Assumptions!$C$19 | F34: =Assumptions!$C$19
A35: NOPAT = EBIT x (1 - tax rate) | B35: =B33*(1-B34) | C35: =C33*(1-C34) | D35: =D33*(1-D34) | E35: =E33*(1-E34) | F35: =F33*(1-F34)
A36: add back depreciation and amortisation | B36: ='Balance Sheet'!E8 | C36: ='Balance Sheet'!F8 | D36: ='Balance Sheet'!G8 | E36: ='Balance Sheet'!H8 | F36: ='Balance Sheet'!I8
A37: less capital expenditure | B37: =-'Balance Sheet'!E7 | C37: =-'Balance Sheet'!F7 | D37: =-'Balance Sheet'!G7 | E37: =-'Balance Sheet'!H7 | F37: =-'Balance Sheet'!I7
A38: less increase in working capital | B38: =-('Balance Sheet'!E33-'Balance Sheet'!D33-(Assumptions!$C$200+Assumptions!$C$201-Assumptions!$C$202)) | C38: =-('Balance Sheet'!F33-'Balance Sheet'!E33) | D38: =-('Balance Sheet'!G33-'Balance Sheet'!F33) | E38: =-('Balance Sheet'!H33-'Balance Sheet'!G33) | F38: =-('Balance Sheet'!I33-'Balance Sheet'!H33)
A39: Free cash flow to the firm | B39: =B35+B36+B37+B38 | C39: =C35+C36+C37+C38 | D39: =D35+D36+D37+D38 | E39: =E35+E36+E37+E38 | F39: =F35+F36+F37+F38
A40: Discount factor | B40: =1/(1+$C$24)^1 | C40: =1/(1+$C$24)^2 | D40: =1/(1+$C$24)^3 | E40: =1/(1+$C$24)^4 | F40: =1/(1+$C$24)^5
A41: Present value of free cash flow to the firm | B41: =B39*B40 | C41: =C39*C40 | D41: =D39*D40 | E41: =E39*E40 | F41: =F39*F40
A43: TERMINAL BLOCK AND ENTERPRISE VALUE
A44: Terminal growth rate | C44: =Assumptions!$C$193
A45: Terminal return on invested capital | C45: =Assumptions!$C$195
A46: Terminal-year NOPAT (one year beyond the window) | C46: =F35*(1+C44)
A47: Reinvestment rate = growth / return on capital | C47: =C44/C45
A48: Net debt in the terminal year, off this model's own balance sheet | C48: ='Balance Sheet'!I34 | D48: This model's own 2030 balance sheet has the firm holding net cash. A self-audit of this study proposed capitalising the terminal block at the cost of equity on that basis, and it was accepted and priced before being implemented. It was then reversed. The capital-structure weights above are struck on GROSS debt, because interest is paid on the gross balance and cash is bridged separately — and a firm holding cash alongside undiminished gross borrowings has not de-levered. Reading the terminal structure off net debt after refusing to read today's off net debt is one quantity treated two ways. The terminal net debt is published here because it is worth seeing; it does not set the rate.
A49: Terminal capitalisation rate | C49: =$C$24
A50: Terminal value | C50: =C46*(1-C47)/(C49-C44)
A51: Present value of the terminal value | C51: =C50*F40
A52: Present value of the explicit five years | C52: =SUM(B41:F41)
A53: Enterprise value at 31 December 2025 | C53: =C52+C51
A54: Terminal value as a share of enterprise value | C54: =C51/C53
A56: CAPACITY-PLATEAU CASE — the same waterfall on the plateau fleet plan
B57: FY2026E | C57: FY2027E | D57: FY2028E | E57: FY2029E | F57: FY2030E
A58: EBITDA excluding joint-venture results | B58: =Segments!E125 | C58: =Segments!F125 | D58: =Segments!G125 | E58: =Segments!H125 | F58: =Segments!I125
A59: less depreciation and amortisation | B59: =-'Balance Sheet'!E41 | C59: =-'Balance Sheet'!F41 | D59: =-'Balance Sheet'!G41 | E59: =-'Balance Sheet'!H41 | F59: =-'Balance Sheet'!I41
A60: EBIT | B60: =B58+B59 | C60: =C58+C59 | D60: =D58+D59 | E60: =E58+E59 | F60: =F58+F59
A61: NOPAT = EBIT x (1 - tax rate) | B61: =B60*(1-Assumptions!$C$19) | C61: =C60*(1-Assumptions!$C$19) | D61: =D60*(1-Assumptions!$C$19) | E61: =E60*(1-Assumptions!$C$19) | F61: =F60*(1-Assumptions!$C$19)
A62: add back depreciation and amortisation | B62: ='Balance Sheet'!E41 | C62: ='Balance Sheet'!F41 | D62: ='Balance Sheet'!G41 | E62: ='Balance Sheet'!H41 | F62: ='Balance Sheet'!I41
A63: less capital expenditure | B63: =-'Balance Sheet'!E40 | C63: =-'Balance Sheet'!F40 | D63: =-'Balance Sheet'!G40 | E63: =-'Balance Sheet'!H40 | F63: =-'Balance Sheet'!I40
A64: less increase in working capital | B64: =-('Balance Sheet'!E43-'Balance Sheet'!D33-(Assumptions!$C$200+Assumptions!$C$201-Assumptions!$C$202)) | C64: =-('Balance Sheet'!F43-'Balance Sheet'!E43) | D64: =-('Balance Sheet'!G43-'Balance Sheet'!F43) | E64: =-('Balance Sheet'!H43-'Balance Sheet'!G43) | F64: =-('Balance Sheet'!I43-'Balance Sheet'!H43)
A65: Free cash flow to the firm — plateau case | B65: =B61+B62+B63+B64 | C65: =C61+C62+C63+C64 | D65: =D61+D62+D63+D64 | E65: =E61+E62+E63+E64 | F65: =F61+F62+F63+F64
A66: Discount factor | B66: =1/(1+$C$24)^1 | C66: =1/(1+$C$24)^2 | D66: =1/(1+$C$24)^3 | E66: =1/(1+$C$24)^4 | F66: =1/(1+$C$24)^5
A67: Present value | B67: =B65*B66 | C67: =C65*C66 | D67: =D65*D66 | E67: =E65*E66 | F67: =F65*F66
A68: Terminal growth rate — plateau | C68: =Assumptions!$C$194
A69: Terminal-year NOPAT | C69: =F61*(1+C68)
A70: Net debt in the terminal year — plateau | C70: ='Balance Sheet'!I55
A71: Terminal capitalisation rate — plateau | C71: =$C$24
A72: Terminal value | C72: =C69*(1-C68/C45)/(C71-C68)
A73: Present value of the terminal value | C73: =C72*F66
A74: Present value of the explicit five years | C74: =SUM(B67:F67)
A75: Enterprise value — plateau, at 31 December 2025 | C75: =C74+C73
A76: Terminal value as a share of enterprise value | C76: =C73/C75

Sheet Income Statement
A1: Income statement — three audited years and the five-year forecast
A3: USD thousands | B3: FY2023 | C3: FY2024 | D3: FY2025 | E3: FY2026E | F3: FY2027E | G3: FY2028E | H3: FY2029E | I3: FY2030E
A4: Revenue | B4: =Segments!B41 | C4: =Segments!C41 | D4: =Segments!D41 | E4: =Segments!E41 | F4: =Segments!F41 | G4: =Segments!G41 | H4: =Segments!H41 | I4: =Segments!I41
A5: EBITDA | B5: =Segments!B61 | C5: =Segments!C61 | D5: =Segments!D61 | E5: =Segments!E61 | F5: =Segments!F61 | G5: =Segments!G61 | H5: =Segments!H61 | I5: =Segments!I61
A6: EBITDA margin | B6: =B5/B4 | C6: =C5/C4 | D6: =D5/D4 | E6: =E5/E4 | F6: =F5/F4 | G6: =G5/G4 | H6: =H5/H4 | I6: =I5/I4
A7: Depreciation and amortisation | B7: =-'Balance Sheet'!B8 | C7: =-'Balance Sheet'!C8 | D7: =-'Balance Sheet'!D8 | E7: =-'Balance Sheet'!E8 | F7: =-'Balance Sheet'!F8 | G7: =-'Balance Sheet'!G8 | H7: =-'Balance Sheet'!H8 | I7: =-'Balance Sheet'!I8
A8: Share of joint-venture results | B8: 0 | C8: 8490 | D8: 29000 | E8: =Segments!E59 | F8: =Segments!F59 | G8: =Segments!G59 | H8: =Segments!H59 | I8: =Segments!I59
A9: EBIT (after depreciation, before joint ventures) | B9: =B5-B8+B7 | C9: =C5-C8+C7 | D9: =D5-D8+D7 | E9: =E5-E8+E7 | F9: =F5-F8+F7 | G9: =G5-G8+G7 | H9: =H5-H8+H7 | I9: =I5-I8+I7
A10: Finance cost | B10: -74577 | C10: -135995 | D10: -109463 | E10: =-'Balance Sheet'!E22*DCF!$C$14 | F10: =-'Balance Sheet'!F22*DCF!$C$14 | G10: =-'Balance Sheet'!G22*DCF!$C$14 | H10: =-'Balance Sheet'!H22*DCF!$C$14 | I10: =-'Balance Sheet'!I22*DCF!$C$14
A11: Finance income | B11: 15727 | C11: 11736 | D11: 11626 | E11: =('Balance Sheet'!D18+Assumptions!$C$203-Assumptions!$C$211+Assumptions!$C$212)*Assumptions!$C$17 | F11: ='Balance Sheet'!E18*Assumptions!$C$17 | G11: ='Balance Sheet'!F18*Assumptions!$C$17 | H11: ='Balance Sheet'!G18*Assumptions!$C$17 | I11: ='Balance Sheet'!H18*Assumptions!$C$17
A12: Profit before tax | B12: =B9+B8+B10+B11 | C12: =C9+C8+C10+C11 | D12: =D9+D8+D10+D11 | E12: =E9+E8+E10+E11 | F12: =F9+F8+F10+F11 | G12: =G9+G8+G10+G11 | H12: =H9+H8+H10+H11 | I12: =I9+I8+I10+I11
A13: Income tax | B13: 0 | C13: -128510 | D13: -139099 | E13: =-E12*Assumptions!$C$19 | F13: =-F12*Assumptions!$C$19 | G13: =-G12*Assumptions!$C$19 | H13: =-H12*Assumptions!$C$19 | I13: =-I12*Assumptions!$C$19
A14: Profit after tax | B14: =B12+B13 | C14: =C12+C13 | D14: =D12+D13 | E14: =E12+E13 | F14: =F12+F13 | G14: =G12+G13 | H14: =H12+H13 | I14: =I12+I13
A15: Net margin | B15: =B14/B4 | C15: =C14/C4 | D15: =D14/D4 | E15: =E14/E4 | F15: =F14/F4 | G15: =G14/G4 | H15: =H14/H4 | I15: =I14/I4

Sheet Balance Sheet
A1: Balance sheet — three audited years and the five-year roll-forward
A3: USD thousands | B3: FY2023 | C3: FY2024 | D3: FY2025 | E3: FY2026E | F3: FY2027E | G3: FY2028E | H3: FY2029E | I3: FY2030E
A4: FIXED-ASSET ROLL-FORWARD
A5: Opening property, equipment, right-of-use and intangibles | E5: =(Assumptions!$C$224+Assumptions!$C$225+Assumptions!$C$226) | F5: =E9 | G5: =F9 | H5: =G9 | I5: =H9
A6: Acquired with the 2026 business combinations | B6: 0 | C6: 0 | D6: 0 | E6: =(Assumptions!$C$197+Assumptions!$C$198+Assumptions!$C$199) | F6: =0 | G6: =0 | H6: =0 | I6: =0
A7: Capital expenditure | B7: 1062274 | C7: 761822 | D7: 814876 | E7: =Assumptions!$C$162 | F7: =Assumptions!$C$163 | G7: =Assumptions!$C$164 | H7: =Assumptions!$C$165 | I7: =Assumptions!$C$166
A8: Depreciation and amortisation | B8: 391247 | C8: 458452 | D8: 512319 | E8: =(E5+E6)*Assumptions!$C$176 | F8: =(F5+F6)*Assumptions!$C$176 | G8: =(G5+G6)*Assumptions!$C$176 | H8: =(H5+H6)*Assumptions!$C$176 | I8: =(I5+I6)*Assumptions!$C$176
A9: Closing fixed assets | B9: =4847540.0+173911.0+5432.0 | C9: =5352674.0+23310.0+5301.0 | D9: =5477158.0+45729.0+10769.0 | E9: =E5+E6+E7-E8 | F9: =F5+F6+F7-F8 | G9: =G5+G6+G7-G8 | H9: =H5+H6+H7-H8 | I9: =I5+I6+I7-I8
A11: ASSETS
A12: Fixed assets | B12: 5026883 | C12: 5381285 | D12: 5533656 | E12: =E9 | F12: =F9 | G12: =G9 | H12: =H9 | I12: =I9
A13: Other non-current assets | B13: 1654 | C13: 3627 | D13: =Assumptions!$C$218+Assumptions!$C$219+Assumptions!$C$213 | E13: =(D13-Assumptions!$C$213) | F13: =(D13-Assumptions!$C$213) | G13: =(D13-Assumptions!$C$213) | H13: =(D13-Assumptions!$C$213) | I13: =(D13-Assumptions!$C$213)
A14: Investment in joint ventures | B14: 0 | C14: 275240 | D14: =Assumptions!$C$220 | E14: =Assumptions!$C$220 | F14: =Assumptions!$C$220 | G14: =Assumptions!$C$220 | H14: =Assumptions!$C$220 | I14: =Assumptions!$C$220
A15: Inventories | B15: 206107 | C15: 223083 | D15: 279030 | E15: =E33*1.05969746801311 | F15: =F33*1.05969746801311 | G15: =G33*1.05969746801311 | H15: =H33*1.05969746801311 | I15: =I33*1.05969746801311
A16: Trade and other receivables | B16: 153946 | C16: 185958 | D16: 150376 | E16: =E33*0.5710965360353346 | F16: =F33*0.5710965360353346 | G16: =G33*0.5710965360353346 | H16: =H33*0.5710965360353346 | I16: =I33*0.5710965360353346
A17: Due from related parties | B17: 986696 | C17: 1361282 | D17: 1364794 | E17: =E33*5.183201613301382 | F17: =F33*5.183201613301382 | G17: =G33*5.183201613301382 | H17: =H33*5.183201613301382 | I17: =I33*5.183201613301382
A18: Cash and cash equivalents | B18: 364839 | C18: 335996 | D18: =Assumptions!$C$221 | E18: ='Cash Flow'!E14 | F18: ='Cash Flow'!F14 | G18: ='Cash Flow'!G14 | H18: ='Cash Flow'!H14 | I18: ='Cash Flow'!I14
A19: Total assets | B19: =SUM(B12:B18) | C19: =SUM(C12:C18) | D19: =SUM(D12:D18) | E19: =SUM(E12:E18) | F19: =SUM(F12:F18) | G19: =SUM(G12:G18) | H19: =SUM(H12:H18) | I19: =SUM(I12:I18)
A21: LIABILITIES AND EQUITY
A22: Borrowings and lease liabilities | B22: 2181475 | C22: 2319907 | D22: =Assumptions!$C$215+Assumptions!$C$216 | E22: =(Assumptions!$C$215+Assumptions!$C$216)+(Assumptions!$C$204+Assumptions!$C$205) | F22: =(Assumptions!$C$215+Assumptions!$C$216)+(Assumptions!$C$204+Assumptions!$C$205) | G22: =(Assumptions!$C$215+Assumptions!$C$216)+(Assumptions!$C$204+Assumptions!$C$205) | H22: =(Assumptions!$C$215+Assumptions!$C$216)+(Assumptions!$C$204+Assumptions!$C$205) | I22: =(Assumptions!$C$215+Assumptions!$C$216)+(Assumptions!$C$204+Assumptions!$C$205)
A23: Trade and other payables | B23: 929770 | C23: 1240598 | D23: 1114818 | E23: =E33*4.2338451488923745 | F23: =F33*4.2338451488923745 | G23: =G33*4.2338451488923745 | H23: =H33*4.2338451488923745 | I23: =I33*4.2338451488923745
A24: Due to related parties | B24: 250237 | C24: 250850 | D24: 416071 | E24: =E33*1.5801504684574514 | F24: =F33*1.5801504684574514 | G24: =G33*1.5801504684574514 | H24: =H33*1.5801504684574514 | I24: =I33*1.5801504684574514
A25: Employees' end of service benefits | B25: 114422 | C25: 129947 | D25: =Assumptions!$C$217 | E25: =(Assumptions!$C$217+Assumptions!$C$208)*(1+Assumptions!$C$122)^1 | F25: =(Assumptions!$C$217+Assumptions!$C$208)*(1+Assumptions!$C$122)^2 | G25: =(Assumptions!$C$217+Assumptions!$C$208)*(1+Assumptions!$C$122)^3 | H25: =(Assumptions!$C$217+Assumptions!$C$208)*(1+Assumptions!$C$122)^4 | I25: =(Assumptions!$C$217+Assumptions!$C$208)*(1+Assumptions!$C$122)^5
A26: Income tax payable | B26: 0 | C26: 15000 | D26: =Assumptions!$C$223 | E26: =-'Income Statement'!E13*0.07908036722046888 | F26: =-'Income Statement'!F13*0.07908036722046888 | G26: =-'Income Statement'!G13*0.07908036722046888 | H26: =-'Income Statement'!H13*0.07908036722046888 | I26: =-'Income Statement'!I13*0.07908036722046888
A27: Liabilities assumed with the 2026 acquisitions | B27: 0 | C27: 0 | D27: 0 | E27: =(Assumptions!$C$206+Assumptions!$C$207+Assumptions!$C$209) | F27: =(Assumptions!$C$206+Assumptions!$C$207+Assumptions!$C$209) | G27: =(Assumptions!$C$206+Assumptions!$C$207+Assumptions!$C$209) | H27: =(Assumptions!$C$206+Assumptions!$C$207+Assumptions!$C$209) | I27: =(Assumptions!$C$206+Assumptions!$C$207+Assumptions!$C$209)
A28: Total liabilities | B28: =SUM(B22:B26) | C28: =SUM(C22:C26) | D28: =SUM(D22:D26) | E28: =SUM(E22:E27) | F28: =SUM(F22:F27) | G28: =SUM(G22:G27) | H28: =SUM(H22:H27) | I28: =SUM(I22:I27)
A29: Non-controlling interests | B29: 0 | C29: 0 | D29: 0 | E29: =Assumptions!$C$210 | F29: =Assumptions!$C$210 | G29: =Assumptions!$C$210 | H29: =Assumptions!$C$210 | I29: =Assumptions!$C$210
A30: Equity attributable to owners of the company | B30: 3264221 | C30: 3810169 | D30: =Assumptions!$C$222 | E30: =E19-E28-E29 | F30: =F19-F28-F29 | G30: =G19-G28-G29 | H30: =H19-H28-H29 | I30: =I19-I28-I29
A31: Total liabilities and equity | B31: =B28+B29+B30 | C31: =C28+C29+C30 | D31: =D28+D29+D30 | E31: =E28+E29+E30 | F31: =F28+F29+F30 | G31: =G28+G29+G30 | H31: =H28+H29+H30 | I31: =I28+I29+I30
A33: Working capital | B33: =B15+B16+B17-B23-B24 | C33: =C15+C16+C17-C23-C24 | D33: =D15+D16+D17-D23-D24 | E33: =Segments!E41*Assumptions!$C$185 | F33: =Segments!F41*Assumptions!$C$185 | G33: =Segments!G41*Assumptions!$C$185 | H33: =Segments!H41*Assumptions!$C$185 | I33: =Segments!I41*Assumptions!$C$185
A34: Net debt | B34: =B22-B18 | C34: =C22-C18 | D34: =D22-D18 | E34: =E22-E18 | F34: =F22-F18 | G34: =G22-G18 | H34: =H22-H18 | I34: =I22-I18
A35: Net debt / EBITDA | B35: =B34/Segments!B61 | C35: =C34/Segments!C61 | D35: =D34/Segments!D61 | E35: =E34/Segments!E61 | F35: =F34/Segments!F61 | G35: =G34/Segments!G61 | H35: =H34/Segments!H61 | I35: =I34/Segments!I61
A37: CAPACITY-PLATEAU CASE — FIXED ASSETS AND WORKING CAPITAL
A38: Opening fixed assets | E38: =(Assumptions!$C$224+Assumptions!$C$225+Assumptions!$C$226) | F38: =E42 | G38: =F42 | H38: =G42 | I38: =H42
A39: Acquired with the 2026 business combinations | E39: =(Assumptions!$C$197+Assumptions!$C$198+Assumptions!$C$199) | F39: =0 | G39: =0 | H39: =0 | I39: =0
A40: Capital expenditure | E40: =Assumptions!$C$167 | F40: =Assumptions!$C$168 | G40: =Assumptions!$C$169 | H40: =Assumptions!$C$170 | I40: =Assumptions!$C$171
A41: Depreciation and amortisation | E41: =(E38+E39)*Assumptions!$C$176 | F41: =(F38+F39)*Assumptions!$C$176 | G41: =(G38+G39)*Assumptions!$C$176 | H41: =(H38+H39)*Assumptions!$C$176 | I41: =(I38+I39)*Assumptions!$C$176
A42: Closing fixed assets | E42: =E38+E39+E40-E41 | F42: =F38+F39+F40-F41 | G42: =G38+G39+G40-G41 | H42: =H38+H39+H40-H41 | I42: =I38+I39+I40-I41
A43: Working capital | E43: =Segments!E103*Assumptions!$C$185 | F43: =Segments!F103*Assumptions!$C$185 | G43: =Segments!G103*Assumptions!$C$185 | H43: =Segments!H103*Assumptions!$C$185 | I43: =Segments!I103*Assumptions!$C$185
A44: Borrowings and lease liabilities | E44: =(Assumptions!$C$215+Assumptions!$C$216)+(Assumptions!$C$204+Assumptions!$C$205) | F44: =(Assumptions!$C$215+Assumptions!$C$216)+(Assumptions!$C$204+Assumptions!$C$205) | G44: =(Assumptions!$C$215+Assumptions!$C$216)+(Assumptions!$C$204+Assumptions!$C$205) | H44: =(Assumptions!$C$215+Assumptions!$C$216)+(Assumptions!$C$204+Assumptions!$C$205) | I44: =(Assumptions!$C$215+Assumptions!$C$216)+(Assumptions!$C$204+Assumptions!$C$205)
A45: Finance cost | E45: =E44*(Assumptions!$C$15+Assumptions!$C$16) | F45: =F44*(Assumptions!$C$15+Assumptions!$C$16) | G45: =G44*(Assumptions!$C$15+Assumptions!$C$16) | H45: =H44*(Assumptions!$C$15+Assumptions!$C$16) | I45: =I44*(Assumptions!$C$15+Assumptions!$C$16)
A46: Finance income | E46: =(Assumptions!$C$221+Assumptions!$C$203-Assumptions!$C$211+Assumptions!$C$212)*Assumptions!$C$17 | F46: =(E54)*Assumptions!$C$17 | G46: =(F54)*Assumptions!$C$17 | H46: =(G54)*Assumptions!$C$17 | I46: =(H54)*Assumptions!$C$17
A47: Share of joint-venture results | E47: =Segments!E121 | F47: =Segments!F121 | G47: =Segments!G121 | H47: =Segments!H121 | I47: =Segments!I121
A48: EBIT | E48: =Segments!E125-E41 | F48: =Segments!F125-F41 | G48: =Segments!G125-G41 | H48: =Segments!H125-H41 | I48: =Segments!I125-I41
A49: Profit before tax | E49: =E48+E47-E45+E46 | F49: =F48+F47-F45+F46 | G49: =G48+G47-G45+G46 | H49: =H48+H47-H45+H46 | I49: =I48+I47-I45+I46
A50: Income tax | E50: =E49*Assumptions!$C$19 | F50: =F49*Assumptions!$C$19 | G50: =G49*Assumptions!$C$19 | H50: =H49*Assumptions!$C$19 | I50: =I49*Assumptions!$C$19
A51: Profit after tax | E51: =E49-E50 | F51: =F49-F50 | G51: =G49-G50 | H51: =H49-H50 | I51: =I49-I50
A52: Employees' end of service benefits | E52: =(Assumptions!$C$217+Assumptions!$C$208)*(1+Assumptions!$C$122)^1 | F52: =(Assumptions!$C$217+Assumptions!$C$208)*(1+Assumptions!$C$122)^2 | G52: =(Assumptions!$C$217+Assumptions!$C$208)*(1+Assumptions!$C$122)^3 | H52: =(Assumptions!$C$217+Assumptions!$C$208)*(1+Assumptions!$C$122)^4 | I52: =(Assumptions!$C$217+Assumptions!$C$208)*(1+Assumptions!$C$122)^5
A53: Income tax payable | E53: =E50*0.07908036722046888 | F53: =F50*0.07908036722046888 | G53: =G50*0.07908036722046888 | H53: =H50*0.07908036722046888 | I53: =I50*0.07908036722046888
A54: Closing cash | E54: =Assumptions!$C$221+Assumptions!$C$203-Assumptions!$C$211+Assumptions!$C$212+E51+E41-(E43-D33-(Assumptions!$C$200+Assumptions!$C$201-Assumptions!$C$202))+(E52-(Assumptions!$C$217+Assumptions!$C$208))+(E53-Assumptions!$C$223)-E40-Assumptions!$C$190*(1+Assumptions!$C$191)^0 | F54: =E54+F51+F41-(F43-E43)+(F52-E52)+(F53-E53)-F40-Assumptions!$C$190*(1+Assumptions!$C$191)^1 | G54: =F54+G51+G41-(G43-F43)+(G52-F52)+(G53-F53)-G40-Assumptions!$C$190*(1+Assumptions!$C$191)^2 | H54: =G54+H51+H41-(H43-G43)+(H52-G52)+(H53-G53)-H40-Assumptions!$C$190*(1+Assumptions!$C$191)^3 | I54: =H54+I51+I41-(I43-H43)+(I52-H52)+(I53-H53)-I40-Assumptions!$C$190*(1+Assumptions!$C$191)^4
A55: Net debt | E55: =E44-E54 | F55: =F44-F54 | G55: =G44-G54 | H55: =H44-H54 | I55: =I44-I54

Sheet Cash Flow
A1: Cash flow — the free-cash-flow bridge and the movement in cash
A3: USD thousands | B3: FY2023 | C3: FY2024 | D3: FY2025 | E3: FY2026E | F3: FY2027E | G3: FY2028E | H3: FY2029E | I3: FY2030E
A4: Profit after tax | B4: ='Income Statement'!B14 | C4: ='Income Statement'!C14 | D4: ='Income Statement'!D14 | E4: ='Income Statement'!E14 | F4: ='Income Statement'!F14 | G4: ='Income Statement'!G14 | H4: ='Income Statement'!H14 | I4: ='Income Statement'!I14
A5: Depreciation and amortisation | B5: ='Balance Sheet'!B8 | C5: ='Balance Sheet'!C8 | D5: ='Balance Sheet'!D8 | E5: ='Balance Sheet'!E8 | F5: ='Balance Sheet'!F8 | G5: ='Balance Sheet'!G8 | H5: ='Balance Sheet'!H8 | I5: ='Balance Sheet'!I8
A6: Increase in working capital | E6: =-('Balance Sheet'!E33-'Balance Sheet'!D33-(Assumptions!$C$200+Assumptions!$C$201-Assumptions!$C$202)) | F6: =-('Balance Sheet'!F33-'Balance Sheet'!E33) | G6: =-('Balance Sheet'!G33-'Balance Sheet'!F33) | H6: =-('Balance Sheet'!H33-'Balance Sheet'!G33) | I6: =-('Balance Sheet'!I33-'Balance Sheet'!H33)
A7: Movement in provisions and tax payable | E7: =('Balance Sheet'!E25-'Balance Sheet'!D25-Assumptions!$C$208)+('Balance Sheet'!E26-'Balance Sheet'!D26) | F7: =('Balance Sheet'!F25-'Balance Sheet'!E25)+('Balance Sheet'!F26-'Balance Sheet'!E26) | G7: =('Balance Sheet'!G25-'Balance Sheet'!F25)+('Balance Sheet'!G26-'Balance Sheet'!F26) | H7: =('Balance Sheet'!H25-'Balance Sheet'!G25)+('Balance Sheet'!H26-'Balance Sheet'!G26) | I7: =('Balance Sheet'!I25-'Balance Sheet'!H25)+('Balance Sheet'!I26-'Balance Sheet'!H26)
A8: Net cash from operating activities | B8: 1355056 | C8: 1653666 | D8: 2225843 | E8: =E4+E5+E6+E7 | F8: =F4+F5+F6+F7 | G8: =G4+G5+G6+G7 | H8: =H4+H5+H6+H7 | I8: =I4+I5+I6+I7
A9: Capital expenditure | B9: =-'Balance Sheet'!B7 | C9: =-'Balance Sheet'!C7 | D9: =-'Balance Sheet'!D7 | E9: =-'Balance Sheet'!E7 | F9: =-'Balance Sheet'!F7 | G9: =-'Balance Sheet'!G7 | H9: =-'Balance Sheet'!H7 | I9: =-'Balance Sheet'!I7
A10: Net cash on the 2026 business combinations | E10: =Assumptions!$C$203-Assumptions!$C$211+Assumptions!$C$212 | F10: =0 | G10: =0 | H10: =0 | I10: =0
A11: Dividends paid | B11: -699559 | C11: -752452 | D11: -1143567 | E11: =-Assumptions!$C$190*(1+Assumptions!$C$191)^0 | F11: =-Assumptions!$C$190*(1+Assumptions!$C$191)^1 | G11: =-Assumptions!$C$190*(1+Assumptions!$C$191)^2 | H11: =-Assumptions!$C$190*(1+Assumptions!$C$191)^3 | I11: =-Assumptions!$C$190*(1+Assumptions!$C$191)^4
A12: Net movement in cash | E12: =E8+E9+E10+E11 | F12: =F8+F9+F10+F11 | G12: =G8+G9+G10+G11 | H12: =H8+H9+H10+H11 | I12: =I8+I9+I10+I11
A13: Opening cash | E13: =Assumptions!$C$221 | F13: =E14 | G13: =F14 | H13: =G14 | I13: =H14
A14: Closing cash | E14: =E13+E12 | F14: =F13+F12 | G14: =G13+G12 | H14: =H13+H12 | I14: =I13+I12
A15: Memo: free cash flow to the firm | E15: =('Income Statement'!E9*(1-Assumptions!$C$19))+E5+E9+E6 | F15: =('Income Statement'!F9*(1-Assumptions!$C$19))+F5+F9+F6 | G15: =('Income Statement'!G9*(1-Assumptions!$C$19))+G5+G9+G6 | H15: =('Income Statement'!H9*(1-Assumptions!$C$19))+H5+H9+H6 | I15: =('Income Statement'!I9*(1-Assumptions!$C$19))+I5+I9+I6

Sheet Summary Financials
A1: Summary financials — the eight-year picture on one page
A3: USD thousands unless stated | B3: FY2023 | C3: FY2024 | D3: FY2025 | E3: FY2026E | F3: FY2027E | G3: FY2028E | H3: FY2029E | I3: FY2030E
A4: Revenue | B4: ='Income Statement'!B4 | C4: ='Income Statement'!C4 | D4: ='Income Statement'!D4 | E4: ='Income Statement'!E4 | F4: ='Income Statement'!F4 | G4: ='Income Statement'!G4 | H4: ='Income Statement'!H4 | I4: ='Income Statement'!I4
A5: EBITDA | B5: ='Income Statement'!B5 | C5: ='Income Statement'!C5 | D5: ='Income Statement'!D5 | E5: ='Income Statement'!E5 | F5: ='Income Statement'!F5 | G5: ='Income Statement'!G5 | H5: ='Income Statement'!H5 | I5: ='Income Statement'!I5
A6: EBITDA margin | B6: ='Income Statement'!B6 | C6: ='Income Statement'!C6 | D6: ='Income Statement'!D6 | E6: ='Income Statement'!E6 | F6: ='Income Statement'!F6 | G6: ='Income Statement'!G6 | H6: ='Income Statement'!H6 | I6: ='Income Statement'!I6
A7: Profit after tax | B7: ='Income Statement'!B14 | C7: ='Income Statement'!C14 | D7: ='Income Statement'!D14 | E7: ='Income Statement'!E14 | F7: ='Income Statement'!F14 | G7: ='Income Statement'!G14 | H7: ='Income Statement'!H14 | I7: ='Income Statement'!I14
A8: Net margin | B8: ='Income Statement'!B15 | C8: ='Income Statement'!C15 | D8: ='Income Statement'!D15 | E8: ='Income Statement'!E15 | F8: ='Income Statement'!F15 | G8: ='Income Statement'!G15 | H8: ='Income Statement'!H15 | I8: ='Income Statement'!I15
A9: Capital expenditure | B9: ='Balance Sheet'!B7 | C9: ='Balance Sheet'!C7 | D9: ='Balance Sheet'!D7 | E9: ='Balance Sheet'!E7 | F9: ='Balance Sheet'!F7 | G9: ='Balance Sheet'!G7 | H9: ='Balance Sheet'!H7 | I9: ='Balance Sheet'!I7
A10: Net debt | B10: ='Balance Sheet'!B34 | C10: ='Balance Sheet'!C34 | D10: ='Balance Sheet'!D34 | E10: ='Balance Sheet'!E34 | F10: ='Balance Sheet'!F34 | G10: ='Balance Sheet'!G34 | H10: ='Balance Sheet'!H34 | I10: ='Balance Sheet'!I34
A11: Net debt / EBITDA | B11: ='Balance Sheet'!B35 | C11: ='Balance Sheet'!C35 | D11: ='Balance Sheet'!D35 | E11: ='Balance Sheet'!E35 | F11: ='Balance Sheet'!F35 | G11: ='Balance Sheet'!G35 | H11: ='Balance Sheet'!H35 | I11: ='Balance Sheet'!I35
A12: Total equity | B12: ='Balance Sheet'!B30 | C12: ='Balance Sheet'!C30 | D12: ='Balance Sheet'!D30 | E12: ='Balance Sheet'!E30 | F12: ='Balance Sheet'!F30 | G12: ='Balance Sheet'!G30 | H12: ='Balance Sheet'!H30 | I12: ='Balance Sheet'!I30
A13: Working capital | B13: ='Balance Sheet'!B33 | C13: ='Balance Sheet'!C33 | D13: ='Balance Sheet'!D33 | E13: ='Balance Sheet'!E33 | F13: ='Balance Sheet'!F33 | G13: ='Balance Sheet'!G33 | H13: ='Balance Sheet'!H33 | I13: ='Balance Sheet'!I33
A15: Return on invested capital | E15: =DCF!B35/('Balance Sheet'!E30+'Balance Sheet'!E34) | F15: =DCF!C35/('Balance Sheet'!F30+'Balance Sheet'!F34) | G15: =DCF!D35/('Balance Sheet'!G30+'Balance Sheet'!G34) | H15: =DCF!E35/('Balance Sheet'!H30+'Balance Sheet'!H34) | I15: =DCF!F35/('Balance Sheet'!I30+'Balance Sheet'!I34)

Sheet Monte Carlo
A1: Probability map — a whole-model re-run; these cells do NOT redraw when a driver changes
A2: Each figure below is the outcome of 50,000 simulated price paths struck on 07-Aug-2026. They are pasted because every one of them is a complete re-simulation, not an arithmetic function of a cell on the Assumptions sheet. Changing a valuation driver does not move them.
B4: One month | C4: Three months | D4: Note
A5: Check date | B5: 2026-09-07 | C5: 2026-11-09
A6: 5th percentile (AED) | B6: 5.2610531 | C6: 4.7440873
A7: 25th percentile (AED) | B7: 5.6680917 | C7: 5.448513
A8: 50th percentile (AED) | B8: 5.9377001 | C8: 5.9390345
A9: 75th percentile (AED) | B9: 6.2216015 | C9: 6.4718248
A10: 95th percentile (AED) | B10: 6.6884366 | C10: 7.4435682
A11: Probability of finishing above the current price | B11: 0.4976 | C11: 0.49956
A12: Probability of finishing 10% or more above | B12: 0.08798 | C12: 0.22738
A13: Probability of finishing 10% or more below | B13: 0.07288 | C13: 0.20606
A14: Probability of touching +10% at any point | B14: 0.14622 | C14: 0.41784
A15: Probability of touching -10% at any point | B15: 0.11776 | C15: 0.37572
A16: Probability of touching +20% at any point | B16: 0.01514 | C16: 0.15284
A17: Probability of touching -20% at any point | B17: 0.00514 | C17: 0.08854
A18: Annualised volatility at the anchor | B18: 0.27138216 | C18: 0.28422228

Sheet Sensitivity
A1: Sensitivity — whole-model re-runs; these grids do NOT redraw when a driver changes
A2: Each cell below is a complete revaluation of the model at a different pair of inputs, computed and pasted. They are the one place in this workbook where a number is not a live formula, and that is deliberate: a grid of full model re-runs cannot be expressed as arithmetic over a single set of driver cells.
A4: Discounted-cash-flow value (AED/share) — cost of capital against terminal growth
B5: 0.01 | C5: 0.015 | D5: 0.02 | E5: 0.025 | F5: 0.03
A6: 0.070017 | B6: 6.4276639 | C6: 6.7686017 | D6: 7.1758434 | E6: 7.6714822 | F6: 8.2886528
A7: 0.075017 | B7: 5.8956475 | C7: 6.168292 | D7: 6.4888367 | E7: 6.8716469 | F7: 7.3374698
A8: 0.080017 | B8: 5.439481 | C8: 5.6600744 | D8: 5.9159362 | E8: 6.2166819 | F8: 6.5757722
A9: 0.085017 | B9: 5.0440029 | C9: 5.2242275 | D9: 5.4308274 | E9: 5.6703947 | F9: 5.9519176
A10: 0.090017 | B10: 4.6978409 | C10: 4.8462873 | D10: 5.0147125 | E10: 5.2077257 | F10: 5.4314723
A13: EBITDA-margin shift (percentage points of revenue)
B14: -0.04 | C14: -0.02 | D14: 0 | E14: 0.02 | F14: 0.04
B15: 5.455912 | C15: 5.8363108 | D15: 6.2167096 | E15: 6.5971084 | F15: 6.9775071
A17: Equity beta
B18: 0.5 | C18: 0.664 | D18: 0.795 | E18: 0.9 | F18: 1.01
B19: 8.2559478 | C19: 6.989098 | D19: 6.2167096 | E19: 5.7056313 | F19: 5.2488372

Sheet Per-Share & Ratios
A1: Per-share figures and ratios — every cell a formula
A3: AED per share unless stated | B3: FY2023 | C3: FY2024 | D3: FY2025 | E3: FY2026E | F3: FY2027E | G3: FY2028E | H3: FY2029E | I3: FY2030E
A4: Earnings per share | B4: ='Income Statement'!B14/(Assumptions!$C$7-Assumptions!$C$8)*Assumptions!$C$6 | C4: ='Income Statement'!C14/(Assumptions!$C$7-Assumptions!$C$8)*Assumptions!$C$6 | D4: ='Income Statement'!D14/(Assumptions!$C$7-Assumptions!$C$8)*Assumptions!$C$6 | E4: ='Income Statement'!E14/(Assumptions!$C$7-Assumptions!$C$8)*Assumptions!$C$6 | F4: ='Income Statement'!F14/(Assumptions!$C$7-Assumptions!$C$8)*Assumptions!$C$6 | G4: ='Income Statement'!G14/(Assumptions!$C$7-Assumptions!$C$8)*Assumptions!$C$6 | H4: ='Income Statement'!H14/(Assumptions!$C$7-Assumptions!$C$8)*Assumptions!$C$6 | I4: ='Income Statement'!I14/(Assumptions!$C$7-Assumptions!$C$8)*Assumptions!$C$6
A5: Dividend per share | E5: =-'Cash Flow'!E11/(Assumptions!$C$7-Assumptions!$C$8)*Assumptions!$C$6 | F5: =-'Cash Flow'!F11/(Assumptions!$C$7-Assumptions!$C$8)*Assumptions!$C$6 | G5: =-'Cash Flow'!G11/(Assumptions!$C$7-Assumptions!$C$8)*Assumptions!$C$6 | H5: =-'Cash Flow'!H11/(Assumptions!$C$7-Assumptions!$C$8)*Assumptions!$C$6 | I5: =-'Cash Flow'!I11/(Assumptions!$C$7-Assumptions!$C$8)*Assumptions!$C$6
A6: Book value per share | B6: ='Balance Sheet'!B30/(Assumptions!$C$7-Assumptions!$C$8)*Assumptions!$C$6 | C6: ='Balance Sheet'!C30/(Assumptions!$C$7-Assumptions!$C$8)*Assumptions!$C$6 | D6: ='Balance Sheet'!D30/(Assumptions!$C$7-Assumptions!$C$8)*Assumptions!$C$6 | E6: ='Balance Sheet'!E30/(Assumptions!$C$7-Assumptions!$C$8)*Assumptions!$C$6 | F6: ='Balance Sheet'!F30/(Assumptions!$C$7-Assumptions!$C$8)*Assumptions!$C$6 | G6: ='Balance Sheet'!G30/(Assumptions!$C$7-Assumptions!$C$8)*Assumptions!$C$6 | H6: ='Balance Sheet'!H30/(Assumptions!$C$7-Assumptions!$C$8)*Assumptions!$C$6 | I6: ='Balance Sheet'!I30/(Assumptions!$C$7-Assumptions!$C$8)*Assumptions!$C$6
A7: Free cash flow per share | E7: ='Cash Flow'!E15/(Assumptions!$C$7-Assumptions!$C$8)*Assumptions!$C$6 | F7: ='Cash Flow'!F15/(Assumptions!$C$7-Assumptions!$C$8)*Assumptions!$C$6 | G7: ='Cash Flow'!G15/(Assumptions!$C$7-Assumptions!$C$8)*Assumptions!$C$6 | H7: ='Cash Flow'!H15/(Assumptions!$C$7-Assumptions!$C$8)*Assumptions!$C$6 | I7: ='Cash Flow'!I15/(Assumptions!$C$7-Assumptions!$C$8)*Assumptions!$C$6
A9: RATIOS AT THE CURRENT MARKET PRICE
A10: Price / earnings | B10: =Assumptions!$C$5/B4 | C10: =Assumptions!$C$5/C4 | D10: =Assumptions!$C$5/D4 | E10: =Assumptions!$C$5/E4 | F10: =Assumptions!$C$5/F4 | G10: =Assumptions!$C$5/G4 | H10: =Assumptions!$C$5/H4 | I10: =Assumptions!$C$5/I4
A11: Dividend yield | E11: =E5/Assumptions!$C$5 | F11: =F5/Assumptions!$C$5 | G11: =G5/Assumptions!$C$5 | H11: =H5/Assumptions!$C$5 | I11: =I5/Assumptions!$C$5
A12: Price / book | B12: =Assumptions!$C$5/B6 | C12: =Assumptions!$C$5/C6 | D12: =Assumptions!$C$5/D6 | E12: =Assumptions!$C$5/E6 | F12: =Assumptions!$C$5/F6 | G12: =Assumptions!$C$5/G6 | H12: =Assumptions!$C$5/H6 | I12: =Assumptions!$C$5/I6

Sheet Peer & Sector
A1: Peer and sector — third-party market data, used for cross-check and for the relative lens only
A2: Every figure on this sheet belongs to another company. Nothing here enters ADNOC Drilling's own income statement, balance sheet or cash flow — those are built exclusively from its own audited filings. Prices are at the close on 07-Aug-2026; balance-sheet and earnings figures are each peer's own latest reported period.
A4: Group | B4: Company | C4: Market cap (USD mn) | D4: Net debt (USD mn) | E4: Enterprise value (USD mn) | F4: Last 12 months EBITDA (USD mn) | G4: EV / EBITDA | H4: Latest period
A5: MENA NOC-contracted driller | B5: ADES Holding | C5: 5167.4197 | D5: 4813.9656 | E5: =C5+D5 | F5: 976.1512 | G5: =E5/F5 | H5: 2026-03-31
A6: MENA NOC-contracted driller | B6: Arabian Drilling | C6: 1960.3733 | D6: 626.85033 | E6: =C6+D6 | F6: 295.61052 | G6: =E6/F6 | H6: 2026-03-31
A7: Global land driller | B7: Helmerich & Payne | C7: 3706.9394 | D7: 1657.689 | E7: =C7+D7 | F7: 794.456 | G7: =E7/F7 | H7: 2026-06-30
A8: Global land driller | B8: Nabors Industries | C8: 1207.6136 | D8: 1618.75 | E8: =C8+D8 | F8: 1308.166 | G8: =E8/F8 | H8: 2026-06-30
A9: Global land driller | B9: Patterson-UTI | C9: 3764.2236 | D9: 1084.557 | E9: =C9+D9 | F9: 872.833 | G9: =E9/F9 | H9: 2026-06-30
A10: Global land driller | B10: Precision Drilling | C10: 973.58778 | D10: 630.732 | E10: =C10+D10 | F10: 228.669 | G10: =E10/F10 | H10: 2026-06-30
A11: Global offshore driller | B11: Valaris | C11: 5455.6552 | D11: 624.3 | E11: =C11+D11 | F11: 606.3 | G11: =E11/F11 | H11: 2026-06-30
A12: Global offshore driller | B12: Noble Corporation | C12: 6508.5728 | D12: 1432.222 | E12: =C12+D12 | F12: 928.575 | G12: =E12/F12 | H12: 2026-06-30
A13: Global offshore driller | B13: Borr Drilling | C13: 1187.7261 | D13: 2058.9 | E13: =C13+D13 | F13: 452 | G13: =E13/F13 | H13: 2026-03-31
A14: Diversified oilfield services | B14: SLB | C14: 74993.757 | D14: 10055 | E14: =C14+D14 | F14: 6663 | G14: =E14/F14 | H14: 2026-06-30
A15: Diversified oilfield services | B15: Halliburton | C15: 26596.26 | D15: 6151 | E15: =C15+D15 | F15: 3592 | G15: =E15/F15 | H15: 2026-06-30
A16: Diversified oilfield services | B16: Baker Hughes | C16: 61077.727 | D16: 526 | E16: =C16+D16 | F16: 5080 | G16: =E16/F16 | H16: 2026-06-30
A17: Diversified oilfield services | B17: Weatherford Intl | C17: 6233.676 | D17: 522 | E17: =C17+D17 | F17: 848 | G17: =E17/F17 | H17: 2026-06-30
A19: ADNOC Drilling at the market price | B19: ADNOC Drilling | C19: =DCF!$C$19/1000 | D19: =DCF!$C$20/1000 | E19: =C19+D19 | F19: =Assumptions!$C$252/1000 | G19: =E19/F19
