Workbook

Sheet READ FIRST
A1: READ FIRST | B1: Egyptian International Pharmaceutical Industries Company (EIPICO)
A2: What this workbook is | B2: An educational valuation model of a listed Egyptian pharmaceutical manufacturer, built from the company's own audited financial statements. It is not investment advice, it contains no rating and no price target, and it expresses value as a range.
A3: THE WORKBOOK CALCULATES | B3: Every figure that can be derived from a driver is a live formula. Change a driver on the Assumptions sheet and the cost of capital, the glide, the discount factors, the cash-flow waterfall, the terminal block, the three statements, the bridge and every ratio all move. This claim is tested, not asserted: a driver test perturbs each input in place, re-evaluates the whole workbook and checks the headline moves in the right direction.
A4: Pasted cell class 1 of 4 — audited and disclosed history | B4: The FY2023, FY2024 and FY2025 columns of the Income Statement, Balance Sheet and Cash Flow sheets, and the disclosed operating statistics on Segments. Where a line is both disclosed and derivable, the DISCLOSED figure is carried. Blue type marks a pasted cell.
A5: Pasted cell class 2 of 4 — the unit build's output | B5: The FY2024 and FY2025 pack volumes and realised prices per pack on the Segments sheet. These come from reconciling the board's disclosed pack counts against the revenue note's channel split; flattened into a grid the reconciliation would be unreadable. Everything downstream of them — every forecast year — is a formula.
A6: Pasted cell class 3 of 4 — whole-model re-runs | B6: The Monte Carlo percentile map and touch ladder, and the Sensitivity grids. Each of those cells is a COMPLETE revaluation of the model at a different input, or a full 50,000-path simulation. THEY DO NOT REDRAW WHEN A DRIVER CHANGES. Everything else on those two sheets is a formula.
A7: Pasted cell class 4 of 4 — the measured-error multipliers | B7: The factors behind the far-year ranges at the foot of the Income Statement sheet. They are a measurement of how far this method's own projections have landed from what the company later reported, so they are an observation and not something the model can derive. The ranges they produce ARE formulas and move with the projection above them.
A8: Blue means input, black means formula | B8: Blue type is a pasted number. Black type is calculated in the sheet.
A9: The contested judgement is carried both ways | B9: The credit-loss and provision charge is the study's single most consequential contested judgement. Frame A treats it as a permanent cost of doing business; Frame B treats it as normalising. Both run all the way through to a value per share and both are published. They are never averaged into one number.
A10: Currency and units | B10: Egyptian pounds. Money in millions unless a row says otherwise; per-share figures in pounds; packs and units in millions.
A11: Basis and date | B11: Audited CONSOLIDATED financial statements. Share price 127.30 at 2026-09-03; 168.755750 million shares in issue. Fiscal year ends 31 December.

Sheet Summary
A1: SUMMARY VALUATION TABLE | B1: EGP / share | C1: Against the market price | D1: Note
A2: Discounted cash flow — Frame A | B2: ='Fundamental Valuation'!B2 | C2: =B2/Assumptions!$C$3-1 | D2: Terminal value 79% of core enterprise value, 61% of total
A3: Discounted cash flow — Frame B | B3: ='Fundamental Valuation'!B3 | C3: =B3/Assumptions!$C$3-1 | D3: Terminal value 79% of core enterprise value, 64% of total
A4: Book value and sustainable return | B4: ='Fundamental Valuation'!B4 | C4: =B4/Assumptions!$C$3-1 | D4: Justified 1.16 times book
A5: Relative multiples | B5: ='Fundamental Valuation'!B5 | C5: =B5/Assumptions!$C$3-1 | D5: Three multiples averaged on the sheet
A6: Normalised earnings power | B6: ='Fundamental Valuation'!B6 | C6: =B6/Assumptions!$C$3-1 | D6: Three-year average margin
A7: CENTRE — FRAME A (the cash-flow lens, unweighted) | B7: ='Fundamental Valuation'!B7 | C7: =B7/Assumptions!$C$3-1 | D7: A range, not a target. No rating is expressed anywhere in this workbook.
A8: CENTRE — FRAME B (the cash-flow lens, unweighted) | B8: ='Fundamental Valuation'!B8 | C8: =B8/Assumptions!$C$3-1 | D8: TWO CENTRES, NEVER AVERAGED INTO ONE. Which one you use is a judgement about the debtor book, and it is yours to make rather than ours to bury.
A9: Field low to field high | B9: ='Fundamental Valuation'!B10 | C9: ='Fundamental Valuation'!B11
A10: Market price | B10: =Assumptions!$C$3
A12: KEY FIGURES
A13: Market capitalisation (EGP mn) | B13: =Assumptions!$C$103
A14: Net debt (EGP mn) | B14: =Assumptions!$C$104
A15: Enterprise value (EGP mn) | B15: =Assumptions!$C$103+Assumptions!$C$104+Assumptions!$C$80
A16: FY2025 revenue (EGP mn) | B16: ='Income Statement'!D2
A17: FY2025 EBITDA (EGP mn) | B17: ='Income Statement'!D17
A18: FY2025 attributable profit (EGP mn) | B18: ='Income Statement'!D26
A19: Trailing price / earnings | B19: =Assumptions!$C$3/('Income Statement'!D26/Assumptions!$C$8)
A20: Trailing enterprise value / EBITDA | B20: =(Assumptions!$C$103+Assumptions!$C$104+Assumptions!$C$80)/'Income Statement'!D17
A21: Cost of equity | B21: =Assumptions!$C$98
A22: Weighted average cost of capital, year one | B22: =Assumptions!$C$107
A23: Terminal weighted average cost of capital | B23: =Assumptions!$C$113
A24: Terminal value as a percentage of enterprise value | B24: =DCF!B34
A25: Dividend per share proposed for FY2025 (EGP) | B25: 3.5
A26: Dividend yield at the market price | B26: =B25/Assumptions!$C$3

Sheet Fundamental Valuation
A1: Lens | B1: Value (EGP/share) | C1: Weight | D1: How it is built
A2: Discounted cash flow — Frame A (provision charge permanent) | B2: =('SOTP Bridge'!B11)/Assumptions!$C$8 | C2: 0.5 | D2: Five explicit years of free cash flow to the firm, discounted on a glide from the current to the terminal cost of capital, plus a terminal value on the growth-over-return reinvestment identity.
A3: Discounted cash flow — Frame B (provision charge normalising) | B3: =DCF!B47 | C3: 0.5 | D3: The identical model with the single contested judgement resolved the other way. Published beside Frame A, never averaged into it.
A4: Book value and sustainable return | B4: =(('Relative & Normalized'!B6-Assumptions!$C$62)/(Assumptions!$C$110-Assumptions!$C$62))*'Balance Sheet'!D20 | C4: 0.2 | D4: Book value per share multiplied by (sustainable return less growth) over (perpetual cost of equity less growth). EVERY term is live: the sustainable return reads the forecast return-on-equity path, and the perpetual cost of equity reads beta, the terminal risk-free rate and the terminal premium.
A5: Relative multiples | B5: ='Relative & Normalized'!C29 | C5: 0.15 | D5: Three multiples triangulated ON the sheet, EACH APPLIED TO THE EARNINGS OF ITS OWN PERIOD — the forward multiple this model's own economics justify on forward earnings, and the company's own four-year mean and a cost-of-equity-adjusted struck peer reference on trailing earnings.
A6: Normalised earnings power | B6: ='Relative & Normalized'!B37 | C6: 0.15 | D6: The three-year average operating margin applied to forecast revenue, capitalised at the perpetual cost of equity on the payout that the growth rate permits.
A7: CENTRE — FRAME A (the cash-flow lens, unweighted) | B7: =B2 | D7: The centre of each frame IS its own cash-flow read. The three lenses that do not turn on the contested judgement are published beside it and averaged into neither.
A8: CENTRE — FRAME B (the cash-flow lens, unweighted) | B8: =B3 | D8: THE TWO CENTRES ARE NOT AVERAGED. One number covering both frames is a straight average of them, which is exactly what this study says it never does.
A9: Memo — the retired weighted blend this edition replaced, on Frame A | B9: =B2*C2+B4*C4+B5*C5+B6*C6 | D9: Printed so the change is visible rather than only described. Its weights had never been tested out of sample, and one of the four readings it carried is not a lens this class uses at all.
A10: Low of the field | B10: =MIN(B2:B6)
A11: High of the field | B11: =MAX(B2:B6)
A12: Market price | B12: =Assumptions!$C$3
A13: Market price relative to the Frame A centre | B13: =B12/B7-1
A14: Market price relative to the Frame B centre | B14: =B12/B8-1

Sheet Assumptions
A1: Driver | B1: Basis | C1: FY2026E | D1: FY2027E | E1: FY2028E | F1: FY2029E | G1: FY2030E
A2: ANCHORS
A3: Share price (EGP) | B3: Last close of the uploaded exchange price history, 2026-09-03 | C3: 127.3
A4: Shares in issue at 31 December 2022 (million) | B4: Board report, capital and shareholders table | C4: 99.1705
A5: Shares in issue, FY2023 and FY2024 (million) | B5: Board report | C5: 148.75575
A6: Weighted-average shares, FY2025 (million) | B6: Audited — the capital increase completed during the year | C6: 162.01602
A7: Attributable profit, FY2022 (EGP mn) | B7: Board report, eleven-year profit table | C7: 587.04062
A8: Shares in issue (million) | B8: Capital note (13): issued capital of EGP 1,687,557,500 at EGP 10 nominal a share | C8: 168.75575
A9: Corporate income tax rate | B9: Egyptian statutory rate | C9: 0.225
A10: Effective tax rate on forecast pre-tax profit | B10: Above statutory to allow for the solidarity contribution and disallowed items | C10: 0.235
A11: VOLUME AND PRICE
A12: Domestic pack volume growth | B12: Not capacity-constrained at 65% utilisation | C12: 0.055 | D12: 0.08 | E12: 0.075 | F12: 0.065 | G12: 0.055
A13: Export pack volume growth | B13: Hard-currency export growth was 10% in FY2025 | C13: 0.05 | D13: 0.09 | E13: 0.085 | F13: 0.08 | G13: 0.07
A14: Domestic price per pack growth | B14: Administered prices track inflation, no real gain | C14: 0.05 | D14: 0.08 | E14: 0.075 | F14: 0.065 | G14: 0.055
A15: Export price per pack growth (USD) | B15: Competitive generic export pricing | C15: 0.01 | D15: 0.01 | E15: 0.01 | F15: 0.01 | G15: 0.01
A16: Contract-manufacturing revenue growth | B16: Small line, idle-capacity utilisation | C16: 0.15 | D16: 0.12 | E16: 0.1 | F16: 0.08 | G16: 0.07
A17: Exchange rate (EGP per USD, period average) | B17: Partial real-rate reversal as domestic inflation converges | C17: 55.1141 | D17: 60.2223 | E17: 64.0413 | F17: 67.1652 | G17: 70.1139
A18: COST STACK — ONE ESCALATOR PER DRIVER CLASS
A19: Cost share: imported active ingredients | B19: Cost of sales note (26) | C19: 0.5488
A20: Cost share: packaging materials | B20: Cost of sales note (26) | C20: 0.2456
A21: Cost share: labour | B21: Cost of sales note (26), wages plus benefits plus social insurance | C21: 0.0977
A22: Cost share: energy and utilities | B22: Cost of sales note (26) | C22: 0.0342
A23: Cost share: other consumables and services | B23: Cost of sales note (26) | C23: 0.0571
A24: Cost share: depreciation | B24: disclosure — the audited split is shown for completeness, but depreciation is EXCLUDED from the escalated unit cost by design and enters exactly once, from the property roll-forward. This row drives nothing and is meant to drive nothing | C24: 0.0166
A25: Escalator: hard-currency ingredient price | B25: Applied THROUGH the exchange-rate path, never a domestic index | C25: 0.02
A26: Imported share of the packaging line | B26: The balance is made in-house | C26: 0.55
A27: Escalator: Egyptian wages | B27: Minimum-wage resets run above consumer prices | C27: 0.14 | D27: 0.12 | E27: 0.1 | F27: 0.085 | G27: 0.075
A28: Escalator: regulated energy tariffs | B28: Subsidy reform, ABOVE consumer prices | C28: 0.18 | D28: 0.15 | E28: 0.12 | F28: 0.1 | G28: 0.08
A29: Escalator: domestic consumer prices | B29: Applied only to genuinely domestic lines | C29: 0.16 | D29: 0.12 | E29: 0.09 | F29: 0.075 | G29: 0.07
A30: OPERATING EXPENSE, CAPITAL AND WORKING CAPITAL
A31: Selling and marketing / revenue | B31: Disclosed 12.9% -> 12.4% -> 10.7% | C31: 0.104 | D31: 0.102 | E31: 0.1 | F31: 0.099 | G31: 0.098
A32: Research and development / revenue | B32: Rising with the biosimilar pipeline | C32: 0.0085 | D32: 0.009 | E32: 0.0095 | F32: 0.01 | G32: 0.01
A33: General and administrative / revenue | B33: Held near the FY2025 level | C33: 0.0235 | D33: 0.0235 | E33: 0.023 | F33: 0.0228 | G33: 0.0225
A34: FRAME A — provision charge / revenue | B34: Permanent, at the three-year average | C34: 0.0525 | D34: 0.0525 | E34: 0.0525 | F34: 0.0525 | G34: 0.0525
A35: FRAME B — provision charge / revenue | B35: Normalising as the book seasons | C35: 0.045 | D35: 0.038 | E35: 0.032 | F35: 0.028 | G35: 0.025
A36: Capital expenditure / revenue | B36: Falls as the construction cycle completes | C36: 0.125 | D36: 0.045 | E36: 0.035 | F36: 0.032 | G36: 0.03
A37: Transfers out of construction (EGP mn) | B37: The plant was licensed in December 2025 and enters service | C37: 3400 | D37: 1100 | E37: 400 | F37: 200 | G37: 200
A38: Depreciation rate on the property base | B38: About a sixteen-year blended life | C38: 0.062
A39: Inventory days | B39: An eight-month strategic stockpile, stated policy | C39: 265 | D39: 258 | E39: 250 | F39: 245 | G39: 240
A40: Receivable days | B40: Distributor-concentrated book plus export terms | C40: 126 | D40: 122 | E40: 118 | F40: 115 | G40: 112
A41: Payable days | B41: Audited FY2025 implies 54 days | C41: 55 | D41: 56 | E41: 57 | F41: 58 | G41: 58
A42: Dividend payout ratio | B42: EGP 3.50 a share proposed for FY2025 on attributable profit | C42: 0.4
A43: COST OF CAPITAL
A44: Ten-year local-currency government yield | B44: House cost-of-capital reference print | C44: 0.23
A45: Sovereign credit-default-swap spread | B45: Country risk-premium file, Egypt row, read live | C45: 0.0342
A46: Country equity risk premium (swap basis) | B46: Same file, same row | C46: 0.095164
A47: Adjusted default spread (rating basis) | B47: Same file — the alternative | C47: 0.059702
A48: Country equity risk premium (rating basis) | B48: Same file — the alternative | C48: 0.134806
A49: Beta | B49: Own-stock weekly regression against a 36-name local composite, five years; R-squared 0.235, n = 257 | C49: 0.66581884
A50: Cost of local-currency debt | B50: Sovereign yield plus 250 basis points | C50: 0.255
A51: Hard-currency coupon | B51: Dollar and euro term loans | C51: 0.075
A52: Expected currency depreciation for the debt charge | B52: Carries foreign-currency debt at its LOCAL-EQUIVALENT cost | C52: 0.045
A53: Hard-currency share of the term-loan book | B53: Borrowings note (17), by lender and currency | C53: 0.50203241
A54: Normalised risk-free convergence path | B54: NOT a cost of debt: the first point is the normalised risk-free rate. Only the SHAPE of this row enters the model — the discount-rate glide rebases it to its own endpoints, so the levels cancel | C54: 0.189 | D54: 0.178 | E54: 0.166 | F54: 0.156 | G54: 0.148
A55: Finance cost charged to profit (EGP mn) | B55: What the profit and loss account actually bears — NOT the marginal cost of debt above. Calibrated to the first quarter of 2026 | C55: 1250 | D55: 1210 | E55: 1150 | F55: 1090 | G55: 1030
A56: Terminal risk-free rate | B56: A sourced 5% medium-term inflation target plus an UNSOURCED 5.5-point real convention. The real leg is an assertion, it is the widest single lever in the study, and it is an open item — see the terminal grid | C56: 0.125
A57: Terminal equity risk premium | B57: Normalised toward the rating-class norm | C57: 0.07
A58: Terminal local-currency borrowing rate | B58: Long-run Egyptian norm | C58: 0.15
A59: Terminal hard-currency coupon | B59: Long-run norm | C59: 0.065
A60: Terminal debt weight — DERIVED, market-value basis | B60: Today's net debt over market capitalisation plus net debt. Not an assumption; the earlier edition's 20% was neither this nor the book reading below | C60: 0.25528904
A61: Terminal debt weight — the funded forecast balance sheet at FY2030E | B61: disclosure — the BOOK reading, published beside the market reading above rather than chosen between in silence. The valuation uses the market reading, because a weighted average cost of capital weights market values; this row drives nothing | C61: 0.4792091
A62: Terminal growth | B62: Pound-nominal, against a 5% terminal inflation rate — about zero in real terms | C62: 0.07
A63: Normalised associate contribution (EGP mn) | B63: Three disclosed years, reconciled to this model's own income statement: 74.508, 151.581, 512.085 — mean 246.058. The first quarter of 2026 annualises to 52.5, but the auditor states two holdings' statements were not received, so that quarter is evidence, not a run-rate | C63: 250
A64: Associate earnings multiple | B64: Below the Gulf listed range for a minority, unlisted, non-controlled stake | C64: 11
A65: Struck peer reference price-earnings multiple | B65: MARKET DATA, cross-check layer. The MIDPOINT of the only two disclosed observations (26.7x and 16.0x) — NOT a median of a peer set, and the peers are not named, so it cannot be rebuilt from their filings | C65: 21.35
A66: Cost of equity faced by the struck reference companies | B66: The ONE difference the peer multiple is adjusted for, registered here rather than typed inside the adjustment so a reader can see what the adjustment is made of | C66: 0.1
A67: OPENING BALANCE SHEET (AUDITED, 31 DECEMBER 2025)
A68: Property, plant and equipment, net | B68: Note (4) | C68: 3069.7479
A69: Projects under construction | B69: Note (6) | C69: 4901.2238
A70: Inventories, net | B70: Note (9) | C70: 3887.0776
A71: Trade and notes receivable, net | B71: Note (10) | C71: 3325.0441
A72: Other debtors | B72: Note (11) | C72: 356.78696
A73: Trade and notes payable | B73: Note (22) | C73: 780.41697
A74: Other creditors | B74: Note (23) | C74: 1044.8323
A75: Cash and bank balances | B75: Note (12) | C75: 1433.4269
A76: Gross borrowings including leases | B76: Notes (17), (18) and (21) | C76: 8797.7256
A77: Attributable profit, FY2025 (EGP mn) | B77: Audited — the trailing earnings base for every trailing multiple | C77: 1441.6577
A78: Equity attributable to the holding company | B78: Audited | C78: 6243.1315
A79: Non-controlling interests, audited 31 December 2025 | B79: disclosure — the audited December figure, shown so the reader can see both. It is SUPERSEDED for valuation by the March figure below, because almost all of it was the active-ingredient company and that company was deconsolidated in the first quarter of 2026. This row drives the balance sheet history only | C79: 288.70461
... A95: FY2025 average exchange rate | B95: Note (36) | C95: 49.48
A96: DERIVED IN THIS SHEET (formulas, not inputs)
A97: Normalised risk-free rate = yield less sovereign spread | B97: calculated | C97: =$C$44-$C$45
A98: Cost of equity = normalised risk-free + beta x premium | B98: calculated | C98: =$C$97+$C$49*$C$46
A99: Cost of equity, rating basis (published alternative) | B99: calculated | C99: =($C$44-$C$47)+$C$49*$C$48
A100: Hard-currency debt at LOCAL-EQUIVALENT cost | B100: calculated | C100: =(1+$C$51)*(1+$C$52)-1
A101: Blended marginal cost of debt | B101: calculated | C101: =(1-$C$53)*$C$50+$C$53*$C$100
A102: Cost of debt after tax | B102: calculated | C102: =$C$101*(1-$C$9)
A103: Market capitalisation (EGP mn) | B103: calculated | C103: =$C$3*$C$8
A104: Net debt (EGP mn) | B104: calculated | C104: =$C$76-$C$75
A105: Equity weight (net basis) | B105: calculated | C105: =$C$103/($C$103+$C$104)
A106: Debt weight (net basis) | B106: calculated | C106: =1-$C$105
A107: Weighted average cost of capital, year one | B107: calculated | C107: =$C$105*$C$98+$C$106*$C$102
A108: Debt weight (gross basis) | B108: calculated | C108: =$C$76/($C$103+$C$76)
A109: Weighted average cost of capital, gross-debt basis | B109: calculated | C109: =(1-$C$108)*$C$98+$C$108*$C$102
A110: Terminal cost of equity | B110: calculated | C110: =$C$56+$C$49*$C$57
A111: Terminal cost of debt | B111: calculated | C111: =(1-$C$53)*$C$58+$C$53*((1+$C$59)*1.03-1)
A112: Terminal cost of debt after tax | B112: calculated | C112: =$C$111*(1-$C$9)
A113: Terminal weighted average cost of capital | B113: calculated | C113: =(1-$C$60)*$C$110+$C$60*$C$112
A114: Glide fraction (derived from the convergence path — SHAPE only) | B114: calculated: (this year's cost of debt less the last year's) over (the first year's less the last year's) | C114: =(C$54-$G$54)/($C$54-$G$54) | D114: =(D$54-$G$54)/($C$54-$G$54) | E114: =(E$54-$G$54)/($C$54-$G$54) | F114: =(F$54-$G$54)/($C$54-$G$54) | G114: =(G$54-$G$54)/($C$54-$G$54)
A115: Discount rate | B115: calculated: terminal rate plus the glide fraction of the gap to year one | C115: =$C$113+($C$107-$C$113)*C$114 | D115: =$C$113+($C$107-$C$113)*D$114 | E115: =$C$113+($C$107-$C$113)*E$114 | F115: =$C$113+($C$107-$C$113)*F$114 | G115: =$C$113+($C$107-$C$113)*G$114
...

Sheet SOTP Bridge
A1: Enterprise value to equity value bridge | B1: EGP million | C1: EGP / share
A2: Core enterprise value — discounted cash flow of the operating business | B2: =DCF!B33 | C2: =B2/Assumptions!$C$8
A3: of which the terminal value (memorandum) | B3: =DCF!B30 | C3: =B3/Assumptions!$C$8
A4: terminal value as a percentage of core enterprise value | B4: =DCF!B34
A5: Add: earning associates at normalised earnings x the multiple | B5: =Assumptions!$C$63*Assumptions!$C$64 | C5: =B5/Assumptions!$C$8
A6: Add: the pre-revenue active-ingredient company at carrying cost | B6: =Assumptions!$C$81 | C6: =B6/Assumptions!$C$8
A7: Add: assets held for sale | B7: =Assumptions!$C$82 | C7: =B7/Assumptions!$C$8
A8: TOTAL ENTERPRISE VALUE | B8: =B2+B5+B6+B7 | C8: =B8/Assumptions!$C$8
A9: Less: net debt | B9: =-Assumptions!$C$104 | C9: =B9/Assumptions!$C$8
A10: Less: non-controlling interests, post-deconsolidation | B10: =-Assumptions!$C$80 | C10: =B10/Assumptions!$C$8
A11: EQUITY VALUE | B11: =B8+B9+B10 | C11: =B11/Assumptions!$C$8
A13: Value per share — Frame A | B13: =B11 | C13: =B13/Assumptions!$C$8

Sheet Segments
A1: Volume and price build | B1: FY2024 | C1: FY2025 | D1: FY2026E | E1: FY2027E | F1: FY2028E | G1: FY2029E | H1: FY2030E
A2: Domestic packs sold (million) | B2: 244.272 | C2: =Assumptions!$C$88-Assumptions!$C$89 | D2: =C2*(1+Assumptions!C$12) | E2: =D2*(1+Assumptions!D$12) | F2: =E2*(1+Assumptions!E$12) | G2: =F2*(1+Assumptions!F$12) | H2: =G2*(1+Assumptions!G$12)
A3: Export packs sold (million) | B3: 54.7 | C3: =Assumptions!$C$89 | D3: =C3*(1+Assumptions!C$13) | E3: =D3*(1+Assumptions!D$13) | F3: =E3*(1+Assumptions!E$13) | G3: =F3*(1+Assumptions!F$13) | H3: =G3*(1+Assumptions!G$13)
A4: Domestic realised price per pack (EGP) — own preparations only | B4: =B7/B2 | C4: =C7/C2 | D4: =C4*(1+Assumptions!C$14) | E4: =D4*(1+Assumptions!D$14) | F4: =E4*(1+Assumptions!E$14) | G4: =F4*(1+Assumptions!F$14) | H4: =G4*(1+Assumptions!G$14)
A5: Export realised price per pack (USD) | B5: =B8/B3/B6 | C5: =C8/C3/C6 | D5: =C5*(1+Assumptions!C$15) | E5: =D5*(1+Assumptions!D$15) | F5: =E5*(1+Assumptions!E$15) | G5: =F5*(1+Assumptions!F$15) | H5: =G5*(1+Assumptions!G$15)
A6: Exchange rate (EGP per USD) | B6: 47.74 | C6: 49.48 | D6: =Assumptions!C$17 | E6: =Assumptions!D$17 | F6: =Assumptions!E$17 | G6: =Assumptions!F$17 | H6: =Assumptions!G$17
A7: Domestic revenue, own preparations (EGP mn) | B7: =7104.16-B8 | C7: =Assumptions!$C$91-C8 | D7: =D2*D4 | E7: =E2*E4 | F7: =F2*F4 | G7: =G2*G4 | H7: =H2*H4
A8: Export revenue (EGP mn) | B8: 2500.1559 | C8: =Assumptions!$C$90 | D8: =D3*D5*D6 | E8: =E3*E5*E6 | F8: =F3*F5*F6 | G8: =G3*G5*G6 | H8: =H3*H5*H6
A9: Contract-manufactured packs (million) | B9: 8.874 | C9: =Assumptions!$C$93 | D9: =C9*(1+Assumptions!C$16) | E9: =D9*(1+Assumptions!D$16) | F9: =E9*(1+Assumptions!E$16) | G9: =F9*(1+Assumptions!F$16) | H9: =G9*(1+Assumptions!G$16)
A10: Contract-manufacturing FEE per pack (EGP) | B10: =35.835829/B9 | C10: =Assumptions!$C$94/C9 | D10: =C10*(1+Assumptions!C$14) | E10: =D10*(1+Assumptions!D$14) | F10: =E10*(1+Assumptions!E$14) | G10: =F10*(1+Assumptions!F$14) | H10: =G10*(1+Assumptions!G$14)
A11: Contract product resold through own channels, per pack (EGP) | B11: =(259.912-35.835829)/B9 | C11: =(Assumptions!$C$92-Assumptions!$C$94)/C9 | D11: =C11*(1+Assumptions!C$14) | E11: =D11*(1+Assumptions!D$14) | F11: =E11*(1+Assumptions!E$14) | G11: =F11*(1+Assumptions!F$14) | H11: =G11*(1+Assumptions!G$14)
A12: Contract-manufacturing revenue — fee (EGP mn) | B12: =B9*B10 | C12: =C9*C10 | D12: =D9*D10 | E12: =E9*E10 | F12: =F9*F10 | G12: =G9*G10 | H12: =H9*H10
A13: Contract product resold through own channels (EGP mn) | B13: =B9*B11 | C13: =C9*C11 | D13: =D9*D11 | E13: =E9*E11 | F13: =F9*F11 | G13: =G9*G11 | H13: =H9*H11
A14: Total packs sold (million) | B14: 307.846 | C14: 357.295 | D14: =D2+D3+D9 | E14: =E2+E3+E9 | F14: =F2+F3+F9 | G14: =G2+G3+G9 | H14: =H2+H3+H9
A15: REVENUE, consolidated (EGP mn) | B15: 7590.5456 | C15: 9441.3793 | D15: =(D7+D8+D12+D13)*Assumptions!$C$87 | E15: =(E7+E8+E12+E13)*Assumptions!$C$87 | F15: =(F7+F8+F12+F13)*Assumptions!$C$87 | G15: =(G7+G8+G12+G13)*Assumptions!$C$87 | H15: =(H7+H8+H12+H13)*Assumptions!$C$87
A17: DISCLOSED CAPACITY AND UTILISATION
A18: Units produced (million) | B18: 2143.68 | C18: 2207.95
A19: Available capacity (million units) | B19: 3383.06 | C19: 3383.06
A20: Capacity utilisation | B20: =B18/B19 | C20: =C18/C19
A21: Registered preparations produced | B21: 401 | C21: 414
A22: Average headcount | B22: 4880 | C22: 4981
A23: Revenue per employee (EGP) | B23: =B15*1000000/B22 | C23: =C15*1000000/C22
A25: COST ESCALATOR INDEX (base FY2025 = 1.000)
A26: Imported active ingredients | D26: =((1+Assumptions!$C$25)*(Segments!D6/Assumptions!$C$95)) | E26: =D26*((1+Assumptions!$C$25)*(Segments!E6/Segments!D6)) | F26: =E26*((1+Assumptions!$C$25)*(Segments!F6/Segments!E6)) | G26: =F26*((1+Assumptions!$C$25)*(Segments!G6/Segments!F6)) | H26: =G26*((1+Assumptions!$C$25)*(Segments!H6/Segments!G6))
A27: Packaging materials | D27: =(Assumptions!$C$26*(1+Assumptions!$C$25)*(Segments!D6/Assumptions!$C$95)+(1-Assumptions!$C$26)*(1+Assumptions!C$29)) | E27: =D27*(Assumptions!$C$26*(1+Assumptions!$C$25)*(Segments!E6/Segments!D6)+(1-Assumptions!$C$26)*(1+Assumptions!D$29)) | F27: =E27*(Assumptions!$C$26*(1+Assumptions!$C$25)*(Segments!F6/Segments!E6)+(1-Assumptions!$C$26)*(1+Assumptions!E$29)) | G27: =F27*(Assumptions!$C$26*(1+Assumptions!$C$25)*(Segments!G6/Segments!F6)+(1-Assumptions!$C$26)*(1+Assumptions!F$29)) | H27: =G27*(Assumptions!$C$26*(1+Assumptions!$C$25)*(Segments!H6/Segments!G6)+(1-Assumptions!$C$26)*(1+Assumptions!G$29))
A28: Labour | D28: =(1+Assumptions!C$27) | E28: =D28*(1+Assumptions!D$27) | F28: =E28*(1+Assumptions!E$27) | G28: =F28*(1+Assumptions!F$27) | H28: =G28*(1+Assumptions!G$27)
A29: Energy and utilities | D29: =(1+Assumptions!C$28) | E29: =D29*(1+Assumptions!D$28) | F29: =E29*(1+Assumptions!E$28) | G29: =F29*(1+Assumptions!F$28) | H29: =G29*(1+Assumptions!G$28)
A30: Other consumables and services | D30: =(1+Assumptions!C$29) | E30: =D30*(1+Assumptions!D$29) | F30: =E30*(1+Assumptions!E$29) | G30: =F30*(1+Assumptions!F$29) | H30: =G30*(1+Assumptions!G$29)
A31: Blended cash-cost index | D31: =(Assumptions!$C$19*D26+Assumptions!$C$20*D27+Assumptions!$C$21*D28+Assumptions!$C$22*D29+Assumptions!$C$23*D30)/(Assumptions!$C$19+Assumptions!$C$20+Assumptions!$C$21+Assumptions!$C$22+Assumptions!$C$23) | E31: =(Assumptions!$C$19*E26+Assumptions!$C$20*E27+Assumptions!$C$21*E28+Assumptions!$C$22*E29+Assumptions!$C$23*E30)/(Assumptions!$C$19+Assumptions!$C$20+Assumptions!$C$21+Assumptions!$C$22+Assumptions!$C$23) | F31: =(Assumptions!$C$19*F26+Assumptions!$C$20*F27+Assumptions!$C$21*F28+Assumptions!$C$22*F29+Assumptions!$C$23*F30)/(Assumptions!$C$19+Assumptions!$C$20+Assumptions!$C$21+Assumptions!$C$22+Assumptions!$C$23) | G31: =(Assumptions!$C$19*G26+Assumptions!$C$20*G27+Assumptions!$C$21*G28+Assumptions!$C$22*G29+Assumptions!$C$23*G30)/(Assumptions!$C$19+Assumptions!$C$20+Assumptions!$C$21+Assumptions!$C$22+Assumptions!$C$23) | H31: =(Assumptions!$C$19*H26+Assumptions!$C$20*H27+Assumptions!$C$21*H28+Assumptions!$C$22*H29+Assumptions!$C$23*H30)/(Assumptions!$C$19+Assumptions!$C$20+Assumptions!$C$21+Assumptions!$C$22+Assumptions!$C$23)
A32: Cash cost per pack (EGP) | D32: =Assumptions!$C$86*D31 | E32: =Assumptions!$C$86*E31 | F32: =Assumptions!$C$86*F31 | G32: =Assumptions!$C$86*G31 | H32: =Assumptions!$C$86*H31
A34: PROPERTY ROLL-FORWARD (EGP mn)
A35: Opening property, plant and equipment | D35: =Assumptions!$C$68 | E35: =D39 | F35: =E39 | G35: =F39 | H35: =G39
A36: Transfers in from construction | D36: =Assumptions!C$37 | E36: =Assumptions!D$37 | F36: =Assumptions!E$37 | G36: =Assumptions!F$37 | H36: =Assumptions!G$37
A37: Depreciation charge | D37: =-Assumptions!$C$38*(D35+D36/2) | E37: =-Assumptions!$C$38*(E35+E36/2) | F37: =-Assumptions!$C$38*(F35+F36/2) | G37: =-Assumptions!$C$38*(G35+G36/2) | H37: =-Assumptions!$C$38*(H35+H36/2)
A38: Amortisation of right-of-use and intangible assets | D38: =-Assumptions!$C$84 | E38: =-Assumptions!$C$84 | F38: =-Assumptions!$C$84 | G38: =-Assumptions!$C$84 | H38: =-Assumptions!$C$84
A39: Closing property, plant and equipment | D39: =D35+D36+D37 | E39: =E35+E36+E37 | F39: =F35+F36+F37 | G39: =G35+G36+G37 | H39: =H35+H36+H37
A40: Capital expenditure | D40: =D15*Assumptions!C$36 | E40: =E15*Assumptions!D$36 | F40: =F15*Assumptions!E$36 | G40: =G15*Assumptions!F$36 | H40: =H15*Assumptions!G$36
A41: Total depreciation and amortisation | D41: =-D37-D38 | E41: =-E37-E38 | F41: =-F37-F38 | G41: =-G37-G38 | H41: =-H37-H38
A42: Opening construction balance | D42: =Assumptions!$C$69 | E42: =D44 | F42: =E44 | G42: =F44 | H42: =G44
A43: Additions less transfers out | D43: =D40-D36 | E43: =E40-E36 | F43: =F40-F36 | G43: =G40-G36 | H43: =H40-H36
A44: Closing construction balance | D44: =D42+D43 | E44: =E42+E43 | F44: =F42+F43 | G44: =G42+G43 | H44: =H42+H43

Sheet Relative & Normalized
A1: Triangulation | B1: Multiple | C1: Value (EGP/share) | D1: Note
A2: SUSTAINABLE RETURN ON EQUITY — COMPUTED FROM THE FORECAST, NOT ASSERTED
A3: Return on average equity, FY2028E | B3: ='Income Statement'!G26/(('Balance Sheet'!F14+'Balance Sheet'!G14)/2)
A4: Return on average equity, FY2029E | B4: ='Income Statement'!H26/(('Balance Sheet'!G14+'Balance Sheet'!H14)/2)
A5: Return on average equity, FY2030E | B5: ='Income Statement'!I26/(('Balance Sheet'!H14+'Balance Sheet'!I14)/2)
A6: Sustainable return — the mean of the last three forecast years | B6: =AVERAGE(B3:B5) | D6: The forecast path RISES through the window rather than settling, so the sustainable return is the mean of its last three years — read from the path here, never typed
A7: Payout the growth rate permits = 1 less growth over the sustainable return | B7: =1-Assumptions!$C$62/B6
A9: FY2026E attributable earnings per share — Frame A | B9: ='Income Statement'!E27
A10: FY2026E attributable earnings per share — Frame B | B10: =((DCF!B38-Assumptions!C$55)*(1-Assumptions!$C$10)+Assumptions!$C$63-18.0)/Assumptions!$C$8
A11: Average of the two frames — the FORWARD earnings base | B11: =AVERAGE(B9:B10) | D11: Averaging the two frames' EARNINGS is not averaging the two VALUATIONS: the frames are published as two separate centres and are never averaged into one
A12: TRAILING attributable earnings per share, FY2025, on the count in issue today | B12: =Assumptions!$C$77/Assumptions!$C$8 | D12: The base for the two TRAILING multiples below. A trailing multiple applied to forward earnings would mismatch the periods
A15: THE COMPANY'S OWN TRADED MULTIPLE HISTORY
A16: Year | B16: Year-end close | C16: Attributable EPS | D16: Price / earnings
A17: 2022 | B17: 28.08 | C17: =Assumptions!$C$7/Assumptions!$C$4 | D17: =B17/C17
A18: 2023 | B18: 36.5 | C18: ='Income Statement'!B26/Assumptions!$C$5 | D18: =B18/C18
A19: 2024 | B19: 45.91 | C19: ='Income Statement'!C26/Assumptions!$C$5 | D19: =B19/C19
A20: 2025 | B20: 77.5 | C20: ='Income Statement'!D26/Assumptions!$C$6 | D20: =B20/C20
A21: Four-year mean | D21: =AVERAGE(D17:D20)
A22: Trailing multiple today — on the share count IN ISSUE | B22: =Assumptions!$C$3 | C22: =B12 | D22: =B22/C22
A23: Trailing multiple today — on the AUDITED WEIGHTED-AVERAGE count for FY2025 | B23: =Assumptions!$C$3 | C23: =Assumptions!$C$77/162.016024 | D23: =B23/C23 | F23: TWO SHARE COUNTS, BOTH PUBLISHED. The capital increase from 148.755750 to 168.755750 million shares completed during FY2025, so that year has a weighted-average count of 162.016024 million and a closing count of 168.755750 million. Both readings of the trailing multiple are legitimate; neither is stated alone.
A25: THE THREE MULTIPLES, EACH ON THE EARNINGS OF ITS OWN PERIOD
A26: Justified forward multiple from this model, on FY2026E earnings | B26: =B7/(Assumptions!$C$110-Assumptions!$C$62) | C26: =B26*B11 | D26: A FORWARD multiple, applied to FORWARD earnings — built from this model's own sustainable return and perpetual cost of equity
A27: The company's own four-year mean multiple, on trailing earnings | B27: =D21 | C27: =B27*B12 | D27: A TRAILING multiple, applied to TRAILING earnings — year-end closes against audited attributable profit, each year on its own weighted-average share count
A28: Struck peer reference, cost-of-equity adjusted, on trailing earnings | B28: =Assumptions!$C$65*(Assumptions!$C$66-Assumptions!$C$62)/(Assumptions!$C$110-Assumptions!$C$62) | C28: =B28*B12 | D28: A TRAILING multiple, applied to TRAILING earnings. The midpoint of the two disclosed observations, not a median of a peer set; those companies face a cost of equity near 10%, not this one
A29: AVERAGE OF THE THREE — the relative lens | B29: =AVERAGE(B26:B28) | C29: =AVERAGE(C26:C28)
A31: NORMALISED EARNINGS POWER
A32: Three-year average operating margin | B32: =AVERAGE('Income Statement'!B15/'Income Statement'!B2,'Income Statement'!C15/'Income Statement'!C2,'Income Statement'!D15/'Income Statement'!D2)
A33: FY2027E revenue | B33: ='Income Statement'!F2
A34: Normalised operating profit | B34: =B32*B33
A35: Normalised earnings per share | B35: =((B34-2.0-Assumptions!D$55)*(1-Assumptions!$C$10)+Assumptions!$C$63-18.0)/Assumptions!$C$8
A36: Payout the growth rate permits | B36: =1-Assumptions!$C$62/0.18754717
A37: NORMALISED EARNINGS POWER VALUE | B37: =B35*B36/(Assumptions!$C$110-Assumptions!$C$62)

Sheet DCF
A1: EGP million | B1: FY2026E | C1: FY2027E | D1: FY2028E | E1: FY2029E | F1: FY2030E | G1: Terminal
A2: Revenue | B2: ='Income Statement'!E2 | C2: ='Income Statement'!F2 | D2: ='Income Statement'!G2 | E2: ='Income Statement'!H2 | F2: ='Income Statement'!I2
A3: EBITDA | B3: ='Income Statement'!E17 | C3: ='Income Statement'!F17 | D3: ='Income Statement'!G17 | E3: ='Income Statement'!H17 | F3: ='Income Statement'!I17
A4: EBITDA margin = EBITDA / revenue | B4: =B3/B2 | C4: =C3/C2 | D4: =D3/D2 | E4: =E3/E2 | F4: =F3/F2
A5: Less depreciation and amortisation | B5: =-Segments!D41 | C5: =-Segments!E41 | D5: =-Segments!F41 | E5: =-Segments!G41 | F5: =-Segments!H41
A6: EBIT = EBITDA less depreciation and amortisation | B6: =B3+B5 | C6: =C3+C5 | D6: =D3+D5 | E6: =E3+E5 | F6: =F3+F5
A7: Tax rate — the EFFECTIVE rate the business bears, not the statutory rate | B7: =Assumptions!$C$10 | C7: =Assumptions!$C$10 | D7: =Assumptions!$C$10 | E7: =Assumptions!$C$10 | F7: =Assumptions!$C$10
A8: NOPAT = EBIT x (1 less the tax rate) | B8: =B6*(1-B7) | C8: =C6*(1-C7) | D8: =D6*(1-D7) | E8: =E6*(1-E7) | F8: =F6*(1-F7)
A9: Add back depreciation and amortisation | B9: =Segments!D41 | C9: =Segments!E41 | D9: =Segments!F41 | E9: =Segments!G41 | F9: =Segments!H41
A10: Less capital expenditure | B10: =-Segments!D40 | C10: =-Segments!E40 | D10: =-Segments!F40 | E10: =-Segments!G40 | F10: =-Segments!H40
A11: Less the increase in working capital | B11: ='Cash Flow'!E7 | C11: ='Cash Flow'!F7 | D11: ='Cash Flow'!G7 | E11: ='Cash Flow'!H7 | F11: ='Cash Flow'!I7
A12: FREE CASH FLOW TO THE FIRM | B12: =B8+B9+B10+B11 | C12: =C8+C9+C10+C11 | D12: =D8+D9+D10+D11 | E12: =E8+E9+E10+E11 | F12: =F8+F9+F10+F11
A13: Discount rate | B13: =Assumptions!C$115 | C13: =Assumptions!D$115 | D13: =Assumptions!E$115 | E13: =Assumptions!F$115 | F13: =Assumptions!G$115
A14: Discount factor | B14: =Assumptions!C$116 | C14: =Assumptions!D$116 | D14: =Assumptions!E$116 | E14: =Assumptions!F$116 | F14: =Assumptions!G$116
A15: PRESENT VALUE OF FREE CASH FLOW TO THE FIRM | B15: =B12*B14 | C15: =C12*C14 | D15: =D12*D14 | E15: =E12*E14 | F15: =F12*F14
A17: TERMINAL BLOCK
A18: Invested capital at FY2030E — property, construction, working capital and intangibles | B18: ='Balance Sheet'!I2+'Balance Sheet'!I3+'Balance Sheet'!I19+Assumptions!$C$83
A19: Return on invested capital, FY2030E — the model's OWN, read from the rows above | B19: =F8/B18 | D19: This is what sets terminal reinvestment. It is not an assumption and there is no cell to type it into.
A20: Terminal depreciation catch-up — the parked construction balance at the depreciation rate | B20: ='Balance Sheet'!I3*Assumptions!$C$38 | D20: Construction still parked at FY2030E has never entered the depreciable base. A perpetuity cannot capitalise profit on capital it never charges.
A21: Terminal NOPAT, on FY2030E money = final-year NOPAT less the depreciation the parked construction balance has never been charged. It is NOT grown here: the terminal value row below grows the whole free cash flow one year | B21: =F8-B20*(1-Assumptions!$C$10)
A22: Plus book depreciation (terminal NOPAT is already net of it) | B22: =423.085728
A23: Less maintenance at current cost — book depreciation escalated over half the useful life the company itself discloses | B23: =-674.802126
A24: Less the capital behind real growth | B24: =-0.000000
A25: Less inflation on working capital | B25: =-717.450174
A26: Terminal free cash flow to the firm | B26: =B21+B22+B23+B24+B25
A27: Terminal discount rate | B27: =Assumptions!$C$113
A28: Terminal growth | B28: =Assumptions!$C$62
A29: TERMINAL VALUE — the free cash flow above, grown one year and capitalised | B29: =B26*(1+B28)/(B27-B28)
A30: Present value of the terminal value | B30: =B29*F14
A32: Sum of the present values of forecast free cash flow | B32: =SUM(B15:F15)
A33: CORE ENTERPRISE VALUE | B33: =B32+B30
A34: Terminal value as a percentage of CORE enterprise value | B34: =B30/B33
A35: Terminal value as a percentage of TOTAL enterprise value (both are published) | B35: =B30/(B33+Assumptions!$C$63*Assumptions!$C$64+Assumptions!$C$81+Assumptions!$C$82)
A37: FRAME B — THE SAME MODEL WITH THE CONTESTED JUDGEMENT RESOLVED THE OTHER WAY
A38: EBIT on Frame B = Frame A EBIT plus the difference in the provision charge | B38: =B6+('Income Statement'!E12-'Income Statement'!E11) | C38: =C6+('Income Statement'!F12-'Income Statement'!F11) | D38: =D6+('Income Statement'!G12-'Income Statement'!G11) | E38: =E6+('Income Statement'!H12-'Income Statement'!H11) | F38: =F6+('Income Statement'!I12-'Income Statement'!I11)
A39: NOPAT on Frame B | B39: =B38*(1-B7) | C39: =C38*(1-C7) | D39: =D38*(1-D7) | E39: =E38*(1-E7) | F39: =F38*(1-F7)
A40: Free cash flow to the firm on Frame B | B40: =B39+B9+B10+B11 | C40: =C39+C9+C10+C11 | D40: =D39+D9+D10+D11 | E40: =E39+E9+E10+E11 | F40: =F39+F9+F10+F11
A41: Present value of free cash flow on Frame B | B41: =B40*B14 | C41: =C40*C14 | D41: =D40*D14 | E41: =E40*E14 | F41: =F40*F14
A42: Return on invested capital, FY2030E — Frame B's own | B42: =F39/B18
A43: Terminal NOPAT on Frame B, on FY2030E money, less the parked construction depreciation — not grown here, for the same reason as Frame A | B43: =F39-B20*(1-Assumptions!$C$10)
A44: Terminal free cash flow on Frame B — the same construction as Frame A: NOPAT plus book depreciation, less maintenance at current cost, less growth capital, less inflation on working capital | B44: =B43+-969.166571
A45: Terminal value on Frame B | B45: =B44*(1+B28)/(B27-B28)
A46: Core enterprise value on Frame B | B46: =SUM(B41:F41)+B45*F14
A47: VALUE PER SHARE ON FRAME B | B47: =(B46+Assumptions!$C$63*Assumptions!$C$64+Assumptions!$C$81+Assumptions!$C$82-Assumptions!$C$104-Assumptions!$C$80)/Assumptions!$C$8

Sheet Income Statement
A1: EGP million | B1: FY2023 | C1: FY2024 | D1: FY2025 | E1: FY2026E | F1: FY2027E | G1: FY2028E | H1: FY2029E | I1: FY2030E
A2: Revenue | B2: 5231.6656 | C2: 7590.5456 | D2: 9441.3793 | E2: =Segments!D15 | F2: =Segments!E15 | G2: =Segments!F15 | H2: =Segments!G15 | I2: =Segments!H15
A3: Cost of sales | B3: -2896.3434 | C3: -4184.3829 | D3: -5287.1409 | E3: =-(E4+E5) | F3: =-(F4+F5) | G3: =-(G4+G5) | H3: =-(H4+H5) | I3: =-(I4+I5)
A4: of which cash cost (packs x cash cost per pack, escalated) | B4: 2896.3434 | C4: 4184.3829 | D4: 5193.6433 | E4: =Segments!D14*Assumptions!$C$86*Segments!D$31 | F4: =Segments!E14*Assumptions!$C$86*Segments!E$31 | G4: =Segments!F14*Assumptions!$C$86*Segments!F$31 | H4: =Segments!G14*Assumptions!$C$86*Segments!G$31 | I4: =Segments!H14*Assumptions!$C$86*Segments!H$31
A5: of which depreciation charged to production | B5: 0 | C5: 0 | D5: 93.49756 | E5: =Segments!D$41*Assumptions!$C$85 | F5: =Segments!E$41*Assumptions!$C$85 | G5: =Segments!F$41*Assumptions!$C$85 | H5: =Segments!G$41*Assumptions!$C$85 | I5: =Segments!H$41*Assumptions!$C$85
A6: Gross profit | B6: =B2+B3 | C6: =C2+C3 | D6: =D2+D3 | E6: =E2+E3 | F6: =F2+F3 | G6: =G2+G3 | H6: =H2+H3 | I6: =I2+I3
A7: Gross margin | B7: =B6/B2 | C7: =C6/C2 | D7: =D6/D2 | E7: =E6/E2 | F7: =F6/F2 | G7: =G6/G2 | H7: =H6/H2 | I7: =I6/I2
A8: Selling and marketing | B8: -648.29168 | C8: -915.02118 | D8: -1000.1289 | E8: =-E2*Assumptions!C$31 | F8: =-F2*Assumptions!D$31 | G8: =-G2*Assumptions!E$31 | H8: =-H2*Assumptions!F$31 | I8: =-I2*Assumptions!G$31
A9: Research and development | B9: -43.227785 | C9: -70.460824 | D9: -70.935883 | E9: =-E2*Assumptions!C$32 | F9: =-F2*Assumptions!D$32 | G9: =-G2*Assumptions!E$32 | H9: =-H2*Assumptions!F$32 | I9: =-I2*Assumptions!G$32
A10: General and administrative | B10: -147.46099 | C10: -188.49293 | D10: -221.13686 | E10: =-E2*Assumptions!C$33 | F10: =-F2*Assumptions!D$33 | G10: =-G2*Assumptions!E$33 | H10: =-H2*Assumptions!F$33 | I10: =-I2*Assumptions!G$33
A11: Credit losses, inventory write-downs and provisions — FRAME A | B11: -265 | C11: -702 | D11: -494.21837 | E11: =-E2*Assumptions!C$34 | F11: =-F2*Assumptions!D$34 | G11: =-G2*Assumptions!E$34 | H11: =-H2*Assumptions!F$34 | I11: =-I2*Assumptions!G$34
A12: The same charge on FRAME B (memorandum) | B12: -265 | C12: -702 | D12: -494.21837 | E12: =-E2*Assumptions!C$35 | F12: =-F2*Assumptions!D$35 | G12: =-G2*Assumptions!E$35 | H12: =-H2*Assumptions!F$35 | I12: =-I2*Assumptions!G$35
A13: Board remuneration and attendance | B13: -2.02 | C13: -1.58 | D13: -1.828 | E13: -2 | F13: -2 | G13: -2 | H13: -2 | I13: -2
A14: Depreciation charged to selling and administrative expense | B14: 0 | C14: 0 | D14: 0 | E14: =-Segments!D41*(1-Assumptions!$C$85) | F14: =-Segments!E41*(1-Assumptions!$C$85) | G14: =-Segments!F41*(1-Assumptions!$C$85) | H14: =-Segments!G41*(1-Assumptions!$C$85) | I14: =-Segments!H41*(1-Assumptions!$C$85)
A15: Operating profit (EBIT) | B15: =B6+B8+B9+B10+B11+B13+B14 | C15: =C6+C8+C9+C10+C11+C13+C14 | D15: =D6+D8+D9+D10+D11+D13+D14 | E15: =E6+E8+E9+E10+E11+E13+E14 | F15: =F6+F8+F9+F10+F11+F13+F14 | G15: =G6+G8+G9+G10+G11+G13+G14 | H15: =H6+H8+H9+H10+H11+H13+H14 | I15: =I6+I8+I9+I10+I11+I13+I14
A16: Depreciation and amortisation (memorandum) | B16: 105.24975 | C16: 102.81185 | D16: 117.72537 | E16: =Segments!D$41 | F16: =Segments!E$41 | G16: =Segments!F$41 | H16: =Segments!G$41 | I16: =Segments!H$41
A17: EBITDA | B17: =B15+B16 | C17: =C15+C16 | D17: =D15+D16 | E17: =E15+E16 | F17: =F15+F16 | G17: =G15+G16 | H17: =H15+H16 | I17: =I15+I16
A18: Finance costs | B18: -407.7052 | C18: -960.13197 | D18: -1332.9466 | E18: =-Assumptions!C$55 | F18: =-Assumptions!D$55 | G18: =-Assumptions!E$55 | H18: =-Assumptions!F$55 | I18: =-Assumptions!G$55
A19: Share of results of associates | B19: 74.508447 | C19: 151.58093 | D19: 512.08464 | E19: =Assumptions!$C$63 | F19: =Assumptions!$C$63 | G19: =Assumptions!$C$63 | H19: =Assumptions!$C$63 | I19: =Assumptions!$C$63
A20: Dividend distribution tax | B20: -4.123733 | C20: -4.468933 | D20: -16.58542 | E20: 0 | F20: 0 | G20: 0 | H20: 0 | I20: 0
A21: Interest income, exchange differences and other income | B21: 191.25427 | C21: 814.78223 | D21: 267.35884 | E21: 0 | F21: 0 | G21: 0 | H21: 0 | I21: 0
A22: Profit before tax | B22: =B15+B18+B19+B21+B20 | C22: =C15+C18+C19+C21+C20 | D22: =D15+D18+D19+D21+D20 | E22: =E15+E18+E19+E21+E20 | F22: =F15+F18+F19+F21+F20 | G22: =G15+G18+G19+G21+G20 | H22: =H15+H18+H19+H21+H20 | I22: =I15+I18+I19+I21+I20
A23: Income tax and the statutory solidarity contribution | B23: -259.94915 | C23: -433.4465 | D23: -338.00884 | E23: =-(E22-E19)*Assumptions!$C$10 | F23: =-(F22-F19)*Assumptions!$C$10 | G23: =-(G22-G19)*Assumptions!$C$10 | H23: =-(H22-H19)*Assumptions!$C$10 | I23: =-(I22-I19)*Assumptions!$C$10
A24: Profit for the year | B24: =B22+B23 | C24: =C22+C23 | D24: =D22+D23 | E24: =E22+E23 | F24: =F22+F23 | G24: =G22+G23 | H24: =H22+H23 | I24: =I22+I23
A25: Less non-controlling interests | B25: -0.988615 | C25: -1.206525 | D25: -16.235315 | E25: -18 | F25: -18 | G25: -18 | H25: -18 | I25: -18
A26: Profit attributable to the holding company | B26: =B24+B25 | C26: =C24+C25 | D26: =D24+D25 | E26: =E24+E25 | F26: =F24+F25 | G26: =G24+G25 | H26: =H24+H25 | I26: =I24+I25
A27: Earnings per share (EGP) | B27: =B26/148.75575 | C27: =C26/148.75575 | D27: =D26/162.016024 | E27: =E26/Assumptions!$C$8 | F27: =F26/Assumptions!$C$8 | G27: =G26/Assumptions!$C$8 | H27: =H26/Assumptions!$C$8 | I27: =I26/Assumptions!$C$8
A29: YEARS THREE TO FIVE AS RANGES — the method replayed on this company's own past, year by year, and scored against what was later reported | K29: Factor | L29: Readings
A30: MULTIPLY the projection by the factor: above one means the outturn came in ABOVE the projection. The basis is a SPAN — the widest and the narrowest of the readings behind it, never a percentile.
A31: Revenue — low of the range | G31: =G2*K31 | H31: no measured range | I31: no measured range | K31: 1.7315304 | L31: 3
A32: Revenue — high of the range | G32: =G2*K32 | H32: no measured range | I32: no measured range | K32: 2.0234553 | L32: 3
A33: Cost of sales — low of the range | G33: =G3*K33 | H33: no measured range | I33: no measured range | K33: 1.6465008 | L33: 3
A34: Cost of sales — high of the range | G34: =G3*K34 | H34: no measured range | I34: no measured range | K34: 1.9468985 | L34: 3
A35: Gross profit — low of the range | G35: =G6*K35 | H35: no measured range | I35: no measured range | K35: 1.8303897 | L35: 3
A36: Gross profit — high of the range | G36: =G6*K36 | H36: no measured range | I36: no measured range | K36: 2.1300563 | L36: 3
A37: Profit for the year — low of the range | G37: =G24*K37 | H37: no measured range | I37: no measured range | K37: 1.7192128 | L37: 3
A38: Profit for the year — high of the range | G38: =G24*K38 | H38: no measured range | I38: no measured range | K38: 3.4050136 | L38: 3
A39: Depreciation and amortisation — low of the range | G39: =G16*K39 | H39: no measured range | I39: no measured range | K39: 0.56170003 | L39: 2
A40: Depreciation and amortisation — high of the range | G40: =G16*K40 | H40: no measured range | I40: no measured range | K40: 0.6032344 | L40: 2
A41: The fourth and fifth forecast years carry no measured range: the replay covers three years ahead and no further, and none is invented for them.

Sheet Balance Sheet
A1: EGP million | B1: FY2023 | C1: FY2024 | D1: FY2025 | E1: FY2026E | F1: FY2027E | G1: FY2028E | H1: FY2029E | I1: FY2030E
A2: Property, plant and equipment, net | B2: 963.64537 | C2: 1045.2305 | D2: =Assumptions!$C$68 | E2: =Segments!D39 | F2: =Segments!E39 | G2: =Segments!F39 | H2: =Segments!G39 | I2: =Segments!H39
A3: Projects under construction | B3: 3058.2117 | C3: 5693.5664 | D3: =Assumptions!$C$69 | E3: =Segments!D44 | F3: =Segments!E44 | G3: =Segments!F44 | H3: =Segments!G44 | I3: =Segments!H44
A4: Associates, intangibles, right-of-use, deferred tax and assets held for sale | B4: 483.14534 | C4: 519.21419 | D4: 1299.5989 | E4: =D4 | F4: =D4 | G4: =D4 | H4: =D4 | I4: =D4
A5: Inventories, net | B5: 2242.3957 | C5: 3584.6999 | D5: =Assumptions!$C$70 | E5: =('Income Statement'!E3*-1)*Assumptions!C$39/365 | F5: =('Income Statement'!F3*-1)*Assumptions!D$39/365 | G5: =('Income Statement'!G3*-1)*Assumptions!E$39/365 | H5: =('Income Statement'!H3*-1)*Assumptions!F$39/365 | I5: =('Income Statement'!I3*-1)*Assumptions!G$39/365
A6: Trade and notes receivable, net | B6: 2357.8555 | C6: 3049.2752 | D6: =Assumptions!$C$71 | E6: ='Income Statement'!E2*Assumptions!C$40/365 | F6: ='Income Statement'!F2*Assumptions!D$40/365 | G6: ='Income Statement'!G2*Assumptions!E$40/365 | H6: ='Income Statement'!H2*Assumptions!F$40/365 | I6: ='Income Statement'!I2*Assumptions!G$40/365
A7: Other debtors and debit balances | B7: 197.73103 | C7: 185.58435 | D7: =Assumptions!$C$72 | E7: ='Income Statement'!E2/9441.379305*Assumptions!$C$72 | F7: ='Income Statement'!F2/9441.379305*Assumptions!$C$72 | G7: ='Income Statement'!G2/9441.379305*Assumptions!$C$72 | H7: ='Income Statement'!H2/9441.379305*Assumptions!$C$72 | I7: ='Income Statement'!I2/9441.379305*Assumptions!$C$72
A8: Cash and bank balances | B8: 675.79824 | C8: 1295.3869 | D8: =Assumptions!$C$75 | E8: =Assumptions!$C$75 | F8: =Assumptions!$C$75 | G8: =Assumptions!$C$75 | H8: =Assumptions!$C$75 | I8: =Assumptions!$C$75
A9: TOTAL ASSETS | B9: =SUM(B2:B8) | C9: =SUM(C2:C8) | D9: =SUM(D2:D8) | E9: =SUM(E2:E8) | F9: =SUM(F2:F8) | G9: =SUM(G2:G8) | H9: =SUM(H2:H8) | I9: =SUM(I2:I8)
A10: Trade and notes payable | B10: 176.35389 | C10: 410.39162 | D10: =Assumptions!$C$73 | E10: =('Income Statement'!E3*-1)*Assumptions!C$41/365 | F10: =('Income Statement'!F3*-1)*Assumptions!D$41/365 | G10: =('Income Statement'!G3*-1)*Assumptions!E$41/365 | H10: =('Income Statement'!H3*-1)*Assumptions!F$41/365 | I10: =('Income Statement'!I3*-1)*Assumptions!G$41/365
A11: Other creditors and credit balances | B11: 230.67538 | C11: 367.42118 | D11: =Assumptions!$C$74 | E11: ='Income Statement'!E2/9441.379305*Assumptions!$C$74 | F11: ='Income Statement'!F2/9441.379305*Assumptions!$C$74 | G11: ='Income Statement'!G2/9441.379305*Assumptions!$C$74 | H11: ='Income Statement'!H2/9441.379305*Assumptions!$C$74 | I11: ='Income Statement'!I2/9441.379305*Assumptions!$C$74
A12: Provisions, income tax payable and deferred tax | B12: 435.07939 | C12: 737.37392 | D12: 1117.6606 | E12: =D12 | F12: =D12 | G12: =D12 | H12: =D12 | I12: =D12
A13: Gross borrowings including leases | B13: 4879.9735 | C13: 9200.0329 | D13: =Assumptions!$C$76 | E13: =E9-E10-E11-E12-E14-E15 | F13: =F9-F10-F11-F12-F14-F15 | G13: =G9-G10-G11-G12-G14-G15 | H13: =H9-H10-H11-H12-H14-H15 | I13: =I9-I10-I11-I12-I14-I15
A14: Equity attributable to the holding company | B14: 4257.4081 | C14: 4653.7692 | D14: =Assumptions!$C$78 | E14: =Assumptions!$C$78+'Income Statement'!E26*(1-Assumptions!$C$42) | F14: =E14+'Income Statement'!F26*(1-Assumptions!$C$42) | G14: =F14+'Income Statement'!G26*(1-Assumptions!$C$42) | H14: =G14+'Income Statement'!H26*(1-Assumptions!$C$42) | I14: =H14+'Income Statement'!I26*(1-Assumptions!$C$42)
A15: Non-controlling interests | B15: 3.394945 | C15: 3.816172 | D15: =Assumptions!$C$79 | E15: =Assumptions!$C$80 | F15: =Assumptions!$C$80 | G15: =Assumptions!$C$80 | H15: =Assumptions!$C$80 | I15: =Assumptions!$C$80
A16: TOTAL LIABILITIES AND EQUITY | B16: =B10+B11+B12+B13+B14+B15 | C16: =C10+C11+C12+C13+C14+C15 | D16: =D10+D11+D12+D13+D14+D15 | E16: =E10+E11+E12+E13+E14+E15 | F16: =F10+F11+F12+F13+F14+F15 | G16: =G10+G11+G12+G13+G14+G15 | H16: =H10+H11+H12+H13+H14+H15 | I16: =I10+I11+I12+I13+I14+I15
A17: BALANCE CHECK — total assets less total liabilities and equity | B17: =B9-B16 | C17: =C9-C16 | D17: =D9-D16 | E17: =E9-E16 | F17: =F9-F16 | G17: =G9-G16 | H17: =H9-H16 | I17: =I9-I16 | J17: ZERO IN EVERY FORECAST COLUMN, BY CONSTRUCTION — gross borrowings are the funding plug. The earlier edition never computed this row at all and its forecast columns were out by up to 6.6% of total assets. The three audited columns carry small residuals (-4.1, +0.2, +0.4 on assets of 10.0bn to 18.3bn, under 0.05%) from grouping the filed statement into these line captions; they are shown rather than suppressed.
A18: NET DEBT | B18: =B13-B8 | C18: =C13-C8 | D18: =D13-D8 | E18: =E13-E8 | F18: =F13-F8 | G18: =G13-G8 | H18: =H13-H8 | I18: =I13-I8
A19: Net working capital | B19: =B5+B6+B7-B10-B11 | C19: =C5+C6+C7-C10-C11 | D19: =D5+D6+D7-D10-D11 | E19: =E5+E6+E7-E10-E11 | F19: =F5+F6+F7-F10-F11 | G19: =G5+G6+G7-G10-G11 | H19: =H5+H6+H7-H10-H11 | I19: =I5+I6+I7-I10-I11
A20: Book value per share (EGP) | B20: =B14/148.75575 | C20: =C14/148.75575 | D20: =D14/168.75575 | E20: =E14/Assumptions!$C$8 | F20: =F14/Assumptions!$C$8 | G20: =G14/Assumptions!$C$8 | H20: =H14/Assumptions!$C$8 | I20: =I14/Assumptions!$C$8

Sheet Cash Flow
A1: EGP million | B1: FY2023 | C1: FY2024 | D1: FY2025 | E1: FY2026E | F1: FY2027E | G1: FY2028E | H1: FY2029E | I1: FY2030E
A2: Operating profit (EBIT) | B2: ='Income Statement'!B15 | C2: ='Income Statement'!C15 | D2: ='Income Statement'!D15 | E2: ='Income Statement'!E15 | F2: ='Income Statement'!F15 | G2: ='Income Statement'!G15 | H2: ='Income Statement'!H15 | I2: ='Income Statement'!I15
A3: Tax on operating profit at the EFFECTIVE rate the business bears | B3: =-B2*Assumptions!$C$10 | C3: =-C2*Assumptions!$C$10 | D3: =-D2*Assumptions!$C$10 | E3: =-E2*Assumptions!$C$10 | F3: =-F2*Assumptions!$C$10 | G3: =-G2*Assumptions!$C$10 | H3: =-H2*Assumptions!$C$10 | I3: =-I2*Assumptions!$C$10
A4: Operating profit after tax (NOPAT) | B4: =B2+B3 | C4: =C2+C3 | D4: =D2+D3 | E4: =E2+E3 | F4: =F2+F3 | G4: =G2+G3 | H4: =H2+H3 | I4: =I2+I3
A5: Add back depreciation and amortisation | B5: ='Income Statement'!B16 | C5: ='Income Statement'!C16 | D5: ='Income Statement'!D16 | E5: ='Income Statement'!E16 | F5: ='Income Statement'!F16 | G5: ='Income Statement'!G16 | H5: ='Income Statement'!H16 | I5: ='Income Statement'!I16
A6: Less capital expenditure | B6: -2290.1946 | C6: -2846.2397 | D6: -1354.6652 | E6: =-Segments!D40 | F6: =-Segments!E40 | G6: =-Segments!F40 | H6: =-Segments!G40 | I6: =-Segments!H40
A7: Less the increase in working capital | B7: -835.71513 | C7: -2426.8135 | D7: -428.2195 | E7: =-('Balance Sheet'!E19-'Balance Sheet'!D19) | F7: =-('Balance Sheet'!F19-'Balance Sheet'!E19) | G7: =-('Balance Sheet'!G19-'Balance Sheet'!F19) | H7: =-('Balance Sheet'!H19-'Balance Sheet'!G19) | I7: =-('Balance Sheet'!I19-'Balance Sheet'!H19)
A8: FREE CASH FLOW TO THE FIRM | E8: =E4+E5+E6+E7 | F8: =F4+F5+F6+F7 | G8: =G4+G5+G6+G7 | H8: =H4+H5+H6+H7 | I8: =I4+I5+I6+I7
A10: Memorandum — audited operating, investing and financing cash flow
A11: Net cash from operating activities | B11: 92.483752 | C11: -1274.4881 | D11: 1093.5161
A12: Net cash used in investing activities | B12: -2329.64 | C12: -2679.0289 | D12: -1201.7266
A13: Net cash from financing activities | B13: 2209.8249 | C13: 3853.615 | D13: 262.41196

Sheet Summary Financials
A1: EGP million | B1: FY2023 | C1: FY2024 | D1: FY2025 | E1: FY2026E | F1: FY2027E | G1: FY2028E | H1: FY2029E | I1: FY2030E
A2: Revenue | B2: ='Income Statement'!B2 | C2: ='Income Statement'!C2 | D2: ='Income Statement'!D2 | E2: ='Income Statement'!E2 | F2: ='Income Statement'!F2 | G2: ='Income Statement'!G2 | H2: ='Income Statement'!H2 | I2: ='Income Statement'!I2
A3: Gross profit | B3: ='Income Statement'!B6 | C3: ='Income Statement'!C6 | D3: ='Income Statement'!D6 | E3: ='Income Statement'!E6 | F3: ='Income Statement'!F6 | G3: ='Income Statement'!G6 | H3: ='Income Statement'!H6 | I3: ='Income Statement'!I6
A4: EBITDA | B4: ='Income Statement'!B17 | C4: ='Income Statement'!C17 | D4: ='Income Statement'!D17 | E4: ='Income Statement'!E17 | F4: ='Income Statement'!F17 | G4: ='Income Statement'!G17 | H4: ='Income Statement'!H17 | I4: ='Income Statement'!I17
A5: Operating profit | B5: ='Income Statement'!B15 | C5: ='Income Statement'!C15 | D5: ='Income Statement'!D15 | E5: ='Income Statement'!E15 | F5: ='Income Statement'!F15 | G5: ='Income Statement'!G15 | H5: ='Income Statement'!H15 | I5: ='Income Statement'!I15
A6: Profit before tax | B6: ='Income Statement'!B22 | C6: ='Income Statement'!C22 | D6: ='Income Statement'!D22 | E6: ='Income Statement'!E22 | F6: ='Income Statement'!F22 | G6: ='Income Statement'!G22 | H6: ='Income Statement'!H22 | I6: ='Income Statement'!I22
A7: Profit attributable to the holding company | B7: ='Income Statement'!B26 | C7: ='Income Statement'!C26 | D7: ='Income Statement'!D26 | E7: ='Income Statement'!E26 | F7: ='Income Statement'!F26 | G7: ='Income Statement'!G26 | H7: ='Income Statement'!H26 | I7: ='Income Statement'!I26
A8: Gross margin | B8: ='Income Statement'!B6/'Income Statement'!B2 | C8: ='Income Statement'!C6/'Income Statement'!C2 | D8: ='Income Statement'!D6/'Income Statement'!D2 | E8: ='Income Statement'!E6/'Income Statement'!E2 | F8: ='Income Statement'!F6/'Income Statement'!F2 | G8: ='Income Statement'!G6/'Income Statement'!G2 | H8: ='Income Statement'!H6/'Income Statement'!H2 | I8: ='Income Statement'!I6/'Income Statement'!I2
A9: EBITDA margin | B9: ='Income Statement'!B17/'Income Statement'!B2 | C9: ='Income Statement'!C17/'Income Statement'!C2 | D9: ='Income Statement'!D17/'Income Statement'!D2 | E9: ='Income Statement'!E17/'Income Statement'!E2 | F9: ='Income Statement'!F17/'Income Statement'!F2 | G9: ='Income Statement'!G17/'Income Statement'!G2 | H9: ='Income Statement'!H17/'Income Statement'!H2 | I9: ='Income Statement'!I17/'Income Statement'!I2
A10: Operating margin | B10: ='Income Statement'!B15/'Income Statement'!B2 | C10: ='Income Statement'!C15/'Income Statement'!C2 | D10: ='Income Statement'!D15/'Income Statement'!D2 | E10: ='Income Statement'!E15/'Income Statement'!E2 | F10: ='Income Statement'!F15/'Income Statement'!F2 | G10: ='Income Statement'!G15/'Income Statement'!G2 | H10: ='Income Statement'!H15/'Income Statement'!H2 | I10: ='Income Statement'!I15/'Income Statement'!I2
A11: Net margin | B11: ='Income Statement'!B26/'Income Statement'!B2 | C11: ='Income Statement'!C26/'Income Statement'!C2 | D11: ='Income Statement'!D26/'Income Statement'!D2 | E11: ='Income Statement'!E26/'Income Statement'!E2 | F11: ='Income Statement'!F26/'Income Statement'!F2 | G11: ='Income Statement'!G26/'Income Statement'!G2 | H11: ='Income Statement'!H26/'Income Statement'!H2 | I11: ='Income Statement'!I26/'Income Statement'!I2

Sheet Monte Carlo
A1: Probabilistic price map | B1: One month | C1: Three months | D1: Note
A2: THESE CELLS ARE A WHOLE-MODEL RE-RUN — 50,000 simulated price paths each. They do NOT redraw when a driver on the Assumptions sheet changes.
A3: Anchor price (EGP) | B3: 130.05 | C3: 130.05 | D3: Anchored 2026-08-06
A4: Check date | B4: 2026-09-06 | C4: 2026-11-08 | D4: A calendar date, resolved to the exchange's first real trading session
A5: 5th percentile of the simulated distribution | B5: 103.80077 | C5: 94.395405
A6: 25th percentile of the simulated distribution | B6: 120.56328 | C6: 118.41684
A7: 50th percentile of the simulated distribution | B7: 131.69333 | C7: 135.3037
A8: 75th percentile of the simulated distribution | B8: 143.94294 | C8: 154.39335
A9: 95th percentile of the simulated distribution | B9: 167.16948 | C9: 193.81966
A10: Probability of finishing above the anchor | B10: 0.53802 | C10: 0.58168
A11: Probability of finishing 10% or more above | B11: 0.26388 | C11: 0.38614
A12: Probability of finishing 10% or more below | B12: 0.1869 | C12: 0.23222
A13: Probability of TOUCHING 10% above at any point | B13: 0.43044 | C13: 0.63828
A14: Probability of TOUCHING 10% below at any point | B14: 0.3294 | C14: 0.47868
A15: Annualised volatility used | B15: 0.62898316 | C15: 0.53554934
A17: CALIBRATION EVIDENCE
A18: Window set | B18: Windows | C18: Skill against the benchmark | D18: Probability-transform uniformity
A19: Full cleaned history (2012-05-23 to 2026-03-24) | B19: 56 | C19: -0.017714367 | D19: chi-square p = 0.166, Kolmogorov-Smirnov p = 0.478 — roughly uniform
A20: Last five years of origins (2021-09-19 to 2026-03-24) | B20: 19 | C20: 0.0021479229 | D20: chi-square p = 0.447, Kolmogorov-Smirnov p = 0.676 — roughly uniform
A21: Post-break window set (2022-06-20 to 2026-03-24) | B21: 16 | C21: -0.010858171 | D21: chi-square p = 0.331, Kolmogorov-Smirnov p = 0.144 — roughly uniform

Sheet Sensitivity
A1: Value per share (EGP) — each cell is a COMPLETE revaluation
A2: THESE GRIDS ARE WHOLE-MODEL RE-RUNS. Each cell re-runs the entire model at a different input. They do NOT redraw when a driver on the Assumptions sheet changes.
A4: Shift in the cost of equity (basis points) | B4: -200 | C4: -100 | D4: 0 | E4: 100 | F4: 200
A5: Value per share | B5: 45.588965 | C5: 37.726292 | D5: 31.297656 | E5: 25.945552 | F5: 21.422153
A7: Terminal growth | B7: 0.03 | C7: 0.04 | D7: 0.05 | E7: 0.06 | F7: 0.07
A8: Value per share | B8: 22.784634 | C8: 24.403489 | D8: 26.29549 | E8: 28.549508 | F8: 31.297656
A10: Beta | B10: 0.45 | C10: 0.55 | D10: 0.66581884 | E10: 0.75 | F10: 0.9
A11: Value per share | B11: 42.075704 | C11: 36.67897 | D11: 31.297656 | E11: 27.86582 | F11: 22.557403
A13: Provision charge as a share of revenue | B13: 0.025 | C13: 0.035 | D13: 0.0525 | E13: 0.065 | F13: 0.08
A14: Value per share | B14: 49.166349 | C14: 42.668642 | D14: 31.297656 | E14: 23.175523 | F14: 13.428963
A16: Exchange-rate path, scaled | B16: 0.9 | C16: 0.95 | D16: 1 | E16: 1.05 | F16: 1.1
A17: Value per share | B17: 44.548061 | C17: 37.922859 | D17: 31.297656 | E17: 24.672453 | F17: 18.04725
A19: Shift in domestic volume growth | B19: -0.04 | C19: -0.02 | D19: 0 | E19: 0.02 | F19: 0.04
A20: Value per share | B20: 37.282402 | C20: 34.388803 | D20: 31.297656 | E20: 27.998117 | F20: 24.478941
... A30: +200 basis points | B30: 16.204663 | C30: 17.250617 | D30: 18.439425 | E30: 19.811104 | F30: 21.422153
A32: THE CRUX — reverse valuation
A33: Additional FY2030E revenue required to reach the market price (EGP mn) | B33: 9341.7333
A34: as a share of FY2030E revenue | B34: 0.334233
A35: in US dollars a year (mn) | B35: 133.23654
A36: as a multiple of the plant's stated USD 100 million cost | B36: 1.3323654

Sheet Per-Share & Ratios
B1: FY2023 | C1: FY2024 | D1: FY2025 | E1: FY2026E | F1: FY2027E | G1: FY2028E | H1: FY2029E | I1: FY2030E
A2: Earnings per share (EGP) | B2: ='Income Statement'!B27 | C2: ='Income Statement'!C27 | D2: ='Income Statement'!D27 | E2: ='Income Statement'!E27 | F2: ='Income Statement'!F27 | G2: ='Income Statement'!G27 | H2: ='Income Statement'!H27 | I2: ='Income Statement'!I27
A3: Book value per share (EGP) | B3: ='Balance Sheet'!B20 | C3: ='Balance Sheet'!C20 | D3: ='Balance Sheet'!D20 | E3: ='Balance Sheet'!E20 | F3: ='Balance Sheet'!F20 | G3: ='Balance Sheet'!G20 | H3: ='Balance Sheet'!H20 | I3: ='Balance Sheet'!I20
A4: Dividend per share (EGP) | B4: 2 | C4: 3 | D4: 3.5 | E4: ='Income Statement'!E27*Assumptions!$C$42 | F4: ='Income Statement'!F27*Assumptions!$C$42 | G4: ='Income Statement'!G27*Assumptions!$C$42 | H4: ='Income Statement'!H27*Assumptions!$C$42 | I4: ='Income Statement'!I27*Assumptions!$C$42
A5: Return on average equity | E5: ='Income Statement'!E26/(('Balance Sheet'!D14+'Balance Sheet'!E14)/2) | F5: ='Income Statement'!F26/(('Balance Sheet'!E14+'Balance Sheet'!F14)/2) | G5: ='Income Statement'!G26/(('Balance Sheet'!F14+'Balance Sheet'!G14)/2) | H5: ='Income Statement'!H26/(('Balance Sheet'!G14+'Balance Sheet'!H14)/2) | I5: ='Income Statement'!I26/(('Balance Sheet'!H14+'Balance Sheet'!I14)/2)
A6: Net debt / EBITDA | E6: =('Balance Sheet'!E13-Assumptions!$C$75)/'Income Statement'!E17 | F6: =('Balance Sheet'!F13-Assumptions!$C$75)/'Income Statement'!F17 | G6: =('Balance Sheet'!G13-Assumptions!$C$75)/'Income Statement'!G17 | H6: =('Balance Sheet'!H13-Assumptions!$C$75)/'Income Statement'!H17 | I6: =('Balance Sheet'!I13-Assumptions!$C$75)/'Income Statement'!I17
A7: Inventory days | E7: =Assumptions!C$39 | F7: =Assumptions!D$39 | G7: =Assumptions!E$39 | H7: =Assumptions!F$39 | I7: =Assumptions!G$39
A8: Receivable days | E8: =Assumptions!C$40 | F8: =Assumptions!D$40 | G8: =Assumptions!E$40 | H8: =Assumptions!F$40 | I8: =Assumptions!G$40
A9: Payable days | E9: =Assumptions!C$41 | F9: =Assumptions!D$41 | G9: =Assumptions!E$41 | H9: =Assumptions!F$41 | I9: =Assumptions!G$41
A10: Cash conversion cycle (days) | E10: =E7+E8-E9 | F10: =F7+F8-F9 | G10: =G7+G8-G9 | H10: =H7+H8-H9 | I10: =I7+I8-I9
A11: Return on invested capital | E11: =('Income Statement'!E15*(1-Assumptions!$C$10))/('Balance Sheet'!E2+'Balance Sheet'!E3+'Balance Sheet'!E19+Assumptions!$C$83) | F11: =('Income Statement'!F15*(1-Assumptions!$C$10))/('Balance Sheet'!F2+'Balance Sheet'!F3+'Balance Sheet'!F19+Assumptions!$C$83) | G11: =('Income Statement'!G15*(1-Assumptions!$C$10))/('Balance Sheet'!G2+'Balance Sheet'!G3+'Balance Sheet'!G19+Assumptions!$C$83) | H11: =('Income Statement'!H15*(1-Assumptions!$C$10))/('Balance Sheet'!H2+'Balance Sheet'!H3+'Balance Sheet'!H19+Assumptions!$C$83) | I11: =('Income Statement'!I15*(1-Assumptions!$C$10))/('Balance Sheet'!I2+'Balance Sheet'!I3+'Balance Sheet'!I19+Assumptions!$C$83)

Sheet Peer & Sector
A1: Peer / reference | B1: Multiple | C1: Basis | D1: Provenance
A2: Peer multiples are MARKET DATA and sit in the cross-check layer. No peer figure is used to build any historical number for the subject company.
A3: Listed Saudi Arabian generics manufacturer | B3: 26.7 | C3: Trailing price / earnings | D3: Public-comparables service, 2025 basis — cross-check only. This company is not named and its financial statements are not published here, so this multiple cannot be rebuilt from its filings
A4: Regional and international generic manufacturers, mid-cap | B4: 16 | C4: Trailing price / earnings | D4: Range observed across the peer set — cross-check only
A5: STRUCK REFERENCE USED — the midpoint of the two above | B5: =AVERAGE(B3:B4) | C5: Trailing price / earnings | D5: NOT a median of a disclosed peer set: two observations have a midpoint, and this cell computes it. The lens runs a 13-26 times band around it
A6: The subject company today | B6: =Assumptions!$C$3/('Income Statement'!D26/Assumptions!$C$8) | C6: Trailing price / earnings | D6: Computed in this sheet from the audited attributable profit and the market price
A7: The subject company's own four-year mean | B7: ='Relative & Normalized'!D21 | C7: Trailing price / earnings | D7: Computed from year-end closes and audited profit — entirely primary
A8: Discount of the subject to the struck reference | B8: =B6/B5-1 | D8: The peers face a cost of equity near 10%; this company's perpetual cost of equity is 14.9% and its current cost of equity 24.8%. The discount is not an anomaly to be closed.
A10: SECTOR OPERATING BENCHMARKS (the subject, computed here)
A11: Gross margin, FY2025 | B11: ='Income Statement'!D7
A12: EBITDA margin, FY2025 | B12: ='Income Statement'!D17/'Income Statement'!D2
A13: Return on average equity, FY2025 | B13: ='Income Statement'!D26/(('Balance Sheet'!C14+'Balance Sheet'!D14)/2)
A14: Capacity utilisation, FY2025 | B14: =Segments!C20
A15: Cash conversion cycle, FY2025 (days) | B15: 343.01452
A16: Export share of revenue, FY2025 | B16: 0.31430576
