Workbook

Sheet READ FIRST
A1: Testahil — Emirates Integrated Telecommunications Company PJSC (DFM: DU)
A3: Companion model · Independent Valuation Study · Educational analysis · Not investment advice
A5: What this workbook is. A transparent companion to the du valuation study. Every blue cell is an input;
A6: every black cell is a formula; green cells link across sheets.
A8: IT IS FORMULA-DRIVEN. Every figure that can be derived arithmetically from a driver is a live formula, so
A9: you can change a blue cell on Assumptions and watch the model reprice: the cost of capital is built from
A10: the risk-free rate net of the sovereign spread, beta and the premium rather than pasted; the discount
A11: factors compound from the glide; and the income statement, balance sheet, cash flow, ratios and all four
A12: lenses chain off the same cells.
A14: THREE THINGS ARE PASTED VALUES, and it is worth knowing exactly which. First, audited and disclosed
A15: history — the primary record, not a calculation. Second, the unit build's output: forecast revenue for
A16: the four segments the company itself discloses (Mobile, Fixed, Wholesale, ICT and associated telecom
... A78: Ratios · Peer & Sector.

Sheet Summary
A1: Summary — valuation at a glance
A2: All values link live to their source sheets
A4: Lens | B4: Bear | C4: Base | D4: Bull | E4: Role | G4: vs price
A5: Discounted cash flow (primary) | B5: 9.6021659 | C5: =DCF!C63 | D5: 25.215899 | E5: THE CENTRAL — the class primary | G5: =C5/$C$15-1
A6: Relative multiples | B6: ='Relative & Normalized'!C12 | C6: ='Relative & Normalized'!C11 | D6: ='Relative & Normalized'!D12 | E6: cross-check | G6: =C6/$C$15-1
A7: Normalised earnings power | B7: ='Relative & Normalized'!E27 | C7: ='Relative & Normalized'!C27 | D7: ='Relative & Normalized'!F27 | E7: REMOVED — not a lens this class publishes | G7: =C7/$C$15-1
A8: Book value and sustainable return | B8: ='Relative & Normalized'!E35 | C8: ='Relative & Normalized'!C35 | D8: ='Relative & Normalized'!F35 | E8: a disclosed floor, never weighted | G8: =C8/$C$15-1
A9: THE CENTRAL — the cash-flow lens, not an average | B9: =B5 | C9: =C5 | D9: =D5 | E9: the class primary | G9: =C9/$C$15-1
A10: NOT AVERAGED — the retired blend, published unused | C10: =C5*0.45+C6*0.25+C7*0.2+C8*0.1 | E10: retired 02-Sep-2026 | G10: =C10/$C$15-1
A11: Span across the lenses (min/max) — a spread between METHODS, not a range around the answer | B11: =MIN(B5:B8) | D11: =MAX(D5:D8)
A12: Contested judgement, other way — no terminal re-rating (Framing 2) | C12: ='Fundamental Valuation'!C18 | G12: =C12/$C$15-1
A13: Terminal value share of DCF enterprise value | C13: =DCF!C29
A14: Expert panel median | C14: ='Fundamental Valuation'!C27 | G14: =C14/$C$15-1
A15: Market price (anchor) | C15: 11.38
A17: Key figure | B17: Value
A18: Shares outstanding (mn) | C18: =Assumptions!$C$6
A19: Market capitalisation (AED mn) | C19: =$C$15*C18
A20: Lease liabilities, FY2025 (AED mn) — the only debt-like item | C20: =Assumptions!$C$87
A21: Cash and term deposits, FY2025 (AED mn) | C21: =Assumptions!$C$88
A22: FY2025 revenue (AED mn) | C22: ='Income Statement'!D5
A23: FY2025 EBITDA (AED mn) | C23: ='Income Statement'!D9
A24: FY2025 net profit (AED mn) | C24: ='Income Statement'!D18
A25: Cost of capital — explicit window | C25: =DCF!C47
A26: Cost of capital — terminal | C26: =DCF!C54
A27: Terminal growth | C27: =DCF!C24

Sheet Fundamental Valuation
A1: Fundamental valuation — the four lenses and the contested judgement
A4: Lens / step | B4: Basis | C4: AED per share
A5: Discounted cash flow | B5: links to the DCF sheet | C5: =DCF!C63
A6: bear | B6: ARPU −5%, subscribers −250k, margins −3%, +100bp cost of capital, g 2% | C6: 9.6021659
A7: bull | B7: ARPU +3%, subscribers +200k, margins +1.5%, −50bp cost of capital, g 3% | C7: 25.215899
A8: Relative multiples | B8: 12.9x justified P/E on FY2026E earnings | C8: ='Relative & Normalized'!C11
A9: Normalised earnings power | B9: 12.9x normalised earnings per share | C9: ='Relative & Normalized'!C27
A10: Book value and sustainable return | B10: justified price-to-book on sustainable return on equity | C10: ='Relative & Normalized'!C35
A12: THE CENTRAL — the cash-flow lens itself, not an average of the four | C12: =Summary!C9
A14: THE CONTESTED JUDGEMENT — THE REQUIRED RETURN, BOTH WAYS
A15: Framing 1: du's own measured beta sets the cost of equity | C15: =DCF!C63
A16: the terminal that implies — exit multiple on terminal EBITDA | C16: 8.0961682
A17: against du's OWN current trailing EV/EBITDA | C17: 6.9870345
A18: Framing 2: no terminal re-rating — du's current multiple held in perpetuity | C18: 13.775499
A19: The judgement is worth (Framing 1 less Framing 2, per share) | C19: =C15-C18
A20: Post-2029 fiscal tail: the pre-2024 royalty construction returns after the disclosed 2027-2029 extension lapses | C20: 13.196777
A22: EXPERT PANEL
A23: Expert | B23: Method | C23: Base (AED/share) | D23: Low | E23: High
A24: Expert 1 | B24: earnings power | C24: 11.527962 | D24: 9.5512784 | E24: 13.175198
A25: Expert 2 | B25: dividend stream | C25: 15.320566 | D25: 9.4121874 | E25: 19.899495
A26: Expert 3 | B26: cash returns vs cost of capital | C26: 15.759805 | D26: 10.580918 | E26: 17.650981
A27: Panel median | C27: =MEDIAN(C24:C26)
A29: The risk-free tenor question, priced
A30: There is no liquid 10-year AED government point. The base model uses the Jan-2031 AED T-bond (4.48%); discounting instead at the peg-extrapolated 10-year proxy (4.69%) is an engine re-run worth the figure at right | C30: 14.868734

Sheet Assumptions
A1: Assumptions — every input in the model
A2: Blue cells are inputs. Change one and the model reprices: everything downstream is a formula.
A3: Input | B3: FY26E | C3: FY27E | D3: FY28E | E3: FY29E | F3: FY30E
A4: Anchors
A5: Spot price (AED) | C5: 11.38
A6: Shares outstanding (mn) | C6: 4532.906
A7: AED 1.8bn combined annual royalty-and-tax FLOOR — Cabinet decision 8/38 of 2023 and expressly retained in the 2027-2029 extension du disclosed on 24-Jul-2026. MODELLED from 08-09-2026: it does not bind in the base case and the model now says so rather than assuming it (AED mn) | C7: 1800
A8: Combined federal royalty + income tax rate (Framing A, audited FY2025) | C8: 0.4357
A9: Regulated revenue share (Framing B base, audited FY2023) | C9: 0.69
A10: Framing B — royalty rate on regulated revenue | C10: 0.15
A11: Framing B — royalty rate on regulated profit | C11: 0.3
A13: H1-2026 reviewed segment actuals — the base the FY2026 build chains off
A14: Mobile revenue, six months to 30-Jun-2026 (AED mn, reviewed) | C14: 3646.314
A15: Fixed revenue, six months to 30-Jun-2026 (AED mn, reviewed) | C15: 2382.608
A16: Mobile subscribers at 30-Jun-2026 ('000, reviewed period end) | C16: 9280
A17: Fixed subscribers at 30-Jun-2026 ('000, reviewed period end) | C17: 744
A18: Wholesale revenue FY2025 (AED mn, audited) | C18: 2568.222
A19: ICT revenue FY2025 (AED mn, audited) | C19: 1882.558
A20: Wholesale revenue, six months to 30-Jun-2026 (AED mn, reviewed) | C20: 1257.566
A21: ICT revenue, six months to 30-Jun-2026 (AED mn, reviewed) | C21: 911.085
A23: Unit build — mobile and fixed (subscribers x ARPU)
A24: Mobile subscribers, end of year ('000) | B24: 9450 | C24: 9760 | D24: 10010 | E24: 10240 | F24: 10450
A25: Fixed subscribers, end of year ('000) | B25: 760 | C25: 790 | D25: 815 | E25: 838 | F25: 858
A26: Blended mobile ARPU (AED/month) | B26: 63.4 | C26: 63.6 | D26: 63.8 | E26: 64 | F26: 64.2
A27: Implied fixed revenue per subscriber (AED/month) | B27: 537 | C27: 545 | D27: 553 | E27: 561 | F27: 569
A28: Wholesale revenue growth | B28: -0.008 | C28: 0.015 | D28: 0.02 | E28: 0.02 | F28: 0.02
A29: ICT and associated telecom revenue growth | B29: 0.079 | C29: 0.11 | D29: 0.1 | E29: 0.09 | F29: 0.08
A31: Direct-cost stack — cost per unit, one escalator per driver class. CONTRIBUTION MARGIN IS NOT AN INPUT HERE: it is computed on the Segments sheet as what is left after each cost line is grown on its own physical driver.
A32: Mobile interconnect cost, H1-2026 actual (AED/subscriber/month) | C32: 16.813808
A33: Mobile interconnect escalator (termination rates, OTT substitution) | C33: -0.015
A34: Mobile commission cost, H1-2026 actual (AED/subscriber/month) | C34: 6.3068549
A35: Mobile commission escalator (acquisition/retention cost) | C35: 0.03
A36: Mobile devices and direct services, H1-2026 actual (AED/subscriber/month) | C36: 0.95654235
A37: Mobile devices escalator (held flat — lumpy, no trend read into it) | C37: 0
A38: Fixed capacity and direct cost, H1-2026 actual (AED/subscriber/month) | C38: 68.353167
A39: Fixed capacity escalator (held flat against an observed decline) | C39: 0
A40: Wholesale direct cost / wholesale revenue (H1-2026 rate, held flat) | C40: 0.1558
A41: ICT direct cost / ICT revenue (H1-2026 rate, held flat) | C41: 0.7848
A42: Mobile direct cost, six months to 30-Jun-2026 (AED mn, reviewed) | C42: 1371.245
A43: Fixed direct cost, six months to 30-Jun-2026 (AED mn, reviewed) | C43: 303.283
... A46: Blended ARPU drift (mix-exhaustion sensitivity; zero in the base case) | C46: 0
A48: Operating expense stack — one escalator per cost class
A49: Staff cost, FY2026E level (AED mn) | C49: 1035.16
A50: Staff escalator (UAE wage inflation) | C50: 0.02
A51: Network & maintenance, FY2025 base (AED mn, audited) | C51: 963.878
A52: Network escalator (network scale) | C52: 0.03
A53: Administrative expense, FY2025 base (AED mn, audited) | C53: 189.654
A54: Administrative escalator (CPI) | C54: 0.02
A55: Other operating expense, FY2025 base (AED mn, audited) | C55: 133.192
A56: Other-expense escalator (CPI) | C56: 0.02
A57: Marketing / revenue | C57: 0.018
A58: Telecom licence and related fees / revenue (regulatory revenue share) | C58: 0.027
A59: Expected credit losses / revenue | C59: 0.0145
A60: Other operating income (AED mn/yr) | C60: 15
A62: Capital intensity and working capital
A63: Capital expenditure / revenue | B63: 0.155 | C63: 0.15 | D63: 0.145 | E63: 0.135 | F63: 0.13
A64: Tangible share of capex (audited FY2025) | C64: 0.866
A65: PP&E depreciation rate on opening balance (audited FY2025) | C65: 0.1583
A66: Intangibles amortisation rate on opening balance (audited FY2025) | C66: 0.289
A67: Lease replacement charged inside the explicit window (AED mn) — ZERO by construction: the lease liability is deducted in FULL as debt in the bridge, so charging renewal here as well would bill the same obligation twice. The renewal is paid for in the terminal instead. This row carried the retired replacement path (355 / 350 / 345 / 340 / 335) until 08-09-2026, live in the delivered workbook, while the study document printed zeros for the same row | B67: 355 | C67: 350 | D67: 345 | E67: 340 | F67: 335
A68: Net working capital / revenue (audited FY2025 component days) | C68: -0.066797477
A70: Cost of capital
A71: Risk-free rate — Jan-2031 AED T-bond (longest liquid AED tenor) | C71: 0.0448
A72: UAE sovereign default spread (netted out; MARKET-observed basis, +4bp over UST on this very bond — the RATINGS-table basis is 42bp and is the published alternative, not this cell; the label said "Aa2 rating basis" until 08-09-2026) | C72: 0.0004
A73: Equity risk premium (UAE total, MARKET basis — mature 4.23% plus a country premium scaled off the SAME 4bp that was stripped above; the ratings basis is 4.87% and is the published alternative. The label said "rating basis" until 08-09-2026) | C73: 0.0429
A74: Beta (DU weekly vs FTSE ADX General, 5y) | C74: 0.5568988
A75: Marginal cost of debt (AED sovereign + GCC telecom spread) | C75: 0.051
A76: AED risk-free path (defines the glide) | B76: 0.0448 | C76: 0.0444 | D76: 0.0439 | E76: 0.0435 | F76: 0.043
A77: Terminal risk-free rate | C77: 0.043
A78: Terminal equity risk premium | C78: 0.0429
A79: Terminal cost of debt | C79: 0.049
A80: Terminal debt weight | C80: 0.05
A81: Terminal REAL growth (stated, not derived) | C81: 0
A82: Terminal inflation — UAE house macro path | C82: 0.02
A83: Weighted asset life, DERIVED from notes 6 and 8 (gross cost of the depreciable owned base over the year's own charge) | C83: 16.699659
A84: Terminal growth = (1+inflation)(1+real growth) − 1 | C84: =(1+$C$82)*(1+$C$81)-1
A86: Balance-sheet and bridge anchors
A87: Lease liabilities at FY2025 (AED mn, audited — the only debt-like item) | C87: 1938.819
A88: Cash and term deposits at FY2025 (AED mn, audited) | C88: 2249.719
A89: Equity-accounted investees at carrying value (AED mn) | C89: 0.511
A90: Forecast dividend payout ratio (FY2024 actual 98%, FY2025 ~100%) | C90: 0.98
A91: Yield on cash and term deposits (audited FY2025 effective) | C91: 0.033
A92: Lease interest rate (audited FY2025 effective) | C92: 0.036
A93: Dividends gone ex between 31-Dec-2025 and the anchor (AED/share) | C93: 0.66
A94: Days from the 31-Dec-2025 valuation date to the 2026-09-07 price anchor | C94: 250
A95: Incremental capital per unit of real terminal growth (AED mn) — DERIVED from the forecast's own invested-capital and revenue paths: (IC(FY30E) − IC(FY26E)) / (revenue(FY30E) − revenue(FY26E)) x revenue(FY30E). It is what a unit of real growth would cost, and the terminal charges for it. This figure was a LITERAL inside the terminal formula until 08-09-2026, so the workbook stopped repricing off-base | C95: 10429.869
A97: Lens inputs
A98: Justified price/earnings — Mobily's own, re-derived from its issuer filings. NOT A PEER MEDIAN and this study claims none: only two of six peers survive as clean observations. The label read "GCC telecom peer median" until 08-09-2026 | C98: 12.9
A99: Peer benchmark dividend yield | C99: 0.0489
A100: Sustainable return on equity | C100: 0.27

Sheet SOTP Bridge
A1: Enterprise value to equity — the bridge
A2: du has no drawn borrowings and no minority interests: the bridge is leases out, cash and deposits in
A4: Step | B4: AED mn | C4: Per share (AED)
A5: Present value of the five forecast years | C5: =DCF!C27 | D5: =C5/Assumptions!$C$6
A6: Present value of the terminal value | C6: =DCF!C28 | D6: =C6/Assumptions!$C$6
A7: Enterprise value | C7: =C5+C6 | D7: =C7/Assumptions!$C$6
A8: Less lease liabilities (the only debt-like item) | C8: =-Assumptions!$C$87 | D8: =C8/Assumptions!$C$6
A9: Plus cash and term deposits | C9: =Assumptions!$C$88 | D9: =C9/Assumptions!$C$6
A10: Plus equity-accounted investees at carrying value | C10: =Assumptions!$C$89 | D10: =C10/Assumptions!$C$6
A11: Equity value | C11: =C7+C8+C9+C10 | D11: =C11/Assumptions!$C$6
A13: Terminal value as a share of enterprise value | C13: =DCF!C29
A14: No minority interests: every subsidiary is wholly owned (the two H1-2026 Cayman SPVs are 100%-held); non-controlling interests do not appear on the audited balance sheet.

Sheet Segments
A1: Segments — the unit build and the margin stack
A2: FY2025 disclosed revenue and contribution margins; forecast segment revenue is the unit build's OUTPUT (pasted, blue) and everything below it is formula
A4: Segment | B4: FY2025 revenue | C4: Share | D4: FY2025 margin | E4: FY26E | F4: FY27E | G4: FY28E | H4: FY29E | I4: FY30E
A5: Mobile | B5: 7074.936 | C5: =B5/$B$9 | D5: 0.60829412 | E5: =Assumptions!$C$14+(Assumptions!$C$16+Assumptions!$B$24)/2*Assumptions!$B$26*6/1000 | F5: =(Assumptions!$B$24+Assumptions!$C$24)/2*Assumptions!$C$26*(1+Assumptions!$C$46)^1*12/1000 | G5: =(Assumptions!$C$24+Assumptions!$D$24)/2*Assumptions!$D$26*(1+Assumptions!$C$46)^2*12/1000 | H5: =(Assumptions!$D$24+Assumptions!$E$24)/2*Assumptions!$E$26*(1+Assumptions!$C$46)^3*12/1000 | I5: =(Assumptions!$E$24+Assumptions!$F$24)/2*Assumptions!$F$26*(1+Assumptions!$C$46)^4*12/1000
A6: Fixed | B6: 4379.705 | C6: =B6/$B$9 | D6: 0.85801509 | E6: =Assumptions!$C$15+(Assumptions!$C$17+Assumptions!$B$25)/2*Assumptions!$B$27*6/1000 | F6: =(Assumptions!$B$25+Assumptions!$C$25)/2*Assumptions!$C$27*(1+Assumptions!$C$46)^1*12/1000 | G6: =(Assumptions!$C$25+Assumptions!$D$25)/2*Assumptions!$D$27*(1+Assumptions!$C$46)^2*12/1000 | H6: =(Assumptions!$D$25+Assumptions!$E$25)/2*Assumptions!$E$27*(1+Assumptions!$C$46)^3*12/1000 | I6: =(Assumptions!$E$25+Assumptions!$F$25)/2*Assumptions!$F$27*(1+Assumptions!$C$46)^4*12/1000
A7: Wholesale | B7: 2568.222 | C7: =B7/$B$9 | D7: 0.86420605 | E7: =Assumptions!$C$18*(1+Assumptions!$B$28) | F7: =E7*(1+Assumptions!$C$28) | G7: =F7*(1+Assumptions!$D$28) | H7: =G7*(1+Assumptions!$E$28) | I7: =H7*(1+Assumptions!$F$28)
A8: ICT and associated telecom services | B8: 1882.558 | C8: =B8/$B$9 | D8: 0.1939 | E8: =Assumptions!$C$19*(1+Assumptions!$B$29) | F8: =E8*(1+Assumptions!$C$29) | G8: =F8*(1+Assumptions!$D$29) | H8: =G8*(1+Assumptions!$E$29) | I8: =H8*(1+Assumptions!$F$29)
A9: Total revenue | B9: =SUM(B5:B8) | C9: =SUM(C5:C8) | E9: =SUM(E5:E8) | F9: =SUM(F5:F8) | G9: =SUM(G5:G8) | H9: =SUM(H5:H8) | I9: =SUM(I5:I8)
A11: Direct cost per unit — each line grown on its own physical driver | B11: FY26E | C11: FY27E | D11: FY28E | E11: FY29E | F11: FY30E
A12: Mobile interconnect (AED per subscriber per month) | B12: =Assumptions!$C$32*(1+Assumptions!$C$33)^0 | C12: =Assumptions!$C$32*(1+Assumptions!$C$33)^1 | D12: =Assumptions!$C$32*(1+Assumptions!$C$33)^2 | E12: =Assumptions!$C$32*(1+Assumptions!$C$33)^3 | F12: =Assumptions!$C$32*(1+Assumptions!$C$33)^4
A13: Mobile commission (AED per subscriber per month) | B13: =Assumptions!$C$34*(1+Assumptions!$C$35)^0 | C13: =Assumptions!$C$34*(1+Assumptions!$C$35)^1 | D13: =Assumptions!$C$34*(1+Assumptions!$C$35)^2 | E13: =Assumptions!$C$34*(1+Assumptions!$C$35)^3 | F13: =Assumptions!$C$34*(1+Assumptions!$C$35)^4
A14: Mobile devices and direct services (AED per subscriber per month) | B14: =Assumptions!$C$36*(1+Assumptions!$C$37)^0 | C14: =Assumptions!$C$36*(1+Assumptions!$C$37)^1 | D14: =Assumptions!$C$36*(1+Assumptions!$C$37)^2 | E14: =Assumptions!$C$36*(1+Assumptions!$C$37)^3 | F14: =Assumptions!$C$36*(1+Assumptions!$C$37)^4
A15: Mobile — total direct cost per subscriber per month | B15: =B12+B13+B14 | C15: =C12+C13+C14 | D15: =D12+D13+D14 | E15: =E12+E13+E14 | F15: =F12+F13+F14
A16: Fixed capacity and direct cost (AED per subscriber per month) | B16: =Assumptions!$C$38*(1+Assumptions!$C$39)^0 | C16: =Assumptions!$C$38*(1+Assumptions!$C$39)^1 | D16: =Assumptions!$C$38*(1+Assumptions!$C$39)^2 | E16: =Assumptions!$C$38*(1+Assumptions!$C$39)^3 | F16: =Assumptions!$C$38*(1+Assumptions!$C$39)^4
A17: Wholesale direct cost / wholesale revenue (no disclosed unit — flagged) | B17: =Assumptions!$C$40 | C17: =Assumptions!$C$40 | D17: =Assumptions!$C$40 | E17: =Assumptions!$C$40 | F17: =Assumptions!$C$40
A18: ICT direct cost / ICT revenue (no disclosed unit — flagged) | B18: =Assumptions!$C$41 | C18: =Assumptions!$C$41 | D18: =Assumptions!$C$41 | E18: =Assumptions!$C$41 | F18: =Assumptions!$C$41
A20: Direct cost (AED mn) — volume x cost per unit | B20: FY26E | C20: FY27E | D20: FY28E | E20: FY29E | F20: FY30E
A21: Mobile | B21: =Assumptions!$C$42+(Assumptions!$C$16+Assumptions!$B$24)/2*B15*6/1000 | C21: =(Assumptions!$B$24+Assumptions!$C$24)/2*C15*12/1000 | D21: =(Assumptions!$C$24+Assumptions!$D$24)/2*D15*12/1000 | E21: =(Assumptions!$D$24+Assumptions!$E$24)/2*E15*12/1000 | F21: =(Assumptions!$E$24+Assumptions!$F$24)/2*F15*12/1000
A22: Fixed | B22: =Assumptions!$C$43+(Assumptions!$C$17+Assumptions!$B$25)/2*B16*6/1000 | C22: =(Assumptions!$B$25+Assumptions!$C$25)/2*C16*12/1000 | D22: =(Assumptions!$C$25+Assumptions!$D$25)/2*D16*12/1000 | E22: =(Assumptions!$D$25+Assumptions!$E$25)/2*E16*12/1000 | F22: =(Assumptions!$E$25+Assumptions!$F$25)/2*F16*12/1000
A23: Wholesale | B23: =Assumptions!$C$44+(E7-Assumptions!$C$20)*B17 | C23: =F7*C17 | D23: =G7*D17 | E23: =H7*E17 | F23: =I7*F17
A24: ICT and associated telecom services | B24: =Assumptions!$C$45+(E8-Assumptions!$C$21)*B18 | C24: =F8*C18 | D24: =G8*D18 | E24: =H8*E18 | F24: =I8*F18
A25: Total direct cost | B25: =SUM(B21:B24) | C25: =SUM(C21:C24) | D25: =SUM(D21:D24) | E25: =SUM(E21:E24) | F25: =SUM(F21:F24)
A27: Contribution = revenue less direct cost — AN OUTPUT, NOT AN INPUT | B27: FY26E | C27: FY27E | D27: FY28E | E27: FY29E | F27: FY30E
A28: Mobile | B28: =E5-B21 | C28: =F5-C21 | D28: =G5-D21 | E28: =H5-E21 | F28: =I5-F21
A29: Fixed | B29: =E6-B22 | C29: =F6-C22 | D29: =G6-D22 | E29: =H6-E22 | F29: =I6-F22
A30: Wholesale | B30: =E7-B23 | C30: =F7-C23 | D30: =G7-D23 | E30: =H7-E23 | F30: =I7-F23
A31: ICT and associated telecom services | B31: =E8-B24 | C31: =F8-C24 | D31: =G8-D24 | E31: =H8-E24 | F31: =I8-F24
A32: Total contribution | B32: =SUM(B28:B31) | C32: =SUM(C28:C31) | D32: =SUM(D28:D31) | E32: =SUM(E28:E31) | F32: =SUM(F28:F31)
A34: Contribution margin — computed, never assumed | B34: FY26E | C34: FY27E | D34: FY28E | E34: FY29E | F34: FY30E
A35: Mobile | B35: =B28/E5 | C35: =C28/F5 | D35: =D28/G5 | E35: =E28/H5 | F35: =F28/I5
A36: Fixed | B36: =B29/E6 | C36: =C29/F6 | D36: =D29/G6 | E36: =E29/H6 | F36: =F29/I6
A37: Wholesale | B37: =B30/E7 | C37: =C30/F7 | D37: =D30/G7 | E37: =E30/H7 | F37: =F30/I7
A38: ICT and associated telecom services | B38: =B31/E8 | C38: =C31/F8 | D38: =D31/G8 | E38: =E31/H8 | F38: =F31/I8
A39: Group gross margin | B39: =B32/E9 | C39: =C32/F9 | D39: =D32/G9 | E39: =E32/H9 | F39: =F32/I9
A41: Operating expense stack — one escalator per cost class | B41: FY26E | C41: FY27E | D41: FY28E | E41: FY29E | F41: FY30E
A42: Staff (wage escalator) | B42: =Assumptions!$C$49*(1+Assumptions!$C$50)^0 | C42: =Assumptions!$C$49*(1+Assumptions!$C$50)^1 | D42: =Assumptions!$C$49*(1+Assumptions!$C$50)^2 | E42: =Assumptions!$C$49*(1+Assumptions!$C$50)^3 | F42: =Assumptions!$C$49*(1+Assumptions!$C$50)^4
A43: Network & maintenance (network-scale escalator) | B43: =Assumptions!$C$51*(1+Assumptions!$C$52)^1 | C43: =Assumptions!$C$51*(1+Assumptions!$C$52)^2 | D43: =Assumptions!$C$51*(1+Assumptions!$C$52)^3 | E43: =Assumptions!$C$51*(1+Assumptions!$C$52)^4 | F43: =Assumptions!$C$51*(1+Assumptions!$C$52)^5
A44: Marketing (% of revenue) | B44: =E9*Assumptions!$C$57 | C44: =F9*Assumptions!$C$57 | D44: =G9*Assumptions!$C$57 | E44: =H9*Assumptions!$C$57 | F44: =I9*Assumptions!$C$57
A45: Telecom licence and related fees (% of revenue) | B45: =E9*Assumptions!$C$58 | C45: =F9*Assumptions!$C$58 | D45: =G9*Assumptions!$C$58 | E45: =H9*Assumptions!$C$58 | F45: =I9*Assumptions!$C$58
A46: Administrative (CPI escalator) | B46: =Assumptions!$C$53*(1+Assumptions!$C$54)^1 | C46: =Assumptions!$C$53*(1+Assumptions!$C$54)^2 | D46: =Assumptions!$C$53*(1+Assumptions!$C$54)^3 | E46: =Assumptions!$C$53*(1+Assumptions!$C$54)^4 | F46: =Assumptions!$C$53*(1+Assumptions!$C$54)^5
A47: Other operating expense (CPI escalator) | B47: =Assumptions!$C$55*(1+Assumptions!$C$56)^1 | C47: =Assumptions!$C$55*(1+Assumptions!$C$56)^2 | D47: =Assumptions!$C$55*(1+Assumptions!$C$56)^3 | E47: =Assumptions!$C$55*(1+Assumptions!$C$56)^4 | F47: =Assumptions!$C$55*(1+Assumptions!$C$56)^5
A48: Expected credit losses (% of revenue) | B48: =E9*Assumptions!$C$59 | C48: =F9*Assumptions!$C$59 | D48: =G9*Assumptions!$C$59 | E48: =H9*Assumptions!$C$59 | F48: =I9*Assumptions!$C$59
A49: Less other operating income | B49: =-Assumptions!$C$60 | C49: =-Assumptions!$C$60 | D49: =-Assumptions!$C$60 | E49: =-Assumptions!$C$60 | F49: =-Assumptions!$C$60
A50: Total operating expenses before D&A | B50: =SUM(B42:B49) | C50: =SUM(C42:C49) | D50: =SUM(D42:D49) | E50: =SUM(E42:E49) | F50: =SUM(F42:F49)
A51: Group EBITDA (contribution less the opex stack) | B51: =B32-B50 | C51: =C32-C50 | D51: =D32-D50 | E51: =E32-E50 | F51: =F32-F50
A52: Group EBITDA margin | B52: =B51/E$9 | C52: =C51/F$9 | D52: =D51/G$9 | E52: =E51/H$9 | F52: =F51/I$9
A54: The unit build behind Mobile and Fixed (triangulation shown, not asserted) | B54: FY26E | C54: FY27E | D54: FY28E | E54: FY29E | F54: FY30E
A55: Mobile subscribers, end of year ('000) | B55: =Assumptions!$B$24 | C55: =Assumptions!$C$24 | D55: =Assumptions!$D$24 | E55: =Assumptions!$E$24 | F55: =Assumptions!$F$24
A56: Average mobile base ('000) — (prior end + end)/2 | B56: =(9280+Assumptions!$B$24)/2 | C56: =(Assumptions!$B$24+Assumptions!$C$24)/2 | D56: =(Assumptions!$C$24+Assumptions!$D$24)/2 | E56: =(Assumptions!$D$24+Assumptions!$E$24)/2 | F56: =(Assumptions!$E$24+Assumptions!$F$24)/2
A57: Blended mobile ARPU (AED/month) | B57: =Assumptions!$B$26 | C57: =Assumptions!$C$26 | D57: =Assumptions!$D$26 | E57: =Assumptions!$E$26 | F57: =Assumptions!$F$26
A58: Unit-implied mobile revenue — average base x ARPU x 12 (FY2026 is H1 actual + unit-built H2, so the check applies from FY2027) | B58: - | C58: =C56*C57*12/1000 | D58: =D56*D57*12/1000 | E58: =E56*E57*12/1000 | F58: =F56*F57*12/1000
A59: Pasted mobile segment revenue (the build output above) | B59: =E5 | C59: =F5 | D59: =G5 | E59: =H5 | F59: =I5
A60: Check — unit-implied less pasted | B60: - | C60: =C58-C59 | D60: =D58-D59 | E60: =E58-E59 | F60: =F58-F59
A61: FY2025 reconciliation: average base 9,310k x ARPU 63.3 x 12 = 7,072 vs the audited mobile segment 7,075 (−0.04%). Wholesale and ICT have no disclosed unit KPIs — segment-level growth is the finest sourced level, and that gap is flagged.

Sheet Relative & Normalized
A1: Relative multiples and normalised earnings power
A4: Relative lens | B4: Value
A5: FY2026E earnings per share (AED) | C5: ='Income Statement'!E19
A6: Justified price / earnings (Mobily's own, from its issuer filings — no peer median is claimed) | C6: =Assumptions!$C$98
A7: Implied value at 31-Dec-2025 (AED) | C7: =C5*C6
A8: Anchor accretion factor | C8: =DCF!C62
A9: Less dividends gone ex between the valuation date and the anchor (0.40 final + 0.26 interim, AED) | C9: =Assumptions!$C$93
A11: Implied value per share at the anchor (AED) | C11: =C7*C8-C9
A12: Bear at 12.0x (C) / bull at 18.5x (D), same construction | C12: =C5*12*C8-C9 | D12: =C5*18.5*C8-C9
A13: Trailing price / earnings | C13: =Assumptions!$C$5/'Income Statement'!D19
A14: Trailing enterprise value / EBITDA | C14: =((Assumptions!$C$5*Assumptions!$C$6)+Assumptions!$C$87-Assumptions!$C$88)/'Income Statement'!D9
A15: Dividend-yield cross: FY2026E dividend per share (AED) | C15: ='Income Statement'!E20
A16: Peer benchmark dividend yield | C16: =Assumptions!$C$99
A17: Implied value from the yield cross (AED) | C17: =C15/C16
A19: Normalised earnings lens — mid-cycle margin (FY2028E) at current (FY2026E) scale | B19: Value
A20: Current-scale revenue (FY2026E, AED mn) | C20: =DCF!B5
A21: Mid-cycle EBITDA margin (FY2028E) | C21: =DCF!D7
A22: Normalised EBITDA (AED mn) | C22: =C20*C21
A23: Normalised EBIT (AED mn) — less FY2026E depreciation and amortisation | C23: =C22+'Income Statement'!E11
A24: Net finance income (FY2026E, AED mn) | C24: ='Income Statement'!E13+'Income Statement'!E14
A25: Normalised net profit (AED mn) | C25: =(C23+C24)*(1-Assumptions!$C$8)
A26: Normalised earnings per share (AED) | C26: =C25/Assumptions!$C$6
A27: Implied value per share at the anchor (AED) | C27: =C26*Assumptions!$C$98*DCF!$C$62-Assumptions!$C$93 | D27: bear 12.0x (E) / bull 18.5x (F): | E27: =C26*12*DCF!$C$62-Assumptions!$C$93 | F27: =C26*18.5*DCF!$C$62-Assumptions!$C$93
A29: Book lens | B29: Value
A30: Book value per share (AED) | C30: ='Balance Sheet'!D14/Assumptions!$C$6
A31: Sustainable return on equity | C31: =Assumptions!$C$100
A32: Trailing return on equity | C32: ='Income Statement'!D18/(('Balance Sheet'!C14+'Balance Sheet'!D14)/2)
A33: Perpetual (terminal) cost of equity — a steady-state multiple takes a steady-state rate | C33: =DCF!C50
A34: Justified price / book | C34: =(C31-Assumptions!$C$84)/(C33-Assumptions!$C$84)
A35: Implied value per share at the anchor (AED) | C35: =C30*C34*DCF!$C$62-Assumptions!$C$93 | D35: bear / bull constructions (E / F): | E35: =((Assumptions!$C$100-Assumptions!$C$84)/((DCF!C40+DCF!C50)/2+0.01-Assumptions!$C$84))*C30*DCF!$C$62-Assumptions!$C$93 | F35: =((Assumptions!$C$100+0.02-Assumptions!$C$84)/(DCF!C50-Assumptions!$C$84))*C30*DCF!$C$62-Assumptions!$C$93

Sheet DCF
A1: Discounted cash flow — the full waterfall
A2: Every line is a live formula: the cost of capital is built below, the glide is derived from the AED risk-free path, and the terminal value is capitalised at the terminal rate and discounted at the year-5 factor
A4: AED mn | B4: FY26E | C4: FY27E | D4: FY28E | E4: FY29E | F4: FY30E
A5: Revenue | B5: =Segments!E9 | C5: =Segments!F9 | D5: =Segments!G9 | E5: =Segments!H9 | F5: =Segments!I9
A6: EBITDA | B6: =Segments!B51 | C6: =Segments!C51 | D6: =Segments!D51 | E6: =Segments!E51 | F6: =Segments!F51
A7: EBITDA margin | B7: =B6/B5 | C7: =C6/C5 | D7: =D6/D5 | E7: =E6/E5 | F7: =F6/F5
A8: Less depreciation and amortisation | B8: ='Income Statement'!E11 | C8: ='Income Statement'!F11 | D8: ='Income Statement'!G11 | E8: ='Income Statement'!H11 | F8: ='Income Statement'!I11
A9: EBIT | B9: =B6+B8 | C9: =C6+C8 | D9: =D6+D8 | E9: =E6+E8 | F9: =F6+F8
A10: NOPAT — EBIT less the combined royalty and tax charge at 43.6%, FLOORED at the disclosed AED 1,800mn (it does not bind in the base case) | B10: =B9-MAX(B9*Assumptions!$C$8,Assumptions!$C$7) | C10: =C9-MAX(C9*Assumptions!$C$8,Assumptions!$C$7) | D10: =D9-MAX(D9*Assumptions!$C$8,Assumptions!$C$7) | E10: =E9-MAX(E9*Assumptions!$C$8,Assumptions!$C$7) | F10: =F9-MAX(F9*Assumptions!$C$8,Assumptions!$C$7)
A11: Add back depreciation and amortisation | B11: =-B8 | C11: =-C8 | D11: =-D8 | E11: =-E8 | F11: =-F8
A12: Less capital expenditure | B12: =-B5*Assumptions!$B$63 | C12: =-C5*Assumptions!$C$63 | D12: =-D5*Assumptions!$D$63 | E12: =-E5*Assumptions!$E$63 | F12: =-F5*Assumptions!$F$63
A13: Memo — lease replacement at right-of-use depreciation, NOT deducted (leases are debt) | B13: =Assumptions!$B$67 | C13: =Assumptions!$C$67 | D13: =Assumptions!$D$67 | E13: =Assumptions!$E$67 | F13: =Assumptions!$F$67
A14: Less change in working capital | B14: =-(B5*Assumptions!$C$68-'Balance Sheet'!D11) | C14: =-(C5-B5)*Assumptions!$C$68 | D14: =-(D5-C5)*Assumptions!$C$68 | E14: =-(E5-D5)*Assumptions!$C$68 | F14: =-(F5-E5)*Assumptions!$C$68
A15: Free cash flow to the firm | B15: =B10+B11+B12+B14 | C15: =C10+C11+C12+C14 | D15: =D10+D11+D12+D14 | E15: =E10+E11+E12+E14 | F15: =F10+F11+F12+F14
A16: Forward cost of capital | B16: =$C$47-($C$47-$C$54)*B58 | C16: =$C$47-($C$47-$C$54)*C58 | D16: =$C$47-($C$47-$C$54)*D58 | E16: =$C$47-($C$47-$C$54)*E58 | F16: =$C$47-($C$47-$C$54)*F58
A17: Discount factor | B17: =1/(1+B16) | C17: =B17/(1+C16) | D17: =C17/(1+D16) | E17: =D17/(1+E16) | F17: =E17/(1+F16)
A18: Present value of FCFF | B18: =B15*B17 | C18: =C15*C17 | D18: =D15*D17 | E18: =E15*E17 | F18: =F15*F17
A20: TERMINAL VALUE, BRIDGE AND THE ANCHOR ROLL
A21: FY2030E operating profit after tax — the perpetuity grows this once (AED mn) | C21: =F10
A22: Terminal free cash flow — built line by line at rows 70-77 (AED mn) | C22: =C77
A23: Terminal free cash flow as a share of terminal profit | C23: =C22/C21
A24: Terminal growth — (1+inflation)(1+real growth)−1, both at rows 70-71 | C24: =(1+C70)*(1+C71)-1
A25: Terminal cost of capital | C25: =C54
A26: Terminal value — terminal free cash flow C22 grown one year, capitalised (AED mn) | C26: =C22*(1+C24)/(C25-C24)
A27: Present value of the five forecast years (AED mn) | C27: =SUM(B18:F18)
A28: Present value of the terminal value (AED mn) | C28: =C26*F17
A29: Terminal value as a share of enterprise value | C29: =C28/(C27+C28)
A30: Enterprise value (AED mn) | C30: =C27+C28
A31: Equity value (AED mn) | C31: ='SOTP Bridge'!C11
A32: Fair value per share at 31-Dec-2025 (AED) | C32: =C31/Assumptions!$C$6
A34: COST OF CAPITAL — BUILT HERE, NOT ASSUMED
A35: Risk-free rate — Jan-2031 AED T-bond (longest liquid AED tenor) | C35: =Assumptions!$C$71
A36: Less UAE sovereign default spread (removed to avoid double-counting) | C36: =Assumptions!$C$72
A37: Risk-free rate net of the sovereign spread | C37: =C35-C36
A38: Beta (DU weekly vs the FTSE ADX General, 5 years) | C38: =Assumptions!$C$74
A39: Equity risk premium (UAE total, MARKET basis) | C39: =Assumptions!$C$73
A40: Cost of equity, explicit window | C40: =C37+C38*C39
A41: Marginal cost of debt (AED sovereign + GCC telecom spread) | C41: =Assumptions!$C$75
A42: Cost of debt after tax (interest shields both fiscal legs) | C42: =C41*(1-Assumptions!$C$8)
A43: Market capitalisation (AED mn) | C43: =Assumptions!$C$5*Assumptions!$C$6
A44: Lease liabilities — the only debt-like item (AED mn) | C44: =Assumptions!$C$87
A45: Debt weight (leases / (leases + market capitalisation)) | C45: =C44/(C44+C43)
A46: Equity weight | C46: =1-C45
A47: Cost of capital, explicit window | C47: =C46*C40+C45*C42
A48: Terminal risk-free rate | C48: =Assumptions!$C$77
A49: Terminal risk-free net of the sovereign spread | C49: =C48-C36
A50: Terminal cost of equity | C50: =C49+C38*Assumptions!$C$78
A51: Terminal cost of debt | C51: =Assumptions!$C$79
A52: Terminal cost of debt after tax | C52: =C51*(1-Assumptions!$C$8)
A53: Terminal debt weight | C53: =Assumptions!$C$80
A54: Terminal cost of capital | C54: =(1-C53)*C50+C53*C52
A56: The glide — inherited from the AED risk-free path, not invented | B56: FY26E | C56: FY27E | D56: FY28E | E56: FY29E | F56: FY30E
A57: AED risk-free path | B57: =Assumptions!$B$76 | C57: =Assumptions!$C$76 | D57: =Assumptions!$D$76 | E57: =Assumptions!$E$76 | F57: =Assumptions!$F$76
A58: Glide fraction — cumulative progress of the easing | B58: =($B$57-B57)/($B$57-$F$57) | C58: =($B$57-C57)/($B$57-$F$57) | D58: =($B$57-D57)/($B$57-$F$57) | E58: =($B$57-E57)/($B$57-$F$57) | F58: =($B$57-F57)/($B$57-$F$57)
A59: Note: row 16 above is the explicit-window cost of capital walked down to the terminal rate by the glide fraction on row 58. du carries no debt whose cost could define the glide, so the cost-of-money path itself (the AED risk-free path) does — the shape is inherited, not a second free parameter.
A61: THE ANCHOR ROLL — one date, one price of time
A62: Anchor accretion factor — (1 + cost of equity)^(days to anchor / 365) | C62: =(1+C40)^(Assumptions!$C$94/365)
A63: Fair value per share at the 2026-09-07 anchor (AED) | C63: =C32*C62-Assumptions!$C$93
A64: The bridge on row 32 is dated 31-Dec-2025 (the audited balance-sheet date it nets leases and cash at). Row 63 rolls it to the anchor at the cost of equity, net of the AED 0.66 of dividends whose EX-DATE falls in between — TWO dividends, not one: the AED 0.40 final FY2025 (ex 12-Mar-2026, paid 28-Apr-2026) and the AED 0.26 H1-2026 interim (ex 31-Jul-2026, paid 21-Aug-2026). Every lens on every sheet is rolled the same way. This note said the interim "stays in the share" until 08-09-2026, beside a cell that had netted it since 17 August.
A66: THE TERMINAL, LINE BY LINE — capital maintained at replacement cost over the asset life the depreciation notes themselves imply
A67: The retired construction grew terminal profit and deducted a reinvestment rate set by the growth rate over the return on capital, which is arithmetically the same as rebuilding the whole capital base every 1/g years — a fact about the dirham's peg to the dollar rather than about a mobile network. The asset life below is DERIVED from notes 6 and 8: the gross cost of the depreciable owned base over the year's own charge.
A70: Terminal inflation — UAE house macro path | C70: =Assumptions!$C$82
A71: Terminal REAL growth (stated) | C71: =Assumptions!$C$81
A72: Weighted asset life, derived from notes 6 and 8 (years) | C72: =Assumptions!$C$83
A73: Terminal operating profit after tax (from row 21) | C73: =C21
A74: Plus depreciation and amortisation — THE FULL FY2030E charge, property, intangibles and right-of-use alike, because terminal profit is already struck after all of it and the lease renews in perpetuity like any other asset. This cell was a PASTED CONSTANT until 08-09-2026, and its label said the right-of-use charge was neither added back nor charged, which is the reverse of what the model does | C74: =-F8
A75: Less capital maintenance at replacement cost — that charge escalated over half the derived life | C75: =-C74*(1+C70)^(C72/2)
A76: Less capital for real growth, and less inflation on working capital (a CREDIT here: this company collects before it pays). BOTH constants inside this formula were pasted until 08-09-2026; both are links now | C76: =-C71*Assumptions!$C$95-C70*(F5*Assumptions!$C$68)
A77: Terminal free cash flow | C77: =SUM(C73:C76)
A78: Memo — the no-growth perpetuity at book depreciation, a diagnostic and not a bound | C78: =C21/C25

Sheet Income Statement
A1: Income statement — three years historical, five years forecast
A2: AED mn, consolidated. History is the audited record; every forecast line is a formula
A4: AED mn | B4: FY2023 | C4: FY2024 | D4: FY2025 | E4: FY26E | F4: FY27E | G4: FY28E | H4: FY29E | I4: FY30E
A5: Revenue | B5: 13636.34 | C5: 14635.917 | D5: 15905.421 | E5: =DCF!B5 | F5: =DCF!C5 | G5: =DCF!D5 | H5: =DCF!E5 | I5: =DCF!F5
A6: Direct costs (interconnect, commissions, devices) | B6: - | C6: -4818.442 | D6: -5259.425 | E6: =-(DCF!B5-Segments!B32) | F6: =-(DCF!C5-Segments!C32) | G6: =-(DCF!D5-Segments!D32) | H6: =-(DCF!E5-Segments!E32) | I6: =-(DCF!F5-Segments!F32)
A7: Segment contribution | B7: - | C7: =C5+C6 | D7: =D5+D6 | E7: =E5+E6 | F7: =F5+F6 | G7: =G5+G6 | H7: =H5+H6 | I7: =I5+I6
A8: Operating expenses before D&A | B8: - | C8: -3347.636 | D8: -3307.608 | E8: =-Segments!B50 | F8: =-Segments!C50 | G8: =-Segments!D50 | H8: =-Segments!E50 | I8: =-Segments!F50
A9: EBITDA | B9: 5799.601 | C9: =C7+C8 | D9: =D7+D8 | E9: =DCF!B6 | F9: =DCF!C6 | G9: =DCF!D6 | H9: =DCF!E6 | I9: =DCF!F6
A10: EBITDA margin | B10: =B9/B5 | C10: =C9/C5 | D10: =D9/D5 | E10: =E9/E5 | F10: =F9/F5 | G10: =G9/G5 | H10: =H9/H5 | I10: =I9/I5
A11: Depreciation and amortisation | B11: -2198.277 | C11: -2153.59 | D11: -2167.933 | E11: =-('Balance Sheet'!E6+'Balance Sheet'!E9+Assumptions!$B$67) | F11: =-('Balance Sheet'!F6+'Balance Sheet'!F9+Assumptions!$C$67) | G11: =-('Balance Sheet'!G6+'Balance Sheet'!G9+Assumptions!$D$67) | H11: =-('Balance Sheet'!H6+'Balance Sheet'!H9+Assumptions!$E$67) | I11: =-('Balance Sheet'!I6+'Balance Sheet'!I9+Assumptions!$F$67)
A12: Operating profit (EBIT) | B12: =B9+B11 | C12: =C9+C11 | D12: =D9+D11 | E12: =E9+E11 | F12: =F9+F11 | G12: =G9+G11 | H12: =H9+H11 | I12: =I9+I11
A13: Interest income | B13: 61.327 | C13: 82.214 | D13: 74.672 | E13: =Assumptions!$C$91*MAX('Balance Sheet'!D12,0) | F13: =Assumptions!$C$91*MAX('Balance Sheet'!E12,0) | G13: =Assumptions!$C$91*MAX('Balance Sheet'!F12,0) | H13: =Assumptions!$C$91*MAX('Balance Sheet'!G12,0) | I13: =Assumptions!$C$91*MAX('Balance Sheet'!H12,0)
A14: Interest expense (principally leases) | B14: -101.43 | C14: -89.77 | D14: -95.054 | E14: =-Assumptions!$C$92*'Balance Sheet'!E13 | F14: =-Assumptions!$C$92*'Balance Sheet'!F13 | G14: =-Assumptions!$C$92*'Balance Sheet'!G13 | H14: =-Assumptions!$C$92*'Balance Sheet'!H13 | I14: =-Assumptions!$C$92*'Balance Sheet'!I13
A15: Share of equity-accounted investments | B15: -2.72 | C15: -2.427 | D15: -0.894
A16: Profit before federal royalty and income tax | B16: 3558.501 | C16: 4306.151 | D16: 5149.122 | E16: =E12+E13+E14 | F16: =F12+F13+F14 | G16: =G12+G13+G14 | H16: =H12+H13+H14 | I16: =I12+I13+I14
A17: Federal royalty and income tax | B17: -1890.65 | C17: -1818.604 | D17: -2244.037 | E17: =-E16*Assumptions!$C$8 | F17: =-F16*Assumptions!$C$8 | G17: =-G16*Assumptions!$C$8 | H17: =-H16*Assumptions!$C$8 | I17: =-I16*Assumptions!$C$8
A18: Net profit | B18: =B16+B17 | C18: =C16+C17 | D18: =D16+D17 | E18: =E16+E17 | F18: =F16+F17 | G18: =G16+G17 | H18: =H16+H17 | I18: =I16+I17
A19: Earnings per share (AED) | B19: =B18/Assumptions!$C$6 | C19: =C18/Assumptions!$C$6 | D19: =D18/Assumptions!$C$6 | E19: =E18/Assumptions!$C$6 | F19: =F18/Assumptions!$C$6 | G19: =G18/Assumptions!$C$6 | H19: =H18/Assumptions!$C$6 | I19: =I18/Assumptions!$C$6
A20: Dividend per share (AED) | B20: 0.34 | C20: 0.54 | D20: 0.64 | E20: =E19*Assumptions!$C$90 | F20: =F19*Assumptions!$C$90 | G20: =G19*Assumptions!$C$90 | H20: =H19*Assumptions!$C$90 | I20: =I19*Assumptions!$C$90
A22: Notes: FY2024-25 are the audited IFRS 18 face (EBITDA is printed); FY2023 predates IFRS 18 — its by-nature split is not shown ("-") and its EBITDA is derived from audited components and flagged. The historical profit-before-royalty line is the printed figure (small net-impairment items keep it from being a three-line sum; the forecast has none). FY2023 royalty is the old-regime charge (15% of regulated revenue + 30% of regulated profit); no corporate income tax existed before 2024.

Sheet Balance Sheet
A1: Balance sheet — condensed
A2: AED mn, consolidated. Every FY2023-25 line is the audited closing figure. du carries ZERO drawn borrowings in every year shown
A4: AED mn | B4: FY2023 | C4: FY2024 | D4: FY2025 | E4: FY26E | F4: FY27E | G4: FY28E | H4: FY29E | I4: FY30E
A5: Property, plant and equipment | B5: 9722.7 | C5: 9838.448 | D5: 10288.767 | E5: =D5-DCF!B12*Assumptions!$C$64-E6 | F5: =E5-DCF!C12*Assumptions!$C$64-F6 | G5: =F5-DCF!D12*Assumptions!$C$64-G6 | H5: =G5-DCF!E12*Assumptions!$C$64-H6 | I5: =H5-DCF!F12*Assumptions!$C$64-I6
A6: of which depreciation charge (memo) | B6: 1544.182 | C6: 1569.189 | D6: 1557.989 | E6: =Assumptions!$C$65*D5 | F6: =Assumptions!$C$65*E5 | G6: =Assumptions!$C$65*F5 | H6: =Assumptions!$C$65*G5 | I6: =Assumptions!$C$65*H5
A7: Right-of-use assets | B7: 1597.185 | C7: 1657.217 | D7: 1515.395 | E7: =$D$7 | F7: =$D$7 | G7: =$D$7 | H7: =$D$7 | I7: =$D$7
A8: Intangible assets (excl. goodwill) | B8: 1110.769 | C8: 846.932 | D8: 869.6 | E8: =D8-DCF!B12*(1-Assumptions!$C$64)-E9 | F8: =E8-DCF!C12*(1-Assumptions!$C$64)-F9 | G8: =F8-DCF!D12*(1-Assumptions!$C$64)-G9 | H8: =G8-DCF!E12*(1-Assumptions!$C$64)-H9 | I8: =H8-DCF!F12*(1-Assumptions!$C$64)-I9
A9: of which amortisation charge (memo) | B9: 209.053 | C9: 209.896 | D9: 245.881 | E9: =Assumptions!$C$66*D8 | F9: =Assumptions!$C$66*E8 | G9: =Assumptions!$C$66*F8 | H9: =Assumptions!$C$66*G8 | I9: =Assumptions!$C$66*H8
A10: Goodwill | B10: - | C10: 413.22 | D10: 413.22 | E10: =$D$10 | F10: =$D$10 | G10: =$D$10 | H10: =$D$10 | I10: =$D$10
A11: Net working capital (royalty accrual excluded) | B11: -964.851 | C11: -1220.184 | D11: -1062.442 | E11: ='Income Statement'!E5*Assumptions!$C$68 | F11: ='Income Statement'!F5*Assumptions!$C$68 | G11: ='Income Statement'!G5*Assumptions!$C$68 | H11: ='Income Statement'!H5*Assumptions!$C$68 | I11: ='Income Statement'!I5*Assumptions!$C$68
A12: Cash and term deposits | B12: 1936.622 | C12: 2283.252 | D12: 2249.719 | E12: =D12+'Income Statement'!E18-'Income Statement'!E11+DCF!B12+DCF!B14-'Income Statement'!E18*Assumptions!$C$90 | F12: =E12+'Income Statement'!F18-'Income Statement'!F11+DCF!C12+DCF!C14-'Income Statement'!F18*Assumptions!$C$90 | G12: =F12+'Income Statement'!G18-'Income Statement'!G11+DCF!D12+DCF!D14-'Income Statement'!G18*Assumptions!$C$90 | H12: =G12+'Income Statement'!H18-'Income Statement'!H11+DCF!E12+DCF!E14-'Income Statement'!H18*Assumptions!$C$90 | I12: =H12+'Income Statement'!I18-'Income Statement'!I11+DCF!F12+DCF!F14-'Income Statement'!I18*Assumptions!$C$90
A13: Lease liabilities (the only debt-like item) | B13: 2104.959 | C13: 1998.687 | D13: 1938.819 | E13: =$D$13 | F13: =$D$13 | G13: =$D$13 | H13: =$D$13 | I13: =$D$13
A14: Total equity | B14: 9243.213 | C14: 9878.445 | D14: 10148.291 | E14: =D14+'Income Statement'!E18*(1-Assumptions!$C$90) | F14: =E14+'Income Statement'!F18*(1-Assumptions!$C$90) | G14: =F14+'Income Statement'!G18*(1-Assumptions!$C$90) | H14: =G14+'Income Statement'!H18*(1-Assumptions!$C$90) | I14: =H14+'Income Statement'!I18*(1-Assumptions!$C$90)
A15: Net cash after lease liabilities | B15: =B12-B13 | C15: =C12-C13 | D15: =D12-D13 | E15: =E12-E13 | F15: =F12-F13 | G15: =G12-G13 | H15: =H12-H13 | I15: =I12-I13
A16: Lease liabilities / EBITDA | B16: =B13/'Income Statement'!B9 | C16: =C13/'Income Statement'!C9 | D16: =D13/'Income Statement'!D9 | E16: =E13/'Income Statement'!E9 | F16: =F13/'Income Statement'!F9 | G16: =G13/'Income Statement'!G9 | H16: =H13/'Income Statement'!H9 | I16: =I13/'Income Statement'!I9
A18: Notes: a CONDENSED layout — receivables, payables, contract balances and the royalty accrual are netted inside the working-capital line, so the sheet does not foot to total assets. The FY2023 payables line still contained the royalty accrual (AED 2,033mn, separately disclosed from FY2024); it is excluded here in every year so the series is like-for-like. The lease book is held flat (replacement = depreciation); the FY2025 goodwill balance is carried unchanged. Cash and term deposits roll forward from profit less the ~98% payout — the H1-2026 interims (term deposits nil at 30-Jun-2026 after the AED 4.1bn royalty-plus-dividend outflow) show exactly this mechanic mid-year.

Sheet Cash Flow
A1: Cash flow — historical markers and the forecast waterfall
A2: AED mn
A4: AED mn | B4: FY2024 | C4: FY2025 | D4: FY26E | E4: FY27E | F4: FY28E | G4: FY29E | H4: FY30E
A5: EBITDA | B5: ='Income Statement'!C9 | C5: ='Income Statement'!D9 | D5: ='Income Statement'!E9 | E5: ='Income Statement'!F9 | F5: ='Income Statement'!G9 | G5: ='Income Statement'!H9 | H5: ='Income Statement'!I9
A6: Federal royalty and income tax paid | B6: -1928.939 | C6: -1883.442
A7: Net cash generated from operating activities | B7: 4636.508 | C7: 5229.823
A8: Purchase of PP&E and intangibles | B8: -1920.468 | C8: -2353.23
A9: NOPAT | B9: - | C9: - | D9: =DCF!B10 | E9: =DCF!C10 | F9: =DCF!D10 | G9: =DCF!E10 | H9: =DCF!F10
A10: Add back depreciation and amortisation | B10: - | C10: - | D10: =DCF!B11 | E10: =DCF!C11 | F10: =DCF!D11 | G10: =DCF!E11 | H10: =DCF!F11
A11: Capital expenditure | B11: - | C11: - | D11: =DCF!B12 | E11: =DCF!C12 | F11: =DCF!D12 | G11: =DCF!E12 | H11: =DCF!F12
A12: Memo — lease replacement, NOT deducted (leases are debt) | B12: - | C12: - | D12: =DCF!B13 | E12: =DCF!C13 | F12: =DCF!D13 | G12: =DCF!E13 | H12: =DCF!F13
A13: Change in working capital | B13: - | C13: =-('Balance Sheet'!D11-'Balance Sheet'!C11) | D13: =DCF!B14 | E13: =DCF!C14 | F13: =DCF!D14 | G13: =DCF!E14 | H13: =DCF!F14
A14: Free cash flow to the firm | B14: - | C14: - | D14: =D9+D10+D11+D13 | E14: =E9+E10+E11+E13 | F14: =F9+F10+F11+F13 | G14: =G9+G10+G11+G13 | H14: =H9+H10+H11+H13
A16: Dividends paid | B16: -1858.491 | C16: -2629.085 | D16: =-'Income Statement'!E18*Assumptions!$C$90 | E16: =-'Income Statement'!F18*Assumptions!$C$90 | F16: =-'Income Statement'!G18*Assumptions!$C$90 | G16: =-'Income Statement'!H18*Assumptions!$C$90 | H16: =-'Income Statement'!I18*Assumptions!$C$90
A17: Cash conversion — operating cash flow as a share of EBITDA, FY2025 | C17: =C7/C5
A18: du converts EBITDA to operating cash at over 70% AFTER the 43.6% fiscal take — the negative-working-capital model means growth releases cash. The constraint on equity cash flow is the ~100% payout plus the data-centre capex ramp, which is why term deposits fell to nil at 30-Jun-2026.

Sheet Summary Financials
A1: Summary financials — the eight-year picture
A2: AED mn unless stated. Every cell on this sheet is a link or a ratio; nothing is typed twice
A4: AED mn | B4: FY2023 | C4: FY2024 | D4: FY2025 | E4: FY26E | F4: FY27E | G4: FY28E | H4: FY29E | I4: FY30E
A5: Revenue | B5: ='Income Statement'!B5 | C5: ='Income Statement'!C5 | D5: ='Income Statement'!D5 | E5: ='Income Statement'!E5 | F5: ='Income Statement'!F5 | G5: ='Income Statement'!G5 | H5: ='Income Statement'!H5 | I5: ='Income Statement'!I5
A6: Revenue growth | B6: - | C6: =C5/B5-1 | D6: =D5/C5-1 | E6: =E5/D5-1 | F6: =F5/E5-1 | G6: =G5/F5-1 | H6: =H5/G5-1 | I6: =I5/H5-1
A7: EBITDA | B7: ='Income Statement'!B9 | C7: ='Income Statement'!C9 | D7: ='Income Statement'!D9 | E7: ='Income Statement'!E9 | F7: ='Income Statement'!F9 | G7: ='Income Statement'!G9 | H7: ='Income Statement'!H9 | I7: ='Income Statement'!I9
A8: EBITDA margin | B8: =B7/B5 | C8: =C7/C5 | D8: =D7/D5 | E8: =E7/E5 | F8: =F7/F5 | G8: =G7/G5 | H8: =H7/H5 | I8: =I7/I5
A9: EBIT | B9: ='Income Statement'!B12 | C9: ='Income Statement'!C12 | D9: ='Income Statement'!D12 | E9: ='Income Statement'!E12 | F9: ='Income Statement'!F12 | G9: ='Income Statement'!G12 | H9: ='Income Statement'!H12 | I9: ='Income Statement'!I12
A10: Net profit | B10: ='Income Statement'!B18 | C10: ='Income Statement'!C18 | D10: ='Income Statement'!D18 | E10: ='Income Statement'!E18 | F10: ='Income Statement'!F18 | G10: ='Income Statement'!G18 | H10: ='Income Statement'!H18 | I10: ='Income Statement'!I18
A11: Free cash flow to the firm | B11: - | C11: - | D11: - | E11: ='Cash Flow'!D14 | F11: ='Cash Flow'!E14 | G11: ='Cash Flow'!F14 | H11: ='Cash Flow'!G14 | I11: ='Cash Flow'!H14
A12: Net cash after lease liabilities | B12: ='Balance Sheet'!B15 | C12: ='Balance Sheet'!C15 | D12: ='Balance Sheet'!D15 | E12: ='Balance Sheet'!E15 | F12: ='Balance Sheet'!F15 | G12: ='Balance Sheet'!G15 | H12: ='Balance Sheet'!H15 | I12: ='Balance Sheet'!I15
A13: Invested capital | B13: - | C13: ='Balance Sheet'!C5+'Balance Sheet'!C7+'Balance Sheet'!C8+'Balance Sheet'!C10+'Balance Sheet'!C11 | D13: ='Balance Sheet'!D5+'Balance Sheet'!D7+'Balance Sheet'!D8+'Balance Sheet'!D10+'Balance Sheet'!D11 | E13: ='Balance Sheet'!E5+'Balance Sheet'!E7+'Balance Sheet'!E8+'Balance Sheet'!E10+'Balance Sheet'!E11 | F13: ='Balance Sheet'!F5+'Balance Sheet'!F7+'Balance Sheet'!F8+'Balance Sheet'!F10+'Balance Sheet'!F11 | G13: ='Balance Sheet'!G5+'Balance Sheet'!G7+'Balance Sheet'!G8+'Balance Sheet'!G10+'Balance Sheet'!G11 | H13: ='Balance Sheet'!H5+'Balance Sheet'!H7+'Balance Sheet'!H8+'Balance Sheet'!H10+'Balance Sheet'!H11 | I13: ='Balance Sheet'!I5+'Balance Sheet'!I7+'Balance Sheet'!I8+'Balance Sheet'!I10+'Balance Sheet'!I11
A14: Return on invested capital (average capital) | B14: - | C14: - | D14: - | E14: =DCF!B10/((D13+E13)/2) | F14: =DCF!C10/((E13+F13)/2) | G14: =DCF!D10/((F13+G13)/2) | H14: =DCF!E10/((G13+H13)/2) | I14: =DCF!F10/((H13+I13)/2)
A16: Invested capital = PP&E + right-of-use assets + intangibles + goodwill + net working capital (negative for du). FY2023 is not shown because goodwill was not disclosed as a separate line that year.

Sheet Monte Carlo
A1: Probabilistic price map
A2: A map of price dispersion. It carries no view on value and is never blended with the valuation. Each figure is an engine output, not a formula.
A4: Horizon | B4: 5th | C4: 25th | D4: Median | E4: 75th | F4: 95th | G4: P(above spot)
A5: One month — to 2026-10-07 | B5: 10.02735 | C5: 10.906181 | D5: 11.431215 | E5: 11.983621 | F5: 13.058483 | G5: 0.52604
A6: Three months — to 2026-12-07 | B6: 9.279305 | C6: 10.659241 | D6: 11.535234 | E6: 12.460516 | F6: 14.319354 | G6: 0.54716
A8: Level event | B8: One month | C8: Three months
A9: Finishes 10% or more above spot | B9: 0.11152 | C9: 0.23774
A10: Finishes 10% or more below spot | B10: 0.07536 | C10: 0.1614
A11: Touches 10% above spot at any point | B11: 0.17924 | C11: 0.41296
A12: Touches 10% below spot at any point | B12: 0.12822 | C12: 0.30582
A14: Engine setting | B14: Value
A15: Simulated paths | C15: 50000
A16: Annualised volatility (3-month anchor) | C16: 0.299394
A17: Spot price (AED) | C17: =Summary!C15
A18: Anchor date | C18: 2026-09-07

Sheet Sensitivity
A1: Sensitivity — what the valuation needs the world to do
A2: AED per share. Each cell is a complete re-run of the model, including the unit build, so these grids are engine outputs rather than formulas and do NOT redraw when a driver is changed.
A4: Terminal cost of capital (rows) x terminal growth (columns)
B5: 1.5% | C5: 2.0% | D5: 2.5% | E5: 3.0% | F5: 3.5%
A6: 5.45% | B6: 17.696823 | C6: 19.697519 | D6: 22.37232 | E6: 26.133122 | F6: 31.813219
A7: 5.95% | B7: 15.841731 | C7: 17.358611 | D7: 19.312029 | E7: 21.923589 | F7: 25.595428
A8: 6.45% | B8: 14.360216 | C8: 15.543769 | D8: 17.024415 | E8: 18.931142 | F8: 21.48024
A9: 6.95% | B9: 13.14956 | C9: 14.094354 | D9: 15.249324 | E9: 16.694184 | F9: 18.554794
A10: 7.45% | B10: 12.141544 | C10: 12.90989 | D10: 13.831612 | E10: 14.95835 | F10: 16.367865
A12: Explicit-window cost of capital (columns) x terminal cost of capital (rows)
B13: 5.69% | C13: 6.19% | D13: 6.69% | E13: 7.19% | F13: 7.69%
A14: terminal 5.45% | B14: 20.176521 | C14: 19.935171 | D14: 19.697519 | E14: 19.463494 | F14: 19.233029
A15: terminal 5.95% | B15: 17.78008 | C15: 17.567722 | D15: 17.358611 | E15: 17.152683 | F15: 16.949879
A16: terminal 6.45% | B16: 15.920598 | C16: 15.730736 | D16: 15.543769 | E16: 15.359642 | F16: 15.178301
A17: terminal 6.95% | B17: 14.435533 | C17: 14.263636 | D17: 14.094354 | E17: 13.927638 | F17: 13.763438
A18: terminal 7.45% | B18: 13.221936 | C18: 13.064721 | D18: 12.90989 | E18: 12.757401 | F18: 12.607208
A20: Single-driver sensitivities — five engine re-runs per row; the parameter grid for each row is shown beside its name
A21: Driver (parameter grid) | H21: Swing
A22: Beta (regression CI ends, then priors) (0.31 / 0.56 / 0.65 / 0.80 / 1.00) | B22: 20.220941 | C22: 15.543769 | D22: 14.284942 | E22: 12.625128 | F22: 10.91523 | H22: =MAX(B22:F22)-MIN(B22:F22)
A23: Combined fiscal take (top of grid = the pre-2024 construction's FY2023 take) (40.0% / 43.6% / 47.0% / 50.0% / 53.1%) | B23: 16.677077 | C23: 15.543769 | D23: 14.454905 | E23: 13.502546 | F23: 12.518441 | H23: =MAX(B23:F23)-MIN(B23:F23)
A24: Blended ARPU multiplier — applied to BOTH the mobile ARPU and the implied fixed revenue-per-subscriber paths (0.92x / 0.96x / 1.00x / 1.04x / 1.08x) | B24: 13.126061 | C24: 14.334915 | D24: 15.543769 | E24: 16.752623 | F24: 17.961477 | H24: =MAX(B24:F24)-MIN(B24:F24)
A25: Subscriber path shift ('000) — applied in full to the mobile base and at 8% of that to the fixed base (-400 / -200 / +0 / +200 / +400) | B25: 14.758818 | C25: 15.151294 | D25: 15.543769 | E25: 15.936245 | F25: 16.32872 | H25: =MAX(B25:F25)-MIN(B25:F25)
A26: Direct cost per unit, multiplicative (0.94x / 0.97x / 1.00x / 1.03x / 1.06x) | B26: 16.543534 | C26: 16.043652 | D26: 15.543769 | E26: 15.043887 | F26: 14.544004 | H26: =MAX(B26:F26)-MIN(B26:F26)
A27: Blended ARPU drift per year (mix exhaustion) (-2.5% / -1.5% / +0.0% / +0.5% / +1.0%) | B27: 12.702005 | C27: 13.813038 | D27: 15.543769 | E27: 16.138142 | F27: 16.741393 | H27: =MAX(B27:F27)-MIN(B27:F27)
A28: Capex path multiplier (0.850x / 0.925x / 1.000x / 1.100x / 1.200x) | B28: 16.453505 | C28: 15.998637 | D28: 15.543769 | E28: 14.937279 | F28: 14.330789 | H28: =MAX(B28:F28)-MIN(B28:F28)
A29: Working capital / revenue (-10.0% / -8.5% / -6.7% / -5.0% / -3.0%) | B29: 15.729917 | C29: 15.64582 | D29: 15.543769 | E29: 15.449595 | F29: 15.337467 | H29: =MAX(B29:F29)-MIN(B29:F29)
A30: Asset life, years — derived from the depreciation notes (10.7 / 13.7 / 16.7 / 19.7 / 22.7) | B30: 16.219263 | C30: 15.886512 | D30: 15.54373 | E30: 15.190612 | F30: 14.826848 | H30: =MAX(B30:F30)-MIN(B30:F30)
A31: Terminal growth (at base cost of capital) (1.5% / 2.0% / 2.5% / 3.0% / 3.5%) | B31: 14.360216 | C31: 15.543769 | D31: 17.024415 | E31: 18.931142 | F31: 21.48024 | H31: =MAX(B31:F31)-MIN(B31:F31)

Sheet Per-Share & Ratios
A1: Per-share and ratio analysis
A2: The indicator set for an integrated telecom operator: ARPU, subscribers, margin, capital intensity, cash conversion and the dividend. Every ratio is a formula off the statements.
A4: Measure | B4: FY2023 | C4: FY2024 | D4: FY2025 | E4: FY26E | F4: FY27E | G4: FY28E | H4: FY29E | I4: FY30E
A5: Earnings per share (AED) | B5: ='Income Statement'!B19 | C5: ='Income Statement'!C19 | D5: ='Income Statement'!D19 | E5: ='Income Statement'!E19 | F5: ='Income Statement'!F19 | G5: ='Income Statement'!G19 | H5: ='Income Statement'!H19 | I5: ='Income Statement'!I19
A6: Dividend per share (AED) | B6: ='Income Statement'!B20 | C6: ='Income Statement'!C20 | D6: ='Income Statement'!D20 | E6: ='Income Statement'!E20 | F6: ='Income Statement'!F20 | G6: ='Income Statement'!G20 | H6: ='Income Statement'!H20 | I6: ='Income Statement'!I20
A7: Payout ratio | B7: ='Income Statement'!B20/'Income Statement'!B19 | C7: ='Income Statement'!C20/'Income Statement'!C19 | D7: ='Income Statement'!D20/'Income Statement'!D19 | E7: ='Income Statement'!E20/'Income Statement'!E19 | F7: ='Income Statement'!F20/'Income Statement'!F19 | G7: ='Income Statement'!G20/'Income Statement'!G19 | H7: ='Income Statement'!H20/'Income Statement'!H19 | I7: ='Income Statement'!I20/'Income Statement'!I19
A8: Dividend yield at the anchor spot | B8: ='Income Statement'!B20/Assumptions!$C$5 | C8: ='Income Statement'!C20/Assumptions!$C$5 | D8: ='Income Statement'!D20/Assumptions!$C$5 | E8: ='Income Statement'!E20/Assumptions!$C$5 | F8: ='Income Statement'!F20/Assumptions!$C$5 | G8: ='Income Statement'!G20/Assumptions!$C$5 | H8: ='Income Statement'!H20/Assumptions!$C$5 | I8: ='Income Statement'!I20/Assumptions!$C$5
A9: Book value per share (AED) | B9: ='Balance Sheet'!B14/Assumptions!$C$6 | C9: ='Balance Sheet'!C14/Assumptions!$C$6 | D9: ='Balance Sheet'!D14/Assumptions!$C$6 | E9: ='Balance Sheet'!E14/Assumptions!$C$6 | F9: ='Balance Sheet'!F14/Assumptions!$C$6 | G9: ='Balance Sheet'!G14/Assumptions!$C$6 | H9: ='Balance Sheet'!H14/Assumptions!$C$6 | I9: ='Balance Sheet'!I14/Assumptions!$C$6
A10: Free cash flow to the firm per share (AED) | B10: - | C10: - | D10: - | E10: ='Summary Financials'!E11/Assumptions!$C$6 | F10: ='Summary Financials'!F11/Assumptions!$C$6 | G10: ='Summary Financials'!G11/Assumptions!$C$6 | H10: ='Summary Financials'!H11/Assumptions!$C$6 | I10: ='Summary Financials'!I11/Assumptions!$C$6
A11: EBITDA margin | B11: ='Summary Financials'!B8 | C11: ='Summary Financials'!C8 | D11: ='Summary Financials'!D8 | E11: ='Summary Financials'!E8 | F11: ='Summary Financials'!F8 | G11: ='Summary Financials'!G8 | H11: ='Summary Financials'!H8 | I11: ='Summary Financials'!I8
A12: EBIT margin | B12: ='Income Statement'!B12/'Income Statement'!B5 | C12: ='Income Statement'!C12/'Income Statement'!C5 | D12: ='Income Statement'!D12/'Income Statement'!D5 | E12: ='Income Statement'!E12/'Income Statement'!E5 | F12: ='Income Statement'!F12/'Income Statement'!F5 | G12: ='Income Statement'!G12/'Income Statement'!G5 | H12: ='Income Statement'!H12/'Income Statement'!H5 | I12: ='Income Statement'!I12/'Income Statement'!I5
A13: Net margin | B13: ='Income Statement'!B18/'Income Statement'!B5 | C13: ='Income Statement'!C18/'Income Statement'!C5 | D13: ='Income Statement'!D18/'Income Statement'!D5 | E13: ='Income Statement'!E18/'Income Statement'!E5 | F13: ='Income Statement'!F18/'Income Statement'!F5 | G13: ='Income Statement'!G18/'Income Statement'!G5 | H13: ='Income Statement'!H18/'Income Statement'!H5 | I13: ='Income Statement'!I18/'Income Statement'!I5
A14: Return on equity | B14: - | C14: ='Income Statement'!C18/(('Balance Sheet'!B14+'Balance Sheet'!C14)/2) | D14: ='Income Statement'!D18/(('Balance Sheet'!C14+'Balance Sheet'!D14)/2) | E14: ='Income Statement'!E18/(('Balance Sheet'!D14+'Balance Sheet'!E14)/2) | F14: ='Income Statement'!F18/(('Balance Sheet'!E14+'Balance Sheet'!F14)/2) | G14: ='Income Statement'!G18/(('Balance Sheet'!F14+'Balance Sheet'!G14)/2) | H14: ='Income Statement'!H18/(('Balance Sheet'!G14+'Balance Sheet'!H14)/2) | I14: ='Income Statement'!I18/(('Balance Sheet'!H14+'Balance Sheet'!I14)/2)
A15: Return on invested capital | B15: - | C15: - | D15: - | E15: ='Summary Financials'!E14 | F15: ='Summary Financials'!F14 | G15: ='Summary Financials'!G14 | H15: ='Summary Financials'!H14 | I15: ='Summary Financials'!I14
A16: Capital expenditure / revenue (capital intensity) | B16: - | C16: - | D16: - | E16: =-'Cash Flow'!D11/'Income Statement'!E5 | F16: =-'Cash Flow'!E11/'Income Statement'!F5 | G16: =-'Cash Flow'!F11/'Income Statement'!G5 | H16: =-'Cash Flow'!G11/'Income Statement'!H5 | I16: =-'Cash Flow'!H11/'Income Statement'!I5
A17: Lease liabilities / EBITDA | B17: ='Balance Sheet'!B16 | C17: ='Balance Sheet'!C16 | D17: ='Balance Sheet'!D16 | E17: ='Balance Sheet'!E16 | F17: ='Balance Sheet'!F16 | G17: ='Balance Sheet'!G16 | H17: ='Balance Sheet'!H16 | I17: ='Balance Sheet'!I16
A18: Working capital / revenue | B18: ='Balance Sheet'!B11/'Income Statement'!B5 | C18: ='Balance Sheet'!C11/'Income Statement'!C5 | D18: ='Balance Sheet'!D11/'Income Statement'!D5 | E18: ='Balance Sheet'!E11/'Income Statement'!E5 | F18: ='Balance Sheet'!F11/'Income Statement'!F5 | G18: ='Balance Sheet'!G11/'Income Statement'!G5 | H18: ='Balance Sheet'!H11/'Income Statement'!H5 | I18: ='Balance Sheet'!I11/'Income Statement'!I5
A20: Operating KPIs (company-disclosed history, house forecast)
A21: Mobile subscribers, end of year ('000) | B21: - | C21: 8916 | D21: 9704 | E21: =Assumptions!$B$24 | F21: =Assumptions!$C$24 | G21: =Assumptions!$D$24 | H21: =Assumptions!$E$24 | I21: =Assumptions!$F$24
A22: Fixed subscribers, end of year ('000) | B22: - | C22: 682 | D22: 735 | E22: =Assumptions!$B$25 | F22: =Assumptions!$C$25 | G22: =Assumptions!$D$25 | H22: =Assumptions!$E$25 | I22: =Assumptions!$F$25
A23: Blended mobile ARPU (AED/month) | B23: - | C23: 65.8 | D23: 63.3 | E23: =Assumptions!$B$26 | F23: =Assumptions!$C$26 | G23: =Assumptions!$D$26 | H23: =Assumptions!$E$26 | I23: =Assumptions!$F$26
A25: Subscriber and ARPU history are the company's own year-end prints; FY2023 is not shown because the KPI series in the current disclosure pack starts at Q4-2024. The Q2-2026 actual mobile base is 9,280k after the war quarter (total base −412k on the quarter), which is the base the forecast recovers from.

Sheet Peer & Sector
A1: Peer frame and sector context
A2: Aggregator multiple reads, labelled cross-check — never a build source. du computed from its own audited figures
A4: Company | B4: Market | C4: Trailing P/E | D4: Dividend yield | E4: Relevance / caution
A5: e& (EAND) | B5: UAE (ADX) | C5: ~20.7x | D5: ~4.8% | E5: the other half of the duopoly; scale, international assets and a higher multiple
A6: stc | B6: Saudi Arabia | C6: ~18.9x | D6: ~5.2% | E6: regional benchmark payer; the yield anchor for the cross-check
A7: Mobily | B7: Saudi Arabia | C7: ~15.5x | D7: ~2.9% | E7: closest structural analogue — the #2 operator that closed the gap; the justified P/E
A8: Ooredoo | B8: Qatar | C8: ~12.5x | D8: ~4.6% | E8: multi-market; softer growth, lower multiple
A9: Zain | B9: Kuwait | C9: ~9x | D9: ~6-7% | E9: levered multi-market; the low end of the bracket
A10: Omantel | B10: Oman | C10: ~11.4x | D10: ~6.7% | E10: small-market incumbent; yield-heavy
A11: Deutsche Telekom / Vodafone | B11: Developed markets | C11: n/m | D11: 3.4% / n/m | E11: the developed-market bracket: slower growth, more leverage, lower returns
A13: du own multiples (computed live) | B13: Value
A14: Trailing price / earnings | B14: ='Relative & Normalized'!C13
A15: Trailing enterprise value / EBITDA | B15: ='Relative & Normalized'!C14
A16: Trailing dividend yield (FY2025 DPS / spot) | B16: ='Income Statement'!D20/Assumptions!$C$5
A17: Justified price / earnings applied | B17: ='Relative & Normalized'!C6
A19: Peer EV/EBITDA was not reliably sourceable from public aggregators at the sweep date (net-debt figures missing); the relative lens therefore runs on P/E and dividend yield, both sourced, and that limitation is stated rather than papered over.
